{
  "id": 7541609,
  "type": "Feature",
  "properties": {
    "tgn:hierarchy":[
        "tgn:7541609",
        "tgn:7001242",
        "tgn:7016833",
        "tgn:1001088",
        "tgn:7029392"
    ],
    "tgn:id":7541609,
    "tgn:name:en":"Tir'at Darw\u012bsh",
    "tgn:placetype":[
        "aat:300006075"
    ]
},
  "bbox": [],
  "geometry": {"coordinates":[30.783672,28.410448],"type":"Point"}
}