{
  "id": 2504394,
  "type": "Feature",
  "properties": {
    "tgn:hierarchy":[
        "tgn:2504394",
        "tgn:1000001",
        "tgn:1002240",
        "tgn:7012149",
        "tgn:7007255",
        "tgn:7029392"
    ],
    "tgn:id":2504394,
    "tgn:name":"Meadows Fork",
    "tgn:placetype":[
        "aat:300008699"
    ]
},
  "bbox": [],
  "geometry": {"coordinates":[-83.2167,38.4333],"type":"Point"}
}