<<<<<<< HEAD
{
  "id": 7487108,
  "type": "Feature",
  "properties": {
    "tgn:hierarchy":[
        "tgn:7487108",
        "tgn:7487020",
        "tgn:1000004",
        "tgn:1000141",
        "tgn:7029392"
    ],
    "tgn:id":7487108,
    "tgn:name":"Baguali",
    "tgn:placetype":[
        "aat:300008347"
    ]
},
  "bbox": [],
  "geometry": {"coordinates":[120.961649,24.532597],"type":"Point"}
}
=======
{"geometry":{"type":"Point","coordinates":[120.961649,24.532597]},"type":"Feature","properties":{"hierarchy":["tgn:7487108","tgn:7487020","tgn:1000004","tgn:1000141","tgn:7029392"],"placetype":["aat:300008347"],"id":7487108,"name:xx":"Baguali"}}
>>>>>>> 03f74aca74312dbeaf24d7e61306dd6a786dc3d0
