{
  "id": 2707969,
  "type": "Feature",
  "properties": {
    "tgn:hierarchy":[
        "tgn:2707969",
        "tgn:1000001",
        "tgn:7012149",
        "tgn:1002967",
        "tgn:7007520",
        "tgn:7029392"
    ],
    "tgn:id":2707969,
    "tgn:name":"Swift Lake",
    "tgn:placetype":[
        "aat:300008680"
    ]
},
  "bbox": [],
  "geometry": {"coordinates":[-85.8833,42.0667],"type":"Point"}
}