{
  "id": 7349196,
  "type": "Feature",
  "properties": {
    "tgn:hierarchy":[
        "tgn:7349196",
        "tgn:7005581",
        "tgn:1000001",
        "tgn:7005560",
        "tgn:7029392"
    ],
    "tgn:id":7349196,
    "tgn:name":"Aguada",
    "tgn:placetype":[
        "aat:300006207"
    ]
},
  "bbox": [],
  "geometry": {"coordinates":[-107.516667,30.983333],"type":"Point"}
}