{
  "id": 2741203,
  "type": "Feature",
  "properties": {
    "tgn:hierarchy":[
        "tgn:2741203",
        "tgn:1000001",
        "tgn:7012149",
        "tgn:2002110",
        "tgn:7007827",
        "tgn:7029392"
    ],
    "tgn:id":2741203,
    "tgn:name":"Upper Twin Canyon",
    "tgn:placetype":[
        "aat:300008761"
    ]
},
  "bbox": [],
  "geometry": {"coordinates":[-109.55,39.15],"type":"Point"}
}