<<<<<<< HEAD
{
  "id": 2338433,
  "type": "Feature",
  "properties": {
    "tgn:hierarchy":[
        "tgn:2338433",
        "tgn:1000001",
        "tgn:7012149",
        "tgn:7018871",
        "tgn:7007920",
        "tgn:7029392"
    ],
    "tgn:id":2338433,
    "tgn:name":"Foy",
    "tgn:placetype":[
        "aat:300008347"
    ]
},
  "bbox": [],
  "geometry": {"coordinates":[-122.3333,47.7333],"type":"Point"}
}
=======
{"geometry":{"type":"Point","coordinates":[-122.333300,47.733300]},"type":"Feature","properties":{"hierarchy":["tgn:2338433","tgn:1000001","tgn:7012149","tgn:7018871","tgn:7007920","tgn:7029392"],"placetype":["aat:300008347"],"id":2338433,"name:xx":"Foy"}}
>>>>>>> 03f74aca74312dbeaf24d7e61306dd6a786dc3d0
