{
  "id": 7220560,
  "type": "Feature",
  "properties": {
    "tgn:hierarchy":[
        "tgn:7220560",
        "tgn:7011270",
        "tgn:7002674",
        "tgn:1000003",
        "tgn:1000074",
        "tgn:7029392"
    ],
    "tgn:id":7220560,
    "tgn:name":"Vath\u00ed",
    "tgn:placetype":[
        "aat:300008347"
    ]
},
  "bbox": [],
  "geometry": {"coordinates":[24.683333,36.933333],"type":"Point"}
}