{
  "id": 7388166,
  "type": "Feature",
  "properties": {
    "tgn:hierarchy":[
        "tgn:7388166",
        "tgn:1000001",
        "tgn:7005595",
        "tgn:7005560",
        "tgn:7029392"
    ],
    "tgn:id":7388166,
    "tgn:name":"Potrero",
    "tgn:placetype":[
        "aat:300008347"
    ]
},
  "bbox": [],
  "geometry": {"coordinates":[-107.233333,25.333333],"type":"Point"}
}