{
  "id": 7500688,
  "type": "Feature",
  "properties": {
    "tgn:hierarchy":[
        "tgn:7500688",
        "tgn:7488858",
        "tgn:1000004",
        "tgn:1000141",
        "tgn:7029392"
    ],
    "tgn:id":7500688,
    "tgn:name":"Andingwan",
    "tgn:placetype":[
        "aat:300008347"
    ]
},
  "bbox": [],
  "geometry": {"coordinates":[120.784722,23.644167],"type":"Point"}
}