<<<<<<< HEAD
{
  "id": 2765917,
  "type": "Feature",
  "properties": {
    "tgn:hierarchy":[
        "tgn:2765917",
        "tgn:1000001",
        "tgn:7012149",
        "tgn:2001312",
        "tgn:7007524",
        "tgn:7029392"
    ],
    "tgn:id":2765917,
    "tgn:name":"White Highland Hills",
    "tgn:placetype":[
        "aat:300008697"
    ]
},
  "bbox": [],
  "geometry": {"coordinates":[-106.0833,48.7333],"type":"Point"}
}
=======
{"geometry":{"type":"Point","coordinates":[-106.083300,48.733300]},"type":"Feature","properties":{"hierarchy":["tgn:2765917","tgn:1000001","tgn:7012149","tgn:2001312","tgn:7007524","tgn:7029392"],"placetype":["aat:300008697"],"id":2765917,"name:xx":"White Highland Hills"}}
>>>>>>> 03f74aca74312dbeaf24d7e61306dd6a786dc3d0
