{
  "id": 1068511,
  "type": "Feature",
  "properties": {
    "tgn:hierarchy":[
        "tgn:1068511",
        "tgn:1000004",
        "tgn:7002082",
        "tgn:1000111",
        "tgn:7029392"
    ],
    "tgn:id":1068511,
    "tgn:name":"Guxiandu",
    "tgn:placetype":[
        "aat:300008347"
    ]
},
  "bbox": [],
  "geometry": {"coordinates":[116.8667,29.0833],"type":"Point"}
}