{
  "id": 2709988,
  "type": "Feature",
  "properties": {
    "tgn:hierarchy":[
        "tgn:2709988",
        "tgn:1000001",
        "tgn:7012149",
        "tgn:2000480",
        "tgn:7007250",
        "tgn:7029392"
    ],
    "tgn:id":2709988,
    "tgn:name":"Talapus Creek",
    "tgn:placetype":[
        "aat:300008706"
    ]
},
  "bbox": [],
  "geometry": {"coordinates":[-116.4833,46.9333],"type":"Point"}
}