{
  "id": 7404649,
  "type": "Feature",
  "properties": {
    "tgn:hierarchy":[
        "tgn:7404649",
        "tgn:7005585",
        "tgn:1000001",
        "tgn:7005560",
        "tgn:7029392"
    ],
    "tgn:id":7404649,
    "tgn:name":"El Manch\u00f3n",
    "tgn:placetype":[
        "aat:300008347"
    ]
},
  "bbox": [],
  "geometry": {"coordinates":[-100.033333,18.133333],"type":"Point"}
}