{
  "id": 2701016,
  "type": "Feature",
  "properties": {
    "tgn:hierarchy":[
        "tgn:2701016",
        "tgn:1000001",
        "tgn:7012149",
        "tgn:1002598",
        "tgn:7007523",
        "tgn:7029392"
    ],
    "tgn:id":2701016,
    "tgn:name":"Sugar Creek",
    "tgn:placetype":[
        "aat:300008706"
    ]
},
  "bbox": [],
  "geometry": {"coordinates":[-90.95,39.1333],"type":"Point"}
}