{
  "id": 7279069,
  "type": "Feature",
  "properties": {
    "tgn:hierarchy":[
        "tgn:7279069",
        "tgn:1001623",
        "tgn:1000049",
        "tgn:1000002",
        "tgn:7029392"
    ],
    "tgn:id":7279069,
    "tgn:name":"Rudolphy, Pen\u00ednsula",
    "tgn:placetype":[
        "aat:300008804"
    ]
},
  "bbox": [],
  "geometry": {"coordinates":[-73.583333,-45.316667],"type":"Point"}
}