{
  "id": 2146184,
  "type": "Feature",
  "properties": {
    "tgn:hierarchy":[
        "tgn:2146184",
        "tgn:1000001",
        "tgn:7012149",
        "tgn:1002761",
        "tgn:7007706",
        "tgn:7029392"
    ],
    "tgn:id":2146184,
    "tgn:name":"Ballast Island",
    "tgn:placetype":[
        "aat:300008791"
    ]
},
  "bbox": [],
  "geometry": {"coordinates":[-82.7833,41.6667],"type":"Point"}
}