{
  "id": 7389970,
  "type": "Feature",
  "properties": {
    "tgn:hierarchy":[
        "tgn:7389970",
        "tgn:7005581",
        "tgn:1000001",
        "tgn:7005560",
        "tgn:7029392"
    ],
    "tgn:id":7389970,
    "tgn:name":"Rancho Grande",
    "tgn:placetype":[
        "aat:300008347"
    ]
},
  "bbox": [],
  "geometry": {"coordinates":[-105.283333,28.083333],"type":"Point"}
}