<<<<<<< HEAD
{
  "id": 2255100,
  "type": "Feature",
  "properties": {
    "tgn:hierarchy":[
        "tgn:2255100",
        "tgn:1000001",
        "tgn:7006451",
        "tgn:2000093",
        "tgn:7012149",
        "tgn:7029392"
    ],
    "tgn:id":2255100,
    "tgn:name":"Cooper Forks",
    "tgn:placetype":[
        "aat:300008699"
    ]
},
  "bbox": [],
  "geometry": {"coordinates":[-110.8333,33.85],"type":"Point"}
}
=======
{"geometry":{"type":"Point","coordinates":[-110.833300,33.850000]},"type":"Feature","properties":{"hierarchy":["tgn:2255100","tgn:1000001","tgn:7006451","tgn:2000093","tgn:7012149","tgn:7029392"],"placetype":["aat:300008699"],"id":2255100,"name:xx":"Cooper Forks"}}
>>>>>>> 03f74aca74312dbeaf24d7e61306dd6a786dc3d0
