{
  "id": 7490619,
  "type": "Feature",
  "properties": {
    "tgn:hierarchy":[
        "tgn:7490619",
        "tgn:1000004",
        "tgn:7001009",
        "tgn:1000141",
        "tgn:7029392"
    ],
    "tgn:id":7490619,
    "tgn:name":"Sancun Li",
    "tgn:placetype":[
        "aat:300387200"
    ]
},
  "bbox": [],
  "geometry": {"coordinates":[120.700338,24.231371],"type":"Point"}
}