{
  "id": 2730186,
  "type": "Feature",
  "properties": {
    "tgn:hierarchy":[
        "tgn:2730186",
        "tgn:1000001",
        "tgn:7012149",
        "tgn:1002924",
        "tgn:7007568",
        "tgn:7029392"
    ],
    "tgn:id":2730186,
    "tgn:name":"Trout Pond",
    "tgn:placetype":[
        "aat:300006191"
    ]
},
  "bbox": [],
  "geometry": {"coordinates":[-72.35,40.9833],"type":"Point"}
}