{
  "id": 7276072,
  "type": "Feature",
  "properties": {
    "tgn:hierarchy":[
        "tgn:7276072",
        "tgn:1001702",
        "tgn:1000049",
        "tgn:1000002",
        "tgn:7029392"
    ],
    "tgn:id":7276072,
    "tgn:name":"Terencio, Punta",
    "tgn:placetype":[
        "aat:300386846"
    ]
},
  "bbox": [],
  "geometry": {"coordinates":[-73.766667,-52.283333],"type":"Point"}
}