{
  "id": 7300004,
  "type": "Feature",
  "properties": {
    "tgn:hierarchy":[
        "tgn:7300004",
        "tgn:7002825",
        "tgn:7016622",
        "tgn:1000003",
        "tgn:1000095",
        "tgn:7029392"
    ],
    "tgn:id":7300004,
    "tgn:name":"Teseguite",
    "tgn:placetype":[
        "aat:300008347"
    ]
},
  "bbox": [],
  "geometry": {"coordinates":[-13.533333,29.05],"type":"Point"}
}