{
  "id": 2151386,
  "type": "Feature",
  "properties": {
    "tgn:hierarchy":[
        "tgn:2151386",
        "tgn:1000001",
        "tgn:2002367",
        "tgn:7012149",
        "tgn:7007923",
        "tgn:7029392"
    ],
    "tgn:id":2151386,
    "tgn:name":"Bates Reservoir",
    "tgn:placetype":[
        "aat:300006191"
    ]
},
  "bbox": [],
  "geometry": {"coordinates":[-105.2333,44.8167],"type":"Point"}
}