{
  "id": 7231982,
  "type": "Feature",
  "properties": {
    "tgn:hierarchy":[
        "tgn:7231982",
        "tgn:7002690",
        "tgn:7012056",
        "tgn:1000003",
        "tgn:1000074",
        "tgn:7029392"
    ],
    "tgn:id":7231982,
    "tgn:name":"Koulo\u00fakonas O\u0155os",
    "tgn:placetype":[
        "aat:300008795"
    ]
},
  "bbox": [],
  "geometry": {"coordinates":[24.866667,35.366667],"type":"Point"}
}