{
  "id": 2074851,
  "type": "Feature",
  "properties": {
    "tgn:hierarchy":[
        "tgn:2074851",
        "tgn:1000001",
        "tgn:7012149",
        "tgn:2001532",
        "tgn:7007709",
        "tgn:7029392"
    ],
    "tgn:id":2074851,
    "tgn:name":"Grays Chapel",
    "tgn:placetype":[
        "aat:300008347",
        "aat:300387210"
    ]
},
  "bbox": [],
  "geometry": {"coordinates":[-79.6833,35.8167],"type":"Point"}
}