{
  "id": 2110304,
  "type": "Feature",
  "properties": {
    "tgn:hierarchy":[
        "tgn:2110304",
        "tgn:1000001",
        "tgn:7012149",
        "tgn:1002411",
        "tgn:7007919",
        "tgn:7029392"
    ],
    "tgn:id":2110304,
    "tgn:name":"Allmondsville",
    "tgn:placetype":[
        "aat:300008347"
    ]
},
  "bbox": [],
  "geometry": {"coordinates":[-76.65,37.3833],"type":"Point"}
}