{
  "id": 1043020,
  "type": "Feature",
  "properties": {
    "tgn:hierarchy":[
        "tgn:1043020",
        "tgn:7001199",
        "tgn:7003491",
        "tgn:1000003",
        "tgn:1000078",
        "tgn:7029392"
    ],
    "tgn:id":1043020,
    "tgn:name":"Summerhill",
    "tgn:placetype":[
        "aat:300008347"
    ]
},
  "bbox": [],
  "geometry": {"coordinates":[-6.7333,53.4833],"type":"Point"}
}