{
  "id": 7009056,
  "type": "Feature",
  "properties": {
    "tgn:hierarchy":[
        "tgn:7009056",
        "tgn:1000003",
        "tgn:7002892",
        "tgn:1000070",
        "tgn:7029392"
    ],
    "tgn:id":7009056,
    "tgn:name":"Confolens",
    "tgn:placetype":[
        "aat:300008347"
    ]
},
  "bbox": [],
  "geometry": {"coordinates":[0.6667,46.0167],"type":"Point"}
}