{
  "id": 2147302,
  "type": "Feature",
  "properties": {
    "tgn:hierarchy":[
        "tgn:2147302",
        "tgn:1000001",
        "tgn:7006451",
        "tgn:7012149",
        "tgn:2000104",
        "tgn:7029392"
    ],
    "tgn:id":2147302,
    "tgn:name":"Baragan Mountain",
    "tgn:placetype":[
        "aat:300008798"
    ]
},
  "bbox": [],
  "geometry": {"coordinates":[-113.4333,33.0833],"type":"Point"}
}