{
  "id": 2568156,
  "type": "Feature",
  "properties": {
    "tgn:hierarchy":[
        "tgn:2568156",
        "tgn:1000001",
        "tgn:2002310",
        "tgn:7012149",
        "tgn:7007922",
        "tgn:7029392"
    ],
    "tgn:id":2568156,
    "tgn:name":"Parent Slu",
    "tgn:placetype":[
        "aat:300008699"
    ]
},
  "bbox": [],
  "geometry": {"coordinates":[-92.0333,44.4167],"type":"Point"}
}