{
  "id": 2207200,
  "type": "Feature",
  "properties": {
    "tgn:hierarchy":[
        "tgn:2207200",
        "tgn:1000001",
        "tgn:7012149",
        "tgn:2000291",
        "tgn:7007240",
        "tgn:7029392"
    ],
    "tgn:id":2207200,
    "tgn:name":"Bunker Donation",
    "tgn:placetype":[
        "aat:300008347"
    ]
},
  "bbox": [],
  "geometry": {"coordinates":[-85.8667,30.5167],"type":"Point"}
}