<<<<<<< HEAD
{
  "id": 7379320,
  "type": "Feature",
  "properties": {
    "tgn:hierarchy":[
        "tgn:7379320",
        "tgn:1000001",
        "tgn:7005595",
        "tgn:7005560",
        "tgn:7029392"
    ],
    "tgn:id":7379320,
    "tgn:name":"Mezquitillo",
    "tgn:placetype":[
        "aat:300008347"
    ]
},
  "bbox": [],
  "geometry": {"coordinates":[-107.883333,24.966667],"type":"Point"}
}
=======
{"geometry":{"type":"Point","coordinates":[-107.883333,24.966667]},"type":"Feature","properties":{"hierarchy":["tgn:7379320","tgn:1000001","tgn:7005595","tgn:7005560","tgn:7029392"],"placetype":["aat:300008347"],"id":7379320,"name:xx":"Mezquitillo"}}
>>>>>>> 03f74aca74312dbeaf24d7e61306dd6a786dc3d0
