{
  "id": 2527579,
  "type": "Feature",
  "properties": {
    "tgn:hierarchy":[
        "tgn:2527579",
        "tgn:1000001",
        "tgn:7012149",
        "tgn:7007157",
        "tgn:1002956",
        "tgn:7029392"
    ],
    "tgn:id":2527579,
    "tgn:name":"Mount Whitney Ditch",
    "tgn:placetype":[
        "aat:300006075"
    ]
},
  "bbox": [],
  "geometry": {"coordinates":[-118.8167,36.1333],"type":"Point"}
}