{
  "id": 7008423,
  "type": "Feature",
  "properties": {
    "tgn:hierarchy":[
        "tgn:7008423",
        "tgn:1000003",
        "tgn:7002889",
        "tgn:1000070",
        "tgn:7029392"
    ],
    "tgn:id":7008423,
    "tgn:name":"Rodez",
    "tgn:placetype":[
        "aat:300008347",
        "aat:300387218",
        "aat:300387225",
        "aat:300387512",
        "aat:300387235",
        "aat:300008375",
        "aat:300387302",
        "aat:300387291",
        "aat:300387286"
    ]
},
  "bbox": [],
  "geometry": {"coordinates":[2.5667,44.35],"type":"Point"}
}