{
  "id": 1025166,
  "type": "Feature",
  "properties": {
    "tgn:hierarchy":[
        "tgn:1025166",
        "tgn:1000842",
        "tgn:1000002",
        "tgn:1000059",
        "tgn:7029392"
    ],
    "tgn:id":1025166,
    "tgn:name":"La Majada",
    "tgn:placetype":[
        "aat:300008347"
    ]
},
  "bbox": [],
  "geometry": {"coordinates":[-67.0167,10.45],"type":"Point"}
}