{
  "id": 2322079,
  "type": "Feature",
  "properties": {
    "tgn:hierarchy":[
        "tgn:2322079",
        "tgn:1000001",
        "tgn:7012149",
        "tgn:1002423",
        "tgn:7007568",
        "tgn:7029392"
    ],
    "tgn:id":2322079,
    "tgn:name":"Fall Creek",
    "tgn:placetype":[
        "aat:300008706"
    ]
},
  "bbox": [],
  "geometry": {"coordinates":[-74.15,42.3333],"type":"Point"}
}