{
  "id": 7121684,
  "type": "Feature",
  "properties": {
    "tgn:hierarchy":[
        "tgn:7121684",
        "tgn:7003669",
        "tgn:1000003",
        "tgn:7000084",
        "tgn:7029392"
    ],
    "tgn:id":7121684,
    "tgn:name":"Petzmannsberg",
    "tgn:placetype":[
        "aat:300008347"
    ]
},
  "bbox": [],
  "geometry": {"coordinates":[11.433333,50.116667],"type":"Point"}
}