{
  "id": 1032701,
  "type": "Feature",
  "properties": {
    "tgn:hierarchy":[
        "tgn:1032701",
        "tgn:1000003",
        "tgn:7002893",
        "tgn:1000070",
        "tgn:7029392"
    ],
    "tgn:id":1032701,
    "tgn:name":"Clisson",
    "tgn:placetype":[
        "aat:300008347"
    ]
},
  "bbox": [],
  "geometry": {"coordinates":[-1.2667,47.0833],"type":"Point"}
}