{
  "id": 2493395,
  "type": "Feature",
  "properties": {
    "tgn:hierarchy":[
        "tgn:2493395",
        "tgn:1000001",
        "tgn:2001429",
        "tgn:7012149",
        "tgn:7007566",
        "tgn:7029392"
    ],
    "tgn:id":2493395,
    "tgn:name":"Marrs Spring",
    "tgn:placetype":[
        "aat:300008697"
    ]
},
  "bbox": [],
  "geometry": {"coordinates":[-108.4667,33.3167],"type":"Point"}
}