{
  "id": 2079019,
  "type": "Feature",
  "properties": {
    "tgn:hierarchy":[
        "tgn:2079019",
        "tgn:1000001",
        "tgn:7012149",
        "tgn:1002432",
        "tgn:7007706",
        "tgn:7029392"
    ],
    "tgn:id":2079019,
    "tgn:name":"College Hill",
    "tgn:placetype":[
        "aat:300008347"
    ]
},
  "bbox": [],
  "geometry": {"coordinates":[-81.6333,40.0333],"type":"Point"}
}