{
  "id": 2239338,
  "type": "Feature",
  "properties": {
    "tgn:hierarchy":[
        "tgn:2239338",
        "tgn:7002659",
        "tgn:1000001",
        "tgn:7012149",
        "tgn:2000031",
        "tgn:7029392"
    ],
    "tgn:id":2239338,
    "tgn:name":"Church Branch",
    "tgn:placetype":[
        "aat:300008699"
    ]
},
  "bbox": [],
  "geometry": {"coordinates":[-88.05,32.9667],"type":"Point"}
}