{
  "id": 2212185,
  "type": "Feature",
  "properties": {
    "tgn:hierarchy":[
        "tgn:2212185",
        "tgn:1000001",
        "tgn:2002146",
        "tgn:7012149",
        "tgn:7007919",
        "tgn:7029392"
    ],
    "tgn:id":2212185,
    "tgn:name":"Buzzard Ridge",
    "tgn:placetype":[
        "aat:300266640"
    ]
},
  "bbox": [],
  "geometry": {"coordinates":[-79.5667,37.5167],"type":"Point"}
}