{
  "id": 1083938,
  "type": "Feature",
  "properties": {
    "tgn:hierarchy":[
        "tgn:1083938",
        "tgn:1000004",
        "tgn:1001307",
        "tgn:1000135",
        "tgn:7029392"
    ],
    "tgn:id":1083938,
    "tgn:name":"Alimodian",
    "tgn:placetype":[
        "aat:300008347"
    ]
},
  "bbox": [],
  "geometry": {"coordinates":[122.4333,10.8167],"type":"Point"}
}