{
  "id": 2063430,
  "type": "Feature",
  "properties": {
    "tgn:hierarchy":[
        "tgn:2063430",
        "tgn:1000001",
        "tgn:7014352",
        "tgn:7012149",
        "tgn:7007564",
        "tgn:7029392"
    ],
    "tgn:id":2063430,
    "tgn:name":"Foyes Corner",
    "tgn:placetype":[
        "aat:300008347"
    ]
},
  "bbox": [],
  "geometry": {"coordinates":[-70.7333,43.0333],"type":"Point"}
}