{
  "id": 2648874,
  "type": "Feature",
  "properties": {
    "tgn:hierarchy":[
        "tgn:2648874",
        "tgn:1000001",
        "tgn:7012149",
        "tgn:2001067",
        "tgn:7007521",
        "tgn:7029392"
    ],
    "tgn:id":2648874,
    "tgn:name":"Scott Bevier Creek",
    "tgn:placetype":[
        "aat:300008706"
    ]
},
  "bbox": [],
  "geometry": {"coordinates":[-92.15,47.8833],"type":"Point"}
}