{
  "id": 7559172,
  "type": "Feature",
  "properties": {
    "tgn:hierarchy":[
        "tgn:7559172",
        "tgn:1001828",
        "tgn:1000004",
        "tgn:7000198",
        "tgn:7029392"
    ],
    "tgn:id":7559172,
    "tgn:name:en":"Sarj\u0101khanpet",
    "tgn:placetype":[
        "aat:300008347"
    ]
},
  "bbox": [],
  "geometry": {"coordinates":[77.766667,17.033333],"type":"Point"}
}