{
  "id": 1097738,
  "type": "Feature",
  "properties": {
    "tgn:hierarchy":[
        "tgn:1097738",
        "tgn:7000490",
        "tgn:1000006",
        "tgn:7001828",
        "tgn:7029392"
    ],
    "tgn:id":1097738,
    "tgn:name":"Narellan",
    "tgn:placetype":[
        "aat:300008347"
    ]
},
  "bbox": [],
  "geometry": {"coordinates":[150.7333,-34.0333],"type":"Point"}
}