{
  "id": 7515054,
  "type": "Feature",
  "properties": {
    "tgn:hierarchy":[
        "tgn:7515054",
        "tgn:1009227",
        "tgn:1000226",
        "tgn:1000006",
        "tgn:7016850",
        "tgn:7029392"
    ],
    "tgn:id":7515054,
    "tgn:name:en":"Canary Creek",
    "tgn:placetype":[
        "aat:300008699"
    ]
},
  "bbox": [],
  "geometry": {"coordinates":[170.966667,-42.766667],"type":"Point"}
}