<<<<<<< HEAD
{
  "id": 2402979,
  "type": "Feature",
  "properties": {
    "tgn:hierarchy":[
        "tgn:2402979",
        "tgn:1000001",
        "tgn:7012149",
        "tgn:1002742",
        "tgn:7007920",
        "tgn:7029392"
    ],
    "tgn:id":2402979,
    "tgn:name":"Houghs Mine",
    "tgn:placetype":[
        "aat:300000390"
    ]
},
  "bbox": [],
  "geometry": {"coordinates":[-119.7333,48.4667],"type":"Point"}
}
=======
{"geometry":{"type":"Point","coordinates":[-119.733300,48.466700]},"type":"Feature","properties":{"hierarchy":["tgn:2402979","tgn:1000001","tgn:7012149","tgn:1002742","tgn:7007920","tgn:7029392"],"placetype":["aat:300000390"],"id":2402979,"name:xx":"Houghs Mine"}}
>>>>>>> 03f74aca74312dbeaf24d7e61306dd6a786dc3d0
