{
  "id": 2512583,
  "type": "Feature",
  "properties": {
    "tgn:hierarchy":[
        "tgn:2512583",
        "tgn:2000455",
        "tgn:1000001",
        "tgn:7012149",
        "tgn:7007250",
        "tgn:7029392"
    ],
    "tgn:id":2512583,
    "tgn:name":"Mill Creek",
    "tgn:placetype":[
        "aat:300008706"
    ]
},
  "bbox": [],
  "geometry": {"coordinates":[-111.55,42.2333],"type":"Point"}
}