<<<<<<< HEAD
{
  "id": 7244921,
  "type": "Feature",
  "properties": {
    "tgn:hierarchy":[
        "tgn:7244921",
        "tgn:7003465",
        "tgn:1000003",
        "tgn:1000063",
        "tgn:4012014",
        "tgn:7029392"
    ],
    "tgn:id":7244921,
    "tgn:name":"Auf Beescht",
    "tgn:placetype":[
        "aat:300008347"
    ]
},
  "bbox": [],
  "geometry": {"coordinates":[5.766667,49.883333],"type":"Point"}
}
=======
{"geometry":{"type":"Point","coordinates":[5.766667,49.883333]},"type":"Feature","properties":{"hierarchy":["tgn:7244921","tgn:7003465","tgn:1000003","tgn:1000063","tgn:4012014","tgn:7029392"],"placetype":["aat:300008347"],"id":7244921,"name:xx":"Auf Beescht"}}
>>>>>>> 03f74aca74312dbeaf24d7e61306dd6a786dc3d0
