{
  "id": 2227949,
  "type": "Feature",
  "properties": {
    "tgn:hierarchy":[
        "tgn:2227949",
        "tgn:1000001",
        "tgn:7012149",
        "tgn:2002194",
        "tgn:7007919",
        "tgn:7029392"
    ],
    "tgn:id":2227949,
    "tgn:name":"Cedar Bluff Hollow",
    "tgn:placetype":[
        "aat:300008761"
    ]
},
  "bbox": [],
  "geometry": {"coordinates":[-81.8667,36.6167],"type":"Point"}
}