{
  "id": 2549939,
  "type": "Feature",
  "properties": {
    "tgn:hierarchy":[
        "tgn:2549939",
        "tgn:2001423",
        "tgn:1000001",
        "tgn:7012149",
        "tgn:7007564",
        "tgn:7029392"
    ],
    "tgn:id":2549939,
    "tgn:name":"North Wakefield",
    "tgn:placetype":[
        "aat:300008347"
    ]
},
  "bbox": [],
  "geometry": {"coordinates":[-71.05,43.6333],"type":"Point"}
}