<<<<<<< HEAD
{
  "id": 7054852,
  "type": "Feature",
  "properties": {
    "tgn:hierarchy":[
        "tgn:7054852",
        "tgn:1000003",
        "tgn:7003122",
        "tgn:1000080",
        "tgn:7029392"
    ],
    "tgn:id":7054852,
    "tgn:name":"Mollachella, Rocca",
    "tgn:placetype":[
        "aat:300011692"
    ]
},
  "bbox": [],
  "geometry": {"coordinates":[13.866667,37.083333],"type":"Point"}
}
=======
{"geometry":{"type":"Point","coordinates":[13.866667,37.083333]},"type":"Feature","properties":{"hierarchy":["tgn:7054852","tgn:1000003","tgn:7003122","tgn:1000080","tgn:7029392"],"placetype":["aat:300011692"],"id":7054852,"name:xx":"Mollachella, Rocca"}}
>>>>>>> 03f74aca74312dbeaf24d7e61306dd6a786dc3d0
