{
  "id": 1133531,
  "type": "Feature",
  "properties": {
    "tgn:hierarchy":[
        "tgn:1133531",
        "tgn:7003028",
        "tgn:1000003",
        "tgn:1000062",
        "tgn:7029392"
    ],
    "tgn:id":1133531,
    "tgn:name":"Katschbach",
    "tgn:placetype":[
        "aat:300008706"
    ]
},
  "bbox": [],
  "geometry": {"coordinates":[14.2833,47.1333],"type":"Point"}
}