{
  "id": 2197159,
  "type": "Feature",
  "properties": {
    "tgn:hierarchy":[
        "tgn:2197159",
        "tgn:1000001",
        "tgn:7012149",
        "tgn:1002877",
        "tgn:7007706",
        "tgn:7029392"
    ],
    "tgn:id":2197159,
    "tgn:name":"Brouse Run",
    "tgn:placetype":[
        "aat:300008699"
    ]
},
  "bbox": [],
  "geometry": {"coordinates":[-83.0667,38.7167],"type":"Point"}
}