{
  "id": 2597116,
  "type": "Feature",
  "properties": {
    "tgn:hierarchy":[
        "tgn:2597116",
        "tgn:1000001",
        "tgn:2001435",
        "tgn:7012149",
        "tgn:7007566",
        "tgn:7029392"
    ],
    "tgn:id":2597116,
    "tgn:name":"Powers Tank",
    "tgn:placetype":[
        "aat:300006191"
    ]
},
  "bbox": [],
  "geometry": {"coordinates":[-106.7833,32.7167],"type":"Point"}
}