{
  "id": 7459436,
  "type": "Feature",
  "properties": {
    "tgn:hierarchy":[
        "tgn:7459436",
        "tgn:7002444",
        "tgn:1000003",
        "tgn:7008094",
        "tgn:7008591",
        "tgn:7029392"
    ],
    "tgn:id":7459436,
    "tgn:name:en":"Orosay",
    "tgn:placetype":[
        "aat:300008791"
    ]
},
  "bbox": [],
  "geometry": {"coordinates":[-7.416667,57.033333],"type":"Point"}
}