{
  "id": 7233069,
  "type": "Feature",
  "properties": {
    "tgn:hierarchy":[
        "tgn:7233069",
        "tgn:7002715",
        "tgn:7002731",
        "tgn:1000003",
        "tgn:1000074",
        "tgn:7029392"
    ],
    "tgn:id":7233069,
    "tgn:name":"Korfalo\u00fa",
    "tgn:placetype":[
        "aat:300008347"
    ]
},
  "bbox": [],
  "geometry": {"coordinates":[23.183333,40.716667],"type":"Point"}
}