{
  "id": 2159531,
  "type": "Feature",
  "properties": {
    "tgn:hierarchy":[
        "tgn:2159531",
        "tgn:1000001",
        "tgn:7016172",
        "tgn:7012149",
        "tgn:2000161",
        "tgn:7029392"
    ],
    "tgn:id":2159531,
    "tgn:name":"Bee Mountain",
    "tgn:placetype":[
        "aat:300008798"
    ]
},
  "bbox": [],
  "geometry": {"coordinates":[-94.2333,34.4667],"type":"Point"}
}