<<<<<<< HEAD
{
  "id": 2764166,
  "type": "Feature",
  "properties": {
    "tgn:hierarchy":[
        "tgn:2764166",
        "tgn:1000001",
        "tgn:7012149",
        "tgn:7007157",
        "tgn:1002957",
        "tgn:7029392"
    ],
    "tgn:id":2764166,
    "tgn:name":"Wheeler Peak",
    "tgn:placetype":[
        "aat:300008798"
    ]
},
  "bbox": [],
  "geometry": {"coordinates":[-119.7167,38.0833],"type":"Point"}
}
=======
{"geometry":{"type":"Point","coordinates":[-119.716700,38.083300]},"type":"Feature","properties":{"hierarchy":["tgn:2764166","tgn:1000001","tgn:7012149","tgn:7007157","tgn:1002957","tgn:7029392"],"placetype":["aat:300008798"],"id":2764166,"name:xx":"Wheeler Peak"}}
>>>>>>> 03f74aca74312dbeaf24d7e61306dd6a786dc3d0
