{
  "id": 2248306,
  "type": "Feature",
  "properties": {
    "tgn:hierarchy":[
        "tgn:2248306",
        "tgn:1000001",
        "tgn:7012149",
        "tgn:7016021",
        "tgn:7007568",
        "tgn:7029392"
    ],
    "tgn:id":2248306,
    "tgn:name":"Cold Pond",
    "tgn:placetype":[
        "aat:300008680"
    ]
},
  "bbox": [],
  "geometry": {"coordinates":[-74.7667,44.4167],"type":"Point"}
}