{
  "id": 7081318,
  "type": "Feature",
  "properties": {
    "tgn:hierarchy":[
        "tgn:7081318",
        "tgn:1000003",
        "tgn:7003682",
        "tgn:7000084",
        "tgn:7029392"
    ],
    "tgn:id":7081318,
    "tgn:name":"Wingerts Berg",
    "tgn:placetype":[
        "aat:300008777"
    ]
},
  "bbox": [],
  "geometry": {"coordinates":[7.566667,49.766667],"type":"Point"}
}