{
  "id": 7542999,
  "type": "Feature",
  "properties": {
    "tgn:hierarchy":[
        "tgn:7542999",
        "tgn:7001242",
        "tgn:7016833",
        "tgn:7001336",
        "tgn:7029392"
    ],
    "tgn:id":7542999,
    "tgn:name:en":"Judayrah, Jabal",
    "tgn:placetype":[
        "aat:300008795"
    ]
},
  "bbox": [],
  "geometry": {"coordinates":[34.433735,28.890197],"type":"Point"}
}