{
  "id": 7440745,
  "type": "Feature",
  "properties": {
    "tgn:hierarchy":[
        "tgn:7440745",
        "tgn:1000001",
        "tgn:7005595",
        "tgn:7005560",
        "tgn:7029392"
    ],
    "tgn:id":7440745,
    "tgn:name":"Santa Apolonia",
    "tgn:placetype":[
        "aat:300008347"
    ]
},
  "bbox": [],
  "geometry": {"coordinates":[-106.283333,23.95],"type":"Point"}
}