<<<<<<< HEAD
{
  "id": 7374264,
  "type": "Feature",
  "properties": {
    "tgn:hierarchy":[
        "tgn:7374264",
        "tgn:7005586",
        "tgn:1000001",
        "tgn:7005560",
        "tgn:7029392"
    ],
    "tgn:id":7374264,
    "tgn:name":"La Malague\u00f1a, Cerro",
    "tgn:placetype":[
        "aat:300008795"
    ]
},
  "bbox": [],
  "geometry": {"coordinates":[-103.233333,19.716667],"type":"Point"}
}
=======
{"geometry":{"type":"Point","coordinates":[-103.233333,19.716667]},"type":"Feature","properties":{"hierarchy":["tgn:7374264","tgn:7005586","tgn:1000001","tgn:7005560","tgn:7029392"],"placetype":["aat:300008795"],"id":7374264,"name:xx":"La Malague\u00f1a, Cerro"}}
>>>>>>> 03f74aca74312dbeaf24d7e61306dd6a786dc3d0
