{
  "id": 2750159,
  "type": "Feature",
  "properties": {
    "tgn:hierarchy":[
        "tgn:2750159",
        "tgn:1000001",
        "tgn:7012149",
        "tgn:2001514",
        "tgn:7007709",
        "tgn:7029392"
    ],
    "tgn:id":2750159,
    "tgn:name":"Walton Crawley Branch",
    "tgn:placetype":[
        "aat:300008699"
    ]
},
  "bbox": [],
  "geometry": {"coordinates":[-81.8833,35.6333],"type":"Point"}
}