{
  "id": 2172731,
  "type": "Feature",
  "properties": {
    "tgn:hierarchy":[
        "tgn:2172731",
        "tgn:1000001",
        "tgn:7012149",
        "tgn:2001716",
        "tgn:7007708",
        "tgn:7029392"
    ],
    "tgn:id":2172731,
    "tgn:name":"Bills Creek",
    "tgn:placetype":[
        "aat:300008706"
    ]
},
  "bbox": [],
  "geometry": {"coordinates":[-122.4333,43.5667],"type":"Point"}
}