{
  "id": 2201448,
  "type": "Feature",
  "properties": {
    "tgn:hierarchy":[
        "tgn:2201448",
        "tgn:1000001",
        "tgn:7012149",
        "tgn:2000927",
        "tgn:7007515",
        "tgn:7029392"
    ],
    "tgn:id":2201448,
    "tgn:name":"Buck Brook",
    "tgn:placetype":[
        "aat:300008699"
    ]
},
  "bbox": [],
  "geometry": {"coordinates":[-68.4833,45.2167],"type":"Point"}
}