{
  "id": 7213167,
  "type": "Feature",
  "properties": {
    "tgn:hierarchy":[
        "tgn:7213167",
        "tgn:1000003",
        "tgn:7003688",
        "tgn:7000084",
        "tgn:7029392"
    ],
    "tgn:id":7213167,
    "tgn:name":"Bondelum",
    "tgn:placetype":[
        "aat:300008347"
    ]
},
  "bbox": [],
  "geometry": {"coordinates":[9.266667,54.566667],"type":"Point"}
}