{
  "id": 2671352,
  "type": "Feature",
  "properties": {
    "tgn:hierarchy":[
        "tgn:2671352",
        "tgn:1000001",
        "tgn:7012149",
        "tgn:2002158",
        "tgn:7007919",
        "tgn:7029392"
    ],
    "tgn:id":2671352,
    "tgn:name":"Smith Hill",
    "tgn:placetype":[
        "aat:300008798"
    ]
},
  "bbox": [],
  "geometry": {"coordinates":[-80.2667,37.0333],"type":"Point"}
}