{
  "id": 2683946,
  "type": "Feature",
  "properties": {
    "tgn:hierarchy":[
        "tgn:2683946",
        "tgn:1000001",
        "tgn:7012149",
        "tgn:1002701",
        "tgn:7007706",
        "tgn:7029392"
    ],
    "tgn:id":2683946,
    "tgn:name":"Spencer",
    "tgn:placetype":[
        "aat:300008347"
    ]
},
  "bbox": [],
  "geometry": {"coordinates":[-81.8833,40.05],"type":"Point"}
}