{
  "id": 2409350,
  "type": "Feature",
  "properties": {
    "tgn:hierarchy":[
        "tgn:2409350",
        "tgn:1000001",
        "tgn:7012149",
        "tgn:1002768",
        "tgn:7007240",
        "tgn:7029392"
    ],
    "tgn:id":2409350,
    "tgn:name":"Ida, Lake",
    "tgn:placetype":[
        "aat:300008680"
    ]
},
  "bbox": [],
  "geometry": {"coordinates":[-80.0667,26.4667],"type":"Point"}
}