{
  "id": 2222245,
  "type": "Feature",
  "properties": {
    "tgn:hierarchy":[
        "tgn:2222245",
        "tgn:1000001",
        "tgn:7012149",
        "tgn:1002980",
        "tgn:7007826",
        "tgn:7029392"
    ],
    "tgn:id":2222245,
    "tgn:name":"Carolina",
    "tgn:placetype":[
        "aat:300008347"
    ]
},
  "bbox": [],
  "geometry": {"coordinates":[-95.3833,30.7833],"type":"Point"}
}