{
  "id": 2453954,
  "type": "Feature",
  "properties": {
    "tgn:hierarchy":[
        "tgn:2453954",
        "tgn:1000001",
        "tgn:7012149",
        "tgn:7007158",
        "tgn:7029392"
    ],
    "tgn:id":2453954,
    "tgn:name":"Little Creek",
    "tgn:placetype":[
        "aat:300008706"
    ]
},
  "bbox": [],
  "geometry": {"coordinates":[-107.7667,40.1667],"type":"Point"}
}