{
  "id": 2637622,
  "type": "Feature",
  "properties": {
    "tgn:hierarchy":[
        "tgn:2637622",
        "tgn:1000001",
        "tgn:7012149",
        "tgn:2002371",
        "tgn:7007923",
        "tgn:7029392"
    ],
    "tgn:id":2637622,
    "tgn:name":"Saint Marys Spring",
    "tgn:placetype":[
        "aat:300008697"
    ]
},
  "bbox": [],
  "geometry": {"coordinates":[-108.45,42.35],"type":"Point"}
}