{
  "id": 2732490,
  "type": "Feature",
  "properties": {
    "tgn:hierarchy":[
        "tgn:2732490",
        "tgn:1000001",
        "tgn:7012149",
        "tgn:2001908",
        "tgn:7007825",
        "tgn:7029392"
    ],
    "tgn:id":2732490,
    "tgn:name":"Turkey Cock Branch",
    "tgn:placetype":[
        "aat:300008699"
    ]
},
  "bbox": [],
  "geometry": {"coordinates":[-84.9667,35.65],"type":"Point"}
}