{
  "id": 7306481,
  "type": "Feature",
  "properties": {
    "tgn:hierarchy":[
        "tgn:7306481",
        "tgn:7002759",
        "tgn:7002845",
        "tgn:1000003",
        "tgn:1000095",
        "tgn:7029392"
    ],
    "tgn:id":7306481,
    "tgn:name":"Malej\u00e1n",
    "tgn:placetype":[
        "aat:300008347"
    ]
},
  "bbox": [],
  "geometry": {"coordinates":[-1.55,41.833333],"type":"Point"}
}