{
  "id": 7146978,
  "type": "Feature",
  "properties": {
    "tgn:hierarchy":[
        "tgn:7146978",
        "tgn:1000003",
        "tgn:7000094",
        "tgn:7000084",
        "tgn:7029392"
    ],
    "tgn:id":7146978,
    "tgn:name":"Klein Petershagen",
    "tgn:placetype":[
        "aat:300008347"
    ]
},
  "bbox": [],
  "geometry": {"coordinates":[13.283333,54.133333],"type":"Point"}
}