{
  "id": 1064315,
  "type": "Feature",
  "properties": {
    "tgn:hierarchy":[
        "tgn:1064315",
        "tgn:7003748",
        "tgn:1000003",
        "tgn:7011731",
        "tgn:7029392"
    ],
    "tgn:id":1064315,
    "tgn:name":"Ramosch",
    "tgn:placetype":[
        "aat:300008347"
    ]
},
  "bbox": [],
  "geometry": {"coordinates":[10.3833,46.85],"type":"Point"}
}