{
  "id": 2704834,
  "type": "Feature",
  "properties": {
    "tgn:hierarchy":[
        "tgn:2704834",
        "tgn:1002178",
        "tgn:1000001",
        "tgn:7012149",
        "tgn:7007565",
        "tgn:7029392"
    ],
    "tgn:id":2704834,
    "tgn:name":"Sunset Lake",
    "tgn:placetype":[
        "aat:300006191"
    ]
},
  "bbox": [],
  "geometry": {"coordinates":[-74.15,41.0833],"type":"Point"}
}