{
  "id": 7446259,
  "type": "Feature",
  "properties": {
    "tgn:hierarchy":[
        "tgn:7446259",
        "tgn:7002443",
        "tgn:1000003",
        "tgn:7018993",
        "tgn:7008591",
        "tgn:7029392"
    ],
    "tgn:id":7446259,
    "tgn:name:en":"Rhoscrowther",
    "tgn:placetype":[
        "aat:300008347"
    ]
},
  "bbox": [],
  "geometry": {"coordinates":[-5.030833,51.679444],"type":"Point"}
}