{
  "id": 2285587,
  "type": "Feature",
  "properties": {
    "tgn:hierarchy":[
        "tgn:2285587",
        "tgn:1000001",
        "tgn:7012149",
        "tgn:7007158",
        "tgn:7029392"
    ],
    "tgn:id":2285587,
    "tgn:name":"Devils Hole",
    "tgn:placetype":[
        "aat:300008761"
    ]
},
  "bbox": [],
  "geometry": {"coordinates":[-106.9833,38.1333],"type":"Point"}
}