{
  "id": 2511220,
  "type": "Feature",
  "properties": {
    "tgn:hierarchy":[
        "tgn:2511220",
        "tgn:1000001",
        "tgn:7012149",
        "tgn:7007525",
        "tgn:7029392"
    ],
    "tgn:id":2511220,
    "tgn:name":"Mike Kern Hills",
    "tgn:placetype":[
        "aat:300008798"
    ]
},
  "bbox": [],
  "geometry": {"coordinates":[-103.4833,42.85],"type":"Point"}
}