{
  "id": 2295663,
  "type": "Feature",
  "properties": {
    "tgn:hierarchy":[
        "tgn:2295663",
        "tgn:2000090",
        "tgn:1000001",
        "tgn:7006451",
        "tgn:7012149",
        "tgn:7029392"
    ],
    "tgn:id":2295663,
    "tgn:name":"Driveway Hall Spring",
    "tgn:placetype":[
        "aat:300008697"
    ]
},
  "bbox": [],
  "geometry": {"coordinates":[-109.5667,34.1333],"type":"Point"}
}