<<<<<<< HEAD
{
  "id": 7172073,
  "type": "Feature",
  "properties": {
    "tgn:hierarchy":[
        "tgn:7172073",
        "tgn:1000003",
        "tgn:7003677",
        "tgn:7000084",
        "tgn:7029392"
    ],
    "tgn:id":7172073,
    "tgn:name":"Herrig",
    "tgn:placetype":[
        "aat:300008347"
    ]
},
  "bbox": [],
  "geometry": {"coordinates":[6.716667,50.8],"type":"Point"}
}
=======
{"geometry":{"type":"Point","coordinates":[6.716667,50.800000]},"type":"Feature","properties":{"hierarchy":["tgn:7172073","tgn:1000003","tgn:7003677","tgn:7000084","tgn:7029392"],"placetype":["aat:300008347"],"id":7172073,"name:xx":"Herrig"}}
>>>>>>> 03f74aca74312dbeaf24d7e61306dd6a786dc3d0
