{
  "id": 2059812,
  "type": "Feature",
  "properties": {
    "tgn:hierarchy":[
        "tgn:2059812",
        "tgn:1000001",
        "tgn:7012149",
        "tgn:1002671",
        "tgn:7007523",
        "tgn:7029392"
    ],
    "tgn:id":2059812,
    "tgn:name":"Mount Pleasant",
    "tgn:placetype":[
        "aat:300008347"
    ]
},
  "bbox": [],
  "geometry": {"coordinates":[-92.5167,38.3667],"type":"Point"}
}