{
  "id": 7228922,
  "type": "Feature",
  "properties": {
    "tgn:hierarchy":[
        "tgn:7228922",
        "tgn:7002745",
        "tgn:7017076",
        "tgn:1000003",
        "tgn:1000074",
        "tgn:7029392"
    ],
    "tgn:id":7228922,
    "tgn:name":"L\u00e9vki, \u00d3rmos",
    "tgn:placetype":[
        "aat:300132316"
    ]
},
  "bbox": [],
  "geometry": {"coordinates":[22.983333,36.483333],"type":"Point"}
}