{
  "id": 2295698,
  "type": "Feature",
  "properties": {
    "tgn:hierarchy":[
        "tgn:2295698",
        "tgn:1000001",
        "tgn:2000458",
        "tgn:7012149",
        "tgn:7007250",
        "tgn:7029392"
    ],
    "tgn:id":2295698,
    "tgn:name":"Drop Canyon",
    "tgn:placetype":[
        "aat:300008761"
    ]
},
  "bbox": [],
  "geometry": {"coordinates":[-114.0667,43.6167],"type":"Point"}
}