{
  "id": 1138441,
  "type": "Feature",
  "properties": {
    "tgn:hierarchy":[
        "tgn:1138441",
        "tgn:1000004",
        "tgn:7011496",
        "tgn:7002435",
        "tgn:7029392"
    ],
    "tgn:id":1138441,
    "tgn:name":"Sovetskoye",
    "tgn:placetype":[
        "aat:300008347"
    ]
},
  "bbox": [],
  "geometry": {"coordinates":[43.5667,43.2833],"type":"Point"}
}