{
  "id": 7170663,
  "type": "Feature",
  "properties": {
    "tgn:hierarchy":[
        "tgn:7170663",
        "tgn:7003669",
        "tgn:1000003",
        "tgn:7000084",
        "tgn:7029392"
    ],
    "tgn:id":7170663,
    "tgn:name":"Hinflucht",
    "tgn:placetype":[
        "aat:300000206"
    ]
},
  "bbox": [],
  "geometry": {"coordinates":[12.366667,48.716667],"type":"Point"}
}