{
  "id": 7510329,
  "type": "Feature",
  "properties": {
    "tgn:hierarchy":[
        "tgn:7510329",
        "tgn:7016670",
        "tgn:1008380",
        "tgn:1000226",
        "tgn:1000006",
        "tgn:7029392"
    ],
    "tgn:id":7510329,
    "tgn:name:en":"Te Kapu",
    "tgn:placetype":[
        "aat:300008795"
    ]
},
  "bbox": [],
  "geometry": {"coordinates":[177.883333,-39.15],"type":"Point"}
}