{
  "id": 7417755,
  "type": "Feature",
  "properties": {
    "tgn:hierarchy":[
        "tgn:7417755",
        "tgn:1000001",
        "tgn:7005591",
        "tgn:7005560",
        "tgn:7029392"
    ],
    "tgn:id":7417755,
    "tgn:name:es":"La Providencia",
    "tgn:placetype":[
        "aat:300008347"
    ]
},
  "bbox": [],
  "geometry": {"coordinates":[-97.6875,17.974167],"type":"Point"}
}