{
  "id": 7408720,
  "type": "Feature",
  "properties": {
    "tgn:hierarchy":[
        "tgn:7408720",
        "tgn:7005580",
        "tgn:1000001",
        "tgn:7005560",
        "tgn:7029392"
    ],
    "tgn:id":7408720,
    "tgn:name":"Francisco J. Grajales",
    "tgn:placetype":[
        "aat:300008347"
    ]
},
  "bbox": [],
  "geometry": {"coordinates":[-90.625,16.116667],"type":"Point"}
}