{
  "id": 2467500,
  "type": "Feature",
  "properties": {
    "tgn:hierarchy":[
        "tgn:2467500",
        "tgn:1000001",
        "tgn:7012149",
        "tgn:2001254",
        "tgn:7007523",
        "tgn:7029392"
    ],
    "tgn:id":2467500,
    "tgn:name":"Long Hollow",
    "tgn:placetype":[
        "aat:300008761"
    ]
},
  "bbox": [],
  "geometry": {"coordinates":[-90.8833,38.0667],"type":"Point"}
}