{
  "id": 7331853,
  "type": "Feature",
  "properties": {
    "tgn:hierarchy":[
        "tgn:7331853",
        "tgn:7002825",
        "tgn:7016622",
        "tgn:1000003",
        "tgn:1000095",
        "tgn:7029392"
    ],
    "tgn:id":7331853,
    "tgn:name":"La Caleta",
    "tgn:placetype":[
        "aat:300132317"
    ]
},
  "bbox": [],
  "geometry": {"coordinates":[-13.416667,29.183333],"type":"Point"}
}