{
  "id": 7568203,
  "type": "Feature",
  "properties": {
    "tgn:hierarchy":[
        "tgn:7568203",
        "tgn:1001828",
        "tgn:1000004",
        "tgn:7000198",
        "tgn:7029392"
    ],
    "tgn:id":7568203,
    "tgn:name:en":"Mans\u0101npalli",
    "tgn:placetype":[
        "aat:300008347"
    ]
},
  "bbox": [],
  "geometry": {"coordinates":[78.053333,17.455],"type":"Point"}
}