{
  "id": 7222165,
  "type": "Feature",
  "properties": {
    "tgn:hierarchy":[
        "tgn:7222165",
        "tgn:7002709",
        "tgn:7002705",
        "tgn:1000003",
        "tgn:1000074",
        "tgn:7029392"
    ],
    "tgn:id":7222165,
    "tgn:name":"S\u00fdvota",
    "tgn:placetype":[
        "aat:300008347"
    ]
},
  "bbox": [],
  "geometry": {"coordinates":[20.25,39.406667],"type":"Point"}
}