{
  "id": 1124462,
  "type": "Feature",
  "properties": {
    "tgn:hierarchy":[
        "tgn:1124462",
        "tgn:1000715",
        "tgn:1000001",
        "tgn:7005554",
        "tgn:7029392"
    ],
    "tgn:id":1124462,
    "tgn:name":"Guayape, R\u00edo",
    "tgn:placetype":[
        "aat:300008707"
    ]
},
  "bbox": [],
  "geometry": {"coordinates":[-85.983,14.416],"type":"Point"}
}