<<<<<<< HEAD
{
  "id": 2338237,
  "type": "Feature",
  "properties": {
    "tgn:hierarchy":[
        "tgn:2338237",
        "tgn:1000001",
        "tgn:7012149",
        "tgn:7029392"
    ],
    "tgn:id":2338237,
    "tgn:name":"Fox Run",
    "tgn:placetype":[
        "aat:300008699"
    ]
},
  "bbox": [],
  "geometry": {"coordinates":[-84.8167,39.2],"type":"Point"}
}
=======
{"geometry":{"type":"Point","coordinates":[-84.816700,39.200000]},"type":"Feature","properties":{"hierarchy":["tgn:2338237","tgn:1000001","tgn:7012149","tgn:7029392"],"placetype":["aat:300008699"],"id":2338237,"name:xx":"Fox Run"}}
>>>>>>> 03f74aca74312dbeaf24d7e61306dd6a786dc3d0
