{
  "id": 1101679,
  "type": "Feature",
  "properties": {
    "tgn:hierarchy":[
        "tgn:1101679",
        "tgn:7006477",
        "tgn:1001522",
        "tgn:1000002",
        "tgn:7029392"
    ],
    "tgn:id":1101679,
    "tgn:name":"Los Glaciares, Parque Nacional",
    "tgn:placetype":[
        "aat:300008189",
        "aat:300263063"
    ]
},
  "bbox": [],
  "geometry": {"coordinates":[-73.0833,-49.8667],"type":"Point"}
}