{
  "id": 2461826,
  "type": "Feature",
  "properties": {
    "tgn:hierarchy":[
        "tgn:2461826",
        "tgn:2000945",
        "tgn:1000001",
        "tgn:7012149",
        "tgn:7007520",
        "tgn:7029392"
    ],
    "tgn:id":2461826,
    "tgn:name":"Little Torch Lake",
    "tgn:placetype":[
        "aat:300008680"
    ]
},
  "bbox": [],
  "geometry": {"coordinates":[-85.3167,45.1833],"type":"Point"}
}