{
  "id": 2167087,
  "type": "Feature",
  "properties": {
    "tgn:hierarchy":[
        "tgn:2167087",
        "tgn:1000001",
        "tgn:7012149",
        "tgn:2002123",
        "tgn:7007827",
        "tgn:7029392"
    ],
    "tgn:id":2167087,
    "tgn:name":"Big Canyon",
    "tgn:placetype":[
        "aat:300008761"
    ]
},
  "bbox": [],
  "geometry": {"coordinates":[-112.5333,40.25],"type":"Point"}
}