{
  "id": 7228008,
  "type": "Feature",
  "properties": {
    "tgn:hierarchy":[
        "tgn:7228008",
        "tgn:1042193",
        "tgn:7002705",
        "tgn:1000003",
        "tgn:1000074",
        "tgn:7029392"
    ],
    "tgn:id":7228008,
    "tgn:name":"Kastrosyki\u00e1, \u00c1kra",
    "tgn:placetype":[
        "aat:300008850"
    ]
},
  "bbox": [],
  "geometry": {"coordinates":[20.635278,39.093889],"type":"Point"}
}