{
  "id": 2376532,
  "type": "Feature",
  "properties": {
    "tgn:hierarchy":[
        "tgn:2376532",
        "tgn:1000001",
        "tgn:2000317",
        "tgn:7012149",
        "tgn:7007248",
        "tgn:7029392"
    ],
    "tgn:id":2376532,
    "tgn:name":"Hards Pond",
    "tgn:placetype":[
        "aat:300006191"
    ]
},
  "bbox": [],
  "geometry": {"coordinates":[-84.8833,32.3167],"type":"Point"}
}