{
  "id": 7250259,
  "type": "Feature",
  "properties": {
    "tgn:hierarchy":[
        "tgn:7250259",
        "tgn:7007877",
        "tgn:1000003",
        "tgn:1000063",
        "tgn:4012014",
        "tgn:7029392"
    ],
    "tgn:id":7250259,
    "tgn:name":"Moulin, \u00c9tang du",
    "tgn:placetype":[
        "aat:300008680"
    ]
},
  "bbox": [],
  "geometry": {"coordinates":[4.266667,50.133333],"type":"Point"}
}