{
  "id": 7002034,
  "type": "Feature",
  "properties": {
    "tgn:hierarchy":[
        "tgn:7002034",
        "tgn:7000530",
        "tgn:7002030",
        "tgn:7000529",
        "tgn:1000006",
        "tgn:7029392"
    ],
    "tgn:id":7002034,
    "tgn:name":"Pangai",
    "tgn:placetype":[
        "aat:300008347",
        "aat:300008372"
    ]
},
  "bbox": [],
  "geometry": {"coordinates":[-174.3833,-19.8333],"type":"Point"}
}