{
  "id": 7223319,
  "type": "Feature",
  "properties": {
    "tgn:hierarchy":[
        "tgn:7223319",
        "tgn:7002741",
        "tgn:7017076",
        "tgn:1000003",
        "tgn:1000074",
        "tgn:7029392"
    ],
    "tgn:id":7223319,
    "tgn:name":"S\u00e9litsa",
    "tgn:placetype":[
        "aat:300008347"
    ]
},
  "bbox": [],
  "geometry": {"coordinates":[22.133333,38.183333],"type":"Point"}
}