{
  "id": 7561432,
  "type": "Feature",
  "properties": {
    "tgn:hierarchy":[
        "tgn:7561432",
        "tgn:1000004",
        "tgn:7000198",
        "tgn:7016722",
        "tgn:7029392"
    ],
    "tgn:id":7561432,
    "tgn:name:en":"Arwal",
    "tgn:placetype":[
        "aat:300008347"
    ]
},
  "bbox": [],
  "geometry": {"coordinates":[79.7932,27.2269],"type":"Point"}
}