{
  "id": 7394282,
  "type": "Feature",
  "properties": {
    "tgn:hierarchy":[
        "tgn:7394282",
        "tgn:1001836",
        "tgn:1000001",
        "tgn:7005560",
        "tgn:7029392"
    ],
    "tgn:id":7394282,
    "tgn:name":"San Buto",
    "tgn:placetype":[
        "aat:300005433"
    ]
},
  "bbox": [],
  "geometry": {"coordinates":[-112.033333,24.75],"type":"Point"}
}