{
  "id": 2072028,
  "type": "Feature",
  "properties": {
    "tgn:hierarchy":[
        "tgn:2072028",
        "tgn:1000001",
        "tgn:7012149",
        "tgn:1002926",
        "tgn:7007568",
        "tgn:7029392"
    ],
    "tgn:id":2072028,
    "tgn:name":"Roosa Gap",
    "tgn:placetype":[
        "aat:300008347"
    ]
},
  "bbox": [],
  "geometry": {"coordinates":[-74.4167,41.5833],"type":"Point"}
}