{
  "id": 2463899,
  "type": "Feature",
  "properties": {
    "tgn:hierarchy":[
        "tgn:2463899",
        "tgn:1000001",
        "tgn:2001260",
        "tgn:7012149",
        "tgn:7007524",
        "tgn:7029392"
    ],
    "tgn:id":2463899,
    "tgn:name":"Lockridge Spring",
    "tgn:placetype":[
        "aat:300008697"
    ]
},
  "bbox": [],
  "geometry": {"coordinates":[-113.0167,45.2667],"type":"Point"}
}