{
  "id": 7502847,
  "type": "Feature",
  "properties": {
    "tgn:hierarchy":[
        "tgn:7502847",
        "tgn:1000004",
        "tgn:7471332",
        "tgn:1000141",
        "tgn:7029392"
    ],
    "tgn:id":7502847,
    "tgn:name":"Fucuo",
    "tgn:placetype":[
        "aat:300008347"
    ]
},
  "bbox": [],
  "geometry": {"coordinates":[120.998056,24.881389],"type":"Point"}
}