{
  "id": 2502303,
  "type": "Feature",
  "properties": {
    "tgn:hierarchy":[
        "tgn:2502303",
        "tgn:1000001",
        "tgn:7016172",
        "tgn:7012149",
        "tgn:2000177",
        "tgn:7029392"
    ],
    "tgn:id":2502303,
    "tgn:name":"McKinney Hill",
    "tgn:placetype":[
        "aat:300008798"
    ]
},
  "bbox": [],
  "geometry": {"coordinates":[-91.9167,35.25],"type":"Point"}
}