{
  "id": 7034217,
  "type": "Feature",
  "properties": {
    "tgn:hierarchy":[
        "tgn:7034217",
        "tgn:1003468",
        "tgn:1000003",
        "tgn:7010380",
        "tgn:1000080",
        "tgn:7029392"
    ],
    "tgn:id":7034217,
    "tgn:name":"Cimalo, Canale del",
    "tgn:placetype":[
        "aat:300008699"
    ]
},
  "bbox": [],
  "geometry": {"coordinates":[18.060556,40.545278],"type":"Point"}
}