<<<<<<< HEAD
{
  "id": 2339022,
  "type": "Feature",
  "properties": {
    "tgn:hierarchy":[
        "tgn:2339022",
        "tgn:1000001",
        "tgn:7012149",
        "tgn:2000234",
        "tgn:7007158",
        "tgn:7029392"
    ],
    "tgn:id":2339022,
    "tgn:name":"Franklin Mesa",
    "tgn:placetype":[
        "aat:300008798"
    ]
},
  "bbox": [],
  "geometry": {"coordinates":[-107.9833,38.4833],"type":"Point"}
}
=======
{"geometry":{"type":"Point","coordinates":[-107.983300,38.483300]},"type":"Feature","properties":{"hierarchy":["tgn:2339022","tgn:1000001","tgn:7012149","tgn:2000234","tgn:7007158","tgn:7029392"],"placetype":["aat:300008798"],"id":2339022,"name:xx":"Franklin Mesa"}}
>>>>>>> 03f74aca74312dbeaf24d7e61306dd6a786dc3d0
