{
  "id": 2132743,
  "type": "Feature",
  "properties": {
    "tgn:hierarchy":[
        "tgn:2132743",
        "tgn:1000001",
        "tgn:2002106",
        "tgn:7012149",
        "tgn:7007827",
        "tgn:7029392"
    ],
    "tgn:id":2132743,
    "tgn:name":"Anchorage",
    "tgn:placetype":[
        "aat:300008347"
    ]
},
  "bbox": [],
  "geometry": {"coordinates":[-112.0167,41.0833],"type":"Point"}
}