{
  "id": 2356138,
  "type": "Feature",
  "properties": {
    "tgn:hierarchy":[
        "tgn:2356138",
        "tgn:1000001",
        "tgn:7012149",
        "tgn:1002596",
        "tgn:7007706",
        "tgn:7029392"
    ],
    "tgn:id":2356138,
    "tgn:name":"Goose Run",
    "tgn:placetype":[
        "aat:300008699"
    ]
},
  "bbox": [],
  "geometry": {"coordinates":[-82.55,40.2333],"type":"Point"}
}