{
  "id": 2110992,
  "type": "Feature",
  "properties": {
    "tgn:hierarchy":[
        "tgn:2110992",
        "tgn:1000001",
        "tgn:7012149",
        "tgn:2002194",
        "tgn:7007919",
        "tgn:7029392"
    ],
    "tgn:id":2110992,
    "tgn:name":"Cedar Bluff",
    "tgn:placetype":[
        "aat:300008347",
        "aat:300387210"
    ]
},
  "bbox": [],
  "geometry": {"coordinates":[-81.85,36.6333],"type":"Point"}
}