{
  "id": 2495159,
  "type": "Feature",
  "properties": {
    "tgn:hierarchy":[
        "tgn:2495159",
        "tgn:1000001",
        "tgn:7012149",
        "tgn:2000493",
        "tgn:7007250",
        "tgn:7029392"
    ],
    "tgn:id":2495159,
    "tgn:name":"Mary Alice Lake",
    "tgn:placetype":[
        "aat:300008680"
    ]
},
  "bbox": [],
  "geometry": {"coordinates":[-114.4333,42.5833],"type":"Point"}
}