{
  "id": 2479739,
  "type": "Feature",
  "properties": {
    "tgn:hierarchy":[
        "tgn:2479739",
        "tgn:1000001",
        "tgn:2000669",
        "tgn:7012149",
        "tgn:7007254",
        "tgn:7029392"
    ],
    "tgn:id":2479739,
    "tgn:name":"Lake Creek",
    "tgn:placetype":[
        "aat:300008706"
    ]
},
  "bbox": [],
  "geometry": {"coordinates":[-96.0333,37.0333],"type":"Point"}
}