{
  "id": 2639867,
  "type": "Feature",
  "properties": {
    "tgn:hierarchy":[
        "tgn:2639867",
        "tgn:1000001",
        "tgn:7012149",
        "tgn:2001420",
        "tgn:7007526",
        "tgn:7029392"
    ],
    "tgn:id":2639867,
    "tgn:name":"Sammy Springs",
    "tgn:placetype":[
        "aat:300008697"
    ]
},
  "bbox": [],
  "geometry": {"coordinates":[-115.3167,39.4333],"type":"Point"}
}