{
  "id": 7357664,
  "type": "Feature",
  "properties": {
    "tgn:hierarchy":[
        "tgn:7357664",
        "tgn:1000001",
        "tgn:1001960",
        "tgn:7005560",
        "tgn:7029392"
    ],
    "tgn:id":7357664,
    "tgn:name":"Culebra, Cerro",
    "tgn:placetype":[
        "aat:300008795"
    ]
},
  "bbox": [],
  "geometry": {"coordinates":[-110.55,29.316667],"type":"Point"}
}