{
  "id": 2546825,
  "type": "Feature",
  "properties": {
    "tgn:hierarchy":[
        "tgn:2546825",
        "tgn:1000001",
        "tgn:2001409",
        "tgn:7012149",
        "tgn:7007526",
        "tgn:7029392"
    ],
    "tgn:id":2546825,
    "tgn:name":"North Fork Mississippi Canyon",
    "tgn:placetype":[
        "aat:300008761"
    ]
},
  "bbox": [],
  "geometry": {"coordinates":[-118.0667,39.8833],"type":"Point"}
}