<<<<<<< HEAD
{
  "id": 2400372,
  "type": "Feature",
  "properties": {
    "tgn:hierarchy":[
        "tgn:2400372",
        "tgn:2002240",
        "tgn:1000001",
        "tgn:7012149",
        "tgn:7007920",
        "tgn:7029392"
    ],
    "tgn:id":2400372,
    "tgn:name":"Horse Heaven",
    "tgn:placetype":[
        "aat:300008347"
    ]
},
  "bbox": [],
  "geometry": {"coordinates":[-119.5333,46.1],"type":"Point"}
}
=======
{"geometry":{"type":"Point","coordinates":[-119.533300,46.100000]},"type":"Feature","properties":{"hierarchy":["tgn:2400372","tgn:2002240","tgn:1000001","tgn:7012149","tgn:7007920","tgn:7029392"],"placetype":["aat:300008347"],"id":2400372,"name:xx":"Horse Heaven"}}
>>>>>>> 03f74aca74312dbeaf24d7e61306dd6a786dc3d0
