{
  "id": 2431467,
  "type": "Feature",
  "properties": {
    "tgn:hierarchy":[
        "tgn:2431467",
        "tgn:7006450",
        "tgn:1000001",
        "tgn:7012149",
        "tgn:2000082",
        "tgn:7029392"
    ],
    "tgn:id":2431467,
    "tgn:name":"Karta Bay",
    "tgn:placetype":[
        "aat:300132316"
    ]
},
  "bbox": [],
  "geometry": {"coordinates":[-132.5333,55.5667],"type":"Point"}
}