<<<<<<< HEAD
{
  "id": 7480921,
  "type": "Feature",
  "properties": {
    "tgn:hierarchy":[
        "tgn:7480921",
        "tgn:1000004",
        "tgn:1000454",
        "tgn:1000141",
        "tgn:7029392"
    ],
    "tgn:id":7480921,
    "tgn:name":"Zhengoutou",
    "tgn:placetype":[
        "aat:300008347"
    ]
},
  "bbox": [],
  "geometry": {"coordinates":[121.34528,25.118268],"type":"Point"}
}
=======
{"geometry":{"type":"Point","coordinates":[121.345280,25.118268]},"type":"Feature","properties":{"hierarchy":["tgn:7480921","tgn:1000004","tgn:1000454","tgn:1000141","tgn:7029392"],"placetype":["aat:300008347"],"id":7480921,"name:xx":"Zhengoutou"}}
>>>>>>> 03f74aca74312dbeaf24d7e61306dd6a786dc3d0
