{
  "id": 7480921,
  "type": "Feature",
  "properties": {
    "tgn:hierarchy":[
        "tgn:7480921",
        "tgn:1000004",
        "tgn:1000454",
        "tgn:1000141",
        "tgn:7029392"
    ],
    "tgn:id":7480921,
    "tgn:name":"Zhengoutou",
    "tgn:placetype":[
        "aat:300008347"
    ]
},
  "bbox": [],
  "geometry": {"coordinates":[121.34528,25.118268],"type":"Point"}
}