{
  "id": 2343976,
  "type": "Feature",
  "properties": {
    "tgn:hierarchy":[
        "tgn:2343976",
        "tgn:1008293",
        "tgn:1000001",
        "tgn:1002705",
        "tgn:7012149",
        "tgn:7007517",
        "tgn:7029392"
    ],
    "tgn:id":2343976,
    "tgn:name":"Galls, The",
    "tgn:placetype":[
        "aat:300008794"
    ]
},
  "bbox": [],
  "geometry": {"coordinates":[-70.0167,41.3667],"type":"Point"}
}