{
  "id": 2378311,
  "type": "Feature",
  "properties": {
    "tgn:hierarchy":[
        "tgn:2378311",
        "tgn:1000001",
        "tgn:7012149",
        "tgn:2002060",
        "tgn:7007826",
        "tgn:7029392"
    ],
    "tgn:id":2378311,
    "tgn:name":"Harris Spring",
    "tgn:placetype":[
        "aat:300008697"
    ]
},
  "bbox": [],
  "geometry": {"coordinates":[-99.6167,29.7167],"type":"Point"}
}