<<<<<<< HEAD
{
  "id": 2400010,
  "type": "Feature",
  "properties": {
    "tgn:hierarchy":[
        "tgn:2400010",
        "tgn:1000001",
        "tgn:7006451",
        "tgn:7012149",
        "tgn:2000103",
        "tgn:7029392"
    ],
    "tgn:id":2400010,
    "tgn:name":"Horse Creek",
    "tgn:placetype":[
        "aat:300008706"
    ]
},
  "bbox": [],
  "geometry": {"coordinates":[-112.4167,33.9333],"type":"Point"}
}
=======
{"geometry":{"type":"Point","coordinates":[-112.416700,33.933300]},"type":"Feature","properties":{"hierarchy":["tgn:2400010","tgn:1000001","tgn:7006451","tgn:7012149","tgn:2000103","tgn:7029392"],"placetype":["aat:300008706"],"id":2400010,"name:xx":"Horse Creek"}}
>>>>>>> 03f74aca74312dbeaf24d7e61306dd6a786dc3d0
