{
  "id": 2729201,
  "type": "Feature",
  "properties": {
    "tgn:hierarchy":[
        "tgn:2729201",
        "tgn:1000001",
        "tgn:2001409",
        "tgn:7012149",
        "tgn:7007526",
        "tgn:7029392"
    ],
    "tgn:id":2729201,
    "tgn:name":"Trinity",
    "tgn:placetype":[
        "aat:300008347"
    ]
},
  "bbox": [],
  "geometry": {"coordinates":[-118.7333,39.9333],"type":"Point"}
}