{
  "id": 1002220,
  "type": "Feature",
  "properties": {
    "tgn:hierarchy":[
        "tgn:1002220",
        "tgn:1000001",
        "tgn:7012149",
        "tgn:7007826",
        "tgn:7029392"
    ],
    "tgn:id":1002220,
    "tgn:name":"Caldwell",
    "tgn:placetype":[
        "aat:300387145",
        "aat:300000771"
    ]
},
  "bbox": [],
  "geometry": {"coordinates":[-97.6167,29.8333],"type":"Point"}
}