{
  "id": 2189131,
  "type": "Feature",
  "properties": {
    "tgn:hierarchy":[
        "tgn:2189131",
        "tgn:1002165",
        "tgn:1000001",
        "tgn:7012149",
        "tgn:7007517",
        "tgn:7029392"
    ],
    "tgn:id":2189131,
    "tgn:name":"Bound Brook",
    "tgn:placetype":[
        "aat:300008699"
    ]
},
  "bbox": [],
  "geometry": {"coordinates":[-70.0667,41.9667],"type":"Point"}
}