<<<<<<< HEAD
{
  "id": 7373092,
  "type": "Feature",
  "properties": {
    "tgn:hierarchy":[
        "tgn:7373092",
        "tgn:7005586",
        "tgn:1000001",
        "tgn:7005560",
        "tgn:7029392"
    ],
    "tgn:id":7373092,
    "tgn:name":"La Laja",
    "tgn:placetype":[
        "aat:300008347"
    ]
},
  "bbox": [],
  "geometry": {"coordinates":[-102.2,21.383333],"type":"Point"}
}
=======
{"geometry":{"type":"Point","coordinates":[-102.200000,21.383333]},"type":"Feature","properties":{"hierarchy":["tgn:7373092","tgn:7005586","tgn:1000001","tgn:7005560","tgn:7029392"],"placetype":["aat:300008347"],"id":7373092,"name:xx":"La Laja"}}
>>>>>>> 03f74aca74312dbeaf24d7e61306dd6a786dc3d0
