{
  "id": 7110903,
  "type": "Feature",
  "properties": {
    "tgn:hierarchy":[
        "tgn:7110903",
        "tgn:7003669",
        "tgn:1000003",
        "tgn:7000084",
        "tgn:7029392"
    ],
    "tgn:id":7110903,
    "tgn:name":"Pr\u00fcnthal",
    "tgn:placetype":[
        "aat:300008347"
    ]
},
  "bbox": [],
  "geometry": {"coordinates":[11.783333,49.166667],"type":"Point"}
}