{
  "id": 7409339,
  "type": "Feature",
  "properties": {
    "tgn:hierarchy":[
        "tgn:7409339",
        "tgn:1000001",
        "tgn:7005590",
        "tgn:7005560",
        "tgn:7029392"
    ],
    "tgn:id":7409339,
    "tgn:name":"El Pedregal",
    "tgn:placetype":[
        "aat:300008347"
    ]
},
  "bbox": [],
  "geometry": {"coordinates":[-100.290278,19.958333],"type":"Point"}
}