{
  "id": 7055040,
  "type": "Feature",
  "properties": {
    "tgn:hierarchy":[
        "tgn:7055040",
        "tgn:1003430",
        "tgn:1000003",
        "tgn:7003126",
        "tgn:1000080",
        "tgn:7029392"
    ],
    "tgn:id":7055040,
    "tgn:name":"Pollein",
    "tgn:placetype":[
        "aat:300008347"
    ]
},
  "bbox": [],
  "geometry": {"coordinates":[7.35,45.733333],"type":"Point"}
}