{
  "id": 7154644,
  "type": "Feature",
  "properties": {
    "tgn:hierarchy":[
        "tgn:7154644",
        "tgn:1000003",
        "tgn:7003685",
        "tgn:7000084",
        "tgn:7029392"
    ],
    "tgn:id":7154644,
    "tgn:name":"Katzen-Berg",
    "tgn:placetype":[
        "aat:300008777"
    ]
},
  "bbox": [],
  "geometry": {"coordinates":[13.116667,51.316667],"type":"Point"}
}