{
  "id": 2392878,
  "type": "Feature",
  "properties": {
    "tgn:hierarchy":[
        "tgn:2392878",
        "tgn:1000001",
        "tgn:7012149",
        "tgn:7029392"
    ],
    "tgn:id":2392878,
    "tgn:name":"Hobolochitto Creek",
    "tgn:placetype":[
        "aat:300008706"
    ]
},
  "bbox": [],
  "geometry": {"coordinates":[-89.6833,30.5333],"type":"Point"}
}