{
  "id": 2639555,
  "type": "Feature",
  "properties": {
    "tgn:hierarchy":[
        "tgn:2639555",
        "tgn:7002659",
        "tgn:1000001",
        "tgn:7012149",
        "tgn:2000035",
        "tgn:7029392"
    ],
    "tgn:id":2639555,
    "tgn:name":"Saltpetre Cave",
    "tgn:placetype":[
        "aat:300008746"
    ]
},
  "bbox": [],
  "geometry": {"coordinates":[-85.7667,34.7333],"type":"Point"}
}