{
  "id": 7566027,
  "type": "Feature",
  "properties": {
    "tgn:hierarchy":[
        "tgn:7566027",
        "tgn:1000004",
        "tgn:7000198",
        "tgn:7016722",
        "tgn:7029392"
    ],
    "tgn:id":7566027,
    "tgn:name:en":"Jarehar",
    "tgn:placetype":[
        "aat:300008347"
    ]
},
  "bbox": [],
  "geometry": {"coordinates":[79.71417,26.828618],"type":"Point"}
}