{
  "id": 2527150,
  "type": "Feature",
  "properties": {
    "tgn:hierarchy":[
        "tgn:2527150",
        "tgn:1000001",
        "tgn:1002308",
        "tgn:7012149",
        "tgn:7007710",
        "tgn:7029392"
    ],
    "tgn:id":2527150,
    "tgn:name":"Mount Hope",
    "tgn:placetype":[
        "aat:300008347"
    ]
},
  "bbox": [],
  "geometry": {"coordinates":[-79.95,41.5833],"type":"Point"}
}