{
  "id": 1043761,
  "type": "Feature",
  "properties": {
    "tgn:hierarchy":[
        "tgn:1043761",
        "tgn:7003005",
        "tgn:7003014",
        "tgn:1000003",
        "tgn:1000080",
        "tgn:7029392"
    ],
    "tgn:id":1043761,
    "tgn:name":"Camerota",
    "tgn:placetype":[
        "aat:300008347"
    ]
},
  "bbox": [],
  "geometry": {"coordinates":[15.366667,40.033333],"type":"Point"}
}