{
  "id": 7528167,
  "type": "Feature",
  "properties": {
    "tgn:hierarchy":[
        "tgn:7528167",
        "tgn:7001242",
        "tgn:7001311",
        "tgn:7016833",
        "tgn:7029392"
    ],
    "tgn:id":7528167,
    "tgn:name:en":"Umm Diw\u00e2n, W\u00e2di",
    "tgn:placetype":[
        "aat:300379998"
    ]
},
  "bbox": [],
  "geometry": {"coordinates":[34.175231,25.501448],"type":"Point"}
}