{
  "id": 2190356,
  "type": "Feature",
  "properties": {
    "tgn:hierarchy":[
        "tgn:2190356",
        "tgn:1000001",
        "tgn:7012149",
        "tgn:1002891",
        "tgn:7007708",
        "tgn:7029392"
    ],
    "tgn:id":2190356,
    "tgn:name":"Box Canyon",
    "tgn:placetype":[
        "aat:300008761"
    ]
},
  "bbox": [],
  "geometry": {"coordinates":[-120.6333,45.6833],"type":"Point"}
}