{
  "id": 7401686,
  "type": "Feature",
  "properties": {
    "tgn:hierarchy":[
        "tgn:7401686",
        "tgn:1000001",
        "tgn:7005599",
        "tgn:7005560",
        "tgn:7029392"
    ],
    "tgn:id":7401686,
    "tgn:name":"Dos R\u00edos",
    "tgn:placetype":[
        "aat:300008347"
    ]
},
  "bbox": [],
  "geometry": {"coordinates":[-97.033333,18.941667],"type":"Point"}
}