{
  "id": 7250963,
  "type": "Feature",
  "properties": {
    "tgn:hierarchy":[
        "tgn:7250963",
        "tgn:7003457",
        "tgn:1000003",
        "tgn:1000063",
        "tgn:7018236",
        "tgn:7029392"
    ],
    "tgn:id":7250963,
    "tgn:name":"Oostdorp",
    "tgn:placetype":[
        "aat:300008347"
    ]
},
  "bbox": [],
  "geometry": {"coordinates":[3.951736,50.883908],"type":"Point"}
}