{
  "id": 2754539,
  "type": "Feature",
  "properties": {
    "tgn:hierarchy":[
        "tgn:2754539",
        "tgn:1002808",
        "tgn:1000001",
        "tgn:7012149",
        "tgn:7007711",
        "tgn:7029392"
    ],
    "tgn:id":2754539,
    "tgn:name":"Wayland",
    "tgn:placetype":[
        "aat:300008347"
    ]
},
  "bbox": [],
  "geometry": {"coordinates":[-71.4667,41.7667],"type":"Point"}
}