{
  "id": 2716500,
  "type": "Feature",
  "properties": {
    "tgn:hierarchy":[
        "tgn:2716500",
        "tgn:1000001",
        "tgn:2001473",
        "tgn:7012149",
        "tgn:7007709",
        "tgn:7029392"
    ],
    "tgn:id":2716500,
    "tgn:name":"The Lagoon",
    "tgn:placetype":[
        "aat:300132316"
    ]
},
  "bbox": [],
  "geometry": {"coordinates":[-82.55,35.5333],"type":"Point"}
}