{
  "id": 7385826,
  "type": "Feature",
  "properties": {
    "tgn:hierarchy":[
        "tgn:7385826",
        "tgn:7005586",
        "tgn:1000001",
        "tgn:7005560",
        "tgn:7029392"
    ],
    "tgn:id":7385826,
    "tgn:name":"Pintor, Sierra el",
    "tgn:placetype":[
        "aat:300008795"
    ]
},
  "bbox": [],
  "geometry": {"coordinates":[-104.983333,20.25],"type":"Point"}
}