<<<<<<< HEAD
{
  "id": 2405235,
  "type": "Feature",
  "properties": {
    "tgn:hierarchy":[
        "tgn:2405235",
        "tgn:1000001",
        "tgn:7012149",
        "tgn:2001878",
        "tgn:7007825",
        "tgn:7029392"
    ],
    "tgn:id":2405235,
    "tgn:name":"Huff Hollow",
    "tgn:placetype":[
        "aat:300008761"
    ]
},
  "bbox": [],
  "geometry": {"coordinates":[-87.75,36.3167],"type":"Point"}
}
=======
{"geometry":{"type":"Point","coordinates":[-87.750000,36.316700]},"type":"Feature","properties":{"hierarchy":["tgn:2405235","tgn:1000001","tgn:7012149","tgn:2001878","tgn:7007825","tgn:7029392"],"placetype":["aat:300008761"],"id":2405235,"name:xx":"Huff Hollow"}}
>>>>>>> 03f74aca74312dbeaf24d7e61306dd6a786dc3d0
