{
  "id": 1011659,
  "type": "Feature",
  "properties": {
    "tgn:hierarchy":[
        "tgn:1011659",
        "tgn:1000004",
        "tgn:1001449",
        "tgn:1000135",
        "tgn:7029392"
    ],
    "tgn:id":1011659,
    "tgn:name":"Bonbonon Point",
    "tgn:placetype":[
        "aat:300386846"
    ]
},
  "bbox": [],
  "geometry": {"coordinates":[123.1333,9.05],"type":"Point"}
}