{
  "id": 7429407,
  "type": "Feature",
  "properties": {
    "tgn:hierarchy":[
        "tgn:7429407",
        "tgn:7005583",
        "tgn:1000001",
        "tgn:7005560",
        "tgn:7029392"
    ],
    "tgn:id":7429407,
    "tgn:name":"Corral de Barranco",
    "tgn:placetype":[
        "aat:300008347"
    ]
},
  "bbox": [],
  "geometry": {"coordinates":[-105.216667,23.983333],"type":"Point"}
}