{
  "id": 2629784,
  "type": "Feature",
  "properties": {
    "tgn:hierarchy":[
        "tgn:2629784",
        "tgn:1000001",
        "tgn:7012149",
        "tgn:2001279",
        "tgn:7007524",
        "tgn:7029392"
    ],
    "tgn:id":2629784,
    "tgn:name":"Ross Fork",
    "tgn:placetype":[
        "aat:300008699"
    ]
},
  "bbox": [],
  "geometry": {"coordinates":[-113.7667,46.0333],"type":"Point"}
}