{
  "id": 2620720,
  "type": "Feature",
  "properties": {
    "tgn:hierarchy":[
        "tgn:2620720",
        "tgn:1000001",
        "tgn:7012149",
        "tgn:2001718",
        "tgn:7007708",
        "tgn:7029392"
    ],
    "tgn:id":2620720,
    "tgn:name":"Riverside Reservoir Number Two",
    "tgn:placetype":[
        "aat:300006191"
    ]
},
  "bbox": [],
  "geometry": {"coordinates":[-118.1667,43.5667],"type":"Point"}
}