{
  "id": 7443042,
  "type": "Feature",
  "properties": {
    "tgn:hierarchy":[
        "tgn:7443042",
        "tgn:7002444",
        "tgn:1000003",
        "tgn:7008072",
        "tgn:7008591",
        "tgn:7029392"
    ],
    "tgn:id":7443042,
    "tgn:name:en":"Thornielee Station",
    "tgn:placetype":[
        "aat:300007783"
    ]
},
  "bbox": [],
  "geometry": {"coordinates":[-2.933333,55.616667],"type":"Point"}
}