{
  "id": 7323554,
  "type": "Feature",
  "properties": {
    "tgn:hierarchy":[
        "tgn:7323554",
        "tgn:7008911",
        "tgn:1000003",
        "tgn:7002763",
        "tgn:1000095",
        "tgn:7029392"
    ],
    "tgn:id":7323554,
    "tgn:name":"Robellada",
    "tgn:placetype":[
        "aat:300008347"
    ]
},
  "bbox": [],
  "geometry": {"coordinates":[-4.916667,43.333333],"type":"Point"}
}