<<<<<<< HEAD
{
  "id": 2760265,
  "type": "Feature",
  "properties": {
    "tgn:hierarchy":[
        "tgn:2760265",
        "tgn:1000001",
        "tgn:7012149",
        "tgn:7007710",
        "tgn:7029392"
    ],
    "tgn:id":2760265,
    "tgn:name":"West Fork Run",
    "tgn:placetype":[
        "aat:300008699"
    ]
},
  "bbox": [],
  "geometry": {"coordinates":[-78.9167,41.65],"type":"Point"}
}
=======
{"geometry":{"type":"Point","coordinates":[-78.916700,41.650000]},"type":"Feature","properties":{"hierarchy":["tgn:2760265","tgn:1000001","tgn:7012149","tgn:7007710","tgn:7029392"],"placetype":["aat:300008699"],"id":2760265,"name:xx":"West Fork Run"}}
>>>>>>> 03f74aca74312dbeaf24d7e61306dd6a786dc3d0
