{
  "id": 2520204,
  "type": "Feature",
  "properties": {
    "tgn:hierarchy":[
        "tgn:2520204",
        "tgn:1000001",
        "tgn:7012149",
        "tgn:2002112",
        "tgn:7007827",
        "tgn:7029392"
    ],
    "tgn:id":2520204,
    "tgn:name":"Mona Reservoir",
    "tgn:placetype":[
        "aat:300006191"
    ]
},
  "bbox": [],
  "geometry": {"coordinates":[-111.8667,39.8167],"type":"Point"}
}