<<<<<<< HEAD
{
  "id": 2256251,
  "type": "Feature",
  "properties": {
    "tgn:hierarchy":[
        "tgn:2256251",
        "tgn:1000001",
        "tgn:7012149",
        "tgn:1002584",
        "tgn:7007826",
        "tgn:7029392"
    ],
    "tgn:id":2256251,
    "tgn:name":"Copperas Creek",
    "tgn:placetype":[
        "aat:300008706"
    ]
},
  "bbox": [],
  "geometry": {"coordinates":[-96.9,30.3833],"type":"Point"}
}
=======
{"geometry":{"type":"Point","coordinates":[-96.900000,30.383300]},"type":"Feature","properties":{"hierarchy":["tgn:2256251","tgn:1000001","tgn:7012149","tgn:1002584","tgn:7007826","tgn:7029392"],"placetype":["aat:300008706"],"id":2256251,"name:xx":"Copperas Creek"}}
>>>>>>> 03f74aca74312dbeaf24d7e61306dd6a786dc3d0
