{
  "id": 2575606,
  "type": "Feature",
  "properties": {
    "tgn:hierarchy":[
        "tgn:2575606",
        "tgn:1000001",
        "tgn:7016172",
        "tgn:7012149",
        "tgn:2000163",
        "tgn:7029392"
    ],
    "tgn:id":2575606,
    "tgn:name":"Peppers Lake",
    "tgn:placetype":[
        "aat:300008680"
    ]
},
  "bbox": [],
  "geometry": {"coordinates":[-91.4167,34.7333],"type":"Point"}
}