{
  "id": 7366465,
  "type": "Feature",
  "properties": {
    "tgn:hierarchy":[
        "tgn:7366465",
        "tgn:1001853",
        "tgn:1000001",
        "tgn:7005560",
        "tgn:7029392"
    ],
    "tgn:id":7366465,
    "tgn:name":"Esmeralda",
    "tgn:placetype":[
        "aat:300007783"
    ]
},
  "bbox": [],
  "geometry": {"coordinates":[-103.65,27.283333],"type":"Point"}
}