{
  "id": 1063324,
  "type": "Feature",
  "properties": {
    "tgn:hierarchy":[
        "tgn:1063324",
        "tgn:1000003",
        "tgn:7024622",
        "tgn:1000097",
        "tgn:7029392"
    ],
    "tgn:id":1063324,
    "tgn:name":"Ljungbyhed",
    "tgn:placetype":[
        "aat:300008347"
    ]
},
  "bbox": [],
  "geometry": {"coordinates":[13.2167,56.0667],"type":"Point"}
}