<<<<<<< HEAD
{
  "id": 7110207,
  "type": "Feature",
  "properties": {
    "tgn:hierarchy":[
        "tgn:7110207",
        "tgn:1000003",
        "tgn:7000094",
        "tgn:7000084",
        "tgn:7029392"
    ],
    "tgn:id":7110207,
    "tgn:name":"P\u00fcschow",
    "tgn:placetype":[
        "aat:300008347"
    ]
},
  "bbox": [],
  "geometry": {"coordinates":[11.9,54.016667],"type":"Point"}
}
=======
{"geometry":{"type":"Point","coordinates":[11.900000,54.016667]},"type":"Feature","properties":{"hierarchy":["tgn:7110207","tgn:1000003","tgn:7000094","tgn:7000084","tgn:7029392"],"placetype":["aat:300008347"],"id":7110207,"name:xx":"P\u00fcschow"}}
>>>>>>> 03f74aca74312dbeaf24d7e61306dd6a786dc3d0
