{
  "id": 2447899,
  "type": "Feature",
  "properties": {
    "tgn:hierarchy":[
        "tgn:2447899",
        "tgn:1000001",
        "tgn:2000468",
        "tgn:7012149",
        "tgn:7007250",
        "tgn:7029392"
    ],
    "tgn:id":2447899,
    "tgn:name":"Lidy Hot Springs",
    "tgn:placetype":[
        "aat:300008697"
    ]
},
  "bbox": [],
  "geometry": {"coordinates":[-112.55,44.1333],"type":"Point"}
}