{
  "id": 1139115,
  "type": "Feature",
  "properties": {
    "tgn:hierarchy":[
        "tgn:1139115",
        "tgn:1000004",
        "tgn:1000960",
        "tgn:1000111",
        "tgn:7029392"
    ],
    "tgn:id":1139115,
    "tgn:name":"Huangzhuang",
    "tgn:placetype":[
        "aat:300008347"
    ]
},
  "bbox": [],
  "geometry": {"coordinates":[117.5167,39.4833],"type":"Point"}
}