{
  "id": 2056287,
  "type": "Feature",
  "properties": {
    "tgn:hierarchy":[
        "tgn:2056287",
        "tgn:1000001",
        "tgn:7012149",
        "tgn:2001139",
        "tgn:7007522",
        "tgn:7029392"
    ],
    "tgn:id":2056287,
    "tgn:name":"Delta",
    "tgn:placetype":[
        "aat:300008347",
        "aat:300387210"
    ]
},
  "bbox": [],
  "geometry": {"coordinates":[-90.1167,34.4167],"type":"Point"}
}