{
  "id": 2097611,
  "type": "Feature",
  "properties": {
    "tgn:hierarchy":[
        "tgn:2097611",
        "tgn:1000001",
        "tgn:7012149",
        "tgn:2001832",
        "tgn:7007713",
        "tgn:7029392"
    ],
    "tgn:id":2097611,
    "tgn:name":"Viborg",
    "tgn:placetype":[
        "aat:300008347"
    ]
},
  "bbox": [],
  "geometry": {"coordinates":[-97.0667,43.1667],"type":"Point"}
}