{
  "id": 2452275,
  "type": "Feature",
  "properties": {
    "tgn:hierarchy":[
        "tgn:2452275",
        "tgn:1000001",
        "tgn:7012149",
        "tgn:2002371",
        "tgn:7007923",
        "tgn:7029392"
    ],
    "tgn:id":2452275,
    "tgn:name":"Little Bob Lake",
    "tgn:placetype":[
        "aat:300008680"
    ]
},
  "bbox": [],
  "geometry": {"coordinates":[-109.4167,43.2333],"type":"Point"}
}