{
  "id": 7509634,
  "type": "Feature",
  "properties": {
    "tgn:hierarchy":[
        "tgn:7509634",
        "tgn:1008380",
        "tgn:1000226",
        "tgn:7018426",
        "tgn:1000006",
        "tgn:7029392"
    ],
    "tgn:id":7509634,
    "tgn:name:en":"Te Uku",
    "tgn:placetype":[
        "aat:300008347"
    ]
},
  "bbox": [],
  "geometry": {"coordinates":[174.966667,-37.833333],"type":"Point"}
}