{
  "id": 2303217,
  "type": "Feature",
  "properties": {
    "tgn:hierarchy":[
        "tgn:2303217",
        "tgn:1000001",
        "tgn:7012149",
        "tgn:2001667",
        "tgn:7007707",
        "tgn:7029392"
    ],
    "tgn:id":2303217,
    "tgn:name":"Eagle Bend Lake",
    "tgn:placetype":[
        "aat:300008680"
    ]
},
  "bbox": [],
  "geometry": {"coordinates":[-94.8167,33.7667],"type":"Point"}
}