{
  "id": 7539682,
  "type": "Feature",
  "properties": {
    "tgn:hierarchy":[
        "tgn:7539682",
        "tgn:7001242",
        "tgn:7016833",
        "tgn:1001113",
        "tgn:7029392"
    ],
    "tgn:id":7539682,
    "tgn:name:en":"Qamr\u016bnah",
    "tgn:placetype":[
        "aat:300008347"
    ]
},
  "bbox": [],
  "geometry": {"coordinates":[31.301478,30.475388],"type":"Point"}
}