<<<<<<< HEAD
{
  "id": 2768752,
  "type": "Feature",
  "properties": {
    "tgn:hierarchy":[
        "tgn:2768752",
        "tgn:1000001",
        "tgn:7012149",
        "tgn:1002352",
        "tgn:7007710",
        "tgn:7029392"
    ],
    "tgn:id":2768752,
    "tgn:name":"Whitman Hollow",
    "tgn:placetype":[
        "aat:300008761"
    ]
},
  "bbox": [],
  "geometry": {"coordinates":[-78.45,41.5],"type":"Point"}
}
=======
{"geometry":{"type":"Point","coordinates":[-78.450000,41.500000]},"type":"Feature","properties":{"hierarchy":["tgn:2768752","tgn:1000001","tgn:7012149","tgn:1002352","tgn:7007710","tgn:7029392"],"placetype":["aat:300008761"],"id":2768752,"name:xx":"Whitman Hollow"}}
>>>>>>> 03f74aca74312dbeaf24d7e61306dd6a786dc3d0
