<<<<<<< HEAD
{
  "id": 2405869,
  "type": "Feature",
  "properties": {
    "tgn:hierarchy":[
        "tgn:2405869",
        "tgn:1000001",
        "tgn:2000922",
        "tgn:7012149",
        "tgn:7007515",
        "tgn:7029392"
    ],
    "tgn:id":2405869,
    "tgn:name":"Hulls Cove",
    "tgn:placetype":[
        "aat:300132316"
    ]
},
  "bbox": [],
  "geometry": {"coordinates":[-68.2333,44.4],"type":"Point"}
}
=======
{"geometry":{"type":"Point","coordinates":[-68.233300,44.400000]},"type":"Feature","properties":{"hierarchy":["tgn:2405869","tgn:1000001","tgn:2000922","tgn:7012149","tgn:7007515","tgn:7029392"],"placetype":["aat:300132316"],"id":2405869,"name:xx":"Hulls Cove"}}
>>>>>>> 03f74aca74312dbeaf24d7e61306dd6a786dc3d0
