{
  "id": 7589765,
  "type": "Feature",
  "properties": {
    "tgn:hierarchy":[
        "tgn:7589765",
        "tgn:1000004",
        "tgn:7000198",
        "tgn:7016883",
        "tgn:7029392"
    ],
    "tgn:id":7589765,
    "tgn:name:en":"Karaudi\u0101n",
    "tgn:placetype":[
        "aat:300008347"
    ]
},
  "bbox": [],
  "geometry": {"coordinates":[76.079661,30.681936],"type":"Point"}
}