{
  "id": 7394903,
  "type": "Feature",
  "properties": {
    "tgn:hierarchy":[
        "tgn:7394903",
        "tgn:1000001",
        "tgn:7005600",
        "tgn:7005560",
        "tgn:7029392"
    ],
    "tgn:id":7394903,
    "tgn:name":"San Crisanto",
    "tgn:placetype":[
        "aat:300008347"
    ]
},
  "bbox": [],
  "geometry": {"coordinates":[-89.166667,21.333333],"type":"Point"}
}