{
  "id": 1122747,
  "type": "Feature",
  "properties": {
    "tgn:hierarchy":[
        "tgn:1122747",
        "tgn:7001242",
        "tgn:1000149",
        "tgn:7000392",
        "tgn:7029392"
    ],
    "tgn:id":1122747,
    "tgn:name":"Chiambala",
    "tgn:placetype":[
        "aat:300008707"
    ]
},
  "bbox": [],
  "geometry": {"coordinates":[11.8167,-16.3667],"type":"Point"}
}