<<<<<<< HEAD
{
  "id": 7058428,
  "type": "Feature",
  "properties": {
    "tgn:hierarchy":[
        "tgn:7058428",
        "tgn:7003168",
        "tgn:1000003",
        "tgn:7009760",
        "tgn:1000080",
        "tgn:7029392"
    ],
    "tgn:id":7058428,
    "tgn:name":"Ancaiano",
    "tgn:placetype":[
        "aat:300008347"
    ]
},
  "bbox": [],
  "geometry": {"coordinates":[11.216667,43.3],"type":"Point"}
}
=======
{"geometry":{"type":"Point","coordinates":[11.216667,43.300000]},"type":"Feature","properties":{"hierarchy":["tgn:7058428","tgn:7003168","tgn:1000003","tgn:7009760","tgn:1000080","tgn:7029392"],"placetype":["aat:300008347"],"id":7058428,"name:xx":"Ancaiano"}}
>>>>>>> 03f74aca74312dbeaf24d7e61306dd6a786dc3d0
