{
  "id": 1056934,
  "type": "Feature",
  "properties": {
    "tgn:hierarchy":[
        "tgn:1056934",
        "tgn:1000003",
        "tgn:7011670",
        "tgn:7006660",
        "tgn:7029392"
    ],
    "tgn:id":1056934,
    "tgn:name":"Melitopol",
    "tgn:placetype":[
        "aat:300008347"
    ]
},
  "bbox": [],
  "geometry": {"coordinates":[35.3667,46.85],"type":"Point"}
}