<<<<<<< HEAD
{
  "id": 7356408,
  "type": "Feature",
  "properties": {
    "tgn:hierarchy":[
        "tgn:7356408",
        "tgn:7005581",
        "tgn:1000001",
        "tgn:7005560",
        "tgn:7029392"
    ],
    "tgn:id":7356408,
    "tgn:name":"Rancho Cerros Colorados",
    "tgn:placetype":[
        "aat:300000241"
    ]
},
  "bbox": [],
  "geometry": {"coordinates":[-105.383333,30.833333],"type":"Point"}
}
=======
{"geometry":{"type":"Point","coordinates":[-105.383333,30.833333]},"type":"Feature","properties":{"hierarchy":["tgn:7356408","tgn:7005581","tgn:1000001","tgn:7005560","tgn:7029392"],"placetype":["aat:300000241"],"id":7356408,"name:xx":"Rancho Cerros Colorados"}}
>>>>>>> 03f74aca74312dbeaf24d7e61306dd6a786dc3d0
