{
  "id": 2191919,
  "type": "Feature",
  "properties": {
    "tgn:hierarchy":[
        "tgn:2191919",
        "tgn:1000001",
        "tgn:7012149",
        "tgn:2002291",
        "tgn:7013961",
        "tgn:7029392"
    ],
    "tgn:id":2191919,
    "tgn:name":"Brady Gate",
    "tgn:placetype":[
        "aat:300008347"
    ]
},
  "bbox": [],
  "geometry": {"coordinates":[-80.0667,38.5333],"type":"Point"}
}