{
  "id": 7477061,
  "type": "Feature",
  "properties": {
    "tgn:hierarchy":[
        "tgn:7477061",
        "tgn:7487020",
        "tgn:1000004",
        "tgn:1000141",
        "tgn:7029392"
    ],
    "tgn:id":7477061,
    "tgn:name":"Sheliao",
    "tgn:placetype":[
        "aat:300008347"
    ]
},
  "bbox": [],
  "geometry": {"coordinates":[120.984811,24.635507],"type":"Point"}
}