{
  "id": 7318613,
  "type": "Feature",
  "properties": {
    "tgn:hierarchy":[
        "tgn:7318613",
        "tgn:7002464",
        "tgn:1000049",
        "tgn:1000002",
        "tgn:7029392"
    ],
    "tgn:id":7318613,
    "tgn:name":"Collacagua, Morro",
    "tgn:placetype":[
        "aat:300008795"
    ]
},
  "bbox": [],
  "geometry": {"coordinates":[-68.95,-20.05],"type":"Point"}
}