{
  "id": 7286061,
  "type": "Feature",
  "properties": {
    "tgn:hierarchy":[
        "tgn:7286061",
        "tgn:1001623",
        "tgn:1000049",
        "tgn:1000002",
        "tgn:7029392"
    ],
    "tgn:id":7286061,
    "tgn:name":"Justiniano, Isla",
    "tgn:placetype":[
        "aat:300008791"
    ]
},
  "bbox": [],
  "geometry": {"coordinates":[-74.316667,-48.25],"type":"Point"}
}