{
  "id": 2689021,
  "type": "Feature",
  "properties": {
    "tgn:hierarchy":[
        "tgn:2689021",
        "tgn:2001423",
        "tgn:1000001",
        "tgn:7012149",
        "tgn:7007564",
        "tgn:7029392"
    ],
    "tgn:id":2689021,
    "tgn:name":"Square Brook",
    "tgn:placetype":[
        "aat:300008699"
    ]
},
  "bbox": [],
  "geometry": {"coordinates":[-71.0667,43.8333],"type":"Point"}
}