{
  "id": 7309697,
  "type": "Feature",
  "properties": {
    "tgn:hierarchy":[
        "tgn:7309697",
        "tgn:7016598",
        "tgn:1000049",
        "tgn:1000002",
        "tgn:7029392"
    ],
    "tgn:id":7309697,
    "tgn:name":"Nuestra Se\u00f1ora, Bah\u00eda",
    "tgn:placetype":[
        "aat:300132316"
    ]
},
  "bbox": [],
  "geometry": {"coordinates":[-70.466667,-25.25],"type":"Point"}
}