{
  "id": 2630752,
  "type": "Feature",
  "properties": {
    "tgn:hierarchy":[
        "tgn:2630752",
        "tgn:1000001",
        "tgn:7016172",
        "tgn:7012149",
        "tgn:2000152",
        "tgn:7029392"
    ],
    "tgn:id":2630752,
    "tgn:name":"Round Lake",
    "tgn:placetype":[
        "aat:300008680"
    ]
},
  "bbox": [],
  "geometry": {"coordinates":[-91.2833,34.55],"type":"Point"}
}