{
  "id": 2352121,
  "type": "Feature",
  "properties": {
    "tgn:hierarchy":[
        "tgn:2352121",
        "tgn:1000001",
        "tgn:1002174",
        "tgn:7012149",
        "tgn:7007826",
        "tgn:7029392"
    ],
    "tgn:id":2352121,
    "tgn:name":"Glover Branch",
    "tgn:placetype":[
        "aat:300008699"
    ]
},
  "bbox": [],
  "geometry": {"coordinates":[-97.8333,30.9167],"type":"Point"}
}