{
  "id": 7456631,
  "type": "Feature",
  "properties": {
    "tgn:hierarchy":[
        "tgn:7456631",
        "tgn:7002444",
        "tgn:1000003",
        "tgn:7008082",
        "tgn:7008591",
        "tgn:7029392"
    ],
    "tgn:id":7456631,
    "tgn:name:en":"Pocan Smoo",
    "tgn:placetype":[
        "aat:300008746"
    ]
},
  "bbox": [],
  "geometry": {"coordinates":[-4.716667,58.566667],"type":"Point"}
}