{
  "id": 2169635,
  "type": "Feature",
  "properties": {
    "tgn:hierarchy":[
        "tgn:2169635",
        "tgn:1000001",
        "tgn:7012149",
        "tgn:2000609",
        "tgn:7007253",
        "tgn:7029392"
    ],
    "tgn:id":2169635,
    "tgn:name":"Big Mill Creek Public Hunting Area",
    "tgn:placetype":[
        "aat:300055621"
    ]
},
  "bbox": [],
  "geometry": {"coordinates":[-90.5333,42.2667],"type":"Point"}
}