<<<<<<< HEAD
{
  "id": 7058273,
  "type": "Feature",
  "properties": {
    "tgn:hierarchy":[
        "tgn:7058273",
        "tgn:7003170",
        "tgn:1000003",
        "tgn:7003125",
        "tgn:1000080",
        "tgn:7029392"
    ],
    "tgn:id":7058273,
    "tgn:name":"Anna, Fosso dell'",
    "tgn:placetype":[
        "aat:300008699"
    ]
},
  "bbox": [],
  "geometry": {"coordinates":[12.75,43.05],"type":"Point"}
}
=======
{"geometry":{"type":"Point","coordinates":[12.750000,43.050000]},"type":"Feature","properties":{"hierarchy":["tgn:7058273","tgn:7003170","tgn:1000003","tgn:7003125","tgn:1000080","tgn:7029392"],"placetype":["aat:300008699"],"id":7058273,"name:xx":"Anna, Fosso dell'"}}
>>>>>>> 03f74aca74312dbeaf24d7e61306dd6a786dc3d0
