{
  "id": 7353631,
  "type": "Feature",
  "properties": {
    "tgn:hierarchy":[
        "tgn:7353631",
        "tgn:7005581",
        "tgn:1000001",
        "tgn:7005560",
        "tgn:7029392"
    ],
    "tgn:id":7353631,
    "tgn:name":"Berm\u00fadez, Arroyo",
    "tgn:placetype":[
        "aat:300008699"
    ]
},
  "bbox": [],
  "geometry": {"coordinates":[-108.983333,28.133333],"type":"Point"}
}