<<<<<<< HEAD
{
  "id": 7353631,
  "type": "Feature",
  "properties": {
    "tgn:hierarchy":[
        "tgn:7353631",
        "tgn:7005581",
        "tgn:1000001",
        "tgn:7005560",
        "tgn:7029392"
    ],
    "tgn:id":7353631,
    "tgn:name":"Berm\u00fadez, Arroyo",
    "tgn:placetype":[
        "aat:300008699"
    ]
},
  "bbox": [],
  "geometry": {"coordinates":[-108.983333,28.133333],"type":"Point"}
}
=======
{"geometry":{"type":"Point","coordinates":[-108.983333,28.133333]},"type":"Feature","properties":{"hierarchy":["tgn:7353631","tgn:7005581","tgn:1000001","tgn:7005560","tgn:7029392"],"placetype":["aat:300008699"],"id":7353631,"name:xx":"Berm\u00fadez, Arroyo"}}
>>>>>>> 03f74aca74312dbeaf24d7e61306dd6a786dc3d0
