{
  "id": 7122357,
  "type": "Feature",
  "properties": {
    "tgn:hierarchy":[
        "tgn:7122357",
        "tgn:1000003",
        "tgn:7003685",
        "tgn:7000084",
        "tgn:7029392"
    ],
    "tgn:id":7122357,
    "tgn:name":"Bahnhof Neukirchen-Wyhra",
    "tgn:placetype":[
        "aat:300007783"
    ]
},
  "bbox": [],
  "geometry": {"coordinates":[12.535,51.084167],"type":"Point"}
}