<<<<<<< HEAD
{
  "id": 7361902,
  "type": "Feature",
  "properties": {
    "tgn:hierarchy":[
        "tgn:7361902",
        "tgn:7005581",
        "tgn:1000001",
        "tgn:7005560",
        "tgn:7029392"
    ],
    "tgn:id":7361902,
    "tgn:name":"El P\u00e1jaro, Cerro",
    "tgn:placetype":[
        "aat:300008795"
    ]
},
  "bbox": [],
  "geometry": {"coordinates":[-106.816667,28.35],"type":"Point"}
}
=======
{"geometry":{"type":"Point","coordinates":[-106.816667,28.350000]},"type":"Feature","properties":{"hierarchy":["tgn:7361902","tgn:7005581","tgn:1000001","tgn:7005560","tgn:7029392"],"placetype":["aat:300008795"],"id":7361902,"name:xx":"El P\u00e1jaro, Cerro"}}
>>>>>>> 03f74aca74312dbeaf24d7e61306dd6a786dc3d0
