{
  "id": 7046021,
  "type": "Feature",
  "properties": {
    "tgn:hierarchy":[
        "tgn:7046021",
        "tgn:7003137",
        "tgn:1000003",
        "tgn:7003080",
        "tgn:1000080",
        "tgn:7029392"
    ],
    "tgn:id":7046021,
    "tgn:name":"Cassino",
    "tgn:placetype":[
        "aat:300008347"
    ]
},
  "bbox": [],
  "geometry": {"coordinates":[13.216667,42.666667],"type":"Point"}
}