{
  "id": 1124029,
  "type": "Feature",
  "properties": {
    "tgn:hierarchy":[
        "tgn:1124029",
        "tgn:7005685",
        "tgn:1000001",
        "tgn:7005804",
        "tgn:7029392"
    ],
    "tgn:id":1124029,
    "tgn:name":"Froid, Ruisseau",
    "tgn:placetype":[
        "aat:300008707"
    ]
},
  "bbox": [],
  "geometry": {"coordinates":[-74.7667,46.3833],"type":"Point"}
}