{
  "id": 2557229,
  "type": "Feature",
  "properties": {
    "tgn:hierarchy":[
        "tgn:2557229",
        "tgn:1000001",
        "tgn:7012149",
        "tgn:2001861",
        "tgn:7007825",
        "tgn:7029392"
    ],
    "tgn:id":2557229,
    "tgn:name":"Old Jamestown Reservoir",
    "tgn:placetype":[
        "aat:300006191"
    ]
},
  "bbox": [],
  "geometry": {"coordinates":[-84.8833,36.4167],"type":"Point"}
}