{
  "id": 7316308,
  "type": "Feature",
  "properties": {
    "tgn:hierarchy":[
        "tgn:7316308",
        "tgn:1001657",
        "tgn:1000049",
        "tgn:1000002",
        "tgn:7029392"
    ],
    "tgn:id":7316308,
    "tgn:name":"Cardizal, Loma",
    "tgn:placetype":[
        "aat:300008777"
    ]
},
  "bbox": [],
  "geometry": {"coordinates":[-71.266667,-30.216667],"type":"Point"}
}