{
  "id": 2746494,
  "type": "Feature",
  "properties": {
    "tgn:hierarchy":[
        "tgn:2746494",
        "tgn:1000001",
        "tgn:7012149",
        "tgn:2000537",
        "tgn:7007251",
        "tgn:7029392"
    ],
    "tgn:id":2746494,
    "tgn:name":"Wabash Levee Ditch",
    "tgn:placetype":[
        "aat:300006075"
    ]
},
  "bbox": [],
  "geometry": {"coordinates":[-88.0667,38.0167],"type":"Point"}
}