{
  "id": 7445920,
  "type": "Feature",
  "properties": {
    "tgn:hierarchy":[
        "tgn:7445920",
        "tgn:7019094",
        "tgn:7002444",
        "tgn:1000003",
        "tgn:7008591",
        "tgn:7029392"
    ],
    "tgn:id":7445920,
    "tgn:name:en":"South Bank",
    "tgn:placetype":[
        "aat:300386970"
    ]
},
  "bbox": [],
  "geometry": {"coordinates":[-6.733333,56.45],"type":"Point"}
}