{
  "id": 7578090,
  "type": "Feature",
  "properties": {
    "tgn:hierarchy":[
        "tgn:7578090",
        "tgn:1000004",
        "tgn:7000198",
        "tgn:1001998",
        "tgn:7029392"
    ],
    "tgn:id":7578090,
    "tgn:name:en":"Tuidang",
    "tgn:placetype":[
        "aat:300008347"
    ]
},
  "bbox": [],
  "geometry": {"coordinates":[92.828724,22.254441],"type":"Point"}
}