{
  "id": 2253044,
  "type": "Feature",
  "properties": {
    "tgn:hierarchy":[
        "tgn:2253044",
        "tgn:1000001",
        "tgn:7020676",
        "tgn:7012149",
        "tgn:7007256",
        "tgn:7029392"
    ],
    "tgn:id":2253044,
    "tgn:name":"Constance Ditch",
    "tgn:placetype":[
        "aat:300006075"
    ]
},
  "bbox": [],
  "geometry": {"coordinates":[-92.6667,29.6167],"type":"Point"}
}