{
  "id": 7291949,
  "type": "Feature",
  "properties": {
    "tgn:hierarchy":[
        "tgn:7291949",
        "tgn:1001708",
        "tgn:1000049",
        "tgn:1000002",
        "tgn:7029392"
    ],
    "tgn:id":7291949,
    "tgn:name":"El Peral, Loma",
    "tgn:placetype":[
        "aat:300387002"
    ]
},
  "bbox": [],
  "geometry": {"coordinates":[-70.583333,-33.766667],"type":"Point"}
}