{
  "id": 2629053,
  "type": "Feature",
  "properties": {
    "tgn:hierarchy":[
        "tgn:2629053",
        "tgn:1000001",
        "tgn:7012149",
        "tgn:1002877",
        "tgn:7007706",
        "tgn:7029392"
    ],
    "tgn:id":2629053,
    "tgn:name":"Rose Hill",
    "tgn:placetype":[
        "aat:300008798"
    ]
},
  "bbox": [],
  "geometry": {"coordinates":[-82.95,38.8833],"type":"Point"}
}