{
  "id": 7018871,
  "type": "Feature",
  "properties": {
    "tgn:hierarchy":[
        "tgn:7018871",
        "tgn:1000001",
        "tgn:7012149",
        "tgn:7007920",
        "tgn:7029392"
    ],
    "tgn:id":7018871,
    "tgn:name":"King",
    "tgn:placetype":[
        "aat:300387145",
        "aat:300000771"
    ]
},
  "bbox": [],
  "geometry": {"coordinates":[-121.8167,47.4667],"type":"Point"}
}