{
  "id": 2023714,
  "type": "Feature",
  "properties": {
    "tgn:hierarchy":[
        "tgn:2023714",
        "tgn:1000001",
        "tgn:7012149",
        "tgn:2000401",
        "tgn:7007248",
        "tgn:7029392"
    ],
    "tgn:id":2023714,
    "tgn:name":"Nebo",
    "tgn:placetype":[
        "aat:300008347",
        "aat:300387210"
    ]
},
  "bbox": [],
  "geometry": {"coordinates":[-84.8167,33.8333],"type":"Point"}
}