<<<<<<< HEAD
{
  "id": 2769660,
  "type": "Feature",
  "properties": {
    "tgn:hierarchy":[
        "tgn:2769660",
        "tgn:1000001",
        "tgn:7012149",
        "tgn:2000344",
        "tgn:7007248",
        "tgn:7029392"
    ],
    "tgn:id":2769660,
    "tgn:name":"Wig Lake",
    "tgn:placetype":[
        "aat:300008680"
    ]
},
  "bbox": [],
  "geometry": {"coordinates":[-82.1833,32.8],"type":"Point"}
}
=======
{"geometry":{"type":"Point","coordinates":[-82.183300,32.800000]},"type":"Feature","properties":{"hierarchy":["tgn:2769660","tgn:1000001","tgn:7012149","tgn:2000344","tgn:7007248","tgn:7029392"],"placetype":["aat:300008680"],"id":2769660,"name:xx":"Wig Lake"}}
>>>>>>> 03f74aca74312dbeaf24d7e61306dd6a786dc3d0
