{
  "id": 2549238,
  "type": "Feature",
  "properties": {
    "tgn:hierarchy":[
        "tgn:2549238",
        "tgn:1000001",
        "tgn:7013942",
        "tgn:7012149",
        "tgn:7007517",
        "tgn:7029392"
    ],
    "tgn:id":2549238,
    "tgn:name":"North River Reservoir",
    "tgn:placetype":[
        "aat:300006191"
    ]
},
  "bbox": [],
  "geometry": {"coordinates":[-72.7167,42.65],"type":"Point"}
}