{
  "id": 2675544,
  "type": "Feature",
  "properties": {
    "tgn:hierarchy":[
        "tgn:2675544",
        "tgn:1000001",
        "tgn:7012149",
        "tgn:2001287",
        "tgn:7007524",
        "tgn:7029392"
    ],
    "tgn:id":2675544,
    "tgn:name":"Solly Coulee",
    "tgn:placetype":[
        "aat:300008761"
    ]
},
  "bbox": [],
  "geometry": {"coordinates":[-105.75,47.6667],"type":"Point"}
}