{
  "id": 7286585,
  "type": "Feature",
  "properties": {
    "tgn:hierarchy":[
        "tgn:7286585",
        "tgn:7016598",
        "tgn:1000049",
        "tgn:1000002",
        "tgn:7029392"
    ],
    "tgn:id":7286585,
    "tgn:name":"Guti\u00e9rrez, Cerro",
    "tgn:placetype":[
        "aat:300008777"
    ]
},
  "bbox": [],
  "geometry": {"coordinates":[-69.633333,-21.516667],"type":"Point"}
}