{
  "id": 1131970,
  "type": "Feature",
  "properties": {
    "tgn:hierarchy":[
        "tgn:1131970",
        "tgn:1001277",
        "tgn:7002560",
        "tgn:1000051",
        "tgn:1000002",
        "tgn:7029392"
    ],
    "tgn:id":1131970,
    "tgn:name":"Yaguachi, R\u00edo",
    "tgn:placetype":[
        "aat:300008707"
    ]
},
  "bbox": [],
  "geometry": {"coordinates":[-79.7333,-2.0333],"type":"Point"}
}