{
  "id": 2585501,
  "type": "Feature",
  "properties": {
    "tgn:hierarchy":[
        "tgn:2585501",
        "tgn:1000001",
        "tgn:7012149",
        "tgn:2000183",
        "tgn:7007157",
        "tgn:7029392"
    ],
    "tgn:id":2585501,
    "tgn:name":"Pinyon Creek",
    "tgn:placetype":[
        "aat:300008706"
    ]
},
  "bbox": [],
  "geometry": {"coordinates":[-118.3333,36.7333],"type":"Point"}
}