{
  "id": 7493104,
  "type": "Feature",
  "properties": {
    "tgn:hierarchy":[
        "tgn:7493104",
        "tgn:1000004",
        "tgn:1000454",
        "tgn:1000141",
        "tgn:7029392"
    ],
    "tgn:id":7493104,
    "tgn:name":"Shanjia",
    "tgn:placetype":[
        "aat:300008347"
    ]
},
  "bbox": [],
  "geometry": {"coordinates":[121.393436,24.972114],"type":"Point"}
}