{
  "id": 2007300,
  "type": "Feature",
  "properties": {
    "tgn:hierarchy":[
        "tgn:2007300",
        "tgn:1000001",
        "tgn:7006451",
        "tgn:7012149",
        "tgn:2000100",
        "tgn:7029392"
    ],
    "tgn:id":2007300,
    "tgn:name":"San Xavier",
    "tgn:placetype":[
        "aat:300008347"
    ]
},
  "bbox": [],
  "geometry": {"coordinates":[-111.0833,31.9667],"type":"Point"}
}