{
  "id": 7470702,
  "type": "Feature",
  "properties": {
    "tgn:hierarchy":[
        "tgn:7470702",
        "tgn:1000004",
        "tgn:7001014",
        "tgn:1000141",
        "tgn:7029392"
    ],
    "tgn:id":7470702,
    "tgn:name":"Houzhuangzi",
    "tgn:placetype":[
        "aat:300008347"
    ]
},
  "bbox": [],
  "geometry": {"coordinates":[120.5225,23.699722],"type":"Point"}
}