{
  "id": 2189272,
  "type": "Feature",
  "properties": {
    "tgn:hierarchy":[
        "tgn:2189272",
        "tgn:1000001",
        "tgn:7012149",
        "tgn:2001297",
        "tgn:7007524",
        "tgn:7029392"
    ],
    "tgn:id":2189272,
    "tgn:name":"Boundary Reservoir",
    "tgn:placetype":[
        "aat:300006191"
    ]
},
  "bbox": [],
  "geometry": {"coordinates":[-106.1667,45.1667],"type":"Point"}
}