{
  "id": 2441829,
  "type": "Feature",
  "properties": {
    "tgn:hierarchy":[
        "tgn:2441829",
        "tgn:1000001",
        "tgn:2001633",
        "tgn:7012149",
        "tgn:7007707",
        "tgn:7029392"
    ],
    "tgn:id":2441829,
    "tgn:name":"Kolpin Mountain",
    "tgn:placetype":[
        "aat:300008798"
    ]
},
  "bbox": [],
  "geometry": {"coordinates":[-95.05,35.8833],"type":"Point"}
}