<<<<<<< HEAD
{
  "id": 7024543,
  "type": "Feature",
  "properties": {
    "tgn:hierarchy":[
        "tgn:7024543",
        "tgn:7593552",
        "tgn:1000001",
        "tgn:7024573",
        "tgn:7029392"
    ],
    "tgn:id":7024543,
    "tgn:name":"Qeqertarsuaq",
    "tgn:placetype":[
        "aat:300008791"
    ]
},
  "bbox": [],
  "geometry": {"coordinates":[-57.15,74.7],"type":"Point"}
}
=======
{"geometry":{"type":"Point","coordinates":[-57.150000,74.700000]},"type":"Feature","properties":{"hierarchy":["tgn:7024543","tgn:7593552","tgn:1000001","tgn:7024573","tgn:7029392"],"placetype":["aat:300008791"],"id":7024543,"name:xx":"Qeqertarsuaq"}}
>>>>>>> 03f74aca74312dbeaf24d7e61306dd6a786dc3d0
