<<<<<<< HEAD
{
  "id": 7488983,
  "type": "Feature",
  "properties": {
    "tgn:hierarchy":[
        "tgn:7488983",
        "tgn:1000004",
        "tgn:7001013",
        "tgn:1000141",
        "tgn:7029392"
    ],
    "tgn:id":7488983,
    "tgn:name":"Kulinglin",
    "tgn:placetype":[
        "aat:300008347"
    ]
},
  "bbox": [],
  "geometry": {"coordinates":[121.35,25.066667],"type":"Point"}
}
=======
{"geometry":{"type":"Point","coordinates":[121.350000,25.066667]},"type":"Feature","properties":{"hierarchy":["tgn:7488983","tgn:1000004","tgn:7001013","tgn:1000141","tgn:7029392"],"placetype":["aat:300008347"],"id":7488983,"name:xx":"Kulinglin"}}
>>>>>>> 03f74aca74312dbeaf24d7e61306dd6a786dc3d0
