{
  "id": 2346982,
  "type": "Feature",
  "properties": {
    "tgn:hierarchy":[
        "tgn:2346982",
        "tgn:1000001",
        "tgn:7006451",
        "tgn:7012149",
        "tgn:2000100",
        "tgn:7029392"
    ],
    "tgn:id":2346982,
    "tgn:name":"Gemelo Tank",
    "tgn:placetype":[
        "aat:300006191"
    ]
},
  "bbox": [],
  "geometry": {"coordinates":[-111.0833,31.8167],"type":"Point"}
}