{
  "id": 1024898,
  "type": "Feature",
  "properties": {
    "tgn:hierarchy":[
        "tgn:1024898",
        "tgn:1000611",
        "tgn:1000002",
        "tgn:1000058",
        "tgn:7029392"
    ],
    "tgn:id":1024898,
    "tgn:name":"Fray Marcos",
    "tgn:placetype":[
        "aat:300008347"
    ]
},
  "bbox": [],
  "geometry": {"coordinates":[-55.7167,-34.2167],"type":"Point"}
}