{
  "id": 2602948,
  "type": "Feature",
  "properties": {
    "tgn:hierarchy":[
        "tgn:2602948",
        "tgn:7014010",
        "tgn:1000001",
        "tgn:1002344",
        "tgn:7012149",
        "tgn:7007517",
        "tgn:7029392"
    ],
    "tgn:id":2602948,
    "tgn:name":"Quampache Bottom",
    "tgn:placetype":[
        "aat:300008761"
    ]
},
  "bbox": [],
  "geometry": {"coordinates":[-70.1833,41.2667],"type":"Point"}
}