{
  "id": 2434981,
  "type": "Feature",
  "properties": {
    "tgn:hierarchy":[
        "tgn:2434981",
        "tgn:1000001",
        "tgn:7012149",
        "tgn:7016020",
        "tgn:7007710",
        "tgn:7029392"
    ],
    "tgn:id":2434981,
    "tgn:name":"Kent Hollow",
    "tgn:placetype":[
        "aat:300008761"
    ]
},
  "bbox": [],
  "geometry": {"coordinates":[-78.3667,41.8333],"type":"Point"}
}