{
  "id": 2326526,
  "type": "Feature",
  "properties": {
    "tgn:hierarchy":[
        "tgn:2326526",
        "tgn:1000001",
        "tgn:7012149",
        "tgn:2000969",
        "tgn:7007520",
        "tgn:7029392"
    ],
    "tgn:id":2326526,
    "tgn:name":"Finlander Reef",
    "tgn:placetype":[
        "aat:300132348"
    ]
},
  "bbox": [],
  "geometry": {"coordinates":[-89.0833,47.9667],"type":"Point"}
}