{
  "id": 2108128,
  "type": "Feature",
  "properties": {
    "tgn:hierarchy":[
        "tgn:2108128",
        "tgn:1000001",
        "tgn:7012149",
        "tgn:1002244",
        "tgn:7007826",
        "tgn:7029392"
    ],
    "tgn:id":2108128,
    "tgn:name":"Turkey Creek",
    "tgn:placetype":[
        "aat:300008347",
        "aat:300387210"
    ]
},
  "bbox": [],
  "geometry": {"coordinates":[-94.5667,32.95],"type":"Point"}
}