{
  "id": 7527916,
  "type": "Feature",
  "properties": {
    "tgn:hierarchy":[
        "tgn:7527916",
        "tgn:7001242",
        "tgn:7016833",
        "tgn:7001334",
        "tgn:7029392"
    ],
    "tgn:id":7527916,
    "tgn:name:en":"Umm al Qu\u015f\u016br, 'Ayn",
    "tgn:placetype":[
        "aat:300008697"
    ]
},
  "bbox": [],
  "geometry": {"coordinates":[30.669393,25.745931],"type":"Point"}
}