{
  "id": 7430959,
  "type": "Feature",
  "properties": {
    "tgn:hierarchy":[
        "tgn:7430959",
        "tgn:1001853",
        "tgn:1000001",
        "tgn:7005560",
        "tgn:7029392"
    ],
    "tgn:id":7430959,
    "tgn:name":"Las Cruces",
    "tgn:placetype":[
        "aat:300008347"
    ]
},
  "bbox": [],
  "geometry": {"coordinates":[-101.166667,27.716667],"type":"Point"}
}