{
  "id": 2719062,
  "type": "Feature",
  "properties": {
    "tgn:hierarchy":[
        "tgn:2719062",
        "tgn:1000001",
        "tgn:7012149",
        "tgn:2000880",
        "tgn:7007256",
        "tgn:7029392"
    ],
    "tgn:id":2719062,
    "tgn:name":"Thornwell Drainage Canal",
    "tgn:placetype":[
        "aat:300006075"
    ]
},
  "bbox": [],
  "geometry": {"coordinates":[-92.7833,30.0667],"type":"Point"}
}