{
  "id": 7517474,
  "type": "Feature",
  "properties": {
    "tgn:hierarchy":[
        "tgn:7517474",
        "tgn:7016670",
        "tgn:1008380",
        "tgn:1000226",
        "tgn:1000006",
        "tgn:7029392"
    ],
    "tgn:id":7517474,
    "tgn:name:en":"McNutts",
    "tgn:placetype":[
        "aat:300000206"
    ]
},
  "bbox": [],
  "geometry": {"coordinates":[176.533333,-40.116667],"type":"Point"}
}