{
  "id": 7277664,
  "type": "Feature",
  "properties": {
    "tgn:hierarchy":[
        "tgn:7277664",
        "tgn:1001657",
        "tgn:1000049",
        "tgn:1000002",
        "tgn:7029392"
    ],
    "tgn:id":7277664,
    "tgn:name":"Verbena, Cerro",
    "tgn:placetype":[
        "aat:300008795"
    ]
},
  "bbox": [],
  "geometry": {"coordinates":[-71.266667,-31.616667],"type":"Point"}
}