{
  "id": 2526338,
  "type": "Feature",
  "properties": {
    "tgn:hierarchy":[
        "tgn:2526338",
        "tgn:1000001",
        "tgn:7012149",
        "tgn:2002066",
        "tgn:7007826",
        "tgn:7029392"
    ],
    "tgn:id":2526338,
    "tgn:name":"Moss Hill",
    "tgn:placetype":[
        "aat:300008798"
    ]
},
  "bbox": [],
  "geometry": {"coordinates":[-93.6833,31.35],"type":"Point"}
}