{
  "id": 2410049,
  "type": "Feature",
  "properties": {
    "tgn:hierarchy":[
        "tgn:2410049",
        "tgn:1000001",
        "tgn:7012149",
        "tgn:1002423",
        "tgn:7007568",
        "tgn:7029392"
    ],
    "tgn:id":2410049,
    "tgn:name":"Inbocht Bay",
    "tgn:placetype":[
        "aat:300132316"
    ]
},
  "bbox": [],
  "geometry": {"coordinates":[-73.8833,42.1667],"type":"Point"}
}