{
  "id": 1046910,
  "type": "Feature",
  "properties": {
    "tgn:hierarchy":[
        "tgn:1046910",
        "tgn:1003440",
        "tgn:1000003",
        "tgn:7003124",
        "tgn:1000080",
        "tgn:7029392"
    ],
    "tgn:id":1046910,
    "tgn:name":"Silandro",
    "tgn:placetype":[
        "aat:300008347"
    ]
},
  "bbox": [],
  "geometry": {"coordinates":[10.766667,46.633333],"type":"Point"}
}