{
  "id": 2508862,
  "type": "Feature",
  "properties": {
    "tgn:hierarchy":[
        "tgn:2508862",
        "tgn:1000001",
        "tgn:7012149",
        "tgn:2000476",
        "tgn:7007250",
        "tgn:7029392"
    ],
    "tgn:id":2508862,
    "tgn:name":"Middle Fork Clarks Fork",
    "tgn:placetype":[
        "aat:300008699"
    ]
},
  "bbox": [],
  "geometry": {"coordinates":[-116.4667,45.45],"type":"Point"}
}