{
  "id": 1057624,
  "type": "Feature",
  "properties": {
    "tgn:hierarchy":[
        "tgn:1057624",
        "tgn:1000004",
        "tgn:1003555",
        "tgn:7018214",
        "tgn:7002435",
        "tgn:7029392"
    ],
    "tgn:id":1057624,
    "tgn:name":"Novoaleksandrovsk",
    "tgn:placetype":[
        "aat:300008347"
    ]
},
  "bbox": [],
  "geometry": {"coordinates":[41.2333,45.5167],"type":"Point"}
}