{
  "id": 2406477,
  "type": "Feature",
  "properties": {
    "tgn:hierarchy":[
        "tgn:2406477",
        "tgn:1000001",
        "tgn:7012149",
        "tgn:1002920",
        "tgn:7007568",
        "tgn:7029392"
    ],
    "tgn:id":2406477,
    "tgn:name":"Hungry Hollow",
    "tgn:placetype":[
        "aat:300008761"
    ]
},
  "bbox": [],
  "geometry": {"coordinates":[-77.5667,42.3333],"type":"Point"}
}