<<<<<<< HEAD
{
  "id": 2406477,
  "type": "Feature",
  "properties": {
    "tgn:hierarchy":[
        "tgn:2406477",
        "tgn:1000001",
        "tgn:7012149",
        "tgn:1002920",
        "tgn:7007568",
        "tgn:7029392"
    ],
    "tgn:id":2406477,
    "tgn:name":"Hungry Hollow",
    "tgn:placetype":[
        "aat:300008761"
    ]
},
  "bbox": [],
  "geometry": {"coordinates":[-77.5667,42.3333],"type":"Point"}
}
=======
{"geometry":{"type":"Point","coordinates":[-77.566700,42.333300]},"type":"Feature","properties":{"hierarchy":["tgn:2406477","tgn:1000001","tgn:7012149","tgn:1002920","tgn:7007568","tgn:7029392"],"placetype":["aat:300008761"],"id":2406477,"name:xx":"Hungry Hollow"}}
>>>>>>> 03f74aca74312dbeaf24d7e61306dd6a786dc3d0
