{
  "id": 2670457,
  "type": "Feature",
  "properties": {
    "tgn:hierarchy":[
        "tgn:2670457",
        "tgn:1000001",
        "tgn:7012149",
        "tgn:2001165",
        "tgn:7007522",
        "tgn:7029392"
    ],
    "tgn:id":2670457,
    "tgn:name":"Smallwood Hills",
    "tgn:placetype":[
        "aat:300008798"
    ]
},
  "bbox": [],
  "geometry": {"coordinates":[-89.25,32.9667],"type":"Point"}
}