{
  "id": 2321478,
  "type": "Feature",
  "properties": {
    "tgn:hierarchy":[
        "tgn:2321478",
        "tgn:1000001",
        "tgn:7012149",
        "tgn:2001985",
        "tgn:7007826",
        "tgn:7029392"
    ],
    "tgn:id":2321478,
    "tgn:name":"Fairmont",
    "tgn:placetype":[
        "aat:300008347"
    ]
},
  "bbox": [],
  "geometry": {"coordinates":[-101.05,34.25],"type":"Point"}
}