{
  "id": 7491279,
  "type": "Feature",
  "properties": {
    "tgn:hierarchy":[
        "tgn:7491279",
        "tgn:1000004",
        "tgn:7467799",
        "tgn:1000141",
        "tgn:7029392"
    ],
    "tgn:id":7491279,
    "tgn:name":"Banludian",
    "tgn:placetype":[
        "aat:300008347"
    ]
},
  "bbox": [],
  "geometry": {"coordinates":[120.467222,24.048611],"type":"Point"}
}