<<<<<<< HEAD
{
  "id": 7023620,
  "type": "Feature",
  "properties": {
    "tgn:hierarchy":[
        "tgn:7023620",
        "tgn:1000001",
        "tgn:7012149",
        "tgn:7007825",
        "tgn:7029392"
    ],
    "tgn:id":7023620,
    "tgn:name":"Overall Creek",
    "tgn:placetype":[
        "aat:300008706"
    ]
},
  "bbox": [],
  "geometry": {"coordinates":[-86.6667,35.7333],"type":"Point"}
}
=======
{"geometry":{"type":"Point","coordinates":[-86.666700,35.733300]},"type":"Feature","properties":{"hierarchy":["tgn:7023620","tgn:1000001","tgn:7012149","tgn:7007825","tgn:7029392"],"placetype":["aat:300008706"],"id":7023620,"name:xx":"Overall Creek"}}
>>>>>>> 03f74aca74312dbeaf24d7e61306dd6a786dc3d0
