{
  "id": 7023620,
  "type": "Feature",
  "properties": {
    "tgn:hierarchy":[
        "tgn:7023620",
        "tgn:1000001",
        "tgn:7012149",
        "tgn:7007825",
        "tgn:7029392"
    ],
    "tgn:id":7023620,
    "tgn:name":"Overall Creek",
    "tgn:placetype":[
        "aat:300008706"
    ]
},
  "bbox": [],
  "geometry": {"coordinates":[-86.6667,35.7333],"type":"Point"}
}