{
  "id": 2431085,
  "type": "Feature",
  "properties": {
    "tgn:hierarchy":[
        "tgn:2431085",
        "tgn:7006450",
        "tgn:1000001",
        "tgn:7012149",
        "tgn:7029392"
    ],
    "tgn:id":2431085,
    "tgn:name":"Kangilipak, Lake",
    "tgn:placetype":[
        "aat:300008680"
    ]
},
  "bbox": [],
  "geometry": {"coordinates":[-159.1167,67.9833],"type":"Point"}
}