{
  "id": 2330414,
  "type": "Feature",
  "properties": {
    "tgn:hierarchy":[
        "tgn:2330414",
        "tgn:1000001",
        "tgn:1002714",
        "tgn:7012149",
        "tgn:7007159",
        "tgn:7029392"
    ],
    "tgn:id":2330414,
    "tgn:name":"Flat Brook",
    "tgn:placetype":[
        "aat:300008699"
    ]
},
  "bbox": [],
  "geometry": {"coordinates":[-72.0667,41.3833],"type":"Point"}
}