{
  "id": 2103545,
  "type": "Feature",
  "properties": {
    "tgn:hierarchy":[
        "tgn:2103545",
        "tgn:1000001",
        "tgn:7012149",
        "tgn:1002230",
        "tgn:7007826",
        "tgn:7029392"
    ],
    "tgn:id":2103545,
    "tgn:name":"Crossroads",
    "tgn:placetype":[
        "aat:300008347",
        "aat:300387210"
    ]
},
  "bbox": [],
  "geometry": {"coordinates":[-94.95,32.9167],"type":"Point"}
}