{
  "id": 1008787,
  "type": "Feature",
  "properties": {
    "tgn:hierarchy":[
        "tgn:1008787",
        "tgn:1000001",
        "tgn:7012149",
        "tgn:1002924",
        "tgn:7007568",
        "tgn:7029392"
    ],
    "tgn:id":1008787,
    "tgn:name":"Robins Island",
    "tgn:placetype":[
        "aat:300008791"
    ]
},
  "bbox": [],
  "geometry": {"coordinates":[-72.45,40.9667],"type":"Point"}
}