{
  "id": 7255483,
  "type": "Feature",
  "properties": {
    "tgn:hierarchy":[
        "tgn:7255483",
        "tgn:7007877",
        "tgn:1000003",
        "tgn:1000063",
        "tgn:4012014",
        "tgn:7029392"
    ],
    "tgn:id":7255483,
    "tgn:name":"Rognaux, Rieu des",
    "tgn:placetype":[
        "aat:300008699"
    ]
},
  "bbox": [],
  "geometry": {"coordinates":[3.933333,50.416667],"type":"Point"}
}