{
  "id": 7234464,
  "type": "Feature",
  "properties": {
    "tgn:hierarchy":[
        "tgn:7234464",
        "tgn:7011163",
        "tgn:7002674",
        "tgn:1000003",
        "tgn:1000074",
        "tgn:7029392"
    ],
    "tgn:id":7234464,
    "tgn:name":"Dh\u00e1fni",
    "tgn:placetype":[
        "aat:300008347"
    ]
},
  "bbox": [],
  "geometry": {"coordinates":[25.166667,39.95],"type":"Point"}
}