{
  "id": 7561271,
  "type": "Feature",
  "properties": {
    "tgn:hierarchy":[
        "tgn:7561271",
        "tgn:1000004",
        "tgn:7000198",
        "tgn:7016722",
        "tgn:7029392"
    ],
    "tgn:id":7561271,
    "tgn:name:en":"Bhasr\u0101ra",
    "tgn:placetype":[
        "aat:300008347"
    ]
},
  "bbox": [],
  "geometry": {"coordinates":[79.261063,27.941951],"type":"Point"}
}