<<<<<<< HEAD
{
  "id": 7485138,
  "type": "Feature",
  "properties": {
    "tgn:hierarchy":[
        "tgn:7485138",
        "tgn:1000004",
        "tgn:7467799",
        "tgn:1000141",
        "tgn:7029392"
    ],
    "tgn:id":7485138,
    "tgn:name":"Xili Qiao",
    "tgn:placetype":[
        "aat:300007836"
    ]
},
  "bbox": [],
  "geometry": {"coordinates":[120.485278,24.104722],"type":"Point"}
}
=======
{"geometry":{"type":"Point","coordinates":[120.485278,24.104722]},"type":"Feature","properties":{"hierarchy":["tgn:7485138","tgn:1000004","tgn:7467799","tgn:1000141","tgn:7029392"],"placetype":["aat:300007836"],"id":7485138,"name:xx":"Xili Qiao"}}
>>>>>>> 03f74aca74312dbeaf24d7e61306dd6a786dc3d0
