{
  "id": 2559522,
  "type": "Feature",
  "properties": {
    "tgn:hierarchy":[
        "tgn:2559522",
        "tgn:1000001",
        "tgn:7012149",
        "tgn:2001298",
        "tgn:7007524",
        "tgn:7029392"
    ],
    "tgn:id":2559522,
    "tgn:name":"Ontario Millsite",
    "tgn:placetype":[
        "aat:300000390"
    ]
},
  "bbox": [],
  "geometry": {"coordinates":[-112.3333,46.4167],"type":"Point"}
}