{
  "id": 7313116,
  "type": "Feature",
  "properties": {
    "tgn:hierarchy":[
        "tgn:7313116",
        "tgn:1001623",
        "tgn:1000049",
        "tgn:1000002",
        "tgn:7029392"
    ],
    "tgn:id":7313116,
    "tgn:name":"Lobato, Caleta",
    "tgn:placetype":[
        "aat:300132317"
    ]
},
  "bbox": [],
  "geometry": {"coordinates":[-74.783333,-45.883333],"type":"Point"}
}