{
  "id": 7482487,
  "type": "Feature",
  "properties": {
    "tgn:hierarchy":[
        "tgn:7482487",
        "tgn:1000004",
        "tgn:7490934",
        "tgn:1000141",
        "tgn:7029392"
    ],
    "tgn:id":7482487,
    "tgn:name":"Beiluke",
    "tgn:placetype":[
        "aat:300008347"
    ]
},
  "bbox": [],
  "geometry": {"coordinates":[120.226389,23.205278],"type":"Point"}
}