<<<<<<< HEAD
{
  "id": 7482487,
  "type": "Feature",
  "properties": {
    "tgn:hierarchy":[
        "tgn:7482487",
        "tgn:1000004",
        "tgn:7490934",
        "tgn:1000141",
        "tgn:7029392"
    ],
    "tgn:id":7482487,
    "tgn:name":"Beiluke",
    "tgn:placetype":[
        "aat:300008347"
    ]
},
  "bbox": [],
  "geometry": {"coordinates":[120.226389,23.205278],"type":"Point"}
}
=======
{"geometry":{"type":"Point","coordinates":[120.226389,23.205278]},"type":"Feature","properties":{"hierarchy":["tgn:7482487","tgn:1000004","tgn:7490934","tgn:1000141","tgn:7029392"],"placetype":["aat:300008347"],"id":7482487,"name:xx":"Beiluke"}}
>>>>>>> 03f74aca74312dbeaf24d7e61306dd6a786dc3d0
