{
  "id": 1094386,
  "type": "Feature",
  "properties": {
    "tgn:hierarchy":[
        "tgn:1094386",
        "tgn:7001242",
        "tgn:1001082",
        "tgn:7441551",
        "tgn:7029392"
    ],
    "tgn:id":1094386,
    "tgn:name":"Nagishot",
    "tgn:placetype":[
        "aat:300008347"
    ]
},
  "bbox": [],
  "geometry": {"coordinates":[33.5667,4.2667],"type":"Point"}
}