{
  "id": 7163276,
  "type": "Feature",
  "properties": {
    "tgn:hierarchy":[
        "tgn:7163276",
        "tgn:7003669",
        "tgn:1000003",
        "tgn:7000084",
        "tgn:7029392"
    ],
    "tgn:id":7163276,
    "tgn:name":"H\u00f6rmann",
    "tgn:placetype":[
        "aat:300000206"
    ]
},
  "bbox": [],
  "geometry": {"coordinates":[12.666667,48.166667],"type":"Point"}
}