{
  "id": 7260217,
  "type": "Feature",
  "properties": {
    "tgn:hierarchy":[
        "tgn:7260217",
        "tgn:7003619",
        "tgn:1000003",
        "tgn:7016845",
        "tgn:7029392"
    ],
    "tgn:id":7260217,
    "tgn:name:nl":"De Kievit",
    "tgn:placetype":[
        "aat:300387502"
    ]
},
  "bbox": [],
  "geometry": {"coordinates":[6.116667,52.066667],"type":"Point"}
}