{
  "id": 7437479,
  "type": "Feature",
  "properties": {
    "tgn:hierarchy":[
        "tgn:7437479",
        "tgn:7005583",
        "tgn:1000001",
        "tgn:7005560",
        "tgn:7029392"
    ],
    "tgn:id":7437479,
    "tgn:name":"Santa Teresa",
    "tgn:placetype":[
        "aat:300000241"
    ]
},
  "bbox": [],
  "geometry": {"coordinates":[-104.886667,24.572778],"type":"Point"}
}