{
  "id": 2343646,
  "type": "Feature",
  "properties": {
    "tgn:hierarchy":[
        "tgn:2343646",
        "tgn:1000001",
        "tgn:7012149",
        "tgn:7007158",
        "tgn:2000247",
        "tgn:7029392"
    ],
    "tgn:id":2343646,
    "tgn:name":"Galfy Boy Mine",
    "tgn:placetype":[
        "aat:300000390"
    ]
},
  "bbox": [],
  "geometry": {"coordinates":[-107.65,37.8833],"type":"Point"}
}