<<<<<<< HEAD
{
  "id": 7376796,
  "type": "Feature",
  "properties": {
    "tgn:hierarchy":[
        "tgn:7376796",
        "tgn:7005580",
        "tgn:1000001",
        "tgn:7005560",
        "tgn:7029392"
    ],
    "tgn:id":7376796,
    "tgn:name":"Las Margaritas",
    "tgn:placetype":[
        "aat:300008347"
    ]
},
  "bbox": [],
  "geometry": {"coordinates":[-93.1,15.55],"type":"Point"}
}
=======
{"geometry":{"type":"Point","coordinates":[-93.100000,15.550000]},"type":"Feature","properties":{"hierarchy":["tgn:7376796","tgn:7005580","tgn:1000001","tgn:7005560","tgn:7029392"],"placetype":["aat:300008347"],"id":7376796,"name:xx":"Las Margaritas"}}
>>>>>>> 03f74aca74312dbeaf24d7e61306dd6a786dc3d0
