{
  "id": 7475052,
  "type": "Feature",
  "properties": {
    "tgn:hierarchy":[
        "tgn:7475052",
        "tgn:1000004",
        "tgn:7001009",
        "tgn:1000141",
        "tgn:7029392"
    ],
    "tgn:id":7475052,
    "tgn:name":"Toubiankeng Xi",
    "tgn:placetype":[
        "aat:300008699"
    ]
},
  "bbox": [],
  "geometry": {"coordinates":[120.665065,24.080827],"type":"Point"}
}