<<<<<<< HEAD
{
  "id": 7475052,
  "type": "Feature",
  "properties": {
    "tgn:hierarchy":[
        "tgn:7475052",
        "tgn:1000004",
        "tgn:7001009",
        "tgn:1000141",
        "tgn:7029392"
    ],
    "tgn:id":7475052,
    "tgn:name":"Toubiankeng Xi",
    "tgn:placetype":[
        "aat:300008699"
    ]
},
  "bbox": [],
  "geometry": {"coordinates":[120.665065,24.080827],"type":"Point"}
}
=======
{"geometry":{"type":"Point","coordinates":[120.665065,24.080827]},"type":"Feature","properties":{"hierarchy":["tgn:7475052","tgn:1000004","tgn:7001009","tgn:1000141","tgn:7029392"],"placetype":["aat:300008699"],"id":7475052,"name:xx":"Toubiankeng Xi"}}
>>>>>>> 03f74aca74312dbeaf24d7e61306dd6a786dc3d0
