<<<<<<< HEAD
{
  "id": 2767533,
  "type": "Feature",
  "properties": {
    "tgn:hierarchy":[
        "tgn:2767533",
        "tgn:1000001",
        "tgn:7012149",
        "tgn:2002282",
        "tgn:7013961",
        "tgn:7029392"
    ],
    "tgn:id":2767533,
    "tgn:name":"White Tree Hill",
    "tgn:placetype":[
        "aat:300008798"
    ]
},
  "bbox": [],
  "geometry": {"coordinates":[-80.7667,37.4833],"type":"Point"}
}
=======
{"geometry":{"type":"Point","coordinates":[-80.766700,37.483300]},"type":"Feature","properties":{"hierarchy":["tgn:2767533","tgn:1000001","tgn:7012149","tgn:2002282","tgn:7013961","tgn:7029392"],"placetype":["aat:300008798"],"id":2767533,"name:xx":"White Tree Hill"}}
>>>>>>> 03f74aca74312dbeaf24d7e61306dd6a786dc3d0
