{
  "id": 2026059,
  "type": "Feature",
  "properties": {
    "tgn:hierarchy":[
        "tgn:2026059",
        "tgn:1000001",
        "tgn:7012149",
        "tgn:2000484",
        "tgn:7007250",
        "tgn:7029392"
    ],
    "tgn:id":2026059,
    "tgn:name":"Rexburg",
    "tgn:placetype":[
        "aat:300008347"
    ]
},
  "bbox": [],
  "geometry": {"coordinates":[-111.7833,43.8167],"type":"Point"}
}