{
  "id": 2755708,
  "type": "Feature",
  "properties": {
    "tgn:hierarchy":[
        "tgn:2755708",
        "tgn:1000001",
        "tgn:7012149",
        "tgn:2000346",
        "tgn:7007248",
        "tgn:7029392"
    ],
    "tgn:id":2755708,
    "tgn:name":"Weece Mill Creek",
    "tgn:placetype":[
        "aat:300008706"
    ]
},
  "bbox": [],
  "geometry": {"coordinates":[-84.2667,34.9833],"type":"Point"}
}