{
  "id": 2732375,
  "type": "Feature",
  "properties": {
    "tgn:hierarchy":[
        "tgn:2732375",
        "tgn:1000001",
        "tgn:7012149",
        "tgn:2002353",
        "tgn:7007922",
        "tgn:7029392"
    ],
    "tgn:id":2732375,
    "tgn:name":"Turk Spring",
    "tgn:placetype":[
        "aat:300008697"
    ]
},
  "bbox": [],
  "geometry": {"coordinates":[-91.4333,46.0333],"type":"Point"}
}