{
  "id": 7427061,
  "type": "Feature",
  "properties": {
    "tgn:hierarchy":[
        "tgn:7427061",
        "tgn:7005581",
        "tgn:1000001",
        "tgn:7005560",
        "tgn:7029392"
    ],
    "tgn:id":7427061,
    "tgn:name":"Las Tunitas",
    "tgn:placetype":[
        "aat:300008347"
    ]
},
  "bbox": [],
  "geometry": {"coordinates":[-108.383333,27.55],"type":"Point"}
}