{
  "id": 2576854,
  "type": "Feature",
  "properties": {
    "tgn:hierarchy":[
        "tgn:2576854",
        "tgn:1000001",
        "tgn:7012149",
        "tgn:2001449",
        "tgn:7007566",
        "tgn:7029392"
    ],
    "tgn:id":2576854,
    "tgn:name":"Petaca Tank",
    "tgn:placetype":[
        "aat:300006191"
    ]
},
  "bbox": [],
  "geometry": {"coordinates":[-106.05,36.6667],"type":"Point"}
}