{
  "id": 7557262,
  "type": "Feature",
  "properties": {
    "tgn:hierarchy":[
        "tgn:7557262",
        "tgn:1000004",
        "tgn:1001869",
        "tgn:7000198",
        "tgn:7029392"
    ],
    "tgn:id":7557262,
    "tgn:name:en":"Salabatpura",
    "tgn:placetype":[
        "aat:300000745"
    ]
},
  "bbox": [],
  "geometry": {"coordinates":[72.833333,21.166667],"type":"Point"}
}