<<<<<<< HEAD
{
  "id": 2338798,
  "type": "Feature",
  "properties": {
    "tgn:hierarchy":[
        "tgn:2338798",
        "tgn:1000001",
        "tgn:7012149",
        "tgn:2001036",
        "tgn:7007521",
        "tgn:7029392"
    ],
    "tgn:id":2338798,
    "tgn:name":"Frank Lake",
    "tgn:placetype":[
        "aat:300008680"
    ]
},
  "bbox": [],
  "geometry": {"coordinates":[-91.2833,47.65],"type":"Point"}
}
=======
{"geometry":{"type":"Point","coordinates":[-91.283300,47.650000]},"type":"Feature","properties":{"hierarchy":["tgn:2338798","tgn:1000001","tgn:7012149","tgn:2001036","tgn:7007521","tgn:7029392"],"placetype":["aat:300008680"],"id":2338798,"name:xx":"Frank Lake"}}
>>>>>>> 03f74aca74312dbeaf24d7e61306dd6a786dc3d0
