{
  "id": 2048620,
  "type": "Feature",
  "properties": {
    "tgn:hierarchy":[
        "tgn:2048620",
        "tgn:1002238",
        "tgn:1000001",
        "tgn:7012149",
        "tgn:7007516",
        "tgn:7029392"
    ],
    "tgn:id":2048620,
    "tgn:name":"Sandyville",
    "tgn:placetype":[
        "aat:300008347"
    ]
},
  "bbox": [],
  "geometry": {"coordinates":[-76.9167,39.5167],"type":"Point"}
}