{
  "id": 2092963,
  "type": "Feature",
  "properties": {
    "tgn:hierarchy":[
        "tgn:2092963",
        "tgn:1000001",
        "tgn:1002272",
        "tgn:7012149",
        "tgn:7007710",
        "tgn:7029392"
    ],
    "tgn:id":2092963,
    "tgn:name":"Shannondale",
    "tgn:placetype":[
        "aat:300008347"
    ]
},
  "bbox": [],
  "geometry": {"coordinates":[-79.2167,41.0667],"type":"Point"}
}