{
  "id": 7295664,
  "type": "Feature",
  "properties": {
    "tgn:hierarchy":[
        "tgn:7295664",
        "tgn:7002803",
        "tgn:1001647",
        "tgn:1000003",
        "tgn:1000095",
        "tgn:7029392"
    ],
    "tgn:id":7295664,
    "tgn:name":"Villavaliente",
    "tgn:placetype":[
        "aat:300008347"
    ]
},
  "bbox": [],
  "geometry": {"coordinates":[-1.45,39.133333],"type":"Point"}
}