{
  "id": 2671849,
  "type": "Feature",
  "properties": {
    "tgn:hierarchy":[
        "tgn:2671849",
        "tgn:1000001",
        "tgn:1002840",
        "tgn:7012149",
        "tgn:7007828",
        "tgn:7029392"
    ],
    "tgn:id":2671849,
    "tgn:name":"Smith Pond",
    "tgn:placetype":[
        "aat:300008680"
    ]
},
  "bbox": [],
  "geometry": {"coordinates":[-73.05,43.7167],"type":"Point"}
}