{
  "id": 1004463,
  "type": "Feature",
  "properties": {
    "tgn:hierarchy":[
        "tgn:1004463",
        "tgn:7003138",
        "tgn:1000003",
        "tgn:7003080",
        "tgn:1000080",
        "tgn:7000874",
        "tgn:7029392"
    ],
    "tgn:id":1004463,
    "tgn:name":"Finocchio",
    "tgn:placetype":[
        "aat:300000745"
    ]
},
  "bbox": [],
  "geometry": {"coordinates":[12.6833,41.8833],"type":"Point"}
}