{
  "id": 7174820,
  "type": "Feature",
  "properties": {
    "tgn:hierarchy":[
        "tgn:7174820",
        "tgn:1000003",
        "tgn:7003678",
        "tgn:7000084",
        "tgn:7029392"
    ],
    "tgn:id":7174820,
    "tgn:name":"Gro\u00dfer Gruben-Hauck",
    "tgn:placetype":[
        "aat:300008777"
    ]
},
  "bbox": [],
  "geometry": {"coordinates":[9.933333,50.583333],"type":"Point"}
}