{
  "id": 2426101,
  "type": "Feature",
  "properties": {
    "tgn:hierarchy":[
        "tgn:2426101",
        "tgn:1000001",
        "tgn:7012149",
        "tgn:1002795",
        "tgn:7007826",
        "tgn:7029392"
    ],
    "tgn:id":2426101,
    "tgn:name":"Jones Branch",
    "tgn:placetype":[
        "aat:300008699"
    ]
},
  "bbox": [],
  "geometry": {"coordinates":[-94.6833,31.05],"type":"Point"}
}