{
  "id": 7418858,
  "type": "Feature",
  "properties": {
    "tgn:hierarchy":[
        "tgn:7418858",
        "tgn:1001835",
        "tgn:1000001",
        "tgn:7005560",
        "tgn:7029392"
    ],
    "tgn:id":7418858,
    "tgn:name":"La Pila, Ca\u00f1ada",
    "tgn:placetype":[
        "aat:300266554",
        "aat:300008699"
    ]
},
  "bbox": [],
  "geometry": {"coordinates":[-116.806111,32.116111],"type":"Point"}
}