{
  "id": 7008252,
  "type": "Feature",
  "properties": {
    "tgn:hierarchy":[
        "tgn:7008252",
        "tgn:1000003",
        "tgn:7002875",
        "tgn:1000070",
        "tgn:7029392"
    ],
    "tgn:id":7008252,
    "tgn:name":"Guillon",
    "tgn:placetype":[
        "aat:300008347"
    ]
},
  "bbox": [],
  "geometry": {"coordinates":[4.0833,47.5167],"type":"Point"}
}