<<<<<<< HEAD
{
  "id": 2336124,
  "type": "Feature",
  "properties": {
    "tgn:hierarchy":[
        "tgn:2336124",
        "tgn:1000001",
        "tgn:2001938",
        "tgn:7012149",
        "tgn:7007826",
        "tgn:7029392"
    ],
    "tgn:id":2336124,
    "tgn:name":"Foster Hollow",
    "tgn:placetype":[
        "aat:300008761"
    ]
},
  "bbox": [],
  "geometry": {"coordinates":[-99.5,29.7333],"type":"Point"}
}
=======
{"geometry":{"type":"Point","coordinates":[-99.500000,29.733300]},"type":"Feature","properties":{"hierarchy":["tgn:2336124","tgn:1000001","tgn:2001938","tgn:7012149","tgn:7007826","tgn:7029392"],"placetype":["aat:300008761"],"id":2336124,"name:xx":"Foster Hollow"}}
>>>>>>> 03f74aca74312dbeaf24d7e61306dd6a786dc3d0
