{
  "id": 7375923,
  "type": "Feature",
  "properties": {
    "tgn:hierarchy":[
        "tgn:7375923",
        "tgn:7005586",
        "tgn:1000001",
        "tgn:7005560",
        "tgn:7029392"
    ],
    "tgn:id":7375923,
    "tgn:name":"Las Higueras",
    "tgn:placetype":[
        "aat:300008347"
    ]
},
  "bbox": [],
  "geometry": {"coordinates":[-103.166667,19.583333],"type":"Point"}
}