{
  "id": 2744380,
  "type": "Feature",
  "properties": {
    "tgn:hierarchy":[
        "tgn:2744380",
        "tgn:1000001",
        "tgn:1002189",
        "tgn:7012149",
        "tgn:7007255",
        "tgn:7029392"
    ],
    "tgn:id":2744380,
    "tgn:name":"Verona Branch",
    "tgn:placetype":[
        "aat:300008699"
    ]
},
  "bbox": [],
  "geometry": {"coordinates":[-84.65,38.8167],"type":"Point"}
}