{
  "id": 2089675,
  "type": "Feature",
  "properties": {
    "tgn:hierarchy":[
        "tgn:2089675",
        "tgn:1000001",
        "tgn:7012149",
        "tgn:7014185",
        "tgn:7007710",
        "tgn:7029392"
    ],
    "tgn:id":2089675,
    "tgn:name":"Juniata",
    "tgn:placetype":[
        "aat:300008347"
    ]
},
  "bbox": [],
  "geometry": {"coordinates":[-79.6833,39.9833],"type":"Point"}
}