{
  "id": 2565998,
  "type": "Feature",
  "properties": {
    "tgn:hierarchy":[
        "tgn:2565998",
        "tgn:1000001",
        "tgn:7012149",
        "tgn:7007157",
        "tgn:1003046",
        "tgn:7029392"
    ],
    "tgn:id":2565998,
    "tgn:name":"Palmer Canyon",
    "tgn:placetype":[
        "aat:300008761"
    ]
},
  "bbox": [],
  "geometry": {"coordinates":[-122.2167,38.7333],"type":"Point"}
}