<<<<<<< HEAD
{
  "id": 7374941,
  "type": "Feature",
  "properties": {
    "tgn:hierarchy":[
        "tgn:7374941",
        "tgn:7005583",
        "tgn:1000001",
        "tgn:7005560",
        "tgn:7029392"
    ],
    "tgn:id":7374941,
    "tgn:name":"Laborcita",
    "tgn:placetype":[
        "aat:300008347"
    ]
},
  "bbox": [],
  "geometry": {"coordinates":[-104.35,23.533333],"type":"Point"}
}
=======
{"geometry":{"type":"Point","coordinates":[-104.350000,23.533333]},"type":"Feature","properties":{"hierarchy":["tgn:7374941","tgn:7005583","tgn:1000001","tgn:7005560","tgn:7029392"],"placetype":["aat:300008347"],"id":7374941,"name:xx":"Laborcita"}}
>>>>>>> 03f74aca74312dbeaf24d7e61306dd6a786dc3d0
