{
  "id": 7589243,
  "type": "Feature",
  "properties": {
    "tgn:hierarchy":[
        "tgn:7589243",
        "tgn:1000004",
        "tgn:7000198",
        "tgn:1001977",
        "tgn:7029392"
    ],
    "tgn:id":7589243,
    "tgn:name:en":"Western Channel",
    "tgn:placetype":[
        "aat:300387026"
    ]
},
  "bbox": [],
  "geometry": {"coordinates":[87.966111,21.268056],"type":"Point"}
}