{
  "id": 7530058,
  "type": "Feature",
  "properties": {
    "tgn:hierarchy":[
        "tgn:7530058",
        "tgn:7001242",
        "tgn:7016833",
        "tgn:1001083",
        "tgn:7029392"
    ],
    "tgn:id":7530058,
    "tgn:name":"Shirkat al Mas\u0101bik al \u1e28ad\u012bthah",
    "tgn:placetype":[
        "aat:300004792"
    ]
},
  "bbox": [],
  "geometry": {"coordinates":[31.188619,30.128396],"type":"Point"}
}