{
  "id": 1095661,
  "type": "Feature",
  "properties": {
    "tgn:hierarchy":[
        "tgn:1095661",
        "tgn:7001242",
        "tgn:7016833",
        "tgn:1001088",
        "tgn:7029392"
    ],
    "tgn:id":1095661,
    "tgn:name:en":"Qulubb\u0101",
    "tgn:placetype":[
        "aat:300008347"
    ]
},
  "bbox": [],
  "geometry": {"coordinates":[30.831191,27.753582],"type":"Point"}
}