{
  "id": 7483864,
  "type": "Feature",
  "properties": {
    "tgn:hierarchy":[
        "tgn:7483864",
        "tgn:1000004",
        "tgn:7001009",
        "tgn:1000141",
        "tgn:7029392"
    ],
    "tgn:id":7483864,
    "tgn:name":"Fanziliao Haiti",
    "tgn:placetype":[
        "aat:300006156"
    ]
},
  "bbox": [],
  "geometry": {"coordinates":[120.584722,24.318056],"type":"Point"}
}