<<<<<<< HEAD
{
  "id": 7483461,
  "type": "Feature",
  "properties": {
    "tgn:hierarchy":[
        "tgn:7483461",
        "tgn:1000004",
        "tgn:7491221",
        "tgn:1000141",
        "tgn:7029392"
    ],
    "tgn:id":7483461,
    "tgn:name":"Baisha",
    "tgn:placetype":[
        "aat:300008347"
    ]
},
  "bbox": [],
  "geometry": {"coordinates":[121.5,22.638333],"type":"Point"}
}
=======
{"geometry":{"type":"Point","coordinates":[121.500000,22.638333]},"type":"Feature","properties":{"hierarchy":["tgn:7483461","tgn:1000004","tgn:7491221","tgn:1000141","tgn:7029392"],"placetype":["aat:300008347"],"id":7483461,"name:xx":"Baisha"}}
>>>>>>> 03f74aca74312dbeaf24d7e61306dd6a786dc3d0
