{
  "id": 2162447,
  "type": "Feature",
  "properties": {
    "tgn:hierarchy":[
        "tgn:2162447",
        "tgn:1000001",
        "tgn:7012149",
        "tgn:2001879",
        "tgn:7007825",
        "tgn:7029392"
    ],
    "tgn:id":2162447,
    "tgn:name":"Ben Holland Hollow",
    "tgn:placetype":[
        "aat:300008761"
    ]
},
  "bbox": [],
  "geometry": {"coordinates":[-87.5833,36.05],"type":"Point"}
}