{
  "id": 1040582,
  "type": "Feature",
  "properties": {
    "tgn:hierarchy":[
        "tgn:1040582",
        "tgn:7003669",
        "tgn:1000003",
        "tgn:7000084",
        "tgn:7029392"
    ],
    "tgn:id":1040582,
    "tgn:name":"Oberscheinfeld",
    "tgn:placetype":[
        "aat:300008347"
    ]
},
  "bbox": [],
  "geometry": {"coordinates":[10.433333,49.716667],"type":"Point"}
}