{
  "id": 7256778,
  "type": "Feature",
  "properties": {
    "tgn:hierarchy":[
        "tgn:7256778",
        "tgn:7007877",
        "tgn:1000003",
        "tgn:1000063",
        "tgn:4012014",
        "tgn:7029392"
    ],
    "tgn:id":7256778,
    "tgn:name":"Wilbeauroux",
    "tgn:placetype":[
        "aat:300008347"
    ]
},
  "bbox": [],
  "geometry": {"coordinates":[4.383333,50.45],"type":"Point"}
}