{
  "id": 7524245,
  "type": "Feature",
  "properties": {
    "tgn:hierarchy":[
        "tgn:7524245",
        "tgn:7001242",
        "tgn:7001105",
        "tgn:7016833",
        "tgn:7029392"
    ],
    "tgn:id":7524245,
    "tgn:name:en":"Al Mudawwarah",
    "tgn:placetype":[
        "aat:300008777"
    ]
},
  "bbox": [],
  "geometry": {"coordinates":[30.348823,29.174682],"type":"Point"}
}