{
  "id": 7397710,
  "type": "Feature",
  "properties": {
    "tgn:hierarchy":[
        "tgn:7397710",
        "tgn:1000001",
        "tgn:1001960",
        "tgn:7005560",
        "tgn:7029392"
    ],
    "tgn:id":7397710,
    "tgn:name":"San Nicol\u00e1s",
    "tgn:placetype":[
        "aat:300008347"
    ]
},
  "bbox": [],
  "geometry": {"coordinates":[-109.183333,28.433333],"type":"Point"}
}