{
  "id": 7126321,
  "type": "Feature",
  "properties": {
    "tgn:hierarchy":[
        "tgn:7126321",
        "tgn:7003692",
        "tgn:1000003",
        "tgn:7000084",
        "tgn:7029392"
    ],
    "tgn:id":7126321,
    "tgn:name":"Oberh\u00f6llgrund",
    "tgn:placetype":[
        "aat:300000206"
    ]
},
  "bbox": [],
  "geometry": {"coordinates":[9.083333,49.466667],"type":"Point"}
}