<<<<<<< HEAD
{
  "id": 2406914,
  "type": "Feature",
  "properties": {
    "tgn:hierarchy":[
        "tgn:2406914",
        "tgn:1000001",
        "tgn:2000470",
        "tgn:7012149",
        "tgn:7007250",
        "tgn:7029392"
    ],
    "tgn:id":2406914,
    "tgn:name":"Hunter Creek Summit",
    "tgn:placetype":[
        "aat:300008798"
    ]
},
  "bbox": [],
  "geometry": {"coordinates":[-114.35,43.95],"type":"Point"}
}
=======
{"geometry":{"type":"Point","coordinates":[-114.350000,43.950000]},"type":"Feature","properties":{"hierarchy":["tgn:2406914","tgn:1000001","tgn:2000470","tgn:7012149","tgn:7007250","tgn:7029392"],"placetype":["aat:300008798"],"id":2406914,"name:xx":"Hunter Creek Summit"}}
>>>>>>> 03f74aca74312dbeaf24d7e61306dd6a786dc3d0
