{
  "id": 2750239,
  "type": "Feature",
  "properties": {
    "tgn:hierarchy":[
        "tgn:2750239",
        "tgn:1000001",
        "tgn:7012149",
        "tgn:2002018",
        "tgn:7007826",
        "tgn:7029392"
    ],
    "tgn:id":2750239,
    "tgn:name":"Waltonia",
    "tgn:placetype":[
        "aat:300008347"
    ]
},
  "bbox": [],
  "geometry": {"coordinates":[-99.2833,30.0667],"type":"Point"}
}