<<<<<<< HEAD
{
  "id": 2150338,
  "type": "Feature",
  "properties": {
    "tgn:hierarchy":[
        "tgn:2150338",
        "tgn:1000001",
        "tgn:7012149",
        "tgn:2001275",
        "tgn:7007524",
        "tgn:7029392"
    ],
    "tgn:id":2150338,
    "tgn:name":"Basin Cabin Spring",
    "tgn:placetype":[
        "aat:300008697"
    ]
},
  "bbox": [],
  "geometry": {"coordinates":[-111.2333,44.7],"type":"Point"}
}
=======
{"geometry":{"type":"Point","coordinates":[-111.233300,44.700000]},"type":"Feature","properties":{"hierarchy":["tgn:2150338","tgn:1000001","tgn:7012149","tgn:2001275","tgn:7007524","tgn:7029392"],"placetype":["aat:300008697"],"id":2150338,"name:xx":"Basin Cabin Spring"}}
>>>>>>> 03f74aca74312dbeaf24d7e61306dd6a786dc3d0
