{
  "id": 2728421,
  "type": "Feature",
  "properties": {
    "tgn:hierarchy":[
        "tgn:2728421",
        "tgn:1000001",
        "tgn:1002493",
        "tgn:7012149",
        "tgn:7007565",
        "tgn:7029392"
    ],
    "tgn:id":2728421,
    "tgn:name":"Treasure Island",
    "tgn:placetype":[
        "aat:300008791"
    ]
},
  "bbox": [],
  "geometry": {"coordinates":[-75.05,40.4667],"type":"Point"}
}