{
  "id": 2722056,
  "type": "Feature",
  "properties": {
    "tgn:hierarchy":[
        "tgn:2722056",
        "tgn:1000001",
        "tgn:7006451",
        "tgn:7012149",
        "tgn:2000098",
        "tgn:7029392"
    ],
    "tgn:id":2722056,
    "tgn:name":"Timber Wash",
    "tgn:placetype":[
        "aat:300008699"
    ]
},
  "bbox": [],
  "geometry": {"coordinates":[-113.8833,35.05],"type":"Point"}
}