<<<<<<< HEAD
{
  "id": 7240468,
  "type": "Feature",
  "properties": {
    "tgn:hierarchy":[
        "tgn:7240468",
        "tgn:7007877",
        "tgn:1000003",
        "tgn:1000063",
        "tgn:4012014",
        "tgn:7029392"
    ],
    "tgn:id":7240468,
    "tgn:name":"Estinnes-au-Mont",
    "tgn:placetype":[
        "aat:300008347"
    ]
},
  "bbox": [],
  "geometry": {"coordinates":[4.083333,50.4],"type":"Point"}
}
=======
{"geometry":{"type":"Point","coordinates":[4.083333,50.400000]},"type":"Feature","properties":{"hierarchy":["tgn:7240468","tgn:7007877","tgn:1000003","tgn:1000063","tgn:4012014","tgn:7029392"],"placetype":["aat:300008347"],"id":7240468,"name:xx":"Estinnes-au-Mont"}}
>>>>>>> 03f74aca74312dbeaf24d7e61306dd6a786dc3d0
