{
  "id": 2677939,
  "type": "Feature",
  "properties": {
    "tgn:hierarchy":[
        "tgn:2677939",
        "tgn:1000001",
        "tgn:7012149",
        "tgn:7007524",
        "tgn:7029392"
    ],
    "tgn:id":2677939,
    "tgn:name":"South Fork American Fork",
    "tgn:placetype":[
        "aat:300008699"
    ]
},
  "bbox": [],
  "geometry": {"coordinates":[-110.35,46.1167],"type":"Point"}
}