{
  "id": 7585784,
  "type": "Feature",
  "properties": {
    "tgn:hierarchy":[
        "tgn:7585784",
        "tgn:1000004",
        "tgn:7000198",
        "tgn:7000799",
        "tgn:7029392"
    ],
    "tgn:id":7585784,
    "tgn:name:en":"B\u0101ndi",
    "tgn:placetype":[
        "aat:300008347"
    ]
},
  "bbox": [],
  "geometry": {"coordinates":[74.193572,34.308131],"type":"Point"}
}