{
  "id": 2494126,
  "type": "Feature",
  "properties": {
    "tgn:hierarchy":[
        "tgn:2494126",
        "tgn:1000001",
        "tgn:2000469",
        "tgn:7012149",
        "tgn:7007250",
        "tgn:7029392"
    ],
    "tgn:id":2494126,
    "tgn:name":"Marten Hill",
    "tgn:placetype":[
        "aat:300008798"
    ]
},
  "bbox": [],
  "geometry": {"coordinates":[-115.1333,46.55],"type":"Point"}
}