{
  "id": 7331168,
  "type": "Feature",
  "properties": {
    "tgn:hierarchy":[
        "tgn:7331168",
        "tgn:7001165",
        "tgn:1000003",
        "tgn:7002793",
        "tgn:1000095",
        "tgn:7029392"
    ],
    "tgn:id":7331168,
    "tgn:name":"Grande, R\u00edo",
    "tgn:placetype":[
        "aat:300008699"
    ]
},
  "bbox": [],
  "geometry": {"coordinates":[-0.733333,39.116667],"type":"Point"}
}