<<<<<<< HEAD
{
  "id": 2760630,
  "type": "Feature",
  "properties": {
    "tgn:hierarchy":[
        "tgn:2760630",
        "tgn:1000001",
        "tgn:7006451",
        "tgn:2000092",
        "tgn:7012149",
        "tgn:7029392"
    ],
    "tgn:id":2760630,
    "tgn:name":"West Fork Willow Creek",
    "tgn:placetype":[
        "aat:300008706"
    ]
},
  "bbox": [],
  "geometry": {"coordinates":[-110.9833,34.55],"type":"Point"}
}
=======
{"geometry":{"type":"Point","coordinates":[-110.983300,34.550000]},"type":"Feature","properties":{"hierarchy":["tgn:2760630","tgn:1000001","tgn:7006451","tgn:2000092","tgn:7012149","tgn:7029392"],"placetype":["aat:300008706"],"id":2760630,"name:xx":"West Fork Willow Creek"}}
>>>>>>> 03f74aca74312dbeaf24d7e61306dd6a786dc3d0
