<<<<<<< HEAD
{
  "id": 7176515,
  "type": "Feature",
  "properties": {
    "tgn:hierarchy":[
        "tgn:7176515",
        "tgn:1000003",
        "tgn:7003682",
        "tgn:7000084",
        "tgn:7029392"
    ],
    "tgn:id":7176515,
    "tgn:name":"Hahn bei Marienberg",
    "tgn:placetype":[
        "aat:300008347"
    ]
},
  "bbox": [],
  "geometry": {"coordinates":[7.933333,50.633333],"type":"Point"}
}
=======
{"geometry":{"type":"Point","coordinates":[7.933333,50.633333]},"type":"Feature","properties":{"hierarchy":["tgn:7176515","tgn:1000003","tgn:7003682","tgn:7000084","tgn:7029392"],"placetype":["aat:300008347"],"id":7176515,"name:xx":"Hahn bei Marienberg"}}
>>>>>>> 03f74aca74312dbeaf24d7e61306dd6a786dc3d0
