{
  "id": 7543251,
  "type": "Feature",
  "properties": {
    "tgn:hierarchy":[
        "tgn:7543251",
        "tgn:7001242",
        "tgn:7016833",
        "tgn:7000122",
        "tgn:7029392"
    ],
    "tgn:id":7543251,
    "tgn:name:en":"Naj' al Q\u0101rah",
    "tgn:placetype":[
        "aat:300008347"
    ]
},
  "bbox": [],
  "geometry": {"coordinates":[32.849664,25.035124],"type":"Point"}
}