{
  "id": 7078269,
  "type": "Feature",
  "properties": {
    "tgn:hierarchy":[
        "tgn:7078269",
        "tgn:1000003",
        "tgn:7000094",
        "tgn:7000084",
        "tgn:7029392"
    ],
    "tgn:id":7078269,
    "tgn:name":"Z\u00fcsedom",
    "tgn:placetype":[
        "aat:300008347"
    ]
},
  "bbox": [],
  "geometry": {"coordinates":[14.016667,53.45],"type":"Point"}
}