<<<<<<< HEAD
{
  "id": 2762777,
  "type": "Feature",
  "properties": {
    "tgn:hierarchy":[
        "tgn:2762777",
        "tgn:1000001",
        "tgn:7012149",
        "tgn:7007157",
        "tgn:7014475",
        "tgn:7029392"
    ],
    "tgn:id":2762777,
    "tgn:name":"Western Mines",
    "tgn:placetype":[
        "aat:300000390"
    ]
},
  "bbox": [],
  "geometry": {"coordinates":[-121.4667,37.4],"type":"Point"}
}
=======
{"geometry":{"type":"Point","coordinates":[-121.466700,37.400000]},"type":"Feature","properties":{"hierarchy":["tgn:2762777","tgn:1000001","tgn:7012149","tgn:7007157","tgn:7014475","tgn:7029392"],"placetype":["aat:300000390"],"id":2762777,"name:xx":"Western Mines"}}
>>>>>>> 03f74aca74312dbeaf24d7e61306dd6a786dc3d0
