{
  "id": 7058259,
  "type": "Feature",
  "properties": {
    "tgn:hierarchy":[
        "tgn:7058259",
        "tgn:7003166",
        "tgn:1000003",
        "tgn:7009760",
        "tgn:1000080",
        "tgn:7029392"
    ],
    "tgn:id":7058259,
    "tgn:name":"Anqua",
    "tgn:placetype":[
        "aat:300008347"
    ]
},
  "bbox": [],
  "geometry": {"coordinates":[10.983333,43.216667],"type":"Point"}
}