{
  "id": 7094679,
  "type": "Feature",
  "properties": {
    "tgn:hierarchy":[
        "tgn:7094679",
        "tgn:1000003",
        "tgn:7003677",
        "tgn:7000084",
        "tgn:7029392"
    ],
    "tgn:id":7094679,
    "tgn:name":"Schulze Niehoff",
    "tgn:placetype":[
        "aat:300000206"
    ]
},
  "bbox": [],
  "geometry": {"coordinates":[7.45,52.05],"type":"Point"}
}