{
  "id": 7096496,
  "type": "Feature",
  "properties": {
    "tgn:hierarchy":[
        "tgn:7096496",
        "tgn:1000003",
        "tgn:7003688",
        "tgn:7000084",
        "tgn:7029392"
    ],
    "tgn:id":7096496,
    "tgn:name":"Sehestedt",
    "tgn:placetype":[
        "aat:300008347"
    ]
},
  "bbox": [],
  "geometry": {"coordinates":[9.816667,54.366667],"type":"Point"}
}