<<<<<<< HEAD
{
  "id": 7112160,
  "type": "Feature",
  "properties": {
    "tgn:hierarchy":[
        "tgn:7112160",
        "tgn:7000096",
        "tgn:1000003",
        "tgn:7000084",
        "tgn:7029392"
    ],
    "tgn:id":7112160,
    "tgn:name":"Rheinsberg, Forst",
    "tgn:placetype":[
        "aat:300008863"
    ]
},
  "bbox": [],
  "geometry": {"coordinates":[12.866667,53.1],"type":"Point"}
}
=======
{"geometry":{"type":"Point","coordinates":[12.866667,53.100000]},"type":"Feature","properties":{"hierarchy":["tgn:7112160","tgn:7000096","tgn:1000003","tgn:7000084","tgn:7029392"],"placetype":["aat:300008863"],"id":7112160,"name:xx":"Rheinsberg, Forst"}}
>>>>>>> 03f74aca74312dbeaf24d7e61306dd6a786dc3d0
