{
  "id": 7483678,
  "type": "Feature",
  "properties": {
    "tgn:hierarchy":[
        "tgn:7483678",
        "tgn:1000004",
        "tgn:7489179",
        "tgn:1000141",
        "tgn:7029392"
    ],
    "tgn:id":7483678,
    "tgn:name":"Renze Xincun",
    "tgn:placetype":[
        "aat:300000498"
    ]
},
  "bbox": [],
  "geometry": {"coordinates":[121.898611,24.9425],"type":"Point"}
}