{
  "id": 7399335,
  "type": "Feature",
  "properties": {
    "tgn:hierarchy":[
        "tgn:7399335",
        "tgn:1000001",
        "tgn:7005593",
        "tgn:7005560",
        "tgn:7029392"
    ],
    "tgn:id":7399335,
    "tgn:name":"Apap\u00e1taro",
    "tgn:placetype":[
        "aat:300008347"
    ]
},
  "bbox": [],
  "geometry": {"coordinates":[-100.366667,20.466667],"type":"Point"}
}