{
  "id": 2413556,
  "type": "Feature",
  "properties": {
    "tgn:hierarchy":[
        "tgn:2413556",
        "tgn:1000001",
        "tgn:1002275",
        "tgn:7012149",
        "tgn:7007920",
        "tgn:7029392"
    ],
    "tgn:id":2413556,
    "tgn:name":"Ireland",
    "tgn:placetype":[
        "aat:300008347"
    ]
},
  "bbox": [],
  "geometry": {"coordinates":[-122.3667,45.65],"type":"Point"}
}