{
  "id": 7190904,
  "type": "Feature",
  "properties": {
    "tgn:hierarchy":[
        "tgn:7190904",
        "tgn:7003669",
        "tgn:1000003",
        "tgn:7000084",
        "tgn:7029392"
    ],
    "tgn:id":7190904,
    "tgn:name":"F\u00f6rstersgrund",
    "tgn:placetype":[
        "aat:300008347"
    ]
},
  "bbox": [],
  "geometry": {"coordinates":[10.733333,50.016667],"type":"Point"}
}