<<<<<<< HEAD
{
  "id": 2704749,
  "type": "Feature",
  "properties": {
    "tgn:hierarchy":[
        "tgn:2704749",
        "tgn:1000001",
        "tgn:1002359",
        "tgn:7012149",
        "tgn:7007517",
        "tgn:7029392"
    ],
    "tgn:id":2704749,
    "tgn:name":"Sunset Hill",
    "tgn:placetype":[
        "aat:300008798"
    ]
},
  "bbox": [],
  "geometry": {"coordinates":[-70.6833,42.6167],"type":"Point"}
}
=======
{"geometry":{"type":"Point","coordinates":[-70.683300,42.616700]},"type":"Feature","properties":{"hierarchy":["tgn:2704749","tgn:1000001","tgn:1002359","tgn:7012149","tgn:7007517","tgn:7029392"],"placetype":["aat:300008798"],"id":2704749,"name:xx":"Sunset Hill"}}
>>>>>>> 03f74aca74312dbeaf24d7e61306dd6a786dc3d0
