{
  "id": 2024425,
  "type": "Feature",
  "properties": {
    "tgn:hierarchy":[
        "tgn:2024425",
        "tgn:1000001",
        "tgn:7012149",
        "tgn:2000390",
        "tgn:7007248",
        "tgn:7029392"
    ],
    "tgn:id":2024425,
    "tgn:name":"Stovall",
    "tgn:placetype":[
        "aat:300008347"
    ]
},
  "bbox": [],
  "geometry": {"coordinates":[-84.85,32.95],"type":"Point"}
}