{
  "id": 7463038,
  "type": "Feature",
  "properties": {
    "tgn:hierarchy":[
        "tgn:7463038",
        "tgn:7019182",
        "tgn:7002448",
        "tgn:1000003",
        "tgn:7008591",
        "tgn:7029392"
    ],
    "tgn:id":7463038,
    "tgn:name:en":"Lighthouse Island",
    "tgn:placetype":[
        "aat:300008791"
    ]
},
  "bbox": [],
  "geometry": {"coordinates":[-5.516667,54.683333],"type":"Point"}
}