{
  "id": 7553853,
  "type": "Feature",
  "properties": {
    "tgn:hierarchy":[
        "tgn:7553853",
        "tgn:1000004",
        "tgn:7000198",
        "tgn:1001895",
        "tgn:7029392"
    ],
    "tgn:id":7553853,
    "tgn:name:en":"Mali and Munjeri",
    "tgn:placetype":[
        "aat:300000745"
    ]
},
  "bbox": [],
  "geometry": {"coordinates":[73.866667,18.533333],"type":"Point"}
}