{
  "id": 1117203,
  "type": "Feature",
  "properties": {
    "tgn:hierarchy":[
        "tgn:1117203",
        "tgn:7001242",
        "tgn:7016833",
        "tgn:1001123",
        "tgn:7029392"
    ],
    "tgn:id":1117203,
    "tgn:name":"Manzilah, Bu\u1e29ayrat al",
    "tgn:placetype":[
        "aat:300008680"
    ]
},
  "bbox": [],
  "geometry": {"coordinates":[32.192,31.262],"type":"Point"}
}