{
  "id": 7304294,
  "type": "Feature",
  "properties": {
    "tgn:hierarchy":[
        "tgn:7304294",
        "tgn:7002758",
        "tgn:1001316",
        "tgn:1000003",
        "tgn:1000095",
        "tgn:7029392"
    ],
    "tgn:id":7304294,
    "tgn:name":"Los Centenares",
    "tgn:placetype":[
        "aat:300008347"
    ]
},
  "bbox": [],
  "geometry": {"coordinates":[-2.733333,38.083333],"type":"Point"}
}