{
  "id": 2058489,
  "type": "Feature",
  "properties": {
    "tgn:hierarchy":[
        "tgn:2058489",
        "tgn:1000001",
        "tgn:7012149",
        "tgn:7016167",
        "tgn:7007523",
        "tgn:7029392"
    ],
    "tgn:id":2058489,
    "tgn:name":"Crystal Lake Park",
    "tgn:placetype":[
        "aat:300008347"
    ]
},
  "bbox": [],
  "geometry": {"coordinates":[-90.4333,38.6167],"type":"Point"}
}