{
  "id": 7118127,
  "type": "Feature",
  "properties": {
    "tgn:hierarchy":[
        "tgn:7118127",
        "tgn:7003692",
        "tgn:1000003",
        "tgn:7000084",
        "tgn:7029392"
    ],
    "tgn:id":7118127,
    "tgn:name":"Oberschwarzach",
    "tgn:placetype":[
        "aat:300008347"
    ]
},
  "bbox": [],
  "geometry": {"coordinates":[8.994722,49.381389],"type":"Point"}
}