<<<<<<< HEAD
{
  "id": 7118127,
  "type": "Feature",
  "properties": {
    "tgn:hierarchy":[
        "tgn:7118127",
        "tgn:7003692",
        "tgn:1000003",
        "tgn:7000084",
        "tgn:7029392"
    ],
    "tgn:id":7118127,
    "tgn:name":"Oberschwarzach",
    "tgn:placetype":[
        "aat:300008347"
    ]
},
  "bbox": [],
  "geometry": {"coordinates":[8.994722,49.381389],"type":"Point"}
}
=======
{"geometry":{"type":"Point","coordinates":[8.994722,49.381389]},"type":"Feature","properties":{"hierarchy":["tgn:7118127","tgn:7003692","tgn:1000003","tgn:7000084","tgn:7029392"],"placetype":["aat:300008347"],"id":7118127,"name:xx":"Oberschwarzach"}}
>>>>>>> 03f74aca74312dbeaf24d7e61306dd6a786dc3d0
