{
  "id": 1047483,
  "type": "Feature",
  "properties": {
    "tgn:hierarchy":[
        "tgn:1047483",
        "tgn:7024843",
        "tgn:1000003",
        "tgn:7008516",
        "tgn:1000080",
        "tgn:7029392"
    ],
    "tgn:id":1047483,
    "tgn:name":"Viserba",
    "tgn:placetype":[
        "aat:300008347"
    ]
},
  "bbox": [],
  "geometry": {"coordinates":[12.536111,44.093333],"type":"Point"}
}