{
  "id": 2402939,
  "type": "Feature",
  "properties": {
    "tgn:hierarchy":[
        "tgn:2402939",
        "tgn:2001001",
        "tgn:1000001",
        "tgn:7012149",
        "tgn:7007521",
        "tgn:7029392"
    ],
    "tgn:id":2402939,
    "tgn:name":"Houg Lake",
    "tgn:placetype":[
        "aat:300008680"
    ]
},
  "bbox": [],
  "geometry": {"coordinates":[-95.85,46.95],"type":"Point"}
}