<<<<<<< HEAD
{
  "id": 2402939,
  "type": "Feature",
  "properties": {
    "tgn:hierarchy":[
        "tgn:2402939",
        "tgn:2001001",
        "tgn:1000001",
        "tgn:7012149",
        "tgn:7007521",
        "tgn:7029392"
    ],
    "tgn:id":2402939,
    "tgn:name":"Houg Lake",
    "tgn:placetype":[
        "aat:300008680"
    ]
},
  "bbox": [],
  "geometry": {"coordinates":[-95.85,46.95],"type":"Point"}
}
=======
{"geometry":{"type":"Point","coordinates":[-95.850000,46.950000]},"type":"Feature","properties":{"hierarchy":["tgn:2402939","tgn:2001001","tgn:1000001","tgn:7012149","tgn:7007521","tgn:7029392"],"placetype":["aat:300008680"],"id":2402939,"name:xx":"Houg Lake"}}
>>>>>>> 03f74aca74312dbeaf24d7e61306dd6a786dc3d0
