{
  "id": 2364657,
  "type": "Feature",
  "properties": {
    "tgn:hierarchy":[
        "tgn:2364657",
        "tgn:1000001",
        "tgn:7016106",
        "tgn:7012149",
        "tgn:7007516",
        "tgn:7029392"
    ],
    "tgn:id":2364657,
    "tgn:name":"Greenbriar Lake",
    "tgn:placetype":[
        "aat:300006191"
    ]
},
  "bbox": [],
  "geometry": {"coordinates":[-77.6167,39.5333],"type":"Point"}
}