{
  "id": 7340835,
  "type": "Feature",
  "properties": {
    "tgn:hierarchy":[
        "tgn:7340835",
        "tgn:7008911",
        "tgn:1000003",
        "tgn:7002763",
        "tgn:1000095",
        "tgn:7029392"
    ],
    "tgn:id":7340835,
    "tgn:name":"Busto",
    "tgn:placetype":[
        "aat:300008347"
    ]
},
  "bbox": [],
  "geometry": {"coordinates":[-6.45,43.55],"type":"Point"}
}