{
  "id": 2185152,
  "type": "Feature",
  "properties": {
    "tgn:hierarchy":[
        "tgn:2185152",
        "tgn:1000001",
        "tgn:1002479",
        "tgn:7012149",
        "tgn:7007240",
        "tgn:7029392"
    ],
    "tgn:id":2185152,
    "tgn:name":"Boggy Creek",
    "tgn:placetype":[
        "aat:300008706"
    ]
},
  "bbox": [],
  "geometry": {"coordinates":[-82.25,27.7667],"type":"Point"}
}