{
  "id": 7362604,
  "type": "Feature",
  "properties": {
    "tgn:hierarchy":[
        "tgn:7362604",
        "tgn:7016644",
        "tgn:1000001",
        "tgn:7005560",
        "tgn:7029392"
    ],
    "tgn:id":7362604,
    "tgn:name":"El Carrizal",
    "tgn:placetype":[
        "aat:300008347"
    ]
},
  "bbox": [],
  "geometry": {"coordinates":[-103.816667,18.766667],"type":"Point"}
}