{
  "id": 7505992,
  "type": "Feature",
  "properties": {
    "tgn:hierarchy":[
        "tgn:7505992",
        "tgn:1009227",
        "tgn:1000226",
        "tgn:1000006",
        "tgn:7016850",
        "tgn:7029392"
    ],
    "tgn:id":7505992,
    "tgn:name:en":"Shearer Swamp",
    "tgn:placetype":[
        "aat:300008903"
    ]
},
  "bbox": [],
  "geometry": {"coordinates":[170.733333,-42.916667],"type":"Point"}
}