{
  "id": 7277082,
  "type": "Feature",
  "properties": {
    "tgn:hierarchy":[
        "tgn:7277082",
        "tgn:7002464",
        "tgn:1000049",
        "tgn:1000002",
        "tgn:7029392"
    ],
    "tgn:id":7277082,
    "tgn:name":"Jacnone, Cerro",
    "tgn:placetype":[
        "aat:300008795"
    ]
},
  "bbox": [],
  "geometry": {"coordinates":[-69.983611,-17.569444],"type":"Point"}
}