{
  "id": 7009788,
  "type": "Feature",
  "properties": {
    "tgn:hierarchy":[
        "tgn:7009788",
        "tgn:5000432",
        "tgn:7002444",
        "tgn:1000003",
        "tgn:7008591",
        "tgn:7029392"
    ],
    "tgn:id":7009788,
    "tgn:name:en":"Dee",
    "tgn:placetype":[
        "aat:300008707",
        "aat:300008699"
    ]
},
  "bbox": [],
  "geometry": {"coordinates":[-2.116667,57.15],"type":"Point"}
}