{
  "id": 2645173,
  "type": "Feature",
  "properties": {
    "tgn:hierarchy":[
        "tgn:2645173",
        "tgn:1000001",
        "tgn:2001702",
        "tgn:7012149",
        "tgn:7007708",
        "tgn:7029392"
    ],
    "tgn:id":2645173,
    "tgn:name":"Saunders Lake",
    "tgn:placetype":[
        "aat:300008680"
    ]
},
  "bbox": [],
  "geometry": {"coordinates":[-124.2167,43.5333],"type":"Point"}
}