<<<<<<< HEAD
{
  "id": 7472189,
  "type": "Feature",
  "properties": {
    "tgn:hierarchy":[
        "tgn:7472189",
        "tgn:1000004",
        "tgn:7467799",
        "tgn:1000141",
        "tgn:7029392"
    ],
    "tgn:id":7472189,
    "tgn:name":"Shisanhu",
    "tgn:placetype":[
        "aat:300008347"
    ]
},
  "bbox": [],
  "geometry": {"coordinates":[120.380997,23.913838],"type":"Point"}
}
=======
{"geometry":{"type":"Point","coordinates":[120.380997,23.913838]},"type":"Feature","properties":{"hierarchy":["tgn:7472189","tgn:1000004","tgn:7467799","tgn:1000141","tgn:7029392"],"placetype":["aat:300008347"],"id":7472189,"name:xx":"Shisanhu"}}
>>>>>>> 03f74aca74312dbeaf24d7e61306dd6a786dc3d0
