{
  "id": 7560448,
  "type": "Feature",
  "properties": {
    "tgn:hierarchy":[
        "tgn:7560448",
        "tgn:1000004",
        "tgn:7000198",
        "tgn:7016722",
        "tgn:7029392"
    ],
    "tgn:id":7560448,
    "tgn:name:en":"Patia",
    "tgn:placetype":[
        "aat:300008347"
    ]
},
  "bbox": [],
  "geometry": {"coordinates":[79.41642,27.176994],"type":"Point"}
}