{
  "id": 2671818,
  "type": "Feature",
  "properties": {
    "tgn:hierarchy":[
        "tgn:2671818",
        "tgn:1000001",
        "tgn:2001424",
        "tgn:7012149",
        "tgn:7007564",
        "tgn:7029392"
    ],
    "tgn:id":2671818,
    "tgn:name":"Smith Pond",
    "tgn:placetype":[
        "aat:300008680"
    ]
},
  "bbox": [],
  "geometry": {"coordinates":[-72.1333,43.5833],"type":"Point"}
}