{
  "id": 1089259,
  "type": "Feature",
  "properties": {
    "tgn:hierarchy":[
        "tgn:1089259",
        "tgn:1001143",
        "tgn:7001242",
        "tgn:1000159",
        "tgn:7029392"
    ],
    "tgn:id":1089259,
    "tgn:name":"Lukuni",
    "tgn:placetype":[
        "aat:300008347"
    ]
},
  "bbox": [],
  "geometry": {"coordinates":[17.2667,-5.8333],"type":"Point"}
}