{
  "id": 2451169,
  "type": "Feature",
  "properties": {
    "tgn:hierarchy":[
        "tgn:2451169",
        "tgn:1000001",
        "tgn:7012149",
        "tgn:7007157",
        "tgn:7014475",
        "tgn:7029392"
    ],
    "tgn:id":2451169,
    "tgn:name":"Little Arthur Creek",
    "tgn:placetype":[
        "aat:300008706"
    ]
},
  "bbox": [],
  "geometry": {"coordinates":[-121.75,37.05],"type":"Point"}
}