{
  "id": 1078392,
  "type": "Feature",
  "properties": {
    "tgn:hierarchy":[
        "tgn:1078392",
        "tgn:1000004",
        "tgn:1001502",
        "tgn:1000116",
        "tgn:7029392"
    ],
    "tgn:id":1078392,
    "tgn:name":"Pujut",
    "tgn:placetype":[
        "aat:300008347"
    ]
},
  "bbox": [],
  "geometry": {"coordinates":[100.65,1.4167],"type":"Point"}
}