{
  "id": 7331712,
  "type": "Feature",
  "properties": {
    "tgn:hierarchy":[
        "tgn:7331712",
        "tgn:1001439",
        "tgn:1000003",
        "tgn:7002797",
        "tgn:1000095",
        "tgn:7029392"
    ],
    "tgn:id":7331712,
    "tgn:name":"La Pinilla",
    "tgn:placetype":[
        "aat:300008347"
    ]
},
  "bbox": [],
  "geometry": {"coordinates":[-1.283333,37.683333],"type":"Point"}
}