{
  "id": 2438076,
  "type": "Feature",
  "properties": {
    "tgn:hierarchy":[
        "tgn:2438076",
        "tgn:1000001",
        "tgn:2001409",
        "tgn:7012149",
        "tgn:7007526",
        "tgn:7029392"
    ],
    "tgn:id":2438076,
    "tgn:name":"King Solomon Mine",
    "tgn:placetype":[
        "aat:300000390"
    ]
},
  "bbox": [],
  "geometry": {"coordinates":[-117.7667,39.75],"type":"Point"}
}