{
  "id": 2336199,
  "type": "Feature",
  "properties": {
    "tgn:hierarchy":[
        "tgn:2336199",
        "tgn:1000001",
        "tgn:1002359",
        "tgn:7012149",
        "tgn:7007517",
        "tgn:7029392"
    ],
    "tgn:id":2336199,
    "tgn:name":"Foster Pond",
    "tgn:placetype":[
        "aat:300008680"
    ]
},
  "bbox": [],
  "geometry": {"coordinates":[-70.9167,42.4833],"type":"Point"}
}