<<<<<<< HEAD
{
  "id": 2336199,
  "type": "Feature",
  "properties": {
    "tgn:hierarchy":[
        "tgn:2336199",
        "tgn:1000001",
        "tgn:1002359",
        "tgn:7012149",
        "tgn:7007517",
        "tgn:7029392"
    ],
    "tgn:id":2336199,
    "tgn:name":"Foster Pond",
    "tgn:placetype":[
        "aat:300008680"
    ]
},
  "bbox": [],
  "geometry": {"coordinates":[-70.9167,42.4833],"type":"Point"}
}
=======
{"geometry":{"type":"Point","coordinates":[-70.916700,42.483300]},"type":"Feature","properties":{"hierarchy":["tgn:2336199","tgn:1000001","tgn:1002359","tgn:7012149","tgn:7007517","tgn:7029392"],"placetype":["aat:300008680"],"id":2336199,"name:xx":"Foster Pond"}}
>>>>>>> 03f74aca74312dbeaf24d7e61306dd6a786dc3d0
