{
  "id": 2190654,
  "type": "Feature",
  "properties": {
    "tgn:hierarchy":[
        "tgn:2190654",
        "tgn:1000001",
        "tgn:7012149",
        "tgn:2001449",
        "tgn:7007566",
        "tgn:7029392"
    ],
    "tgn:id":2190654,
    "tgn:name":"Box Tank",
    "tgn:placetype":[
        "aat:300006191"
    ]
},
  "bbox": [],
  "geometry": {"coordinates":[-107.3167,36.9833],"type":"Point"}
}