{
  "id": 7083840,
  "type": "Feature",
  "properties": {
    "tgn:hierarchy":[
        "tgn:7083840",
        "tgn:7000096",
        "tgn:1000003",
        "tgn:7000084",
        "tgn:7029392"
    ],
    "tgn:id":7083840,
    "tgn:name":"F\u00f6rsterei Wilhelmseichen",
    "tgn:placetype":[
        "aat:300004792"
    ]
},
  "bbox": [],
  "geometry": {"coordinates":[13.683333,52.95],"type":"Point"}
}