{
  "id": 7238980,
  "type": "Feature",
  "properties": {
    "tgn:hierarchy":[
        "tgn:7238980",
        "tgn:7003456",
        "tgn:1000003",
        "tgn:1000063",
        "tgn:7018236",
        "tgn:7029392"
    ],
    "tgn:id":7238980,
    "tgn:name":"Groenheuvel",
    "tgn:placetype":[
        "aat:300008347"
    ]
},
  "bbox": [],
  "geometry": {"coordinates":[4.933333,51.066667],"type":"Point"}
}