{
  "id": 2494830,
  "type": "Feature",
  "properties": {
    "tgn:hierarchy":[
        "tgn:2494830",
        "tgn:1000001",
        "tgn:7012149",
        "tgn:7014021",
        "tgn:7007709",
        "tgn:7029392"
    ],
    "tgn:id":2494830,
    "tgn:name":"Martindale",
    "tgn:placetype":[
        "aat:300008347"
    ]
},
  "bbox": [],
  "geometry": {"coordinates":[-80.9333,35.3167],"type":"Point"}
}