{
  "id": 7035164,
  "type": "Feature",
  "properties": {
    "tgn:hierarchy":[
        "tgn:7035164",
        "tgn:1003506",
        "tgn:1000003",
        "tgn:7002993",
        "tgn:1000080",
        "tgn:7029392"
    ],
    "tgn:id":7035164,
    "tgn:name":"Lubia, Monte",
    "tgn:placetype":[
        "aat:300008795"
    ]
},
  "bbox": [],
  "geometry": {"coordinates":[13.451111,46.207778],"type":"Point"}
}