{
  "id": 2336667,
  "type": "Feature",
  "properties": {
    "tgn:hierarchy":[
        "tgn:2336667",
        "tgn:1000001",
        "tgn:2001414",
        "tgn:7012149",
        "tgn:7007526",
        "tgn:7029392"
    ],
    "tgn:id":2336667,
    "tgn:name":"Four Springs",
    "tgn:placetype":[
        "aat:300008697"
    ]
},
  "bbox": [],
  "geometry": {"coordinates":[-118.5833,41.7333],"type":"Point"}
}