{
  "id": 7442314,
  "type": "Feature",
  "properties": {
    "tgn:hierarchy":[
        "tgn:7442314",
        "tgn:7002445",
        "tgn:1000003",
        "tgn:7011961",
        "tgn:7008591",
        "tgn:7029392"
    ],
    "tgn:id":7442314,
    "tgn:name:en":"Saint Alban's Ledge",
    "tgn:placetype":[
        "aat:300386885"
    ]
},
  "bbox": [],
  "geometry": {"coordinates":[-2.083333,50.55],"type":"Point"}
}