{
  "id": 7039951,
  "type": "Feature",
  "properties": {
    "tgn:hierarchy":[
        "tgn:7039951",
        "tgn:1003459",
        "tgn:1000003",
        "tgn:7002993",
        "tgn:1000080",
        "tgn:7029392"
    ],
    "tgn:id":7039951,
    "tgn:name":"Sdobba, Punta",
    "tgn:placetype":[
        "aat:300386846"
    ]
},
  "bbox": [],
  "geometry": {"coordinates":[13.553056,45.729167],"type":"Point"}
}