{
  "id": 7219887,
  "type": "Feature",
  "properties": {
    "tgn:hierarchy":[
        "tgn:7219887",
        "tgn:7011330",
        "tgn:7002674",
        "tgn:1000003",
        "tgn:1000074",
        "tgn:7029392"
    ],
    "tgn:id":7219887,
    "tgn:name":"P\u00edthos",
    "tgn:placetype":[
        "aat:300387200"
    ]
},
  "bbox": [],
  "geometry": {"coordinates":[27.163611,36.8725],"type":"Point"}
}