{
  "id": 7149854,
  "type": "Feature",
  "properties": {
    "tgn:hierarchy":[
        "tgn:7149854",
        "tgn:1000003",
        "tgn:7003682",
        "tgn:7000084",
        "tgn:7029392"
    ],
    "tgn:id":7149854,
    "tgn:name":"Krautscheid",
    "tgn:placetype":[
        "aat:300008347"
    ]
},
  "bbox": [],
  "geometry": {"coordinates":[6.333333,50.066667],"type":"Point"}
}