{
  "id": 2715284,
  "type": "Feature",
  "properties": {
    "tgn:hierarchy":[
        "tgn:2715284",
        "tgn:1000001",
        "tgn:7012149",
        "tgn:1002598",
        "tgn:7007523",
        "tgn:7029392"
    ],
    "tgn:id":2715284,
    "tgn:name":"Terbrock Lake",
    "tgn:placetype":[
        "aat:300006191"
    ]
},
  "bbox": [],
  "geometry": {"coordinates":[-91.0833,39.0167],"type":"Point"}
}