{
  "id": 2690372,
  "type": "Feature",
  "properties": {
    "tgn:hierarchy":[
        "tgn:2690372",
        "tgn:1000001",
        "tgn:7006451",
        "tgn:2000092",
        "tgn:7012149",
        "tgn:7029392"
    ],
    "tgn:id":2690372,
    "tgn:name":"Stagg Tank",
    "tgn:placetype":[
        "aat:300006191"
    ]
},
  "bbox": [],
  "geometry": {"coordinates":[-111.5833,35.4333],"type":"Point"}
}