{
  "id": 7478657,
  "type": "Feature",
  "properties": {
    "tgn:hierarchy":[
        "tgn:7478657",
        "tgn:1000004",
        "tgn:7489179",
        "tgn:1000141",
        "tgn:7029392"
    ],
    "tgn:id":7478657,
    "tgn:name":"Masai Guoxiao",
    "tgn:placetype":[
        "aat:300006495"
    ]
},
  "bbox": [],
  "geometry": {"coordinates":[121.835702,24.620976],"type":"Point"}
}