{
  "id": 2587600,
  "type": "Feature",
  "properties": {
    "tgn:hierarchy":[
        "tgn:2587600",
        "tgn:1000001",
        "tgn:7012149",
        "tgn:2001245",
        "tgn:7007523",
        "tgn:7029392"
    ],
    "tgn:id":2587600,
    "tgn:name":"Pleasant Retreat",
    "tgn:placetype":[
        "aat:300008347"
    ]
},
  "bbox": [],
  "geometry": {"coordinates":[-92.2167,40.3667],"type":"Point"}
}