{
  "id": 2773999,
  "type": "Feature",
  "properties": {
    "tgn:hierarchy":[
        "tgn:2773999",
        "tgn:1000001",
        "tgn:2001266",
        "tgn:7012149",
        "tgn:7007524",
        "tgn:7029392"
    ],
    "tgn:id":2773999,
    "tgn:name":"Willow Creek",
    "tgn:placetype":[
        "aat:300008706"
    ]
},
  "bbox": [],
  "geometry": {"coordinates":[-111.65,47.15],"type":"Point"}
}