{
  "id": 2370015,
  "type": "Feature",
  "properties": {
    "tgn:hierarchy":[
        "tgn:2370015",
        "tgn:1000001",
        "tgn:2001429",
        "tgn:7012149",
        "tgn:7007566",
        "tgn:7029392"
    ],
    "tgn:id":2370015,
    "tgn:name":"Gutierrezville",
    "tgn:placetype":[
        "aat:300008347"
    ]
},
  "bbox": [],
  "geometry": {"coordinates":[-107.9167,34.05],"type":"Point"}
}