{
  "id": 7591970,
  "type": "Feature",
  "properties": {
    "tgn:hierarchy":[
        "tgn:7591970",
        "tgn:1000004",
        "tgn:7000198",
        "tgn:7000799",
        "tgn:7029392"
    ],
    "tgn:id":7591970,
    "tgn:name:en":"Lamb\u012bker",
    "tgn:placetype":[
        "aat:300008347"
    ]
},
  "bbox": [],
  "geometry": {"coordinates":[74.878418,32.994328],"type":"Point"}
}