{
  "id": 2704053,
  "type": "Feature",
  "properties": {
    "tgn:hierarchy":[
        "tgn:2704053",
        "tgn:1000001",
        "tgn:2001014",
        "tgn:7012149",
        "tgn:7007521",
        "tgn:7029392"
    ],
    "tgn:id":2704053,
    "tgn:name":"Sunfish Lake",
    "tgn:placetype":[
        "aat:300008680"
    ]
},
  "bbox": [],
  "geometry": {"coordinates":[-90.15,47.9833],"type":"Point"}
}