{
  "id": 7127902,
  "type": "Feature",
  "properties": {
    "tgn:hierarchy":[
        "tgn:7127902",
        "tgn:1000003",
        "tgn:7003678",
        "tgn:7000084",
        "tgn:7029392"
    ],
    "tgn:id":7127902,
    "tgn:name":"Ober-Moos",
    "tgn:placetype":[
        "aat:300008347"
    ]
},
  "bbox": [],
  "geometry": {"coordinates":[9.366667,50.466667],"type":"Point"}
}