{
  "id": 7033563,
  "type": "Feature",
  "properties": {
    "tgn:hierarchy":[
        "tgn:7033563",
        "tgn:7003128",
        "tgn:1000003",
        "tgn:7008516",
        "tgn:1000080",
        "tgn:7029392"
    ],
    "tgn:id":7033563,
    "tgn:name":"Argine Agosta",
    "tgn:placetype":[
        "aat:300170882"
    ]
},
  "bbox": [],
  "geometry": {"coordinates":[12.104167,44.615556],"type":"Point"}
}