{
  "id": 7482477,
  "type": "Feature",
  "properties": {
    "tgn:hierarchy":[
        "tgn:7482477",
        "tgn:1000004",
        "tgn:7490934",
        "tgn:1000141",
        "tgn:7029392"
    ],
    "tgn:id":7482477,
    "tgn:name":"Chaotian Gong",
    "tgn:placetype":[
        "aat:300007595"
    ]
},
  "bbox": [],
  "geometry": {"coordinates":[120.091111,23.19],"type":"Point"}
}