<<<<<<< HEAD
{
  "id": 2405085,
  "type": "Feature",
  "properties": {
    "tgn:hierarchy":[
        "tgn:2405085",
        "tgn:1000001",
        "tgn:7012149",
        "tgn:2000291",
        "tgn:7007240",
        "tgn:7029392"
    ],
    "tgn:id":2405085,
    "tgn:name":"Hudson Pond",
    "tgn:placetype":[
        "aat:300008680"
    ]
},
  "bbox": [],
  "geometry": {"coordinates":[-85.6667,30.5667],"type":"Point"}
}
=======
{"geometry":{"type":"Point","coordinates":[-85.666700,30.566700]},"type":"Feature","properties":{"hierarchy":["tgn:2405085","tgn:1000001","tgn:7012149","tgn:2000291","tgn:7007240","tgn:7029392"],"placetype":["aat:300008680"],"id":2405085,"name:xx":"Hudson Pond"}}
>>>>>>> 03f74aca74312dbeaf24d7e61306dd6a786dc3d0
