{
  "id": 2252715,
  "type": "Feature",
  "properties": {
    "tgn:hierarchy":[
        "tgn:2252715",
        "tgn:1000001",
        "tgn:7012149",
        "tgn:1003005",
        "tgn:7007520",
        "tgn:7029392"
    ],
    "tgn:id":2252715,
    "tgn:name":"Conners Creek",
    "tgn:placetype":[
        "aat:300008678"
    ]
},
  "bbox": [],
  "geometry": {"coordinates":[-82.95,42.35],"type":"Point"}
}