{
  "id": 7582904,
  "type": "Feature",
  "properties": {
    "tgn:hierarchy":[
        "tgn:7582904",
        "tgn:1000004",
        "tgn:7000198",
        "tgn:7016788",
        "tgn:7029392"
    ],
    "tgn:id":7582904,
    "tgn:name:en":"K\u0101impsar",
    "tgn:placetype":[
        "aat:300008347"
    ]
},
  "bbox": [],
  "geometry": {"coordinates":[75.585082,28.093292],"type":"Point"}
}