{
  "id": 2038598,
  "type": "Feature",
  "properties": {
    "tgn:hierarchy":[
        "tgn:2038598",
        "tgn:1000001",
        "tgn:2000775",
        "tgn:7012149",
        "tgn:7007255",
        "tgn:7029392"
    ],
    "tgn:id":2038598,
    "tgn:name":"Dunbar",
    "tgn:placetype":[
        "aat:300008347"
    ]
},
  "bbox": [],
  "geometry": {"coordinates":[-86.75,37.1833],"type":"Point"}
}