<<<<<<< HEAD
{
  "id": 7373014,
  "type": "Feature",
  "properties": {
    "tgn:hierarchy":[
        "tgn:7373014",
        "tgn:1000001",
        "tgn:7005601",
        "tgn:7005560",
        "tgn:7029392"
    ],
    "tgn:id":7373014,
    "tgn:name":"La Palma",
    "tgn:placetype":[
        "aat:300008347"
    ]
},
  "bbox": [],
  "geometry": {"coordinates":[-103.3,21.816667],"type":"Point"}
}
=======
{"geometry":{"type":"Point","coordinates":[-103.300000,21.816667]},"type":"Feature","properties":{"hierarchy":["tgn:7373014","tgn:1000001","tgn:7005601","tgn:7005560","tgn:7029392"],"placetype":["aat:300008347"],"id":7373014,"name:xx":"La Palma"}}
>>>>>>> 03f74aca74312dbeaf24d7e61306dd6a786dc3d0
