{
  "id": 7439743,
  "type": "Feature",
  "properties": {
    "tgn:hierarchy":[
        "tgn:7439743",
        "tgn:7005583",
        "tgn:1000001",
        "tgn:7005560",
        "tgn:7029392"
    ],
    "tgn:id":7439743,
    "tgn:name":"San Mart\u00edn de Cachila",
    "tgn:placetype":[
        "aat:300008347"
    ]
},
  "bbox": [],
  "geometry": {"coordinates":[-104.466667,24.816667],"type":"Point"}
}