{
  "id": 2141880,
  "type": "Feature",
  "properties": {
    "tgn:hierarchy":[
        "tgn:2141880",
        "tgn:1000001",
        "tgn:7012149",
        "tgn:2001438",
        "tgn:7007566",
        "tgn:7029392"
    ],
    "tgn:id":2141880,
    "tgn:name":"Baca, Ca\u00f1on de",
    "tgn:placetype":[
        "aat:300008761"
    ]
},
  "bbox": [],
  "geometry": {"coordinates":[-105.1667,34.95],"type":"Point"}
}