{
  "id": 2420029,
  "type": "Feature",
  "properties": {
    "tgn:hierarchy":[
        "tgn:2420029",
        "tgn:1000001",
        "tgn:7012149",
        "tgn:2002030",
        "tgn:7007826",
        "tgn:7029392"
    ],
    "tgn:id":2420029,
    "tgn:name":"Jeckers Cove",
    "tgn:placetype":[
        "aat:300132316"
    ]
},
  "bbox": [],
  "geometry": {"coordinates":[-98.4667,30.7833],"type":"Point"}
}