{
  "id": 7389422,
  "type": "Feature",
  "properties": {
    "tgn:hierarchy":[
        "tgn:7389422",
        "tgn:1000001",
        "tgn:7005594",
        "tgn:7005560",
        "tgn:7029392"
    ],
    "tgn:id":7389422,
    "tgn:name":"Refugio",
    "tgn:placetype":[
        "aat:300008347"
    ]
},
  "bbox": [],
  "geometry": {"coordinates":[-99.916667,22.566667],"type":"Point"}
}