{
  "id": 2616422,
  "type": "Feature",
  "properties": {
    "tgn:hierarchy":[
        "tgn:2616422",
        "tgn:1000001",
        "tgn:7013368",
        "tgn:7012149",
        "tgn:7007709",
        "tgn:7029392"
    ],
    "tgn:id":2616422,
    "tgn:name":"Rice Creek",
    "tgn:placetype":[
        "aat:300008706"
    ]
},
  "bbox": [],
  "geometry": {"coordinates":[-77.0333,35.4667],"type":"Point"}
}