<<<<<<< HEAD
{
  "id": 2409516,
  "type": "Feature",
  "properties": {
    "tgn:hierarchy":[
        "tgn:2409516",
        "tgn:1000001",
        "tgn:2001484",
        "tgn:7012149",
        "tgn:7007709",
        "tgn:7029392"
    ],
    "tgn:id":2409516,
    "tgn:name":"Idlewild Terrace Apartments",
    "tgn:placetype":[
        "aat:300008347"
    ]
},
  "bbox": [],
  "geometry": {"coordinates":[-81.5333,35.2667],"type":"Point"}
}
=======
{"geometry":{"type":"Point","coordinates":[-81.533300,35.266700]},"type":"Feature","properties":{"hierarchy":["tgn:2409516","tgn:1000001","tgn:2001484","tgn:7012149","tgn:7007709","tgn:7029392"],"placetype":["aat:300008347"],"id":2409516,"name:xx":"Idlewild Terrace Apartments"}}
>>>>>>> 03f74aca74312dbeaf24d7e61306dd6a786dc3d0
