{
  "id": 1071438,
  "type": "Feature",
  "properties": {
    "tgn:hierarchy":[
        "tgn:1071438",
        "tgn:1000004",
        "tgn:7002082",
        "tgn:1000111",
        "tgn:7029392"
    ],
    "tgn:id":1071438,
    "tgn:name":"Shangdundu",
    "tgn:placetype":[
        "aat:300008347"
    ]
},
  "bbox": [],
  "geometry": {"coordinates":[116.2667,27.9333],"type":"Point"}
}