{
  "id": 2357684,
  "type": "Feature",
  "properties": {
    "tgn:hierarchy":[
        "tgn:2357684",
        "tgn:7006450",
        "tgn:1000001",
        "tgn:7012149",
        "tgn:2000085",
        "tgn:7029392"
    ],
    "tgn:id":2357684,
    "tgn:name":"Grace Creek",
    "tgn:placetype":[
        "aat:300008706"
    ]
},
  "bbox": [],
  "geometry": {"coordinates":[-141.35,64.1833],"type":"Point"}
}