{
  "id": 2762387,
  "type": "Feature",
  "properties": {
    "tgn:hierarchy":[
        "tgn:2762387",
        "tgn:1000001",
        "tgn:7012149",
        "tgn:1002897",
        "tgn:7007920",
        "tgn:7029392"
    ],
    "tgn:id":2762387,
    "tgn:name":"West Twin Butte",
    "tgn:placetype":[
        "aat:300008798"
    ]
},
  "bbox": [],
  "geometry": {"coordinates":[-121.7667,46.1167],"type":"Point"}
}