<<<<<<< HEAD
{
  "id": 2762387,
  "type": "Feature",
  "properties": {
    "tgn:hierarchy":[
        "tgn:2762387",
        "tgn:1000001",
        "tgn:7012149",
        "tgn:1002897",
        "tgn:7007920",
        "tgn:7029392"
    ],
    "tgn:id":2762387,
    "tgn:name":"West Twin Butte",
    "tgn:placetype":[
        "aat:300008798"
    ]
},
  "bbox": [],
  "geometry": {"coordinates":[-121.7667,46.1167],"type":"Point"}
}
=======
{"geometry":{"type":"Point","coordinates":[-121.766700,46.116700]},"type":"Feature","properties":{"hierarchy":["tgn:2762387","tgn:1000001","tgn:7012149","tgn:1002897","tgn:7007920","tgn:7029392"],"placetype":["aat:300008798"],"id":2762387,"name:xx":"West Twin Butte"}}
>>>>>>> 03f74aca74312dbeaf24d7e61306dd6a786dc3d0
