<<<<<<< HEAD
{
  "id": 2250585,
  "type": "Feature",
  "properties": {
    "tgn:hierarchy":[
        "tgn:2250585",
        "tgn:1000001",
        "tgn:7012149",
        "tgn:2002112",
        "tgn:7007827",
        "tgn:7029392"
    ],
    "tgn:id":2250585,
    "tgn:name":"Colorado Chief",
    "tgn:placetype":[
        "aat:300000390"
    ]
},
  "bbox": [],
  "geometry": {"coordinates":[-112.1167,39.95],"type":"Point"}
}
=======
{"geometry":{"type":"Point","coordinates":[-112.116700,39.950000]},"type":"Feature","properties":{"hierarchy":["tgn:2250585","tgn:1000001","tgn:7012149","tgn:2002112","tgn:7007827","tgn:7029392"],"placetype":["aat:300000390"],"id":2250585,"name:xx":"Colorado Chief"}}
>>>>>>> 03f74aca74312dbeaf24d7e61306dd6a786dc3d0
