{
  "id": 7414831,
  "type": "Feature",
  "properties": {
    "tgn:hierarchy":[
        "tgn:7414831",
        "tgn:1000001",
        "tgn:7005591",
        "tgn:7005560",
        "tgn:7029392"
    ],
    "tgn:id":7414831,
    "tgn:name:es":"Santa Mar\u00eda Asunci\u00f3n",
    "tgn:placetype":[
        "aat:300008347"
    ]
},
  "bbox": [],
  "geometry": {"coordinates":[-98.014167,17.528333],"type":"Point"}
}