{
  "id": 2347569,
  "type": "Feature",
  "properties": {
    "tgn:hierarchy":[
        "tgn:2347569",
        "tgn:1000001",
        "tgn:7012149",
        "tgn:2001167",
        "tgn:7007522",
        "tgn:7029392"
    ],
    "tgn:id":2347569,
    "tgn:name":"George, Lake",
    "tgn:placetype":[
        "aat:300008680"
    ]
},
  "bbox": [],
  "geometry": {"coordinates":[-90.6167,32.75],"type":"Point"}
}