{
  "id": 2290103,
  "type": "Feature",
  "properties": {
    "tgn:hierarchy":[
        "tgn:2290103",
        "tgn:1002201",
        "tgn:1000001",
        "tgn:7012149",
        "tgn:7007517",
        "tgn:7029392"
    ],
    "tgn:id":2290103,
    "tgn:name":"Doctors Point",
    "tgn:placetype":[
        "aat:300008850"
    ]
},
  "bbox": [],
  "geometry": {"coordinates":[-71.0667,41.5667],"type":"Point"}
}