{
  "id": 1077990,
  "type": "Feature",
  "properties": {
    "tgn:hierarchy":[
        "tgn:1077990",
        "tgn:1001321",
        "tgn:1000004",
        "tgn:1000116",
        "tgn:7029392"
    ],
    "tgn:id":1077990,
    "tgn:name":"Lemahabang",
    "tgn:placetype":[
        "aat:300008347"
    ]
},
  "bbox": [],
  "geometry": {"coordinates":[107.45,-6.2833],"type":"Point"}
}