{
  "id": 7378166,
  "type": "Feature",
  "properties": {
    "tgn:hierarchy":[
        "tgn:7378166",
        "tgn:7005581",
        "tgn:1000001",
        "tgn:7005560",
        "tgn:7029392"
    ],
    "tgn:id":7378166,
    "tgn:name":"Rancho Las Pampas",
    "tgn:placetype":[
        "aat:300000241"
    ]
},
  "bbox": [],
  "geometry": {"coordinates":[-105.183333,27.266667],"type":"Point"}
}