{
  "id": 2205880,
  "type": "Feature",
  "properties": {
    "tgn:hierarchy":[
        "tgn:2205880",
        "tgn:1002338",
        "tgn:1000001",
        "tgn:7012149",
        "tgn:7007516",
        "tgn:7029392"
    ],
    "tgn:id":2205880,
    "tgn:name":"Bull Point Island",
    "tgn:placetype":[
        "aat:300008791"
    ]
},
  "bbox": [],
  "geometry": {"coordinates":[-76.1167,38.4167],"type":"Point"}
}