{
  "id": 7304742,
  "type": "Feature",
  "properties": {
    "tgn:hierarchy":[
        "tgn:7304742",
        "tgn:7002847",
        "tgn:1001647",
        "tgn:1000003",
        "tgn:1000095",
        "tgn:7029392"
    ],
    "tgn:id":7304742,
    "tgn:name":"Layos",
    "tgn:placetype":[
        "aat:300008347"
    ]
},
  "bbox": [],
  "geometry": {"coordinates":[-4.05,39.766667],"type":"Point"}
}