<<<<<<< HEAD
{
  "id": 7351282,
  "type": "Feature",
  "properties": {
    "tgn:hierarchy":[
        "tgn:7351282",
        "tgn:7005583",
        "tgn:1000001",
        "tgn:7005560",
        "tgn:7029392"
    ],
    "tgn:id":7351282,
    "tgn:name":"Bola, Cerro",
    "tgn:placetype":[
        "aat:300008777"
    ]
},
  "bbox": [],
  "geometry": {"coordinates":[-103.783333,26.533333],"type":"Point"}
}
=======
{"geometry":{"type":"Point","coordinates":[-103.783333,26.533333]},"type":"Feature","properties":{"hierarchy":["tgn:7351282","tgn:7005583","tgn:1000001","tgn:7005560","tgn:7029392"],"placetype":["aat:300008777"],"id":7351282,"name:xx":"Bola, Cerro"}}
>>>>>>> 03f74aca74312dbeaf24d7e61306dd6a786dc3d0
