{
  "id": 7297193,
  "type": "Feature",
  "properties": {
    "tgn:hierarchy":[
        "tgn:7297193",
        "tgn:7002835",
        "tgn:7001158",
        "tgn:1000003",
        "tgn:1000095",
        "tgn:7029392"
    ],
    "tgn:id":7297193,
    "tgn:name":"Taragudo",
    "tgn:placetype":[
        "aat:300008347"
    ]
},
  "bbox": [],
  "geometry": {"coordinates":[-5.583333,41.183333],"type":"Point"}
}