{
  "id": 2772021,
  "type": "Feature",
  "properties": {
    "tgn:hierarchy":[
        "tgn:2772021",
        "tgn:1000001",
        "tgn:7012149",
        "tgn:7007523",
        "tgn:7029392"
    ],
    "tgn:id":2772021,
    "tgn:name":"Wilkinson Creek",
    "tgn:placetype":[
        "aat:300008706"
    ]
},
  "bbox": [],
  "geometry": {"coordinates":[-93.1667,37.75],"type":"Point"}
}