{
  "id": 2751625,
  "type": "Feature",
  "properties": {
    "tgn:hierarchy":[
        "tgn:2751625",
        "tgn:1000001",
        "tgn:2002369",
        "tgn:7012149",
        "tgn:7007923",
        "tgn:7029392"
    ],
    "tgn:id":2751625,
    "tgn:name":"Warner Reservoir Number 2",
    "tgn:placetype":[
        "aat:300006191"
    ]
},
  "bbox": [],
  "geometry": {"coordinates":[-105.4667,42.7833],"type":"Point"}
}