<<<<<<< HEAD
{
  "id": 7051410,
  "type": "Feature",
  "properties": {
    "tgn:hierarchy":[
        "tgn:7051410",
        "tgn:1000003",
        "tgn:1001651",
        "tgn:7003122",
        "tgn:1000080",
        "tgn:7029392"
    ],
    "tgn:id":7051410,
    "tgn:name":"La Chiesa",
    "tgn:placetype":[
        "aat:300008347"
    ]
},
  "bbox": [],
  "geometry": {"coordinates":[14.55,37.083333],"type":"Point"}
}
=======
{"geometry":{"type":"Point","coordinates":[14.550000,37.083333]},"type":"Feature","properties":{"hierarchy":["tgn:7051410","tgn:1000003","tgn:1001651","tgn:7003122","tgn:1000080","tgn:7029392"],"placetype":["aat:300008347"],"id":7051410,"name:xx":"La Chiesa"}}
>>>>>>> 03f74aca74312dbeaf24d7e61306dd6a786dc3d0
