{
  "id": 2314459,
  "type": "Feature",
  "properties": {
    "tgn:hierarchy":[
        "tgn:2314459",
        "tgn:1000001",
        "tgn:7012149",
        "tgn:1002458",
        "tgn:7007255",
        "tgn:7029392"
    ],
    "tgn:id":2314459,
    "tgn:name":"Elk Lick",
    "tgn:placetype":[
        "aat:300008699"
    ]
},
  "bbox": [],
  "geometry": {"coordinates":[-84.1167,38.4333],"type":"Point"}
}