{
  "id": 7591722,
  "type": "Feature",
  "properties": {
    "tgn:hierarchy":[
        "tgn:7591722",
        "tgn:1000004",
        "tgn:7000198",
        "tgn:7000799",
        "tgn:7029392"
    ],
    "tgn:id":7591722,
    "tgn:name:en":"Dangid\u0101r",
    "tgn:placetype":[
        "aat:300008347"
    ]
},
  "bbox": [],
  "geometry": {"coordinates":[75.207053,34.528854],"type":"Point"}
}