{
  "id": 7367903,
  "type": "Feature",
  "properties": {
    "tgn:hierarchy":[
        "tgn:7367903",
        "tgn:7005583",
        "tgn:1000001",
        "tgn:7005560",
        "tgn:7029392"
    ],
    "tgn:id":7367903,
    "tgn:name":"El Salto",
    "tgn:placetype":[
        "aat:300008347"
    ]
},
  "bbox": [],
  "geometry": {"coordinates":[-106.183333,24.916667],"type":"Point"}
}