{
  "id": 1088224,
  "type": "Feature",
  "properties": {
    "tgn:hierarchy":[
        "tgn:1088224",
        "tgn:7001242",
        "tgn:1001455",
        "tgn:1000153",
        "tgn:7029392"
    ],
    "tgn:id":1088224,
    "tgn:name":"Maroua",
    "tgn:placetype":[
        "aat:300008347",
        "aat:300008375",
        "aat:300387285",
        "aat:300387286"
    ]
},
  "bbox": [],
  "geometry": {"coordinates":[14.3333,10.5833],"type":"Point"}
}