{
  "id": 2116066,
  "type": "Feature",
  "properties": {
    "tgn:hierarchy":[
        "tgn:2116066",
        "tgn:1000001",
        "tgn:1002275",
        "tgn:7012149",
        "tgn:7007920",
        "tgn:7029392"
    ],
    "tgn:id":2116066,
    "tgn:name":"La Center",
    "tgn:placetype":[
        "aat:300008347"
    ]
},
  "bbox": [],
  "geometry": {"coordinates":[-122.6667,45.85],"type":"Point"}
}