{
  "id": 7133496,
  "type": "Feature",
  "properties": {
    "tgn:hierarchy":[
        "tgn:7133496",
        "tgn:7003669",
        "tgn:1000003",
        "tgn:7000084",
        "tgn:7029392"
    ],
    "tgn:id":7133496,
    "tgn:name":"Moosbach",
    "tgn:placetype":[
        "aat:300008347"
    ]
},
  "bbox": [],
  "geometry": {"coordinates":[10.85,49.266667],"type":"Point"}
}