{
  "id": 7410298,
  "type": "Feature",
  "properties": {
    "tgn:hierarchy":[
        "tgn:7410298",
        "tgn:1000001",
        "tgn:7005592",
        "tgn:7005560",
        "tgn:7029392"
    ],
    "tgn:id":7410298,
    "tgn:name":"Los H\u00fameros",
    "tgn:placetype":[
        "aat:300008347"
    ]
},
  "bbox": [],
  "geometry": {"coordinates":[-97.458333,19.680556],"type":"Point"}
}