{
  "id": 2625085,
  "type": "Feature",
  "properties": {
    "tgn:hierarchy":[
        "tgn:2625085",
        "tgn:1000001",
        "tgn:1002695",
        "tgn:7012149",
        "tgn:7007565",
        "tgn:7029392"
    ],
    "tgn:id":2625085,
    "tgn:name":"Rockaway Valley",
    "tgn:placetype":[
        "aat:300008761"
    ]
},
  "bbox": [],
  "geometry": {"coordinates":[-74.3833,40.9667],"type":"Point"}
}