{
  "id": 7523563,
  "type": "Feature",
  "properties": {
    "tgn:hierarchy":[
        "tgn:7523563",
        "tgn:7001242",
        "tgn:7016833",
        "tgn:7001336",
        "tgn:7029392"
    ],
    "tgn:id":7523563,
    "tgn:name:en":"El-Aqaba",
    "tgn:placetype":[
        "aat:300055621"
    ]
},
  "bbox": [],
  "geometry": {"coordinates":[33.286944,29.033611],"type":"Point"}
}