{
  "id": 1010911,
  "type": "Feature",
  "properties": {
    "tgn:hierarchy":[
        "tgn:1010911",
        "tgn:7017441",
        "tgn:1000001",
        "tgn:7004643",
        "tgn:7029392"
    ],
    "tgn:id":1010911,
    "tgn:name":"Mala Pascua, Cabo",
    "tgn:placetype":[
        "aat:300008850"
    ]
},
  "bbox": [],
  "geometry": {"coordinates":[-65.9167,17.9833],"type":"Point"}
}