{
  "id": 7306960,
  "type": "Feature",
  "properties": {
    "tgn:hierarchy":[
        "tgn:7306960",
        "tgn:7002811",
        "tgn:1000003",
        "tgn:7003837",
        "tgn:1000095",
        "tgn:7029392"
    ],
    "tgn:id":7306960,
    "tgn:name":"Magasca, R\u00edo",
    "tgn:placetype":[
        "aat:300008699"
    ]
},
  "bbox": [],
  "geometry": {"coordinates":[-6.133333,39.533333],"type":"Point"}
}