{
  "id": 1059932,
  "type": "Feature",
  "properties": {
    "tgn:hierarchy":[
        "tgn:1059932",
        "tgn:1000003",
        "tgn:1003410",
        "tgn:7006660",
        "tgn:7029392"
    ],
    "tgn:id":1059932,
    "tgn:name":"Sumy",
    "tgn:placetype":[
        "aat:300008347",
        "aat:300008389",
        "aat:300387220"
    ]
},
  "bbox": [],
  "geometry": {"coordinates":[34.8167,50.9167],"type":"Point"}
}