{
  "id": 7265596,
  "type": "Feature",
  "properties": {
    "tgn:hierarchy":[
        "tgn:7265596",
        "tgn:7003614",
        "tgn:1000003",
        "tgn:7016845",
        "tgn:7029392"
    ],
    "tgn:id":7265596,
    "tgn:name:nl":"Hunnenkloosterberg",
    "tgn:placetype":[
        "aat:300008777"
    ]
},
  "bbox": [],
  "geometry": {"coordinates":[6.366667,52.733333],"type":"Point"}
}