{
  "id": 7546812,
  "type": "Feature",
  "properties": {
    "tgn:hierarchy":[
        "tgn:7546812",
        "tgn:1000004",
        "tgn:7000198",
        "tgn:7031786",
        "tgn:7029392"
    ],
    "tgn:id":7546812,
    "tgn:name:en":"Abbott Mount",
    "tgn:placetype":[
        "aat:300008795"
    ]
},
  "bbox": [],
  "geometry": {"coordinates":[80.083333,29.433333],"type":"Point"}
}