{
  "id": 2643595,
  "type": "Feature",
  "properties": {
    "tgn:hierarchy":[
        "tgn:2643595",
        "tgn:1000001",
        "tgn:1002480",
        "tgn:7012149",
        "tgn:7007564",
        "tgn:7029392"
    ],
    "tgn:id":2643595,
    "tgn:name":"Sandy Pond",
    "tgn:placetype":[
        "aat:300008680"
    ]
},
  "bbox": [],
  "geometry": {"coordinates":[-71.4667,42.7333],"type":"Point"}
}