{
  "id": 7384649,
  "type": "Feature",
  "properties": {
    "tgn:hierarchy":[
        "tgn:7384649",
        "tgn:7005586",
        "tgn:1000001",
        "tgn:7005560",
        "tgn:7029392"
    ],
    "tgn:id":7384649,
    "tgn:name":"Mismaloya, Boca",
    "tgn:placetype":[
        "aat:300387057"
    ]
},
  "bbox": [],
  "geometry": {"coordinates":[-105.516667,19.966667],"type":"Point"}
}