{
  "id": 7361551,
  "type": "Feature",
  "properties": {
    "tgn:hierarchy":[
        "tgn:7361551",
        "tgn:1000001",
        "tgn:7005591",
        "tgn:7005560",
        "tgn:7029392"
    ],
    "tgn:id":7361551,
    "tgn:name":"El J\u00edcaro",
    "tgn:placetype":[
        "aat:300008347"
    ]
},
  "bbox": [],
  "geometry": {"coordinates":[-98.083333,16.183333],"type":"Point"}
}