{
  "id": 2344856,
  "type": "Feature",
  "properties": {
    "tgn:hierarchy":[
        "tgn:2344856",
        "tgn:2001837",
        "tgn:1000001",
        "tgn:7012149",
        "tgn:7007825",
        "tgn:7029392"
    ],
    "tgn:id":2344856,
    "tgn:name":"Garden Spot, The",
    "tgn:placetype":[
        "aat:300008798"
    ]
},
  "bbox": [],
  "geometry": {"coordinates":[-84.4333,36.15],"type":"Point"}
}