{
  "id": 7285566,
  "type": "Feature",
  "properties": {
    "tgn:hierarchy":[
        "tgn:7285566",
        "tgn:7002464",
        "tgn:1000049",
        "tgn:1000002",
        "tgn:7029392"
    ],
    "tgn:id":7285566,
    "tgn:name":"Plaza, Cerro",
    "tgn:placetype":[
        "aat:300008795"
    ]
},
  "bbox": [],
  "geometry": {"coordinates":[-68.883333,-19.883333],"type":"Point"}
}