{
  "id": 7199131,
  "type": "Feature",
  "properties": {
    "tgn:hierarchy":[
        "tgn:7199131",
        "tgn:7003669",
        "tgn:1000003",
        "tgn:7000084",
        "tgn:7029392"
    ],
    "tgn:id":7199131,
    "tgn:name":"Eben",
    "tgn:placetype":[
        "aat:300008347"
    ]
},
  "bbox": [],
  "geometry": {"coordinates":[13.133333,49.15],"type":"Point"}
}