<<<<<<< HEAD
{
  "id": 2258195,
  "type": "Feature",
  "properties": {
    "tgn:hierarchy":[
        "tgn:2258195",
        "tgn:2001732",
        "tgn:1000001",
        "tgn:7012149",
        "tgn:7007712",
        "tgn:7029392"
    ],
    "tgn:id":2258195,
    "tgn:name":"Cote Bas Landing",
    "tgn:placetype":[
        "aat:300008347"
    ]
},
  "bbox": [],
  "geometry": {"coordinates":[-79.9167,33.0],"type":"Point"}
}
=======
{"geometry":{"type":"Point","coordinates":[-79.916700,33.000000]},"type":"Feature","properties":{"hierarchy":["tgn:2258195","tgn:2001732","tgn:1000001","tgn:7012149","tgn:7007712","tgn:7029392"],"placetype":["aat:300008347"],"id":2258195,"name:xx":"Cote Bas Landing"}}
>>>>>>> 03f74aca74312dbeaf24d7e61306dd6a786dc3d0
