<<<<<<< HEAD
{
  "id": 2150981,
  "type": "Feature",
  "properties": {
    "tgn:hierarchy":[
        "tgn:2150981",
        "tgn:1000001",
        "tgn:1003037",
        "tgn:7012149",
        "tgn:7007516",
        "tgn:7029392"
    ],
    "tgn:id":2150981,
    "tgn:name":"Bassett Creek",
    "tgn:placetype":[
        "aat:300008706"
    ]
},
  "bbox": [],
  "geometry": {"coordinates":[-75.2333,38.25],"type":"Point"}
}
=======
{"geometry":{"type":"Point","coordinates":[-75.233300,38.250000]},"type":"Feature","properties":{"hierarchy":["tgn:2150981","tgn:1000001","tgn:1003037","tgn:7012149","tgn:7007516","tgn:7029392"],"placetype":["aat:300008706"],"id":2150981,"name:xx":"Bassett Creek"}}
>>>>>>> 03f74aca74312dbeaf24d7e61306dd6a786dc3d0
