{
  "id": 2687527,
  "type": "Feature",
  "properties": {
    "tgn:hierarchy":[
        "tgn:2687527",
        "tgn:1000001",
        "tgn:2002254",
        "tgn:7012149",
        "tgn:7013961",
        "tgn:7029392"
    ],
    "tgn:id":2687527,
    "tgn:name":"Spring Mill Spring",
    "tgn:placetype":[
        "aat:300008697"
    ]
},
  "bbox": [],
  "geometry": {"coordinates":[-77.95,39.55],"type":"Point"}
}