{
  "id": 1003909,
  "type": "Feature",
  "properties": {
    "tgn:hierarchy":[
        "tgn:1003909",
        "tgn:7018908",
        "tgn:7002445",
        "tgn:1000003",
        "tgn:7008136",
        "tgn:7008591",
        "tgn:7029392"
    ],
    "tgn:id":1003909,
    "tgn:name":"Abbey Wood",
    "tgn:placetype":[
        "aat:300000745"
    ]
},
  "bbox": [],
  "geometry": {"coordinates":[0.1333,51.4833],"type":"Point"}
}