{
  "id": 7070063,
  "type": "Feature",
  "properties": {
    "tgn:hierarchy":[
        "tgn:7070063",
        "tgn:1000003",
        "tgn:7003676",
        "tgn:7000084",
        "tgn:7029392"
    ],
    "tgn:id":7070063,
    "tgn:name":"Stein-Berg",
    "tgn:placetype":[
        "aat:300008777"
    ]
},
  "bbox": [],
  "geometry": {"coordinates":[8.083333,52.366667],"type":"Point"}
}