{
  "id": 2267228,
  "type": "Feature",
  "properties": {
    "tgn:hierarchy":[
        "tgn:2267228",
        "tgn:1000001",
        "tgn:7012149",
        "tgn:1002402",
        "tgn:7007523",
        "tgn:7029392"
    ],
    "tgn:id":2267228,
    "tgn:name":"Crider Hollow",
    "tgn:placetype":[
        "aat:300008761"
    ]
},
  "bbox": [],
  "geometry": {"coordinates":[-91.6167,38.4667],"type":"Point"}
}