{
  "id": 1080143,
  "type": "Feature",
  "properties": {
    "tgn:hierarchy":[
        "tgn:1080143",
        "tgn:1000004",
        "tgn:1000962",
        "tgn:7000896",
        "tgn:1000120",
        "tgn:7029392"
    ],
    "tgn:id":1080143,
    "tgn:name":"Hisai",
    "tgn:placetype":[
        "aat:300008347"
    ]
},
  "bbox": [],
  "geometry": {"coordinates":[135.4667,34.4167],"type":"Point"}
}