{
  "id": 2192510,
  "type": "Feature",
  "properties": {
    "tgn:hierarchy":[
        "tgn:2192510",
        "tgn:1000001",
        "tgn:7012149",
        "tgn:7007251",
        "tgn:7029392"
    ],
    "tgn:id":2192510,
    "tgn:name":"Brandywine Creek",
    "tgn:placetype":[
        "aat:300008706"
    ]
},
  "bbox": [],
  "geometry": {"coordinates":[-90.0167,41.0167],"type":"Point"}
}