{
  "id": 2781353,
  "type": "Feature",
  "properties": {
    "tgn:hierarchy":[
        "tgn:2781353",
        "tgn:1000001",
        "tgn:2001747",
        "tgn:7012149",
        "tgn:7007712",
        "tgn:7029392"
    ],
    "tgn:id":2781353,
    "tgn:name":"Woodland Homes",
    "tgn:placetype":[
        "aat:300008347"
    ]
},
  "bbox": [],
  "geometry": {"coordinates":[-82.35,34.85],"type":"Point"}
}