{
  "id": 2689175,
  "type": "Feature",
  "properties": {
    "tgn:hierarchy":[
        "tgn:2689175",
        "tgn:1000001",
        "tgn:1002316",
        "tgn:7012149",
        "tgn:7007922",
        "tgn:7029392"
    ],
    "tgn:id":2689175,
    "tgn:name":"Squaw Bay",
    "tgn:placetype":[
        "aat:300132316"
    ]
},
  "bbox": [],
  "geometry": {"coordinates":[-89.3333,43.05],"type":"Point"}
}