{
  "id": 2541634,
  "type": "Feature",
  "properties": {
    "tgn:hierarchy":[
        "tgn:2541634",
        "tgn:1000001",
        "tgn:7012149",
        "tgn:2001722",
        "tgn:7007708",
        "tgn:7029392"
    ],
    "tgn:id":2541634,
    "tgn:name":"Nine Point Creek",
    "tgn:placetype":[
        "aat:300008706"
    ]
},
  "bbox": [],
  "geometry": {"coordinates":[-116.8667,45.2167],"type":"Point"}
}