<<<<<<< HEAD
{
  "id": 2251235,
  "type": "Feature",
  "properties": {
    "tgn:hierarchy":[
        "tgn:2251235",
        "tgn:1000001",
        "tgn:7012149",
        "tgn:1002303",
        "tgn:7007826",
        "tgn:7029392"
    ],
    "tgn:id":2251235,
    "tgn:name":"Comanche Village III",
    "tgn:placetype":[
        "aat:300008347"
    ]
},
  "bbox": [],
  "geometry": {"coordinates":[-97.8167,31.1333],"type":"Point"}
}
=======
{"geometry":{"type":"Point","coordinates":[-97.816700,31.133300]},"type":"Feature","properties":{"hierarchy":["tgn:2251235","tgn:1000001","tgn:7012149","tgn:1002303","tgn:7007826","tgn:7029392"],"placetype":["aat:300008347"],"id":2251235,"name:xx":"Comanche Village III"}}
>>>>>>> 03f74aca74312dbeaf24d7e61306dd6a786dc3d0
