<<<<<<< HEAD
{
  "id": 2766232,
  "type": "Feature",
  "properties": {
    "tgn:hierarchy":[
        "tgn:2766232",
        "tgn:1000001",
        "tgn:7012149",
        "tgn:2002361",
        "tgn:7007922",
        "tgn:7029392"
    ],
    "tgn:id":2766232,
    "tgn:name":"White Lake",
    "tgn:placetype":[
        "aat:300008680"
    ]
},
  "bbox": [],
  "geometry": {"coordinates":[-88.9167,44.35],"type":"Point"}
}
=======
{"geometry":{"type":"Point","coordinates":[-88.916700,44.350000]},"type":"Feature","properties":{"hierarchy":["tgn:2766232","tgn:1000001","tgn:7012149","tgn:2002361","tgn:7007922","tgn:7029392"],"placetype":["aat:300008680"],"id":2766232,"name:xx":"White Lake"}}
>>>>>>> 03f74aca74312dbeaf24d7e61306dd6a786dc3d0
