{
  "id": 2296972,
  "type": "Feature",
  "properties": {
    "tgn:hierarchy":[
        "tgn:2296972",
        "tgn:1000001",
        "tgn:2001631",
        "tgn:7012149",
        "tgn:7007707",
        "tgn:7029392"
    ],
    "tgn:id":2296972,
    "tgn:name":"Dry Creek",
    "tgn:placetype":[
        "aat:300008706"
    ]
},
  "bbox": [],
  "geometry": {"coordinates":[-97.85,35.4167],"type":"Point"}
}