{
  "id": 7300545,
  "type": "Feature",
  "properties": {
    "tgn:hierarchy":[
        "tgn:7300545",
        "tgn:7002826",
        "tgn:7001158",
        "tgn:1000003",
        "tgn:1000095",
        "tgn:7029392"
    ],
    "tgn:id":7300545,
    "tgn:name":"Valdecastre, Arroyo",
    "tgn:placetype":[
        "aat:300266554",
        "aat:300008699"
    ]
},
  "bbox": [],
  "geometry": {"coordinates":[-5.233333,42.45],"type":"Point"}
}