{
  "id": 7413983,
  "type": "Feature",
  "properties": {
    "tgn:hierarchy":[
        "tgn:7413983",
        "tgn:1000001",
        "tgn:7005598",
        "tgn:7005560",
        "tgn:7029392"
    ],
    "tgn:id":7413983,
    "tgn:name":"D\u00edaz Ordaz",
    "tgn:placetype":[
        "aat:300008347"
    ]
},
  "bbox": [],
  "geometry": {"coordinates":[-98.465278,19.561111],"type":"Point"}
}