{
  "id": 2053848,
  "type": "Feature",
  "properties": {
    "tgn:hierarchy":[
        "tgn:2053848",
        "tgn:1000001",
        "tgn:7012149",
        "tgn:2001067",
        "tgn:7007521",
        "tgn:7029392"
    ],
    "tgn:id":2053848,
    "tgn:name":"Angora",
    "tgn:placetype":[
        "aat:300008347"
    ]
},
  "bbox": [],
  "geometry": {"coordinates":[-92.6333,47.7667],"type":"Point"}
}