{
  "id": 2228065,
  "type": "Feature",
  "properties": {
    "tgn:hierarchy":[
        "tgn:2228065",
        "tgn:1000001",
        "tgn:7012149",
        "tgn:2001272",
        "tgn:7007524",
        "tgn:7029392"
    ],
    "tgn:id":2228065,
    "tgn:name":"Cedar Butte",
    "tgn:placetype":[
        "aat:300008798"
    ]
},
  "bbox": [],
  "geometry": {"coordinates":[-104.1333,46.45],"type":"Point"}
}