<<<<<<< HEAD
{
  "id": 2156503,
  "type": "Feature",
  "properties": {
    "tgn:hierarchy":[
        "tgn:2156503",
        "tgn:1000001",
        "tgn:7012149",
        "tgn:1002746",
        "tgn:7007568",
        "tgn:7029392"
    ],
    "tgn:id":2156503,
    "tgn:name":"Beartrap Creek",
    "tgn:placetype":[
        "aat:300008706"
    ]
},
  "bbox": [],
  "geometry": {"coordinates":[-76.1333,43.1167],"type":"Point"}
}
=======
{"geometry":{"type":"Point","coordinates":[-76.133300,43.116700]},"type":"Feature","properties":{"hierarchy":["tgn:2156503","tgn:1000001","tgn:7012149","tgn:1002746","tgn:7007568","tgn:7029392"],"placetype":["aat:300008706"],"id":2156503,"name:xx":"Beartrap Creek"}}
>>>>>>> 03f74aca74312dbeaf24d7e61306dd6a786dc3d0
