<<<<<<< HEAD
{
  "id": 2158832,
  "type": "Feature",
  "properties": {
    "tgn:hierarchy":[
        "tgn:2158832",
        "tgn:1000001",
        "tgn:7012149",
        "tgn:1002993",
        "tgn:7007568",
        "tgn:7029392"
    ],
    "tgn:id":2158832,
    "tgn:name":"Becker Hill",
    "tgn:placetype":[
        "aat:300008798"
    ]
},
  "bbox": [],
  "geometry": {"coordinates":[-73.5167,43.0],"type":"Point"}
}
=======
{"geometry":{"type":"Point","coordinates":[-73.516700,43.000000]},"type":"Feature","properties":{"hierarchy":["tgn:2158832","tgn:1000001","tgn:7012149","tgn:1002993","tgn:7007568","tgn:7029392"],"placetype":["aat:300008798"],"id":2158832,"name:xx":"Becker Hill"}}
>>>>>>> 03f74aca74312dbeaf24d7e61306dd6a786dc3d0
