{
  "id": 7501660,
  "type": "Feature",
  "properties": {
    "tgn:hierarchy":[
        "tgn:7501660",
        "tgn:1000004",
        "tgn:7492971",
        "tgn:1000141",
        "tgn:7029392"
    ],
    "tgn:id":7501660,
    "tgn:name":"Yonggang Qiao",
    "tgn:placetype":[
        "aat:300007836"
    ]
},
  "bbox": [],
  "geometry": {"coordinates":[120.816111,21.999722],"type":"Point"}
}