{
  "id": 1035850,
  "type": "Feature",
  "properties": {
    "tgn:hierarchy":[
        "tgn:1035850",
        "tgn:1000003",
        "tgn:7002888",
        "tgn:1000070",
        "tgn:7029392"
    ],
    "tgn:id":1035850,
    "tgn:name":"Thiaucourt-Regni\u00e9ville",
    "tgn:placetype":[
        "aat:300008347"
    ]
},
  "bbox": [],
  "geometry": {"coordinates":[5.8667,48.95],"type":"Point"}
}