<<<<<<< HEAD
{
  "id": 7110151,
  "type": "Feature",
  "properties": {
    "tgn:hierarchy":[
        "tgn:7110151",
        "tgn:1000003",
        "tgn:7003676",
        "tgn:7000084",
        "tgn:7029392"
    ],
    "tgn:id":7110151,
    "tgn:name":"Ramena",
    "tgn:placetype":[
        "aat:300000206"
    ]
},
  "bbox": [],
  "geometry": {"coordinates":[9.483333,52.2],"type":"Point"}
}
=======
{"geometry":{"type":"Point","coordinates":[9.483333,52.200000]},"type":"Feature","properties":{"hierarchy":["tgn:7110151","tgn:1000003","tgn:7003676","tgn:7000084","tgn:7029392"],"placetype":["aat:300000206"],"id":7110151,"name:xx":"Ramena"}}
>>>>>>> 03f74aca74312dbeaf24d7e61306dd6a786dc3d0
