{
  "id": 7567018,
  "type": "Feature",
  "properties": {
    "tgn:hierarchy":[
        "tgn:7567018",
        "tgn:1001828",
        "tgn:1000004",
        "tgn:7000198",
        "tgn:7029392"
    ],
    "tgn:id":7567018,
    "tgn:name:en":"Kisht\u0101pur",
    "tgn:placetype":[
        "aat:300008347"
    ]
},
  "bbox": [],
  "geometry": {"coordinates":[78.74,17.795],"type":"Point"}
}