{
  "id": 7342937,
  "type": "Feature",
  "properties": {
    "tgn:hierarchy":[
        "tgn:7342937",
        "tgn:7002818",
        "tgn:1001647",
        "tgn:1000003",
        "tgn:1000095",
        "tgn:7029392"
    ],
    "tgn:id":7342937,
    "tgn:name":"Calder\u00f3n, Cerro",
    "tgn:placetype":[
        "aat:300008777"
    ]
},
  "bbox": [],
  "geometry": {"coordinates":[-2.133333,39.85],"type":"Point"}
}