{
  "id": 1049883,
  "type": "Feature",
  "properties": {
    "tgn:hierarchy":[
        "tgn:1049883",
        "tgn:7003833",
        "tgn:7011003",
        "tgn:1000003",
        "tgn:1000090",
        "tgn:7029392"
    ],
    "tgn:id":1049883,
    "tgn:name":"Ponta Delgada",
    "tgn:placetype":[
        "aat:300008347",
        "aat:300008389",
        "aat:300387222",
        "aat:300264742",
        "aat:300387512",
        "aat:300387220",
        "aat:300120599",
        "aat:300387291"
    ]
},
  "bbox": [],
  "geometry": {"coordinates":[-25.6667,37.7333],"type":"Point"}
}