{
  "id": 2571619,
  "type": "Feature",
  "properties": {
    "tgn:hierarchy":[
        "tgn:2571619",
        "tgn:1000001",
        "tgn:7012149",
        "tgn:2001449",
        "tgn:7007566",
        "tgn:7029392"
    ],
    "tgn:id":2571619,
    "tgn:name":"Pavo Mine",
    "tgn:placetype":[
        "aat:300000390"
    ]
},
  "bbox": [],
  "geometry": {"coordinates":[-106.0167,36.4833],"type":"Point"}
}