{
  "id": 7312875,
  "type": "Feature",
  "properties": {
    "tgn:hierarchy":[
        "tgn:7312875",
        "tgn:1001699",
        "tgn:1000049",
        "tgn:1000002",
        "tgn:7029392"
    ],
    "tgn:id":7312875,
    "tgn:name":"Lameguapi, R\u00edo",
    "tgn:placetype":[
        "aat:300008699"
    ]
},
  "bbox": [],
  "geometry": {"coordinates":[-73.716667,-40.183333],"type":"Point"}
}