{
  "id": 2447761,
  "type": "Feature",
  "properties": {
    "tgn:hierarchy":[
        "tgn:2447761",
        "tgn:1000001",
        "tgn:2002261",
        "tgn:7012149",
        "tgn:7013961",
        "tgn:7029392"
    ],
    "tgn:id":2447761,
    "tgn:name":"Lick Run",
    "tgn:placetype":[
        "aat:300008699"
    ]
},
  "bbox": [],
  "geometry": {"coordinates":[-80.8833,37.9667],"type":"Point"}
}