<<<<<<< HEAD
{
  "id": 2331504,
  "type": "Feature",
  "properties": {
    "tgn:hierarchy":[
        "tgn:2331504",
        "tgn:1000001",
        "tgn:7006451",
        "tgn:7012149",
        "tgn:2000098",
        "tgn:7029392"
    ],
    "tgn:id":2331504,
    "tgn:name":"Flattop Wash",
    "tgn:placetype":[
        "aat:300008699"
    ]
},
  "bbox": [],
  "geometry": {"coordinates":[-114.0167,34.8],"type":"Point"}
}
=======
{"geometry":{"type":"Point","coordinates":[-114.016700,34.800000]},"type":"Feature","properties":{"hierarchy":["tgn:2331504","tgn:1000001","tgn:7006451","tgn:7012149","tgn:2000098","tgn:7029392"],"placetype":["aat:300008699"],"id":2331504,"name:xx":"Flattop Wash"}}
>>>>>>> 03f74aca74312dbeaf24d7e61306dd6a786dc3d0
