{
  "id": 7429022,
  "type": "Feature",
  "properties": {
    "tgn:hierarchy":[
        "tgn:7429022",
        "tgn:1001835",
        "tgn:1000001",
        "tgn:7005560",
        "tgn:7029392"
    ],
    "tgn:id":7429022,
    "tgn:name":"Punta Baja",
    "tgn:placetype":[
        "aat:300008347"
    ]
},
  "bbox": [],
  "geometry": {"coordinates":[-115.816667,29.966667],"type":"Point"}
}