{
  "id": 7211986,
  "type": "Feature",
  "properties": {
    "tgn:hierarchy":[
        "tgn:7211986",
        "tgn:1000003",
        "tgn:7003688",
        "tgn:7000084",
        "tgn:7029392"
    ],
    "tgn:id":7211986,
    "tgn:name":"Billwattbr\u00fcck",
    "tgn:placetype":[
        "aat:300000206"
    ]
},
  "bbox": [],
  "geometry": {"coordinates":[9.716667,54.633333],"type":"Point"}
}