{
  "id": 2204451,
  "type": "Feature",
  "properties": {
    "tgn:hierarchy":[
        "tgn:2204451",
        "tgn:1000001",
        "tgn:7012149",
        "tgn:2001666",
        "tgn:7007707",
        "tgn:7029392"
    ],
    "tgn:id":2204451,
    "tgn:name":"Buffalo Creek",
    "tgn:placetype":[
        "aat:300008706"
    ]
},
  "bbox": [],
  "geometry": {"coordinates":[-97.65,35.0667],"type":"Point"}
}