{
  "id": 2487614,
  "type": "Feature",
  "properties": {
    "tgn:hierarchy":[
        "tgn:2487614",
        "tgn:1000001",
        "tgn:7012149",
        "tgn:2000789",
        "tgn:7007255",
        "tgn:7029392"
    ],
    "tgn:id":2487614,
    "tgn:name":"Left Fork Hoods Fork",
    "tgn:placetype":[
        "aat:300008699"
    ]
},
  "bbox": [],
  "geometry": {"coordinates":[-82.6833,37.4333],"type":"Point"}
}