<<<<<<< HEAD
{
  "id": 7021766,
  "type": "Feature",
  "properties": {
    "tgn:hierarchy":[
        "tgn:7021766",
        "tgn:1000001",
        "tgn:7012149",
        "tgn:2001759",
        "tgn:7007712",
        "tgn:7029392"
    ],
    "tgn:id":7021766,
    "tgn:name":"Andersons Millpond",
    "tgn:placetype":[
        "aat:300006191"
    ]
},
  "bbox": [],
  "geometry": {"coordinates":[-79.8333,34.6833],"type":"Point"}
}
=======
{"geometry":{"type":"Point","coordinates":[-79.833300,34.683300]},"type":"Feature","properties":{"hierarchy":["tgn:7021766","tgn:1000001","tgn:7012149","tgn:2001759","tgn:7007712","tgn:7029392"],"placetype":["aat:300006191"],"id":7021766,"name:xx":"Andersons Millpond"}}
>>>>>>> 03f74aca74312dbeaf24d7e61306dd6a786dc3d0
