{
  "id": 2270475,
  "type": "Feature",
  "properties": {
    "tgn:hierarchy":[
        "tgn:2270475",
        "tgn:1000001",
        "tgn:7012149",
        "tgn:2002073",
        "tgn:7007826",
        "tgn:7029392"
    ],
    "tgn:id":2270475,
    "tgn:name":"Crystal Lake",
    "tgn:placetype":[
        "aat:300006191"
    ]
},
  "bbox": [],
  "geometry": {"coordinates":[-94.0667,31.9667],"type":"Point"}
}