{
  "id": 2784390,
  "type": "Feature",
  "properties": {
    "tgn:hierarchy":[
        "tgn:2784390",
        "tgn:1000001",
        "tgn:7006451",
        "tgn:2000091",
        "tgn:7012149",
        "tgn:7029392"
    ],
    "tgn:id":2784390,
    "tgn:name":"Yaqui Canyon",
    "tgn:placetype":[
        "aat:300008761"
    ]
},
  "bbox": [],
  "geometry": {"coordinates":[-110.2667,31.3333],"type":"Point"}
}