{
  "id": 1106975,
  "type": "Feature",
  "properties": {
    "tgn:hierarchy":[
        "tgn:1106975",
        "tgn:1000001",
        "tgn:7012149",
        "tgn:7029392"
    ],
    "tgn:id":1106975,
    "tgn:name":"White Rocks",
    "tgn:placetype":[
        "aat:300008795"
    ]
},
  "bbox": [],
  "geometry": {"coordinates":[-83.4333,36.6667],"type":"Point"}
}