{
  "id": 7250181,
  "type": "Feature",
  "properties": {
    "tgn:hierarchy":[
        "tgn:7250181",
        "tgn:7003460",
        "tgn:1000003",
        "tgn:1000063",
        "tgn:4012014",
        "tgn:7029392"
    ],
    "tgn:id":7250181,
    "tgn:name":"Profondval",
    "tgn:placetype":[
        "aat:300008347"
    ]
},
  "bbox": [],
  "geometry": {"coordinates":[5.472334,50.614439],"type":"Point"}
}