{
  "id": 7112532,
  "type": "Feature",
  "properties": {
    "tgn:hierarchy":[
        "tgn:7112532",
        "tgn:1000003",
        "tgn:7003682",
        "tgn:7000084",
        "tgn:7029392"
    ],
    "tgn:id":7112532,
    "tgn:name":"Rindenb\u00fchl",
    "tgn:placetype":[
        "aat:300008777"
    ]
},
  "bbox": [],
  "geometry": {"coordinates":[7.866667,49.25],"type":"Point"}
}