{
  "id": 7207869,
  "type": "Feature",
  "properties": {
    "tgn:hierarchy":[
        "tgn:7207869",
        "tgn:1000003",
        "tgn:7003687",
        "tgn:7000084",
        "tgn:7029392"
    ],
    "tgn:id":7207869,
    "tgn:name":"Buchen-Berg",
    "tgn:placetype":[
        "aat:300008777"
    ]
},
  "bbox": [],
  "geometry": {"coordinates":[10.933333,51.95],"type":"Point"}
}