{
  "id": 7082358,
  "type": "Feature",
  "properties": {
    "tgn:hierarchy":[
        "tgn:7082358",
        "tgn:1000003",
        "tgn:7003682",
        "tgn:7000084",
        "tgn:7029392"
    ],
    "tgn:id":7082358,
    "tgn:name":"Wengenroth",
    "tgn:placetype":[
        "aat:300008347"
    ]
},
  "bbox": [],
  "geometry": {"coordinates":[7.983333,50.55],"type":"Point"}
}