{
  "id": 7378107,
  "type": "Feature",
  "properties": {
    "tgn:hierarchy":[
        "tgn:7378107",
        "tgn:7005584",
        "tgn:1000001",
        "tgn:7005560",
        "tgn:7029392"
    ],
    "tgn:id":7378107,
    "tgn:name":"La Virgen",
    "tgn:placetype":[
        "aat:300008347"
    ]
},
  "bbox": [],
  "geometry": {"coordinates":[-101.483333,21.416667],"type":"Point"}
}