{
  "id": 7070462,
  "type": "Feature",
  "properties": {
    "tgn:hierarchy":[
        "tgn:7070462",
        "tgn:1000003",
        "tgn:7003677",
        "tgn:7000084",
        "tgn:7029392"
    ],
    "tgn:id":7070462,
    "tgn:name":"Stein",
    "tgn:placetype":[
        "aat:300008777"
    ]
},
  "bbox": [],
  "geometry": {"coordinates":[8.516667,51.266667],"type":"Point"}
}