{
  "id": 2262406,
  "type": "Feature",
  "properties": {
    "tgn:hierarchy":[
        "tgn:2262406",
        "tgn:1000001",
        "tgn:7012149",
        "tgn:7007157",
        "tgn:2000186",
        "tgn:7029392"
    ],
    "tgn:id":2262406,
    "tgn:name":"Cow Head Lake",
    "tgn:placetype":[
        "aat:300008680"
    ]
},
  "bbox": [],
  "geometry": {"coordinates":[-120.0167,41.9167],"type":"Point"}
}