{
  "id": 1079413,
  "type": "Feature",
  "properties": {
    "tgn:hierarchy":[
        "tgn:1079413",
        "tgn:1001072",
        "tgn:1000004",
        "tgn:1000118",
        "tgn:7029392"
    ],
    "tgn:id":1079413,
    "tgn:name":"Az-Zubayr",
    "tgn:placetype":[
        "aat:300008347"
    ]
},
  "bbox": [],
  "geometry": {"coordinates":[47.6833,30.3833],"type":"Point"}
}