{
  "id": 2767232,
  "type": "Feature",
  "properties": {
    "tgn:hierarchy":[
        "tgn:2767232",
        "tgn:1000001",
        "tgn:7006451",
        "tgn:2000091",
        "tgn:7012149",
        "tgn:7029392"
    ],
    "tgn:id":2767232,
    "tgn:name":"White Rock Spring",
    "tgn:placetype":[
        "aat:300008697"
    ]
},
  "bbox": [],
  "geometry": {"coordinates":[-109.5167,32.1667],"type":"Point"}
}