{
  "id": 2022624,
  "type": "Feature",
  "properties": {
    "tgn:hierarchy":[
        "tgn:2022624",
        "tgn:1000001",
        "tgn:7012149",
        "tgn:2000355",
        "tgn:7007248",
        "tgn:7029392"
    ],
    "tgn:id":2022624,
    "tgn:name":"Damascus",
    "tgn:placetype":[
        "aat:300008347"
    ]
},
  "bbox": [],
  "geometry": {"coordinates":[-84.9333,34.55],"type":"Point"}
}