{
  "id": 2131020,
  "type": "Feature",
  "properties": {
    "tgn:hierarchy":[
        "tgn:2131020",
        "tgn:7006450",
        "tgn:1000001",
        "tgn:7019698",
        "tgn:7012149",
        "tgn:7029392"
    ],
    "tgn:id":2131020,
    "tgn:name":"Alpenglow, Mount",
    "tgn:placetype":[
        "aat:300008798"
    ]
},
  "bbox": [],
  "geometry": {"coordinates":[-149.3167,60.8667],"type":"Point"}
}