{
  "id": 2257297,
  "type": "Feature",
  "properties": {
    "tgn:hierarchy":[
        "tgn:2257297",
        "tgn:1000001",
        "tgn:7012149",
        "tgn:7007158",
        "tgn:2000248",
        "tgn:7029392"
    ],
    "tgn:id":2257297,
    "tgn:name":"Cornforth Ditch",
    "tgn:placetype":[
        "aat:300006075"
    ]
},
  "bbox": [],
  "geometry": {"coordinates":[-108.2167,38.0667],"type":"Point"}
}