{
  "id": 2281643,
  "type": "Feature",
  "properties": {
    "tgn:hierarchy":[
        "tgn:2281643",
        "tgn:1000001",
        "tgn:7012149",
        "tgn:2000612",
        "tgn:7007253",
        "tgn:7029392"
    ],
    "tgn:id":2281643,
    "tgn:name":"Deer Creek",
    "tgn:placetype":[
        "aat:300008706"
    ]
},
  "bbox": [],
  "geometry": {"coordinates":[-91.75,41.6833],"type":"Point"}
}