{
  "id": 2096517,
  "type": "Feature",
  "properties": {
    "tgn:hierarchy":[
        "tgn:2096517",
        "tgn:2001731",
        "tgn:1000001",
        "tgn:7012149",
        "tgn:7007712",
        "tgn:7029392"
    ],
    "tgn:id":2096517,
    "tgn:name":"Pritchardville",
    "tgn:placetype":[
        "aat:300008347",
        "aat:300387210"
    ]
},
  "bbox": [],
  "geometry": {"coordinates":[-80.95,32.2333],"type":"Point"}
}