{
  "id": 2078956,
  "type": "Feature",
  "properties": {
    "tgn:hierarchy":[
        "tgn:2078956",
        "tgn:1002136",
        "tgn:1000001",
        "tgn:7012149",
        "tgn:7007706",
        "tgn:7029392"
    ],
    "tgn:id":2078956,
    "tgn:name":"Clayton",
    "tgn:placetype":[
        "aat:300008347",
        "aat:300387210"
    ]
},
  "bbox": [],
  "geometry": {"coordinates":[-83.6667,38.7333],"type":"Point"}
}