{
  "id": 2423185,
  "type": "Feature",
  "properties": {
    "tgn:hierarchy":[
        "tgn:2423185",
        "tgn:1000001",
        "tgn:7012149",
        "tgn:7007250",
        "tgn:7029392"
    ],
    "tgn:id":2423185,
    "tgn:name":"Joes Creek",
    "tgn:placetype":[
        "aat:300008706"
    ]
},
  "bbox": [],
  "geometry": {"coordinates":[-116.1333,44.3667],"type":"Point"}
}