{
  "id": 2204391,
  "type": "Feature",
  "properties": {
    "tgn:hierarchy":[
        "tgn:2204391",
        "tgn:1000001",
        "tgn:7012149",
        "tgn:2000762",
        "tgn:7007254",
        "tgn:7029392"
    ],
    "tgn:id":2204391,
    "tgn:name":"Buffalo Creek",
    "tgn:placetype":[
        "aat:300008706"
    ]
},
  "bbox": [],
  "geometry": {"coordinates":[-95.7167,37.6667],"type":"Point"}
}