{
  "id": 2273572,
  "type": "Feature",
  "properties": {
    "tgn:hierarchy":[
        "tgn:2273572",
        "tgn:1000001",
        "tgn:7012149",
        "tgn:2001872",
        "tgn:7007825",
        "tgn:7029392"
    ],
    "tgn:id":2273572,
    "tgn:name":"Cypress Slough",
    "tgn:placetype":[
        "aat:300008699"
    ]
},
  "bbox": [],
  "geometry": {"coordinates":[-88.1833,35.3333],"type":"Point"}
}