{
  "id": 7448661,
  "type": "Feature",
  "properties": {
    "tgn:hierarchy":[
        "tgn:7448661",
        "tgn:7002444",
        "tgn:7008074",
        "tgn:1000003",
        "tgn:7008591",
        "tgn:7029392"
    ],
    "tgn:id":7448661,
    "tgn:name:en":"Spango Water",
    "tgn:placetype":[
        "aat:300008699"
    ]
},
  "bbox": [],
  "geometry": {"coordinates":[-3.85,55.433333],"type":"Point"}
}