{
  "id": 1013981,
  "type": "Feature",
  "properties": {
    "tgn:hierarchy":[
        "tgn:1013981",
        "tgn:7005685",
        "tgn:1000001",
        "tgn:7005734",
        "tgn:7029392"
    ],
    "tgn:id":1013981,
    "tgn:name":"Poplar Point",
    "tgn:placetype":[
        "aat:300008347"
    ]
},
  "bbox": [],
  "geometry": {"coordinates":[-97.95,50.0667],"type":"Point"}
}