<<<<<<< HEAD
{
  "id": 7353690,
  "type": "Feature",
  "properties": {
    "tgn:hierarchy":[
        "tgn:7353690",
        "tgn:1001835",
        "tgn:1000001",
        "tgn:7005560",
        "tgn:7029392"
    ],
    "tgn:id":7353690,
    "tgn:name":"\u00c1nimas, Bah\u00eda de las",
    "tgn:placetype":[
        "aat:300132316"
    ]
},
  "bbox": [],
  "geometry": {"coordinates":[-113.333333,28.833333],"type":"Point"}
}
=======
{"geometry":{"type":"Point","coordinates":[-113.333333,28.833333]},"type":"Feature","properties":{"hierarchy":["tgn:7353690","tgn:1001835","tgn:1000001","tgn:7005560","tgn:7029392"],"placetype":["aat:300132316"],"id":7353690,"name:xx":"\u00c1nimas, Bah\u00eda de las"}}
>>>>>>> 03f74aca74312dbeaf24d7e61306dd6a786dc3d0
