{
  "id": 7175914,
  "type": "Feature",
  "properties": {
    "tgn:hierarchy":[
        "tgn:7175914",
        "tgn:1000003",
        "tgn:7003688",
        "tgn:7000084",
        "tgn:7029392"
    ],
    "tgn:id":7175914,
    "tgn:name":"Gro\u00dfen Holz",
    "tgn:placetype":[
        "aat:300008863"
    ]
},
  "bbox": [],
  "geometry": {"coordinates":[10.366667,54.25],"type":"Point"}
}