<<<<<<< HEAD
{
  "id": 2766487,
  "type": "Feature",
  "properties": {
    "tgn:hierarchy":[
        "tgn:2766487",
        "tgn:1000001",
        "tgn:7012149",
        "tgn:2002194",
        "tgn:7007919",
        "tgn:7029392"
    ],
    "tgn:id":2766487,
    "tgn:name":"White Oak Branch",
    "tgn:placetype":[
        "aat:300008699"
    ]
},
  "bbox": [],
  "geometry": {"coordinates":[-81.6833,36.6167],"type":"Point"}
}
=======
{"geometry":{"type":"Point","coordinates":[-81.683300,36.616700]},"type":"Feature","properties":{"hierarchy":["tgn:2766487","tgn:1000001","tgn:7012149","tgn:2002194","tgn:7007919","tgn:7029392"],"placetype":["aat:300008699"],"id":2766487,"name:xx":"White Oak Branch"}}
>>>>>>> 03f74aca74312dbeaf24d7e61306dd6a786dc3d0
