{
  "id": 2766487,
  "type": "Feature",
  "properties": {
    "tgn:hierarchy":[
        "tgn:2766487",
        "tgn:1000001",
        "tgn:7012149",
        "tgn:2002194",
        "tgn:7007919",
        "tgn:7029392"
    ],
    "tgn:id":2766487,
    "tgn:name":"White Oak Branch",
    "tgn:placetype":[
        "aat:300008699"
    ]
},
  "bbox": [],
  "geometry": {"coordinates":[-81.6833,36.6167],"type":"Point"}
}