<<<<<<< HEAD
{
  "id": 7369080,
  "type": "Feature",
  "properties": {
    "tgn:hierarchy":[
        "tgn:7369080",
        "tgn:1000001",
        "tgn:7005599",
        "tgn:7005560",
        "tgn:7029392"
    ],
    "tgn:id":7369080,
    "tgn:name":"Ixmatlahuac\u00e1n",
    "tgn:placetype":[
        "aat:300008347"
    ]
},
  "bbox": [],
  "geometry": {"coordinates":[-95.833333,18.45],"type":"Point"}
}
=======
{"geometry":{"type":"Point","coordinates":[-95.833333,18.450000]},"type":"Feature","properties":{"hierarchy":["tgn:7369080","tgn:1000001","tgn:7005599","tgn:7005560","tgn:7029392"],"placetype":["aat:300008347"],"id":7369080,"name:xx":"Ixmatlahuac\u00e1n"}}
>>>>>>> 03f74aca74312dbeaf24d7e61306dd6a786dc3d0
