{
  "id": 7222363,
  "type": "Feature",
  "properties": {
    "tgn:hierarchy":[
        "tgn:7222363",
        "tgn:4003773",
        "tgn:7001395",
        "tgn:1000003",
        "tgn:1000074",
        "tgn:7029392"
    ],
    "tgn:id":7222363,
    "tgn:name":"Paliokh\u00f3rafa",
    "tgn:placetype":[
        "aat:300008347"
    ]
},
  "bbox": [],
  "geometry": {"coordinates":[21.716667,38.783333],"type":"Point"}
}