{
  "id": 2569896,
  "type": "Feature",
  "properties": {
    "tgn:hierarchy":[
        "tgn:2569896",
        "tgn:1000001",
        "tgn:7012149",
        "tgn:2002114",
        "tgn:7007827",
        "tgn:7029392"
    ],
    "tgn:id":2569896,
    "tgn:name":"Partridge Mountain",
    "tgn:placetype":[
        "aat:300008798"
    ]
},
  "bbox": [],
  "geometry": {"coordinates":[-112.2333,39.3167],"type":"Point"}
}