{
  "id": 7443873,
  "type": "Feature",
  "properties": {
    "tgn:hierarchy":[
        "tgn:7443873",
        "tgn:7002445",
        "tgn:1000003",
        "tgn:7008139",
        "tgn:7008591",
        "tgn:7029392"
    ],
    "tgn:id":7443873,
    "tgn:name:en":"West Stourmouth",
    "tgn:placetype":[
        "aat:300008347"
    ]
},
  "bbox": [],
  "geometry": {"coordinates":[-1.25,51.316667],"type":"Point"}
}