<<<<<<< HEAD
{
  "id": 7117187,
  "type": "Feature",
  "properties": {
    "tgn:hierarchy":[
        "tgn:7117187",
        "tgn:1000003",
        "tgn:7003688",
        "tgn:7000084",
        "tgn:7029392"
    ],
    "tgn:id":7117187,
    "tgn:name":"Naturschutzgebiet Oehe-Schleim\u00fcnde",
    "tgn:placetype":[
        "aat:300008178"
    ]
},
  "bbox": [],
  "geometry": {"coordinates":[10.033333,54.683333],"type":"Point"}
}
=======
{"geometry":{"type":"Point","coordinates":[10.033333,54.683333]},"type":"Feature","properties":{"hierarchy":["tgn:7117187","tgn:1000003","tgn:7003688","tgn:7000084","tgn:7029392"],"placetype":["aat:300008178"],"id":7117187,"name:xx":"Naturschutzgebiet Oehe-Schleim\u00fcnde"}}
>>>>>>> 03f74aca74312dbeaf24d7e61306dd6a786dc3d0
