{
  "id": 2315765,
  "type": "Feature",
  "properties": {
    "tgn:hierarchy":[
        "tgn:2315765",
        "tgn:1000001",
        "tgn:7012149",
        "tgn:2000611",
        "tgn:7007253",
        "tgn:7029392"
    ],
    "tgn:id":2315765,
    "tgn:name":"Ellmaker",
    "tgn:placetype":[
        "aat:300008347"
    ]
},
  "bbox": [],
  "geometry": {"coordinates":[-92.0667,40.9667],"type":"Point"}
}