{
  "id": 7507756,
  "type": "Feature",
  "properties": {
    "tgn:hierarchy":[
        "tgn:7507756",
        "tgn:1009227",
        "tgn:1000226",
        "tgn:7016822",
        "tgn:1000006",
        "tgn:7029392"
    ],
    "tgn:id":7507756,
    "tgn:name:en":"Pisgah, Mount",
    "tgn:placetype":[
        "aat:300008795"
    ]
},
  "bbox": [],
  "geometry": {"coordinates":[167.516667,-45.116667],"type":"Point"}
}