<<<<<<< HEAD
{
  "id": 2336149,
  "type": "Feature",
  "properties": {
    "tgn:hierarchy":[
        "tgn:2336149",
        "tgn:1000001",
        "tgn:7012149",
        "tgn:1002737",
        "tgn:7007520",
        "tgn:7029392"
    ],
    "tgn:id":2336149,
    "tgn:name":"Foster Lake",
    "tgn:placetype":[
        "aat:300008680"
    ]
},
  "bbox": [],
  "geometry": {"coordinates":[-83.45,42.7],"type":"Point"}
}
=======
{"geometry":{"type":"Point","coordinates":[-83.450000,42.700000]},"type":"Feature","properties":{"hierarchy":["tgn:2336149","tgn:1000001","tgn:7012149","tgn:1002737","tgn:7007520","tgn:7029392"],"placetype":["aat:300008680"],"id":2336149,"name:xx":"Foster Lake"}}
>>>>>>> 03f74aca74312dbeaf24d7e61306dd6a786dc3d0
