{
  "id": 2029727,
  "type": "Feature",
  "properties": {
    "tgn:hierarchy":[
        "tgn:2029727",
        "tgn:1000001",
        "tgn:1002187",
        "tgn:7012149",
        "tgn:7007251",
        "tgn:7029392"
    ],
    "tgn:id":2029727,
    "tgn:name":"Poplar Grove",
    "tgn:placetype":[
        "aat:300008347"
    ]
},
  "bbox": [],
  "geometry": {"coordinates":[-88.8167,42.3667],"type":"Point"}
}