{
  "id": 7033830,
  "type": "Feature",
  "properties": {
    "tgn:hierarchy":[
        "tgn:7033830",
        "tgn:1000003",
        "tgn:7003236",
        "tgn:1000080",
        "tgn:7029392"
    ],
    "tgn:id":7033830,
    "tgn:name":"La Sedia, Scoglio",
    "tgn:placetype":[
        "aat:300011692"
    ]
},
  "bbox": [],
  "geometry": {"coordinates":[9.216667,44.316667],"type":"Point"}
}