{
  "id": 2453556,
  "type": "Feature",
  "properties": {
    "tgn:hierarchy":[
        "tgn:2453556",
        "tgn:1000001",
        "tgn:7012149",
        "tgn:2001556",
        "tgn:7007709",
        "tgn:7029392"
    ],
    "tgn:id":2453556,
    "tgn:name":"Little Cole Mountain",
    "tgn:placetype":[
        "aat:300008798"
    ]
},
  "bbox": [],
  "geometry": {"coordinates":[-82.2167,35.8667],"type":"Point"}
}