{
  "id": 2254639,
  "type": "Feature",
  "properties": {
    "tgn:hierarchy":[
        "tgn:2254639",
        "tgn:1000001",
        "tgn:7012149",
        "tgn:1002646",
        "tgn:7007826",
        "tgn:7029392"
    ],
    "tgn:id":2254639,
    "tgn:name":"Coon Island",
    "tgn:placetype":[
        "aat:300008791"
    ]
},
  "bbox": [],
  "geometry": {"coordinates":[-96.2167,28.65],"type":"Point"}
}