{
  "id": 7380906,
  "type": "Feature",
  "properties": {
    "tgn:hierarchy":[
        "tgn:7380906",
        "tgn:1000001",
        "tgn:1001960",
        "tgn:7005560",
        "tgn:7029392"
    ],
    "tgn:id":7380906,
    "tgn:name":"Los \u00c1lamos",
    "tgn:placetype":[
        "aat:300008347"
    ]
},
  "bbox": [],
  "geometry": {"coordinates":[-111.416667,31.25],"type":"Point"}
}