{
  "id": 2089315,
  "type": "Feature",
  "properties": {
    "tgn:hierarchy":[
        "tgn:2089315",
        "tgn:1000001",
        "tgn:7012149",
        "tgn:1002612",
        "tgn:7007710",
        "tgn:7029392"
    ],
    "tgn:id":2089315,
    "tgn:name":"Hilldale",
    "tgn:placetype":[
        "aat:300008347"
    ]
},
  "bbox": [],
  "geometry": {"coordinates":[-75.8333,41.2833],"type":"Point"}
}