{
  "id": 2317826,
  "type": "Feature",
  "properties": {
    "tgn:hierarchy":[
        "tgn:2317826",
        "tgn:1000001",
        "tgn:7012149",
        "tgn:7007157",
        "tgn:2000187",
        "tgn:7029392"
    ],
    "tgn:id":2317826,
    "tgn:name":"English Bar",
    "tgn:placetype":[
        "aat:300132348"
    ]
},
  "bbox": [],
  "geometry": {"coordinates":[-120.8167,39.8667],"type":"Point"}
}