{
  "id": 7263094,
  "type": "Feature",
  "properties": {
    "tgn:concordances":{
        "gn:id":"2757746"
    },
    "tgn:hierarchy":[
        "tgn:7263094",
        "tgn:1000003",
        "tgn:7003622",
        "tgn:7016845",
        "tgn:7029392"
    ],
    "tgn:id":7263094,
    "tgn:name:nl":"De Bramert",
    "tgn:placetype":[
        "aat:300008347"
    ]
},
  "bbox": [],
  "geometry": {"coordinates":[5.783333,50.983333],"type":"Point"}
}