{
  "id": 2130153,
  "type": "Feature",
  "properties": {
    "tgn:hierarchy":[
        "tgn:2130153",
        "tgn:7002659",
        "tgn:1000001",
        "tgn:7012149",
        "tgn:2000066",
        "tgn:7029392"
    ],
    "tgn:id":2130153,
    "tgn:name":"Allen Mill Creek",
    "tgn:placetype":[
        "aat:300008706"
    ]
},
  "bbox": [],
  "geometry": {"coordinates":[-87.5667,34.25],"type":"Point"}
}