{
  "id": 7474734,
  "type": "Feature",
  "properties": {
    "tgn:hierarchy":[
        "tgn:7474734",
        "tgn:1000004",
        "tgn:7492971",
        "tgn:1000141",
        "tgn:7029392"
    ],
    "tgn:id":7474734,
    "tgn:name":"Yonglong",
    "tgn:placetype":[
        "aat:300008347"
    ]
},
  "bbox": [],
  "geometry": {"coordinates":[120.518747,22.7535],"type":"Point"}
}