<<<<<<< HEAD
{
  "id": 7474734,
  "type": "Feature",
  "properties": {
    "tgn:hierarchy":[
        "tgn:7474734",
        "tgn:1000004",
        "tgn:7492971",
        "tgn:1000141",
        "tgn:7029392"
    ],
    "tgn:id":7474734,
    "tgn:name":"Yonglong",
    "tgn:placetype":[
        "aat:300008347"
    ]
},
  "bbox": [],
  "geometry": {"coordinates":[120.518747,22.7535],"type":"Point"}
}
=======
{"geometry":{"type":"Point","coordinates":[120.518747,22.753500]},"type":"Feature","properties":{"hierarchy":["tgn:7474734","tgn:1000004","tgn:7492971","tgn:1000141","tgn:7029392"],"placetype":["aat:300008347"],"id":7474734,"name:xx":"Yonglong"}}
>>>>>>> 03f74aca74312dbeaf24d7e61306dd6a786dc3d0
