{
  "id": 7545305,
  "type": "Feature",
  "properties": {
    "tgn:hierarchy":[
        "tgn:7545305",
        "tgn:1000004",
        "tgn:1001992",
        "tgn:7000198",
        "tgn:7029392"
    ],
    "tgn:id":7545305,
    "tgn:name:en":"Amb\u0101b\u0101ri",
    "tgn:placetype":[
        "aat:300008347"
    ]
},
  "bbox": [],
  "geometry": {"coordinates":[73.15,20.166667],"type":"Point"}
}