{
  "id": 2430561,
  "type": "Feature",
  "properties": {
    "tgn:hierarchy":[
        "tgn:2430561",
        "tgn:1000001",
        "tgn:7012149",
        "tgn:2000814",
        "tgn:7007255",
        "tgn:7029392"
    ],
    "tgn:id":2430561,
    "tgn:name":"Kalberer Quarry",
    "tgn:placetype":[
        "aat:300000390"
    ]
},
  "bbox": [],
  "geometry": {"coordinates":[-88.3667,37.1333],"type":"Point"}
}