{
  "id": 7380373,
  "type": "Feature",
  "properties": {
    "tgn:hierarchy":[
        "tgn:7380373",
        "tgn:7005586",
        "tgn:1000001",
        "tgn:7005560",
        "tgn:7029392"
    ],
    "tgn:id":7380373,
    "tgn:name":"Los Hornitos",
    "tgn:placetype":[
        "aat:300008347"
    ]
},
  "bbox": [],
  "geometry": {"coordinates":[-104.183333,20.733333],"type":"Point"}
}