{
  "id": 2603807,
  "type": "Feature",
  "properties": {
    "tgn:hierarchy":[
        "tgn:2603807",
        "tgn:1000001",
        "tgn:2001410",
        "tgn:7012149",
        "tgn:7007526",
        "tgn:7029392"
    ],
    "tgn:id":2603807,
    "tgn:name":"Quiet Cove",
    "tgn:placetype":[
        "aat:300132316"
    ]
},
  "bbox": [],
  "geometry": {"coordinates":[-114.7333,36.1333],"type":"Point"}
}