{
  "id": 7255429,
  "type": "Feature",
  "properties": {
    "tgn:hierarchy":[
        "tgn:7255429",
        "tgn:7018239",
        "tgn:1000003",
        "tgn:1000063",
        "tgn:7018236",
        "tgn:7029392"
    ],
    "tgn:id":7255429,
    "tgn:name":"Rommersom",
    "tgn:placetype":[
        "aat:300008347"
    ]
},
  "bbox": [],
  "geometry": {"coordinates":[4.899359,50.781959],"type":"Point"}
}