{
  "id": 2070698,
  "type": "Feature",
  "properties": {
    "tgn:hierarchy":[
        "tgn:2070698",
        "tgn:1000001",
        "tgn:7012149",
        "tgn:1002708",
        "tgn:7007568",
        "tgn:7029392"
    ],
    "tgn:id":2070698,
    "tgn:name":"Muttontown",
    "tgn:placetype":[
        "aat:300008347"
    ]
},
  "bbox": [],
  "geometry": {"coordinates":[-73.5333,40.8167],"type":"Point"}
}