{
  "id": 2211089,
  "type": "Feature",
  "properties": {
    "tgn:hierarchy":[
        "tgn:2211089",
        "tgn:1000001",
        "tgn:7006451",
        "tgn:7012149",
        "tgn:2000104",
        "tgn:7029392"
    ],
    "tgn:id":2211089,
    "tgn:name":"Butler Mountains",
    "tgn:placetype":[
        "aat:300008798"
    ]
},
  "bbox": [],
  "geometry": {"coordinates":[-114.2333,32.3833],"type":"Point"}
}