{
  "id": 2021373,
  "type": "Feature",
  "properties": {
    "tgn:hierarchy":[
        "tgn:2021373",
        "tgn:1000001",
        "tgn:7012149",
        "tgn:2000290",
        "tgn:7007240",
        "tgn:7029392"
    ],
    "tgn:id":2021373,
    "tgn:name":"Steele Church",
    "tgn:placetype":[
        "aat:300008347",
        "aat:300387210"
    ]
},
  "bbox": [],
  "geometry": {"coordinates":[-86.1333,30.6333],"type":"Point"}
}