{
  "id": 7126533,
  "type": "Feature",
  "properties": {
    "tgn:hierarchy":[
        "tgn:7126533",
        "tgn:1000003",
        "tgn:7000094",
        "tgn:7000084",
        "tgn:7029392"
    ],
    "tgn:id":7126533,
    "tgn:name":"Oberhof",
    "tgn:placetype":[
        "aat:300008347"
    ]
},
  "bbox": [],
  "geometry": {"coordinates":[11.233333,53.95],"type":"Point"}
}