{
  "id": 7043888,
  "type": "Feature",
  "properties": {
    "tgn:hierarchy":[
        "tgn:7043888",
        "tgn:7003137",
        "tgn:1000003",
        "tgn:7003080",
        "tgn:1000080",
        "tgn:7029392"
    ],
    "tgn:id":7043888,
    "tgn:name":"Croce, Monte",
    "tgn:placetype":[
        "aat:300008795"
    ]
},
  "bbox": [],
  "geometry": {"coordinates":[12.983333,42.116667],"type":"Point"}
}