{
  "id": 7403200,
  "type": "Feature",
  "properties": {
    "tgn:hierarchy":[
        "tgn:7403200",
        "tgn:1000001",
        "tgn:7005600",
        "tgn:7005560",
        "tgn:7029392"
    ],
    "tgn:id":7403200,
    "tgn:name":"Millet",
    "tgn:placetype":[
        "aat:300008347"
    ]
},
  "bbox": [],
  "geometry": {"coordinates":[-89.383333,20.975],"type":"Point"}
}