{
  "id": 1012087,
  "type": "Feature",
  "properties": {
    "tgn:hierarchy":[
        "tgn:1012087",
        "tgn:1007857",
        "tgn:1010116",
        "tgn:1000223",
        "tgn:1000006",
        "tgn:7029392"
    ],
    "tgn:id":1012087,
    "tgn:name":"Lef\u00e8vre, Pointe",
    "tgn:placetype":[
        "aat:300386846"
    ]
},
  "bbox": [],
  "geometry": {"coordinates":[167.0167,-20.9167],"type":"Point"}
}