{
  "id": 2316872,
  "type": "Feature",
  "properties": {
    "tgn:hierarchy":[
        "tgn:2316872",
        "tgn:1000001",
        "tgn:7012149",
        "tgn:1002514",
        "tgn:7007251",
        "tgn:7029392"
    ],
    "tgn:id":2316872,
    "tgn:name":"Emerson City",
    "tgn:placetype":[
        "aat:300008347"
    ]
},
  "bbox": [],
  "geometry": {"coordinates":[-89.0333,38.1333],"type":"Point"}
}