{
  "id": 2118764,
  "type": "Feature",
  "properties": {
    "tgn:hierarchy":[
        "tgn:2118764",
        "tgn:1000001",
        "tgn:7012149",
        "tgn:2002275",
        "tgn:7013961",
        "tgn:7029392"
    ],
    "tgn:id":2118764,
    "tgn:name":"Jordan",
    "tgn:placetype":[
        "aat:300008347",
        "aat:300387210"
    ]
},
  "bbox": [],
  "geometry": {"coordinates":[-80.0667,39.5333],"type":"Point"}
}