{
  "id": 2194603,
  "type": "Feature",
  "properties": {
    "tgn:hierarchy":[
        "tgn:2194603",
        "tgn:1000001",
        "tgn:7012149",
        "tgn:1002441",
        "tgn:7007706",
        "tgn:7029392"
    ],
    "tgn:id":2194603,
    "tgn:name":"Bridgeview Harbor",
    "tgn:placetype":[
        "aat:300008678"
    ]
},
  "bbox": [],
  "geometry": {"coordinates":[-84.4167,39.05],"type":"Point"}
}