<<<<<<< HEAD
{
  "id": 2150548,
  "type": "Feature",
  "properties": {
    "tgn:hierarchy":[
        "tgn:2150548",
        "tgn:1000001",
        "tgn:7006451",
        "tgn:2000092",
        "tgn:7012149",
        "tgn:7029392"
    ],
    "tgn:id":2150548,
    "tgn:name":"Basin Tank",
    "tgn:placetype":[
        "aat:300006191"
    ]
},
  "bbox": [],
  "geometry": {"coordinates":[-111.25,34.6],"type":"Point"}
}
=======
{"geometry":{"type":"Point","coordinates":[-111.250000,34.600000]},"type":"Feature","properties":{"hierarchy":["tgn:2150548","tgn:1000001","tgn:7006451","tgn:2000092","tgn:7012149","tgn:7029392"],"placetype":["aat:300006191"],"id":2150548,"name:xx":"Basin Tank"}}
>>>>>>> 03f74aca74312dbeaf24d7e61306dd6a786dc3d0
