{
  "id": 7217641,
  "type": "Feature",
  "properties": {
    "tgn:hierarchy":[
        "tgn:7217641",
        "tgn:7011164",
        "tgn:7002674",
        "tgn:1000003",
        "tgn:1000074",
        "tgn:7029392"
    ],
    "tgn:id":7217641,
    "tgn:name":"Tr\u00edton, Vr\u00e1chos",
    "tgn:placetype":[
        "aat:300011692"
    ]
},
  "bbox": [],
  "geometry": {"coordinates":[26.787778,37.636667],"type":"Point"}
}