{
  "id": 1088109,
  "type": "Feature",
  "properties": {
    "tgn:hierarchy":[
        "tgn:1088109",
        "tgn:1000824",
        "tgn:7001242",
        "tgn:1000150",
        "tgn:7029392"
    ],
    "tgn:id":1088109,
    "tgn:name":"Serowe",
    "tgn:placetype":[
        "aat:300008347",
        "aat:300387222"
    ]
},
  "bbox": [],
  "geometry": {"coordinates":[26.7333,-22.4167],"type":"Point"}
}