{
  "id": 7571627,
  "type": "Feature",
  "properties": {
    "tgn:hierarchy":[
        "tgn:7571627",
        "tgn:1000004",
        "tgn:7000198",
        "tgn:1001894",
        "tgn:7029392"
    ],
    "tgn:id":7571627,
    "tgn:name:en":"Hatni River",
    "tgn:placetype":[
        "aat:300008699"
    ]
},
  "bbox": [],
  "geometry": {"coordinates":[74.453787,22.03872],"type":"Point"}
}