{
  "id": 7367920,
  "type": "Feature",
  "properties": {
    "tgn:hierarchy":[
        "tgn:7367920",
        "tgn:1000001",
        "tgn:7005590",
        "tgn:7005560",
        "tgn:7029392"
    ],
    "tgn:id":7367920,
    "tgn:name":"El Salto",
    "tgn:placetype":[
        "aat:300008347"
    ]
},
  "bbox": [],
  "geometry": {"coordinates":[-102.116667,20.166667],"type":"Point"}
}