{
  "id": 2695314,
  "type": "Feature",
  "properties": {
    "tgn:hierarchy":[
        "tgn:2695314",
        "tgn:1000001",
        "tgn:7012149",
        "tgn:7007157",
        "tgn:7014516",
        "tgn:7029392"
    ],
    "tgn:id":2695314,
    "tgn:name":"Stillwater Cove",
    "tgn:placetype":[
        "aat:300132316"
    ]
},
  "bbox": [],
  "geometry": {"coordinates":[-123.2833,38.5333],"type":"Point"}
}