{
  "id": 2038368,
  "type": "Feature",
  "properties": {
    "tgn:hierarchy":[
        "tgn:2038368",
        "tgn:1000001",
        "tgn:7012149",
        "tgn:2000841",
        "tgn:7007255",
        "tgn:7029392"
    ],
    "tgn:id":2038368,
    "tgn:name":"Creelsboro",
    "tgn:placetype":[
        "aat:300008347",
        "aat:300387210"
    ]
},
  "bbox": [],
  "geometry": {"coordinates":[-85.1833,36.8833],"type":"Point"}
}