{
  "id": 7393843,
  "type": "Feature",
  "properties": {
    "tgn:hierarchy":[
        "tgn:7393843",
        "tgn:7005581",
        "tgn:1000001",
        "tgn:7005560",
        "tgn:7029392"
    ],
    "tgn:id":7393843,
    "tgn:name":"San Francisco del Mezquital",
    "tgn:placetype":[
        "aat:300008347"
    ]
},
  "bbox": [],
  "geometry": {"coordinates":[-105.266667,27.983333],"type":"Point"}
}