<<<<<<< HEAD
{
  "id": 7480812,
  "type": "Feature",
  "properties": {
    "tgn:hierarchy":[
        "tgn:7480812",
        "tgn:1000004",
        "tgn:1000454",
        "tgn:1000141",
        "tgn:7029392"
    ],
    "tgn:id":7480812,
    "tgn:name":"Zhonghe Diliu Gongmu",
    "tgn:placetype":[
        "aat:300266755"
    ]
},
  "bbox": [],
  "geometry": {"coordinates":[121.47869,25.003464],"type":"Point"}
}
=======
{"geometry":{"type":"Point","coordinates":[121.478690,25.003464]},"type":"Feature","properties":{"hierarchy":["tgn:7480812","tgn:1000004","tgn:1000454","tgn:1000141","tgn:7029392"],"placetype":["aat:300266755"],"id":7480812,"name:xx":"Zhonghe Diliu Gongmu"}}
>>>>>>> 03f74aca74312dbeaf24d7e61306dd6a786dc3d0
