{
  "id": 2603971,
  "type": "Feature",
  "properties": {
    "tgn:hierarchy":[
        "tgn:2603971",
        "tgn:1000001",
        "tgn:7012149",
        "tgn:1002460",
        "tgn:7007826",
        "tgn:7029392"
    ],
    "tgn:id":2603971,
    "tgn:name":"Quiney",
    "tgn:placetype":[
        "aat:300008347"
    ]
},
  "bbox": [],
  "geometry": {"coordinates":[-94.4167,32.5167],"type":"Point"}
}