{
  "id": 2044610,
  "type": "Feature",
  "properties": {
    "tgn:hierarchy":[
        "tgn:2044610",
        "tgn:2000919",
        "tgn:1000001",
        "tgn:7012149",
        "tgn:7007515",
        "tgn:7029392"
    ],
    "tgn:id":2044610,
    "tgn:name":"Chapman",
    "tgn:placetype":[
        "aat:300008347"
    ]
},
  "bbox": [],
  "geometry": {"coordinates":[-68.15,46.6333],"type":"Point"}
}