{
  "id": 2386872,
  "type": "Feature",
  "properties": {
    "tgn:hierarchy":[
        "tgn:2386872",
        "tgn:1000001",
        "tgn:7012149",
        "tgn:1002924",
        "tgn:7007568",
        "tgn:7029392"
    ],
    "tgn:id":2386872,
    "tgn:name":"Herod Point Shoal",
    "tgn:placetype":[
        "aat:300132348"
    ]
},
  "bbox": [],
  "geometry": {"coordinates":[-72.8333,40.9667],"type":"Point"}
}