{
  "id": 7439307,
  "type": "Feature",
  "properties": {
    "tgn:hierarchy":[
        "tgn:7439307",
        "tgn:1000001",
        "tgn:7005601",
        "tgn:7005560",
        "tgn:7029392"
    ],
    "tgn:id":7439307,
    "tgn:name":"Tecolotla",
    "tgn:placetype":[
        "aat:300008347"
    ]
},
  "bbox": [],
  "geometry": {"coordinates":[-96.933333,18.583333],"type":"Point"}
}