{
  "id": 1094302,
  "type": "Feature",
  "properties": {
    "tgn:hierarchy":[
        "tgn:1094302",
        "tgn:7001242",
        "tgn:1001082",
        "tgn:7441551",
        "tgn:7029392"
    ],
    "tgn:id":1094302,
    "tgn:name":"Keyala",
    "tgn:placetype":[
        "aat:300008347"
    ]
},
  "bbox": [],
  "geometry": {"coordinates":[32.8667,4.45],"type":"Point"}
}