{
  "id": 2782904,
  "type": "Feature",
  "properties": {
    "tgn:hierarchy":[
        "tgn:2782904",
        "tgn:1000001",
        "tgn:7012149",
        "tgn:2002191",
        "tgn:7007919",
        "tgn:7029392"
    ],
    "tgn:id":2782904,
    "tgn:name":"Worthy Mine",
    "tgn:placetype":[
        "aat:300000390"
    ]
},
  "bbox": [],
  "geometry": {"coordinates":[-81.6667,36.8667],"type":"Point"}
}