{
  "id": 1129271,
  "type": "Feature",
  "properties": {
    "tgn:hierarchy":[
        "tgn:1129271",
        "tgn:7002871",
        "tgn:1000003",
        "tgn:1000070",
        "tgn:7029392"
    ],
    "tgn:id":1129271,
    "tgn:name":"S\u00e9nouire",
    "tgn:placetype":[
        "aat:300008707"
    ]
},
  "bbox": [],
  "geometry": {"coordinates":[3.4167,45.25],"type":"Point"}
}