{
  "id": 7212891,
  "type": "Feature",
  "properties": {
    "tgn:hierarchy":[
        "tgn:7212891",
        "tgn:1000003",
        "tgn:7003685",
        "tgn:7000084",
        "tgn:7029392"
    ],
    "tgn:id":7212891,
    "tgn:name":"Bienenholz",
    "tgn:placetype":[
        "aat:300008863"
    ]
},
  "bbox": [],
  "geometry": {"coordinates":[13.516667,50.75],"type":"Point"}
}