{
  "id": 7537189,
  "type": "Feature",
  "properties": {
    "tgn:hierarchy":[
        "tgn:7537189",
        "tgn:7001242",
        "tgn:7016833",
        "tgn:7001334",
        "tgn:7029392"
    ],
    "tgn:id":7537189,
    "tgn:name:en":"Qurta",
    "tgn:placetype":[
        "aat:300055621"
    ]
},
  "bbox": [],
  "geometry": {"coordinates":[32.616667,23.15],"type":"Point"}
}