{
  "id": 2442404,
  "type": "Feature",
  "properties": {
    "tgn:hierarchy":[
        "tgn:2442404",
        "tgn:1000001",
        "tgn:7012149",
        "tgn:1002552",
        "tgn:7007920",
        "tgn:7029392"
    ],
    "tgn:id":2442404,
    "tgn:name":"Kriegler Lake",
    "tgn:placetype":[
        "aat:300008680"
    ]
},
  "bbox": [],
  "geometry": {"coordinates":[-122.75,47.45],"type":"Point"}
}