{
  "id": 2233301,
  "type": "Feature",
  "properties": {
    "tgn:hierarchy":[
        "tgn:2233301",
        "tgn:7006450",
        "tgn:1000001",
        "tgn:7012149",
        "tgn:7019760",
        "tgn:7029392"
    ],
    "tgn:id":2233301,
    "tgn:name":"Charley Glacier",
    "tgn:placetype":[
        "aat:300008835"
    ]
},
  "bbox": [],
  "geometry": {"coordinates":[-137.15,58.85],"type":"Point"}
}