{
  "id": 1064966,
  "type": "Feature",
  "properties": {
    "tgn:hierarchy":[
        "tgn:1064966",
        "tgn:7017299",
        "tgn:1000003",
        "tgn:7006663",
        "tgn:7029392"
    ],
    "tgn:id":1064966,
    "tgn:name":"Crikvenica",
    "tgn:placetype":[
        "aat:300008347"
    ]
},
  "bbox": [],
  "geometry": {"coordinates":[14.6667,45.1833],"type":"Point"}
}