{
  "id": 2222380,
  "type": "Feature",
  "properties": {
    "tgn:hierarchy":[
        "tgn:2222380",
        "tgn:1000001",
        "tgn:7012149",
        "tgn:2000975",
        "tgn:7007520",
        "tgn:7029392"
    ],
    "tgn:id":2222380,
    "tgn:name":"Carp River Lake",
    "tgn:placetype":[
        "aat:300006191"
    ]
},
  "bbox": [],
  "geometry": {"coordinates":[-87.45,46.4833],"type":"Point"}
}