<<<<<<< HEAD
{
  "id": 7171990,
  "type": "Feature",
  "properties": {
    "tgn:hierarchy":[
        "tgn:7171990",
        "tgn:7000096",
        "tgn:1000003",
        "tgn:7000084",
        "tgn:7029392"
    ],
    "tgn:id":7171990,
    "tgn:name":"Hinzhof",
    "tgn:placetype":[
        "aat:300000206"
    ]
},
  "bbox": [],
  "geometry": {"coordinates":[13.75,53.433333],"type":"Point"}
}
=======
{"geometry":{"type":"Point","coordinates":[13.750000,53.433333]},"type":"Feature","properties":{"hierarchy":["tgn:7171990","tgn:7000096","tgn:1000003","tgn:7000084","tgn:7029392"],"placetype":["aat:300000206"],"id":7171990,"name:xx":"Hinzhof"}}
>>>>>>> 03f74aca74312dbeaf24d7e61306dd6a786dc3d0
