{
  "id": 7171990,
  "type": "Feature",
  "properties": {
    "tgn:hierarchy":[
        "tgn:7171990",
        "tgn:7000096",
        "tgn:1000003",
        "tgn:7000084",
        "tgn:7029392"
    ],
    "tgn:id":7171990,
    "tgn:name":"Hinzhof",
    "tgn:placetype":[
        "aat:300000206"
    ]
},
  "bbox": [],
  "geometry": {"coordinates":[13.75,53.433333],"type":"Point"}
}