{
  "id": 2040561,
  "type": "Feature",
  "properties": {
    "tgn:hierarchy":[
        "tgn:2040561",
        "tgn:1000001",
        "tgn:7012149",
        "tgn:2000839",
        "tgn:7007255",
        "tgn:7029392"
    ],
    "tgn:id":2040561,
    "tgn:name":"Oak Hill",
    "tgn:placetype":[
        "aat:300008347",
        "aat:300387210"
    ]
},
  "bbox": [],
  "geometry": {"coordinates":[-84.6333,37.05],"type":"Point"}
}