{
  "id": 1076507,
  "type": "Feature",
  "properties": {
    "tgn:hierarchy":[
        "tgn:1076507",
        "tgn:1000004",
        "tgn:7000198",
        "tgn:1001894",
        "tgn:7029392"
    ],
    "tgn:id":1076507,
    "tgn:name:en":"Pachmarh\u012b",
    "tgn:placetype":[
        "aat:300008347"
    ]
},
  "bbox": [],
  "geometry": {"coordinates":[78.433702,22.470446],"type":"Point"}
}