{
  "id": 1076555,
  "type": "Feature",
  "properties": {
    "tgn:hierarchy":[
        "tgn:1076555",
        "tgn:1000004",
        "tgn:7000198",
        "tgn:7016788",
        "tgn:7029392"
    ],
    "tgn:id":1076555,
    "tgn:name:en":"Parsad",
    "tgn:placetype":[
        "aat:300008347"
    ]
},
  "bbox": [],
  "geometry": {"coordinates":[73.709278,24.194256],"type":"Point"}
}