{
  "id": 2552353,
  "type": "Feature",
  "properties": {
    "tgn:hierarchy":[
        "tgn:2552353",
        "tgn:1000001",
        "tgn:2001737",
        "tgn:7012149",
        "tgn:7007712",
        "tgn:7029392"
    ],
    "tgn:id":2552353,
    "tgn:name":"Number Twelve, Lake",
    "tgn:placetype":[
        "aat:300006191"
    ]
},
  "bbox": [],
  "geometry": {"coordinates":[-80.2167,34.5667],"type":"Point"}
}