<<<<<<< HEAD
{
  "id": 2331195,
  "type": "Feature",
  "properties": {
    "tgn:hierarchy":[
        "tgn:2331195",
        "tgn:7002659",
        "tgn:1000001",
        "tgn:7012149",
        "tgn:2000036",
        "tgn:7029392"
    ],
    "tgn:id":2331195,
    "tgn:name":"Flat Top Mine Number 1 Impoundment",
    "tgn:placetype":[
        "aat:300006191"
    ]
},
  "bbox": [],
  "geometry": {"coordinates":[-87.0167,33.65],"type":"Point"}
}
=======
{"geometry":{"type":"Point","coordinates":[-87.016700,33.650000]},"type":"Feature","properties":{"hierarchy":["tgn:2331195","tgn:7002659","tgn:1000001","tgn:7012149","tgn:2000036","tgn:7029392"],"placetype":["aat:300006191"],"id":2331195,"name:xx":"Flat Top Mine Number 1 Impoundment"}}
>>>>>>> 03f74aca74312dbeaf24d7e61306dd6a786dc3d0
