{
  "id": 7136872,
  "type": "Feature",
  "properties": {
    "tgn:hierarchy":[
        "tgn:7136872",
        "tgn:1000003",
        "tgn:7003685",
        "tgn:7000084",
        "tgn:7029392"
    ],
    "tgn:id":7136872,
    "tgn:name":"Talsperre Lehnm\u00fchle",
    "tgn:placetype":[
        "aat:300006191"
    ]
},
  "bbox": [],
  "geometry": {"coordinates":[13.583333,50.816667],"type":"Point"}
}