{
  "id": 7164563,
  "type": "Feature",
  "properties": {
    "tgn:hierarchy":[
        "tgn:7164563",
        "tgn:7003669",
        "tgn:1000003",
        "tgn:7000084",
        "tgn:7029392"
    ],
    "tgn:id":7164563,
    "tgn:name":"Hungenberg",
    "tgn:placetype":[
        "aat:300008347"
    ]
},
  "bbox": [],
  "geometry": {"coordinates":[12.266667,49.95],"type":"Point"}
}