{
  "id": 2243506,
  "type": "Feature",
  "properties": {
    "tgn:hierarchy":[
        "tgn:2243506",
        "tgn:7006450",
        "tgn:1000001",
        "tgn:7019674",
        "tgn:7012149",
        "tgn:7029392"
    ],
    "tgn:id":2243506,
    "tgn:name":"Cleary Hill Mine",
    "tgn:placetype":[
        "aat:300000390"
    ]
},
  "bbox": [],
  "geometry": {"coordinates":[-147.4333,65.0667],"type":"Point"}
}