{
  "id": 2136910,
  "type": "Feature",
  "properties": {
    "tgn:hierarchy":[
        "tgn:2136910",
        "tgn:1000001",
        "tgn:7012149",
        "tgn:7007827",
        "tgn:7029392"
    ],
    "tgn:id":2136910,
    "tgn:name":"Argyle Ridge",
    "tgn:placetype":[
        "aat:300266640"
    ]
},
  "bbox": [],
  "geometry": {"coordinates":[-110.55,39.8333],"type":"Point"}
}