<<<<<<< HEAD
{
  "id": 7171030,
  "type": "Feature",
  "properties": {
    "tgn:hierarchy":[
        "tgn:7171030",
        "tgn:1000003",
        "tgn:7003677",
        "tgn:7000084",
        "tgn:7029392"
    ],
    "tgn:id":7171030,
    "tgn:name":"Hirschley",
    "tgn:placetype":[
        "aat:300132356"
    ]
},
  "bbox": [],
  "geometry": {"coordinates":[6.416667,50.616667],"type":"Point"}
}
=======
{"geometry":{"type":"Point","coordinates":[6.416667,50.616667]},"type":"Feature","properties":{"hierarchy":["tgn:7171030","tgn:1000003","tgn:7003677","tgn:7000084","tgn:7029392"],"placetype":["aat:300132356"],"id":7171030,"name:xx":"Hirschley"}}
>>>>>>> 03f74aca74312dbeaf24d7e61306dd6a786dc3d0
