{
  "id": 2226171,
  "type": "Feature",
  "properties": {
    "tgn:hierarchy":[
        "tgn:2226171",
        "tgn:1000001",
        "tgn:7012149",
        "tgn:7022542",
        "tgn:7007825",
        "tgn:7029392"
    ],
    "tgn:id":2226171,
    "tgn:name":"Cate Spring",
    "tgn:placetype":[
        "aat:300008697"
    ]
},
  "bbox": [],
  "geometry": {"coordinates":[-84.6667,35.4167],"type":"Point"}
}