{
  "id": 2398339,
  "type": "Feature",
  "properties": {
    "tgn:hierarchy":[
        "tgn:2398339",
        "tgn:1000001",
        "tgn:7012149",
        "tgn:2002156",
        "tgn:7007919",
        "tgn:7029392"
    ],
    "tgn:id":2398339,
    "tgn:name":"Hooper Rock Creek",
    "tgn:placetype":[
        "aat:300008706"
    ]
},
  "bbox": [],
  "geometry": {"coordinates":[-78.1667,37.7167],"type":"Point"}
}