<<<<<<< HEAD
{
  "id": 2332303,
  "type": "Feature",
  "properties": {
    "tgn:hierarchy":[
        "tgn:2332303",
        "tgn:1000001",
        "tgn:7012149",
        "tgn:2002348",
        "tgn:7007922",
        "tgn:7029392"
    ],
    "tgn:id":2332303,
    "tgn:name":"Flood Creek",
    "tgn:placetype":[
        "aat:300008706"
    ]
},
  "bbox": [],
  "geometry": {"coordinates":[-90.5333,45.9167],"type":"Point"}
}
=======
{"geometry":{"type":"Point","coordinates":[-90.533300,45.916700]},"type":"Feature","properties":{"hierarchy":["tgn:2332303","tgn:1000001","tgn:7012149","tgn:2002348","tgn:7007922","tgn:7029392"],"placetype":["aat:300008706"],"id":2332303,"name:xx":"Flood Creek"}}
>>>>>>> 03f74aca74312dbeaf24d7e61306dd6a786dc3d0
