{
  "id": 7389202,
  "type": "Feature",
  "properties": {
    "tgn:hierarchy":[
        "tgn:7389202",
        "tgn:1000001",
        "tgn:7005600",
        "tgn:7005560",
        "tgn:7029392"
    ],
    "tgn:id":7389202,
    "tgn:name":"Sahcab\u00e1",
    "tgn:placetype":[
        "aat:300008347"
    ]
},
  "bbox": [],
  "geometry": {"coordinates":[-88.283333,20.433333],"type":"Point"}
}