<<<<<<< HEAD
{
  "id": 7021351,
  "type": "Feature",
  "properties": {
    "tgn:hierarchy":[
        "tgn:7021351",
        "tgn:1000001",
        "tgn:7012149",
        "tgn:2002291",
        "tgn:7013961",
        "tgn:7029392"
    ],
    "tgn:id":7021351,
    "tgn:name":"Falls Run",
    "tgn:placetype":[
        "aat:300008699"
    ]
},
  "bbox": [],
  "geometry": {"coordinates":[-79.55,38.75],"type":"Point"}
}
=======
{"geometry":{"type":"Point","coordinates":[-79.550000,38.750000]},"type":"Feature","properties":{"hierarchy":["tgn:7021351","tgn:1000001","tgn:7012149","tgn:2002291","tgn:7013961","tgn:7029392"],"placetype":["aat:300008699"],"id":7021351,"name:xx":"Falls Run"}}
>>>>>>> 03f74aca74312dbeaf24d7e61306dd6a786dc3d0
