{
  "id": 2313922,
  "type": "Feature",
  "properties": {
    "tgn:hierarchy":[
        "tgn:2313922",
        "tgn:1000001",
        "tgn:1002665",
        "tgn:7012149",
        "tgn:7007517",
        "tgn:7029392"
    ],
    "tgn:id":2313922,
    "tgn:name":"Eliot Hill",
    "tgn:placetype":[
        "aat:300008798"
    ]
},
  "bbox": [],
  "geometry": {"coordinates":[-71.3333,42.25],"type":"Point"}
}