{
  "id": 2553679,
  "type": "Feature",
  "properties": {
    "tgn:hierarchy":[
        "tgn:2553679",
        "tgn:1000001",
        "tgn:7012149",
        "tgn:2000205",
        "tgn:7007158",
        "tgn:7029392"
    ],
    "tgn:id":2553679,
    "tgn:name":"Oak Grove Mountain",
    "tgn:placetype":[
        "aat:300008798"
    ]
},
  "bbox": [],
  "geometry": {"coordinates":[-105.4833,38.2333],"type":"Point"}
}