<<<<<<< HEAD
{
  "id": 7374190,
  "type": "Feature",
  "properties": {
    "tgn:hierarchy":[
        "tgn:7374190",
        "tgn:7005586",
        "tgn:1000001",
        "tgn:7005560",
        "tgn:7029392"
    ],
    "tgn:id":7374190,
    "tgn:name":"Laguna Colorada",
    "tgn:placetype":[
        "aat:300000241"
    ]
},
  "bbox": [],
  "geometry": {"coordinates":[-102.816667,20.75],"type":"Point"}
}
=======
{"geometry":{"type":"Point","coordinates":[-102.816667,20.750000]},"type":"Feature","properties":{"hierarchy":["tgn:7374190","tgn:7005586","tgn:1000001","tgn:7005560","tgn:7029392"],"placetype":["aat:300000241"],"id":7374190,"name:xx":"Laguna Colorada"}}
>>>>>>> 03f74aca74312dbeaf24d7e61306dd6a786dc3d0
