{
  "id": 7374190,
  "type": "Feature",
  "properties": {
    "tgn:hierarchy":[
        "tgn:7374190",
        "tgn:7005586",
        "tgn:1000001",
        "tgn:7005560",
        "tgn:7029392"
    ],
    "tgn:id":7374190,
    "tgn:name":"Laguna Colorada",
    "tgn:placetype":[
        "aat:300000241"
    ]
},
  "bbox": [],
  "geometry": {"coordinates":[-102.816667,20.75],"type":"Point"}
}