{
  "id": 2638736,
  "type": "Feature",
  "properties": {
    "tgn:hierarchy":[
        "tgn:2638736",
        "tgn:1000001",
        "tgn:7012149",
        "tgn:2002029",
        "tgn:7007826",
        "tgn:7029392"
    ],
    "tgn:id":2638736,
    "tgn:name":"Salt Branch Ramirena Creek",
    "tgn:placetype":[
        "aat:300008706"
    ]
},
  "bbox": [],
  "geometry": {"coordinates":[-98.3167,28.15],"type":"Point"}
}