{
  "id": 5000905,
  "type": "Feature",
  "properties": {
    "tgn:hierarchy":[
        "tgn:5000905",
        "tgn:7002445",
        "tgn:7019021",
        "tgn:1000003",
        "tgn:7008591",
        "tgn:7029392"
    ],
    "tgn:id":5000905,
    "tgn:name":"Englishcombe",
    "tgn:placetype":[
        "aat:300008347"
    ]
},
  "bbox": [],
  "geometry": {"coordinates":[-2.406,51.351],"type":"Point"}
}