{
  "id": 2657289,
  "type": "Feature",
  "properties": {
    "tgn:hierarchy":[
        "tgn:2657289",
        "tgn:1000001",
        "tgn:2000458",
        "tgn:7012149",
        "tgn:7007250",
        "tgn:7029392"
    ],
    "tgn:id":2657289,
    "tgn:name":"Sheep Trail Butte",
    "tgn:placetype":[
        "aat:300008798"
    ]
},
  "bbox": [],
  "geometry": {"coordinates":[-113.45,43.3333],"type":"Point"}
}