{
  "id": 7319403,
  "type": "Feature",
  "properties": {
    "tgn:hierarchy":[
        "tgn:7319403",
        "tgn:1001699",
        "tgn:1000049",
        "tgn:1000002",
        "tgn:7029392"
    ],
    "tgn:id":7319403,
    "tgn:name":"Amancay",
    "tgn:placetype":[
        "aat:300000206"
    ]
},
  "bbox": [],
  "geometry": {"coordinates":[-73.466667,-41.233333],"type":"Point"}
}