{
  "id": 2324976,
  "type": "Feature",
  "properties": {
    "tgn:hierarchy":[
        "tgn:2324976",
        "tgn:1000001",
        "tgn:7012149",
        "tgn:2001722",
        "tgn:7007708",
        "tgn:7029392"
    ],
    "tgn:id":2324976,
    "tgn:name":"Ferguson Spring",
    "tgn:placetype":[
        "aat:300008697"
    ]
},
  "bbox": [],
  "geometry": {"coordinates":[-117.7167,45.8167],"type":"Point"}
}