{
  "id": 7262392,
  "type": "Feature",
  "properties": {
    "tgn:hierarchy":[
        "tgn:7262392",
        "tgn:7003615",
        "tgn:1000003",
        "tgn:7016845",
        "tgn:7029392"
    ],
    "tgn:id":7262392,
    "tgn:name:nl":"Hanzetocht",
    "tgn:placetype":[
        "aat:300006075"
    ]
},
  "bbox": [],
  "geometry": {"coordinates":[5.716667,52.533333],"type":"Point"}
}