{
  "id": 7073179,
  "type": "Feature",
  "properties": {
    "tgn:hierarchy":[
        "tgn:7073179",
        "tgn:1000003",
        "tgn:7003682",
        "tgn:7000084",
        "tgn:7029392"
    ],
    "tgn:id":7073179,
    "tgn:name":"Landkreis S\u00fcdliche Weinstra\u00dfe",
    "tgn:placetype":[
        "aat:300387198"
    ]
},
  "bbox": [],
  "geometry": {"coordinates":[8.074722,49.217778],"type":"Point"}
}