{
  "id": 7152307,
  "type": "Feature",
  "properties": {
    "tgn:hierarchy":[
        "tgn:7152307",
        "tgn:7003669",
        "tgn:1000003",
        "tgn:7000084",
        "tgn:7029392"
    ],
    "tgn:id":7152307,
    "tgn:name":"Kalvarien Berg",
    "tgn:placetype":[
        "aat:300008777"
    ]
},
  "bbox": [],
  "geometry": {"coordinates":[12.666667,49.233333],"type":"Point"}
}