{
  "id": 7502853,
  "type": "Feature",
  "properties": {
    "tgn:hierarchy":[
        "tgn:7502853",
        "tgn:1000004",
        "tgn:7001002",
        "tgn:1000141",
        "tgn:7029392"
    ],
    "tgn:id":7502853,
    "tgn:name":"Houhu",
    "tgn:placetype":[
        "aat:300000745"
    ]
},
  "bbox": [],
  "geometry": {"coordinates":[120.960278,24.821389],"type":"Point"}
}