{
  "id": 2341646,
  "type": "Feature",
  "properties": {
    "tgn:hierarchy":[
        "tgn:2341646",
        "tgn:1000001",
        "tgn:7012149",
        "tgn:2001255",
        "tgn:7007523",
        "tgn:7029392"
    ],
    "tgn:id":2341646,
    "tgn:name":"Frontier Lake",
    "tgn:placetype":[
        "aat:300006191"
    ]
},
  "bbox": [],
  "geometry": {"coordinates":[-90.5833,37.2333],"type":"Point"}
}