<<<<<<< HEAD
{
  "id": 2403994,
  "type": "Feature",
  "properties": {
    "tgn:hierarchy":[
        "tgn:2403994",
        "tgn:1000001",
        "tgn:7012149",
        "tgn:2000361",
        "tgn:7007248",
        "tgn:7029392"
    ],
    "tgn:id":2403994,
    "tgn:name":"Howell Grove",
    "tgn:placetype":[
        "aat:300008347"
    ]
},
  "bbox": [],
  "geometry": {"coordinates":[-83.0833,33.3167],"type":"Point"}
}
=======
{"geometry":{"type":"Point","coordinates":[-83.083300,33.316700]},"type":"Feature","properties":{"hierarchy":["tgn:2403994","tgn:1000001","tgn:7012149","tgn:2000361","tgn:7007248","tgn:7029392"],"placetype":["aat:300008347"],"id":2403994,"name:xx":"Howell Grove"}}
>>>>>>> 03f74aca74312dbeaf24d7e61306dd6a786dc3d0
