<<<<<<< HEAD
{
  "id": 2339539,
  "type": "Feature",
  "properties": {
    "tgn:hierarchy":[
        "tgn:2339539",
        "tgn:1000001",
        "tgn:2002370",
        "tgn:7012149",
        "tgn:7007923",
        "tgn:7029392"
    ],
    "tgn:id":2339539,
    "tgn:name":"Freda Creek",
    "tgn:placetype":[
        "aat:300008706"
    ]
},
  "bbox": [],
  "geometry": {"coordinates":[-104.8667,44.2],"type":"Point"}
}
=======
{"geometry":{"type":"Point","coordinates":[-104.866700,44.200000]},"type":"Feature","properties":{"hierarchy":["tgn:2339539","tgn:1000001","tgn:2002370","tgn:7012149","tgn:7007923","tgn:7029392"],"placetype":["aat:300008706"],"id":2339539,"name:xx":"Freda Creek"}}
>>>>>>> 03f74aca74312dbeaf24d7e61306dd6a786dc3d0
