<<<<<<< HEAD
{
  "id": 7173226,
  "type": "Feature",
  "properties": {
    "tgn:hierarchy":[
        "tgn:7173226",
        "tgn:7000096",
        "tgn:1000003",
        "tgn:7000084",
        "tgn:7029392"
    ],
    "tgn:id":7173226,
    "tgn:name":"Gro\u00dfer Teich",
    "tgn:placetype":[
        "aat:300387087"
    ]
},
  "bbox": [],
  "geometry": {"coordinates":[14.016667,51.483333],"type":"Point"}
}
=======
{"geometry":{"type":"Point","coordinates":[14.016667,51.483333]},"type":"Feature","properties":{"hierarchy":["tgn:7173226","tgn:7000096","tgn:1000003","tgn:7000084","tgn:7029392"],"placetype":["aat:300387087"],"id":7173226,"name:xx":"Gro\u00dfer Teich"}}
>>>>>>> 03f74aca74312dbeaf24d7e61306dd6a786dc3d0
