{
  "id": 7173226,
  "type": "Feature",
  "properties": {
    "tgn:hierarchy":[
        "tgn:7173226",
        "tgn:7000096",
        "tgn:1000003",
        "tgn:7000084",
        "tgn:7029392"
    ],
    "tgn:id":7173226,
    "tgn:name":"Gro\u00dfer Teich",
    "tgn:placetype":[
        "aat:300387087"
    ]
},
  "bbox": [],
  "geometry": {"coordinates":[14.016667,51.483333],"type":"Point"}
}