{
  "id": 2309878,
  "type": "Feature",
  "properties": {
    "tgn:hierarchy":[
        "tgn:2309878",
        "tgn:1000001",
        "tgn:7012149",
        "tgn:2001114",
        "tgn:7007522",
        "tgn:7029392"
    ],
    "tgn:id":2309878,
    "tgn:name":"Eastman",
    "tgn:placetype":[
        "aat:300008347"
    ]
},
  "bbox": [],
  "geometry": {"coordinates":[-88.2333,34.3333],"type":"Point"}
}