{
  "id": 7480646,
  "type": "Feature",
  "properties": {
    "tgn:hierarchy":[
        "tgn:7480646",
        "tgn:7468018",
        "tgn:1000004",
        "tgn:1000141",
        "tgn:7029392"
    ],
    "tgn:id":7480646,
    "tgn:name":"Yongling Gong",
    "tgn:placetype":[
        "aat:300007595"
    ]
},
  "bbox": [],
  "geometry": {"coordinates":[120.1746,23.4629],"type":"Point"}
}