{
  "id": 2301152,
  "type": "Feature",
  "properties": {
    "tgn:hierarchy":[
        "tgn:2301152",
        "tgn:1000001",
        "tgn:7012149",
        "tgn:7007255",
        "tgn:7029392"
    ],
    "tgn:id":2301152,
    "tgn:name":"Dunkan Branch",
    "tgn:placetype":[
        "aat:300008699"
    ]
},
  "bbox": [],
  "geometry": {"coordinates":[-83.6333,37.8333],"type":"Point"}
}