{
  "id": 7216257,
  "type": "Feature",
  "properties": {
    "tgn:hierarchy":[
        "tgn:7216257",
        "tgn:1000003",
        "tgn:7003682",
        "tgn:7000084",
        "tgn:7029392"
    ],
    "tgn:id":7216257,
    "tgn:name":"Altdorf",
    "tgn:placetype":[
        "aat:300008347"
    ]
},
  "bbox": [],
  "geometry": {"coordinates":[8.216111,49.287222],"type":"Point"}
}