{
  "id": 2021721,
  "type": "Feature",
  "properties": {
    "tgn:hierarchy":[
        "tgn:2021721",
        "tgn:2000258",
        "tgn:1000001",
        "tgn:7012149",
        "tgn:7007240",
        "tgn:7029392"
    ],
    "tgn:id":2021721,
    "tgn:name":"West Bay",
    "tgn:placetype":[
        "aat:300008347"
    ]
},
  "bbox": [],
  "geometry": {"coordinates":[-85.85,30.2833],"type":"Point"}
}