{
  "id": 7478112,
  "type": "Feature",
  "properties": {
    "tgn:hierarchy":[
        "tgn:7478112",
        "tgn:1000004",
        "tgn:7492971",
        "tgn:1000141",
        "tgn:7029392"
    ],
    "tgn:id":7478112,
    "tgn:name":"Datan Guoxiao",
    "tgn:placetype":[
        "aat:300006495"
    ]
},
  "bbox": [],
  "geometry": {"coordinates":[120.495817,22.456639],"type":"Point"}
}