{
  "id": 7585342,
  "type": "Feature",
  "properties": {
    "tgn:hierarchy":[
        "tgn:7585342",
        "tgn:1000004",
        "tgn:7000198",
        "tgn:7016788",
        "tgn:7029392"
    ],
    "tgn:id":7585342,
    "tgn:name:en":"Ham\u012bri Kal\u0101n",
    "tgn:placetype":[
        "aat:300008347"
    ]
},
  "bbox": [],
  "geometry": {"coordinates":[75.387308,28.175511],"type":"Point"}
}