{
  "id": 2646818,
  "type": "Feature",
  "properties": {
    "tgn:hierarchy":[
        "tgn:2646818",
        "tgn:7002659",
        "tgn:1000001",
        "tgn:7012149",
        "tgn:2000028",
        "tgn:7029392"
    ],
    "tgn:id":2646818,
    "tgn:name":"Scareum Mountain",
    "tgn:placetype":[
        "aat:300008798"
    ]
},
  "bbox": [],
  "geometry": {"coordinates":[-87.8833,33.65],"type":"Point"}
}