{
  "id": 2379292,
  "type": "Feature",
  "properties": {
    "tgn:hierarchy":[
        "tgn:2379292",
        "tgn:1000001",
        "tgn:7012149",
        "tgn:7007157",
        "tgn:1002857",
        "tgn:7029392"
    ],
    "tgn:id":2379292,
    "tgn:name":"Harvard Hill",
    "tgn:placetype":[
        "aat:300008798"
    ]
},
  "bbox": [],
  "geometry": {"coordinates":[-116.65,34.9333],"type":"Point"}
}