{
  "id": 7558871,
  "type": "Feature",
  "properties": {
    "tgn:hierarchy":[
        "tgn:7558871",
        "tgn:1000004",
        "tgn:7000198",
        "tgn:7000799",
        "tgn:7029392"
    ],
    "tgn:id":7558871,
    "tgn:name:en":"Qara T\u0101gh Pass",
    "tgn:placetype":[
        "aat:300259572"
    ]
},
  "bbox": [],
  "geometry": {"coordinates":[78.312714,35.723532],"type":"Point"}
}