{
  "id": 2570446,
  "type": "Feature",
  "properties": {
    "tgn:hierarchy":[
        "tgn:2570446",
        "tgn:1000001",
        "tgn:7013368",
        "tgn:7012149",
        "tgn:7007709",
        "tgn:7029392"
    ],
    "tgn:id":2570446,
    "tgn:name":"Pate Creek",
    "tgn:placetype":[
        "aat:300008706"
    ]
},
  "bbox": [],
  "geometry": {"coordinates":[-76.65,35.2667],"type":"Point"}
}