<<<<<<< HEAD
{
  "id": 2333985,
  "type": "Feature",
  "properties": {
    "tgn:hierarchy":[
        "tgn:2333985",
        "tgn:1000001",
        "tgn:7016172",
        "tgn:7012149",
        "tgn:2000150",
        "tgn:7029392"
    ],
    "tgn:id":2333985,
    "tgn:name":"Ford Islands",
    "tgn:placetype":[
        "aat:300386853"
    ]
},
  "bbox": [],
  "geometry": {"coordinates":[-94.0,33.25],"type":"Point"}
}
=======
{"geometry":{"type":"Point","coordinates":[-94.000000,33.250000]},"type":"Feature","properties":{"hierarchy":["tgn:2333985","tgn:1000001","tgn:7016172","tgn:7012149","tgn:2000150","tgn:7029392"],"placetype":["aat:300386853"],"id":2333985,"name:xx":"Ford Islands"}}
>>>>>>> 03f74aca74312dbeaf24d7e61306dd6a786dc3d0
