{
  "id": 7054867,
  "type": "Feature",
  "properties": {
    "tgn:hierarchy":[
        "tgn:7054867",
        "tgn:7003170",
        "tgn:1000003",
        "tgn:7003125",
        "tgn:1000080",
        "tgn:7029392"
    ],
    "tgn:id":7054867,
    "tgn:name":"Molino Moscano",
    "tgn:placetype":[
        "aat:300008347"
    ]
},
  "bbox": [],
  "geometry": {"coordinates":[12.416667,43.466667],"type":"Point"}
}