<<<<<<< HEAD
{
  "id": 2253064,
  "type": "Feature",
  "properties": {
    "tgn:hierarchy":[
        "tgn:2253064",
        "tgn:1000001",
        "tgn:7012149",
        "tgn:2002124",
        "tgn:7007827",
        "tgn:7029392"
    ],
    "tgn:id":2253064,
    "tgn:name":"Constantine Canyon",
    "tgn:placetype":[
        "aat:300008761"
    ]
},
  "bbox": [],
  "geometry": {"coordinates":[-109.4333,40.6333],"type":"Point"}
}
=======
{"geometry":{"type":"Point","coordinates":[-109.433300,40.633300]},"type":"Feature","properties":{"hierarchy":["tgn:2253064","tgn:1000001","tgn:7012149","tgn:2002124","tgn:7007827","tgn:7029392"],"placetype":["aat:300008761"],"id":2253064,"name:xx":"Constantine Canyon"}}
>>>>>>> 03f74aca74312dbeaf24d7e61306dd6a786dc3d0
