{
  "id": 2580648,
  "type": "Feature",
  "properties": {
    "tgn:hierarchy":[
        "tgn:2580648",
        "tgn:1000001",
        "tgn:7012149",
        "tgn:2000818",
        "tgn:7007255",
        "tgn:7029392"
    ],
    "tgn:id":2580648,
    "tgn:name":"Pigeon Roost Branch",
    "tgn:placetype":[
        "aat:300008699"
    ]
},
  "bbox": [],
  "geometry": {"coordinates":[-84.4333,36.7333],"type":"Point"}
}