{
  "id": 2486697,
  "type": "Feature",
  "properties": {
    "tgn:hierarchy":[
        "tgn:2486697",
        "tgn:1000001",
        "tgn:7012149",
        "tgn:2002118",
        "tgn:7007827",
        "tgn:7029392"
    ],
    "tgn:id":2486697,
    "tgn:name":"Ledgewood",
    "tgn:placetype":[
        "aat:300008347"
    ]
},
  "bbox": [],
  "geometry": {"coordinates":[-111.9333,40.6333],"type":"Point"}
}