{
  "id": 2728715,
  "type": "Feature",
  "properties": {
    "tgn:hierarchy":[
        "tgn:2728715",
        "tgn:1000001",
        "tgn:7012149",
        "tgn:2002090",
        "tgn:7007826",
        "tgn:7029392"
    ],
    "tgn:id":2728715,
    "tgn:name":"Tres Picos Tank",
    "tgn:placetype":[
        "aat:300006191"
    ]
},
  "bbox": [],
  "geometry": {"coordinates":[-98.9833,27.55],"type":"Point"}
}