{
  "id": 2296854,
  "type": "Feature",
  "properties": {
    "tgn:hierarchy":[
        "tgn:2296854",
        "tgn:1000001",
        "tgn:7012149",
        "tgn:2001155",
        "tgn:7007522",
        "tgn:7029392"
    ],
    "tgn:id":2296854,
    "tgn:name":"Dry Creek",
    "tgn:placetype":[
        "aat:300008347"
    ]
},
  "bbox": [],
  "geometry": {"coordinates":[-88.7333,34.6667],"type":"Point"}
}