{
  "id": 2633752,
  "type": "Feature",
  "properties": {
    "tgn:hierarchy":[
        "tgn:2633752",
        "tgn:1000001",
        "tgn:7012149",
        "tgn:2000233",
        "tgn:7007158",
        "tgn:7029392"
    ],
    "tgn:id":2633752,
    "tgn:name":"Rush Creek Reservoir",
    "tgn:placetype":[
        "aat:300006075"
    ]
},
  "bbox": [],
  "geometry": {"coordinates":[-108.2333,37.4667],"type":"Point"}
}