{
  "id": 2317084,
  "type": "Feature",
  "properties": {
    "tgn:hierarchy":[
        "tgn:2317084",
        "tgn:1000001",
        "tgn:7012149",
        "tgn:2002118",
        "tgn:7007827",
        "tgn:7029392"
    ],
    "tgn:id":2317084,
    "tgn:name":"Emigration Tunnel Spring",
    "tgn:placetype":[
        "aat:300008697"
    ]
},
  "bbox": [],
  "geometry": {"coordinates":[-111.7833,40.75],"type":"Point"}
}