{
  "id": 7086722,
  "type": "Feature",
  "properties": {
    "tgn:hierarchy":[
        "tgn:7086722",
        "tgn:1000003",
        "tgn:7000094",
        "tgn:7000084",
        "tgn:7029392"
    ],
    "tgn:id":7086722,
    "tgn:name":"Wars-Berge",
    "tgn:placetype":[
        "aat:300008777"
    ]
},
  "bbox": [],
  "geometry": {"coordinates":[13.316667,53.333333],"type":"Point"}
}