<<<<<<< HEAD
{
  "id": 2339046,
  "type": "Feature",
  "properties": {
    "tgn:hierarchy":[
        "tgn:2339046",
        "tgn:1002215",
        "tgn:1000001",
        "tgn:7012149",
        "tgn:7007565",
        "tgn:7029392"
    ],
    "tgn:id":2339046,
    "tgn:name":"Franklin Park",
    "tgn:placetype":[
        "aat:300008347"
    ]
},
  "bbox": [],
  "geometry": {"coordinates":[-74.9,40.0167],"type":"Point"}
}
=======
{"geometry":{"type":"Point","coordinates":[-74.900000,40.016700]},"type":"Feature","properties":{"hierarchy":["tgn:2339046","tgn:1002215","tgn:1000001","tgn:7012149","tgn:7007565","tgn:7029392"],"placetype":["aat:300008347"],"id":2339046,"name:xx":"Franklin Park"}}
>>>>>>> 03f74aca74312dbeaf24d7e61306dd6a786dc3d0
