{
  "id": 2507177,
  "type": "Feature",
  "properties": {
    "tgn:hierarchy":[
        "tgn:2507177",
        "tgn:1000001",
        "tgn:2000924",
        "tgn:7012149",
        "tgn:7007515",
        "tgn:7029392"
    ],
    "tgn:id":2507177,
    "tgn:name":"Metinic Green Island",
    "tgn:placetype":[
        "aat:300008791"
    ]
},
  "bbox": [],
  "geometry": {"coordinates":[-69.1333,43.85],"type":"Point"}
}