{
  "id": 7537465,
  "type": "Feature",
  "properties": {
    "tgn:hierarchy":[
        "tgn:7537465",
        "tgn:7001242",
        "tgn:7016833",
        "tgn:7001334",
        "tgn:7029392"
    ],
    "tgn:id":7537465,
    "tgn:name:en":"Naq' al Birkah, W\u0101d\u012b",
    "tgn:placetype":[
        "aat:300379998"
    ]
},
  "bbox": [],
  "geometry": {"coordinates":[32.614712,25.84899],"type":"Point"}
}