{
  "id": 2134797,
  "type": "Feature",
  "properties": {
    "tgn:hierarchy":[
        "tgn:2134797",
        "tgn:1000001",
        "tgn:7012149",
        "tgn:2002383",
        "tgn:7007923",
        "tgn:7029392"
    ],
    "tgn:id":2134797,
    "tgn:name":"Antelope Draw",
    "tgn:placetype":[
        "aat:300008761"
    ]
},
  "bbox": [],
  "geometry": {"coordinates":[-109.0333,41.3833],"type":"Point"}
}