{
  "id": 1013297,
  "type": "Feature",
  "properties": {
    "tgn:hierarchy":[
        "tgn:1013297",
        "tgn:7005694",
        "tgn:7005685",
        "tgn:1000001",
        "tgn:7029392"
    ],
    "tgn:id":1013297,
    "tgn:name":"Sherwood Park",
    "tgn:placetype":[
        "aat:300008347"
    ]
},
  "bbox": [],
  "geometry": {"coordinates":[-113.3167,53.5167],"type":"Point"}
}