{
  "id": 7550184,
  "type": "Feature",
  "properties": {
    "tgn:hierarchy":[
        "tgn:7550184",
        "tgn:1000004",
        "tgn:7000198",
        "tgn:7016788",
        "tgn:7029392"
    ],
    "tgn:id":7550184,
    "tgn:name:en":"B\u012bsalpur",
    "tgn:placetype":[
        "aat:300008347"
    ]
},
  "bbox": [],
  "geometry": {"coordinates":[73.314035,26.231592],"type":"Point"}
}