{
  "id": 7299380,
  "type": "Feature",
  "properties": {
    "tgn:hierarchy":[
        "tgn:7299380",
        "tgn:7002822",
        "tgn:1001647",
        "tgn:1000003",
        "tgn:1000095",
        "tgn:7029392"
    ],
    "tgn:id":7299380,
    "tgn:name":"Valdevaca, Arroyo",
    "tgn:placetype":[
        "aat:300266554",
        "aat:300008699"
    ]
},
  "bbox": [],
  "geometry": {"coordinates":[-3.316667,40.733333],"type":"Point"}
}