<<<<<<< HEAD
{
  "id": 7247789,
  "type": "Feature",
  "properties": {
    "tgn:hierarchy":[
        "tgn:7247789",
        "tgn:7003456",
        "tgn:1000003",
        "tgn:1000063",
        "tgn:7018236",
        "tgn:7029392"
    ],
    "tgn:id":7247789,
    "tgn:name":"Duivelshoek",
    "tgn:placetype":[
        "aat:300008347"
    ]
},
  "bbox": [],
  "geometry": {"coordinates":[4.383333,51.166667],"type":"Point"}
}
=======
{"geometry":{"type":"Point","coordinates":[4.383333,51.166667]},"type":"Feature","properties":{"hierarchy":["tgn:7247789","tgn:7003456","tgn:1000003","tgn:1000063","tgn:7018236","tgn:7029392"],"placetype":["aat:300008347"],"id":7247789,"name:xx":"Duivelshoek"}}
>>>>>>> 03f74aca74312dbeaf24d7e61306dd6a786dc3d0
