{
  "id": 7247789,
  "type": "Feature",
  "properties": {
    "tgn:hierarchy":[
        "tgn:7247789",
        "tgn:7003456",
        "tgn:1000003",
        "tgn:1000063",
        "tgn:7018236",
        "tgn:7029392"
    ],
    "tgn:id":7247789,
    "tgn:name":"Duivelshoek",
    "tgn:placetype":[
        "aat:300008347"
    ]
},
  "bbox": [],
  "geometry": {"coordinates":[4.383333,51.166667],"type":"Point"}
}