{
  "id": 7165196,
  "type": "Feature",
  "properties": {
    "tgn:hierarchy":[
        "tgn:7165196",
        "tgn:7003669",
        "tgn:1000003",
        "tgn:7000084",
        "tgn:7029392"
    ],
    "tgn:id":7165196,
    "tgn:name":"Iglersreuth",
    "tgn:placetype":[
        "aat:300008347"
    ]
},
  "bbox": [],
  "geometry": {"coordinates":[12.366667,49.816667],"type":"Point"}
}