{
  "id": 7480453,
  "type": "Feature",
  "properties": {
    "tgn:hierarchy":[
        "tgn:7480453",
        "tgn:1000004",
        "tgn:7490934",
        "tgn:1000141",
        "tgn:7029392"
    ],
    "tgn:id":7480453,
    "tgn:name":"Liushuang Qiao",
    "tgn:placetype":[
        "aat:300007836"
    ]
},
  "bbox": [],
  "geometry": {"coordinates":[120.364431,23.172141],"type":"Point"}
}