{
  "id": 1140284,
  "type": "Feature",
  "properties": {
    "tgn:hierarchy":[
        "tgn:1140284",
        "tgn:1001048",
        "tgn:1000004",
        "tgn:7000231",
        "tgn:7029392"
    ],
    "tgn:id":1140284,
    "tgn:name":"Sar Dasht",
    "tgn:placetype":[
        "aat:300008347"
    ]
},
  "bbox": [],
  "geometry": {"coordinates":[45.4833,36.15],"type":"Point"}
}