{
  "id": 7088032,
  "type": "Feature",
  "properties": {
    "tgn:hierarchy":[
        "tgn:7088032",
        "tgn:1000003",
        "tgn:7003676",
        "tgn:7000084",
        "tgn:7029392"
    ],
    "tgn:id":7088032,
    "tgn:name":"Weddersehl",
    "tgn:placetype":[
        "aat:300008347"
    ]
},
  "bbox": [],
  "geometry": {"coordinates":[10.55,52.733333],"type":"Point"}
}