{
  "id": 7113549,
  "type": "Feature",
  "properties": {
    "tgn:hierarchy":[
        "tgn:7113549",
        "tgn:7000096",
        "tgn:1000003",
        "tgn:7000084",
        "tgn:7029392"
    ],
    "tgn:id":7113549,
    "tgn:name":"Rettungshaus",
    "tgn:placetype":[
        "aat:300000206"
    ]
},
  "bbox": [],
  "geometry": {"coordinates":[13.133333,52.683333],"type":"Point"}
}