<<<<<<< HEAD
{
  "id": 7113549,
  "type": "Feature",
  "properties": {
    "tgn:hierarchy":[
        "tgn:7113549",
        "tgn:7000096",
        "tgn:1000003",
        "tgn:7000084",
        "tgn:7029392"
    ],
    "tgn:id":7113549,
    "tgn:name":"Rettungshaus",
    "tgn:placetype":[
        "aat:300000206"
    ]
},
  "bbox": [],
  "geometry": {"coordinates":[13.133333,52.683333],"type":"Point"}
}
=======
{"geometry":{"type":"Point","coordinates":[13.133333,52.683333]},"type":"Feature","properties":{"hierarchy":["tgn:7113549","tgn:7000096","tgn:1000003","tgn:7000084","tgn:7029392"],"placetype":["aat:300000206"],"id":7113549,"name:xx":"Rettungshaus"}}
>>>>>>> 03f74aca74312dbeaf24d7e61306dd6a786dc3d0
