<<<<<<< HEAD
{
  "id": 2257971,
  "type": "Feature",
  "properties": {
    "tgn:hierarchy":[
        "tgn:2257971",
        "tgn:1000001",
        "tgn:2002368",
        "tgn:7012149",
        "tgn:7007923",
        "tgn:7029392"
    ],
    "tgn:id":2257971,
    "tgn:name":"Cortez Creek",
    "tgn:placetype":[
        "aat:300008706"
    ]
},
  "bbox": [],
  "geometry": {"coordinates":[-106.45,41.3833],"type":"Point"}
}
=======
{"geometry":{"type":"Point","coordinates":[-106.450000,41.383300]},"type":"Feature","properties":{"hierarchy":["tgn:2257971","tgn:1000001","tgn:2002368","tgn:7012149","tgn:7007923","tgn:7029392"],"placetype":["aat:300008706"],"id":2257971,"name:xx":"Cortez Creek"}}
>>>>>>> 03f74aca74312dbeaf24d7e61306dd6a786dc3d0
