{
  "id": 7317766,
  "type": "Feature",
  "properties": {
    "tgn:hierarchy":[
        "tgn:7317766",
        "tgn:1001623",
        "tgn:1000049",
        "tgn:1000002",
        "tgn:7029392"
    ],
    "tgn:id":7317766,
    "tgn:name":"Circo, R\u00edo",
    "tgn:placetype":[
        "aat:300008699"
    ]
},
  "bbox": [],
  "geometry": {"coordinates":[-73.266667,-46.416667],"type":"Point"}
}