{
  "id": 2546749,
  "type": "Feature",
  "properties": {
    "tgn:hierarchy":[
        "tgn:2546749",
        "tgn:1000001",
        "tgn:7012149",
        "tgn:2001720",
        "tgn:7007708",
        "tgn:7029392"
    ],
    "tgn:id":2546749,
    "tgn:name":"North Fork McKay Creek",
    "tgn:placetype":[
        "aat:300008706"
    ]
},
  "bbox": [],
  "geometry": {"coordinates":[-118.45,45.5833],"type":"Point"}
}