{
  "id": 7226705,
  "type": "Feature",
  "properties": {
    "tgn:hierarchy":[
        "tgn:7226705",
        "tgn:7002748",
        "tgn:7001399",
        "tgn:1000003",
        "tgn:1000074",
        "tgn:7029392"
    ],
    "tgn:id":7226705,
    "tgn:name":"Pro\u00e1stion",
    "tgn:placetype":[
        "aat:300008347"
    ]
},
  "bbox": [],
  "geometry": {"coordinates":[21.9025,39.488611],"type":"Point"}
}