{
  "id": 2406848,
  "type": "Feature",
  "properties": {
    "tgn:hierarchy":[
        "tgn:2406848",
        "tgn:7006450",
        "tgn:1000001",
        "tgn:7012149",
        "tgn:2124014",
        "tgn:7029392"
    ],
    "tgn:id":2406848,
    "tgn:name":"Hunter Creek",
    "tgn:placetype":[
        "aat:300008706"
    ]
},
  "bbox": [],
  "geometry": {"coordinates":[-162.25,66.0167],"type":"Point"}
}