<<<<<<< HEAD
{
  "id": 2406848,
  "type": "Feature",
  "properties": {
    "tgn:hierarchy":[
        "tgn:2406848",
        "tgn:7006450",
        "tgn:1000001",
        "tgn:7012149",
        "tgn:2124014",
        "tgn:7029392"
    ],
    "tgn:id":2406848,
    "tgn:name":"Hunter Creek",
    "tgn:placetype":[
        "aat:300008706"
    ]
},
  "bbox": [],
  "geometry": {"coordinates":[-162.25,66.0167],"type":"Point"}
}
=======
{"geometry":{"type":"Point","coordinates":[-162.250000,66.016700]},"type":"Feature","properties":{"hierarchy":["tgn:2406848","tgn:7006450","tgn:1000001","tgn:7012149","tgn:2124014","tgn:7029392"],"placetype":["aat:300008706"],"id":2406848,"name:xx":"Hunter Creek"}}
>>>>>>> 03f74aca74312dbeaf24d7e61306dd6a786dc3d0
