<<<<<<< HEAD
{
  "id": 7353452,
  "type": "Feature",
  "properties": {
    "tgn:hierarchy":[
        "tgn:7353452",
        "tgn:7005584",
        "tgn:1000001",
        "tgn:7005560",
        "tgn:7029392"
    ],
    "tgn:id":7353452,
    "tgn:name":"Buenavista de Ballesteros",
    "tgn:placetype":[
        "aat:300008347"
    ]
},
  "bbox": [],
  "geometry": {"coordinates":[-100.683333,20.033333],"type":"Point"}
}
=======
{"geometry":{"type":"Point","coordinates":[-100.683333,20.033333]},"type":"Feature","properties":{"hierarchy":["tgn:7353452","tgn:7005584","tgn:1000001","tgn:7005560","tgn:7029392"],"placetype":["aat:300008347"],"id":7353452,"name:xx":"Buenavista de Ballesteros"}}
>>>>>>> 03f74aca74312dbeaf24d7e61306dd6a786dc3d0
