<<<<<<< HEAD
{
  "id": 2250642,
  "type": "Feature",
  "properties": {
    "tgn:hierarchy":[
        "tgn:2250642",
        "tgn:1000001",
        "tgn:7012149",
        "tgn:2002376",
        "tgn:7007923",
        "tgn:7029392"
    ],
    "tgn:id":2250642,
    "tgn:name":"Colorado River Divide Great Basin",
    "tgn:placetype":[
        "aat:300386845"
    ]
},
  "bbox": [],
  "geometry": {"coordinates":[-110.6167,41.85],"type":"Point"}
}
=======
{"geometry":{"type":"Point","coordinates":[-110.616700,41.850000]},"type":"Feature","properties":{"hierarchy":["tgn:2250642","tgn:1000001","tgn:7012149","tgn:2002376","tgn:7007923","tgn:7029392"],"placetype":["aat:300386845"],"id":2250642,"name:xx":"Colorado River Divide Great Basin"}}
>>>>>>> 03f74aca74312dbeaf24d7e61306dd6a786dc3d0
