{
  "id": 2477851,
  "type": "Feature",
  "properties": {
    "tgn:hierarchy":[
        "tgn:2477851",
        "tgn:1000001",
        "tgn:7012149",
        "tgn:2001461",
        "tgn:7007568",
        "tgn:7029392"
    ],
    "tgn:id":2477851,
    "tgn:name":"MacNaughton Mountain",
    "tgn:placetype":[
        "aat:300008798"
    ]
},
  "bbox": [],
  "geometry": {"coordinates":[-74.05,44.1333],"type":"Point"}
}