{
  "id": 7081284,
  "type": "Feature",
  "properties": {
    "tgn:hierarchy":[
        "tgn:7081284",
        "tgn:7003692",
        "tgn:1000003",
        "tgn:7000084",
        "tgn:7029392"
    ],
    "tgn:id":7081284,
    "tgn:name":"Witzmannsweiler",
    "tgn:placetype":[
        "aat:300008347"
    ]
},
  "bbox": [],
  "geometry": {"coordinates":[9.630833,49.105833],"type":"Point"}
}