{
  "id": 2560414,
  "type": "Feature",
  "properties": {
    "tgn:hierarchy":[
        "tgn:2560414",
        "tgn:1000001",
        "tgn:7012149",
        "tgn:2002124",
        "tgn:7007827",
        "tgn:7029392"
    ],
    "tgn:id":2560414,
    "tgn:name":"Orchid Draw",
    "tgn:placetype":[
        "aat:300008761"
    ]
},
  "bbox": [],
  "geometry": {"coordinates":[-109.3167,40.45],"type":"Point"}
}