{
  "id": 7504398,
  "type": "Feature",
  "properties": {
    "tgn:hierarchy":[
        "tgn:7504398",
        "tgn:1008380",
        "tgn:1000226",
        "tgn:7018426",
        "tgn:1000006",
        "tgn:7029392"
    ],
    "tgn:id":7504398,
    "tgn:name:en":"Waitakaruru Stream",
    "tgn:placetype":[
        "aat:300008699"
    ]
},
  "bbox": [],
  "geometry": {"coordinates":[175.533333,-37.666667],"type":"Point"}
}