{
  "id": 2667631,
  "type": "Feature",
  "properties": {
    "tgn:hierarchy":[
        "tgn:2667631",
        "tgn:1000001",
        "tgn:7012149",
        "tgn:2001682",
        "tgn:7007707",
        "tgn:7029392"
    ],
    "tgn:id":2667631,
    "tgn:name":"Skull Creek",
    "tgn:placetype":[
        "aat:300008706"
    ]
},
  "bbox": [],
  "geometry": {"coordinates":[-96.7667,35.9833],"type":"Point"}
}