{
  "id": 2506774,
  "type": "Feature",
  "properties": {
    "tgn:hierarchy":[
        "tgn:2506774",
        "tgn:1000001",
        "tgn:7012149",
        "tgn:7007157",
        "tgn:1002684",
        "tgn:7029392"
    ],
    "tgn:id":2506774,
    "tgn:name":"Mescal Ridge",
    "tgn:placetype":[
        "aat:300266640"
    ]
},
  "bbox": [],
  "geometry": {"coordinates":[-121.8333,36.35],"type":"Point"}
}