{
  "id": 2718832,
  "type": "Feature",
  "properties": {
    "tgn:hierarchy":[
        "tgn:2718832",
        "tgn:1000001",
        "tgn:7012149",
        "tgn:2001961",
        "tgn:7007826",
        "tgn:7029392"
    ],
    "tgn:id":2718832,
    "tgn:name":"Thorn Hill",
    "tgn:placetype":[
        "aat:300008347"
    ]
},
  "bbox": [],
  "geometry": {"coordinates":[-98.0833,29.7333],"type":"Point"}
}