{
  "id": 2725055,
  "type": "Feature",
  "properties": {
    "tgn:hierarchy":[
        "tgn:2725055",
        "tgn:1000001",
        "tgn:7012149",
        "tgn:2002173",
        "tgn:7007919",
        "tgn:7029392"
    ],
    "tgn:id":2725055,
    "tgn:name":"Tomtit Branch",
    "tgn:placetype":[
        "aat:300008699"
    ]
},
  "bbox": [],
  "geometry": {"coordinates":[-78.6333,36.6667],"type":"Point"}
}