{
  "id": 2275860,
  "type": "Feature",
  "properties": {
    "tgn:hierarchy":[
        "tgn:2275860",
        "tgn:1000001",
        "tgn:7012149",
        "tgn:2001870",
        "tgn:7007825",
        "tgn:7029392"
    ],
    "tgn:id":2275860,
    "tgn:name":"Dark Hollow",
    "tgn:placetype":[
        "aat:300008761"
    ]
},
  "bbox": [],
  "geometry": {"coordinates":[-83.1833,36.55],"type":"Point"}
}