{
  "id": 1078513,
  "type": "Feature",
  "properties": {
    "tgn:hierarchy":[
        "tgn:1078513",
        "tgn:1000004",
        "tgn:1008813",
        "tgn:1001467",
        "tgn:1000116",
        "tgn:7029392"
    ],
    "tgn:id":1078513,
    "tgn:name":"Sedah",
    "tgn:placetype":[
        "aat:300008347"
    ]
},
  "bbox": [],
  "geometry": {"coordinates":[123.2667,-10.7667],"type":"Point"}
}