{
  "id": 2315205,
  "type": "Feature",
  "properties": {
    "tgn:hierarchy":[
        "tgn:2315205",
        "tgn:1000001",
        "tgn:7012149",
        "tgn:7014366",
        "tgn:7007252",
        "tgn:7029392"
    ],
    "tgn:id":2315205,
    "tgn:name":"Eller Ditch",
    "tgn:placetype":[
        "aat:300006075"
    ]
},
  "bbox": [],
  "geometry": {"coordinates":[-86.1167,41.6333],"type":"Point"}
}