{
  "id": 5001929,
  "type": "Feature",
  "properties": {
    "tgn:hierarchy":[
        "tgn:5001929",
        "tgn:7002690",
        "tgn:7012056",
        "tgn:1000003",
        "tgn:1000074",
        "tgn:7029392"
    ],
    "tgn:id":5001929,
    "tgn:name":"G\u00e1zion",
    "tgn:placetype":[
        "aat:300008347"
    ]
},
  "bbox": [],
  "geometry": {"coordinates":[25.066667,35.333333],"type":"Point"}
}