{
  "id": 2388848,
  "type": "Feature",
  "properties": {
    "tgn:hierarchy":[
        "tgn:2388848",
        "tgn:1000001",
        "tgn:7012149",
        "tgn:2000217",
        "tgn:7007158",
        "tgn:7029392"
    ],
    "tgn:id":2388848,
    "tgn:name":"Hidden Lake",
    "tgn:placetype":[
        "aat:300006191"
    ]
},
  "bbox": [],
  "geometry": {"coordinates":[-107.0333,38.15],"type":"Point"}
}