{
  "id": 2475492,
  "type": "Feature",
  "properties": {
    "tgn:hierarchy":[
        "tgn:2475492",
        "tgn:1000001",
        "tgn:2002102",
        "tgn:7012149",
        "tgn:7007827",
        "tgn:7029392"
    ],
    "tgn:id":2475492,
    "tgn:name":"Lucin Pit",
    "tgn:placetype":[
        "aat:300000390"
    ]
},
  "bbox": [],
  "geometry": {"coordinates":[-113.7833,41.3333],"type":"Point"}
}