{
  "id": 7369767,
  "type": "Feature",
  "properties": {
    "tgn:hierarchy":[
        "tgn:7369767",
        "tgn:1000001",
        "tgn:7005601",
        "tgn:7005560",
        "tgn:7029392"
    ],
    "tgn:id":7369767,
    "tgn:name":"El Jag\u00fcey",
    "tgn:placetype":[
        "aat:300008347"
    ]
},
  "bbox": [],
  "geometry": {"coordinates":[-101.666667,24.733333],"type":"Point"}
}