{
  "id": 2494258,
  "type": "Feature",
  "properties": {
    "tgn:hierarchy":[
        "tgn:2494258",
        "tgn:1002143",
        "tgn:1000001",
        "tgn:7012149",
        "tgn:7007252",
        "tgn:7029392"
    ],
    "tgn:id":2494258,
    "tgn:name":"Martin Branch",
    "tgn:placetype":[
        "aat:300008699"
    ]
},
  "bbox": [],
  "geometry": {"coordinates":[-84.9333,41.05],"type":"Point"}
}