{
  "id": 2568823,
  "type": "Feature",
  "properties": {
    "tgn:hierarchy":[
        "tgn:2568823",
        "tgn:1000001",
        "tgn:7012149",
        "tgn:7014334",
        "tgn:7007919",
        "tgn:7029392"
    ],
    "tgn:id":2568823,
    "tgn:name":"Parker Field",
    "tgn:placetype":[
        "aat:300008347"
    ]
},
  "bbox": [],
  "geometry": {"coordinates":[-77.45,37.5667],"type":"Point"}
}