{
  "id": 2085307,
  "type": "Feature",
  "properties": {
    "tgn:hierarchy":[
        "tgn:2085307",
        "tgn:1000001",
        "tgn:2001705",
        "tgn:7012149",
        "tgn:7007708",
        "tgn:7029392"
    ],
    "tgn:id":2085307,
    "tgn:name":"Plainview",
    "tgn:placetype":[
        "aat:300008347",
        "aat:300387210"
    ]
},
  "bbox": [],
  "geometry": {"coordinates":[-121.45,44.2333],"type":"Point"}
}