{
  "id": 7105883,
  "type": "Feature",
  "properties": {
    "tgn:hierarchy":[
        "tgn:7105883",
        "tgn:1000003",
        "tgn:7003678",
        "tgn:7000084",
        "tgn:7029392"
    ],
    "tgn:id":7105883,
    "tgn:name":"Schmittenborn",
    "tgn:placetype":[
        "aat:300008697"
    ]
},
  "bbox": [],
  "geometry": {"coordinates":[8.45,50.433333],"type":"Point"}
}