{
  "id": 7225116,
  "type": "Feature",
  "properties": {
    "tgn:hierarchy":[
        "tgn:7225116",
        "tgn:7002681",
        "tgn:7001395",
        "tgn:1000003",
        "tgn:1000074",
        "tgn:7029392"
    ],
    "tgn:id":7225116,
    "tgn:name":"R\u00e9peza",
    "tgn:placetype":[
        "aat:300008795"
    ]
},
  "bbox": [],
  "geometry": {"coordinates":[24.45,38.116667],"type":"Point"}
}