{
  "id": 2374076,
  "type": "Feature",
  "properties": {
    "tgn:hierarchy":[
        "tgn:2374076",
        "tgn:1002132",
        "tgn:1000001",
        "tgn:7012149",
        "tgn:7007919",
        "tgn:7029392"
    ],
    "tgn:id":2374076,
    "tgn:name":"Hammock Point",
    "tgn:placetype":[
        "aat:300008850"
    ]
},
  "bbox": [],
  "geometry": {"coordinates":[-75.4167,37.8833],"type":"Point"}
}