{
  "id": 2100309,
  "type": "Feature",
  "properties": {
    "tgn:hierarchy":[
        "tgn:2100309",
        "tgn:1000001",
        "tgn:7012149",
        "tgn:2001893",
        "tgn:7007825",
        "tgn:7029392"
    ],
    "tgn:id":2100309,
    "tgn:name":"Medon",
    "tgn:placetype":[
        "aat:300008347"
    ]
},
  "bbox": [],
  "geometry": {"coordinates":[-88.8667,35.45],"type":"Point"}
}