{
  "id": 2143271,
  "type": "Feature",
  "properties": {
    "tgn:hierarchy":[
        "tgn:2143271",
        "tgn:1000001",
        "tgn:7012149",
        "tgn:7007157",
        "tgn:1002858",
        "tgn:7029392"
    ],
    "tgn:id":2143271,
    "tgn:name":"Bailey Creek",
    "tgn:placetype":[
        "aat:300008706"
    ]
},
  "bbox": [],
  "geometry": {"coordinates":[-116.6333,33.1167],"type":"Point"}
}