{
  "id": 7304281,
  "type": "Feature",
  "properties": {
    "tgn:hierarchy":[
        "tgn:7304281",
        "tgn:7002803",
        "tgn:1001647",
        "tgn:1000003",
        "tgn:1000095",
        "tgn:7029392"
    ],
    "tgn:id":7304281,
    "tgn:name":"Los Chortales",
    "tgn:placetype":[
        "aat:300008347"
    ]
},
  "bbox": [],
  "geometry": {"coordinates":[-1.45,38.666667],"type":"Point"}
}