{
  "id": 7041349,
  "type": "Feature",
  "properties": {
    "tgn:hierarchy":[
        "tgn:7041349",
        "tgn:1000003",
        "tgn:7003151",
        "tgn:7003237",
        "tgn:1000080",
        "tgn:7029392"
    ],
    "tgn:id":7041349,
    "tgn:name":"San Martino Siccomario",
    "tgn:placetype":[
        "aat:300008347"
    ]
},
  "bbox": [],
  "geometry": {"coordinates":[9.133333,45.15],"type":"Point"}
}