{
  "id": 2681615,
  "type": "Feature",
  "properties": {
    "tgn:hierarchy":[
        "tgn:2681615",
        "tgn:1000001",
        "tgn:1003023",
        "tgn:7012149",
        "tgn:7007516",
        "tgn:7029392"
    ],
    "tgn:id":2681615,
    "tgn:name":"South Prong Wicomico River",
    "tgn:placetype":[
        "aat:300008707"
    ]
},
  "bbox": [],
  "geometry": {"coordinates":[-75.5667,38.35],"type":"Point"}
}