{
  "id": 2618278,
  "type": "Feature",
  "properties": {
    "tgn:hierarchy":[
        "tgn:2618278",
        "tgn:1000001",
        "tgn:7012149",
        "tgn:2002189",
        "tgn:7007919",
        "tgn:7029392"
    ],
    "tgn:id":2618278,
    "tgn:name":"Riggs Chapel Cave",
    "tgn:placetype":[
        "aat:300008746"
    ]
},
  "bbox": [],
  "geometry": {"coordinates":[-82.6667,36.7333],"type":"Point"}
}