{
  "id": 2536290,
  "type": "Feature",
  "properties": {
    "tgn:hierarchy":[
        "tgn:2536290",
        "tgn:1000001",
        "tgn:7012149",
        "tgn:7007157",
        "tgn:2000185",
        "tgn:7029392"
    ],
    "tgn:id":2536290,
    "tgn:name":"Navarro Ridge",
    "tgn:placetype":[
        "aat:300266640"
    ]
},
  "bbox": [],
  "geometry": {"coordinates":[-123.6833,39.1833],"type":"Point"}
}