{
  "id": 7337068,
  "type": "Feature",
  "properties": {
    "tgn:hierarchy":[
        "tgn:7337068",
        "tgn:7002808",
        "tgn:7030216",
        "tgn:1000003",
        "tgn:1000095",
        "tgn:7029392"
    ],
    "tgn:id":7337068,
    "tgn:name":"Corr\u00f3 de Vall",
    "tgn:placetype":[
        "aat:300008347"
    ]
},
  "bbox": [],
  "geometry": {"coordinates":[2.302641,41.631515],"type":"Point"}
}