{
  "id": 2286974,
  "type": "Feature",
  "properties": {
    "tgn:hierarchy":[
        "tgn:2286974",
        "tgn:1000001",
        "tgn:7012149",
        "tgn:1002993",
        "tgn:7007568",
        "tgn:7029392"
    ],
    "tgn:id":2286974,
    "tgn:name":"Dick Hill",
    "tgn:placetype":[
        "aat:300008798"
    ]
},
  "bbox": [],
  "geometry": {"coordinates":[-73.3667,43.35],"type":"Point"}
}