{
  "id": 7530108,
  "type": "Feature",
  "properties": {
    "tgn:hierarchy":[
        "tgn:7530108",
        "tgn:7001242",
        "tgn:7016833",
        "tgn:7001335",
        "tgn:7029392"
    ],
    "tgn:id":7530108,
    "tgn:name":"Khuzayrat Umm San\u0101k, W\u0101d\u012b",
    "tgn:placetype":[
        "aat:300379998"
    ]
},
  "bbox": [],
  "geometry": {"coordinates":[34.129605,30.076083],"type":"Point"}
}