{
  "id": 1043173,
  "type": "Feature",
  "properties": {
    "tgn:hierarchy":[
        "tgn:1043173",
        "tgn:7009084",
        "tgn:7004154",
        "tgn:1000003",
        "tgn:1000080",
        "tgn:7029392"
    ],
    "tgn:id":1043173,
    "tgn:name":"Alfedena",
    "tgn:placetype":[
        "aat:300008347"
    ]
},
  "bbox": [],
  "geometry": {"coordinates":[14.033333,41.733333],"type":"Point"}
}