<<<<<<< HEAD
{
  "id": 7369687,
  "type": "Feature",
  "properties": {
    "tgn:hierarchy":[
        "tgn:7369687",
        "tgn:7005583",
        "tgn:1000001",
        "tgn:7005560",
        "tgn:7029392"
    ],
    "tgn:id":7369687,
    "tgn:name":"Huarichic",
    "tgn:placetype":[
        "aat:300008347"
    ]
},
  "bbox": [],
  "geometry": {"coordinates":[-103.7,25.2],"type":"Point"}
}
=======
{"geometry":{"type":"Point","coordinates":[-103.700000,25.200000]},"type":"Feature","properties":{"hierarchy":["tgn:7369687","tgn:7005583","tgn:1000001","tgn:7005560","tgn:7029392"],"placetype":["aat:300008347"],"id":7369687,"name:xx":"Huarichic"}}
>>>>>>> 03f74aca74312dbeaf24d7e61306dd6a786dc3d0
