{
  "id": 2699852,
  "type": "Feature",
  "properties": {
    "tgn:hierarchy":[
        "tgn:2699852",
        "tgn:1000001",
        "tgn:7012149",
        "tgn:2001286",
        "tgn:7007524",
        "tgn:7029392"
    ],
    "tgn:id":2699852,
    "tgn:name":"Studebaker Draw",
    "tgn:placetype":[
        "aat:300008761"
    ]
},
  "bbox": [],
  "geometry": {"coordinates":[-115.7833,48.5833],"type":"Point"}
}