{
  "id": 2689721,
  "type": "Feature",
  "properties": {
    "tgn:hierarchy":[
        "tgn:2689721",
        "tgn:1000001",
        "tgn:7012149",
        "tgn:2001455",
        "tgn:7007566",
        "tgn:7029392"
    ],
    "tgn:id":2689721,
    "tgn:name":"Squaw Tit",
    "tgn:placetype":[
        "aat:300008798"
    ]
},
  "bbox": [],
  "geometry": {"coordinates":[-106.6167,32.9833],"type":"Point"}
}