<<<<<<< HEAD
{
  "id": 2254582,
  "type": "Feature",
  "properties": {
    "tgn:hierarchy":[
        "tgn:2254582",
        "tgn:1002141",
        "tgn:1000001",
        "tgn:7012149",
        "tgn:7007568",
        "tgn:7029392"
    ],
    "tgn:id":2254582,
    "tgn:name":"Coon Hollow",
    "tgn:placetype":[
        "aat:300008761"
    ]
},
  "bbox": [],
  "geometry": {"coordinates":[-78.2167,42.0667],"type":"Point"}
}
=======
{"geometry":{"type":"Point","coordinates":[-78.216700,42.066700]},"type":"Feature","properties":{"hierarchy":["tgn:2254582","tgn:1002141","tgn:1000001","tgn:7012149","tgn:7007568","tgn:7029392"],"placetype":["aat:300008761"],"id":2254582,"name:xx":"Coon Hollow"}}
>>>>>>> 03f74aca74312dbeaf24d7e61306dd6a786dc3d0
