{
  "id": 7318638,
  "type": "Feature",
  "properties": {
    "tgn:hierarchy":[
        "tgn:7318638",
        "tgn:1001637",
        "tgn:1000049",
        "tgn:1000002",
        "tgn:7029392"
    ],
    "tgn:id":7318638,
    "tgn:name":"Colihue",
    "tgn:placetype":[
        "aat:300008347"
    ]
},
  "bbox": [],
  "geometry": {"coordinates":[-72.766667,-37.366667],"type":"Point"}
}