{
  "id": 7532646,
  "type": "Feature",
  "properties": {
    "tgn:hierarchy":[
        "tgn:7532646",
        "tgn:7001242",
        "tgn:7016833",
        "tgn:1001091",
        "tgn:7029392"
    ],
    "tgn:id":7532646,
    "tgn:name":"Masjid 'Al\u012b B\u0101sh\u0101",
    "tgn:placetype":[
        "aat:300007544"
    ]
},
  "bbox": [],
  "geometry": {"coordinates":[31.256354,30.042376],"type":"Point"}
}