{
  "id": 2159376,
  "type": "Feature",
  "properties": {
    "tgn:hierarchy":[
        "tgn:2159376",
        "tgn:1000001",
        "tgn:7012149",
        "tgn:2001862",
        "tgn:7007825",
        "tgn:7029392"
    ],
    "tgn:id":2159376,
    "tgn:name":"Bee Cliff Hollow",
    "tgn:placetype":[
        "aat:300008761"
    ]
},
  "bbox": [],
  "geometry": {"coordinates":[-85.8667,35.0833],"type":"Point"}
}