{
  "id": 2647880,
  "type": "Feature",
  "properties": {
    "tgn:hierarchy":[
        "tgn:2647880",
        "tgn:1000001",
        "tgn:2002146",
        "tgn:7012149",
        "tgn:7007919",
        "tgn:7029392"
    ],
    "tgn:id":2647880,
    "tgn:name":"Schoolhouse Branch",
    "tgn:placetype":[
        "aat:300008699"
    ]
},
  "bbox": [],
  "geometry": {"coordinates":[-79.9833,37.6333],"type":"Point"}
}