{
  "id": 7546690,
  "type": "Feature",
  "properties": {
    "tgn:hierarchy":[
        "tgn:7546690",
        "tgn:1000004",
        "tgn:7000198",
        "tgn:1001894",
        "tgn:7029392"
    ],
    "tgn:id":7546690,
    "tgn:name:en":"Antri",
    "tgn:placetype":[
        "aat:300008347"
    ]
},
  "bbox": [],
  "geometry": {"coordinates":[78.210265,26.058044],"type":"Point"}
}