{
  "id": 7546851,
  "type": "Feature",
  "properties": {
    "tgn:hierarchy":[
        "tgn:7546851",
        "tgn:1000004",
        "tgn:1001869",
        "tgn:7000198",
        "tgn:7029392"
    ],
    "tgn:id":7546851,
    "tgn:name:en":"Balol",
    "tgn:placetype":[
        "aat:300008347"
    ]
},
  "bbox": [],
  "geometry": {"coordinates":[72.116667,22.533333],"type":"Point"}
}