{
  "id": 7034681,
  "type": "Feature",
  "properties": {
    "tgn:hierarchy":[
        "tgn:7034681",
        "tgn:7015163",
        "tgn:1000003",
        "tgn:7003121",
        "tgn:1000080",
        "tgn:7029392"
    ],
    "tgn:id":7034681,
    "tgn:name":"Secca, Cala",
    "tgn:placetype":[
        "aat:300132317"
    ]
},
  "bbox": [],
  "geometry": {"coordinates":[8.186389,40.954722],"type":"Point"}
}