{
  "id": 1021614,
  "type": "Feature",
  "properties": {
    "tgn:hierarchy":[
        "tgn:1021614",
        "tgn:7016581",
        "tgn:1000047",
        "tgn:7002455",
        "tgn:1000002",
        "tgn:7029392"
    ],
    "tgn:id":1021614,
    "tgn:name":"Igreja Nova",
    "tgn:placetype":[
        "aat:300008347"
    ]
},
  "bbox": [],
  "geometry": {"coordinates":[-36.65,-10.1167],"type":"Point"}
}