{
  "id": 7249512,
  "type": "Feature",
  "properties": {
    "tgn:hierarchy":[
        "tgn:7249512",
        "tgn:7003460",
        "tgn:1000003",
        "tgn:1000063",
        "tgn:4012014",
        "tgn:7029392"
    ],
    "tgn:id":7249512,
    "tgn:name":"Oudoumont",
    "tgn:placetype":[
        "aat:300008347"
    ]
},
  "bbox": [],
  "geometry": {"coordinates":[5.326146,50.624686],"type":"Point"}
}