<<<<<<< HEAD
{
  "id": 2766262,
  "type": "Feature",
  "properties": {
    "tgn:hierarchy":[
        "tgn:2766262",
        "tgn:1000001",
        "tgn:7012149",
        "tgn:7013940",
        "tgn:7007709",
        "tgn:7029392"
    ],
    "tgn:id":2766262,
    "tgn:name":"White Level",
    "tgn:placetype":[
        "aat:300008347"
    ]
},
  "bbox": [],
  "geometry": {"coordinates":[-78.1333,36.1167],"type":"Point"}
}
=======
{"geometry":{"type":"Point","coordinates":[-78.133300,36.116700]},"type":"Feature","properties":{"hierarchy":["tgn:2766262","tgn:1000001","tgn:7012149","tgn:7013940","tgn:7007709","tgn:7029392"],"placetype":["aat:300008347"],"id":2766262,"name:xx":"White Level"}}
>>>>>>> 03f74aca74312dbeaf24d7e61306dd6a786dc3d0
