{
  "id": 2058321,
  "type": "Feature",
  "properties": {
    "tgn:hierarchy":[
        "tgn:2058321",
        "tgn:1000001",
        "tgn:7012149",
        "tgn:2001209",
        "tgn:7007523",
        "tgn:7029392"
    ],
    "tgn:id":2058321,
    "tgn:name":"Central City",
    "tgn:placetype":[
        "aat:300008347"
    ]
},
  "bbox": [],
  "geometry": {"coordinates":[-94.5833,37.0833],"type":"Point"}
}