{
  "id": 2399671,
  "type": "Feature",
  "properties": {
    "tgn:hierarchy":[
        "tgn:2399671",
        "tgn:1000001",
        "tgn:7012149",
        "tgn:2001534",
        "tgn:7007709",
        "tgn:7029392"
    ],
    "tgn:id":2399671,
    "tgn:name":"Horns Old Millpond",
    "tgn:placetype":[
        "aat:300006191"
    ]
},
  "bbox": [],
  "geometry": {"coordinates":[-79.1833,34.45],"type":"Point"}
}