{
  "id": 2326481,
  "type": "Feature",
  "properties": {
    "tgn:hierarchy":[
        "tgn:2326481",
        "tgn:1000001",
        "tgn:2001266",
        "tgn:7012149",
        "tgn:7007524",
        "tgn:7029392"
    ],
    "tgn:id":2326481,
    "tgn:name":"Finigan Creek",
    "tgn:placetype":[
        "aat:300008706"
    ]
},
  "bbox": [],
  "geometry": {"coordinates":[-111.8167,47.2333],"type":"Point"}
}