{
  "id": 7375904,
  "type": "Feature",
  "properties": {
    "tgn:hierarchy":[
        "tgn:7375904",
        "tgn:1001853",
        "tgn:1000001",
        "tgn:7005560",
        "tgn:7029392"
    ],
    "tgn:id":7375904,
    "tgn:name":"Las Higueras",
    "tgn:placetype":[
        "aat:300008347"
    ]
},
  "bbox": [],
  "geometry": {"coordinates":[-101.666667,27.416667],"type":"Point"}
}