<<<<<<< HEAD
{
  "id": 2336217,
  "type": "Feature",
  "properties": {
    "tgn:hierarchy":[
        "tgn:2336217",
        "tgn:1000001",
        "tgn:2000866",
        "tgn:7012149",
        "tgn:7007256",
        "tgn:7029392"
    ],
    "tgn:id":2336217,
    "tgn:name":"Foster Ridge",
    "tgn:placetype":[
        "aat:300266640"
    ]
},
  "bbox": [],
  "geometry": {"coordinates":[-91.8833,31.3833],"type":"Point"}
}
=======
{"geometry":{"type":"Point","coordinates":[-91.883300,31.383300]},"type":"Feature","properties":{"hierarchy":["tgn:2336217","tgn:1000001","tgn:2000866","tgn:7012149","tgn:7007256","tgn:7029392"],"placetype":["aat:300266640"],"id":2336217,"name:xx":"Foster Ridge"}}
>>>>>>> 03f74aca74312dbeaf24d7e61306dd6a786dc3d0
