{
  "id": 7467616,
  "type": "Feature",
  "properties": {
    "tgn:hierarchy":[
        "tgn:7467616",
        "tgn:1000004",
        "tgn:7490934",
        "tgn:1000141",
        "tgn:7029392"
    ],
    "tgn:id":7467616,
    "tgn:name":"Anye",
    "tgn:placetype":[
        "aat:300008347"
    ]
},
  "bbox": [],
  "geometry": {"coordinates":[120.245,23.158611],"type":"Point"}
}