{
  "id": 2569579,
  "type": "Feature",
  "properties": {
    "tgn:hierarchy":[
        "tgn:2569579",
        "tgn:7006450",
        "tgn:1000001",
        "tgn:7012149",
        "tgn:2000082",
        "tgn:7029392"
    ],
    "tgn:id":2569579,
    "tgn:name":"Parrot Lake",
    "tgn:placetype":[
        "aat:300008680"
    ]
},
  "bbox": [],
  "geometry": {"coordinates":[-132.8667,54.8167],"type":"Point"}
}