{
  "id": 7078127,
  "type": "Feature",
  "properties": {
    "tgn:hierarchy":[
        "tgn:7078127",
        "tgn:1000003",
        "tgn:7003687",
        "tgn:7000084",
        "tgn:7029392"
    ],
    "tgn:id":7078127,
    "tgn:name":"Siestedt",
    "tgn:placetype":[
        "aat:300387200"
    ]
},
  "bbox": [],
  "geometry": {"coordinates":[11.083333,52.316667],"type":"Point"}
}