{
  "id": 7093017,
  "type": "Feature",
  "properties": {
    "tgn:hierarchy":[
        "tgn:7093017",
        "tgn:7003669",
        "tgn:1000003",
        "tgn:7000084",
        "tgn:7029392"
    ],
    "tgn:id":7093017,
    "tgn:name":"Schwande",
    "tgn:placetype":[
        "aat:300000206"
    ]
},
  "bbox": [],
  "geometry": {"coordinates":[10.266667,47.416667],"type":"Point"}
}