{
  "id": 7285511,
  "type": "Feature",
  "properties": {
    "tgn:hierarchy":[
        "tgn:7285511",
        "tgn:1001657",
        "tgn:1000049",
        "tgn:1000002",
        "tgn:7029392"
    ],
    "tgn:id":7285511,
    "tgn:name":"Pueblo Nuevo",
    "tgn:placetype":[
        "aat:300008347"
    ]
},
  "bbox": [],
  "geometry": {"coordinates":[-71.233333,-30.85],"type":"Point"}
}