<<<<<<< HEAD
{
  "id": 2401007,
  "type": "Feature",
  "properties": {
    "tgn:hierarchy":[
        "tgn:2401007",
        "tgn:1000001",
        "tgn:7006451",
        "tgn:7012149",
        "tgn:2000104",
        "tgn:7029392"
    ],
    "tgn:id":2401007,
    "tgn:name":"Horse Tanks",
    "tgn:placetype":[
        "aat:300006191"
    ]
},
  "bbox": [],
  "geometry": {"coordinates":[-114.2,33.2],"type":"Point"}
}
=======
{"geometry":{"type":"Point","coordinates":[-114.200000,33.200000]},"type":"Feature","properties":{"hierarchy":["tgn:2401007","tgn:1000001","tgn:7006451","tgn:7012149","tgn:2000104","tgn:7029392"],"placetype":["aat:300006191"],"id":2401007,"name:xx":"Horse Tanks"}}
>>>>>>> 03f74aca74312dbeaf24d7e61306dd6a786dc3d0
