{
  "id": 7348072,
  "type": "Feature",
  "properties": {
    "tgn:hierarchy":[
        "tgn:7348072",
        "tgn:7002758",
        "tgn:7002830",
        "tgn:1000003",
        "tgn:1000095",
        "tgn:7029392"
    ],
    "tgn:id":7348072,
    "tgn:name":"Alaminos, Cerro",
    "tgn:placetype":[
        "aat:300008777"
    ]
},
  "bbox": [],
  "geometry": {"coordinates":[-4.733333,36.616667],"type":"Point"}
}