{
  "id": 7333759,
  "type": "Feature",
  "properties": {
    "tgn:hierarchy":[
        "tgn:7333759",
        "tgn:7002825",
        "tgn:7016622",
        "tgn:1000003",
        "tgn:1000095",
        "tgn:7029392"
    ],
    "tgn:id":7333759,
    "tgn:name":"Escamas, Punta",
    "tgn:placetype":[
        "aat:300386846"
    ]
},
  "bbox": [],
  "geometry": {"coordinates":[-13.416667,29.15],"type":"Point"}
}