{
  "id": 2536556,
  "type": "Feature",
  "properties": {
    "tgn:hierarchy":[
        "tgn:2536556",
        "tgn:2124017",
        "tgn:7006450",
        "tgn:1000001",
        "tgn:7012149",
        "tgn:7029392"
    ],
    "tgn:id":2536556,
    "tgn:name":"Near Point",
    "tgn:placetype":[
        "aat:300008798"
    ]
},
  "bbox": [],
  "geometry": {"coordinates":[-149.65,61.15],"type":"Point"}
}