<<<<<<< HEAD
{
  "id": 7111892,
  "type": "Feature",
  "properties": {
    "tgn:hierarchy":[
        "tgn:7111892",
        "tgn:7003669",
        "tgn:1000003",
        "tgn:7000084",
        "tgn:7029392"
    ],
    "tgn:id":7111892,
    "tgn:name":"Richardsreut",
    "tgn:placetype":[
        "aat:300008347"
    ]
},
  "bbox": [],
  "geometry": {"coordinates":[13.6,48.733333],"type":"Point"}
}
=======
{"geometry":{"type":"Point","coordinates":[13.600000,48.733333]},"type":"Feature","properties":{"hierarchy":["tgn:7111892","tgn:7003669","tgn:1000003","tgn:7000084","tgn:7029392"],"placetype":["aat:300008347"],"id":7111892,"name:xx":"Richardsreut"}}
>>>>>>> 03f74aca74312dbeaf24d7e61306dd6a786dc3d0
