{
  "id": 7321676,
  "type": "Feature",
  "properties": {
    "tgn:hierarchy":[
        "tgn:7321676",
        "tgn:7016598",
        "tgn:1000049",
        "tgn:1000002",
        "tgn:7029392"
    ],
    "tgn:id":7321676,
    "tgn:name":"Callejon Tresajos, Quebrada",
    "tgn:placetype":[
        "aat:300266554",
        "aat:300008699"
    ]
},
  "bbox": [],
  "geometry": {"coordinates":[-68.233333,-21.566667],"type":"Point"}
}