{
  "id": 2282088,
  "type": "Feature",
  "properties": {
    "tgn:hierarchy":[
        "tgn:2282088",
        "tgn:1000001",
        "tgn:7012149",
        "tgn:1002392",
        "tgn:7007157",
        "tgn:7029392"
    ],
    "tgn:id":2282088,
    "tgn:name":"Deer Lake",
    "tgn:placetype":[
        "aat:300008680"
    ]
},
  "bbox": [],
  "geometry": {"coordinates":[-119.0833,37.2833],"type":"Point"}
}