{
  "id": 7535484,
  "type": "Feature",
  "properties": {
    "tgn:hierarchy":[
        "tgn:7535484",
        "tgn:7001242",
        "tgn:7016833",
        "tgn:1001113",
        "tgn:7029392"
    ],
    "tgn:id":7535484,
    "tgn:name":"Kafr al B\u0101z",
    "tgn:placetype":[
        "aat:300008347"
    ]
},
  "bbox": [],
  "geometry": {"coordinates":[31.703298,30.725994],"type":"Point"}
}