<<<<<<< HEAD
{
  "id": 7378096,
  "type": "Feature",
  "properties": {
    "tgn:hierarchy":[
        "tgn:7378096",
        "tgn:1000001",
        "tgn:1001960",
        "tgn:7005560",
        "tgn:7029392"
    ],
    "tgn:id":7378096,
    "tgn:name":"Rancho Las Chinches",
    "tgn:placetype":[
        "aat:300000241"
    ]
},
  "bbox": [],
  "geometry": {"coordinates":[-110.116667,28.516667],"type":"Point"}
}
=======
{"geometry":{"type":"Point","coordinates":[-110.116667,28.516667]},"type":"Feature","properties":{"hierarchy":["tgn:7378096","tgn:1000001","tgn:1001960","tgn:7005560","tgn:7029392"],"placetype":["aat:300000241"],"id":7378096,"name:xx":"Rancho Las Chinches"}}
>>>>>>> 03f74aca74312dbeaf24d7e61306dd6a786dc3d0
