{
  "id": 2400634,
  "type": "Feature",
  "properties": {
    "tgn:hierarchy":[
        "tgn:2400634",
        "tgn:1000001",
        "tgn:7012149",
        "tgn:2000494",
        "tgn:7007250",
        "tgn:7029392"
    ],
    "tgn:id":2400634,
    "tgn:name":"Horse Mountain",
    "tgn:placetype":[
        "aat:300008798"
    ]
},
  "bbox": [],
  "geometry": {"coordinates":[-114.8667,45.1167],"type":"Point"}
}