{
  "id": 7543672,
  "type": "Feature",
  "properties": {
    "tgn:hierarchy":[
        "tgn:7543672",
        "tgn:7001242",
        "tgn:7016833",
        "tgn:7001336",
        "tgn:7029392"
    ],
    "tgn:id":7543672,
    "tgn:name":"Darb al Kh\u016btl\u012bah",
    "tgn:placetype":[
        "aat:300000626"
    ]
},
  "bbox": [],
  "geometry": {"coordinates":[33.255833,29.836389],"type":"Point"}
}