{
  "id": 7061145,
  "type": "Feature",
  "properties": {
    "tgn:hierarchy":[
        "tgn:7061145",
        "tgn:1000003",
        "tgn:7003688",
        "tgn:7000084",
        "tgn:7029392"
    ],
    "tgn:id":7061145,
    "tgn:name":"Aschenberg",
    "tgn:placetype":[
        "aat:300000206"
    ]
},
  "bbox": [],
  "geometry": {"coordinates":[9.983333,54.533333],"type":"Point"}
}