{
  "id": 2456037,
  "type": "Feature",
  "properties": {
    "tgn:hierarchy":[
        "tgn:2456037",
        "tgn:1000001",
        "tgn:2001261",
        "tgn:7012149",
        "tgn:7007524",
        "tgn:7029392"
    ],
    "tgn:id":2456037,
    "tgn:name":"Little Hawk Lake",
    "tgn:placetype":[
        "aat:300008680"
    ]
},
  "bbox": [],
  "geometry": {"coordinates":[-106.9167,45.5833],"type":"Point"}
}