{
  "id": 7297909,
  "type": "Feature",
  "properties": {
    "tgn:hierarchy":[
        "tgn:7297909",
        "tgn:7002807",
        "tgn:1000003",
        "tgn:7003837",
        "tgn:1000095",
        "tgn:7029392"
    ],
    "tgn:id":7297909,
    "tgn:name":"Soledad",
    "tgn:placetype":[
        "aat:300008347"
    ]
},
  "bbox": [],
  "geometry": {"coordinates":[-6.466667,38.65],"type":"Point"}
}