{
  "id": 2202579,
  "type": "Feature",
  "properties": {
    "tgn:hierarchy":[
        "tgn:2202579",
        "tgn:1000001",
        "tgn:7016172",
        "tgn:2000120",
        "tgn:7012149",
        "tgn:7029392"
    ],
    "tgn:id":2202579,
    "tgn:name":"Buck Snort",
    "tgn:placetype":[
        "aat:300008347"
    ]
},
  "bbox": [],
  "geometry": {"coordinates":[-90.6333,35.8833],"type":"Point"}
}