<<<<<<< HEAD
{
  "id": 2338900,
  "type": "Feature",
  "properties": {
    "tgn:hierarchy":[
        "tgn:2338900",
        "tgn:1000001",
        "tgn:7012149",
        "tgn:2000785",
        "tgn:7007255",
        "tgn:7029392"
    ],
    "tgn:id":2338900,
    "tgn:name":"Franklin Branch",
    "tgn:placetype":[
        "aat:300008699"
    ]
},
  "bbox": [],
  "geometry": {"coordinates":[-85.4667,36.85],"type":"Point"}
}
=======
{"geometry":{"type":"Point","coordinates":[-85.466700,36.850000]},"type":"Feature","properties":{"hierarchy":["tgn:2338900","tgn:1000001","tgn:7012149","tgn:2000785","tgn:7007255","tgn:7029392"],"placetype":["aat:300008699"],"id":2338900,"name:xx":"Franklin Branch"}}
>>>>>>> 03f74aca74312dbeaf24d7e61306dd6a786dc3d0
