{
  "id": 2315031,
  "type": "Feature",
  "properties": {
    "tgn:hierarchy":[
        "tgn:2315031",
        "tgn:1000001",
        "tgn:2001411",
        "tgn:7012149",
        "tgn:7007526",
        "tgn:7029392"
    ],
    "tgn:id":2315031,
    "tgn:name":"Elko Summit Reservoir Number One",
    "tgn:placetype":[
        "aat:300006191"
    ]
},
  "bbox": [],
  "geometry": {"coordinates":[-115.7167,40.75],"type":"Point"}
}