{
  "id": 1101650,
  "type": "Feature",
  "properties": {
    "tgn:hierarchy":[
        "tgn:1101650",
        "tgn:1000004",
        "tgn:1001372",
        "tgn:7000299",
        "tgn:7029392"
    ],
    "tgn:id":1101650,
    "tgn:name":"Ky\u014fngju Kukrip Kongw\u014fn",
    "tgn:placetype":[
        "aat:300008189"
    ]
},
  "bbox": [],
  "geometry": {"coordinates":[129.25,35.7833],"type":"Point"}
}