{
  "id": 2542883,
  "type": "Feature",
  "properties": {
    "tgn:hierarchy":[
        "tgn:2542883",
        "tgn:1000001",
        "tgn:2000470",
        "tgn:7012149",
        "tgn:7007250",
        "tgn:7029392"
    ],
    "tgn:id":2542883,
    "tgn:name":"Nolan Lake",
    "tgn:placetype":[
        "aat:300006191"
    ]
},
  "bbox": [],
  "geometry": {"coordinates":[-113.5333,44.0167],"type":"Point"}
}