{
  "id": 2423629,
  "type": "Feature",
  "properties": {
    "tgn:hierarchy":[
        "tgn:2423629",
        "tgn:2002365",
        "tgn:1000001",
        "tgn:7012149",
        "tgn:7007923",
        "tgn:7029392"
    ],
    "tgn:id":2423629,
    "tgn:name":"John McCreary Ditch",
    "tgn:placetype":[
        "aat:300006075"
    ]
},
  "bbox": [],
  "geometry": {"coordinates":[-105.9667,41.3167],"type":"Point"}
}