{
  "id": 2354364,
  "type": "Feature",
  "properties": {
    "tgn:hierarchy":[
        "tgn:2354364",
        "tgn:1000001",
        "tgn:7012149",
        "tgn:2001104",
        "tgn:7007522",
        "tgn:7029392"
    ],
    "tgn:id":2354364,
    "tgn:name":"Goldman Branch",
    "tgn:placetype":[
        "aat:300008699"
    ]
},
  "bbox": [],
  "geometry": {"coordinates":[-90.7667,31.5333],"type":"Point"}
}