{
  "id": 2394112,
  "type": "Feature",
  "properties": {
    "tgn:hierarchy":[
        "tgn:2394112",
        "tgn:1000001",
        "tgn:7012149",
        "tgn:7007709",
        "tgn:7029392"
    ],
    "tgn:id":2394112,
    "tgn:name":"Hogan Creek",
    "tgn:placetype":[
        "aat:300008706"
    ]
},
  "bbox": [],
  "geometry": {"coordinates":[-80.6167,36.35],"type":"Point"}
}