{
  "id": 7540164,
  "type": "Feature",
  "properties": {
    "tgn:hierarchy":[
        "tgn:7540164",
        "tgn:7001242",
        "tgn:7016833",
        "tgn:1001225",
        "tgn:7029392"
    ],
    "tgn:id":7540164,
    "tgn:name:en":"Saqq\u0101yah, Birkat as",
    "tgn:placetype":[
        "aat:300008680"
    ]
},
  "bbox": [],
  "geometry": {"coordinates":[31.775137,31.291052],"type":"Point"}
}