{
  "id": 1049333,
  "type": "Feature",
  "properties": {
    "tgn:hierarchy":[
        "tgn:1049333",
        "tgn:1000003",
        "tgn:7024119",
        "tgn:7006366",
        "tgn:7029392"
    ],
    "tgn:id":1049333,
    "tgn:name":"Ostr\u00f3w Wielkopolski",
    "tgn:placetype":[
        "aat:300008347",
        "aat:300008389",
        "aat:300387270",
        "aat:300387302"
    ]
},
  "bbox": [],
  "geometry": {"coordinates":[17.8167,51.65],"type":"Point"}
}