{
  "id": 7224752,
  "type": "Feature",
  "properties": {
    "tgn:hierarchy":[
        "tgn:7224752",
        "tgn:7002728",
        "tgn:7002715",
        "tgn:1000003",
        "tgn:1000074",
        "tgn:7029392"
    ],
    "tgn:id":7224752,
    "tgn:name":"Riz\u00e1rion",
    "tgn:placetype":[
        "aat:300008347"
    ]
},
  "bbox": [],
  "geometry": {"coordinates":[22.083889,40.787222],"type":"Point"}
}