{
  "id": 7284737,
  "type": "Feature",
  "properties": {
    "tgn:hierarchy":[
        "tgn:7284737",
        "tgn:7002464",
        "tgn:1000049",
        "tgn:1000002",
        "tgn:7029392"
    ],
    "tgn:id":7284737,
    "tgn:name":"Piguagua, Quebrada",
    "tgn:placetype":[
        "aat:300266554",
        "aat:300008699"
    ]
},
  "bbox": [],
  "geometry": {"coordinates":[-69.233333,-19.783333],"type":"Point"}
}