{
  "id": 7068148,
  "type": "Feature",
  "properties": {
    "tgn:hierarchy":[
        "tgn:7068148",
        "tgn:7003669",
        "tgn:1000003",
        "tgn:7000084",
        "tgn:7029392"
    ],
    "tgn:id":7068148,
    "tgn:name":"Tribur",
    "tgn:placetype":[
        "aat:300008347"
    ]
},
  "bbox": [],
  "geometry": {"coordinates":[10.283333,49.15],"type":"Point"}
}