{
  "id": 2371820,
  "type": "Feature",
  "properties": {
    "tgn:hierarchy":[
        "tgn:2371820",
        "tgn:1000001",
        "tgn:7012149",
        "tgn:7029392"
    ],
    "tgn:id":2371820,
    "tgn:name":"Hales Fork",
    "tgn:placetype":[
        "aat:300008699"
    ]
},
  "bbox": [],
  "geometry": {"coordinates":[-85.8333,33.8667],"type":"Point"}
}