{
  "id": 2697452,
  "type": "Feature",
  "properties": {
    "tgn:hierarchy":[
        "tgn:2697452",
        "tgn:1000001",
        "tgn:7012149",
        "tgn:1002392",
        "tgn:7007157",
        "tgn:7029392"
    ],
    "tgn:id":2697452,
    "tgn:name":"Stony Point",
    "tgn:placetype":[
        "aat:300008798"
    ]
},
  "bbox": [],
  "geometry": {"coordinates":[-119.45,36.8333],"type":"Point"}
}