{
  "id": 7008648,
  "type": "Feature",
  "properties": {
    "tgn:hierarchy":[
        "tgn:7008648",
        "tgn:1000003",
        "tgn:7002875",
        "tgn:1000070",
        "tgn:7029392"
    ],
    "tgn:id":7008648,
    "tgn:name":"Arcy-sur-Cure",
    "tgn:placetype":[
        "aat:300008347",
        "aat:300387006"
    ]
},
  "bbox": [],
  "geometry": {"coordinates":[3.75,47.7667],"type":"Point"}
}