{
  "id": 2704022,
  "type": "Feature",
  "properties": {
    "tgn:hierarchy":[
        "tgn:2704022",
        "tgn:1000001",
        "tgn:7012149",
        "tgn:2001709",
        "tgn:7007708",
        "tgn:7029392"
    ],
    "tgn:id":2704022,
    "tgn:name":"Sundown Ridge",
    "tgn:placetype":[
        "aat:300266640"
    ]
},
  "bbox": [],
  "geometry": {"coordinates":[-119.35,43.6167],"type":"Point"}
}