{
  "id": 2524441,
  "type": "Feature",
  "properties": {
    "tgn:hierarchy":[
        "tgn:2524441",
        "tgn:1000001",
        "tgn:7012149",
        "tgn:2001225",
        "tgn:7007523",
        "tgn:7029392"
    ],
    "tgn:id":2524441,
    "tgn:name":"Morgan Spring",
    "tgn:placetype":[
        "aat:300008697"
    ]
},
  "bbox": [],
  "geometry": {"coordinates":[-91.1833,36.55],"type":"Point"}
}