<<<<<<< HEAD
{
  "id": 2402533,
  "type": "Feature",
  "properties": {
    "tgn:hierarchy":[
        "tgn:2402533",
        "tgn:1000001",
        "tgn:7012149",
        "tgn:2001716",
        "tgn:7007708",
        "tgn:7029392"
    ],
    "tgn:id":2402533,
    "tgn:name":"Hospital Creek",
    "tgn:placetype":[
        "aat:300008706"
    ]
},
  "bbox": [],
  "geometry": {"coordinates":[-122.55,43.8333],"type":"Point"}
}
=======
{"geometry":{"type":"Point","coordinates":[-122.550000,43.833300]},"type":"Feature","properties":{"hierarchy":["tgn:2402533","tgn:1000001","tgn:7012149","tgn:2001716","tgn:7007708","tgn:7029392"],"placetype":["aat:300008706"],"id":2402533,"name:xx":"Hospital Creek"}}
>>>>>>> 03f74aca74312dbeaf24d7e61306dd6a786dc3d0
