{
  "id": 2174445,
  "type": "Feature",
  "properties": {
    "tgn:hierarchy":[
        "tgn:2174445",
        "tgn:1000001",
        "tgn:2001747",
        "tgn:7012149",
        "tgn:7007712",
        "tgn:7029392"
    ],
    "tgn:id":2174445,
    "tgn:name":"Bishop Heights",
    "tgn:placetype":[
        "aat:300008347"
    ]
},
  "bbox": [],
  "geometry": {"coordinates":[-82.3167,34.7667],"type":"Point"}
}