{
  "id": 7412436,
  "type": "Feature",
  "properties": {
    "tgn:hierarchy":[
        "tgn:7412436",
        "tgn:7005587",
        "tgn:1000001",
        "tgn:7005560",
        "tgn:7029392"
    ],
    "tgn:id":7412436,
    "tgn:name:es":"Puerto La Palma",
    "tgn:placetype":[
        "aat:300008347"
    ]
},
  "bbox": [],
  "geometry": {"coordinates":[-98.836111,20.179167],"type":"Point"}
}