{
  "id": 7238322,
  "type": "Feature",
  "properties": {
    "tgn:hierarchy":[
        "tgn:7238322",
        "tgn:7003456",
        "tgn:1000003",
        "tgn:1000063",
        "tgn:7018236",
        "tgn:7029392"
    ],
    "tgn:id":7238322,
    "tgn:name":"Het Spek",
    "tgn:placetype":[
        "aat:300008347"
    ]
},
  "bbox": [],
  "geometry": {"coordinates":[4.711077,51.08211],"type":"Point"}
}