{
  "id": 2375844,
  "type": "Feature",
  "properties": {
    "tgn:hierarchy":[
        "tgn:2375844",
        "tgn:1000001",
        "tgn:7012149",
        "tgn:2000711",
        "tgn:7007254",
        "tgn:7029392"
    ],
    "tgn:id":2375844,
    "tgn:name":"Happy Hollow Lake",
    "tgn:placetype":[
        "aat:300006191"
    ]
},
  "bbox": [],
  "geometry": {"coordinates":[-95.0333,39.3333],"type":"Point"}
}