{
  "id": 7080181,
  "type": "Feature",
  "properties": {
    "tgn:hierarchy":[
        "tgn:7080181",
        "tgn:1000003",
        "tgn:7003677",
        "tgn:7000084",
        "tgn:7029392"
    ],
    "tgn:id":7080181,
    "tgn:name":"Winterberg",
    "tgn:placetype":[
        "aat:300387200"
    ]
},
  "bbox": [],
  "geometry": {"coordinates":[8.883333,52.166667],"type":"Point"}
}