{
  "id": 2219350,
  "type": "Feature",
  "properties": {
    "tgn:hierarchy":[
        "tgn:2219350",
        "tgn:1000001",
        "tgn:7012149",
        "tgn:2000476",
        "tgn:7007250",
        "tgn:7029392"
    ],
    "tgn:id":2219350,
    "tgn:name":"Cannon Ball Mountain",
    "tgn:placetype":[
        "aat:300008798"
    ]
},
  "bbox": [],
  "geometry": {"coordinates":[-116.4667,45.3167],"type":"Point"}
}