{
  "id": 2243770,
  "type": "Feature",
  "properties": {
    "tgn:hierarchy":[
        "tgn:2243770",
        "tgn:1000001",
        "tgn:7012149",
        "tgn:2001456",
        "tgn:7007566",
        "tgn:7029392"
    ],
    "tgn:id":2243770,
    "tgn:name":"Clequa Tank",
    "tgn:placetype":[
        "aat:300006191"
    ]
},
  "bbox": [],
  "geometry": {"coordinates":[-107.05,34.55],"type":"Point"}
}