{
  "id": 7014121,
  "type": "Feature",
  "properties": {
    "tgn:hierarchy":[
        "tgn:7014121",
        "tgn:2000002",
        "tgn:7002659",
        "tgn:1000001",
        "tgn:7012149",
        "tgn:7029392"
    ],
    "tgn:id":7014121,
    "tgn:name":"Eufaula",
    "tgn:placetype":[
        "aat:300008347"
    ]
},
  "bbox": [],
  "geometry": {"coordinates":[-85.1333,31.8833],"type":"Point"}
}