{
  "id": 7591885,
  "type": "Feature",
  "properties": {
    "tgn:hierarchy":[
        "tgn:7591885",
        "tgn:1000004",
        "tgn:7000198",
        "tgn:7000799",
        "tgn:7029392"
    ],
    "tgn:id":7591885,
    "tgn:name:en":"Paleh\u0101lw\u0101li Khad",
    "tgn:placetype":[
        "aat:300008699"
    ]
},
  "bbox": [],
  "geometry": {"coordinates":[74.927778,32.672222],"type":"Point"}
}