{
  "id": 7580499,
  "type": "Feature",
  "properties": {
    "tgn:hierarchy":[
        "tgn:7580499",
        "tgn:1000004",
        "tgn:7000198",
        "tgn:1001998",
        "tgn:7029392"
    ],
    "tgn:id":7580499,
    "tgn:name:en":"Thingsai",
    "tgn:placetype":[
        "aat:300008347"
    ]
},
  "bbox": [],
  "geometry": {"coordinates":[93.098675,22.928381],"type":"Point"}
}