<<<<<<< HEAD
{
  "id": 2402515,
  "type": "Feature",
  "properties": {
    "tgn:hierarchy":[
        "tgn:2402515",
        "tgn:1000001",
        "tgn:2000922",
        "tgn:7012149",
        "tgn:7007515",
        "tgn:7029392"
    ],
    "tgn:id":2402515,
    "tgn:name":"Hosmer Ledge",
    "tgn:placetype":[
        "aat:300132348"
    ]
},
  "bbox": [],
  "geometry": {"coordinates":[-68.8,44.3667],"type":"Point"}
}
=======
{"geometry":{"type":"Point","coordinates":[-68.800000,44.366700]},"type":"Feature","properties":{"hierarchy":["tgn:2402515","tgn:1000001","tgn:2000922","tgn:7012149","tgn:7007515","tgn:7029392"],"placetype":["aat:300132348"],"id":2402515,"name:xx":"Hosmer Ledge"}}
>>>>>>> 03f74aca74312dbeaf24d7e61306dd6a786dc3d0
