{
  "id": 7374923,
  "type": "Feature",
  "properties": {
    "tgn:hierarchy":[
        "tgn:7374923",
        "tgn:7005586",
        "tgn:1000001",
        "tgn:7005560",
        "tgn:7029392"
    ],
    "tgn:id":7374923,
    "tgn:name":"Labor de Medina",
    "tgn:placetype":[
        "aat:300008347"
    ]
},
  "bbox": [],
  "geometry": {"coordinates":[-103.916667,20.466667],"type":"Point"}
}