{
  "id": 7051774,
  "type": "Feature",
  "properties": {
    "tgn:hierarchy":[
        "tgn:7051774",
        "tgn:1003464",
        "tgn:1000003",
        "tgn:7003241",
        "tgn:1000080",
        "tgn:7029392"
    ],
    "tgn:id":7051774,
    "tgn:name":"Il Rio, Fiume",
    "tgn:placetype":[
        "aat:300008699"
    ]
},
  "bbox": [],
  "geometry": {"coordinates":[14.466667,41.516667],"type":"Point"}
}