{
  "id": 7554852,
  "type": "Feature",
  "properties": {
    "tgn:hierarchy":[
        "tgn:7554852",
        "tgn:1000004",
        "tgn:7000198",
        "tgn:1001894",
        "tgn:7029392"
    ],
    "tgn:id":7554852,
    "tgn:name:en":"Naigarh\u012b",
    "tgn:placetype":[
        "aat:300008347"
    ]
},
  "bbox": [],
  "geometry": {"coordinates":[81.777068,24.787776],"type":"Point"}
}