{
  "id": 7322246,
  "type": "Feature",
  "properties": {
    "tgn:hierarchy":[
        "tgn:7322246",
        "tgn:1001702",
        "tgn:1000049",
        "tgn:1000002",
        "tgn:7029392"
    ],
    "tgn:id":7322246,
    "tgn:name":"Bascu\u00f1\u00e1n, Islote",
    "tgn:placetype":[
        "aat:300008791"
    ]
},
  "bbox": [],
  "geometry": {"coordinates":[-75.288611,-50.358333],"type":"Point"}
}