{
  "id": 2378026,
  "type": "Feature",
  "properties": {
    "tgn:hierarchy":[
        "tgn:2378026",
        "tgn:1000001",
        "tgn:7012149",
        "tgn:2000332",
        "tgn:7007248",
        "tgn:7029392"
    ],
    "tgn:id":2378026,
    "tgn:name":"Harris Creek",
    "tgn:placetype":[
        "aat:300008706"
    ]
},
  "bbox": [],
  "geometry": {"coordinates":[-85.55,34.8833],"type":"Point"}
}