{
  "id": 2019229,
  "type": "Feature",
  "properties": {
    "tgn:hierarchy":[
        "tgn:2019229",
        "tgn:1000001",
        "tgn:7012149",
        "tgn:1002977",
        "tgn:7007240",
        "tgn:7029392"
    ],
    "tgn:id":2019229,
    "tgn:name":"Emporia",
    "tgn:placetype":[
        "aat:300008347"
    ]
},
  "bbox": [],
  "geometry": {"coordinates":[-81.4667,29.1833],"type":"Point"}
}