{
  "id": 2731939,
  "type": "Feature",
  "properties": {
    "tgn:hierarchy":[
        "tgn:2731939",
        "tgn:7006450",
        "tgn:1000001",
        "tgn:7019698",
        "tgn:7012149",
        "tgn:7029392"
    ],
    "tgn:id":2731939,
    "tgn:name":"Tundra Lake",
    "tgn:placetype":[
        "aat:300008680"
    ]
},
  "bbox": [],
  "geometry": {"coordinates":[-150.6333,60.85],"type":"Point"}
}