<<<<<<< HEAD
{
  "id": 7351967,
  "type": "Feature",
  "properties": {
    "tgn:hierarchy":[
        "tgn:7351967",
        "tgn:7005586",
        "tgn:1000001",
        "tgn:7005560",
        "tgn:7029392"
    ],
    "tgn:id":7351967,
    "tgn:name":"Calabazas",
    "tgn:placetype":[
        "aat:300000241"
    ]
},
  "bbox": [],
  "geometry": {"coordinates":[-102.616667,20.733333],"type":"Point"}
}
=======
{"geometry":{"type":"Point","coordinates":[-102.616667,20.733333]},"type":"Feature","properties":{"hierarchy":["tgn:7351967","tgn:7005586","tgn:1000001","tgn:7005560","tgn:7029392"],"placetype":["aat:300000241"],"id":7351967,"name:xx":"Calabazas"}}
>>>>>>> 03f74aca74312dbeaf24d7e61306dd6a786dc3d0
