{
  "id": 2561062,
  "type": "Feature",
  "properties": {
    "tgn:hierarchy":[
        "tgn:2561062",
        "tgn:1000001",
        "tgn:7012149",
        "tgn:2002346",
        "tgn:7007922",
        "tgn:7029392"
    ],
    "tgn:id":2561062,
    "tgn:name":"Orr Lake",
    "tgn:placetype":[
        "aat:300008680"
    ]
},
  "bbox": [],
  "geometry": {"coordinates":[-92.6667,45.6167],"type":"Point"}
}