{
  "id": 7161514,
  "type": "Feature",
  "properties": {
    "tgn:hierarchy":[
        "tgn:7161514",
        "tgn:7003669",
        "tgn:1000003",
        "tgn:7000084",
        "tgn:7029392"
    ],
    "tgn:id":7161514,
    "tgn:name":"H\u00f6chst\u00e4dten",
    "tgn:placetype":[
        "aat:300008347"
    ]
},
  "bbox": [],
  "geometry": {"coordinates":[10.766667,50.116667],"type":"Point"}
}