<<<<<<< HEAD
{
  "id": 7470693,
  "type": "Feature",
  "properties": {
    "tgn:hierarchy":[
        "tgn:7470693",
        "tgn:1000004",
        "tgn:7004300",
        "tgn:1000141",
        "tgn:7029392"
    ],
    "tgn:id":7470693,
    "tgn:name":"Qingluo",
    "tgn:placetype":[
        "aat:300008347"
    ]
},
  "bbox": [],
  "geometry": {"coordinates":[119.649513,23.599451],"type":"Point"}
}
=======
{"geometry":{"type":"Point","coordinates":[119.649513,23.599451]},"type":"Feature","properties":{"hierarchy":["tgn:7470693","tgn:1000004","tgn:7004300","tgn:1000141","tgn:7029392"],"placetype":["aat:300008347"],"id":7470693,"name:xx":"Qingluo"}}
>>>>>>> 03f74aca74312dbeaf24d7e61306dd6a786dc3d0
