{
  "id": 7470693,
  "type": "Feature",
  "properties": {
    "tgn:hierarchy":[
        "tgn:7470693",
        "tgn:1000004",
        "tgn:7004300",
        "tgn:1000141",
        "tgn:7029392"
    ],
    "tgn:id":7470693,
    "tgn:name":"Qingluo",
    "tgn:placetype":[
        "aat:300008347"
    ]
},
  "bbox": [],
  "geometry": {"coordinates":[119.649513,23.599451],"type":"Point"}
}