{
  "id": 7348114,
  "type": "Feature",
  "properties": {
    "tgn:hierarchy":[
        "tgn:7348114",
        "tgn:7002834",
        "tgn:1000003",
        "tgn:7002786",
        "tgn:1000095",
        "tgn:7029392"
    ],
    "tgn:id":7348114,
    "tgn:name":"\u00c1balo",
    "tgn:placetype":[
        "aat:300008347"
    ]
},
  "bbox": [],
  "geometry": {"coordinates":[-8.716667,42.65],"type":"Point"}
}