{
  "id": 2559813,
  "type": "Feature",
  "properties": {
    "tgn:hierarchy":[
        "tgn:2559813",
        "tgn:1000001",
        "tgn:7012149",
        "tgn:2000511",
        "tgn:7007251",
        "tgn:7029392"
    ],
    "tgn:id":2559813,
    "tgn:name":"Ophiem",
    "tgn:placetype":[
        "aat:300008347"
    ]
},
  "bbox": [],
  "geometry": {"coordinates":[-90.3833,41.25],"type":"Point"}
}