{
  "id": 2346389,
  "type": "Feature",
  "properties": {
    "tgn:hierarchy":[
        "tgn:2346389",
        "tgn:1000001",
        "tgn:7012149",
        "tgn:2001140",
        "tgn:7007522",
        "tgn:7029392"
    ],
    "tgn:id":2346389,
    "tgn:name":"Gator Lake",
    "tgn:placetype":[
        "aat:300008680"
    ]
},
  "bbox": [],
  "geometry": {"coordinates":[-89.7833,30.8333],"type":"Point"}
}