{
  "id": 2691095,
  "type": "Feature",
  "properties": {
    "tgn:hierarchy":[
        "tgn:2691095",
        "tgn:1000001",
        "tgn:7012149",
        "tgn:1002554",
        "tgn:7007920",
        "tgn:7029392"
    ],
    "tgn:id":2691095,
    "tgn:name":"Stanley Spring",
    "tgn:placetype":[
        "aat:300008697"
    ]
},
  "bbox": [],
  "geometry": {"coordinates":[-121.15,45.6833],"type":"Point"}
}