{
  "id": 7477141,
  "type": "Feature",
  "properties": {
    "tgn:hierarchy":[
        "tgn:7477141",
        "tgn:1000004",
        "tgn:7001013",
        "tgn:1000141",
        "tgn:7029392"
    ],
    "tgn:id":7477141,
    "tgn:name":"Dadaocheng",
    "tgn:placetype":[
        "aat:300008347"
    ]
},
  "bbox": [],
  "geometry": {"coordinates":[121.193853,25.015512],"type":"Point"}
}