{
  "id": 7479251,
  "type": "Feature",
  "properties": {
    "tgn:hierarchy":[
        "tgn:7479251",
        "tgn:1000004",
        "tgn:7491221",
        "tgn:1000141",
        "tgn:7029392"
    ],
    "tgn:id":7479251,
    "tgn:name":"Beikeng Luqiao",
    "tgn:placetype":[
        "aat:300007836"
    ]
},
  "bbox": [],
  "geometry": {"coordinates":[121.023611,22.656389],"type":"Point"}
}