<<<<<<< HEAD
{
  "id": 7479251,
  "type": "Feature",
  "properties": {
    "tgn:hierarchy":[
        "tgn:7479251",
        "tgn:1000004",
        "tgn:7491221",
        "tgn:1000141",
        "tgn:7029392"
    ],
    "tgn:id":7479251,
    "tgn:name":"Beikeng Luqiao",
    "tgn:placetype":[
        "aat:300007836"
    ]
},
  "bbox": [],
  "geometry": {"coordinates":[121.023611,22.656389],"type":"Point"}
}
=======
{"geometry":{"type":"Point","coordinates":[121.023611,22.656389]},"type":"Feature","properties":{"hierarchy":["tgn:7479251","tgn:1000004","tgn:7491221","tgn:1000141","tgn:7029392"],"placetype":["aat:300007836"],"id":7479251,"name:xx":"Beikeng Luqiao"}}
>>>>>>> 03f74aca74312dbeaf24d7e61306dd6a786dc3d0
