{
  "id": 2354429,
  "type": "Feature",
  "properties": {
    "tgn:hierarchy":[
        "tgn:2354429",
        "tgn:1000001",
        "tgn:2001775",
        "tgn:7012149",
        "tgn:7007713",
        "tgn:7029392"
    ],
    "tgn:id":2354429,
    "tgn:name":"Goldsmith, Lake",
    "tgn:placetype":[
        "aat:300008680"
    ]
},
  "bbox": [],
  "geometry": {"coordinates":[-96.95,44.3333],"type":"Point"}
}