{
  "id": 7199245,
  "type": "Feature",
  "properties": {
    "tgn:hierarchy":[
        "tgn:7199245",
        "tgn:7003669",
        "tgn:1000003",
        "tgn:7000084",
        "tgn:7029392"
    ],
    "tgn:id":7199245,
    "tgn:name":"Eichenb\u00fchl",
    "tgn:placetype":[
        "aat:300008347"
    ]
},
  "bbox": [],
  "geometry": {"coordinates":[9.329167,49.705556],"type":"Point"}
}