{
  "id": 7269884,
  "type": "Feature",
  "properties": {
    "tgn:hierarchy":[
        "tgn:7269884",
        "tgn:7003616",
        "tgn:1000003",
        "tgn:7016845",
        "tgn:7029392"
    ],
    "tgn:id":7269884,
    "tgn:name:nl":"Middenhoofdvaart",
    "tgn:placetype":[
        "aat:300006075"
    ]
},
  "bbox": [],
  "geometry": {"coordinates":[5.916667,52.983333],"type":"Point"}
}