{
  "id": 1128138,
  "type": "Feature",
  "properties": {
    "tgn:hierarchy":[
        "tgn:1128138",
        "tgn:7002872",
        "tgn:1000003",
        "tgn:1000070",
        "tgn:7029392"
    ],
    "tgn:id":1128138,
    "tgn:name":"Orbec",
    "tgn:placetype":[
        "aat:300008707"
    ]
},
  "bbox": [],
  "geometry": {"coordinates":[0.2333,49.15],"type":"Point"}
}