{
  "id": 7483675,
  "type": "Feature",
  "properties": {
    "tgn:hierarchy":[
        "tgn:7483675",
        "tgn:1000004",
        "tgn:7489179",
        "tgn:1000141",
        "tgn:7029392"
    ],
    "tgn:id":7483675,
    "tgn:name":"Dali Yugang",
    "tgn:placetype":[
        "aat:300008678"
    ]
},
  "bbox": [],
  "geometry": {"coordinates":[121.921667,24.962778],"type":"Point"}
}