{
  "id": 2728862,
  "type": "Feature",
  "properties": {
    "tgn:hierarchy":[
        "tgn:2728862",
        "tgn:1000001",
        "tgn:7012149",
        "tgn:2001288",
        "tgn:7007524",
        "tgn:7029392"
    ],
    "tgn:id":2728862,
    "tgn:name":"Triangle Lake",
    "tgn:placetype":[
        "aat:300008680"
    ]
},
  "bbox": [],
  "geometry": {"coordinates":[-112.0167,45.5167],"type":"Point"}
}