{
  "id": 1024442,
  "type": "Feature",
  "properties": {
    "tgn:hierarchy":[
        "tgn:1024442",
        "tgn:1001172",
        "tgn:1000002",
        "tgn:1000056",
        "tgn:7029392"
    ],
    "tgn:id":1024442,
    "tgn:name":"Chavarr\u00eda",
    "tgn:placetype":[
        "aat:300008347"
    ]
},
  "bbox": [],
  "geometry": {"coordinates":[-77.0833,-12.0167],"type":"Point"}
}