<<<<<<< HEAD
{
  "id": 2761957,
  "type": "Feature",
  "properties": {
    "tgn:hierarchy":[
        "tgn:2761957",
        "tgn:1002247",
        "tgn:1000001",
        "tgn:7012149",
        "tgn:7007516",
        "tgn:7029392"
    ],
    "tgn:id":2761957,
    "tgn:name":"West Rock Station",
    "tgn:placetype":[
        "aat:300008347"
    ]
},
  "bbox": [],
  "geometry": {"coordinates":[-76.15,39.6333],"type":"Point"}
}
=======
{"geometry":{"type":"Point","coordinates":[-76.150000,39.633300]},"type":"Feature","properties":{"hierarchy":["tgn:2761957","tgn:1002247","tgn:1000001","tgn:7012149","tgn:7007516","tgn:7029392"],"placetype":["aat:300008347"],"id":2761957,"name:xx":"West Rock Station"}}
>>>>>>> 03f74aca74312dbeaf24d7e61306dd6a786dc3d0
