{
  "id": 7521082,
  "type": "Feature",
  "properties": {
    "tgn:hierarchy":[
        "tgn:7521082",
        "tgn:7001242",
        "tgn:7016833",
        "tgn:1001079",
        "tgn:7029392"
    ],
    "tgn:id":7521082,
    "tgn:name:en":"Al Mall\u0101\u1e29ah",
    "tgn:placetype":[
        "aat:300007783"
    ]
},
  "bbox": [],
  "geometry": {"coordinates":[29.987222,31.208056],"type":"Point"}
}