{
  "id": 1054011,
  "type": "Feature",
  "properties": {
    "tgn:hierarchy":[
        "tgn:1054011",
        "tgn:1000003",
        "tgn:7011666",
        "tgn:7006660",
        "tgn:7029392"
    ],
    "tgn:id":1054011,
    "tgn:name":"Hlobyne",
    "tgn:placetype":[
        "aat:300008347"
    ]
},
  "bbox": [],
  "geometry": {"coordinates":[33.2833,49.3833],"type":"Point"}
}