{
  "id": 2506034,
  "type": "Feature",
  "properties": {
    "tgn:hierarchy":[
        "tgn:2506034",
        "tgn:7006450",
        "tgn:1000001",
        "tgn:7012149",
        "tgn:2124005",
        "tgn:7029392"
    ],
    "tgn:id":2506034,
    "tgn:name":"Meridian Creek",
    "tgn:placetype":[
        "aat:300008706"
    ]
},
  "bbox": [],
  "geometry": {"coordinates":[-159.9833,68.8167],"type":"Point"}
}