{
  "id": 2486077,
  "type": "Feature",
  "properties": {
    "tgn:hierarchy":[
        "tgn:2486077",
        "tgn:1000001",
        "tgn:7012149",
        "tgn:1002742",
        "tgn:7007920",
        "tgn:7029392"
    ],
    "tgn:id":2486077,
    "tgn:name":"Leader Lake",
    "tgn:placetype":[
        "aat:300006191"
    ]
},
  "bbox": [],
  "geometry": {"coordinates":[-119.6833,48.35],"type":"Point"}
}