{
  "id": 7520354,
  "type": "Feature",
  "properties": {
    "tgn:hierarchy":[
        "tgn:7520354",
        "tgn:7001242",
        "tgn:7016833",
        "tgn:1001418",
        "tgn:7029392"
    ],
    "tgn:id":7520354,
    "tgn:name:en":"\u0100b\u0101r Ab\u016b Sir'",
    "tgn:placetype":[
        "aat:300006207"
    ]
},
  "bbox": [],
  "geometry": {"coordinates":[26.175853,31.347128],"type":"Point"}
}