{
  "id": 2173651,
  "type": "Feature",
  "properties": {
    "tgn:hierarchy":[
        "tgn:2173651",
        "tgn:1000001",
        "tgn:2002109",
        "tgn:7012149",
        "tgn:7007827",
        "tgn:7029392"
    ],
    "tgn:id":2173651,
    "tgn:name":"Birch Spring Knoll",
    "tgn:placetype":[
        "aat:300008798"
    ]
},
  "bbox": [],
  "geometry": {"coordinates":[-112.6167,37.6667],"type":"Point"}
}