{
  "id": 7315995,
  "type": "Feature",
  "properties": {
    "tgn:hierarchy":[
        "tgn:7315995",
        "tgn:7002464",
        "tgn:1000049",
        "tgn:1000002",
        "tgn:7029392"
    ],
    "tgn:id":7315995,
    "tgn:name":"Cavancha, Caleta",
    "tgn:placetype":[
        "aat:300132316"
    ]
},
  "bbox": [],
  "geometry": {"coordinates":[-70.148611,-20.583333],"type":"Point"}
}