{
  "id": 7311099,
  "type": "Feature",
  "properties": {
    "tgn:hierarchy":[
        "tgn:7311099",
        "tgn:1001708",
        "tgn:1000049",
        "tgn:1000002",
        "tgn:7029392"
    ],
    "tgn:id":7311099,
    "tgn:name":"Negro, Cerro",
    "tgn:placetype":[
        "aat:300008795"
    ]
},
  "bbox": [],
  "geometry": {"coordinates":[-70.683333,-33.633333],"type":"Point"}
}