{
  "id": 2222414,
  "type": "Feature",
  "properties": {
    "tgn:hierarchy":[
        "tgn:2222414",
        "tgn:1002201",
        "tgn:1000001",
        "tgn:7012149",
        "tgn:7007517",
        "tgn:7029392"
    ],
    "tgn:id":2222414,
    "tgn:name":"Carpenter Brook",
    "tgn:placetype":[
        "aat:300008699"
    ]
},
  "bbox": [],
  "geometry": {"coordinates":[-71.2667,41.8333],"type":"Point"}
}