{
  "id": 7310129,
  "type": "Feature",
  "properties": {
    "tgn:hierarchy":[
        "tgn:7310129",
        "tgn:1001702",
        "tgn:1000049",
        "tgn:1000002",
        "tgn:7029392"
    ],
    "tgn:id":7310129,
    "tgn:name":"Orientales, Picos",
    "tgn:placetype":[
        "aat:300008795"
    ]
},
  "bbox": [],
  "geometry": {"coordinates":[-75.320833,-50.028333],"type":"Point"}
}