{
  "id": 7328781,
  "type": "Feature",
  "properties": {
    "tgn:hierarchy":[
        "tgn:7328781",
        "tgn:7002824",
        "tgn:1000003",
        "tgn:7002786",
        "tgn:1000095",
        "tgn:7029392"
    ],
    "tgn:id":7328781,
    "tgn:name":"Queiroso",
    "tgn:placetype":[
        "aat:300008347"
    ]
},
  "bbox": [],
  "geometry": {"coordinates":[-9.266667,43.033333],"type":"Point"}
}