{
  "id": 7077320,
  "type": "Feature",
  "properties": {
    "tgn:hierarchy":[
        "tgn:7077320",
        "tgn:7003669",
        "tgn:1000003",
        "tgn:7000084",
        "tgn:7029392"
    ],
    "tgn:id":7077320,
    "tgn:name":"Kreisfreie Stadt Erlangen",
    "tgn:placetype":[
        "aat:300387198"
    ]
},
  "bbox": [],
  "geometry": {"coordinates":[10.989444,49.578889],"type":"Point"}
}