<<<<<<< HEAD
{
  "id": 7378411,
  "type": "Feature",
  "properties": {
    "tgn:hierarchy":[
        "tgn:7378411",
        "tgn:1000001",
        "tgn:7005591",
        "tgn:7005560",
        "tgn:7029392"
    ],
    "tgn:id":7378411,
    "tgn:name":"Las Piletas",
    "tgn:placetype":[
        "aat:300008347"
    ]
},
  "bbox": [],
  "geometry": {"coordinates":[-94.833333,16.633333],"type":"Point"}
}
=======
{"geometry":{"type":"Point","coordinates":[-94.833333,16.633333]},"type":"Feature","properties":{"hierarchy":["tgn:7378411","tgn:1000001","tgn:7005591","tgn:7005560","tgn:7029392"],"placetype":["aat:300008347"],"id":7378411,"name:xx":"Las Piletas"}}
>>>>>>> 03f74aca74312dbeaf24d7e61306dd6a786dc3d0
