<<<<<<< HEAD
{
  "id": 2258780,
  "type": "Feature",
  "properties": {
    "tgn:hierarchy":[
        "tgn:2258780",
        "tgn:1000001",
        "tgn:7006451",
        "tgn:7012149",
        "tgn:2000103",
        "tgn:7029392"
    ],
    "tgn:id":2258780,
    "tgn:name":"Cottonwood Creek",
    "tgn:placetype":[
        "aat:300008706"
    ]
},
  "bbox": [],
  "geometry": {"coordinates":[-113.1,34.5333],"type":"Point"}
}
=======
{"geometry":{"type":"Point","coordinates":[-113.100000,34.533300]},"type":"Feature","properties":{"hierarchy":["tgn:2258780","tgn:1000001","tgn:7006451","tgn:7012149","tgn:2000103","tgn:7029392"],"placetype":["aat:300008706"],"id":2258780,"name:xx":"Cottonwood Creek"}}
>>>>>>> 03f74aca74312dbeaf24d7e61306dd6a786dc3d0
