{
  "id": 7293350,
  "type": "Feature",
  "properties": {
    "tgn:hierarchy":[
        "tgn:7293350",
        "tgn:7001158",
        "tgn:7002848",
        "tgn:1000003",
        "tgn:1000095",
        "tgn:7029392"
    ],
    "tgn:id":7293350,
    "tgn:name":"Vi\u00f1ales, Arroyo de",
    "tgn:placetype":[
        "aat:300266554",
        "aat:300008699"
    ]
},
  "bbox": [],
  "geometry": {"coordinates":[-5.25,42.05],"type":"Point"}
}