{
  "id": 7301411,
  "type": "Feature",
  "properties": {
    "tgn:hierarchy":[
        "tgn:7301411",
        "tgn:7002806",
        "tgn:7001158",
        "tgn:1000003",
        "tgn:1000095",
        "tgn:7029392"
    ],
    "tgn:id":7301411,
    "tgn:name":"Merdero, R\u00edo",
    "tgn:placetype":[
        "aat:300008699"
    ]
},
  "bbox": [],
  "geometry": {"coordinates":[-4.816667,40.866667],"type":"Point"}
}