{
  "id": 2026586,
  "type": "Feature",
  "properties": {
    "tgn:hierarchy":[
        "tgn:2026586",
        "tgn:1002134",
        "tgn:1000001",
        "tgn:7012149",
        "tgn:7007251",
        "tgn:7029392"
    ],
    "tgn:id":2026586,
    "tgn:name":"Beverly",
    "tgn:placetype":[
        "aat:300008347"
    ]
},
  "bbox": [],
  "geometry": {"coordinates":[-90.9833,39.7833],"type":"Point"}
}