{
  "id": 2266447,
  "type": "Feature",
  "properties": {
    "tgn:hierarchy":[
        "tgn:2266447",
        "tgn:1000001",
        "tgn:7016172",
        "tgn:2000119",
        "tgn:7012149",
        "tgn:7029392"
    ],
    "tgn:id":2266447,
    "tgn:name":"Creben Creek",
    "tgn:placetype":[
        "aat:300008706"
    ]
},
  "bbox": [],
  "geometry": {"coordinates":[-92.5333,35.2833],"type":"Point"}
}