{
  "id": 7565215,
  "type": "Feature",
  "properties": {
    "tgn:hierarchy":[
        "tgn:7565215",
        "tgn:1000004",
        "tgn:7000198",
        "tgn:7016722",
        "tgn:7029392"
    ],
    "tgn:id":7565215,
    "tgn:name:en":"Ajanpur",
    "tgn:placetype":[
        "aat:300008347"
    ]
},
  "bbox": [],
  "geometry": {"coordinates":[79.46086,26.493703],"type":"Point"}
}