{
  "id": 7266480,
  "type": "Feature",
  "properties": {
    "tgn:hierarchy":[
        "tgn:7266480",
        "tgn:7003615",
        "tgn:1000003",
        "tgn:7016845",
        "tgn:7029392"
    ],
    "tgn:id":7266480,
    "tgn:name:nl":"Henri Piccardthoeve",
    "tgn:placetype":[
        "aat:300000206"
    ]
},
  "bbox": [],
  "geometry": {"coordinates":[5.666667,52.583333],"type":"Point"}
}