{
  "id": 2169716,
  "type": "Feature",
  "properties": {
    "tgn:hierarchy":[
        "tgn:2169716",
        "tgn:1000001",
        "tgn:2001414",
        "tgn:7012149",
        "tgn:7007526",
        "tgn:7029392"
    ],
    "tgn:id":2169716,
    "tgn:name":"Big Mountain",
    "tgn:placetype":[
        "aat:300008798"
    ]
},
  "bbox": [],
  "geometry": {"coordinates":[-118.9833,41.7167],"type":"Point"}
}