{
  "id": 2263620,
  "type": "Feature",
  "properties": {
    "tgn:hierarchy":[
        "tgn:2263620",
        "tgn:1000001",
        "tgn:7012149",
        "tgn:7029392"
    ],
    "tgn:id":2263620,
    "tgn:name":"Coyle Run",
    "tgn:placetype":[
        "aat:300008699"
    ]
},
  "bbox": [],
  "geometry": {"coordinates":[-78.0667,39.2667],"type":"Point"}
}