{
  "id": 7115554,
  "type": "Feature",
  "properties": {
    "tgn:hierarchy":[
        "tgn:7115554",
        "tgn:7003669",
        "tgn:1000003",
        "tgn:7000084",
        "tgn:7029392"
    ],
    "tgn:id":7115554,
    "tgn:name":"Oisching",
    "tgn:placetype":[
        "aat:300000206"
    ]
},
  "bbox": [],
  "geometry": {"coordinates":[13.116667,48.833333],"type":"Point"}
}