<<<<<<< HEAD
{
  "id": 7177995,
  "type": "Feature",
  "properties": {
    "tgn:hierarchy":[
        "tgn:7177995",
        "tgn:1000003",
        "tgn:7000094",
        "tgn:7000084",
        "tgn:7029392"
    ],
    "tgn:id":7177995,
    "tgn:name":"Hangerien",
    "tgn:placetype":[
        "aat:300266640"
    ]
},
  "bbox": [],
  "geometry": {"coordinates":[13.583333,54.4],"type":"Point"}
}
=======
{"geometry":{"type":"Point","coordinates":[13.583333,54.400000]},"type":"Feature","properties":{"hierarchy":["tgn:7177995","tgn:1000003","tgn:7000094","tgn:7000084","tgn:7029392"],"placetype":["aat:300266640"],"id":7177995,"name:xx":"Hangerien"}}
>>>>>>> 03f74aca74312dbeaf24d7e61306dd6a786dc3d0
