<<<<<<< HEAD
{
  "id": 2762372,
  "type": "Feature",
  "properties": {
    "tgn:hierarchy":[
        "tgn:2762372",
        "tgn:1000001",
        "tgn:7012149",
        "tgn:1003042",
        "tgn:7007920",
        "tgn:7029392"
    ],
    "tgn:id":2762372,
    "tgn:name":"West Turbine Lateral",
    "tgn:placetype":[
        "aat:300006075"
    ]
},
  "bbox": [],
  "geometry": {"coordinates":[-119.9,46.3167],"type":"Point"}
}
=======
{"geometry":{"type":"Point","coordinates":[-119.900000,46.316700]},"type":"Feature","properties":{"hierarchy":["tgn:2762372","tgn:1000001","tgn:7012149","tgn:1003042","tgn:7007920","tgn:7029392"],"placetype":["aat:300006075"],"id":2762372,"name:xx":"West Turbine Lateral"}}
>>>>>>> 03f74aca74312dbeaf24d7e61306dd6a786dc3d0
