{
  "id": 7274423,
  "type": "Feature",
  "properties": {
    "tgn:hierarchy":[
        "tgn:7274423",
        "tgn:7003616",
        "tgn:1000003",
        "tgn:7016845",
        "tgn:7029392"
    ],
    "tgn:id":7274423,
    "tgn:name:nl":"Zwaagstergaasten",
    "tgn:placetype":[
        "aat:300387200"
    ]
},
  "bbox": [],
  "geometry": {"coordinates":[6.083333,53.05],"type":"Point"}
}