<<<<<<< HEAD
{
  "id": 2336596,
  "type": "Feature",
  "properties": {
    "tgn:hierarchy":[
        "tgn:2336596",
        "tgn:1000001",
        "tgn:2001638",
        "tgn:7012149",
        "tgn:7007707",
        "tgn:7029392"
    ],
    "tgn:id":2336596,
    "tgn:name":"Four Mile Crossing",
    "tgn:placetype":[
        "aat:300008347"
    ]
},
  "bbox": [],
  "geometry": {"coordinates":[-98.4333,34.6833],"type":"Point"}
}
=======
{"geometry":{"type":"Point","coordinates":[-98.433300,34.683300]},"type":"Feature","properties":{"hierarchy":["tgn:2336596","tgn:1000001","tgn:2001638","tgn:7012149","tgn:7007707","tgn:7029392"],"placetype":["aat:300008347"],"id":2336596,"name:xx":"Four Mile Crossing"}}
>>>>>>> 03f74aca74312dbeaf24d7e61306dd6a786dc3d0
