{
  "id": 7317215,
  "type": "Feature",
  "properties": {
    "tgn:hierarchy":[
        "tgn:7317215",
        "tgn:1001768",
        "tgn:1000049",
        "tgn:1000002",
        "tgn:7029392"
    ],
    "tgn:id":7317215,
    "tgn:name":"Conc\u00f3n Alto",
    "tgn:placetype":[
        "aat:300000206"
    ]
},
  "bbox": [],
  "geometry": {"coordinates":[-71.45,-32.95],"type":"Point"}
}