{
  "id": 7479022,
  "type": "Feature",
  "properties": {
    "tgn:hierarchy":[
        "tgn:7479022",
        "tgn:7001001",
        "tgn:1000004",
        "tgn:1000141",
        "tgn:7029392"
    ],
    "tgn:id":7479022,
    "tgn:name":"Jiahua Zhongxue",
    "tgn:placetype":[
        "aat:300006495"
    ]
},
  "bbox": [],
  "geometry": {"coordinates":[120.478056,23.481944],"type":"Point"}
}