{
  "id": 2447517,
  "type": "Feature",
  "properties": {
    "tgn:hierarchy":[
        "tgn:2447517",
        "tgn:1000001",
        "tgn:7012149",
        "tgn:1003003",
        "tgn:7007251",
        "tgn:7029392"
    ],
    "tgn:id":2447517,
    "tgn:name":"Lick Creek Lateral",
    "tgn:placetype":[
        "aat:300006075"
    ]
},
  "bbox": [],
  "geometry": {"coordinates":[-88.2333,38.4333],"type":"Point"}
}