{
  "id": 7538833,
  "type": "Feature",
  "properties": {
    "tgn:hierarchy":[
        "tgn:7538833",
        "tgn:7001242",
        "tgn:7001311",
        "tgn:7016833",
        "tgn:7029392"
    ],
    "tgn:id":7538833,
    "tgn:name:en":"B\u00eer Man\u00eeh",
    "tgn:placetype":[
        "aat:300006207"
    ]
},
  "bbox": [],
  "geometry": {"coordinates":[33.607389,25.556953],"type":"Point"}
}