{
  "id": 1016896,
  "type": "Feature",
  "properties": {
    "tgn:hierarchy":[
        "tgn:1016896",
        "tgn:7015035",
        "tgn:1000001",
        "tgn:7005870",
        "tgn:7029392"
    ],
    "tgn:id":1016896,
    "tgn:name":"Case-Pilote",
    "tgn:placetype":[
        "aat:300008347"
    ]
},
  "bbox": [],
  "geometry": {"coordinates":[-61.1333,14.6333],"type":"Point"}
}