{
  "id": 7495427,
  "type": "Feature",
  "properties": {
    "tgn:hierarchy":[
        "tgn:7495427",
        "tgn:7001004",
        "tgn:1000004",
        "tgn:1000141",
        "tgn:7029392"
    ],
    "tgn:id":7495427,
    "tgn:name":"Gaoting Shan",
    "tgn:placetype":[
        "aat:300008798"
    ]
},
  "bbox": [],
  "geometry": {"coordinates":[120.754378,23.270683],"type":"Point"}
}