{
  "id": 2111667,
  "type": "Feature",
  "properties": {
    "tgn:hierarchy":[
        "tgn:2111667",
        "tgn:1000001",
        "tgn:7012149",
        "tgn:7014334",
        "tgn:7007919",
        "tgn:7029392"
    ],
    "tgn:id":2111667,
    "tgn:name":"Ethel",
    "tgn:placetype":[
        "aat:300008347",
        "aat:300387210"
    ]
},
  "bbox": [],
  "geometry": {"coordinates":[-76.7667,37.9833],"type":"Point"}
}