{
  "id": 7491901,
  "type": "Feature",
  "properties": {
    "tgn:hierarchy":[
        "tgn:7491901",
        "tgn:1000004",
        "tgn:7001009",
        "tgn:1000141",
        "tgn:7029392"
    ],
    "tgn:id":7491901,
    "tgn:name":"Baojue Si Dafo",
    "tgn:placetype":[
        "aat:300006958"
    ]
},
  "bbox": [],
  "geometry": {"coordinates":[120.6876,24.1598],"type":"Point"}
}