{
  "id": 1015254,
  "type": "Feature",
  "properties": {
    "tgn:hierarchy":[
        "tgn:1015254",
        "tgn:7005685",
        "tgn:1000001",
        "tgn:7005803",
        "tgn:7029392"
    ],
    "tgn:id":1015254,
    "tgn:name":"North Rustico",
    "tgn:placetype":[
        "aat:300008347"
    ]
},
  "bbox": [],
  "geometry": {"coordinates":[-63.3333,46.4333],"type":"Point"}
}