{
  "id": 2777072,
  "type": "Feature",
  "properties": {
    "tgn:hierarchy":[
        "tgn:2777072",
        "tgn:1000001",
        "tgn:7012149",
        "tgn:1002298",
        "tgn:7007157",
        "tgn:7029392"
    ],
    "tgn:id":2777072,
    "tgn:name":"Windy Point",
    "tgn:placetype":[
        "aat:300008798"
    ]
},
  "bbox": [],
  "geometry": {"coordinates":[-121.8667,37.85],"type":"Point"}
}