{
  "id": 2781257,
  "type": "Feature",
  "properties": {
    "tgn:hierarchy":[
        "tgn:2781257",
        "tgn:1000001",
        "tgn:7016172",
        "tgn:7012149",
        "tgn:2000147",
        "tgn:7029392"
    ],
    "tgn:id":2781257,
    "tgn:name":"Woodiel Acres",
    "tgn:placetype":[
        "aat:300008347"
    ]
},
  "bbox": [],
  "geometry": {"coordinates":[-91.9667,34.9667],"type":"Point"}
}