{
  "id": 2681166,
  "type": "Feature",
  "properties": {
    "tgn:hierarchy":[
        "tgn:2681166",
        "tgn:1000001",
        "tgn:7012149",
        "tgn:2002114",
        "tgn:7007827",
        "tgn:7029392"
    ],
    "tgn:id":2681166,
    "tgn:name":"South Mountain",
    "tgn:placetype":[
        "aat:300008798"
    ]
},
  "bbox": [],
  "geometry": {"coordinates":[-112.4333,38.7167],"type":"Point"}
}