{
  "id": 2553565,
  "type": "Feature",
  "properties": {
    "tgn:hierarchy":[
        "tgn:2553565",
        "tgn:1000001",
        "tgn:2001945",
        "tgn:7012149",
        "tgn:7007826",
        "tgn:7029392"
    ],
    "tgn:id":2553565,
    "tgn:name":"Oak Draw",
    "tgn:placetype":[
        "aat:300008761"
    ]
},
  "bbox": [],
  "geometry": {"coordinates":[-102.75,30.0167],"type":"Point"}
}