{
  "id": 2081422,
  "type": "Feature",
  "properties": {
    "tgn:hierarchy":[
        "tgn:2081422",
        "tgn:1000001",
        "tgn:7012149",
        "tgn:1002701",
        "tgn:7007706",
        "tgn:7029392"
    ],
    "tgn:id":2081422,
    "tgn:name":"Pleasant Grove",
    "tgn:placetype":[
        "aat:300008347"
    ]
},
  "bbox": [],
  "geometry": {"coordinates":[-81.95,39.95],"type":"Point"}
}