{
  "id": 2386469,
  "type": "Feature",
  "properties": {
    "tgn:hierarchy":[
        "tgn:2386469",
        "tgn:1000001",
        "tgn:7012149",
        "tgn:2002127",
        "tgn:7007827",
        "tgn:7029392"
    ],
    "tgn:id":2386469,
    "tgn:name":"Herbs Point",
    "tgn:placetype":[
        "aat:300008850"
    ]
},
  "bbox": [],
  "geometry": {"coordinates":[-113.1167,37.4333],"type":"Point"}
}