{
  "id": 7571076,
  "type": "Feature",
  "properties": {
    "tgn:hierarchy":[
        "tgn:7571076",
        "tgn:1000004",
        "tgn:7000198",
        "tgn:7000799",
        "tgn:7029392"
    ],
    "tgn:id":7571076,
    "tgn:name:en":"Kalit",
    "tgn:placetype":[
        "aat:300008347"
    ]
},
  "bbox": [],
  "geometry": {"coordinates":[74.542767,32.879588],"type":"Point"}
}