{
  "id": 2252046,
  "type": "Feature",
  "properties": {
    "tgn:hierarchy":[
        "tgn:2252046",
        "tgn:1000001",
        "tgn:1002218",
        "tgn:7012149",
        "tgn:7007157",
        "tgn:7029392"
    ],
    "tgn:id":2252046,
    "tgn:name":"Concow Creek",
    "tgn:placetype":[
        "aat:300008706"
    ]
},
  "bbox": [],
  "geometry": {"coordinates":[-121.4833,39.8167],"type":"Point"}
}