{
  "id": 7279218,
  "type": "Feature",
  "properties": {
    "tgn:hierarchy":[
        "tgn:7279218",
        "tgn:1001657",
        "tgn:1000049",
        "tgn:1000002",
        "tgn:7029392"
    ],
    "tgn:id":7279218,
    "tgn:name":"Romerales",
    "tgn:placetype":[
        "aat:300008347"
    ]
},
  "bbox": [],
  "geometry": {"coordinates":[-71.233333,-29.766667],"type":"Point"}
}