<<<<<<< HEAD
{
  "id": 7358688,
  "type": "Feature",
  "properties": {
    "tgn:hierarchy":[
        "tgn:7358688",
        "tgn:1001853",
        "tgn:1000001",
        "tgn:7005560",
        "tgn:7029392"
    ],
    "tgn:id":7358688,
    "tgn:name":"Colorada, Sierra",
    "tgn:placetype":[
        "aat:300008795"
    ]
},
  "bbox": [],
  "geometry": {"coordinates":[-102.783333,26.9],"type":"Point"}
}
=======
{"geometry":{"type":"Point","coordinates":[-102.783333,26.900000]},"type":"Feature","properties":{"hierarchy":["tgn:7358688","tgn:1001853","tgn:1000001","tgn:7005560","tgn:7029392"],"placetype":["aat:300008795"],"id":7358688,"name:xx":"Colorada, Sierra"}}
>>>>>>> 03f74aca74312dbeaf24d7e61306dd6a786dc3d0
