{
  "id": 2707846,
  "type": "Feature",
  "properties": {
    "tgn:hierarchy":[
        "tgn:2707846",
        "tgn:7006450",
        "tgn:1000001",
        "tgn:7019698",
        "tgn:7012149",
        "tgn:7029392"
    ],
    "tgn:id":2707846,
    "tgn:name":"Swetmann Mine",
    "tgn:placetype":[
        "aat:300000390"
    ]
},
  "bbox": [],
  "geometry": {"coordinates":[-149.55,60.7667],"type":"Point"}
}