{
  "id": 7495567,
  "type": "Feature",
  "properties": {
    "tgn:hierarchy":[
        "tgn:7495567",
        "tgn:1000004",
        "tgn:7001013",
        "tgn:1000141",
        "tgn:7029392"
    ],
    "tgn:id":7495567,
    "tgn:name":"Shunhe Qiao",
    "tgn:placetype":[
        "aat:300007836"
    ]
},
  "bbox": [],
  "geometry": {"coordinates":[121.308483,24.867182],"type":"Point"}
}