{
  "id": 2168460,
  "type": "Feature",
  "properties": {
    "tgn:hierarchy":[
        "tgn:2168460",
        "tgn:1000001",
        "tgn:7012149",
        "tgn:2000290",
        "tgn:7007240",
        "tgn:7029392"
    ],
    "tgn:id":2168460,
    "tgn:name":"Big Hammock",
    "tgn:placetype":[
        "aat:300008347"
    ]
},
  "bbox": [],
  "geometry": {"coordinates":[-86.3667,30.0333],"type":"Point"}
}