{
  "id": 2462625,
  "type": "Feature",
  "properties": {
    "tgn:hierarchy":[
        "tgn:2462625",
        "tgn:1000001",
        "tgn:7012149",
        "tgn:7007523",
        "tgn:7029392"
    ],
    "tgn:id":2462625,
    "tgn:name":"Little Wilson Creek",
    "tgn:placetype":[
        "aat:300008706"
    ]
},
  "bbox": [],
  "geometry": {"coordinates":[-93.1167,37.45],"type":"Point"}
}