{
  "id": 7040418,
  "type": "Feature",
  "properties": {
    "tgn:hierarchy":[
        "tgn:7040418",
        "tgn:1003505",
        "tgn:1000003",
        "tgn:7002993",
        "tgn:1000080",
        "tgn:7029392"
    ],
    "tgn:id":7040418,
    "tgn:name":"Sant'Andrea, Punta",
    "tgn:placetype":[
        "aat:300386846"
    ]
},
  "bbox": [],
  "geometry": {"coordinates":[13.75,45.65],"type":"Point"}
}