{
  "id": 7302450,
  "type": "Feature",
  "properties": {
    "tgn:hierarchy":[
        "tgn:7302450",
        "tgn:7002824",
        "tgn:1000003",
        "tgn:7002786",
        "tgn:1000095",
        "tgn:7029392"
    ],
    "tgn:id":7302450,
    "tgn:name":"Ora\u00f1a de Ameneiro, Arroyo de la",
    "tgn:placetype":[
        "aat:300008699"
    ]
},
  "bbox": [],
  "geometry": {"coordinates":[-8.066667,43.45],"type":"Point"}
}