{
  "id": 7293009,
  "type": "Feature",
  "properties": {
    "tgn:hierarchy":[
        "tgn:7293009",
        "tgn:1001630",
        "tgn:1000049",
        "tgn:1000002",
        "tgn:7029392"
    ],
    "tgn:id":7293009,
    "tgn:name":"El Sauce",
    "tgn:placetype":[
        "aat:300008697"
    ]
},
  "bbox": [],
  "geometry": {"coordinates":[-69.916667,-27.316667],"type":"Point"}
}