{
  "id": 2074941,
  "type": "Feature",
  "properties": {
    "tgn:hierarchy":[
        "tgn:2074941",
        "tgn:1000001",
        "tgn:7012149",
        "tgn:7014128",
        "tgn:7007709",
        "tgn:7029392"
    ],
    "tgn:id":2074941,
    "tgn:name":"Grissom",
    "tgn:placetype":[
        "aat:300008347",
        "aat:300387210"
    ]
},
  "bbox": [],
  "geometry": {"coordinates":[-78.5833,36.0667],"type":"Point"}
}