{
  "id": 7363483,
  "type": "Feature",
  "properties": {
    "tgn:hierarchy":[
        "tgn:7363483",
        "tgn:1000001",
        "tgn:7005597",
        "tgn:7005560",
        "tgn:7029392"
    ],
    "tgn:id":7363483,
    "tgn:name":"El Chaparro, Isla",
    "tgn:placetype":[
        "aat:300008791"
    ]
},
  "bbox": [],
  "geometry": {"coordinates":[-97.583333,24.95],"type":"Point"}
}