{
  "id": 7400159,
  "type": "Feature",
  "properties": {
    "tgn:hierarchy":[
        "tgn:7400159",
        "tgn:1000001",
        "tgn:7005599",
        "tgn:7005560",
        "tgn:7029392"
    ],
    "tgn:id":7400159,
    "tgn:name":"Heriberto Jara",
    "tgn:placetype":[
        "aat:300008347"
    ]
},
  "bbox": [],
  "geometry": {"coordinates":[-94.775,17.366667],"type":"Point"}
}