{
  "id": 2227386,
  "type": "Feature",
  "properties": {
    "tgn:hierarchy":[
        "tgn:2227386",
        "tgn:1000001",
        "tgn:7012149",
        "tgn:2001256",
        "tgn:7007523",
        "tgn:7029392"
    ],
    "tgn:id":2227386,
    "tgn:name":"Cave Spring",
    "tgn:placetype":[
        "aat:300008697"
    ]
},
  "bbox": [],
  "geometry": {"coordinates":[-92.9667,37.2167],"type":"Point"}
}