{
  "id": 2528128,
  "type": "Feature",
  "properties": {
    "tgn:hierarchy":[
        "tgn:2528128",
        "tgn:1000001",
        "tgn:7012149",
        "tgn:7007252",
        "tgn:7029392"
    ],
    "tgn:id":2528128,
    "tgn:name":"Mountain Tea Ridge",
    "tgn:placetype":[
        "aat:300266640"
    ]
},
  "bbox": [],
  "geometry": {"coordinates":[-86.1333,39.2333],"type":"Point"}
}