{
  "id": 7109667,
  "type": "Feature",
  "properties": {
    "tgn:hierarchy":[
        "tgn:7109667",
        "tgn:7003669",
        "tgn:1000003",
        "tgn:7000084",
        "tgn:7029392"
    ],
    "tgn:id":7109667,
    "tgn:name":"Ramsen",
    "tgn:placetype":[
        "aat:300000206"
    ]
},
  "bbox": [],
  "geometry": {"coordinates":[12.716667,47.766667],"type":"Point"}
}