{
  "id": 2101660,
  "type": "Feature",
  "properties": {
    "tgn:hierarchy":[
        "tgn:2101660",
        "tgn:1000001",
        "tgn:7012149",
        "tgn:2001919",
        "tgn:7007825",
        "tgn:7029392"
    ],
    "tgn:id":2101660,
    "tgn:name":"Station Camp",
    "tgn:placetype":[
        "aat:300008347",
        "aat:300387210"
    ]
},
  "bbox": [],
  "geometry": {"coordinates":[-86.55,36.3833],"type":"Point"}
}