{
  "id": 7535048,
  "type": "Feature",
  "properties": {
    "tgn:hierarchy":[
        "tgn:7535048",
        "tgn:7001242",
        "tgn:7001105",
        "tgn:7016833",
        "tgn:7029392"
    ],
    "tgn:id":7535048,
    "tgn:name:en":"Kafr Ab\u016b Shanab",
    "tgn:placetype":[
        "aat:300008347"
    ]
},
  "bbox": [],
  "geometry": {"coordinates":[30.682677,29.422413],"type":"Point"}
}