{
  "id": 2562927,
  "type": "Feature",
  "properties": {
    "tgn:hierarchy":[
        "tgn:2562927",
        "tgn:1000001",
        "tgn:7012149",
        "tgn:1002700",
        "tgn:7007520",
        "tgn:7029392"
    ],
    "tgn:id":2562927,
    "tgn:name":"Ovidhall Lake Creek",
    "tgn:placetype":[
        "aat:300008706"
    ]
},
  "bbox": [],
  "geometry": {"coordinates":[-85.8333,43.25],"type":"Point"}
}