{
  "id": 7097201,
  "type": "Feature",
  "properties": {
    "tgn:hierarchy":[
        "tgn:7097201",
        "tgn:7000096",
        "tgn:1000003",
        "tgn:7000084",
        "tgn:7029392"
    ],
    "tgn:id":7097201,
    "tgn:name":"St\u00e4bchen",
    "tgn:placetype":[
        "aat:300008347"
    ]
},
  "bbox": [],
  "geometry": {"coordinates":[13.816667,52.366667],"type":"Point"}
}