{
  "id": 1074877,
  "type": "Feature",
  "properties": {
    "tgn:hierarchy":[
        "tgn:1074877",
        "tgn:1000004",
        "tgn:7000198",
        "tgn:1001996",
        "tgn:7029392"
    ],
    "tgn:id":1074877,
    "tgn:name":"Brahmaur",
    "tgn:placetype":[
        "aat:300008347"
    ]
},
  "bbox": [],
  "geometry": {"coordinates":[76.538705,32.443808],"type":"Point"}
}