{
  "id": 1000598,
  "type": "Feature",
  "properties": {
    "tgn:hierarchy":[
        "tgn:1000598",
        "tgn:7001242",
        "tgn:7016752",
        "tgn:7029392"
    ],
    "tgn:id":1000598,
    "tgn:name:fr":"Alger",
    "tgn:placetype":[
        "aat:300387064",
        "aat:300000772"
    ]
},
  "bbox": [],
  "geometry": {"coordinates":[3.166,36.75],"type":"Point"}
}