<<<<<<< HEAD
{
  "id": 2404644,
  "type": "Feature",
  "properties": {
    "tgn:hierarchy":[
        "tgn:2404644",
        "tgn:1000001",
        "tgn:7012149",
        "tgn:2001750",
        "tgn:7007712",
        "tgn:7029392"
    ],
    "tgn:id":2404644,
    "tgn:name":"Huckabee Heights",
    "tgn:placetype":[
        "aat:300008347"
    ]
},
  "bbox": [],
  "geometry": {"coordinates":[-79.0667,33.8167],"type":"Point"}
}
=======
{"geometry":{"type":"Point","coordinates":[-79.066700,33.816700]},"type":"Feature","properties":{"hierarchy":["tgn:2404644","tgn:1000001","tgn:7012149","tgn:2001750","tgn:7007712","tgn:7029392"],"placetype":["aat:300008347"],"id":2404644,"name:xx":"Huckabee Heights"}}
>>>>>>> 03f74aca74312dbeaf24d7e61306dd6a786dc3d0
