{
  "id": 7278318,
  "type": "Feature",
  "properties": {
    "tgn:hierarchy":[
        "tgn:7278318",
        "tgn:1001699",
        "tgn:1000049",
        "tgn:1000002",
        "tgn:7029392"
    ],
    "tgn:id":7278318,
    "tgn:name":"Estaci\u00f3n Vivanco",
    "tgn:placetype":[
        "aat:300007783"
    ]
},
  "bbox": [],
  "geometry": {"coordinates":[-72.633333,-40.366667],"type":"Point"}
}