{
  "id": 1115839,
  "type": "Feature",
  "properties": {
    "tgn:hierarchy":[
        "tgn:1115839",
        "tgn:1002215",
        "tgn:1000001",
        "tgn:7012149",
        "tgn:7007565",
        "tgn:7029392"
    ],
    "tgn:id":1115839,
    "tgn:name":"Centennial Lake",
    "tgn:placetype":[
        "aat:300008680"
    ]
},
  "bbox": [],
  "geometry": {"coordinates":[-74.8333,39.8333],"type":"Point"}
}