{
  "id": 1089375,
  "type": "Feature",
  "properties": {
    "tgn:hierarchy":[
        "tgn:1089375",
        "tgn:7001242",
        "tgn:7016654",
        "tgn:1000159",
        "tgn:7029392"
    ],
    "tgn:id":1089375,
    "tgn:name":"Mpoka",
    "tgn:placetype":[
        "aat:300008347"
    ]
},
  "bbox": [],
  "geometry": {"coordinates":[17.0333,-1.4333],"type":"Point"}
}