{
  "id": 2761778,
  "type": "Feature",
  "properties": {
    "tgn:hierarchy":[
        "tgn:2761778",
        "tgn:1000001",
        "tgn:7012149",
        "tgn:2002017",
        "tgn:7007826",
        "tgn:7029392"
    ],
    "tgn:id":2761778,
    "tgn:name":"West Prong Duck Creek",
    "tgn:placetype":[
        "aat:300008706"
    ]
},
  "bbox": [],
  "geometry": {"coordinates":[-100.8333,33.3833],"type":"Point"}
}