{
  "id": 7282408,
  "type": "Feature",
  "properties": {
    "tgn:hierarchy":[
        "tgn:7282408",
        "tgn:7002464",
        "tgn:1000049",
        "tgn:1000002",
        "tgn:7029392"
    ],
    "tgn:id":7282408,
    "tgn:name":"Pisiga, Vegas de",
    "tgn:placetype":[
        "aat:300008686"
    ]
},
  "bbox": [],
  "geometry": {"coordinates":[-68.65,-19.283333],"type":"Point"}
}