<<<<<<< HEAD
{
  "id": 7484370,
  "type": "Feature",
  "properties": {
    "tgn:hierarchy":[
        "tgn:7484370",
        "tgn:1000004",
        "tgn:7492971",
        "tgn:1000141",
        "tgn:7029392"
    ],
    "tgn:id":7484370,
    "tgn:name":"Ziqiang Qiao",
    "tgn:placetype":[
        "aat:300007836"
    ]
},
  "bbox": [],
  "geometry": {"coordinates":[120.598056,22.378056],"type":"Point"}
}
=======
{"geometry":{"type":"Point","coordinates":[120.598056,22.378056]},"type":"Feature","properties":{"hierarchy":["tgn:7484370","tgn:1000004","tgn:7492971","tgn:1000141","tgn:7029392"],"placetype":["aat:300007836"],"id":7484370,"name:xx":"Ziqiang Qiao"}}
>>>>>>> 03f74aca74312dbeaf24d7e61306dd6a786dc3d0
