{
  "id": 7002377,
  "type": "Feature",
  "properties": {
    "tgn:hierarchy":[
        "tgn:7002377",
        "tgn:1001302",
        "tgn:1000004",
        "tgn:1000122",
        "tgn:7029392"
    ],
    "tgn:id":7002377,
    "tgn:name":"Panmunj\u014fm",
    "tgn:placetype":[
        "aat:300008347"
    ]
},
  "bbox": [],
  "geometry": {"coordinates":[126.6333,37.9833],"type":"Point"}
}