{
  "id": 2006929,
  "type": "Feature",
  "properties": {
    "tgn:hierarchy":[
        "tgn:2006929",
        "tgn:1000001",
        "tgn:7006451",
        "tgn:2000091",
        "tgn:7012149",
        "tgn:7029392"
    ],
    "tgn:id":2006929,
    "tgn:name":"Kansas Settlement",
    "tgn:placetype":[
        "aat:300008347"
    ]
},
  "bbox": [],
  "geometry": {"coordinates":[-109.75,32.05],"type":"Point"}
}