{
  "id": 7591473,
  "type": "Feature",
  "properties": {
    "tgn:hierarchy":[
        "tgn:7591473",
        "tgn:1000004",
        "tgn:7000198",
        "tgn:7000799",
        "tgn:7029392"
    ],
    "tgn:id":7591473,
    "tgn:name:en":"Mangu di Pati\u0101n",
    "tgn:placetype":[
        "aat:300008347"
    ]
},
  "bbox": [],
  "geometry": {"coordinates":[74.710081,32.991512],"type":"Point"}
}