{
  "id": 2480220,
  "type": "Feature",
  "properties": {
    "tgn:hierarchy":[
        "tgn:2480220",
        "tgn:1000001",
        "tgn:7012149",
        "tgn:2001160",
        "tgn:7007522",
        "tgn:7029392"
    ],
    "tgn:id":2480220,
    "tgn:name":"Lake Park",
    "tgn:placetype":[
        "aat:300008347"
    ]
},
  "bbox": [],
  "geometry": {"coordinates":[-90.8167,32.2333],"type":"Point"}
}