{
  "id": 7488948,
  "type": "Feature",
  "properties": {
    "tgn:hierarchy":[
        "tgn:7488948",
        "tgn:1000004",
        "tgn:7001013",
        "tgn:1000141",
        "tgn:7029392"
    ],
    "tgn:id":7488948,
    "tgn:name":"Longtan Chi",
    "tgn:placetype":[
        "aat:300008680"
    ]
},
  "bbox": [],
  "geometry": {"coordinates":[121.21,24.861667],"type":"Point"}
}