<<<<<<< HEAD
{
  "id": 7488948,
  "type": "Feature",
  "properties": {
    "tgn:hierarchy":[
        "tgn:7488948",
        "tgn:1000004",
        "tgn:7001013",
        "tgn:1000141",
        "tgn:7029392"
    ],
    "tgn:id":7488948,
    "tgn:name":"Longtan Chi",
    "tgn:placetype":[
        "aat:300008680"
    ]
},
  "bbox": [],
  "geometry": {"coordinates":[121.21,24.861667],"type":"Point"}
}
=======
{"geometry":{"type":"Point","coordinates":[121.210000,24.861667]},"type":"Feature","properties":{"hierarchy":["tgn:7488948","tgn:1000004","tgn:7001013","tgn:1000141","tgn:7029392"],"placetype":["aat:300008680"],"id":7488948,"name:xx":"Longtan Chi"}}
>>>>>>> 03f74aca74312dbeaf24d7e61306dd6a786dc3d0
