{
  "id": 7131517,
  "type": "Feature",
  "properties": {
    "tgn:hierarchy":[
        "tgn:7131517",
        "tgn:1000003",
        "tgn:7003676",
        "tgn:7000084",
        "tgn:7029392"
    ],
    "tgn:id":7131517,
    "tgn:name":"Mariental, Staatsforst",
    "tgn:placetype":[
        "aat:300008863"
    ]
},
  "bbox": [],
  "geometry": {"coordinates":[10.966667,52.266667],"type":"Point"}
}