{
  "id": 7002329,
  "type": "Feature",
  "properties": {
    "tgn:hierarchy":[
        "tgn:7002329",
        "tgn:7001285",
        "tgn:1000004",
        "tgn:7018450",
        "tgn:1000144",
        "tgn:7029392"
    ],
    "tgn:id":7002329,
    "tgn:name:en":"Troy",
    "tgn:placetype":[
        "aat:300008347",
        "aat:300000810",
        "aat:300167671",
        "aat:300019275"
    ]
},
  "bbox": [],
  "geometry": {"coordinates":[26.25,39.95],"type":"Point"}
}