{
  "id": 7279479,
  "type": "Feature",
  "properties": {
    "tgn:hierarchy":[
        "tgn:7279479",
        "tgn:1001699",
        "tgn:1000049",
        "tgn:1000002",
        "tgn:7029392"
    ],
    "tgn:id":7279479,
    "tgn:name":"R\u00edo Blanco",
    "tgn:placetype":[
        "aat:300000206"
    ]
},
  "bbox": [],
  "geometry": {"coordinates":[-73.533333,-40.833333],"type":"Point"}
}