{
  "id": 7217655,
  "type": "Feature",
  "properties": {
    "tgn:hierarchy":[
        "tgn:7217655",
        "tgn:7011164",
        "tgn:7002674",
        "tgn:1000003",
        "tgn:1000074",
        "tgn:7029392"
    ],
    "tgn:id":7217655,
    "tgn:name":"Foni\u00e1s, \u00c1kra",
    "tgn:placetype":[
        "aat:300386846"
    ]
},
  "bbox": [],
  "geometry": {"coordinates":[26.953611,37.685833],"type":"Point"}
}