{
  "id": 2507221,
  "type": "Feature",
  "properties": {
    "tgn:hierarchy":[
        "tgn:2507221",
        "tgn:1000001",
        "tgn:7012149",
        "tgn:7007157",
        "tgn:2000185",
        "tgn:7029392"
    ],
    "tgn:id":2507221,
    "tgn:name":"Mettick Creek",
    "tgn:placetype":[
        "aat:300008706"
    ]
},
  "bbox": [],
  "geometry": {"coordinates":[-123.5333,39.25],"type":"Point"}
}