{
  "id": 2048573,
  "type": "Feature",
  "properties": {
    "tgn:hierarchy":[
        "tgn:2048573",
        "tgn:1000001",
        "tgn:2000939",
        "tgn:7012149",
        "tgn:7007516",
        "tgn:7029392"
    ],
    "tgn:id":2048573,
    "tgn:name":"Royal Oak",
    "tgn:placetype":[
        "aat:300008347"
    ]
},
  "bbox": [],
  "geometry": {"coordinates":[-76.1667,38.7333],"type":"Point"}
}