{
  "id": 2361223,
  "type": "Feature",
  "properties": {
    "tgn:hierarchy":[
        "tgn:2361223",
        "tgn:1000001",
        "tgn:2002109",
        "tgn:7012149",
        "tgn:7007827",
        "tgn:7029392"
    ],
    "tgn:id":2361223,
    "tgn:name":"Gravel Hill",
    "tgn:placetype":[
        "aat:300008798"
    ]
},
  "bbox": [],
  "geometry": {"coordinates":[-112.0333,37.65],"type":"Point"}
}