{
  "id": 2061242,
  "type": "Feature",
  "properties": {
    "tgn:hierarchy":[
        "tgn:2061242",
        "tgn:1000001",
        "tgn:7012149",
        "tgn:2001283",
        "tgn:7007524",
        "tgn:7029392"
    ],
    "tgn:id":2061242,
    "tgn:name":"Dayton",
    "tgn:placetype":[
        "aat:300008347"
    ]
},
  "bbox": [],
  "geometry": {"coordinates":[-114.2667,47.85],"type":"Point"}
}