{
  "id": 2115686,
  "type": "Feature",
  "properties": {
    "tgn:hierarchy":[
        "tgn:2115686",
        "tgn:1000001",
        "tgn:7012149",
        "tgn:1002979",
        "tgn:7007920",
        "tgn:7029392"
    ],
    "tgn:id":2115686,
    "tgn:name":"Eden",
    "tgn:placetype":[
        "aat:300008347",
        "aat:300387210"
    ]
},
  "bbox": [],
  "geometry": {"coordinates":[-123.65,46.2833],"type":"Point"}
}