{
  "id": 7583918,
  "type": "Feature",
  "properties": {
    "tgn:hierarchy":[
        "tgn:7583918",
        "tgn:1000004",
        "tgn:1001869",
        "tgn:7000198",
        "tgn:7029392"
    ],
    "tgn:id":7583918,
    "tgn:name:en":"Wondh",
    "tgn:placetype":[
        "aat:300008347"
    ]
},
  "bbox": [],
  "geometry": {"coordinates":[70.398315,23.29858],"type":"Point"}
}