<<<<<<< HEAD
{
  "id": 2256354,
  "type": "Feature",
  "properties": {
    "tgn:hierarchy":[
        "tgn:2256354",
        "tgn:1002300",
        "tgn:1000001",
        "tgn:7012149",
        "tgn:7007564",
        "tgn:7029392"
    ],
    "tgn:id":2256354,
    "tgn:name":"Copperville",
    "tgn:placetype":[
        "aat:300008347"
    ]
},
  "bbox": [],
  "geometry": {"coordinates":[-71.2333,44.5333],"type":"Point"}
}
=======
{"geometry":{"type":"Point","coordinates":[-71.233300,44.533300]},"type":"Feature","properties":{"hierarchy":["tgn:2256354","tgn:1002300","tgn:1000001","tgn:7012149","tgn:7007564","tgn:7029392"],"placetype":["aat:300008347"],"id":2256354,"name:xx":"Copperville"}}
>>>>>>> 03f74aca74312dbeaf24d7e61306dd6a786dc3d0
