{
  "id": 1067331,
  "type": "Feature",
  "properties": {
    "tgn:hierarchy":[
        "tgn:1067331",
        "tgn:1000004",
        "tgn:7002087",
        "tgn:1000111",
        "tgn:7029392"
    ],
    "tgn:id":1067331,
    "tgn:name":"Dacun",
    "tgn:placetype":[
        "aat:300008347"
    ]
},
  "bbox": [],
  "geometry": {"coordinates":[101.1333,27.9167],"type":"Point"}
}