<<<<<<< HEAD
{
  "id": 7377425,
  "type": "Feature",
  "properties": {
    "tgn:hierarchy":[
        "tgn:7377425",
        "tgn:7005580",
        "tgn:1000001",
        "tgn:7005560",
        "tgn:7029392"
    ],
    "tgn:id":7377425,
    "tgn:name":"Las Nubes, Cerro",
    "tgn:placetype":[
        "aat:300008795"
    ]
},
  "bbox": [],
  "geometry": {"coordinates":[-92.45,15.3],"type":"Point"}
}
=======
{"geometry":{"type":"Point","coordinates":[-92.450000,15.300000]},"type":"Feature","properties":{"hierarchy":["tgn:7377425","tgn:7005580","tgn:1000001","tgn:7005560","tgn:7029392"],"placetype":["aat:300008795"],"id":7377425,"name:xx":"Las Nubes, Cerro"}}
>>>>>>> 03f74aca74312dbeaf24d7e61306dd6a786dc3d0
