<<<<<<< HEAD
{
  "id": 7367748,
  "type": "Feature",
  "properties": {
    "tgn:hierarchy":[
        "tgn:7367748",
        "tgn:7005586",
        "tgn:1000001",
        "tgn:7005560",
        "tgn:7029392"
    ],
    "tgn:id":7367748,
    "tgn:name":"El Salitre",
    "tgn:placetype":[
        "aat:300008347"
    ]
},
  "bbox": [],
  "geometry": {"coordinates":[-101.75,21.916667],"type":"Point"}
}
=======
{"geometry":{"type":"Point","coordinates":[-101.750000,21.916667]},"type":"Feature","properties":{"hierarchy":["tgn:7367748","tgn:7005586","tgn:1000001","tgn:7005560","tgn:7029392"],"placetype":["aat:300008347"],"id":7367748,"name:xx":"El Salitre"}}
>>>>>>> 03f74aca74312dbeaf24d7e61306dd6a786dc3d0
