{
  "id": 7163074,
  "type": "Feature",
  "properties": {
    "tgn:hierarchy":[
        "tgn:7163074",
        "tgn:1000003",
        "tgn:7003677",
        "tgn:7000084",
        "tgn:7029392"
    ],
    "tgn:id":7163074,
    "tgn:name":"In den H\u00f6ffeln",
    "tgn:placetype":[
        "aat:300008777"
    ]
},
  "bbox": [],
  "geometry": {"coordinates":[6.816667,50.483333],"type":"Point"}
}