{
  "id": 2081424,
  "type": "Feature",
  "properties": {
    "tgn:hierarchy":[
        "tgn:2081424",
        "tgn:1000001",
        "tgn:7012149",
        "tgn:1002662",
        "tgn:7007706",
        "tgn:7029392"
    ],
    "tgn:id":2081424,
    "tgn:name":"Pleasant Hill",
    "tgn:placetype":[
        "aat:300008347"
    ]
},
  "bbox": [],
  "geometry": {"coordinates":[-84.3333,40.05],"type":"Point"}
}