{
  "id": 2273148,
  "type": "Feature",
  "properties": {
    "tgn:hierarchy":[
        "tgn:2273148",
        "tgn:1000001",
        "tgn:7012149",
        "tgn:7007157",
        "tgn:1002901",
        "tgn:7029392"
    ],
    "tgn:id":2273148,
    "tgn:name":"Cygnus",
    "tgn:placetype":[
        "aat:300008347"
    ]
},
  "bbox": [],
  "geometry": {"coordinates":[-122.0833,38.15],"type":"Point"}
}