{
  "id": 7503314,
  "type": "Feature",
  "properties": {
    "tgn:hierarchy":[
        "tgn:7503314",
        "tgn:1000004",
        "tgn:7004300",
        "tgn:1000141",
        "tgn:7029392"
    ],
    "tgn:id":7503314,
    "tgn:name":"Yantun Shan",
    "tgn:placetype":[
        "aat:300008777"
    ]
},
  "bbox": [],
  "geometry": {"coordinates":[119.616667,23.252222],"type":"Point"}
}