{
  "id": 7206389,
  "type": "Feature",
  "properties": {
    "tgn:hierarchy":[
        "tgn:7206389",
        "tgn:1000003",
        "tgn:7003678",
        "tgn:7000084",
        "tgn:7029392"
    ],
    "tgn:id":7206389,
    "tgn:name":"Hof Campf",
    "tgn:placetype":[
        "aat:300000206"
    ]
},
  "bbox": [],
  "geometry": {"coordinates":[8.783333,51.15],"type":"Point"}
}