{
  "id": 2277710,
  "type": "Feature",
  "properties": {
    "tgn:hierarchy":[
        "tgn:2277710",
        "tgn:1000001",
        "tgn:7012149",
        "tgn:2002264",
        "tgn:7013961",
        "tgn:7029392"
    ],
    "tgn:id":2277710,
    "tgn:name":"Davy Run",
    "tgn:placetype":[
        "aat:300008699"
    ]
},
  "bbox": [],
  "geometry": {"coordinates":[-80.1833,38.0167],"type":"Point"}
}