{
  "id": 7581133,
  "type": "Feature",
  "properties": {
    "tgn:hierarchy":[
        "tgn:7581133",
        "tgn:1000004",
        "tgn:7000198",
        "tgn:1001895",
        "tgn:7029392"
    ],
    "tgn:id":7581133,
    "tgn:name:en":"Sunk Rock",
    "tgn:placetype":[
        "aat:300011692"
    ]
},
  "bbox": [],
  "geometry": {"coordinates":[72.833333,18.888611],"type":"Point"}
}