{
  "id": 2501975,
  "type": "Feature",
  "properties": {
    "tgn:hierarchy":[
        "tgn:2501975",
        "tgn:1000001",
        "tgn:7012149",
        "tgn:7007826",
        "tgn:7029392"
    ],
    "tgn:id":2501975,
    "tgn:name":"McKegan Draw",
    "tgn:placetype":[
        "aat:300008761"
    ]
},
  "bbox": [],
  "geometry": {"coordinates":[-100.0667,30.6333],"type":"Point"}
}