{
  "id": 1116938,
  "type": "Feature",
  "properties": {
    "tgn:hierarchy":[
        "tgn:1116938",
        "tgn:7024077",
        "tgn:1000003",
        "tgn:1000069",
        "tgn:7029392"
    ],
    "tgn:id":1116938,
    "tgn:name":"Kyr\u00f6sj\u00e4rvi",
    "tgn:placetype":[
        "aat:300008680"
    ]
},
  "bbox": [],
  "geometry": {"coordinates":[23.1667,61.75],"type":"Point"}
}