{
  "id": 2618819,
  "type": "Feature",
  "properties": {
    "tgn:hierarchy":[
        "tgn:2618819",
        "tgn:1000001",
        "tgn:7012149",
        "tgn:2002270",
        "tgn:7013961",
        "tgn:7029392"
    ],
    "tgn:id":2618819,
    "tgn:name":"Right Fork Twomile Creek",
    "tgn:placetype":[
        "aat:300008706"
    ]
},
  "bbox": [],
  "geometry": {"coordinates":[-81.5833,38.4333],"type":"Point"}
}