{
  "id": 2500531,
  "type": "Feature",
  "properties": {
    "tgn:hierarchy":[
        "tgn:2500531",
        "tgn:1000001",
        "tgn:7016172",
        "tgn:7012149",
        "tgn:2000144",
        "tgn:7029392"
    ],
    "tgn:id":2500531,
    "tgn:name":"McDonald Lake",
    "tgn:placetype":[
        "aat:300008680"
    ]
},
  "bbox": [],
  "geometry": {"coordinates":[-91.7167,34.15],"type":"Point"}
}