{
  "id": 2265663,
  "type": "Feature",
  "properties": {
    "tgn:hierarchy":[
        "tgn:2265663",
        "tgn:1000001",
        "tgn:1003028",
        "tgn:7012149",
        "tgn:7007159",
        "tgn:7029392"
    ],
    "tgn:id":2265663,
    "tgn:name":"Crann Brook",
    "tgn:placetype":[
        "aat:300008699"
    ]
},
  "bbox": [],
  "geometry": {"coordinates":[-72.0833,41.8833],"type":"Point"}
}