{
  "id": 7498290,
  "type": "Feature",
  "properties": {
    "tgn:hierarchy":[
        "tgn:7498290",
        "tgn:7001004",
        "tgn:1000004",
        "tgn:1000141",
        "tgn:7029392"
    ],
    "tgn:id":7498290,
    "tgn:name":"Nantouhe Qiao",
    "tgn:placetype":[
        "aat:300007836"
    ]
},
  "bbox": [],
  "geometry": {"coordinates":[120.534386,22.881776],"type":"Point"}
}