{
  "id": 7505642,
  "type": "Feature",
  "properties": {
    "tgn:hierarchy":[
        "tgn:7505642",
        "tgn:1008380",
        "tgn:7000507",
        "tgn:1000226",
        "tgn:1000006",
        "tgn:7029392"
    ],
    "tgn:id":7505642,
    "tgn:name:en":"Whananaki Inlet",
    "tgn:placetype":[
        "aat:300132316"
    ]
},
  "bbox": [],
  "geometry": {"coordinates":[174.466667,-35.516667],"type":"Point"}
}