{
  "id": 7476744,
  "type": "Feature",
  "properties": {
    "tgn:hierarchy":[
        "tgn:7476744",
        "tgn:7488858",
        "tgn:1000004",
        "tgn:1000141",
        "tgn:7029392"
    ],
    "tgn:id":7476744,
    "tgn:name":"Qinglong Qiao",
    "tgn:placetype":[
        "aat:300007836"
    ]
},
  "bbox": [],
  "geometry": {"coordinates":[120.914421,23.793184],"type":"Point"}
}