{
  "id": 2228223,
  "type": "Feature",
  "properties": {
    "tgn:hierarchy":[
        "tgn:2228223",
        "tgn:1000001",
        "tgn:7016172",
        "tgn:7012149",
        "tgn:2000128",
        "tgn:7029392"
    ],
    "tgn:id":2228223,
    "tgn:name":"Cedar Creek",
    "tgn:placetype":[
        "aat:300008706"
    ]
},
  "bbox": [],
  "geometry": {"coordinates":[-93.9667,35.5167],"type":"Point"}
}