{
  "id": 1072414,
  "type": "Feature",
  "properties": {
    "tgn:hierarchy":[
        "tgn:1072414",
        "tgn:1000004",
        "tgn:7002078",
        "tgn:1000111",
        "tgn:7029392"
    ],
    "tgn:id":1072414,
    "tgn:name":"Wamiao",
    "tgn:placetype":[
        "aat:300008347"
    ]
},
  "bbox": [],
  "geometry": {"coordinates":[113.0333,30.8167],"type":"Point"}
}