{
  "id": 7253359,
  "type": "Feature",
  "properties": {
    "tgn:hierarchy":[
        "tgn:7253359",
        "tgn:7003458",
        "tgn:1000003",
        "tgn:1000063",
        "tgn:7018236",
        "tgn:7029392"
    ],
    "tgn:id":7253359,
    "tgn:name":"Schaakse",
    "tgn:placetype":[
        "aat:300008347"
    ]
},
  "bbox": [],
  "geometry": {"coordinates":[3.092181,51.046248],"type":"Point"}
}