{
  "id": 2320634,
  "type": "Feature",
  "properties": {
    "tgn:hierarchy":[
        "tgn:2320634",
        "tgn:1000001",
        "tgn:2000779",
        "tgn:7012149",
        "tgn:7007255",
        "tgn:7029392"
    ],
    "tgn:id":2320634,
    "tgn:name":"Ewing Ridge",
    "tgn:placetype":[
        "aat:300266640"
    ]
},
  "bbox": [],
  "geometry": {"coordinates":[-85.0333,37.2333],"type":"Point"}
}