<<<<<<< HEAD
{
  "id": 2331057,
  "type": "Feature",
  "properties": {
    "tgn:hierarchy":[
        "tgn:2331057",
        "tgn:1000001",
        "tgn:7012149",
        "tgn:2001541",
        "tgn:7007709",
        "tgn:7029392"
    ],
    "tgn:id":2331057,
    "tgn:name":"Flat Shoals Creek",
    "tgn:placetype":[
        "aat:300008706"
    ]
},
  "bbox": [],
  "geometry": {"coordinates":[-80.2333,36.3667],"type":"Point"}
}
=======
{"geometry":{"type":"Point","coordinates":[-80.233300,36.366700]},"type":"Feature","properties":{"hierarchy":["tgn:2331057","tgn:1000001","tgn:7012149","tgn:2001541","tgn:7007709","tgn:7029392"],"placetype":["aat:300008706"],"id":2331057,"name:xx":"Flat Shoals Creek"}}
>>>>>>> 03f74aca74312dbeaf24d7e61306dd6a786dc3d0
