{
  "id": 2331057,
  "type": "Feature",
  "properties": {
    "tgn:hierarchy":[
        "tgn:2331057",
        "tgn:1000001",
        "tgn:7012149",
        "tgn:2001541",
        "tgn:7007709",
        "tgn:7029392"
    ],
    "tgn:id":2331057,
    "tgn:name":"Flat Shoals Creek",
    "tgn:placetype":[
        "aat:300008706"
    ]
},
  "bbox": [],
  "geometry": {"coordinates":[-80.2333,36.3667],"type":"Point"}
}