{
  "id": 2157066,
  "type": "Feature",
  "properties": {
    "tgn:hierarchy":[
        "tgn:2157066",
        "tgn:1000001",
        "tgn:7012149",
        "tgn:7007710",
        "tgn:7029392"
    ],
    "tgn:id":2157066,
    "tgn:name":"Beaver Branch",
    "tgn:placetype":[
        "aat:300008699"
    ]
},
  "bbox": [],
  "geometry": {"coordinates":[-77.9333,40.7833],"type":"Point"}
}