<<<<<<< HEAD
{
  "id": 2157066,
  "type": "Feature",
  "properties": {
    "tgn:hierarchy":[
        "tgn:2157066",
        "tgn:1000001",
        "tgn:7012149",
        "tgn:7007710",
        "tgn:7029392"
    ],
    "tgn:id":2157066,
    "tgn:name":"Beaver Branch",
    "tgn:placetype":[
        "aat:300008699"
    ]
},
  "bbox": [],
  "geometry": {"coordinates":[-77.9333,40.7833],"type":"Point"}
}
=======
{"geometry":{"type":"Point","coordinates":[-77.933300,40.783300]},"type":"Feature","properties":{"hierarchy":["tgn:2157066","tgn:1000001","tgn:7012149","tgn:7007710","tgn:7029392"],"placetype":["aat:300008699"],"id":2157066,"name:xx":"Beaver Branch"}}
>>>>>>> 03f74aca74312dbeaf24d7e61306dd6a786dc3d0
