{
  "id": 2159424,
  "type": "Feature",
  "properties": {
    "tgn:hierarchy":[
        "tgn:2159424",
        "tgn:1000001",
        "tgn:7012149",
        "tgn:2002053",
        "tgn:7007826",
        "tgn:7029392"
    ],
    "tgn:id":2159424,
    "tgn:name":"Bee Creek",
    "tgn:placetype":[
        "aat:300008706"
    ]
},
  "bbox": [],
  "geometry": {"coordinates":[-98.5333,32.8167],"type":"Point"}
}