<<<<<<< HEAD
{
  "id": 2159424,
  "type": "Feature",
  "properties": {
    "tgn:hierarchy":[
        "tgn:2159424",
        "tgn:1000001",
        "tgn:7012149",
        "tgn:2002053",
        "tgn:7007826",
        "tgn:7029392"
    ],
    "tgn:id":2159424,
    "tgn:name":"Bee Creek",
    "tgn:placetype":[
        "aat:300008706"
    ]
},
  "bbox": [],
  "geometry": {"coordinates":[-98.5333,32.8167],"type":"Point"}
}
=======
{"geometry":{"type":"Point","coordinates":[-98.533300,32.816700]},"type":"Feature","properties":{"hierarchy":["tgn:2159424","tgn:1000001","tgn:7012149","tgn:2002053","tgn:7007826","tgn:7029392"],"placetype":["aat:300008706"],"id":2159424,"name:xx":"Bee Creek"}}
>>>>>>> 03f74aca74312dbeaf24d7e61306dd6a786dc3d0
