{
  "id": 2271017,
  "type": "Feature",
  "properties": {
    "tgn:hierarchy":[
        "tgn:2271017",
        "tgn:1000001",
        "tgn:7012149",
        "tgn:2000203",
        "tgn:7007158",
        "tgn:7029392"
    ],
    "tgn:id":2271017,
    "tgn:name":"Cuchilla Alta Creek",
    "tgn:placetype":[
        "aat:300008706"
    ]
},
  "bbox": [],
  "geometry": {"coordinates":[-105.2333,37.1333],"type":"Point"}
}