{
  "id": 2185704,
  "type": "Feature",
  "properties": {
    "tgn:hierarchy":[
        "tgn:2185704",
        "tgn:1000001",
        "tgn:7012149",
        "tgn:7007250",
        "tgn:7029392"
    ],
    "tgn:id":2185704,
    "tgn:name":"Boise River Wildlife Management Area",
    "tgn:placetype":[
        "aat:300008178"
    ]
},
  "bbox": [],
  "geometry": {"coordinates":[-115.7167,43.5667],"type":"Point"}
}