{
  "id": 7413429,
  "type": "Feature",
  "properties": {
    "tgn:hierarchy":[
        "tgn:7413429",
        "tgn:1000001",
        "tgn:7005596",
        "tgn:7005560",
        "tgn:7029392"
    ],
    "tgn:id":7413429,
    "tgn:name:es":"Estaci\u00f3n Lomas Tristes",
    "tgn:placetype":[
        "aat:300007783"
    ]
},
  "bbox": [],
  "geometry": {"coordinates":[-92.6625,17.591667],"type":"Point"}
}