{
  "id": 7339232,
  "type": "Feature",
  "properties": {
    "tgn:hierarchy":[
        "tgn:7339232",
        "tgn:7002824",
        "tgn:1000003",
        "tgn:7002786",
        "tgn:1000095",
        "tgn:7029392"
    ],
    "tgn:id":7339232,
    "tgn:name":"Deza, R\u00edo",
    "tgn:placetype":[
        "aat:300008699"
    ]
},
  "bbox": [],
  "geometry": {"coordinates":[-8.333333,42.783333],"type":"Point"}
}