{
  "id": 2749284,
  "type": "Feature",
  "properties": {
    "tgn:hierarchy":[
        "tgn:2749284",
        "tgn:1000001",
        "tgn:7012149",
        "tgn:2001721",
        "tgn:7007708",
        "tgn:7029392"
    ],
    "tgn:id":2749284,
    "tgn:name":"Waller Reservoir 3",
    "tgn:placetype":[
        "aat:300006191"
    ]
},
  "bbox": [],
  "geometry": {"coordinates":[-117.75,45.5833],"type":"Point"}
}