{
  "id": 2730784,
  "type": "Feature",
  "properties": {
    "tgn:hierarchy":[
        "tgn:2730784",
        "tgn:1000001",
        "tgn:1002271",
        "tgn:7012149",
        "tgn:7007920",
        "tgn:7029392"
    ],
    "tgn:id":2730784,
    "tgn:name":"Tskawahyah Island",
    "tgn:placetype":[
        "aat:300008791"
    ]
},
  "bbox": [],
  "geometry": {"coordinates":[-124.7333,48.1667],"type":"Point"}
}