{
  "id": 2678933,
  "type": "Feature",
  "properties": {
    "tgn:hierarchy":[
        "tgn:2678933",
        "tgn:1000001",
        "tgn:7012149",
        "tgn:2002382",
        "tgn:7007923",
        "tgn:7029392"
    ],
    "tgn:id":2678933,
    "tgn:name":"South Fork Gypsum Creek",
    "tgn:placetype":[
        "aat:300008706"
    ]
},
  "bbox": [],
  "geometry": {"coordinates":[-109.8833,43.25],"type":"Point"}
}