{
  "id": 2411793,
  "type": "Feature",
  "properties": {
    "tgn:hierarchy":[
        "tgn:2411793",
        "tgn:1000001",
        "tgn:7016172",
        "tgn:7012149",
        "tgn:7029392"
    ],
    "tgn:id":2411793,
    "tgn:name":"Indian Mountain",
    "tgn:placetype":[
        "aat:300266640"
    ]
},
  "bbox": [],
  "geometry": {"coordinates":[-92.9833,34.5333],"type":"Point"}
}