{
  "id": 7421010,
  "type": "Feature",
  "properties": {
    "tgn:hierarchy":[
        "tgn:7421010",
        "tgn:1000001",
        "tgn:7005589",
        "tgn:7005560",
        "tgn:7029392"
    ],
    "tgn:id":7421010,
    "tgn:name:es":"Silla, Cerro de la",
    "tgn:placetype":[
        "aat:300008795"
    ]
},
  "bbox": [],
  "geometry": {"coordinates":[-100.218611,25.625],"type":"Point"}
}