<<<<<<< HEAD
{
  "id": 7478595,
  "type": "Feature",
  "properties": {
    "tgn:hierarchy":[
        "tgn:7478595",
        "tgn:7487020",
        "tgn:1000004",
        "tgn:1000141",
        "tgn:7029392"
    ],
    "tgn:id":7478595,
    "tgn:name":"Miaoli Suidao",
    "tgn:placetype":[
        "aat:300007899"
    ]
},
  "bbox": [],
  "geometry": {"coordinates":[120.808614,24.554271],"type":"Point"}
}
=======
{"geometry":{"type":"Point","coordinates":[120.808614,24.554271]},"type":"Feature","properties":{"hierarchy":["tgn:7478595","tgn:7487020","tgn:1000004","tgn:1000141","tgn:7029392"],"placetype":["aat:300007899"],"id":7478595,"name:xx":"Miaoli Suidao"}}
>>>>>>> 03f74aca74312dbeaf24d7e61306dd6a786dc3d0
