{
  "id": 7478595,
  "type": "Feature",
  "properties": {
    "tgn:hierarchy":[
        "tgn:7478595",
        "tgn:7487020",
        "tgn:1000004",
        "tgn:1000141",
        "tgn:7029392"
    ],
    "tgn:id":7478595,
    "tgn:name":"Miaoli Suidao",
    "tgn:placetype":[
        "aat:300007899"
    ]
},
  "bbox": [],
  "geometry": {"coordinates":[120.808614,24.554271],"type":"Point"}
}