{
  "id": 2717209,
  "type": "Feature",
  "properties": {
    "tgn:hierarchy":[
        "tgn:2717209",
        "tgn:7006450",
        "tgn:1000001",
        "tgn:7019674",
        "tgn:7012149",
        "tgn:7029392"
    ],
    "tgn:id":2717209,
    "tgn:name":"Third Pup",
    "tgn:placetype":[
        "aat:300008699"
    ]
},
  "bbox": [],
  "geometry": {"coordinates":[-146.6333,65.1667],"type":"Point"}
}