{
  "id": 1099570,
  "type": "Feature",
  "properties": {
    "tgn:hierarchy":[
        "tgn:1099570",
        "tgn:7006160",
        "tgn:1000946",
        "tgn:1000006",
        "tgn:7029392"
    ],
    "tgn:id":1099570,
    "tgn:name":"Sag Sag",
    "tgn:placetype":[
        "aat:300008347"
    ]
},
  "bbox": [],
  "geometry": {"coordinates":[148.3667,-5.5667],"type":"Point"}
}