{
  "id": 7429136,
  "type": "Feature",
  "properties": {
    "tgn:hierarchy":[
        "tgn:7429136",
        "tgn:1001853",
        "tgn:1000001",
        "tgn:7005560",
        "tgn:7029392"
    ],
    "tgn:id":7429136,
    "tgn:name":"Estaci\u00f3n Mezquital",
    "tgn:placetype":[
        "aat:300007783"
    ]
},
  "bbox": [],
  "geometry": {"coordinates":[-101.183333,27.766667],"type":"Point"}
}