{
  "id": 2061041,
  "type": "Feature",
  "properties": {
    "tgn:hierarchy":[
        "tgn:2061041",
        "tgn:1000001",
        "tgn:2001260",
        "tgn:7012149",
        "tgn:7007524",
        "tgn:7029392"
    ],
    "tgn:id":2061041,
    "tgn:name":"Barretts",
    "tgn:placetype":[
        "aat:300387016"
    ]
},
  "bbox": [],
  "geometry": {"coordinates":[-112.7333,45.1167],"type":"Point"}
}