{
  "id": 2468579,
  "type": "Feature",
  "properties": {
    "tgn:hierarchy":[
        "tgn:2468579",
        "tgn:1000001",
        "tgn:7012149",
        "tgn:2000556",
        "tgn:7007252",
        "tgn:7029392"
    ],
    "tgn:id":2468579,
    "tgn:name":"Long Pond",
    "tgn:placetype":[
        "aat:300008680"
    ]
},
  "bbox": [],
  "geometry": {"coordinates":[-87.55,39.2333],"type":"Point"}
}