{
  "id": 2488787,
  "type": "Feature",
  "properties": {
    "tgn:hierarchy":[
        "tgn:2488787",
        "tgn:1000001",
        "tgn:2001945",
        "tgn:7012149",
        "tgn:7007826",
        "tgn:7029392"
    ],
    "tgn:id":2488787,
    "tgn:name":"Mailbox Tank",
    "tgn:placetype":[
        "aat:300006191"
    ]
},
  "bbox": [],
  "geometry": {"coordinates":[-103.1333,29.4667],"type":"Point"}
}