<<<<<<< HEAD
{
  "id": 7489269,
  "type": "Feature",
  "properties": {
    "tgn:hierarchy":[
        "tgn:7489269",
        "tgn:7468018",
        "tgn:1000004",
        "tgn:1000141",
        "tgn:7029392"
    ],
    "tgn:id":7489269,
    "tgn:name":"Neibu Shan",
    "tgn:placetype":[
        "aat:300008777"
    ]
},
  "bbox": [],
  "geometry": {"coordinates":[120.572906,23.440239],"type":"Point"}
}
=======
{"geometry":{"type":"Point","coordinates":[120.572906,23.440239]},"type":"Feature","properties":{"hierarchy":["tgn:7489269","tgn:7468018","tgn:1000004","tgn:1000141","tgn:7029392"],"placetype":["aat:300008777"],"id":7489269,"name:xx":"Neibu Shan"}}
>>>>>>> 03f74aca74312dbeaf24d7e61306dd6a786dc3d0
