{
  "id": 7560059,
  "type": "Feature",
  "properties": {
    "tgn:hierarchy":[
        "tgn:7560059",
        "tgn:1000004",
        "tgn:7000198",
        "tgn:7016722",
        "tgn:7029392"
    ],
    "tgn:id":7560059,
    "tgn:name:en":"Bhararpura",
    "tgn:placetype":[
        "aat:300008347"
    ]
},
  "bbox": [],
  "geometry": {"coordinates":[79.212512,26.93669],"type":"Point"}
}