{
  "id": 2530830,
  "type": "Feature",
  "properties": {
    "tgn:hierarchy":[
        "tgn:2530830",
        "tgn:7006450",
        "tgn:1000001",
        "tgn:2124053",
        "tgn:7012149",
        "tgn:7029392"
    ],
    "tgn:id":2530830,
    "tgn:name":"Mudflow Creek",
    "tgn:placetype":[
        "aat:300008706"
    ]
},
  "bbox": [],
  "geometry": {"coordinates":[-148.05,61.8333],"type":"Point"}
}