{
  "id": 7321947,
  "type": "Feature",
  "properties": {
    "tgn:hierarchy":[
        "tgn:7321947",
        "tgn:1001630",
        "tgn:1000049",
        "tgn:1000002",
        "tgn:7029392"
    ],
    "tgn:id":7321947,
    "tgn:name":"Brava, Playa",
    "tgn:placetype":[
        "aat:300008816"
    ]
},
  "bbox": [],
  "geometry": {"coordinates":[-71.083333,-27.816667],"type":"Point"}
}