<<<<<<< HEAD
{
  "id": 7052315,
  "type": "Feature",
  "properties": {
    "tgn:hierarchy":[
        "tgn:7052315",
        "tgn:7003006",
        "tgn:1000003",
        "tgn:7002997",
        "tgn:1000080",
        "tgn:7029392"
    ],
    "tgn:id":7052315,
    "tgn:name":"Pellestrina, Isola di",
    "tgn:placetype":[
        "aat:300008791"
    ]
},
  "bbox": [],
  "geometry": {"coordinates":[12.316667,45.283333],"type":"Point"}
}
=======
{"geometry":{"type":"Point","coordinates":[12.316667,45.283333]},"type":"Feature","properties":{"hierarchy":["tgn:7052315","tgn:7003006","tgn:1000003","tgn:7002997","tgn:1000080","tgn:7029392"],"placetype":["aat:300008791"],"id":7052315,"name:xx":"Pellestrina, Isola di"}}
>>>>>>> 03f74aca74312dbeaf24d7e61306dd6a786dc3d0
