{
  "id": 7052315,
  "type": "Feature",
  "properties": {
    "tgn:hierarchy":[
        "tgn:7052315",
        "tgn:7003006",
        "tgn:1000003",
        "tgn:7002997",
        "tgn:1000080",
        "tgn:7029392"
    ],
    "tgn:id":7052315,
    "tgn:name":"Pellestrina, Isola di",
    "tgn:placetype":[
        "aat:300008791"
    ]
},
  "bbox": [],
  "geometry": {"coordinates":[12.316667,45.283333],"type":"Point"}
}