<<<<<<< HEAD
{
  "id": 2769991,
  "type": "Feature",
  "properties": {
    "tgn:hierarchy":[
        "tgn:2769991",
        "tgn:7013349",
        "tgn:1000001",
        "tgn:7012149",
        "tgn:7007708",
        "tgn:7029392"
    ],
    "tgn:id":2769991,
    "tgn:name":"Wilcox Ditch",
    "tgn:placetype":[
        "aat:300006075"
    ]
},
  "bbox": [],
  "geometry": {"coordinates":[-118.0333,44.9],"type":"Point"}
}
=======
{"geometry":{"type":"Point","coordinates":[-118.033300,44.900000]},"type":"Feature","properties":{"hierarchy":["tgn:2769991","tgn:7013349","tgn:1000001","tgn:7012149","tgn:7007708","tgn:7029392"],"placetype":["aat:300006075"],"id":2769991,"name:xx":"Wilcox Ditch"}}
>>>>>>> 03f74aca74312dbeaf24d7e61306dd6a786dc3d0
