<<<<<<< HEAD
{
  "id": 2251053,
  "type": "Feature",
  "properties": {
    "tgn:hierarchy":[
        "tgn:2251053",
        "tgn:1000001",
        "tgn:2001418",
        "tgn:7012149",
        "tgn:7007526",
        "tgn:7029392"
    ],
    "tgn:id":2251053,
    "tgn:name":"Column Cave",
    "tgn:placetype":[
        "aat:300008746"
    ]
},
  "bbox": [],
  "geometry": {"coordinates":[-116.15,36.2833],"type":"Point"}
}
=======
{"geometry":{"type":"Point","coordinates":[-116.150000,36.283300]},"type":"Feature","properties":{"hierarchy":["tgn:2251053","tgn:1000001","tgn:2001418","tgn:7012149","tgn:7007526","tgn:7029392"],"placetype":["aat:300008746"],"id":2251053,"name:xx":"Column Cave"}}
>>>>>>> 03f74aca74312dbeaf24d7e61306dd6a786dc3d0
