<<<<<<< HEAD
{
  "id": 7023659,
  "type": "Feature",
  "properties": {
    "tgn:hierarchy":[
        "tgn:7023659",
        "tgn:1000001",
        "tgn:7012149",
        "tgn:7007255",
        "tgn:7029392"
    ],
    "tgn:id":7023659,
    "tgn:name":"Perry Fork",
    "tgn:placetype":[
        "aat:300008699"
    ]
},
  "bbox": [],
  "geometry": {"coordinates":[-83.2333,38.4],"type":"Point"}
}
=======
{"geometry":{"type":"Point","coordinates":[-83.233300,38.400000]},"type":"Feature","properties":{"hierarchy":["tgn:7023659","tgn:1000001","tgn:7012149","tgn:7007255","tgn:7029392"],"placetype":["aat:300008699"],"id":7023659,"name:xx":"Perry Fork"}}
>>>>>>> 03f74aca74312dbeaf24d7e61306dd6a786dc3d0
