{
  "id": 7422292,
  "type": "Feature",
  "properties": {
    "tgn:hierarchy":[
        "tgn:7422292",
        "tgn:1000001",
        "tgn:1001960",
        "tgn:7005560",
        "tgn:7029392"
    ],
    "tgn:id":7422292,
    "tgn:name":"Estaci\u00f3n Cuchuta",
    "tgn:placetype":[
        "aat:300007783"
    ]
},
  "bbox": [],
  "geometry": {"coordinates":[-109.583333,30.816667],"type":"Point"}
}