{
  "id": 7224107,
  "type": "Feature",
  "properties": {
    "tgn:hierarchy":[
        "tgn:7224107",
        "tgn:7011270",
        "tgn:7002674",
        "tgn:1000003",
        "tgn:1000074",
        "tgn:7029392"
    ],
    "tgn:id":7224107,
    "tgn:name":"P\u00fdrgos",
    "tgn:placetype":[
        "aat:300008347"
    ]
},
  "bbox": [],
  "geometry": {"coordinates":[25.44951,36.383281],"type":"Point"}
}