{
  "id": 7124585,
  "type": "Feature",
  "properties": {
    "tgn:hierarchy":[
        "tgn:7124585",
        "tgn:1000003",
        "tgn:7003678",
        "tgn:7000084",
        "tgn:7029392"
    ],
    "tgn:id":7124585,
    "tgn:name":"Neunkircher H\u00f6he",
    "tgn:placetype":[
        "aat:300008795"
    ]
},
  "bbox": [],
  "geometry": {"coordinates":[8.771667,49.720556],"type":"Point"}
}