<<<<<<< HEAD
{
  "id": 2762516,
  "type": "Feature",
  "properties": {
    "tgn:hierarchy":[
        "tgn:2762516",
        "tgn:1000001",
        "tgn:7012149",
        "tgn:2002384",
        "tgn:7007923",
        "tgn:7029392"
    ],
    "tgn:id":2762516,
    "tgn:name":"West Whetstone Creek",
    "tgn:placetype":[
        "aat:300008706"
    ]
},
  "bbox": [],
  "geometry": {"coordinates":[-110.4,43.9833],"type":"Point"}
}
=======
{"geometry":{"type":"Point","coordinates":[-110.400000,43.983300]},"type":"Feature","properties":{"hierarchy":["tgn:2762516","tgn:1000001","tgn:7012149","tgn:2002384","tgn:7007923","tgn:7029392"],"placetype":["aat:300008706"],"id":2762516,"name:xx":"West Whetstone Creek"}}
>>>>>>> 03f74aca74312dbeaf24d7e61306dd6a786dc3d0
