{
  "id": 2141737,
  "type": "Feature",
  "properties": {
    "tgn:hierarchy":[
        "tgn:2141737",
        "tgn:1000001",
        "tgn:7012149",
        "tgn:7007157",
        "tgn:2000187",
        "tgn:7029392"
    ],
    "tgn:id":2141737,
    "tgn:name":"Babcock Peak",
    "tgn:placetype":[
        "aat:300008798"
    ]
},
  "bbox": [],
  "geometry": {"coordinates":[-120.5833,40.0833],"type":"Point"}
}