<<<<<<< HEAD
{
  "id": 7365629,
  "type": "Feature",
  "properties": {
    "tgn:hierarchy":[
        "tgn:7365629",
        "tgn:1000001",
        "tgn:7005589",
        "tgn:7005560",
        "tgn:7029392"
    ],
    "tgn:id":7365629,
    "tgn:name":"Fuera Vacas",
    "tgn:placetype":[
        "aat:300008347"
    ]
},
  "bbox": [],
  "geometry": {"coordinates":[-99.866667,25.016667],"type":"Point"}
}
=======
{"geometry":{"type":"Point","coordinates":[-99.866667,25.016667]},"type":"Feature","properties":{"hierarchy":["tgn:7365629","tgn:1000001","tgn:7005589","tgn:7005560","tgn:7029392"],"placetype":["aat:300008347"],"id":7365629,"name:xx":"Fuera Vacas"}}
>>>>>>> 03f74aca74312dbeaf24d7e61306dd6a786dc3d0
