{
  "id": 2590015,
  "type": "Feature",
  "properties": {
    "tgn:hierarchy":[
        "tgn:2590015",
        "tgn:1000001",
        "tgn:2000468",
        "tgn:7012149",
        "tgn:7007250",
        "tgn:7029392"
    ],
    "tgn:id":2590015,
    "tgn:name":"Poison Creek",
    "tgn:placetype":[
        "aat:300008706"
    ]
},
  "bbox": [],
  "geometry": {"coordinates":[-112.4833,44.45],"type":"Point"}
}