{
  "id": 2550481,
  "type": "Feature",
  "properties": {
    "tgn:hierarchy":[
        "tgn:2550481",
        "tgn:1000001",
        "tgn:7012149",
        "tgn:1002633",
        "tgn:7007252",
        "tgn:7029392"
    ],
    "tgn:id":2550481,
    "tgn:name":"Northwood",
    "tgn:placetype":[
        "aat:300008347"
    ]
},
  "bbox": [],
  "geometry": {"coordinates":[-86.1167,39.8167],"type":"Point"}
}