{
  "id": 7554060,
  "type": "Feature",
  "properties": {
    "tgn:hierarchy":[
        "tgn:7554060",
        "tgn:1000004",
        "tgn:7000198",
        "tgn:7016788",
        "tgn:7029392"
    ],
    "tgn:id":7554060,
    "tgn:name:en":"N\u012bpal",
    "tgn:placetype":[
        "aat:300008347"
    ]
},
  "bbox": [],
  "geometry": {"coordinates":[73.526969,25.397953],"type":"Point"}
}