<<<<<<< HEAD
{
  "id": 7056385,
  "type": "Feature",
  "properties": {
    "tgn:hierarchy":[
        "tgn:7056385",
        "tgn:7003170",
        "tgn:1000003",
        "tgn:7003125",
        "tgn:1000080",
        "tgn:7029392"
    ],
    "tgn:id":7056385,
    "tgn:name":"Ocre",
    "tgn:placetype":[
        "aat:300008347"
    ]
},
  "bbox": [],
  "geometry": {"coordinates":[12.966667,42.6],"type":"Point"}
}
=======
{"geometry":{"type":"Point","coordinates":[12.966667,42.600000]},"type":"Feature","properties":{"hierarchy":["tgn:7056385","tgn:7003170","tgn:1000003","tgn:7003125","tgn:1000080","tgn:7029392"],"placetype":["aat:300008347"],"id":7056385,"name:xx":"Ocre"}}
>>>>>>> 03f74aca74312dbeaf24d7e61306dd6a786dc3d0
