{
  "id": 1118726,
  "type": "Feature",
  "properties": {
    "tgn:hierarchy":[
        "tgn:1118726",
        "tgn:7005685",
        "tgn:1000001",
        "tgn:7005804",
        "tgn:7029392"
    ],
    "tgn:id":1118726,
    "tgn:name":"William, Lac",
    "tgn:placetype":[
        "aat:300008680"
    ]
},
  "bbox": [],
  "geometry": {"coordinates":[-71.5667,46.1167],"type":"Point"}
}