{
  "id": 2511706,
  "type": "Feature",
  "properties": {
    "tgn:hierarchy":[
        "tgn:2511706",
        "tgn:7016099",
        "tgn:1000001",
        "tgn:7012149",
        "tgn:7007516",
        "tgn:7029392"
    ],
    "tgn:id":2511706,
    "tgn:name":"Milestone Manor",
    "tgn:placetype":[
        "aat:300008347"
    ]
},
  "bbox": [],
  "geometry": {"coordinates":[-76.6333,39.4667],"type":"Point"}
}