{
  "id": 2447927,
  "type": "Feature",
  "properties": {
    "tgn:hierarchy":[
        "tgn:2447927",
        "tgn:1000001",
        "tgn:7012149",
        "tgn:2002342",
        "tgn:7007922",
        "tgn:7029392"
    ],
    "tgn:id":2447927,
    "tgn:name":"Liege Lake",
    "tgn:placetype":[
        "aat:300008680"
    ]
},
  "bbox": [],
  "geometry": {"coordinates":[-89.5833,45.6833],"type":"Point"}
}