{
  "id": 7315233,
  "type": "Feature",
  "properties": {
    "tgn:hierarchy":[
        "tgn:7315233",
        "tgn:1001699",
        "tgn:1000049",
        "tgn:1000002",
        "tgn:7029392"
    ],
    "tgn:id":7315233,
    "tgn:name":"Chonchi",
    "tgn:placetype":[
        "aat:300008347"
    ]
},
  "bbox": [],
  "geometry": {"coordinates":[-73.809167,-42.612778],"type":"Point"}
}