{
  "id": 7567055,
  "type": "Feature",
  "properties": {
    "tgn:hierarchy":[
        "tgn:7567055",
        "tgn:1000004",
        "tgn:7000198",
        "tgn:7031786",
        "tgn:7029392"
    ],
    "tgn:id":7567055,
    "tgn:name:en":"Bijnaur",
    "tgn:placetype":[
        "aat:300008347"
    ]
},
  "bbox": [],
  "geometry": {"coordinates":[78.560215,29.856696],"type":"Point"}
}