{
  "id": 7438268,
  "type": "Feature",
  "properties": {
    "tgn:hierarchy":[
        "tgn:7438268",
        "tgn:7005581",
        "tgn:1000001",
        "tgn:7005560",
        "tgn:7029392"
    ],
    "tgn:id":7438268,
    "tgn:name":"Talam\u00e1n",
    "tgn:placetype":[
        "aat:300008347"
    ]
},
  "bbox": [],
  "geometry": {"coordinates":[-106.233333,28.166667],"type":"Point"}
}