<<<<<<< HEAD
{
  "id": 7021600,
  "type": "Feature",
  "properties": {
    "tgn:hierarchy":[
        "tgn:7021600",
        "tgn:1000001",
        "tgn:7012149",
        "tgn:2000291",
        "tgn:7007240",
        "tgn:7029392"
    ],
    "tgn:id":7021600,
    "tgn:name":"Bob Russ Lakes",
    "tgn:placetype":[
        "aat:300008680"
    ]
},
  "bbox": [],
  "geometry": {"coordinates":[-85.7667,30.5],"type":"Point"}
}
=======
{"geometry":{"type":"Point","coordinates":[-85.766700,30.500000]},"type":"Feature","properties":{"hierarchy":["tgn:7021600","tgn:1000001","tgn:7012149","tgn:2000291","tgn:7007240","tgn:7029392"],"placetype":["aat:300008680"],"id":7021600,"name:xx":"Bob Russ Lakes"}}
>>>>>>> 03f74aca74312dbeaf24d7e61306dd6a786dc3d0
