{
  "id": 2361751,
  "type": "Feature",
  "properties": {
    "tgn:hierarchy":[
        "tgn:2361751",
        "tgn:1000001",
        "tgn:7012149",
        "tgn:2002353",
        "tgn:7007922",
        "tgn:7029392"
    ],
    "tgn:id":2361751,
    "tgn:name":"Graveyard Springs",
    "tgn:placetype":[
        "aat:300008697"
    ]
},
  "bbox": [],
  "geometry": {"coordinates":[-91.3833,45.95],"type":"Point"}
}