{
  "id": 2284097,
  "type": "Feature",
  "properties": {
    "tgn:hierarchy":[
        "tgn:2284097",
        "tgn:2000947",
        "tgn:1000001",
        "tgn:7012149",
        "tgn:7007520",
        "tgn:7029392"
    ],
    "tgn:id":2284097,
    "tgn:name":"Denomie Creek",
    "tgn:placetype":[
        "aat:300008706"
    ]
},
  "bbox": [],
  "geometry": {"coordinates":[-88.3667,46.6667],"type":"Point"}
}