{
  "id": 7525267,
  "type": "Feature",
  "properties": {
    "tgn:hierarchy":[
        "tgn:7525267",
        "tgn:7001242",
        "tgn:7016833",
        "tgn:1001335",
        "tgn:7029392"
    ],
    "tgn:id":7525267,
    "tgn:name:en":"Baghd\u0101d, Jaz\u012brat",
    "tgn:placetype":[
        "aat:300008791"
    ]
},
  "bbox": [],
  "geometry": {"coordinates":[30.747778,31.383611],"type":"Point"}
}