{
  "id": 7468793,
  "type": "Feature",
  "properties": {
    "tgn:hierarchy":[
        "tgn:7468793",
        "tgn:1000957",
        "tgn:1000004",
        "tgn:1000141",
        "tgn:7029392"
    ],
    "tgn:id":7468793,
    "tgn:name":"Xiangzhangcuo",
    "tgn:placetype":[
        "aat:300008347"
    ]
},
  "bbox": [],
  "geometry": {"coordinates":[121.666016,25.081958],"type":"Point"}
}