<<<<<<< HEAD
{
  "id": 2401460,
  "type": "Feature",
  "properties": {
    "tgn:hierarchy":[
        "tgn:2401460",
        "tgn:1000001",
        "tgn:7016172",
        "tgn:7012149",
        "tgn:2000144",
        "tgn:7029392"
    ],
    "tgn:id":2401460,
    "tgn:name":"Horseshoe Brake",
    "tgn:placetype":[
        "aat:300008905"
    ]
},
  "bbox": [],
  "geometry": {"coordinates":[-91.6167,33.8833],"type":"Point"}
}
=======
{"geometry":{"type":"Point","coordinates":[-91.616700,33.883300]},"type":"Feature","properties":{"hierarchy":["tgn:2401460","tgn:1000001","tgn:7016172","tgn:7012149","tgn:2000144","tgn:7029392"],"placetype":["aat:300008905"],"id":2401460,"name:xx":"Horseshoe Brake"}}
>>>>>>> 03f74aca74312dbeaf24d7e61306dd6a786dc3d0
