{
  "id": 1028250,
  "type": "Feature",
  "properties": {
    "tgn:hierarchy":[
        "tgn:1028250",
        "tgn:7002445",
        "tgn:1000003",
        "tgn:7008117",
        "tgn:7008591",
        "tgn:7029392"
    ],
    "tgn:id":1028250,
    "tgn:name:en":"Abbey Town",
    "tgn:placetype":[
        "aat:300008347"
    ]
},
  "bbox": [],
  "geometry": {"coordinates":[-3.283333,54.833333],"type":"Point"}
}