{
  "id": 7022077,
  "type": "Feature",
  "properties": {
    "tgn:hierarchy":[
        "tgn:7022077",
        "tgn:1000001",
        "tgn:7012149",
        "tgn:2002171",
        "tgn:7007919",
        "tgn:7029392"
    ],
    "tgn:id":7022077,
    "tgn:name":"Dixon Millpond",
    "tgn:placetype":[
        "aat:300006191"
    ]
},
  "bbox": [],
  "geometry": {"coordinates":[-78.0167,36.8833],"type":"Point"}
}