{
  "id": 2439323,
  "type": "Feature",
  "properties": {
    "tgn:hierarchy":[
        "tgn:2439323",
        "tgn:1000001",
        "tgn:7012149",
        "tgn:2001821",
        "tgn:7007713",
        "tgn:7029392"
    ],
    "tgn:id":2439323,
    "tgn:name":"Kirk Cordes Number 30 Reservoir",
    "tgn:placetype":[
        "aat:300006191"
    ]
},
  "bbox": [],
  "geometry": {"coordinates":[-102.0833,44.2667],"type":"Point"}
}