{
  "id": 2225133,
  "type": "Feature",
  "properties": {
    "tgn:hierarchy":[
        "tgn:2225133",
        "tgn:1000001",
        "tgn:7012149",
        "tgn:2001308",
        "tgn:7007524",
        "tgn:7029392"
    ],
    "tgn:id":2225133,
    "tgn:name":"Castle Creek",
    "tgn:placetype":[
        "aat:300008706"
    ]
},
  "bbox": [],
  "geometry": {"coordinates":[-110.05,45.6167],"type":"Point"}
}