{
  "id": 2170107,
  "type": "Feature",
  "properties": {
    "tgn:hierarchy":[
        "tgn:2170107",
        "tgn:1000001",
        "tgn:7012149",
        "tgn:7007712",
        "tgn:7029392"
    ],
    "tgn:id":2170107,
    "tgn:name":"Big Pond",
    "tgn:placetype":[
        "aat:300006191"
    ]
},
  "bbox": [],
  "geometry": {"coordinates":[-80.8333,32.4333],"type":"Point"}
}