{
  "id": 2340664,
  "type": "Feature",
  "properties": {
    "tgn:hierarchy":[
        "tgn:2340664",
        "tgn:1000001",
        "tgn:7012149",
        "tgn:2000975",
        "tgn:7007520",
        "tgn:7029392"
    ],
    "tgn:id":2340664,
    "tgn:name":"Frenchy Lake",
    "tgn:placetype":[
        "aat:300008680"
    ]
},
  "bbox": [],
  "geometry": {"coordinates":[-87.8167,46.2833],"type":"Point"}
}