{
  "id": 2433160,
  "type": "Feature",
  "properties": {
    "tgn:hierarchy":[
        "tgn:2433160",
        "tgn:1000001",
        "tgn:7012149",
        "tgn:2001913",
        "tgn:7007825",
        "tgn:7029392"
    ],
    "tgn:id":2433160,
    "tgn:name":"Kell Ridge",
    "tgn:placetype":[
        "aat:300266640"
    ]
},
  "bbox": [],
  "geometry": {"coordinates":[-85.35,35.2667],"type":"Point"}
}