{
  "id": 1055567,
  "type": "Feature",
  "properties": {
    "tgn:hierarchy":[
        "tgn:1055567",
        "tgn:7012076",
        "tgn:1000003",
        "tgn:7006660",
        "tgn:7029392"
    ],
    "tgn:id":1055567,
    "tgn:name":"Kon'kove",
    "tgn:placetype":[
        "aat:300008347"
    ]
},
  "bbox": [],
  "geometry": {"coordinates":[38.1667,47.3333],"type":"Point"}
}