{
  "id": 7035848,
  "type": "Feature",
  "properties": {
    "tgn:hierarchy":[
        "tgn:7035848",
        "tgn:7003006",
        "tgn:1000003",
        "tgn:7002997",
        "tgn:1000080",
        "tgn:7029392"
    ],
    "tgn:id":7035848,
    "tgn:name":"Rosapineta",
    "tgn:placetype":[
        "aat:300008347"
    ]
},
  "bbox": [],
  "geometry": {"coordinates":[12.320556,45.134167],"type":"Point"}
}