{
  "id": 7206546,
  "type": "Feature",
  "properties": {
    "tgn:hierarchy":[
        "tgn:7206546",
        "tgn:1000003",
        "tgn:7003687",
        "tgn:7000084",
        "tgn:7029392"
    ],
    "tgn:id":7206546,
    "tgn:name":"Dadewitzer Mark",
    "tgn:placetype":[
        "aat:300055621"
    ]
},
  "bbox": [],
  "geometry": {"coordinates":[12.05,51.983333],"type":"Point"}
}