{
  "id": 2399853,
  "type": "Feature",
  "properties": {
    "tgn:hierarchy":[
        "tgn:2399853",
        "tgn:1000001",
        "tgn:7012149",
        "tgn:2001714",
        "tgn:7007708",
        "tgn:7029392"
    ],
    "tgn:id":2399853,
    "tgn:name":"Horse Camp Reservoir",
    "tgn:placetype":[
        "aat:300006191"
    ]
},
  "bbox": [],
  "geometry": {"coordinates":[-121.0167,42.0833],"type":"Point"}
}