{
  "id": 2278551,
  "type": "Feature",
  "properties": {
    "tgn:hierarchy":[
        "tgn:2278551",
        "tgn:1000001",
        "tgn:2000470",
        "tgn:7012149",
        "tgn:7007250",
        "tgn:7029392"
    ],
    "tgn:id":2278551,
    "tgn:name":"Dead Cat Canyon",
    "tgn:placetype":[
        "aat:300008761"
    ]
},
  "bbox": [],
  "geometry": {"coordinates":[-113.8833,44.35],"type":"Point"}
}