{
  "id": 2178642,
  "type": "Feature",
  "properties": {
    "tgn:hierarchy":[
        "tgn:2178642",
        "tgn:1000001",
        "tgn:7012149",
        "tgn:2002251",
        "tgn:7007920",
        "tgn:7029392"
    ],
    "tgn:id":2178642,
    "tgn:name":"Blacksnake Ridge",
    "tgn:placetype":[
        "aat:300266640"
    ]
},
  "bbox": [],
  "geometry": {"coordinates":[-118.05,46.0667],"type":"Point"}
}