{
  "id": 2690006,
  "type": "Feature",
  "properties": {
    "tgn:hierarchy":[
        "tgn:2690006",
        "tgn:1000001",
        "tgn:7012149",
        "tgn:1002821",
        "tgn:7007568",
        "tgn:7029392"
    ],
    "tgn:id":2690006,
    "tgn:name":"Staats Point",
    "tgn:placetype":[
        "aat:300008850"
    ]
},
  "bbox": [],
  "geometry": {"coordinates":[-73.75,42.5667],"type":"Point"}
}