<<<<<<< HEAD
{
  "id": 7356716,
  "type": "Feature",
  "properties": {
    "tgn:hierarchy":[
        "tgn:7356716",
        "tgn:1000001",
        "tgn:7005595",
        "tgn:7005560",
        "tgn:7029392"
    ],
    "tgn:id":7356716,
    "tgn:name":"Ceuta, Bahia de",
    "tgn:placetype":[
        "aat:300008679"
    ]
},
  "bbox": [],
  "geometry": {"coordinates":[-107.266667,24.166667],"type":"Point"}
}
=======
{"geometry":{"type":"Point","coordinates":[-107.266667,24.166667]},"type":"Feature","properties":{"hierarchy":["tgn:7356716","tgn:1000001","tgn:7005595","tgn:7005560","tgn:7029392"],"placetype":["aat:300008679"],"id":7356716,"name:xx":"Ceuta, Bahia de"}}
>>>>>>> 03f74aca74312dbeaf24d7e61306dd6a786dc3d0
