{
  "id": 2089216,
  "type": "Feature",
  "properties": {
    "tgn:hierarchy":[
        "tgn:2089216",
        "tgn:1000001",
        "tgn:1002278",
        "tgn:7012149",
        "tgn:7007710",
        "tgn:7029392"
    ],
    "tgn:id":2089216,
    "tgn:name":"Helvetia",
    "tgn:placetype":[
        "aat:300008347"
    ]
},
  "bbox": [],
  "geometry": {"coordinates":[-78.7667,41.0333],"type":"Point"}
}