{
  "id": 1063878,
  "type": "Feature",
  "properties": {
    "tgn:hierarchy":[
        "tgn:1063878",
        "tgn:7003742",
        "tgn:1000003",
        "tgn:7011731",
        "tgn:7029392"
    ],
    "tgn:id":1063878,
    "tgn:name":"Adelboden",
    "tgn:placetype":[
        "aat:300008347"
    ]
},
  "bbox": [],
  "geometry": {"coordinates":[7.5667,46.4833],"type":"Point"}
}