{
  "id": 7504425,
  "type": "Feature",
  "properties": {
    "tgn:hierarchy":[
        "tgn:7504425",
        "tgn:1009227",
        "tgn:1000226",
        "tgn:7018437",
        "tgn:1000006",
        "tgn:7029392"
    ],
    "tgn:id":7504425,
    "tgn:name:en":"Wairuna Peak",
    "tgn:placetype":[
        "aat:300008798"
    ]
},
  "bbox": [],
  "geometry": {"coordinates":[169.216667,-46.166667],"type":"Point"}
}