<<<<<<< HEAD
{
  "id": 7112525,
  "type": "Feature",
  "properties": {
    "tgn:hierarchy":[
        "tgn:7112525",
        "tgn:1000003",
        "tgn:7003678",
        "tgn:7000084",
        "tgn:7029392"
    ],
    "tgn:id":7112525,
    "tgn:name":"Rinderb\u00fcgener Hof",
    "tgn:placetype":[
        "aat:300000206"
    ]
},
  "bbox": [],
  "geometry": {"coordinates":[9.2,50.3],"type":"Point"}
}
=======
{"geometry":{"type":"Point","coordinates":[9.200000,50.300000]},"type":"Feature","properties":{"hierarchy":["tgn:7112525","tgn:1000003","tgn:7003678","tgn:7000084","tgn:7029392"],"placetype":["aat:300000206"],"id":7112525,"name:xx":"Rinderb\u00fcgener Hof"}}
>>>>>>> 03f74aca74312dbeaf24d7e61306dd6a786dc3d0
