{
  "id": 7225083,
  "type": "Feature",
  "properties": {
    "tgn:hierarchy":[
        "tgn:7225083",
        "tgn:7011167",
        "tgn:7001338",
        "tgn:1000003",
        "tgn:1000074",
        "tgn:7029392"
    ],
    "tgn:id":7225083,
    "tgn:name":"R\u00edfion",
    "tgn:placetype":[
        "aat:300008347"
    ]
},
  "bbox": [],
  "geometry": {"coordinates":[20.383333,38.233333],"type":"Point"}
}