<<<<<<< HEAD
{
  "id": 2766247,
  "type": "Feature",
  "properties": {
    "tgn:hierarchy":[
        "tgn:2766247",
        "tgn:1000001",
        "tgn:7012149",
        "tgn:1002742",
        "tgn:7007920",
        "tgn:7029392"
    ],
    "tgn:id":2766247,
    "tgn:name":"White Lakes",
    "tgn:placetype":[
        "aat:300008680"
    ]
},
  "bbox": [],
  "geometry": {"coordinates":[-120.5333,48.9],"type":"Point"}
}
=======
{"geometry":{"type":"Point","coordinates":[-120.533300,48.900000]},"type":"Feature","properties":{"hierarchy":["tgn:2766247","tgn:1000001","tgn:7012149","tgn:1002742","tgn:7007920","tgn:7029392"],"placetype":["aat:300008680"],"id":2766247,"name:xx":"White Lakes"}}
>>>>>>> 03f74aca74312dbeaf24d7e61306dd6a786dc3d0
