{
  "id": 2691883,
  "type": "Feature",
  "properties": {
    "tgn:hierarchy":[
        "tgn:2691883",
        "tgn:1000001",
        "tgn:7012149",
        "tgn:2001722",
        "tgn:7007708",
        "tgn:7029392"
    ],
    "tgn:id":2691883,
    "tgn:name":"Starvation Spring",
    "tgn:placetype":[
        "aat:300008697"
    ]
},
  "bbox": [],
  "geometry": {"coordinates":[-117.2333,45.6167],"type":"Point"}
}