{
  "id": 7499727,
  "type": "Feature",
  "properties": {
    "tgn:hierarchy":[
        "tgn:7499727",
        "tgn:1000004",
        "tgn:1000959",
        "tgn:1000141",
        "tgn:7029392"
    ],
    "tgn:id":7499727,
    "tgn:name":"Songshan Daqiao",
    "tgn:placetype":[
        "aat:300007836"
    ]
},
  "bbox": [],
  "geometry": {"coordinates":[121.526708,25.072601],"type":"Point"}
}