{
  "id": 2435767,
  "type": "Feature",
  "properties": {
    "tgn:hierarchy":[
        "tgn:2435767",
        "tgn:1000001",
        "tgn:7012149",
        "tgn:2001822",
        "tgn:7007713",
        "tgn:7029392"
    ],
    "tgn:id":2435767,
    "tgn:name":"Ketterlins Point",
    "tgn:placetype":[
        "aat:300008850"
    ]
},
  "bbox": [],
  "geometry": {"coordinates":[-102.2167,45.75],"type":"Point"}
}