{
  "id": 7551765,
  "type": "Feature",
  "properties": {
    "tgn:hierarchy":[
        "tgn:7551765",
        "tgn:1000004",
        "tgn:7000198",
        "tgn:7016694",
        "tgn:7029392"
    ],
    "tgn:id":7551765,
    "tgn:name:en":"Chhedak",
    "tgn:placetype":[
        "aat:300008347"
    ]
},
  "bbox": [],
  "geometry": {"coordinates":[86.85,20.683333],"type":"Point"}
}