{
  "id": 2516525,
  "type": "Feature",
  "properties": {
    "tgn:hierarchy":[
        "tgn:2516525",
        "tgn:1000001",
        "tgn:7012149",
        "tgn:7007157",
        "tgn:1002956",
        "tgn:7029392"
    ],
    "tgn:id":2516525,
    "tgn:name":"Mineral King",
    "tgn:placetype":[
        "aat:300008347"
    ]
},
  "bbox": [],
  "geometry": {"coordinates":[-118.5833,36.45],"type":"Point"}
}