{
  "id": 7101774,
  "type": "Feature",
  "properties": {
    "tgn:hierarchy":[
        "tgn:7101774",
        "tgn:7003669",
        "tgn:1000003",
        "tgn:7000084",
        "tgn:7029392"
    ],
    "tgn:id":7101774,
    "tgn:name":"R\u00f6thenlohe",
    "tgn:placetype":[
        "aat:300008347"
    ]
},
  "bbox": [],
  "geometry": {"coordinates":[11.75,49.75],"type":"Point"}
}