<<<<<<< HEAD
{
  "id": 2406759,
  "type": "Feature",
  "properties": {
    "tgn:hierarchy":[
        "tgn:2406759",
        "tgn:1000001",
        "tgn:7012149",
        "tgn:7007711",
        "tgn:7029392"
    ],
    "tgn:id":2406759,
    "tgn:name":"Hunt River",
    "tgn:placetype":[
        "aat:300008707"
    ]
},
  "bbox": [],
  "geometry": {"coordinates":[-71.4833,41.5833],"type":"Point"}
}
=======
{"geometry":{"type":"Point","coordinates":[-71.483300,41.583300]},"type":"Feature","properties":{"hierarchy":["tgn:2406759","tgn:1000001","tgn:7012149","tgn:7007711","tgn:7029392"],"placetype":["aat:300008707"],"id":2406759,"name:xx":"Hunt River"}}
>>>>>>> 03f74aca74312dbeaf24d7e61306dd6a786dc3d0
