{
  "id": 2089960,
  "type": "Feature",
  "properties": {
    "tgn:hierarchy":[
        "tgn:2089960",
        "tgn:1000001",
        "tgn:7012149",
        "tgn:1002690",
        "tgn:7007710",
        "tgn:7029392"
    ],
    "tgn:id":2089960,
    "tgn:name":"Lansdale",
    "tgn:placetype":[
        "aat:300008347"
    ]
},
  "bbox": [],
  "geometry": {"coordinates":[-75.2833,40.2333],"type":"Point"}
}