{
  "id": 2780848,
  "type": "Feature",
  "properties": {
    "tgn:hierarchy":[
        "tgn:2780848",
        "tgn:1000001",
        "tgn:2002135",
        "tgn:7012149",
        "tgn:7007828",
        "tgn:7029392"
    ],
    "tgn:id":2780848,
    "tgn:name":"Woodard Brook",
    "tgn:placetype":[
        "aat:300008699"
    ]
},
  "bbox": [],
  "geometry": {"coordinates":[-72.7667,44.0833],"type":"Point"}
}