{
  "id": 2656780,
  "type": "Feature",
  "properties": {
    "tgn:hierarchy":[
        "tgn:2656780",
        "tgn:1000001",
        "tgn:7006451",
        "tgn:7012149",
        "tgn:7029392"
    ],
    "tgn:id":2656780,
    "tgn:name":"Sheep Creek Point",
    "tgn:placetype":[
        "aat:300008850"
    ]
},
  "bbox": [],
  "geometry": {"coordinates":[-110.7833,34.2833],"type":"Point"}
}