{
  "id": 7029353,
  "type": "Feature",
  "properties": {
    "tgn:hierarchy":[
        "tgn:7029353",
        "tgn:7002445",
        "tgn:1000003",
        "tgn:7008166",
        "tgn:7008591",
        "tgn:7029392"
    ],
    "tgn:id":7029353,
    "tgn:name":"Skipwith",
    "tgn:placetype":[
        "aat:300008347",
        "aat:300008372"
    ]
},
  "bbox": [],
  "geometry": {"coordinates":[-0.983333,53.833333],"type":"Point"}
}