{
  "id": 7507531,
  "type": "Feature",
  "properties": {
    "tgn:hierarchy":[
        "tgn:7507531",
        "tgn:7520092",
        "tgn:1008380",
        "tgn:1000226",
        "tgn:1000006",
        "tgn:7029392"
    ],
    "tgn:id":7507531,
    "tgn:name:en":"Pourewa Island",
    "tgn:placetype":[
        "aat:300008791"
    ]
},
  "bbox": [],
  "geometry": {"coordinates":[178.35,-38.383333],"type":"Point"}
}