{
  "id": 2746777,
  "type": "Feature",
  "properties": {
    "tgn:hierarchy":[
        "tgn:2746777",
        "tgn:1000001",
        "tgn:1002347",
        "tgn:7012149",
        "tgn:7007568",
        "tgn:7029392"
    ],
    "tgn:id":2746777,
    "tgn:name":"Wades Brook",
    "tgn:placetype":[
        "aat:300008699"
    ]
},
  "bbox": [],
  "geometry": {"coordinates":[-73.95,41.45],"type":"Point"}
}