{
  "id": 7386573,
  "type": "Feature",
  "properties": {
    "tgn:hierarchy":[
        "tgn:7386573",
        "tgn:7005586",
        "tgn:1000001",
        "tgn:7005560",
        "tgn:7029392"
    ],
    "tgn:id":7386573,
    "tgn:name":"Planta",
    "tgn:placetype":[
        "aat:300008347"
    ]
},
  "bbox": [],
  "geometry": {"coordinates":[-104.25,21.216667],"type":"Point"}
}