{
  "id": 7414579,
  "type": "Feature",
  "properties": {
    "tgn:hierarchy":[
        "tgn:7414579",
        "tgn:1000001",
        "tgn:7005591",
        "tgn:7005560",
        "tgn:7029392"
    ],
    "tgn:id":7414579,
    "tgn:name:es":"Tequisistl\u00e1n, R\u00edo",
    "tgn:placetype":[
        "aat:300008699"
    ]
},
  "bbox": [],
  "geometry": {"coordinates":[-95.656111,16.375],"type":"Point"}
}