{
  "id": 2566421,
  "type": "Feature",
  "properties": {
    "tgn:hierarchy":[
        "tgn:2566421",
        "tgn:1000001",
        "tgn:7006451",
        "tgn:7012149",
        "tgn:2000102",
        "tgn:7029392"
    ],
    "tgn:id":2566421,
    "tgn:name":"Palomas Tank",
    "tgn:placetype":[
        "aat:300006191"
    ]
},
  "bbox": [],
  "geometry": {"coordinates":[-111.2667,31.4667],"type":"Point"}
}