{
  "id": 7510514,
  "type": "Feature",
  "properties": {
    "tgn:hierarchy":[
        "tgn:7510514",
        "tgn:1009227",
        "tgn:1000226",
        "tgn:7018437",
        "tgn:1000006",
        "tgn:7029392"
    ],
    "tgn:id":7510514,
    "tgn:name:en":"Southern Reservoir",
    "tgn:placetype":[
        "aat:300006191"
    ]
},
  "bbox": [],
  "geometry": {"coordinates":[170.45,-45.883333],"type":"Point"}
}