{
  "id": 7194726,
  "type": "Feature",
  "properties": {
    "tgn:hierarchy":[
        "tgn:7194726",
        "tgn:7003669",
        "tgn:1000003",
        "tgn:7000084",
        "tgn:7029392"
    ],
    "tgn:id":7194726,
    "tgn:name":"Dobel",
    "tgn:placetype":[
        "aat:300000206"
    ]
},
  "bbox": [],
  "geometry": {"coordinates":[12.333333,47.966667],"type":"Point"}
}