{
  "id": 2531983,
  "type": "Feature",
  "properties": {
    "tgn:hierarchy":[
        "tgn:2531983",
        "tgn:1000001",
        "tgn:7012149",
        "tgn:2002190",
        "tgn:7007919",
        "tgn:7029392"
    ],
    "tgn:id":2531983,
    "tgn:name":"Mumaw Hill",
    "tgn:placetype":[
        "aat:300008798"
    ]
},
  "bbox": [],
  "geometry": {"coordinates":[-78.6833,38.8333],"type":"Point"}
}