{
  "id": 2675947,
  "type": "Feature",
  "properties": {
    "tgn:hierarchy":[
        "tgn:2675947",
        "tgn:1000001",
        "tgn:7012149",
        "tgn:2002113",
        "tgn:7007827",
        "tgn:7029392"
    ],
    "tgn:id":2675947,
    "tgn:name":"Sooner Rocks",
    "tgn:placetype":[
        "aat:300008798"
    ]
},
  "bbox": [],
  "geometry": {"coordinates":[-111.05,37.3167],"type":"Point"}
}