{
  "id": 7531629,
  "type": "Feature",
  "properties": {
    "tgn:hierarchy":[
        "tgn:7531629",
        "tgn:7001242",
        "tgn:7016833",
        "tgn:1001079",
        "tgn:7029392"
    ],
    "tgn:id":7531629,
    "tgn:name:en":"Naj' al A\u1e29w\u0101l",
    "tgn:placetype":[
        "aat:300008347"
    ]
},
  "bbox": [],
  "geometry": {"coordinates":[29.720658,31.00737],"type":"Point"}
}