{
  "id": 7404061,
  "type": "Feature",
  "properties": {
    "tgn:hierarchy":[
        "tgn:7404061",
        "tgn:7016644",
        "tgn:1000001",
        "tgn:7005560",
        "tgn:7029392"
    ],
    "tgn:id":7404061,
    "tgn:name":"La Zapotera",
    "tgn:placetype":[
        "aat:300008347"
    ]
},
  "bbox": [],
  "geometry": {"coordinates":[-103.716667,18.716667],"type":"Point"}
}