{
  "id": 2725689,
  "type": "Feature",
  "properties": {
    "tgn:hierarchy":[
        "tgn:2725689",
        "tgn:7002659",
        "tgn:1000001",
        "tgn:7012149",
        "tgn:2000056",
        "tgn:7029392"
    ],
    "tgn:id":2725689,
    "tgn:name":"Torbert Lake",
    "tgn:placetype":[
        "aat:300006191"
    ]
},
  "bbox": [],
  "geometry": {"coordinates":[-85.35,32.3667],"type":"Point"}
}