{
  "id": 7128865,
  "type": "Feature",
  "properties": {
    "tgn:hierarchy":[
        "tgn:7128865",
        "tgn:7003692",
        "tgn:1000003",
        "tgn:7000084",
        "tgn:7029392"
    ],
    "tgn:id":7128865,
    "tgn:name":"Oberer Bauernhof",
    "tgn:placetype":[
        "aat:300000206"
    ]
},
  "bbox": [],
  "geometry": {"coordinates":[8.133333,48.266667],"type":"Point"}
}