{
  "id": 7291090,
  "type": "Feature",
  "properties": {
    "tgn:hierarchy":[
        "tgn:7291090",
        "tgn:1001702",
        "tgn:1000049",
        "tgn:1000002",
        "tgn:7029392"
    ],
    "tgn:id":7291090,
    "tgn:name":"D\u00e9lano, Caleta",
    "tgn:placetype":[
        "aat:300132317"
    ]
},
  "bbox": [],
  "geometry": {"coordinates":[-72.616667,-51.816667],"type":"Point"}
}