{
  "id": 2229060,
  "type": "Feature",
  "properties": {
    "tgn:hierarchy":[
        "tgn:2229060",
        "tgn:1000001",
        "tgn:7012149",
        "tgn:2001032",
        "tgn:7007521",
        "tgn:7029392"
    ],
    "tgn:id":2229060,
    "tgn:name":"Cedar Island Lake",
    "tgn:placetype":[
        "aat:300008905"
    ]
},
  "bbox": [],
  "geometry": {"coordinates":[-94.9833,45.2833],"type":"Point"}
}