{
  "id": 1038821,
  "type": "Feature",
  "properties": {
    "tgn:hierarchy":[
        "tgn:1038821",
        "tgn:7003692",
        "tgn:1000003",
        "tgn:7000084",
        "tgn:7029392"
    ],
    "tgn:id":1038821,
    "tgn:name":"Dingelsdorf",
    "tgn:placetype":[
        "aat:300008347"
    ]
},
  "bbox": [],
  "geometry": {"coordinates":[9.15,47.733333],"type":"Point"}
}