<<<<<<< HEAD
{
  "id": 7379287,
  "type": "Feature",
  "properties": {
    "tgn:hierarchy":[
        "tgn:7379287",
        "tgn:1000001",
        "tgn:7005589",
        "tgn:7005560",
        "tgn:7029392"
    ],
    "tgn:id":7379287,
    "tgn:name":"Los Sauces",
    "tgn:placetype":[
        "aat:300008347"
    ]
},
  "bbox": [],
  "geometry": {"coordinates":[-100.083333,24.866667],"type":"Point"}
}
=======
{"geometry":{"type":"Point","coordinates":[-100.083333,24.866667]},"type":"Feature","properties":{"hierarchy":["tgn:7379287","tgn:1000001","tgn:7005589","tgn:7005560","tgn:7029392"],"placetype":["aat:300008347"],"id":7379287,"name:xx":"Los Sauces"}}
>>>>>>> 03f74aca74312dbeaf24d7e61306dd6a786dc3d0
