{
  "id": 2615089,
  "type": "Feature",
  "properties": {
    "tgn:hierarchy":[
        "tgn:2615089",
        "tgn:1000001",
        "tgn:2001268",
        "tgn:7012149",
        "tgn:7007524",
        "tgn:7029392"
    ],
    "tgn:id":2615089,
    "tgn:name":"Reservation Creek",
    "tgn:placetype":[
        "aat:300008706"
    ]
},
  "bbox": [],
  "geometry": {"coordinates":[-106.0333,46.4167],"type":"Point"}
}