{
  "id": 2314365,
  "type": "Feature",
  "properties": {
    "tgn:hierarchy":[
        "tgn:2314365",
        "tgn:1000001",
        "tgn:7012149",
        "tgn:2001309",
        "tgn:7007524",
        "tgn:7029392"
    ],
    "tgn:id":2314365,
    "tgn:name":"Elk Hill",
    "tgn:placetype":[
        "aat:300008798"
    ]
},
  "bbox": [],
  "geometry": {"coordinates":[-112.8667,47.6833],"type":"Point"}
}