{
  "id": 2040098,
  "type": "Feature",
  "properties": {
    "tgn:hierarchy":[
        "tgn:2040098",
        "tgn:1000001",
        "tgn:7012149",
        "tgn:2000832",
        "tgn:7007255",
        "tgn:7029392"
    ],
    "tgn:id":2040098,
    "tgn:name":"Lynn City",
    "tgn:placetype":[
        "aat:300008347"
    ]
},
  "bbox": [],
  "geometry": {"coordinates":[-87.25,37.3667],"type":"Point"}
}