{
  "id": 2492798,
  "type": "Feature",
  "properties": {
    "tgn:hierarchy":[
        "tgn:2492798",
        "tgn:1000001",
        "tgn:7012149",
        "tgn:7007157",
        "tgn:7014004",
        "tgn:7029392"
    ],
    "tgn:id":2492798,
    "tgn:name":"Mariposa Lake",
    "tgn:placetype":[
        "aat:300006191"
    ]
},
  "bbox": [],
  "geometry": {"coordinates":[-120.1333,37.2833],"type":"Point"}
}