{
  "id": 2544761,
  "type": "Feature",
  "properties": {
    "tgn:hierarchy":[
        "tgn:2544761",
        "tgn:1000001",
        "tgn:7012149",
        "tgn:7007253",
        "tgn:7029392"
    ],
    "tgn:id":2544761,
    "tgn:name":"North Coal Creek",
    "tgn:placetype":[
        "aat:300008706"
    ]
},
  "bbox": [],
  "geometry": {"coordinates":[-92.8833,41.1833],"type":"Point"}
}