{
  "id": 2630809,
  "type": "Feature",
  "properties": {
    "tgn:hierarchy":[
        "tgn:2630809",
        "tgn:1000001",
        "tgn:7012149",
        "tgn:2000888",
        "tgn:7007256",
        "tgn:7029392"
    ],
    "tgn:id":2630809,
    "tgn:name":"Round Lake",
    "tgn:placetype":[
        "aat:300008680"
    ]
},
  "bbox": [],
  "geometry": {"coordinates":[-93.05,31.8667],"type":"Point"}
}