{
  "id": 2607588,
  "type": "Feature",
  "properties": {
    "tgn:hierarchy":[
        "tgn:2607588",
        "tgn:1000001",
        "tgn:7012149",
        "tgn:2000226",
        "tgn:7007158",
        "tgn:7029392"
    ],
    "tgn:id":2607588,
    "tgn:name":"Rapid Creek",
    "tgn:placetype":[
        "aat:300008706"
    ]
},
  "bbox": [],
  "geometry": {"coordinates":[-105.8833,40.6833],"type":"Point"}
}