{
  "id": 2260544,
  "type": "Feature",
  "properties": {
    "tgn:hierarchy":[
        "tgn:2260544",
        "tgn:1000001",
        "tgn:7012149",
        "tgn:2001038",
        "tgn:7007521",
        "tgn:7029392"
    ],
    "tgn:id":2260544,
    "tgn:name":"County Ditch Number Fortyfive",
    "tgn:placetype":[
        "aat:300006075"
    ]
},
  "bbox": [],
  "geometry": {"coordinates":[-93.55,44.4333],"type":"Point"}
}