{
  "id": 2344568,
  "type": "Feature",
  "properties": {
    "tgn:hierarchy":[
        "tgn:2344568",
        "tgn:1000001",
        "tgn:7006451",
        "tgn:7012149",
        "tgn:2000097",
        "tgn:7029392"
    ],
    "tgn:id":2344568,
    "tgn:name":"Garambullo Wash",
    "tgn:placetype":[
        "aat:300008699"
    ]
},
  "bbox": [],
  "geometry": {"coordinates":[-112.3167,33.75],"type":"Point"}
}