{
  "id": 1051632,
  "type": "Feature",
  "properties": {
    "tgn:hierarchy":[
        "tgn:1051632",
        "tgn:1000004",
        "tgn:7011604",
        "tgn:7018214",
        "tgn:7002435",
        "tgn:7029392"
    ],
    "tgn:id":1051632,
    "tgn:name":"Sherstobitovo",
    "tgn:placetype":[
        "aat:300008347"
    ]
},
  "bbox": [],
  "geometry": {"coordinates":[78.8667,57.2167],"type":"Point"}
}