{
  "id": 1088830,
  "type": "Feature",
  "properties": {
    "tgn:hierarchy":[
        "tgn:1088830",
        "tgn:7001242",
        "tgn:7016654",
        "tgn:1000159",
        "tgn:7029392"
    ],
    "tgn:id":1088830,
    "tgn:name":"Boende",
    "tgn:placetype":[
        "aat:300008347"
    ]
},
  "bbox": [],
  "geometry": {"coordinates":[20.85,-0.25],"type":"Point"}
}