{
  "id": 2559041,
  "type": "Feature",
  "properties": {
    "tgn:hierarchy":[
        "tgn:2559041",
        "tgn:1000001",
        "tgn:7016172",
        "tgn:7012149",
        "tgn:2000147",
        "tgn:7029392"
    ],
    "tgn:id":2559041,
    "tgn:name":"Omni Lake",
    "tgn:placetype":[
        "aat:300006191"
    ]
},
  "bbox": [],
  "geometry": {"coordinates":[-92.0167,35.0167],"type":"Point"}
}