{
  "id": 2770523,
  "type": "Feature",
  "properties": {
    "tgn:hierarchy":[
        "tgn:2770523",
        "tgn:1000001",
        "tgn:7020676",
        "tgn:7012149",
        "tgn:7007256",
        "tgn:7029392"
    ],
    "tgn:id":2770523,
    "tgn:name":"Wild Ridge",
    "tgn:placetype":[
        "aat:300266640"
    ]
},
  "bbox": [],
  "geometry": {"coordinates":[-92.7833,29.9167],"type":"Point"}
}