{
  "id": 7247787,
  "type": "Feature",
  "properties": {
    "tgn:hierarchy":[
        "tgn:7247787",
        "tgn:7003457",
        "tgn:1000003",
        "tgn:1000063",
        "tgn:7018236",
        "tgn:7029392"
    ],
    "tgn:id":7247787,
    "tgn:name":"Duivenkeet",
    "tgn:placetype":[
        "aat:300000206"
    ]
},
  "bbox": [],
  "geometry": {"coordinates":[4.233333,51.183333],"type":"Point"}
}