{
  "id": 2001827,
  "type": "Feature",
  "properties": {
    "tgn:hierarchy":[
        "tgn:2001827",
        "tgn:1000001",
        "tgn:7012149",
        "tgn:7007713",
        "tgn:7029392"
    ],
    "tgn:id":2001827,
    "tgn:name":"Spink",
    "tgn:placetype":[
        "aat:300387145",
        "aat:300000771"
    ]
},
  "bbox": [],
  "geometry": {"coordinates":[-98.3167,44.9333],"type":"Point"}
}