{
  "id": 2231553,
  "type": "Feature",
  "properties": {
    "tgn:hierarchy":[
        "tgn:2231553",
        "tgn:1000001",
        "tgn:7012149",
        "tgn:7007526",
        "tgn:7029392"
    ],
    "tgn:id":2231553,
    "tgn:name":"Chalk Mountain",
    "tgn:placetype":[
        "aat:300008798"
    ]
},
  "bbox": [],
  "geometry": {"coordinates":[-115.9167,37.5167],"type":"Point"}
}