{
  "id": 2295515,
  "type": "Feature",
  "properties": {
    "tgn:hierarchy":[
        "tgn:2295515",
        "tgn:2001935",
        "tgn:1000001",
        "tgn:7012149",
        "tgn:7007826",
        "tgn:7029392"
    ],
    "tgn:id":2295515,
    "tgn:name":"Dripping Spring",
    "tgn:placetype":[
        "aat:300008697"
    ]
},
  "bbox": [],
  "geometry": {"coordinates":[-101.3667,34.9333],"type":"Point"}
}