{
  "id": 2454445,
  "type": "Feature",
  "properties": {
    "tgn:hierarchy":[
        "tgn:2454445",
        "tgn:1000001",
        "tgn:7012149",
        "tgn:2002348",
        "tgn:7007922",
        "tgn:7029392"
    ],
    "tgn:id":2454445,
    "tgn:name":"Little Dardis Lake",
    "tgn:placetype":[
        "aat:300008680"
    ]
},
  "bbox": [],
  "geometry": {"coordinates":[-90.3333,45.7167],"type":"Point"}
}