{
  "id": 7388931,
  "type": "Feature",
  "properties": {
    "tgn:hierarchy":[
        "tgn:7388931",
        "tgn:7005581",
        "tgn:1000001",
        "tgn:7005560",
        "tgn:7029392"
    ],
    "tgn:id":7388931,
    "tgn:name":"Pusanachic",
    "tgn:placetype":[
        "aat:300008347"
    ]
},
  "bbox": [],
  "geometry": {"coordinates":[-107.85,27.716667],"type":"Point"}
}