{
  "id": 1006771,
  "type": "Feature",
  "properties": {
    "tgn:hierarchy":[
        "tgn:1006771",
        "tgn:1000660",
        "tgn:1000002",
        "tgn:1000056",
        "tgn:7029392"
    ],
    "tgn:id":1006771,
    "tgn:name":"Chao, Isla",
    "tgn:placetype":[
        "aat:300008791"
    ]
},
  "bbox": [],
  "geometry": {"coordinates":[-78.7833,-8.75],"type":"Point"}
}