{
  "id": 7514737,
  "type": "Feature",
  "properties": {
    "tgn:hierarchy":[
        "tgn:7514737",
        "tgn:1009227",
        "tgn:1000226",
        "tgn:7016822",
        "tgn:1000006",
        "tgn:7029392"
    ],
    "tgn:id":7514737,
    "tgn:name:en":"Deas Head",
    "tgn:placetype":[
        "aat:300008850"
    ]
},
  "bbox": [],
  "geometry": {"coordinates":[166.216667,-50.533333],"type":"Point"}
}