{
  "id": 7236175,
  "type": "Feature",
  "properties": {
    "tgn:hierarchy":[
        "tgn:7236175",
        "tgn:7002692",
        "tgn:7012056",
        "tgn:1000003",
        "tgn:1000074",
        "tgn:7029392"
    ],
    "tgn:id":7236175,
    "tgn:name":"\u00c1yios Vas\u00edlios",
    "tgn:placetype":[
        "aat:300008347"
    ]
},
  "bbox": [],
  "geometry": {"coordinates":[25.583333,35.016667],"type":"Point"}
}