{
  "id": 2482122,
  "type": "Feature",
  "properties": {
    "tgn:hierarchy":[
        "tgn:2482122",
        "tgn:1000001",
        "tgn:7012149",
        "tgn:2124023",
        "tgn:7007248",
        "tgn:7029392"
    ],
    "tgn:id":2482122,
    "tgn:name":"Lanford Lake",
    "tgn:placetype":[
        "aat:300006191"
    ]
},
  "bbox": [],
  "geometry": {"coordinates":[-84.15,33.7833],"type":"Point"}
}