{
  "id": 1093333,
  "type": "Feature",
  "properties": {
    "tgn:hierarchy":[
        "tgn:1093333",
        "tgn:7001242",
        "tgn:7017574",
        "tgn:1000193",
        "tgn:7029392"
    ],
    "tgn:id":1093333,
    "tgn:name":"Lydenburg",
    "tgn:placetype":[
        "aat:300008347"
    ]
},
  "bbox": [],
  "geometry": {"coordinates":[30.4833,-25.1667],"type":"Point"}
}