{
  "id": 7230176,
  "type": "Feature",
  "properties": {
    "tgn:hierarchy":[
        "tgn:7230176",
        "tgn:7002690",
        "tgn:7012056",
        "tgn:1000003",
        "tgn:1000074",
        "tgn:7029392"
    ],
    "tgn:id":7230176,
    "tgn:name":"Khorevtian\u00e1",
    "tgn:placetype":[
        "aat:300008347"
    ]
},
  "bbox": [],
  "geometry": {"coordinates":[23.683333,35.466667],"type":"Point"}
}