{
  "id": 7191185,
  "type": "Feature",
  "properties": {
    "tgn:hierarchy":[
        "tgn:7191185",
        "tgn:7000096",
        "tgn:1000003",
        "tgn:7000084",
        "tgn:7029392"
    ],
    "tgn:id":7191185,
    "tgn:name":"Finkenkrug",
    "tgn:placetype":[
        "aat:300000745"
    ]
},
  "bbox": [],
  "geometry": {"coordinates":[13.066667,52.566667],"type":"Point"}
}