{
  "id": 7254056,
  "type": "Feature",
  "properties": {
    "tgn:hierarchy":[
        "tgn:7254056",
        "tgn:7003460",
        "tgn:1000003",
        "tgn:1000063",
        "tgn:4012014",
        "tgn:7029392"
    ],
    "tgn:id":7254056,
    "tgn:name":"Souxhon",
    "tgn:placetype":[
        "aat:300008347"
    ]
},
  "bbox": [],
  "geometry": {"coordinates":[5.457004,50.609472],"type":"Point"}
}