{
  "id": 2786249,
  "type": "Feature",
  "properties": {
    "tgn:hierarchy":[
        "tgn:2786249",
        "tgn:1000001",
        "tgn:7012149",
        "tgn:1002525",
        "tgn:7007252",
        "tgn:7029392"
    ],
    "tgn:id":2786249,
    "tgn:name":"Youngs Creek",
    "tgn:placetype":[
        "aat:300008706"
    ]
},
  "bbox": [],
  "geometry": {"coordinates":[-86.1333,39.5333],"type":"Point"}
}