{
  "id": 7387149,
  "type": "Feature",
  "properties": {
    "tgn:hierarchy":[
        "tgn:7387149",
        "tgn:1000001",
        "tgn:7005597",
        "tgn:7005560",
        "tgn:7029392"
    ],
    "tgn:id":7387149,
    "tgn:name":"Rancho Asturias",
    "tgn:placetype":[
        "aat:300008347"
    ]
},
  "bbox": [],
  "geometry": {"coordinates":[-98.45,25.883333],"type":"Point"}
}