<<<<<<< HEAD
{
  "id": 2764440,
  "type": "Feature",
  "properties": {
    "tgn:hierarchy":[
        "tgn:2764440",
        "tgn:1000001",
        "tgn:7012149",
        "tgn:2002069",
        "tgn:7007826",
        "tgn:7029392"
    ],
    "tgn:id":2764440,
    "tgn:name":"Whey Hollow",
    "tgn:placetype":[
        "aat:300008761"
    ]
},
  "bbox": [],
  "geometry": {"coordinates":[-98.5667,31.0667],"type":"Point"}
}
=======
{"geometry":{"type":"Point","coordinates":[-98.566700,31.066700]},"type":"Feature","properties":{"hierarchy":["tgn:2764440","tgn:1000001","tgn:7012149","tgn:2002069","tgn:7007826","tgn:7029392"],"placetype":["aat:300008761"],"id":2764440,"name:xx":"Whey Hollow"}}
>>>>>>> 03f74aca74312dbeaf24d7e61306dd6a786dc3d0
