{
  "id": 7497926,
  "type": "Feature",
  "properties": {
    "tgn:hierarchy":[
        "tgn:7497926",
        "tgn:7001004",
        "tgn:1000004",
        "tgn:1000141",
        "tgn:7029392"
    ],
    "tgn:id":7497926,
    "tgn:name":"Gaofeng Qiao",
    "tgn:placetype":[
        "aat:300007836"
    ]
},
  "bbox": [],
  "geometry": {"coordinates":[120.387064,22.634378],"type":"Point"}
}