{
  "id": 7165387,
  "type": "Feature",
  "properties": {
    "tgn:hierarchy":[
        "tgn:7165387",
        "tgn:7003669",
        "tgn:1000003",
        "tgn:7000084",
        "tgn:7029392"
    ],
    "tgn:id":7165387,
    "tgn:name":"Igenhausen",
    "tgn:placetype":[
        "aat:300008347"
    ]
},
  "bbox": [],
  "geometry": {"coordinates":[11.05,48.466667],"type":"Point"}
}