{
  "id": 2482395,
  "type": "Feature",
  "properties": {
    "tgn:hierarchy":[
        "tgn:2482395",
        "tgn:1000001",
        "tgn:7012149",
        "tgn:2001924",
        "tgn:7007825",
        "tgn:7029392"
    ],
    "tgn:id":2482395,
    "tgn:name":"Lanie Pit",
    "tgn:placetype":[
        "aat:300008746"
    ]
},
  "bbox": [],
  "geometry": {"coordinates":[-85.45,35.7833],"type":"Point"}
}