{
  "id": 2194110,
  "type": "Feature",
  "properties": {
    "tgn:hierarchy":[
        "tgn:2194110",
        "tgn:1000001",
        "tgn:7012149",
        "tgn:1002774",
        "tgn:7007709",
        "tgn:7029392"
    ],
    "tgn:id":2194110,
    "tgn:name":"Brickhouse Point",
    "tgn:placetype":[
        "aat:300008850"
    ]
},
  "bbox": [],
  "geometry": {"coordinates":[-76.15,36.25],"type":"Point"}
}