{
  "id": 1093258,
  "type": "Feature",
  "properties": {
    "tgn:hierarchy":[
        "tgn:1093258",
        "tgn:7001242",
        "tgn:7017584",
        "tgn:1000193",
        "tgn:7029392"
    ],
    "tgn:id":1093258,
    "tgn:name":"Komkans",
    "tgn:placetype":[
        "aat:300008347"
    ]
},
  "bbox": [],
  "geometry": {"coordinates":[18.15,-31.2667],"type":"Point"}
}