{
  "id": 2776342,
  "type": "Feature",
  "properties": {
    "tgn:hierarchy":[
        "tgn:2776342",
        "tgn:1000001",
        "tgn:7012149",
        "tgn:2001067",
        "tgn:7007521",
        "tgn:7029392"
    ],
    "tgn:id":2776342,
    "tgn:name":"Winchester Lake",
    "tgn:placetype":[
        "aat:300008680"
    ]
},
  "bbox": [],
  "geometry": {"coordinates":[-92.55,48.0333],"type":"Point"}
}