<<<<<<< HEAD
{
  "id": 2761301,
  "type": "Feature",
  "properties": {
    "tgn:hierarchy":[
        "tgn:2761301",
        "tgn:1000001",
        "tgn:7012149",
        "tgn:7007157",
        "tgn:1002791",
        "tgn:7029392"
    ],
    "tgn:id":2761301,
    "tgn:name":"West Meadow Creek",
    "tgn:placetype":[
        "aat:300008706"
    ]
},
  "bbox": [],
  "geometry": {"coordinates":[-120.25,39.0667],"type":"Point"}
}
=======
{"geometry":{"type":"Point","coordinates":[-120.250000,39.066700]},"type":"Feature","properties":{"hierarchy":["tgn:2761301","tgn:1000001","tgn:7012149","tgn:7007157","tgn:1002791","tgn:7029392"],"placetype":["aat:300008706"],"id":2761301,"name:xx":"West Meadow Creek"}}
>>>>>>> 03f74aca74312dbeaf24d7e61306dd6a786dc3d0
