{
  "id": 1069909,
  "type": "Feature",
  "properties": {
    "tgn:hierarchy":[
        "tgn:1069909",
        "tgn:1000004",
        "tgn:1001261",
        "tgn:1000111",
        "tgn:7029392"
    ],
    "tgn:id":1069909,
    "tgn:name":"Linxia",
    "tgn:placetype":[
        "aat:300008347"
    ]
},
  "bbox": [],
  "geometry": {"coordinates":[103.1333,35.5167],"type":"Point"}
}