{
  "id": 7032178,
  "type": "Feature",
  "properties": {
    "tgn:hierarchy":[
        "tgn:7032178",
        "tgn:1000003",
        "tgn:7002892",
        "tgn:1000070",
        "tgn:7029392"
    ],
    "tgn:id":7032178,
    "tgn:name":"Cordouan, Plateau de",
    "tgn:placetype":[
        "aat:300008808"
    ]
},
  "bbox": [],
  "geometry": {"coordinates":[-1.203,45.583],"type":"Point"}
}