{
  "id": 7286582,
  "type": "Feature",
  "properties": {
    "tgn:hierarchy":[
        "tgn:7286582",
        "tgn:7002464",
        "tgn:1000049",
        "tgn:1000002",
        "tgn:7029392"
    ],
    "tgn:id":7286582,
    "tgn:name":"Gutijane",
    "tgn:placetype":[
        "aat:300008347"
    ]
},
  "bbox": [],
  "geometry": {"coordinates":[-69.05,-18.516667],"type":"Point"}
}