{
  "id": 7567907,
  "type": "Feature",
  "properties": {
    "tgn:hierarchy":[
        "tgn:7567907",
        "tgn:1001828",
        "tgn:1000004",
        "tgn:7000198",
        "tgn:7029392"
    ],
    "tgn:id":7567907,
    "tgn:name:en":"Sirsangundia",
    "tgn:placetype":[
        "aat:300008347"
    ]
},
  "bbox": [],
  "geometry": {"coordinates":[78.831944,17.997222],"type":"Point"}
}