{
  "id": 2564497,
  "type": "Feature",
  "properties": {
    "tgn:hierarchy":[
        "tgn:2564497",
        "tgn:1000001",
        "tgn:2002107",
        "tgn:7012149",
        "tgn:7007827",
        "tgn:7029392"
    ],
    "tgn:id":2564497,
    "tgn:name":"Packard Lake",
    "tgn:placetype":[
        "aat:300008680"
    ]
},
  "bbox": [],
  "geometry": {"coordinates":[-110.8333,40.6667],"type":"Point"}
}