{
  "id": 7560674,
  "type": "Feature",
  "properties": {
    "tgn:hierarchy":[
        "tgn:7560674",
        "tgn:1000004",
        "tgn:7000198",
        "tgn:7016722",
        "tgn:7029392"
    ],
    "tgn:id":7560674,
    "tgn:name:en":"Karanpur",
    "tgn:placetype":[
        "aat:300008347"
    ]
},
  "bbox": [],
  "geometry": {"coordinates":[79.564258,27.532731],"type":"Point"}
}