{
  "id": 7133303,
  "type": "Feature",
  "properties": {
    "tgn:hierarchy":[
        "tgn:7133303",
        "tgn:1000003",
        "tgn:7003682",
        "tgn:7000084",
        "tgn:7029392"
    ],
    "tgn:id":7133303,
    "tgn:name":"Neidhof",
    "tgn:placetype":[
        "aat:300000206"
    ]
},
  "bbox": [],
  "geometry": {"coordinates":[7.033333,50.016667],"type":"Point"}
}