{
  "id": 7218950,
  "type": "Feature",
  "properties": {
    "tgn:hierarchy":[
        "tgn:7218950",
        "tgn:7002707",
        "tgn:7002705",
        "tgn:1000003",
        "tgn:1000074",
        "tgn:7029392"
    ],
    "tgn:id":7218950,
    "tgn:name":"Vrad\u00e9ton",
    "tgn:placetype":[
        "aat:300008347"
    ]
},
  "bbox": [],
  "geometry": {"coordinates":[20.777222,39.895278],"type":"Point"}
}