<<<<<<< HEAD
{
  "id": 7357415,
  "type": "Feature",
  "properties": {
    "tgn:hierarchy":[
        "tgn:7357415",
        "tgn:7005581",
        "tgn:1000001",
        "tgn:7005560",
        "tgn:7029392"
    ],
    "tgn:id":7357415,
    "tgn:name":"Rancho Corral de Duarte",
    "tgn:placetype":[
        "aat:300000241"
    ]
},
  "bbox": [],
  "geometry": {"coordinates":[-106.066667,26.85],"type":"Point"}
}
=======
{"geometry":{"type":"Point","coordinates":[-106.066667,26.850000]},"type":"Feature","properties":{"hierarchy":["tgn:7357415","tgn:7005581","tgn:1000001","tgn:7005560","tgn:7029392"],"placetype":["aat:300000241"],"id":7357415,"name:xx":"Rancho Corral de Duarte"}}
>>>>>>> 03f74aca74312dbeaf24d7e61306dd6a786dc3d0
