{
  "id": 1104849,
  "type": "Feature",
  "properties": {
    "tgn:hierarchy":[
        "tgn:1104849",
        "tgn:1000001",
        "tgn:7012149",
        "tgn:7007157",
        "tgn:7014475",
        "tgn:7029392"
    ],
    "tgn:id":1104849,
    "tgn:name":"Hamilton, Mount",
    "tgn:placetype":[
        "aat:300008795"
    ]
},
  "bbox": [],
  "geometry": {"coordinates":[-121.6333,37.3333],"type":"Point"}
}