{
  "id": 7393350,
  "type": "Feature",
  "properties": {
    "tgn:hierarchy":[
        "tgn:7393350",
        "tgn:1000001",
        "tgn:7005591",
        "tgn:7005560",
        "tgn:7029392"
    ],
    "tgn:id":7393350,
    "tgn:name":"San Antonio Encinal",
    "tgn:placetype":[
        "aat:300008347"
    ]
},
  "bbox": [],
  "geometry": {"coordinates":[-96.116667,18.066667],"type":"Point"}
}