{
  "id": 7064351,
  "type": "Feature",
  "properties": {
    "tgn:hierarchy":[
        "tgn:7064351",
        "tgn:7003669",
        "tgn:1000003",
        "tgn:7000084",
        "tgn:7029392"
    ],
    "tgn:id":7064351,
    "tgn:name":"Unterbr\u00fccklein",
    "tgn:placetype":[
        "aat:300008347"
    ]
},
  "bbox": [],
  "geometry": {"coordinates":[11.483333,50.033333],"type":"Point"}
}