<<<<<<< HEAD
{
  "id": 7176811,
  "type": "Feature",
  "properties": {
    "tgn:hierarchy":[
        "tgn:7176811",
        "tgn:7000096",
        "tgn:1000003",
        "tgn:7000084",
        "tgn:7029392"
    ],
    "tgn:id":7176811,
    "tgn:name":"G\u00fcterberg",
    "tgn:placetype":[
        "aat:300008347"
    ]
},
  "bbox": [],
  "geometry": {"coordinates":[13.766667,53.466667],"type":"Point"}
}
=======
{"geometry":{"type":"Point","coordinates":[13.766667,53.466667]},"type":"Feature","properties":{"hierarchy":["tgn:7176811","tgn:7000096","tgn:1000003","tgn:7000084","tgn:7029392"],"placetype":["aat:300008347"],"id":7176811,"name:xx":"G\u00fcterberg"}}
>>>>>>> 03f74aca74312dbeaf24d7e61306dd6a786dc3d0
