{
  "id": 2521205,
  "type": "Feature",
  "properties": {
    "tgn:hierarchy":[
        "tgn:2521205",
        "tgn:1000001",
        "tgn:7012149",
        "tgn:2000364",
        "tgn:7007248",
        "tgn:7029392"
    ],
    "tgn:id":2521205,
    "tgn:name":"Monteideo",
    "tgn:placetype":[
        "aat:300008347"
    ]
},
  "bbox": [],
  "geometry": {"coordinates":[-82.8333,34.3333],"type":"Point"}
}