{
  "id": 7561466,
  "type": "Feature",
  "properties": {
    "tgn:hierarchy":[
        "tgn:7561466",
        "tgn:1000004",
        "tgn:7000198",
        "tgn:7016722",
        "tgn:7029392"
    ],
    "tgn:id":7561466,
    "tgn:name:en":"Shankarpur",
    "tgn:placetype":[
        "aat:300008347"
    ]
},
  "bbox": [],
  "geometry": {"coordinates":[79.121846,26.854869],"type":"Point"}
}