<<<<<<< HEAD
{
  "id": 2401582,
  "type": "Feature",
  "properties": {
    "tgn:hierarchy":[
        "tgn:2401582",
        "tgn:1000001",
        "tgn:7012149",
        "tgn:2001713",
        "tgn:7007708",
        "tgn:7029392"
    ],
    "tgn:id":2401582,
    "tgn:name":"Horseshoe Gulch",
    "tgn:placetype":[
        "aat:300008761"
    ]
},
  "bbox": [],
  "geometry": {"coordinates":[-123.5333,42.0833],"type":"Point"}
}
=======
{"geometry":{"type":"Point","coordinates":[-123.533300,42.083300]},"type":"Feature","properties":{"hierarchy":["tgn:2401582","tgn:1000001","tgn:7012149","tgn:2001713","tgn:7007708","tgn:7029392"],"placetype":["aat:300008761"],"id":2401582,"name:xx":"Horseshoe Gulch"}}
>>>>>>> 03f74aca74312dbeaf24d7e61306dd6a786dc3d0
