{
  "id": 2374061,
  "type": "Feature",
  "properties": {
    "tgn:hierarchy":[
        "tgn:2374061",
        "tgn:1000001",
        "tgn:7012149",
        "tgn:2001880",
        "tgn:7007825",
        "tgn:7029392"
    ],
    "tgn:id":2374061,
    "tgn:name":"Hammock Hollow",
    "tgn:placetype":[
        "aat:300008761"
    ]
},
  "bbox": [],
  "geometry": {"coordinates":[-85.5833,36.2833],"type":"Point"}
}