{
  "id": 7577817,
  "type": "Feature",
  "properties": {
    "tgn:hierarchy":[
        "tgn:7577817",
        "tgn:1000004",
        "tgn:7000198",
        "tgn:7000799",
        "tgn:7029392"
    ],
    "tgn:id":7577817,
    "tgn:name:en":"Khreuh",
    "tgn:placetype":[
        "aat:300008347"
    ]
},
  "bbox": [],
  "geometry": {"coordinates":[74.998994,34.01777],"type":"Point"}
}