{
  "id": 2639902,
  "type": "Feature",
  "properties": {
    "tgn:hierarchy":[
        "tgn:2639902",
        "tgn:1000001",
        "tgn:7012149",
        "tgn:2002188",
        "tgn:7007919",
        "tgn:7029392"
    ],
    "tgn:id":2639902,
    "tgn:name":"Sample Branch",
    "tgn:placetype":[
        "aat:300008699"
    ]
},
  "bbox": [],
  "geometry": {"coordinates":[-81.8833,37.05],"type":"Point"}
}