{
  "id": 7205526,
  "type": "Feature",
  "properties": {
    "tgn:hierarchy":[
        "tgn:7205526",
        "tgn:7003669",
        "tgn:1000003",
        "tgn:7000084",
        "tgn:7029392"
    ],
    "tgn:id":7205526,
    "tgn:name":"Burker Wald",
    "tgn:placetype":[
        "aat:300008863"
    ]
},
  "bbox": [],
  "geometry": {"coordinates":[10.466667,49.15],"type":"Point"}
}