{
  "id": 7152083,
  "type": "Feature",
  "properties": {
    "tgn:hierarchy":[
        "tgn:7152083",
        "tgn:1000003",
        "tgn:7000094",
        "tgn:7000084",
        "tgn:7029392"
    ],
    "tgn:id":7152083,
    "tgn:name":"Kaminshof",
    "tgn:placetype":[
        "aat:300008347"
    ]
},
  "bbox": [],
  "geometry": {"coordinates":[11.65,53.983333],"type":"Point"}
}