{
  "id": 2766208,
  "type": "Feature",
  "properties": {
    "tgn:hierarchy":[
        "tgn:2766208",
        "tgn:1000001",
        "tgn:7012149",
        "tgn:1002441",
        "tgn:7007706",
        "tgn:7029392"
    ],
    "tgn:id":2766208,
    "tgn:name":"White Lake",
    "tgn:placetype":[
        "aat:300006191"
    ]
},
  "bbox": [],
  "geometry": {"coordinates":[-84.3167,39.0667],"type":"Point"}
}