{
  "id": 7443505,
  "type": "Feature",
  "properties": {
    "tgn:hierarchy":[
        "tgn:7443505",
        "tgn:7002445",
        "tgn:1000003",
        "tgn:7026489",
        "tgn:7008591",
        "tgn:7029392"
    ],
    "tgn:id":7443505,
    "tgn:name:en":"Tilehurst",
    "tgn:placetype":[
        "aat:300008347"
    ]
},
  "bbox": [],
  "geometry": {"coordinates":[-1.033333,51.45],"type":"Point"}
}