{
  "id": 7584121,
  "type": "Feature",
  "properties": {
    "tgn:hierarchy":[
        "tgn:7584121",
        "tgn:1000004",
        "tgn:7000198",
        "tgn:1001894",
        "tgn:7029392"
    ],
    "tgn:id":7584121,
    "tgn:name:en":"Gum\u0101ngan Pah\u0101r",
    "tgn:placetype":[
        "aat:300008795"
    ]
},
  "bbox": [],
  "geometry": {"coordinates":[78.947951,24.916691],"type":"Point"}
}