{
  "id": 7550708,
  "type": "Feature",
  "properties": {
    "tgn:hierarchy":[
        "tgn:7550708",
        "tgn:1000004",
        "tgn:7000198",
        "tgn:7016722",
        "tgn:7029392"
    ],
    "tgn:id":7550708,
    "tgn:name:en":"Birdha",
    "tgn:placetype":[
        "aat:300008347"
    ]
},
  "bbox": [],
  "geometry": {"coordinates":[78.484284,24.542878],"type":"Point"}
}