{
  "id": 2273052,
  "type": "Feature",
  "properties": {
    "tgn:hierarchy":[
        "tgn:2273052",
        "tgn:1000001",
        "tgn:2001786",
        "tgn:7012149",
        "tgn:7007713",
        "tgn:7029392"
    ],
    "tgn:id":2273052,
    "tgn:name":"Cuyahogo Mine",
    "tgn:placetype":[
        "aat:300000390"
    ]
},
  "bbox": [],
  "geometry": {"coordinates":[-103.4167,43.85],"type":"Point"}
}