{
  "id": 2775945,
  "type": "Feature",
  "properties": {
    "tgn:hierarchy":[
        "tgn:2775945",
        "tgn:1000001",
        "tgn:7012149",
        "tgn:2001854",
        "tgn:7007825",
        "tgn:7029392"
    ],
    "tgn:id":2775945,
    "tgn:name":"Wilson Pen Branch",
    "tgn:placetype":[
        "aat:300008699"
    ]
},
  "bbox": [],
  "geometry": {"coordinates":[-85.0167,35.8667],"type":"Point"}
}