{
  "id": 2458534,
  "type": "Feature",
  "properties": {
    "tgn:hierarchy":[
        "tgn:2458534",
        "tgn:1000001",
        "tgn:7012149",
        "tgn:2000834",
        "tgn:7007255",
        "tgn:7029392"
    ],
    "tgn:id":2458534,
    "tgn:name":"Little No Creek",
    "tgn:placetype":[
        "aat:300008706"
    ]
},
  "bbox": [],
  "geometry": {"coordinates":[-86.95,37.5167],"type":"Point"}
}