{
  "id": 2416261,
  "type": "Feature",
  "properties": {
    "tgn:hierarchy":[
        "tgn:2416261",
        "tgn:1000001",
        "tgn:1002286",
        "tgn:7012149",
        "tgn:7007710",
        "tgn:7029392"
    ],
    "tgn:id":2416261,
    "tgn:name":"J U Branch",
    "tgn:placetype":[
        "aat:300008699"
    ]
},
  "bbox": [],
  "geometry": {"coordinates":[-77.8333,41.2167],"type":"Point"}
}