{
  "id": 2126244,
  "type": "Feature",
  "properties": {
    "tgn:hierarchy":[
        "tgn:2126244",
        "tgn:1000001",
        "tgn:7012149",
        "tgn:2001907",
        "tgn:7007825",
        "tgn:7029392"
    ],
    "tgn:id":2126244,
    "tgn:name":"Adkins Branch",
    "tgn:placetype":[
        "aat:300008699"
    ]
},
  "bbox": [],
  "geometry": {"coordinates":[-85.15,36.1333],"type":"Point"}
}