{
  "id": 6006048,
  "type": "Feature",
  "properties": {
    "tgn:hierarchy":[
        "tgn:6006048",
        "tgn:1000003",
        "tgn:7006656",
        "tgn:7029392"
    ],
    "tgn:id":6006048,
    "tgn:name":"Transnistria",
    "tgn:placetype":[
        "aat:300387346"
    ]
},
  "bbox": [],
  "geometry": {"coordinates":[29.25,47.333333],"type":"Point"}
}