{
  "id": 7295742,
  "type": "Feature",
  "properties": {
    "tgn:hierarchy":[
        "tgn:7295742",
        "tgn:7002847",
        "tgn:1001647",
        "tgn:1000003",
        "tgn:1000095",
        "tgn:7029392"
    ],
    "tgn:id":7295742,
    "tgn:name":"Villanueva de Bogas",
    "tgn:placetype":[
        "aat:300008347"
    ]
},
  "bbox": [],
  "geometry": {"coordinates":[-3.65,39.716667],"type":"Point"}
}