{
  "id": 2217504,
  "type": "Feature",
  "properties": {
    "tgn:hierarchy":[
        "tgn:2217504",
        "tgn:1000001",
        "tgn:7012149",
        "tgn:2001719",
        "tgn:7007708",
        "tgn:7029392"
    ],
    "tgn:id":2217504,
    "tgn:name":"Campbell Creek",
    "tgn:placetype":[
        "aat:300008706"
    ]
},
  "bbox": [],
  "geometry": {"coordinates":[-119.6667,45.1833],"type":"Point"}
}