{
  "id": 7489748,
  "type": "Feature",
  "properties": {
    "tgn:hierarchy":[
        "tgn:7489748",
        "tgn:1000004",
        "tgn:7490934",
        "tgn:1000141",
        "tgn:7029392"
    ],
    "tgn:id":7489748,
    "tgn:name":"Pizidi",
    "tgn:placetype":[
        "aat:300008347"
    ]
},
  "bbox": [],
  "geometry": {"coordinates":[120.27,23.295278],"type":"Point"}
}