{
  "id": 2223987,
  "type": "Feature",
  "properties": {
    "tgn:hierarchy":[
        "tgn:2223987",
        "tgn:1000001",
        "tgn:7012149",
        "tgn:2001296",
        "tgn:7007524",
        "tgn:7029392"
    ],
    "tgn:id":2223987,
    "tgn:name":"Cartwright Coulee Ditch",
    "tgn:placetype":[
        "aat:300006075"
    ]
},
  "bbox": [],
  "geometry": {"coordinates":[-112.5167,48.2667],"type":"Point"}
}