{
  "id": 2237868,
  "type": "Feature",
  "properties": {
    "tgn:hierarchy":[
        "tgn:2237868",
        "tgn:1000001",
        "tgn:7012149",
        "tgn:7007157",
        "tgn:2000185",
        "tgn:7029392"
    ],
    "tgn:id":2237868,
    "tgn:name":"Chipmonk Spring",
    "tgn:placetype":[
        "aat:300008697"
    ]
},
  "bbox": [],
  "geometry": {"coordinates":[-122.9333,39.5167],"type":"Point"}
}