{
  "id": 7147202,
  "type": "Feature",
  "properties": {
    "tgn:hierarchy":[
        "tgn:7147202",
        "tgn:1000003",
        "tgn:7003685",
        "tgn:7000084",
        "tgn:7029392"
    ],
    "tgn:id":7147202,
    "tgn:name":"Kleinneusch\u00f6nberg",
    "tgn:placetype":[
        "aat:300008347"
    ]
},
  "bbox": [],
  "geometry": {"coordinates":[13.316667,50.683333],"type":"Point"}
}