<<<<<<< HEAD
{
  "id": 7170818,
  "type": "Feature",
  "properties": {
    "tgn:hierarchy":[
        "tgn:7170818",
        "tgn:1000003",
        "tgn:7003685",
        "tgn:7000084",
        "tgn:7029392"
    ],
    "tgn:id":7170818,
    "tgn:name":"Hirschwinkel",
    "tgn:placetype":[
        "aat:300000206"
    ]
},
  "bbox": [],
  "geometry": {"coordinates":[14.766667,51.35],"type":"Point"}
}
=======
{"geometry":{"type":"Point","coordinates":[14.766667,51.350000]},"type":"Feature","properties":{"hierarchy":["tgn:7170818","tgn:1000003","tgn:7003685","tgn:7000084","tgn:7029392"],"placetype":["aat:300000206"],"id":7170818,"name:xx":"Hirschwinkel"}}
>>>>>>> 03f74aca74312dbeaf24d7e61306dd6a786dc3d0
