{
  "id": 2300650,
  "type": "Feature",
  "properties": {
    "tgn:hierarchy":[
        "tgn:2300650",
        "tgn:1000001",
        "tgn:7012149",
        "tgn:2001980",
        "tgn:7007826",
        "tgn:7029392"
    ],
    "tgn:id":2300650,
    "tgn:name":"Dunbar Cave",
    "tgn:placetype":[
        "aat:300008746"
    ]
},
  "bbox": [],
  "geometry": {"coordinates":[-100.55,29.9333],"type":"Point"}
}