{
  "id": 7277579,
  "type": "Feature",
  "properties": {
    "tgn:hierarchy":[
        "tgn:7277579",
        "tgn:1001702",
        "tgn:1000049",
        "tgn:1000002",
        "tgn:7029392"
    ],
    "tgn:id":7277579,
    "tgn:name":"Wodsworth, Bah\u00eda",
    "tgn:placetype":[
        "aat:300132316"
    ]
},
  "bbox": [],
  "geometry": {"coordinates":[-74.05,-52.983333],"type":"Point"}
}