{
  "id": 7019981,
  "type": "Feature",
  "properties": {
    "tgn:hierarchy":[
        "tgn:7019981",
        "tgn:1000001",
        "tgn:7012149",
        "tgn:2002379",
        "tgn:7007923",
        "tgn:7029392"
    ],
    "tgn:id":7019981,
    "tgn:name":"Irma Lake",
    "tgn:placetype":[
        "aat:300006191"
    ]
},
  "bbox": [],
  "geometry": {"coordinates":[-109.25,44.3167],"type":"Point"}
}