{
  "id": 2594949,
  "type": "Feature",
  "properties": {
    "tgn:hierarchy":[
        "tgn:2594949",
        "tgn:1000001",
        "tgn:7012149",
        "tgn:2001710",
        "tgn:7007708",
        "tgn:7029392"
    ],
    "tgn:id":2594949,
    "tgn:name":"Post Canyon",
    "tgn:placetype":[
        "aat:300008761"
    ]
},
  "bbox": [],
  "geometry": {"coordinates":[-121.6167,45.6667],"type":"Point"}
}