{
  "id": 7103514,
  "type": "Feature",
  "properties": {
    "tgn:hierarchy":[
        "tgn:7103514",
        "tgn:1000003",
        "tgn:7000094",
        "tgn:7000084",
        "tgn:7029392"
    ],
    "tgn:id":7103514,
    "tgn:name":"Saalkow",
    "tgn:placetype":[
        "aat:300008347"
    ]
},
  "bbox": [],
  "geometry": {"coordinates":[13.216667,54.333333],"type":"Point"}
}