<<<<<<< HEAD
{
  "id": 7368494,
  "type": "Feature",
  "properties": {
    "tgn:hierarchy":[
        "tgn:7368494",
        "tgn:1000001",
        "tgn:7005599",
        "tgn:7005560",
        "tgn:7029392"
    ],
    "tgn:id":7368494,
    "tgn:name":"Guacholula",
    "tgn:placetype":[
        "aat:300008347"
    ]
},
  "bbox": [],
  "geometry": {"coordinates":[-98.016667,21.3],"type":"Point"}
}
=======
{"geometry":{"type":"Point","coordinates":[-98.016667,21.300000]},"type":"Feature","properties":{"hierarchy":["tgn:7368494","tgn:1000001","tgn:7005599","tgn:7005560","tgn:7029392"],"placetype":["aat:300008347"],"id":7368494,"name:xx":"Guacholula"}}
>>>>>>> 03f74aca74312dbeaf24d7e61306dd6a786dc3d0
