{
  "id": 7293168,
  "type": "Feature",
  "properties": {
    "tgn:hierarchy":[
        "tgn:7293168",
        "tgn:1001657",
        "tgn:1000049",
        "tgn:1000002",
        "tgn:7029392"
    ],
    "tgn:id":7293168,
    "tgn:name":"Cha\u00f1ar",
    "tgn:placetype":[
        "aat:300008347"
    ]
},
  "bbox": [],
  "geometry": {"coordinates":[-70.633333,-30.283333],"type":"Point"}
}