{
  "id": 7294413,
  "type": "Feature",
  "properties": {
    "tgn:hierarchy":[
        "tgn:7294413",
        "tgn:7002842",
        "tgn:7001158",
        "tgn:1000003",
        "tgn:1000095",
        "tgn:7029392"
    ],
    "tgn:id":7294413,
    "tgn:name":"Valpierde, Arroyo",
    "tgn:placetype":[
        "aat:300266554",
        "aat:300008699"
    ]
},
  "bbox": [],
  "geometry": {"coordinates":[-2.883333,41.45],"type":"Point"}
}