{
  "id": 7001481,
  "type": "Feature",
  "properties": {
    "tgn:hierarchy":[
        "tgn:7001481",
        "tgn:1000004",
        "tgn:7002078",
        "tgn:1000111",
        "tgn:7029392"
    ],
    "tgn:id":7001481,
    "tgn:name":"Qichun",
    "tgn:placetype":[
        "aat:300008347",
        "aat:300008375"
    ]
},
  "bbox": [],
  "geometry": {"coordinates":[115.4333,30.25],"type":"Point"}
}