{
  "id": 5003640,
  "type": "Feature",
  "properties": {
    "tgn:hierarchy":[
        "tgn:5003640",
        "tgn:1000004",
        "tgn:1002084",
        "tgn:1000140",
        "tgn:7029392"
    ],
    "tgn:id":5003640,
    "tgn:name":"Kufayr",
    "tgn:placetype":[
        "aat:300008347",
        "aat:300008375"
    ]
},
  "bbox": [],
  "geometry": {"coordinates":[36.3167,35.7667],"type":"Point"}
}