<<<<<<< HEAD
{
  "id": 7357665,
  "type": "Feature",
  "properties": {
    "tgn:hierarchy":[
        "tgn:7357665",
        "tgn:1000001",
        "tgn:1001893",
        "tgn:7005560",
        "tgn:7029392"
    ],
    "tgn:id":7357665,
    "tgn:name":"Culebra, Cerro",
    "tgn:placetype":[
        "aat:300008795"
    ]
},
  "bbox": [],
  "geometry": {"coordinates":[-99.4,18.866667],"type":"Point"}
}
=======
{"geometry":{"type":"Point","coordinates":[-99.400000,18.866667]},"type":"Feature","properties":{"hierarchy":["tgn:7357665","tgn:1000001","tgn:1001893","tgn:7005560","tgn:7029392"],"placetype":["aat:300008795"],"id":7357665,"name:xx":"Culebra, Cerro"}}
>>>>>>> 03f74aca74312dbeaf24d7e61306dd6a786dc3d0
