{
  "id": 2488518,
  "type": "Feature",
  "properties": {
    "tgn:hierarchy":[
        "tgn:2488518",
        "tgn:1000001",
        "tgn:7012149",
        "tgn:2002125",
        "tgn:7007827",
        "tgn:7029392"
    ],
    "tgn:id":2488518,
    "tgn:name":"Mahogany Ridge",
    "tgn:placetype":[
        "aat:300266640"
    ]
},
  "bbox": [],
  "geometry": {"coordinates":[-111.5833,39.95],"type":"Point"}
}