{
  "id": 1087600,
  "type": "Feature",
  "properties": {
    "tgn:hierarchy":[
        "tgn:1087600",
        "tgn:7001242",
        "tgn:7016752",
        "tgn:1000775",
        "tgn:7029392"
    ],
    "tgn:id":1087600,
    "tgn:name":"Tit",
    "tgn:placetype":[
        "aat:300008347"
    ]
},
  "bbox": [],
  "geometry": {"coordinates":[5.1833,22.9833],"type":"Point"}
}