{
  "id": 7419198,
  "type": "Feature",
  "properties": {
    "tgn:hierarchy":[
        "tgn:7419198",
        "tgn:1000001",
        "tgn:7005589",
        "tgn:7005560",
        "tgn:7029392"
    ],
    "tgn:id":7419198,
    "tgn:name:es":"El Chiripa",
    "tgn:placetype":[
        "aat:300008347"
    ]
},
  "bbox": [],
  "geometry": {"coordinates":[-100.359167,23.731944],"type":"Point"}
}