{
  "id": 1065088,
  "type": "Feature",
  "properties": {
    "tgn:hierarchy":[
        "tgn:1065088",
        "tgn:1000003",
        "tgn:4011927",
        "tgn:7006669",
        "tgn:7029392"
    ],
    "tgn:id":1065088,
    "tgn:name":"Kula",
    "tgn:placetype":[
        "aat:300008347"
    ]
},
  "bbox": [],
  "geometry": {"coordinates":[19.5333,45.6167],"type":"Point"}
}