<<<<<<< HEAD
{
  "id": 2257914,
  "type": "Feature",
  "properties": {
    "tgn:hierarchy":[
        "tgn:2257914",
        "tgn:2001732",
        "tgn:1000001",
        "tgn:7012149",
        "tgn:7007712",
        "tgn:7029392"
    ],
    "tgn:id":2257914,
    "tgn:name":"Corsada",
    "tgn:placetype":[
        "aat:300008347"
    ]
},
  "bbox": [],
  "geometry": {"coordinates":[-80.1833,33.3667],"type":"Point"}
}
=======
{"geometry":{"type":"Point","coordinates":[-80.183300,33.366700]},"type":"Feature","properties":{"hierarchy":["tgn:2257914","tgn:2001732","tgn:1000001","tgn:7012149","tgn:7007712","tgn:7029392"],"placetype":["aat:300008347"],"id":2257914,"name:xx":"Corsada"}}
>>>>>>> 03f74aca74312dbeaf24d7e61306dd6a786dc3d0
