<<<<<<< HEAD
{
  "id": 2766645,
  "type": "Feature",
  "properties": {
    "tgn:hierarchy":[
        "tgn:2766645",
        "tgn:1000001",
        "tgn:7016172",
        "tgn:7012149",
        "tgn:2000168",
        "tgn:7029392"
    ],
    "tgn:id":2766645,
    "tgn:name":"White Oak Hollow",
    "tgn:placetype":[
        "aat:300008761"
    ]
},
  "bbox": [],
  "geometry": {"coordinates":[-93.85,34.8167],"type":"Point"}
}
=======
{"geometry":{"type":"Point","coordinates":[-93.850000,34.816700]},"type":"Feature","properties":{"hierarchy":["tgn:2766645","tgn:1000001","tgn:7016172","tgn:7012149","tgn:2000168","tgn:7029392"],"placetype":["aat:300008761"],"id":2766645,"name:xx":"White Oak Hollow"}}
>>>>>>> 03f74aca74312dbeaf24d7e61306dd6a786dc3d0
