{
  "id": 7279972,
  "type": "Feature",
  "properties": {
    "tgn:hierarchy":[
        "tgn:7279972",
        "tgn:1001699",
        "tgn:1000049",
        "tgn:1000002",
        "tgn:7029392"
    ],
    "tgn:id":7279972,
    "tgn:name":"Refugio",
    "tgn:placetype":[
        "aat:300008347"
    ]
},
  "bbox": [],
  "geometry": {"coordinates":[-72.813333,-42.576389],"type":"Point"}
}