<<<<<<< HEAD
{
  "id": 2251551,
  "type": "Feature",
  "properties": {
    "tgn:hierarchy":[
        "tgn:2251551",
        "tgn:1002716",
        "tgn:1000001",
        "tgn:7012149",
        "tgn:7007711",
        "tgn:7029392"
    ],
    "tgn:id":2251551,
    "tgn:name":"Common Fence Point",
    "tgn:placetype":[
        "aat:300008850"
    ]
},
  "bbox": [],
  "geometry": {"coordinates":[-71.2167,41.65],"type":"Point"}
}
=======
{"geometry":{"type":"Point","coordinates":[-71.216700,41.650000]},"type":"Feature","properties":{"hierarchy":["tgn:2251551","tgn:1002716","tgn:1000001","tgn:7012149","tgn:7007711","tgn:7029392"],"placetype":["aat:300008850"],"id":2251551,"name:xx":"Common Fence Point"}}
>>>>>>> 03f74aca74312dbeaf24d7e61306dd6a786dc3d0
