{
  "id": 7464436,
  "type": "Feature",
  "properties": {
    "tgn:hierarchy":[
        "tgn:7464436",
        "tgn:7002443",
        "tgn:5000555",
        "tgn:1000003",
        "tgn:7008591",
        "tgn:7029392"
    ],
    "tgn:id":7464436,
    "tgn:name:en":"Berwyn Station",
    "tgn:placetype":[
        "aat:300007783"
    ]
},
  "bbox": [],
  "geometry": {"coordinates":[-3.183333,52.983333],"type":"Point"}
}