{
  "id": 7012091,
  "type": "Feature",
  "properties": {
    "tgn:hierarchy":[
        "tgn:7012091",
        "tgn:7002445",
        "tgn:7011781",
        "tgn:7018933",
        "tgn:1000003",
        "tgn:7008136",
        "tgn:7008591",
        "tgn:7029392"
    ],
    "tgn:id":7012091,
    "tgn:name":"Putney",
    "tgn:placetype":[
        "aat:300000745"
    ]
},
  "bbox": [],
  "geometry": {"coordinates":[-0.2333,51.4667],"type":"Point"}
}