{
  "id": 2303867,
  "type": "Feature",
  "properties": {
    "tgn:hierarchy":[
        "tgn:2303867",
        "tgn:1000001",
        "tgn:7012149",
        "tgn:2000974",
        "tgn:7007520",
        "tgn:7029392"
    ],
    "tgn:id":2303867,
    "tgn:name":"Eagle Point",
    "tgn:placetype":[
        "aat:300008850"
    ]
},
  "bbox": [],
  "geometry": {"coordinates":[-86.2167,44.35],"type":"Point"}
}