{
  "id": 2261850,
  "type": "Feature",
  "properties": {
    "tgn:hierarchy":[
        "tgn:2261850",
        "tgn:1000001",
        "tgn:2002109",
        "tgn:7012149",
        "tgn:7007827",
        "tgn:7029392"
    ],
    "tgn:id":2261850,
    "tgn:name":"Cove, The",
    "tgn:placetype":[
        "aat:300386845"
    ]
},
  "bbox": [],
  "geometry": {"coordinates":[-110.25,37.9833],"type":"Point"}
}