{
  "id": 7392403,
  "type": "Feature",
  "properties": {
    "tgn:hierarchy":[
        "tgn:7392403",
        "tgn:1001853",
        "tgn:1000001",
        "tgn:7005560",
        "tgn:7029392"
    ],
    "tgn:id":7392403,
    "tgn:name":"Rancho El Milagro",
    "tgn:placetype":[
        "aat:300008347"
    ]
},
  "bbox": [],
  "geometry": {"coordinates":[-102.733333,28.816667],"type":"Point"}
}