{
  "id": 2776779,
  "type": "Feature",
  "properties": {
    "tgn:hierarchy":[
        "tgn:2776779",
        "tgn:2000090",
        "tgn:1000001",
        "tgn:7006451",
        "tgn:7012149",
        "tgn:7029392"
    ],
    "tgn:id":2776779,
    "tgn:name":"Window Rock",
    "tgn:placetype":[
        "aat:300008798"
    ]
},
  "bbox": [],
  "geometry": {"coordinates":[-109.55,36.4833],"type":"Point"}
}