{
  "id": 7454167,
  "type": "Feature",
  "properties": {
    "tgn:hierarchy":[
        "tgn:7454167",
        "tgn:7002444",
        "tgn:1000003",
        "tgn:7008082",
        "tgn:7008591",
        "tgn:7029392"
    ],
    "tgn:id":7454167,
    "tgn:name:en":"Corrybrough",
    "tgn:placetype":[
        "aat:300008347"
    ]
},
  "bbox": [],
  "geometry": {"coordinates":[-3.95,57.35],"type":"Point"}
}