{
  "id": 1005506,
  "type": "Feature",
  "properties": {
    "tgn:hierarchy":[
        "tgn:1005506",
        "tgn:7005685",
        "tgn:1000001",
        "tgn:7005804",
        "tgn:1007525",
        "tgn:7029392"
    ],
    "tgn:id":1005506,
    "tgn:name":"Saint-Fran\u00e7ois-de-Laval",
    "tgn:placetype":[
        "aat:300008347"
    ]
},
  "bbox": [],
  "geometry": {"coordinates":[-73.5667,45.6667],"type":"Point"}
}