{
  "id": 7505163,
  "type": "Feature",
  "properties": {
    "tgn:hierarchy":[
        "tgn:7505163",
        "tgn:1009227",
        "tgn:1000226",
        "tgn:7016822",
        "tgn:1000006",
        "tgn:7029392"
    ],
    "tgn:id":7505163,
    "tgn:name:en":"Borchgrevink Bay",
    "tgn:placetype":[
        "aat:300132316"
    ]
},
  "bbox": [],
  "geometry": {"coordinates":[169.191111,-52.472778],"type":"Point"}
}