<<<<<<< HEAD
{
  "id": 7173093,
  "type": "Feature",
  "properties": {
    "tgn:hierarchy":[
        "tgn:7173093",
        "tgn:1000003",
        "tgn:7003676",
        "tgn:7000084",
        "tgn:7029392"
    ],
    "tgn:id":7173093,
    "tgn:name":"Gro\u00dfe Aa",
    "tgn:placetype":[
        "aat:300008699"
    ]
},
  "bbox": [],
  "geometry": {"coordinates":[7.383333,52.416667],"type":"Point"}
}
=======
{"geometry":{"type":"Point","coordinates":[7.383333,52.416667]},"type":"Feature","properties":{"hierarchy":["tgn:7173093","tgn:1000003","tgn:7003676","tgn:7000084","tgn:7029392"],"placetype":["aat:300008699"],"id":7173093,"name:xx":"Gro\u00dfe Aa"}}
>>>>>>> 03f74aca74312dbeaf24d7e61306dd6a786dc3d0
