{
  "id": 2371620,
  "type": "Feature",
  "properties": {
    "tgn:hierarchy":[
        "tgn:2371620",
        "tgn:1000001",
        "tgn:7012149",
        "tgn:2001763",
        "tgn:7007712",
        "tgn:7029392"
    ],
    "tgn:id":2371620,
    "tgn:name":"Hale",
    "tgn:placetype":[
        "aat:300008347"
    ]
},
  "bbox": [],
  "geometry": {"coordinates":[-82.5333,34.8167],"type":"Point"}
}