{
  "id": 7234111,
  "type": "Feature",
  "properties": {
    "tgn:hierarchy":[
        "tgn:7234111",
        "tgn:7011270",
        "tgn:7002674",
        "tgn:1000003",
        "tgn:1000074",
        "tgn:7029392"
    ],
    "tgn:id":7234111,
    "tgn:name":"Akh\u00e1psi, \u00c1kra",
    "tgn:placetype":[
        "aat:300008850"
    ]
},
  "bbox": [],
  "geometry": {"coordinates":[25.416667,37.133333],"type":"Point"}
}