{
  "id": 2015690,
  "type": "Feature",
  "properties": {
    "tgn:hierarchy":[
        "tgn:2015690",
        "tgn:1000001",
        "tgn:7012149",
        "tgn:2000209",
        "tgn:7007158",
        "tgn:7029392"
    ],
    "tgn:id":2015690,
    "tgn:name":"Greenland",
    "tgn:placetype":[
        "aat:300008347",
        "aat:300387210"
    ]
},
  "bbox": [],
  "geometry": {"coordinates":[-104.85,39.1667],"type":"Point"}
}