{
  "id": 2781914,
  "type": "Feature",
  "properties": {
    "tgn:hierarchy":[
        "tgn:2781914",
        "tgn:7002659",
        "tgn:1000001",
        "tgn:7012149",
        "tgn:2000057",
        "tgn:7029392"
    ],
    "tgn:id":2781914,
    "tgn:name":"Woods Island",
    "tgn:placetype":[
        "aat:300008791"
    ]
},
  "bbox": [],
  "geometry": {"coordinates":[-86.05,33.7667],"type":"Point"}
}