{
  "id": 7206685,
  "type": "Feature",
  "properties": {
    "tgn:hierarchy":[
        "tgn:7206685",
        "tgn:1000003",
        "tgn:7003676",
        "tgn:7000084",
        "tgn:7029392"
    ],
    "tgn:id":7206685,
    "tgn:name":"Burgforde",
    "tgn:placetype":[
        "aat:300387200"
    ]
},
  "bbox": [],
  "geometry": {"coordinates":[7.95,53.283333],"type":"Point"}
}