{
  "id": 2434863,
  "type": "Feature",
  "properties": {
    "tgn:hierarchy":[
        "tgn:2434863",
        "tgn:1000001",
        "tgn:7012149",
        "tgn:1002891",
        "tgn:7007708",
        "tgn:7029392"
    ],
    "tgn:id":2434863,
    "tgn:name":"Kenny Spring",
    "tgn:placetype":[
        "aat:300008697"
    ]
},
  "bbox": [],
  "geometry": {"coordinates":[-120.5167,45.4833],"type":"Point"}
}