{
  "id": 1014627,
  "type": "Feature",
  "properties": {
    "tgn:hierarchy":[
        "tgn:1014627",
        "tgn:7005685",
        "tgn:1000001",
        "tgn:7013154",
        "tgn:7029392"
    ],
    "tgn:id":1014627,
    "tgn:name":"Burgessville",
    "tgn:placetype":[
        "aat:300008347"
    ]
},
  "bbox": [],
  "geometry": {"coordinates":[-80.65,43.0167],"type":"Point"}
}