{
  "id": 7528873,
  "type": "Feature",
  "properties": {
    "tgn:hierarchy":[
        "tgn:7528873",
        "tgn:7001242",
        "tgn:7001311",
        "tgn:7016833",
        "tgn:7029392"
    ],
    "tgn:id":7528873,
    "tgn:name:en":"Umm Kur\u016bsh, Jabal",
    "tgn:placetype":[
        "aat:300008795"
    ]
},
  "bbox": [],
  "geometry": {"coordinates":[34.082331,22.674156],"type":"Point"}
}