{
  "id": 7189957,
  "type": "Feature",
  "properties": {
    "tgn:hierarchy":[
        "tgn:7189957",
        "tgn:1000003",
        "tgn:7000094",
        "tgn:7000084",
        "tgn:7029392"
    ],
    "tgn:id":7189957,
    "tgn:name":"Einhusen",
    "tgn:placetype":[
        "aat:300008347"
    ]
},
  "bbox": [],
  "geometry": {"coordinates":[11.416667,53.983333],"type":"Point"}
}