{
  "id": 7590914,
  "type": "Feature",
  "properties": {
    "tgn:hierarchy":[
        "tgn:7590914",
        "tgn:1000004",
        "tgn:7000198",
        "tgn:7000799",
        "tgn:7029392"
    ],
    "tgn:id":7590914,
    "tgn:name:en":"Saidgarh",
    "tgn:placetype":[
        "aat:300008347"
    ]
},
  "bbox": [],
  "geometry": {"coordinates":[74.884204,32.54638],"type":"Point"}
}