{
  "id": 2541265,
  "type": "Feature",
  "properties": {
    "tgn:hierarchy":[
        "tgn:2541265",
        "tgn:1000001",
        "tgn:7012149",
        "tgn:1002708",
        "tgn:7007568",
        "tgn:7029392"
    ],
    "tgn:id":2541265,
    "tgn:name":"Nicks Point",
    "tgn:placetype":[
        "aat:300008850"
    ]
},
  "bbox": [],
  "geometry": {"coordinates":[-73.5333,40.6333],"type":"Point"}
}