{
  "id": 1103997,
  "type": "Feature",
  "properties": {
    "tgn:hierarchy":[
        "tgn:1103997",
        "tgn:1000003",
        "tgn:7029392"
    ],
    "tgn:id":1103997,
    "tgn:name:de":"Blindenhorn",
    "tgn:placetype":[
        "aat:300008795"
    ]
},
  "bbox": [],
  "geometry": {"coordinates":[8.3167,46.4167],"type":"Point"}
}