{
  "id": 7479167,
  "type": "Feature",
  "properties": {
    "tgn:hierarchy":[
        "tgn:7479167",
        "tgn:1000004",
        "tgn:7490934",
        "tgn:1000141",
        "tgn:7029392"
    ],
    "tgn:id":7479167,
    "tgn:name":"Chengda Yixuezhongxin",
    "tgn:placetype":[
        "aat:300006653"
    ]
},
  "bbox": [],
  "geometry": {"coordinates":[120.219444,23.001667],"type":"Point"}
}