<<<<<<< HEAD
{
  "id": 7479167,
  "type": "Feature",
  "properties": {
    "tgn:hierarchy":[
        "tgn:7479167",
        "tgn:1000004",
        "tgn:7490934",
        "tgn:1000141",
        "tgn:7029392"
    ],
    "tgn:id":7479167,
    "tgn:name":"Chengda Yixuezhongxin",
    "tgn:placetype":[
        "aat:300006653"
    ]
},
  "bbox": [],
  "geometry": {"coordinates":[120.219444,23.001667],"type":"Point"}
}
=======
{"geometry":{"type":"Point","coordinates":[120.219444,23.001667]},"type":"Feature","properties":{"hierarchy":["tgn:7479167","tgn:1000004","tgn:7490934","tgn:1000141","tgn:7029392"],"placetype":["aat:300006653"],"id":7479167,"name:xx":"Chengda Yixuezhongxin"}}
>>>>>>> 03f74aca74312dbeaf24d7e61306dd6a786dc3d0
