{
  "id": 2262779,
  "type": "Feature",
  "properties": {
    "tgn:hierarchy":[
        "tgn:2262779",
        "tgn:1000001",
        "tgn:7012149",
        "tgn:1002945",
        "tgn:7007710",
        "tgn:7029392"
    ],
    "tgn:id":2262779,
    "tgn:name":"Cowanesque Lake Fifteen",
    "tgn:placetype":[
        "aat:300006191"
    ]
},
  "bbox": [],
  "geometry": {"coordinates":[-77.1667,41.9667],"type":"Point"}
}