{
  "id": 2098255,
  "type": "Feature",
  "properties": {
    "tgn:hierarchy":[
        "tgn:2098255",
        "tgn:1000001",
        "tgn:7012149",
        "tgn:2001849",
        "tgn:7007825",
        "tgn:7029392"
    ],
    "tgn:id":2098255,
    "tgn:name":"Caney Valley",
    "tgn:placetype":[
        "aat:300008347"
    ]
},
  "bbox": [],
  "geometry": {"coordinates":[-83.4333,36.4167],"type":"Point"}
}