{
  "id": 2417871,
  "type": "Feature",
  "properties": {
    "tgn:hierarchy":[
        "tgn:2417871",
        "tgn:1000001",
        "tgn:2002151",
        "tgn:7012149",
        "tgn:7007919",
        "tgn:7029392"
    ],
    "tgn:id":2417871,
    "tgn:name":"Jackson Knob",
    "tgn:placetype":[
        "aat:300008798"
    ]
},
  "bbox": [],
  "geometry": {"coordinates":[-80.5667,36.7333],"type":"Point"}
}