{
  "id": 2678368,
  "type": "Feature",
  "properties": {
    "tgn:hierarchy":[
        "tgn:2678368",
        "tgn:1000001",
        "tgn:7012149",
        "tgn:7007826",
        "tgn:7029392"
    ],
    "tgn:id":2678368,
    "tgn:name":"South Fork Champion Creek",
    "tgn:placetype":[
        "aat:300008706"
    ]
},
  "bbox": [],
  "geometry": {"coordinates":[-100.5167,32.2667],"type":"Point"}
}