{
  "id": 7567276,
  "type": "Feature",
  "properties": {
    "tgn:hierarchy":[
        "tgn:7567276",
        "tgn:1001828",
        "tgn:1000004",
        "tgn:7000198",
        "tgn:7029392"
    ],
    "tgn:id":7567276,
    "tgn:name:en":"M\u0101saipet Railroad Station",
    "tgn:placetype":[
        "aat:300007783"
    ]
},
  "bbox": [],
  "geometry": {"coordinates":[78.466944,17.8775],"type":"Point"}
}