{
  "id": 2168009,
  "type": "Feature",
  "properties": {
    "tgn:hierarchy":[
        "tgn:2168009",
        "tgn:1000001",
        "tgn:7012149",
        "tgn:2002373",
        "tgn:7007923",
        "tgn:7029392"
    ],
    "tgn:id":2168009,
    "tgn:name":"Big Eagle Spring",
    "tgn:placetype":[
        "aat:300008697"
    ]
},
  "bbox": [],
  "geometry": {"coordinates":[-108.3167,43.5333],"type":"Point"}
}