{
  "id": 2633594,
  "type": "Feature",
  "properties": {
    "tgn:hierarchy":[
        "tgn:2633594",
        "tgn:1000001",
        "tgn:7012149",
        "tgn:7029392"
    ],
    "tgn:id":2633594,
    "tgn:name":"Ruprecht Hollow",
    "tgn:placetype":[
        "aat:300008761"
    ]
},
  "bbox": [],
  "geometry": {"coordinates":[-91.45,36.4833],"type":"Point"}
}