{
  "id": 7124040,
  "type": "Feature",
  "properties": {
    "tgn:hierarchy":[
        "tgn:7124040",
        "tgn:7000096",
        "tgn:1000003",
        "tgn:7000084",
        "tgn:7029392"
    ],
    "tgn:id":7124040,
    "tgn:name":"Neub\u00fcckchen",
    "tgn:placetype":[
        "aat:300000206"
    ]
},
  "bbox": [],
  "geometry": {"coordinates":[14.033333,52.05],"type":"Point"}
}