{
  "id": 2441966,
  "type": "Feature",
  "properties": {
    "tgn:hierarchy":[
        "tgn:2441966",
        "tgn:1000001",
        "tgn:7012149",
        "tgn:7007157",
        "tgn:7029392"
    ],
    "tgn:id":2441966,
    "tgn:name":"Koopman Canyon",
    "tgn:placetype":[
        "aat:300008761"
    ]
},
  "bbox": [],
  "geometry": {"coordinates":[-121.95,37.7167],"type":"Point"}
}