{
  "id": 2308613,
  "type": "Feature",
  "properties": {
    "tgn:hierarchy":[
        "tgn:2308613",
        "tgn:1000001",
        "tgn:7012149",
        "tgn:1002407",
        "tgn:7007568",
        "tgn:7029392"
    ],
    "tgn:id":2308613,
    "tgn:name":"East Oakfield",
    "tgn:placetype":[
        "aat:300008347"
    ]
},
  "bbox": [],
  "geometry": {"coordinates":[-78.2333,43.0833],"type":"Point"}
}