{
  "id": 7272831,
  "type": "Feature",
  "properties": {
    "tgn:concordances":{
        "gn:id":"2745215"
    },
    "tgn:hierarchy":[
        "tgn:7272831",
        "tgn:1000003",
        "tgn:7003624",
        "tgn:7016845",
        "tgn:7029392"
    ],
    "tgn:id":7272831,
    "tgn:name:nl":"Vrachelen",
    "tgn:placetype":[
        "aat:300008347"
    ]
},
  "bbox": [],
  "geometry": {"coordinates":[4.833333,51.65],"type":"Point"}
}