{
  "id": 2424208,
  "type": "Feature",
  "properties": {
    "tgn:hierarchy":[
        "tgn:2424208",
        "tgn:1000001",
        "tgn:7012149",
        "tgn:7007157",
        "tgn:2000184",
        "tgn:7029392"
    ],
    "tgn:id":2424208,
    "tgn:name":"Johns Valley",
    "tgn:placetype":[
        "aat:300008761"
    ]
},
  "bbox": [],
  "geometry": {"coordinates":[-121.1833,41.0333],"type":"Point"}
}