{
  "id": 2436876,
  "type": "Feature",
  "properties": {
    "tgn:hierarchy":[
        "tgn:2436876",
        "tgn:1000001",
        "tgn:7019179",
        "tgn:7012149",
        "tgn:7007253",
        "tgn:7029392"
    ],
    "tgn:id":2436876,
    "tgn:name":"Kilgore Creek",
    "tgn:placetype":[
        "aat:300008706"
    ]
},
  "bbox": [],
  "geometry": {"coordinates":[-93.7167,40.7167],"type":"Point"}
}