{
  "id": 7453280,
  "type": "Feature",
  "properties": {
    "tgn:hierarchy":[
        "tgn:7453280",
        "tgn:7019094",
        "tgn:7002444",
        "tgn:1000003",
        "tgn:7008591",
        "tgn:7029392"
    ],
    "tgn:id":7453280,
    "tgn:name:en":"Ciaran, Loch",
    "tgn:placetype":[
        "aat:300008680"
    ]
},
  "bbox": [],
  "geometry": {"coordinates":[-5.533333,55.716667],"type":"Point"}
}