{
  "id": 2692269,
  "type": "Feature",
  "properties": {
    "tgn:hierarchy":[
        "tgn:2692269",
        "tgn:1000001",
        "tgn:7012149",
        "tgn:1002883",
        "tgn:7007706",
        "tgn:7029392"
    ],
    "tgn:id":2692269,
    "tgn:name":"Staub Ditch",
    "tgn:placetype":[
        "aat:300006075"
    ]
},
  "bbox": [],
  "geometry": {"coordinates":[-83.2667,41.1167],"type":"Point"}
}