{
  "id": 7535745,
  "type": "Feature",
  "properties": {
    "tgn:hierarchy":[
        "tgn:7535745",
        "tgn:7001242",
        "tgn:7016833",
        "tgn:1001092",
        "tgn:7029392"
    ],
    "tgn:id":7535745,
    "tgn:name":"Kafr al Jazz\u0101r",
    "tgn:placetype":[
        "aat:300008347"
    ]
},
  "bbox": [],
  "geometry": {"coordinates":[31.171375,30.474615],"type":"Point"}
}