<<<<<<< HEAD
{
  "id": 2406392,
  "type": "Feature",
  "properties": {
    "tgn:hierarchy":[
        "tgn:2406392",
        "tgn:2000918",
        "tgn:1000001",
        "tgn:7012149",
        "tgn:7007515",
        "tgn:7029392"
    ],
    "tgn:id":2406392,
    "tgn:name":"Hunger, Mount",
    "tgn:placetype":[
        "aat:300008798"
    ]
},
  "bbox": [],
  "geometry": {"coordinates":[-70.4,44.1167],"type":"Point"}
}
=======
{"geometry":{"type":"Point","coordinates":[-70.400000,44.116700]},"type":"Feature","properties":{"hierarchy":["tgn:2406392","tgn:2000918","tgn:1000001","tgn:7012149","tgn:7007515","tgn:7029392"],"placetype":["aat:300008798"],"id":2406392,"name:xx":"Hunger, Mount"}}
>>>>>>> 03f74aca74312dbeaf24d7e61306dd6a786dc3d0
