{
  "id": 7424777,
  "type": "Feature",
  "properties": {
    "tgn:hierarchy":[
        "tgn:7424777",
        "tgn:1000001",
        "tgn:7005597",
        "tgn:7005560",
        "tgn:7029392"
    ],
    "tgn:id":7424777,
    "tgn:name":"Sim\u00f3n Bol\u00edvar",
    "tgn:placetype":[
        "aat:300008347"
    ]
},
  "bbox": [],
  "geometry": {"coordinates":[-97.916667,24.566667],"type":"Point"}
}