<<<<<<< HEAD
{
  "id": 2250666,
  "type": "Feature",
  "properties": {
    "tgn:hierarchy":[
        "tgn:2250666",
        "tgn:1000001",
        "tgn:7012149",
        "tgn:2002057",
        "tgn:7007826",
        "tgn:7029392"
    ],
    "tgn:id":2250666,
    "tgn:name":"Colorado, Canyon",
    "tgn:placetype":[
        "aat:300008761"
    ]
},
  "bbox": [],
  "geometry": {"coordinates":[-104.05,29.3333],"type":"Point"}
}
=======
{"geometry":{"type":"Point","coordinates":[-104.050000,29.333300]},"type":"Feature","properties":{"hierarchy":["tgn:2250666","tgn:1000001","tgn:7012149","tgn:2002057","tgn:7007826","tgn:7029392"],"placetype":["aat:300008761"],"id":2250666,"name:xx":"Colorado, Canyon"}}
>>>>>>> 03f74aca74312dbeaf24d7e61306dd6a786dc3d0
