{
  "id": 2250666,
  "type": "Feature",
  "properties": {
    "tgn:hierarchy":[
        "tgn:2250666",
        "tgn:1000001",
        "tgn:7012149",
        "tgn:2002057",
        "tgn:7007826",
        "tgn:7029392"
    ],
    "tgn:id":2250666,
    "tgn:name":"Colorado, Canyon",
    "tgn:placetype":[
        "aat:300008761"
    ]
},
  "bbox": [],
  "geometry": {"coordinates":[-104.05,29.3333],"type":"Point"}
}