{
  "id": 2710994,
  "type": "Feature",
  "properties": {
    "tgn:hierarchy":[
        "tgn:2710994",
        "tgn:1000001",
        "tgn:7012149",
        "tgn:2001447",
        "tgn:7007566",
        "tgn:7029392"
    ],
    "tgn:id":2710994,
    "tgn:name":"Tank Number 2",
    "tgn:placetype":[
        "aat:300006191"
    ]
},
  "bbox": [],
  "geometry": {"coordinates":[-105.0833,32.3333],"type":"Point"}
}