{
  "id": 1065734,
  "type": "Feature",
  "properties": {
    "tgn:hierarchy":[
        "tgn:1065734",
        "tgn:7000189",
        "tgn:1000004",
        "tgn:1000105",
        "tgn:7029392"
    ],
    "tgn:id":1065734,
    "tgn:name":"Jagann\u0101thganj Gh\u0101t",
    "tgn:placetype":[
        "aat:300008347"
    ]
},
  "bbox": [],
  "geometry": {"coordinates":[89.8167,24.75],"type":"Point"}
}