{
  "id": 2208000,
  "type": "Feature",
  "properties": {
    "tgn:hierarchy":[
        "tgn:2208000",
        "tgn:1000001",
        "tgn:7012149",
        "tgn:2000984",
        "tgn:7007520",
        "tgn:7029392"
    ],
    "tgn:id":2208000,
    "tgn:name":"Burke Creek",
    "tgn:placetype":[
        "aat:300008706"
    ]
},
  "bbox": [],
  "geometry": {"coordinates":[-86.3833,43.55],"type":"Point"}
}