{
  "id": 2427282,
  "type": "Feature",
  "properties": {
    "tgn:hierarchy":[
        "tgn:2427282",
        "tgn:1000001",
        "tgn:7012149",
        "tgn:2001211",
        "tgn:7007523",
        "tgn:7029392"
    ],
    "tgn:id":2427282,
    "tgn:name":"Jordan Creek",
    "tgn:placetype":[
        "aat:300008706"
    ]
},
  "bbox": [],
  "geometry": {"coordinates":[-92.55,37.7833],"type":"Point"}
}