{
  "id": 2708067,
  "type": "Feature",
  "properties": {
    "tgn:hierarchy":[
        "tgn:2708067",
        "tgn:1000001",
        "tgn:7012149",
        "tgn:2001274",
        "tgn:7007524",
        "tgn:7029392"
    ],
    "tgn:id":2708067,
    "tgn:name":"Swimming Lake",
    "tgn:placetype":[
        "aat:300008680"
    ]
},
  "bbox": [],
  "geometry": {"coordinates":[-114.0833,48.1833],"type":"Point"}
}