<<<<<<< HEAD
{
  "id": 7056939,
  "type": "Feature",
  "properties": {
    "tgn:hierarchy":[
        "tgn:7056939",
        "tgn:7003170",
        "tgn:1000003",
        "tgn:7003125",
        "tgn:1000080",
        "tgn:7029392"
    ],
    "tgn:id":7056939,
    "tgn:name":"Bazzano Superiore",
    "tgn:placetype":[
        "aat:300008347"
    ]
},
  "bbox": [],
  "geometry": {"coordinates":[12.8,42.783333],"type":"Point"}
}
=======
{"geometry":{"type":"Point","coordinates":[12.800000,42.783333]},"type":"Feature","properties":{"hierarchy":["tgn:7056939","tgn:7003170","tgn:1000003","tgn:7003125","tgn:1000080","tgn:7029392"],"placetype":["aat:300008347"],"id":7056939,"name:xx":"Bazzano Superiore"}}
>>>>>>> 03f74aca74312dbeaf24d7e61306dd6a786dc3d0
