{
  "id": 7504243,
  "type": "Feature",
  "properties": {
    "tgn:hierarchy":[
        "tgn:7504243",
        "tgn:1009227",
        "tgn:7001866",
        "tgn:1000226",
        "tgn:1000006",
        "tgn:7029392"
    ],
    "tgn:id":7504243,
    "tgn:name:en":"Wakanui Creek",
    "tgn:placetype":[
        "aat:300008699"
    ]
},
  "bbox": [],
  "geometry": {"coordinates":[171.866667,-44.033333],"type":"Point"}
}