{
  "id": 7325220,
  "type": "Feature",
  "properties": {
    "tgn:hierarchy":[
        "tgn:7325220",
        "tgn:7001158",
        "tgn:7002850",
        "tgn:1000003",
        "tgn:1000095",
        "tgn:7029392"
    ],
    "tgn:id":7325220,
    "tgn:name":"Santa Cruz de los Cu\u00e9rragos",
    "tgn:placetype":[
        "aat:300008347"
    ]
},
  "bbox": [],
  "geometry": {"coordinates":[-6.533333,41.933333],"type":"Point"}
}