{
  "id": 2121304,
  "type": "Feature",
  "properties": {
    "tgn:hierarchy":[
        "tgn:2121304",
        "tgn:1000001",
        "tgn:2002311",
        "tgn:7012149",
        "tgn:7007922",
        "tgn:7029392"
    ],
    "tgn:id":2121304,
    "tgn:name":"Grantsburg",
    "tgn:placetype":[
        "aat:300008347"
    ]
},
  "bbox": [],
  "geometry": {"coordinates":[-92.6667,45.7667],"type":"Point"}
}