<<<<<<< HEAD
{
  "id": 2153202,
  "type": "Feature",
  "properties": {
    "tgn:hierarchy":[
        "tgn:2153202",
        "tgn:1000001",
        "tgn:7012149",
        "tgn:1003018",
        "tgn:7007919",
        "tgn:7029392"
    ],
    "tgn:id":2153202,
    "tgn:name":"Beales Mill Run",
    "tgn:placetype":[
        "aat:300008699"
    ]
},
  "bbox": [],
  "geometry": {"coordinates":[-76.6833,38.05],"type":"Point"}
}
=======
{"geometry":{"type":"Point","coordinates":[-76.683300,38.050000]},"type":"Feature","properties":{"hierarchy":["tgn:2153202","tgn:1000001","tgn:7012149","tgn:1003018","tgn:7007919","tgn:7029392"],"placetype":["aat:300008699"],"id":2153202,"name:xx":"Beales Mill Run"}}
>>>>>>> 03f74aca74312dbeaf24d7e61306dd6a786dc3d0
