{
  "id": 2775863,
  "type": "Feature",
  "properties": {
    "tgn:hierarchy":[
        "tgn:2775863",
        "tgn:1000001",
        "tgn:7012149",
        "tgn:2001769",
        "tgn:7007712",
        "tgn:7029392"
    ],
    "tgn:id":2775863,
    "tgn:name":"Wilson Lake",
    "tgn:placetype":[
        "aat:300008680"
    ]
},
  "bbox": [],
  "geometry": {"coordinates":[-79.5167,33.6667],"type":"Point"}
}