{
  "id": 7159197,
  "type": "Feature",
  "properties": {
    "tgn:hierarchy":[
        "tgn:7159197",
        "tgn:7003669",
        "tgn:1000003",
        "tgn:7000084",
        "tgn:7029392"
    ],
    "tgn:id":7159197,
    "tgn:name":"H\u00f6henrain",
    "tgn:placetype":[
        "aat:300008777"
    ]
},
  "bbox": [],
  "geometry": {"coordinates":[11.283333,48.033333],"type":"Point"}
}