{
  "id": 2543541,
  "type": "Feature",
  "properties": {
    "tgn:hierarchy":[
        "tgn:2543541",
        "tgn:1000001",
        "tgn:7012149",
        "tgn:2000344",
        "tgn:7007248",
        "tgn:7029392"
    ],
    "tgn:id":2543541,
    "tgn:name":"Norristown Junction",
    "tgn:placetype":[
        "aat:300008347"
    ]
},
  "bbox": [],
  "geometry": {"coordinates":[-82.4833,32.55],"type":"Point"}
}