<<<<<<< HEAD
{
  "id": 2159167,
  "type": "Feature",
  "properties": {
    "tgn:hierarchy":[
        "tgn:2159167",
        "tgn:1000001",
        "tgn:7006451",
        "tgn:2000092",
        "tgn:7012149",
        "tgn:7029392"
    ],
    "tgn:id":2159167,
    "tgn:name":"Bedrock Canyon",
    "tgn:placetype":[
        "aat:300008761"
    ]
},
  "bbox": [],
  "geometry": {"coordinates":[-112.35,36.3167],"type":"Point"}
}
=======
{"geometry":{"type":"Point","coordinates":[-112.350000,36.316700]},"type":"Feature","properties":{"hierarchy":["tgn:2159167","tgn:1000001","tgn:7006451","tgn:2000092","tgn:7012149","tgn:7029392"],"placetype":["aat:300008761"],"id":2159167,"name:xx":"Bedrock Canyon"}}
>>>>>>> 03f74aca74312dbeaf24d7e61306dd6a786dc3d0
