{
  "id": 7559635,
  "type": "Feature",
  "properties": {
    "tgn:hierarchy":[
        "tgn:7559635",
        "tgn:1000004",
        "tgn:7000198",
        "tgn:1001977",
        "tgn:7029392"
    ],
    "tgn:id":7559635,
    "tgn:name:en":"Rukni",
    "tgn:placetype":[
        "aat:300007783"
    ]
},
  "bbox": [],
  "geometry": {"coordinates":[86.548217,23.552707],"type":"Point"}
}