{
  "id": 7555821,
  "type": "Feature",
  "properties": {
    "tgn:hierarchy":[
        "tgn:7555821",
        "tgn:1000004",
        "tgn:7018318",
        "tgn:7000198",
        "tgn:7029392"
    ],
    "tgn:id":7555821,
    "tgn:name:en":"Nanuz",
    "tgn:placetype":[
        "aat:300008347"
    ]
},
  "bbox": [],
  "geometry": {"coordinates":[74.133333,15.516667],"type":"Point"}
}