{
  "id": 7322594,
  "type": "Feature",
  "properties": {
    "tgn:hierarchy":[
        "tgn:7322594",
        "tgn:7002808",
        "tgn:7030216",
        "tgn:1000003",
        "tgn:1000095",
        "tgn:7029392"
    ],
    "tgn:id":7322594,
    "tgn:name":"San Adri\u00e1n de Bes\u00f3s",
    "tgn:placetype":[
        "aat:300008347"
    ]
},
  "bbox": [],
  "geometry": {"coordinates":[2.217771,41.440471],"type":"Point"}
}