<<<<<<< HEAD
{
  "id": 7369719,
  "type": "Feature",
  "properties": {
    "tgn:hierarchy":[
        "tgn:7369719",
        "tgn:1000001",
        "tgn:1001937",
        "tgn:7005560",
        "tgn:7029392"
    ],
    "tgn:id":7369719,
    "tgn:name":"Huanacaxtle",
    "tgn:placetype":[
        "aat:300387007"
    ]
},
  "bbox": [],
  "geometry": {"coordinates":[-88.883333,17.9],"type":"Point"}
}
=======
{"geometry":{"type":"Point","coordinates":[-88.883333,17.900000]},"type":"Feature","properties":{"hierarchy":["tgn:7369719","tgn:1000001","tgn:1001937","tgn:7005560","tgn:7029392"],"placetype":["aat:300387007"],"id":7369719,"name:xx":"Huanacaxtle"}}
>>>>>>> 03f74aca74312dbeaf24d7e61306dd6a786dc3d0
