{
  "id": 2446966,
  "type": "Feature",
  "properties": {
    "tgn:hierarchy":[
        "tgn:2446966",
        "tgn:1000001",
        "tgn:7012149",
        "tgn:1002414",
        "tgn:7007826",
        "tgn:7029392"
    ],
    "tgn:id":2446966,
    "tgn:name":"Liberty Creek",
    "tgn:placetype":[
        "aat:300008706"
    ]
},
  "bbox": [],
  "geometry": {"coordinates":[-97.6333,29.45],"type":"Point"}
}