{
  "id": 7533006,
  "type": "Feature",
  "properties": {
    "tgn:hierarchy":[
        "tgn:7533006",
        "tgn:7001242",
        "tgn:7016833",
        "tgn:1001335",
        "tgn:7029392"
    ],
    "tgn:id":7533006,
    "tgn:name:en":"Tur'at ar Ramyah wa al Man\u1e29alah",
    "tgn:placetype":[
        "aat:300006075"
    ]
},
  "bbox": [],
  "geometry": {"coordinates":[30.805011,31.158723],"type":"Point"}
}