{
  "id": 2280226,
  "type": "Feature",
  "properties": {
    "tgn:hierarchy":[
        "tgn:2280226",
        "tgn:1000001",
        "tgn:7012149",
        "tgn:2002302",
        "tgn:7013961",
        "tgn:7029392"
    ],
    "tgn:id":2280226,
    "tgn:name":"Deaver Fork",
    "tgn:placetype":[
        "aat:300008699"
    ]
},
  "bbox": [],
  "geometry": {"coordinates":[-81.2833,39.0167],"type":"Point"}
}