{
  "id": 7398960,
  "type": "Feature",
  "properties": {
    "tgn:hierarchy":[
        "tgn:7398960",
        "tgn:1000001",
        "tgn:1001893",
        "tgn:7005560",
        "tgn:7029392"
    ],
    "tgn:id":7398960,
    "tgn:name":"Las Jaras",
    "tgn:placetype":[
        "aat:300008347"
    ]
},
  "bbox": [],
  "geometry": {"coordinates":[-99.650833,19.956944],"type":"Point"}
}