{
  "id": 1126030,
  "type": "Feature",
  "properties": {
    "tgn:hierarchy":[
        "tgn:1126030",
        "tgn:7003692",
        "tgn:1000003",
        "tgn:7000084",
        "tgn:7029392"
    ],
    "tgn:id":1126030,
    "tgn:name":"Lein",
    "tgn:placetype":[
        "aat:300008707",
        "aat:300008699"
    ]
},
  "bbox": [],
  "geometry": {"coordinates":[9.206111,49.168056],"type":"Point"}
}