{
  "id": 7442620,
  "type": "Feature",
  "properties": {
    "tgn:hierarchy":[
        "tgn:7442620",
        "tgn:7002444",
        "tgn:1000003",
        "tgn:7008082",
        "tgn:7008591",
        "tgn:7029392"
    ],
    "tgn:id":7442620,
    "tgn:name:en":"Shandwick Bay",
    "tgn:placetype":[
        "aat:300132317"
    ]
},
  "bbox": [],
  "geometry": {"coordinates":[-3.908333,57.75],"type":"Point"}
}