<<<<<<< HEAD
{
  "id": 7023459,
  "type": "Feature",
  "properties": {
    "tgn:hierarchy":[
        "tgn:7023459",
        "tgn:7002659",
        "tgn:1000001",
        "tgn:7012149",
        "tgn:7029392"
    ],
    "tgn:id":7023459,
    "tgn:name":"Moccasin Creek",
    "tgn:placetype":[
        "aat:300008706"
    ]
},
  "bbox": [],
  "geometry": {"coordinates":[-87.6333,32.0],"type":"Point"}
}
=======
{"geometry":{"type":"Point","coordinates":[-87.633300,32.000000]},"type":"Feature","properties":{"hierarchy":["tgn:7023459","tgn:7002659","tgn:1000001","tgn:7012149","tgn:7029392"],"placetype":["aat:300008706"],"id":7023459,"name:xx":"Moccasin Creek"}}
>>>>>>> 03f74aca74312dbeaf24d7e61306dd6a786dc3d0
