<<<<<<< HEAD
{
  "id": 2151052,
  "type": "Feature",
  "properties": {
    "tgn:hierarchy":[
        "tgn:2151052",
        "tgn:1000001",
        "tgn:2001588",
        "tgn:7012149",
        "tgn:7007705",
        "tgn:7029392"
    ],
    "tgn:id":2151052,
    "tgn:name":"Basswood Lake",
    "tgn:placetype":[
        "aat:300008680"
    ]
},
  "bbox": [],
  "geometry": {"coordinates":[-98.3667,47.6667],"type":"Point"}
}
=======
{"geometry":{"type":"Point","coordinates":[-98.366700,47.666700]},"type":"Feature","properties":{"hierarchy":["tgn:2151052","tgn:1000001","tgn:2001588","tgn:7012149","tgn:7007705","tgn:7029392"],"placetype":["aat:300008680"],"id":2151052,"name:xx":"Basswood Lake"}}
>>>>>>> 03f74aca74312dbeaf24d7e61306dd6a786dc3d0
