{
  "id": 2728154,
  "type": "Feature",
  "properties": {
    "tgn:hierarchy":[
        "tgn:2728154",
        "tgn:1002141",
        "tgn:1000001",
        "tgn:7012149",
        "tgn:7007568",
        "tgn:7029392"
    ],
    "tgn:id":2728154,
    "tgn:name":"Trapping Brook",
    "tgn:placetype":[
        "aat:300008699"
    ]
},
  "bbox": [],
  "geometry": {"coordinates":[-77.85,42.1167],"type":"Point"}
}