{
  "id": 7421042,
  "type": "Feature",
  "properties": {
    "tgn:hierarchy":[
        "tgn:7421042",
        "tgn:1001836",
        "tgn:1000001",
        "tgn:7005560",
        "tgn:7029392"
    ],
    "tgn:id":7421042,
    "tgn:name":"Paso Hondo",
    "tgn:placetype":[
        "aat:300008347"
    ]
},
  "bbox": [],
  "geometry": {"coordinates":[-112.1875,26.359167],"type":"Point"}
}