{
  "id": 2586963,
  "type": "Feature",
  "properties": {
    "tgn:hierarchy":[
        "tgn:2586963",
        "tgn:1000001",
        "tgn:7012149",
        "tgn:1002800",
        "tgn:7007710",
        "tgn:7029392"
    ],
    "tgn:id":2586963,
    "tgn:name":"Plank Creek",
    "tgn:placetype":[
        "aat:300008706"
    ]
},
  "bbox": [],
  "geometry": {"coordinates":[-78.0833,41.9667],"type":"Point"}
}