<<<<<<< HEAD
{
  "id": 2400760,
  "type": "Feature",
  "properties": {
    "tgn:hierarchy":[
        "tgn:2400760",
        "tgn:1000001",
        "tgn:7012149",
        "tgn:7014344",
        "tgn:7007919",
        "tgn:7029392"
    ],
    "tgn:id":2400760,
    "tgn:name":"Horse Pen Branch",
    "tgn:placetype":[
        "aat:300008699"
    ]
},
  "bbox": [],
  "geometry": {"coordinates":[-80.0,37.3667],"type":"Point"}
}
=======
{"geometry":{"type":"Point","coordinates":[-80.000000,37.366700]},"type":"Feature","properties":{"hierarchy":["tgn:2400760","tgn:1000001","tgn:7012149","tgn:7014344","tgn:7007919","tgn:7029392"],"placetype":["aat:300008699"],"id":2400760,"name:xx":"Horse Pen Branch"}}
>>>>>>> 03f74aca74312dbeaf24d7e61306dd6a786dc3d0
