{
  "id": 2772406,
  "type": "Feature",
  "properties": {
    "tgn:hierarchy":[
        "tgn:2772406",
        "tgn:1000001",
        "tgn:7012149",
        "tgn:2001442",
        "tgn:7007566",
        "tgn:7029392"
    ],
    "tgn:id":2772406,
    "tgn:name":"Williams",
    "tgn:placetype":[
        "aat:300000390"
    ]
},
  "bbox": [],
  "geometry": {"coordinates":[-105.6833,33.7167],"type":"Point"}
}