{
  "id": 2541953,
  "type": "Feature",
  "properties": {
    "tgn:hierarchy":[
        "tgn:2541953",
        "tgn:1000001",
        "tgn:7012149",
        "tgn:2001437",
        "tgn:7007566",
        "tgn:7029392"
    ],
    "tgn:id":2541953,
    "tgn:name":"Ninetysix Creek",
    "tgn:placetype":[
        "aat:300008706"
    ]
},
  "bbox": [],
  "geometry": {"coordinates":[-108.35,32.3333],"type":"Point"}
}