{
  "id": 7347710,
  "type": "Feature",
  "properties": {
    "tgn:hierarchy":[
        "tgn:7347710",
        "tgn:7002807",
        "tgn:1000003",
        "tgn:7003837",
        "tgn:1000095",
        "tgn:7029392"
    ],
    "tgn:id":7347710,
    "tgn:name":"Arroyo de San Serv\u00e1n",
    "tgn:placetype":[
        "aat:300008347"
    ]
},
  "bbox": [],
  "geometry": {"coordinates":[-6.45,38.85],"type":"Point"}
}