{
  "id": 2692414,
  "type": "Feature",
  "properties": {
    "tgn:hierarchy":[
        "tgn:2692414",
        "tgn:1000001",
        "tgn:7012149",
        "tgn:2002264",
        "tgn:7013961",
        "tgn:7029392"
    ],
    "tgn:id":2692414,
    "tgn:name":"Steam Mill Hollow",
    "tgn:placetype":[
        "aat:300008761"
    ]
},
  "bbox": [],
  "geometry": {"coordinates":[-80.1667,37.8833],"type":"Point"}
}