{
  "id": 2114931,
  "type": "Feature",
  "properties": {
    "tgn:hierarchy":[
        "tgn:2114931",
        "tgn:1000001",
        "tgn:7012149",
        "tgn:2002193",
        "tgn:7007919",
        "tgn:7029392"
    ],
    "tgn:id":2114931,
    "tgn:name":"Waterlick",
    "tgn:placetype":[
        "aat:300008347",
        "aat:300387210"
    ]
},
  "bbox": [],
  "geometry": {"coordinates":[-78.2833,38.95],"type":"Point"}
}