{
  "id": 2452117,
  "type": "Feature",
  "properties": {
    "tgn:hierarchy":[
        "tgn:2452117",
        "tgn:1000001",
        "tgn:7012149",
        "tgn:2001437",
        "tgn:7007566",
        "tgn:7029392"
    ],
    "tgn:id":2452117,
    "tgn:name":"Little Black Mountain",
    "tgn:placetype":[
        "aat:300008798"
    ]
},
  "bbox": [],
  "geometry": {"coordinates":[-108.6333,32.8333],"type":"Point"}
}