{
  "id": 7072016,
  "type": "Feature",
  "properties": {
    "tgn:hierarchy":[
        "tgn:7072016",
        "tgn:7003669",
        "tgn:1000003",
        "tgn:7000084",
        "tgn:7029392"
    ],
    "tgn:id":7072016,
    "tgn:name":"Sumpering",
    "tgn:placetype":[
        "aat:300008347"
    ]
},
  "bbox": [],
  "geometry": {"coordinates":[13.116667,48.966667],"type":"Point"}
}