{
  "id": 1077005,
  "type": "Feature",
  "properties": {
    "tgn:hierarchy":[
        "tgn:1077005",
        "tgn:1000004",
        "tgn:7000198",
        "tgn:7016788",
        "tgn:7029392"
    ],
    "tgn:id":1077005,
    "tgn:name:en":"Sirohi",
    "tgn:placetype":[
        "aat:300008347"
    ]
},
  "bbox": [],
  "geometry": {"coordinates":[72.861,24.883],"type":"Point"}
}