{
  "id": 2778046,
  "type": "Feature",
  "properties": {
    "tgn:hierarchy":[
        "tgn:2778046",
        "tgn:1000001",
        "tgn:2001432",
        "tgn:7012149",
        "tgn:7007566",
        "tgn:7029392"
    ],
    "tgn:id":2778046,
    "tgn:name":"Wire Hill",
    "tgn:placetype":[
        "aat:300266640"
    ]
},
  "bbox": [],
  "geometry": {"coordinates":[-104.1167,36.55],"type":"Point"}
}