{
  "id": 7045088,
  "type": "Feature",
  "properties": {
    "tgn:hierarchy":[
        "tgn:7045088",
        "tgn:7003128",
        "tgn:1000003",
        "tgn:7008516",
        "tgn:1000080",
        "tgn:7029392"
    ],
    "tgn:id":7045088,
    "tgn:name":"Correggi",
    "tgn:placetype":[
        "aat:300008347"
    ]
},
  "bbox": [],
  "geometry": {"coordinates":[11.833333,44.783333],"type":"Point"}
}