<<<<<<< HEAD
{
  "id": 2251669,
  "type": "Feature",
  "properties": {
    "tgn:hierarchy":[
        "tgn:2251669",
        "tgn:1000001",
        "tgn:7012149",
        "tgn:2001752",
        "tgn:7007712",
        "tgn:7029392"
    ],
    "tgn:id":2251669,
    "tgn:name":"Company Pond",
    "tgn:placetype":[
        "aat:300006191"
    ]
},
  "bbox": [],
  "geometry": {"coordinates":[-80.8,34.15],"type":"Point"}
}
=======
{"geometry":{"type":"Point","coordinates":[-80.800000,34.150000]},"type":"Feature","properties":{"hierarchy":["tgn:2251669","tgn:1000001","tgn:7012149","tgn:2001752","tgn:7007712","tgn:7029392"],"placetype":["aat:300006191"],"id":2251669,"name:xx":"Company Pond"}}
>>>>>>> 03f74aca74312dbeaf24d7e61306dd6a786dc3d0
