{
  "id": 7157727,
  "type": "Feature",
  "properties": {
    "tgn:hierarchy":[
        "tgn:7157727",
        "tgn:1000003",
        "tgn:7003677",
        "tgn:7000084",
        "tgn:7029392"
    ],
    "tgn:id":7157727,
    "tgn:name":"Kissingerh\u00f6fen",
    "tgn:placetype":[
        "aat:300000206"
    ]
},
  "bbox": [],
  "geometry": {"coordinates":[7.766667,51.65],"type":"Point"}
}