{
  "id": 7326211,
  "type": "Feature",
  "properties": {
    "tgn:hierarchy":[
        "tgn:7326211",
        "tgn:7002760",
        "tgn:1000003",
        "tgn:1000095",
        "tgn:7029392"
    ],
    "tgn:id":7326211,
    "tgn:name":"Pilas",
    "tgn:placetype":[
        "aat:300008347"
    ]
},
  "bbox": [],
  "geometry": {"coordinates":[-3.483333,43.183333],"type":"Point"}
}