<<<<<<< HEAD
{
  "id": 2766833,
  "type": "Feature",
  "properties": {
    "tgn:hierarchy":[
        "tgn:2766833",
        "tgn:1002132",
        "tgn:1000001",
        "tgn:7012149",
        "tgn:7007919",
        "tgn:7029392"
    ],
    "tgn:id":2766833,
    "tgn:name":"White Perch Cove",
    "tgn:placetype":[
        "aat:300132316"
    ]
},
  "bbox": [],
  "geometry": {"coordinates":[-75.7,37.5167],"type":"Point"}
}
=======
{"geometry":{"type":"Point","coordinates":[-75.700000,37.516700]},"type":"Feature","properties":{"hierarchy":["tgn:2766833","tgn:1002132","tgn:1000001","tgn:7012149","tgn:7007919","tgn:7029392"],"placetype":["aat:300132316"],"id":2766833,"name:xx":"White Perch Cove"}}
>>>>>>> 03f74aca74312dbeaf24d7e61306dd6a786dc3d0
