{
  "id": 7244941,
  "type": "Feature",
  "properties": {
    "tgn:hierarchy":[
        "tgn:7244941",
        "tgn:7003460",
        "tgn:1000003",
        "tgn:1000063",
        "tgn:4012014",
        "tgn:7029392"
    ],
    "tgn:id":7244941,
    "tgn:name":"Ayeneux",
    "tgn:placetype":[
        "aat:300008347"
    ]
},
  "bbox": [],
  "geometry": {"coordinates":[5.716667,50.616667],"type":"Point"}
}