<<<<<<< HEAD
{
  "id": 2155987,
  "type": "Feature",
  "properties": {
    "tgn:hierarchy":[
        "tgn:2155987",
        "tgn:1000001",
        "tgn:7012149",
        "tgn:7007250",
        "tgn:7029392"
    ],
    "tgn:id":2155987,
    "tgn:name":"Bear Wallow Creek",
    "tgn:placetype":[
        "aat:300008706"
    ]
},
  "bbox": [],
  "geometry": {"coordinates":[-115.9333,44.2333],"type":"Point"}
}
=======
{"geometry":{"type":"Point","coordinates":[-115.933300,44.233300]},"type":"Feature","properties":{"hierarchy":["tgn:2155987","tgn:1000001","tgn:7012149","tgn:7007250","tgn:7029392"],"placetype":["aat:300008706"],"id":2155987,"name:xx":"Bear Wallow Creek"}}
>>>>>>> 03f74aca74312dbeaf24d7e61306dd6a786dc3d0
