{
  "id": 7264898,
  "type": "Feature",
  "properties": {
    "tgn:concordances":{
        "gn:id":"2751514"
    },
    "tgn:hierarchy":[
        "tgn:7264898",
        "tgn:7003619",
        "tgn:1000003",
        "tgn:7016845",
        "tgn:7029392"
    ],
    "tgn:id":7264898,
    "tgn:name:nl":"Loerbeek",
    "tgn:placetype":[
        "aat:300008347"
    ]
},
  "bbox": [],
  "geometry": {"coordinates":[6.216667,51.933333],"type":"Point"}
}