{
  "id": 1022210,
  "type": "Feature",
  "properties": {
    "tgn:hierarchy":[
        "tgn:1022210",
        "tgn:1001945",
        "tgn:1000047",
        "tgn:7002457",
        "tgn:1000002",
        "tgn:7029392"
    ],
    "tgn:id":1022210,
    "tgn:name":"Nhandeara",
    "tgn:placetype":[
        "aat:300008347"
    ]
},
  "bbox": [],
  "geometry": {"coordinates":[-50.0333,-20.6667],"type":"Point"}
}