{
  "id": 7552767,
  "type": "Feature",
  "properties": {
    "tgn:hierarchy":[
        "tgn:7552767",
        "tgn:1000004",
        "tgn:7000198",
        "tgn:7000799",
        "tgn:7029392"
    ],
    "tgn:id":7552767,
    "tgn:name:en":"M\u016bdil",
    "tgn:placetype":[
        "aat:300008347"
    ]
},
  "bbox": [],
  "geometry": {"coordinates":[78.231146,33.399037],"type":"Point"}
}