{
  "id": 2755014,
  "type": "Feature",
  "properties": {
    "tgn:hierarchy":[
        "tgn:2755014",
        "tgn:1000001",
        "tgn:7012149",
        "tgn:1002654",
        "tgn:7007706",
        "tgn:7029392"
    ],
    "tgn:id":2755014,
    "tgn:name":"Weavers",
    "tgn:placetype":[
        "aat:300008347"
    ]
},
  "bbox": [],
  "geometry": {"coordinates":[-81.6833,40.9833],"type":"Point"}
}