{
  "id": 2746046,
  "type": "Feature",
  "properties": {
    "tgn:hierarchy":[
        "tgn:2746046",
        "tgn:1000001",
        "tgn:7012149",
        "tgn:2001452",
        "tgn:7007566",
        "tgn:7029392"
    ],
    "tgn:id":2746046,
    "tgn:name":"Volcano Peak",
    "tgn:placetype":[
        "aat:300008798"
    ]
},
  "bbox": [],
  "geometry": {"coordinates":[-108.75,36.9167],"type":"Point"}
}