{
  "id": 7302942,
  "type": "Feature",
  "properties": {
    "tgn:hierarchy":[
        "tgn:7302942",
        "tgn:7002820",
        "tgn:7030216",
        "tgn:1000003",
        "tgn:1000095",
        "tgn:7029392"
    ],
    "tgn:id":7302942,
    "tgn:name":"Negre, Cabo",
    "tgn:placetype":[
        "aat:300008850"
    ]
},
  "bbox": [],
  "geometry": {"coordinates":[3.216667,41.966667],"type":"Point"}
}