{
  "id": 1076043,
  "type": "Feature",
  "properties": {
    "tgn:hierarchy":[
        "tgn:1076043",
        "tgn:1000004",
        "tgn:7000198",
        "tgn:1001894",
        "tgn:7029392"
    ],
    "tgn:id":1076043,
    "tgn:name:en":"M\u0101chalpur",
    "tgn:placetype":[
        "aat:300008347"
    ]
},
  "bbox": [],
  "geometry": {"coordinates":[76.315925,24.127346],"type":"Point"}
}