{
  "id": 2031954,
  "type": "Feature",
  "properties": {
    "tgn:hierarchy":[
        "tgn:2031954",
        "tgn:1000001",
        "tgn:7012149",
        "tgn:1002694",
        "tgn:7007252",
        "tgn:7029392"
    ],
    "tgn:id":2031954,
    "tgn:name":"Gasburg",
    "tgn:placetype":[
        "aat:300008347"
    ]
},
  "bbox": [],
  "geometry": {"coordinates":[-86.4333,39.5833],"type":"Point"}
}