{
  "id": 7072879,
  "type": "Feature",
  "properties": {
    "tgn:hierarchy":[
        "tgn:7072879",
        "tgn:7003669",
        "tgn:1000003",
        "tgn:7000084",
        "tgn:7029392"
    ],
    "tgn:id":7072879,
    "tgn:name":"Tannfeld",
    "tgn:placetype":[
        "aat:300008347"
    ]
},
  "bbox": [],
  "geometry": {"coordinates":[11.416667,49.966667],"type":"Point"}
}