{
  "id": 2379223,
  "type": "Feature",
  "properties": {
    "tgn:hierarchy":[
        "tgn:2379223",
        "tgn:1000001",
        "tgn:7012149",
        "tgn:7007157",
        "tgn:2000184",
        "tgn:7029392"
    ],
    "tgn:id":2379223,
    "tgn:name":"Hartson Lake",
    "tgn:placetype":[
        "aat:300008680"
    ]
},
  "bbox": [],
  "geometry": {"coordinates":[-120.3667,40.2833],"type":"Point"}
}