{
  "id": 7065385,
  "type": "Feature",
  "properties": {
    "tgn:hierarchy":[
        "tgn:7065385",
        "tgn:7003692",
        "tgn:1000003",
        "tgn:7000084",
        "tgn:7029392"
    ],
    "tgn:id":7065385,
    "tgn:name":"Stettberg",
    "tgn:placetype":[
        "aat:300008777"
    ]
},
  "bbox": [],
  "geometry": {"coordinates":[10.233333,48.583333],"type":"Point"}
}