{
  "id": 2172228,
  "type": "Feature",
  "properties": {
    "tgn:hierarchy":[
        "tgn:2172228",
        "tgn:1000001",
        "tgn:7012149",
        "tgn:2000928",
        "tgn:7007515",
        "tgn:7029392"
    ],
    "tgn:id":2172228,
    "tgn:name":"Bigney Cove",
    "tgn:placetype":[
        "aat:300132316"
    ]
},
  "bbox": [],
  "geometry": {"coordinates":[-69.6667,45.85],"type":"Point"}
}