{
  "id": 2145468,
  "type": "Feature",
  "properties": {
    "tgn:hierarchy":[
        "tgn:2145468",
        "tgn:1000001",
        "tgn:1002657",
        "tgn:7012149",
        "tgn:7007565",
        "tgn:7029392"
    ],
    "tgn:id":2145468,
    "tgn:name":"Baldpate Mountain",
    "tgn:placetype":[
        "aat:300008798"
    ]
},
  "bbox": [],
  "geometry": {"coordinates":[-74.8667,40.3167],"type":"Point"}
}