{
  "id": 2544665,
  "type": "Feature",
  "properties": {
    "tgn:hierarchy":[
        "tgn:2544665",
        "tgn:1000001",
        "tgn:7012149",
        "tgn:1002624",
        "tgn:7007568",
        "tgn:7029392"
    ],
    "tgn:id":2544665,
    "tgn:name":"North Cazenovia",
    "tgn:placetype":[
        "aat:300008347"
    ]
},
  "bbox": [],
  "geometry": {"coordinates":[-75.8667,42.9833],"type":"Point"}
}