{
  "id": 7397759,
  "type": "Feature",
  "properties": {
    "tgn:hierarchy":[
        "tgn:7397759",
        "tgn:1000001",
        "tgn:1001893",
        "tgn:7005560",
        "tgn:7029392"
    ],
    "tgn:id":7397759,
    "tgn:name":"Dolores",
    "tgn:placetype":[
        "aat:300008347"
    ]
},
  "bbox": [],
  "geometry": {"coordinates":[-99.494722,19.4025],"type":"Point"}
}