{
  "id": 2577245,
  "type": "Feature",
  "properties": {
    "tgn:hierarchy":[
        "tgn:2577245",
        "tgn:1000001",
        "tgn:7012149",
        "tgn:2002061",
        "tgn:7007826",
        "tgn:7029392"
    ],
    "tgn:id":2577245,
    "tgn:name":"Peters Creek",
    "tgn:placetype":[
        "aat:300008706"
    ]
},
  "bbox": [],
  "geometry": {"coordinates":[-94.7333,33.4667],"type":"Point"}
}