{
  "id": 7043776,
  "type": "Feature",
  "properties": {
    "tgn:hierarchy":[
        "tgn:7043776",
        "tgn:7003164",
        "tgn:1000003",
        "tgn:7009760",
        "tgn:1000080",
        "tgn:7029392"
    ],
    "tgn:id":7043776,
    "tgn:name":"Gabbro",
    "tgn:placetype":[
        "aat:300008347"
    ]
},
  "bbox": [],
  "geometry": {"coordinates":[10.433333,43.483333],"type":"Point"}
}