{
  "id": 7283466,
  "type": "Feature",
  "properties": {
    "tgn:hierarchy":[
        "tgn:7283466",
        "tgn:7002464",
        "tgn:1000049",
        "tgn:1000002",
        "tgn:7029392"
    ],
    "tgn:id":7283466,
    "tgn:name":"Paquisa",
    "tgn:placetype":[
        "aat:300008347"
    ]
},
  "bbox": [],
  "geometry": {"coordinates":[-69.05,-18.666667],"type":"Point"}
}