{
  "id": 2096883,
  "type": "Feature",
  "properties": {
    "tgn:hierarchy":[
        "tgn:2096883",
        "tgn:1000001",
        "tgn:2001734",
        "tgn:7012149",
        "tgn:7007712",
        "tgn:7029392"
    ],
    "tgn:id":2096883,
    "tgn:name":"Warren Crossroads",
    "tgn:placetype":[
        "aat:300008347",
        "aat:300387210"
    ]
},
  "bbox": [],
  "geometry": {"coordinates":[-80.2667,32.8167],"type":"Point"}
}