{
  "id": 7038186,
  "type": "Feature",
  "properties": {
    "tgn:hierarchy":[
        "tgn:7038186",
        "tgn:1001724",
        "tgn:1000003",
        "tgn:7003121",
        "tgn:1000080",
        "tgn:7029392"
    ],
    "tgn:id":7038186,
    "tgn:name":"Tortol\u00ec, Stagno di",
    "tgn:placetype":[
        "aat:300008679"
    ]
},
  "bbox": [],
  "geometry": {"coordinates":[9.670278,39.943333],"type":"Point"}
}