{
  "id": 7187789,
  "type": "Feature",
  "properties": {
    "tgn:hierarchy":[
        "tgn:7187789",
        "tgn:1000003",
        "tgn:7003682",
        "tgn:7000084",
        "tgn:7029392"
    ],
    "tgn:id":7187789,
    "tgn:name":"Ettringen Bell-Berg",
    "tgn:placetype":[
        "aat:300008777"
    ]
},
  "bbox": [],
  "geometry": {"coordinates":[7.233333,50.35],"type":"Point"}
}