{
  "id": 7308830,
  "type": "Feature",
  "properties": {
    "tgn:hierarchy":[
        "tgn:7308830",
        "tgn:1001702",
        "tgn:1000049",
        "tgn:1000002",
        "tgn:7029392"
    ],
    "tgn:id":7308830,
    "tgn:name":"Los Ventisqueros, Fiordo de",
    "tgn:placetype":[
        "aat:300008676"
    ]
},
  "bbox": [],
  "geometry": {"coordinates":[-72.916667,-52.666667],"type":"Point"}
}