{
  "id": 2189436,
  "type": "Feature",
  "properties": {
    "tgn:hierarchy":[
        "tgn:2189436",
        "tgn:1000001",
        "tgn:2001179",
        "tgn:7012149",
        "tgn:7007523",
        "tgn:7029392"
    ],
    "tgn:id":2189436,
    "tgn:name":"Boutin, Lake",
    "tgn:placetype":[
        "aat:300006191"
    ]
},
  "bbox": [],
  "geometry": {"coordinates":[-89.4833,37.45],"type":"Point"}
}