{
  "id": 2229551,
  "type": "Feature",
  "properties": {
    "tgn:hierarchy":[
        "tgn:2229551",
        "tgn:1000001",
        "tgn:1002714",
        "tgn:7012149",
        "tgn:7007159",
        "tgn:7029392"
    ],
    "tgn:id":2229551,
    "tgn:name":"Cedar Pond Brook",
    "tgn:placetype":[
        "aat:300008699"
    ]
},
  "bbox": [],
  "geometry": {"coordinates":[-72.2833,41.4333],"type":"Point"}
}