{
  "id": 2667164,
  "type": "Feature",
  "properties": {
    "tgn:hierarchy":[
        "tgn:2667164",
        "tgn:1000001",
        "tgn:2001840",
        "tgn:7012149",
        "tgn:7007825",
        "tgn:7029392"
    ],
    "tgn:id":2667164,
    "tgn:name":"Skillern Creek",
    "tgn:placetype":[
        "aat:300008706"
    ]
},
  "bbox": [],
  "geometry": {"coordinates":[-85.15,35.5333],"type":"Point"}
}