{
  "id": 7445462,
  "type": "Feature",
  "properties": {
    "tgn:hierarchy":[
        "tgn:7445462",
        "tgn:7002445",
        "tgn:1000003",
        "tgn:7008168",
        "tgn:7008591",
        "tgn:7029392"
    ],
    "tgn:id":7445462,
    "tgn:name:en":"Wittenham",
    "tgn:placetype":[
        "aat:300008347"
    ]
},
  "bbox": [],
  "geometry": {"coordinates":[-1.216667,51.633333],"type":"Point"}
}