{
  "id": 2778552,
  "type": "Feature",
  "properties": {
    "tgn:hierarchy":[
        "tgn:2778552",
        "tgn:1000001",
        "tgn:7012149",
        "tgn:1002679",
        "tgn:7007520",
        "tgn:7029392"
    ],
    "tgn:id":2778552,
    "tgn:name":"Wittkop Drain",
    "tgn:placetype":[
        "aat:300008699"
    ]
},
  "bbox": [],
  "geometry": {"coordinates":[-83.6333,41.9333],"type":"Point"}
}