{
  "id": 7008089,
  "type": "Feature",
  "properties": {
    "tgn:hierarchy":[
        "tgn:7008089",
        "tgn:7002444",
        "tgn:1000003",
        "tgn:7008591",
        "tgn:7029392"
    ],
    "tgn:id":7008089,
    "tgn:name:en":"Tayside",
    "tgn:placetype":[
        "aat:300387179",
        "aat:300387064",
        "aat:300236112"
    ]
},
  "bbox": [],
  "geometry": {"coordinates":[-3.533333,56.416667],"type":"Point"}
}