{
  "id": 7557280,
  "type": "Feature",
  "properties": {
    "tgn:hierarchy":[
        "tgn:7557280",
        "tgn:1000004",
        "tgn:7000198",
        "tgn:7000799",
        "tgn:7029392"
    ],
    "tgn:id":7557280,
    "tgn:name:en":"P\u012br Panj\u0101l Pass",
    "tgn:placetype":[
        "aat:300259572"
    ]
},
  "bbox": [],
  "geometry": {"coordinates":[74.519699,33.629791],"type":"Point"}
}