{
  "id": 2063846,
  "type": "Feature",
  "properties": {
    "tgn:hierarchy":[
        "tgn:2063846",
        "tgn:1000001",
        "tgn:2001427",
        "tgn:7012149",
        "tgn:7007564",
        "tgn:7029392"
    ],
    "tgn:id":2063846,
    "tgn:name":"Sunapee",
    "tgn:placetype":[
        "aat:300008347"
    ]
},
  "bbox": [],
  "geometry": {"coordinates":[-72.0833,43.3833],"type":"Point"}
}