{
  "id": 2034127,
  "type": "Feature",
  "properties": {
    "tgn:hierarchy":[
        "tgn:2034127",
        "tgn:1000001",
        "tgn:7012149",
        "tgn:2000548",
        "tgn:7007252",
        "tgn:7029392"
    ],
    "tgn:id":2034127,
    "tgn:name":"Whitehall",
    "tgn:placetype":[
        "aat:300008347",
        "aat:300387210"
    ]
},
  "bbox": [],
  "geometry": {"coordinates":[-86.6833,39.1667],"type":"Point"}
}