{
  "id": 7402473,
  "type": "Feature",
  "properties": {
    "tgn:hierarchy":[
        "tgn:7402473",
        "tgn:1000001",
        "tgn:1001937",
        "tgn:7005560",
        "tgn:7029392"
    ],
    "tgn:id":7402473,
    "tgn:name":"El Mirador",
    "tgn:placetype":[
        "aat:300008347"
    ]
},
  "bbox": [],
  "geometry": {"coordinates":[-88.645833,19.233333],"type":"Point"}
}