{
  "id": 7106610,
  "type": "Feature",
  "properties": {
    "tgn:hierarchy":[
        "tgn:7106610",
        "tgn:7003692",
        "tgn:1000003",
        "tgn:7000084",
        "tgn:7029392"
    ],
    "tgn:id":7106610,
    "tgn:name":"Schlegel Berg",
    "tgn:placetype":[
        "aat:300008777"
    ]
},
  "bbox": [],
  "geometry": {"coordinates":[9.75,48.133333],"type":"Point"}
}