{
  "id": 2780649,
  "type": "Feature",
  "properties": {
    "tgn:hierarchy":[
        "tgn:2780649",
        "tgn:1002167",
        "tgn:1000001",
        "tgn:7012149",
        "tgn:7007252",
        "tgn:7029392"
    ],
    "tgn:id":2780649,
    "tgn:name":"Wood Lake",
    "tgn:placetype":[
        "aat:300008680"
    ]
},
  "bbox": [],
  "geometry": {"coordinates":[-85.95,39.1667],"type":"Point"}
}