{
  "id": 7427461,
  "type": "Feature",
  "properties": {
    "tgn:hierarchy":[
        "tgn:7427461",
        "tgn:1000001",
        "tgn:7005594",
        "tgn:7005560",
        "tgn:7029392"
    ],
    "tgn:id":7427461,
    "tgn:name":"El Zacatonal",
    "tgn:placetype":[
        "aat:300008347"
    ]
},
  "bbox": [],
  "geometry": {"coordinates":[-101.016667,23.216667],"type":"Point"}
}