{
  "id": 2181989,
  "type": "Feature",
  "properties": {
    "tgn:hierarchy":[
        "tgn:2181989",
        "tgn:2002101",
        "tgn:1000001",
        "tgn:7012149",
        "tgn:7007827",
        "tgn:7029392"
    ],
    "tgn:id":2181989,
    "tgn:name":"Blue Lake",
    "tgn:placetype":[
        "aat:300006191"
    ]
},
  "bbox": [],
  "geometry": {"coordinates":[-112.4167,38.3833],"type":"Point"}
}