{
  "id": 2186662,
  "type": "Feature",
  "properties": {
    "tgn:hierarchy":[
        "tgn:2186662",
        "tgn:1000001",
        "tgn:7012149",
        "tgn:2000425",
        "tgn:7007248",
        "tgn:7029392"
    ],
    "tgn:id":2186662,
    "tgn:name":"Boney Creek",
    "tgn:placetype":[
        "aat:300008706"
    ]
},
  "bbox": [],
  "geometry": {"coordinates":[-83.05,31.8667],"type":"Point"}
}