{
  "id": 7084891,
  "type": "Feature",
  "properties": {
    "tgn:hierarchy":[
        "tgn:7084891",
        "tgn:7000096",
        "tgn:1000003",
        "tgn:7000084",
        "tgn:7029392"
    ],
    "tgn:id":7084891,
    "tgn:name":"Wei\u00dfer See",
    "tgn:placetype":[
        "aat:300008680"
    ]
},
  "bbox": [],
  "geometry": {"coordinates":[13.116667,53.133333],"type":"Point"}
}