{
  "id": 2611507,
  "type": "Feature",
  "properties": {
    "tgn:hierarchy":[
        "tgn:2611507",
        "tgn:1000001",
        "tgn:7012149",
        "tgn:2002063",
        "tgn:7007826",
        "tgn:7029392"
    ],
    "tgn:id":2611507,
    "tgn:name":"Red Mill Tank",
    "tgn:placetype":[
        "aat:300006191"
    ]
},
  "bbox": [],
  "geometry": {"coordinates":[-96.9667,28.3833],"type":"Point"}
}