{
  "id": 7060479,
  "type": "Feature",
  "properties": {
    "tgn:hierarchy":[
        "tgn:7060479",
        "tgn:1000003",
        "tgn:7003678",
        "tgn:7000084",
        "tgn:7029392"
    ],
    "tgn:id":7060479,
    "tgn:name":"Alten Buseck",
    "tgn:placetype":[
        "aat:300008347"
    ]
},
  "bbox": [],
  "geometry": {"coordinates":[8.75,50.616667],"type":"Point"}
}