<<<<<<< HEAD
{
  "id": 2337316,
  "type": "Feature",
  "properties": {
    "tgn:hierarchy":[
        "tgn:2337316",
        "tgn:1000001",
        "tgn:7012149",
        "tgn:2001290",
        "tgn:7007524",
        "tgn:7029392"
    ],
    "tgn:id":2337316,
    "tgn:name":"Fourth of July Gulch",
    "tgn:placetype":[
        "aat:300008761"
    ]
},
  "bbox": [],
  "geometry": {"coordinates":[-115.1833,47.1667],"type":"Point"}
}
=======
{"geometry":{"type":"Point","coordinates":[-115.183300,47.166700]},"type":"Feature","properties":{"hierarchy":["tgn:2337316","tgn:1000001","tgn:7012149","tgn:2001290","tgn:7007524","tgn:7029392"],"placetype":["aat:300008761"],"id":2337316,"name:xx":"Fourth of July Gulch"}}
>>>>>>> 03f74aca74312dbeaf24d7e61306dd6a786dc3d0
