{
  "id": 2695166,
  "type": "Feature",
  "properties": {
    "tgn:hierarchy":[
        "tgn:2695166",
        "tgn:7002659",
        "tgn:1000001",
        "tgn:7012149",
        "tgn:2000029",
        "tgn:7029392"
    ],
    "tgn:id":2695166,
    "tgn:name":"Stillhouse Hollow",
    "tgn:placetype":[
        "aat:300008761"
    ]
},
  "bbox": [],
  "geometry": {"coordinates":[-87.5333,34.4167],"type":"Point"}
}