<<<<<<< HEAD
{
  "id": 2769361,
  "type": "Feature",
  "properties": {
    "tgn:hierarchy":[
        "tgn:2769361",
        "tgn:1000001",
        "tgn:1002276",
        "tgn:7012149",
        "tgn:7007708",
        "tgn:7029392"
    ],
    "tgn:id":2769361,
    "tgn:name":"Wickiup Mountain",
    "tgn:placetype":[
        "aat:300008798"
    ]
},
  "bbox": [],
  "geometry": {"coordinates":[-123.5833,46.1],"type":"Point"}
}
=======
{"geometry":{"type":"Point","coordinates":[-123.583300,46.100000]},"type":"Feature","properties":{"hierarchy":["tgn:2769361","tgn:1000001","tgn:1002276","tgn:7012149","tgn:7007708","tgn:7029392"],"placetype":["aat:300008798"],"id":2769361,"name:xx":"Wickiup Mountain"}}
>>>>>>> 03f74aca74312dbeaf24d7e61306dd6a786dc3d0
