{
  "id": 2046259,
  "type": "Feature",
  "properties": {
    "tgn:hierarchy":[
        "tgn:2046259",
        "tgn:1000001",
        "tgn:7016106",
        "tgn:7012149",
        "tgn:7007516",
        "tgn:7029392"
    ],
    "tgn:id":2046259,
    "tgn:name":"Big Spring",
    "tgn:placetype":[
        "aat:300008347"
    ]
},
  "bbox": [],
  "geometry": {"coordinates":[-77.9333,39.6167],"type":"Point"}
}