{
  "id": 7049495,
  "type": "Feature",
  "properties": {
    "tgn:hierarchy":[
        "tgn:7049495",
        "tgn:7005880",
        "tgn:1000003",
        "tgn:7003237",
        "tgn:1000080",
        "tgn:7029392"
    ],
    "tgn:id":7049495,
    "tgn:name":"Gazzo",
    "tgn:placetype":[
        "aat:300008347"
    ]
},
  "bbox": [],
  "geometry": {"coordinates":[10.883333,45.166667],"type":"Point"}
}