{
  "id": 2479527,
  "type": "Feature",
  "properties": {
    "tgn:hierarchy":[
        "tgn:2479527",
        "tgn:1000001",
        "tgn:7012149",
        "tgn:2001714",
        "tgn:7007708",
        "tgn:7029392"
    ],
    "tgn:id":2479527,
    "tgn:name":"Lajeunesse Creek",
    "tgn:placetype":[
        "aat:300008706"
    ]
},
  "bbox": [],
  "geometry": {"coordinates":[-121.95,42.2833],"type":"Point"}
}