{
  "id": 7394592,
  "type": "Feature",
  "properties": {
    "tgn:hierarchy":[
        "tgn:7394592",
        "tgn:1000001",
        "tgn:7005592",
        "tgn:7005560",
        "tgn:7029392"
    ],
    "tgn:id":7394592,
    "tgn:name":"San Jos\u00e9 Ayotla",
    "tgn:placetype":[
        "aat:300008347"
    ]
},
  "bbox": [],
  "geometry": {"coordinates":[-98.05,19.916667],"type":"Point"}
}