{
  "id": 1011109,
  "type": "Feature",
  "properties": {
    "tgn:hierarchy":[
        "tgn:1011109",
        "tgn:1000004",
        "tgn:1001481",
        "tgn:1000135",
        "tgn:7029392"
    ],
    "tgn:id":1011109,
    "tgn:name":"Ross, Cape",
    "tgn:placetype":[
        "aat:300008850"
    ]
},
  "bbox": [],
  "geometry": {"coordinates":[119.2167,10.9333],"type":"Point"}
}