{
  "id": 2459137,
  "type": "Feature",
  "properties": {
    "tgn:hierarchy":[
        "tgn:2459137",
        "tgn:1000001",
        "tgn:7012149",
        "tgn:7013941",
        "tgn:7007568",
        "tgn:7029392"
    ],
    "tgn:id":2459137,
    "tgn:name":"Little Pine Pond",
    "tgn:placetype":[
        "aat:300008680"
    ]
},
  "bbox": [],
  "geometry": {"coordinates":[-74.15,44.25],"type":"Point"}
}