{
  "id": 7297601,
  "type": "Feature",
  "properties": {
    "tgn:hierarchy":[
        "tgn:7297601",
        "tgn:7002826",
        "tgn:7001158",
        "tgn:1000003",
        "tgn:1000095",
        "tgn:7029392"
    ],
    "tgn:id":7297601,
    "tgn:name":"Soto y Am\u00edo",
    "tgn:placetype":[
        "aat:300008347"
    ]
},
  "bbox": [],
  "geometry": {"coordinates":[-5.883333,42.766667],"type":"Point"}
}