{
  "id": 7011907,
  "type": "Feature",
  "properties": {
    "tgn:hierarchy":[
        "tgn:7011907",
        "tgn:7002445",
        "tgn:7008103",
        "tgn:1000003",
        "tgn:7008591",
        "tgn:7029392"
    ],
    "tgn:id":7011907,
    "tgn:name:en":"Bedford",
    "tgn:placetype":[
        "aat:300387277",
        "aat:300008347",
        "aat:300008416",
        "aat:300387220",
        "aat:300008375",
        "aat:300387270",
        "aat:300387302"
    ]
},
  "bbox": [],
  "geometry": {"coordinates":[-0.45,52.133333],"type":"Point"}
}