{
  "id": 2247475,
  "type": "Feature",
  "properties": {
    "tgn:hierarchy":[
        "tgn:2247475",
        "tgn:1000001",
        "tgn:7012149",
        "tgn:2000907",
        "tgn:7007256",
        "tgn:7029392"
    ],
    "tgn:id":2247475,
    "tgn:name":"Coffee Point",
    "tgn:placetype":[
        "aat:300008850"
    ]
},
  "bbox": [],
  "geometry": {"coordinates":[-91.0833,32.0167],"type":"Point"}
}