{
  "id": 1115738,
  "type": "Feature",
  "properties": {
    "tgn:hierarchy":[
        "tgn:1115738",
        "tgn:1000003",
        "tgn:1003396",
        "tgn:7006660",
        "tgn:7029392"
    ],
    "tgn:id":1115738,
    "tgn:name":"Burnas, ozero",
    "tgn:placetype":[
        "aat:300008680"
    ]
},
  "bbox": [],
  "geometry": {"coordinates":[30.1333,45.8667],"type":"Point"}
}