{
  "id": 7591181,
  "type": "Feature",
  "properties": {
    "tgn:hierarchy":[
        "tgn:7591181",
        "tgn:1000004",
        "tgn:7000198",
        "tgn:7000799",
        "tgn:7029392"
    ],
    "tgn:id":7591181,
    "tgn:name:en":"Chak Mohammady\u0101r",
    "tgn:placetype":[
        "aat:300008347"
    ]
},
  "bbox": [],
  "geometry": {"coordinates":[74.760112,32.587313],"type":"Point"}
}