{
  "id": 7564510,
  "type": "Feature",
  "properties": {
    "tgn:hierarchy":[
        "tgn:7564510",
        "tgn:1000004",
        "tgn:7000198",
        "tgn:7016722",
        "tgn:7029392"
    ],
    "tgn:id":7564510,
    "tgn:name:en":"Bhadaura",
    "tgn:placetype":[
        "aat:300008347"
    ]
},
  "bbox": [],
  "geometry": {"coordinates":[79.493243,26.393063],"type":"Point"}
}