{
  "id": 2574578,
  "type": "Feature",
  "properties": {
    "tgn:hierarchy":[
        "tgn:2574578",
        "tgn:1000001",
        "tgn:7012149",
        "tgn:2001879",
        "tgn:7007825",
        "tgn:7029392"
    ],
    "tgn:id":2574578,
    "tgn:name":"Pemberton Branch",
    "tgn:placetype":[
        "aat:300008699"
    ]
},
  "bbox": [],
  "geometry": {"coordinates":[-87.55,35.95],"type":"Point"}
}