{
  "id": 2079720,
  "type": "Feature",
  "properties": {
    "tgn:hierarchy":[
        "tgn:2079720",
        "tgn:1000001",
        "tgn:7012149",
        "tgn:1002689",
        "tgn:7007706",
        "tgn:7029392"
    ],
    "tgn:id":2079720,
    "tgn:name":"Germantown",
    "tgn:placetype":[
        "aat:300008347"
    ]
},
  "bbox": [],
  "geometry": {"coordinates":[-84.3667,39.6167],"type":"Point"}
}