{
  "id": 1019466,
  "type": "Feature",
  "properties": {
    "tgn:hierarchy":[
        "tgn:1019466",
        "tgn:7006477",
        "tgn:7006348",
        "tgn:1000002",
        "tgn:7029392"
    ],
    "tgn:id":1019466,
    "tgn:name":"Fort\u00edn Uno",
    "tgn:placetype":[
        "aat:300008347"
    ]
},
  "bbox": [],
  "geometry": {"coordinates":[-65.4333,-38.8333],"type":"Point"}
}