{
  "id": 2172702,
  "type": "Feature",
  "properties": {
    "tgn:hierarchy":[
        "tgn:2172702",
        "tgn:1000001",
        "tgn:7012149",
        "tgn:2002290",
        "tgn:7013961",
        "tgn:7029392"
    ],
    "tgn:id":2172702,
    "tgn:name":"Bills Branch",
    "tgn:placetype":[
        "aat:300008699"
    ]
},
  "bbox": [],
  "geometry": {"coordinates":[-80.9667,37.7833],"type":"Point"}
}