{
  "id": 7390402,
  "type": "Feature",
  "properties": {
    "tgn:hierarchy":[
        "tgn:7390402",
        "tgn:7005583",
        "tgn:1000001",
        "tgn:7005560",
        "tgn:7029392"
    ],
    "tgn:id":7390402,
    "tgn:name":"Rancho La Concepci\u00f3n",
    "tgn:placetype":[
        "aat:300008347"
    ]
},
  "bbox": [],
  "geometry": {"coordinates":[-103.45,24.583333],"type":"Point"}
}