{
  "id": 7234070,
  "type": "Feature",
  "properties": {
    "tgn:hierarchy":[
        "tgn:7234070",
        "tgn:7011171",
        "tgn:7001395",
        "tgn:1000003",
        "tgn:1000074",
        "tgn:7029392"
    ],
    "tgn:id":7234070,
    "tgn:name":"Akhladher\u00ed",
    "tgn:placetype":[
        "aat:300008347"
    ]
},
  "bbox": [],
  "geometry": {"coordinates":[24.166667,38.483333],"type":"Point"}
}