<<<<<<< HEAD
{
  "id": 7372876,
  "type": "Feature",
  "properties": {
    "tgn:hierarchy":[
        "tgn:7372876",
        "tgn:7005583",
        "tgn:1000001",
        "tgn:7005560",
        "tgn:7029392"
    ],
    "tgn:id":7372876,
    "tgn:name":"La Flor",
    "tgn:placetype":[
        "aat:300008347"
    ]
},
  "bbox": [],
  "geometry": {"coordinates":[-104.1,25.25],"type":"Point"}
}
=======
{"geometry":{"type":"Point","coordinates":[-104.100000,25.250000]},"type":"Feature","properties":{"hierarchy":["tgn:7372876","tgn:7005583","tgn:1000001","tgn:7005560","tgn:7029392"],"placetype":["aat:300008347"],"id":7372876,"name:xx":"La Flor"}}
>>>>>>> 03f74aca74312dbeaf24d7e61306dd6a786dc3d0
