{
  "id": 1011540,
  "type": "Feature",
  "properties": {
    "tgn:hierarchy":[
        "tgn:1011540",
        "tgn:1000139",
        "tgn:7004345",
        "tgn:1000004",
        "tgn:7000261",
        "tgn:7029392"
    ],
    "tgn:id":1011540,
    "tgn:name":"\u02bb\u0100rah, Ra's al-",
    "tgn:placetype":[
        "aat:300386846"
    ]
},
  "bbox": [],
  "geometry": {"coordinates":[43.95,12.6333],"type":"Point"}
}