{
  "id": 2572720,
  "type": "Feature",
  "properties": {
    "tgn:hierarchy":[
        "tgn:2572720",
        "tgn:2001423",
        "tgn:1000001",
        "tgn:7012149",
        "tgn:7007564",
        "tgn:7029392"
    ],
    "tgn:id":2572720,
    "tgn:name":"Peaked Mountain",
    "tgn:placetype":[
        "aat:300008798"
    ]
},
  "bbox": [],
  "geometry": {"coordinates":[-71.0833,44.0333],"type":"Point"}
}