{
  "id": 2514918,
  "type": "Feature",
  "properties": {
    "tgn:hierarchy":[
        "tgn:2514918",
        "tgn:1000001",
        "tgn:7012149",
        "tgn:1002613",
        "tgn:7007710",
        "tgn:7029392"
    ],
    "tgn:id":2514918,
    "tgn:name":"Miller Run Natural Area",
    "tgn:placetype":[
        "aat:300055621"
    ]
},
  "bbox": [],
  "geometry": {"coordinates":[-77.45,41.3667],"type":"Point"}
}