{
  "id": 2285681,
  "type": "Feature",
  "properties": {
    "tgn:hierarchy":[
        "tgn:2285681",
        "tgn:1000001",
        "tgn:7012149",
        "tgn:1002545",
        "tgn:7007157",
        "tgn:7029392"
    ],
    "tgn:id":2285681,
    "tgn:name":"Devils Kitchen",
    "tgn:placetype":[
        "aat:300008761"
    ]
},
  "bbox": [],
  "geometry": {"coordinates":[-119.15,34.8833],"type":"Point"}
}