{
  "id": 7535421,
  "type": "Feature",
  "properties": {
    "tgn:hierarchy":[
        "tgn:7535421",
        "tgn:7001242",
        "tgn:7001311",
        "tgn:7016833",
        "tgn:7029392"
    ],
    "tgn:id":7535421,
    "tgn:name:en":"Hyndman Reefs",
    "tgn:placetype":[
        "aat:300008808"
    ]
},
  "bbox": [],
  "geometry": {"coordinates":[34.05,26.65],"type":"Point"}
}