{
  "id": 7528890,
  "type": "Feature",
  "properties": {
    "tgn:hierarchy":[
        "tgn:7528890",
        "tgn:7001242",
        "tgn:7016833",
        "tgn:1001418",
        "tgn:7029392"
    ],
    "tgn:id":7528890,
    "tgn:name:en":"S\u012bd\u012b al Fu\u1e11ayl",
    "tgn:placetype":[
        "aat:300005926"
    ]
},
  "bbox": [],
  "geometry": {"coordinates":[25.327534,31.345156],"type":"Point"}
}