{
  "id": 7412504,
  "type": "Feature",
  "properties": {
    "tgn:hierarchy":[
        "tgn:7412504",
        "tgn:7005587",
        "tgn:1000001",
        "tgn:7005560",
        "tgn:7029392"
    ],
    "tgn:id":7412504,
    "tgn:name:es":"Cuaxontla",
    "tgn:placetype":[
        "aat:300008347"
    ]
},
  "bbox": [],
  "geometry": {"coordinates":[-98.723611,21.076389],"type":"Point"}
}