{
  "id": 1016562,
  "type": "Feature",
  "properties": {
    "tgn:hierarchy":[
        "tgn:1016562",
        "tgn:7005463",
        "tgn:1000001",
        "tgn:7005441",
        "tgn:7029392"
    ],
    "tgn:id":1016562,
    "tgn:name":"Delgado",
    "tgn:placetype":[
        "aat:300008347",
        "aat:300008389"
    ]
},
  "bbox": [],
  "geometry": {"coordinates":[-89.1667,13.7167],"type":"Point"}
}