{
  "id": 7509467,
  "type": "Feature",
  "properties": {
    "tgn:hierarchy":[
        "tgn:7509467",
        "tgn:1009227",
        "tgn:1000226",
        "tgn:7018437",
        "tgn:1000006",
        "tgn:7029392"
    ],
    "tgn:id":7509467,
    "tgn:name:en":"Waikoura Creek",
    "tgn:placetype":[
        "aat:300008699"
    ]
},
  "bbox": [],
  "geometry": {"coordinates":[170.883333,-44.95],"type":"Point"}
}