{
  "id": 2683314,
  "type": "Feature",
  "properties": {
    "tgn:hierarchy":[
        "tgn:2683314",
        "tgn:1000001",
        "tgn:7012149",
        "tgn:7007523",
        "tgn:7029392"
    ],
    "tgn:id":2683314,
    "tgn:name":"Sparkling Hollow",
    "tgn:placetype":[
        "aat:300008761"
    ]
},
  "bbox": [],
  "geometry": {"coordinates":[-92.0833,36.9667],"type":"Point"}
}