{
  "id": 2508918,
  "type": "Feature",
  "properties": {
    "tgn:hierarchy":[
        "tgn:2508918",
        "tgn:1000001",
        "tgn:7012149",
        "tgn:2001722",
        "tgn:7007708",
        "tgn:7029392"
    ],
    "tgn:id":2508918,
    "tgn:name":"Middle Fork Crow Creek",
    "tgn:placetype":[
        "aat:300008706"
    ]
},
  "bbox": [],
  "geometry": {"coordinates":[-117.1167,45.45],"type":"Point"}
}