{
  "id": 2341374,
  "type": "Feature",
  "properties": {
    "tgn:hierarchy":[
        "tgn:2341374",
        "tgn:1000001",
        "tgn:7012149",
        "tgn:2002387",
        "tgn:7007923",
        "tgn:7029392"
    ],
    "tgn:id":2341374,
    "tgn:name":"Frog Creek",
    "tgn:placetype":[
        "aat:300008706"
    ]
},
  "bbox": [],
  "geometry": {"coordinates":[-105.0333,43.5667],"type":"Point"}
}