{
  "id": 1019966,
  "type": "Feature",
  "properties": {
    "tgn:hierarchy":[
        "tgn:1019966",
        "tgn:1001160",
        "tgn:7006477",
        "tgn:1000002",
        "tgn:7029392"
    ],
    "tgn:id":1019966,
    "tgn:name":"Salliquel\u00f3",
    "tgn:placetype":[
        "aat:300008347"
    ]
},
  "bbox": [],
  "geometry": {"coordinates":[-62.9167,-36.75],"type":"Point"}
}