{
  "id": 2560416,
  "type": "Feature",
  "properties": {
    "tgn:hierarchy":[
        "tgn:2560416",
        "tgn:1000001",
        "tgn:7012149",
        "tgn:7013961",
        "tgn:7029392"
    ],
    "tgn:id":2560416,
    "tgn:name":"Orchid Fork",
    "tgn:placetype":[
        "aat:300008699"
    ]
},
  "bbox": [],
  "geometry": {"coordinates":[-80.8167,38.45],"type":"Point"}
}