{
  "id": 1089355,
  "type": "Feature",
  "properties": {
    "tgn:hierarchy":[
        "tgn:1089355",
        "tgn:7001242",
        "tgn:7016654",
        "tgn:1000159",
        "tgn:7029392"
    ],
    "tgn:id":1089355,
    "tgn:name":"Mokumbusu",
    "tgn:placetype":[
        "aat:300008347"
    ]
},
  "bbox": [],
  "geometry": {"coordinates":[21.0667,1.7333],"type":"Point"}
}