{
  "id": 7578429,
  "type": "Feature",
  "properties": {
    "tgn:hierarchy":[
        "tgn:7578429",
        "tgn:1000004",
        "tgn:1001869",
        "tgn:7000198",
        "tgn:7029392"
    ],
    "tgn:id":7578429,
    "tgn:name:en":"Vithodar",
    "tgn:placetype":[
        "aat:300008347"
    ]
},
  "bbox": [],
  "geometry": {"coordinates":[72.185268,24.42295],"type":"Point"}
}