{
  "id": 7579733,
  "type": "Feature",
  "properties": {
    "tgn:hierarchy":[
        "tgn:7579733",
        "tgn:1000004",
        "tgn:7000198",
        "tgn:1001895",
        "tgn:7029392"
    ],
    "tgn:id":7579733,
    "tgn:name:en":"Songir",
    "tgn:placetype":[
        "aat:300008347"
    ]
},
  "bbox": [],
  "geometry": {"coordinates":[74.787547,21.080333],"type":"Point"}
}