{
  "id": 1124758,
  "type": "Feature",
  "properties": {
    "tgn:hierarchy":[
        "tgn:1124758",
        "tgn:1000003",
        "tgn:7003676",
        "tgn:7000084",
        "tgn:7029392"
    ],
    "tgn:id":1124758,
    "tgn:name":"Hunte",
    "tgn:placetype":[
        "aat:300008707",
        "aat:300008699"
    ]
},
  "bbox": [],
  "geometry": {"coordinates":[8.483333,53.233333],"type":"Point"}
}