{
  "id": 7036401,
  "type": "Feature",
  "properties": {
    "tgn:hierarchy":[
        "tgn:7036401",
        "tgn:1003464",
        "tgn:1000003",
        "tgn:7003241",
        "tgn:1000080",
        "tgn:7029392"
    ],
    "tgn:id":7036401,
    "tgn:name":"Verrino, Torrente",
    "tgn:placetype":[
        "aat:300008699"
    ]
},
  "bbox": [],
  "geometry": {"coordinates":[14.45,41.733333],"type":"Point"}
}