{
  "id": 2519921,
  "type": "Feature",
  "properties": {
    "tgn:hierarchy":[
        "tgn:2519921",
        "tgn:1002808",
        "tgn:1000001",
        "tgn:7012149",
        "tgn:7007711",
        "tgn:7029392"
    ],
    "tgn:id":2519921,
    "tgn:name":"Molasses Hill",
    "tgn:placetype":[
        "aat:300008798"
    ]
},
  "bbox": [],
  "geometry": {"coordinates":[-71.4333,41.9167],"type":"Point"}
}