{
  "id": 2249124,
  "type": "Feature",
  "properties": {
    "tgn:hierarchy":[
        "tgn:2249124",
        "tgn:1000001",
        "tgn:2002149",
        "tgn:7012149",
        "tgn:7007919",
        "tgn:7029392"
    ],
    "tgn:id":2249124,
    "tgn:name":"Cole Creek",
    "tgn:placetype":[
        "aat:300008706"
    ]
},
  "bbox": [],
  "geometry": {"coordinates":[-78.2833,37.65],"type":"Point"}
}