{
  "id": 2440923,
  "type": "Feature",
  "properties": {
    "tgn:hierarchy":[
        "tgn:2440923",
        "tgn:1000001",
        "tgn:1002209",
        "tgn:7012149",
        "tgn:7007252",
        "tgn:7029392"
    ],
    "tgn:id":2440923,
    "tgn:name":"Knob Hill",
    "tgn:placetype":[
        "aat:300008798"
    ]
},
  "bbox": [],
  "geometry": {"coordinates":[-86.0833,39.2167],"type":"Point"}
}