{
  "id": 2212905,
  "type": "Feature",
  "properties": {
    "tgn:hierarchy":[
        "tgn:2212905",
        "tgn:1000001",
        "tgn:7012149",
        "tgn:2001862",
        "tgn:7007825",
        "tgn:7029392"
    ],
    "tgn:id":2212905,
    "tgn:name":"Caney Hollow Cave",
    "tgn:placetype":[
        "aat:300008746"
    ]
},
  "bbox": [],
  "geometry": {"coordinates":[-86.25,35.1167],"type":"Point"}
}