{
  "id": 2218724,
  "type": "Feature",
  "properties": {
    "tgn:hierarchy":[
        "tgn:2218724",
        "tgn:1000001",
        "tgn:7012149",
        "tgn:2001889",
        "tgn:7007825",
        "tgn:7029392"
    ],
    "tgn:id":2218724,
    "tgn:name":"Cane Island",
    "tgn:placetype":[
        "aat:300386851",
        "aat:300008791"
    ]
},
  "bbox": [],
  "geometry": {"coordinates":[-84.1667,35.7833],"type":"Point"}
}