{
  "id": 2302270,
  "type": "Feature",
  "properties": {
    "tgn:hierarchy":[
        "tgn:2302270",
        "tgn:1000001",
        "tgn:7012149",
        "tgn:2001718",
        "tgn:7007708",
        "tgn:7029392"
    ],
    "tgn:id":2302270,
    "tgn:name":"Dutch John Creek",
    "tgn:placetype":[
        "aat:300008706"
    ]
},
  "bbox": [],
  "geometry": {"coordinates":[-118.0833,44.1833],"type":"Point"}
}