<<<<<<< HEAD
{
  "id": 7362620,
  "type": "Feature",
  "properties": {
    "tgn:hierarchy":[
        "tgn:7362620",
        "tgn:7005586",
        "tgn:1000001",
        "tgn:7005560",
        "tgn:7029392"
    ],
    "tgn:id":7362620,
    "tgn:name":"El Maguey, Cerro",
    "tgn:placetype":[
        "aat:300008795"
    ]
},
  "bbox": [],
  "geometry": {"coordinates":[-102.65,20.733333],"type":"Point"}
}
=======
{"geometry":{"type":"Point","coordinates":[-102.650000,20.733333]},"type":"Feature","properties":{"hierarchy":["tgn:7362620","tgn:7005586","tgn:1000001","tgn:7005560","tgn:7029392"],"placetype":["aat:300008795"],"id":7362620,"name:xx":"El Maguey, Cerro"}}
>>>>>>> 03f74aca74312dbeaf24d7e61306dd6a786dc3d0
