{
  "id": 2516345,
  "type": "Feature",
  "properties": {
    "tgn:hierarchy":[
        "tgn:2516345",
        "tgn:7013388",
        "tgn:1000001",
        "tgn:7012149",
        "tgn:7007517",
        "tgn:7029392"
    ],
    "tgn:id":2516345,
    "tgn:name":"Miner Brook",
    "tgn:placetype":[
        "aat:300008699"
    ]
},
  "bbox": [],
  "geometry": {"coordinates":[-73.0833,42.15],"type":"Point"}
}