{
  "id": 7511366,
  "type": "Feature",
  "properties": {
    "tgn:hierarchy":[
        "tgn:7511366",
        "tgn:1009227",
        "tgn:1000226",
        "tgn:1000006",
        "tgn:7016850",
        "tgn:7029392"
    ],
    "tgn:id":7511366,
    "tgn:name:en":"Murray Creek",
    "tgn:placetype":[
        "aat:300008699"
    ]
},
  "bbox": [],
  "geometry": {"coordinates":[171.05,-42.866667],"type":"Point"}
}