{
  "id": 2581417,
  "type": "Feature",
  "properties": {
    "tgn:hierarchy":[
        "tgn:2581417",
        "tgn:1000001",
        "tgn:7016172",
        "tgn:2000112",
        "tgn:7012149",
        "tgn:7029392"
    ],
    "tgn:id":2581417,
    "tgn:name":"Pilot Knob",
    "tgn:placetype":[
        "aat:300008798"
    ]
},
  "bbox": [],
  "geometry": {"coordinates":[-93.3333,36.2333],"type":"Point"}
}