{
  "id": 2144977,
  "type": "Feature",
  "properties": {
    "tgn:hierarchy":[
        "tgn:2144977",
        "tgn:1000001",
        "tgn:7012149",
        "tgn:2002187",
        "tgn:7007919",
        "tgn:7029392"
    ],
    "tgn:id":2144977,
    "tgn:name":"Bald Knob",
    "tgn:placetype":[
        "aat:300008798"
    ]
},
  "bbox": [],
  "geometry": {"coordinates":[-79.05,38.5833],"type":"Point"}
}