{
  "id": 2393278,
  "type": "Feature",
  "properties": {
    "tgn:hierarchy":[
        "tgn:2393278",
        "tgn:1002143",
        "tgn:1000001",
        "tgn:7012149",
        "tgn:7007252",
        "tgn:7029392"
    ],
    "tgn:id":2393278,
    "tgn:name":"Hoffman Creek",
    "tgn:placetype":[
        "aat:300008706"
    ]
},
  "bbox": [],
  "geometry": {"coordinates":[-84.5833,41.0167],"type":"Point"}
}