{
  "id": 2429170,
  "type": "Feature",
  "properties": {
    "tgn:hierarchy":[
        "tgn:2429170",
        "tgn:7006450",
        "tgn:1000001",
        "tgn:7030547",
        "tgn:7012149",
        "tgn:7029392"
    ],
    "tgn:id":2429170,
    "tgn:name":"June Creek",
    "tgn:placetype":[
        "aat:300008706"
    ]
},
  "bbox": [],
  "geometry": {"coordinates":[-149.25,64.1167],"type":"Point"}
}