{
  "id": 7243183,
  "type": "Feature",
  "properties": {
    "tgn:hierarchy":[
        "tgn:7243183",
        "tgn:7003457",
        "tgn:1000003",
        "tgn:1000063",
        "tgn:7018236",
        "tgn:7029392"
    ],
    "tgn:id":7243183,
    "tgn:name":"Krevelhoek",
    "tgn:placetype":[
        "aat:300008347"
    ]
},
  "bbox": [],
  "geometry": {"coordinates":[3.983333,50.95],"type":"Point"}
}