{
  "id": 2009556,
  "type": "Feature",
  "properties": {
    "tgn:hierarchy":[
        "tgn:2009556",
        "tgn:1000001",
        "tgn:7016172",
        "tgn:7012149",
        "tgn:2000176",
        "tgn:7029392"
    ],
    "tgn:id":2009556,
    "tgn:name":"Spring Valley",
    "tgn:placetype":[
        "aat:300008347",
        "aat:300387210"
    ]
},
  "bbox": [],
  "geometry": {"coordinates":[-93.9333,36.1667],"type":"Point"}
}