{
  "id": 7117089,
  "type": "Feature",
  "properties": {
    "tgn:hierarchy":[
        "tgn:7117089",
        "tgn:1000003",
        "tgn:7003682",
        "tgn:7000084",
        "tgn:7029392"
    ],
    "tgn:id":7117089,
    "tgn:name":"Orschbach",
    "tgn:placetype":[
        "aat:300008699"
    ]
},
  "bbox": [],
  "geometry": {"coordinates":[6.85,49.883333],"type":"Point"}
}