{
  "id": 2045618,
  "type": "Feature",
  "properties": {
    "tgn:hierarchy":[
        "tgn:2045618",
        "tgn:2000918",
        "tgn:1000001",
        "tgn:7012149",
        "tgn:7007515",
        "tgn:7029392"
    ],
    "tgn:id":2045618,
    "tgn:name":"South Durham",
    "tgn:placetype":[
        "aat:300008347",
        "aat:300387210"
    ]
},
  "bbox": [],
  "geometry": {"coordinates":[-70.0667,43.9333],"type":"Point"}
}