{
  "id": 7580879,
  "type": "Feature",
  "properties": {
    "tgn:hierarchy":[
        "tgn:7580879",
        "tgn:1000004",
        "tgn:7000198",
        "tgn:1001894",
        "tgn:7029392"
    ],
    "tgn:id":7580879,
    "tgn:name:en":"Sh\u0101mgarh",
    "tgn:placetype":[
        "aat:300008347"
    ]
},
  "bbox": [],
  "geometry": {"coordinates":[75.639032,24.188174],"type":"Point"}
}