{
  "id": 7316880,
  "type": "Feature",
  "properties": {
    "tgn:hierarchy":[
        "tgn:7316880",
        "tgn:7002464",
        "tgn:1000049",
        "tgn:1000002",
        "tgn:7029392"
    ],
    "tgn:id":7316880,
    "tgn:name":"Chislluma, R\u00edo",
    "tgn:placetype":[
        "aat:300266554",
        "aat:300008699"
    ]
},
  "bbox": [],
  "geometry": {"coordinates":[-69.683333,-17.716667],"type":"Point"}
}