{
  "id": 2737150,
  "type": "Feature",
  "properties": {
    "tgn:hierarchy":[
        "tgn:2737150",
        "tgn:1000001",
        "tgn:7012149",
        "tgn:2001719",
        "tgn:7007708",
        "tgn:7029392"
    ],
    "tgn:id":2737150,
    "tgn:name":"Two Spring Creek",
    "tgn:placetype":[
        "aat:300008706"
    ]
},
  "bbox": [],
  "geometry": {"coordinates":[-119.3833,45.05],"type":"Point"}
}