{
  "id": 7580559,
  "type": "Feature",
  "properties": {
    "tgn:hierarchy":[
        "tgn:7580559",
        "tgn:1000004",
        "tgn:7018318",
        "tgn:7000198",
        "tgn:7029392"
    ],
    "tgn:id":7580559,
    "tgn:name:en":"Vainguinim",
    "tgn:placetype":[
        "aat:300008347"
    ]
},
  "bbox": [],
  "geometry": {"coordinates":[73.883333,15.566667],"type":"Point"}
}