{
  "id": 2650999,
  "type": "Feature",
  "properties": {
    "tgn:hierarchy":[
        "tgn:2650999",
        "tgn:1000001",
        "tgn:7012149",
        "tgn:2000477",
        "tgn:7007250",
        "tgn:7029392"
    ],
    "tgn:id":2650999,
    "tgn:name":"Second Owsley Canal",
    "tgn:placetype":[
        "aat:300006075"
    ]
},
  "bbox": [],
  "geometry": {"coordinates":[-112.4833,43.7833],"type":"Point"}
}