{
  "id": 7276911,
  "type": "Feature",
  "properties": {
    "tgn:hierarchy":[
        "tgn:7276911",
        "tgn:1001708",
        "tgn:1000049",
        "tgn:1000002",
        "tgn:7029392"
    ],
    "tgn:id":7276911,
    "tgn:name":"Yerbas Buenas, Quebrada de",
    "tgn:placetype":[
        "aat:300008699"
    ]
},
  "bbox": [],
  "geometry": {"coordinates":[-71.033333,-33.783333],"type":"Point"}
}