{
  "id": 2501539,
  "type": "Feature",
  "properties": {
    "tgn:hierarchy":[
        "tgn:2501539",
        "tgn:1000001",
        "tgn:7012149",
        "tgn:7007157",
        "tgn:2000191",
        "tgn:7029392"
    ],
    "tgn:id":2501539,
    "tgn:name":"McGuire Gulch",
    "tgn:placetype":[
        "aat:300008761"
    ]
},
  "bbox": [],
  "geometry": {"coordinates":[-122.8167,41.0833],"type":"Point"}
}