{
  "id": 1022348,
  "type": "Feature",
  "properties": {
    "tgn:hierarchy":[
        "tgn:1022348",
        "tgn:1001945",
        "tgn:1000047",
        "tgn:7002457",
        "tgn:1000002",
        "tgn:7029392"
    ],
    "tgn:id":1022348,
    "tgn:name":"Paranapiacaba",
    "tgn:placetype":[
        "aat:300008347"
    ]
},
  "bbox": [],
  "geometry": {"coordinates":[-46.3167,-23.7833],"type":"Point"}
}