{
  "id": 2324761,
  "type": "Feature",
  "properties": {
    "tgn:hierarchy":[
        "tgn:2324761",
        "tgn:1000001",
        "tgn:2001653",
        "tgn:7012149",
        "tgn:7007707",
        "tgn:7029392"
    ],
    "tgn:id":2324761,
    "tgn:name":"Fenton Lake",
    "tgn:placetype":[
        "aat:300006191"
    ]
},
  "bbox": [],
  "geometry": {"coordinates":[-95.1667,35.2333],"type":"Point"}
}