{
  "id": 7585891,
  "type": "Feature",
  "properties": {
    "tgn:hierarchy":[
        "tgn:7585891",
        "tgn:1000004",
        "tgn:7000198",
        "tgn:7000799",
        "tgn:7029392"
    ],
    "tgn:id":7585891,
    "tgn:name:en":"L\u0101rmarg",
    "tgn:placetype":[
        "aat:300008347"
    ]
},
  "bbox": [],
  "geometry": {"coordinates":[74.762798,34.326309],"type":"Point"}
}