{
  "id": 2642720,
  "type": "Feature",
  "properties": {
    "tgn:hierarchy":[
        "tgn:2642720",
        "tgn:1000001",
        "tgn:1002480",
        "tgn:7012149",
        "tgn:7007564",
        "tgn:7029392"
    ],
    "tgn:id":2642720,
    "tgn:name":"Sandhill Pond",
    "tgn:placetype":[
        "aat:300008680"
    ]
},
  "bbox": [],
  "geometry": {"coordinates":[-71.7333,42.9167],"type":"Point"}
}