{
  "id": 7511129,
  "type": "Feature",
  "properties": {
    "tgn:hierarchy":[
        "tgn:7511129",
        "tgn:1009227",
        "tgn:1000226",
        "tgn:1000006",
        "tgn:7016850",
        "tgn:7029392"
    ],
    "tgn:id":7511129,
    "tgn:name:en":"Slaty Creek",
    "tgn:placetype":[
        "aat:300008699"
    ]
},
  "bbox": [],
  "geometry": {"coordinates":[171.533333,-42.266667],"type":"Point"}
}