{
  "id": 2531147,
  "type": "Feature",
  "properties": {
    "tgn:hierarchy":[
        "tgn:2531147",
        "tgn:1000001",
        "tgn:2000264",
        "tgn:7012149",
        "tgn:7007240",
        "tgn:7029392"
    ],
    "tgn:id":2531147,
    "tgn:name":"Mulberry Cove",
    "tgn:placetype":[
        "aat:300132316"
    ]
},
  "bbox": [],
  "geometry": {"coordinates":[-81.6667,30.2167],"type":"Point"}
}