{
  "id": 7594247,
  "type": "Feature",
  "properties": {
    "tgn:hierarchy":[
        "tgn:7594247",
        "tgn:1000003",
        "tgn:7005729",
        "tgn:7029392"
    ],
    "tgn:id":7594247,
    "tgn:name":"\u017bejtun",
    "tgn:placetype":[
        "aat:300387064",
        "aat:300387205"
    ]
},
  "bbox": [],
  "geometry": {"coordinates":[14.533333,35.857778],"type":"Point"}
}