<<<<<<< HEAD
{
  "id": 7052285,
  "type": "Feature",
  "properties": {
    "tgn:hierarchy":[
        "tgn:7052285",
        "tgn:7003013",
        "tgn:7003005",
        "tgn:1000003",
        "tgn:1000080",
        "tgn:7029392"
    ],
    "tgn:id":7052285,
    "tgn:name":"Penna, Scoglio",
    "tgn:placetype":[
        "aat:300008791"
    ]
},
  "bbox": [],
  "geometry": {"coordinates":[14.35,40.566667],"type":"Point"}
}
=======
{"geometry":{"type":"Point","coordinates":[14.350000,40.566667]},"type":"Feature","properties":{"hierarchy":["tgn:7052285","tgn:7003013","tgn:7003005","tgn:1000003","tgn:1000080","tgn:7029392"],"placetype":["aat:300008791"],"id":7052285,"name:xx":"Penna, Scoglio"}}
>>>>>>> 03f74aca74312dbeaf24d7e61306dd6a786dc3d0
