{
  "id": 2147882,
  "type": "Feature",
  "properties": {
    "tgn:hierarchy":[
        "tgn:2147882",
        "tgn:1000001",
        "tgn:2000951",
        "tgn:7012149",
        "tgn:7007520",
        "tgn:7029392"
    ],
    "tgn:id":2147882,
    "tgn:name":"Barhite Lake",
    "tgn:placetype":[
        "aat:300008680"
    ]
},
  "bbox": [],
  "geometry": {"coordinates":[-84.65,45.25],"type":"Point"}
}