{
  "id": 7286867,
  "type": "Feature",
  "properties": {
    "tgn:hierarchy":[
        "tgn:7286867",
        "tgn:7002464",
        "tgn:1000049",
        "tgn:1000002",
        "tgn:7029392"
    ],
    "tgn:id":7286867,
    "tgn:name":"Gua\u00f1ada, Quebrada",
    "tgn:placetype":[
        "aat:300266554",
        "aat:300008699"
    ]
},
  "bbox": [],
  "geometry": {"coordinates":[-68.883333,-20.466667],"type":"Point"}
}