{
  "id": 1044874,
  "type": "Feature",
  "properties": {
    "tgn:hierarchy":[
        "tgn:1044874",
        "tgn:1000003",
        "tgn:7003122",
        "tgn:1001762",
        "tgn:1000080",
        "tgn:7029392"
    ],
    "tgn:id":1044874,
    "tgn:name":"Granitola Torretta",
    "tgn:placetype":[
        "aat:300008347"
    ]
},
  "bbox": [],
  "geometry": {"coordinates":[12.5667,37.5667],"type":"Point"}
}