{
  "id": 7574194,
  "type": "Feature",
  "properties": {
    "tgn:hierarchy":[
        "tgn:7574194",
        "tgn:1000004",
        "tgn:7000198",
        "tgn:7016788",
        "tgn:7029392"
    ],
    "tgn:id":7574194,
    "tgn:name:en":"Genji",
    "tgn:placetype":[
        "aat:300008347"
    ]
},
  "bbox": [],
  "geometry": {"coordinates":[73.692039,23.715906],"type":"Point"}
}