{
  "id": 7527911,
  "type": "Feature",
  "properties": {
    "tgn:hierarchy":[
        "tgn:7527911",
        "tgn:7001242",
        "tgn:7001311",
        "tgn:7016833",
        "tgn:7029392"
    ],
    "tgn:id":7527911,
    "tgn:name:en":"Umm Ara, Gebel",
    "tgn:placetype":[
        "aat:300008795"
    ]
},
  "bbox": [],
  "geometry": {"coordinates":[33.792102,22.494469],"type":"Point"}
}