<<<<<<< HEAD
{
  "id": 2764363,
  "type": "Feature",
  "properties": {
    "tgn:hierarchy":[
        "tgn:2764363",
        "tgn:1000001",
        "tgn:7012149",
        "tgn:2000748",
        "tgn:7007254",
        "tgn:7029392"
    ],
    "tgn:id":2764363,
    "tgn:name":"Whetstone Creek",
    "tgn:placetype":[
        "aat:300008706"
    ]
},
  "bbox": [],
  "geometry": {"coordinates":[-95.5333,38.9833],"type":"Point"}
}
=======
{"geometry":{"type":"Point","coordinates":[-95.533300,38.983300]},"type":"Feature","properties":{"hierarchy":["tgn:2764363","tgn:1000001","tgn:7012149","tgn:2000748","tgn:7007254","tgn:7029392"],"placetype":["aat:300008706"],"id":2764363,"name:xx":"Whetstone Creek"}}
>>>>>>> 03f74aca74312dbeaf24d7e61306dd6a786dc3d0
