{
  "id": 7460234,
  "type": "Feature",
  "properties": {
    "tgn:hierarchy":[
        "tgn:7460234",
        "tgn:7002444",
        "tgn:7008074",
        "tgn:1000003",
        "tgn:7008591",
        "tgn:7029392"
    ],
    "tgn:id":7460234,
    "tgn:name:en":"Lochwood Mains",
    "tgn:placetype":[
        "aat:300008347"
    ]
},
  "bbox": [],
  "geometry": {"coordinates":[-3.433333,55.25],"type":"Point"}
}