{
  "id": 1091791,
  "type": "Feature",
  "properties": {
    "tgn:hierarchy":[
        "tgn:1091791",
        "tgn:7001242",
        "tgn:1000589",
        "tgn:1000181",
        "tgn:7029392"
    ],
    "tgn:id":1091791,
    "tgn:name":"Nguigmi",
    "tgn:placetype":[
        "aat:300008347"
    ]
},
  "bbox": [],
  "geometry": {"coordinates":[13.1167,14.25],"type":"Point"}
}