{
  "id": 7352833,
  "type": "Feature",
  "properties": {
    "tgn:hierarchy":[
        "tgn:7352833",
        "tgn:1000001",
        "tgn:1001893",
        "tgn:7005560",
        "tgn:7029392"
    ],
    "tgn:id":7352833,
    "tgn:name":"Alto de la Tableta, Cerro",
    "tgn:placetype":[
        "aat:300008795"
    ]
},
  "bbox": [],
  "geometry": {"coordinates":[-106.95,25.616667],"type":"Point"}
}