{
  "id": 7396034,
  "type": "Feature",
  "properties": {
    "tgn:hierarchy":[
        "tgn:7396034",
        "tgn:1000001",
        "tgn:7005601",
        "tgn:7005560",
        "tgn:7029392"
    ],
    "tgn:id":7396034,
    "tgn:name":"San Felipe",
    "tgn:placetype":[
        "aat:300008347"
    ]
},
  "bbox": [],
  "geometry": {"coordinates":[-103.216667,22.45],"type":"Point"}
}