{
  "id": 2309719,
  "type": "Feature",
  "properties": {
    "tgn:hierarchy":[
        "tgn:2309719",
        "tgn:1000001",
        "tgn:7012149",
        "tgn:2001420",
        "tgn:7007526",
        "tgn:7029392"
    ],
    "tgn:id":2309719,
    "tgn:name":"Easter Springs",
    "tgn:placetype":[
        "aat:300008697"
    ]
},
  "bbox": [],
  "geometry": {"coordinates":[-115.3333,39.0333],"type":"Point"}
}