{
  "id": 7557375,
  "type": "Feature",
  "properties": {
    "tgn:hierarchy":[
        "tgn:7557375",
        "tgn:7001819",
        "tgn:1000004",
        "tgn:7000198",
        "tgn:7029392"
    ],
    "tgn:id":7557375,
    "tgn:name:en":"Plongliang",
    "tgn:placetype":[
        "aat:300008347"
    ]
},
  "bbox": [],
  "geometry": {"coordinates":[96.555441,28.278424],"type":"Point"}
}