{
  "id": 7232244,
  "type": "Feature",
  "properties": {
    "tgn:hierarchy":[
        "tgn:7232244",
        "tgn:7002680",
        "tgn:7001395",
        "tgn:1000003",
        "tgn:1000074",
        "tgn:7029392"
    ],
    "tgn:id":7232244,
    "tgn:name":"Makrino\u00fa",
    "tgn:placetype":[
        "aat:300008347"
    ]
},
  "bbox": [],
  "geometry": {"coordinates":[21.616667,38.466667],"type":"Point"}
}