{
  "id": 2636606,
  "type": "Feature",
  "properties": {
    "tgn:hierarchy":[
        "tgn:2636606",
        "tgn:1000001",
        "tgn:2001419",
        "tgn:7012149",
        "tgn:7007526",
        "tgn:7029392"
    ],
    "tgn:id":2636606,
    "tgn:name":"Sage Hen Mine",
    "tgn:placetype":[
        "aat:300000390"
    ]
},
  "bbox": [],
  "geometry": {"coordinates":[-118.8333,40.55],"type":"Point"}
}