{
  "id": 7587576,
  "type": "Feature",
  "properties": {
    "tgn:hierarchy":[
        "tgn:7587576",
        "tgn:1000004",
        "tgn:7000198",
        "tgn:1001977",
        "tgn:7029392"
    ],
    "tgn:id":7587576,
    "tgn:name:en":"Sukdebpur",
    "tgn:placetype":[
        "aat:300008347"
    ]
},
  "bbox": [],
  "geometry": {"coordinates":[88.276389,22.150833],"type":"Point"}
}