{
  "id": 2582787,
  "type": "Feature",
  "properties": {
    "tgn:hierarchy":[
        "tgn:2582787",
        "tgn:1000001",
        "tgn:2000271",
        "tgn:7012149",
        "tgn:7007240",
        "tgn:7029392"
    ],
    "tgn:id":2582787,
    "tgn:name":"Pine Island",
    "tgn:placetype":[
        "aat:300008791"
    ]
},
  "bbox": [],
  "geometry": {"coordinates":[-82.8333,30.45],"type":"Point"}
}