{
  "id": 7135571,
  "type": "Feature",
  "properties": {
    "tgn:hierarchy":[
        "tgn:7135571",
        "tgn:1000003",
        "tgn:7003676",
        "tgn:7000084",
        "tgn:7029392"
    ],
    "tgn:id":7135571,
    "tgn:name":"M\u00f6llering",
    "tgn:placetype":[
        "aat:300000206"
    ]
},
  "bbox": [],
  "geometry": {"coordinates":[7.233333,52.366667],"type":"Point"}
}