{
  "id": 1070061,
  "type": "Feature",
  "properties": {
    "tgn:hierarchy":[
        "tgn:1070061",
        "tgn:1000004",
        "tgn:7018118",
        "tgn:1000111",
        "tgn:7029392"
    ],
    "tgn:id":1070061,
    "tgn:name":"Longgang",
    "tgn:placetype":[
        "aat:300008347"
    ]
},
  "bbox": [],
  "geometry": {"coordinates":[101.15,24.6833],"type":"Point"}
}