<<<<<<< HEAD
{
  "id": 2151333,
  "type": "Feature",
  "properties": {
    "tgn:hierarchy":[
        "tgn:2151333",
        "tgn:1000001",
        "tgn:7012149",
        "tgn:2001195",
        "tgn:7007523",
        "tgn:7029392"
    ],
    "tgn:id":2151333,
    "tgn:name":"Bates Hollow",
    "tgn:placetype":[
        "aat:300008761"
    ]
},
  "bbox": [],
  "geometry": {"coordinates":[-91.2667,37.65],"type":"Point"}
}
=======
{"geometry":{"type":"Point","coordinates":[-91.266700,37.650000]},"type":"Feature","properties":{"hierarchy":["tgn:2151333","tgn:1000001","tgn:7012149","tgn:2001195","tgn:7007523","tgn:7029392"],"placetype":["aat:300008761"],"id":2151333,"name:xx":"Bates Hollow"}}
>>>>>>> 03f74aca74312dbeaf24d7e61306dd6a786dc3d0
