{
  "id": 2319815,
  "type": "Feature",
  "properties": {
    "tgn:hierarchy":[
        "tgn:2319815",
        "tgn:1000001",
        "tgn:7006451",
        "tgn:2000091",
        "tgn:7012149",
        "tgn:7029392"
    ],
    "tgn:id":2319815,
    "tgn:name":"Eureka Spring",
    "tgn:placetype":[
        "aat:300008697"
    ]
},
  "bbox": [],
  "geometry": {"coordinates":[-110.3167,32.3667],"type":"Point"}
}