{
  "id": 2005076,
  "type": "Feature",
  "properties": {
    "tgn:hierarchy":[
        "tgn:2005076",
        "tgn:7002659",
        "tgn:1000001",
        "tgn:7012149",
        "tgn:2000065",
        "tgn:7029392"
    ],
    "tgn:id":2005076,
    "tgn:name":"Rehoboth",
    "tgn:placetype":[
        "aat:300008347",
        "aat:300387210"
    ]
},
  "bbox": [],
  "geometry": {"coordinates":[-87.3667,32.1833],"type":"Point"}
}