<<<<<<< HEAD
{
  "id": 2151350,
  "type": "Feature",
  "properties": {
    "tgn:hierarchy":[
        "tgn:2151350",
        "tgn:1000001",
        "tgn:7012149",
        "tgn:2000221",
        "tgn:7007158",
        "tgn:7029392"
    ],
    "tgn:id":2151350,
    "tgn:name":"Bates Lake",
    "tgn:placetype":[
        "aat:300006191"
    ]
},
  "bbox": [],
  "geometry": {"coordinates":[-105.05,39.8],"type":"Point"}
}
=======
{"geometry":{"type":"Point","coordinates":[-105.050000,39.800000]},"type":"Feature","properties":{"hierarchy":["tgn:2151350","tgn:1000001","tgn:7012149","tgn:2000221","tgn:7007158","tgn:7029392"],"placetype":["aat:300006191"],"id":2151350,"name:xx":"Bates Lake"}}
>>>>>>> 03f74aca74312dbeaf24d7e61306dd6a786dc3d0
