{
  "id": 1032250,
  "type": "Feature",
  "properties": {
    "tgn:hierarchy":[
        "tgn:1032250",
        "tgn:1000003",
        "tgn:7002875",
        "tgn:1000070",
        "tgn:7029392"
    ],
    "tgn:id":1032250,
    "tgn:name":"Bourbon-Lancy",
    "tgn:placetype":[
        "aat:300008347"
    ]
},
  "bbox": [],
  "geometry": {"coordinates":[3.7667,46.6167],"type":"Point"}
}