{
  "id": 1011672,
  "type": "Feature",
  "properties": {
    "tgn:hierarchy":[
        "tgn:1011672",
        "tgn:7002038",
        "tgn:1006044",
        "tgn:1000217",
        "tgn:1000006",
        "tgn:7029392"
    ],
    "tgn:id":1011672,
    "tgn:name":"Bridges Point",
    "tgn:placetype":[
        "aat:300386846"
    ]
},
  "bbox": [],
  "geometry": {"coordinates":[-157.4833,1.9833],"type":"Point"}
}