{
  "id": 7395757,
  "type": "Feature",
  "properties": {
    "tgn:hierarchy":[
        "tgn:7395757",
        "tgn:7005580",
        "tgn:1000001",
        "tgn:7005560",
        "tgn:7029392"
    ],
    "tgn:id":7395757,
    "tgn:name":"San Esteban",
    "tgn:placetype":[
        "aat:300008347"
    ]
},
  "bbox": [],
  "geometry": {"coordinates":[-93.316667,16.366667],"type":"Point"}
}