{
  "id": 7143294,
  "type": "Feature",
  "properties": {
    "tgn:hierarchy":[
        "tgn:7143294",
        "tgn:1000003",
        "tgn:7003676",
        "tgn:7000084",
        "tgn:7029392"
    ],
    "tgn:id":7143294,
    "tgn:name":"Linden",
    "tgn:placetype":[
        "aat:300008347"
    ]
},
  "bbox": [],
  "geometry": {"coordinates":[10.366667,52.983333],"type":"Point"}
}