{
  "id": 1085836,
  "type": "Feature",
  "properties": {
    "tgn:hierarchy":[
        "tgn:1085836",
        "tgn:1000004",
        "tgn:1001606",
        "tgn:7018453",
        "tgn:1000144",
        "tgn:7029392"
    ],
    "tgn:id":1085836,
    "tgn:name":"\u015eefaatl\u0131",
    "tgn:placetype":[
        "aat:300008347"
    ]
},
  "bbox": [],
  "geometry": {"coordinates":[34.7667,39.5167],"type":"Point"}
}