{
  "id": 2700898,
  "type": "Feature",
  "properties": {
    "tgn:hierarchy":[
        "tgn:2700898",
        "tgn:1000001",
        "tgn:7012149",
        "tgn:2000430",
        "tgn:7007248",
        "tgn:7029392"
    ],
    "tgn:id":2700898,
    "tgn:name":"Sugar Cove",
    "tgn:placetype":[
        "aat:300386845"
    ]
},
  "bbox": [],
  "geometry": {"coordinates":[-83.6167,34.9833],"type":"Point"}
}