{
  "id": 7568441,
  "type": "Feature",
  "properties": {
    "tgn:hierarchy":[
        "tgn:7568441",
        "tgn:1000004",
        "tgn:7000198",
        "tgn:7016788",
        "tgn:7029392"
    ],
    "tgn:id":7568441,
    "tgn:name:en":"Derajsar",
    "tgn:placetype":[
        "aat:300008347"
    ]
},
  "bbox": [],
  "geometry": {"coordinates":[74.648049,28.060353],"type":"Point"}
}