{
  "id": 1085365,
  "type": "Feature",
  "properties": {
    "tgn:hierarchy":[
        "tgn:1085365",
        "tgn:7468018",
        "tgn:1000004",
        "tgn:1000141",
        "tgn:7029392"
    ],
    "tgn:id":1085365,
    "tgn:name":"Pu-tai",
    "tgn:placetype":[
        "aat:300008347"
    ]
},
  "bbox": [],
  "geometry": {"coordinates":[120.161541,23.377953],"type":"Point"}
}