{
  "id": 2738601,
  "type": "Feature",
  "properties": {
    "tgn:hierarchy":[
        "tgn:2738601",
        "tgn:1000001",
        "tgn:7012149",
        "tgn:2000445",
        "tgn:7007248",
        "tgn:7029392"
    ],
    "tgn:id":2738601,
    "tgn:name":"Unicoi Lake",
    "tgn:placetype":[
        "aat:300006191"
    ]
},
  "bbox": [],
  "geometry": {"coordinates":[-83.5167,34.7167],"type":"Point"}
}