{
  "id": 2298660,
  "type": "Feature",
  "properties": {
    "tgn:hierarchy":[
        "tgn:2298660",
        "tgn:1000001",
        "tgn:7012149",
        "tgn:2002371",
        "tgn:7007923",
        "tgn:7029392"
    ],
    "tgn:id":2298660,
    "tgn:name":"Dry Twin Creek",
    "tgn:placetype":[
        "aat:300008706"
    ]
},
  "bbox": [],
  "geometry": {"coordinates":[-108.4333,42.6333],"type":"Point"}
}