{
  "id": 7385461,
  "type": "Feature",
  "properties": {
    "tgn:hierarchy":[
        "tgn:7385461",
        "tgn:1000001",
        "tgn:7005589",
        "tgn:7005560",
        "tgn:7029392"
    ],
    "tgn:id":7385461,
    "tgn:name":"Palo Alto",
    "tgn:placetype":[
        "aat:300008347"
    ]
},
  "bbox": [],
  "geometry": {"coordinates":[-99.916667,25.383333],"type":"Point"}
}