{
  "id": 2413684,
  "type": "Feature",
  "properties": {
    "tgn:hierarchy":[
        "tgn:2413684",
        "tgn:1000001",
        "tgn:7012149",
        "tgn:7007157",
        "tgn:2000185",
        "tgn:7029392"
    ],
    "tgn:id":2413684,
    "tgn:name":"Irish Creek",
    "tgn:placetype":[
        "aat:300008706"
    ]
},
  "bbox": [],
  "geometry": {"coordinates":[-123.6333,39.0167],"type":"Point"}
}