{
  "id": 7131633,
  "type": "Feature",
  "properties": {
    "tgn:hierarchy":[
        "tgn:7131633",
        "tgn:1000003",
        "tgn:7003677",
        "tgn:7000084",
        "tgn:7029392"
    ],
    "tgn:id":7131633,
    "tgn:name":"Meroder Wald",
    "tgn:placetype":[
        "aat:300008863"
    ]
},
  "bbox": [],
  "geometry": {"coordinates":[6.383333,50.783333],"type":"Point"}
}