{
  "id": 2526280,
  "type": "Feature",
  "properties": {
    "tgn:hierarchy":[
        "tgn:2526280",
        "tgn:1000001",
        "tgn:7012149",
        "tgn:2000494",
        "tgn:7007250",
        "tgn:7029392"
    ],
    "tgn:id":2526280,
    "tgn:name":"Moss Creek",
    "tgn:placetype":[
        "aat:300008706"
    ]
},
  "bbox": [],
  "geometry": {"coordinates":[-115.65,45.0167],"type":"Point"}
}