{
  "id": 2221600,
  "type": "Feature",
  "properties": {
    "tgn:hierarchy":[
        "tgn:2221600",
        "tgn:1000001",
        "tgn:7012149",
        "tgn:1002961",
        "tgn:7007568",
        "tgn:7029392"
    ],
    "tgn:id":2221600,
    "tgn:name":"Carl Mountain",
    "tgn:placetype":[
        "aat:300008798"
    ]
},
  "bbox": [],
  "geometry": {"coordinates":[-74.2333,42.0833],"type":"Point"}
}