{
  "id": 2560090,
  "type": "Feature",
  "properties": {
    "tgn:hierarchy":[
        "tgn:2560090",
        "tgn:1000001",
        "tgn:2001101",
        "tgn:7012149",
        "tgn:7007522",
        "tgn:7029392"
    ],
    "tgn:id":2560090,
    "tgn:name":"Ora Swamp",
    "tgn:placetype":[
        "aat:300008905"
    ]
},
  "bbox": [],
  "geometry": {"coordinates":[-89.55,31.65],"type":"Point"}
}