{
  "id": 2507833,
  "type": "Feature",
  "properties": {
    "tgn:hierarchy":[
        "tgn:2507833",
        "tgn:7002659",
        "tgn:1000001",
        "tgn:7012149",
        "tgn:2000048",
        "tgn:7029392"
    ],
    "tgn:id":2507833,
    "tgn:name":"Mickers Creek",
    "tgn:placetype":[
        "aat:300008706"
    ]
},
  "bbox": [],
  "geometry": {"coordinates":[-88.1333,30.8833],"type":"Point"}
}