{
  "id": 7300413,
  "type": "Feature",
  "properties": {
    "tgn:hierarchy":[
        "tgn:7300413",
        "tgn:7002822",
        "tgn:1001647",
        "tgn:1000003",
        "tgn:1000095",
        "tgn:7029392"
    ],
    "tgn:id":7300413,
    "tgn:name":"Torrecilla del Pinar",
    "tgn:placetype":[
        "aat:300008347"
    ]
},
  "bbox": [],
  "geometry": {"coordinates":[-2.083333,40.833333],"type":"Point"}
}