{
  "id": 2517754,
  "type": "Feature",
  "properties": {
    "tgn:hierarchy":[
        "tgn:2517754",
        "tgn:1000001",
        "tgn:1002477",
        "tgn:7012149",
        "tgn:7007240",
        "tgn:7029392"
    ],
    "tgn:id":2517754,
    "tgn:name":"Mirror Lake",
    "tgn:placetype":[
        "aat:300008680"
    ]
},
  "bbox": [],
  "geometry": {"coordinates":[-81.35,27.2667],"type":"Point"}
}