{
  "id": 2477016,
  "type": "Feature",
  "properties": {
    "tgn:hierarchy":[
        "tgn:2477016",
        "tgn:1000001",
        "tgn:1002194",
        "tgn:7012149",
        "tgn:7007710",
        "tgn:7029392"
    ],
    "tgn:id":2477016,
    "tgn:name":"Lynch Hill",
    "tgn:placetype":[
        "aat:300008798"
    ]
},
  "bbox": [],
  "geometry": {"coordinates":[-76.5333,41.7667],"type":"Point"}
}