{
  "id": 1094429,
  "type": "Feature",
  "properties": {
    "tgn:hierarchy":[
        "tgn:1094429",
        "tgn:7001242",
        "tgn:1000201",
        "tgn:1001368",
        "tgn:7029392"
    ],
    "tgn:id":1094429,
    "tgn:name":"Salim",
    "tgn:placetype":[
        "aat:300008347"
    ]
},
  "bbox": [],
  "geometry": {"coordinates":[28.6667,12.8667],"type":"Point"}
}