{
  "id": 1018161,
  "type": "Feature",
  "properties": {
    "tgn:hierarchy":[
        "tgn:1018161",
        "tgn:1000001",
        "tgn:7005591",
        "tgn:7005560",
        "tgn:7029392"
    ],
    "tgn:id":1018161,
    "tgn:name:es":"San Blas Atempa",
    "tgn:placetype":[
        "aat:300008347"
    ]
},
  "bbox": [],
  "geometry": {"coordinates":[-95.2225,16.326389],"type":"Point"}
}