{
  "id": 1067346,
  "type": "Feature",
  "properties": {
    "tgn:hierarchy":[
        "tgn:1067346",
        "tgn:1000004",
        "tgn:1001390",
        "tgn:1000111",
        "tgn:7029392"
    ],
    "tgn:id":1067346,
    "tgn:name":"Dafanhe",
    "tgn:placetype":[
        "aat:300008347"
    ]
},
  "bbox": [],
  "geometry": {"coordinates":[123.7167,42.2167],"type":"Point"}
}