{
  "id": 7460498,
  "type": "Feature",
  "properties": {
    "tgn:hierarchy":[
        "tgn:7460498",
        "tgn:7002445",
        "tgn:1000003",
        "tgn:7008117",
        "tgn:7008591",
        "tgn:7029392"
    ],
    "tgn:id":7460498,
    "tgn:name:en":"Leadgate",
    "tgn:placetype":[
        "aat:300008347"
    ]
},
  "bbox": [],
  "geometry": {"coordinates":[-2.45,54.783333],"type":"Point"}
}