{
  "id": 1009710,
  "type": "Feature",
  "properties": {
    "tgn:hierarchy":[
        "tgn:1009710",
        "tgn:7002444",
        "tgn:1000003",
        "tgn:7029508",
        "tgn:7008591",
        "tgn:7029392"
    ],
    "tgn:id":1009710,
    "tgn:name:en":"West Burra",
    "tgn:placetype":[
        "aat:300008791"
    ]
},
  "bbox": [],
  "geometry": {"coordinates":[-1.35,60.083333],"type":"Point"}
}