{
  "id": 2256865,
  "type": "Feature",
  "properties": {
    "tgn:hierarchy":[
        "tgn:2256865",
        "tgn:1000001",
        "tgn:2001410",
        "tgn:7012149",
        "tgn:7007526",
        "tgn:7029392"
    ],
    "tgn:id":2256865,
    "tgn:name":"Corkscrew Canyon",
    "tgn:placetype":[
        "aat:300008761"
    ]
},
  "bbox": [],
  "geometry": {"coordinates":[-115.25,36.4667],"type":"Point"}
}