{
  "id": 7128491,
  "type": "Feature",
  "properties": {
    "tgn:hierarchy":[
        "tgn:7128491",
        "tgn:1000003",
        "tgn:7003688",
        "tgn:7000084",
        "tgn:7029392"
    ],
    "tgn:id":7128491,
    "tgn:name":"Niehof",
    "tgn:placetype":[
        "aat:300000206"
    ]
},
  "bbox": [],
  "geometry": {"coordinates":[10.966667,54.183333],"type":"Point"}
}