{
  "id": 1011267,
  "type": "Feature",
  "properties": {
    "tgn:hierarchy":[
        "tgn:1011267",
        "tgn:1001641",
        "tgn:1000003",
        "tgn:7003121",
        "tgn:1000080",
        "tgn:7003508",
        "tgn:7029392"
    ],
    "tgn:id":1011267,
    "tgn:name":"Sperone, Capo",
    "tgn:placetype":[
        "aat:300008850"
    ]
},
  "bbox": [],
  "geometry": {"coordinates":[8.416667,38.95],"type":"Point"}
}