{
  "id": 7568252,
  "type": "Feature",
  "properties": {
    "tgn:hierarchy":[
        "tgn:7568252",
        "tgn:1000004",
        "tgn:7000198",
        "tgn:7016788",
        "tgn:7029392"
    ],
    "tgn:id":7568252,
    "tgn:name:en":"N\u0101sera",
    "tgn:placetype":[
        "aat:300008347"
    ]
},
  "bbox": [],
  "geometry": {"coordinates":[75.502811,25.00692],"type":"Point"}
}