<<<<<<< HEAD
{
  "id": 7022857,
  "type": "Feature",
  "properties": {
    "tgn:hierarchy":[
        "tgn:7022857",
        "tgn:1000001",
        "tgn:7012149",
        "tgn:7007827",
        "tgn:7029392"
    ],
    "tgn:id":7022857,
    "tgn:name":"Duck Fork Reservoir",
    "tgn:placetype":[
        "aat:300006191"
    ]
},
  "bbox": [],
  "geometry": {"coordinates":[-111.4333,39.1667],"type":"Point"}
}
=======
{"geometry":{"type":"Point","coordinates":[-111.433300,39.166700]},"type":"Feature","properties":{"hierarchy":["tgn:7022857","tgn:1000001","tgn:7012149","tgn:7007827","tgn:7029392"],"placetype":["aat:300006191"],"id":7022857,"name:xx":"Duck Fork Reservoir"}}
>>>>>>> 03f74aca74312dbeaf24d7e61306dd6a786dc3d0
