{
  "id": 7022857,
  "type": "Feature",
  "properties": {
    "tgn:hierarchy":[
        "tgn:7022857",
        "tgn:1000001",
        "tgn:7012149",
        "tgn:7007827",
        "tgn:7029392"
    ],
    "tgn:id":7022857,
    "tgn:name":"Duck Fork Reservoir",
    "tgn:placetype":[
        "aat:300006191"
    ]
},
  "bbox": [],
  "geometry": {"coordinates":[-111.4333,39.1667],"type":"Point"}
}