{
  "id": 2592916,
  "type": "Feature",
  "properties": {
    "tgn:hierarchy":[
        "tgn:2592916",
        "tgn:1000001",
        "tgn:7012149",
        "tgn:2002174",
        "tgn:7007919",
        "tgn:7029392"
    ],
    "tgn:id":2592916,
    "tgn:name":"Poplar Branch",
    "tgn:placetype":[
        "aat:300008699"
    ]
},
  "bbox": [],
  "geometry": {"coordinates":[-80.4667,37.0333],"type":"Point"}
}