{
  "id": 7591276,
  "type": "Feature",
  "properties": {
    "tgn:hierarchy":[
        "tgn:7591276",
        "tgn:1000004",
        "tgn:7000198",
        "tgn:7000799",
        "tgn:7029392"
    ],
    "tgn:id":7591276,
    "tgn:name:en":"Pal\u0101tan",
    "tgn:placetype":[
        "aat:300008347"
    ]
},
  "bbox": [],
  "geometry": {"coordinates":[74.447786,32.842018],"type":"Point"}
}