<<<<<<< HEAD
{
  "id": 2769087,
  "type": "Feature",
  "properties": {
    "tgn:hierarchy":[
        "tgn:2769087",
        "tgn:7006450",
        "tgn:1000001",
        "tgn:7012149",
        "tgn:7029392"
    ],
    "tgn:id":2769087,
    "tgn:name":"Whittier Glacier",
    "tgn:placetype":[
        "aat:300008835"
    ]
},
  "bbox": [],
  "geometry": {"coordinates":[-135.8667,58.7],"type":"Point"}
}
=======
{"geometry":{"type":"Point","coordinates":[-135.866700,58.700000]},"type":"Feature","properties":{"hierarchy":["tgn:2769087","tgn:7006450","tgn:1000001","tgn:7012149","tgn:7029392"],"placetype":["aat:300008835"],"id":2769087,"name:xx":"Whittier Glacier"}}
>>>>>>> 03f74aca74312dbeaf24d7e61306dd6a786dc3d0
