{
  "id": 1128000,
  "type": "Feature",
  "properties": {
    "tgn:hierarchy":[
        "tgn:1128000",
        "tgn:1000001",
        "tgn:7012149",
        "tgn:7007248",
        "tgn:7029392"
    ],
    "tgn:id":1128000,
    "tgn:name":"Ocmulgee",
    "tgn:placetype":[
        "aat:300008707"
    ]
},
  "bbox": [],
  "geometry": {"coordinates":[-83.8333,33.3167],"type":"Point"}
}