{
  "id": 1098868,
  "type": "Feature",
  "properties": {
    "tgn:hierarchy":[
        "tgn:1098868",
        "tgn:7016670",
        "tgn:1008380",
        "tgn:1000226",
        "tgn:1000006",
        "tgn:7029392"
    ],
    "tgn:id":1098868,
    "tgn:name:en":"Bay View",
    "tgn:placetype":[
        "aat:300008347"
    ]
},
  "bbox": [],
  "geometry": {"coordinates":[176.883333,-39.416667],"type":"Point"}
}