{
  "id": 2146616,
  "type": "Feature",
  "properties": {
    "tgn:hierarchy":[
        "tgn:2146616",
        "tgn:1000001",
        "tgn:7020676",
        "tgn:7012149",
        "tgn:7007256",
        "tgn:7029392"
    ],
    "tgn:id":2146616,
    "tgn:name":"Bancroft Canal",
    "tgn:placetype":[
        "aat:300006075"
    ]
},
  "bbox": [],
  "geometry": {"coordinates":[-93.5667,30.0167],"type":"Point"}
}