{
  "id": 7502091,
  "type": "Feature",
  "properties": {
    "tgn:hierarchy":[
        "tgn:7502091",
        "tgn:1000004",
        "tgn:7001009",
        "tgn:1000141",
        "tgn:7029392"
    ],
    "tgn:id":7502091,
    "tgn:name":"Dengxinku",
    "tgn:placetype":[
        "aat:300008347"
    ]
},
  "bbox": [],
  "geometry": {"coordinates":[120.852823,24.107719],"type":"Point"}
}