{
  "id": 7585081,
  "type": "Feature",
  "properties": {
    "tgn:hierarchy":[
        "tgn:7585081",
        "tgn:1000004",
        "tgn:7000198",
        "tgn:1001894",
        "tgn:7029392"
    ],
    "tgn:id":7585081,
    "tgn:name:en":"Chhipari\u0101khera",
    "tgn:placetype":[
        "aat:300167671"
    ]
},
  "bbox": [],
  "geometry": {"coordinates":[78.956231,24.651973],"type":"Point"}
}