{
  "id": 7397328,
  "type": "Feature",
  "properties": {
    "tgn:hierarchy":[
        "tgn:7397328",
        "tgn:1000001",
        "tgn:7005599",
        "tgn:7005560",
        "tgn:7029392"
    ],
    "tgn:id":7397328,
    "tgn:name":"San Sebasti\u00e1n",
    "tgn:placetype":[
        "aat:300008347"
    ]
},
  "bbox": [],
  "geometry": {"coordinates":[-97.533333,21.333333],"type":"Point"}
}