{
  "id": 2346787,
  "type": "Feature",
  "properties": {
    "tgn:hierarchy":[
        "tgn:2346787",
        "tgn:1000001",
        "tgn:2000198",
        "tgn:7012149",
        "tgn:7007158",
        "tgn:7029392"
    ],
    "tgn:id":2346787,
    "tgn:name":"Geer Gulch",
    "tgn:placetype":[
        "aat:300008761"
    ]
},
  "bbox": [],
  "geometry": {"coordinates":[-105.3167,40.1333],"type":"Point"}
}