{
  "id": 2735865,
  "type": "Feature",
  "properties": {
    "tgn:hierarchy":[
        "tgn:2735865",
        "tgn:1000001",
        "tgn:7012149",
        "tgn:2000277",
        "tgn:7007240",
        "tgn:7029392"
    ],
    "tgn:id":2735865,
    "tgn:name":"Twin Lakes",
    "tgn:placetype":[
        "aat:300008680"
    ]
},
  "bbox": [],
  "geometry": {"coordinates":[-84.1333,30.3667],"type":"Point"}
}