{
  "id": 7439994,
  "type": "Feature",
  "properties": {
    "tgn:hierarchy":[
        "tgn:7439994",
        "tgn:1000001",
        "tgn:7005591",
        "tgn:7005560",
        "tgn:7029392"
    ],
    "tgn:id":7439994,
    "tgn:name":"Santa Mar\u00eda Ipalapa",
    "tgn:placetype":[
        "aat:300008347"
    ]
},
  "bbox": [],
  "geometry": {"coordinates":[-98.033333,16.633333],"type":"Point"}
}