{
  "id": 7130626,
  "type": "Feature",
  "properties": {
    "tgn:hierarchy":[
        "tgn:7130626",
        "tgn:1000003",
        "tgn:7003677",
        "tgn:7000084",
        "tgn:7029392"
    ],
    "tgn:id":7130626,
    "tgn:name":"Mittelsorpe",
    "tgn:placetype":[
        "aat:300008347"
    ]
},
  "bbox": [],
  "geometry": {"coordinates":[8.366667,51.183333],"type":"Point"}
}