{
  "id": 2137837,
  "type": "Feature",
  "properties": {
    "tgn:hierarchy":[
        "tgn:2137837",
        "tgn:1000001",
        "tgn:7012149",
        "tgn:2002004",
        "tgn:7007826",
        "tgn:7029392"
    ],
    "tgn:id":2137837,
    "tgn:name":"Arrington Tank",
    "tgn:placetype":[
        "aat:300006191"
    ]
},
  "bbox": [],
  "geometry": {"coordinates":[-101.2167,32.1833],"type":"Point"}
}