{
  "id": 7181226,
  "type": "Feature",
  "properties": {
    "tgn:hierarchy":[
        "tgn:7181226",
        "tgn:1000003",
        "tgn:7003688",
        "tgn:7000084",
        "tgn:7029392"
    ],
    "tgn:id":7181226,
    "tgn:name":"Garstedt",
    "tgn:placetype":[
        "aat:300000745"
    ]
},
  "bbox": [],
  "geometry": {"coordinates":[9.966667,53.683333],"type":"Point"}
}