{
  "id": 2431247,
  "type": "Feature",
  "properties": {
    "tgn:hierarchy":[
        "tgn:2431247",
        "tgn:1002483",
        "tgn:7019080",
        "tgn:1000001",
        "tgn:7012149",
        "tgn:7007249",
        "tgn:7029392"
    ],
    "tgn:id":2431247,
    "tgn:name":"Kapalama Stream",
    "tgn:placetype":[
        "aat:300008699"
    ]
},
  "bbox": [],
  "geometry": {"coordinates":[-157.8167,21.35],"type":"Point"}
}