{
  "id": 1104187,
  "type": "Feature",
  "properties": {
    "tgn:hierarchy":[
        "tgn:1104187",
        "tgn:7003005",
        "tgn:7003014",
        "tgn:1000003",
        "tgn:1000080",
        "tgn:7029392"
    ],
    "tgn:id":1104187,
    "tgn:name":"Cervati, Monte",
    "tgn:placetype":[
        "aat:300008795"
    ]
},
  "bbox": [],
  "geometry": {"coordinates":[15.483333,40.283333],"type":"Point"}
}