{
  "id": 1099873,
  "type": "Feature",
  "properties": {
    "tgn:hierarchy":[
        "tgn:1099873",
        "tgn:7003138",
        "tgn:1000003",
        "tgn:7003080",
        "tgn:1000080",
        "tgn:7029392"
    ],
    "tgn:id":1099873,
    "tgn:name":"Porto di Traiano, Necropoli del",
    "tgn:placetype":[
        "aat:300387004",
        "aat:300000372",
        "aat:300008057"
    ]
},
  "bbox": [],
  "geometry": {"coordinates":[12.2667,41.7667],"type":"Point"}
}