{
  "id": 2682635,
  "type": "Feature",
  "properties": {
    "tgn:hierarchy":[
        "tgn:2682635",
        "tgn:1000001",
        "tgn:7012149",
        "tgn:2002183",
        "tgn:7007919",
        "tgn:7029392"
    ],
    "tgn:id":2682635,
    "tgn:name":"Southerns Cave Number 3",
    "tgn:placetype":[
        "aat:300008746"
    ]
},
  "bbox": [],
  "geometry": {"coordinates":[-80.6833,37.05],"type":"Point"}
}