{
  "id": 7057084,
  "type": "Feature",
  "properties": {
    "tgn:hierarchy":[
        "tgn:7057084",
        "tgn:7003163",
        "tgn:1000003",
        "tgn:7009760",
        "tgn:1000080",
        "tgn:7029392"
    ],
    "tgn:id":7057084,
    "tgn:name":"Barbiallo",
    "tgn:placetype":[
        "aat:300008347"
    ]
},
  "bbox": [],
  "geometry": {"coordinates":[10.883333,43.616667],"type":"Point"}
}