{
  "id": 7199883,
  "type": "Feature",
  "properties": {
    "tgn:hierarchy":[
        "tgn:7199883",
        "tgn:1000003",
        "tgn:7003676",
        "tgn:7000084",
        "tgn:7029392"
    ],
    "tgn:id":7199883,
    "tgn:name":"Dreibergen",
    "tgn:placetype":[
        "aat:300008347"
    ]
},
  "bbox": [],
  "geometry": {"coordinates":[8.016667,53.216667],"type":"Point"}
}