{
  "id": 7558595,
  "type": "Feature",
  "properties": {
    "tgn:hierarchy":[
        "tgn:7558595",
        "tgn:1001828",
        "tgn:1000004",
        "tgn:7000198",
        "tgn:7029392"
    ],
    "tgn:id":7558595,
    "tgn:name:en":"R\u0101yavaram",
    "tgn:placetype":[
        "aat:300008347"
    ]
},
  "bbox": [],
  "geometry": {"coordinates":[79.316667,15.716667],"type":"Point"}
}