{
  "id": 2273413,
  "type": "Feature",
  "properties": {
    "tgn:hierarchy":[
        "tgn:2273413",
        "tgn:1000001",
        "tgn:7012149",
        "tgn:2002186",
        "tgn:7007919",
        "tgn:7029392"
    ],
    "tgn:id":2273413,
    "tgn:name":"Cypress Falls Caves",
    "tgn:placetype":[
        "aat:300008746"
    ]
},
  "bbox": [],
  "geometry": {"coordinates":[-79.2333,37.8833],"type":"Point"}
}