{
  "id": 2577851,
  "type": "Feature",
  "properties": {
    "tgn:hierarchy":[
        "tgn:2577851",
        "tgn:1000001",
        "tgn:7012149",
        "tgn:7013855",
        "tgn:7007251",
        "tgn:7029392"
    ],
    "tgn:id":2577851,
    "tgn:name":"Petite Lake",
    "tgn:placetype":[
        "aat:300008680"
    ]
},
  "bbox": [],
  "geometry": {"coordinates":[-88.1167,42.4167],"type":"Point"}
}