{
  "id": 2686750,
  "type": "Feature",
  "properties": {
    "tgn:hierarchy":[
        "tgn:2686750",
        "tgn:1000001",
        "tgn:7012149",
        "tgn:2002327",
        "tgn:7007922",
        "tgn:7029392"
    ],
    "tgn:id":2686750,
    "tgn:name":"Spring Creek",
    "tgn:placetype":[
        "aat:300008706"
    ]
},
  "bbox": [],
  "geometry": {"coordinates":[-90.45,46.25],"type":"Point"}
}