{
  "id": 2423739,
  "type": "Feature",
  "properties": {
    "tgn:hierarchy":[
        "tgn:2423739",
        "tgn:1000001",
        "tgn:7012149",
        "tgn:2002043",
        "tgn:7007826",
        "tgn:7029392"
    ],
    "tgn:id":2423739,
    "tgn:name":"John Tang Tank",
    "tgn:placetype":[
        "aat:300006191"
    ]
},
  "bbox": [],
  "geometry": {"coordinates":[-100.9167,32.1167],"type":"Point"}
}