{
  "id": 2655428,
  "type": "Feature",
  "properties": {
    "tgn:hierarchy":[
        "tgn:2655428",
        "tgn:1000001",
        "tgn:7012149",
        "tgn:1002596",
        "tgn:7007706",
        "tgn:7029392"
    ],
    "tgn:id":2655428,
    "tgn:name":"Sharon Valley",
    "tgn:placetype":[
        "aat:300008761"
    ]
},
  "bbox": [],
  "geometry": {"coordinates":[-82.4833,40.0833],"type":"Point"}
}