{
  "id": 2450319,
  "type": "Feature",
  "properties": {
    "tgn:hierarchy":[
        "tgn:2450319",
        "tgn:1000001",
        "tgn:7013368",
        "tgn:7012149",
        "tgn:7007709",
        "tgn:7029392"
    ],
    "tgn:id":2450319,
    "tgn:name":"Liniar Bay",
    "tgn:placetype":[
        "aat:300132316"
    ]
},
  "bbox": [],
  "geometry": {"coordinates":[-76.5833,35.4167],"type":"Point"}
}