{
  "id": 7294611,
  "type": "Feature",
  "properties": {
    "tgn:hierarchy":[
        "tgn:7294611",
        "tgn:7008912",
        "tgn:7030216",
        "tgn:1000003",
        "tgn:1000095",
        "tgn:7029392"
    ],
    "tgn:id":7294611,
    "tgn:name":"Vallfogona de Balaguer",
    "tgn:placetype":[
        "aat:300008347"
    ]
},
  "bbox": [],
  "geometry": {"coordinates":[0.813849,41.752114],"type":"Point"}
}