{
  "id": 7395605,
  "type": "Feature",
  "properties": {
    "tgn:hierarchy":[
        "tgn:7395605",
        "tgn:1000001",
        "tgn:1001893",
        "tgn:7005560",
        "tgn:7029392"
    ],
    "tgn:id":7395605,
    "tgn:name":"San Dieguito Xochimanca",
    "tgn:placetype":[
        "aat:300008347"
    ]
},
  "bbox": [],
  "geometry": {"coordinates":[-98.816667,19.483333],"type":"Point"}
}