{
  "id": 7593935,
  "type": "Feature",
  "properties": {
    "tgn:hierarchy":[
        "tgn:7593935",
        "tgn:1000004",
        "tgn:7593934",
        "tgn:7029392"
    ],
    "tgn:id":7593935,
    "tgn:name":"Dhekelia",
    "tgn:placetype":[
        "aat:300164060"
    ]
},
  "bbox": [],
  "geometry": {"coordinates":[33.745,35.001],"type":"Point"}
}