{
  "id": 2083259,
  "type": "Feature",
  "properties": {
    "tgn:hierarchy":[
        "tgn:2083259",
        "tgn:1000001",
        "tgn:7012149",
        "tgn:2001674",
        "tgn:7007707",
        "tgn:7029392"
    ],
    "tgn:id":2083259,
    "tgn:name":"Gansel",
    "tgn:placetype":[
        "aat:300387016"
    ]
},
  "bbox": [],
  "geometry": {"coordinates":[-97.3667,36.2667],"type":"Point"}
}