{
  "id": 2072557,
  "type": "Feature",
  "properties": {
    "tgn:hierarchy":[
        "tgn:2072557",
        "tgn:1000001",
        "tgn:7012149",
        "tgn:1002708",
        "tgn:7007568",
        "tgn:7029392"
    ],
    "tgn:id":2072557,
    "tgn:name":"Stewart Manor",
    "tgn:placetype":[
        "aat:300008347"
    ]
},
  "bbox": [],
  "geometry": {"coordinates":[-73.6833,40.7167],"type":"Point"}
}