{
  "id": 7094955,
  "type": "Feature",
  "properties": {
    "tgn:hierarchy":[
        "tgn:7094955",
        "tgn:1000003",
        "tgn:7003685",
        "tgn:7000084",
        "tgn:7029392"
    ],
    "tgn:id":7094955,
    "tgn:name":"Sch\u00f6ne H\u00f6he",
    "tgn:placetype":[
        "aat:300008777"
    ]
},
  "bbox": [],
  "geometry": {"coordinates":[13.983333,51.033333],"type":"Point"}
}