{
  "id": 2244372,
  "type": "Feature",
  "properties": {
    "tgn:hierarchy":[
        "tgn:2244372",
        "tgn:1000001",
        "tgn:7012149",
        "tgn:1002402",
        "tgn:7007523",
        "tgn:7029392"
    ],
    "tgn:id":2244372,
    "tgn:name":"Clifty Creek",
    "tgn:placetype":[
        "aat:300008706"
    ]
},
  "bbox": [],
  "geometry": {"coordinates":[-91.4167,38.5333],"type":"Point"}
}