{
  "id": 7050383,
  "type": "Feature",
  "properties": {
    "tgn:hierarchy":[
        "tgn:7050383",
        "tgn:1001730",
        "tgn:1000003",
        "tgn:7003121",
        "tgn:1000080",
        "tgn:7029392"
    ],
    "tgn:id":7050383,
    "tgn:name":"Norbello, Monte de",
    "tgn:placetype":[
        "aat:300008795"
    ]
},
  "bbox": [],
  "geometry": {"coordinates":[8.75,40.166667],"type":"Point"}
}