{
  "id": 2324765,
  "type": "Feature",
  "properties": {
    "tgn:hierarchy":[
        "tgn:2324765",
        "tgn:1000001",
        "tgn:7019982",
        "tgn:7012149",
        "tgn:7007517",
        "tgn:7029392"
    ],
    "tgn:id":2324765,
    "tgn:name":"Fenton Mountain",
    "tgn:placetype":[
        "aat:300008798"
    ]
},
  "bbox": [],
  "geometry": {"coordinates":[-72.25,42.1333],"type":"Point"}
}