{
  "id": 2111297,
  "type": "Feature",
  "properties": {
    "tgn:hierarchy":[
        "tgn:2111297",
        "tgn:1000001",
        "tgn:7012149",
        "tgn:2002164",
        "tgn:7007919",
        "tgn:7029392"
    ],
    "tgn:id":2111297,
    "tgn:name":"Comers Rock",
    "tgn:placetype":[
        "aat:300008347"
    ]
},
  "bbox": [],
  "geometry": {"coordinates":[-81.2333,36.7333],"type":"Point"}
}