{
  "id": 7236761,
  "type": "Feature",
  "properties": {
    "tgn:hierarchy":[
        "tgn:7236761",
        "tgn:7011330",
        "tgn:7002674",
        "tgn:1000003",
        "tgn:1000074",
        "tgn:7029392"
    ],
    "tgn:id":7236761,
    "tgn:name":"\u00c1yios Is\u00eddhoros",
    "tgn:placetype":[
        "aat:300008347"
    ]
},
  "bbox": [],
  "geometry": {"coordinates":[27.85,36.15],"type":"Point"}
}