{
  "id": 7005559,
  "type": "Feature",
  "properties": {
    "tgn:hierarchy":[
        "tgn:7005559",
        "tgn:1000001",
        "tgn:7005556",
        "tgn:7029392"
    ],
    "tgn:id":7005559,
    "tgn:name":"Surrey",
    "tgn:placetype":[
        "aat:300000771"
    ]
},
  "bbox": [],
  "geometry": {"coordinates":[-76.566,18.083],"type":"Point"}
}