{
  "id": 7166373,
  "type": "Feature",
  "properties": {
    "tgn:hierarchy":[
        "tgn:7166373",
        "tgn:1000003",
        "tgn:7000094",
        "tgn:7000084",
        "tgn:7029392"
    ],
    "tgn:id":7166373,
    "tgn:name":"Waldw\u00e4rter Heideholz",
    "tgn:placetype":[
        "aat:300004792"
    ]
},
  "bbox": [],
  "geometry": {"coordinates":[13.366667,53.75],"type":"Point"}
}