{
  "id": 2545255,
  "type": "Feature",
  "properties": {
    "tgn:hierarchy":[
        "tgn:2545255",
        "tgn:2000456",
        "tgn:1000001",
        "tgn:7012149",
        "tgn:7007250",
        "tgn:7029392"
    ],
    "tgn:id":2545255,
    "tgn:name":"North Fork Alder Creek",
    "tgn:placetype":[
        "aat:300008706"
    ]
},
  "bbox": [],
  "geometry": {"coordinates":[-116.7667,47.1667],"type":"Point"}
}