{
  "id": 7384341,
  "type": "Feature",
  "properties": {
    "tgn:hierarchy":[
        "tgn:7384341",
        "tgn:1000001",
        "tgn:7005597",
        "tgn:7005560",
        "tgn:7029392"
    ],
    "tgn:id":7384341,
    "tgn:name":"Pailas",
    "tgn:placetype":[
        "aat:300387033"
    ]
},
  "bbox": [],
  "geometry": {"coordinates":[-98.166667,23.416667],"type":"Point"}
}