{
  "id": 2595885,
  "type": "Feature",
  "properties": {
    "tgn:hierarchy":[
        "tgn:2595885",
        "tgn:1000001",
        "tgn:7012149",
        "tgn:7007826",
        "tgn:7029392"
    ],
    "tgn:id":2595885,
    "tgn:name":"Pottawatomie Creek",
    "tgn:placetype":[
        "aat:300008706"
    ]
},
  "bbox": [],
  "geometry": {"coordinates":[-95.8833,32.35],"type":"Point"}
}