{
  "id": 7014122,
  "type": "Feature",
  "properties": {
    "tgn:hierarchy":[
        "tgn:7014122",
        "tgn:1000001",
        "tgn:7012149",
        "tgn:2001716",
        "tgn:7007708",
        "tgn:7029392"
    ],
    "tgn:id":7014122,
    "tgn:name":"Eugene",
    "tgn:placetype":[
        "aat:300008347",
        "aat:300008416",
        "aat:300008389",
        "aat:300387308",
        "aat:300005135",
        "aat:300264742",
        "aat:300387270",
        "aat:300387302",
        "aat:300387291"
    ]
},
  "bbox": [],
  "geometry": {"coordinates":[-123.0833,44.05],"type":"Point"}
}