{
  "id": 2681193,
  "type": "Feature",
  "properties": {
    "tgn:hierarchy":[
        "tgn:2681193",
        "tgn:1000001",
        "tgn:2001416",
        "tgn:7012149",
        "tgn:7007526",
        "tgn:7029392"
    ],
    "tgn:id":2681193,
    "tgn:name":"South Mud Spring",
    "tgn:placetype":[
        "aat:300008697"
    ]
},
  "bbox": [],
  "geometry": {"coordinates":[-114.6833,38.2833],"type":"Point"}
}