{
  "id": 2347020,
  "type": "Feature",
  "properties": {
    "tgn:hierarchy":[
        "tgn:2347020",
        "tgn:1000001",
        "tgn:7012149",
        "tgn:2001491",
        "tgn:7007709",
        "tgn:7029392"
    ],
    "tgn:id":2347020,
    "tgn:name":"Genele, Lake",
    "tgn:placetype":[
        "aat:300006191"
    ]
},
  "bbox": [],
  "geometry": {"coordinates":[-77.95,35.15],"type":"Point"}
}