<<<<<<< HEAD
{
  "id": 7475322,
  "type": "Feature",
  "properties": {
    "tgn:hierarchy":[
        "tgn:7475322",
        "tgn:7468018",
        "tgn:1000004",
        "tgn:1000141",
        "tgn:7029392"
    ],
    "tgn:id":7475322,
    "tgn:name":"Zaozhi",
    "tgn:placetype":[
        "aat:300008347"
    ]
},
  "bbox": [],
  "geometry": {"coordinates":[120.440252,23.622479],"type":"Point"}
}
=======
{"geometry":{"type":"Point","coordinates":[120.440252,23.622479]},"type":"Feature","properties":{"hierarchy":["tgn:7475322","tgn:7468018","tgn:1000004","tgn:1000141","tgn:7029392"],"placetype":["aat:300008347"],"id":7475322,"name:xx":"Zaozhi"}}
>>>>>>> 03f74aca74312dbeaf24d7e61306dd6a786dc3d0
