{
  "id": 2449074,
  "type": "Feature",
  "properties": {
    "tgn:hierarchy":[
        "tgn:2449074",
        "tgn:1000001",
        "tgn:2001431",
        "tgn:7012149",
        "tgn:7007566",
        "tgn:7029392"
    ],
    "tgn:id":2449074,
    "tgn:name":"Limekiln Canyon",
    "tgn:placetype":[
        "aat:300008761"
    ]
},
  "bbox": [],
  "geometry": {"coordinates":[-108.0333,35.15],"type":"Point"}
}