{
  "id": 2546194,
  "type": "Feature",
  "properties": {
    "tgn:hierarchy":[
        "tgn:2546194",
        "tgn:1000001",
        "tgn:7012149",
        "tgn:1002990",
        "tgn:7007708",
        "tgn:7029392"
    ],
    "tgn:id":2546194,
    "tgn:name":"North Fork Fivemile Creek",
    "tgn:placetype":[
        "aat:300008706"
    ]
},
  "bbox": [],
  "geometry": {"coordinates":[-121.4333,45.45],"type":"Point"}
}