<<<<<<< HEAD
{
  "id": 2158227,
  "type": "Feature",
  "properties": {
    "tgn:hierarchy":[
        "tgn:2158227",
        "tgn:1000001",
        "tgn:7012149",
        "tgn:2000358",
        "tgn:7007248",
        "tgn:7029392"
    ],
    "tgn:id":2158227,
    "tgn:name":"Beaver Ruin Creek",
    "tgn:placetype":[
        "aat:300008706"
    ]
},
  "bbox": [],
  "geometry": {"coordinates":[-84.2,33.9333],"type":"Point"}
}
=======
{"geometry":{"type":"Point","coordinates":[-84.200000,33.933300]},"type":"Feature","properties":{"hierarchy":["tgn:2158227","tgn:1000001","tgn:7012149","tgn:2000358","tgn:7007248","tgn:7029392"],"placetype":["aat:300008706"],"id":2158227,"name:xx":"Beaver Ruin Creek"}}
>>>>>>> 03f74aca74312dbeaf24d7e61306dd6a786dc3d0
