{
  "id": 7038057,
  "type": "Feature",
  "properties": {
    "tgn:hierarchy":[
        "tgn:7038057",
        "tgn:1003460",
        "tgn:1000003",
        "tgn:7009760",
        "tgn:1000080",
        "tgn:7029392"
    ],
    "tgn:id":7038057,
    "tgn:name":"Talamone, Baia di",
    "tgn:placetype":[
        "aat:300132316"
    ]
},
  "bbox": [],
  "geometry": {"coordinates":[11.15,42.55],"type":"Point"}
}