{
  "id": 2217282,
  "type": "Feature",
  "properties": {
    "tgn:hierarchy":[
        "tgn:2217282",
        "tgn:1000001",
        "tgn:7012149",
        "tgn:2002359",
        "tgn:7007922",
        "tgn:7029392"
    ],
    "tgn:id":2217282,
    "tgn:name":"Camp Twelve Lake",
    "tgn:placetype":[
        "aat:300008680"
    ]
},
  "bbox": [],
  "geometry": {"coordinates":[-89.3667,45.9833],"type":"Point"}
}