{
  "id": 7414098,
  "type": "Feature",
  "properties": {
    "tgn:hierarchy":[
        "tgn:7414098",
        "tgn:1000001",
        "tgn:7005596",
        "tgn:7005560",
        "tgn:7029392"
    ],
    "tgn:id":7414098,
    "tgn:name:es":"La Torre",
    "tgn:placetype":[
        "aat:300008347"
    ]
},
  "bbox": [],
  "geometry": {"coordinates":[-91.179167,17.908333],"type":"Point"}
}