{
  "id": 2068372,
  "type": "Feature",
  "properties": {
    "tgn:hierarchy":[
        "tgn:2068372",
        "tgn:1000001",
        "tgn:7012149",
        "tgn:7014287",
        "tgn:7007568",
        "tgn:7029392"
    ],
    "tgn:id":2068372,
    "tgn:name":"Cassville",
    "tgn:placetype":[
        "aat:300008347"
    ]
},
  "bbox": [],
  "geometry": {"coordinates":[-75.25,42.9333],"type":"Point"}
}