{
  "id": 1133165,
  "type": "Feature",
  "properties": {
    "tgn:hierarchy":[
        "tgn:1133165",
        "tgn:1000001",
        "tgn:1002313",
        "tgn:7012149",
        "tgn:7007706",
        "tgn:7029392"
    ],
    "tgn:id":1133165,
    "tgn:name":"Euclid Creek",
    "tgn:placetype":[
        "aat:300008706"
    ]
},
  "bbox": [],
  "geometry": {"coordinates":[-81.4833,41.4833],"type":"Point"}
}