<<<<<<< HEAD
{
  "id": 2151084,
  "type": "Feature",
  "properties": {
    "tgn:hierarchy":[
        "tgn:2151084",
        "tgn:1000001",
        "tgn:7012149",
        "tgn:2002376",
        "tgn:7007923",
        "tgn:7029392"
    ],
    "tgn:id":2151084,
    "tgn:name":"Bastow, Lake",
    "tgn:placetype":[
        "aat:300008680"
    ]
},
  "bbox": [],
  "geometry": {"coordinates":[-110.75,42.7833],"type":"Point"}
}
=======
{"geometry":{"type":"Point","coordinates":[-110.750000,42.783300]},"type":"Feature","properties":{"hierarchy":["tgn:2151084","tgn:1000001","tgn:7012149","tgn:2002376","tgn:7007923","tgn:7029392"],"placetype":["aat:300008680"],"id":2151084,"name:xx":"Bastow, Lake"}}
>>>>>>> 03f74aca74312dbeaf24d7e61306dd6a786dc3d0
