{
  "id": 7582221,
  "type": "Feature",
  "properties": {
    "tgn:hierarchy":[
        "tgn:7582221",
        "tgn:1000004",
        "tgn:7000198",
        "tgn:7016788",
        "tgn:7029392"
    ],
    "tgn:id":7582221,
    "tgn:name:en":"Kithal\u0101na Johra",
    "tgn:placetype":[
        "aat:300008688"
    ]
},
  "bbox": [],
  "geometry": {"coordinates":[75.574241,28.440836],"type":"Point"}
}