{
  "id": 7590260,
  "type": "Feature",
  "properties": {
    "tgn:hierarchy":[
        "tgn:7590260",
        "tgn:1000004",
        "tgn:7000198",
        "tgn:7000799",
        "tgn:7029392"
    ],
    "tgn:id":7590260,
    "tgn:name:en":"Chanpura P\u0101\u012bn",
    "tgn:placetype":[
        "aat:300008347"
    ]
},
  "bbox": [],
  "geometry": {"coordinates":[73.819444,34.373611],"type":"Point"}
}