{
  "id": 2658065,
  "type": "Feature",
  "properties": {
    "tgn:hierarchy":[
        "tgn:2658065",
        "tgn:1000001",
        "tgn:7012149",
        "tgn:2000846",
        "tgn:7007255",
        "tgn:7029392"
    ],
    "tgn:id":2658065,
    "tgn:name":"Shelly Creek",
    "tgn:placetype":[
        "aat:300008706"
    ]
},
  "bbox": [],
  "geometry": {"coordinates":[-87.9167,36.9167],"type":"Point"}
}