{
  "id": 2448683,
  "type": "Feature",
  "properties": {
    "tgn:hierarchy":[
        "tgn:2448683",
        "tgn:1000001",
        "tgn:7012149",
        "tgn:1003038",
        "tgn:7007517",
        "tgn:7029392"
    ],
    "tgn:id":2448683,
    "tgn:name":"Lily Pond",
    "tgn:placetype":[
        "aat:300008680"
    ]
},
  "bbox": [],
  "geometry": {"coordinates":[-71.85,42.0333],"type":"Point"}
}