{
  "id": 7555771,
  "type": "Feature",
  "properties": {
    "tgn:hierarchy":[
        "tgn:7555771",
        "tgn:1000004",
        "tgn:7000198",
        "tgn:1001894",
        "tgn:7029392"
    ],
    "tgn:id":7555771,
    "tgn:name:en":"Maneri",
    "tgn:placetype":[
        "aat:300008347"
    ]
},
  "bbox": [],
  "geometry": {"coordinates":[80.240885,23.109232],"type":"Point"}
}