{
  "id": 2203517,
  "type": "Feature",
  "properties": {
    "tgn:hierarchy":[
        "tgn:2203517",
        "tgn:1000001",
        "tgn:7012149",
        "tgn:2001527",
        "tgn:7007709",
        "tgn:7029392"
    ],
    "tgn:id":2203517,
    "tgn:name":"Buckle Swamp",
    "tgn:placetype":[
        "aat:300008905"
    ]
},
  "bbox": [],
  "geometry": {"coordinates":[-78.1667,34.3833],"type":"Point"}
}