{
  "id": 2207056,
  "type": "Feature",
  "properties": {
    "tgn:hierarchy":[
        "tgn:2207056",
        "tgn:1000001",
        "tgn:7012149",
        "tgn:2000818",
        "tgn:7007255",
        "tgn:7029392"
    ],
    "tgn:id":2207056,
    "tgn:name":"Buncomb Branch",
    "tgn:placetype":[
        "aat:300008699"
    ]
},
  "bbox": [],
  "geometry": {"coordinates":[-84.4667,36.6667],"type":"Point"}
}