{
  "id": 7470560,
  "type": "Feature",
  "properties": {
    "tgn:hierarchy":[
        "tgn:7470560",
        "tgn:1000004",
        "tgn:7467799",
        "tgn:1000141",
        "tgn:7029392"
    ],
    "tgn:id":7470560,
    "tgn:name":"Hemei Zhen",
    "tgn:placetype":[
        "aat:300387173"
    ]
},
  "bbox": [],
  "geometry": {"coordinates":[120.4975,24.112222],"type":"Point"}
}