{
  "id": 7032653,
  "type": "Feature",
  "properties": {
    "tgn:hierarchy":[
        "tgn:7032653",
        "tgn:7001242",
        "tgn:7016833",
        "tgn:7001336",
        "tgn:7029392"
    ],
    "tgn:id":7032653,
    "tgn:name":"Serabit el-Khadim",
    "tgn:placetype":[
        "aat:300008347",
        "aat:300000810",
        "aat:300167671",
        "aat:300000390"
    ]
},
  "bbox": [],
  "geometry": {"coordinates":[33.457,29.008],"type":"Point"}
}