{
  "id": 2773701,
  "type": "Feature",
  "properties": {
    "tgn:hierarchy":[
        "tgn:2773701",
        "tgn:7002659",
        "tgn:1000001",
        "tgn:7012149",
        "tgn:2000044",
        "tgn:7029392"
    ],
    "tgn:id":2773701,
    "tgn:name":"Willow Bend",
    "tgn:placetype":[
        "aat:300008347"
    ]
},
  "bbox": [],
  "geometry": {"coordinates":[-86.5333,34.6333],"type":"Point"}
}