{
  "id": 2000092,
  "type": "Feature",
  "properties": {
    "tgn:hierarchy":[
        "tgn:2000092",
        "tgn:1000001",
        "tgn:7006451",
        "tgn:7012149",
        "tgn:7029392"
    ],
    "tgn:id":2000092,
    "tgn:name":"Coconino",
    "tgn:placetype":[
        "aat:300387145",
        "aat:300000771"
    ]
},
  "bbox": [],
  "geometry": {"coordinates":[-112.1333,36.0833],"type":"Point"}
}