{
  "id": 7527999,
  "type": "Feature",
  "properties": {
    "tgn:hierarchy":[
        "tgn:7527999",
        "tgn:7001242",
        "tgn:7016833",
        "tgn:7001312",
        "tgn:7029392"
    ],
    "tgn:id":7527999,
    "tgn:name:en":"Sij\u012bn al Kawm",
    "tgn:placetype":[
        "aat:300008347"
    ]
},
  "bbox": [],
  "geometry": {"coordinates":[31.055987,30.908805],"type":"Point"}
}