{
  "id": 2213689,
  "type": "Feature",
  "properties": {
    "tgn:hierarchy":[
        "tgn:2213689",
        "tgn:1000001",
        "tgn:7012149",
        "tgn:2001712",
        "tgn:7007708",
        "tgn:7029392"
    ],
    "tgn:id":2213689,
    "tgn:name":"Cache Creek",
    "tgn:placetype":[
        "aat:300008706"
    ]
},
  "bbox": [],
  "geometry": {"coordinates":[-121.6333,44.7333],"type":"Point"}
}