{
  "id": 7172106,
  "type": "Feature",
  "properties": {
    "tgn:hierarchy":[
        "tgn:7172106",
        "tgn:1000003",
        "tgn:7003682",
        "tgn:7000084",
        "tgn:7029392"
    ],
    "tgn:id":7172106,
    "tgn:name":"Herrenwald",
    "tgn:placetype":[
        "aat:300008863"
    ]
},
  "bbox": [],
  "geometry": {"coordinates":[7.733333,49.216667],"type":"Point"}
}