{
  "id": 7158716,
  "type": "Feature",
  "properties": {
    "tgn:hierarchy":[
        "tgn:7158716",
        "tgn:7003669",
        "tgn:1000003",
        "tgn:7000084",
        "tgn:7029392"
    ],
    "tgn:id":7158716,
    "tgn:name":"H\u00f6henstetten",
    "tgn:placetype":[
        "aat:300008347"
    ]
},
  "bbox": [],
  "geometry": {"coordinates":[12.616667,47.983333],"type":"Point"}
}