{
  "id": 2203420,
  "type": "Feature",
  "properties": {
    "tgn:hierarchy":[
        "tgn:2203420",
        "tgn:1000001",
        "tgn:7012149",
        "tgn:2001534",
        "tgn:7007709",
        "tgn:7029392"
    ],
    "tgn:id":2203420,
    "tgn:name":"Buckhorn Swamp",
    "tgn:placetype":[
        "aat:300008699"
    ]
},
  "bbox": [],
  "geometry": {"coordinates":[-79.0167,34.9167],"type":"Point"}
}