{
  "id": 2738754,
  "type": "Feature",
  "properties": {
    "tgn:hierarchy":[
        "tgn:2738754",
        "tgn:1000001",
        "tgn:1002253",
        "tgn:7012149",
        "tgn:7007251",
        "tgn:7029392"
    ],
    "tgn:id":2738754,
    "tgn:name":"Union Drainage Ditch Number 1",
    "tgn:placetype":[
        "aat:300006075"
    ]
},
  "bbox": [],
  "geometry": {"coordinates":[-88.0833,40.1833],"type":"Point"}
}