{
  "id": 2319616,
  "type": "Feature",
  "properties": {
    "tgn:hierarchy":[
        "tgn:2319616",
        "tgn:1000001",
        "tgn:7012149",
        "tgn:1002298",
        "tgn:7007157",
        "tgn:7029392"
    ],
    "tgn:id":2319616,
    "tgn:name":"Eugene Spring",
    "tgn:placetype":[
        "aat:300008697"
    ]
},
  "bbox": [],
  "geometry": {"coordinates":[-121.95,37.7167],"type":"Point"}
}