{
  "id": 2712486,
  "type": "Feature",
  "properties": {
    "tgn:hierarchy":[
        "tgn:2712486",
        "tgn:1000001",
        "tgn:7006451",
        "tgn:2000092",
        "tgn:7012149",
        "tgn:7029392"
    ],
    "tgn:id":2712486,
    "tgn:name":"Taylor Basin",
    "tgn:placetype":[
        "aat:300386845"
    ]
},
  "bbox": [],
  "geometry": {"coordinates":[-111.9667,34.9833],"type":"Point"}
}