{
  "id": 7449262,
  "type": "Feature",
  "properties": {
    "tgn:hierarchy":[
        "tgn:7449262",
        "tgn:7002444",
        "tgn:1000003",
        "tgn:7008082",
        "tgn:7008591",
        "tgn:7029392"
    ],
    "tgn:id":7449262,
    "tgn:name:en":"Einich, Gleann",
    "tgn:placetype":[
        "aat:300008761"
    ]
},
  "bbox": [],
  "geometry": {"coordinates":[-3.766667,57.133333],"type":"Point"}
}