{
  "id": 7473775,
  "type": "Feature",
  "properties": {
    "tgn:hierarchy":[
        "tgn:7473775",
        "tgn:1000004",
        "tgn:7004300",
        "tgn:1000141",
        "tgn:7029392"
    ],
    "tgn:id":7473775,
    "tgn:name":"Dongwei",
    "tgn:placetype":[
        "aat:300008347"
    ]
},
  "bbox": [],
  "geometry": {"coordinates":[119.601938,23.569636],"type":"Point"}
}