<<<<<<< HEAD
{
  "id": 7365103,
  "type": "Feature",
  "properties": {
    "tgn:hierarchy":[
        "tgn:7365103",
        "tgn:7005586",
        "tgn:1000001",
        "tgn:7005560",
        "tgn:7029392"
    ],
    "tgn:id":7365103,
    "tgn:name":"Emiliano Zapata Yautepec",
    "tgn:placetype":[
        "aat:300008347"
    ]
},
  "bbox": [],
  "geometry": {"coordinates":[-105.15,19.8],"type":"Point"}
}
=======
{"geometry":{"type":"Point","coordinates":[-105.150000,19.800000]},"type":"Feature","properties":{"hierarchy":["tgn:7365103","tgn:7005586","tgn:1000001","tgn:7005560","tgn:7029392"],"placetype":["aat:300008347"],"id":7365103,"name:xx":"Emiliano Zapata Yautepec"}}
>>>>>>> 03f74aca74312dbeaf24d7e61306dd6a786dc3d0
