<<<<<<< HEAD
{
  "id": 7055000,
  "type": "Feature",
  "properties": {
    "tgn:hierarchy":[
        "tgn:7055000",
        "tgn:7015163",
        "tgn:1000003",
        "tgn:7003121",
        "tgn:1000080",
        "tgn:7029392"
    ],
    "tgn:id":7055000,
    "tgn:name":"Liscia di Vacca",
    "tgn:placetype":[
        "aat:300132316"
    ]
},
  "bbox": [],
  "geometry": {"coordinates":[9.5,41.15],"type":"Point"}
}
=======
{"geometry":{"type":"Point","coordinates":[9.500000,41.150000]},"type":"Feature","properties":{"hierarchy":["tgn:7055000","tgn:7015163","tgn:1000003","tgn:7003121","tgn:1000080","tgn:7029392"],"placetype":["aat:300132316"],"id":7055000,"name:xx":"Liscia di Vacca"}}
>>>>>>> 03f74aca74312dbeaf24d7e61306dd6a786dc3d0
