{
  "id": 2657158,
  "type": "Feature",
  "properties": {
    "tgn:hierarchy":[
        "tgn:2657158",
        "tgn:1000001",
        "tgn:7012149",
        "tgn:2000489",
        "tgn:7007250",
        "tgn:7029392"
    ],
    "tgn:id":2657158,
    "tgn:name":"Sheep Ridge",
    "tgn:placetype":[
        "aat:300266640"
    ]
},
  "bbox": [],
  "geometry": {"coordinates":[-116.6667,44.05],"type":"Point"}
}