{
  "id": 2657142,
  "type": "Feature",
  "properties": {
    "tgn:hierarchy":[
        "tgn:2657142",
        "tgn:1000001",
        "tgn:2001414",
        "tgn:7012149",
        "tgn:7007526",
        "tgn:7029392"
    ],
    "tgn:id":2657142,
    "tgn:name":"Sheep Ranch Springs",
    "tgn:placetype":[
        "aat:300008697"
    ]
},
  "bbox": [],
  "geometry": {"coordinates":[-118.1333,41.7333],"type":"Point"}
}