{
  "id": 1074151,
  "type": "Feature",
  "properties": {
    "tgn:hierarchy":[
        "tgn:1074151",
        "tgn:1000004",
        "tgn:7005232",
        "tgn:1000111",
        "tgn:7029392"
    ],
    "tgn:id":1074151,
    "tgn:name":"Zhukeng",
    "tgn:placetype":[
        "aat:300008347"
    ]
},
  "bbox": [],
  "geometry": {"coordinates":[112.9167,23.8167],"type":"Point"}
}