{
  "id": 7424563,
  "type": "Feature",
  "properties": {
    "tgn:hierarchy":[
        "tgn:7424563",
        "tgn:1000001",
        "tgn:7005597",
        "tgn:7005560",
        "tgn:7029392"
    ],
    "tgn:id":7424563,
    "tgn:name":"La Soledad",
    "tgn:placetype":[
        "aat:300008347"
    ]
},
  "bbox": [],
  "geometry": {"coordinates":[-99.066667,24.083333],"type":"Point"}
}