{
  "id": 2538420,
  "type": "Feature",
  "properties": {
    "tgn:hierarchy":[
        "tgn:2538420",
        "tgn:7006450",
        "tgn:1000001",
        "tgn:7012149",
        "tgn:2000087",
        "tgn:7029392"
    ],
    "tgn:id":2538420,
    "tgn:name":"Neragon Island",
    "tgn:placetype":[
        "aat:300008791"
    ]
},
  "bbox": [],
  "geometry": {"coordinates":[-165.9833,61.9167],"type":"Point"}
}