{
  "id": 7460790,
  "type": "Feature",
  "properties": {
    "tgn:hierarchy":[
        "tgn:7460790",
        "tgn:7002445",
        "tgn:1000003",
        "tgn:7008166",
        "tgn:7008591",
        "tgn:7029392"
    ],
    "tgn:id":7460790,
    "tgn:name:en":"Kex Beck",
    "tgn:placetype":[
        "aat:300008699"
    ]
},
  "bbox": [],
  "geometry": {"coordinates":[-1.883333,53.966667],"type":"Point"}
}