<<<<<<< HEAD
{
  "id": 7178066,
  "type": "Feature",
  "properties": {
    "tgn:hierarchy":[
        "tgn:7178066",
        "tgn:1000003",
        "tgn:7003678",
        "tgn:7000084",
        "tgn:7029392"
    ],
    "tgn:id":7178066,
    "tgn:name":"Hainerberg",
    "tgn:placetype":[
        "aat:300008777"
    ]
},
  "bbox": [],
  "geometry": {"coordinates":[8.268273,50.072844],"type":"Point"}
}
=======
{"geometry":{"type":"Point","coordinates":[8.268273,50.072844]},"type":"Feature","properties":{"hierarchy":["tgn:7178066","tgn:1000003","tgn:7003678","tgn:7000084","tgn:7029392"],"placetype":["aat:300008777"],"id":7178066,"name:xx":"Hainerberg"}}
>>>>>>> 03f74aca74312dbeaf24d7e61306dd6a786dc3d0
