{
  "id": 7265193,
  "type": "Feature",
  "properties": {
    "tgn:concordances":{
        "gn:id":"2752816"
    },
    "tgn:hierarchy":[
        "tgn:7265193",
        "tgn:7003619",
        "tgn:1000003",
        "tgn:7016845",
        "tgn:7029392"
    ],
    "tgn:id":7265193,
    "tgn:name:nl":"Klaarwater",
    "tgn:placetype":[
        "aat:300008347"
    ]
},
  "bbox": [],
  "geometry": {"coordinates":[5.483333,52.166667],"type":"Point"}
}