{
  "id": 1120497,
  "type": "Feature",
  "properties": {
    "tgn:hierarchy":[
        "tgn:1120497",
        "tgn:1001342",
        "tgn:1000004",
        "tgn:7000299",
        "tgn:7029392"
    ],
    "tgn:id":1120497,
    "tgn:name":"Soyang-ch\u014fsuji",
    "tgn:placetype":[
        "aat:300006191"
    ]
},
  "bbox": [],
  "geometry": {"coordinates":[127.8833,37.9333],"type":"Point"}
}