{
  "id": 7507121,
  "type": "Feature",
  "properties": {
    "tgn:hierarchy":[
        "tgn:7507121",
        "tgn:1009227",
        "tgn:1000226",
        "tgn:7018437",
        "tgn:1000006",
        "tgn:7029392"
    ],
    "tgn:id":7507121,
    "tgn:name:en":"Quail Burn",
    "tgn:placetype":[
        "aat:300008699"
    ]
},
  "bbox": [],
  "geometry": {"coordinates":[169.95,-44.45],"type":"Point"}
}