{
  "id": 7114569,
  "type": "Feature",
  "properties": {
    "tgn:hierarchy":[
        "tgn:7114569",
        "tgn:7003669",
        "tgn:1000003",
        "tgn:7000084",
        "tgn:7029392"
    ],
    "tgn:id":7114569,
    "tgn:name":"Ritzlersreuth",
    "tgn:placetype":[
        "aat:300008347"
    ]
},
  "bbox": [],
  "geometry": {"coordinates":[12.25,49.716667],"type":"Point"}
}