<<<<<<< HEAD
{
  "id": 2158601,
  "type": "Feature",
  "properties": {
    "tgn:hierarchy":[
        "tgn:2158601",
        "tgn:7002659",
        "tgn:1000001",
        "tgn:7012149",
        "tgn:2000041",
        "tgn:7029392"
    ],
    "tgn:id":2158601,
    "tgn:name":"Beaverdam Spring",
    "tgn:placetype":[
        "aat:300008697"
    ]
},
  "bbox": [],
  "geometry": {"coordinates":[-86.8167,34.7],"type":"Point"}
}
=======
{"geometry":{"type":"Point","coordinates":[-86.816700,34.700000]},"type":"Feature","properties":{"hierarchy":["tgn:2158601","tgn:7002659","tgn:1000001","tgn:7012149","tgn:2000041","tgn:7029392"],"placetype":["aat:300008697"],"id":2158601,"name:xx":"Beaverdam Spring"}}
>>>>>>> 03f74aca74312dbeaf24d7e61306dd6a786dc3d0
