{
  "id": 7180010,
  "type": "Feature",
  "properties": {
    "tgn:hierarchy":[
        "tgn:7180010",
        "tgn:7003669",
        "tgn:1000003",
        "tgn:7000084",
        "tgn:7029392"
    ],
    "tgn:id":7180010,
    "tgn:name":"Friedendorf",
    "tgn:placetype":[
        "aat:300008347"
    ]
},
  "bbox": [],
  "geometry": {"coordinates":[12.716667,49.283333],"type":"Point"}
}