<<<<<<< HEAD
{
  "id": 2334565,
  "type": "Feature",
  "properties": {
    "tgn:hierarchy":[
        "tgn:2334565",
        "tgn:1000001",
        "tgn:7012149",
        "tgn:1002691",
        "tgn:7007826",
        "tgn:7029392"
    ],
    "tgn:id":2334565,
    "tgn:name":"Forest, Lake",
    "tgn:placetype":[
        "aat:300006191"
    ]
},
  "bbox": [],
  "geometry": {"coordinates":[-95.5833,30.3167],"type":"Point"}
}
=======
{"geometry":{"type":"Point","coordinates":[-95.583300,30.316700]},"type":"Feature","properties":{"hierarchy":["tgn:2334565","tgn:1000001","tgn:7012149","tgn:1002691","tgn:7007826","tgn:7029392"],"placetype":["aat:300006191"],"id":2334565,"name:xx":"Forest, Lake"}}
>>>>>>> 03f74aca74312dbeaf24d7e61306dd6a786dc3d0
