{
  "id": 7037222,
  "type": "Feature",
  "properties": {
    "tgn:hierarchy":[
        "tgn:7037222",
        "tgn:1000003",
        "tgn:7003142",
        "tgn:7003236",
        "tgn:1000080",
        "tgn:7029392"
    ],
    "tgn:id":7037222,
    "tgn:name":"Vallescura",
    "tgn:placetype":[
        "aat:300008347"
    ]
},
  "bbox": [],
  "geometry": {"coordinates":[9.283333,44.516667],"type":"Point"}
}