{
  "id": 2462938,
  "type": "Feature",
  "properties": {
    "tgn:hierarchy":[
        "tgn:2462938",
        "tgn:1000001",
        "tgn:7012149",
        "tgn:2001526",
        "tgn:7007709",
        "tgn:7029392"
    ],
    "tgn:id":2462938,
    "tgn:name":"Live Oak Bay",
    "tgn:placetype":[
        "aat:300132316"
    ]
},
  "bbox": [],
  "geometry": {"coordinates":[-76.9167,35.0167],"type":"Point"}
}