{
  "id": 7525042,
  "type": "Feature",
  "properties": {
    "tgn:hierarchy":[
        "tgn:7525042",
        "tgn:7001242",
        "tgn:7016833",
        "tgn:1001418",
        "tgn:7029392"
    ],
    "tgn:id":7525042,
    "tgn:name:en":"Mars\u00e1 a\u1e11 \u1e10ab'ah",
    "tgn:placetype":[
        "aat:300386968"
    ]
},
  "bbox": [],
  "geometry": {"coordinates":[28.47919,31.065251],"type":"Point"}
}