{
  "id": 2502177,
  "type": "Feature",
  "properties": {
    "tgn:hierarchy":[
        "tgn:2502177",
        "tgn:1000001",
        "tgn:7012149",
        "tgn:2000219",
        "tgn:7007158",
        "tgn:7029392"
    ],
    "tgn:id":2502177,
    "tgn:name":"McKinley Clay Reservoir",
    "tgn:placetype":[
        "aat:300006191"
    ]
},
  "bbox": [],
  "geometry": {"coordinates":[-105.4833,37.85],"type":"Point"}
}