<<<<<<< HEAD
{
  "id": 2403445,
  "type": "Feature",
  "properties": {
    "tgn:hierarchy":[
        "tgn:2403445",
        "tgn:1002933",
        "tgn:1000001",
        "tgn:7012149",
        "tgn:7007239",
        "tgn:7029392"
    ],
    "tgn:id":2403445,
    "tgn:name":"Houston-Thorogood Ditch",
    "tgn:placetype":[
        "aat:300008699"
    ]
},
  "bbox": [],
  "geometry": {"coordinates":[-75.3333,38.5333],"type":"Point"}
}
=======
{"geometry":{"type":"Point","coordinates":[-75.333300,38.533300]},"type":"Feature","properties":{"hierarchy":["tgn:2403445","tgn:1002933","tgn:1000001","tgn:7012149","tgn:7007239","tgn:7029392"],"placetype":["aat:300008699"],"id":2403445,"name:xx":"Houston-Thorogood Ditch"}}
>>>>>>> 03f74aca74312dbeaf24d7e61306dd6a786dc3d0
