{
  "id": 1018368,
  "type": "Feature",
  "properties": {
    "tgn:hierarchy":[
        "tgn:1018368",
        "tgn:7005581",
        "tgn:1000001",
        "tgn:7005560",
        "tgn:7029392"
    ],
    "tgn:id":1018368,
    "tgn:name":"Tacubaya",
    "tgn:placetype":[
        "aat:300008347"
    ]
},
  "bbox": [],
  "geometry": {"coordinates":[-104.566667,28.333333],"type":"Point"}
}