{
  "id": 2633774,
  "type": "Feature",
  "properties": {
    "tgn:hierarchy":[
        "tgn:2633774",
        "tgn:1000001",
        "tgn:7012149",
        "tgn:2001272",
        "tgn:7007524",
        "tgn:7029392"
    ],
    "tgn:id":2633774,
    "tgn:name":"Rush Hall Reservoir",
    "tgn:placetype":[
        "aat:300006191"
    ]
},
  "bbox": [],
  "geometry": {"coordinates":[-104.2667,46.5833],"type":"Point"}
}