{
  "id": 7489669,
  "type": "Feature",
  "properties": {
    "tgn:hierarchy":[
        "tgn:7489669",
        "tgn:7001004",
        "tgn:1000004",
        "tgn:1000141",
        "tgn:7029392"
    ],
    "tgn:id":7489669,
    "tgn:name":"Dabu",
    "tgn:placetype":[
        "aat:300008347"
    ]
},
  "bbox": [],
  "geometry": {"coordinates":[120.321389,22.825278],"type":"Point"}
}