{
  "id": 7416137,
  "type": "Feature",
  "properties": {
    "tgn:hierarchy":[
        "tgn:7416137",
        "tgn:1000001",
        "tgn:7005591",
        "tgn:7005560",
        "tgn:7029392"
    ],
    "tgn:id":7416137,
    "tgn:name:es":"Los Pericos",
    "tgn:placetype":[
        "aat:300008347"
    ]
},
  "bbox": [],
  "geometry": {"coordinates":[-94.109167,16.805556],"type":"Point"}
}