{
  "id": 2344321,
  "type": "Feature",
  "properties": {
    "tgn:hierarchy":[
        "tgn:2344321",
        "tgn:7030516",
        "tgn:7006450",
        "tgn:1000001",
        "tgn:7012149",
        "tgn:7029392"
    ],
    "tgn:id":2344321,
    "tgn:name":"Gannet Rocks",
    "tgn:placetype":[
        "aat:300008791"
    ]
},
  "bbox": [],
  "geometry": {"coordinates":[-176.6167,51.8667],"type":"Point"}
}