{
  "id": 7222096,
  "type": "Feature",
  "properties": {
    "tgn:hierarchy":[
        "tgn:7222096",
        "tgn:7002715",
        "tgn:7002731",
        "tgn:1000003",
        "tgn:1000074",
        "tgn:7029392"
    ],
    "tgn:id":7222096,
    "tgn:name":"Mikrok\u00f3mi",
    "tgn:placetype":[
        "aat:300008347"
    ]
},
  "bbox": [],
  "geometry": {"coordinates":[23.283333,40.716667],"type":"Point"}
}