<<<<<<< HEAD
{
  "id": 2766199,
  "type": "Feature",
  "properties": {
    "tgn:hierarchy":[
        "tgn:2766199",
        "tgn:1000001",
        "tgn:7012149",
        "tgn:1002746",
        "tgn:7007568",
        "tgn:7029392"
    ],
    "tgn:id":2766199,
    "tgn:name":"White Lake",
    "tgn:placetype":[
        "aat:300008680"
    ]
},
  "bbox": [],
  "geometry": {"coordinates":[-76.0333,43.0],"type":"Point"}
}
=======
{"geometry":{"type":"Point","coordinates":[-76.033300,43.000000]},"type":"Feature","properties":{"hierarchy":["tgn:2766199","tgn:1000001","tgn:7012149","tgn:1002746","tgn:7007568","tgn:7029392"],"placetype":["aat:300008680"],"id":2766199,"name:xx":"White Lake"}}
>>>>>>> 03f74aca74312dbeaf24d7e61306dd6a786dc3d0
