{
  "id": 1053671,
  "type": "Feature",
  "properties": {
    "tgn:hierarchy":[
        "tgn:1053671",
        "tgn:1003361",
        "tgn:1000003",
        "tgn:7006660",
        "tgn:7029392"
    ],
    "tgn:id":1053671,
    "tgn:name":"Dovhen'ke",
    "tgn:placetype":[
        "aat:300008347"
    ]
},
  "bbox": [],
  "geometry": {"coordinates":[37.3167,49.0167],"type":"Point"}
}