{
  "id": 7402597,
  "type": "Feature",
  "properties": {
    "tgn:hierarchy":[
        "tgn:7402597",
        "tgn:1000001",
        "tgn:1001937",
        "tgn:7005560",
        "tgn:7029392"
    ],
    "tgn:id":7402597,
    "tgn:name":"Paila, Boca",
    "tgn:placetype":[
        "aat:300185707"
    ]
},
  "bbox": [],
  "geometry": {"coordinates":[-87.458333,20.008333],"type":"Point"}
}