{
  "id": 1026059,
  "type": "Feature",
  "properties": {
    "tgn:hierarchy":[
        "tgn:1026059",
        "tgn:7003023",
        "tgn:1000003",
        "tgn:1000062",
        "tgn:7029392"
    ],
    "tgn:id":1026059,
    "tgn:name":"Schachendorf",
    "tgn:placetype":[
        "aat:300008347"
    ]
},
  "bbox": [],
  "geometry": {"coordinates":[16.4333,47.2667],"type":"Point"}
}