{
  "id": 2632183,
  "type": "Feature",
  "properties": {
    "tgn:hierarchy":[
        "tgn:2632183",
        "tgn:1000001",
        "tgn:7012149",
        "tgn:2002035",
        "tgn:7007826",
        "tgn:7029392"
    ],
    "tgn:id":2632183,
    "tgn:name":"Rowland Tank",
    "tgn:placetype":[
        "aat:300006191"
    ]
},
  "bbox": [],
  "geometry": {"coordinates":[-98.6833,28.0667],"type":"Point"}
}