{
  "id": 2598885,
  "type": "Feature",
  "properties": {
    "tgn:hierarchy":[
        "tgn:2598885",
        "tgn:1000001",
        "tgn:7012149",
        "tgn:7007157",
        "tgn:1003050",
        "tgn:7029392"
    ],
    "tgn:id":2598885,
    "tgn:name":"Prince Albert Creek",
    "tgn:placetype":[
        "aat:300008706"
    ]
},
  "bbox": [],
  "geometry": {"coordinates":[-121.2333,39.45],"type":"Point"}
}