{
  "id": 7456884,
  "type": "Feature",
  "properties": {
    "tgn:hierarchy":[
        "tgn:7456884",
        "tgn:7008532",
        "tgn:7002443",
        "tgn:1000003",
        "tgn:7008591",
        "tgn:7029392"
    ],
    "tgn:id":7456884,
    "tgn:name:en":"Piscar, Maen",
    "tgn:placetype":[
        "aat:300011692"
    ]
},
  "bbox": [],
  "geometry": {"coordinates":[-4.616667,53.25],"type":"Point"}
}