{
  "id": 2169383,
  "type": "Feature",
  "properties": {
    "tgn:hierarchy":[
        "tgn:2169383",
        "tgn:1000001",
        "tgn:7012149",
        "tgn:2001543",
        "tgn:7007709",
        "tgn:7029392"
    ],
    "tgn:id":2169383,
    "tgn:name":"Big Laurel",
    "tgn:placetype":[
        "aat:300008347"
    ]
},
  "bbox": [],
  "geometry": {"coordinates":[-83.35,35.3333],"type":"Point"}
}