{
  "id": 2221046,
  "type": "Feature",
  "properties": {
    "tgn:hierarchy":[
        "tgn:2221046",
        "tgn:1002300",
        "tgn:1000001",
        "tgn:7012149",
        "tgn:7007564",
        "tgn:7029392"
    ],
    "tgn:id":2221046,
    "tgn:name":"Carberry, Mount",
    "tgn:placetype":[
        "aat:300008798"
    ]
},
  "bbox": [],
  "geometry": {"coordinates":[-71.1667,44.45],"type":"Point"}
}