{
  "id": 2603412,
  "type": "Feature",
  "properties": {
    "tgn:hierarchy":[
        "tgn:2603412",
        "tgn:1000001",
        "tgn:7012149",
        "tgn:7019676",
        "tgn:7007566",
        "tgn:7029392"
    ],
    "tgn:id":2603412,
    "tgn:name":"Quebrada, Laguna",
    "tgn:placetype":[
        "aat:300006191"
    ]
},
  "bbox": [],
  "geometry": {"coordinates":[-107.35,35.3333],"type":"Point"}
}