{
  "id": 7557040,
  "type": "Feature",
  "properties": {
    "tgn:hierarchy":[
        "tgn:7557040",
        "tgn:1000004",
        "tgn:7000198",
        "tgn:7016788",
        "tgn:7029392"
    ],
    "tgn:id":7557040,
    "tgn:name:en":"Seron\u012b Road",
    "tgn:placetype":[
        "aat:300007783"
    ]
},
  "bbox": [],
  "geometry": {"coordinates":[76.885289,25.945795],"type":"Point"}
}