{
  "id": 2244932,
  "type": "Feature",
  "properties": {
    "tgn:hierarchy":[
        "tgn:2244932",
        "tgn:1000001",
        "tgn:7012149",
        "tgn:2000802",
        "tgn:7007255",
        "tgn:7029392"
    ],
    "tgn:id":2244932,
    "tgn:name":"Clover Bottom Creek",
    "tgn:placetype":[
        "aat:300008706"
    ]
},
  "bbox": [],
  "geometry": {"coordinates":[-84.1333,37.4833],"type":"Point"}
}