{
  "id": 2138895,
  "type": "Feature",
  "properties": {
    "tgn:hierarchy":[
        "tgn:2138895",
        "tgn:1000001",
        "tgn:1002724",
        "tgn:7012149",
        "tgn:7007517",
        "tgn:7029392"
    ],
    "tgn:id":2138895,
    "tgn:name":"Ashcroft",
    "tgn:placetype":[
        "aat:300008347"
    ]
},
  "bbox": [],
  "geometry": {"coordinates":[-71.15,42.2333],"type":"Point"}
}