<<<<<<< HEAD
{
  "id": 2409962,
  "type": "Feature",
  "properties": {
    "tgn:hierarchy":[
        "tgn:2409962",
        "tgn:1000001",
        "tgn:7012149",
        "tgn:2001554",
        "tgn:7007709",
        "tgn:7029392"
    ],
    "tgn:id":2409962,
    "tgn:name":"Imperial Estates",
    "tgn:placetype":[
        "aat:300008347"
    ]
},
  "bbox": [],
  "geometry": {"coordinates":[-77.8667,35.7],"type":"Point"}
}
=======
{"geometry":{"type":"Point","coordinates":[-77.866700,35.700000]},"type":"Feature","properties":{"hierarchy":["tgn:2409962","tgn:1000001","tgn:7012149","tgn:2001554","tgn:7007709","tgn:7029392"],"placetype":["aat:300008347"],"id":2409962,"name:xx":"Imperial Estates"}}
>>>>>>> 03f74aca74312dbeaf24d7e61306dd6a786dc3d0
