{
  "id": 1013370,
  "type": "Feature",
  "properties": {
    "tgn:hierarchy":[
        "tgn:1013370",
        "tgn:7005735",
        "tgn:7005685",
        "tgn:1000001",
        "tgn:7029392"
    ],
    "tgn:id":1013370,
    "tgn:name":"Alice Arm",
    "tgn:placetype":[
        "aat:300008347"
    ]
},
  "bbox": [],
  "geometry": {"coordinates":[-129.5167,55.4833],"type":"Point"}
}