{
  "id": 2693930,
  "type": "Feature",
  "properties": {
    "tgn:hierarchy":[
        "tgn:2693930",
        "tgn:1000001",
        "tgn:2000921",
        "tgn:7012149",
        "tgn:7007515",
        "tgn:7029392"
    ],
    "tgn:id":2693930,
    "tgn:name":"Stetson Pond",
    "tgn:placetype":[
        "aat:300008680"
    ]
},
  "bbox": [],
  "geometry": {"coordinates":[-70.4667,44.8333],"type":"Point"}
}