{
  "id": 2210586,
  "type": "Feature",
  "properties": {
    "tgn:hierarchy":[
        "tgn:2210586",
        "tgn:1000001",
        "tgn:7012149",
        "tgn:2001553",
        "tgn:7007709",
        "tgn:7029392"
    ],
    "tgn:id":2210586,
    "tgn:name":"Bussels Creek",
    "tgn:placetype":[
        "aat:300008706"
    ]
},
  "bbox": [],
  "geometry": {"coordinates":[-81.0167,36.05],"type":"Point"}
}