{
  "id": 2369006,
  "type": "Feature",
  "properties": {
    "tgn:hierarchy":[
        "tgn:2369006",
        "tgn:1000001",
        "tgn:7012149",
        "tgn:2001996",
        "tgn:7007826",
        "tgn:7029392"
    ],
    "tgn:id":2369006,
    "tgn:name":"Gum Branch",
    "tgn:placetype":[
        "aat:300008699"
    ]
},
  "bbox": [],
  "geometry": {"coordinates":[-98.0667,31.85],"type":"Point"}
}