<<<<<<< HEAD
{
  "id": 2255478,
  "type": "Feature",
  "properties": {
    "tgn:hierarchy":[
        "tgn:2255478",
        "tgn:1000001",
        "tgn:7012149",
        "tgn:2002169",
        "tgn:7007919",
        "tgn:7029392"
    ],
    "tgn:id":2255478,
    "tgn:name":"Cope Cave",
    "tgn:placetype":[
        "aat:300008746"
    ]
},
  "bbox": [],
  "geometry": {"coordinates":[-83.2333,36.65],"type":"Point"}
}
=======
{"geometry":{"type":"Point","coordinates":[-83.233300,36.650000]},"type":"Feature","properties":{"hierarchy":["tgn:2255478","tgn:1000001","tgn:7012149","tgn:2002169","tgn:7007919","tgn:7029392"],"placetype":["aat:300008746"],"id":2255478,"name:xx":"Cope Cave"}}
>>>>>>> 03f74aca74312dbeaf24d7e61306dd6a786dc3d0
