{
  "id": 7519084,
  "type": "Feature",
  "properties": {
    "tgn:hierarchy":[
        "tgn:7519084",
        "tgn:1009227",
        "tgn:1000226",
        "tgn:1000006",
        "tgn:7016850",
        "tgn:7029392"
    ],
    "tgn:id":7519084,
    "tgn:name:en":"Aranui Creek",
    "tgn:placetype":[
        "aat:300008699"
    ]
},
  "bbox": [],
  "geometry": {"coordinates":[171.483333,-41.933333],"type":"Point"}
}