{
  "id": 2278900,
  "type": "Feature",
  "properties": {
    "tgn:hierarchy":[
        "tgn:2278900",
        "tgn:1000001",
        "tgn:7012149",
        "tgn:2002024",
        "tgn:7007826",
        "tgn:7029392"
    ],
    "tgn:id":2278900,
    "tgn:name":"Dead Man Branch",
    "tgn:placetype":[
        "aat:300008699"
    ]
},
  "bbox": [],
  "geometry": {"coordinates":[-95.6167,33.85],"type":"Point"}
}