{
  "id": 2352349,
  "type": "Feature",
  "properties": {
    "tgn:hierarchy":[
        "tgn:2352349",
        "tgn:1000001",
        "tgn:7012149",
        "tgn:2001283",
        "tgn:7007524",
        "tgn:7029392"
    ],
    "tgn:id":2352349,
    "tgn:name":"Goat Creek",
    "tgn:placetype":[
        "aat:300008706"
    ]
},
  "bbox": [],
  "geometry": {"coordinates":[-113.65,47.75],"type":"Point"}
}