{
  "id": 7281261,
  "type": "Feature",
  "properties": {
    "tgn:hierarchy":[
        "tgn:7281261",
        "tgn:1001702",
        "tgn:1000049",
        "tgn:1000002",
        "tgn:7029392"
    ],
    "tgn:id":7281261,
    "tgn:name":"Sep\u00falveda, Seno",
    "tgn:placetype":[
        "aat:300008676"
    ]
},
  "bbox": [],
  "geometry": {"coordinates":[-72.516667,-54.033333],"type":"Point"}
}