{
  "id": 2591223,
  "type": "Feature",
  "properties": {
    "tgn:hierarchy":[
        "tgn:2591223",
        "tgn:1000001",
        "tgn:7012149",
        "tgn:2001709",
        "tgn:7007708",
        "tgn:7029392"
    ],
    "tgn:id":2591223,
    "tgn:name":"Pollock Draw Reservoir",
    "tgn:placetype":[
        "aat:300006191"
    ]
},
  "bbox": [],
  "geometry": {"coordinates":[-118.2833,43.1167],"type":"Point"}
}