{
  "id": 7083742,
  "type": "Feature",
  "properties": {
    "tgn:hierarchy":[
        "tgn:7083742",
        "tgn:7003669",
        "tgn:1000003",
        "tgn:7000084",
        "tgn:7029392"
    ],
    "tgn:id":7083742,
    "tgn:name":"Wellerstadt",
    "tgn:placetype":[
        "aat:300008347"
    ]
},
  "bbox": [],
  "geometry": {"coordinates":[11.033333,49.666667],"type":"Point"}
}