{
  "id": 7246912,
  "type": "Feature",
  "properties": {
    "tgn:hierarchy":[
        "tgn:7246912",
        "tgn:7018239",
        "tgn:1000003",
        "tgn:1000063",
        "tgn:7018236",
        "tgn:7029392"
    ],
    "tgn:id":7246912,
    "tgn:name":"Centrale Hut",
    "tgn:placetype":[
        "aat:300008347"
    ]
},
  "bbox": [],
  "geometry": {"coordinates":[4.383333,50.75],"type":"Point"}
}