{
  "id": 1101300,
  "type": "Feature",
  "properties": {
    "tgn:hierarchy":[
        "tgn:1101300",
        "tgn:1000003",
        "tgn:1000062",
        "tgn:7029392"
    ],
    "tgn:id":1101300,
    "tgn:name":"Felber-Tauern",
    "tgn:placetype":[
        "aat:300007899"
    ]
},
  "bbox": [],
  "geometry": {"coordinates":[12.5167,47.1333],"type":"Point"}
}