{
  "id": 2631619,
  "type": "Feature",
  "properties": {
    "tgn:hierarchy":[
        "tgn:2631619",
        "tgn:1000001",
        "tgn:2002136",
        "tgn:7012149",
        "tgn:7007828",
        "tgn:7029392"
    ],
    "tgn:id":2631619,
    "tgn:name":"Round Top Mountain Ski Area",
    "tgn:placetype":[
        "aat:300055621"
    ]
},
  "bbox": [],
  "geometry": {"coordinates":[-72.7333,43.5333],"type":"Point"}
}