{
  "id": 7578662,
  "type": "Feature",
  "properties": {
    "tgn:hierarchy":[
        "tgn:7578662",
        "tgn:1000004",
        "tgn:1001842",
        "tgn:7000198",
        "tgn:7029392"
    ],
    "tgn:id":7578662,
    "tgn:name:en":"Sisai",
    "tgn:placetype":[
        "aat:300008347"
    ]
},
  "bbox": [],
  "geometry": {"coordinates":[84.565146,26.189084],"type":"Point"}
}