{
  "id": 2385278,
  "type": "Feature",
  "properties": {
    "tgn:hierarchy":[
        "tgn:2385278",
        "tgn:1000001",
        "tgn:1002286",
        "tgn:7012149",
        "tgn:7007710",
        "tgn:7029392"
    ],
    "tgn:id":2385278,
    "tgn:name":"Hemlock Spring",
    "tgn:placetype":[
        "aat:300008697"
    ]
},
  "bbox": [],
  "geometry": {"coordinates":[-77.2167,41.05],"type":"Point"}
}