{
  "id": 7419851,
  "type": "Feature",
  "properties": {
    "tgn:hierarchy":[
        "tgn:7419851",
        "tgn:1000001",
        "tgn:7005589",
        "tgn:7005560",
        "tgn:7029392"
    ],
    "tgn:id":7419851,
    "tgn:name:es":"San Miguel",
    "tgn:placetype":[
        "aat:300008347"
    ]
},
  "bbox": [],
  "geometry": {"coordinates":[-100.156111,26.558333],"type":"Point"}
}