{
  "id": 2505011,
  "type": "Feature",
  "properties": {
    "tgn:hierarchy":[
        "tgn:2505011",
        "tgn:1000001",
        "tgn:2002109",
        "tgn:7012149",
        "tgn:7007827",
        "tgn:7029392"
    ],
    "tgn:id":2505011,
    "tgn:name":"Meeks Draw",
    "tgn:placetype":[
        "aat:300008761"
    ]
},
  "bbox": [],
  "geometry": {"coordinates":[-111.4167,38.1167],"type":"Point"}
}