{
  "id": 2015996,
  "type": "Feature",
  "properties": {
    "tgn:hierarchy":[
        "tgn:2015996",
        "tgn:1000001",
        "tgn:2000202",
        "tgn:7012149",
        "tgn:7007158",
        "tgn:7029392"
    ],
    "tgn:id":2015996,
    "tgn:name":"Mogote",
    "tgn:placetype":[
        "aat:300008347"
    ]
},
  "bbox": [],
  "geometry": {"coordinates":[-106.0833,37.05],"type":"Point"}
}