{
  "id": 2363718,
  "type": "Feature",
  "properties": {
    "tgn:hierarchy":[
        "tgn:2363718",
        "tgn:1000001",
        "tgn:7012149",
        "tgn:2002341",
        "tgn:7007922",
        "tgn:7029392"
    ],
    "tgn:id":2363718,
    "tgn:name":"Green Island",
    "tgn:placetype":[
        "aat:300008791"
    ]
},
  "bbox": [],
  "geometry": {"coordinates":[-88.2167,45.0333],"type":"Point"}
}