{
  "id": 2230163,
  "type": "Feature",
  "properties": {
    "tgn:hierarchy":[
        "tgn:2230163",
        "tgn:1000001",
        "tgn:7012149",
        "tgn:1002604",
        "tgn:7007568",
        "tgn:7029392"
    ],
    "tgn:id":2230163,
    "tgn:name":"Cement Plant Pond",
    "tgn:placetype":[
        "aat:300008680"
    ]
},
  "bbox": [],
  "geometry": {"coordinates":[-77.8167,42.9667],"type":"Point"}
}