<<<<<<< HEAD
{
  "id": 7481105,
  "type": "Feature",
  "properties": {
    "tgn:hierarchy":[
        "tgn:7481105",
        "tgn:1000004",
        "tgn:7490934",
        "tgn:1000141",
        "tgn:7029392"
    ],
    "tgn:id":7481105,
    "tgn:name":"Kunshen Qiao",
    "tgn:placetype":[
        "aat:300007836"
    ]
},
  "bbox": [],
  "geometry": {"coordinates":[120.135254,23.283051],"type":"Point"}
}
=======
{"geometry":{"type":"Point","coordinates":[120.135254,23.283051]},"type":"Feature","properties":{"hierarchy":["tgn:7481105","tgn:1000004","tgn:7490934","tgn:1000141","tgn:7029392"],"placetype":["aat:300007836"],"id":7481105,"name:xx":"Kunshen Qiao"}}
>>>>>>> 03f74aca74312dbeaf24d7e61306dd6a786dc3d0
