{
  "id": 7511308,
  "type": "Feature",
  "properties": {
    "tgn:hierarchy":[
        "tgn:7511308",
        "tgn:1009227",
        "tgn:1000226",
        "tgn:7520095",
        "tgn:1000006",
        "tgn:7029392"
    ],
    "tgn:id":7511308,
    "tgn:name:en":"Travers River",
    "tgn:placetype":[
        "aat:300008699"
    ]
},
  "bbox": [],
  "geometry": {"coordinates":[172.816667,-41.866667],"type":"Point"}
}