{
  "id": 7276065,
  "type": "Feature",
  "properties": {
    "tgn:hierarchy":[
        "tgn:7276065",
        "tgn:1001695",
        "tgn:1000049",
        "tgn:1000002",
        "tgn:7029392"
    ],
    "tgn:id":7276065,
    "tgn:name":"Tipaume, Estero",
    "tgn:placetype":[
        "aat:300008699"
    ]
},
  "bbox": [],
  "geometry": {"coordinates":[-70.866667,-34.383333],"type":"Point"}
}