{
  "id": 7584649,
  "type": "Feature",
  "properties": {
    "tgn:hierarchy":[
        "tgn:7584649",
        "tgn:1000004",
        "tgn:7000198",
        "tgn:1001894",
        "tgn:7029392"
    ],
    "tgn:id":7584649,
    "tgn:name:en":"Kunwarpura",
    "tgn:placetype":[
        "aat:300008347"
    ]
},
  "bbox": [],
  "geometry": {"coordinates":[78.821961,24.768714],"type":"Point"}
}