{
  "id": 7398891,
  "type": "Feature",
  "properties": {
    "tgn:hierarchy":[
        "tgn:7398891",
        "tgn:1000001",
        "tgn:1001893",
        "tgn:7005560",
        "tgn:7029392"
    ],
    "tgn:id":7398891,
    "tgn:name":"Santa Clara de Ju\u00e1rez",
    "tgn:placetype":[
        "aat:300008347"
    ]
},
  "bbox": [],
  "geometry": {"coordinates":[-99.611667,19.724444],"type":"Point"}
}