{
  "id": 2719695,
  "type": "Feature",
  "properties": {
    "tgn:hierarchy":[
        "tgn:2719695",
        "tgn:1000001",
        "tgn:7012149",
        "tgn:2001846",
        "tgn:7007825",
        "tgn:7029392"
    ],
    "tgn:id":2719695,
    "tgn:name":"Three Mountains",
    "tgn:placetype":[
        "aat:300008347"
    ]
},
  "bbox": [],
  "geometry": {"coordinates":[-82.25,36.2333],"type":"Point"}
}