{
  "id": 7393961,
  "type": "Feature",
  "properties": {
    "tgn:hierarchy":[
        "tgn:7393961",
        "tgn:7005585",
        "tgn:1000001",
        "tgn:7005560",
        "tgn:7029392"
    ],
    "tgn:id":7393961,
    "tgn:name":"San Juan Tetelcingo",
    "tgn:placetype":[
        "aat:300008347"
    ]
},
  "bbox": [],
  "geometry": {"coordinates":[-99.35,17.916667],"type":"Point"}
}