{
  "id": 2362047,
  "type": "Feature",
  "properties": {
    "tgn:hierarchy":[
        "tgn:2362047",
        "tgn:1000001",
        "tgn:7006451",
        "tgn:2000092",
        "tgn:7012149",
        "tgn:7029392"
    ],
    "tgn:id":2362047,
    "tgn:name":"Gray Spring",
    "tgn:placetype":[
        "aat:300008697"
    ]
},
  "bbox": [],
  "geometry": {"coordinates":[-111.95,35.1167],"type":"Point"}
}