{
  "id": 1133126,
  "type": "Feature",
  "properties": {
    "tgn:hierarchy":[
        "tgn:1133126",
        "tgn:1000001",
        "tgn:7012149",
        "tgn:7007705",
        "tgn:7029392"
    ],
    "tgn:id":1133126,
    "tgn:name":"Egg Creek",
    "tgn:placetype":[
        "aat:300008706"
    ]
},
  "bbox": [],
  "geometry": {"coordinates":[-101.4833,48.55],"type":"Point"}
}