{
  "id": 7256138,
  "type": "Feature",
  "properties": {
    "tgn:hierarchy":[
        "tgn:7256138",
        "tgn:1000003",
        "tgn:7003613",
        "tgn:7016845",
        "tgn:7029392"
    ],
    "tgn:id":7256138,
    "tgn:name:nl":"Besloten Venen",
    "tgn:placetype":[
        "aat:300387200"
    ]
},
  "bbox": [],
  "geometry": {"coordinates":[6.633333,53.116667],"type":"Point"}
}