{
  "id": 7584757,
  "type": "Feature",
  "properties": {
    "tgn:hierarchy":[
        "tgn:7584757",
        "tgn:1000004",
        "tgn:7000198",
        "tgn:1001894",
        "tgn:7029392"
    ],
    "tgn:id":7584757,
    "tgn:name:en":"Itaiya",
    "tgn:placetype":[
        "aat:300008347"
    ]
},
  "bbox": [],
  "geometry": {"coordinates":[78.138708,24.08366],"type":"Point"}
}