{
  "id": 7515503,
  "type": "Feature",
  "properties": {
    "tgn:hierarchy":[
        "tgn:7515503",
        "tgn:1008380",
        "tgn:7000507",
        "tgn:1000226",
        "tgn:1000006",
        "tgn:7029392"
    ],
    "tgn:id":7515503,
    "tgn:name:en":"Onekainga",
    "tgn:placetype":[
        "aat:300008777"
    ]
},
  "bbox": [],
  "geometry": {"coordinates":[174.433333,-35.483333],"type":"Point"}
}