{
  "id": 2291031,
  "type": "Feature",
  "properties": {
    "tgn:hierarchy":[
        "tgn:2291031",
        "tgn:1000001",
        "tgn:7012149",
        "tgn:7019676",
        "tgn:7007566",
        "tgn:7029392"
    ],
    "tgn:id":2291031,
    "tgn:name":"Dog Spring Canyon",
    "tgn:placetype":[
        "aat:300008761"
    ]
},
  "bbox": [],
  "geometry": {"coordinates":[-108.3667,35.7333],"type":"Point"}
}