{
  "id": 2081081,
  "type": "Feature",
  "properties": {
    "tgn:hierarchy":[
        "tgn:2081081",
        "tgn:1000001",
        "tgn:7012149",
        "tgn:1002441",
        "tgn:7007706",
        "tgn:7029392"
    ],
    "tgn:id":2081081,
    "tgn:name":"Northbrook",
    "tgn:placetype":[
        "aat:300008347"
    ]
},
  "bbox": [],
  "geometry": {"coordinates":[-84.5833,39.2333],"type":"Point"}
}