{
  "id": 7458985,
  "type": "Feature",
  "properties": {
    "tgn:hierarchy":[
        "tgn:7458985",
        "tgn:7002445",
        "tgn:1000003",
        "tgn:7008134",
        "tgn:7008591",
        "tgn:7029392"
    ],
    "tgn:id":7458985,
    "tgn:name:en":"Outer Owers",
    "tgn:placetype":[
        "aat:300387036"
    ]
},
  "bbox": [],
  "geometry": {"coordinates":[-0.683333,50.666667],"type":"Point"}
}