{
  "id": 2703325,
  "type": "Feature",
  "properties": {
    "tgn:hierarchy":[
        "tgn:2703325",
        "tgn:7014201",
        "tgn:1000001",
        "tgn:7012149",
        "tgn:7007239",
        "tgn:7029392"
    ],
    "tgn:id":2703325,
    "tgn:name":"Summit Bridge",
    "tgn:placetype":[
        "aat:300008347"
    ]
},
  "bbox": [],
  "geometry": {"coordinates":[-75.7167,39.5333],"type":"Point"}
}