{
  "id": 7589274,
  "type": "Feature",
  "properties": {
    "tgn:hierarchy":[
        "tgn:7589274",
        "tgn:1000004",
        "tgn:7000198",
        "tgn:7000799",
        "tgn:7029392"
    ],
    "tgn:id":7589274,
    "tgn:name:en":"Fagipur",
    "tgn:placetype":[
        "aat:300008347"
    ]
},
  "bbox": [],
  "geometry": {"coordinates":[74.297222,34.298611],"type":"Point"}
}