<<<<<<< HEAD
{
  "id": 7020401,
  "type": "Feature",
  "properties": {
    "tgn:hierarchy":[
        "tgn:7020401",
        "tgn:1000001",
        "tgn:2001263",
        "tgn:7012149",
        "tgn:7007524",
        "tgn:7029392"
    ],
    "tgn:id":7020401,
    "tgn:name":"Hummingbird Mine",
    "tgn:placetype":[
        "aat:300000390"
    ]
},
  "bbox": [],
  "geometry": {"coordinates":[-111.4,46.6167],"type":"Point"}
}
=======
{"geometry":{"type":"Point","coordinates":[-111.400000,46.616700]},"type":"Feature","properties":{"hierarchy":["tgn:7020401","tgn:1000001","tgn:2001263","tgn:7012149","tgn:7007524","tgn:7029392"],"placetype":["aat:300000390"],"id":7020401,"name:xx":"Hummingbird Mine"}}
>>>>>>> 03f74aca74312dbeaf24d7e61306dd6a786dc3d0
