{
  "id": 7032308,
  "type": "Feature",
  "properties": {
    "tgn:hierarchy":[
        "tgn:7032308",
        "tgn:7001680",
        "tgn:7001242",
        "tgn:1000184",
        "tgn:7029392"
    ],
    "tgn:id":7032308,
    "tgn:name:fr":"Bretagne, Pointe de",
    "tgn:placetype":[
        "aat:300386846"
    ]
},
  "bbox": [],
  "geometry": {"coordinates":[55.2833,21.1833],"type":"Point"}
}