<<<<<<< HEAD
{
  "id": 7370205,
  "type": "Feature",
  "properties": {
    "tgn:hierarchy":[
        "tgn:7370205",
        "tgn:7005584",
        "tgn:1000001",
        "tgn:7005560",
        "tgn:7029392"
    ],
    "tgn:id":7370205,
    "tgn:name":"Jamaica",
    "tgn:placetype":[
        "aat:300008347"
    ]
},
  "bbox": [],
  "geometry": {"coordinates":[-100.7,21.116667],"type":"Point"}
}
=======
{"geometry":{"type":"Point","coordinates":[-100.700000,21.116667]},"type":"Feature","properties":{"hierarchy":["tgn:7370205","tgn:7005584","tgn:1000001","tgn:7005560","tgn:7029392"],"placetype":["aat:300008347"],"id":7370205,"name:xx":"Jamaica"}}
>>>>>>> 03f74aca74312dbeaf24d7e61306dd6a786dc3d0
