{
  "id": 7185237,
  "type": "Feature",
  "properties": {
    "tgn:hierarchy":[
        "tgn:7185237",
        "tgn:1000003",
        "tgn:7003677",
        "tgn:7000084",
        "tgn:7029392"
    ],
    "tgn:id":7185237,
    "tgn:name":"Gesthuysen",
    "tgn:placetype":[
        "aat:300008347"
    ]
},
  "bbox": [],
  "geometry": {"coordinates":[6.383333,51.716667],"type":"Point"}
}