{
  "id": 1116410,
  "type": "Feature",
  "properties": {
    "tgn:hierarchy":[
        "tgn:1116410",
        "tgn:7002444",
        "tgn:1000003",
        "tgn:7008082",
        "tgn:7008591",
        "tgn:7029392"
    ],
    "tgn:id":1116410,
    "tgn:name":"Glascarnoch, Loch",
    "tgn:placetype":[
        "aat:300008680"
    ]
},
  "bbox": [],
  "geometry": {"coordinates":[-4.8333,57.6667],"type":"Point"}
}