{
  "id": 1049414,
  "type": "Feature",
  "properties": {
    "tgn:hierarchy":[
        "tgn:1049414",
        "tgn:1000003",
        "tgn:7024114",
        "tgn:7006366",
        "tgn:7029392"
    ],
    "tgn:id":1049414,
    "tgn:name":"Recz",
    "tgn:placetype":[
        "aat:300008347"
    ]
},
  "bbox": [],
  "geometry": {"coordinates":[15.5667,53.2833],"type":"Point"}
}