{
  "id": 7175638,
  "type": "Feature",
  "properties": {
    "tgn:hierarchy":[
        "tgn:7175638",
        "tgn:1000003",
        "tgn:7000094",
        "tgn:7000084",
        "tgn:7029392"
    ],
    "tgn:id":7175638,
    "tgn:name":"Gro\u00dfe Spornitzer Wiese",
    "tgn:placetype":[
        "aat:300386990"
    ]
},
  "bbox": [],
  "geometry": {"coordinates":[11.633333,53.433333],"type":"Point"}
}