{
  "id": 7348606,
  "type": "Feature",
  "properties": {
    "tgn:hierarchy":[
        "tgn:7348606",
        "tgn:1000001",
        "tgn:7005595",
        "tgn:7005560",
        "tgn:7029392"
    ],
    "tgn:id":7348606,
    "tgn:name":"Ajoro, Punta",
    "tgn:placetype":[
        "aat:300386846"
    ]
},
  "bbox": [],
  "geometry": {"coordinates":[-109.016667,25.466667],"type":"Point"}
}