{
  "id": 7043791,
  "type": "Feature",
  "properties": {
    "tgn:hierarchy":[
        "tgn:7043791",
        "tgn:1000003",
        "tgn:7003152",
        "tgn:7003237",
        "tgn:1000080",
        "tgn:7029392"
    ],
    "tgn:id":7043791,
    "tgn:name":"Fusine",
    "tgn:placetype":[
        "aat:300008347"
    ]
},
  "bbox": [],
  "geometry": {"coordinates":[9.733333,46.15],"type":"Point"}
}