<<<<<<< HEAD
{
  "id": 7175848,
  "type": "Feature",
  "properties": {
    "tgn:hierarchy":[
        "tgn:7175848",
        "tgn:1000003",
        "tgn:7000094",
        "tgn:7000084",
        "tgn:7029392"
    ],
    "tgn:id":7175848,
    "tgn:name":"Gro\u00df Voigtshagen",
    "tgn:placetype":[
        "aat:300008347"
    ]
},
  "bbox": [],
  "geometry": {"coordinates":[11.05,53.916667],"type":"Point"}
}
=======
{"geometry":{"type":"Point","coordinates":[11.050000,53.916667]},"type":"Feature","properties":{"hierarchy":["tgn:7175848","tgn:1000003","tgn:7000094","tgn:7000084","tgn:7029392"],"placetype":["aat:300008347"],"id":7175848,"name:xx":"Gro\u00df Voigtshagen"}}
>>>>>>> 03f74aca74312dbeaf24d7e61306dd6a786dc3d0
