{
  "id": 2696781,
  "type": "Feature",
  "properties": {
    "tgn:hierarchy":[
        "tgn:2696781",
        "tgn:1000001",
        "tgn:7014090",
        "tgn:7012149",
        "tgn:7007565",
        "tgn:7029392"
    ],
    "tgn:id":2696781,
    "tgn:name":"Stonehurst East",
    "tgn:placetype":[
        "aat:300008347"
    ]
},
  "bbox": [],
  "geometry": {"coordinates":[-74.2833,40.2167],"type":"Point"}
}