{
  "id": 7198747,
  "type": "Feature",
  "properties": {
    "tgn:hierarchy":[
        "tgn:7198747",
        "tgn:1000003",
        "tgn:7003677",
        "tgn:7000084",
        "tgn:7029392"
    ],
    "tgn:id":7198747,
    "tgn:name":"Dringenburg",
    "tgn:placetype":[
        "aat:300000206"
    ]
},
  "bbox": [],
  "geometry": {"coordinates":[6.933333,51.616667],"type":"Point"}
}