{
  "id": 7450799,
  "type": "Feature",
  "properties": {
    "tgn:hierarchy":[
        "tgn:7450799",
        "tgn:7002445",
        "tgn:1000003",
        "tgn:7008160",
        "tgn:7008591",
        "tgn:7029392"
    ],
    "tgn:id":7450799,
    "tgn:name:en":"Gat Channel",
    "tgn:placetype":[
        "aat:300008713"
    ]
},
  "bbox": [],
  "geometry": {"coordinates":[0.25,52.933333],"type":"Point"}
}