{
  "id": 7570031,
  "type": "Feature",
  "properties": {
    "tgn:hierarchy":[
        "tgn:7570031",
        "tgn:1000004",
        "tgn:7000198",
        "tgn:1001895",
        "tgn:7029392"
    ],
    "tgn:id":7570031,
    "tgn:name:en":"B\u0101ple",
    "tgn:placetype":[
        "aat:300008347"
    ]
},
  "bbox": [],
  "geometry": {"coordinates":[72.984167,18.557222],"type":"Point"}
}