{
  "id": 7059997,
  "type": "Feature",
  "properties": {
    "tgn:hierarchy":[
        "tgn:7059997",
        "tgn:1000003",
        "tgn:7003682",
        "tgn:7000084",
        "tgn:7029392"
    ],
    "tgn:id":7059997,
    "tgn:name":"Altenhof",
    "tgn:placetype":[
        "aat:300000206"
    ]
},
  "bbox": [],
  "geometry": {"coordinates":[6.75,50.016667],"type":"Point"}
}