{
  "id": 7591907,
  "type": "Feature",
  "properties": {
    "tgn:hierarchy":[
        "tgn:7591907",
        "tgn:1000004",
        "tgn:7000198",
        "tgn:7000799",
        "tgn:7029392"
    ],
    "tgn:id":7591907,
    "tgn:name:en":"Dali\u0101ri",
    "tgn:placetype":[
        "aat:300008347"
    ]
},
  "bbox": [],
  "geometry": {"coordinates":[74.23006,33.174028],"type":"Point"}
}