<<<<<<< HEAD
{
  "id": 2769206,
  "type": "Feature",
  "properties": {
    "tgn:hierarchy":[
        "tgn:2769206",
        "tgn:2001466",
        "tgn:1000001",
        "tgn:7012149",
        "tgn:7007709",
        "tgn:7029392"
    ],
    "tgn:id":2769206,
    "tgn:name":"Whortleberry Creek",
    "tgn:placetype":[
        "aat:300008706"
    ]
},
  "bbox": [],
  "geometry": {"coordinates":[-79.95,34.8333],"type":"Point"}
}
=======
{"geometry":{"type":"Point","coordinates":[-79.950000,34.833300]},"type":"Feature","properties":{"hierarchy":["tgn:2769206","tgn:2001466","tgn:1000001","tgn:7012149","tgn:7007709","tgn:7029392"],"placetype":["aat:300008706"],"id":2769206,"name:xx":"Whortleberry Creek"}}
>>>>>>> 03f74aca74312dbeaf24d7e61306dd6a786dc3d0
