{
  "id": 7563643,
  "type": "Feature",
  "properties": {
    "tgn:hierarchy":[
        "tgn:7563643",
        "tgn:1000004",
        "tgn:7000198",
        "tgn:1001894",
        "tgn:7029392"
    ],
    "tgn:id":7563643,
    "tgn:name:en":"Sati",
    "tgn:placetype":[
        "aat:300008347"
    ]
},
  "bbox": [],
  "geometry": {"coordinates":[79.477045,24.983706],"type":"Point"}
}