{
  "id": 2772945,
  "type": "Feature",
  "properties": {
    "tgn:hierarchy":[
        "tgn:2772945",
        "tgn:1000001",
        "tgn:7012149",
        "tgn:2001715",
        "tgn:7007708",
        "tgn:7029392"
    ],
    "tgn:id":2772945,
    "tgn:name":"Williams Mill",
    "tgn:placetype":[
        "aat:300008347"
    ]
},
  "bbox": [],
  "geometry": {"coordinates":[-121.1833,43.2333],"type":"Point"}
}