{
  "id": 2693734,
  "type": "Feature",
  "properties": {
    "tgn:hierarchy":[
        "tgn:2693734",
        "tgn:1000001",
        "tgn:7012149",
        "tgn:2000903",
        "tgn:7007256",
        "tgn:7029392"
    ],
    "tgn:id":2693734,
    "tgn:name":"Stephenville",
    "tgn:placetype":[
        "aat:300008347"
    ]
},
  "bbox": [],
  "geometry": {"coordinates":[-91.15,29.7667],"type":"Point"}
}