{
  "id": 2348868,
  "type": "Feature",
  "properties": {
    "tgn:hierarchy":[
        "tgn:2348868",
        "tgn:1000001",
        "tgn:2001703",
        "tgn:7012149",
        "tgn:7007708",
        "tgn:7029392"
    ],
    "tgn:id":2348868,
    "tgn:name":"Gibson Spring",
    "tgn:placetype":[
        "aat:300008697"
    ]
},
  "bbox": [],
  "geometry": {"coordinates":[-120.55,44.05],"type":"Point"}
}