{
  "id": 1016597,
  "type": "Feature",
  "properties": {
    "tgn:hierarchy":[
        "tgn:1016597",
        "tgn:7018312",
        "tgn:1006440",
        "tgn:1000001",
        "tgn:7004545",
        "tgn:7029392"
    ],
    "tgn:id":1016597,
    "tgn:name":"Deshaies",
    "tgn:placetype":[
        "aat:300008347"
    ]
},
  "bbox": [],
  "geometry": {"coordinates":[-61.7833,16.3167],"type":"Point"}
}