{
  "id": 2257099,
  "type": "Feature",
  "properties": {
    "tgn:hierarchy":[
        "tgn:2257099",
        "tgn:1000001",
        "tgn:1002236",
        "tgn:7012149",
        "tgn:7007252",
        "tgn:7029392"
    ],
    "tgn:id":2257099,
    "tgn:name":"Cornell Ditch",
    "tgn:placetype":[
        "aat:300006075"
    ]
},
  "bbox": [],
  "geometry": {"coordinates":[-86.3667,40.65],"type":"Point"}
}