<<<<<<< HEAD
{
  "id": 2257099,
  "type": "Feature",
  "properties": {
    "tgn:hierarchy":[
        "tgn:2257099",
        "tgn:1000001",
        "tgn:1002236",
        "tgn:7012149",
        "tgn:7007252",
        "tgn:7029392"
    ],
    "tgn:id":2257099,
    "tgn:name":"Cornell Ditch",
    "tgn:placetype":[
        "aat:300006075"
    ]
},
  "bbox": [],
  "geometry": {"coordinates":[-86.3667,40.65],"type":"Point"}
}
=======
{"geometry":{"type":"Point","coordinates":[-86.366700,40.650000]},"type":"Feature","properties":{"hierarchy":["tgn:2257099","tgn:1000001","tgn:1002236","tgn:7012149","tgn:7007252","tgn:7029392"],"placetype":["aat:300006075"],"id":2257099,"name:xx":"Cornell Ditch"}}
>>>>>>> 03f74aca74312dbeaf24d7e61306dd6a786dc3d0
