{
  "id": 1047474,
  "type": "Feature",
  "properties": {
    "tgn:hierarchy":[
        "tgn:1047474",
        "tgn:1003488",
        "tgn:1000003",
        "tgn:7002993",
        "tgn:1000080",
        "tgn:7029392"
    ],
    "tgn:id":1047474,
    "tgn:name":"Villotta",
    "tgn:placetype":[
        "aat:300008347"
    ]
},
  "bbox": [],
  "geometry": {"coordinates":[12.773333,45.875833],"type":"Point"}
}