{
  "id": 7497474,
  "type": "Feature",
  "properties": {
    "tgn:hierarchy":[
        "tgn:7497474",
        "tgn:7001004",
        "tgn:1000004",
        "tgn:1000141",
        "tgn:7029392"
    ],
    "tgn:id":7497474,
    "tgn:name":"Haishan",
    "tgn:placetype":[
        "aat:300008347"
    ]
},
  "bbox": [],
  "geometry": {"coordinates":[120.321372,22.546077],"type":"Point"}
}