{
  "id": 7031009,
  "type": "Feature",
  "properties": {
    "tgn:hierarchy":[
        "tgn:7031009",
        "tgn:7002445",
        "tgn:1000003",
        "tgn:7008167",
        "tgn:7008591",
        "tgn:7029392"
    ],
    "tgn:id":7031009,
    "tgn:name:en":"Brinsley",
    "tgn:placetype":[
        "aat:300008347",
        "aat:300008372"
    ]
},
  "bbox": [],
  "geometry": {"coordinates":[-1.316667,53.016667],"type":"Point"}
}