<<<<<<< HEAD
{
  "id": 7176169,
  "type": "Feature",
  "properties": {
    "tgn:hierarchy":[
        "tgn:7176169",
        "tgn:7003692",
        "tgn:1000003",
        "tgn:7000084",
        "tgn:7029392"
    ],
    "tgn:id":7176169,
    "tgn:name":"Gro\u00dfe Lauter",
    "tgn:placetype":[
        "aat:300008699"
    ]
},
  "bbox": [],
  "geometry": {"coordinates":[9.583333,48.233333],"type":"Point"}
}
=======
{"geometry":{"type":"Point","coordinates":[9.583333,48.233333]},"type":"Feature","properties":{"hierarchy":["tgn:7176169","tgn:7003692","tgn:1000003","tgn:7000084","tgn:7029392"],"placetype":["aat:300008699"],"id":7176169,"name:xx":"Gro\u00dfe Lauter"}}
>>>>>>> 03f74aca74312dbeaf24d7e61306dd6a786dc3d0
