{
  "id": 7331531,
  "type": "Feature",
  "properties": {
    "tgn:hierarchy":[
        "tgn:7331531",
        "tgn:7002813",
        "tgn:7002758",
        "tgn:1000003",
        "tgn:1000095",
        "tgn:7029392"
    ],
    "tgn:id":7331531,
    "tgn:name":"La Laguna",
    "tgn:placetype":[
        "aat:300008347"
    ]
},
  "bbox": [],
  "geometry": {"coordinates":[-5.666667,36.866667],"type":"Point"}
}