{
  "id": 7558268,
  "type": "Feature",
  "properties": {
    "tgn:hierarchy":[
        "tgn:7558268",
        "tgn:1000004",
        "tgn:1001842",
        "tgn:7000198",
        "tgn:7029392"
    ],
    "tgn:id":7558268,
    "tgn:name:en":"Pasr\u0101ha",
    "tgn:placetype":[
        "aat:300008347"
    ]
},
  "bbox": [],
  "geometry": {"coordinates":[86.704269,25.396729],"type":"Point"}
}