{
  "id": 2053867,
  "type": "Feature",
  "properties": {
    "tgn:hierarchy":[
        "tgn:2053867",
        "tgn:2000999",
        "tgn:1000001",
        "tgn:7012149",
        "tgn:7007521",
        "tgn:7029392"
    ],
    "tgn:id":2053867,
    "tgn:name":"Arthyde",
    "tgn:placetype":[
        "aat:300008347",
        "aat:300387210"
    ]
},
  "bbox": [],
  "geometry": {"coordinates":[-93.0833,46.35],"type":"Point"}
}