{
  "id": 1056720,
  "type": "Feature",
  "properties": {
    "tgn:hierarchy":[
        "tgn:1056720",
        "tgn:7012076",
        "tgn:1000003",
        "tgn:7006660",
        "tgn:7029392"
    ],
    "tgn:id":1056720,
    "tgn:name":"Malaja Janisol'",
    "tgn:placetype":[
        "aat:300008347"
    ]
},
  "bbox": [],
  "geometry": {"coordinates":[37.3333,47.3667],"type":"Point"}
}