{
  "id": 7285166,
  "type": "Feature",
  "properties": {
    "tgn:hierarchy":[
        "tgn:7285166",
        "tgn:1001630",
        "tgn:1000049",
        "tgn:1000002",
        "tgn:7029392"
    ],
    "tgn:id":7285166,
    "tgn:name":"Piedra Colgada",
    "tgn:placetype":[
        "aat:300008347"
    ]
},
  "bbox": [],
  "geometry": {"coordinates":[-70.466667,-27.283333],"type":"Point"}
}