{
  "id": 7560936,
  "type": "Feature",
  "properties": {
    "tgn:hierarchy":[
        "tgn:7560936",
        "tgn:1000004",
        "tgn:7000198",
        "tgn:7016722",
        "tgn:7029392"
    ],
    "tgn:id":7560936,
    "tgn:name:en":"Nagia Honum\u0101n",
    "tgn:placetype":[
        "aat:300008347"
    ]
},
  "bbox": [],
  "geometry": {"coordinates":[79.226841,26.852898],"type":"Point"}
}