{
  "id": 2214378,
  "type": "Feature",
  "properties": {
    "tgn:hierarchy":[
        "tgn:2214378",
        "tgn:1000001",
        "tgn:1002286",
        "tgn:7012149",
        "tgn:7007710",
        "tgn:7029392"
    ],
    "tgn:id":2214378,
    "tgn:name":"Calamity Hollow",
    "tgn:placetype":[
        "aat:300008761"
    ]
},
  "bbox": [],
  "geometry": {"coordinates":[-77.7333,41.45],"type":"Point"}
}