{
  "id": 7577806,
  "type": "Feature",
  "properties": {
    "tgn:hierarchy":[
        "tgn:7577806",
        "tgn:1000004",
        "tgn:1001842",
        "tgn:7000198",
        "tgn:7029392"
    ],
    "tgn:id":7577806,
    "tgn:name:en":"Kulh\u0101ria",
    "tgn:placetype":[
        "aat:300008347"
    ]
},
  "bbox": [],
  "geometry": {"coordinates":[84.772092,25.57318],"type":"Point"}
}