{
  "id": 2370669,
  "type": "Feature",
  "properties": {
    "tgn:hierarchy":[
        "tgn:2370669",
        "tgn:1000001",
        "tgn:2001436",
        "tgn:7012149",
        "tgn:7007566",
        "tgn:7029392"
    ],
    "tgn:id":2370669,
    "tgn:name":"Hackberry Slope",
    "tgn:placetype":[
        "aat:300055621"
    ]
},
  "bbox": [],
  "geometry": {"coordinates":[-104.2833,32.4167],"type":"Point"}
}