<<<<<<< HEAD
{
  "id": 7114021,
  "type": "Feature",
  "properties": {
    "tgn:hierarchy":[
        "tgn:7114021",
        "tgn:7003669",
        "tgn:1000003",
        "tgn:7000084",
        "tgn:7029392"
    ],
    "tgn:id":7114021,
    "tgn:name":"Reschbach Klause",
    "tgn:placetype":[
        "aat:300386834"
    ]
},
  "bbox": [],
  "geometry": {"coordinates":[13.55,48.966667],"type":"Point"}
}
=======
{"geometry":{"type":"Point","coordinates":[13.550000,48.966667]},"type":"Feature","properties":{"hierarchy":["tgn:7114021","tgn:7003669","tgn:1000003","tgn:7000084","tgn:7029392"],"placetype":["aat:300386834"],"id":7114021,"name:xx":"Reschbach Klause"}}
>>>>>>> 03f74aca74312dbeaf24d7e61306dd6a786dc3d0
