{
  "id": 2594711,
  "type": "Feature",
  "properties": {
    "tgn:hierarchy":[
        "tgn:2594711",
        "tgn:1000001",
        "tgn:7012149",
        "tgn:2001451",
        "tgn:7007566",
        "tgn:7029392"
    ],
    "tgn:id":2594711,
    "tgn:name":"Posos, Cerros de los",
    "tgn:placetype":[
        "aat:300266640"
    ]
},
  "bbox": [],
  "geometry": {"coordinates":[-106.4167,35.9333],"type":"Point"}
}