{
  "id": 2188909,
  "type": "Feature",
  "properties": {
    "tgn:hierarchy":[
        "tgn:2188909",
        "tgn:1000001",
        "tgn:1002340",
        "tgn:7012149",
        "tgn:7007526",
        "tgn:7029392"
    ],
    "tgn:id":2188909,
    "tgn:name":"Boulder Hill",
    "tgn:placetype":[
        "aat:300008798"
    ]
},
  "bbox": [],
  "geometry": {"coordinates":[-119.3333,38.6833],"type":"Point"}
}