{
  "id": 2289838,
  "type": "Feature",
  "properties": {
    "tgn:hierarchy":[
        "tgn:2289838",
        "tgn:1000001",
        "tgn:7012149",
        "tgn:2002175",
        "tgn:7007919",
        "tgn:7029392"
    ],
    "tgn:id":2289838,
    "tgn:name":"Dobie Mountain",
    "tgn:placetype":[
        "aat:300008798"
    ]
},
  "bbox": [],
  "geometry": {"coordinates":[-78.8833,37.9667],"type":"Point"}
}