{
  "id": 2000947,
  "type": "Feature",
  "properties": {
    "tgn:hierarchy":[
        "tgn:2000947",
        "tgn:1000001",
        "tgn:7012149",
        "tgn:7007520",
        "tgn:7029392"
    ],
    "tgn:id":2000947,
    "tgn:name":"Baraga",
    "tgn:placetype":[
        "aat:300387145",
        "aat:300000771"
    ]
},
  "bbox": [],
  "geometry": {"coordinates":[-88.3667,46.65],"type":"Point"}
}