{
  "id": 7358391,
  "type": "Feature",
  "properties": {
    "tgn:hierarchy":[
        "tgn:7358391",
        "tgn:1000001",
        "tgn:1001960",
        "tgn:7005560",
        "tgn:7029392"
    ],
    "tgn:id":7358391,
    "tgn:name":"Coloniatte Juan de la Barrera",
    "tgn:placetype":[
        "aat:300387200"
    ]
},
  "bbox": [],
  "geometry": {"coordinates":[-112.25,30.55],"type":"Point"}
}