{
  "id": 7047715,
  "type": "Feature",
  "properties": {
    "tgn:hierarchy":[
        "tgn:7047715",
        "tgn:1000003",
        "tgn:7003155",
        "tgn:7003122",
        "tgn:1000080",
        "tgn:7029392"
    ],
    "tgn:id":7047715,
    "tgn:name":"Casa Pettinato",
    "tgn:placetype":[
        "aat:300008347"
    ]
},
  "bbox": [],
  "geometry": {"coordinates":[14.633333,37.766667],"type":"Point"}
}