{
  "id": 2482386,
  "type": "Feature",
  "properties": {
    "tgn:hierarchy":[
        "tgn:2482386",
        "tgn:1000001",
        "tgn:7012149",
        "tgn:2001716",
        "tgn:7007708",
        "tgn:7029392"
    ],
    "tgn:id":2482386,
    "tgn:name":"Langworthy Creek",
    "tgn:placetype":[
        "aat:300008706"
    ]
},
  "bbox": [],
  "geometry": {"coordinates":[-123.4333,44.0167],"type":"Point"}
}