{
  "id": 1096092,
  "type": "Feature",
  "properties": {
    "tgn:hierarchy":[
        "tgn:1096092",
        "tgn:7000490",
        "tgn:1000006",
        "tgn:7001834",
        "tgn:7029392"
    ],
    "tgn:id":1096092,
    "tgn:name":"Amery",
    "tgn:placetype":[
        "aat:300008347"
    ]
},
  "bbox": [],
  "geometry": {"coordinates":[117.05,-31.1833],"type":"Point"}
}