<<<<<<< HEAD
{
  "id": 7355982,
  "type": "Feature",
  "properties": {
    "tgn:hierarchy":[
        "tgn:7355982",
        "tgn:1000001",
        "tgn:7005599",
        "tgn:7005560",
        "tgn:7029392"
    ],
    "tgn:id":7355982,
    "tgn:name":"Cerro Alto",
    "tgn:placetype":[
        "aat:300008347"
    ]
},
  "bbox": [],
  "geometry": {"coordinates":[-95.966667,18.65],"type":"Point"}
}
=======
{"geometry":{"type":"Point","coordinates":[-95.966667,18.650000]},"type":"Feature","properties":{"hierarchy":["tgn:7355982","tgn:1000001","tgn:7005599","tgn:7005560","tgn:7029392"],"placetype":["aat:300008347"],"id":7355982,"name:xx":"Cerro Alto"}}
>>>>>>> 03f74aca74312dbeaf24d7e61306dd6a786dc3d0
