{
  "id": 2327684,
  "type": "Feature",
  "properties": {
    "tgn:hierarchy":[
        "tgn:2327684",
        "tgn:1000001",
        "tgn:2001586",
        "tgn:7012149",
        "tgn:7007705",
        "tgn:7029392"
    ],
    "tgn:id":2327684,
    "tgn:name":"Fish Creek",
    "tgn:placetype":[
        "aat:300008706"
    ]
},
  "bbox": [],
  "geometry": {"coordinates":[-101.2833,46.7333],"type":"Point"}
}