{
  "id": 2392704,
  "type": "Feature",
  "properties": {
    "tgn:hierarchy":[
        "tgn:2392704",
        "tgn:7002659",
        "tgn:1000001",
        "tgn:2000005",
        "tgn:7012149",
        "tgn:7029392"
    ],
    "tgn:id":2392704,
    "tgn:name":"Hobbie Lee Lake",
    "tgn:placetype":[
        "aat:300006191"
    ]
},
  "bbox": [],
  "geometry": {"coordinates":[-85.6667,32.0333],"type":"Point"}
}