{
  "id": 2352621,
  "type": "Feature",
  "properties": {
    "tgn:hierarchy":[
        "tgn:2352621",
        "tgn:1000001",
        "tgn:7012149",
        "tgn:7007158",
        "tgn:2000244",
        "tgn:7029392"
    ],
    "tgn:id":2352621,
    "tgn:name":"Goat Ranch Gulch",
    "tgn:placetype":[
        "aat:300008761"
    ]
},
  "bbox": [],
  "geometry": {"coordinates":[-106.2333,37.45],"type":"Point"}
}