{
  "id": 2380563,
  "type": "Feature",
  "properties": {
    "tgn:hierarchy":[
        "tgn:2380563",
        "tgn:1000001",
        "tgn:2001786",
        "tgn:7012149",
        "tgn:7007713",
        "tgn:7029392"
    ],
    "tgn:id":2380563,
    "tgn:name":"Haven Canyon",
    "tgn:placetype":[
        "aat:300008761"
    ]
},
  "bbox": [],
  "geometry": {"coordinates":[-103.5333,43.6667],"type":"Point"}
}