{
  "id": 7274432,
  "type": "Feature",
  "properties": {
    "tgn:hierarchy":[
        "tgn:7274432",
        "tgn:7003614",
        "tgn:1000003",
        "tgn:7016845",
        "tgn:7029392"
    ],
    "tgn:id":7274432,
    "tgn:name:nl":"Zuursche Landen",
    "tgn:placetype":[
        "aat:300387200"
    ]
},
  "bbox": [],
  "geometry": {"coordinates":[6.533333,53.083333],"type":"Point"}
}