{
  "id": 1067906,
  "type": "Feature",
  "properties": {
    "tgn:hierarchy":[
        "tgn:1067906",
        "tgn:1000004",
        "tgn:7001319",
        "tgn:1000111",
        "tgn:7029392"
    ],
    "tgn:id":1067906,
    "tgn:name":"Duopatela",
    "tgn:placetype":[
        "aat:300008347"
    ]
},
  "bbox": [],
  "geometry": {"coordinates":[88.2333,28.4667],"type":"Point"}
}