<<<<<<< HEAD
{
  "id": 7376090,
  "type": "Feature",
  "properties": {
    "tgn:hierarchy":[
        "tgn:7376090",
        "tgn:7005581",
        "tgn:1000001",
        "tgn:7005560",
        "tgn:7029392"
    ],
    "tgn:id":7376090,
    "tgn:name":"La Sierrita",
    "tgn:placetype":[
        "aat:300008777"
    ]
},
  "bbox": [],
  "geometry": {"coordinates":[-104.516667,29.45],"type":"Point"}
}
=======
{"geometry":{"type":"Point","coordinates":[-104.516667,29.450000]},"type":"Feature","properties":{"hierarchy":["tgn:7376090","tgn:7005581","tgn:1000001","tgn:7005560","tgn:7029392"],"placetype":["aat:300008777"],"id":7376090,"name:xx":"La Sierrita"}}
>>>>>>> 03f74aca74312dbeaf24d7e61306dd6a786dc3d0
