{
  "id": 7521382,
  "type": "Feature",
  "properties": {
    "tgn:hierarchy":[
        "tgn:7521382",
        "tgn:7001242",
        "tgn:7016833",
        "tgn:1001079",
        "tgn:7029392"
    ],
    "tgn:id":7521382,
    "tgn:name:en":"Akr\u0101sh, Jaz\u012brat al",
    "tgn:placetype":[
        "aat:300008791"
    ]
},
  "bbox": [],
  "geometry": {"coordinates":[29.783333,31.15],"type":"Point"}
}