<<<<<<< HEAD
{
  "id": 2337844,
  "type": "Feature",
  "properties": {
    "tgn:hierarchy":[
        "tgn:2337844",
        "tgn:1000001",
        "tgn:7012149",
        "tgn:2001029",
        "tgn:7007521",
        "tgn:7029392"
    ],
    "tgn:id":2337844,
    "tgn:name":"Fox Farm Lake",
    "tgn:placetype":[
        "aat:300008680"
    ]
},
  "bbox": [],
  "geometry": {"coordinates":[-93.6167,47.6833],"type":"Point"}
}
=======
{"geometry":{"type":"Point","coordinates":[-93.616700,47.683300]},"type":"Feature","properties":{"hierarchy":["tgn:2337844","tgn:1000001","tgn:7012149","tgn:2001029","tgn:7007521","tgn:7029392"],"placetype":["aat:300008680"],"id":2337844,"name:xx":"Fox Farm Lake"}}
>>>>>>> 03f74aca74312dbeaf24d7e61306dd6a786dc3d0
