<<<<<<< HEAD
{
  "id": 7356600,
  "type": "Feature",
  "properties": {
    "tgn:hierarchy":[
        "tgn:7356600",
        "tgn:7005585",
        "tgn:1000001",
        "tgn:7005560",
        "tgn:7029392"
    ],
    "tgn:id":7356600,
    "tgn:name":"Carricito",
    "tgn:placetype":[
        "aat:300008347"
    ]
},
  "bbox": [],
  "geometry": {"coordinates":[-101.516667,18.1],"type":"Point"}
}
=======
{"geometry":{"type":"Point","coordinates":[-101.516667,18.100000]},"type":"Feature","properties":{"hierarchy":["tgn:7356600","tgn:7005585","tgn:1000001","tgn:7005560","tgn:7029392"],"placetype":["aat:300008347"],"id":7356600,"name:xx":"Carricito"}}
>>>>>>> 03f74aca74312dbeaf24d7e61306dd6a786dc3d0
