{
  "id": 7341093,
  "type": "Feature",
  "properties": {
    "tgn:hierarchy":[
        "tgn:7341093",
        "tgn:7002758",
        "tgn:7002821",
        "tgn:1000003",
        "tgn:1000095",
        "tgn:7029392"
    ],
    "tgn:id":7341093,
    "tgn:name":"Buenavista",
    "tgn:placetype":[
        "aat:300008347"
    ]
},
  "bbox": [],
  "geometry": {"coordinates":[-3.716667,37.233333],"type":"Point"}
}