{
  "id": 2203372,
  "type": "Feature",
  "properties": {
    "tgn:hierarchy":[
        "tgn:2203372",
        "tgn:1000001",
        "tgn:7012149",
        "tgn:7007919",
        "tgn:7029392"
    ],
    "tgn:id":2203372,
    "tgn:name":"Buckhorn Ridge",
    "tgn:placetype":[
        "aat:300266640"
    ]
},
  "bbox": [],
  "geometry": {"coordinates":[-81.8833,36.8833],"type":"Point"}
}