{
  "id": 2323563,
  "type": "Feature",
  "properties": {
    "tgn:hierarchy":[
        "tgn:2323563",
        "tgn:1000001",
        "tgn:7012149",
        "tgn:1002785",
        "tgn:7007920",
        "tgn:7029392"
    ],
    "tgn:id":2323563,
    "tgn:name":"Farrell Marsh",
    "tgn:placetype":[
        "aat:300008905"
    ]
},
  "bbox": [],
  "geometry": {"coordinates":[-122.5833,47.15],"type":"Point"}
}