{
  "id": 1108228,
  "type": "Feature",
  "properties": {
    "tgn:hierarchy":[
        "tgn:1108228",
        "tgn:7000096",
        "tgn:1000003",
        "tgn:7000084",
        "tgn:7029392"
    ],
    "tgn:id":1108228,
    "tgn:name":"Stahl-Berg",
    "tgn:placetype":[
        "aat:300008777"
    ]
},
  "bbox": [],
  "geometry": {"coordinates":[13.766667,52.35],"type":"Point"}
}