{
  "id": 1042193,
  "type": "Feature",
  "properties": {
    "tgn:hierarchy":[
        "tgn:1042193",
        "tgn:7002705",
        "tgn:1000003",
        "tgn:1000074",
        "tgn:7029392"
    ],
    "tgn:id":1042193,
    "tgn:name":"Pr\u00e9veza",
    "tgn:placetype":[
        "aat:300387145",
        "aat:300000772",
        "aat:300387131"
    ]
},
  "bbox": [],
  "geometry": {"coordinates":[20.6667,39.1667],"type":"Point"}
}