{
  "id": 2167370,
  "type": "Feature",
  "properties": {
    "tgn:hierarchy":[
        "tgn:2167370",
        "tgn:1000001",
        "tgn:2001481",
        "tgn:7012149",
        "tgn:7007709",
        "tgn:7029392"
    ],
    "tgn:id":2167370,
    "tgn:name":"Big Cove Branch",
    "tgn:placetype":[
        "aat:300008699"
    ]
},
  "bbox": [],
  "geometry": {"coordinates":[-83.8333,35.2333],"type":"Point"}
}