{
  "id": 7584187,
  "type": "Feature",
  "properties": {
    "tgn:hierarchy":[
        "tgn:7584187",
        "tgn:1000004",
        "tgn:7000198",
        "tgn:7016788",
        "tgn:7029392"
    ],
    "tgn:id":7584187,
    "tgn:name:en":"Gogatia Ch\u0101rn\u0101n",
    "tgn:placetype":[
        "aat:300008347"
    ]
},
  "bbox": [],
  "geometry": {"coordinates":[75.047361,28.623627],"type":"Point"}
}