{
  "id": 2539377,
  "type": "Feature",
  "properties": {
    "tgn:hierarchy":[
        "tgn:2539377",
        "tgn:7030516",
        "tgn:7006450",
        "tgn:1000001",
        "tgn:7012149",
        "tgn:7029392"
    ],
    "tgn:id":2539377,
    "tgn:name":"New Lakes",
    "tgn:placetype":[
        "aat:300008680"
    ]
},
  "bbox": [],
  "geometry": {"coordinates":[177.6333,51.95],"type":"Point"}
}