{
  "id": 7217704,
  "type": "Feature",
  "properties": {
    "tgn:hierarchy":[
        "tgn:7217704",
        "tgn:7002690",
        "tgn:7012056",
        "tgn:1000003",
        "tgn:1000074",
        "tgn:7029392"
    ],
    "tgn:id":7217704,
    "tgn:name":"Yerop\u00f3tamos",
    "tgn:placetype":[
        "aat:300008699"
    ]
},
  "bbox": [],
  "geometry": {"coordinates":[24.65,35.416667],"type":"Point"}
}