{
  "id": 2356068,
  "type": "Feature",
  "properties": {
    "tgn:hierarchy":[
        "tgn:2356068",
        "tgn:1000001",
        "tgn:7012149",
        "tgn:2001852",
        "tgn:7007825",
        "tgn:7029392"
    ],
    "tgn:id":2356068,
    "tgn:name":"Goose Pond",
    "tgn:placetype":[
        "aat:300008680"
    ]
},
  "bbox": [],
  "geometry": {"coordinates":[-86.0167,35.3833],"type":"Point"}
}