{
  "id": 2235910,
  "type": "Feature",
  "properties": {
    "tgn:hierarchy":[
        "tgn:2235910",
        "tgn:7021987",
        "tgn:1000001",
        "tgn:7012149",
        "tgn:7007516",
        "tgn:7029392"
    ],
    "tgn:id":2235910,
    "tgn:name":"Cheswolde",
    "tgn:placetype":[
        "aat:300008347"
    ]
},
  "bbox": [],
  "geometry": {"coordinates":[-76.6833,39.35],"type":"Point"}
}