{
  "id": 2140832,
  "type": "Feature",
  "properties": {
    "tgn:hierarchy":[
        "tgn:2140832",
        "tgn:1000001",
        "tgn:7012149",
        "tgn:2000986",
        "tgn:7007520",
        "tgn:7029392"
    ],
    "tgn:id":2140832,
    "tgn:name":"Avant Pond",
    "tgn:placetype":[
        "aat:300008680"
    ]
},
  "bbox": [],
  "geometry": {"coordinates":[-88.9833,46.3333],"type":"Point"}
}