{
  "id": 2665618,
  "type": "Feature",
  "properties": {
    "tgn:hierarchy":[
        "tgn:2665618",
        "tgn:1000001",
        "tgn:7012149",
        "tgn:2002189",
        "tgn:7007919",
        "tgn:7029392"
    ],
    "tgn:id":2665618,
    "tgn:name":"Sinking Spring",
    "tgn:placetype":[
        "aat:300008697"
    ]
},
  "bbox": [],
  "geometry": {"coordinates":[-82.4333,36.8333],"type":"Point"}
}