{
  "id": 7313395,
  "type": "Feature",
  "properties": {
    "tgn:hierarchy":[
        "tgn:7313395",
        "tgn:1001699",
        "tgn:1000049",
        "tgn:1000002",
        "tgn:7029392"
    ],
    "tgn:id":7313395,
    "tgn:name":"Legleufu, Estero",
    "tgn:placetype":[
        "aat:300008699"
    ]
},
  "bbox": [],
  "geometry": {"coordinates":[-72.733333,-39.833333],"type":"Point"}
}