{
  "id": 7099466,
  "type": "Feature",
  "properties": {
    "tgn:hierarchy":[
        "tgn:7099466",
        "tgn:7003692",
        "tgn:1000003",
        "tgn:7000084",
        "tgn:7029392"
    ],
    "tgn:id":7099466,
    "tgn:name":"Klosterhof",
    "tgn:placetype":[
        "aat:300000206"
    ]
},
  "bbox": [],
  "geometry": {"coordinates":[8.483333,48.133333],"type":"Point"}
}