{
  "id": 2285461,
  "type": "Feature",
  "properties": {
    "tgn:hierarchy":[
        "tgn:2285461",
        "tgn:7006450",
        "tgn:1000001",
        "tgn:7012149",
        "tgn:2000088",
        "tgn:7029392"
    ],
    "tgn:id":2285461,
    "tgn:name":"Devils Elbow",
    "tgn:placetype":[
        "aat:300132316"
    ]
},
  "bbox": [],
  "geometry": {"coordinates":[-133.6833,56.6333],"type":"Point"}
}