<<<<<<< HEAD
{
  "id": 2157585,
  "type": "Feature",
  "properties": {
    "tgn:hierarchy":[
        "tgn:2157585",
        "tgn:1000001",
        "tgn:7012149",
        "tgn:2001036",
        "tgn:7007521",
        "tgn:7029392"
    ],
    "tgn:id":2157585,
    "tgn:name":"Beaver Crossing",
    "tgn:placetype":[
        "aat:300008347"
    ]
},
  "bbox": [],
  "geometry": {"coordinates":[-91.5167,47.2333],"type":"Point"}
}
=======
{"geometry":{"type":"Point","coordinates":[-91.516700,47.233300]},"type":"Feature","properties":{"hierarchy":["tgn:2157585","tgn:1000001","tgn:7012149","tgn:2001036","tgn:7007521","tgn:7029392"],"placetype":["aat:300008347"],"id":2157585,"name:xx":"Beaver Crossing"}}
>>>>>>> 03f74aca74312dbeaf24d7e61306dd6a786dc3d0
