{
  "id": 7222443,
  "type": "Feature",
  "properties": {
    "tgn:hierarchy":[
        "tgn:7222443",
        "tgn:7002715",
        "tgn:7002731",
        "tgn:1000003",
        "tgn:1000074",
        "tgn:7029392"
    ],
    "tgn:id":7222443,
    "tgn:name":"Met\u00f3khion Patriotik\u00f3n",
    "tgn:placetype":[
        "aat:300008347"
    ]
},
  "bbox": [],
  "geometry": {"coordinates":[23.35,40.15],"type":"Point"}
}