{
  "id": 7451596,
  "type": "Feature",
  "properties": {
    "tgn:hierarchy":[
        "tgn:7451596",
        "tgn:7002445",
        "tgn:1000003",
        "tgn:7008134",
        "tgn:7008591",
        "tgn:7029392"
    ],
    "tgn:id":7451596,
    "tgn:name:en":"East Bank",
    "tgn:placetype":[
        "aat:300387036"
    ]
},
  "bbox": [],
  "geometry": {"coordinates":[-0.666667,50.683333],"type":"Point"}
}