{
  "id": 2241153,
  "type": "Feature",
  "properties": {
    "tgn:hierarchy":[
        "tgn:2241153",
        "tgn:1000001",
        "tgn:7012149",
        "tgn:2001211",
        "tgn:7007523",
        "tgn:7029392"
    ],
    "tgn:id":2241153,
    "tgn:name":"Clark Ford",
    "tgn:placetype":[
        "aat:300008347"
    ]
},
  "bbox": [],
  "geometry": {"coordinates":[-92.3833,37.5167],"type":"Point"}
}