{
  "id": 2546281,
  "type": "Feature",
  "properties": {
    "tgn:hierarchy":[
        "tgn:2546281",
        "tgn:1000001",
        "tgn:1002326",
        "tgn:7012149",
        "tgn:7007706",
        "tgn:7029392"
    ],
    "tgn:id":2546281,
    "tgn:name":"North Fork Gordon Creek",
    "tgn:placetype":[
        "aat:300008706"
    ]
},
  "bbox": [],
  "geometry": {"coordinates":[-84.7333,41.35],"type":"Point"}
}