{
  "id": 2438223,
  "type": "Feature",
  "properties": {
    "tgn:hierarchy":[
        "tgn:2438223",
        "tgn:1000001",
        "tgn:7012149",
        "tgn:2001909",
        "tgn:7007825",
        "tgn:7029392"
    ],
    "tgn:id":2438223,
    "tgn:name":"Kings Bar",
    "tgn:placetype":[
        "aat:300132348"
    ]
},
  "bbox": [],
  "geometry": {"coordinates":[-84.65,35.7833],"type":"Point"}
}