{
  "id": 7483535,
  "type": "Feature",
  "properties": {
    "tgn:hierarchy":[
        "tgn:7483535",
        "tgn:7001004",
        "tgn:1000004",
        "tgn:1000141",
        "tgn:7029392"
    ],
    "tgn:id":7483535,
    "tgn:name":"Tengzhi Shan",
    "tgn:placetype":[
        "aat:300008798"
    ]
},
  "bbox": [],
  "geometry": {"coordinates":[120.738611,23.062222],"type":"Point"}
}