<<<<<<< HEAD
{
  "id": 2403484,
  "type": "Feature",
  "properties": {
    "tgn:hierarchy":[
        "tgn:2403484",
        "tgn:1000001",
        "tgn:7012149",
        "tgn:7007157",
        "tgn:2000189",
        "tgn:7029392"
    ],
    "tgn:id":2403484,
    "tgn:name":"Hovey Point",
    "tgn:placetype":[
        "aat:300008850"
    ]
},
  "bbox": [],
  "geometry": {"coordinates":[-121.5,41.8333],"type":"Point"}
}
=======
{"geometry":{"type":"Point","coordinates":[-121.500000,41.833300]},"type":"Feature","properties":{"hierarchy":["tgn:2403484","tgn:1000001","tgn:7012149","tgn:7007157","tgn:2000189","tgn:7029392"],"placetype":["aat:300008850"],"id":2403484,"name:xx":"Hovey Point"}}
>>>>>>> 03f74aca74312dbeaf24d7e61306dd6a786dc3d0
