{
  "id": 2624438,
  "type": "Feature",
  "properties": {
    "tgn:hierarchy":[
        "tgn:2624438",
        "tgn:2002365",
        "tgn:1000001",
        "tgn:7012149",
        "tgn:7007923",
        "tgn:7029392"
    ],
    "tgn:id":2624438,
    "tgn:name":"Rock Mountain",
    "tgn:placetype":[
        "aat:300008798"
    ]
},
  "bbox": [],
  "geometry": {"coordinates":[-105.3667,42.35],"type":"Point"}
}