{
  "id": 2312961,
  "type": "Feature",
  "properties": {
    "tgn:hierarchy":[
        "tgn:2312961",
        "tgn:1000001",
        "tgn:7012149",
        "tgn:1002619",
        "tgn:7007523",
        "tgn:7029392"
    ],
    "tgn:id":2312961,
    "tgn:name":"Elam Creek",
    "tgn:placetype":[
        "aat:300008706"
    ]
},
  "bbox": [],
  "geometry": {"coordinates":[-92.65,39.7833],"type":"Point"}
}