<<<<<<< HEAD
{
  "id": 7029659,
  "type": "Feature",
  "properties": {
    "tgn:hierarchy":[
        "tgn:7029659",
        "tgn:7002810",
        "tgn:7001158",
        "tgn:1000003",
        "tgn:1000095",
        "tgn:7029392"
    ],
    "tgn:id":7029659,
    "tgn:name:es":"Mu\u00f1eca",
    "tgn:placetype":[
        "aat:300008347"
    ]
},
  "bbox": [],
  "geometry": {"coordinates":[-4.8,42.8],"type":"Point"}
}
=======
{"geometry":{"type":"Point","coordinates":[-4.800000,42.800000]},"type":"Feature","properties":{"hierarchy":["tgn:7029659","tgn:7002810","tgn:7001158","tgn:1000003","tgn:1000095","tgn:7029392"],"placetype":["aat:300008347"],"id":7029659,"name:es":"Mu\u00f1eca"}}
>>>>>>> 03f74aca74312dbeaf24d7e61306dd6a786dc3d0
