{
  "id": 2716060,
  "type": "Feature",
  "properties": {
    "tgn:hierarchy":[
        "tgn:2716060",
        "tgn:1000001",
        "tgn:7012149",
        "tgn:7007157",
        "tgn:1002972",
        "tgn:7029392"
    ],
    "tgn:id":2716060,
    "tgn:name":"Thacher Creek",
    "tgn:placetype":[
        "aat:300008706"
    ]
},
  "bbox": [],
  "geometry": {"coordinates":[-119.15,34.4833],"type":"Point"}
}