{
  "id": 2496717,
  "type": "Feature",
  "properties": {
    "tgn:hierarchy":[
        "tgn:2496717",
        "tgn:1000001",
        "tgn:7012149",
        "tgn:1002487",
        "tgn:7007252",
        "tgn:7029392"
    ],
    "tgn:id":2496717,
    "tgn:name":"Matthew Howell Ditch",
    "tgn:placetype":[
        "aat:300006075"
    ]
},
  "bbox": [],
  "geometry": {"coordinates":[-85.9333,40.5167],"type":"Point"}
}