{
  "id": 2217396,
  "type": "Feature",
  "properties": {
    "tgn:hierarchy":[
        "tgn:2217396",
        "tgn:1000001",
        "tgn:2000772",
        "tgn:7012149",
        "tgn:7007255",
        "tgn:7029392"
    ],
    "tgn:id":2217396,
    "tgn:name":"Campbell Branch",
    "tgn:placetype":[
        "aat:300008699"
    ]
},
  "bbox": [],
  "geometry": {"coordinates":[-83.2667,37.4167],"type":"Point"}
}