{
  "id": 7436239,
  "type": "Feature",
  "properties": {
    "tgn:hierarchy":[
        "tgn:7436239",
        "tgn:7005583",
        "tgn:1000001",
        "tgn:7005560",
        "tgn:7029392"
    ],
    "tgn:id":7436239,
    "tgn:name":"Tayafe",
    "tgn:placetype":[
        "aat:300008347"
    ]
},
  "bbox": [],
  "geometry": {"coordinates":[-104.616667,24.033333],"type":"Point"}
}