{
  "id": 2266937,
  "type": "Feature",
  "properties": {
    "tgn:hierarchy":[
        "tgn:2266937",
        "tgn:1000001",
        "tgn:7012149",
        "tgn:7007157",
        "tgn:1002656",
        "tgn:7029392"
    ],
    "tgn:id":2266937,
    "tgn:name":"Cressey Lateral",
    "tgn:placetype":[
        "aat:300006075"
    ]
},
  "bbox": [],
  "geometry": {"coordinates":[-120.6333,37.4167],"type":"Point"}
}