{
  "id": 2564355,
  "type": "Feature",
  "properties": {
    "tgn:hierarchy":[
        "tgn:2564355",
        "tgn:1000001",
        "tgn:7012149",
        "tgn:7007566",
        "tgn:7029392"
    ],
    "tgn:id":2564355,
    "tgn:name":"Pacheco Tank",
    "tgn:placetype":[
        "aat:300006191"
    ]
},
  "bbox": [],
  "geometry": {"coordinates":[-104.75,33.9833],"type":"Point"}
}