{
  "id": 7008471,
  "type": "Feature",
  "properties": {
    "tgn:hierarchy":[
        "tgn:7008471",
        "tgn:1000003",
        "tgn:7001097",
        "tgn:1000070",
        "tgn:7029392"
    ],
    "tgn:id":7008471,
    "tgn:name":"Valenciennes",
    "tgn:placetype":[
        "aat:300008347",
        "aat:300387218",
        "aat:300008375",
        "aat:300387302"
    ]
},
  "bbox": [],
  "geometry": {"coordinates":[3.5333,50.3667],"type":"Point"}
}