{
  "id": 7010774,
  "type": "Feature",
  "properties": {
    "tgn:hierarchy":[
        "tgn:7010774",
        "tgn:7003821",
        "tgn:1000003",
        "tgn:1000090",
        "tgn:7029392"
    ],
    "tgn:id":7010774,
    "tgn:name":"Borba",
    "tgn:placetype":[
        "aat:300008347",
        "aat:300387218"
    ]
},
  "bbox": [],
  "geometry": {"coordinates":[-7.454,38.805],"type":"Point"}
}