{
  "id": 7542796,
  "type": "Feature",
  "properties": {
    "tgn:hierarchy":[
        "tgn:7542796",
        "tgn:7001242",
        "tgn:7016833",
        "tgn:7001336",
        "tgn:7029392"
    ],
    "tgn:id":7542796,
    "tgn:name:en":"Ab\u016b Samrah, W\u0101d\u012b",
    "tgn:placetype":[
        "aat:300379998"
    ]
},
  "bbox": [],
  "geometry": {"coordinates":[34.390278,28.701944],"type":"Point"}
}