{
  "id": 2724580,
  "type": "Feature",
  "properties": {
    "tgn:hierarchy":[
        "tgn:2724580",
        "tgn:1000001",
        "tgn:7012149",
        "tgn:2001247",
        "tgn:7007523",
        "tgn:7029392"
    ],
    "tgn:id":2724580,
    "tgn:name":"Tomahawk Hollow",
    "tgn:placetype":[
        "aat:300008761"
    ]
},
  "bbox": [],
  "geometry": {"coordinates":[-91.2167,37.3333],"type":"Point"}
}