{
  "id": 7506283,
  "type": "Feature",
  "properties": {
    "tgn:hierarchy":[
        "tgn:7506283",
        "tgn:7000509",
        "tgn:1008380",
        "tgn:1000226",
        "tgn:1000006",
        "tgn:7029392"
    ],
    "tgn:id":7506283,
    "tgn:name:en":"Rurima Rocks",
    "tgn:placetype":[
        "aat:300011692"
    ]
},
  "bbox": [],
  "geometry": {"coordinates":[176.883333,-37.833333],"type":"Point"}
}