{
  "id": 7591252,
  "type": "Feature",
  "properties": {
    "tgn:hierarchy":[
        "tgn:7591252",
        "tgn:1000004",
        "tgn:7000198",
        "tgn:7031786",
        "tgn:7029392"
    ],
    "tgn:id":7591252,
    "tgn:name:en":"Jamn\u012bpur",
    "tgn:placetype":[
        "aat:300008347"
    ]
},
  "bbox": [],
  "geometry": {"coordinates":[77.771274,30.434013],"type":"Point"}
}