{
  "id": 1004884,
  "type": "Feature",
  "properties": {
    "tgn:hierarchy":[
        "tgn:1004884",
        "tgn:7002445",
        "tgn:1000003",
        "tgn:7029504",
        "tgn:7008591",
        "tgn:7029392"
    ],
    "tgn:id":1004884,
    "tgn:name:en":"Knowsley",
    "tgn:placetype":[
        "aat:300387064",
        "aat:300000778",
        "aat:300387071"
    ]
},
  "bbox": [],
  "geometry": {"coordinates":[-2.85,53.45],"type":"Point"}
}