{
  "id": 1112375,
  "type": "Feature",
  "properties": {
    "tgn:hierarchy":[
        "tgn:1112375",
        "tgn:1000004",
        "tgn:7017024",
        "tgn:7018214",
        "tgn:7002435",
        "tgn:7029392"
    ],
    "tgn:id":1112375,
    "tgn:name":"Faddeya, Zaliv",
    "tgn:placetype":[
        "aat:300132315"
    ]
},
  "bbox": [],
  "geometry": {"coordinates":[107.3333,76.6667],"type":"Point"}
}