{
  "id": 7514306,
  "type": "Feature",
  "properties": {
    "tgn:hierarchy":[
        "tgn:7514306",
        "tgn:1009227",
        "tgn:1000226",
        "tgn:7016822",
        "tgn:1000006",
        "tgn:7029392"
    ],
    "tgn:id":7514306,
    "tgn:name:en":"Dunsdale",
    "tgn:placetype":[
        "aat:300008798"
    ]
},
  "bbox": [],
  "geometry": {"coordinates":[168.666667,-46.133333],"type":"Point"}
}