{
  "id": 7535142,
  "type": "Feature",
  "properties": {
    "tgn:hierarchy":[
        "tgn:7535142",
        "tgn:7001242",
        "tgn:1001075",
        "tgn:7016833",
        "tgn:7029392"
    ],
    "tgn:id":7535142,
    "tgn:name:en":"Kafr ad Daww\u0101r, Ma\u015frif",
    "tgn:placetype":[
        "aat:300387086"
    ]
},
  "bbox": [],
  "geometry": {"coordinates":[30.15,31.166667],"type":"Point"}
}