{
  "id": 2149111,
  "type": "Feature",
  "properties": {
    "tgn:hierarchy":[
        "tgn:2149111",
        "tgn:1000001",
        "tgn:2001646",
        "tgn:7012149",
        "tgn:7007707",
        "tgn:7029392"
    ],
    "tgn:id":2149111,
    "tgn:name":"Barr",
    "tgn:placetype":[
        "aat:300008347"
    ]
},
  "bbox": [],
  "geometry": {"coordinates":[-98.0333,36.2167],"type":"Point"}
}