{
  "id": 2369099,
  "type": "Feature",
  "properties": {
    "tgn:hierarchy":[
        "tgn:2369099",
        "tgn:1000001",
        "tgn:2002263",
        "tgn:7012149",
        "tgn:7013961",
        "tgn:7029392"
    ],
    "tgn:id":2369099,
    "tgn:name":"Gum Hollow",
    "tgn:placetype":[
        "aat:300008761"
    ]
},
  "bbox": [],
  "geometry": {"coordinates":[-79.1667,38.95],"type":"Point"}
}