{
  "id": 7234421,
  "type": "Feature",
  "properties": {
    "tgn:hierarchy":[
        "tgn:7234421",
        "tgn:7002690",
        "tgn:7012056",
        "tgn:1000003",
        "tgn:1000074",
        "tgn:7029392"
    ],
    "tgn:id":7234421,
    "tgn:name":"Dhamav\u00f3los",
    "tgn:placetype":[
        "aat:300008347"
    ]
},
  "bbox": [],
  "geometry": {"coordinates":[24.75,35.35],"type":"Point"}
}