{
  "id": 2387772,
  "type": "Feature",
  "properties": {
    "tgn:hierarchy":[
        "tgn:2387772",
        "tgn:2000942",
        "tgn:1000001",
        "tgn:7012149",
        "tgn:7007520",
        "tgn:7029392"
    ],
    "tgn:id":2387772,
    "tgn:name":"Hickey Hill",
    "tgn:placetype":[
        "aat:300008798"
    ]
},
  "bbox": [],
  "geometry": {"coordinates":[-83.55,44.8333],"type":"Point"}
}