{
  "id": 2617468,
  "type": "Feature",
  "properties": {
    "tgn:hierarchy":[
        "tgn:2617468",
        "tgn:1000001",
        "tgn:2002103",
        "tgn:7012149",
        "tgn:7007827",
        "tgn:7029392"
    ],
    "tgn:id":2617468,
    "tgn:name":"Richmond Knoll",
    "tgn:placetype":[
        "aat:300008798"
    ]
},
  "bbox": [],
  "geometry": {"coordinates":[-111.7833,41.95],"type":"Point"}
}