{
  "id": 1075617,
  "type": "Feature",
  "properties": {
    "tgn:hierarchy":[
        "tgn:1075617",
        "tgn:1000004",
        "tgn:7000198",
        "tgn:7016788",
        "tgn:7029392"
    ],
    "tgn:id":1075617,
    "tgn:name":"Jalawar",
    "tgn:placetype":[
        "aat:300008347"
    ]
},
  "bbox": [],
  "geometry": {"coordinates":[76.165029,24.596764],"type":"Point"}
}