{
  "id": 2488681,
  "type": "Feature",
  "properties": {
    "tgn:hierarchy":[
        "tgn:2488681",
        "tgn:1000001",
        "tgn:7012149",
        "tgn:7007708",
        "tgn:7029392"
    ],
    "tgn:id":2488681,
    "tgn:name":"Maiden Peak",
    "tgn:placetype":[
        "aat:300008798"
    ]
},
  "bbox": [],
  "geometry": {"coordinates":[-121.95,43.6167],"type":"Point"}
}