{
  "id": 7119102,
  "type": "Feature",
  "properties": {
    "tgn:hierarchy":[
        "tgn:7119102",
        "tgn:7003669",
        "tgn:1000003",
        "tgn:7000084",
        "tgn:7029392"
    ],
    "tgn:id":7119102,
    "tgn:name":"Piehl",
    "tgn:placetype":[
        "aat:300000206"
    ]
},
  "bbox": [],
  "geometry": {"coordinates":[12.433333,49.033333],"type":"Point"}
}