{
  "id": 7256188,
  "type": "Feature",
  "properties": {
    "tgn:concordances":{
        "gn:id":"2759087"
    },
    "tgn:hierarchy":[
        "tgn:7256188",
        "tgn:1000003",
        "tgn:7003622",
        "tgn:7016845",
        "tgn:7029392"
    ],
    "tgn:id":7256188,
    "tgn:name:nl":"Berkelaar",
    "tgn:placetype":[
        "aat:300008347"
    ]
},
  "bbox": [],
  "geometry": {"coordinates":[5.866667,51.116667],"type":"Point"}
}