{
  "id": 2712915,
  "type": "Feature",
  "properties": {
    "tgn:hierarchy":[
        "tgn:2712915",
        "tgn:1000001",
        "tgn:7012149",
        "tgn:2001289",
        "tgn:7007524",
        "tgn:7029392"
    ],
    "tgn:id":2712915,
    "tgn:name":"Taylor Hills",
    "tgn:placetype":[
        "aat:300008798"
    ]
},
  "bbox": [],
  "geometry": {"coordinates":[-111.0167,46.9667],"type":"Point"}
}