<<<<<<< HEAD
{
  "id": 2335810,
  "type": "Feature",
  "properties": {
    "tgn:hierarchy":[
        "tgn:2335810",
        "tgn:1000001",
        "tgn:7012149",
        "tgn:7007157",
        "tgn:1002957",
        "tgn:7029392"
    ],
    "tgn:id":2335810,
    "tgn:name":"Fortynine Mine",
    "tgn:placetype":[
        "aat:300000390",
        "aat:300386993"
    ]
},
  "bbox": [],
  "geometry": {"coordinates":[-120.4,37.7333],"type":"Point"}
}
=======
{"geometry":{"type":"Point","coordinates":[-120.400000,37.733300]},"type":"Feature","properties":{"hierarchy":["tgn:2335810","tgn:1000001","tgn:7012149","tgn:7007157","tgn:1002957","tgn:7029392"],"placetype":["aat:300000390","aat:300386993"],"id":2335810,"name:xx":"Fortynine Mine"}}
>>>>>>> 03f74aca74312dbeaf24d7e61306dd6a786dc3d0
