{
  "id": 7290654,
  "type": "Feature",
  "properties": {
    "tgn:hierarchy":[
        "tgn:7290654",
        "tgn:1001692",
        "tgn:1000049",
        "tgn:1000002",
        "tgn:7029392"
    ],
    "tgn:id":7290654,
    "tgn:name":"Cuntruncahue",
    "tgn:placetype":[
        "aat:300387200"
    ]
},
  "bbox": [],
  "geometry": {"coordinates":[-72.683333,-39.416667],"type":"Point"}
}