{
  "id": 1055587,
  "type": "Feature",
  "properties": {
    "tgn:hierarchy":[
        "tgn:1055587",
        "tgn:1000003",
        "tgn:1003410",
        "tgn:7006660",
        "tgn:7029392"
    ],
    "tgn:id":1055587,
    "tgn:name":"Konotop",
    "tgn:placetype":[
        "aat:300008347"
    ]
},
  "bbox": [],
  "geometry": {"coordinates":[33.2333,51.25],"type":"Point"}
}