<<<<<<< HEAD
{
  "id": 2763158,
  "type": "Feature",
  "properties": {
    "tgn:hierarchy":[
        "tgn:2763158",
        "tgn:1002201",
        "tgn:1000001",
        "tgn:7012149",
        "tgn:7007517",
        "tgn:7029392"
    ],
    "tgn:id":2763158,
    "tgn:name":"Westview Park",
    "tgn:placetype":[
        "aat:300008347"
    ]
},
  "bbox": [],
  "geometry": {"coordinates":[-70.95,41.6333],"type":"Point"}
}
=======
{"geometry":{"type":"Point","coordinates":[-70.950000,41.633300]},"type":"Feature","properties":{"hierarchy":["tgn:2763158","tgn:1002201","tgn:1000001","tgn:7012149","tgn:7007517","tgn:7029392"],"placetype":["aat:300008347"],"id":2763158,"name:xx":"Westview Park"}}
>>>>>>> 03f74aca74312dbeaf24d7e61306dd6a786dc3d0
