{
  "id": 2001773,
  "type": "Feature",
  "properties": {
    "tgn:hierarchy":[
        "tgn:2001773",
        "tgn:1000001",
        "tgn:7012149",
        "tgn:7007713",
        "tgn:7029392"
    ],
    "tgn:id":2001773,
    "tgn:name":"Bennett",
    "tgn:placetype":[
        "aat:300387145",
        "aat:300000771"
    ]
},
  "bbox": [],
  "geometry": {"coordinates":[-101.6833,43.1833],"type":"Point"}
}