{
  "id": 2778430,
  "type": "Feature",
  "properties": {
    "tgn:hierarchy":[
        "tgn:2778430",
        "tgn:1000001",
        "tgn:7012149",
        "tgn:2001920",
        "tgn:7007825",
        "tgn:7029392"
    ],
    "tgn:id":2778430,
    "tgn:name":"Witherington Lake",
    "tgn:placetype":[
        "aat:300006191"
    ]
},
  "bbox": [],
  "geometry": {"coordinates":[-89.8667,35.5167],"type":"Point"}
}