{
  "id": 2282702,
  "type": "Feature",
  "properties": {
    "tgn:hierarchy":[
        "tgn:2282702",
        "tgn:1000001",
        "tgn:7012149",
        "tgn:2001420",
        "tgn:7007526",
        "tgn:7029392"
    ],
    "tgn:id":2282702,
    "tgn:name":"Deerhead Canyon",
    "tgn:placetype":[
        "aat:300008761"
    ]
},
  "bbox": [],
  "geometry": {"coordinates":[-114.2167,39.2833],"type":"Point"}
}