{
  "id": 7276401,
  "type": "Feature",
  "properties": {
    "tgn:hierarchy":[
        "tgn:7276401",
        "tgn:1001705",
        "tgn:1000049",
        "tgn:1000002",
        "tgn:7029392"
    ],
    "tgn:id":7276401,
    "tgn:name":"Ticautaro",
    "tgn:placetype":[
        "aat:300000206"
    ]
},
  "bbox": [],
  "geometry": {"coordinates":[-72.416667,-36.166667],"type":"Point"}
}