{
  "id": 2358508,
  "type": "Feature",
  "properties": {
    "tgn:hierarchy":[
        "tgn:2358508",
        "tgn:1000001",
        "tgn:7012149",
        "tgn:2000206",
        "tgn:7007158",
        "tgn:7029392"
    ],
    "tgn:id":2358508,
    "tgn:name":"Grand Vrew Mesa",
    "tgn:placetype":[
        "aat:300008798"
    ]
},
  "bbox": [],
  "geometry": {"coordinates":[-107.6833,38.6833],"type":"Point"}
}