{
  "id": 1039033,
  "type": "Feature",
  "properties": {
    "tgn:hierarchy":[
        "tgn:1039033",
        "tgn:1000003",
        "tgn:7003676",
        "tgn:7000084",
        "tgn:7029392"
    ],
    "tgn:id":1039033,
    "tgn:name":"Esterwegen",
    "tgn:placetype":[
        "aat:300008347"
    ]
},
  "bbox": [],
  "geometry": {"coordinates":[7.616667,52.983333],"type":"Point"}
}