{
  "id": 7466978,
  "type": "Feature",
  "properties": {
    "tgn:hierarchy":[
        "tgn:7466978",
        "tgn:5000432",
        "tgn:7002444",
        "tgn:1000003",
        "tgn:7008591",
        "tgn:7029392"
    ],
    "tgn:id":7466978,
    "tgn:name:en":"Birse, Forest of",
    "tgn:placetype":[
        "aat:300008863"
    ]
},
  "bbox": [],
  "geometry": {"coordinates":[-2.783333,56.983333],"type":"Point"}
}