{
  "id": 2073991,
  "type": "Feature",
  "properties": {
    "tgn:hierarchy":[
        "tgn:2073991",
        "tgn:1000001",
        "tgn:7012149",
        "tgn:2001486",
        "tgn:7007709",
        "tgn:7029392"
    ],
    "tgn:id":2073991,
    "tgn:name":"Cayton",
    "tgn:placetype":[
        "aat:300008347"
    ]
},
  "bbox": [],
  "geometry": {"coordinates":[-76.9833,35.25],"type":"Point"}
}