<<<<<<< HEAD
{
  "id": 7024266,
  "type": "Feature",
  "properties": {
    "tgn:hierarchy":[
        "tgn:7024266",
        "tgn:1000003",
        "tgn:7029392"
    ],
    "tgn:id":7024266,
    "tgn:name:fr":"Auvergne",
    "tgn:placetype":[
        "aat:300387178"
    ]
},
  "bbox": [],
  "geometry": {"coordinates":[2.5833,45.4167],"type":"Point"}
}
=======
{"geometry":{"type":"Point","coordinates":[2.583300,45.416700]},"type":"Feature","properties":{"hierarchy":["tgn:7024266","tgn:1000003","tgn:7029392"],"placetype":["aat:300387178"],"name:fr":"Auvergne","id":7024266}}
>>>>>>> 03f74aca74312dbeaf24d7e61306dd6a786dc3d0
