{
  "id": 7554132,
  "type": "Feature",
  "properties": {
    "tgn:hierarchy":[
        "tgn:7554132",
        "tgn:1000004",
        "tgn:7000198",
        "tgn:7016694",
        "tgn:7029392"
    ],
    "tgn:id":7554132,
    "tgn:name:en":"Mahulapada",
    "tgn:placetype":[
        "aat:300008347"
    ]
},
  "bbox": [],
  "geometry": {"coordinates":[85.116964,21.632255],"type":"Point"}
}