{
  "id": 2142443,
  "type": "Feature",
  "properties": {
    "tgn:hierarchy":[
        "tgn:2142443",
        "tgn:1000001",
        "tgn:7012149",
        "tgn:7020792",
        "tgn:7007524",
        "tgn:7029392"
    ],
    "tgn:id":2142443,
    "tgn:name":"Bacon Ditch",
    "tgn:placetype":[
        "aat:300006075"
    ]
},
  "bbox": [],
  "geometry": {"coordinates":[-113.1833,45.9167],"type":"Point"}
}