{
  "id": 7545843,
  "type": "Feature",
  "properties": {
    "tgn:hierarchy":[
        "tgn:7545843",
        "tgn:1000004",
        "tgn:7000198",
        "tgn:7016694",
        "tgn:7029392"
    ],
    "tgn:id":7545843,
    "tgn:name:en":"B\u0101huda River",
    "tgn:placetype":[
        "aat:300008699"
    ]
},
  "bbox": [],
  "geometry": {"coordinates":[84.75,19.066667],"type":"Point"}
}