{
  "id": 2033083,
  "type": "Feature",
  "properties": {
    "tgn:hierarchy":[
        "tgn:2033083",
        "tgn:1000001",
        "tgn:7012149",
        "tgn:1002838",
        "tgn:7007252",
        "tgn:7029392"
    ],
    "tgn:id":2033083,
    "tgn:name":"New Salem",
    "tgn:placetype":[
        "aat:300008347"
    ]
},
  "bbox": [],
  "geometry": {"coordinates":[-85.35,39.5333],"type":"Point"}
}