{
  "id": 1079372,
  "type": "Feature",
  "properties": {
    "tgn:hierarchy":[
        "tgn:1079372",
        "tgn:1001109",
        "tgn:1000004",
        "tgn:1000118",
        "tgn:7001784",
        "tgn:7029392"
    ],
    "tgn:id":1079372,
    "tgn:name":"\u1e24alabjah",
    "tgn:placetype":[
        "aat:300008347"
    ]
},
  "bbox": [],
  "geometry": {"coordinates":[45.9833,35.1833],"type":"Point"}
}