{
  "id": 7422113,
  "type": "Feature",
  "properties": {
    "tgn:hierarchy":[
        "tgn:7422113",
        "tgn:1000001",
        "tgn:7005601",
        "tgn:7005560",
        "tgn:7029392"
    ],
    "tgn:id":7422113,
    "tgn:name":"Huiscuilco, Arroyo",
    "tgn:placetype":[
        "aat:300008699"
    ]
},
  "bbox": [],
  "geometry": {"coordinates":[-102.866667,21.333333],"type":"Point"}
}