{
  "id": 2525522,
  "type": "Feature",
  "properties": {
    "tgn:hierarchy":[
        "tgn:2525522",
        "tgn:1000001",
        "tgn:2000776",
        "tgn:7012149",
        "tgn:7007255",
        "tgn:7029392"
    ],
    "tgn:id":2525522,
    "tgn:name":"Morse Ridge",
    "tgn:placetype":[
        "aat:300266640"
    ]
},
  "bbox": [],
  "geometry": {"coordinates":[-87.85,37.2167],"type":"Point"}
}