{
  "id": 7535259,
  "type": "Feature",
  "properties": {
    "tgn:hierarchy":[
        "tgn:7535259",
        "tgn:7001242",
        "tgn:7016833",
        "tgn:1001418",
        "tgn:7029392"
    ],
    "tgn:id":7535259,
    "tgn:name:en":"\u1e28unaysh\u0101t, Ghurd al",
    "tgn:placetype":[
        "aat:300008750"
    ]
},
  "bbox": [],
  "geometry": {"coordinates":[29.796184,30.113902],"type":"Point"}
}