{
  "id": 2581719,
  "type": "Feature",
  "properties": {
    "tgn:hierarchy":[
        "tgn:2581719",
        "tgn:1000001",
        "tgn:7012149",
        "tgn:2001457",
        "tgn:7007566",
        "tgn:7029392"
    ],
    "tgn:id":2581719,
    "tgn:name":"Pinabete Peak",
    "tgn:placetype":[
        "aat:300008798"
    ]
},
  "bbox": [],
  "geometry": {"coordinates":[-105.5167,36.75],"type":"Point"}
}