{
  "id": 2279266,
  "type": "Feature",
  "properties": {
    "tgn:hierarchy":[
        "tgn:2279266",
        "tgn:1000001",
        "tgn:7012149",
        "tgn:2001718",
        "tgn:7007708",
        "tgn:7029392"
    ],
    "tgn:id":2279266,
    "tgn:name":"Deadman Butte",
    "tgn:placetype":[
        "aat:300008798"
    ]
},
  "bbox": [],
  "geometry": {"coordinates":[-117.35,42.4667],"type":"Point"}
}