{
  "id": 2507791,
  "type": "Feature",
  "properties": {
    "tgn:hierarchy":[
        "tgn:2507791",
        "tgn:2002306",
        "tgn:1000001",
        "tgn:7012149",
        "tgn:7007922",
        "tgn:7029392"
    ],
    "tgn:id":2507791,
    "tgn:name":"Michigan Island",
    "tgn:placetype":[
        "aat:300008791"
    ]
},
  "bbox": [],
  "geometry": {"coordinates":[-90.4667,46.8667],"type":"Point"}
}