{
  "id": 7024907,
  "type": "Feature",
  "properties": {
    "tgn:hierarchy":[
        "tgn:7024907",
        "tgn:7024835",
        "tgn:1000003",
        "tgn:7003120",
        "tgn:1000080",
        "tgn:7029392"
    ],
    "tgn:id":7024907,
    "tgn:name":"Falmenta",
    "tgn:placetype":[
        "aat:300008347"
    ]
},
  "bbox": [],
  "geometry": {"coordinates":[8.583333,46.066667],"type":"Point"}
}