{
  "id": 2025358,
  "type": "Feature",
  "properties": {
    "tgn:hierarchy":[
        "tgn:2025358",
        "tgn:1000001",
        "tgn:2000459",
        "tgn:7012149",
        "tgn:7007250",
        "tgn:7029392"
    ],
    "tgn:id":2025358,
    "tgn:name":"Banks",
    "tgn:placetype":[
        "aat:300008347"
    ]
},
  "bbox": [],
  "geometry": {"coordinates":[-116.1167,44.0667],"type":"Point"}
}