{
  "id": 2368943,
  "type": "Feature",
  "properties": {
    "tgn:hierarchy":[
        "tgn:2368943",
        "tgn:1000001",
        "tgn:7012149",
        "tgn:2001140",
        "tgn:7007522",
        "tgn:7029392"
    ],
    "tgn:id":2368943,
    "tgn:name":"Gum Bayou",
    "tgn:placetype":[
        "aat:300008699"
    ]
},
  "bbox": [],
  "geometry": {"coordinates":[-89.8333,30.6833],"type":"Point"}
}