{
  "id": 2127528,
  "type": "Feature",
  "properties": {
    "tgn:hierarchy":[
        "tgn:2127528",
        "tgn:1000001",
        "tgn:1002328",
        "tgn:7012149",
        "tgn:7007568",
        "tgn:7029392"
    ],
    "tgn:id":2127528,
    "tgn:name":"Al Fisher Brook",
    "tgn:placetype":[
        "aat:300008699"
    ]
},
  "bbox": [],
  "geometry": {"coordinates":[-75.2333,41.9833],"type":"Point"}
}