{
  "id": 7538170,
  "type": "Feature",
  "properties": {
    "tgn:hierarchy":[
        "tgn:7538170",
        "tgn:7001242",
        "tgn:7016833",
        "tgn:1001088",
        "tgn:7029392"
    ],
    "tgn:id":7538170,
    "tgn:name:en":"Nazlat ash Shuraf\u0101'",
    "tgn:placetype":[
        "aat:300008347"
    ]
},
  "bbox": [],
  "geometry": {"coordinates":[30.769031,28.119912],"type":"Point"}
}