{
  "id": 7590525,
  "type": "Feature",
  "properties": {
    "tgn:hierarchy":[
        "tgn:7590525",
        "tgn:1000004",
        "tgn:7000198",
        "tgn:7016722",
        "tgn:7029392"
    ],
    "tgn:id":7590525,
    "tgn:name:en":"Mora",
    "tgn:placetype":[
        "aat:300008347"
    ]
},
  "bbox": [],
  "geometry": {"coordinates":[77.493308,29.684594],"type":"Point"}
}