{
  "id": 7583814,
  "type": "Feature",
  "properties": {
    "tgn:hierarchy":[
        "tgn:7583814",
        "tgn:1000004",
        "tgn:7000198",
        "tgn:7016883",
        "tgn:7029392"
    ],
    "tgn:id":7583814,
    "tgn:name:en":"Ranj\u012btgarh",
    "tgn:placetype":[
        "aat:300008347"
    ]
},
  "bbox": [],
  "geometry": {"coordinates":[76.109142,30.512717],"type":"Point"}
}