{
  "id": 1104655,
  "type": "Feature",
  "properties": {
    "tgn:hierarchy":[
        "tgn:1104655",
        "tgn:7003499",
        "tgn:7001201",
        "tgn:1000003",
        "tgn:1000078",
        "tgn:7029392"
    ],
    "tgn:id":1104655,
    "tgn:name":"Galtymore Mountain",
    "tgn:placetype":[
        "aat:300008795"
    ]
},
  "bbox": [],
  "geometry": {"coordinates":[-8.1833,52.3833],"type":"Point"}
}