<<<<<<< HEAD
{
  "id": 7051523,
  "type": "Feature",
  "properties": {
    "tgn:hierarchy":[
        "tgn:7051523",
        "tgn:1003483",
        "tgn:1000003",
        "tgn:7003240",
        "tgn:1000080",
        "tgn:7029392"
    ],
    "tgn:id":7051523,
    "tgn:name":"Petrella Guidi",
    "tgn:placetype":[
        "aat:300008347"
    ]
},
  "bbox": [],
  "geometry": {"coordinates":[12.25,43.85],"type":"Point"}
}
=======
{"geometry":{"type":"Point","coordinates":[12.250000,43.850000]},"type":"Feature","properties":{"hierarchy":["tgn:7051523","tgn:1003483","tgn:1000003","tgn:7003240","tgn:1000080","tgn:7029392"],"placetype":["aat:300008347"],"id":7051523,"name:xx":"Petrella Guidi"}}
>>>>>>> 03f74aca74312dbeaf24d7e61306dd6a786dc3d0
