{
  "id": 2581778,
  "type": "Feature",
  "properties": {
    "tgn:hierarchy":[
        "tgn:2581778",
        "tgn:2000001",
        "tgn:7002659",
        "tgn:1000001",
        "tgn:7012149",
        "tgn:7029392"
    ],
    "tgn:id":2581778,
    "tgn:name":"Pinchona",
    "tgn:placetype":[
        "aat:300008347"
    ]
},
  "bbox": [],
  "geometry": {"coordinates":[-87.7167,30.9167],"type":"Point"}
}