{
  "id": 2489136,
  "type": "Feature",
  "properties": {
    "tgn:hierarchy":[
        "tgn:2489136",
        "tgn:1000001",
        "tgn:7012149",
        "tgn:7007256",
        "tgn:7029392"
    ],
    "tgn:id":2489136,
    "tgn:name":"Majors Branch",
    "tgn:placetype":[
        "aat:300008699"
    ]
},
  "bbox": [],
  "geometry": {"coordinates":[-92.8333,31.2167],"type":"Point"}
}