{
  "id": 7334385,
  "type": "Feature",
  "properties": {
    "tgn:hierarchy":[
        "tgn:7334385",
        "tgn:7002818",
        "tgn:1001647",
        "tgn:1000003",
        "tgn:1000095",
        "tgn:7029392"
    ],
    "tgn:id":7334385,
    "tgn:name":"El Hocino",
    "tgn:placetype":[
        "aat:300387200"
    ]
},
  "bbox": [],
  "geometry": {"coordinates":[-1.816667,39.433333],"type":"Point"}
}