{
  "id": 2384933,
  "type": "Feature",
  "properties": {
    "tgn:hierarchy":[
        "tgn:2384933",
        "tgn:1000001",
        "tgn:2002369",
        "tgn:7012149",
        "tgn:7007923",
        "tgn:7029392"
    ],
    "tgn:id":2384933,
    "tgn:name":"Helm Creek",
    "tgn:placetype":[
        "aat:300008706"
    ]
},
  "bbox": [],
  "geometry": {"coordinates":[-105.8333,42.5667],"type":"Point"}
}