{
  "id": 2628904,
  "type": "Feature",
  "properties": {
    "tgn:hierarchy":[
        "tgn:2628904",
        "tgn:1000001",
        "tgn:7012149",
        "tgn:2000707",
        "tgn:7007254",
        "tgn:7029392"
    ],
    "tgn:id":2628904,
    "tgn:name":"Rose Bud Creek",
    "tgn:placetype":[
        "aat:300008706"
    ]
},
  "bbox": [],
  "geometry": {"coordinates":[-98.0833,37.5333],"type":"Point"}
}