{
  "id": 2021340,
  "type": "Feature",
  "properties": {
    "tgn:hierarchy":[
        "tgn:2021340",
        "tgn:1000001",
        "tgn:7012149",
        "tgn:1002567",
        "tgn:7007240",
        "tgn:7029392"
    ],
    "tgn:id":2021340,
    "tgn:name":"South Pine Lakes",
    "tgn:placetype":[
        "aat:300008347"
    ]
},
  "bbox": [],
  "geometry": {"coordinates":[-81.4167,28.9167],"type":"Point"}
}