{
  "id": 2248530,
  "type": "Feature",
  "properties": {
    "tgn:hierarchy":[
        "tgn:2248530",
        "tgn:2000919",
        "tgn:1000001",
        "tgn:7012149",
        "tgn:7007515",
        "tgn:7029392"
    ],
    "tgn:id":2248530,
    "tgn:name":"Cold Spring Brook",
    "tgn:placetype":[
        "aat:300008699"
    ]
},
  "bbox": [],
  "geometry": {"coordinates":[-68.1833,46.5667],"type":"Point"}
}