<<<<<<< HEAD
{
  "id": 2705870,
  "type": "Feature",
  "properties": {
    "tgn:hierarchy":[
        "tgn:2705870",
        "tgn:1000001",
        "tgn:7012149",
        "tgn:1003038",
        "tgn:7007517",
        "tgn:7029392"
    ],
    "tgn:id":2705870,
    "tgn:name":"Sutton Falls Reservoir",
    "tgn:placetype":[
        "aat:300006191"
    ]
},
  "bbox": [],
  "geometry": {"coordinates":[-71.7167,42.1],"type":"Point"}
}
=======
{"geometry":{"type":"Point","coordinates":[-71.716700,42.100000]},"type":"Feature","properties":{"hierarchy":["tgn:2705870","tgn:1000001","tgn:7012149","tgn:1003038","tgn:7007517","tgn:7029392"],"placetype":["aat:300006191"],"id":2705870,"name:xx":"Sutton Falls Reservoir"}}
>>>>>>> 03f74aca74312dbeaf24d7e61306dd6a786dc3d0
