{
  "id": 2366868,
  "type": "Feature",
  "properties": {
    "tgn:hierarchy":[
        "tgn:2366868",
        "tgn:2000947",
        "tgn:1000001",
        "tgn:7012149",
        "tgn:7007520",
        "tgn:7029392"
    ],
    "tgn:id":2366868,
    "tgn:name":"Gristmill Creek",
    "tgn:placetype":[
        "aat:300008706"
    ]
},
  "bbox": [],
  "geometry": {"coordinates":[-88.5833,46.7667],"type":"Point"}
}