{
  "id": 1006782,
  "type": "Feature",
  "properties": {
    "tgn:hierarchy":[
        "tgn:1006782",
        "tgn:1000001",
        "tgn:1002410",
        "tgn:7012149",
        "tgn:7007565",
        "tgn:7029392"
    ],
    "tgn:id":1006782,
    "tgn:name":"Chester Island",
    "tgn:placetype":[
        "aat:300008791"
    ]
},
  "bbox": [],
  "geometry": {"coordinates":[-75.3333,39.8333],"type":"Point"}
}