{
  "id": 2572656,
  "type": "Feature",
  "properties": {
    "tgn:hierarchy":[
        "tgn:2572656",
        "tgn:1000001",
        "tgn:2001701",
        "tgn:7012149",
        "tgn:7007708",
        "tgn:7029392"
    ],
    "tgn:id":2572656,
    "tgn:name":"Peak Log Pond",
    "tgn:placetype":[
        "aat:300006191"
    ]
},
  "bbox": [],
  "geometry": {"coordinates":[-123.3167,44.5833],"type":"Point"}
}