{
  "id": 7284725,
  "type": "Feature",
  "properties": {
    "tgn:hierarchy":[
        "tgn:7284725",
        "tgn:1001702",
        "tgn:1000049",
        "tgn:1000002",
        "tgn:7029392"
    ],
    "tgn:id":7284725,
    "tgn:name":"Pike, Islas",
    "tgn:placetype":[
        "aat:300008791"
    ]
},
  "bbox": [],
  "geometry": {"coordinates":[-73.483333,-52.983333],"type":"Point"}
}