{
  "id": 7554018,
  "type": "Feature",
  "properties": {
    "tgn:hierarchy":[
        "tgn:7554018",
        "tgn:1000004",
        "tgn:7000198",
        "tgn:7016722",
        "tgn:7029392"
    ],
    "tgn:id":7554018,
    "tgn:name:en":"M\u0101hpur",
    "tgn:placetype":[
        "aat:300007783"
    ]
},
  "bbox": [],
  "geometry": {"coordinates":[83.246789,25.605344],"type":"Point"}
}