{
  "id": 2541012,
  "type": "Feature",
  "properties": {
    "tgn:hierarchy":[
        "tgn:2541012",
        "tgn:1000001",
        "tgn:1002194",
        "tgn:7012149",
        "tgn:7007710",
        "tgn:7029392"
    ],
    "tgn:id":2541012,
    "tgn:name":"Nichols Point",
    "tgn:placetype":[
        "aat:300008798"
    ]
},
  "bbox": [],
  "geometry": {"coordinates":[-76.4333,41.65],"type":"Point"}
}