{
  "id": 7525957,
  "type": "Feature",
  "properties": {
    "tgn:hierarchy":[
        "tgn:7525957",
        "tgn:7001242",
        "tgn:7016833",
        "tgn:1001114",
        "tgn:7029392"
    ],
    "tgn:id":7525957,
    "tgn:name:en":"S\u012bd\u012b \u1e28umayd",
    "tgn:placetype":[
        "aat:300005926"
    ]
},
  "bbox": [],
  "geometry": {"coordinates":[31.066667,27.283333],"type":"Point"}
}