<<<<<<< HEAD
{
  "id": 2763475,
  "type": "Feature",
  "properties": {
    "tgn:hierarchy":[
        "tgn:2763475",
        "tgn:1000001",
        "tgn:7012149",
        "tgn:2002361",
        "tgn:7007922",
        "tgn:7029392"
    ],
    "tgn:id":2763475,
    "tgn:name":"Weyauwega Lake",
    "tgn:placetype":[
        "aat:300006191"
    ]
},
  "bbox": [],
  "geometry": {"coordinates":[-88.9167,44.3167],"type":"Point"}
}
=======
{"geometry":{"type":"Point","coordinates":[-88.916700,44.316700]},"type":"Feature","properties":{"hierarchy":["tgn:2763475","tgn:1000001","tgn:7012149","tgn:2002361","tgn:7007922","tgn:7029392"],"placetype":["aat:300006191"],"id":2763475,"name:xx":"Weyauwega Lake"}}
>>>>>>> 03f74aca74312dbeaf24d7e61306dd6a786dc3d0
