{
  "id": 7408432,
  "type": "Feature",
  "properties": {
    "tgn:hierarchy":[
        "tgn:7408432",
        "tgn:1000001",
        "tgn:7005590",
        "tgn:7005560",
        "tgn:7029392"
    ],
    "tgn:id":7408432,
    "tgn:name":"Emiliano Zapata",
    "tgn:placetype":[
        "aat:300008347"
    ]
},
  "bbox": [],
  "geometry": {"coordinates":[-101.833333,19.658333],"type":"Point"}
}