{
  "id": 7306977,
  "type": "Feature",
  "properties": {
    "tgn:hierarchy":[
        "tgn:7306977",
        "tgn:7002805",
        "tgn:7002758",
        "tgn:1000003",
        "tgn:1000095",
        "tgn:7029392"
    ],
    "tgn:id":7306977,
    "tgn:name":"Los Mundos",
    "tgn:placetype":[
        "aat:300008347"
    ]
},
  "bbox": [],
  "geometry": {"coordinates":[-2.033333,37.466667],"type":"Point"}
}