{
  "id": 2133580,
  "type": "Feature",
  "properties": {
    "tgn:hierarchy":[
        "tgn:2133580",
        "tgn:1000001",
        "tgn:7012149",
        "tgn:2000926",
        "tgn:7007515",
        "tgn:7029392"
    ],
    "tgn:id":2133580,
    "tgn:name":"Andrews Brook",
    "tgn:placetype":[
        "aat:300008699"
    ]
},
  "bbox": [],
  "geometry": {"coordinates":[-70.8333,44.1833],"type":"Point"}
}