{
  "id": 7270932,
  "type": "Feature",
  "properties": {
    "tgn:hierarchy":[
        "tgn:7270932",
        "tgn:1000003",
        "tgn:7003635",
        "tgn:7016845",
        "tgn:7029392"
    ],
    "tgn:id":7270932,
    "tgn:name:nl":"Soelekerkepolder",
    "tgn:placetype":[
        "aat:300006163"
    ]
},
  "bbox": [],
  "geometry": {"coordinates":[3.716667,51.566667],"type":"Point"}
}