{
  "id": 7272995,
  "type": "Feature",
  "properties": {
    "tgn:concordances":{
        "gn:id":"2745847"
    },
    "tgn:hierarchy":[
        "tgn:7272995",
        "tgn:7003614",
        "tgn:1000003",
        "tgn:7016845",
        "tgn:7029392"
    ],
    "tgn:id":7272995,
    "tgn:name:nl":"Valsteeg",
    "tgn:placetype":[
        "aat:300008347"
    ]
},
  "bbox": [],
  "geometry": {"coordinates":[6.75,52.716667],"type":"Point"}
}