<<<<<<< HEAD
{
  "id": 7175590,
  "type": "Feature",
  "properties": {
    "tgn:hierarchy":[
        "tgn:7175590",
        "tgn:1000003",
        "tgn:7003676",
        "tgn:7000084",
        "tgn:7029392"
    ],
    "tgn:id":7175590,
    "tgn:name":"Gro\u00dfw\u00fcrden",
    "tgn:placetype":[
        "aat:300008347"
    ]
},
  "bbox": [],
  "geometry": {"coordinates":[8.233333,53.533333],"type":"Point"}
}
=======
{"geometry":{"type":"Point","coordinates":[8.233333,53.533333]},"type":"Feature","properties":{"hierarchy":["tgn:7175590","tgn:1000003","tgn:7003676","tgn:7000084","tgn:7029392"],"placetype":["aat:300008347"],"id":7175590,"name:xx":"Gro\u00dfw\u00fcrden"}}
>>>>>>> 03f74aca74312dbeaf24d7e61306dd6a786dc3d0
