{
  "id": 7175590,
  "type": "Feature",
  "properties": {
    "tgn:hierarchy":[
        "tgn:7175590",
        "tgn:1000003",
        "tgn:7003676",
        "tgn:7000084",
        "tgn:7029392"
    ],
    "tgn:id":7175590,
    "tgn:name":"Gro\u00dfw\u00fcrden",
    "tgn:placetype":[
        "aat:300008347"
    ]
},
  "bbox": [],
  "geometry": {"coordinates":[8.233333,53.533333],"type":"Point"}
}