{
  "id": 7407630,
  "type": "Feature",
  "properties": {
    "tgn:hierarchy":[
        "tgn:7407630",
        "tgn:1000001",
        "tgn:1001893",
        "tgn:7005560",
        "tgn:7029392"
    ],
    "tgn:id":7407630,
    "tgn:name":"Pedernales",
    "tgn:placetype":[
        "aat:300008347"
    ]
},
  "bbox": [],
  "geometry": {"coordinates":[-100.108333,19.633333],"type":"Point"}
}