{
  "id": 7153986,
  "type": "Feature",
  "properties": {
    "tgn:hierarchy":[
        "tgn:7153986",
        "tgn:7003669",
        "tgn:1000003",
        "tgn:7000084",
        "tgn:7029392"
    ],
    "tgn:id":7153986,
    "tgn:name":"Johannsbuchbach",
    "tgn:placetype":[
        "aat:300008347"
    ]
},
  "bbox": [],
  "geometry": {"coordinates":[12.583333,48.333333],"type":"Point"}
}