<<<<<<< HEAD
{
  "id": 2336180,
  "type": "Feature",
  "properties": {
    "tgn:hierarchy":[
        "tgn:2336180",
        "tgn:1000001",
        "tgn:7012149",
        "tgn:2001531",
        "tgn:7007709",
        "tgn:7029392"
    ],
    "tgn:id":2336180,
    "tgn:name":"Foster Mountain",
    "tgn:placetype":[
        "aat:300008798"
    ]
},
  "bbox": [],
  "geometry": {"coordinates":[-82.1833,35.25],"type":"Point"}
}
=======
{"geometry":{"type":"Point","coordinates":[-82.183300,35.250000]},"type":"Feature","properties":{"hierarchy":["tgn:2336180","tgn:1000001","tgn:7012149","tgn:2001531","tgn:7007709","tgn:7029392"],"placetype":["aat:300008798"],"id":2336180,"name:xx":"Foster Mountain"}}
>>>>>>> 03f74aca74312dbeaf24d7e61306dd6a786dc3d0
