{
  "id": 7172177,
  "type": "Feature",
  "properties": {
    "tgn:hierarchy":[
        "tgn:7172177",
        "tgn:1000003",
        "tgn:7003677",
        "tgn:7000084",
        "tgn:7029392"
    ],
    "tgn:id":7172177,
    "tgn:name":"Helmer",
    "tgn:placetype":[
        "aat:300000206"
    ]
},
  "bbox": [],
  "geometry": {"coordinates":[6.75,52.083333],"type":"Point"}
}