{
  "id": 7551895,
  "type": "Feature",
  "properties": {
    "tgn:hierarchy":[
        "tgn:7551895",
        "tgn:7001819",
        "tgn:1000004",
        "tgn:7000198",
        "tgn:7029392"
    ],
    "tgn:id":7551895,
    "tgn:name:en":"Dorkang",
    "tgn:placetype":[
        "aat:300008347"
    ]
},
  "bbox": [],
  "geometry": {"coordinates":[94.785478,28.132802],"type":"Point"}
}