{
  "id": 7035119,
  "type": "Feature",
  "properties": {
    "tgn:hierarchy":[
        "tgn:7035119",
        "tgn:1003506",
        "tgn:1000003",
        "tgn:7002993",
        "tgn:1000080",
        "tgn:7029392"
    ],
    "tgn:id":7035119,
    "tgn:name":"Prapotnizza",
    "tgn:placetype":[
        "aat:300008347"
    ]
},
  "bbox": [],
  "geometry": {"coordinates":[13.643611,46.174167],"type":"Point"}
}