{
  "id": 7471616,
  "type": "Feature",
  "properties": {
    "tgn:hierarchy":[
        "tgn:7471616",
        "tgn:1000004",
        "tgn:7490934",
        "tgn:1000141",
        "tgn:7029392"
    ],
    "tgn:id":7471616,
    "tgn:name":"Xiazhou",
    "tgn:placetype":[
        "aat:300008347"
    ]
},
  "bbox": [],
  "geometry": {"coordinates":[120.242778,23.109722],"type":"Point"}
}