{
  "id": 2101763,
  "type": "Feature",
  "properties": {
    "tgn:hierarchy":[
        "tgn:2101763",
        "tgn:1000001",
        "tgn:7012149",
        "tgn:2001864",
        "tgn:7007825",
        "tgn:7029392"
    ],
    "tgn:id":2101763,
    "tgn:name":"Tarpley",
    "tgn:placetype":[
        "aat:300008347",
        "aat:300387210"
    ]
},
  "bbox": [],
  "geometry": {"coordinates":[-86.9833,35.1333],"type":"Point"}
}