{
  "id": 7157904,
  "type": "Feature",
  "properties": {
    "tgn:hierarchy":[
        "tgn:7157904",
        "tgn:1000003",
        "tgn:7003677",
        "tgn:7000084",
        "tgn:7029392"
    ],
    "tgn:id":7157904,
    "tgn:name":"Kleiner Fahren-Berg",
    "tgn:placetype":[
        "aat:300008777"
    ]
},
  "bbox": [],
  "geometry": {"coordinates":[8.533333,51.45],"type":"Point"}
}