{
  "id": 1099409,
  "type": "Feature",
  "properties": {
    "tgn:hierarchy":[
        "tgn:1099409",
        "tgn:1000846",
        "tgn:7006160",
        "tgn:1000006",
        "tgn:7029392"
    ],
    "tgn:id":1099409,
    "tgn:name":"Ailo",
    "tgn:placetype":[
        "aat:300008347"
    ]
},
  "bbox": [],
  "geometry": {"coordinates":[151.6667,-4.8333],"type":"Point"}
}