{
  "id": 2519088,
  "type": "Feature",
  "properties": {
    "tgn:hierarchy":[
        "tgn:2519088",
        "tgn:1000001",
        "tgn:7012149",
        "tgn:2001493",
        "tgn:7007709",
        "tgn:7029392"
    ],
    "tgn:id":2519088,
    "tgn:name":"Mobile City Trailer Park",
    "tgn:placetype":[
        "aat:300008347"
    ]
},
  "bbox": [],
  "geometry": {"coordinates":[-77.7667,35.9833],"type":"Point"}
}