{
  "id": 2528571,
  "type": "Feature",
  "properties": {
    "tgn:hierarchy":[
        "tgn:2528571",
        "tgn:1000001",
        "tgn:7012149",
        "tgn:7007158",
        "tgn:2000248",
        "tgn:7029392"
    ],
    "tgn:id":2528571,
    "tgn:name":"Mucho Grande Mine",
    "tgn:placetype":[
        "aat:300000390"
    ]
},
  "bbox": [],
  "geometry": {"coordinates":[-108.7833,37.9333],"type":"Point"}
}