{
  "id": 2514182,
  "type": "Feature",
  "properties": {
    "tgn:hierarchy":[
        "tgn:2514182",
        "tgn:7002659",
        "tgn:1000001",
        "tgn:7012149",
        "tgn:2000052",
        "tgn:7029392"
    ],
    "tgn:id":2514182,
    "tgn:name":"Miller Brothers Lake Number One",
    "tgn:placetype":[
        "aat:300006191"
    ]
},
  "bbox": [],
  "geometry": {"coordinates":[-87.4667,32.3167],"type":"Point"}
}