<<<<<<< HEAD
{
  "id": 2152417,
  "type": "Feature",
  "properties": {
    "tgn:hierarchy":[
        "tgn:2152417",
        "tgn:1000001",
        "tgn:7012149",
        "tgn:2001274",
        "tgn:7007524",
        "tgn:7029392"
    ],
    "tgn:id":2152417,
    "tgn:name":"Bay Point",
    "tgn:placetype":[
        "aat:300008850"
    ]
},
  "bbox": [],
  "geometry": {"coordinates":[-114.3333,48.4167],"type":"Point"}
}
=======
{"geometry":{"type":"Point","coordinates":[-114.333300,48.416700]},"type":"Feature","properties":{"hierarchy":["tgn:2152417","tgn:1000001","tgn:7012149","tgn:2001274","tgn:7007524","tgn:7029392"],"placetype":["aat:300008850"],"id":2152417,"name:xx":"Bay Point"}}
>>>>>>> 03f74aca74312dbeaf24d7e61306dd6a786dc3d0
