{
  "id": 2290520,
  "type": "Feature",
  "properties": {
    "tgn:hierarchy":[
        "tgn:2290520",
        "tgn:1000001",
        "tgn:2001014",
        "tgn:7012149",
        "tgn:7007521",
        "tgn:7029392"
    ],
    "tgn:id":2290520,
    "tgn:name":"Doe Lake",
    "tgn:placetype":[
        "aat:300008680"
    ]
},
  "bbox": [],
  "geometry": {"coordinates":[-90.7667,48.0167],"type":"Point"}
}