{
  "id": 2618232,
  "type": "Feature",
  "properties": {
    "tgn:hierarchy":[
        "tgn:2618232",
        "tgn:1000001",
        "tgn:7012149",
        "tgn:2002177",
        "tgn:7007919",
        "tgn:7029392"
    ],
    "tgn:id":2618232,
    "tgn:name":"Riga Run",
    "tgn:placetype":[
        "aat:300008699"
    ]
},
  "bbox": [],
  "geometry": {"coordinates":[-77.9167,38.2667],"type":"Point"}
}