{
  "id": 2688976,
  "type": "Feature",
  "properties": {
    "tgn:hierarchy":[
        "tgn:2688976",
        "tgn:1000001",
        "tgn:1002337",
        "tgn:7012149",
        "tgn:7007922",
        "tgn:7029392"
    ],
    "tgn:id":2688976,
    "tgn:name":"Squak Island",
    "tgn:placetype":[
        "aat:300008791"
    ]
},
  "bbox": [],
  "geometry": {"coordinates":[-88.6667,43.5167],"type":"Point"}
}