{
  "id": 2743054,
  "type": "Feature",
  "properties": {
    "tgn:hierarchy":[
        "tgn:2743054",
        "tgn:1000001",
        "tgn:2000108",
        "tgn:7016172",
        "tgn:7012149",
        "tgn:7029392"
    ],
    "tgn:id":2743054,
    "tgn:name":"Van Winkle Hollow Spring",
    "tgn:placetype":[
        "aat:300008697"
    ]
},
  "bbox": [],
  "geometry": {"coordinates":[-93.95,36.2833],"type":"Point"}
}