{
  "id": 7399517,
  "type": "Feature",
  "properties": {
    "tgn:hierarchy":[
        "tgn:7399517",
        "tgn:1000001",
        "tgn:7005599",
        "tgn:7005560",
        "tgn:7029392"
    ],
    "tgn:id":7399517,
    "tgn:name":"Cascajal del R\u00edo",
    "tgn:placetype":[
        "aat:300008347"
    ]
},
  "bbox": [],
  "geometry": {"coordinates":[-95.1625,17.991667],"type":"Point"}
}