{
  "id": 2130992,
  "type": "Feature",
  "properties": {
    "tgn:hierarchy":[
        "tgn:2130992",
        "tgn:7006450",
        "tgn:1000001",
        "tgn:7012149",
        "tgn:2000079",
        "tgn:7029392"
    ],
    "tgn:id":2130992,
    "tgn:name":"Alngeeyak Point",
    "tgn:placetype":[
        "aat:300008850"
    ]
},
  "bbox": [],
  "geometry": {"coordinates":[-169.5833,63.3833],"type":"Point"}
}