{
  "id": 2378541,
  "type": "Feature",
  "properties": {
    "tgn:hierarchy":[
        "tgn:2378541",
        "tgn:1000001",
        "tgn:7012149",
        "tgn:2002360",
        "tgn:7007922",
        "tgn:7029392"
    ],
    "tgn:id":2378541,
    "tgn:name":"Harrison Lake",
    "tgn:placetype":[
        "aat:300008680"
    ]
},
  "bbox": [],
  "geometry": {"coordinates":[-91.8667,45.7833],"type":"Point"}
}