{
  "id": 7118727,
  "type": "Feature",
  "properties": {
    "tgn:hierarchy":[
        "tgn:7118727",
        "tgn:7003692",
        "tgn:1000003",
        "tgn:7000084",
        "tgn:7029392"
    ],
    "tgn:id":7118727,
    "tgn:name":"Peterlingshof",
    "tgn:placetype":[
        "aat:300000206"
    ]
},
  "bbox": [],
  "geometry": {"coordinates":[9.766667,48.716667],"type":"Point"}
}