{
  "id": 2589913,
  "type": "Feature",
  "properties": {
    "tgn:hierarchy":[
        "tgn:2589913",
        "tgn:2000854",
        "tgn:1000001",
        "tgn:7012149",
        "tgn:7007256",
        "tgn:7029392"
    ],
    "tgn:id":2589913,
    "tgn:name":"Pointe Aux Loups, Bayou",
    "tgn:placetype":[
        "aat:300008699"
    ]
},
  "bbox": [],
  "geometry": {"coordinates":[-92.45,30.3167],"type":"Point"}
}