{
  "id": 7539062,
  "type": "Feature",
  "properties": {
    "tgn:hierarchy":[
        "tgn:7539062",
        "tgn:7001242",
        "tgn:7016833",
        "tgn:1001418",
        "tgn:7029392"
    ],
    "tgn:id":7539062,
    "tgn:name:en":"Musawwaj, Jabal",
    "tgn:placetype":[
        "aat:300008795"
    ]
},
  "bbox": [],
  "geometry": {"coordinates":[28.695841,29.262993],"type":"Point"}
}