{
  "id": 1020468,
  "type": "Feature",
  "properties": {
    "tgn:hierarchy":[
        "tgn:1020468",
        "tgn:1000729",
        "tgn:1000046",
        "tgn:1000002",
        "tgn:7029392"
    ],
    "tgn:id":1020468,
    "tgn:name":"Vitichi",
    "tgn:placetype":[
        "aat:300008347"
    ]
},
  "bbox": [],
  "geometry": {"coordinates":[-65.3667,-20.2333],"type":"Point"}
}