{
  "id": 2386989,
  "type": "Feature",
  "properties": {
    "tgn:hierarchy":[
        "tgn:2386989",
        "tgn:1000001",
        "tgn:7012149",
        "tgn:2000539",
        "tgn:7007251",
        "tgn:7029392"
    ],
    "tgn:id":2386989,
    "tgn:name":"Herrin Reservoir",
    "tgn:placetype":[
        "aat:300006191"
    ]
},
  "bbox": [],
  "geometry": {"coordinates":[-89.0333,37.75],"type":"Point"}
}