{
  "id": 2221170,
  "type": "Feature",
  "properties": {
    "tgn:hierarchy":[
        "tgn:2221170",
        "tgn:1000001",
        "tgn:7012149",
        "tgn:2000218",
        "tgn:7007158",
        "tgn:7029392"
    ],
    "tgn:id":2221170,
    "tgn:name":"Carcass Gulch",
    "tgn:placetype":[
        "aat:300008761"
    ]
},
  "bbox": [],
  "geometry": {"coordinates":[-107.15,37.8333],"type":"Point"}
}