<<<<<<< HEAD
{
  "id": 7486339,
  "type": "Feature",
  "properties": {
    "tgn:hierarchy":[
        "tgn:7486339",
        "tgn:7498210",
        "tgn:1000004",
        "tgn:1000141",
        "tgn:7029392"
    ],
    "tgn:id":7486339,
    "tgn:name":"Laotanbo",
    "tgn:placetype":[
        "aat:300386968"
    ]
},
  "bbox": [],
  "geometry": {"coordinates":[120.484795,26.36673],"type":"Point"}
}
=======
{"geometry":{"type":"Point","coordinates":[120.484795,26.366730]},"type":"Feature","properties":{"hierarchy":["tgn:7486339","tgn:7498210","tgn:1000004","tgn:1000141","tgn:7029392"],"placetype":["aat:300386968"],"id":7486339,"name:xx":"Laotanbo"}}
>>>>>>> 03f74aca74312dbeaf24d7e61306dd6a786dc3d0
