{
  "id": 7486339,
  "type": "Feature",
  "properties": {
    "tgn:hierarchy":[
        "tgn:7486339",
        "tgn:7498210",
        "tgn:1000004",
        "tgn:1000141",
        "tgn:7029392"
    ],
    "tgn:id":7486339,
    "tgn:name":"Laotanbo",
    "tgn:placetype":[
        "aat:300386968"
    ]
},
  "bbox": [],
  "geometry": {"coordinates":[120.484795,26.36673],"type":"Point"}
}