{
  "id": 1101844,
  "type": "Feature",
  "properties": {
    "tgn:hierarchy":[
        "tgn:1101844",
        "tgn:1000964",
        "tgn:7001242",
        "tgn:1000155",
        "tgn:7029392"
    ],
    "tgn:id":1101844,
    "tgn:name":"Saint-Floris, Parc National de",
    "tgn:placetype":[
        "aat:300008189"
    ]
},
  "bbox": [],
  "geometry": {"coordinates":[21.5833,9.6667],"type":"Point"}
}