{
  "id": 7584058,
  "type": "Feature",
  "properties": {
    "tgn:hierarchy":[
        "tgn:7584058",
        "tgn:1000004",
        "tgn:7000198",
        "tgn:7016883",
        "tgn:7029392"
    ],
    "tgn:id":7584058,
    "tgn:name:en":"Malakpur",
    "tgn:placetype":[
        "aat:300008347"
    ]
},
  "bbox": [],
  "geometry": {"coordinates":[76.541737,30.22497],"type":"Point"}
}