{
  "id": 2353223,
  "type": "Feature",
  "properties": {
    "tgn:hierarchy":[
        "tgn:2353223",
        "tgn:1000001",
        "tgn:7006451",
        "tgn:7012149",
        "tgn:2000103",
        "tgn:7029392"
    ],
    "tgn:id":2353223,
    "tgn:name":"Gold Bar Mine",
    "tgn:placetype":[
        "aat:300000390"
    ]
},
  "bbox": [],
  "geometry": {"coordinates":[-112.5667,34.0833],"type":"Point"}
}