{
  "id": 7502604,
  "type": "Feature",
  "properties": {
    "tgn:hierarchy":[
        "tgn:7502604",
        "tgn:7001010",
        "tgn:1000004",
        "tgn:1000141",
        "tgn:7029392"
    ],
    "tgn:id":7502604,
    "tgn:name":"Qixinggang",
    "tgn:placetype":[
        "aat:300008347"
    ]
},
  "bbox": [],
  "geometry": {"coordinates":[121.249444,23.749444],"type":"Point"}
}