{
  "id": 2608135,
  "type": "Feature",
  "properties": {
    "tgn:hierarchy":[
        "tgn:2608135",
        "tgn:1000001",
        "tgn:2001737",
        "tgn:7012149",
        "tgn:7007712",
        "tgn:7029392"
    ],
    "tgn:id":2608135,
    "tgn:name":"Rattlesnake Branch",
    "tgn:placetype":[
        "aat:300008699"
    ]
},
  "bbox": [],
  "geometry": {"coordinates":[-80.25,34.6333],"type":"Point"}
}