{
  "id": 2648880,
  "type": "Feature",
  "properties": {
    "tgn:hierarchy":[
        "tgn:2648880",
        "tgn:1000001",
        "tgn:7012149",
        "tgn:7029392"
    ],
    "tgn:id":2648880,
    "tgn:name":"Scott Branch",
    "tgn:placetype":[
        "aat:300008699"
    ]
},
  "bbox": [],
  "geometry": {"coordinates":[-94.45,34.9167],"type":"Point"}
}