{
  "id": 2450135,
  "type": "Feature",
  "properties": {
    "tgn:hierarchy":[
        "tgn:2450135",
        "tgn:1000001",
        "tgn:1003023",
        "tgn:7012149",
        "tgn:7007516",
        "tgn:7029392"
    ],
    "tgn:id":2450135,
    "tgn:name":"Line Creek",
    "tgn:placetype":[
        "aat:300008706"
    ]
},
  "bbox": [],
  "geometry": {"coordinates":[-75.7667,38.2833],"type":"Point"}
}