{
  "id": 7037926,
  "type": "Feature",
  "properties": {
    "tgn:hierarchy":[
        "tgn:7037926",
        "tgn:1000003",
        "tgn:7003142",
        "tgn:7003236",
        "tgn:1000080",
        "tgn:7029392"
    ],
    "tgn:id":7037926,
    "tgn:name":"Val Noci, Lago di",
    "tgn:placetype":[
        "aat:300008680"
    ]
},
  "bbox": [],
  "geometry": {"coordinates":[9.033333,44.483333],"type":"Point"}
}