{
  "id": 2525989,
  "type": "Feature",
  "properties": {
    "tgn:hierarchy":[
        "tgn:2525989",
        "tgn:1000001",
        "tgn:2000460",
        "tgn:7012149",
        "tgn:7007250",
        "tgn:7029392"
    ],
    "tgn:id":2525989,
    "tgn:name":"Mosquito Bay",
    "tgn:placetype":[
        "aat:300132316"
    ]
},
  "bbox": [],
  "geometry": {"coordinates":[-116.8333,48.7333],"type":"Point"}
}