{
  "id": 7105837,
  "type": "Feature",
  "properties": {
    "tgn:hierarchy":[
        "tgn:7105837",
        "tgn:7000096",
        "tgn:1000003",
        "tgn:7000084",
        "tgn:7029392"
    ],
    "tgn:id":7105837,
    "tgn:name":"Schmoll-Berg",
    "tgn:placetype":[
        "aat:300008777"
    ]
},
  "bbox": [],
  "geometry": {"coordinates":[13.583333,53.083333],"type":"Point"}
}