{
  "id": 2725267,
  "type": "Feature",
  "properties": {
    "tgn:hierarchy":[
        "tgn:2725267",
        "tgn:1000001",
        "tgn:7006451",
        "tgn:7012149",
        "tgn:2000103",
        "tgn:7029392"
    ],
    "tgn:id":2725267,
    "tgn:name":"Tonto Mountain",
    "tgn:placetype":[
        "aat:300008798"
    ]
},
  "bbox": [],
  "geometry": {"coordinates":[-112.6667,34.6167],"type":"Point"}
}