{
  "id": 2526027,
  "type": "Feature",
  "properties": {
    "tgn:hierarchy":[
        "tgn:2526027",
        "tgn:1000001",
        "tgn:7012149",
        "tgn:2000216",
        "tgn:7007158",
        "tgn:7029392"
    ],
    "tgn:id":2526027,
    "tgn:name":"Mosquito Creek",
    "tgn:placetype":[
        "aat:300008706"
    ]
},
  "bbox": [],
  "geometry": {"coordinates":[-105.8667,40.4167],"type":"Point"}
}