{
  "id": 1058968,
  "type": "Feature",
  "properties": {
    "tgn:hierarchy":[
        "tgn:1058968",
        "tgn:1000004",
        "tgn:7011531",
        "tgn:7018214",
        "tgn:7002435",
        "tgn:7029392"
    ],
    "tgn:id":1058968,
    "tgn:name":"Rogovskaya",
    "tgn:placetype":[
        "aat:300008347"
    ]
},
  "bbox": [],
  "geometry": {"coordinates":[38.75,45.7333],"type":"Point"}
}