{
  "id": 7217455,
  "type": "Feature",
  "properties": {
    "tgn:hierarchy":[
        "tgn:7217455",
        "tgn:7002681",
        "tgn:7001395",
        "tgn:1000003",
        "tgn:1000074",
        "tgn:7029392"
    ],
    "tgn:id":7217455,
    "tgn:name":"Yiannits\u00e1, \u00c1kra",
    "tgn:placetype":[
        "aat:300386846"
    ]
},
  "bbox": [],
  "geometry": {"coordinates":[23.283333,38.766667],"type":"Point"}
}