{
  "id": 7145334,
  "type": "Feature",
  "properties": {
    "tgn:hierarchy":[
        "tgn:7145334",
        "tgn:1000003",
        "tgn:7003677",
        "tgn:7000084",
        "tgn:7029392"
    ],
    "tgn:id":7145334,
    "tgn:name":"Knollen",
    "tgn:placetype":[
        "aat:300008777"
    ]
},
  "bbox": [],
  "geometry": {"coordinates":[7.65,51.033333],"type":"Point"}
}