{
  "id": 7440147,
  "type": "Feature",
  "properties": {
    "tgn:hierarchy":[
        "tgn:7440147",
        "tgn:7005585",
        "tgn:1000001",
        "tgn:7005560",
        "tgn:7029392"
    ],
    "tgn:id":7440147,
    "tgn:name":"San Marcos, Laguna",
    "tgn:placetype":[
        "aat:300008679"
    ]
},
  "bbox": [],
  "geometry": {"coordinates":[-99.283333,16.666667],"type":"Point"}
}