{
  "id": 2453169,
  "type": "Feature",
  "properties": {
    "tgn:hierarchy":[
        "tgn:2453169",
        "tgn:1000001",
        "tgn:7012149",
        "tgn:7014589",
        "tgn:7007515",
        "tgn:7029392"
    ],
    "tgn:id":2453169,
    "tgn:name":"Little Cathance Lake",
    "tgn:placetype":[
        "aat:300008680"
    ]
},
  "bbox": [],
  "geometry": {"coordinates":[-67.35,44.9333],"type":"Point"}
}