{
  "id": 2395787,
  "type": "Feature",
  "properties": {
    "tgn:hierarchy":[
        "tgn:2395787",
        "tgn:1000001",
        "tgn:7012149",
        "tgn:2001912",
        "tgn:7007825",
        "tgn:7029392"
    ],
    "tgn:id":2395787,
    "tgn:name":"Hollow Rock Branch",
    "tgn:placetype":[
        "aat:300008699"
    ]
},
  "bbox": [],
  "geometry": {"coordinates":[-84.7333,36.5833],"type":"Point"}
}