{
  "id": 7548146,
  "type": "Feature",
  "properties": {
    "tgn:hierarchy":[
        "tgn:7548146",
        "tgn:1000004",
        "tgn:7000198",
        "tgn:7016788",
        "tgn:7029392"
    ],
    "tgn:id":7548146,
    "tgn:name:en":"Alai",
    "tgn:placetype":[
        "aat:300008347"
    ]
},
  "bbox": [],
  "geometry": {"coordinates":[73.577266,27.325984],"type":"Point"}
}