{
  "id": 2074584,
  "type": "Feature",
  "properties": {
    "tgn:hierarchy":[
        "tgn:2074584",
        "tgn:1000001",
        "tgn:7012149",
        "tgn:2001546",
        "tgn:7007709",
        "tgn:7029392"
    ],
    "tgn:id":2074584,
    "tgn:name":"Fairview",
    "tgn:placetype":[
        "aat:300008347",
        "aat:300387210"
    ]
},
  "bbox": [],
  "geometry": {"coordinates":[-80.5333,35.1333],"type":"Point"}
}