{
  "id": 1030005,
  "type": "Feature",
  "properties": {
    "tgn:hierarchy":[
        "tgn:1030005",
        "tgn:7002445",
        "tgn:1000003",
        "tgn:7008118",
        "tgn:7008591",
        "tgn:7029392"
    ],
    "tgn:id":1030005,
    "tgn:name:ang":"Maslach",
    "tgn:placetype":[
        "aat:300008347",
        "aat:300008416",
        "aat:300387220",
        "aat:300000547",
        "aat:300008375",
        "aat:300387302"
    ]
},
  "bbox": [],
  "geometry": {"coordinates":[-1.533333,53.133333],"type":"Point"}
}