{
  "id": 7290554,
  "type": "Feature",
  "properties": {
    "tgn:hierarchy":[
        "tgn:7290554",
        "tgn:1001699",
        "tgn:1000049",
        "tgn:1000002",
        "tgn:7029392"
    ],
    "tgn:id":7290554,
    "tgn:name":"D\u00edaz, Cerro",
    "tgn:placetype":[
        "aat:300008795"
    ]
},
  "bbox": [],
  "geometry": {"coordinates":[-71.733333,-43.65],"type":"Point"}
}