{
  "id": 2365885,
  "type": "Feature",
  "properties": {
    "tgn:hierarchy":[
        "tgn:2365885",
        "tgn:1000001",
        "tgn:7012149",
        "tgn:2001501",
        "tgn:7007709",
        "tgn:7029392"
    ],
    "tgn:id":2365885,
    "tgn:name":"Gretna Green",
    "tgn:placetype":[
        "aat:300008347"
    ]
},
  "bbox": [],
  "geometry": {"coordinates":[-77.85,36.3833],"type":"Point"}
}