{
  "id": 2387533,
  "type": "Feature",
  "properties": {
    "tgn:hierarchy":[
        "tgn:2387533",
        "tgn:1000001",
        "tgn:7012149",
        "tgn:2000221",
        "tgn:7007158",
        "tgn:7029392"
    ],
    "tgn:id":2387533,
    "tgn:name":"Heyden Gulch",
    "tgn:placetype":[
        "aat:300008761"
    ]
},
  "bbox": [],
  "geometry": {"coordinates":[-105.25,39.8667],"type":"Point"}
}