{
  "id": 7566561,
  "type": "Feature",
  "properties": {
    "tgn:hierarchy":[
        "tgn:7566561",
        "tgn:1000004",
        "tgn:1001832",
        "tgn:7000198",
        "tgn:7029392"
    ],
    "tgn:id":7566561,
    "tgn:name:en":"Guma Reserved Forest",
    "tgn:placetype":[
        "aat:300008865"
    ]
},
  "bbox": [],
  "geometry": {"coordinates":[89.958966,26.384291],"type":"Point"}
}