{
  "id": 2476848,
  "type": "Feature",
  "properties": {
    "tgn:hierarchy":[
        "tgn:2476848",
        "tgn:1000001",
        "tgn:7012149",
        "tgn:2002374",
        "tgn:7007923",
        "tgn:7029392"
    ],
    "tgn:id":2476848,
    "tgn:name":"Lyle Reservoir",
    "tgn:placetype":[
        "aat:300006191"
    ]
},
  "bbox": [],
  "geometry": {"coordinates":[-106.7667,43.9167],"type":"Point"}
}