{
  "id": 1005096,
  "type": "Feature",
  "properties": {
    "tgn:hierarchy":[
        "tgn:1005096",
        "tgn:7006453",
        "tgn:1001206",
        "tgn:1000001",
        "tgn:7004624",
        "tgn:7029392"
    ],
    "tgn:id":1005096,
    "tgn:name":"Miramar",
    "tgn:placetype":[
        "aat:300000745"
    ]
},
  "bbox": [],
  "geometry": {"coordinates":[-82.4167,23.1167],"type":"Point"}
}