{
  "id": 7209346,
  "type": "Feature",
  "properties": {
    "tgn:hierarchy":[
        "tgn:7209346",
        "tgn:1000003",
        "tgn:7003682",
        "tgn:7000084",
        "tgn:7029392"
    ],
    "tgn:id":7209346,
    "tgn:name":"Bechtheim",
    "tgn:placetype":[
        "aat:300008347"
    ]
},
  "bbox": [],
  "geometry": {"coordinates":[8.292222,49.727778],"type":"Point"}
}