{
  "id": 2438210,
  "type": "Feature",
  "properties": {
    "tgn:hierarchy":[
        "tgn:2438210",
        "tgn:1002201",
        "tgn:1000001",
        "tgn:7012149",
        "tgn:7007517",
        "tgn:7029392"
    ],
    "tgn:id":2438210,
    "tgn:name":"Kingman Pond",
    "tgn:placetype":[
        "aat:300008680"
    ]
},
  "bbox": [],
  "geometry": {"coordinates":[-71.2167,42.0167],"type":"Point"}
}