{
  "id": 7405500,
  "type": "Feature",
  "properties": {
    "tgn:hierarchy":[
        "tgn:7405500",
        "tgn:7005585",
        "tgn:1000001",
        "tgn:7005560",
        "tgn:7029392"
    ],
    "tgn:id":7405500,
    "tgn:name":"Apintla, Cerro",
    "tgn:placetype":[
        "aat:300008795"
    ]
},
  "bbox": [],
  "geometry": {"coordinates":[-99.883333,17.85],"type":"Point"}
}