{
  "id": 1080469,
  "type": "Feature",
  "properties": {
    "tgn:hierarchy":[
        "tgn:1080469",
        "tgn:1000004",
        "tgn:1000962",
        "tgn:7000896",
        "tgn:1000120",
        "tgn:7029392"
    ],
    "tgn:id":1080469,
    "tgn:name":"Kashiwara",
    "tgn:placetype":[
        "aat:300008347"
    ]
},
  "bbox": [],
  "geometry": {"coordinates":[135.6167,34.5833],"type":"Point"}
}