{
  "id": 2514200,
  "type": "Feature",
  "properties": {
    "tgn:hierarchy":[
        "tgn:2514200",
        "tgn:1000001",
        "tgn:7012149",
        "tgn:7007157",
        "tgn:1002828",
        "tgn:7029392"
    ],
    "tgn:id":2514200,
    "tgn:name":"Miller Canyon",
    "tgn:placetype":[
        "aat:300008761"
    ]
},
  "bbox": [],
  "geometry": {"coordinates":[-117.2167,33.5167],"type":"Point"}
}