{
  "id": 1092864,
  "type": "Feature",
  "properties": {
    "tgn:hierarchy":[
        "tgn:1092864",
        "tgn:7001242",
        "tgn:7017582",
        "tgn:1000193",
        "tgn:7029392"
    ],
    "tgn:id":1092864,
    "tgn:name":"Belmont",
    "tgn:placetype":[
        "aat:300008347"
    ]
},
  "bbox": [],
  "geometry": {"coordinates":[24.3667,-29.4167],"type":"Point"}
}