<<<<<<< HEAD
{
  "id": 7057789,
  "type": "Feature",
  "properties": {
    "tgn:hierarchy":[
        "tgn:7057789",
        "tgn:7007850",
        "tgn:1003491",
        "tgn:1000003",
        "tgn:1000080",
        "tgn:7029392"
    ],
    "tgn:id":7057789,
    "tgn:name":"Armo, Fiumara d'",
    "tgn:placetype":[
        "aat:300008699"
    ]
},
  "bbox": [],
  "geometry": {"coordinates":[15.666667,38.066667],"type":"Point"}
}
=======
{"geometry":{"type":"Point","coordinates":[15.666667,38.066667]},"type":"Feature","properties":{"hierarchy":["tgn:7057789","tgn:7007850","tgn:1003491","tgn:1000003","tgn:1000080","tgn:7029392"],"placetype":["aat:300008699"],"id":7057789,"name:xx":"Armo, Fiumara d'"}}
>>>>>>> 03f74aca74312dbeaf24d7e61306dd6a786dc3d0
