{
  "id": 2399541,
  "type": "Feature",
  "properties": {
    "tgn:hierarchy":[
        "tgn:2399541",
        "tgn:1000001",
        "tgn:2001704",
        "tgn:7012149",
        "tgn:7007708",
        "tgn:7029392"
    ],
    "tgn:id":2399541,
    "tgn:name":"Horner Creek",
    "tgn:placetype":[
        "aat:300008706"
    ]
},
  "bbox": [],
  "geometry": {"coordinates":[-124.35,42.9333],"type":"Point"}
}