<<<<<<< HEAD
{
  "id": 7476463,
  "type": "Feature",
  "properties": {
    "tgn:hierarchy":[
        "tgn:7476463",
        "tgn:7488858",
        "tgn:1000004",
        "tgn:1000141",
        "tgn:7029392"
    ],
    "tgn:id":7476463,
    "tgn:name":"Zhuogun Xi",
    "tgn:placetype":[
        "aat:300008699"
    ]
},
  "bbox": [],
  "geometry": {"coordinates":[120.900966,23.780304],"type":"Point"}
}
=======
{"geometry":{"type":"Point","coordinates":[120.900966,23.780304]},"type":"Feature","properties":{"hierarchy":["tgn:7476463","tgn:7488858","tgn:1000004","tgn:1000141","tgn:7029392"],"placetype":["aat:300008699"],"id":7476463,"name:xx":"Zhuogun Xi"}}
>>>>>>> 03f74aca74312dbeaf24d7e61306dd6a786dc3d0
