{
  "id": 2600131,
  "type": "Feature",
  "properties": {
    "tgn:hierarchy":[
        "tgn:2600131",
        "tgn:7006450",
        "tgn:1000001",
        "tgn:7012149",
        "tgn:2000086",
        "tgn:7029392"
    ],
    "tgn:id":2600131,
    "tgn:name":"Ptarmigan Lake",
    "tgn:placetype":[
        "aat:300008680"
    ]
},
  "bbox": [],
  "geometry": {"coordinates":[-141.1667,61.85],"type":"Point"}
}