{
  "id": 1048395,
  "type": "Feature",
  "properties": {
    "tgn:hierarchy":[
        "tgn:1048395",
        "tgn:7008695",
        "tgn:7002448",
        "tgn:1000003",
        "tgn:7008591",
        "tgn:7029392"
    ],
    "tgn:id":1048395,
    "tgn:name:en":"Muckamore",
    "tgn:placetype":[
        "aat:300008347"
    ]
},
  "bbox": [],
  "geometry": {"coordinates":[-6.15,54.683333],"type":"Point"}
}