{
  "id": 7285663,
  "type": "Feature",
  "properties": {
    "tgn:hierarchy":[
        "tgn:7285663",
        "tgn:1001637",
        "tgn:1000049",
        "tgn:1000002",
        "tgn:7029392"
    ],
    "tgn:id":7285663,
    "tgn:name":"Pichicui, Punta",
    "tgn:placetype":[
        "aat:300386846"
    ]
},
  "bbox": [],
  "geometry": {"coordinates":[-73.45,-37.216667],"type":"Point"}
}