{
  "id": 2622002,
  "type": "Feature",
  "properties": {
    "tgn:hierarchy":[
        "tgn:2622002",
        "tgn:1000001",
        "tgn:7012149",
        "tgn:7007919",
        "tgn:7029392"
    ],
    "tgn:id":2622002,
    "tgn:name":"Roberts Branch",
    "tgn:placetype":[
        "aat:300008699"
    ]
},
  "bbox": [],
  "geometry": {"coordinates":[-77.6667,37.5167],"type":"Point"}
}