{
  "id": 7185972,
  "type": "Feature",
  "properties": {
    "tgn:hierarchy":[
        "tgn:7185972",
        "tgn:7003669",
        "tgn:1000003",
        "tgn:7000084",
        "tgn:7029392"
    ],
    "tgn:id":7185972,
    "tgn:name":"Grafen-Wald",
    "tgn:placetype":[
        "aat:300008863"
    ]
},
  "bbox": [],
  "geometry": {"coordinates":[13.116667,48.35],"type":"Point"}
}