{
  "id": 2037714,
  "type": "Feature",
  "properties": {
    "tgn:hierarchy":[
        "tgn:2037714",
        "tgn:1000001",
        "tgn:1002193",
        "tgn:7012149",
        "tgn:7007255",
        "tgn:7029392"
    ],
    "tgn:id":2037714,
    "tgn:name":"Berlin",
    "tgn:placetype":[
        "aat:300008347"
    ]
},
  "bbox": [],
  "geometry": {"coordinates":[-84.15,38.6833],"type":"Point"}
}