{
  "id": 7288938,
  "type": "Feature",
  "properties": {
    "tgn:hierarchy":[
        "tgn:7288938",
        "tgn:1001630",
        "tgn:1000049",
        "tgn:1000002",
        "tgn:7029392"
    ],
    "tgn:id":7288938,
    "tgn:name":"La Guardia, Vegas de",
    "tgn:placetype":[
        "aat:300008686"
    ]
},
  "bbox": [],
  "geometry": {"coordinates":[-69.566667,-27.716667],"type":"Point"}
}