{
  "id": 2536559,
  "type": "Feature",
  "properties": {
    "tgn:hierarchy":[
        "tgn:2536559",
        "tgn:7006450",
        "tgn:1000001",
        "tgn:7019698",
        "tgn:7012149",
        "tgn:7029392"
    ],
    "tgn:id":2536559,
    "tgn:name":"Nearhouse Mine",
    "tgn:placetype":[
        "aat:300000390"
    ]
},
  "bbox": [],
  "geometry": {"coordinates":[-149.5167,60.85],"type":"Point"}
}