{
  "id": 1055288,
  "type": "Feature",
  "properties": {
    "tgn:hierarchy":[
        "tgn:1055288",
        "tgn:1003373",
        "tgn:1000004",
        "tgn:7018214",
        "tgn:7002435",
        "tgn:7029392"
    ],
    "tgn:id":1055288,
    "tgn:name":"Kimil'tey",
    "tgn:placetype":[
        "aat:300008347"
    ]
},
  "bbox": [],
  "geometry": {"coordinates":[101.9667,54.1333],"type":"Point"}
}