{
  "id": 7532386,
  "type": "Feature",
  "properties": {
    "tgn:hierarchy":[
        "tgn:7532386",
        "tgn:7001242",
        "tgn:7016833",
        "tgn:1001092",
        "tgn:7029392"
    ],
    "tgn:id":7532386,
    "tgn:name":"Mad\u012bnat as Sa'\u0101dah",
    "tgn:placetype":[
        "aat:300000745"
    ]
},
  "bbox": [],
  "geometry": {"coordinates":[31.252033,30.132317],"type":"Point"}
}