{
  "id": 1132233,
  "type": "Feature",
  "properties": {
    "tgn:hierarchy":[
        "tgn:1132233",
        "tgn:1000001",
        "tgn:7012149",
        "tgn:7007157",
        "tgn:7029392"
    ],
    "tgn:id":1132233,
    "tgn:name":"Alamo Creek",
    "tgn:placetype":[
        "aat:300008706"
    ]
},
  "bbox": [],
  "geometry": {"coordinates":[-121.8667,37.8167],"type":"Point"}
}