{
  "id": 7525246,
  "type": "Feature",
  "properties": {
    "tgn:hierarchy":[
        "tgn:7525246",
        "tgn:7001242",
        "tgn:7016833",
        "tgn:1001114",
        "tgn:7029392"
    ],
    "tgn:id":7525246,
    "tgn:name:en":"Bah\u012bj, Jaz\u012brat",
    "tgn:placetype":[
        "aat:300008791"
    ]
},
  "bbox": [],
  "geometry": {"coordinates":[31.133333,27.266667],"type":"Point"}
}