{
  "id": 2277283,
  "type": "Feature",
  "properties": {
    "tgn:hierarchy":[
        "tgn:2277283",
        "tgn:1000001",
        "tgn:7012149",
        "tgn:2000886",
        "tgn:7007256",
        "tgn:7029392"
    ],
    "tgn:id":2277283,
    "tgn:name":"Davis Island",
    "tgn:placetype":[
        "aat:300008791"
    ]
},
  "bbox": [],
  "geometry": {"coordinates":[-91.0333,32.15],"type":"Point"}
}