<<<<<<< HEAD
{
  "id": 7481134,
  "type": "Feature",
  "properties": {
    "tgn:hierarchy":[
        "tgn:7481134",
        "tgn:7001004",
        "tgn:1000004",
        "tgn:1000141",
        "tgn:7029392"
    ],
    "tgn:id":7481134,
    "tgn:name":"Chici Gong",
    "tgn:placetype":[
        "aat:300007595"
    ]
},
  "bbox": [],
  "geometry": {"coordinates":[120.246944,22.736944],"type":"Point"}
}
=======
{"geometry":{"type":"Point","coordinates":[120.246944,22.736944]},"type":"Feature","properties":{"hierarchy":["tgn:7481134","tgn:7001004","tgn:1000004","tgn:1000141","tgn:7029392"],"placetype":["aat:300007595"],"id":7481134,"name:xx":"Chici Gong"}}
>>>>>>> 03f74aca74312dbeaf24d7e61306dd6a786dc3d0
