{
  "id": 7481134,
  "type": "Feature",
  "properties": {
    "tgn:hierarchy":[
        "tgn:7481134",
        "tgn:7001004",
        "tgn:1000004",
        "tgn:1000141",
        "tgn:7029392"
    ],
    "tgn:id":7481134,
    "tgn:name":"Chici Gong",
    "tgn:placetype":[
        "aat:300007595"
    ]
},
  "bbox": [],
  "geometry": {"coordinates":[120.246944,22.736944],"type":"Point"}
}