{
  "id": 2545668,
  "type": "Feature",
  "properties": {
    "tgn:hierarchy":[
        "tgn:2545668",
        "tgn:1000001",
        "tgn:7012149",
        "tgn:7007826",
        "tgn:7029392"
    ],
    "tgn:id":2545668,
    "tgn:name":"North Fork Chambers Creek",
    "tgn:placetype":[
        "aat:300008706"
    ]
},
  "bbox": [],
  "geometry": {"coordinates":[-97.2833,32.45],"type":"Point"}
}