{
  "id": 7433690,
  "type": "Feature",
  "properties": {
    "tgn:hierarchy":[
        "tgn:7433690",
        "tgn:1000001",
        "tgn:1001960",
        "tgn:7005560",
        "tgn:7029392"
    ],
    "tgn:id":7433690,
    "tgn:name":"Rancho Tubaca",
    "tgn:placetype":[
        "aat:300000241"
    ]
},
  "bbox": [],
  "geometry": {"coordinates":[-109.866667,28.083333],"type":"Point"}
}