{
  "id": 1063503,
  "type": "Feature",
  "properties": {
    "tgn:hierarchy":[
        "tgn:1063503",
        "tgn:1000003",
        "tgn:7003774",
        "tgn:1000097",
        "tgn:7029392"
    ],
    "tgn:id":1063503,
    "tgn:name":"Rensj\u00f6n",
    "tgn:placetype":[
        "aat:300008347"
    ]
},
  "bbox": [],
  "geometry": {"coordinates":[19.6333,68.0667],"type":"Point"}
}