{
  "id": 7590928,
  "type": "Feature",
  "properties": {
    "tgn:hierarchy":[
        "tgn:7590928",
        "tgn:1000004",
        "tgn:7000198",
        "tgn:7000799",
        "tgn:7029392"
    ],
    "tgn:id":7590928,
    "tgn:name:en":"Bal\u0101h",
    "tgn:placetype":[
        "aat:300008347"
    ]
},
  "bbox": [],
  "geometry": {"coordinates":[74.754298,32.562487],"type":"Point"}
}