<<<<<<< HEAD
{
  "id": 7057604,
  "type": "Feature",
  "properties": {
    "tgn:hierarchy":[
        "tgn:7057604",
        "tgn:7003008",
        "tgn:1000003",
        "tgn:7002997",
        "tgn:1000080",
        "tgn:7029392"
    ],
    "tgn:id":7057604,
    "tgn:name":"Asiago, Altipiano d'",
    "tgn:placetype":[
        "aat:300386856"
    ]
},
  "bbox": [],
  "geometry": {"coordinates":[11.5,45.9],"type":"Point"}
}
=======
{"geometry":{"type":"Point","coordinates":[11.500000,45.900000]},"type":"Feature","properties":{"hierarchy":["tgn:7057604","tgn:7003008","tgn:1000003","tgn:7002997","tgn:1000080","tgn:7029392"],"placetype":["aat:300386856"],"id":7057604,"name:xx":"Asiago, Altipiano d'"}}
>>>>>>> 03f74aca74312dbeaf24d7e61306dd6a786dc3d0
