<<<<<<< HEAD
{
  "id": 2762954,
  "type": "Feature",
  "properties": {
    "tgn:hierarchy":[
        "tgn:2762954",
        "tgn:1000001",
        "tgn:7012149",
        "tgn:1002406",
        "tgn:7007520",
        "tgn:7029392"
    ],
    "tgn:id":2762954,
    "tgn:name":"Westman Lake",
    "tgn:placetype":[
        "aat:300008680"
    ]
},
  "bbox": [],
  "geometry": {"coordinates":[-83.6833,42.7833],"type":"Point"}
}
=======
{"geometry":{"type":"Point","coordinates":[-83.683300,42.783300]},"type":"Feature","properties":{"hierarchy":["tgn:2762954","tgn:1000001","tgn:7012149","tgn:1002406","tgn:7007520","tgn:7029392"],"placetype":["aat:300008680"],"id":2762954,"name:xx":"Westman Lake"}}
>>>>>>> 03f74aca74312dbeaf24d7e61306dd6a786dc3d0
