{
  "id": 7559752,
  "type": "Feature",
  "properties": {
    "tgn:hierarchy":[
        "tgn:7559752",
        "tgn:1000004",
        "tgn:7000198",
        "tgn:7016722",
        "tgn:7029392"
    ],
    "tgn:id":7559752,
    "tgn:name:en":"Rudi Nagla",
    "tgn:placetype":[
        "aat:300008347"
    ]
},
  "bbox": [],
  "geometry": {"coordinates":[79.445875,27.778069],"type":"Point"}
}