{
  "id": 7307174,
  "type": "Feature",
  "properties": {
    "tgn:hierarchy":[
        "tgn:7307174",
        "tgn:7002810",
        "tgn:7001158",
        "tgn:1000003",
        "tgn:1000095",
        "tgn:7029392"
    ],
    "tgn:id":7307174,
    "tgn:name":"Madrigalejo del Monte",
    "tgn:placetype":[
        "aat:300008347"
    ]
},
  "bbox": [],
  "geometry": {"coordinates":[-3.716667,42.116667],"type":"Point"}
}