{
  "id": 7173633,
  "type": "Feature",
  "properties": {
    "tgn:hierarchy":[
        "tgn:7173633",
        "tgn:1000003",
        "tgn:7003688",
        "tgn:7000084",
        "tgn:7029392"
    ],
    "tgn:id":7173633,
    "tgn:name":"Gro\u00df Niendorf",
    "tgn:placetype":[
        "aat:300008347"
    ]
},
  "bbox": [],
  "geometry": {"coordinates":[10.25,53.85],"type":"Point"}
}