<<<<<<< HEAD
{
  "id": 7021951,
  "type": "Feature",
  "properties": {
    "tgn:hierarchy":[
        "tgn:7021951",
        "tgn:1000001",
        "tgn:7006451",
        "tgn:7012149",
        "tgn:2000097",
        "tgn:7029392"
    ],
    "tgn:id":7021951,
    "tgn:name":"Coyote Spring",
    "tgn:placetype":[
        "aat:300008697"
    ]
},
  "bbox": [],
  "geometry": {"coordinates":[-111.3667,33.7333],"type":"Point"}
}
=======
{"geometry":{"type":"Point","coordinates":[-111.366700,33.733300]},"type":"Feature","properties":{"hierarchy":["tgn:7021951","tgn:1000001","tgn:7006451","tgn:7012149","tgn:2000097","tgn:7029392"],"placetype":["aat:300008697"],"id":7021951,"name:xx":"Coyote Spring"}}
>>>>>>> 03f74aca74312dbeaf24d7e61306dd6a786dc3d0
