{
  "id": 2228702,
  "type": "Feature",
  "properties": {
    "tgn:hierarchy":[
        "tgn:2228702",
        "tgn:1000001",
        "tgn:7012149",
        "tgn:2001241",
        "tgn:7007523",
        "tgn:7029392"
    ],
    "tgn:id":2228702,
    "tgn:name":"Cedar Falls Branch",
    "tgn:placetype":[
        "aat:300008699"
    ]
},
  "bbox": [],
  "geometry": {"coordinates":[-90.45,37.8667],"type":"Point"}
}