{
  "id": 7032061,
  "type": "Feature",
  "properties": {
    "tgn:hierarchy":[
        "tgn:7032061",
        "tgn:7001242",
        "tgn:7001658",
        "tgn:7029392"
    ],
    "tgn:id":7032061,
    "tgn:name":"Debub",
    "tgn:placetype":[
        "aat:300387064",
        "aat:300000774"
    ]
},
  "bbox": [],
  "geometry": {"coordinates":[38.847,14.833],"type":"Point"}
}