<<<<<<< HEAD
{
  "id": 7350637,
  "type": "Feature",
  "properties": {
    "tgn:hierarchy":[
        "tgn:7350637",
        "tgn:1000001",
        "tgn:1001960",
        "tgn:7005560",
        "tgn:7029392"
    ],
    "tgn:id":7350637,
    "tgn:name":"Caba\u00f1a",
    "tgn:placetype":[
        "aat:300008347"
    ]
},
  "bbox": [],
  "geometry": {"coordinates":[-110.366667,28.7],"type":"Point"}
}
=======
{"geometry":{"type":"Point","coordinates":[-110.366667,28.700000]},"type":"Feature","properties":{"hierarchy":["tgn:7350637","tgn:1000001","tgn:1001960","tgn:7005560","tgn:7029392"],"placetype":["aat:300008347"],"id":7350637,"name:xx":"Caba\u00f1a"}}
>>>>>>> 03f74aca74312dbeaf24d7e61306dd6a786dc3d0
