<<<<<<< HEAD
{
  "id": 7248301,
  "type": "Feature",
  "properties": {
    "tgn:hierarchy":[
        "tgn:7248301",
        "tgn:7007877",
        "tgn:1000003",
        "tgn:1000063",
        "tgn:4012014",
        "tgn:7029392"
    ],
    "tgn:id":7248301,
    "tgn:name":"Belval",
    "tgn:placetype":[
        "aat:300008347"
    ]
},
  "bbox": [],
  "geometry": {"coordinates":[3.7,50.716667],"type":"Point"}
}
=======
{"geometry":{"type":"Point","coordinates":[3.700000,50.716667]},"type":"Feature","properties":{"hierarchy":["tgn:7248301","tgn:7007877","tgn:1000003","tgn:1000063","tgn:4012014","tgn:7029392"],"placetype":["aat:300008347"],"id":7248301,"name:xx":"Belval"}}
>>>>>>> 03f74aca74312dbeaf24d7e61306dd6a786dc3d0
