{
  "id": 2708582,
  "type": "Feature",
  "properties": {
    "tgn:hierarchy":[
        "tgn:2708582",
        "tgn:1000001",
        "tgn:7012149",
        "tgn:2001865",
        "tgn:7007825",
        "tgn:7029392"
    ],
    "tgn:id":2708582,
    "tgn:name":"Sycamore Spring",
    "tgn:placetype":[
        "aat:300008697"
    ]
},
  "bbox": [],
  "geometry": {"coordinates":[-83.5667,36.2333],"type":"Point"}
}