{
  "id": 2238467,
  "type": "Feature",
  "properties": {
    "tgn:hierarchy":[
        "tgn:2238467",
        "tgn:1000001",
        "tgn:2002103",
        "tgn:7012149",
        "tgn:7007827",
        "tgn:7029392"
    ],
    "tgn:id":2238467,
    "tgn:name":"Chokecherry Summer Home Area",
    "tgn:placetype":[
        "aat:300008347"
    ]
},
  "bbox": [],
  "geometry": {"coordinates":[-111.65,41.7667],"type":"Point"}
}