{
  "id": 2522260,
  "type": "Feature",
  "properties": {
    "tgn:hierarchy":[
        "tgn:2522260",
        "tgn:1000001",
        "tgn:7012149",
        "tgn:2001161",
        "tgn:7007522",
        "tgn:7029392"
    ],
    "tgn:id":2522260,
    "tgn:name":"Moon Lake",
    "tgn:placetype":[
        "aat:300386845"
    ]
},
  "bbox": [],
  "geometry": {"coordinates":[-90.9167,33.1167],"type":"Point"}
}