{
  "id": 7018137,
  "type": "Feature",
  "properties": {
    "tgn:hierarchy":[
        "tgn:7018137",
        "tgn:1000004",
        "tgn:7002081",
        "tgn:1000111",
        "tgn:7029392"
    ],
    "tgn:id":7018137,
    "tgn:name":"Yinping",
    "tgn:placetype":[
        "aat:300008347"
    ]
},
  "bbox": [],
  "geometry": {"coordinates":[118.6167,34.2667],"type":"Point"}
}