{
  "id": 2534353,
  "type": "Feature",
  "properties": {
    "tgn:hierarchy":[
        "tgn:2534353",
        "tgn:1000001",
        "tgn:7012149",
        "tgn:2001281",
        "tgn:7007524",
        "tgn:7029392"
    ],
    "tgn:id":2534353,
    "tgn:name":"NE NE Section 18 Mine",
    "tgn:placetype":[
        "aat:300000390"
    ]
},
  "bbox": [],
  "geometry": {"coordinates":[-111.8833,46.45],"type":"Point"}
}