{
  "id": 2281685,
  "type": "Feature",
  "properties": {
    "tgn:hierarchy":[
        "tgn:2281685",
        "tgn:1000001",
        "tgn:2001022",
        "tgn:7012149",
        "tgn:7007521",
        "tgn:7029392"
    ],
    "tgn:id":2281685,
    "tgn:name":"Deer Creek",
    "tgn:placetype":[
        "aat:300008706"
    ]
},
  "bbox": [],
  "geometry": {"coordinates":[-93.0833,43.8333],"type":"Point"}
}