<<<<<<< HEAD
{
  "id": 2151554,
  "type": "Feature",
  "properties": {
    "tgn:hierarchy":[
        "tgn:2151554",
        "tgn:1000001",
        "tgn:7012149",
        "tgn:7022207",
        "tgn:7007919",
        "tgn:7029392"
    ],
    "tgn:id":2151554,
    "tgn:name":"Battersea",
    "tgn:placetype":[
        "aat:300008347"
    ]
},
  "bbox": [],
  "geometry": {"coordinates":[-77.4167,37.2167],"type":"Point"}
}
=======
{"geometry":{"type":"Point","coordinates":[-77.416700,37.216700]},"type":"Feature","properties":{"hierarchy":["tgn:2151554","tgn:1000001","tgn:7012149","tgn:7022207","tgn:7007919","tgn:7029392"],"placetype":["aat:300008347"],"id":2151554,"name:xx":"Battersea"}}
>>>>>>> 03f74aca74312dbeaf24d7e61306dd6a786dc3d0
