{
  "id": 2151554,
  "type": "Feature",
  "properties": {
    "tgn:hierarchy":[
        "tgn:2151554",
        "tgn:1000001",
        "tgn:7012149",
        "tgn:7022207",
        "tgn:7007919",
        "tgn:7029392"
    ],
    "tgn:id":2151554,
    "tgn:name":"Battersea",
    "tgn:placetype":[
        "aat:300008347"
    ]
},
  "bbox": [],
  "geometry": {"coordinates":[-77.4167,37.2167],"type":"Point"}
}