{
  "id": 7462659,
  "type": "Feature",
  "properties": {
    "tgn:hierarchy":[
        "tgn:7462659",
        "tgn:7002444",
        "tgn:1000003",
        "tgn:7009907",
        "tgn:7008591",
        "tgn:7029392"
    ],
    "tgn:id":7462659,
    "tgn:name:en":"Inganess, Bay of",
    "tgn:placetype":[
        "aat:300132316"
    ]
},
  "bbox": [],
  "geometry": {"coordinates":[-2.883333,58.983333],"type":"Point"}
}