{
  "id": 7384512,
  "type": "Feature",
  "properties": {
    "tgn:hierarchy":[
        "tgn:7384512",
        "tgn:1000001",
        "tgn:7005591",
        "tgn:7005560",
        "tgn:7029392"
    ],
    "tgn:id":7384512,
    "tgn:name":"Ojamanes",
    "tgn:placetype":[
        "aat:300008347"
    ]
},
  "bbox": [],
  "geometry": {"coordinates":[-94.233333,16.333333],"type":"Point"}
}