{
  "id": 2047029,
  "type": "Feature",
  "properties": {
    "tgn:hierarchy":[
        "tgn:2047029",
        "tgn:2000934",
        "tgn:1000001",
        "tgn:7012149",
        "tgn:7007516",
        "tgn:7029392"
    ],
    "tgn:id":2047029,
    "tgn:name":"Evitts Creek",
    "tgn:placetype":[
        "aat:300387016"
    ]
},
  "bbox": [],
  "geometry": {"coordinates":[-78.7333,39.6167],"type":"Point"}
}