{
  "id": 2105768,
  "type": "Feature",
  "properties": {
    "tgn:hierarchy":[
        "tgn:2105768",
        "tgn:1000001",
        "tgn:7012149",
        "tgn:1002290",
        "tgn:7007826",
        "tgn:7029392"
    ],
    "tgn:id":2105768,
    "tgn:name":"Lowry Crossing",
    "tgn:placetype":[
        "aat:300008347"
    ]
},
  "bbox": [],
  "geometry": {"coordinates":[-96.5333,33.15],"type":"Point"}
}