{
  "id": 1120762,
  "type": "Feature",
  "properties": {
    "tgn:hierarchy":[
        "tgn:1120762",
        "tgn:1002366",
        "tgn:1000001",
        "tgn:7012149",
        "tgn:7007159",
        "tgn:7029392"
    ],
    "tgn:id":1120762,
    "tgn:name":"Westcott Cove",
    "tgn:placetype":[
        "aat:300132317"
    ]
},
  "bbox": [],
  "geometry": {"coordinates":[-73.5167,41.0333],"type":"Point"}
}