{
  "id": 2396212,
  "type": "Feature",
  "properties": {
    "tgn:hierarchy":[
        "tgn:2396212",
        "tgn:1000001",
        "tgn:7012149",
        "tgn:1002742",
        "tgn:7007920",
        "tgn:7029392"
    ],
    "tgn:id":2396212,
    "tgn:name":"Holman Creek",
    "tgn:placetype":[
        "aat:300008706"
    ]
},
  "bbox": [],
  "geometry": {"coordinates":[-120.7167,48.8333],"type":"Point"}
}