<<<<<<< HEAD
{
  "id": 7471375,
  "type": "Feature",
  "properties": {
    "tgn:hierarchy":[
        "tgn:7471375",
        "tgn:1000004",
        "tgn:7492971",
        "tgn:1000141",
        "tgn:7029392"
    ],
    "tgn:id":7471375,
    "tgn:name":"Fangshan Qiao",
    "tgn:placetype":[
        "aat:300007836"
    ]
},
  "bbox": [],
  "geometry": {"coordinates":[120.654444,22.255556],"type":"Point"}
}
=======
{"geometry":{"type":"Point","coordinates":[120.654444,22.255556]},"type":"Feature","properties":{"hierarchy":["tgn:7471375","tgn:1000004","tgn:7492971","tgn:1000141","tgn:7029392"],"placetype":["aat:300007836"],"id":7471375,"name:xx":"Fangshan Qiao"}}
>>>>>>> 03f74aca74312dbeaf24d7e61306dd6a786dc3d0
