{
  "id": 7470488,
  "type": "Feature",
  "properties": {
    "tgn:hierarchy":[
        "tgn:7470488",
        "tgn:7001010",
        "tgn:1000004",
        "tgn:1000141",
        "tgn:7029392"
    ],
    "tgn:id":7470488,
    "tgn:name":"Zhutian",
    "tgn:placetype":[
        "aat:300008347"
    ]
},
  "bbox": [],
  "geometry": {"coordinates":[121.280822,23.225459],"type":"Point"}
}