{
  "id": 2775588,
  "type": "Feature",
  "properties": {
    "tgn:hierarchy":[
        "tgn:2775588",
        "tgn:1000001",
        "tgn:7012149",
        "tgn:2002164",
        "tgn:7007919",
        "tgn:7029392"
    ],
    "tgn:id":2775588,
    "tgn:name":"Wilson Creek",
    "tgn:placetype":[
        "aat:300008706"
    ]
},
  "bbox": [],
  "geometry": {"coordinates":[-81.4833,36.6667],"type":"Point"}
}