{
  "id": 2779455,
  "type": "Feature",
  "properties": {
    "tgn:hierarchy":[
        "tgn:2779455",
        "tgn:1000001",
        "tgn:7012149",
        "tgn:2000966",
        "tgn:7007520",
        "tgn:7029392"
    ],
    "tgn:id":2779455,
    "tgn:name":"Wolf Lake",
    "tgn:placetype":[
        "aat:300008680"
    ]
},
  "bbox": [],
  "geometry": {"coordinates":[-88.65,46.3167],"type":"Point"}
}