{
  "id": 7331390,
  "type": "Feature",
  "properties": {
    "tgn:hierarchy":[
        "tgn:7331390",
        "tgn:7008911",
        "tgn:1000003",
        "tgn:7002763",
        "tgn:1000095",
        "tgn:7029392"
    ],
    "tgn:id":7331390,
    "tgn:name":"La Coba",
    "tgn:placetype":[
        "aat:300008347"
    ]
},
  "bbox": [],
  "geometry": {"coordinates":[-6.966667,43.216667],"type":"Point"}
}