{
  "id": 2702397,
  "type": "Feature",
  "properties": {
    "tgn:hierarchy":[
        "tgn:2702397",
        "tgn:1000001",
        "tgn:1002217",
        "tgn:7012149",
        "tgn:7007710",
        "tgn:7029392"
    ],
    "tgn:id":2702397,
    "tgn:name":"Sullivan Run",
    "tgn:placetype":[
        "aat:300008699"
    ]
},
  "bbox": [],
  "geometry": {"coordinates":[-79.9333,40.8833],"type":"Point"}
}