<<<<<<< HEAD
{
  "id": 7112551,
  "type": "Feature",
  "properties": {
    "tgn:hierarchy":[
        "tgn:7112551",
        "tgn:7003692",
        "tgn:1000003",
        "tgn:7000084",
        "tgn:7029392"
    ],
    "tgn:id":7112551,
    "tgn:name":"Rimpertsweiler",
    "tgn:placetype":[
        "aat:300008347"
    ]
},
  "bbox": [],
  "geometry": {"coordinates":[9.35,47.75],"type":"Point"}
}
=======
{"geometry":{"type":"Point","coordinates":[9.350000,47.750000]},"type":"Feature","properties":{"hierarchy":["tgn:7112551","tgn:7003692","tgn:1000003","tgn:7000084","tgn:7029392"],"placetype":["aat:300008347"],"id":7112551,"name:xx":"Rimpertsweiler"}}
>>>>>>> 03f74aca74312dbeaf24d7e61306dd6a786dc3d0
