{
  "id": 7103754,
  "type": "Feature",
  "properties": {
    "tgn:hierarchy":[
        "tgn:7103754",
        "tgn:7003692",
        "tgn:1000003",
        "tgn:7000084",
        "tgn:7029392"
    ],
    "tgn:id":7103754,
    "tgn:name":"Schadenbirndorf",
    "tgn:placetype":[
        "aat:300008347"
    ]
},
  "bbox": [],
  "geometry": {"coordinates":[8.133333,47.616667],"type":"Point"}
}