{
  "id": 7512280,
  "type": "Feature",
  "properties": {
    "tgn:hierarchy":[
        "tgn:7512280",
        "tgn:1008380",
        "tgn:1000226",
        "tgn:7016827",
        "tgn:1000006",
        "tgn:7029392"
    ],
    "tgn:id":7512280,
    "tgn:name:en":"Inaha Stream",
    "tgn:placetype":[
        "aat:300008699"
    ]
},
  "bbox": [],
  "geometry": {"coordinates":[174.166667,-39.583333],"type":"Point"}
}