{
  "id": 2536034,
  "type": "Feature",
  "properties": {
    "tgn:hierarchy":[
        "tgn:2536034",
        "tgn:1000001",
        "tgn:7006451",
        "tgn:7012149",
        "tgn:2000098",
        "tgn:7029392"
    ],
    "tgn:id":2536034,
    "tgn:name":"Natural Arch",
    "tgn:placetype":[
        "aat:300386837"
    ]
},
  "bbox": [],
  "geometry": {"coordinates":[-112.9167,36.25],"type":"Point"}
}