{
  "id": 2057961,
  "type": "Feature",
  "properties": {
    "tgn:hierarchy":[
        "tgn:2057961",
        "tgn:1000001",
        "tgn:7012149",
        "tgn:2001248",
        "tgn:7007523",
        "tgn:7029392"
    ],
    "tgn:id":2057961,
    "tgn:name":"Baker",
    "tgn:placetype":[
        "aat:300008347"
    ]
},
  "bbox": [],
  "geometry": {"coordinates":[-89.75,36.7667],"type":"Point"}
}