<<<<<<< HEAD
{
  "id": 7050632,
  "type": "Feature",
  "properties": {
    "tgn:hierarchy":[
        "tgn:7050632",
        "tgn:1003489",
        "tgn:7004610",
        "tgn:1000003",
        "tgn:1000080",
        "tgn:7029392"
    ],
    "tgn:id":7050632,
    "tgn:name":"Picerno, Fiumara di",
    "tgn:placetype":[
        "aat:300008699"
    ]
},
  "bbox": [],
  "geometry": {"coordinates":[15.583333,40.666667],"type":"Point"}
}
=======
{"geometry":{"type":"Point","coordinates":[15.583333,40.666667]},"type":"Feature","properties":{"hierarchy":["tgn:7050632","tgn:1003489","tgn:7004610","tgn:1000003","tgn:1000080","tgn:7029392"],"placetype":["aat:300008699"],"id":7050632,"name:xx":"Picerno, Fiumara di"}}
>>>>>>> 03f74aca74312dbeaf24d7e61306dd6a786dc3d0
