{
  "id": 7575098,
  "type": "Feature",
  "properties": {
    "tgn:hierarchy":[
        "tgn:7575098",
        "tgn:1000004",
        "tgn:7000198",
        "tgn:7016788",
        "tgn:7029392"
    ],
    "tgn:id":7575098,
    "tgn:name:en":"Kela Devi",
    "tgn:placetype":[
        "aat:300007783"
    ]
},
  "bbox": [],
  "geometry": {"coordinates":[77.335305,27.027888],"type":"Point"}
}