{
  "id": 7411832,
  "type": "Feature",
  "properties": {
    "tgn:hierarchy":[
        "tgn:7411832",
        "tgn:7005587",
        "tgn:1000001",
        "tgn:7005560",
        "tgn:7029392"
    ],
    "tgn:id":7411832,
    "tgn:name:es":"Zacayahuatl",
    "tgn:placetype":[
        "aat:300008347"
    ]
},
  "bbox": [],
  "geometry": {"coordinates":[-98.355556,20.890278],"type":"Point"}
}