{
  "id": 7110578,
  "type": "Feature",
  "properties": {
    "tgn:hierarchy":[
        "tgn:7110578",
        "tgn:7003692",
        "tgn:1000003",
        "tgn:7000084",
        "tgn:7029392"
    ],
    "tgn:id":7110578,
    "tgn:name":"Rainerwald",
    "tgn:placetype":[
        "aat:300008863"
    ]
},
  "bbox": [],
  "geometry": {"coordinates":[9.216667,48.583333],"type":"Point"}
}