<<<<<<< HEAD
{
  "id": 7472933,
  "type": "Feature",
  "properties": {
    "tgn:hierarchy":[
        "tgn:7472933",
        "tgn:1000004",
        "tgn:7467799",
        "tgn:1000141",
        "tgn:7029392"
    ],
    "tgn:id":7472933,
    "tgn:name":"Fuhai Gongyuan",
    "tgn:placetype":[
        "aat:300008187"
    ]
},
  "bbox": [],
  "geometry": {"coordinates":[120.335194,23.954324],"type":"Point"}
}
=======
{"geometry":{"type":"Point","coordinates":[120.335194,23.954324]},"type":"Feature","properties":{"hierarchy":["tgn:7472933","tgn:1000004","tgn:7467799","tgn:1000141","tgn:7029392"],"placetype":["aat:300008187"],"id":7472933,"name:xx":"Fuhai Gongyuan"}}
>>>>>>> 03f74aca74312dbeaf24d7e61306dd6a786dc3d0
