{
  "id": 7168932,
  "type": "Feature",
  "properties": {
    "tgn:hierarchy":[
        "tgn:7168932",
        "tgn:1000003",
        "tgn:7003677",
        "tgn:7000084",
        "tgn:7029392"
    ],
    "tgn:id":7168932,
    "tgn:name":"H\u00e4ver",
    "tgn:placetype":[
        "aat:300008347"
    ]
},
  "bbox": [],
  "geometry": {"coordinates":[8.666667,52.233333],"type":"Point"}
}