{
  "id": 2366375,
  "type": "Feature",
  "properties": {
    "tgn:hierarchy":[
        "tgn:2366375",
        "tgn:1000001",
        "tgn:7012149",
        "tgn:2001894",
        "tgn:7007825",
        "tgn:7029392"
    ],
    "tgn:id":2366375,
    "tgn:name":"Griffith Creek",
    "tgn:placetype":[
        "aat:300008706"
    ]
},
  "bbox": [],
  "geometry": {"coordinates":[-85.5667,35.2833],"type":"Point"}
}