{
  "id": 7286592,
  "type": "Feature",
  "properties": {
    "tgn:hierarchy":[
        "tgn:7286592",
        "tgn:1001699",
        "tgn:1000049",
        "tgn:1000002",
        "tgn:7029392"
    ],
    "tgn:id":7286592,
    "tgn:name":"Gusano, Grupo",
    "tgn:placetype":[
        "aat:300008791"
    ]
},
  "bbox": [],
  "geometry": {"coordinates":[-73.814167,-44.148056],"type":"Point"}
}