{
  "id": 2430340,
  "type": "Feature",
  "properties": {
    "tgn:hierarchy":[
        "tgn:2430340",
        "tgn:7023902",
        "tgn:1000001",
        "tgn:7012149",
        "tgn:7007249",
        "tgn:7029392"
    ],
    "tgn:id":2430340,
    "tgn:name":"Kaio",
    "tgn:placetype":[
        "aat:300055621"
    ]
},
  "bbox": [],
  "geometry": {"coordinates":[-155.6833,18.9333],"type":"Point"}
}