{
  "id": 7490762,
  "type": "Feature",
  "properties": {
    "tgn:hierarchy":[
        "tgn:7490762",
        "tgn:1000004",
        "tgn:7001009",
        "tgn:1000141",
        "tgn:7029392"
    ],
    "tgn:id":7490762,
    "tgn:name":"Taizhong Chezhan",
    "tgn:placetype":[
        "aat:300007783"
    ]
},
  "bbox": [],
  "geometry": {"coordinates":[120.685713,24.136956],"type":"Point"}
}