{
  "id": 2073342,
  "type": "Feature",
  "properties": {
    "tgn:hierarchy":[
        "tgn:2073342",
        "tgn:1000001",
        "tgn:7012149",
        "tgn:1002924",
        "tgn:7007568",
        "tgn:7029392"
    ],
    "tgn:id":2073342,
    "tgn:name":"Yaphank",
    "tgn:placetype":[
        "aat:300008347"
    ]
},
  "bbox": [],
  "geometry": {"coordinates":[-72.9167,40.8333],"type":"Point"}
}