{
  "id": 2259803,
  "type": "Feature",
  "properties": {
    "tgn:hierarchy":[
        "tgn:2259803",
        "tgn:1000001",
        "tgn:7012149",
        "tgn:2001722",
        "tgn:7007708",
        "tgn:7029392"
    ],
    "tgn:id":2259803,
    "tgn:name":"Cougar Ridge",
    "tgn:placetype":[
        "aat:300266640"
    ]
},
  "bbox": [],
  "geometry": {"coordinates":[-117.6167,45.4667],"type":"Point"}
}