{
  "id": 7517544,
  "type": "Feature",
  "properties": {
    "tgn:hierarchy":[
        "tgn:7517544",
        "tgn:1008380",
        "tgn:1000226",
        "tgn:7018426",
        "tgn:1000006",
        "tgn:7029392"
    ],
    "tgn:id":7517544,
    "tgn:name:en":"Manaia Harbour",
    "tgn:placetype":[
        "aat:300008678"
    ]
},
  "bbox": [],
  "geometry": {"coordinates":[175.45,-36.85],"type":"Point"}
}