{
  "id": 2599488,
  "type": "Feature",
  "properties": {
    "tgn:hierarchy":[
        "tgn:2599488",
        "tgn:2002240",
        "tgn:1000001",
        "tgn:7012149",
        "tgn:7007920",
        "tgn:7029392"
    ],
    "tgn:id":2599488,
    "tgn:name":"Prospect Canyon",
    "tgn:placetype":[
        "aat:300008761"
    ]
},
  "bbox": [],
  "geometry": {"coordinates":[-119.2333,46.0833],"type":"Point"}
}