{
  "id": 2168872,
  "type": "Feature",
  "properties": {
    "tgn:hierarchy":[
        "tgn:2168872",
        "tgn:1000001",
        "tgn:7012149",
        "tgn:7007157",
        "tgn:2000191",
        "tgn:7029392"
    ],
    "tgn:id":2168872,
    "tgn:name":"Big Hunter",
    "tgn:placetype":[
        "aat:300008798"
    ]
},
  "bbox": [],
  "geometry": {"coordinates":[-123.1333,40.1667],"type":"Point"}
}