{
  "id": 2276646,
  "type": "Feature",
  "properties": {
    "tgn:hierarchy":[
        "tgn:2276646",
        "tgn:1000001",
        "tgn:7012149",
        "tgn:2001058",
        "tgn:7007521",
        "tgn:7029392"
    ],
    "tgn:id":2276646,
    "tgn:name":"Davidson",
    "tgn:placetype":[
        "aat:300008347"
    ]
},
  "bbox": [],
  "geometry": {"coordinates":[-96.8333,47.8667],"type":"Point"}
}