{
  "id": 1054765,
  "type": "Feature",
  "properties": {
    "tgn:hierarchy":[
        "tgn:1054765",
        "tgn:7012245",
        "tgn:1000004",
        "tgn:7006661",
        "tgn:7029392"
    ],
    "tgn:id":1054765,
    "tgn:name":"Yuzhnyy Alamyshik",
    "tgn:placetype":[
        "aat:300008347"
    ]
},
  "bbox": [],
  "geometry": {"coordinates":[72.6167,40.7667],"type":"Point"}
}