{
  "id": 2444941,
  "type": "Feature",
  "properties": {
    "tgn:hierarchy":[
        "tgn:2444941",
        "tgn:1000001",
        "tgn:7012149",
        "tgn:1002528",
        "tgn:7007710",
        "tgn:7029392"
    ],
    "tgn:id":2444941,
    "tgn:name":"Leiningers Run",
    "tgn:placetype":[
        "aat:300008699"
    ]
},
  "bbox": [],
  "geometry": {"coordinates":[-77.0833,40.6333],"type":"Point"}
}