{
  "id": 2711267,
  "type": "Feature",
  "properties": {
    "tgn:hierarchy":[
        "tgn:2711267",
        "tgn:1000001",
        "tgn:7006451",
        "tgn:7012149",
        "tgn:2000104",
        "tgn:7029392"
    ],
    "tgn:id":2711267,
    "tgn:name":"Tanque Aloma",
    "tgn:placetype":[
        "aat:300008347"
    ]
},
  "bbox": [],
  "geometry": {"coordinates":[-113.95,32.6833],"type":"Point"}
}