{
  "id": 2558854,
  "type": "Feature",
  "properties": {
    "tgn:hierarchy":[
        "tgn:2558854",
        "tgn:1000001",
        "tgn:2001024",
        "tgn:7012149",
        "tgn:7007521",
        "tgn:7029392"
    ],
    "tgn:id":2558854,
    "tgn:name":"Olson Lake",
    "tgn:placetype":[
        "aat:300008680"
    ]
},
  "bbox": [],
  "geometry": {"coordinates":[-95.7833,45.8667],"type":"Point"}
}