{
  "id": 2190915,
  "type": "Feature",
  "properties": {
    "tgn:hierarchy":[
        "tgn:2190915",
        "tgn:1000001",
        "tgn:7012149",
        "tgn:2000798",
        "tgn:7007255",
        "tgn:7029392"
    ],
    "tgn:id":2190915,
    "tgn:name":"Boyd Knob",
    "tgn:placetype":[
        "aat:300008798"
    ]
},
  "bbox": [],
  "geometry": {"coordinates":[-85.8167,37.2667],"type":"Point"}
}