{
  "id": 7495064,
  "type": "Feature",
  "properties": {
    "tgn:hierarchy":[
        "tgn:7495064",
        "tgn:7468018",
        "tgn:1000004",
        "tgn:1000141",
        "tgn:7029392"
    ],
    "tgn:id":7495064,
    "tgn:name":"Fuyuan Qiao",
    "tgn:placetype":[
        "aat:300007836"
    ]
},
  "bbox": [],
  "geometry": {"coordinates":[120.573353,23.486295],"type":"Point"}
}