{
  "id": 7407705,
  "type": "Feature",
  "properties": {
    "tgn:hierarchy":[
        "tgn:7407705",
        "tgn:1000001",
        "tgn:7005590",
        "tgn:7005560",
        "tgn:7029392"
    ],
    "tgn:id":7407705,
    "tgn:name":"La Laja, R\u00edo",
    "tgn:placetype":[
        "aat:300008699"
    ]
},
  "bbox": [],
  "geometry": {"coordinates":[-100.879167,19.369444],"type":"Point"}
}