{
  "id": 2607837,
  "type": "Feature",
  "properties": {
    "tgn:hierarchy":[
        "tgn:2607837",
        "tgn:1000001",
        "tgn:7012149",
        "tgn:2000888",
        "tgn:7007256",
        "tgn:7029392"
    ],
    "tgn:id":2607837,
    "tgn:name":"Rat Bois, Lake",
    "tgn:placetype":[
        "aat:300008680"
    ]
},
  "bbox": [],
  "geometry": {"coordinates":[-92.8667,31.55],"type":"Point"}
}