{
  "id": 7243133,
  "type": "Feature",
  "properties": {
    "tgn:hierarchy":[
        "tgn:7243133",
        "tgn:7007877",
        "tgn:1000003",
        "tgn:1000063",
        "tgn:4012014",
        "tgn:7029392"
    ],
    "tgn:id":7243133,
    "tgn:name":"Luiseul, Bois de",
    "tgn:placetype":[
        "aat:300008863"
    ]
},
  "bbox": [],
  "geometry": {"coordinates":[4.283333,50.316667],"type":"Point"}
}