{
  "id": 2180427,
  "type": "Feature",
  "properties": {
    "tgn:hierarchy":[
        "tgn:2180427",
        "tgn:1000001",
        "tgn:7012149",
        "tgn:7014589",
        "tgn:7007515",
        "tgn:7029392"
    ],
    "tgn:id":2180427,
    "tgn:name":"Blood Cove",
    "tgn:placetype":[
        "aat:300132316"
    ]
},
  "bbox": [],
  "geometry": {"coordinates":[-67.5667,45.1333],"type":"Point"}
}