{
  "id": 7300288,
  "type": "Feature",
  "properties": {
    "tgn:hierarchy":[
        "tgn:7300288",
        "tgn:7002810",
        "tgn:7001158",
        "tgn:1000003",
        "tgn:1000095",
        "tgn:7029392"
    ],
    "tgn:id":7300288,
    "tgn:name":"Valdelacuesta",
    "tgn:placetype":[
        "aat:300008347"
    ]
},
  "bbox": [],
  "geometry": {"coordinates":[-3.483333,42.866667],"type":"Point"}
}