{
  "id": 7285341,
  "type": "Feature",
  "properties": {
    "tgn:hierarchy":[
        "tgn:7285341",
        "tgn:1001702",
        "tgn:1000049",
        "tgn:1000002",
        "tgn:7029392"
    ],
    "tgn:id":7285341,
    "tgn:name":"Poca Agua, Laguna",
    "tgn:placetype":[
        "aat:300008680"
    ]
},
  "bbox": [],
  "geometry": {"coordinates":[-69.233333,-53.316667],"type":"Point"}
}