{
  "id": 7006120,
  "type": "Feature",
  "properties": {
    "tgn:hierarchy":[
        "tgn:7006120",
        "tgn:7003162",
        "tgn:1000003",
        "tgn:7009760",
        "tgn:1000080",
        "tgn:7029392"
    ],
    "tgn:id":7006120,
    "tgn:name":"Cortona",
    "tgn:placetype":[
        "aat:300008347",
        "aat:300000810",
        "aat:300387315",
        "aat:300386570",
        "aat:300020471",
        "aat:300008375",
        "aat:300387291"
    ]
},
  "bbox": [],
  "geometry": {"coordinates":[11.983333,43.266667],"type":"Point"}
}