{
  "id": 7391088,
  "type": "Feature",
  "properties": {
    "tgn:hierarchy":[
        "tgn:7391088",
        "tgn:1000001",
        "tgn:7005597",
        "tgn:7005560",
        "tgn:7029392"
    ],
    "tgn:id":7391088,
    "tgn:name":"Rancho Chupaderos",
    "tgn:placetype":[
        "aat:300008347"
    ]
},
  "bbox": [],
  "geometry": {"coordinates":[-99.316667,26.633333],"type":"Point"}
}