{
  "id": 2741966,
  "type": "Feature",
  "properties": {
    "tgn:hierarchy":[
        "tgn:2741966",
        "tgn:1000001",
        "tgn:7012149",
        "tgn:1002993",
        "tgn:7007568",
        "tgn:7029392"
    ],
    "tgn:id":2741966,
    "tgn:name":"Vail Hill",
    "tgn:placetype":[
        "aat:300008798"
    ]
},
  "bbox": [],
  "geometry": {"coordinates":[-73.45,43.4667],"type":"Point"}
}