{
  "id": 7278424,
  "type": "Feature",
  "properties": {
    "tgn:hierarchy":[
        "tgn:7278424",
        "tgn:1001657",
        "tgn:1000049",
        "tgn:1000002",
        "tgn:7029392"
    ],
    "tgn:id":7278424,
    "tgn:name":"Conchali, Estero",
    "tgn:placetype":[
        "aat:300008699"
    ]
},
  "bbox": [],
  "geometry": {"coordinates":[-71.500556,-31.869444],"type":"Point"}
}