<<<<<<< HEAD
{
  "id": 7480242,
  "type": "Feature",
  "properties": {
    "tgn:hierarchy":[
        "tgn:7480242",
        "tgn:1000004",
        "tgn:7490934",
        "tgn:1000141",
        "tgn:7029392"
    ],
    "tgn:id":7480242,
    "tgn:name":"Tucheng Guozhong",
    "tgn:placetype":[
        "aat:300006495"
    ]
},
  "bbox": [],
  "geometry": {"coordinates":[120.149722,23.056111],"type":"Point"}
}
=======
{"geometry":{"type":"Point","coordinates":[120.149722,23.056111]},"type":"Feature","properties":{"hierarchy":["tgn:7480242","tgn:1000004","tgn:7490934","tgn:1000141","tgn:7029392"],"placetype":["aat:300006495"],"id":7480242,"name:xx":"Tucheng Guozhong"}}
>>>>>>> 03f74aca74312dbeaf24d7e61306dd6a786dc3d0
