{
  "id": 7480242,
  "type": "Feature",
  "properties": {
    "tgn:hierarchy":[
        "tgn:7480242",
        "tgn:1000004",
        "tgn:7490934",
        "tgn:1000141",
        "tgn:7029392"
    ],
    "tgn:id":7480242,
    "tgn:name":"Tucheng Guozhong",
    "tgn:placetype":[
        "aat:300006495"
    ]
},
  "bbox": [],
  "geometry": {"coordinates":[120.149722,23.056111],"type":"Point"}
}