{
  "id": 2339910,
  "type": "Feature",
  "properties": {
    "tgn:hierarchy":[
        "tgn:2339910",
        "tgn:1000001",
        "tgn:7012149",
        "tgn:2002118",
        "tgn:7007827",
        "tgn:7029392"
    ],
    "tgn:id":2339910,
    "tgn:name":"Freeman Peak",
    "tgn:placetype":[
        "aat:300008798"
    ]
},
  "bbox": [],
  "geometry": {"coordinates":[-112.1667,40.55],"type":"Point"}
}