{
  "id": 2204819,
  "type": "Feature",
  "properties": {
    "tgn:hierarchy":[
        "tgn:2204819",
        "tgn:1000001",
        "tgn:7012149",
        "tgn:2002032",
        "tgn:7007826",
        "tgn:7029392"
    ],
    "tgn:id":2204819,
    "tgn:name":"Buffalo Springs Lake",
    "tgn:placetype":[
        "aat:300008680"
    ]
},
  "bbox": [],
  "geometry": {"coordinates":[-101.6833,33.5333],"type":"Point"}
}