{
  "id": 7539572,
  "type": "Feature",
  "properties": {
    "tgn:hierarchy":[
        "tgn:7539572",
        "tgn:7001242",
        "tgn:7016833",
        "tgn:7001336",
        "tgn:7029392"
    ],
    "tgn:id":7539572,
    "tgn:name:en":"Qalt, W\u0101d\u012b al",
    "tgn:placetype":[
        "aat:300379998"
    ]
},
  "bbox": [],
  "geometry": {"coordinates":[34.616942,29.807602],"type":"Point"}
}