{
  "id": 7126581,
  "type": "Feature",
  "properties": {
    "tgn:hierarchy":[
        "tgn:7126581",
        "tgn:7003692",
        "tgn:1000003",
        "tgn:7000084",
        "tgn:7029392"
    ],
    "tgn:id":7126581,
    "tgn:name":"Oberhippensbach",
    "tgn:placetype":[
        "aat:300000206"
    ]
},
  "bbox": [],
  "geometry": {"coordinates":[8.216667,48.15],"type":"Point"}
}