{
  "id": 2590799,
  "type": "Feature",
  "properties": {
    "tgn:hierarchy":[
        "tgn:2590799",
        "tgn:1000001",
        "tgn:7012149",
        "tgn:2000403",
        "tgn:7007248",
        "tgn:7029392"
    ],
    "tgn:id":2590799,
    "tgn:name":"Polecat Branch",
    "tgn:placetype":[
        "aat:300008699"
    ]
},
  "bbox": [],
  "geometry": {"coordinates":[-84.4167,34.45],"type":"Point"}
}