{
  "id": 1130027,
  "type": "Feature",
  "properties": {
    "tgn:hierarchy":[
        "tgn:1130027",
        "tgn:1000001",
        "tgn:7012149",
        "tgn:7007708",
        "tgn:7029392"
    ],
    "tgn:id":1130027,
    "tgn:name":"Silvies",
    "tgn:placetype":[
        "aat:300008707"
    ]
},
  "bbox": [],
  "geometry": {"coordinates":[-119.2167,44.1167],"type":"Point"}
}