{
  "id": 2608918,
  "type": "Feature",
  "properties": {
    "tgn:hierarchy":[
        "tgn:2608918",
        "tgn:1000001",
        "tgn:7012149",
        "tgn:1002794",
        "tgn:7007708",
        "tgn:7029392"
    ],
    "tgn:id":2608918,
    "tgn:name":"Ratzlaff Reservoir",
    "tgn:placetype":[
        "aat:300006191"
    ]
},
  "bbox": [],
  "geometry": {"coordinates":[-123.3333,44.7833],"type":"Point"}
}