{
  "id": 2355885,
  "type": "Feature",
  "properties": {
    "tgn:hierarchy":[
        "tgn:2355885",
        "tgn:1000001",
        "tgn:7012149",
        "tgn:2002345",
        "tgn:7007922",
        "tgn:7029392"
    ],
    "tgn:id":2355885,
    "tgn:name":"Goose Lake",
    "tgn:placetype":[
        "aat:300132316"
    ]
},
  "bbox": [],
  "geometry": {"coordinates":[-92.4833,44.5833],"type":"Point"}
}