{
  "id": 1036519,
  "type": "Feature",
  "properties": {
    "tgn:hierarchy":[
        "tgn:1036519",
        "tgn:1000003",
        "tgn:7000094",
        "tgn:7000084",
        "tgn:7029392"
    ],
    "tgn:id":1036519,
    "tgn:name":"Brunn",
    "tgn:placetype":[
        "aat:300008347"
    ]
},
  "bbox": [],
  "geometry": {"coordinates":[12.333333,50.65],"type":"Point"}
}