{
  "id": 1060239,
  "type": "Feature",
  "properties": {
    "tgn:hierarchy":[
        "tgn:1060239",
        "tgn:1000004",
        "tgn:7011523",
        "tgn:7002435",
        "tgn:7029392"
    ],
    "tgn:id":1060239,
    "tgn:name":"Ten'gushevo",
    "tgn:placetype":[
        "aat:300008347"
    ]
},
  "bbox": [],
  "geometry": {"coordinates":[42.7333,54.75],"type":"Point"}
}