<<<<<<< HEAD
{
  "id": 7364703,
  "type": "Feature",
  "properties": {
    "tgn:hierarchy":[
        "tgn:7364703",
        "tgn:7005583",
        "tgn:1000001",
        "tgn:7005560",
        "tgn:7029392"
    ],
    "tgn:id":7364703,
    "tgn:name":"Rancho El Sauco",
    "tgn:placetype":[
        "aat:300000241"
    ]
},
  "bbox": [],
  "geometry": {"coordinates":[-105.283333,25.366667],"type":"Point"}
}
=======
{"geometry":{"type":"Point","coordinates":[-105.283333,25.366667]},"type":"Feature","properties":{"hierarchy":["tgn:7364703","tgn:7005583","tgn:1000001","tgn:7005560","tgn:7029392"],"placetype":["aat:300000241"],"id":7364703,"name:xx":"Rancho El Sauco"}}
>>>>>>> 03f74aca74312dbeaf24d7e61306dd6a786dc3d0
