{
  "id": 1129662,
  "type": "Feature",
  "properties": {
    "tgn:hierarchy":[
        "tgn:1129662",
        "tgn:1001945",
        "tgn:1000047",
        "tgn:7002457",
        "tgn:1000002",
        "tgn:7029392"
    ],
    "tgn:id":1129662,
    "tgn:name":"Santo Anast\u00e1cio",
    "tgn:placetype":[
        "aat:300008707"
    ]
},
  "bbox": [],
  "geometry": {"coordinates":[-52.1833,-21.8167],"type":"Point"}
}