{
  "id": 2623951,
  "type": "Feature",
  "properties": {
    "tgn:hierarchy":[
        "tgn:2623951",
        "tgn:1000001",
        "tgn:2000308",
        "tgn:7012149",
        "tgn:7007248",
        "tgn:7029392"
    ],
    "tgn:id":2623951,
    "tgn:name":"Rock Fence Crossroads",
    "tgn:placetype":[
        "aat:300008347"
    ]
},
  "bbox": [],
  "geometry": {"coordinates":[-81.5667,33.0167],"type":"Point"}
}