{
  "id": 2462611,
  "type": "Feature",
  "properties": {
    "tgn:hierarchy":[
        "tgn:2462611",
        "tgn:2000999",
        "tgn:1000001",
        "tgn:7012149",
        "tgn:7007521",
        "tgn:7029392"
    ],
    "tgn:id":2462611,
    "tgn:name":"Little Willow River",
    "tgn:placetype":[
        "aat:300008707"
    ]
},
  "bbox": [],
  "geometry": {"coordinates":[-93.6833,46.7167],"type":"Point"}
}