{
  "id": 7253248,
  "type": "Feature",
  "properties": {
    "tgn:hierarchy":[
        "tgn:7253248",
        "tgn:7003456",
        "tgn:1000003",
        "tgn:1000063",
        "tgn:7018236",
        "tgn:7029392"
    ],
    "tgn:id":7253248,
    "tgn:name":"Sauvegarde",
    "tgn:placetype":[
        "aat:300008347"
    ]
},
  "bbox": [],
  "geometry": {"coordinates":[4.324989,51.081247],"type":"Point"}
}