{
  "id": 7044609,
  "type": "Feature",
  "properties": {
    "tgn:hierarchy":[
        "tgn:7044609",
        "tgn:1003444",
        "tgn:1000003",
        "tgn:7003241",
        "tgn:1000080",
        "tgn:7029392"
    ],
    "tgn:id":7044609,
    "tgn:name":"Fossalto, Rio",
    "tgn:placetype":[
        "aat:300008699"
    ]
},
  "bbox": [],
  "geometry": {"coordinates":[14.583333,41.633333],"type":"Point"}
}