{
  "id": 7542819,
  "type": "Feature",
  "properties": {
    "tgn:hierarchy":[
        "tgn:7542819",
        "tgn:7001242",
        "tgn:7016833",
        "tgn:7001336",
        "tgn:7029392"
    ],
    "tgn:id":7542819,
    "tgn:name:en":"\u1e28uzaymah, Jabal",
    "tgn:placetype":[
        "aat:300008795"
    ]
},
  "bbox": [],
  "geometry": {"coordinates":[34.093421,28.489016],"type":"Point"}
}