{
  "id": 2690542,
  "type": "Feature",
  "properties": {
    "tgn:hierarchy":[
        "tgn:2690542",
        "tgn:1000001",
        "tgn:7012149",
        "tgn:2001723",
        "tgn:7007708",
        "tgn:7029392"
    ],
    "tgn:id":2690542,
    "tgn:name":"Stalling Butte",
    "tgn:placetype":[
        "aat:300008798"
    ]
},
  "bbox": [],
  "geometry": {"coordinates":[-119.6667,44.8833],"type":"Point"}
}