{
  "id": 2609534,
  "type": "Feature",
  "properties": {
    "tgn:hierarchy":[
        "tgn:2609534",
        "tgn:7002659",
        "tgn:1000001",
        "tgn:7012149",
        "tgn:7021514",
        "tgn:7029392"
    ],
    "tgn:id":2609534,
    "tgn:name":"Raymonds Pit",
    "tgn:placetype":[
        "aat:300008746"
    ]
},
  "bbox": [],
  "geometry": {"coordinates":[-85.7167,34.4167],"type":"Point"}
}