{
  "id": 2268584,
  "type": "Feature",
  "properties": {
    "tgn:hierarchy":[
        "tgn:2268584",
        "tgn:1000001",
        "tgn:2001429",
        "tgn:7012149",
        "tgn:7007566",
        "tgn:7029392"
    ],
    "tgn:id":2268584,
    "tgn:name":"Crosby Mountains",
    "tgn:placetype":[
        "aat:300266640"
    ]
},
  "bbox": [],
  "geometry": {"coordinates":[-107.95,34.1667],"type":"Point"}
}