{
  "id": 2225684,
  "type": "Feature",
  "properties": {
    "tgn:hierarchy":[
        "tgn:2225684",
        "tgn:2000195",
        "tgn:1000001",
        "tgn:7012149",
        "tgn:7007158",
        "tgn:7029392"
    ],
    "tgn:id":2225684,
    "tgn:name":"Cat Creek",
    "tgn:placetype":[
        "aat:300008706"
    ]
},
  "bbox": [],
  "geometry": {"coordinates":[-107.1833,37.1667],"type":"Point"}
}