<<<<<<< HEAD
{
  "id": 7360340,
  "type": "Feature",
  "properties": {
    "tgn:hierarchy":[
        "tgn:7360340",
        "tgn:1000001",
        "tgn:7005599",
        "tgn:7005560",
        "tgn:7029392"
    ],
    "tgn:id":7360340,
    "tgn:name":"Cobos",
    "tgn:placetype":[
        "aat:300008347"
    ]
},
  "bbox": [],
  "geometry": {"coordinates":[-97.366667,20.933333],"type":"Point"}
}
=======
{"geometry":{"type":"Point","coordinates":[-97.366667,20.933333]},"type":"Feature","properties":{"hierarchy":["tgn:7360340","tgn:1000001","tgn:7005599","tgn:7005560","tgn:7029392"],"placetype":["aat:300008347"],"id":7360340,"name:xx":"Cobos"}}
>>>>>>> 03f74aca74312dbeaf24d7e61306dd6a786dc3d0
