{
  "id": 7230963,
  "type": "Feature",
  "properties": {
    "tgn:hierarchy":[
        "tgn:7230963",
        "tgn:7002751",
        "tgn:7001399",
        "tgn:1000003",
        "tgn:1000074",
        "tgn:7029392"
    ],
    "tgn:id":7230963,
    "tgn:name":"Kalothr\u00f3nion",
    "tgn:placetype":[
        "aat:300008347"
    ]
},
  "bbox": [],
  "geometry": {"coordinates":[22.583333,38.716667],"type":"Point"}
}