{
  "id": 7318422,
  "type": "Feature",
  "properties": {
    "tgn:hierarchy":[
        "tgn:7318422",
        "tgn:1001699",
        "tgn:1000049",
        "tgn:1000002",
        "tgn:7029392"
    ],
    "tgn:id":7318422,
    "tgn:name":"Punta Chulao",
    "tgn:placetype":[
        "aat:300386846"
    ]
},
  "bbox": [],
  "geometry": {"coordinates":[-72.830833,-42.350278],"type":"Point"}
}