<<<<<<< HEAD
{
  "id": 2761121,
  "type": "Feature",
  "properties": {
    "tgn:hierarchy":[
        "tgn:2761121",
        "tgn:1000001",
        "tgn:2001638",
        "tgn:7012149",
        "tgn:7007707",
        "tgn:7029392"
    ],
    "tgn:id":2761121,
    "tgn:name":"West Lake",
    "tgn:placetype":[
        "aat:300006191"
    ]
},
  "bbox": [],
  "geometry": {"coordinates":[-98.5,34.6667],"type":"Point"}
}
=======
{"geometry":{"type":"Point","coordinates":[-98.500000,34.666700]},"type":"Feature","properties":{"hierarchy":["tgn:2761121","tgn:1000001","tgn:2001638","tgn:7012149","tgn:7007707","tgn:7029392"],"placetype":["aat:300006191"],"id":2761121,"name:xx":"West Lake"}}
>>>>>>> 03f74aca74312dbeaf24d7e61306dd6a786dc3d0
