{
  "id": 2380141,
  "type": "Feature",
  "properties": {
    "tgn:hierarchy":[
        "tgn:2380141",
        "tgn:1000001",
        "tgn:7012149",
        "tgn:7007825",
        "tgn:7029392"
    ],
    "tgn:id":2380141,
    "tgn:name":"Hatchie Bottom",
    "tgn:placetype":[
        "aat:300386845"
    ]
},
  "bbox": [],
  "geometry": {"coordinates":[-89.1667,35.4833],"type":"Point"}
}