{
  "id": 2163079,
  "type": "Feature",
  "properties": {
    "tgn:hierarchy":[
        "tgn:2163079",
        "tgn:1000001",
        "tgn:7012149",
        "tgn:2001526",
        "tgn:7007709",
        "tgn:7029392"
    ],
    "tgn:id":2163079,
    "tgn:name":"Bennett Creek",
    "tgn:placetype":[
        "aat:300008706"
    ]
},
  "bbox": [],
  "geometry": {"coordinates":[-76.6333,35.1833],"type":"Point"}
}