<<<<<<< HEAD
{
  "id": 7051827,
  "type": "Feature",
  "properties": {
    "tgn:hierarchy":[
        "tgn:7051827",
        "tgn:7003008",
        "tgn:1000003",
        "tgn:7002997",
        "tgn:1000080",
        "tgn:7029392"
    ],
    "tgn:id":7051827,
    "tgn:name":"Il Corso",
    "tgn:placetype":[
        "aat:300008347"
    ]
},
  "bbox": [],
  "geometry": {"coordinates":[11.566667,45.516667],"type":"Point"}
}
=======
{"geometry":{"type":"Point","coordinates":[11.566667,45.516667]},"type":"Feature","properties":{"hierarchy":["tgn:7051827","tgn:7003008","tgn:1000003","tgn:7002997","tgn:1000080","tgn:7029392"],"placetype":["aat:300008347"],"id":7051827,"name:xx":"Il Corso"}}
>>>>>>> 03f74aca74312dbeaf24d7e61306dd6a786dc3d0
