{
  "id": 7441084,
  "type": "Feature",
  "properties": {
    "tgn:hierarchy":[
        "tgn:7441084",
        "tgn:1000001",
        "tgn:7005592",
        "tgn:7005560",
        "tgn:7029392"
    ],
    "tgn:id":7441084,
    "tgn:name":"San Lorenzo Almecatla",
    "tgn:placetype":[
        "aat:300008347"
    ]
},
  "bbox": [],
  "geometry": {"coordinates":[-98.233333,19.133333],"type":"Point"}
}