{
  "id": 2773311,
  "type": "Feature",
  "properties": {
    "tgn:hierarchy":[
        "tgn:2773311",
        "tgn:1000001",
        "tgn:7012149",
        "tgn:2000892",
        "tgn:7007256",
        "tgn:7029392"
    ],
    "tgn:id":2773311,
    "tgn:name":"Williamsport",
    "tgn:placetype":[
        "aat:300008347"
    ]
},
  "bbox": [],
  "geometry": {"coordinates":[-91.6667,30.8833],"type":"Point"}
}