{
  "id": 7528168,
  "type": "Feature",
  "properties": {
    "tgn:hierarchy":[
        "tgn:7528168",
        "tgn:7001242",
        "tgn:7001311",
        "tgn:7016833",
        "tgn:7029392"
    ],
    "tgn:id":7528168,
    "tgn:name:en":"Umm D\u012bs\u012b, Jabal",
    "tgn:placetype":[
        "aat:300008795"
    ]
},
  "bbox": [],
  "geometry": {"coordinates":[33.243136,27.027425],"type":"Point"}
}