{
  "id": 7375273,
  "type": "Feature",
  "properties": {
    "tgn:hierarchy":[
        "tgn:7375273",
        "tgn:7005583",
        "tgn:1000001",
        "tgn:7005560",
        "tgn:7029392"
    ],
    "tgn:id":7375273,
    "tgn:name":"Rancho Las Pompas",
    "tgn:placetype":[
        "aat:300000241"
    ]
},
  "bbox": [],
  "geometry": {"coordinates":[-105.616667,26.633333],"type":"Point"}
}