{
  "id": 1011400,
  "type": "Feature",
  "properties": {
    "tgn:hierarchy":[
        "tgn:1011400",
        "tgn:7002444",
        "tgn:7009894",
        "tgn:1000003",
        "tgn:7008094",
        "tgn:7008591",
        "tgn:7029392"
    ],
    "tgn:id":1011400,
    "tgn:name:en":"Barra Head",
    "tgn:placetype":[
        "aat:300008850",
        "aat:300387499"
    ]
},
  "bbox": [],
  "geometry": {"coordinates":[-7.633333,56.766667],"type":"Point"}
}