{
  "id": 2223999,
  "type": "Feature",
  "properties": {
    "tgn:hierarchy":[
        "tgn:2223999",
        "tgn:1000001",
        "tgn:7012149",
        "tgn:2001308",
        "tgn:7007524",
        "tgn:7029392"
    ],
    "tgn:id":2223999,
    "tgn:name":"Cartwright Gulch",
    "tgn:placetype":[
        "aat:300008761"
    ]
},
  "bbox": [],
  "geometry": {"coordinates":[-109.9167,45.7167],"type":"Point"}
}