{
  "id": 2606549,
  "type": "Feature",
  "properties": {
    "tgn:hierarchy":[
        "tgn:2606549",
        "tgn:1000001",
        "tgn:2001596",
        "tgn:7012149",
        "tgn:7007705",
        "tgn:7029392"
    ],
    "tgn:id":2606549,
    "tgn:name":"Rames Lake",
    "tgn:placetype":[
        "aat:300008680"
    ]
},
  "bbox": [],
  "geometry": {"coordinates":[-99.8667,48.95],"type":"Point"}
}