{
  "id": 2361771,
  "type": "Feature",
  "properties": {
    "tgn:hierarchy":[
        "tgn:2361771",
        "tgn:1000001",
        "tgn:7012149",
        "tgn:2001719",
        "tgn:7007708",
        "tgn:7029392"
    ],
    "tgn:id":2361771,
    "tgn:name":"Gravy Creek",
    "tgn:placetype":[
        "aat:300008706"
    ]
},
  "bbox": [],
  "geometry": {"coordinates":[-119.5667,45.1167],"type":"Point"}
}