{
  "id": 2046293,
  "type": "Feature",
  "properties": {
    "tgn:hierarchy":[
        "tgn:2046293",
        "tgn:1000001",
        "tgn:7016101",
        "tgn:7012149",
        "tgn:7007516",
        "tgn:7029392"
    ],
    "tgn:id":2046293,
    "tgn:name":"Blue Mountain",
    "tgn:placetype":[
        "aat:300008347"
    ]
},
  "bbox": [],
  "geometry": {"coordinates":[-77.4167,39.5833],"type":"Point"}
}