{
  "id": 2605299,
  "type": "Feature",
  "properties": {
    "tgn:hierarchy":[
        "tgn:2605299",
        "tgn:1000001",
        "tgn:2001425",
        "tgn:7012149",
        "tgn:7007564",
        "tgn:7029392"
    ],
    "tgn:id":2605299,
    "tgn:name":"Ragged Mountain State Forest",
    "tgn:placetype":[
        "aat:300008863"
    ]
},
  "bbox": [],
  "geometry": {"coordinates":[-71.8167,43.4333],"type":"Point"}
}