{
  "id": 2786620,
  "type": "Feature",
  "properties": {
    "tgn:hierarchy":[
        "tgn:2786620",
        "tgn:1000001",
        "tgn:7012149",
        "tgn:2002267",
        "tgn:7013961",
        "tgn:7029392"
    ],
    "tgn:id":2786620,
    "tgn:name":"Zachs Run",
    "tgn:placetype":[
        "aat:300008699"
    ]
},
  "bbox": [],
  "geometry": {"coordinates":[-80.25,39.2167],"type":"Point"}
}