{
  "id": 2617790,
  "type": "Feature",
  "properties": {
    "tgn:hierarchy":[
        "tgn:2617790",
        "tgn:1000001",
        "tgn:2000470",
        "tgn:7012149",
        "tgn:7007250",
        "tgn:7029392"
    ],
    "tgn:id":2617790,
    "tgn:name":"Rider Creek",
    "tgn:placetype":[
        "aat:300008706"
    ]
},
  "bbox": [],
  "geometry": {"coordinates":[-113.9833,43.85],"type":"Point"}
}