{
  "id": 1011504,
  "type": "Feature",
  "properties": {
    "tgn:hierarchy":[
        "tgn:1011504",
        "tgn:7002443",
        "tgn:1000003",
        "tgn:7018993",
        "tgn:7008591",
        "tgn:7029392"
    ],
    "tgn:id":1011504,
    "tgn:name:en":"Saint Govan's Head",
    "tgn:placetype":[
        "aat:300008850",
        "aat:300387499"
    ]
},
  "bbox": [],
  "geometry": {"coordinates":[-4.925278,51.5975],"type":"Point"}
}