{
  "id": 2569868,
  "type": "Feature",
  "properties": {
    "tgn:hierarchy":[
        "tgn:2569868",
        "tgn:1000001",
        "tgn:7012149",
        "tgn:2001515",
        "tgn:7007709",
        "tgn:7029392"
    ],
    "tgn:id":2569868,
    "tgn:name":"Partridge Creek",
    "tgn:placetype":[
        "aat:300008706"
    ]
},
  "bbox": [],
  "geometry": {"coordinates":[-83.5667,35.2667],"type":"Point"}
}