{
  "id": 1058707,
  "type": "Feature",
  "properties": {
    "tgn:hierarchy":[
        "tgn:1058707",
        "tgn:1000004",
        "tgn:6003149",
        "tgn:7002435",
        "tgn:7029392"
    ],
    "tgn:id":1058707,
    "tgn:name":"Promyshlennyy",
    "tgn:placetype":[
        "aat:300008347"
    ]
},
  "bbox": [],
  "geometry": {"coordinates":[63.9667,67.5667],"type":"Point"}
}