{
  "id": 2646843,
  "type": "Feature",
  "properties": {
    "tgn:hierarchy":[
        "tgn:2646843",
        "tgn:1000001",
        "tgn:7012149",
        "tgn:2001543",
        "tgn:7007709",
        "tgn:7029392"
    ],
    "tgn:id":2646843,
    "tgn:name":"Scarlet Ridge",
    "tgn:placetype":[
        "aat:300266640"
    ]
},
  "bbox": [],
  "geometry": {"coordinates":[-83.5667,35.5167],"type":"Point"}
}