{
  "id": 2036904,
  "type": "Feature",
  "properties": {
    "tgn:hierarchy":[
        "tgn:2036904",
        "tgn:1000001",
        "tgn:7012149",
        "tgn:2000729",
        "tgn:7007254",
        "tgn:7029392"
    ],
    "tgn:id":2036904,
    "tgn:name":"Osage City",
    "tgn:placetype":[
        "aat:300008347"
    ]
},
  "bbox": [],
  "geometry": {"coordinates":[-95.8167,38.6333],"type":"Point"}
}