{
  "id": 7568286,
  "type": "Feature",
  "properties": {
    "tgn:hierarchy":[
        "tgn:7568286",
        "tgn:1000004",
        "tgn:7000198",
        "tgn:1001996",
        "tgn:7029392"
    ],
    "tgn:id":7568286,
    "tgn:name:en":"Bhal\u0101ya",
    "tgn:placetype":[
        "aat:300008347"
    ]
},
  "bbox": [],
  "geometry": {"coordinates":[77.070556,31.184167],"type":"Point"}
}