{
  "id": 7135129,
  "type": "Feature",
  "properties": {
    "tgn:hierarchy":[
        "tgn:7135129",
        "tgn:7003692",
        "tgn:1000003",
        "tgn:7000084",
        "tgn:7029392"
    ],
    "tgn:id":7135129,
    "tgn:name":"Nassau",
    "tgn:placetype":[
        "aat:300008347"
    ]
},
  "bbox": [],
  "geometry": {"coordinates":[9.894444,49.526111],"type":"Point"}
}