{
  "id": 7556995,
  "type": "Feature",
  "properties": {
    "tgn:hierarchy":[
        "tgn:7556995",
        "tgn:1000004",
        "tgn:1001842",
        "tgn:7000198",
        "tgn:7029392"
    ],
    "tgn:id":7556995,
    "tgn:name:en":"Sajhauli",
    "tgn:placetype":[
        "aat:300008347"
    ]
},
  "bbox": [],
  "geometry": {"coordinates":[84.184248,25.145187],"type":"Point"}
}