{
  "id": 2027558,
  "type": "Feature",
  "properties": {
    "tgn:hierarchy":[
        "tgn:2027558",
        "tgn:1000001",
        "tgn:7012149",
        "tgn:7013855",
        "tgn:7007251",
        "tgn:7029392"
    ],
    "tgn:id":2027558,
    "tgn:name":"Dunes Park",
    "tgn:placetype":[
        "aat:300387016"
    ]
},
  "bbox": [],
  "geometry": {"coordinates":[-87.8167,42.4167],"type":"Point"}
}