{
  "id": 2625740,
  "type": "Feature",
  "properties": {
    "tgn:hierarchy":[
        "tgn:2625740",
        "tgn:1000001",
        "tgn:2000108",
        "tgn:7016172",
        "tgn:7012149",
        "tgn:7029392"
    ],
    "tgn:id":2625740,
    "tgn:name":"Rocky Branch",
    "tgn:placetype":[
        "aat:300008699"
    ]
},
  "bbox": [],
  "geometry": {"coordinates":[-93.95,36.3167],"type":"Point"}
}