{
  "id": 1007616,
  "type": "Feature",
  "properties": {
    "tgn:hierarchy":[
        "tgn:1007616",
        "tgn:1010073",
        "tgn:1000004",
        "tgn:7000894",
        "tgn:1001032",
        "tgn:7006216",
        "tgn:1000120",
        "tgn:7029392"
    ],
    "tgn:id":1007616,
    "tgn:name":"Kama-iwa",
    "tgn:placetype":[
        "aat:300008791"
    ]
},
  "bbox": [],
  "geometry": {"coordinates":[141.2833,24.7833],"type":"Point"}
}