{
  "id": 2759087,
  "type": "Feature",
  "properties": {
    "tgn:hierarchy":[
        "tgn:2759087",
        "tgn:1000001",
        "tgn:7012149",
        "tgn:2001709",
        "tgn:7007708",
        "tgn:7029392"
    ],
    "tgn:id":2759087,
    "tgn:name":"West Fork Big Pasture Creek",
    "tgn:placetype":[
        "aat:300008706"
    ]
},
  "bbox": [],
  "geometry": {"coordinates":[-118.55,42.75],"type":"Point"}
}