{
  "id": 1083338,
  "type": "Feature",
  "properties": {
    "tgn:hierarchy":[
        "tgn:1083338",
        "tgn:1000004",
        "tgn:1001490",
        "tgn:1000133",
        "tgn:7029392"
    ],
    "tgn:id":1083338,
    "tgn:name":"Alipur",
    "tgn:placetype":[
        "aat:300008347"
    ]
},
  "bbox": [],
  "geometry": {"coordinates":[70.9833,29.3667],"type":"Point"}
}