<<<<<<< HEAD
{
  "id": 2334001,
  "type": "Feature",
  "properties": {
    "tgn:hierarchy":[
        "tgn:2334001",
        "tgn:1000001",
        "tgn:7012149",
        "tgn:2001544",
        "tgn:7007709",
        "tgn:7029392"
    ],
    "tgn:id":2334001,
    "tgn:name":"Ford Lake",
    "tgn:placetype":[
        "aat:300006191"
    ]
},
  "bbox": [],
  "geometry": {"coordinates":[-82.7667,35.15],"type":"Point"}
}
=======
{"geometry":{"type":"Point","coordinates":[-82.766700,35.150000]},"type":"Feature","properties":{"hierarchy":["tgn:2334001","tgn:1000001","tgn:7012149","tgn:2001544","tgn:7007709","tgn:7029392"],"placetype":["aat:300006191"],"id":2334001,"name:xx":"Ford Lake"}}
>>>>>>> 03f74aca74312dbeaf24d7e61306dd6a786dc3d0
