{
  "id": 7012979,
  "type": "Feature",
  "properties": {
    "tgn:hierarchy":[
        "tgn:7012979",
        "tgn:1000003",
        "tgn:7015121",
        "tgn:7006670",
        "tgn:7029392"
    ],
    "tgn:id":7012979,
    "tgn:name":"Nova Gorica",
    "tgn:placetype":[
        "aat:300008347",
        "aat:300387222",
        "aat:300008375"
    ]
},
  "bbox": [],
  "geometry": {"coordinates":[13.65,45.95],"type":"Point"}
}