{
  "id": 2396760,
  "type": "Feature",
  "properties": {
    "tgn:hierarchy":[
        "tgn:2396760",
        "tgn:7002659",
        "tgn:1000001",
        "tgn:7012149",
        "tgn:2000063",
        "tgn:7029392"
    ],
    "tgn:id":2396760,
    "tgn:name":"Home Creek",
    "tgn:placetype":[
        "aat:300008706"
    ]
},
  "bbox": [],
  "geometry": {"coordinates":[-87.35,33.9833],"type":"Point"}
}