{
  "id": 7130676,
  "type": "Feature",
  "properties": {
    "tgn:hierarchy":[
        "tgn:7130676",
        "tgn:7003669",
        "tgn:1000003",
        "tgn:7000084",
        "tgn:7029392"
    ],
    "tgn:id":7130676,
    "tgn:name":"Mittelramstadt",
    "tgn:placetype":[
        "aat:300008347"
    ]
},
  "bbox": [],
  "geometry": {"coordinates":[10.433333,49.333333],"type":"Point"}
}