{
  "id": 2621510,
  "type": "Feature",
  "properties": {
    "tgn:hierarchy":[
        "tgn:2621510",
        "tgn:1000001",
        "tgn:7012149",
        "tgn:1002553",
        "tgn:7007920",
        "tgn:7029392"
    ],
    "tgn:id":2621510,
    "tgn:name":"Roaring Ridge",
    "tgn:placetype":[
        "aat:300266640"
    ]
},
  "bbox": [],
  "geometry": {"coordinates":[-121.3833,47.3333],"type":"Point"}
}