{
  "id": 7133426,
  "type": "Feature",
  "properties": {
    "tgn:hierarchy":[
        "tgn:7133426",
        "tgn:7003692",
        "tgn:1000003",
        "tgn:7000084",
        "tgn:7029392"
    ],
    "tgn:id":7133426,
    "tgn:name":"M\u00fchlehof",
    "tgn:placetype":[
        "aat:300000206"
    ]
},
  "bbox": [],
  "geometry": {"coordinates":[7.566667,47.666667],"type":"Point"}
}