{
  "id": 7585009,
  "type": "Feature",
  "properties": {
    "tgn:hierarchy":[
        "tgn:7585009",
        "tgn:1000004",
        "tgn:7000198",
        "tgn:1001894",
        "tgn:7029392"
    ],
    "tgn:id":7585009,
    "tgn:name:en":"N\u0101hen",
    "tgn:placetype":[
        "aat:300008347"
    ]
},
  "bbox": [],
  "geometry": {"coordinates":[78.078528,23.999356],"type":"Point"}
}