<<<<<<< HEAD
{
  "id": 7020384,
  "type": "Feature",
  "properties": {
    "tgn:hierarchy":[
        "tgn:7020384",
        "tgn:1000001",
        "tgn:2001261",
        "tgn:7012149",
        "tgn:7007524",
        "tgn:7029392"
    ],
    "tgn:id":7020384,
    "tgn:name":"Canyon Springs Draw",
    "tgn:placetype":[
        "aat:300008761"
    ]
},
  "bbox": [],
  "geometry": {"coordinates":[-106.3833,45.0833],"type":"Point"}
}
=======
{"geometry":{"type":"Point","coordinates":[-106.383300,45.083300]},"type":"Feature","properties":{"hierarchy":["tgn:7020384","tgn:1000001","tgn:2001261","tgn:7012149","tgn:7007524","tgn:7029392"],"placetype":["aat:300008761"],"id":7020384,"name:xx":"Canyon Springs Draw"}}
>>>>>>> 03f74aca74312dbeaf24d7e61306dd6a786dc3d0
