{
  "id": 2207494,
  "type": "Feature",
  "properties": {
    "tgn:hierarchy":[
        "tgn:2207494",
        "tgn:1000001",
        "tgn:1002738",
        "tgn:7012149",
        "tgn:7007565",
        "tgn:7029392"
    ],
    "tgn:id":2207494,
    "tgn:name":"Bunting Sedge",
    "tgn:placetype":[
        "aat:300008791"
    ]
},
  "bbox": [],
  "geometry": {"coordinates":[-74.2667,39.55],"type":"Point"}
}