{
  "id": 2265167,
  "type": "Feature",
  "properties": {
    "tgn:hierarchy":[
        "tgn:2265167",
        "tgn:7006450",
        "tgn:1000001",
        "tgn:7012149",
        "tgn:2000086",
        "tgn:7029392"
    ],
    "tgn:id":2265167,
    "tgn:name":"Cranberry Peak",
    "tgn:placetype":[
        "aat:300008798"
    ]
},
  "bbox": [],
  "geometry": {"coordinates":[-145.9333,61.75],"type":"Point"}
}