{
  "id": 7453667,
  "type": "Feature",
  "properties": {
    "tgn:hierarchy":[
        "tgn:7453667",
        "tgn:7002445",
        "tgn:1000003",
        "tgn:7008178",
        "tgn:7008591",
        "tgn:7029392"
    ],
    "tgn:id":7453667,
    "tgn:name:en":"Crabbs Cross",
    "tgn:placetype":[
        "aat:300008347"
    ]
},
  "bbox": [],
  "geometry": {"coordinates":[-1.933333,52.266667],"type":"Point"}
}