{
  "id": 7501977,
  "type": "Feature",
  "properties": {
    "tgn:hierarchy":[
        "tgn:7501977",
        "tgn:1000004",
        "tgn:7492971",
        "tgn:1000141",
        "tgn:7029392"
    ],
    "tgn:id":7501977,
    "tgn:name":"Gaoshanyan Fude Gong",
    "tgn:placetype":[
        "aat:300007595"
    ]
},
  "bbox": [],
  "geometry": {"coordinates":[120.719722,21.963056],"type":"Point"}
}