{
  "id": 7191664,
  "type": "Feature",
  "properties": {
    "tgn:hierarchy":[
        "tgn:7191664",
        "tgn:7003692",
        "tgn:1000003",
        "tgn:7000084",
        "tgn:7029392"
    ],
    "tgn:id":7191664,
    "tgn:name":"Farnberg",
    "tgn:placetype":[
        "aat:300008795"
    ]
},
  "bbox": [],
  "geometry": {"coordinates":[8.033333,47.766667],"type":"Point"}
}