{
  "id": 7069984,
  "type": "Feature",
  "properties": {
    "tgn:hierarchy":[
        "tgn:7069984",
        "tgn:1000003",
        "tgn:7003677",
        "tgn:7000084",
        "tgn:7029392"
    ],
    "tgn:id":7069984,
    "tgn:name":"Tillemannskath",
    "tgn:placetype":[
        "aat:300000206"
    ]
},
  "bbox": [],
  "geometry": {"coordinates":[6.216667,51.766667],"type":"Point"}
}