{
  "id": 2505186,
  "type": "Feature",
  "properties": {
    "tgn:hierarchy":[
        "tgn:2505186",
        "tgn:1000001",
        "tgn:7012149",
        "tgn:7007157",
        "tgn:1002863",
        "tgn:7029392"
    ],
    "tgn:id":2505186,
    "tgn:name":"Mehlschau Creek",
    "tgn:placetype":[
        "aat:300008706"
    ]
},
  "bbox": [],
  "geometry": {"coordinates":[-120.4667,35.0833],"type":"Point"}
}