{
  "id": 2532023,
  "type": "Feature",
  "properties": {
    "tgn:hierarchy":[
        "tgn:2532023",
        "tgn:1000001",
        "tgn:2001410",
        "tgn:7012149",
        "tgn:7007526",
        "tgn:7029392"
    ],
    "tgn:id":2532023,
    "tgn:name":"Mummy Spring",
    "tgn:placetype":[
        "aat:300008697"
    ]
},
  "bbox": [],
  "geometry": {"coordinates":[-115.6333,36.2833],"type":"Point"}
}