<<<<<<< HEAD
{
  "id": 7371742,
  "type": "Feature",
  "properties": {
    "tgn:hierarchy":[
        "tgn:7371742",
        "tgn:1000001",
        "tgn:7005599",
        "tgn:7005560",
        "tgn:7029392"
    ],
    "tgn:id":7371742,
    "tgn:name":"La Calabaza",
    "tgn:placetype":[
        "aat:300008347"
    ]
},
  "bbox": [],
  "geometry": {"coordinates":[-97.916667,21.391667],"type":"Point"}
}
=======
{"geometry":{"type":"Point","coordinates":[-97.916667,21.391667]},"type":"Feature","properties":{"hierarchy":["tgn:7371742","tgn:1000001","tgn:7005599","tgn:7005560","tgn:7029392"],"placetype":["aat:300008347"],"id":7371742,"name:xx":"La Calabaza"}}
>>>>>>> 03f74aca74312dbeaf24d7e61306dd6a786dc3d0
