{
  "id": 7106252,
  "type": "Feature",
  "properties": {
    "tgn:hierarchy":[
        "tgn:7106252",
        "tgn:1000003",
        "tgn:7000094",
        "tgn:7000084",
        "tgn:7029392"
    ],
    "tgn:id":7106252,
    "tgn:name":"Schalentiner See",
    "tgn:placetype":[
        "aat:300008680"
    ]
},
  "bbox": [],
  "geometry": {"coordinates":[11.933333,53.433333],"type":"Point"}
}