{
  "id": 7455037,
  "type": "Feature",
  "properties": {
    "tgn:hierarchy":[
        "tgn:7455037",
        "tgn:7008532",
        "tgn:7002443",
        "tgn:1000003",
        "tgn:7008591",
        "tgn:7029392"
    ],
    "tgn:id":7455037,
    "tgn:name:en":"Cymyran Bay",
    "tgn:placetype":[
        "aat:300132316"
    ]
},
  "bbox": [],
  "geometry": {"coordinates":[-4.566667,53.233333],"type":"Point"}
}