{
  "id": 2455670,
  "type": "Feature",
  "properties": {
    "tgn:hierarchy":[
        "tgn:2455670",
        "tgn:1000001",
        "tgn:7012149",
        "tgn:2002125",
        "tgn:7007827",
        "tgn:7029392"
    ],
    "tgn:id":2455670,
    "tgn:name":"Little Gough Spring",
    "tgn:placetype":[
        "aat:300008697"
    ]
},
  "bbox": [],
  "geometry": {"coordinates":[-112.05,39.9167],"type":"Point"}
}