{
  "id": 1116763,
  "type": "Feature",
  "properties": {
    "tgn:hierarchy":[
        "tgn:1116763",
        "tgn:7005685",
        "tgn:1000001",
        "tgn:7013154",
        "tgn:7029392"
    ],
    "tgn:id":1116763,
    "tgn:name":"Kabenung Lake",
    "tgn:placetype":[
        "aat:300008680"
    ]
},
  "bbox": [],
  "geometry": {"coordinates":[-85.0333,48.25],"type":"Point"}
}