{
  "id": 2130732,
  "type": "Feature",
  "properties": {
    "tgn:hierarchy":[
        "tgn:2130732",
        "tgn:2000453",
        "tgn:1000001",
        "tgn:7012149",
        "tgn:7007250",
        "tgn:7029392"
    ],
    "tgn:id":2130732,
    "tgn:name":"Allison Creek",
    "tgn:placetype":[
        "aat:300008706"
    ]
},
  "bbox": [],
  "geometry": {"coordinates":[-116.6667,45.1167],"type":"Point"}
}