{
  "id": 7258239,
  "type": "Feature",
  "properties": {
    "tgn:hierarchy":[
        "tgn:7258239",
        "tgn:1000003",
        "tgn:7003613",
        "tgn:7016845",
        "tgn:7029392"
    ],
    "tgn:id":7258239,
    "tgn:name:nl":"Borgercompagnie-Oostkant, Polder",
    "tgn:placetype":[
        "aat:300006163"
    ]
},
  "bbox": [],
  "geometry": {"coordinates":[6.816667,53.133333],"type":"Point"}
}