{
  "id": 7041009,
  "type": "Feature",
  "properties": {
    "tgn:hierarchy":[
        "tgn:7041009",
        "tgn:7002991",
        "tgn:1000003",
        "tgn:7002997",
        "tgn:1000080",
        "tgn:7029392"
    ],
    "tgn:id":7041009,
    "tgn:name":"Sant'Antonio Tortal",
    "tgn:placetype":[
        "aat:300008347"
    ]
},
  "bbox": [],
  "geometry": {"coordinates":[12.100278,46.042222],"type":"Point"}
}