{
  "id": 2415585,
  "type": "Feature",
  "properties": {
    "tgn:hierarchy":[
        "tgn:2415585",
        "tgn:1000001",
        "tgn:2000198",
        "tgn:7012149",
        "tgn:7007158",
        "tgn:7029392"
    ],
    "tgn:id":2415585,
    "tgn:name":"Isolation Lake",
    "tgn:placetype":[
        "aat:300008680"
    ]
},
  "bbox": [],
  "geometry": {"coordinates":[-105.6667,40.1833],"type":"Point"}
}