{
  "id": 2741910,
  "type": "Feature",
  "properties": {
    "tgn:hierarchy":[
        "tgn:2741910",
        "tgn:1000001",
        "tgn:7012149",
        "tgn:7007157",
        "tgn:1002901",
        "tgn:7029392"
    ],
    "tgn:id":2741910,
    "tgn:name":"Vacaville Junction",
    "tgn:placetype":[
        "aat:300008347"
    ]
},
  "bbox": [],
  "geometry": {"coordinates":[-121.95,38.2833],"type":"Point"}
}