{
  "id": 7183652,
  "type": "Feature",
  "properties": {
    "tgn:hierarchy":[
        "tgn:7183652",
        "tgn:1000003",
        "tgn:7003687",
        "tgn:7000084",
        "tgn:7029392"
    ],
    "tgn:id":7183652,
    "tgn:name":"Gohrau",
    "tgn:placetype":[
        "aat:300008347"
    ]
},
  "bbox": [],
  "geometry": {"coordinates":[12.483333,51.816667],"type":"Point"}
}