{
  "id": 7392789,
  "type": "Feature",
  "properties": {
    "tgn:hierarchy":[
        "tgn:7392789",
        "tgn:1001853",
        "tgn:1000001",
        "tgn:7005560",
        "tgn:7029392"
    ],
    "tgn:id":7392789,
    "tgn:name":"San Jeronimo, Ca\u00f1\u00f3n de",
    "tgn:placetype":[
        "aat:300008763"
    ]
},
  "bbox": [],
  "geometry": {"coordinates":[-101.533333,24.95],"type":"Point"}
}