{
  "id": 2209527,
  "type": "Feature",
  "properties": {
    "tgn:hierarchy":[
        "tgn:2209527",
        "tgn:1000001",
        "tgn:7012149",
        "tgn:2000476",
        "tgn:7007250",
        "tgn:7029392"
    ],
    "tgn:id":2209527,
    "tgn:name":"Burpee Mine",
    "tgn:placetype":[
        "aat:300000390"
    ]
},
  "bbox": [],
  "geometry": {"coordinates":[-115.4667,45.5833],"type":"Point"}
}