{
  "id": 1095744,
  "type": "Feature",
  "properties": {
    "tgn:hierarchy":[
        "tgn:1095744",
        "tgn:7001242",
        "tgn:7016833",
        "tgn:1001142",
        "tgn:7029392"
    ],
    "tgn:id":1095744,
    "tgn:name:en":"Tizmant ash Sharq\u012byah",
    "tgn:placetype":[
        "aat:300008347"
    ]
},
  "bbox": [],
  "geometry": {"coordinates":[31.060921,29.054176],"type":"Point"}
}