{
  "id": 7413839,
  "type": "Feature",
  "properties": {
    "tgn:hierarchy":[
        "tgn:7413839",
        "tgn:7005587",
        "tgn:1000001",
        "tgn:7005560",
        "tgn:7029392"
    ],
    "tgn:id":7413839,
    "tgn:name:es":"Tequixco",
    "tgn:placetype":[
        "aat:300008347"
    ]
},
  "bbox": [],
  "geometry": {"coordinates":[-98.558333,20.736111],"type":"Point"}
}