{
  "id": 2664163,
  "type": "Feature",
  "properties": {
    "tgn:hierarchy":[
        "tgn:2664163",
        "tgn:1000001",
        "tgn:7006451",
        "tgn:7012149",
        "tgn:2000100",
        "tgn:7029392"
    ],
    "tgn:id":2664163,
    "tgn:name":"Silver Shield Mine",
    "tgn:placetype":[
        "aat:300000390"
    ]
},
  "bbox": [],
  "geometry": {"coordinates":[-111.2667,31.65],"type":"Point"}
}