<<<<<<< HEAD
{
  "id": 2251193,
  "type": "Feature",
  "properties": {
    "tgn:hierarchy":[
        "tgn:2251193",
        "tgn:1000001",
        "tgn:7012149",
        "tgn:7007157",
        "tgn:1002675",
        "tgn:7029392"
    ],
    "tgn:id":2251193,
    "tgn:name":"Comanche Gulch",
    "tgn:placetype":[
        "aat:300008761"
    ]
},
  "bbox": [],
  "geometry": {"coordinates":[-118.4833,37.7667],"type":"Point"}
}
=======
{"geometry":{"type":"Point","coordinates":[-118.483300,37.766700]},"type":"Feature","properties":{"hierarchy":["tgn:2251193","tgn:1000001","tgn:7012149","tgn:7007157","tgn:1002675","tgn:7029392"],"placetype":["aat:300008761"],"id":2251193,"name:xx":"Comanche Gulch"}}
>>>>>>> 03f74aca74312dbeaf24d7e61306dd6a786dc3d0
