{
  "id": 2709668,
  "type": "Feature",
  "properties": {
    "tgn:hierarchy":[
        "tgn:2709668",
        "tgn:1000001",
        "tgn:7012149",
        "tgn:1002758",
        "tgn:7007568",
        "tgn:7029392"
    ],
    "tgn:id":2709668,
    "tgn:name":"Taft Bay",
    "tgn:placetype":[
        "aat:300132316"
    ]
},
  "bbox": [],
  "geometry": {"coordinates":[-75.95,43.2333],"type":"Point"}
}