<<<<<<< HEAD
{
  "id": 7350038,
  "type": "Feature",
  "properties": {
    "tgn:hierarchy":[
        "tgn:7350038",
        "tgn:1000001",
        "tgn:7005591",
        "tgn:7005560",
        "tgn:7029392"
    ],
    "tgn:id":7350038,
    "tgn:name":"Ahila",
    "tgn:placetype":[
        "aat:300008347"
    ]
},
  "bbox": [],
  "geometry": {"coordinates":[-98.166667,20.283333],"type":"Point"}
}
=======
{"geometry":{"type":"Point","coordinates":[-98.166667,20.283333]},"type":"Feature","properties":{"hierarchy":["tgn:7350038","tgn:1000001","tgn:7005591","tgn:7005560","tgn:7029392"],"placetype":["aat:300008347"],"id":7350038,"name:xx":"Ahila"}}
>>>>>>> 03f74aca74312dbeaf24d7e61306dd6a786dc3d0
