{
  "id": 7559447,
  "type": "Feature",
  "properties": {
    "tgn:hierarchy":[
        "tgn:7559447",
        "tgn:1000004",
        "tgn:7000198",
        "tgn:1001895",
        "tgn:7029392"
    ],
    "tgn:id":7559447,
    "tgn:name:en":"Sarv\u0101r River",
    "tgn:placetype":[
        "aat:300008699"
    ]
},
  "bbox": [],
  "geometry": {"coordinates":[72.783333,19.516667],"type":"Point"}
}