{
  "id": 7381236,
  "type": "Feature",
  "properties": {
    "tgn:hierarchy":[
        "tgn:7381236",
        "tgn:7005581",
        "tgn:1000001",
        "tgn:7005560",
        "tgn:7029392"
    ],
    "tgn:id":7381236,
    "tgn:name":"Maijoma, Desierto",
    "tgn:placetype":[
        "aat:300008916"
    ]
},
  "bbox": [],
  "geometry": {"coordinates":[-104.683333,28.933333],"type":"Point"}
}