{
  "id": 2153731,
  "type": "Feature",
  "properties": {
    "tgn:hierarchy":[
        "tgn:2153731",
        "tgn:1000001",
        "tgn:7012149",
        "tgn:7014589",
        "tgn:7007515",
        "tgn:7029392"
    ],
    "tgn:id":2153731,
    "tgn:name":"Bear Brook",
    "tgn:placetype":[
        "aat:300008699"
    ]
},
  "bbox": [],
  "geometry": {"coordinates":[-67.65,44.8167],"type":"Point"}
}