<<<<<<< HEAD
{
  "id": 2153731,
  "type": "Feature",
  "properties": {
    "tgn:hierarchy":[
        "tgn:2153731",
        "tgn:1000001",
        "tgn:7012149",
        "tgn:7014589",
        "tgn:7007515",
        "tgn:7029392"
    ],
    "tgn:id":2153731,
    "tgn:name":"Bear Brook",
    "tgn:placetype":[
        "aat:300008699"
    ]
},
  "bbox": [],
  "geometry": {"coordinates":[-67.65,44.8167],"type":"Point"}
}
=======
{"geometry":{"type":"Point","coordinates":[-67.650000,44.816700]},"type":"Feature","properties":{"hierarchy":["tgn:2153731","tgn:1000001","tgn:7012149","tgn:7014589","tgn:7007515","tgn:7029392"],"placetype":["aat:300008699"],"id":2153731,"name:xx":"Bear Brook"}}
>>>>>>> 03f74aca74312dbeaf24d7e61306dd6a786dc3d0
