{
  "id": 2204727,
  "type": "Feature",
  "properties": {
    "tgn:hierarchy":[
        "tgn:2204727",
        "tgn:1000001",
        "tgn:7012149",
        "tgn:2001272",
        "tgn:7007524",
        "tgn:7029392"
    ],
    "tgn:id":2204727,
    "tgn:name":"Buffalo Reservoir",
    "tgn:placetype":[
        "aat:300006191"
    ]
},
  "bbox": [],
  "geometry": {"coordinates":[-104.15,46.25],"type":"Point"}
}