{
  "id": 2057547,
  "type": "Feature",
  "properties": {
    "tgn:hierarchy":[
        "tgn:2057547",
        "tgn:1000001",
        "tgn:7012149",
        "tgn:2001163",
        "tgn:7007522",
        "tgn:7029392"
    ],
    "tgn:id":2057547,
    "tgn:name":"Stewart",
    "tgn:placetype":[
        "aat:300008347"
    ]
},
  "bbox": [],
  "geometry": {"coordinates":[-89.4333,33.45],"type":"Point"}
}