<<<<<<< HEAD
{
  "id": 2330248,
  "type": "Feature",
  "properties": {
    "tgn:hierarchy":[
        "tgn:2330248",
        "tgn:1000001",
        "tgn:7006451",
        "tgn:2000092",
        "tgn:7012149",
        "tgn:7029392"
    ],
    "tgn:id":2330248,
    "tgn:name":"Flanigan Tank",
    "tgn:placetype":[
        "aat:300006191"
    ]
},
  "bbox": [],
  "geometry": {"coordinates":[-111.9833,35.4],"type":"Point"}
}
=======
{"geometry":{"type":"Point","coordinates":[-111.983300,35.400000]},"type":"Feature","properties":{"hierarchy":["tgn:2330248","tgn:1000001","tgn:7006451","tgn:2000092","tgn:7012149","tgn:7029392"],"placetype":["aat:300006191"],"id":2330248,"name:xx":"Flanigan Tank"}}
>>>>>>> 03f74aca74312dbeaf24d7e61306dd6a786dc3d0
