{
  "id": 2170807,
  "type": "Feature",
  "properties": {
    "tgn:hierarchy":[
        "tgn:2170807",
        "tgn:1000001",
        "tgn:7012149",
        "tgn:2000837",
        "tgn:7007255",
        "tgn:7029392"
    ],
    "tgn:id":2170807,
    "tgn:name":"Big Shelby Branch",
    "tgn:placetype":[
        "aat:300008699"
    ]
},
  "bbox": [],
  "geometry": {"coordinates":[-82.5667,37.2167],"type":"Point"}
}