{
  "id": 2341874,
  "type": "Feature",
  "properties": {
    "tgn:hierarchy":[
        "tgn:2341874",
        "tgn:1000001",
        "tgn:7012149",
        "tgn:7007157",
        "tgn:2000189",
        "tgn:7029392"
    ],
    "tgn:id":2341874,
    "tgn:name":"Fruit Mountain",
    "tgn:placetype":[
        "aat:300008798"
    ]
},
  "bbox": [],
  "geometry": {"coordinates":[-123.2333,41.95],"type":"Point"}
}