{
  "id": 2727054,
  "type": "Feature",
  "properties": {
    "tgn:hierarchy":[
        "tgn:2727054",
        "tgn:1000001",
        "tgn:7012149",
        "tgn:2001459",
        "tgn:7007566",
        "tgn:7029392"
    ],
    "tgn:id":2727054,
    "tgn:name":"Trabajo Creek",
    "tgn:placetype":[
        "aat:300008706"
    ]
},
  "bbox": [],
  "geometry": {"coordinates":[-103.5333,36.35],"type":"Point"}
}