{
  "id": 2214061,
  "type": "Feature",
  "properties": {
    "tgn:hierarchy":[
        "tgn:2214061",
        "tgn:7002659",
        "tgn:1000001",
        "tgn:7012149",
        "tgn:2000066",
        "tgn:7029392"
    ],
    "tgn:id":2214061,
    "tgn:name":"Cagle Mine",
    "tgn:placetype":[
        "aat:300000390"
    ]
},
  "bbox": [],
  "geometry": {"coordinates":[-87.6167,34.2833],"type":"Point"}
}