{
  "id": 7403151,
  "type": "Feature",
  "properties": {
    "tgn:hierarchy":[
        "tgn:7403151",
        "tgn:1000001",
        "tgn:7005600",
        "tgn:7005560",
        "tgn:7029392"
    ],
    "tgn:id":7403151,
    "tgn:name":"San Jos\u00e9 Montecristo",
    "tgn:placetype":[
        "aat:300008347"
    ]
},
  "bbox": [],
  "geometry": {"coordinates":[-87.6875,21.0625],"type":"Point"}
}