{
  "id": 2131705,
  "type": "Feature",
  "properties": {
    "tgn:hierarchy":[
        "tgn:2131705",
        "tgn:1000001",
        "tgn:7006451",
        "tgn:7012149",
        "tgn:2000100",
        "tgn:7029392"
    ],
    "tgn:id":2131705,
    "tgn:name":"Amado Mine",
    "tgn:placetype":[
        "aat:300000390"
    ]
},
  "bbox": [],
  "geometry": {"coordinates":[-111.3333,31.5833],"type":"Point"}
}