{
  "id": 1099896,
  "type": "Feature",
  "properties": {
    "tgn:hierarchy":[
        "tgn:1099896",
        "tgn:1000001",
        "tgn:7005502",
        "tgn:7029392"
    ],
    "tgn:id":1099896,
    "tgn:name":"Sans-Souci",
    "tgn:placetype":[
        "aat:300008057",
        "aat:300000833",
        "aat:300263063"
    ]
},
  "bbox": [],
  "geometry": {"coordinates":[-72.244,19.573],"type":"Point"}
}