{
  "id": 2158380,
  "type": "Feature",
  "properties": {
    "tgn:hierarchy":[
        "tgn:2158380",
        "tgn:1000001",
        "tgn:7012149",
        "tgn:2001924",
        "tgn:7007825",
        "tgn:7029392"
    ],
    "tgn:id":2158380,
    "tgn:name":"Beaverdam Branch",
    "tgn:placetype":[
        "aat:300008699"
    ]
},
  "bbox": [],
  "geometry": {"coordinates":[-85.4667,35.65],"type":"Point"}
}