{
  "id": 2255619,
  "type": "Feature",
  "properties": {
    "tgn:hierarchy":[
        "tgn:2255619",
        "tgn:1000001",
        "tgn:7012149",
        "tgn:2002067",
        "tgn:7007826",
        "tgn:7029392"
    ],
    "tgn:id":2255619,
    "tgn:name":"Copelle Creek",
    "tgn:placetype":[
        "aat:300008706"
    ]
},
  "bbox": [],
  "geometry": {"coordinates":[-94.1667,31.2833],"type":"Point"}
}