{
  "id": 2264503,
  "type": "Feature",
  "properties": {
    "tgn:hierarchy":[
        "tgn:2264503",
        "tgn:1000001",
        "tgn:7012149",
        "tgn:2001236",
        "tgn:7007523",
        "tgn:7029392"
    ],
    "tgn:id":2264503,
    "tgn:name":"Crabtree Hollow",
    "tgn:placetype":[
        "aat:300008761"
    ]
},
  "bbox": [],
  "geometry": {"coordinates":[-91.0833,37.3167],"type":"Point"}
}