{
  "id": 7339399,
  "type": "Feature",
  "properties": {
    "tgn:hierarchy":[
        "tgn:7339399",
        "tgn:7002805",
        "tgn:7002758",
        "tgn:1000003",
        "tgn:1000095",
        "tgn:7029392"
    ],
    "tgn:id":7339399,
    "tgn:name":"Congreso, Isla del",
    "tgn:placetype":[
        "aat:300008791"
    ]
},
  "bbox": [],
  "geometry": {"coordinates":[-2.433333,35.183333],"type":"Point"}
}