<<<<<<< HEAD
{
  "id": 2762816,
  "type": "Feature",
  "properties": {
    "tgn:hierarchy":[
        "tgn:2762816",
        "tgn:1000001",
        "tgn:7012149",
        "tgn:7007157",
        "tgn:1002656",
        "tgn:7029392"
    ],
    "tgn:id":2762816,
    "tgn:name":"Western States Drain",
    "tgn:placetype":[
        "aat:300006075"
    ]
},
  "bbox": [],
  "geometry": {"coordinates":[-120.9333,37.4],"type":"Point"}
}
=======
{"geometry":{"type":"Point","coordinates":[-120.933300,37.400000]},"type":"Feature","properties":{"hierarchy":["tgn:2762816","tgn:1000001","tgn:7012149","tgn:7007157","tgn:1002656","tgn:7029392"],"placetype":["aat:300006075"],"id":2762816,"name:xx":"Western States Drain"}}
>>>>>>> 03f74aca74312dbeaf24d7e61306dd6a786dc3d0
