<<<<<<< HEAD
{
  "id": 2332973,
  "type": "Feature",
  "properties": {
    "tgn:hierarchy":[
        "tgn:2332973",
        "tgn:1000001",
        "tgn:7012149",
        "tgn:7007157",
        "tgn:2000185",
        "tgn:7029392"
    ],
    "tgn:id":2332973,
    "tgn:name":"Flumeville",
    "tgn:placetype":[
        "aat:300008347"
    ]
},
  "bbox": [],
  "geometry": {"coordinates":[-123.7,38.9167],"type":"Point"}
}
=======
{"geometry":{"type":"Point","coordinates":[-123.700000,38.916700]},"type":"Feature","properties":{"hierarchy":["tgn:2332973","tgn:1000001","tgn:7012149","tgn:7007157","tgn:2000185","tgn:7029392"],"placetype":["aat:300008347"],"id":2332973,"name:xx":"Flumeville"}}
>>>>>>> 03f74aca74312dbeaf24d7e61306dd6a786dc3d0
