{
  "id": 2399424,
  "type": "Feature",
  "properties": {
    "tgn:hierarchy":[
        "tgn:2399424",
        "tgn:1000001",
        "tgn:2000464",
        "tgn:7012149",
        "tgn:7007250",
        "tgn:7029392"
    ],
    "tgn:id":2399424,
    "tgn:name":"Horn Spring",
    "tgn:placetype":[
        "aat:300008697"
    ]
},
  "bbox": [],
  "geometry": {"coordinates":[-114.6333,43.2167],"type":"Point"}
}