{
  "id": 7109483,
  "type": "Feature",
  "properties": {
    "tgn:hierarchy":[
        "tgn:7109483",
        "tgn:7000096",
        "tgn:1000003",
        "tgn:7000084",
        "tgn:7029392"
    ],
    "tgn:id":7109483,
    "tgn:name":"Quenzsee",
    "tgn:placetype":[
        "aat:300008680"
    ]
},
  "bbox": [],
  "geometry": {"coordinates":[12.483333,52.416667],"type":"Point"}
}