{
  "id": 2079401,
  "type": "Feature",
  "properties": {
    "tgn:hierarchy":[
        "tgn:2079401",
        "tgn:1000001",
        "tgn:7012149",
        "tgn:1002398",
        "tgn:7007706",
        "tgn:7029392"
    ],
    "tgn:id":2079401,
    "tgn:name":"Eckley",
    "tgn:placetype":[
        "aat:300387016"
    ]
},
  "bbox": [],
  "geometry": {"coordinates":[-84.2333,41.55],"type":"Point"}
}