{
  "id": 7317878,
  "type": "Feature",
  "properties": {
    "tgn:hierarchy":[
        "tgn:7317878",
        "tgn:7002464",
        "tgn:1000049",
        "tgn:1000002",
        "tgn:7029392"
    ],
    "tgn:id":7317878,
    "tgn:name":"Corregidor, Quebrada del",
    "tgn:placetype":[
        "aat:300266554",
        "aat:300008699"
    ]
},
  "bbox": [],
  "geometry": {"coordinates":[-68.783333,-20.333333],"type":"Point"}
}