<<<<<<< HEAD
{
  "id": 2156711,
  "type": "Feature",
  "properties": {
    "tgn:hierarchy":[
        "tgn:2156711",
        "tgn:1000001",
        "tgn:7012149",
        "tgn:2002371",
        "tgn:7007923",
        "tgn:7029392"
    ],
    "tgn:id":2156711,
    "tgn:name":"Beason Creek",
    "tgn:placetype":[
        "aat:300008706"
    ]
},
  "bbox": [],
  "geometry": {"coordinates":[-108.7667,42.7333],"type":"Point"}
}
=======
{"geometry":{"type":"Point","coordinates":[-108.766700,42.733300]},"type":"Feature","properties":{"hierarchy":["tgn:2156711","tgn:1000001","tgn:7012149","tgn:2002371","tgn:7007923","tgn:7029392"],"placetype":["aat:300008706"],"id":2156711,"name:xx":"Beason Creek"}}
>>>>>>> 03f74aca74312dbeaf24d7e61306dd6a786dc3d0
