{
  "id": 2500705,
  "type": "Feature",
  "properties": {
    "tgn:hierarchy":[
        "tgn:2500705",
        "tgn:1000001",
        "tgn:7012149",
        "tgn:7007826",
        "tgn:7029392"
    ],
    "tgn:id":2500705,
    "tgn:name":"McDowell Creek",
    "tgn:placetype":[
        "aat:300008706"
    ]
},
  "bbox": [],
  "geometry": {"coordinates":[-99.1167,32.8333],"type":"Point"}
}