{
  "id": 7400756,
  "type": "Feature",
  "properties": {
    "tgn:hierarchy":[
        "tgn:7400756",
        "tgn:1000001",
        "tgn:7005599",
        "tgn:7005560",
        "tgn:7029392"
    ],
    "tgn:id":7400756,
    "tgn:name":"Puente Nacional Norte",
    "tgn:placetype":[
        "aat:300008347"
    ]
},
  "bbox": [],
  "geometry": {"coordinates":[-95.733333,18.783333],"type":"Point"}
}