{
  "id": 2432967,
  "type": "Feature",
  "properties": {
    "tgn:hierarchy":[
        "tgn:2432967",
        "tgn:1002132",
        "tgn:1000001",
        "tgn:7012149",
        "tgn:7007919",
        "tgn:7029392"
    ],
    "tgn:id":2432967,
    "tgn:name":"Kegotank Bay",
    "tgn:placetype":[
        "aat:300132316"
    ]
},
  "bbox": [],
  "geometry": {"coordinates":[-75.5167,37.7833],"type":"Point"}
}