{
  "id": 2204616,
  "type": "Feature",
  "properties": {
    "tgn:hierarchy":[
        "tgn:2204616",
        "tgn:1000001",
        "tgn:7012149",
        "tgn:2002383",
        "tgn:7007923",
        "tgn:7029392"
    ],
    "tgn:id":2204616,
    "tgn:name":"Buffalo Hump Lake",
    "tgn:placetype":[
        "aat:300008680"
    ]
},
  "bbox": [],
  "geometry": {"coordinates":[-108.5167,42.0667],"type":"Point"}
}