{
  "id": 7191886,
  "type": "Feature",
  "properties": {
    "tgn:hierarchy":[
        "tgn:7191886",
        "tgn:1000003",
        "tgn:7003688",
        "tgn:7000084",
        "tgn:7029392"
    ],
    "tgn:id":7191886,
    "tgn:name":"Falsh\u00f6ft",
    "tgn:placetype":[
        "aat:300008347"
    ]
},
  "bbox": [],
  "geometry": {"coordinates":[9.966667,54.766667],"type":"Point"}
}