{
  "id": 7405901,
  "type": "Feature",
  "properties": {
    "tgn:hierarchy":[
        "tgn:7405901",
        "tgn:7016644",
        "tgn:1000001",
        "tgn:7005560",
        "tgn:7029392"
    ],
    "tgn:id":7405901,
    "tgn:name":"El Carrizalito",
    "tgn:placetype":[
        "aat:300008347"
    ]
},
  "bbox": [],
  "geometry": {"coordinates":[-103.686111,19.351389],"type":"Point"}
}