{
  "id": 7323574,
  "type": "Feature",
  "properties": {
    "tgn:hierarchy":[
        "tgn:7323574",
        "tgn:7002849",
        "tgn:1000003",
        "tgn:7009604",
        "tgn:1000095",
        "tgn:7029392"
    ],
    "tgn:id":7323574,
    "tgn:name":"Rigoitia",
    "tgn:placetype":[
        "aat:300008347"
    ]
},
  "bbox": [],
  "geometry": {"coordinates":[-2.725231,43.318665],"type":"Point"}
}