{
  "id": 2328544,
  "type": "Feature",
  "properties": {
    "tgn:hierarchy":[
        "tgn:2328544",
        "tgn:7014010",
        "tgn:1000001",
        "tgn:1002344",
        "tgn:7012149",
        "tgn:7007517",
        "tgn:7029392"
    ],
    "tgn:id":2328544,
    "tgn:name":"Fisher Pond",
    "tgn:placetype":[
        "aat:300006191"
    ]
},
  "bbox": [],
  "geometry": {"coordinates":[-70.6833,41.3833],"type":"Point"}
}