{
  "id": 2592769,
  "type": "Feature",
  "properties": {
    "tgn:hierarchy":[
        "tgn:2592769",
        "tgn:1000001",
        "tgn:7012149",
        "tgn:2000218",
        "tgn:7007158",
        "tgn:7029392"
    ],
    "tgn:id":2592769,
    "tgn:name":"Pope Creek",
    "tgn:placetype":[
        "aat:300008706"
    ]
},
  "bbox": [],
  "geometry": {"coordinates":[-107.3833,37.5833],"type":"Point"}
}