{
  "id": 7531901,
  "type": "Feature",
  "properties": {
    "tgn:hierarchy":[
        "tgn:7531901",
        "tgn:7001242",
        "tgn:7016833",
        "tgn:1001091",
        "tgn:7029392"
    ],
    "tgn:id":7531901,
    "tgn:name":"Mustashf\u00e1 al Waf\u0101' wa al Amal",
    "tgn:placetype":[
        "aat:300006676"
    ]
},
  "bbox": [],
  "geometry": {"coordinates":[31.352025,30.045454],"type":"Point"}
}