{
  "id": 2415003,
  "type": "Feature",
  "properties": {
    "tgn:hierarchy":[
        "tgn:2415003",
        "tgn:1000001",
        "tgn:2000939",
        "tgn:7012149",
        "tgn:7007516",
        "tgn:7029392"
    ],
    "tgn:id":2415003,
    "tgn:name":"Island Acres",
    "tgn:placetype":[
        "aat:300008347"
    ]
},
  "bbox": [],
  "geometry": {"coordinates":[-76.1333,38.6667],"type":"Point"}
}