<<<<<<< HEAD
{
  "id": 7242588,
  "type": "Feature",
  "properties": {
    "tgn:hierarchy":[
        "tgn:7242588",
        "tgn:7003466",
        "tgn:1000003",
        "tgn:1000063",
        "tgn:4012014",
        "tgn:7029392"
    ],
    "tgn:id":7242588,
    "tgn:name":"Les Alloux",
    "tgn:placetype":[
        "aat:300008347"
    ]
},
  "bbox": [],
  "geometry": {"coordinates":[4.6,50.45],"type":"Point"}
}
=======
{"geometry":{"type":"Point","coordinates":[4.600000,50.450000]},"type":"Feature","properties":{"hierarchy":["tgn:7242588","tgn:7003466","tgn:1000003","tgn:1000063","tgn:4012014","tgn:7029392"],"placetype":["aat:300008347"],"id":7242588,"name:xx":"Les Alloux"}}
>>>>>>> 03f74aca74312dbeaf24d7e61306dd6a786dc3d0
