{
  "id": 7553909,
  "type": "Feature",
  "properties": {
    "tgn:hierarchy":[
        "tgn:7553909",
        "tgn:1000004",
        "tgn:7000198",
        "tgn:1001895",
        "tgn:7029392"
    ],
    "tgn:id":7553909,
    "tgn:name:en":"Musargagi Point",
    "tgn:placetype":[
        "aat:300386846"
    ]
},
  "bbox": [],
  "geometry": {"coordinates":[73.333333,16.616667],"type":"Point"}
}