{
  "id": 2548633,
  "type": "Feature",
  "properties": {
    "tgn:hierarchy":[
        "tgn:2548633",
        "tgn:1000001",
        "tgn:7012149",
        "tgn:2002122",
        "tgn:7007827",
        "tgn:7029392"
    ],
    "tgn:id":2548633,
    "tgn:name":"North Narrows Ditch",
    "tgn:placetype":[
        "aat:300006075"
    ]
},
  "bbox": [],
  "geometry": {"coordinates":[-111.35,40.9167],"type":"Point"}
}