{
  "id": 2166363,
  "type": "Feature",
  "properties": {
    "tgn:hierarchy":[
        "tgn:2166363",
        "tgn:1000001",
        "tgn:7012149",
        "tgn:2001115",
        "tgn:7007522",
        "tgn:7029392"
    ],
    "tgn:id":2166363,
    "tgn:name":"Big Black Creek",
    "tgn:placetype":[
        "aat:300008706"
    ]
},
  "bbox": [],
  "geometry": {"coordinates":[-88.6667,30.6833],"type":"Point"}
}