{
  "id": 2350691,
  "type": "Feature",
  "properties": {
    "tgn:hierarchy":[
        "tgn:2350691",
        "tgn:1000001",
        "tgn:7012149",
        "tgn:2001195",
        "tgn:7007523",
        "tgn:7029392"
    ],
    "tgn:id":2350691,
    "tgn:name":"Gladden Branch",
    "tgn:placetype":[
        "aat:300008699"
    ]
},
  "bbox": [],
  "geometry": {"coordinates":[-91.5667,37.5167],"type":"Point"}
}