{
  "id": 7407996,
  "type": "Feature",
  "properties": {
    "tgn:hierarchy":[
        "tgn:7407996",
        "tgn:7005580",
        "tgn:1000001",
        "tgn:7005560",
        "tgn:7029392"
    ],
    "tgn:id":7407996,
    "tgn:name":"Efra\u00edn A. Guti\u00e9rrez",
    "tgn:placetype":[
        "aat:300008347"
    ]
},
  "bbox": [],
  "geometry": {"coordinates":[-92.183333,16.336111],"type":"Point"}
}