{
  "id": 1036425,
  "type": "Feature",
  "properties": {
    "tgn:hierarchy":[
        "tgn:1036425",
        "tgn:7000096",
        "tgn:1000003",
        "tgn:7000084",
        "tgn:7029392"
    ],
    "tgn:id":1036425,
    "tgn:name":"Beeskow",
    "tgn:placetype":[
        "aat:300008347"
    ]
},
  "bbox": [],
  "geometry": {"coordinates":[14.25,52.166667],"type":"Point"}
}