{
  "id": 7556059,
  "type": "Feature",
  "properties": {
    "tgn:hierarchy":[
        "tgn:7556059",
        "tgn:1000004",
        "tgn:7000198",
        "tgn:7016722",
        "tgn:7029392"
    ],
    "tgn:id":7556059,
    "tgn:name:en":"Sathla",
    "tgn:placetype":[
        "aat:300008347"
    ]
},
  "bbox": [],
  "geometry": {"coordinates":[77.927811,29.051304],"type":"Point"}
}