{
  "id": 4005119,
  "type": "Feature",
  "properties": {
    "tgn:hierarchy":[
        "tgn:4005119",
        "tgn:7003692",
        "tgn:1000003",
        "tgn:7000084",
        "tgn:7029392"
    ],
    "tgn:id":4005119,
    "tgn:name":"Hoppetenzell",
    "tgn:placetype":[
        "aat:300008347"
    ]
},
  "bbox": [],
  "geometry": {"coordinates":[9.016667,47.883333],"type":"Point"}
}