{
  "id": 7061594,
  "type": "Feature",
  "properties": {
    "tgn:hierarchy":[
        "tgn:7061594",
        "tgn:7003669",
        "tgn:1000003",
        "tgn:7000084",
        "tgn:7029392"
    ],
    "tgn:id":7061594,
    "tgn:name":"Asbach",
    "tgn:placetype":[
        "aat:300008347"
    ]
},
  "bbox": [],
  "geometry": {"coordinates":[11.016667,49.233333],"type":"Point"}
}