<<<<<<< HEAD
{
  "id": 7359719,
  "type": "Feature",
  "properties": {
    "tgn:hierarchy":[
        "tgn:7359719",
        "tgn:1000001",
        "tgn:7005600",
        "tgn:7005560",
        "tgn:7029392"
    ],
    "tgn:id":7359719,
    "tgn:name":"Concepci\u00f3n",
    "tgn:placetype":[
        "aat:300008347"
    ]
},
  "bbox": [],
  "geometry": {"coordinates":[-89.466667,21.166667],"type":"Point"}
}
=======
{"geometry":{"type":"Point","coordinates":[-89.466667,21.166667]},"type":"Feature","properties":{"hierarchy":["tgn:7359719","tgn:1000001","tgn:7005600","tgn:7005560","tgn:7029392"],"placetype":["aat:300008347"],"id":7359719,"name:xx":"Concepci\u00f3n"}}
>>>>>>> 03f74aca74312dbeaf24d7e61306dd6a786dc3d0
