<<<<<<< HEAD
{
  "id": 7115165,
  "type": "Feature",
  "properties": {
    "tgn:hierarchy":[
        "tgn:7115165",
        "tgn:1000003",
        "tgn:7003685",
        "tgn:7000084",
        "tgn:7029392"
    ],
    "tgn:id":7115165,
    "tgn:name":"Ochsen-Berg",
    "tgn:placetype":[
        "aat:300008777"
    ]
},
  "bbox": [],
  "geometry": {"coordinates":[14.0,51.316667],"type":"Point"}
}
=======
{"geometry":{"type":"Point","coordinates":[14.000000,51.316667]},"type":"Feature","properties":{"hierarchy":["tgn:7115165","tgn:1000003","tgn:7003685","tgn:7000084","tgn:7029392"],"placetype":["aat:300008777"],"id":7115165,"name:xx":"Ochsen-Berg"}}
>>>>>>> 03f74aca74312dbeaf24d7e61306dd6a786dc3d0
