{
  "id": 7494762,
  "type": "Feature",
  "properties": {
    "tgn:hierarchy":[
        "tgn:7494762",
        "tgn:7001010",
        "tgn:1000004",
        "tgn:1000141",
        "tgn:7029392"
    ],
    "tgn:id":7494762,
    "tgn:name":"Shajia Shan",
    "tgn:placetype":[
        "aat:300008798"
    ]
},
  "bbox": [],
  "geometry": {"coordinates":[121.301293,23.591317],"type":"Point"}
}