<<<<<<< HEAD
{
  "id": 2404040,
  "type": "Feature",
  "properties": {
    "tgn:hierarchy":[
        "tgn:2404040",
        "tgn:7002659",
        "tgn:1000001",
        "tgn:7012149",
        "tgn:2000022",
        "tgn:7029392"
    ],
    "tgn:id":2404040,
    "tgn:name":"Howell Pond",
    "tgn:placetype":[
        "aat:300006191"
    ]
},
  "bbox": [],
  "geometry": {"coordinates":[-85.45,31.3],"type":"Point"}
}
=======
{"geometry":{"type":"Point","coordinates":[-85.450000,31.300000]},"type":"Feature","properties":{"hierarchy":["tgn:2404040","tgn:7002659","tgn:1000001","tgn:7012149","tgn:2000022","tgn:7029392"],"placetype":["aat:300006191"],"id":2404040,"name:xx":"Howell Pond"}}
>>>>>>> 03f74aca74312dbeaf24d7e61306dd6a786dc3d0
