{
  "id": 7344185,
  "type": "Feature",
  "properties": {
    "tgn:hierarchy":[
        "tgn:7344185",
        "tgn:7008911",
        "tgn:1000003",
        "tgn:7002763",
        "tgn:1000095",
        "tgn:7029392"
    ],
    "tgn:id":7344185,
    "tgn:name":"Barroco, Punta",
    "tgn:placetype":[
        "aat:300386846"
    ]
},
  "bbox": [],
  "geometry": {"coordinates":[-6.65,43.566667],"type":"Point"}
}