{
  "id": 2277140,
  "type": "Feature",
  "properties": {
    "tgn:hierarchy":[
        "tgn:2277140",
        "tgn:7002659",
        "tgn:1000001",
        "tgn:7012149",
        "tgn:2000028",
        "tgn:7029392"
    ],
    "tgn:id":2277140,
    "tgn:name":"Davis Creek Mine",
    "tgn:placetype":[
        "aat:300000390"
    ]
},
  "bbox": [],
  "geometry": {"coordinates":[-87.4667,33.6167],"type":"Point"}
}