{
  "id": 7477925,
  "type": "Feature",
  "properties": {
    "tgn:hierarchy":[
        "tgn:7477925",
        "tgn:1000004",
        "tgn:7467799",
        "tgn:1000141",
        "tgn:7029392"
    ],
    "tgn:id":7477925,
    "tgn:name":"Xucuo",
    "tgn:placetype":[
        "aat:300008347"
    ]
},
  "bbox": [],
  "geometry": {"coordinates":[120.5306,23.95115],"type":"Point"}
}