{
  "id": 2658179,
  "type": "Feature",
  "properties": {
    "tgn:hierarchy":[
        "tgn:2658179",
        "tgn:1000001",
        "tgn:2000197",
        "tgn:7012149",
        "tgn:7007158",
        "tgn:7029392"
    ],
    "tgn:id":2658179,
    "tgn:name":"Shelton Creek",
    "tgn:placetype":[
        "aat:300008706"
    ]
},
  "bbox": [],
  "geometry": {"coordinates":[-102.8833,37.65],"type":"Point"}
}