{
  "id": 2156370,
  "type": "Feature",
  "properties": {
    "tgn:hierarchy":[
        "tgn:2156370",
        "tgn:1000001",
        "tgn:1002480",
        "tgn:7012149",
        "tgn:7007564",
        "tgn:7029392"
    ],
    "tgn:id":2156370,
    "tgn:name":"Bears Den",
    "tgn:placetype":[
        "aat:300008746"
    ]
},
  "bbox": [],
  "geometry": {"coordinates":[-71.6833,42.7167],"type":"Point"}
}