{
  "id": 7491455,
  "type": "Feature",
  "properties": {
    "tgn:hierarchy":[
        "tgn:7491455",
        "tgn:1000004",
        "tgn:7489179",
        "tgn:1000141",
        "tgn:7029392"
    ],
    "tgn:id":7491455,
    "tgn:name":"Beicheng",
    "tgn:placetype":[
        "aat:300000745"
    ]
},
  "bbox": [],
  "geometry": {"coordinates":[121.757367,24.678468],"type":"Point"}
}