{
  "id": 2204535,
  "type": "Feature",
  "properties": {
    "tgn:hierarchy":[
        "tgn:2204535",
        "tgn:1000001",
        "tgn:7012149",
        "tgn:2000486",
        "tgn:7007250",
        "tgn:7029392"
    ],
    "tgn:id":2204535,
    "tgn:name":"Buffalo Draw",
    "tgn:placetype":[
        "aat:300008761"
    ]
},
  "bbox": [],
  "geometry": {"coordinates":[-116.8833,46.1833],"type":"Point"}
}