{
  "id": 7304883,
  "type": "Feature",
  "properties": {
    "tgn:hierarchy":[
        "tgn:7304883",
        "tgn:7002813",
        "tgn:7002758",
        "tgn:1000003",
        "tgn:1000095",
        "tgn:7029392"
    ],
    "tgn:id":7304883,
    "tgn:name":"Laurel, Cerro del",
    "tgn:placetype":[
        "aat:300008777"
    ]
},
  "bbox": [],
  "geometry": {"coordinates":[-5.783333,36.316667],"type":"Point"}
}