{
  "id": 7419915,
  "type": "Feature",
  "properties": {
    "tgn:hierarchy":[
        "tgn:7419915",
        "tgn:1001836",
        "tgn:1000001",
        "tgn:7005560",
        "tgn:7029392"
    ],
    "tgn:id":7419915,
    "tgn:name":"El Comit\u00e1n",
    "tgn:placetype":[
        "aat:300008347"
    ]
},
  "bbox": [],
  "geometry": {"coordinates":[-110.304167,24.125],"type":"Point"}
}