{
  "id": 2287517,
  "type": "Feature",
  "properties": {
    "tgn:hierarchy":[
        "tgn:2287517",
        "tgn:1000001",
        "tgn:7012149",
        "tgn:7007255",
        "tgn:7029392"
    ],
    "tgn:id":2287517,
    "tgn:name":"Difficult Creek",
    "tgn:placetype":[
        "aat:300008706"
    ]
},
  "bbox": [],
  "geometry": {"coordinates":[-86.1333,36.7833],"type":"Point"}
}