{
  "id": 1049231,
  "type": "Feature",
  "properties": {
    "tgn:hierarchy":[
        "tgn:1049231",
        "tgn:1000003",
        "tgn:7024120",
        "tgn:7006366",
        "tgn:7029392"
    ],
    "tgn:id":1049231,
    "tgn:name":"Ma\u0142owice",
    "tgn:placetype":[
        "aat:300008347"
    ]
},
  "bbox": [],
  "geometry": {"coordinates":[15.45,51.5667],"type":"Point"}
}