{
  "id": 2667931,
  "type": "Feature",
  "properties": {
    "tgn:hierarchy":[
        "tgn:2667931",
        "tgn:1000001",
        "tgn:7012149",
        "tgn:2000926",
        "tgn:7007515",
        "tgn:7029392"
    ],
    "tgn:id":2667931,
    "tgn:name":"Skunk Pond",
    "tgn:placetype":[
        "aat:300008680"
    ]
},
  "bbox": [],
  "geometry": {"coordinates":[-70.9833,44.85],"type":"Point"}
}