{
  "id": 7483434,
  "type": "Feature",
  "properties": {
    "tgn:hierarchy":[
        "tgn:7483434",
        "tgn:7487020",
        "tgn:1000004",
        "tgn:1000141",
        "tgn:7029392"
    ],
    "tgn:id":7483434,
    "tgn:name":"Nanxi Qiao",
    "tgn:placetype":[
        "aat:300007836"
    ]
},
  "bbox": [],
  "geometry": {"coordinates":[120.693611,24.3975],"type":"Point"}
}