{
  "id": 7276355,
  "type": "Feature",
  "properties": {
    "tgn:hierarchy":[
        "tgn:7276355",
        "tgn:1001623",
        "tgn:1000049",
        "tgn:1000002",
        "tgn:7029392"
    ],
    "tgn:id":7276355,
    "tgn:name":"Tom\u00e1s, Paso",
    "tgn:placetype":[
        "aat:300387026"
    ]
},
  "bbox": [],
  "geometry": {"coordinates":[-75.283333,-48.15],"type":"Point"}
}