<<<<<<< HEAD
{
  "id": 2405703,
  "type": "Feature",
  "properties": {
    "tgn:hierarchy":[
        "tgn:2405703",
        "tgn:1000001",
        "tgn:2002368",
        "tgn:7012149",
        "tgn:7007923",
        "tgn:7029392"
    ],
    "tgn:id":2405703,
    "tgn:name":"Hugus Draw",
    "tgn:placetype":[
        "aat:300008761"
    ]
},
  "bbox": [],
  "geometry": {"coordinates":[-107.1,41.6833],"type":"Point"}
}
=======
{"geometry":{"type":"Point","coordinates":[-107.100000,41.683300]},"type":"Feature","properties":{"hierarchy":["tgn:2405703","tgn:1000001","tgn:2002368","tgn:7012149","tgn:7007923","tgn:7029392"],"placetype":["aat:300008761"],"id":2405703,"name:xx":"Hugus Draw"}}
>>>>>>> 03f74aca74312dbeaf24d7e61306dd6a786dc3d0
