{
  "id": 2663287,
  "type": "Feature",
  "properties": {
    "tgn:hierarchy":[
        "tgn:2663287",
        "tgn:1000001",
        "tgn:2001326",
        "tgn:7012149",
        "tgn:7007525",
        "tgn:7029392"
    ],
    "tgn:id":2663287,
    "tgn:name":"Silver Creek",
    "tgn:placetype":[
        "aat:300008706"
    ]
},
  "bbox": [],
  "geometry": {"coordinates":[-96.2667,41.9167],"type":"Point"}
}