{
  "id": 7069101,
  "type": "Feature",
  "properties": {
    "tgn:hierarchy":[
        "tgn:7069101",
        "tgn:1000003",
        "tgn:7003678",
        "tgn:7000084",
        "tgn:7029392"
    ],
    "tgn:id":7069101,
    "tgn:name":"Steckeln-Berg",
    "tgn:placetype":[
        "aat:300008777"
    ]
},
  "bbox": [],
  "geometry": {"coordinates":[8.533333,50.933333],"type":"Point"}
}