{
  "id": 2483605,
  "type": "Feature",
  "properties": {
    "tgn:hierarchy":[
        "tgn:2483605",
        "tgn:1000001",
        "tgn:7012149",
        "tgn:2000892",
        "tgn:7007256",
        "tgn:7029392"
    ],
    "tgn:id":2483605,
    "tgn:name":"Latenache Drainage Canal, Bayou",
    "tgn:placetype":[
        "aat:300006075"
    ]
},
  "bbox": [],
  "geometry": {"coordinates":[-91.7167,30.6167],"type":"Point"}
}