{
  "id": 7387355,
  "type": "Feature",
  "properties": {
    "tgn:hierarchy":[
        "tgn:7387355",
        "tgn:7005585",
        "tgn:1000001",
        "tgn:7005560",
        "tgn:7029392"
    ],
    "tgn:id":7387355,
    "tgn:name":"Petatl\u00e1n, Morro de",
    "tgn:placetype":[
        "aat:300386846"
    ]
},
  "bbox": [],
  "geometry": {"coordinates":[-101.466667,17.516667],"type":"Point"}
}