{
  "id": 2631085,
  "type": "Feature",
  "properties": {
    "tgn:hierarchy":[
        "tgn:2631085",
        "tgn:1000001",
        "tgn:2000467",
        "tgn:7012149",
        "tgn:7007250",
        "tgn:7029392"
    ],
    "tgn:id":2631085,
    "tgn:name":"Round Mountain",
    "tgn:placetype":[
        "aat:300008798"
    ]
},
  "bbox": [],
  "geometry": {"coordinates":[-113.2167,42.0167],"type":"Point"}
}