{
  "id": 2722999,
  "type": "Feature",
  "properties": {
    "tgn:hierarchy":[
        "tgn:2722999",
        "tgn:1000001",
        "tgn:7012149",
        "tgn:2001718",
        "tgn:7007708",
        "tgn:7029392"
    ],
    "tgn:id":2722999,
    "tgn:name":"Tire Tube Cave",
    "tgn:placetype":[
        "aat:300008746"
    ]
},
  "bbox": [],
  "geometry": {"coordinates":[-117.9167,42.9833],"type":"Point"}
}