{
  "id": 2157716,
  "type": "Feature",
  "properties": {
    "tgn:hierarchy":[
        "tgn:2157716",
        "tgn:1000001",
        "tgn:7012149",
        "tgn:7007923",
        "tgn:7029392"
    ],
    "tgn:id":2157716,
    "tgn:name":"Beaver Divide",
    "tgn:placetype":[
        "aat:300266640"
    ]
},
  "bbox": [],
  "geometry": {"coordinates":[-107.9333,42.7333],"type":"Point"}
}