<<<<<<< HEAD
{
  "id": 2157716,
  "type": "Feature",
  "properties": {
    "tgn:hierarchy":[
        "tgn:2157716",
        "tgn:1000001",
        "tgn:7012149",
        "tgn:7007923",
        "tgn:7029392"
    ],
    "tgn:id":2157716,
    "tgn:name":"Beaver Divide",
    "tgn:placetype":[
        "aat:300266640"
    ]
},
  "bbox": [],
  "geometry": {"coordinates":[-107.9333,42.7333],"type":"Point"}
}
=======
{"geometry":{"type":"Point","coordinates":[-107.933300,42.733300]},"type":"Feature","properties":{"hierarchy":["tgn:2157716","tgn:1000001","tgn:7012149","tgn:7007923","tgn:7029392"],"placetype":["aat:300266640"],"id":2157716,"name:xx":"Beaver Divide"}}
>>>>>>> 03f74aca74312dbeaf24d7e61306dd6a786dc3d0
