{
  "id": 7424023,
  "type": "Feature",
  "properties": {
    "tgn:hierarchy":[
        "tgn:7424023",
        "tgn:1000001",
        "tgn:1001960",
        "tgn:7005560",
        "tgn:7029392"
    ],
    "tgn:id":7424023,
    "tgn:name":"El Pinito",
    "tgn:placetype":[
        "aat:300008347"
    ]
},
  "bbox": [],
  "geometry": {"coordinates":[-108.733333,29.483333],"type":"Point"}
}