{
  "id": 7094990,
  "type": "Feature",
  "properties": {
    "tgn:hierarchy":[
        "tgn:7094990",
        "tgn:1000003",
        "tgn:7003677",
        "tgn:7000084",
        "tgn:7029392"
    ],
    "tgn:id":7094990,
    "tgn:name":"Seebach",
    "tgn:placetype":[
        "aat:300008795"
    ]
},
  "bbox": [],
  "geometry": {"coordinates":[8.216667,50.966667],"type":"Point"}
}