{
  "id": 2600748,
  "type": "Feature",
  "properties": {
    "tgn:hierarchy":[
        "tgn:2600748",
        "tgn:7030516",
        "tgn:7006450",
        "tgn:1000001",
        "tgn:7012149",
        "tgn:7029392"
    ],
    "tgn:id":2600748,
    "tgn:name":"Pumicestone Bay",
    "tgn:placetype":[
        "aat:300132316"
    ]
},
  "bbox": [],
  "geometry": {"coordinates":[-167.1167,53.5167],"type":"Point"}
}