{
  "id": 2276982,
  "type": "Feature",
  "properties": {
    "tgn:hierarchy":[
        "tgn:2276982",
        "tgn:1000001",
        "tgn:7012149",
        "tgn:2001503",
        "tgn:7007709",
        "tgn:7029392"
    ],
    "tgn:id":2276982,
    "tgn:name":"Davis Cove",
    "tgn:placetype":[
        "aat:300008761"
    ]
},
  "bbox": [],
  "geometry": {"coordinates":[-82.9667,35.5667],"type":"Point"}
}