{
  "id": 7272708,
  "type": "Feature",
  "properties": {
    "tgn:hierarchy":[
        "tgn:7272708",
        "tgn:1000003",
        "tgn:7003627",
        "tgn:7016845",
        "tgn:7029392"
    ],
    "tgn:id":7272708,
    "tgn:name:nl":"Vogelzang, Polder",
    "tgn:placetype":[
        "aat:300006163"
    ]
},
  "bbox": [],
  "geometry": {"coordinates":[4.966667,51.966667],"type":"Point"}
}