<<<<<<< HEAD
{
  "id": 7374108,
  "type": "Feature",
  "properties": {
    "tgn:hierarchy":[
        "tgn:7374108",
        "tgn:1000001",
        "tgn:7005589",
        "tgn:7005560",
        "tgn:7029392"
    ],
    "tgn:id":7374108,
    "tgn:name":"La Comita",
    "tgn:placetype":[
        "aat:300008347"
    ]
},
  "bbox": [],
  "geometry": {"coordinates":[-99.3,25.4],"type":"Point"}
}
=======
{"geometry":{"type":"Point","coordinates":[-99.300000,25.400000]},"type":"Feature","properties":{"hierarchy":["tgn:7374108","tgn:1000001","tgn:7005589","tgn:7005560","tgn:7029392"],"placetype":["aat:300008347"],"id":7374108,"name:xx":"La Comita"}}
>>>>>>> 03f74aca74312dbeaf24d7e61306dd6a786dc3d0
