{
  "id": 7336780,
  "type": "Feature",
  "properties": {
    "tgn:hierarchy":[
        "tgn:7336780",
        "tgn:7002803",
        "tgn:1001647",
        "tgn:1000003",
        "tgn:1000095",
        "tgn:7029392"
    ],
    "tgn:id":7336780,
    "tgn:name":"Fontanar de Arriba",
    "tgn:placetype":[
        "aat:300008347"
    ]
},
  "bbox": [],
  "geometry": {"coordinates":[-1.583333,38.95],"type":"Point"}
}