{
  "id": 2712750,
  "type": "Feature",
  "properties": {
    "tgn:hierarchy":[
        "tgn:2712750",
        "tgn:1000001",
        "tgn:2001411",
        "tgn:7012149",
        "tgn:7007526",
        "tgn:7029392"
    ],
    "tgn:id":2712750,
    "tgn:name":"Taylor Creek",
    "tgn:placetype":[
        "aat:300008706"
    ]
},
  "bbox": [],
  "geometry": {"coordinates":[-116.0667,40.9833],"type":"Point"}
}