{
  "id": 1095932,
  "type": "Feature",
  "properties": {
    "tgn:hierarchy":[
        "tgn:1095932",
        "tgn:7001242",
        "tgn:1001209",
        "tgn:1000209",
        "tgn:7029392"
    ],
    "tgn:id":1095932,
    "tgn:name":"Kalulushi",
    "tgn:placetype":[
        "aat:300008347",
        "aat:300387305",
        "aat:300008375"
    ]
},
  "bbox": [],
  "geometry": {"coordinates":[28.05,-12.8333],"type":"Point"}
}