<<<<<<< HEAD
{
  "id": 7175098,
  "type": "Feature",
  "properties": {
    "tgn:hierarchy":[
        "tgn:7175098",
        "tgn:1000003",
        "tgn:7003676",
        "tgn:7000084",
        "tgn:7029392"
    ],
    "tgn:id":7175098,
    "tgn:name":"Grimm-Berg",
    "tgn:placetype":[
        "aat:300008777"
    ]
},
  "bbox": [],
  "geometry": {"coordinates":[10.4,51.666667],"type":"Point"}
}
=======
{"geometry":{"type":"Point","coordinates":[10.400000,51.666667]},"type":"Feature","properties":{"hierarchy":["tgn:7175098","tgn:1000003","tgn:7003676","tgn:7000084","tgn:7029392"],"placetype":["aat:300008777"],"id":7175098,"name:xx":"Grimm-Berg"}}
>>>>>>> 03f74aca74312dbeaf24d7e61306dd6a786dc3d0
