{
  "id": 7217649,
  "type": "Feature",
  "properties": {
    "tgn:hierarchy":[
        "tgn:7217649",
        "tgn:7011164",
        "tgn:7002674",
        "tgn:1000003",
        "tgn:1000074",
        "tgn:7029392"
    ],
    "tgn:id":7217649,
    "tgn:name":"Ira\u00edon",
    "tgn:placetype":[
        "aat:300008347"
    ]
},
  "bbox": [],
  "geometry": {"coordinates":[26.8825,37.663889],"type":"Point"}
}