{
  "id": 7170368,
  "type": "Feature",
  "properties": {
    "tgn:hierarchy":[
        "tgn:7170368",
        "tgn:7003669",
        "tgn:1000003",
        "tgn:7000084",
        "tgn:7029392"
    ],
    "tgn:id":7170368,
    "tgn:name":"Hitzenhofen",
    "tgn:placetype":[
        "aat:300008347"
    ]
},
  "bbox": [],
  "geometry": {"coordinates":[10.133333,47.95],"type":"Point"}
}