{
  "id": 1023916,
  "type": "Feature",
  "properties": {
    "tgn:hierarchy":[
        "tgn:1023916",
        "tgn:7005071",
        "tgn:1000050",
        "tgn:1000002",
        "tgn:7029392"
    ],
    "tgn:id":1023916,
    "tgn:name":"Pesca",
    "tgn:placetype":[
        "aat:300008347"
    ]
},
  "bbox": [],
  "geometry": {"coordinates":[-73.05,5.55],"type":"Point"}
}