{
  "id": 2493820,
  "type": "Feature",
  "properties": {
    "tgn:hierarchy":[
        "tgn:2493820",
        "tgn:1000001",
        "tgn:7012149",
        "tgn:2000283",
        "tgn:7007240",
        "tgn:7029392"
    ],
    "tgn:id":2493820,
    "tgn:name":"Marshall Creek",
    "tgn:placetype":[
        "aat:300008706"
    ]
},
  "bbox": [],
  "geometry": {"coordinates":[-81.3667,30.0167],"type":"Point"}
}