{
  "id": 2055853,
  "type": "Feature",
  "properties": {
    "tgn:hierarchy":[
        "tgn:2055853",
        "tgn:1000001",
        "tgn:7012149",
        "tgn:2001108",
        "tgn:7007522",
        "tgn:7029392"
    ],
    "tgn:id":2055853,
    "tgn:name":"Ansley",
    "tgn:placetype":[
        "aat:300008347"
    ]
},
  "bbox": [],
  "geometry": {"coordinates":[-89.4833,30.2167],"type":"Point"}
}