{
  "id": 2731768,
  "type": "Feature",
  "properties": {
    "tgn:hierarchy":[
        "tgn:2731768",
        "tgn:7006450",
        "tgn:1000001",
        "tgn:7012149",
        "tgn:2124005",
        "tgn:7029392"
    ],
    "tgn:id":2731768,
    "tgn:name":"Tuluk Creek",
    "tgn:placetype":[
        "aat:300008706"
    ]
},
  "bbox": [],
  "geometry": {"coordinates":[-148.7667,69.3333],"type":"Point"}
}