{
  "id": 2029039,
  "type": "Feature",
  "properties": {
    "tgn:hierarchy":[
        "tgn:2029039",
        "tgn:1000001",
        "tgn:1002377",
        "tgn:7012149",
        "tgn:7007251",
        "tgn:7029392"
    ],
    "tgn:id":2029039,
    "tgn:name":"Melvin",
    "tgn:placetype":[
        "aat:300008347"
    ]
},
  "bbox": [],
  "geometry": {"coordinates":[-88.2333,40.5667],"type":"Point"}
}