{
  "id": 7426716,
  "type": "Feature",
  "properties": {
    "tgn:hierarchy":[
        "tgn:7426716",
        "tgn:1000001",
        "tgn:7005594",
        "tgn:7005560",
        "tgn:7029392"
    ],
    "tgn:id":7426716,
    "tgn:name":"El Cidral",
    "tgn:placetype":[
        "aat:300008347"
    ]
},
  "bbox": [],
  "geometry": {"coordinates":[-99.066667,21.833333],"type":"Point"}
}