{
  "id": 2088473,
  "type": "Feature",
  "properties": {
    "tgn:hierarchy":[
        "tgn:2088473",
        "tgn:1000001",
        "tgn:1002278",
        "tgn:7012149",
        "tgn:7007710",
        "tgn:7029392"
    ],
    "tgn:id":2088473,
    "tgn:name":"Five Points",
    "tgn:placetype":[
        "aat:300008347",
        "aat:300387210"
    ]
},
  "bbox": [],
  "geometry": {"coordinates":[-78.6667,40.7833],"type":"Point"}
}