{
  "id": 2327809,
  "type": "Feature",
  "properties": {
    "tgn:hierarchy":[
        "tgn:2327809",
        "tgn:1000001",
        "tgn:2001779",
        "tgn:7012149",
        "tgn:7007713",
        "tgn:7029392"
    ],
    "tgn:id":2327809,
    "tgn:name":"Fish Draw",
    "tgn:placetype":[
        "aat:300008761"
    ]
},
  "bbox": [],
  "geometry": {"coordinates":[-103.1167,45.1667],"type":"Point"}
}