{
  "id": 1121294,
  "type": "Feature",
  "properties": {
    "tgn:hierarchy":[
        "tgn:1121294",
        "tgn:1000004",
        "tgn:7013207",
        "tgn:7018214",
        "tgn:7002435",
        "tgn:7029392"
    ],
    "tgn:id":1121294,
    "tgn:name":"Archeda",
    "tgn:placetype":[
        "aat:300008707"
    ]
},
  "bbox": [],
  "geometry": {"coordinates":[43.1667,49.8833],"type":"Point"}
}