{
  "id": 2267373,
  "type": "Feature",
  "properties": {
    "tgn:hierarchy":[
        "tgn:2267373",
        "tgn:1000001",
        "tgn:7012149",
        "tgn:2001844",
        "tgn:7007825",
        "tgn:7029392"
    ],
    "tgn:id":2267373,
    "tgn:name":"Crisp",
    "tgn:placetype":[
        "aat:300008347"
    ]
},
  "bbox": [],
  "geometry": {"coordinates":[-85.9833,35.65],"type":"Point"}
}