{
  "id": 2394765,
  "type": "Feature",
  "properties": {
    "tgn:hierarchy":[
        "tgn:2394765",
        "tgn:1000001",
        "tgn:7012149",
        "tgn:1002449",
        "tgn:7013961",
        "tgn:7029392"
    ],
    "tgn:id":2394765,
    "tgn:name":"Holbert Run",
    "tgn:placetype":[
        "aat:300008699"
    ]
},
  "bbox": [],
  "geometry": {"coordinates":[-80.5667,40.4667],"type":"Point"}
}