{
  "id": 7321604,
  "type": "Feature",
  "properties": {
    "tgn:hierarchy":[
        "tgn:7321604",
        "tgn:1001708",
        "tgn:1000049",
        "tgn:1000002",
        "tgn:7029392"
    ],
    "tgn:id":7321604,
    "tgn:name":"Azufre, R\u00edo",
    "tgn:placetype":[
        "aat:300008699"
    ]
},
  "bbox": [],
  "geometry": {"coordinates":[-69.983333,-33.416667],"type":"Point"}
}