{
  "id": 2404929,
  "type": "Feature",
  "properties": {
    "tgn:hierarchy":[
        "tgn:2404929",
        "tgn:7002659",
        "tgn:1000001",
        "tgn:7012149",
        "tgn:2000038",
        "tgn:7029392"
    ],
    "tgn:id":2404929,
    "tgn:name":"Huddon Creek",
    "tgn:placetype":[
        "aat:300008706"
    ]
},
  "bbox": [],
  "geometry": {"coordinates":[-87.65,34.8833],"type":"Point"}
}