<<<<<<< HEAD
{
  "id": 2334653,
  "type": "Feature",
  "properties": {
    "tgn:hierarchy":[
        "tgn:2334653",
        "tgn:1000001",
        "tgn:7012149",
        "tgn:2001849",
        "tgn:7007825",
        "tgn:7029392"
    ],
    "tgn:id":2334653,
    "tgn:name":"Forge Ridge",
    "tgn:placetype":[
        "aat:300266640"
    ]
},
  "bbox": [],
  "geometry": {"coordinates":[-83.5667,36.5667],"type":"Point"}
}
=======
{"geometry":{"type":"Point","coordinates":[-83.566700,36.566700]},"type":"Feature","properties":{"hierarchy":["tgn:2334653","tgn:1000001","tgn:7012149","tgn:2001849","tgn:7007825","tgn:7029392"],"placetype":["aat:300266640"],"id":2334653,"name:xx":"Forge Ridge"}}
>>>>>>> 03f74aca74312dbeaf24d7e61306dd6a786dc3d0
