{
  "id": 2265440,
  "type": "Feature",
  "properties": {
    "tgn:hierarchy":[
        "tgn:2265440",
        "tgn:1000001",
        "tgn:7012149",
        "tgn:2002268",
        "tgn:7013961",
        "tgn:7029392"
    ],
    "tgn:id":2265440,
    "tgn:name":"Crane Knob",
    "tgn:placetype":[
        "aat:300008798"
    ]
},
  "bbox": [],
  "geometry": {"coordinates":[-81.65,38.6167],"type":"Point"}
}