{
  "id": 7452529,
  "type": "Feature",
  "properties": {
    "tgn:hierarchy":[
        "tgn:7452529",
        "tgn:7002444",
        "tgn:1000003",
        "tgn:7008072",
        "tgn:7008591",
        "tgn:7029392"
    ],
    "tgn:id":7452529,
    "tgn:name:en":"Hartsgarth Burn",
    "tgn:placetype":[
        "aat:300008699"
    ]
},
  "bbox": [],
  "geometry": {"coordinates":[-2.783333,55.216667],"type":"Point"}
}