{
  "id": 7040194,
  "type": "Feature",
  "properties": {
    "tgn:hierarchy":[
        "tgn:7040194",
        "tgn:1003450",
        "tgn:7007850",
        "tgn:1000003",
        "tgn:1000080",
        "tgn:7029392"
    ],
    "tgn:id":7040194,
    "tgn:name":"Satacuosco",
    "tgn:placetype":[
        "aat:300008347"
    ]
},
  "bbox": [],
  "geometry": {"coordinates":[16.466667,39.533333],"type":"Point"}
}