{
  "id": 2270761,
  "type": "Feature",
  "properties": {
    "tgn:hierarchy":[
        "tgn:2270761",
        "tgn:1000001",
        "tgn:7012149",
        "tgn:1002763",
        "tgn:7007255",
        "tgn:7029392"
    ],
    "tgn:id":2270761,
    "tgn:name":"Cub Branch",
    "tgn:placetype":[
        "aat:300008699"
    ]
},
  "bbox": [],
  "geometry": {"coordinates":[-84.6833,38.5333],"type":"Point"}
}