{
  "id": 2504655,
  "type": "Feature",
  "properties": {
    "tgn:hierarchy":[
        "tgn:2504655",
        "tgn:1000001",
        "tgn:7012149",
        "tgn:7007158",
        "tgn:7029392"
    ],
    "tgn:id":2504655,
    "tgn:name":"Medano Ditch",
    "tgn:placetype":[
        "aat:300006075"
    ]
},
  "bbox": [],
  "geometry": {"coordinates":[-105.4167,37.8333],"type":"Point"}
}