{
  "id": 2697189,
  "type": "Feature",
  "properties": {
    "tgn:hierarchy":[
        "tgn:2697189",
        "tgn:1000001",
        "tgn:7012149",
        "tgn:7007157",
        "tgn:7029392"
    ],
    "tgn:id":2697189,
    "tgn:name":"Stony Creek",
    "tgn:placetype":[
        "aat:300008706"
    ]
},
  "bbox": [],
  "geometry": {"coordinates":[-122.6333,39.3667],"type":"Point"}
}