{
  "id": 2267702,
  "type": "Feature",
  "properties": {
    "tgn:hierarchy":[
        "tgn:2267702",
        "tgn:1002247",
        "tgn:1000001",
        "tgn:7012149",
        "tgn:7007516",
        "tgn:7029392"
    ],
    "tgn:id":2267702,
    "tgn:name":"Cromleys Mountain",
    "tgn:placetype":[
        "aat:300008798"
    ]
},
  "bbox": [],
  "geometry": {"coordinates":[-76.1667,39.6667],"type":"Point"}
}