{
  "id": 2601296,
  "type": "Feature",
  "properties": {
    "tgn:hierarchy":[
        "tgn:2601296",
        "tgn:1000001",
        "tgn:7012149",
        "tgn:1002879",
        "tgn:7007252",
        "tgn:7029392"
    ],
    "tgn:id":2601296,
    "tgn:name":"Puppy Hollow",
    "tgn:placetype":[
        "aat:300008761"
    ]
},
  "bbox": [],
  "geometry": {"coordinates":[-85.8333,38.6333],"type":"Point"}
}