{
  "id": 7294232,
  "type": "Feature",
  "properties": {
    "tgn:hierarchy":[
        "tgn:7294232",
        "tgn:7001158",
        "tgn:7002848",
        "tgn:1000003",
        "tgn:1000095",
        "tgn:7029392"
    ],
    "tgn:id":7294232,
    "tgn:name":"Valverde de Campos",
    "tgn:placetype":[
        "aat:300008347"
    ]
},
  "bbox": [],
  "geometry": {"coordinates":[-5.033333,41.833333],"type":"Point"}
}