{
  "id": 2467841,
  "type": "Feature",
  "properties": {
    "tgn:hierarchy":[
        "tgn:2467841",
        "tgn:1000001",
        "tgn:7012149",
        "tgn:7007157",
        "tgn:1002957",
        "tgn:7029392"
    ],
    "tgn:id":2467841,
    "tgn:name":"Long Lake",
    "tgn:placetype":[
        "aat:300008680"
    ]
},
  "bbox": [],
  "geometry": {"coordinates":[-119.75,38.1667],"type":"Point"}
}