{
  "id": 7277948,
  "type": "Feature",
  "properties": {
    "tgn:hierarchy":[
        "tgn:7277948",
        "tgn:1001630",
        "tgn:1000049",
        "tgn:1000002",
        "tgn:7029392"
    ],
    "tgn:id":7277948,
    "tgn:name":"Chango, Roca",
    "tgn:placetype":[
        "aat:300011692"
    ]
},
  "bbox": [],
  "geometry": {"coordinates":[-70.85,-27.033333],"type":"Point"}
}