{
  "id": 2302180,
  "type": "Feature",
  "properties": {
    "tgn:hierarchy":[
        "tgn:2302180",
        "tgn:1000001",
        "tgn:7012149",
        "tgn:7007158",
        "tgn:2000253",
        "tgn:7029392"
    ],
    "tgn:id":2302180,
    "tgn:name":"Dutch Girl Lake",
    "tgn:placetype":[
        "aat:300008680"
    ]
},
  "bbox": [],
  "geometry": {"coordinates":[-104.15,40.5833],"type":"Point"}
}