{
  "id": 7238427,
  "type": "Feature",
  "properties": {
    "tgn:hierarchy":[
        "tgn:7238427",
        "tgn:7003460",
        "tgn:1000003",
        "tgn:1000063",
        "tgn:4012014",
        "tgn:7029392"
    ],
    "tgn:id":7238427,
    "tgn:name":"Harduemont",
    "tgn:placetype":[
        "aat:300008347"
    ]
},
  "bbox": [],
  "geometry": {"coordinates":[5.323895,50.633982],"type":"Point"}
}