<<<<<<< HEAD
{
  "id": 2252085,
  "type": "Feature",
  "properties": {
    "tgn:hierarchy":[
        "tgn:2252085",
        "tgn:1000001",
        "tgn:7012149",
        "tgn:2002291",
        "tgn:7013961",
        "tgn:7029392"
    ],
    "tgn:id":2252085,
    "tgn:name":"Condon Run",
    "tgn:placetype":[
        "aat:300008699"
    ]
},
  "bbox": [],
  "geometry": {"coordinates":[-79.6833,38.9333],"type":"Point"}
}
=======
{"geometry":{"type":"Point","coordinates":[-79.683300,38.933300]},"type":"Feature","properties":{"hierarchy":["tgn:2252085","tgn:1000001","tgn:7012149","tgn:2002291","tgn:7013961","tgn:7029392"],"placetype":["aat:300008699"],"id":2252085,"name:xx":"Condon Run"}}
>>>>>>> 03f74aca74312dbeaf24d7e61306dd6a786dc3d0
