{
  "id": 2373295,
  "type": "Feature",
  "properties": {
    "tgn:hierarchy":[
        "tgn:2373295",
        "tgn:7023902",
        "tgn:1000001",
        "tgn:7012149",
        "tgn:7007249",
        "tgn:7029392"
    ],
    "tgn:id":2373295,
    "tgn:name":"Halulu, Puu",
    "tgn:placetype":[
        "aat:300008798"
    ]
},
  "bbox": [],
  "geometry": {"coordinates":[-155.0833,19.3833],"type":"Point"}
}