{
  "id": 7210156,
  "type": "Feature",
  "properties": {
    "tgn:hierarchy":[
        "tgn:7210156",
        "tgn:7003692",
        "tgn:1000003",
        "tgn:7000084",
        "tgn:7029392"
    ],
    "tgn:id":7210156,
    "tgn:name":"Berg Wald",
    "tgn:placetype":[
        "aat:300008863"
    ]
},
  "bbox": [],
  "geometry": {"coordinates":[8.35,48.866667],"type":"Point"}
}