{
  "id": 7222793,
  "type": "Feature",
  "properties": {
    "tgn:hierarchy":[
        "tgn:7222793",
        "tgn:7002681",
        "tgn:7001395",
        "tgn:1000003",
        "tgn:1000074",
        "tgn:7029392"
    ],
    "tgn:id":7222793,
    "tgn:name":"Mess\u00e1pion \u00d3ros",
    "tgn:placetype":[
        "aat:300008795"
    ]
},
  "bbox": [],
  "geometry": {"coordinates":[23.45,38.45],"type":"Point"}
}