{
  "id": 7142902,
  "type": "Feature",
  "properties": {
    "tgn:hierarchy":[
        "tgn:7142902",
        "tgn:1000003",
        "tgn:7003678",
        "tgn:7000084",
        "tgn:7029392"
    ],
    "tgn:id":7142902,
    "tgn:name":"Magdalenenhausen",
    "tgn:placetype":[
        "aat:300000206"
    ]
},
  "bbox": [],
  "geometry": {"coordinates":[8.466667,50.533333],"type":"Point"}
}