{
  "id": 1067897,
  "type": "Feature",
  "properties": {
    "tgn:hierarchy":[
        "tgn:1067897",
        "tgn:1000004",
        "tgn:7002372",
        "tgn:1000111",
        "tgn:7029392"
    ],
    "tgn:id":1067897,
    "tgn:name":"Dunhua",
    "tgn:placetype":[
        "aat:300008347"
    ]
},
  "bbox": [],
  "geometry": {"coordinates":[128.2167,43.35],"type":"Point"}
}