{
  "id": 2743551,
  "type": "Feature",
  "properties": {
    "tgn:hierarchy":[
        "tgn:2743551",
        "tgn:1000001",
        "tgn:7012149",
        "tgn:7007157",
        "tgn:7014475",
        "tgn:7029392"
    ],
    "tgn:id":2743551,
    "tgn:name":"Vasquez Peak",
    "tgn:placetype":[
        "aat:300008798"
    ]
},
  "bbox": [],
  "geometry": {"coordinates":[-121.3833,37.0667],"type":"Point"}
}