{
  "id": 7341047,
  "type": "Feature",
  "properties": {
    "tgn:hierarchy":[
        "tgn:7341047",
        "tgn:7001122",
        "tgn:1000003",
        "tgn:7002765",
        "tgn:1000095",
        "tgn:7029392"
    ],
    "tgn:id":7341047,
    "tgn:name":"B\u00fager",
    "tgn:placetype":[
        "aat:300008347"
    ]
},
  "bbox": [],
  "geometry": {"coordinates":[2.983333,39.75],"type":"Point"}
}