{
  "id": 2175296,
  "type": "Feature",
  "properties": {
    "tgn:hierarchy":[
        "tgn:2175296",
        "tgn:1000001",
        "tgn:7012149",
        "tgn:7007157",
        "tgn:1002684",
        "tgn:7029392"
    ],
    "tgn:id":2175296,
    "tgn:name":"Black Butte",
    "tgn:placetype":[
        "aat:300008798"
    ]
},
  "bbox": [],
  "geometry": {"coordinates":[-121.5333,36.2667],"type":"Point"}
}