{
  "id": 2162005,
  "type": "Feature",
  "properties": {
    "tgn:hierarchy":[
        "tgn:2162005",
        "tgn:1000001",
        "tgn:7006451",
        "tgn:7012149",
        "tgn:2000102",
        "tgn:7029392"
    ],
    "tgn:id":2162005,
    "tgn:name":"Bells, Cave of The",
    "tgn:placetype":[
        "aat:300008746"
    ]
},
  "bbox": [],
  "geometry": {"coordinates":[-110.7667,31.7167],"type":"Point"}
}