{
  "id": 2145453,
  "type": "Feature",
  "properties": {
    "tgn:hierarchy":[
        "tgn:2145453",
        "tgn:1000001",
        "tgn:2002133",
        "tgn:7012149",
        "tgn:7007828",
        "tgn:7029392"
    ],
    "tgn:id":2145453,
    "tgn:name":"Baldin Brook",
    "tgn:placetype":[
        "aat:300008699"
    ]
},
  "bbox": [],
  "geometry": {"coordinates":[-72.4833,44.6167],"type":"Point"}
}