<<<<<<< HEAD
{
  "id": 2155707,
  "type": "Feature",
  "properties": {
    "tgn:hierarchy":[
        "tgn:2155707",
        "tgn:1000001",
        "tgn:7012149",
        "tgn:2001451",
        "tgn:7007566",
        "tgn:7029392"
    ],
    "tgn:id":2155707,
    "tgn:name":"Bear Springs Canyon",
    "tgn:placetype":[
        "aat:300008761"
    ]
},
  "bbox": [],
  "geometry": {"coordinates":[-106.5333,35.6833],"type":"Point"}
}
=======
{"geometry":{"type":"Point","coordinates":[-106.533300,35.683300]},"type":"Feature","properties":{"hierarchy":["tgn:2155707","tgn:1000001","tgn:7012149","tgn:2001451","tgn:7007566","tgn:7029392"],"placetype":["aat:300008761"],"id":2155707,"name:xx":"Bear Springs Canyon"}}
>>>>>>> 03f74aca74312dbeaf24d7e61306dd6a786dc3d0
