{
  "id": 1065637,
  "type": "Feature",
  "properties": {
    "tgn:hierarchy":[
        "tgn:1065637",
        "tgn:7000188",
        "tgn:1000004",
        "tgn:1000105",
        "tgn:7029392"
    ],
    "tgn:id":1065637,
    "tgn:name":"Ch\u0101ndpur",
    "tgn:placetype":[
        "aat:300008347"
    ]
},
  "bbox": [],
  "geometry": {"coordinates":[91.9167,22.1333],"type":"Point"}
}