<<<<<<< HEAD
{
  "id": 2334378,
  "type": "Feature",
  "properties": {
    "tgn:hierarchy":[
        "tgn:2334378",
        "tgn:1000001",
        "tgn:2000459",
        "tgn:7012149",
        "tgn:7007250",
        "tgn:7029392"
    ],
    "tgn:id":2334378,
    "tgn:name":"Forest King Mine",
    "tgn:placetype":[
        "aat:300000390"
    ]
},
  "bbox": [],
  "geometry": {"coordinates":[-115.7667,43.9],"type":"Point"}
}
=======
{"geometry":{"type":"Point","coordinates":[-115.766700,43.900000]},"type":"Feature","properties":{"hierarchy":["tgn:2334378","tgn:1000001","tgn:2000459","tgn:7012149","tgn:7007250","tgn:7029392"],"placetype":["aat:300000390"],"id":2334378,"name:xx":"Forest King Mine"}}
>>>>>>> 03f74aca74312dbeaf24d7e61306dd6a786dc3d0
