{
  "id": 2553427,
  "type": "Feature",
  "properties": {
    "tgn:hierarchy":[
        "tgn:2553427",
        "tgn:1000001",
        "tgn:7012149",
        "tgn:7007157",
        "tgn:1002858",
        "tgn:7029392"
    ],
    "tgn:id":2553427,
    "tgn:name":"Oak Canyon",
    "tgn:placetype":[
        "aat:300008761"
    ]
},
  "bbox": [],
  "geometry": {"coordinates":[-117.0333,32.8833],"type":"Point"}
}