{
  "id": 2557576,
  "type": "Feature",
  "properties": {
    "tgn:hierarchy":[
        "tgn:2557576",
        "tgn:2002141",
        "tgn:1000001",
        "tgn:7012149",
        "tgn:7007919",
        "tgn:7029392"
    ],
    "tgn:id":2557576,
    "tgn:name":"Old Pilot",
    "tgn:placetype":[
        "aat:300008347"
    ]
},
  "bbox": [],
  "geometry": {"coordinates":[-78.9167,37.3167],"type":"Point"}
}