{
  "id": 7025976,
  "type": "Feature",
  "properties": {
    "tgn:hierarchy":[
        "tgn:7025976",
        "tgn:7002445",
        "tgn:1000003",
        "tgn:7011961",
        "tgn:7008591",
        "tgn:7029392"
    ],
    "tgn:id":7025976,
    "tgn:name:ang":"Sturminstre",
    "tgn:placetype":[
        "aat:300008347",
        "aat:300008372"
    ]
},
  "bbox": [],
  "geometry": {"coordinates":[-2.066667,50.783333],"type":"Point"}
}