{
  "id": 2205984,
  "type": "Feature",
  "properties": {
    "tgn:hierarchy":[
        "tgn:2205984",
        "tgn:1000001",
        "tgn:7012149",
        "tgn:2002195",
        "tgn:7007919",
        "tgn:7029392"
    ],
    "tgn:id":2205984,
    "tgn:name":"Bull Run",
    "tgn:placetype":[
        "aat:300008699"
    ]
},
  "bbox": [],
  "geometry": {"coordinates":[-82.3833,36.95],"type":"Point"}
}