{
  "id": 2514985,
  "type": "Feature",
  "properties": {
    "tgn:hierarchy":[
        "tgn:2514985",
        "tgn:7002659",
        "tgn:1000001",
        "tgn:7012149",
        "tgn:2000036",
        "tgn:7029392"
    ],
    "tgn:id":2514985,
    "tgn:name":"Miller Steam Plant Water Storagep",
    "tgn:placetype":[
        "aat:300006191"
    ]
},
  "bbox": [],
  "geometry": {"coordinates":[-87.0667,33.6333],"type":"Point"}
}