{
  "id": 1015812,
  "type": "Feature",
  "properties": {
    "tgn:hierarchy":[
        "tgn:1015812",
        "tgn:7005685",
        "tgn:1000001",
        "tgn:7005804",
        "tgn:7029392"
    ],
    "tgn:id":1015812,
    "tgn:name":"Waterville",
    "tgn:placetype":[
        "aat:300008347"
    ]
},
  "bbox": [],
  "geometry": {"coordinates":[-71.8667,45.2667],"type":"Point"}
}