<<<<<<< HEAD
{
  "id": 7171318,
  "type": "Feature",
  "properties": {
    "tgn:hierarchy":[
        "tgn:7171318",
        "tgn:1000003",
        "tgn:7003676",
        "tgn:7000084",
        "tgn:7029392"
    ],
    "tgn:id":7171318,
    "tgn:name":"Hilwartshausen",
    "tgn:placetype":[
        "aat:300000206"
    ]
},
  "bbox": [],
  "geometry": {"coordinates":[9.65,51.45],"type":"Point"}
}
=======
{"geometry":{"type":"Point","coordinates":[9.650000,51.450000]},"type":"Feature","properties":{"hierarchy":["tgn:7171318","tgn:1000003","tgn:7003676","tgn:7000084","tgn:7029392"],"placetype":["aat:300000206"],"id":7171318,"name:xx":"Hilwartshausen"}}
>>>>>>> 03f74aca74312dbeaf24d7e61306dd6a786dc3d0
