{
  "id": 7171318,
  "type": "Feature",
  "properties": {
    "tgn:hierarchy":[
        "tgn:7171318",
        "tgn:1000003",
        "tgn:7003676",
        "tgn:7000084",
        "tgn:7029392"
    ],
    "tgn:id":7171318,
    "tgn:name":"Hilwartshausen",
    "tgn:placetype":[
        "aat:300000206"
    ]
},
  "bbox": [],
  "geometry": {"coordinates":[9.65,51.45],"type":"Point"}
}