{
  "id": 2220286,
  "type": "Feature",
  "properties": {
    "tgn:hierarchy":[
        "tgn:2220286",
        "tgn:1000001",
        "tgn:7012149",
        "tgn:1002598",
        "tgn:7007523",
        "tgn:7029392"
    ],
    "tgn:id":2220286,
    "tgn:name":"Cap au Gris",
    "tgn:placetype":[
        "aat:300008347"
    ]
},
  "bbox": [],
  "geometry": {"coordinates":[-90.6833,38.9833],"type":"Point"}
}