{
  "id": 7493660,
  "type": "Feature",
  "properties": {
    "tgn:hierarchy":[
        "tgn:7493660",
        "tgn:1000004",
        "tgn:7001013",
        "tgn:1000141",
        "tgn:7029392"
    ],
    "tgn:id":7493660,
    "tgn:name":"Longyankeng",
    "tgn:placetype":[
        "aat:300008347"
    ]
},
  "bbox": [],
  "geometry": {"coordinates":[121.297081,24.871407],"type":"Point"}
}