{
  "id": 7045162,
  "type": "Feature",
  "properties": {
    "tgn:hierarchy":[
        "tgn:7045162",
        "tgn:1003506",
        "tgn:1000003",
        "tgn:7002993",
        "tgn:1000080",
        "tgn:7029392"
    ],
    "tgn:id":7045162,
    "tgn:name":"Castelmonte",
    "tgn:placetype":[
        "aat:300008347"
    ]
},
  "bbox": [],
  "geometry": {"coordinates":[13.521944,46.0925],"type":"Point"}
}