{
  "id": 7204577,
  "type": "Feature",
  "properties": {
    "tgn:hierarchy":[
        "tgn:7204577",
        "tgn:1000003",
        "tgn:7003685",
        "tgn:7000084",
        "tgn:7029392"
    ],
    "tgn:id":7204577,
    "tgn:name":"B\u00f6rnichen",
    "tgn:placetype":[
        "aat:300008347"
    ]
},
  "bbox": [],
  "geometry": {"coordinates":[13.166667,50.866667],"type":"Point"}
}