{
  "id": 4000851,
  "type": "Feature",
  "properties": {
    "tgn:hierarchy":[
        "tgn:4000851",
        "tgn:7003821",
        "tgn:1000003",
        "tgn:1000090",
        "tgn:7029392"
    ],
    "tgn:id":4000851,
    "tgn:name":"Arraiolos",
    "tgn:placetype":[
        "aat:300008347",
        "aat:300387218"
    ]
},
  "bbox": [],
  "geometry": {"coordinates":[-7.984,38.723],"type":"Point"}
}