{
  "id": 2424708,
  "type": "Feature",
  "properties": {
    "tgn:hierarchy":[
        "tgn:2424708",
        "tgn:2002365",
        "tgn:1000001",
        "tgn:7012149",
        "tgn:7007923",
        "tgn:7029392"
    ],
    "tgn:id":2424708,
    "tgn:name":"Johnson Creek",
    "tgn:placetype":[
        "aat:300008706"
    ]
},
  "bbox": [],
  "geometry": {"coordinates":[-105.45,41.7833],"type":"Point"}
}