{
  "id": 7101150,
  "type": "Feature",
  "properties": {
    "tgn:hierarchy":[
        "tgn:7101150",
        "tgn:7003692",
        "tgn:1000003",
        "tgn:7000084",
        "tgn:7029392"
    ],
    "tgn:id":7101150,
    "tgn:name":"Sauggart",
    "tgn:placetype":[
        "aat:300008347"
    ]
},
  "bbox": [],
  "geometry": {"coordinates":[9.633333,48.166667],"type":"Point"}
}