{
  "id": 2173177,
  "type": "Feature",
  "properties": {
    "tgn:hierarchy":[
        "tgn:2173177",
        "tgn:1000001",
        "tgn:7012149",
        "tgn:2002118",
        "tgn:7007827",
        "tgn:7029392"
    ],
    "tgn:id":2173177,
    "tgn:name":"Bingham Tunnel",
    "tgn:placetype":[
        "aat:300000390"
    ]
},
  "bbox": [],
  "geometry": {"coordinates":[-112.0833,40.5167],"type":"Point"}
}