<<<<<<< HEAD
{
  "id": 7480892,
  "type": "Feature",
  "properties": {
    "tgn:hierarchy":[
        "tgn:7480892",
        "tgn:1000004",
        "tgn:7490934",
        "tgn:1000141",
        "tgn:7029392"
    ],
    "tgn:id":7480892,
    "tgn:name":"Tongxin Qiao",
    "tgn:placetype":[
        "aat:300007836"
    ]
},
  "bbox": [],
  "geometry": {"coordinates":[120.36502,23.06007],"type":"Point"}
}
=======
{"geometry":{"type":"Point","coordinates":[120.365020,23.060070]},"type":"Feature","properties":{"hierarchy":["tgn:7480892","tgn:1000004","tgn:7490934","tgn:1000141","tgn:7029392"],"placetype":["aat:300007836"],"id":7480892,"name:xx":"Tongxin Qiao"}}
>>>>>>> 03f74aca74312dbeaf24d7e61306dd6a786dc3d0
