{
  "id": 7547022,
  "type": "Feature",
  "properties": {
    "tgn:hierarchy":[
        "tgn:7547022",
        "tgn:1000004",
        "tgn:7000198",
        "tgn:1001895",
        "tgn:7029392"
    ],
    "tgn:id":7547022,
    "tgn:name:en":"Bembla River",
    "tgn:placetype":[
        "aat:300008699"
    ]
},
  "bbox": [],
  "geometry": {"coordinates":[78.266667,20.583333],"type":"Point"}
}