<<<<<<< HEAD
{
  "id": 7111701,
  "type": "Feature",
  "properties": {
    "tgn:hierarchy":[
        "tgn:7111701",
        "tgn:7003669",
        "tgn:1000003",
        "tgn:7000084",
        "tgn:7029392"
    ],
    "tgn:id":7111701,
    "tgn:name":"Richt",
    "tgn:placetype":[
        "aat:300008347"
    ]
},
  "bbox": [],
  "geometry": {"coordinates":[12.2,49.383333],"type":"Point"}
}
=======
{"geometry":{"type":"Point","coordinates":[12.200000,49.383333]},"type":"Feature","properties":{"hierarchy":["tgn:7111701","tgn:7003669","tgn:1000003","tgn:7000084","tgn:7029392"],"placetype":["aat:300008347"],"id":7111701,"name:xx":"Richt"}}
>>>>>>> 03f74aca74312dbeaf24d7e61306dd6a786dc3d0
