<<<<<<< HEAD
{
  "id": 2257253,
  "type": "Feature",
  "properties": {
    "tgn:hierarchy":[
        "tgn:2257253",
        "tgn:1000001",
        "tgn:7012149",
        "tgn:1002399",
        "tgn:7007710",
        "tgn:7029392"
    ],
    "tgn:id":2257253,
    "tgn:name":"Corner, The",
    "tgn:placetype":[
        "aat:300008761"
    ]
},
  "bbox": [],
  "geometry": {"coordinates":[-78.05,39.7667],"type":"Point"}
}
=======
{"geometry":{"type":"Point","coordinates":[-78.050000,39.766700]},"type":"Feature","properties":{"hierarchy":["tgn:2257253","tgn:1000001","tgn:7012149","tgn:1002399","tgn:7007710","tgn:7029392"],"placetype":["aat:300008761"],"id":2257253,"name:xx":"Corner, The"}}
>>>>>>> 03f74aca74312dbeaf24d7e61306dd6a786dc3d0
