{
  "id": 7280144,
  "type": "Feature",
  "properties": {
    "tgn:hierarchy":[
        "tgn:7280144",
        "tgn:1001702",
        "tgn:1000049",
        "tgn:1000002",
        "tgn:7029392"
    ],
    "tgn:id":7280144,
    "tgn:name":"Redondo, Islote",
    "tgn:placetype":[
        "aat:300008791"
    ]
},
  "bbox": [],
  "geometry": {"coordinates":[-70.166667,-55.066667],"type":"Point"}
}