{
  "id": 2120816,
  "type": "Feature",
  "properties": {
    "tgn:hierarchy":[
        "tgn:2120816",
        "tgn:1000001",
        "tgn:1002421",
        "tgn:7012149",
        "tgn:7007922",
        "tgn:7029392"
    ],
    "tgn:id":2120816,
    "tgn:name":"Brooklyn",
    "tgn:placetype":[
        "aat:300008347"
    ]
},
  "bbox": [],
  "geometry": {"coordinates":[-89.3667,42.85],"type":"Point"}
}