{
  "id": 7290317,
  "type": "Feature",
  "properties": {
    "tgn:hierarchy":[
        "tgn:7290317",
        "tgn:1001630",
        "tgn:1000049",
        "tgn:1000002",
        "tgn:7029392"
    ],
    "tgn:id":7290317,
    "tgn:name":"Do\u00f1a In\u00e9s Chica, Sierra",
    "tgn:placetype":[
        "aat:300008795"
    ]
},
  "bbox": [],
  "geometry": {"coordinates":[-69.416667,-26.066667],"type":"Point"}
}