{
  "id": 2708008,
  "type": "Feature",
  "properties": {
    "tgn:hierarchy":[
        "tgn:2708008",
        "tgn:1000001",
        "tgn:7012149",
        "tgn:2001277",
        "tgn:7007524",
        "tgn:7029392"
    ],
    "tgn:id":2708008,
    "tgn:name":"Swiftcurrent Ridge",
    "tgn:placetype":[
        "aat:300266640"
    ]
},
  "bbox": [],
  "geometry": {"coordinates":[-113.4667,48.85],"type":"Point"}
}