{
  "id": 2612461,
  "type": "Feature",
  "properties": {
    "tgn:hierarchy":[
        "tgn:2612461",
        "tgn:1000001",
        "tgn:2001786",
        "tgn:7012149",
        "tgn:7007713",
        "tgn:7029392"
    ],
    "tgn:id":2612461,
    "tgn:name":"Red Valley",
    "tgn:placetype":[
        "aat:300008761"
    ]
},
  "bbox": [],
  "geometry": {"coordinates":[-103.4167,43.6167],"type":"Point"}
}