{
  "id": 2190543,
  "type": "Feature",
  "properties": {
    "tgn:hierarchy":[
        "tgn:2190543",
        "tgn:1000001",
        "tgn:7012149",
        "tgn:2001526",
        "tgn:7007709",
        "tgn:7029392"
    ],
    "tgn:id":2190543,
    "tgn:name":"Box Point",
    "tgn:placetype":[
        "aat:300008850"
    ]
},
  "bbox": [],
  "geometry": {"coordinates":[-76.6333,35.1667],"type":"Point"}
}