{
  "id": 7187592,
  "type": "Feature",
  "properties": {
    "tgn:hierarchy":[
        "tgn:7187592",
        "tgn:7003669",
        "tgn:1000003",
        "tgn:7000084",
        "tgn:7029392"
    ],
    "tgn:id":7187592,
    "tgn:name":"Etzenberg",
    "tgn:placetype":[
        "aat:300008777"
    ]
},
  "bbox": [],
  "geometry": {"coordinates":[11.916667,48.933333],"type":"Point"}
}