<<<<<<< HEAD
{
  "id": 7057934,
  "type": "Feature",
  "properties": {
    "tgn:hierarchy":[
        "tgn:7057934",
        "tgn:1000003",
        "tgn:7003142",
        "tgn:7003236",
        "tgn:1000080",
        "tgn:7029392"
    ],
    "tgn:id":7057934,
    "tgn:name":"Brizzolara",
    "tgn:placetype":[
        "aat:300008347"
    ]
},
  "bbox": [],
  "geometry": {"coordinates":[9.366667,44.433333],"type":"Point"}
}
=======
{"geometry":{"type":"Point","coordinates":[9.366667,44.433333]},"type":"Feature","properties":{"hierarchy":["tgn:7057934","tgn:1000003","tgn:7003142","tgn:7003236","tgn:1000080","tgn:7029392"],"placetype":["aat:300008347"],"id":7057934,"name:xx":"Brizzolara"}}
>>>>>>> 03f74aca74312dbeaf24d7e61306dd6a786dc3d0
