{
  "id": 7076840,
  "type": "Feature",
  "properties": {
    "tgn:hierarchy":[
        "tgn:7076840",
        "tgn:1000003",
        "tgn:7003676",
        "tgn:7000084",
        "tgn:7029392"
    ],
    "tgn:id":7076840,
    "tgn:name":"Kreisfreie Stadt Oldenburg",
    "tgn:placetype":[
        "aat:300387198"
    ]
},
  "bbox": [],
  "geometry": {"coordinates":[8.235278,53.155],"type":"Point"}
}