{
  "id": 2280780,
  "type": "Feature",
  "properties": {
    "tgn:hierarchy":[
        "tgn:2280780",
        "tgn:1000001",
        "tgn:7012149",
        "tgn:7020792",
        "tgn:7007524",
        "tgn:7029392"
    ],
    "tgn:id":2280780,
    "tgn:name":"Deep Creek",
    "tgn:placetype":[
        "aat:300008706"
    ]
},
  "bbox": [],
  "geometry": {"coordinates":[-113.0667,45.9667],"type":"Point"}
}