{
  "id": 2433636,
  "type": "Feature",
  "properties": {
    "tgn:hierarchy":[
        "tgn:2433636",
        "tgn:7006450",
        "tgn:1000001",
        "tgn:7012149",
        "tgn:2000082",
        "tgn:7029392"
    ],
    "tgn:id":2433636,
    "tgn:name":"Kelly Cove",
    "tgn:placetype":[
        "aat:300132316"
    ]
},
  "bbox": [],
  "geometry": {"coordinates":[-133.6333,55.45],"type":"Point"}
}