{
  "id": 7441448,
  "type": "Feature",
  "properties": {
    "tgn:hierarchy":[
        "tgn:7441448",
        "tgn:1001836",
        "tgn:1000001",
        "tgn:7005560",
        "tgn:7029392"
    ],
    "tgn:id":7441448,
    "tgn:name":"San Nicol\u00e1s",
    "tgn:placetype":[
        "aat:300008347"
    ]
},
  "bbox": [],
  "geometry": {"coordinates":[-112.116667,26.85],"type":"Point"}
}