{
  "id": 2385773,
  "type": "Feature",
  "properties": {
    "tgn:hierarchy":[
        "tgn:2385773",
        "tgn:7006450",
        "tgn:1000001",
        "tgn:7012149",
        "tgn:2000086",
        "tgn:7029392"
    ],
    "tgn:id":2385773,
    "tgn:name":"Heney Creek",
    "tgn:placetype":[
        "aat:300008706"
    ]
},
  "bbox": [],
  "geometry": {"coordinates":[-145.7167,60.5167],"type":"Point"}
}