{
  "id": 7531558,
  "type": "Feature",
  "properties": {
    "tgn:hierarchy":[
        "tgn:7531558",
        "tgn:7001242",
        "tgn:7016833",
        "tgn:7001312",
        "tgn:7029392"
    ],
    "tgn:id":7531558,
    "tgn:name:en":"Kafr a\u0163 \u0162\u016bkh\u012b",
    "tgn:placetype":[
        "aat:300008347"
    ]
},
  "bbox": [],
  "geometry": {"coordinates":[30.998002,30.903059],"type":"Point"}
}