{
  "id": 2146404,
  "type": "Feature",
  "properties": {
    "tgn:hierarchy":[
        "tgn:2146404",
        "tgn:1000001",
        "tgn:7012149",
        "tgn:7007709",
        "tgn:7029392"
    ],
    "tgn:id":2146404,
    "tgn:name":"Balsam Corner",
    "tgn:placetype":[
        "aat:300008798"
    ]
},
  "bbox": [],
  "geometry": {"coordinates":[-83.1667,35.6667],"type":"Point"}
}