{
  "id": 2549507,
  "type": "Feature",
  "properties": {
    "tgn:hierarchy":[
        "tgn:2549507",
        "tgn:1000001",
        "tgn:7012149",
        "tgn:2001447",
        "tgn:7007566",
        "tgn:7029392"
    ],
    "tgn:id":2549507,
    "tgn:name":"North Spring",
    "tgn:placetype":[
        "aat:300008697"
    ]
},
  "bbox": [],
  "geometry": {"coordinates":[-105.75,33.1833],"type":"Point"}
}