{
  "id": 2719868,
  "type": "Feature",
  "properties": {
    "tgn:hierarchy":[
        "tgn:2719868",
        "tgn:1000001",
        "tgn:7012149",
        "tgn:2002291",
        "tgn:7013961",
        "tgn:7029392"
    ],
    "tgn:id":2719868,
    "tgn:name":"Three Spring Run",
    "tgn:placetype":[
        "aat:300008699"
    ]
},
  "bbox": [],
  "geometry": {"coordinates":[-79.6167,38.9667],"type":"Point"}
}