{
  "id": 2320124,
  "type": "Feature",
  "properties": {
    "tgn:hierarchy":[
        "tgn:2320124",
        "tgn:1000001",
        "tgn:7012149",
        "tgn:2001217",
        "tgn:7007523",
        "tgn:7029392"
    ],
    "tgn:id":2320124,
    "tgn:name":"Evans Mountain",
    "tgn:placetype":[
        "aat:300008798"
    ]
},
  "bbox": [],
  "geometry": {"coordinates":[-90.45,37.5833],"type":"Point"}
}