{
  "id": 2041608,
  "type": "Feature",
  "properties": {
    "tgn:hierarchy":[
        "tgn:2041608",
        "tgn:1000001",
        "tgn:7012149",
        "tgn:2000804",
        "tgn:7007255",
        "tgn:7029392"
    ],
    "tgn:id":2041608,
    "tgn:name":"Thelma",
    "tgn:placetype":[
        "aat:300008347"
    ]
},
  "bbox": [],
  "geometry": {"coordinates":[-82.75,37.8167],"type":"Point"}
}