{
  "id": 7534480,
  "type": "Feature",
  "properties": {
    "tgn:hierarchy":[
        "tgn:7534480",
        "tgn:7001242",
        "tgn:7001105",
        "tgn:7016833",
        "tgn:7029392"
    ],
    "tgn:id":7534480,
    "tgn:name:en":"Majr\u016br Qushayshah, \u1e28aw\u1e11",
    "tgn:placetype":[
        "aat:300343519"
    ]
},
  "bbox": [],
  "geometry": {"coordinates":[31.15,29.316667],"type":"Point"}
}