{
  "id": 2256154,
  "type": "Feature",
  "properties": {
    "tgn:hierarchy":[
        "tgn:2256154",
        "tgn:1000001",
        "tgn:7012149",
        "tgn:2001515",
        "tgn:7007709",
        "tgn:7029392"
    ],
    "tgn:id":2256154,
    "tgn:name":"Copper Ridge",
    "tgn:placetype":[
        "aat:300266640"
    ]
},
  "bbox": [],
  "geometry": {"coordinates":[-83.5667,35.2333],"type":"Point"}
}