<<<<<<< HEAD
{
  "id": 2256154,
  "type": "Feature",
  "properties": {
    "tgn:hierarchy":[
        "tgn:2256154",
        "tgn:1000001",
        "tgn:7012149",
        "tgn:2001515",
        "tgn:7007709",
        "tgn:7029392"
    ],
    "tgn:id":2256154,
    "tgn:name":"Copper Ridge",
    "tgn:placetype":[
        "aat:300266640"
    ]
},
  "bbox": [],
  "geometry": {"coordinates":[-83.5667,35.2333],"type":"Point"}
}
=======
{"geometry":{"type":"Point","coordinates":[-83.566700,35.233300]},"type":"Feature","properties":{"hierarchy":["tgn:2256154","tgn:1000001","tgn:7012149","tgn:2001515","tgn:7007709","tgn:7029392"],"placetype":["aat:300266640"],"id":2256154,"name:xx":"Copper Ridge"}}
>>>>>>> 03f74aca74312dbeaf24d7e61306dd6a786dc3d0
