{
  "id": 7402253,
  "type": "Feature",
  "properties": {
    "tgn:hierarchy":[
        "tgn:7402253",
        "tgn:1000001",
        "tgn:7005599",
        "tgn:7005560",
        "tgn:7029392"
    ],
    "tgn:id":7402253,
    "tgn:name":"Mesa de Rodeo",
    "tgn:placetype":[
        "aat:300008347"
    ]
},
  "bbox": [],
  "geometry": {"coordinates":[-96.55,19.644444],"type":"Point"}
}