{
  "id": 1140068,
  "type": "Feature",
  "properties": {
    "tgn:hierarchy":[
        "tgn:1140068",
        "tgn:1000004",
        "tgn:1001390",
        "tgn:1000111",
        "tgn:7029392"
    ],
    "tgn:id":1140068,
    "tgn:name":"Zhenjiang",
    "tgn:placetype":[
        "aat:300008347"
    ]
},
  "bbox": [],
  "geometry": {"coordinates":[125.4667,40.7333],"type":"Point"}
}