{
  "id": 7553274,
  "type": "Feature",
  "properties": {
    "tgn:hierarchy":[
        "tgn:7553274",
        "tgn:1000004",
        "tgn:7000198",
        "tgn:1001894",
        "tgn:7029392"
    ],
    "tgn:id":7553274,
    "tgn:name:en":"Nem\u0101war",
    "tgn:placetype":[
        "aat:300008347"
    ]
},
  "bbox": [],
  "geometry": {"coordinates":[76.981816,22.496455],"type":"Point"}
}