{
  "id": 1098159,
  "type": "Feature",
  "properties": {
    "tgn:hierarchy":[
        "tgn:1098159",
        "tgn:7000490",
        "tgn:1000006",
        "tgn:7001831",
        "tgn:7029392"
    ],
    "tgn:id":1098159,
    "tgn:name":"Second Valley",
    "tgn:placetype":[
        "aat:300008347"
    ]
},
  "bbox": [],
  "geometry": {"coordinates":[138.2333,-35.55],"type":"Point"}
}