{
  "id": 2117622,
  "type": "Feature",
  "properties": {
    "tgn:hierarchy":[
        "tgn:2117622",
        "tgn:1000001",
        "tgn:2002254",
        "tgn:7012149",
        "tgn:7013961",
        "tgn:7029392"
    ],
    "tgn:id":2117622,
    "tgn:name":"Bunker Hill",
    "tgn:placetype":[
        "aat:300008347"
    ]
},
  "bbox": [],
  "geometry": {"coordinates":[-78.05,39.3333],"type":"Point"}
}