{
  "id": 2029789,
  "type": "Feature",
  "properties": {
    "tgn:hierarchy":[
        "tgn:2029789",
        "tgn:1000001",
        "tgn:7012149",
        "tgn:1002531",
        "tgn:7007251",
        "tgn:7029392"
    ],
    "tgn:id":2029789,
    "tgn:name":"Rainbow Hills",
    "tgn:placetype":[
        "aat:300008347"
    ]
},
  "bbox": [],
  "geometry": {"coordinates":[-88.3667,41.9167],"type":"Point"}
}