{
  "id": 7454583,
  "type": "Feature",
  "properties": {
    "tgn:hierarchy":[
        "tgn:7454583",
        "tgn:7002444",
        "tgn:1000003",
        "tgn:7008094",
        "tgn:7008591",
        "tgn:7029392"
    ],
    "tgn:id":7454583,
    "tgn:name:en":"Coppay",
    "tgn:placetype":[
        "aat:300008791"
    ]
},
  "bbox": [],
  "geometry": {"coordinates":[-7.166667,57.833333],"type":"Point"}
}