{
  "id": 1120808,
  "type": "Feature",
  "properties": {
    "tgn:hierarchy":[
        "tgn:1120808",
        "tgn:1003351",
        "tgn:1000004",
        "tgn:7018214",
        "tgn:7002435",
        "tgn:7029392"
    ],
    "tgn:id":1120808,
    "tgn:name":"Chara",
    "tgn:placetype":[
        "aat:300008707"
    ]
},
  "bbox": [],
  "geometry": {"coordinates":[118.25,58.9167],"type":"Point"}
}