{
  "id": 2117783,
  "type": "Feature",
  "properties": {
    "tgn:hierarchy":[
        "tgn:2117783",
        "tgn:1000001",
        "tgn:7012149",
        "tgn:2002271",
        "tgn:7013961",
        "tgn:7029392"
    ],
    "tgn:id":2117783,
    "tgn:name":"Churchville",
    "tgn:placetype":[
        "aat:300008347",
        "aat:300387210"
    ]
},
  "bbox": [],
  "geometry": {"coordinates":[-80.5833,39.0833],"type":"Point"}
}