{
  "id": 2711630,
  "type": "Feature",
  "properties": {
    "tgn:hierarchy":[
        "tgn:2711630",
        "tgn:1000001",
        "tgn:1002328",
        "tgn:7012149",
        "tgn:7007568",
        "tgn:7029392"
    ],
    "tgn:id":2711630,
    "tgn:name":"Tar Hollow",
    "tgn:placetype":[
        "aat:300008761"
    ]
},
  "bbox": [],
  "geometry": {"coordinates":[-75.2167,42.0167],"type":"Point"}
}