{
  "id": 2172172,
  "type": "Feature",
  "properties": {
    "tgn:hierarchy":[
        "tgn:2172172",
        "tgn:1000001",
        "tgn:7012149",
        "tgn:2000183",
        "tgn:7007157",
        "tgn:7029392"
    ],
    "tgn:id":2172172,
    "tgn:name":"Bighorn Mine",
    "tgn:placetype":[
        "aat:300000390"
    ]
},
  "bbox": [],
  "geometry": {"coordinates":[-117.8833,36.6833],"type":"Point"}
}