{
  "id": 7126688,
  "type": "Feature",
  "properties": {
    "tgn:hierarchy":[
        "tgn:7126688",
        "tgn:1000003",
        "tgn:7003677",
        "tgn:7000084",
        "tgn:7029392"
    ],
    "tgn:id":7126688,
    "tgn:name":"Nolting",
    "tgn:placetype":[
        "aat:300000206"
    ]
},
  "bbox": [],
  "geometry": {"coordinates":[8.466667,52.05],"type":"Point"}
}