{
  "id": 2127757,
  "type": "Feature",
  "properties": {
    "tgn:hierarchy":[
        "tgn:2127757",
        "tgn:1000001",
        "tgn:7006451",
        "tgn:7012149",
        "tgn:2000101",
        "tgn:7029392"
    ],
    "tgn:id":2127757,
    "tgn:name":"Alamo Number One Tank",
    "tgn:placetype":[
        "aat:300006191"
    ]
},
  "bbox": [],
  "geometry": {"coordinates":[-111.1667,33.2167],"type":"Point"}
}