{
  "id": 2312921,
  "type": "Feature",
  "properties": {
    "tgn:hierarchy":[
        "tgn:2312921",
        "tgn:1000001",
        "tgn:7012149",
        "tgn:2001446",
        "tgn:7007566",
        "tgn:7029392"
    ],
    "tgn:id":2312921,
    "tgn:name":"El Valle de los Boregos",
    "tgn:placetype":[
        "aat:300055621"
    ]
},
  "bbox": [],
  "geometry": {"coordinates":[-105.3333,36.1167],"type":"Point"}
}