{
  "id": 2177880,
  "type": "Feature",
  "properties": {
    "tgn:hierarchy":[
        "tgn:2177880",
        "tgn:1000001",
        "tgn:7012149",
        "tgn:7029392"
    ],
    "tgn:id":2177880,
    "tgn:name":"Blackamore Creek",
    "tgn:placetype":[
        "aat:300008706"
    ]
},
  "bbox": [],
  "geometry": {"coordinates":[-88.7333,36.5167],"type":"Point"}
}