{
  "id": 2068772,
  "type": "Feature",
  "properties": {
    "tgn:hierarchy":[
        "tgn:2068772",
        "tgn:1000001",
        "tgn:7012149",
        "tgn:1002604",
        "tgn:7007568",
        "tgn:7029392"
    ],
    "tgn:id":2068772,
    "tgn:name":"Dansville",
    "tgn:placetype":[
        "aat:300008347"
    ]
},
  "bbox": [],
  "geometry": {"coordinates":[-77.6833,42.55],"type":"Point"}
}