{
  "id": 7109863,
  "type": "Feature",
  "properties": {
    "tgn:hierarchy":[
        "tgn:7109863",
        "tgn:1000003",
        "tgn:7003676",
        "tgn:7000084",
        "tgn:7029392"
    ],
    "tgn:id":7109863,
    "tgn:name":"Rebenstein",
    "tgn:placetype":[
        "aat:300266640"
    ]
},
  "bbox": [],
  "geometry": {"coordinates":[9.516667,52.05],"type":"Point"}
}