{
  "id": 7120038,
  "type": "Feature",
  "properties": {
    "tgn:hierarchy":[
        "tgn:7120038",
        "tgn:1000003",
        "tgn:7003676",
        "tgn:7000084",
        "tgn:7029392"
    ],
    "tgn:id":7120038,
    "tgn:name":"Pferdeh\u00fctte",
    "tgn:placetype":[
        "aat:300000206"
    ]
},
  "bbox": [],
  "geometry": {"coordinates":[10.416667,53.266667],"type":"Point"}
}