<<<<<<< HEAD
{
  "id": 7022632,
  "type": "Feature",
  "properties": {
    "tgn:hierarchy":[
        "tgn:7022632",
        "tgn:1000001",
        "tgn:7016172",
        "tgn:7012149",
        "tgn:7029392"
    ],
    "tgn:id":7022632,
    "tgn:name":"Cranenest Creek",
    "tgn:placetype":[
        "aat:300008706"
    ]
},
  "bbox": [],
  "geometry": {"coordinates":[-93.2167,36.4],"type":"Point"}
}
=======
{"geometry":{"type":"Point","coordinates":[-93.216700,36.400000]},"type":"Feature","properties":{"hierarchy":["tgn:7022632","tgn:1000001","tgn:7016172","tgn:7012149","tgn:7029392"],"placetype":["aat:300008706"],"id":7022632,"name:xx":"Cranenest Creek"}}
>>>>>>> 03f74aca74312dbeaf24d7e61306dd6a786dc3d0
