{
  "id": 2002101,
  "type": "Feature",
  "properties": {
    "tgn:hierarchy":[
        "tgn:2002101",
        "tgn:1000001",
        "tgn:7012149",
        "tgn:7007827",
        "tgn:7029392"
    ],
    "tgn:id":2002101,
    "tgn:name":"Beaver",
    "tgn:placetype":[
        "aat:300387145",
        "aat:300000771"
    ]
},
  "bbox": [],
  "geometry": {"coordinates":[-113.1167,38.3667],"type":"Point"}
}