{
  "id": 2152391,
  "type": "Feature",
  "properties": {
    "tgn:hierarchy":[
        "tgn:2152391",
        "tgn:2000001",
        "tgn:7002659",
        "tgn:1000001",
        "tgn:7012149",
        "tgn:7029392"
    ],
    "tgn:id":2152391,
    "tgn:name":"Bay Minette Creek",
    "tgn:placetype":[
        "aat:300008706"
    ]
},
  "bbox": [],
  "geometry": {"coordinates":[-87.7833,30.85],"type":"Point"}
}