<<<<<<< HEAD
{
  "id": 2152391,
  "type": "Feature",
  "properties": {
    "tgn:hierarchy":[
        "tgn:2152391",
        "tgn:2000001",
        "tgn:7002659",
        "tgn:1000001",
        "tgn:7012149",
        "tgn:7029392"
    ],
    "tgn:id":2152391,
    "tgn:name":"Bay Minette Creek",
    "tgn:placetype":[
        "aat:300008706"
    ]
},
  "bbox": [],
  "geometry": {"coordinates":[-87.7833,30.85],"type":"Point"}
}
=======
{"geometry":{"type":"Point","coordinates":[-87.783300,30.850000]},"type":"Feature","properties":{"hierarchy":["tgn:2152391","tgn:2000001","tgn:7002659","tgn:1000001","tgn:7012149","tgn:7029392"],"placetype":["aat:300008706"],"id":2152391,"name:xx":"Bay Minette Creek"}}
>>>>>>> 03f74aca74312dbeaf24d7e61306dd6a786dc3d0
