{
  "id": 2100079,
  "type": "Feature",
  "properties": {
    "tgn:hierarchy":[
        "tgn:2100079",
        "tgn:1000001",
        "tgn:7012149",
        "tgn:7022542",
        "tgn:7007825",
        "tgn:7029392"
    ],
    "tgn:id":2100079,
    "tgn:name":"Liberty Hill",
    "tgn:placetype":[
        "aat:300008347",
        "aat:300387210"
    ]
},
  "bbox": [],
  "geometry": {"coordinates":[-84.4333,35.3667],"type":"Point"}
}