{
  "id": 2613218,
  "type": "Feature",
  "properties": {
    "tgn:hierarchy":[
        "tgn:2613218",
        "tgn:1000001",
        "tgn:7012149",
        "tgn:1003005",
        "tgn:7007520",
        "tgn:7029392"
    ],
    "tgn:id":2613218,
    "tgn:name":"Reeck Drain",
    "tgn:placetype":[
        "aat:300008699"
    ]
},
  "bbox": [],
  "geometry": {"coordinates":[-83.2167,42.2667],"type":"Point"}
}