{
  "id": 2489372,
  "type": "Feature",
  "properties": {
    "tgn:hierarchy":[
        "tgn:2489372",
        "tgn:1000001",
        "tgn:7012149",
        "tgn:1002509",
        "tgn:7007520",
        "tgn:7029392"
    ],
    "tgn:id":2489372,
    "tgn:name":"Malay Lake",
    "tgn:placetype":[
        "aat:300008680"
    ]
},
  "bbox": [],
  "geometry": {"coordinates":[-84.35,42.35],"type":"Point"}
}