{
  "id": 2052202,
  "type": "Feature",
  "properties": {
    "tgn:hierarchy":[
        "tgn:2052202",
        "tgn:1000001",
        "tgn:7012149",
        "tgn:1002737",
        "tgn:7007520",
        "tgn:7029392"
    ],
    "tgn:id":2052202,
    "tgn:name":"Holly",
    "tgn:placetype":[
        "aat:300008347"
    ]
},
  "bbox": [],
  "geometry": {"coordinates":[-83.6167,42.7833],"type":"Point"}
}