{
  "id": 7188478,
  "type": "Feature",
  "properties": {
    "tgn:hierarchy":[
        "tgn:7188478",
        "tgn:1000003",
        "tgn:7003677",
        "tgn:7000084",
        "tgn:7029392"
    ],
    "tgn:id":7188478,
    "tgn:name":"Bahnhof Essen-Rellinghausen",
    "tgn:placetype":[
        "aat:300007783"
    ]
},
  "bbox": [],
  "geometry": {"coordinates":[7.05,51.433333],"type":"Point"}
}