{
  "id": 2771203,
  "type": "Feature",
  "properties": {
    "tgn:hierarchy":[
        "tgn:2771203",
        "tgn:1000001",
        "tgn:7012149",
        "tgn:2002291",
        "tgn:7013961",
        "tgn:7029392"
    ],
    "tgn:id":2771203,
    "tgn:name":"Wildcat Ridge",
    "tgn:placetype":[
        "aat:300266640"
    ]
},
  "bbox": [],
  "geometry": {"coordinates":[-79.75,38.9833],"type":"Point"}
}