{
  "id": 2142692,
  "type": "Feature",
  "properties": {
    "tgn:hierarchy":[
        "tgn:2142692",
        "tgn:1000001",
        "tgn:1002395",
        "tgn:7012149",
        "tgn:7007251",
        "tgn:7029392"
    ],
    "tgn:id":2142692,
    "tgn:name":"Badger Creek",
    "tgn:placetype":[
        "aat:300008706"
    ]
},
  "bbox": [],
  "geometry": {"coordinates":[-90.4167,40.3833],"type":"Point"}
}