{
  "id": 2158352,
  "type": "Feature",
  "properties": {
    "tgn:hierarchy":[
        "tgn:2158352",
        "tgn:1002933",
        "tgn:1000001",
        "tgn:7012149",
        "tgn:7007239",
        "tgn:7029392"
    ],
    "tgn:id":2158352,
    "tgn:name":"Beaverdam Branch",
    "tgn:placetype":[
        "aat:300008699"
    ]
},
  "bbox": [],
  "geometry": {"coordinates":[-75.1167,38.7167],"type":"Point"}
}