<<<<<<< HEAD
{
  "id": 2765752,
  "type": "Feature",
  "properties": {
    "tgn:hierarchy":[
        "tgn:2765752",
        "tgn:1000001",
        "tgn:7012149",
        "tgn:1002392",
        "tgn:7007157",
        "tgn:7029392"
    ],
    "tgn:id":2765752,
    "tgn:name":"White Deer Creek",
    "tgn:placetype":[
        "aat:300008706"
    ]
},
  "bbox": [],
  "geometry": {"coordinates":[-119.15,36.8333],"type":"Point"}
}
=======
{"geometry":{"type":"Point","coordinates":[-119.150000,36.833300]},"type":"Feature","properties":{"hierarchy":["tgn:2765752","tgn:1000001","tgn:7012149","tgn:1002392","tgn:7007157","tgn:7029392"],"placetype":["aat:300008706"],"id":2765752,"name:xx":"White Deer Creek"}}
>>>>>>> 03f74aca74312dbeaf24d7e61306dd6a786dc3d0
