{
  "id": 7592108,
  "type": "Feature",
  "properties": {
    "tgn:hierarchy":[
        "tgn:7592108",
        "tgn:1000004",
        "tgn:7000198",
        "tgn:7031786",
        "tgn:7029392"
    ],
    "tgn:id":7592108,
    "tgn:name:en":"Ogip\u0101ni Rao",
    "tgn:placetype":[
        "aat:300008699"
    ]
},
  "bbox": [],
  "geometry": {"coordinates":[77.881788,30.31246],"type":"Point"}
}