{
  "id": 7090774,
  "type": "Feature",
  "properties": {
    "tgn:hierarchy":[
        "tgn:7090774",
        "tgn:7003669",
        "tgn:1000003",
        "tgn:7000084",
        "tgn:7029392"
    ],
    "tgn:id":7090774,
    "tgn:name":"Unterschochen",
    "tgn:placetype":[
        "aat:300000206"
    ]
},
  "bbox": [],
  "geometry": {"coordinates":[10.383333,47.883333],"type":"Point"}
}