{
  "id": 7418262,
  "type": "Feature",
  "properties": {
    "tgn:hierarchy":[
        "tgn:7418262",
        "tgn:1000001",
        "tgn:7005589",
        "tgn:7005560",
        "tgn:7029392"
    ],
    "tgn:id":7418262,
    "tgn:name:es":"Gallos Gueros",
    "tgn:placetype":[
        "aat:300008347"
    ]
},
  "bbox": [],
  "geometry": {"coordinates":[-99.343611,25.109167],"type":"Point"}
}