<<<<<<< HEAD
{
  "id": 7487085,
  "type": "Feature",
  "properties": {
    "tgn:hierarchy":[
        "tgn:7487085",
        "tgn:7488858",
        "tgn:1000004",
        "tgn:1000141",
        "tgn:7029392"
    ],
    "tgn:id":7487085,
    "tgn:name":"Ganzilin",
    "tgn:placetype":[
        "aat:300008347"
    ]
},
  "bbox": [],
  "geometry": {"coordinates":[120.82992,23.801687],"type":"Point"}
}
=======
{"geometry":{"type":"Point","coordinates":[120.829920,23.801687]},"type":"Feature","properties":{"hierarchy":["tgn:7487085","tgn:7488858","tgn:1000004","tgn:1000141","tgn:7029392"],"placetype":["aat:300008347"],"id":7487085,"name:xx":"Ganzilin"}}
>>>>>>> 03f74aca74312dbeaf24d7e61306dd6a786dc3d0
