{
  "id": 7369950,
  "type": "Feature",
  "properties": {
    "tgn:hierarchy":[
        "tgn:7369950",
        "tgn:7005587",
        "tgn:1000001",
        "tgn:7005560",
        "tgn:7029392"
    ],
    "tgn:id":7369950,
    "tgn:name":"Huehuechoca",
    "tgn:placetype":[
        "aat:300008347"
    ]
},
  "bbox": [],
  "geometry": {"coordinates":[-98.316667,19.75],"type":"Point"}
}