{
  "id": 2575607,
  "type": "Feature",
  "properties": {
    "tgn:hierarchy":[
        "tgn:2575607",
        "tgn:1000001",
        "tgn:7016172",
        "tgn:7012149",
        "tgn:2000163",
        "tgn:7029392"
    ],
    "tgn:id":2575607,
    "tgn:name":"Peppers Lake",
    "tgn:placetype":[
        "aat:300008347"
    ]
},
  "bbox": [],
  "geometry": {"coordinates":[-91.4333,34.7333],"type":"Point"}
}