{
  "id": 2288659,
  "type": "Feature",
  "properties": {
    "tgn:hierarchy":[
        "tgn:2288659",
        "tgn:1000001",
        "tgn:7012149",
        "tgn:7007158",
        "tgn:2000245",
        "tgn:7029392"
    ],
    "tgn:id":2288659,
    "tgn:name":"Ditch Creek",
    "tgn:placetype":[
        "aat:300008706"
    ]
},
  "bbox": [],
  "geometry": {"coordinates":[-106.8333,40.6167],"type":"Point"}
}