{
  "id": 7077577,
  "type": "Feature",
  "properties": {
    "tgn:hierarchy":[
        "tgn:7077577",
        "tgn:1000003",
        "tgn:7003689",
        "tgn:7000084",
        "tgn:7029392"
    ],
    "tgn:id":7077577,
    "tgn:name":"Zwischen-Berg",
    "tgn:placetype":[
        "aat:300008777"
    ]
},
  "bbox": [],
  "geometry": {"coordinates":[10.716667,51.566667],"type":"Point"}
}