{
  "id": 7505741,
  "type": "Feature",
  "properties": {
    "tgn:hierarchy":[
        "tgn:7505741",
        "tgn:1009227",
        "tgn:1000226",
        "tgn:7520095",
        "tgn:1000006",
        "tgn:7029392"
    ],
    "tgn:id":7505741,
    "tgn:name:en":"Torrent Bay",
    "tgn:placetype":[
        "aat:300132316"
    ]
},
  "bbox": [],
  "geometry": {"coordinates":[173.05,-40.95],"type":"Point"}
}