{
  "id": 2246838,
  "type": "Feature",
  "properties": {
    "tgn:hierarchy":[
        "tgn:2246838",
        "tgn:1000001",
        "tgn:7012149",
        "tgn:2002090",
        "tgn:7007826",
        "tgn:7029392"
    ],
    "tgn:id":2246838,
    "tgn:name":"Cochio Tank",
    "tgn:placetype":[
        "aat:300006191"
    ]
},
  "bbox": [],
  "geometry": {"coordinates":[-99.65,27.9333],"type":"Point"}
}