{
  "id": 7282085,
  "type": "Feature",
  "properties": {
    "tgn:hierarchy":[
        "tgn:7282085",
        "tgn:1001623",
        "tgn:1000049",
        "tgn:1000002",
        "tgn:7029392"
    ],
    "tgn:id":7282085,
    "tgn:name":"Salto, Lago",
    "tgn:placetype":[
        "aat:300008680"
    ]
},
  "bbox": [],
  "geometry": {"coordinates":[-72.616667,-48.366667],"type":"Point"}
}