{
  "id": 2071370,
  "type": "Feature",
  "properties": {
    "tgn:hierarchy":[
        "tgn:2071370",
        "tgn:1000001",
        "tgn:7012149",
        "tgn:7014287",
        "tgn:7007568",
        "tgn:7029392"
    ],
    "tgn:id":2071370,
    "tgn:name":"North Western",
    "tgn:placetype":[
        "aat:300008347"
    ]
},
  "bbox": [],
  "geometry": {"coordinates":[-75.35,43.3333],"type":"Point"}
}