{
  "id": 1065382,
  "type": "Feature",
  "properties": {
    "tgn:hierarchy":[
        "tgn:1065382",
        "tgn:7016612",
        "tgn:1000004",
        "tgn:1001493",
        "tgn:7029392"
    ],
    "tgn:id":1065382,
    "tgn:name":"Bazar-e Panjva'i",
    "tgn:placetype":[
        "aat:300008347"
    ]
},
  "bbox": [],
  "geometry": {"coordinates":[65.45,31.5333],"type":"Point"}
}