{
  "id": 7556116,
  "type": "Feature",
  "properties": {
    "tgn:hierarchy":[
        "tgn:7556116",
        "tgn:1000004",
        "tgn:7000198",
        "tgn:7016883",
        "tgn:7029392"
    ],
    "tgn:id":7556116,
    "tgn:name:en":"Rurka Kal\u0101n",
    "tgn:placetype":[
        "aat:300008347"
    ]
},
  "bbox": [],
  "geometry": {"coordinates":[75.699597,31.122767],"type":"Point"}
}