{
  "id": 2465586,
  "type": "Feature",
  "properties": {
    "tgn:hierarchy":[
        "tgn:2465586",
        "tgn:1000001",
        "tgn:1002207",
        "tgn:7012149",
        "tgn:7007240",
        "tgn:7029392"
    ],
    "tgn:id":2465586,
    "tgn:name":"Lone Palm Head",
    "tgn:placetype":[
        "aat:300008791"
    ]
},
  "bbox": [],
  "geometry": {"coordinates":[-80.8167,26.1833],"type":"Point"}
}