{
  "id": 1030033,
  "type": "Feature",
  "properties": {
    "tgn:hierarchy":[
        "tgn:1030033",
        "tgn:7002445",
        "tgn:7019027",
        "tgn:1000003",
        "tgn:7029506",
        "tgn:7008591",
        "tgn:7029392"
    ],
    "tgn:id":1030033,
    "tgn:name:en":"Meriden",
    "tgn:placetype":[
        "aat:300008347"
    ]
},
  "bbox": [],
  "geometry": {"coordinates":[-1.616667,52.433333],"type":"Point"}
}