{
  "id": 7554876,
  "type": "Feature",
  "properties": {
    "tgn:hierarchy":[
        "tgn:7554876",
        "tgn:7001819",
        "tgn:1000004",
        "tgn:7000198",
        "tgn:7029392"
    ],
    "tgn:id":7554876,
    "tgn:name:en":"Mi-chi-tun",
    "tgn:placetype":[
        "aat:300008347"
    ]
},
  "bbox": [],
  "geometry": {"coordinates":[93.616667,28.666667],"type":"Point"}
}