{
  "id": 7464148,
  "type": "Feature",
  "properties": {
    "tgn:hierarchy":[
        "tgn:7464148",
        "tgn:7002444",
        "tgn:1000003",
        "tgn:7008094",
        "tgn:7008591",
        "tgn:7029392"
    ],
    "tgn:id":7464148,
    "tgn:name:en":"Breaclete",
    "tgn:placetype":[
        "aat:300008347"
    ]
},
  "bbox": [],
  "geometry": {"coordinates":[-6.833333,58.233333],"type":"Point"}
}