{
  "id": 2683606,
  "type": "Feature",
  "properties": {
    "tgn:hierarchy":[
        "tgn:2683606",
        "tgn:1000001",
        "tgn:7006451",
        "tgn:7012149",
        "tgn:2000099",
        "tgn:7029392"
    ],
    "tgn:id":2683606,
    "tgn:name":"Spearhead Mesa",
    "tgn:placetype":[
        "aat:300008798"
    ]
},
  "bbox": [],
  "geometry": {"coordinates":[-110.0333,36.95],"type":"Point"}
}