{
  "id": 7072278,
  "type": "Feature",
  "properties": {
    "tgn:hierarchy":[
        "tgn:7072278",
        "tgn:7003669",
        "tgn:1000003",
        "tgn:7000084",
        "tgn:7029392"
    ],
    "tgn:id":7072278,
    "tgn:name":"Sulzberg",
    "tgn:placetype":[
        "aat:300008795"
    ]
},
  "bbox": [],
  "geometry": {"coordinates":[12.066667,47.75],"type":"Point"}
}