{
  "id": 2283856,
  "type": "Feature",
  "properties": {
    "tgn:hierarchy":[
        "tgn:2283856",
        "tgn:1000001",
        "tgn:7012149",
        "tgn:2000637",
        "tgn:7007253",
        "tgn:7029392"
    ],
    "tgn:id":2283856,
    "tgn:name":"Denman Woods",
    "tgn:placetype":[
        "aat:300008863"
    ]
},
  "bbox": [],
  "geometry": {"coordinates":[-93.65,41.5667],"type":"Point"}
}