{
  "id": 1012548,
  "type": "Feature",
  "properties": {
    "tgn:hierarchy":[
        "tgn:1012548",
        "tgn:1000004",
        "tgn:1001611",
        "tgn:1000135",
        "tgn:7029392"
    ],
    "tgn:id":1012548,
    "tgn:name":"Tambulian Point",
    "tgn:placetype":[
        "aat:300386846"
    ]
},
  "bbox": [],
  "geometry": {"coordinates":[123.45,7.3667],"type":"Point"}
}