{
  "id": 2206221,
  "type": "Feature",
  "properties": {
    "tgn:hierarchy":[
        "tgn:2206221",
        "tgn:1000001",
        "tgn:7012149",
        "tgn:7029392"
    ],
    "tgn:id":2206221,
    "tgn:name":"Bullard Canyon",
    "tgn:placetype":[
        "aat:300008761"
    ]
},
  "bbox": [],
  "geometry": {"coordinates":[-109.0833,33.3167],"type":"Point"}
}