{
  "id": 2298763,
  "type": "Feature",
  "properties": {
    "tgn:hierarchy":[
        "tgn:2298763",
        "tgn:7006450",
        "tgn:1000001",
        "tgn:7012149",
        "tgn:2000079",
        "tgn:7029392"
    ],
    "tgn:id":2298763,
    "tgn:name":"Dryas Cone",
    "tgn:placetype":[
        "aat:300008798"
    ]
},
  "bbox": [],
  "geometry": {"coordinates":[-163.6333,65.5667],"type":"Point"}
}