{
  "id": 7567263,
  "type": "Feature",
  "properties": {
    "tgn:hierarchy":[
        "tgn:7567263",
        "tgn:1000004",
        "tgn:7000198",
        "tgn:7001797",
        "tgn:7029392"
    ],
    "tgn:id":7567263,
    "tgn:name:en":"Talabur",
    "tgn:placetype":[
        "aat:300008347"
    ]
},
  "bbox": [],
  "geometry": {"coordinates":[80.216389,12.8525],"type":"Point"}
}