{
  "id": 7433991,
  "type": "Feature",
  "properties": {
    "tgn:hierarchy":[
        "tgn:7433991",
        "tgn:1000001",
        "tgn:7005590",
        "tgn:7005560",
        "tgn:7029392"
    ],
    "tgn:id":7433991,
    "tgn:name":"Tiripet\u00edo",
    "tgn:placetype":[
        "aat:300008347"
    ]
},
  "bbox": [],
  "geometry": {"coordinates":[-101.333333,19.55],"type":"Point"}
}