{
  "id": 2022563,
  "type": "Feature",
  "properties": {
    "tgn:hierarchy":[
        "tgn:2022563",
        "tgn:2000296",
        "tgn:1000001",
        "tgn:7012149",
        "tgn:7007248",
        "tgn:7029392"
    ],
    "tgn:id":2022563,
    "tgn:name":"Coopers",
    "tgn:placetype":[
        "aat:300008347"
    ]
},
  "bbox": [],
  "geometry": {"coordinates":[-83.2833,32.9667],"type":"Point"}
}