{
  "id": 2734163,
  "type": "Feature",
  "properties": {
    "tgn:hierarchy":[
        "tgn:2734163",
        "tgn:1000001",
        "tgn:7012149",
        "tgn:2000839",
        "tgn:7007255",
        "tgn:7029392"
    ],
    "tgn:id":2734163,
    "tgn:name":"Turpin Branch",
    "tgn:placetype":[
        "aat:300008699"
    ]
},
  "bbox": [],
  "geometry": {"coordinates":[-84.7167,37.05],"type":"Point"}
}