<<<<<<< HEAD
{
  "id": 2337691,
  "type": "Feature",
  "properties": {
    "tgn:hierarchy":[
        "tgn:2337691",
        "tgn:7002659",
        "tgn:1000001",
        "tgn:7012149",
        "tgn:2000039",
        "tgn:7029392"
    ],
    "tgn:id":2337691,
    "tgn:name":"Fox Creek",
    "tgn:placetype":[
        "aat:300008706"
    ]
},
  "bbox": [],
  "geometry": {"coordinates":[-87.1333,34.5667],"type":"Point"}
}
=======
{"geometry":{"type":"Point","coordinates":[-87.133300,34.566700]},"type":"Feature","properties":{"hierarchy":["tgn:2337691","tgn:7002659","tgn:1000001","tgn:7012149","tgn:2000039","tgn:7029392"],"placetype":["aat:300008706"],"id":2337691,"name:xx":"Fox Creek"}}
>>>>>>> 03f74aca74312dbeaf24d7e61306dd6a786dc3d0
