{
  "id": 2107917,
  "type": "Feature",
  "properties": {
    "tgn:hierarchy":[
        "tgn:2107917",
        "tgn:1000001",
        "tgn:7012149",
        "tgn:1002898",
        "tgn:7007826",
        "tgn:7029392"
    ],
    "tgn:id":2107917,
    "tgn:name":"Swan",
    "tgn:placetype":[
        "aat:300008347"
    ]
},
  "bbox": [],
  "geometry": {"coordinates":[-95.3667,32.4333],"type":"Point"}
}