{
  "id": 2197823,
  "type": "Feature",
  "properties": {
    "tgn:hierarchy":[
        "tgn:2197823",
        "tgn:1000001",
        "tgn:7012149",
        "tgn:2002027",
        "tgn:7007826",
        "tgn:7029392"
    ],
    "tgn:id":2197823,
    "tgn:name":"Brown Number 3 Tank",
    "tgn:placetype":[
        "aat:300006191"
    ]
},
  "bbox": [],
  "geometry": {"coordinates":[-98.8833,28.2833],"type":"Point"}
}