{
  "id": 7434311,
  "type": "Feature",
  "properties": {
    "tgn:hierarchy":[
        "tgn:7434311",
        "tgn:1001853",
        "tgn:1000001",
        "tgn:7005560",
        "tgn:7029392"
    ],
    "tgn:id":7434311,
    "tgn:name":"Venado, Puerto del",
    "tgn:placetype":[
        "aat:300259572"
    ]
},
  "bbox": [],
  "geometry": {"coordinates":[-102.633333,26.366667],"type":"Point"}
}