{
  "id": 7258870,
  "type": "Feature",
  "properties": {
    "tgn:hierarchy":[
        "tgn:7258870",
        "tgn:1000003",
        "tgn:7003622",
        "tgn:7016845",
        "tgn:7029392"
    ],
    "tgn:id":7258870,
    "tgn:name:nl":"Boswachterij Bergen",
    "tgn:placetype":[
        "aat:300008187"
    ]
},
  "bbox": [],
  "geometry": {"coordinates":[6.033333,51.65],"type":"Point"}
}