{
  "id": 7482130,
  "type": "Feature",
  "properties": {
    "tgn:hierarchy":[
        "tgn:7482130",
        "tgn:1000004",
        "tgn:7489179",
        "tgn:1000141",
        "tgn:7029392"
    ],
    "tgn:id":7482130,
    "tgn:name":"Zuoyou Shan",
    "tgn:placetype":[
        "aat:300008798"
    ]
},
  "bbox": [],
  "geometry": {"coordinates":[121.772778,24.455833],"type":"Point"}
}