{
  "id": 2359062,
  "type": "Feature",
  "properties": {
    "tgn:hierarchy":[
        "tgn:2359062",
        "tgn:1000001",
        "tgn:7012149",
        "tgn:7007157",
        "tgn:1002675",
        "tgn:7029392"
    ],
    "tgn:id":2359062,
    "tgn:name":"Granite Mountain",
    "tgn:placetype":[
        "aat:300008798"
    ]
},
  "bbox": [],
  "geometry": {"coordinates":[-118.7667,37.9167],"type":"Point"}
}