{
  "id": 7560049,
  "type": "Feature",
  "properties": {
    "tgn:hierarchy":[
        "tgn:7560049",
        "tgn:1000004",
        "tgn:7000198",
        "tgn:7016722",
        "tgn:7029392"
    ],
    "tgn:id":7560049,
    "tgn:name:en":"Lakhn\u012bpur",
    "tgn:placetype":[
        "aat:300008347"
    ]
},
  "bbox": [],
  "geometry": {"coordinates":[79.021942,26.964444],"type":"Point"}
}