{
  "id": 2626577,
  "type": "Feature",
  "properties": {
    "tgn:hierarchy":[
        "tgn:2626577",
        "tgn:1000001",
        "tgn:7012149",
        "tgn:2001241",
        "tgn:7007523",
        "tgn:7029392"
    ],
    "tgn:id":2626577,
    "tgn:name":"Rocky Knob",
    "tgn:placetype":[
        "aat:300008798"
    ]
},
  "bbox": [],
  "geometry": {"coordinates":[-90.5167,37.6833],"type":"Point"}
}