{
  "id": 2254002,
  "type": "Feature",
  "properties": {
    "tgn:hierarchy":[
        "tgn:2254002",
        "tgn:1000001",
        "tgn:2000920",
        "tgn:7012149",
        "tgn:7007515",
        "tgn:7029392"
    ],
    "tgn:id":2254002,
    "tgn:name":"Cool Rock",
    "tgn:placetype":[
        "aat:300132348"
    ]
},
  "bbox": [],
  "geometry": {"coordinates":[-70.2833,43.55],"type":"Point"}
}