<<<<<<< HEAD
{
  "id": 2254002,
  "type": "Feature",
  "properties": {
    "tgn:hierarchy":[
        "tgn:2254002",
        "tgn:1000001",
        "tgn:2000920",
        "tgn:7012149",
        "tgn:7007515",
        "tgn:7029392"
    ],
    "tgn:id":2254002,
    "tgn:name":"Cool Rock",
    "tgn:placetype":[
        "aat:300132348"
    ]
},
  "bbox": [],
  "geometry": {"coordinates":[-70.2833,43.55],"type":"Point"}
}
=======
{"geometry":{"type":"Point","coordinates":[-70.283300,43.550000]},"type":"Feature","properties":{"hierarchy":["tgn:2254002","tgn:1000001","tgn:2000920","tgn:7012149","tgn:7007515","tgn:7029392"],"placetype":["aat:300132348"],"id":2254002,"name:xx":"Cool Rock"}}
>>>>>>> 03f74aca74312dbeaf24d7e61306dd6a786dc3d0
