{
  "id": 2527331,
  "type": "Feature",
  "properties": {
    "tgn:hierarchy":[
        "tgn:2527331",
        "tgn:1000001",
        "tgn:2002263",
        "tgn:7012149",
        "tgn:7013961",
        "tgn:7029392"
    ],
    "tgn:id":2527331,
    "tgn:name":"Mount Pisgah",
    "tgn:placetype":[
        "aat:300008347"
    ]
},
  "bbox": [],
  "geometry": {"coordinates":[-79.1667,39.2833],"type":"Point"}
}