{
  "id": 2466751,
  "type": "Feature",
  "properties": {
    "tgn:hierarchy":[
        "tgn:2466751",
        "tgn:1000001",
        "tgn:7012149",
        "tgn:1002590",
        "tgn:7007826",
        "tgn:7029392"
    ],
    "tgn:id":2466751,
    "tgn:name":"Long Branch",
    "tgn:placetype":[
        "aat:300008699"
    ]
},
  "bbox": [],
  "geometry": {"coordinates":[-96.2667,31.35],"type":"Point"}
}