<<<<<<< HEAD
{
  "id": 7174904,
  "type": "Feature",
  "properties": {
    "tgn:hierarchy":[
        "tgn:7174904",
        "tgn:1000003",
        "tgn:7003687",
        "tgn:7000084",
        "tgn:7029392"
    ],
    "tgn:id":7174904,
    "tgn:name":"Grube Karoline",
    "tgn:placetype":[
        "aat:300008347"
    ]
},
  "bbox": [],
  "geometry": {"coordinates":[11.066667,52.133333],"type":"Point"}
}
=======
{"geometry":{"type":"Point","coordinates":[11.066667,52.133333]},"type":"Feature","properties":{"hierarchy":["tgn:7174904","tgn:1000003","tgn:7003687","tgn:7000084","tgn:7029392"],"placetype":["aat:300008347"],"id":7174904,"name:xx":"Grube Karoline"}}
>>>>>>> 03f74aca74312dbeaf24d7e61306dd6a786dc3d0
