<<<<<<< HEAD
{
  "id": 2767134,
  "type": "Feature",
  "properties": {
    "tgn:hierarchy":[
        "tgn:2767134",
        "tgn:1000001",
        "tgn:7012149",
        "tgn:1002350",
        "tgn:7007157",
        "tgn:7029392"
    ],
    "tgn:id":2767134,
    "tgn:name":"White Rock Creek",
    "tgn:placetype":[
        "aat:300008706"
    ]
},
  "bbox": [],
  "geometry": {"coordinates":[-120.7167,38.7333],"type":"Point"}
}
=======
{"geometry":{"type":"Point","coordinates":[-120.716700,38.733300]},"type":"Feature","properties":{"hierarchy":["tgn:2767134","tgn:1000001","tgn:7012149","tgn:1002350","tgn:7007157","tgn:7029392"],"placetype":["aat:300008706"],"id":2767134,"name:xx":"White Rock Creek"}}
>>>>>>> 03f74aca74312dbeaf24d7e61306dd6a786dc3d0
