{
  "id": 2642616,
  "type": "Feature",
  "properties": {
    "tgn:hierarchy":[
        "tgn:2642616",
        "tgn:1000001",
        "tgn:7016172",
        "tgn:7012149",
        "tgn:2000125",
        "tgn:7029392"
    ],
    "tgn:id":2642616,
    "tgn:name":"Sanders Lake",
    "tgn:placetype":[
        "aat:300008905"
    ]
},
  "bbox": [],
  "geometry": {"coordinates":[-91.0667,33.8333],"type":"Point"}
}