<<<<<<< HEAD
{
  "id": 7368560,
  "type": "Feature",
  "properties": {
    "tgn:hierarchy":[
        "tgn:7368560",
        "tgn:7005584",
        "tgn:1000001",
        "tgn:7005560",
        "tgn:7029392"
    ],
    "tgn:id":7368560,
    "tgn:name":"Higuera",
    "tgn:placetype":[
        "aat:300008347"
    ]
},
  "bbox": [],
  "geometry": {"coordinates":[-100.15,21.366667],"type":"Point"}
}
=======
{"geometry":{"type":"Point","coordinates":[-100.150000,21.366667]},"type":"Feature","properties":{"hierarchy":["tgn:7368560","tgn:7005584","tgn:1000001","tgn:7005560","tgn:7029392"],"placetype":["aat:300008347"],"id":7368560,"name:xx":"Higuera"}}
>>>>>>> 03f74aca74312dbeaf24d7e61306dd6a786dc3d0
