{
  "id": 7511148,
  "type": "Feature",
  "properties": {
    "tgn:hierarchy":[
        "tgn:7511148",
        "tgn:1009227",
        "tgn:1000226",
        "tgn:7016822",
        "tgn:1000006",
        "tgn:7029392"
    ],
    "tgn:id":7511148,
    "tgn:name:en":"Skelmorlie Peak",
    "tgn:placetype":[
        "aat:300008798"
    ]
},
  "bbox": [],
  "geometry": {"coordinates":[167.95,-44.95],"type":"Point"}
}