{
  "id": 2306076,
  "type": "Feature",
  "properties": {
    "tgn:hierarchy":[
        "tgn:2306076",
        "tgn:1000001",
        "tgn:7012149",
        "tgn:2000829",
        "tgn:7007255",
        "tgn:7029392"
    ],
    "tgn:id":2306076,
    "tgn:name":"East Fork Barren River",
    "tgn:placetype":[
        "aat:300008707"
    ]
},
  "bbox": [],
  "geometry": {"coordinates":[-85.65,36.7667],"type":"Point"}
}