{
  "id": 2708085,
  "type": "Feature",
  "properties": {
    "tgn:hierarchy":[
        "tgn:2708085",
        "tgn:1000001",
        "tgn:7012149",
        "tgn:2001506",
        "tgn:7007709",
        "tgn:7029392"
    ],
    "tgn:id":2708085,
    "tgn:name":"Swindell Fork",
    "tgn:placetype":[
        "aat:300008347"
    ]
},
  "bbox": [],
  "geometry": {"coordinates":[-76.2667,35.4333],"type":"Point"}
}