{
  "id": 1111676,
  "type": "Feature",
  "properties": {
    "tgn:hierarchy":[
        "tgn:1111676",
        "tgn:1003430",
        "tgn:1000003",
        "tgn:7003126",
        "tgn:1000080",
        "tgn:7029392"
    ],
    "tgn:id":1111676,
    "tgn:name":"Gressoney, Val di",
    "tgn:placetype":[
        "aat:300008761"
    ]
},
  "bbox": [],
  "geometry": {"coordinates":[7.833,45.75],"type":"Point"}
}