{
  "id": 2730332,
  "type": "Feature",
  "properties": {
    "tgn:hierarchy":[
        "tgn:2730332",
        "tgn:1000001",
        "tgn:7012149",
        "tgn:7021313",
        "tgn:7007521",
        "tgn:7029392"
    ],
    "tgn:id":2730332,
    "tgn:name":"Troy Creek",
    "tgn:placetype":[
        "aat:300008706"
    ]
},
  "bbox": [],
  "geometry": {"coordinates":[-94.6333,48.3667],"type":"Point"}
}