{
  "id": 7480395,
  "type": "Feature",
  "properties": {
    "tgn:hierarchy":[
        "tgn:7480395",
        "tgn:1000004",
        "tgn:7471332",
        "tgn:1000141",
        "tgn:7029392"
    ],
    "tgn:id":7480395,
    "tgn:name":"Bengpoque",
    "tgn:placetype":[
        "aat:300008347"
    ]
},
  "bbox": [],
  "geometry": {"coordinates":[121.037222,24.885278],"type":"Point"}
}