{
  "id": 2383697,
  "type": "Feature",
  "properties": {
    "tgn:hierarchy":[
        "tgn:2383697",
        "tgn:1000001",
        "tgn:7006451",
        "tgn:2000094",
        "tgn:7012149",
        "tgn:7029392"
    ],
    "tgn:id":2383697,
    "tgn:name":"Heber Tank",
    "tgn:placetype":[
        "aat:300006191"
    ]
},
  "bbox": [],
  "geometry": {"coordinates":[-109.4167,32.85],"type":"Point"}
}