{
  "id": 7438919,
  "type": "Feature",
  "properties": {
    "tgn:hierarchy":[
        "tgn:7438919",
        "tgn:1000001",
        "tgn:7005595",
        "tgn:7005560",
        "tgn:7029392"
    ],
    "tgn:id":7438919,
    "tgn:name":"Tabaya",
    "tgn:placetype":[
        "aat:300008347"
    ]
},
  "bbox": [],
  "geometry": {"coordinates":[-108.05,25.416667],"type":"Point"}
}