{
  "id": 7293665,
  "type": "Feature",
  "properties": {
    "tgn:hierarchy":[
        "tgn:7293665",
        "tgn:7001122",
        "tgn:1000003",
        "tgn:7002765",
        "tgn:1000095",
        "tgn:7029392"
    ],
    "tgn:id":7293665,
    "tgn:name":"Villacarlos",
    "tgn:placetype":[
        "aat:300008347"
    ]
},
  "bbox": [],
  "geometry": {"coordinates":[4.266667,39.883333],"type":"Point"}
}