{
  "id": 7508575,
  "type": "Feature",
  "properties": {
    "tgn:hierarchy":[
        "tgn:7508575",
        "tgn:1008380",
        "tgn:7000507",
        "tgn:1000226",
        "tgn:1000006",
        "tgn:7029392"
    ],
    "tgn:id":7508575,
    "tgn:name:en":"Otamatea River",
    "tgn:placetype":[
        "aat:300008699"
    ]
},
  "bbox": [],
  "geometry": {"coordinates":[174.266667,-36.25],"type":"Point"}
}