{
  "id": 2326459,
  "type": "Feature",
  "properties": {
    "tgn:hierarchy":[
        "tgn:2326459",
        "tgn:1000001",
        "tgn:2000273",
        "tgn:7012149",
        "tgn:7007240",
        "tgn:7029392"
    ],
    "tgn:id":2326459,
    "tgn:name":"Finger Pond",
    "tgn:placetype":[
        "aat:300008680"
    ]
},
  "bbox": [],
  "geometry": {"coordinates":[-85.35,30.85],"type":"Point"}
}