{
  "id": 2759784,
  "type": "Feature",
  "properties": {
    "tgn:hierarchy":[
        "tgn:2759784",
        "tgn:1000001",
        "tgn:7012149",
        "tgn:2001717",
        "tgn:7007708",
        "tgn:7029392"
    ],
    "tgn:id":2759784,
    "tgn:name":"West Fork Keeney Creek",
    "tgn:placetype":[
        "aat:300008706"
    ]
},
  "bbox": [],
  "geometry": {"coordinates":[-122.35,44.2167],"type":"Point"}
}