{
  "id": 1047540,
  "type": "Feature",
  "properties": {
    "tgn:hierarchy":[
        "tgn:1047540",
        "tgn:7003533",
        "tgn:1000003",
        "tgn:7003514",
        "tgn:7029392"
    ],
    "tgn:id":1047540,
    "tgn:name":"Beaufort",
    "tgn:placetype":[
        "aat:300008347"
    ]
},
  "bbox": [],
  "geometry": {"coordinates":[6.2833,49.8333],"type":"Point"}
}