{
  "id": 2483266,
  "type": "Feature",
  "properties": {
    "tgn:hierarchy":[
        "tgn:2483266",
        "tgn:1000001",
        "tgn:7012149",
        "tgn:7007157",
        "tgn:1002867",
        "tgn:7029392"
    ],
    "tgn:id":2483266,
    "tgn:name":"Las Vegas Creek",
    "tgn:placetype":[
        "aat:300008706"
    ]
},
  "bbox": [],
  "geometry": {"coordinates":[-119.8167,34.4667],"type":"Point"}
}