{
  "id": 2691818,
  "type": "Feature",
  "properties": {
    "tgn:hierarchy":[
        "tgn:2691818",
        "tgn:1000001",
        "tgn:7012149",
        "tgn:2001295",
        "tgn:7007524",
        "tgn:7029392"
    ],
    "tgn:id":2691818,
    "tgn:name":"Starter Pond",
    "tgn:placetype":[
        "aat:300006191"
    ]
},
  "bbox": [],
  "geometry": {"coordinates":[-107.7167,48.3833],"type":"Point"}
}