{
  "id": 2776864,
  "type": "Feature",
  "properties": {
    "tgn:hierarchy":[
        "tgn:2776864",
        "tgn:1000001",
        "tgn:7012149",
        "tgn:1002690",
        "tgn:7007710",
        "tgn:7029392"
    ],
    "tgn:id":2776864,
    "tgn:name":"Windsor Pass",
    "tgn:placetype":[
        "aat:300008347"
    ]
},
  "bbox": [],
  "geometry": {"coordinates":[-75.1333,40.1667],"type":"Point"}
}