{
  "id": 1007136,
  "type": "Feature",
  "properties": {
    "tgn:hierarchy":[
        "tgn:1007136",
        "tgn:1001172",
        "tgn:1000002",
        "tgn:1000056",
        "tgn:7029392"
    ],
    "tgn:id":1007136,
    "tgn:name":"Front\u00f3n, Isla",
    "tgn:placetype":[
        "aat:300008791"
    ]
},
  "bbox": [],
  "geometry": {"coordinates":[-77.1833,-12.1167],"type":"Point"}
}