<<<<<<< HEAD
{
  "id": 2251418,
  "type": "Feature",
  "properties": {
    "tgn:hierarchy":[
        "tgn:2251418",
        "tgn:1000001",
        "tgn:1002724",
        "tgn:7012149",
        "tgn:7007517",
        "tgn:7029392"
    ],
    "tgn:id":2251418,
    "tgn:name":"Comeys Pond",
    "tgn:placetype":[
        "aat:300008680"
    ]
},
  "bbox": [],
  "geometry": {"coordinates":[-71.35,42.1],"type":"Point"}
}
=======
{"geometry":{"type":"Point","coordinates":[-71.350000,42.100000]},"type":"Feature","properties":{"hierarchy":["tgn:2251418","tgn:1000001","tgn:1002724","tgn:7012149","tgn:7007517","tgn:7029392"],"placetype":["aat:300008680"],"id":2251418,"name:xx":"Comeys Pond"}}
>>>>>>> 03f74aca74312dbeaf24d7e61306dd6a786dc3d0
