{
  "id": 1119947,
  "type": "Feature",
  "properties": {
    "tgn:hierarchy":[
        "tgn:1119947",
        "tgn:1000004",
        "tgn:7002435",
        "tgn:7029392"
    ],
    "tgn:id":1119947,
    "tgn:name":"Ivan'kovskoye Vodokhranilishche",
    "tgn:placetype":[
        "aat:300006191"
    ]
},
  "bbox": [],
  "geometry": {"coordinates":[36.6667,56.6667],"type":"Point"}
}