{
  "id": 7428126,
  "type": "Feature",
  "properties": {
    "tgn:hierarchy":[
        "tgn:7428126",
        "tgn:1000001",
        "tgn:7005594",
        "tgn:7005560",
        "tgn:7029392"
    ],
    "tgn:id":7428126,
    "tgn:name":"El A\u00f1ejo",
    "tgn:placetype":[
        "aat:300008347"
    ]
},
  "bbox": [],
  "geometry": {"coordinates":[-101.483333,23.516667],"type":"Point"}
}