<<<<<<< HEAD
{
  "id": 2332906,
  "type": "Feature",
  "properties": {
    "tgn:hierarchy":[
        "tgn:2332906",
        "tgn:1000001",
        "tgn:7012149",
        "tgn:7007157",
        "tgn:2000188",
        "tgn:7029392"
    ],
    "tgn:id":2332906,
    "tgn:name":"Fluhart Basin",
    "tgn:placetype":[
        "aat:300386845"
    ]
},
  "bbox": [],
  "geometry": {"coordinates":[-121.9167,40.5833],"type":"Point"}
}
=======
{"geometry":{"type":"Point","coordinates":[-121.916700,40.583300]},"type":"Feature","properties":{"hierarchy":["tgn:2332906","tgn:1000001","tgn:7012149","tgn:7007157","tgn:2000188","tgn:7029392"],"placetype":["aat:300386845"],"id":2332906,"name:xx":"Fluhart Basin"}}
>>>>>>> 03f74aca74312dbeaf24d7e61306dd6a786dc3d0
