{
  "id": 2332906,
  "type": "Feature",
  "properties": {
    "tgn:hierarchy":[
        "tgn:2332906",
        "tgn:1000001",
        "tgn:7012149",
        "tgn:7007157",
        "tgn:2000188",
        "tgn:7029392"
    ],
    "tgn:id":2332906,
    "tgn:name":"Fluhart Basin",
    "tgn:placetype":[
        "aat:300386845"
    ]
},
  "bbox": [],
  "geometry": {"coordinates":[-121.9167,40.5833],"type":"Point"}
}