{
  "id": 7364797,
  "type": "Feature",
  "properties": {
    "tgn:hierarchy":[
        "tgn:7364797",
        "tgn:7005581",
        "tgn:1000001",
        "tgn:7005560",
        "tgn:7029392"
    ],
    "tgn:id":7364797,
    "tgn:name":"Rancho El Puerto",
    "tgn:placetype":[
        "aat:300000241"
    ]
},
  "bbox": [],
  "geometry": {"coordinates":[-105.516667,30.716667],"type":"Point"}
}