{
  "id": 2488905,
  "type": "Feature",
  "properties": {
    "tgn:hierarchy":[
        "tgn:2488905",
        "tgn:1000001",
        "tgn:7012149",
        "tgn:2001197",
        "tgn:7007523",
        "tgn:7029392"
    ],
    "tgn:id":2488905,
    "tgn:name":"Main Ditch Number 10",
    "tgn:placetype":[
        "aat:300006075"
    ]
},
  "bbox": [],
  "geometry": {"coordinates":[-90.0833,36.2167],"type":"Point"}
}