{
  "id": 7331225,
  "type": "Feature",
  "properties": {
    "tgn:hierarchy":[
        "tgn:7331225",
        "tgn:7002758",
        "tgn:7002823",
        "tgn:1000003",
        "tgn:1000095",
        "tgn:7029392"
    ],
    "tgn:id":7331225,
    "tgn:name":"La Redondela",
    "tgn:placetype":[
        "aat:300008347"
    ]
},
  "bbox": [],
  "geometry": {"coordinates":[-7.266667,37.216667],"type":"Point"}
}