{
  "id": 7494029,
  "type": "Feature",
  "properties": {
    "tgn:hierarchy":[
        "tgn:7494029",
        "tgn:1000004",
        "tgn:7491221",
        "tgn:1000141",
        "tgn:7029392"
    ],
    "tgn:id":7494029,
    "tgn:name":"Shiwuhao Qiao",
    "tgn:placetype":[
        "aat:300007836"
    ]
},
  "bbox": [],
  "geometry": {"coordinates":[121.302191,23.098308],"type":"Point"}
}