{
  "id": 2351535,
  "type": "Feature",
  "properties": {
    "tgn:hierarchy":[
        "tgn:2351535",
        "tgn:7016099",
        "tgn:1000001",
        "tgn:7012149",
        "tgn:7007516",
        "tgn:7029392"
    ],
    "tgn:id":2351535,
    "tgn:name":"Glenartney",
    "tgn:placetype":[
        "aat:300008347"
    ]
},
  "bbox": [],
  "geometry": {"coordinates":[-76.7167,39.2167],"type":"Point"}
}