{
  "id": 2079885,
  "type": "Feature",
  "properties": {
    "tgn:hierarchy":[
        "tgn:2079885",
        "tgn:1000001",
        "tgn:7012149",
        "tgn:1002596",
        "tgn:7007706",
        "tgn:7029392"
    ],
    "tgn:id":2079885,
    "tgn:name":"Harbor Hills",
    "tgn:placetype":[
        "aat:300386831"
    ]
},
  "bbox": [],
  "geometry": {"coordinates":[-82.4333,39.9333],"type":"Point"}
}