{
  "id": 2022841,
  "type": "Feature",
  "properties": {
    "tgn:hierarchy":[
        "tgn:2022841",
        "tgn:7002659",
        "tgn:1000001",
        "tgn:2000008",
        "tgn:7012149",
        "tgn:7029392"
    ],
    "tgn:id":2022841,
    "tgn:name":"Evansville",
    "tgn:placetype":[
        "aat:300008347",
        "aat:300387210"
    ]
},
  "bbox": [],
  "geometry": {"coordinates":[-85.2167,33.05],"type":"Point"}
}