{
  "id": 1054867,
  "type": "Feature",
  "properties": {
    "tgn:hierarchy":[
        "tgn:1054867",
        "tgn:7006561",
        "tgn:1000003",
        "tgn:7006542",
        "tgn:7029392"
    ],
    "tgn:id":1054867,
    "tgn:name":"Kaisiadorys",
    "tgn:placetype":[
        "aat:300008347",
        "aat:300387222"
    ]
},
  "bbox": [],
  "geometry": {"coordinates":[24.4833,54.85],"type":"Point"}
}