{
  "id": 7156123,
  "type": "Feature",
  "properties": {
    "tgn:hierarchy":[
        "tgn:7156123",
        "tgn:7003692",
        "tgn:1000003",
        "tgn:7000084",
        "tgn:7029392"
    ],
    "tgn:id":7156123,
    "tgn:name":"Kleinallmendingen",
    "tgn:placetype":[
        "aat:300008347"
    ]
},
  "bbox": [],
  "geometry": {"coordinates":[9.716667,48.333333],"type":"Point"}
}