{
  "id": 2289822,
  "type": "Feature",
  "properties": {
    "tgn:hierarchy":[
        "tgn:2289822",
        "tgn:1000001",
        "tgn:7012149",
        "tgn:2002371",
        "tgn:7007923",
        "tgn:7029392"
    ],
    "tgn:id":2289822,
    "tgn:name":"Dobe Reservoir",
    "tgn:placetype":[
        "aat:300006191"
    ]
},
  "bbox": [],
  "geometry": {"coordinates":[-108.4333,42.6833],"type":"Point"}
}