{
  "id": 7472434,
  "type": "Feature",
  "properties": {
    "tgn:hierarchy":[
        "tgn:7472434",
        "tgn:1000004",
        "tgn:7490934",
        "tgn:1000141",
        "tgn:7029392"
    ],
    "tgn:id":7472434,
    "tgn:name":"Dujia",
    "tgn:placetype":[
        "aat:300008347"
    ]
},
  "bbox": [],
  "geometry": {"coordinates":[120.13,23.160278],"type":"Point"}
}