{
  "id": 2696213,
  "type": "Feature",
  "properties": {
    "tgn:hierarchy":[
        "tgn:2696213",
        "tgn:1000001",
        "tgn:7012149",
        "tgn:2000899",
        "tgn:7007256",
        "tgn:7029392"
    ],
    "tgn:id":2696213,
    "tgn:name":"Stone Branch",
    "tgn:placetype":[
        "aat:300008699"
    ]
},
  "bbox": [],
  "geometry": {"coordinates":[-90.7167,30.75],"type":"Point"}
}