{
  "id": 2189736,
  "type": "Feature",
  "properties": {
    "tgn:hierarchy":[
        "tgn:2189736",
        "tgn:1000001",
        "tgn:7012149",
        "tgn:2000232",
        "tgn:7007158",
        "tgn:7029392"
    ],
    "tgn:id":2189736,
    "tgn:name":"Bower Place",
    "tgn:placetype":[
        "aat:300008347"
    ]
},
  "bbox": [],
  "geometry": {"coordinates":[-108.6833,40.5833],"type":"Point"}
}