{
  "id": 7172432,
  "type": "Feature",
  "properties": {
    "tgn:hierarchy":[
        "tgn:7172432",
        "tgn:7003692",
        "tgn:1000003",
        "tgn:7000084",
        "tgn:7029392"
    ],
    "tgn:id":7172432,
    "tgn:name":"Hintersteinb\u00fchl",
    "tgn:placetype":[
        "aat:300000206"
    ]
},
  "bbox": [],
  "geometry": {"coordinates":[10.083333,48.983333],"type":"Point"}
}