{
  "id": 2665852,
  "type": "Feature",
  "properties": {
    "tgn:hierarchy":[
        "tgn:2665852",
        "tgn:7006450",
        "tgn:1000001",
        "tgn:7012149",
        "tgn:2000089",
        "tgn:7029392"
    ],
    "tgn:id":2665852,
    "tgn:name":"Sirr Creek",
    "tgn:placetype":[
        "aat:300008706"
    ]
},
  "bbox": [],
  "geometry": {"coordinates":[-151.6167,67.55],"type":"Point"}
}