{
  "id": 7160650,
  "type": "Feature",
  "properties": {
    "tgn:hierarchy":[
        "tgn:7160650",
        "tgn:1000003",
        "tgn:7000094",
        "tgn:7000084",
        "tgn:7029392"
    ],
    "tgn:id":7160650,
    "tgn:name":"F\u00f6rsterei H\u00f6ltingsdorf",
    "tgn:placetype":[
        "aat:300004792"
    ]
},
  "bbox": [],
  "geometry": {"coordinates":[11.766667,53.966667],"type":"Point"}
}