{
  "id": 2161907,
  "type": "Feature",
  "properties": {
    "tgn:hierarchy":[
        "tgn:2161907",
        "tgn:1000001",
        "tgn:7012149",
        "tgn:2002126",
        "tgn:7007827",
        "tgn:7029392"
    ],
    "tgn:id":2161907,
    "tgn:name":"Bellows Hollow",
    "tgn:placetype":[
        "aat:300008761"
    ]
},
  "bbox": [],
  "geometry": {"coordinates":[-111.2333,40.3833],"type":"Point"}
}