{
  "id": 2727794,
  "type": "Feature",
  "properties": {
    "tgn:hierarchy":[
        "tgn:2727794",
        "tgn:7002659",
        "tgn:1000001",
        "tgn:7012149",
        "tgn:2000029",
        "tgn:7029392"
    ],
    "tgn:id":2727794,
    "tgn:name":"Trainrobber Cave",
    "tgn:placetype":[
        "aat:300008746"
    ]
},
  "bbox": [],
  "geometry": {"coordinates":[-87.7667,34.3333],"type":"Point"}
}