{
  "id": 7323858,
  "type": "Feature",
  "properties": {
    "tgn:hierarchy":[
        "tgn:7323858",
        "tgn:7002820",
        "tgn:7030216",
        "tgn:1000003",
        "tgn:1000095",
        "tgn:7029392"
    ],
    "tgn:id":7323858,
    "tgn:name":"R\u00edo Tordera, Punta del",
    "tgn:placetype":[
        "aat:300386846"
    ]
},
  "bbox": [],
  "geometry": {"coordinates":[2.783333,41.65],"type":"Point"}
}