{
  "id": 2333698,
  "type": "Feature",
  "properties": {
    "tgn:hierarchy":[
        "tgn:2333698",
        "tgn:1002933",
        "tgn:1000001",
        "tgn:7012149",
        "tgn:7007239",
        "tgn:7029392"
    ],
    "tgn:id":2333698,
    "tgn:name":"Foord Landing",
    "tgn:placetype":[
        "aat:300008347"
    ]
},
  "bbox": [],
  "geometry": {"coordinates":[-75.25,38.8333],"type":"Point"}
}