{
  "id": 7125544,
  "type": "Feature",
  "properties": {
    "tgn:hierarchy":[
        "tgn:7125544",
        "tgn:7003669",
        "tgn:1000003",
        "tgn:7000084",
        "tgn:7029392"
    ],
    "tgn:id":7125544,
    "tgn:name":"Nordheim vor der Rh\u00f6n",
    "tgn:placetype":[
        "aat:300008347"
    ]
},
  "bbox": [],
  "geometry": {"coordinates":[10.183333,50.483333],"type":"Point"}
}