<<<<<<< HEAD
{
  "id": 7057124,
  "type": "Feature",
  "properties": {
    "tgn:hierarchy":[
        "tgn:7057124",
        "tgn:7002994",
        "tgn:1000003",
        "tgn:7002997",
        "tgn:1000080",
        "tgn:7029392"
    ],
    "tgn:id":7057124,
    "tgn:name":"Baone",
    "tgn:placetype":[
        "aat:300008347"
    ]
},
  "bbox": [],
  "geometry": {"coordinates":[11.683333,45.233333],"type":"Point"}
}
=======
{"geometry":{"type":"Point","coordinates":[11.683333,45.233333]},"type":"Feature","properties":{"hierarchy":["tgn:7057124","tgn:7002994","tgn:1000003","tgn:7002997","tgn:1000080","tgn:7029392"],"placetype":["aat:300008347"],"id":7057124,"name:xx":"Baone"}}
>>>>>>> 03f74aca74312dbeaf24d7e61306dd6a786dc3d0
