{
  "id": 2386854,
  "type": "Feature",
  "properties": {
    "tgn:hierarchy":[
        "tgn:2386854",
        "tgn:2001726",
        "tgn:1000001",
        "tgn:7012149",
        "tgn:7007712",
        "tgn:7029392"
    ],
    "tgn:id":2386854,
    "tgn:name":"Herndon Pond",
    "tgn:placetype":[
        "aat:300006191"
    ]
},
  "bbox": [],
  "geometry": {"coordinates":[-81.7833,33.4667],"type":"Point"}
}