{
  "id": 7382458,
  "type": "Feature",
  "properties": {
    "tgn:hierarchy":[
        "tgn:7382458",
        "tgn:1000001",
        "tgn:7005594",
        "tgn:7005560",
        "tgn:7029392"
    ],
    "tgn:id":7382458,
    "tgn:name":"Morales",
    "tgn:placetype":[
        "aat:300008347"
    ]
},
  "bbox": [],
  "geometry": {"coordinates":[-101.033333,22.166667],"type":"Point"}
}