{
  "id": 2141629,
  "type": "Feature",
  "properties": {
    "tgn:hierarchy":[
        "tgn:2141629",
        "tgn:1000001",
        "tgn:7006451",
        "tgn:7012149",
        "tgn:2000103",
        "tgn:7029392"
    ],
    "tgn:id":2141629,
    "tgn:name":"BT Butte",
    "tgn:placetype":[
        "aat:300008798"
    ]
},
  "bbox": [],
  "geometry": {"coordinates":[-112.8833,34.7333],"type":"Point"}
}