{
  "id": 7580886,
  "type": "Feature",
  "properties": {
    "tgn:hierarchy":[
        "tgn:7580886",
        "tgn:1000004",
        "tgn:7000198",
        "tgn:7031786",
        "tgn:7029392"
    ],
    "tgn:id":7580886,
    "tgn:name:en":"Shalshal Pass",
    "tgn:placetype":[
        "aat:300259572"
    ]
},
  "bbox": [],
  "geometry": {"coordinates":[80.07,30.8225],"type":"Point"}
}