{
  "id": 2514139,
  "type": "Feature",
  "properties": {
    "tgn:hierarchy":[
        "tgn:2514139",
        "tgn:2001468",
        "tgn:1000001",
        "tgn:7012149",
        "tgn:7007709",
        "tgn:7029392"
    ],
    "tgn:id":2514139,
    "tgn:name":"Miller Branch",
    "tgn:placetype":[
        "aat:300008699"
    ]
},
  "bbox": [],
  "geometry": {"coordinates":[-81.9333,36.15],"type":"Point"}
}