{
  "id": 2455560,
  "type": "Feature",
  "properties": {
    "tgn:hierarchy":[
        "tgn:2455560",
        "tgn:1000001",
        "tgn:7012149",
        "tgn:7029392"
    ],
    "tgn:id":2455560,
    "tgn:name":"Little Gilbert Creek",
    "tgn:placetype":[
        "aat:300008706"
    ]
},
  "bbox": [],
  "geometry": {"coordinates":[-110.4167,40.95],"type":"Point"}
}