{
  "id": 2721179,
  "type": "Feature",
  "properties": {
    "tgn:hierarchy":[
        "tgn:2721179",
        "tgn:1000001",
        "tgn:7012149",
        "tgn:1002977",
        "tgn:7007240",
        "tgn:7029392"
    ],
    "tgn:id":2721179,
    "tgn:name":"Tiger Bay",
    "tgn:placetype":[
        "aat:300008905"
    ]
},
  "bbox": [],
  "geometry": {"coordinates":[-81.1667,29.1333],"type":"Point"}
}