{
  "id": 2525647,
  "type": "Feature",
  "properties": {
    "tgn:hierarchy":[
        "tgn:2525647",
        "tgn:1000001",
        "tgn:7012149",
        "tgn:2001456",
        "tgn:7007566",
        "tgn:7029392"
    ],
    "tgn:id":2525647,
    "tgn:name":"Morton Tank",
    "tgn:placetype":[
        "aat:300006191"
    ]
},
  "bbox": [],
  "geometry": {"coordinates":[-106.4167,33.9333],"type":"Point"}
}