{
  "id": 2344778,
  "type": "Feature",
  "properties": {
    "tgn:hierarchy":[
        "tgn:2344778",
        "tgn:1000001",
        "tgn:7012149",
        "tgn:2000480",
        "tgn:7007250",
        "tgn:7029392"
    ],
    "tgn:id":2344778,
    "tgn:name":"Garden Gulch",
    "tgn:placetype":[
        "aat:300008761"
    ]
},
  "bbox": [],
  "geometry": {"coordinates":[-116.7333,46.9333],"type":"Point"}
}