{
  "id": 2399246,
  "type": "Feature",
  "properties": {
    "tgn:hierarchy":[
        "tgn:2399246",
        "tgn:1000001",
        "tgn:7012149",
        "tgn:2000989",
        "tgn:7007520",
        "tgn:7029392"
    ],
    "tgn:id":2399246,
    "tgn:name":"Horicon, Lake",
    "tgn:placetype":[
        "aat:300008680"
    ]
},
  "bbox": [],
  "geometry": {"coordinates":[-84.7333,44.9167],"type":"Point"}
}