{
  "id": 2326502,
  "type": "Feature",
  "properties": {
    "tgn:hierarchy":[
        "tgn:2326502",
        "tgn:1000001",
        "tgn:7012149",
        "tgn:7014287",
        "tgn:7007568",
        "tgn:7029392"
    ],
    "tgn:id":2326502,
    "tgn:name":"Fink Hollow",
    "tgn:placetype":[
        "aat:300008347"
    ]
},
  "bbox": [],
  "geometry": {"coordinates":[-75.2667,43.35],"type":"Point"}
}