<<<<<<< HEAD
{
  "id": 7172875,
  "type": "Feature",
  "properties": {
    "tgn:hierarchy":[
        "tgn:7172875",
        "tgn:1000003",
        "tgn:7003685",
        "tgn:7000084",
        "tgn:7029392"
    ],
    "tgn:id":7172875,
    "tgn:name":"Grenz-Teich",
    "tgn:placetype":[
        "aat:300008688"
    ]
},
  "bbox": [],
  "geometry": {"coordinates":[14.416667,51.366667],"type":"Point"}
}
=======
{"geometry":{"type":"Point","coordinates":[14.416667,51.366667]},"type":"Feature","properties":{"hierarchy":["tgn:7172875","tgn:1000003","tgn:7003685","tgn:7000084","tgn:7029392"],"placetype":["aat:300008688"],"id":7172875,"name:xx":"Grenz-Teich"}}
>>>>>>> 03f74aca74312dbeaf24d7e61306dd6a786dc3d0
