{
  "id": 2419573,
  "type": "Feature",
  "properties": {
    "tgn:hierarchy":[
        "tgn:2419573",
        "tgn:1000001",
        "tgn:2002105",
        "tgn:7012149",
        "tgn:7007827",
        "tgn:7029392"
    ],
    "tgn:id":2419573,
    "tgn:name":"Jarvies Canyon",
    "tgn:placetype":[
        "aat:300008761"
    ]
},
  "bbox": [],
  "geometry": {"coordinates":[-109.4833,40.95],"type":"Point"}
}