{
  "id": 2383674,
  "type": "Feature",
  "properties": {
    "tgn:hierarchy":[
        "tgn:2383674",
        "tgn:1000001",
        "tgn:7012149",
        "tgn:1003020",
        "tgn:7007920",
        "tgn:7029392"
    ],
    "tgn:id":2383674,
    "tgn:name":"Heavens-Lass Lagoon",
    "tgn:placetype":[
        "aat:300006191"
    ]
},
  "bbox": [],
  "geometry": {"coordinates":[-122.4167,48.8333],"type":"Point"}
}