{
  "id": 1086047,
  "type": "Feature",
  "properties": {
    "tgn:hierarchy":[
        "tgn:1086047",
        "tgn:1001052",
        "tgn:1000004",
        "tgn:7018450",
        "tgn:1000144",
        "tgn:7029392"
    ],
    "tgn:id":1086047,
    "tgn:name":"Bah\u00e7ek\u00f6y",
    "tgn:placetype":[
        "aat:300008347"
    ]
},
  "bbox": [],
  "geometry": {"coordinates":[28.9833,41.1833],"type":"Point"}
}