{
  "id": 7555768,
  "type": "Feature",
  "properties": {
    "tgn:hierarchy":[
        "tgn:7555768",
        "tgn:1000004",
        "tgn:7000198",
        "tgn:7016694",
        "tgn:7029392"
    ],
    "tgn:id":7555768,
    "tgn:name:en":"M\u0101nesar",
    "tgn:placetype":[
        "aat:300008347"
    ]
},
  "bbox": [],
  "geometry": {"coordinates":[84.03076,21.415705],"type":"Point"}
}