{
  "id": 1057052,
  "type": "Feature",
  "properties": {
    "tgn:hierarchy":[
        "tgn:1057052",
        "tgn:1000004",
        "tgn:1003404",
        "tgn:7018214",
        "tgn:7002435",
        "tgn:7029392"
    ],
    "tgn:id":1057052,
    "tgn:name":"Mo\u010dily",
    "tgn:placetype":[
        "aat:300008347"
    ]
},
  "bbox": [],
  "geometry": {"coordinates":[38.6833,54.3333],"type":"Point"}
}