<<<<<<< HEAD
{
  "id": 2158907,
  "type": "Feature",
  "properties": {
    "tgn:hierarchy":[
        "tgn:2158907",
        "tgn:1000001",
        "tgn:7012149",
        "tgn:2002290",
        "tgn:7013961",
        "tgn:7029392"
    ],
    "tgn:id":2158907,
    "tgn:name":"Beckly Water Supply Number One",
    "tgn:placetype":[
        "aat:300006191"
    ]
},
  "bbox": [],
  "geometry": {"coordinates":[-81.1,37.7],"type":"Point"}
}
=======
{"geometry":{"type":"Point","coordinates":[-81.100000,37.700000]},"type":"Feature","properties":{"hierarchy":["tgn:2158907","tgn:1000001","tgn:7012149","tgn:2002290","tgn:7013961","tgn:7029392"],"placetype":["aat:300006191"],"id":2158907,"name:xx":"Beckly Water Supply Number One"}}
>>>>>>> 03f74aca74312dbeaf24d7e61306dd6a786dc3d0
