{
  "id": 7247917,
  "type": "Feature",
  "properties": {
    "tgn:hierarchy":[
        "tgn:7247917",
        "tgn:7003456",
        "tgn:1000003",
        "tgn:1000063",
        "tgn:7018236",
        "tgn:7029392"
    ],
    "tgn:id":7247917,
    "tgn:name":"De Kleine Barreel",
    "tgn:placetype":[
        "aat:300008347"
    ]
},
  "bbox": [],
  "geometry": {"coordinates":[4.469311,51.265265],"type":"Point"}
}