{
  "id": 2162890,
  "type": "Feature",
  "properties": {
    "tgn:hierarchy":[
        "tgn:2162890",
        "tgn:1000001",
        "tgn:7012149",
        "tgn:2001931",
        "tgn:7007825",
        "tgn:7029392"
    ],
    "tgn:id":2162890,
    "tgn:name":"Benjamin Franklin Lake",
    "tgn:placetype":[
        "aat:300006191"
    ]
},
  "bbox": [],
  "geometry": {"coordinates":[-86.4667,36.15],"type":"Point"}
}