<<<<<<< HEAD
{
  "id": 7114233,
  "type": "Feature",
  "properties": {
    "tgn:hierarchy":[
        "tgn:7114233",
        "tgn:1000003",
        "tgn:7003677",
        "tgn:7000084",
        "tgn:7029392"
    ],
    "tgn:id":7114233,
    "tgn:name":"Renzert",
    "tgn:placetype":[
        "aat:300008347"
    ]
},
  "bbox": [],
  "geometry": {"coordinates":[7.333333,50.816667],"type":"Point"}
}
=======
{"geometry":{"type":"Point","coordinates":[7.333333,50.816667]},"type":"Feature","properties":{"hierarchy":["tgn:7114233","tgn:1000003","tgn:7003677","tgn:7000084","tgn:7029392"],"placetype":["aat:300008347"],"id":7114233,"name:xx":"Renzert"}}
>>>>>>> 03f74aca74312dbeaf24d7e61306dd6a786dc3d0
