{
  "id": 7329484,
  "type": "Feature",
  "properties": {
    "tgn:hierarchy":[
        "tgn:7329484",
        "tgn:7002758",
        "tgn:1001316",
        "tgn:1000003",
        "tgn:1000095",
        "tgn:7029392"
    ],
    "tgn:id":7329484,
    "tgn:name":"Puerto Alto",
    "tgn:placetype":[
        "aat:300008347"
    ]
},
  "bbox": [],
  "geometry": {"coordinates":[-3.683333,37.683333],"type":"Point"}
}