{
  "id": 2511564,
  "type": "Feature",
  "properties": {
    "tgn:hierarchy":[
        "tgn:2511564",
        "tgn:1000001",
        "tgn:7012149",
        "tgn:7007706",
        "tgn:7029392"
    ],
    "tgn:id":2511564,
    "tgn:name":"Mile Run",
    "tgn:placetype":[
        "aat:300008699"
    ]
},
  "bbox": [],
  "geometry": {"coordinates":[-82.7167,40.3833],"type":"Point"}
}