{
  "id": 2512797,
  "type": "Feature",
  "properties": {
    "tgn:hierarchy":[
        "tgn:2512797",
        "tgn:1000001",
        "tgn:7013638",
        "tgn:7012149",
        "tgn:7007568",
        "tgn:7029392"
    ],
    "tgn:id":2512797,
    "tgn:name":"Mill Creek",
    "tgn:placetype":[
        "aat:300008706"
    ]
},
  "bbox": [],
  "geometry": {"coordinates":[-73.7167,42.3667],"type":"Point"}
}