<<<<<<< HEAD
{
  "id": 2405436,
  "type": "Feature",
  "properties": {
    "tgn:hierarchy":[
        "tgn:2405436",
        "tgn:7002659",
        "tgn:1000001",
        "tgn:7012149",
        "tgn:2000052",
        "tgn:7029392"
    ],
    "tgn:id":2405436,
    "tgn:name":"Hugh, Lake",
    "tgn:placetype":[
        "aat:300006191"
    ]
},
  "bbox": [],
  "geometry": {"coordinates":[-87.3667,32.5667],"type":"Point"}
}
=======
{"geometry":{"type":"Point","coordinates":[-87.366700,32.566700]},"type":"Feature","properties":{"hierarchy":["tgn:2405436","tgn:7002659","tgn:1000001","tgn:7012149","tgn:2000052","tgn:7029392"],"placetype":["aat:300006191"],"id":2405436,"name:xx":"Hugh, Lake"}}
>>>>>>> 03f74aca74312dbeaf24d7e61306dd6a786dc3d0
