{
  "id": 2370300,
  "type": "Feature",
  "properties": {
    "tgn:hierarchy":[
        "tgn:2370300",
        "tgn:1000001",
        "tgn:7012149",
        "tgn:7007157",
        "tgn:1002857",
        "tgn:7029392"
    ],
    "tgn:id":2370300,
    "tgn:name":"Gypsy Mine",
    "tgn:placetype":[
        "aat:300000390"
    ]
},
  "bbox": [],
  "geometry": {"coordinates":[-115.8167,34.05],"type":"Point"}
}