{
  "id": 7440275,
  "type": "Feature",
  "properties": {
    "tgn:hierarchy":[
        "tgn:7440275",
        "tgn:1000001",
        "tgn:7005591",
        "tgn:7005560",
        "tgn:7029392"
    ],
    "tgn:id":7440275,
    "tgn:name":"Santa Catarina Loxicha",
    "tgn:placetype":[
        "aat:300008347"
    ]
},
  "bbox": [],
  "geometry": {"coordinates":[-96.766667,16.066667],"type":"Point"}
}