{
  "id": 2721753,
  "type": "Feature",
  "properties": {
    "tgn:hierarchy":[
        "tgn:2721753",
        "tgn:7006450",
        "tgn:1000001",
        "tgn:7012149",
        "tgn:7029392"
    ],
    "tgn:id":2721753,
    "tgn:name":"Timber Creek",
    "tgn:placetype":[
        "aat:300008706"
    ]
},
  "bbox": [],
  "geometry": {"coordinates":[-152.9333,61.8333],"type":"Point"}
}