{
  "id": 7020489,
  "type": "Feature",
  "properties": {
    "tgn:hierarchy":[
        "tgn:7020489",
        "tgn:1000001",
        "tgn:7012149",
        "tgn:2001281",
        "tgn:7007524",
        "tgn:7029392"
    ],
    "tgn:id":7020489,
    "tgn:name":"Mud Springs",
    "tgn:placetype":[
        "aat:300008697"
    ]
},
  "bbox": [],
  "geometry": {"coordinates":[-112.3167,45.8167],"type":"Point"}
}