{
  "id": 1066941,
  "type": "Feature",
  "properties": {
    "tgn:hierarchy":[
        "tgn:1066941",
        "tgn:1000004",
        "tgn:1001678",
        "tgn:1000111",
        "tgn:7029392"
    ],
    "tgn:id":1066941,
    "tgn:name":"Bose",
    "tgn:placetype":[
        "aat:300008347"
    ]
},
  "bbox": [],
  "geometry": {"coordinates":[106.5333,23.9167],"type":"Point"}
}