{
  "id": 7330596,
  "type": "Feature",
  "properties": {
    "tgn:hierarchy":[
        "tgn:7330596",
        "tgn:7002836",
        "tgn:7016622",
        "tgn:1000003",
        "tgn:1000095",
        "tgn:7029392"
    ],
    "tgn:id":7330596,
    "tgn:name":"Guincho, Punta del",
    "tgn:placetype":[
        "aat:300386846"
    ]
},
  "bbox": [],
  "geometry": {"coordinates":[-17.333333,28.116667],"type":"Point"}
}