<<<<<<< HEAD
{
  "id": 7249566,
  "type": "Feature",
  "properties": {
    "tgn:hierarchy":[
        "tgn:7249566",
        "tgn:7003466",
        "tgn:1000003",
        "tgn:1000063",
        "tgn:4012014",
        "tgn:7029392"
    ],
    "tgn:id":7249566,
    "tgn:name":"Mont de Houx",
    "tgn:placetype":[
        "aat:300008347"
    ]
},
  "bbox": [],
  "geometry": {"coordinates":[4.9,50.3],"type":"Point"}
}
=======
{"geometry":{"type":"Point","coordinates":[4.900000,50.300000]},"type":"Feature","properties":{"hierarchy":["tgn:7249566","tgn:7003466","tgn:1000003","tgn:1000063","tgn:4012014","tgn:7029392"],"placetype":["aat:300008347"],"id":7249566,"name:xx":"Mont de Houx"}}
>>>>>>> 03f74aca74312dbeaf24d7e61306dd6a786dc3d0
