{
  "id": 7485662,
  "type": "Feature",
  "properties": {
    "tgn:hierarchy":[
        "tgn:7485662",
        "tgn:1000004",
        "tgn:7490934",
        "tgn:1000141",
        "tgn:7029392"
    ],
    "tgn:id":7485662,
    "tgn:name":"Renci Tang",
    "tgn:placetype":[
        "aat:300007595"
    ]
},
  "bbox": [],
  "geometry": {"coordinates":[120.194167,22.978889],"type":"Point"}
}