{
  "id": 7484938,
  "type": "Feature",
  "properties": {
    "tgn:hierarchy":[
        "tgn:7484938",
        "tgn:1000004",
        "tgn:7491221",
        "tgn:1000141",
        "tgn:7029392"
    ],
    "tgn:id":7484938,
    "tgn:name":"Dazhu Xikou",
    "tgn:placetype":[
        "aat:300387057"
    ]
},
  "bbox": [],
  "geometry": {"coordinates":[120.946111,22.456111],"type":"Point"}
}