<<<<<<< HEAD
{
  "id": 7484938,
  "type": "Feature",
  "properties": {
    "tgn:hierarchy":[
        "tgn:7484938",
        "tgn:1000004",
        "tgn:7491221",
        "tgn:1000141",
        "tgn:7029392"
    ],
    "tgn:id":7484938,
    "tgn:name":"Dazhu Xikou",
    "tgn:placetype":[
        "aat:300387057"
    ]
},
  "bbox": [],
  "geometry": {"coordinates":[120.946111,22.456111],"type":"Point"}
}
=======
{"geometry":{"type":"Point","coordinates":[120.946111,22.456111]},"type":"Feature","properties":{"hierarchy":["tgn:7484938","tgn:1000004","tgn:7491221","tgn:1000141","tgn:7029392"],"placetype":["aat:300387057"],"id":7484938,"name:xx":"Dazhu Xikou"}}
>>>>>>> 03f74aca74312dbeaf24d7e61306dd6a786dc3d0
