<<<<<<< HEAD
{
  "id": 2407285,
  "type": "Feature",
  "properties": {
    "tgn:hierarchy":[
        "tgn:2407285",
        "tgn:7006450",
        "tgn:1000001",
        "tgn:7012149",
        "tgn:2000079",
        "tgn:7029392"
    ],
    "tgn:id":2407285,
    "tgn:name":"Hunting Point",
    "tgn:placetype":[
        "aat:300008850"
    ]
},
  "bbox": [],
  "geometry": {"coordinates":[-162.7,63.5667],"type":"Point"}
}
=======
{"geometry":{"type":"Point","coordinates":[-162.700000,63.566700]},"type":"Feature","properties":{"hierarchy":["tgn:2407285","tgn:7006450","tgn:1000001","tgn:7012149","tgn:2000079","tgn:7029392"],"placetype":["aat:300008850"],"id":2407285,"name:xx":"Hunting Point"}}
>>>>>>> 03f74aca74312dbeaf24d7e61306dd6a786dc3d0
