{
  "id": 7435502,
  "type": "Feature",
  "properties": {
    "tgn:hierarchy":[
        "tgn:7435502",
        "tgn:1000001",
        "tgn:7005589",
        "tgn:7005560",
        "tgn:7029392"
    ],
    "tgn:id":7435502,
    "tgn:name":"Toros, Sierra los",
    "tgn:placetype":[
        "aat:300008795"
    ]
},
  "bbox": [],
  "geometry": {"coordinates":[-99.816667,23.883333],"type":"Point"}
}