{
  "id": 7584834,
  "type": "Feature",
  "properties": {
    "tgn:hierarchy":[
        "tgn:7584834",
        "tgn:1000004",
        "tgn:7000198",
        "tgn:1001894",
        "tgn:7029392"
    ],
    "tgn:id":7584834,
    "tgn:name:en":"Hanum\u0101n S\u0101gar",
    "tgn:placetype":[
        "aat:300008680"
    ]
},
  "bbox": [],
  "geometry": {"coordinates":[78.800344,24.744387],"type":"Point"}
}