<<<<<<< HEAD
{
  "id": 7241508,
  "type": "Feature",
  "properties": {
    "tgn:hierarchy":[
        "tgn:7241508",
        "tgn:7003456",
        "tgn:1000003",
        "tgn:1000063",
        "tgn:7018236",
        "tgn:7029392"
    ],
    "tgn:id":7241508,
    "tgn:name":"Leemkuilen",
    "tgn:placetype":[
        "aat:300008347"
    ]
},
  "bbox": [],
  "geometry": {"coordinates":[4.683333,51.0],"type":"Point"}
}
=======
{"geometry":{"type":"Point","coordinates":[4.683333,51.000000]},"type":"Feature","properties":{"hierarchy":["tgn:7241508","tgn:7003456","tgn:1000003","tgn:1000063","tgn:7018236","tgn:7029392"],"placetype":["aat:300008347"],"id":7241508,"name:xx":"Leemkuilen"}}
>>>>>>> 03f74aca74312dbeaf24d7e61306dd6a786dc3d0
