{
  "id": 2071677,
  "type": "Feature",
  "properties": {
    "tgn:hierarchy":[
        "tgn:2071677",
        "tgn:1000001",
        "tgn:7012149",
        "tgn:1002440",
        "tgn:7007568",
        "tgn:7029392"
    ],
    "tgn:id":2071677,
    "tgn:name":"Piseco",
    "tgn:placetype":[
        "aat:300008347"
    ]
},
  "bbox": [],
  "geometry": {"coordinates":[-74.5167,43.4333],"type":"Point"}
}