<<<<<<< HEAD
{
  "id": 2402126,
  "type": "Feature",
  "properties": {
    "tgn:hierarchy":[
        "tgn:2402126",
        "tgn:1000001",
        "tgn:2001331",
        "tgn:7012149",
        "tgn:7007525",
        "tgn:7029392"
    ],
    "tgn:id":2402126,
    "tgn:name":"Horseshoe Valley",
    "tgn:placetype":[
        "aat:300008761"
    ]
},
  "bbox": [],
  "geometry": {"coordinates":[-100.7,42.2667],"type":"Point"}
}
=======
{"geometry":{"type":"Point","coordinates":[-100.700000,42.266700]},"type":"Feature","properties":{"hierarchy":["tgn:2402126","tgn:1000001","tgn:2001331","tgn:7012149","tgn:7007525","tgn:7029392"],"placetype":["aat:300008761"],"id":2402126,"name:xx":"Horseshoe Valley"}}
>>>>>>> 03f74aca74312dbeaf24d7e61306dd6a786dc3d0
