<<<<<<< HEAD
{
  "id": 2254796,
  "type": "Feature",
  "properties": {
    "tgn:hierarchy":[
        "tgn:2254796",
        "tgn:1000001",
        "tgn:2001173",
        "tgn:7012149",
        "tgn:7007523",
        "tgn:7029392"
    ],
    "tgn:id":2254796,
    "tgn:name":"Cooney Creek",
    "tgn:placetype":[
        "aat:300008706"
    ]
},
  "bbox": [],
  "geometry": {"coordinates":[-93.1167,38.2667],"type":"Point"}
}
=======
{"geometry":{"type":"Point","coordinates":[-93.116700,38.266700]},"type":"Feature","properties":{"hierarchy":["tgn:2254796","tgn:1000001","tgn:2001173","tgn:7012149","tgn:7007523","tgn:7029392"],"placetype":["aat:300008706"],"id":2254796,"name:xx":"Cooney Creek"}}
>>>>>>> 03f74aca74312dbeaf24d7e61306dd6a786dc3d0
