{
  "id": 2438345,
  "type": "Feature",
  "properties": {
    "tgn:hierarchy":[
        "tgn:2438345",
        "tgn:1000001",
        "tgn:2000781",
        "tgn:7012149",
        "tgn:7007255",
        "tgn:7029392"
    ],
    "tgn:id":2438345,
    "tgn:name":"Kings Fork",
    "tgn:placetype":[
        "aat:300008699"
    ]
},
  "bbox": [],
  "geometry": {"coordinates":[-84.0833,37.9167],"type":"Point"}
}