{
  "id": 2514452,
  "type": "Feature",
  "properties": {
    "tgn:hierarchy":[
        "tgn:2514452",
        "tgn:1000001",
        "tgn:7012149",
        "tgn:1003022",
        "tgn:7007252",
        "tgn:7029392"
    ],
    "tgn:id":2514452,
    "tgn:name":"Miller Ditch",
    "tgn:placetype":[
        "aat:300006075"
    ]
},
  "bbox": [],
  "geometry": {"coordinates":[-85.4333,41.1667],"type":"Point"}
}