{
  "id": 7199226,
  "type": "Feature",
  "properties": {
    "tgn:hierarchy":[
        "tgn:7199226",
        "tgn:1000003",
        "tgn:7003688",
        "tgn:7000084",
        "tgn:7029392"
    ],
    "tgn:id":7199226,
    "tgn:name":"Eichenheim",
    "tgn:placetype":[
        "aat:300000206"
    ]
},
  "bbox": [],
  "geometry": {"coordinates":[10.216667,54.383333],"type":"Point"}
}