{
  "id": 7021139,
  "type": "Feature",
  "properties": {
    "tgn:hierarchy":[
        "tgn:7021139",
        "tgn:1000001",
        "tgn:7012149",
        "tgn:2001029",
        "tgn:7007521",
        "tgn:7029392"
    ],
    "tgn:id":7021139,
    "tgn:name":"Egg Lake Impoundment",
    "tgn:placetype":[
        "aat:300006191"
    ]
},
  "bbox": [],
  "geometry": {"coordinates":[-93.9333,47.4833],"type":"Point"}
}