{
  "id": 7397711,
  "type": "Feature",
  "properties": {
    "tgn:hierarchy":[
        "tgn:7397711",
        "tgn:1000001",
        "tgn:1001893",
        "tgn:7005560",
        "tgn:7029392"
    ],
    "tgn:id":7397711,
    "tgn:name":"San Miguel Ca\u00f1adas",
    "tgn:placetype":[
        "aat:300008347"
    ]
},
  "bbox": [],
  "geometry": {"coordinates":[-99.341667,19.716667],"type":"Point"}
}