{
  "id": 2695398,
  "type": "Feature",
  "properties": {
    "tgn:hierarchy":[
        "tgn:2695398",
        "tgn:1000001",
        "tgn:2002148",
        "tgn:7012149",
        "tgn:7007919",
        "tgn:7029392"
    ],
    "tgn:id":2695398,
    "tgn:name":"Stiltner Creek",
    "tgn:placetype":[
        "aat:300008706"
    ]
},
  "bbox": [],
  "geometry": {"coordinates":[-82.1167,37.3167],"type":"Point"}
}