{
  "id": 2512926,
  "type": "Feature",
  "properties": {
    "tgn:hierarchy":[
        "tgn:2512926",
        "tgn:1000001",
        "tgn:7012149",
        "tgn:1002613",
        "tgn:7007710",
        "tgn:7029392"
    ],
    "tgn:id":2512926,
    "tgn:name":"Mill Creek",
    "tgn:placetype":[
        "aat:300008706"
    ]
},
  "bbox": [],
  "geometry": {"coordinates":[-76.75,41.3167],"type":"Point"}
}