{
  "id": 7313634,
  "type": "Feature",
  "properties": {
    "tgn:hierarchy":[
        "tgn:7313634",
        "tgn:1001768",
        "tgn:1000049",
        "tgn:1000002",
        "tgn:7029392"
    ],
    "tgn:id":7313634,
    "tgn:name":"La Vi\u00f1ita",
    "tgn:placetype":[
        "aat:300387200"
    ]
},
  "bbox": [],
  "geometry": {"coordinates":[-70.516667,-32.883333],"type":"Point"}
}