{
  "id": 7058937,
  "type": "Feature",
  "properties": {
    "tgn:hierarchy":[
        "tgn:7058937",
        "tgn:1000003",
        "tgn:7003142",
        "tgn:7003236",
        "tgn:1000080",
        "tgn:7029392"
    ],
    "tgn:id":7058937,
    "tgn:name":"Bocco, Passo del",
    "tgn:placetype":[
        "aat:300259572"
    ]
},
  "bbox": [],
  "geometry": {"coordinates":[9.45,44.416667],"type":"Point"}
}