{
  "id": 2264572,
  "type": "Feature",
  "properties": {
    "tgn:hierarchy":[
        "tgn:2264572",
        "tgn:1000001",
        "tgn:7012149",
        "tgn:2000476",
        "tgn:7007250",
        "tgn:7029392"
    ],
    "tgn:id":2264572,
    "tgn:name":"Crackerjack Mine",
    "tgn:placetype":[
        "aat:300000390"
    ]
},
  "bbox": [],
  "geometry": {"coordinates":[-115.65,45.6167],"type":"Point"}
}