{
  "id": 7028202,
  "type": "Feature",
  "properties": {
    "tgn:hierarchy":[
        "tgn:7028202",
        "tgn:7002445",
        "tgn:1000003",
        "tgn:7008157",
        "tgn:7008591",
        "tgn:7029392"
    ],
    "tgn:id":7028202,
    "tgn:name":"Westborough",
    "tgn:placetype":[
        "aat:300008347",
        "aat:300387007",
        "aat:300008372"
    ]
},
  "bbox": [],
  "geometry": {"coordinates":[-0.728,52.984],"type":"Point"}
}