<<<<<<< HEAD
{
  "id": 7471726,
  "type": "Feature",
  "properties": {
    "tgn:hierarchy":[
        "tgn:7471726",
        "tgn:7498210",
        "tgn:1000004",
        "tgn:1000141",
        "tgn:7029392"
    ],
    "tgn:id":7471726,
    "tgn:name":"Que Shi",
    "tgn:placetype":[
        "aat:300011692"
    ]
},
  "bbox": [],
  "geometry": {"coordinates":[119.983333,26.183333],"type":"Point"}
}
=======
{"geometry":{"type":"Point","coordinates":[119.983333,26.183333]},"type":"Feature","properties":{"hierarchy":["tgn:7471726","tgn:7498210","tgn:1000004","tgn:1000141","tgn:7029392"],"placetype":["aat:300011692"],"id":7471726,"name:xx":"Que Shi"}}
>>>>>>> 03f74aca74312dbeaf24d7e61306dd6a786dc3d0
