{
  "id": 7471726,
  "type": "Feature",
  "properties": {
    "tgn:hierarchy":[
        "tgn:7471726",
        "tgn:7498210",
        "tgn:1000004",
        "tgn:1000141",
        "tgn:7029392"
    ],
    "tgn:id":7471726,
    "tgn:name":"Que Shi",
    "tgn:placetype":[
        "aat:300011692"
    ]
},
  "bbox": [],
  "geometry": {"coordinates":[119.983333,26.183333],"type":"Point"}
}