{
  "id": 7204770,
  "type": "Feature",
  "properties": {
    "tgn:hierarchy":[
        "tgn:7204770",
        "tgn:7003692",
        "tgn:1000003",
        "tgn:7000084",
        "tgn:7029392"
    ],
    "tgn:id":7204770,
    "tgn:name":"B\u00fcchelbach",
    "tgn:placetype":[
        "aat:300387200"
    ]
},
  "bbox": [],
  "geometry": {"coordinates":[8.116667,48.616667],"type":"Point"}
}