{
  "id": 7225165,
  "type": "Feature",
  "properties": {
    "tgn:hierarchy":[
        "tgn:7225165",
        "tgn:7002711",
        "tgn:7001338",
        "tgn:1000003",
        "tgn:1000074",
        "tgn:7029392"
    ],
    "tgn:id":7225165,
    "tgn:name":"Racht\u00e1des",
    "tgn:placetype":[
        "aat:300008347"
    ]
},
  "bbox": [],
  "geometry": {"coordinates":[19.695,39.744167],"type":"Point"}
}