{
  "id": 2501147,
  "type": "Feature",
  "properties": {
    "tgn:hierarchy":[
        "tgn:2501147",
        "tgn:1000001",
        "tgn:7012149",
        "tgn:2002379",
        "tgn:7007923",
        "tgn:7029392"
    ],
    "tgn:id":2501147,
    "tgn:name":"McGee Reservoir",
    "tgn:placetype":[
        "aat:300006191"
    ]
},
  "bbox": [],
  "geometry": {"coordinates":[-108.65,44.2833],"type":"Point"}
}