{
  "id": 2787263,
  "type": "Feature",
  "properties": {
    "tgn:hierarchy":[
        "tgn:2787263",
        "tgn:1000001",
        "tgn:7012149",
        "tgn:1002776",
        "tgn:7007706",
        "tgn:7029392"
    ],
    "tgn:id":2787263,
    "tgn:name":"Zuber Cutoff",
    "tgn:placetype":[
        "aat:300008699"
    ]
},
  "bbox": [],
  "geometry": {"coordinates":[-84.6833,41.1833],"type":"Point"}
}