{
  "id": 1070326,
  "type": "Feature",
  "properties": {
    "tgn:hierarchy":[
        "tgn:1070326",
        "tgn:1000004",
        "tgn:1001390",
        "tgn:1000111",
        "tgn:7029392"
    ],
    "tgn:id":1070326,
    "tgn:name":"Mandehu",
    "tgn:placetype":[
        "aat:300008347"
    ]
},
  "bbox": [],
  "geometry": {"coordinates":[121.55,42.1167],"type":"Point"}
}