{
  "id": 7472121,
  "type": "Feature",
  "properties": {
    "tgn:hierarchy":[
        "tgn:7472121",
        "tgn:7001010",
        "tgn:1000004",
        "tgn:1000141",
        "tgn:7029392"
    ],
    "tgn:id":7472121,
    "tgn:name":"Heren Chezhan",
    "tgn:placetype":[
        "aat:300007783"
    ]
},
  "bbox": [],
  "geometry": {"coordinates":[121.713623,24.242955],"type":"Point"}
}