{
  "id": 1075891,
  "type": "Feature",
  "properties": {
    "tgn:hierarchy":[
        "tgn:1075891",
        "tgn:1000004",
        "tgn:1001832",
        "tgn:7000198",
        "tgn:7029392"
    ],
    "tgn:id":1075891,
    "tgn:name:en":"Kochugaon",
    "tgn:placetype":[
        "aat:300008347"
    ]
},
  "bbox": [],
  "geometry": {"coordinates":[90.076185,26.551792],"type":"Point"}
}