{
  "id": 1071361,
  "type": "Feature",
  "properties": {
    "tgn:hierarchy":[
        "tgn:1071361",
        "tgn:1000004",
        "tgn:7002087",
        "tgn:1000111",
        "tgn:7029392"
    ],
    "tgn:id":1071361,
    "tgn:name":"Sanxingchang",
    "tgn:placetype":[
        "aat:300008347"
    ]
},
  "bbox": [],
  "geometry": {"coordinates":[104.15,30.2667],"type":"Point"}
}