{
  "id": 2100177,
  "type": "Feature",
  "properties": {
    "tgn:hierarchy":[
        "tgn:2100177",
        "tgn:1000001",
        "tgn:7012149",
        "tgn:2001900",
        "tgn:7007825",
        "tgn:7029392"
    ],
    "tgn:id":2100177,
    "tgn:name":"Lynchburg",
    "tgn:placetype":[
        "aat:300008347"
    ]
},
  "bbox": [],
  "geometry": {"coordinates":[-86.3667,35.2667],"type":"Point"}
}