{
  "id": 2464145,
  "type": "Feature",
  "properties": {
    "tgn:hierarchy":[
        "tgn:2464145",
        "tgn:1000001",
        "tgn:7012149",
        "tgn:2002162",
        "tgn:7007919",
        "tgn:7029392"
    ],
    "tgn:id":2464145,
    "tgn:name":"Locust Knob",
    "tgn:placetype":[
        "aat:300008798"
    ]
},
  "bbox": [],
  "geometry": {"coordinates":[-80.5667,37.4333],"type":"Point"}
}