{
  "id": 7365501,
  "type": "Feature",
  "properties": {
    "tgn:hierarchy":[
        "tgn:7365501",
        "tgn:7005580",
        "tgn:1000001",
        "tgn:7005560",
        "tgn:7029392"
    ],
    "tgn:id":7365501,
    "tgn:name":"El Tabl\u00f3n",
    "tgn:placetype":[
        "aat:300008347"
    ]
},
  "bbox": [],
  "geometry": {"coordinates":[-92.966667,16.516667],"type":"Point"}
}