{
  "id": 2659411,
  "type": "Feature",
  "properties": {
    "tgn:hierarchy":[
        "tgn:2659411",
        "tgn:2000948",
        "tgn:1000001",
        "tgn:7012149",
        "tgn:7007520",
        "tgn:7029392"
    ],
    "tgn:id":2659411,
    "tgn:name":"Shinbines Drain",
    "tgn:placetype":[
        "aat:300006075"
    ]
},
  "bbox": [],
  "geometry": {"coordinates":[-84.1167,43.6667],"type":"Point"}
}