{
  "id": 2762109,
  "type": "Feature",
  "properties": {
    "tgn:hierarchy":[
        "tgn:2762109",
        "tgn:1000001",
        "tgn:2001429",
        "tgn:7012149",
        "tgn:7007566",
        "tgn:7029392"
    ],
    "tgn:id":2762109,
    "tgn:name":"West Side Tank South",
    "tgn:placetype":[
        "aat:300006191"
    ]
},
  "bbox": [],
  "geometry": {"coordinates":[-108.8167,33.5833],"type":"Point"}
}