<<<<<<< HEAD
{
  "id": 2255429,
  "type": "Feature",
  "properties": {
    "tgn:hierarchy":[
        "tgn:2255429",
        "tgn:1000001",
        "tgn:7012149",
        "tgn:2000910",
        "tgn:7007256",
        "tgn:7029392"
    ],
    "tgn:id":2255429,
    "tgn:name":"Coot Lake",
    "tgn:placetype":[
        "aat:300008680"
    ]
},
  "bbox": [],
  "geometry": {"coordinates":[-92.1833,29.7],"type":"Point"}
}
=======
{"geometry":{"type":"Point","coordinates":[-92.183300,29.700000]},"type":"Feature","properties":{"hierarchy":["tgn:2255429","tgn:1000001","tgn:7012149","tgn:2000910","tgn:7007256","tgn:7029392"],"placetype":["aat:300008680"],"id":2255429,"name:xx":"Coot Lake"}}
>>>>>>> 03f74aca74312dbeaf24d7e61306dd6a786dc3d0
