{
  "id": 2041345,
  "type": "Feature",
  "properties": {
    "tgn:hierarchy":[
        "tgn:2041345",
        "tgn:1000001",
        "tgn:1002240",
        "tgn:7012149",
        "tgn:7007255",
        "tgn:7029392"
    ],
    "tgn:id":2041345,
    "tgn:name":"Smiths Creek",
    "tgn:placetype":[
        "aat:300008347",
        "aat:300387210"
    ]
},
  "bbox": [],
  "geometry": {"coordinates":[-83.1833,38.45],"type":"Point"}
}