{
  "id": 7492866,
  "type": "Feature",
  "properties": {
    "tgn:hierarchy":[
        "tgn:7492866",
        "tgn:1000957",
        "tgn:1000004",
        "tgn:1000141",
        "tgn:7029392"
    ],
    "tgn:id":7492866,
    "tgn:name":"Shaziyuan",
    "tgn:placetype":[
        "aat:300008347"
    ]
},
  "bbox": [],
  "geometry": {"coordinates":[121.792462,25.139873],"type":"Point"}
}