{
  "id": 7476637,
  "type": "Feature",
  "properties": {
    "tgn:hierarchy":[
        "tgn:7476637",
        "tgn:1000004",
        "tgn:7004300",
        "tgn:1000141",
        "tgn:7029392"
    ],
    "tgn:id":7476637,
    "tgn:name":"Jinghai Gong",
    "tgn:placetype":[
        "aat:300007595"
    ]
},
  "bbox": [],
  "geometry": {"coordinates":[119.621202,23.546312],"type":"Point"}
}