{
  "id": 2031290,
  "type": "Feature",
  "properties": {
    "tgn:hierarchy":[
        "tgn:2031290",
        "tgn:1000001",
        "tgn:1002306",
        "tgn:7012149",
        "tgn:7007252",
        "tgn:7029392"
    ],
    "tgn:id":2031290,
    "tgn:name":"Carefree",
    "tgn:placetype":[
        "aat:300008347"
    ]
},
  "bbox": [],
  "geometry": {"coordinates":[-86.35,38.25],"type":"Point"}
}