{
  "id": 7469151,
  "type": "Feature",
  "properties": {
    "tgn:hierarchy":[
        "tgn:7469151",
        "tgn:1000004",
        "tgn:7001009",
        "tgn:1000141",
        "tgn:7029392"
    ],
    "tgn:id":7469151,
    "tgn:name":"Huamei",
    "tgn:placetype":[
        "aat:300008347"
    ]
},
  "bbox": [],
  "geometry": {"coordinates":[120.674438,24.231236],"type":"Point"}
}