{
  "id": 2567679,
  "type": "Feature",
  "properties": {
    "tgn:hierarchy":[
        "tgn:2567679",
        "tgn:1000001",
        "tgn:7012149",
        "tgn:2001722",
        "tgn:7007708",
        "tgn:7029392"
    ],
    "tgn:id":2567679,
    "tgn:name":"Paradise",
    "tgn:placetype":[
        "aat:300008347"
    ]
},
  "bbox": [],
  "geometry": {"coordinates":[-117.2167,45.9333],"type":"Point"}
}