<<<<<<< HEAD
{
  "id": 7486616,
  "type": "Feature",
  "properties": {
    "tgn:hierarchy":[
        "tgn:7486616",
        "tgn:1000004",
        "tgn:7490934",
        "tgn:1000141",
        "tgn:7029392"
    ],
    "tgn:id":7486616,
    "tgn:name":"Shangmaocaoshan",
    "tgn:placetype":[
        "aat:300008347"
    ]
},
  "bbox": [],
  "geometry": {"coordinates":[120.393889,22.918889],"type":"Point"}
}
=======
{"geometry":{"type":"Point","coordinates":[120.393889,22.918889]},"type":"Feature","properties":{"hierarchy":["tgn:7486616","tgn:1000004","tgn:7490934","tgn:1000141","tgn:7029392"],"placetype":["aat:300008347"],"id":7486616,"name:xx":"Shangmaocaoshan"}}
>>>>>>> 03f74aca74312dbeaf24d7e61306dd6a786dc3d0
