{
  "id": 7244510,
  "type": "Feature",
  "properties": {
    "tgn:hierarchy":[
        "tgn:7244510",
        "tgn:7003458",
        "tgn:1000003",
        "tgn:1000063",
        "tgn:7018236",
        "tgn:7029392"
    ],
    "tgn:id":7244510,
    "tgn:name":"Kwadebrug",
    "tgn:placetype":[
        "aat:300008347"
    ]
},
  "bbox": [],
  "geometry": {"coordinates":[3.267167,50.761242],"type":"Point"}
}