{
  "id": 7223683,
  "type": "Feature",
  "properties": {
    "tgn:hierarchy":[
        "tgn:7223683",
        "tgn:7002725",
        "tgn:7002715",
        "tgn:1000003",
        "tgn:1000074",
        "tgn:7029392"
    ],
    "tgn:id":7223683,
    "tgn:name":"Sarakatsana\u00edikon",
    "tgn:placetype":[
        "aat:300008347"
    ]
},
  "bbox": [],
  "geometry": {"coordinates":[23.283333,41.166667],"type":"Point"}
}