{
  "id": 7411149,
  "type": "Feature",
  "properties": {
    "tgn:hierarchy":[
        "tgn:7411149",
        "tgn:7005587",
        "tgn:1000001",
        "tgn:7005560",
        "tgn:7029392"
    ],
    "tgn:id":7411149,
    "tgn:name:es":"Cerro Colorado",
    "tgn:placetype":[
        "aat:300008347"
    ]
},
  "bbox": [],
  "geometry": {"coordinates":[-99.266667,20.866667],"type":"Point"}
}