{
  "id": 7281234,
  "type": "Feature",
  "properties": {
    "tgn:hierarchy":[
        "tgn:7281234",
        "tgn:1001702",
        "tgn:1000049",
        "tgn:1000002",
        "tgn:7029392"
    ],
    "tgn:id":7281234,
    "tgn:name":"Sesambre, Isla",
    "tgn:placetype":[
        "aat:300008791"
    ]
},
  "bbox": [],
  "geometry": {"coordinates":[-67.033333,-55.45],"type":"Point"}
}