{
  "id": 2334458,
  "type": "Feature",
  "properties": {
    "tgn:hierarchy":[
        "tgn:2334458",
        "tgn:1000001",
        "tgn:1002228",
        "tgn:7012149",
        "tgn:7007709",
        "tgn:7029392"
    ],
    "tgn:id":2334458,
    "tgn:name":"Forest Line Ditch",
    "tgn:placetype":[
        "aat:300006075"
    ]
},
  "bbox": [],
  "geometry": {"coordinates":[-76.4667,36.5167],"type":"Point"}
}