<<<<<<< HEAD
{
  "id": 2334458,
  "type": "Feature",
  "properties": {
    "tgn:hierarchy":[
        "tgn:2334458",
        "tgn:1000001",
        "tgn:1002228",
        "tgn:7012149",
        "tgn:7007709",
        "tgn:7029392"
    ],
    "tgn:id":2334458,
    "tgn:name":"Forest Line Ditch",
    "tgn:placetype":[
        "aat:300006075"
    ]
},
  "bbox": [],
  "geometry": {"coordinates":[-76.4667,36.5167],"type":"Point"}
}
=======
{"geometry":{"type":"Point","coordinates":[-76.466700,36.516700]},"type":"Feature","properties":{"hierarchy":["tgn:2334458","tgn:1000001","tgn:1002228","tgn:7012149","tgn:7007709","tgn:7029392"],"placetype":["aat:300006075"],"id":2334458,"name:xx":"Forest Line Ditch"}}
>>>>>>> 03f74aca74312dbeaf24d7e61306dd6a786dc3d0
