{
  "id": 7348438,
  "type": "Feature",
  "properties": {
    "tgn:hierarchy":[
        "tgn:7348438",
        "tgn:7002836",
        "tgn:7016622",
        "tgn:1000003",
        "tgn:1000095",
        "tgn:7029392"
    ],
    "tgn:id":7348438,
    "tgn:name":"Afur, Barranco",
    "tgn:placetype":[
        "aat:300266554",
        "aat:300008699"
    ]
},
  "bbox": [],
  "geometry": {"coordinates":[-16.25,28.566667],"type":"Point"}
}