{
  "id": 2382894,
  "type": "Feature",
  "properties": {
    "tgn:hierarchy":[
        "tgn:2382894",
        "tgn:1000001",
        "tgn:1002665",
        "tgn:7012149",
        "tgn:7007517",
        "tgn:7029392"
    ],
    "tgn:id":2382894,
    "tgn:name":"Hazen Hill",
    "tgn:placetype":[
        "aat:300008798"
    ]
},
  "bbox": [],
  "geometry": {"coordinates":[-71.65,42.5333],"type":"Point"}
}