{
  "id": 7257786,
  "type": "Feature",
  "properties": {
    "tgn:concordances":{
        "gn:id":"2758722"
    },
    "tgn:hierarchy":[
        "tgn:7257786",
        "tgn:1000003",
        "tgn:7006951",
        "tgn:7016845",
        "tgn:7029392"
    ],
    "tgn:id":7257786,
    "tgn:name:nl":"Boesingheliede",
    "tgn:placetype":[
        "aat:300008347"
    ]
},
  "bbox": [],
  "geometry": {"coordinates":[4.716667,52.366667],"type":"Point"}
}