{
  "id": 2262716,
  "type": "Feature",
  "properties": {
    "tgn:hierarchy":[
        "tgn:2262716",
        "tgn:1002176",
        "tgn:1000001",
        "tgn:7012149",
        "tgn:7007828",
        "tgn:7029392"
    ],
    "tgn:id":2262716,
    "tgn:name":"Cowan Branch",
    "tgn:placetype":[
        "aat:300008699"
    ]
},
  "bbox": [],
  "geometry": {"coordinates":[-73.1167,42.75],"type":"Point"}
}