{
  "id": 7272633,
  "type": "Feature",
  "properties": {
    "tgn:hierarchy":[
        "tgn:7272633",
        "tgn:1000003",
        "tgn:7003632",
        "tgn:7016845",
        "tgn:7029392"
    ],
    "tgn:id":7272633,
    "tgn:name:nl":"Vlietland",
    "tgn:placetype":[
        "aat:300008680"
    ]
},
  "bbox": [],
  "geometry": {"coordinates":[4.466667,52.116667],"type":"Point"}
}