{
  "id": 2747896,
  "type": "Feature",
  "properties": {
    "tgn:hierarchy":[
        "tgn:2747896",
        "tgn:1000001",
        "tgn:7012149",
        "tgn:2001711",
        "tgn:7007708",
        "tgn:7029392"
    ],
    "tgn:id":2747896,
    "tgn:name":"Walch Creek",
    "tgn:placetype":[
        "aat:300008706"
    ]
},
  "bbox": [],
  "geometry": {"coordinates":[-122.45,42.4333],"type":"Point"}
}