{
  "id": 7490767,
  "type": "Feature",
  "properties": {
    "tgn:hierarchy":[
        "tgn:7490767",
        "tgn:7487020",
        "tgn:1000004",
        "tgn:1000141",
        "tgn:7029392"
    ],
    "tgn:id":7490767,
    "tgn:name":"Tai'an",
    "tgn:placetype":[
        "aat:300008347"
    ]
},
  "bbox": [],
  "geometry": {"coordinates":[120.906344,24.446884],"type":"Point"}
}