{
  "id": 2280379,
  "type": "Feature",
  "properties": {
    "tgn:hierarchy":[
        "tgn:2280379",
        "tgn:1000001",
        "tgn:2000920",
        "tgn:7012149",
        "tgn:7007515",
        "tgn:7029392"
    ],
    "tgn:id":2280379,
    "tgn:name":"Decker Brook",
    "tgn:placetype":[
        "aat:300008699"
    ]
},
  "bbox": [],
  "geometry": {"coordinates":[-70.5333,43.9333],"type":"Point"}
}