{
  "id": 2399270,
  "type": "Feature",
  "properties": {
    "tgn:hierarchy":[
        "tgn:2399270",
        "tgn:1000001",
        "tgn:7012149",
        "tgn:2000836",
        "tgn:7007255",
        "tgn:7029392"
    ],
    "tgn:id":2399270,
    "tgn:name":"Horn Branch",
    "tgn:placetype":[
        "aat:300008699"
    ]
},
  "bbox": [],
  "geometry": {"coordinates":[-83.0667,37.0333],"type":"Point"}
}