{
  "id": 7315422,
  "type": "Feature",
  "properties": {
    "tgn:hierarchy":[
        "tgn:7315422",
        "tgn:1001630",
        "tgn:1000049",
        "tgn:1000002",
        "tgn:7029392"
    ],
    "tgn:id":7315422,
    "tgn:name":"Cha\u00f1aral, Llanos de",
    "tgn:placetype":[
        "aat:300008805"
    ]
},
  "bbox": [],
  "geometry": {"coordinates":[-71.416667,-29.066667],"type":"Point"}
}