{
  "id": 7165979,
  "type": "Feature",
  "properties": {
    "tgn:hierarchy":[
        "tgn:7165979",
        "tgn:1000003",
        "tgn:7003676",
        "tgn:7000084",
        "tgn:7029392"
    ],
    "tgn:id":7165979,
    "tgn:name":"Haus Middoge",
    "tgn:placetype":[
        "aat:300000206"
    ]
},
  "bbox": [],
  "geometry": {"coordinates":[7.85,53.633333],"type":"Point"}
}