{
  "id": 7109173,
  "type": "Feature",
  "properties": {
    "tgn:hierarchy":[
        "tgn:7109173",
        "tgn:1000003",
        "tgn:7003676",
        "tgn:7000084",
        "tgn:7029392"
    ],
    "tgn:id":7109173,
    "tgn:name":"Redemoi\u00dfel",
    "tgn:placetype":[
        "aat:300008347"
    ]
},
  "bbox": [],
  "geometry": {"coordinates":[10.933333,53.05],"type":"Point"}
}