{
  "id": 7576811,
  "type": "Feature",
  "properties": {
    "tgn:hierarchy":[
        "tgn:7576811",
        "tgn:1001828",
        "tgn:1000004",
        "tgn:7000198",
        "tgn:7029392"
    ],
    "tgn:id":7576811,
    "tgn:name:en":"Kottag\u016bdem",
    "tgn:placetype":[
        "aat:300008347"
    ]
},
  "bbox": [],
  "geometry": {"coordinates":[80.466667,18.066667],"type":"Point"}
}