{
  "id": 2147781,
  "type": "Feature",
  "properties": {
    "tgn:hierarchy":[
        "tgn:2147781",
        "tgn:7002659",
        "tgn:1000001",
        "tgn:7012149",
        "tgn:2000021",
        "tgn:7029392"
    ],
    "tgn:id":2147781,
    "tgn:name":"Barefoot Mountain",
    "tgn:placetype":[
        "aat:300008798"
    ]
},
  "bbox": [],
  "geometry": {"coordinates":[-86.7833,33.9833],"type":"Point"}
}