<<<<<<< HEAD
{
  "id": 7178623,
  "type": "Feature",
  "properties": {
    "tgn:hierarchy":[
        "tgn:7178623",
        "tgn:7003692",
        "tgn:1000003",
        "tgn:7000084",
        "tgn:7029392"
    ],
    "tgn:id":7178623,
    "tgn:name":"Guldeloh",
    "tgn:placetype":[
        "aat:300008863"
    ]
},
  "bbox": [],
  "geometry": {"coordinates":[8.933333,47.883333],"type":"Point"}
}
=======
{"geometry":{"type":"Point","coordinates":[8.933333,47.883333]},"type":"Feature","properties":{"hierarchy":["tgn:7178623","tgn:7003692","tgn:1000003","tgn:7000084","tgn:7029392"],"placetype":["aat:300008863"],"id":7178623,"name:xx":"Guldeloh"}}
>>>>>>> 03f74aca74312dbeaf24d7e61306dd6a786dc3d0
