{
  "id": 2514982,
  "type": "Feature",
  "properties": {
    "tgn:hierarchy":[
        "tgn:2514982",
        "tgn:1000001",
        "tgn:7012149",
        "tgn:2002046",
        "tgn:7007826",
        "tgn:7029392"
    ],
    "tgn:id":2514982,
    "tgn:name":"Miller Springs",
    "tgn:placetype":[
        "aat:300008699"
    ]
},
  "bbox": [],
  "geometry": {"coordinates":[-101.0167,34.0833],"type":"Point"}
}