{
  "id": 7048919,
  "type": "Feature",
  "properties": {
    "tgn:hierarchy":[
        "tgn:7048919",
        "tgn:7003170",
        "tgn:1000003",
        "tgn:7003125",
        "tgn:1000080",
        "tgn:7029392"
    ],
    "tgn:id":7048919,
    "tgn:name":"Cesoni",
    "tgn:placetype":[
        "aat:300008347"
    ]
},
  "bbox": [],
  "geometry": {"coordinates":[12.983333,42.383333],"type":"Point"}
}