{
  "id": 1125173,
  "type": "Feature",
  "properties": {
    "tgn:hierarchy":[
        "tgn:1125173",
        "tgn:1000004",
        "tgn:7029392"
    ],
    "tgn:id":1125173,
    "tgn:name":"Jhelum",
    "tgn:placetype":[
        "aat:300008707"
    ]
},
  "bbox": [],
  "geometry": {"coordinates":[72.1667,31.1667],"type":"Point"}
}