{
  "id": 7572394,
  "type": "Feature",
  "properties": {
    "tgn:hierarchy":[
        "tgn:7572394",
        "tgn:1000004",
        "tgn:7000198",
        "tgn:1001882",
        "tgn:7029392"
    ],
    "tgn:id":7572394,
    "tgn:name:en":"Honudaki",
    "tgn:placetype":[
        "aat:300008347"
    ]
},
  "bbox": [],
  "geometry": {"coordinates":[77.122222,13.213333],"type":"Point"}
}