{
  "id": 7346889,
  "type": "Feature",
  "properties": {
    "tgn:hierarchy":[
        "tgn:7346889",
        "tgn:7002810",
        "tgn:7001158",
        "tgn:1000003",
        "tgn:1000095",
        "tgn:7029392"
    ],
    "tgn:id":7346889,
    "tgn:name":"Arenillas de Villadiego",
    "tgn:placetype":[
        "aat:300008347"
    ]
},
  "bbox": [],
  "geometry": {"coordinates":[-3.983333,42.533333],"type":"Point"}
}