{
  "id": 7217682,
  "type": "Feature",
  "properties": {
    "tgn:hierarchy":[
        "tgn:7217682",
        "tgn:7002692",
        "tgn:7012056",
        "tgn:1000003",
        "tgn:1000074",
        "tgn:7029392"
    ],
    "tgn:id":7217682,
    "tgn:name":"Gianys\u00e1da, Nis\u00edda",
    "tgn:placetype":[
        "aat:300008791"
    ]
},
  "bbox": [],
  "geometry": {"coordinates":[26.174167,35.3275],"type":"Point"}
}