{
  "id": 2488831,
  "type": "Feature",
  "properties": {
    "tgn:hierarchy":[
        "tgn:2488831",
        "tgn:1000001",
        "tgn:7012149",
        "tgn:2000493",
        "tgn:7007250",
        "tgn:7029392"
    ],
    "tgn:id":2488831,
    "tgn:name":"Main Canal",
    "tgn:placetype":[
        "aat:300006075"
    ]
},
  "bbox": [],
  "geometry": {"coordinates":[-114.5333,42.3333],"type":"Point"}
}