{
  "id": 7360460,
  "type": "Feature",
  "properties": {
    "tgn:hierarchy":[
        "tgn:7360460",
        "tgn:7005583",
        "tgn:1000001",
        "tgn:7005560",
        "tgn:7029392"
    ],
    "tgn:id":7360460,
    "tgn:name":"Cuesta de Palmito",
    "tgn:placetype":[
        "aat:300008347"
    ]
},
  "bbox": [],
  "geometry": {"coordinates":[-104.466667,25.016667],"type":"Point"}
}