{
  "id": 2247134,
  "type": "Feature",
  "properties": {
    "tgn:hierarchy":[
        "tgn:2247134",
        "tgn:1000001",
        "tgn:1002207",
        "tgn:7012149",
        "tgn:7007240",
        "tgn:7029392"
    ],
    "tgn:id":2247134,
    "tgn:name":"Coconut Creek Park",
    "tgn:placetype":[
        "aat:300008347"
    ]
},
  "bbox": [],
  "geometry": {"coordinates":[-80.1667,26.2333],"type":"Point"}
}