<<<<<<< HEAD
{
  "id": 7470635,
  "type": "Feature",
  "properties": {
    "tgn:hierarchy":[
        "tgn:7470635",
        "tgn:1000004",
        "tgn:1000959",
        "tgn:1000141",
        "tgn:7029392"
    ],
    "tgn:id":7470635,
    "tgn:name":"Zhuweili",
    "tgn:placetype":[
        "aat:300055621"
    ]
},
  "bbox": [],
  "geometry": {"coordinates":[121.45,25.133333],"type":"Point"}
}
=======
{"geometry":{"type":"Point","coordinates":[121.450000,25.133333]},"type":"Feature","properties":{"hierarchy":["tgn:7470635","tgn:1000004","tgn:1000959","tgn:1000141","tgn:7029392"],"placetype":["aat:300055621"],"id":7470635,"name:xx":"Zhuweili"}}
>>>>>>> 03f74aca74312dbeaf24d7e61306dd6a786dc3d0
