{
  "id": 2351382,
  "type": "Feature",
  "properties": {
    "tgn:hierarchy":[
        "tgn:2351382",
        "tgn:1000001",
        "tgn:7012149",
        "tgn:2000226",
        "tgn:7007158",
        "tgn:7029392"
    ],
    "tgn:id":2351382,
    "tgn:name":"Glen Echo",
    "tgn:placetype":[
        "aat:300008347"
    ]
},
  "bbox": [],
  "geometry": {"coordinates":[-105.5833,40.6833],"type":"Point"}
}