{
  "id": 2565835,
  "type": "Feature",
  "properties": {
    "tgn:hierarchy":[
        "tgn:2565835",
        "tgn:7006450",
        "tgn:1000001",
        "tgn:7012149",
        "tgn:2000082",
        "tgn:7029392"
    ],
    "tgn:id":2565835,
    "tgn:name":"Palisade Point",
    "tgn:placetype":[
        "aat:300008850"
    ]
},
  "bbox": [],
  "geometry": {"coordinates":[-133.3667,55.5667],"type":"Point"}
}