{
  "id": 2503045,
  "type": "Feature",
  "properties": {
    "tgn:hierarchy":[
        "tgn:2503045",
        "tgn:1000001",
        "tgn:2000952",
        "tgn:7012149",
        "tgn:7007520",
        "tgn:7029392"
    ],
    "tgn:id":2503045,
    "tgn:name":"McNearney Lake",
    "tgn:placetype":[
        "aat:300008680"
    ]
},
  "bbox": [],
  "geometry": {"coordinates":[-84.95,46.4167],"type":"Point"}
}