{
  "id": 2177975,
  "type": "Feature",
  "properties": {
    "tgn:hierarchy":[
        "tgn:2177975",
        "tgn:1000001",
        "tgn:2001409",
        "tgn:7012149",
        "tgn:7007526",
        "tgn:7029392"
    ],
    "tgn:id":2177975,
    "tgn:name":"Blackbird Point",
    "tgn:placetype":[
        "aat:300008850"
    ]
},
  "bbox": [],
  "geometry": {"coordinates":[-119.0667,39.45],"type":"Point"}
}