<<<<<<< HEAD
{
  "id": 7171081,
  "type": "Feature",
  "properties": {
    "tgn:hierarchy":[
        "tgn:7171081",
        "tgn:7003669",
        "tgn:1000003",
        "tgn:7000084",
        "tgn:7029392"
    ],
    "tgn:id":7171081,
    "tgn:name":"Hirsch-Graben",
    "tgn:placetype":[
        "aat:300008699"
    ]
},
  "bbox": [],
  "geometry": {"coordinates":[11.15,47.95],"type":"Point"}
}
=======
{"geometry":{"type":"Point","coordinates":[11.150000,47.950000]},"type":"Feature","properties":{"hierarchy":["tgn:7171081","tgn:7003669","tgn:1000003","tgn:7000084","tgn:7029392"],"placetype":["aat:300008699"],"id":7171081,"name:xx":"Hirsch-Graben"}}
>>>>>>> 03f74aca74312dbeaf24d7e61306dd6a786dc3d0
