{
  "id": 2721930,
  "type": "Feature",
  "properties": {
    "tgn:hierarchy":[
        "tgn:2721930",
        "tgn:1000001",
        "tgn:1002245",
        "tgn:7012149",
        "tgn:7007568",
        "tgn:7029392"
    ],
    "tgn:id":2721930,
    "tgn:name":"Timber Lake",
    "tgn:placetype":[
        "aat:300006191"
    ]
},
  "bbox": [],
  "geometry": {"coordinates":[-78.6833,42.35],"type":"Point"}
}