{
  "id": 2281410,
  "type": "Feature",
  "properties": {
    "tgn:hierarchy":[
        "tgn:2281410",
        "tgn:1000001",
        "tgn:7012149",
        "tgn:1002645",
        "tgn:7007920",
        "tgn:7029392"
    ],
    "tgn:id":2281410,
    "tgn:name":"Deepwater Point",
    "tgn:placetype":[
        "aat:300008850"
    ]
},
  "bbox": [],
  "geometry": {"coordinates":[-123.0167,47.1167],"type":"Point"}
}