{
  "id": 1088380,
  "type": "Feature",
  "properties": {
    "tgn:hierarchy":[
        "tgn:1088380",
        "tgn:1000965",
        "tgn:7001242",
        "tgn:1000155",
        "tgn:7029392"
    ],
    "tgn:id":1088380,
    "tgn:name":"Kabou",
    "tgn:placetype":[
        "aat:300008347"
    ]
},
  "bbox": [],
  "geometry": {"coordinates":[21.7167,5.3333],"type":"Point"}
}