{
  "id": 2445172,
  "type": "Feature",
  "properties": {
    "tgn:hierarchy":[
        "tgn:2445172",
        "tgn:1000001",
        "tgn:7012149",
        "tgn:1002999",
        "tgn:7007526",
        "tgn:7029392"
    ],
    "tgn:id":2445172,
    "tgn:name":"Lemmy Spring",
    "tgn:placetype":[
        "aat:300008697"
    ]
},
  "bbox": [],
  "geometry": {"coordinates":[-119.5667,41.7667],"type":"Point"}
}