<<<<<<< HEAD
{
  "id": 2402658,
  "type": "Feature",
  "properties": {
    "tgn:hierarchy":[
        "tgn:2402658",
        "tgn:1000001",
        "tgn:2001414",
        "tgn:7012149",
        "tgn:7007526",
        "tgn:7029392"
    ],
    "tgn:id":2402658,
    "tgn:name":"Hot Pot",
    "tgn:placetype":[
        "aat:300008697"
    ]
},
  "bbox": [],
  "geometry": {"coordinates":[-117.1,40.9167],"type":"Point"}
}
=======
{"geometry":{"type":"Point","coordinates":[-117.100000,40.916700]},"type":"Feature","properties":{"hierarchy":["tgn:2402658","tgn:1000001","tgn:2001414","tgn:7012149","tgn:7007526","tgn:7029392"],"placetype":["aat:300008697"],"id":2402658,"name:xx":"Hot Pot"}}
>>>>>>> 03f74aca74312dbeaf24d7e61306dd6a786dc3d0
