{
  "id": 2454490,
  "type": "Feature",
  "properties": {
    "tgn:hierarchy":[
        "tgn:2454490",
        "tgn:1000001",
        "tgn:7012149",
        "tgn:2000481",
        "tgn:7007250",
        "tgn:7029392"
    ],
    "tgn:id":2454490,
    "tgn:name":"Little Deep Creek",
    "tgn:placetype":[
        "aat:300008706"
    ]
},
  "bbox": [],
  "geometry": {"coordinates":[-113.9667,45.5833],"type":"Point"}
}