{
  "id": 2762578,
  "type": "Feature",
  "properties": {
    "tgn:hierarchy":[
        "tgn:2762578",
        "tgn:1000001",
        "tgn:7012149",
        "tgn:1002467",
        "tgn:7007919",
        "tgn:7029392"
    ],
    "tgn:id":2762578,
    "tgn:name":"Westbriar",
    "tgn:placetype":[
        "aat:300008347"
    ]
},
  "bbox": [],
  "geometry": {"coordinates":[-77.55,37.6167],"type":"Point"}
}