<<<<<<< HEAD
{
  "id": 2407145,
  "type": "Feature",
  "properties": {
    "tgn:hierarchy":[
        "tgn:2407145",
        "tgn:1000001",
        "tgn:7012149",
        "tgn:2001930",
        "tgn:7007825",
        "tgn:7029392"
    ],
    "tgn:id":2407145,
    "tgn:name":"Hunters Hill",
    "tgn:placetype":[
        "aat:300008347"
    ]
},
  "bbox": [],
  "geometry": {"coordinates":[-86.9,36.0333],"type":"Point"}
}
=======
{"geometry":{"type":"Point","coordinates":[-86.900000,36.033300]},"type":"Feature","properties":{"hierarchy":["tgn:2407145","tgn:1000001","tgn:7012149","tgn:2001930","tgn:7007825","tgn:7029392"],"placetype":["aat:300008347"],"id":2407145,"name:xx":"Hunters Hill"}}
>>>>>>> 03f74aca74312dbeaf24d7e61306dd6a786dc3d0
