{
  "id": 2058368,
  "type": "Feature",
  "properties": {
    "tgn:hierarchy":[
        "tgn:2058368",
        "tgn:1000001",
        "tgn:7012149",
        "tgn:7016167",
        "tgn:7007523",
        "tgn:7029392"
    ],
    "tgn:id":2058368,
    "tgn:name":"Clarkson Valley",
    "tgn:placetype":[
        "aat:300008347"
    ]
},
  "bbox": [],
  "geometry": {"coordinates":[-90.5833,38.6167],"type":"Point"}
}