{
  "id": 7356105,
  "type": "Feature",
  "properties": {
    "tgn:hierarchy":[
        "tgn:7356105",
        "tgn:7005584",
        "tgn:1000001",
        "tgn:7005560",
        "tgn:7029392"
    ],
    "tgn:id":7356105,
    "tgn:name":"Camar\u00f3n",
    "tgn:placetype":[
        "aat:300008347"
    ]
},
  "bbox": [],
  "geometry": {"coordinates":[-100.333333,21.666667],"type":"Point"}
}