{
  "id": 2578500,
  "type": "Feature",
  "properties": {
    "tgn:hierarchy":[
        "tgn:2578500",
        "tgn:1000001",
        "tgn:2002370",
        "tgn:7012149",
        "tgn:7007923",
        "tgn:7029392"
    ],
    "tgn:id":2578500,
    "tgn:name":"Phil Reservoir",
    "tgn:placetype":[
        "aat:300006191"
    ]
},
  "bbox": [],
  "geometry": {"coordinates":[-105.0667,44.25],"type":"Point"}
}