{
  "id": 7200277,
  "type": "Feature",
  "properties": {
    "tgn:hierarchy":[
        "tgn:7200277",
        "tgn:7003669",
        "tgn:1000003",
        "tgn:7000084",
        "tgn:7029392"
    ],
    "tgn:id":7200277,
    "tgn:name":"D\u00fcrrenberg",
    "tgn:placetype":[
        "aat:300008777"
    ]
},
  "bbox": [],
  "geometry": {"coordinates":[10.466667,48.383333],"type":"Point"}
}