{
  "id": 2119176,
  "type": "Feature",
  "properties": {
    "tgn:hierarchy":[
        "tgn:2119176",
        "tgn:1000001",
        "tgn:2002263",
        "tgn:7012149",
        "tgn:7013961",
        "tgn:7029392"
    ],
    "tgn:id":2119176,
    "tgn:name":"Medley",
    "tgn:placetype":[
        "aat:300008347"
    ]
},
  "bbox": [],
  "geometry": {"coordinates":[-79.05,39.1667],"type":"Point"}
}