{
  "id": 2577380,
  "type": "Feature",
  "properties": {
    "tgn:hierarchy":[
        "tgn:2577380",
        "tgn:1000001",
        "tgn:7012149",
        "tgn:1002586",
        "tgn:7007710",
        "tgn:7029392"
    ],
    "tgn:id":2577380,
    "tgn:name":"Peters Store",
    "tgn:placetype":[
        "aat:300008347"
    ]
},
  "bbox": [],
  "geometry": {"coordinates":[-75.6333,40.7167],"type":"Point"}
}