{
  "id": 7219464,
  "type": "Feature",
  "properties": {
    "tgn:hierarchy":[
        "tgn:7219464",
        "tgn:7011161",
        "tgn:7002674",
        "tgn:1000003",
        "tgn:1000074",
        "tgn:7029392"
    ],
    "tgn:id":7219464,
    "tgn:name":"Volisso\u00fa, \u00d3rmos",
    "tgn:placetype":[
        "aat:300132316"
    ]
},
  "bbox": [],
  "geometry": {"coordinates":[25.919722,38.468611],"type":"Point"}
}