{
  "id": 1060550,
  "type": "Feature",
  "properties": {
    "tgn:hierarchy":[
        "tgn:1060550",
        "tgn:1000004",
        "tgn:7014474",
        "tgn:7018214",
        "tgn:7002435",
        "tgn:7029392"
    ],
    "tgn:id":1060550,
    "tgn:name":"Tyr",
    "tgn:placetype":[
        "aat:300008347"
    ]
},
  "bbox": [],
  "geometry": {"coordinates":[139.8333,52.9667],"type":"Point"}
}