{
  "id": 7381048,
  "type": "Feature",
  "properties": {
    "tgn:hierarchy":[
        "tgn:7381048",
        "tgn:7005581",
        "tgn:1000001",
        "tgn:7005560",
        "tgn:7029392"
    ],
    "tgn:id":7381048,
    "tgn:name":"Magueyes, Arroyo de los",
    "tgn:placetype":[
        "aat:300266554",
        "aat:300008699"
    ]
},
  "bbox": [],
  "geometry": {"coordinates":[-103.95,27.95],"type":"Point"}
}