{
  "id": 2429310,
  "type": "Feature",
  "properties": {
    "tgn:hierarchy":[
        "tgn:2429310",
        "tgn:1000001",
        "tgn:7012149",
        "tgn:2001067",
        "tgn:7007521",
        "tgn:7029392"
    ],
    "tgn:id":2429310,
    "tgn:name":"Junior Island",
    "tgn:placetype":[
        "aat:300008791"
    ]
},
  "bbox": [],
  "geometry": {"coordinates":[-92.8333,48.5333],"type":"Point"}
}