{
  "id": 2145722,
  "type": "Feature",
  "properties": {
    "tgn:hierarchy":[
        "tgn:2145722",
        "tgn:1000001",
        "tgn:2000457",
        "tgn:7012149",
        "tgn:7007250",
        "tgn:7029392"
    ],
    "tgn:id":2145722,
    "tgn:name":"Baldy Knoll",
    "tgn:placetype":[
        "aat:300008798"
    ]
},
  "bbox": [],
  "geometry": {"coordinates":[-112.4333,43.3333],"type":"Point"}
}