<<<<<<< HEAD
{
  "id": 7027301,
  "type": "Feature",
  "properties": {
    "tgn:hierarchy":[
        "tgn:7027301",
        "tgn:7002445",
        "tgn:1000003",
        "tgn:7026520",
        "tgn:7008591",
        "tgn:7029392"
    ],
    "tgn:id":7027301,
    "tgn:name":"Orton Longueville",
    "tgn:placetype":[
        "aat:300008347"
    ]
},
  "bbox": [],
  "geometry": {"coordinates":[-0.2833,52.55],"type":"Point"}
}
=======
{"geometry":{"type":"Point","coordinates":[-0.283300,52.550000]},"type":"Feature","properties":{"hierarchy":["tgn:7027301","tgn:7002445","tgn:1000003","tgn:7026520","tgn:7008591","tgn:7029392"],"placetype":["aat:300008347"],"id":7027301,"name:xx":"Orton Longueville"}}
>>>>>>> 03f74aca74312dbeaf24d7e61306dd6a786dc3d0
