{
  "id": 7027301,
  "type": "Feature",
  "properties": {
    "tgn:hierarchy":[
        "tgn:7027301",
        "tgn:7002445",
        "tgn:1000003",
        "tgn:7026520",
        "tgn:7008591",
        "tgn:7029392"
    ],
    "tgn:id":7027301,
    "tgn:name":"Orton Longueville",
    "tgn:placetype":[
        "aat:300008347"
    ]
},
  "bbox": [],
  "geometry": {"coordinates":[-0.2833,52.55],"type":"Point"}
}