{
  "id": 7385862,
  "type": "Feature",
  "properties": {
    "tgn:hierarchy":[
        "tgn:7385862",
        "tgn:7005586",
        "tgn:1000001",
        "tgn:7005560",
        "tgn:7029392"
    ],
    "tgn:id":7385862,
    "tgn:name":"Pedro Virgen",
    "tgn:placetype":[
        "aat:300006191"
    ]
},
  "bbox": [],
  "geometry": {"coordinates":[-103.866667,20.416667],"type":"Point"}
}