{
  "id": 2645903,
  "type": "Feature",
  "properties": {
    "tgn:hierarchy":[
        "tgn:2645903",
        "tgn:1000001",
        "tgn:7012149",
        "tgn:2000484",
        "tgn:7007250",
        "tgn:7029392"
    ],
    "tgn:id":2645903,
    "tgn:name":"Sawmill Gulch",
    "tgn:placetype":[
        "aat:300008761"
    ]
},
  "bbox": [],
  "geometry": {"coordinates":[-111.4833,43.6667],"type":"Point"}
}