{
  "id": 2729282,
  "type": "Feature",
  "properties": {
    "tgn:hierarchy":[
        "tgn:2729282",
        "tgn:1000001",
        "tgn:2001014",
        "tgn:7012149",
        "tgn:7007521",
        "tgn:7029392"
    ],
    "tgn:id":2729282,
    "tgn:name":"Trip Lake",
    "tgn:placetype":[
        "aat:300008680"
    ]
},
  "bbox": [],
  "geometry": {"coordinates":[-90.7333,48.0667],"type":"Point"}
}