{
  "id": 2514638,
  "type": "Feature",
  "properties": {
    "tgn:hierarchy":[
        "tgn:2514638",
        "tgn:1000001",
        "tgn:7012149",
        "tgn:2000278",
        "tgn:7007240",
        "tgn:7029392"
    ],
    "tgn:id":2514638,
    "tgn:name":"Miller Lake",
    "tgn:placetype":[
        "aat:300008680"
    ]
},
  "bbox": [],
  "geometry": {"coordinates":[-85.05,30.2667],"type":"Point"}
}