{
  "id": 2482246,
  "type": "Feature",
  "properties": {
    "tgn:hierarchy":[
        "tgn:2482246",
        "tgn:1000001",
        "tgn:7012149",
        "tgn:2000493",
        "tgn:7007250",
        "tgn:7029392"
    ],
    "tgn:id":2482246,
    "tgn:name":"Langford Flat Creek",
    "tgn:placetype":[
        "aat:300008706"
    ]
},
  "bbox": [],
  "geometry": {"coordinates":[-114.3333,42.1667],"type":"Point"}
}