{
  "id": 2188213,
  "type": "Feature",
  "properties": {
    "tgn:hierarchy":[
        "tgn:2188213",
        "tgn:1000001",
        "tgn:7012149",
        "tgn:2001451",
        "tgn:7007566",
        "tgn:7029392"
    ],
    "tgn:id":2188213,
    "tgn:name":"Bosque Lateral Number Two",
    "tgn:placetype":[
        "aat:300006075"
    ]
},
  "bbox": [],
  "geometry": {"coordinates":[-106.55,35.2833],"type":"Point"}
}