{
  "id": 7101771,
  "type": "Feature",
  "properties": {
    "tgn:hierarchy":[
        "tgn:7101771",
        "tgn:1000003",
        "tgn:7000094",
        "tgn:7000084",
        "tgn:7029392"
    ],
    "tgn:id":7101771,
    "tgn:name":"Rothenmoor",
    "tgn:placetype":[
        "aat:300008347"
    ]
},
  "bbox": [],
  "geometry": {"coordinates":[12.616667,53.65],"type":"Point"}
}