<<<<<<< HEAD
{
  "id": 2334823,
  "type": "Feature",
  "properties": {
    "tgn:hierarchy":[
        "tgn:2334823",
        "tgn:1000001",
        "tgn:7012149",
        "tgn:2002276",
        "tgn:7013961",
        "tgn:7029392"
    ],
    "tgn:id":2334823,
    "tgn:name":"Fork Ridge",
    "tgn:placetype":[
        "aat:300266640"
    ]
},
  "bbox": [],
  "geometry": {"coordinates":[-80.6333,39.8667],"type":"Point"}
}
=======
{"geometry":{"type":"Point","coordinates":[-80.633300,39.866700]},"type":"Feature","properties":{"hierarchy":["tgn:2334823","tgn:1000001","tgn:7012149","tgn:2002276","tgn:7013961","tgn:7029392"],"placetype":["aat:300266640"],"id":2334823,"name:xx":"Fork Ridge"}}
>>>>>>> 03f74aca74312dbeaf24d7e61306dd6a786dc3d0
