{
  "id": 2633428,
  "type": "Feature",
  "properties": {
    "tgn:hierarchy":[
        "tgn:2633428",
        "tgn:1000001",
        "tgn:2002136",
        "tgn:7012149",
        "tgn:7007828",
        "tgn:7029392"
    ],
    "tgn:id":2633428,
    "tgn:name":"Runnenede, Lake",
    "tgn:placetype":[
        "aat:300008680"
    ]
},
  "bbox": [],
  "geometry": {"coordinates":[-72.3833,43.4833],"type":"Point"}
}