{
  "id": 7175231,
  "type": "Feature",
  "properties": {
    "tgn:hierarchy":[
        "tgn:7175231",
        "tgn:1000003",
        "tgn:7000094",
        "tgn:7000084",
        "tgn:7029392"
    ],
    "tgn:id":7175231,
    "tgn:name":"Gro\u00df Flotow",
    "tgn:placetype":[
        "aat:300008347"
    ]
},
  "bbox": [],
  "geometry": {"coordinates":[12.983333,53.55],"type":"Point"}
}