{
  "id": 2273026,
  "type": "Feature",
  "properties": {
    "tgn:hierarchy":[
        "tgn:2273026",
        "tgn:1000001",
        "tgn:7012149",
        "tgn:7016056",
        "tgn:7007520",
        "tgn:7029392"
    ],
    "tgn:id":2273026,
    "tgn:name":"Cuttle Drain",
    "tgn:placetype":[
        "aat:300006075"
    ]
},
  "bbox": [],
  "geometry": {"coordinates":[-82.5333,42.8833],"type":"Point"}
}