{
  "id": 7419999,
  "type": "Feature",
  "properties": {
    "tgn:hierarchy":[
        "tgn:7419999",
        "tgn:7005584",
        "tgn:1000001",
        "tgn:7005560",
        "tgn:7029392"
    ],
    "tgn:id":7419999,
    "tgn:name":"El Naranjero",
    "tgn:placetype":[
        "aat:300008347"
    ]
},
  "bbox": [],
  "geometry": {"coordinates":[-100.777222,21.542222],"type":"Point"}
}