{
  "id": 7537623,
  "type": "Feature",
  "properties": {
    "tgn:hierarchy":[
        "tgn:7537623",
        "tgn:7001242",
        "tgn:7016833",
        "tgn:7001335",
        "tgn:7029392"
    ],
    "tgn:id":7537623,
    "tgn:name":"Rakeib, W\u00e2di el-",
    "tgn:placetype":[
        "aat:300379998"
    ]
},
  "bbox": [],
  "geometry": {"coordinates":[33.551667,30.630278],"type":"Point"}
}