<<<<<<< HEAD
{
  "id": 7374143,
  "type": "Feature",
  "properties": {
    "tgn:hierarchy":[
        "tgn:7374143",
        "tgn:1000001",
        "tgn:7005589",
        "tgn:7005560",
        "tgn:7029392"
    ],
    "tgn:id":7374143,
    "tgn:name":"La Anguila",
    "tgn:placetype":[
        "aat:300008347"
    ]
},
  "bbox": [],
  "geometry": {"coordinates":[-100.2,27.483333],"type":"Point"}
}
=======
{"geometry":{"type":"Point","coordinates":[-100.200000,27.483333]},"type":"Feature","properties":{"hierarchy":["tgn:7374143","tgn:1000001","tgn:7005589","tgn:7005560","tgn:7029392"],"placetype":["aat:300008347"],"id":7374143,"name:xx":"La Anguila"}}
>>>>>>> 03f74aca74312dbeaf24d7e61306dd6a786dc3d0
