{
  "id": 7448618,
  "type": "Feature",
  "properties": {
    "tgn:hierarchy":[
        "tgn:7448618",
        "tgn:7002445",
        "tgn:1000003",
        "tgn:7008165",
        "tgn:7008591",
        "tgn:7029392"
    ],
    "tgn:id":7448618,
    "tgn:name:en":"Spittal Hirst",
    "tgn:placetype":[
        "aat:300387036"
    ]
},
  "bbox": [],
  "geometry": {"coordinates":[-1.85,55.766667],"type":"Point"}
}