{
  "id": 7577498,
  "type": "Feature",
  "properties": {
    "tgn:hierarchy":[
        "tgn:7577498",
        "tgn:1000004",
        "tgn:7000198",
        "tgn:7016788",
        "tgn:7029392"
    ],
    "tgn:id":7577498,
    "tgn:name:en":"Karnisar",
    "tgn:placetype":[
        "aat:300008347"
    ]
},
  "bbox": [],
  "geometry": {"coordinates":[73.054664,28.343019],"type":"Point"}
}