{
  "id": 7206655,
  "type": "Feature",
  "properties": {
    "tgn:hierarchy":[
        "tgn:7206655",
        "tgn:7003669",
        "tgn:1000003",
        "tgn:7000084",
        "tgn:7029392"
    ],
    "tgn:id":7206655,
    "tgn:name":"Burgham",
    "tgn:placetype":[
        "aat:300008347"
    ]
},
  "bbox": [],
  "geometry": {"coordinates":[12.45,47.933333],"type":"Point"}
}