{
  "id": 2733037,
  "type": "Feature",
  "properties": {
    "tgn:hierarchy":[
        "tgn:2733037",
        "tgn:1000001",
        "tgn:7016172",
        "tgn:2000116",
        "tgn:7012149",
        "tgn:7029392"
    ],
    "tgn:id":2733037,
    "tgn:name":"Turkey Knob",
    "tgn:placetype":[
        "aat:300008798"
    ]
},
  "bbox": [],
  "geometry": {"coordinates":[-92.1333,35.6667],"type":"Point"}
}