{
  "id": 2513039,
  "type": "Feature",
  "properties": {
    "tgn:hierarchy":[
        "tgn:2513039",
        "tgn:1000001",
        "tgn:7012149",
        "tgn:7014344",
        "tgn:7007919",
        "tgn:7029392"
    ],
    "tgn:id":2513039,
    "tgn:name":"Mill Creek",
    "tgn:placetype":[
        "aat:300008706"
    ]
},
  "bbox": [],
  "geometry": {"coordinates":[-80.0833,37.25],"type":"Point"}
}