{
  "id": 7404615,
  "type": "Feature",
  "properties": {
    "tgn:hierarchy":[
        "tgn:7404615",
        "tgn:7005585",
        "tgn:1000001",
        "tgn:7005560",
        "tgn:7029392"
    ],
    "tgn:id":7404615,
    "tgn:name":"La Lima, Cerro",
    "tgn:placetype":[
        "aat:300008795"
    ]
},
  "bbox": [],
  "geometry": {"coordinates":[-99.875,17.0625],"type":"Point"}
}