<<<<<<< HEAD
{
  "id": 7177208,
  "type": "Feature",
  "properties": {
    "tgn:hierarchy":[
        "tgn:7177208",
        "tgn:1000003",
        "tgn:7003687",
        "tgn:7000084",
        "tgn:7029392"
    ],
    "tgn:id":7177208,
    "tgn:name":"Hagendorf",
    "tgn:placetype":[
        "aat:300008347"
    ]
},
  "bbox": [],
  "geometry": {"coordinates":[12.25,52.066667],"type":"Point"}
}
=======
{"geometry":{"type":"Point","coordinates":[12.250000,52.066667]},"type":"Feature","properties":{"hierarchy":["tgn:7177208","tgn:1000003","tgn:7003687","tgn:7000084","tgn:7029392"],"placetype":["aat:300008347"],"id":7177208,"name:xx":"Hagendorf"}}
>>>>>>> 03f74aca74312dbeaf24d7e61306dd6a786dc3d0
