{
  "id": 2176695,
  "type": "Feature",
  "properties": {
    "tgn:hierarchy":[
        "tgn:2176695",
        "tgn:1000001",
        "tgn:7006451",
        "tgn:2000092",
        "tgn:7012149",
        "tgn:7029392"
    ],
    "tgn:id":2176695,
    "tgn:name":"Black Mesa",
    "tgn:placetype":[
        "aat:300008798"
    ]
},
  "bbox": [],
  "geometry": {"coordinates":[-111.4333,35.6667],"type":"Point"}
}