{
  "id": 1096490,
  "type": "Feature",
  "properties": {
    "tgn:hierarchy":[
        "tgn:1096490",
        "tgn:7000490",
        "tgn:1000006",
        "tgn:7001830",
        "tgn:7029392"
    ],
    "tgn:id":1096490,
    "tgn:name":"Canungra",
    "tgn:placetype":[
        "aat:300008347"
    ]
},
  "bbox": [],
  "geometry": {"coordinates":[153.1667,-28.0333],"type":"Point"}
}