{
  "id": 7501382,
  "type": "Feature",
  "properties": {
    "tgn:hierarchy":[
        "tgn:7501382",
        "tgn:7488858",
        "tgn:1000004",
        "tgn:1000141",
        "tgn:7029392"
    ],
    "tgn:id":7501382,
    "tgn:name":"Fengguidou",
    "tgn:placetype":[
        "aat:300008347"
    ]
},
  "bbox": [],
  "geometry": {"coordinates":[120.856389,23.667222],"type":"Point"}
}