{
  "id": 2664312,
  "type": "Feature",
  "properties": {
    "tgn:hierarchy":[
        "tgn:2664312",
        "tgn:1000001",
        "tgn:1002479",
        "tgn:7012149",
        "tgn:7007240",
        "tgn:7029392"
    ],
    "tgn:id":2664312,
    "tgn:name":"Silver, Lake",
    "tgn:placetype":[
        "aat:300008680"
    ]
},
  "bbox": [],
  "geometry": {"coordinates":[-82.4833,28.0167],"type":"Point"}
}