{
  "id": 2311693,
  "type": "Feature",
  "properties": {
    "tgn:hierarchy":[
        "tgn:2311693",
        "tgn:1000001",
        "tgn:7012149",
        "tgn:1002818",
        "tgn:7007252",
        "tgn:7029392"
    ],
    "tgn:id":2311693,
    "tgn:name":"Edwards Ditch",
    "tgn:placetype":[
        "aat:300006075"
    ]
},
  "bbox": [],
  "geometry": {"coordinates":[-85.0333,40.0667],"type":"Point"}
}