<<<<<<< HEAD
{
  "id": 2250202,
  "type": "Feature",
  "properties": {
    "tgn:hierarchy":[
        "tgn:2250202",
        "tgn:1000001",
        "tgn:2001747",
        "tgn:7012149",
        "tgn:7007712",
        "tgn:7029392"
    ],
    "tgn:id":2250202,
    "tgn:name":"Collins Lake Dam",
    "tgn:placetype":[
        "aat:300006191"
    ]
},
  "bbox": [],
  "geometry": {"coordinates":[-82.35,34.8],"type":"Point"}
}
=======
{"geometry":{"type":"Point","coordinates":[-82.350000,34.800000]},"type":"Feature","properties":{"hierarchy":["tgn:2250202","tgn:1000001","tgn:2001747","tgn:7012149","tgn:7007712","tgn:7029392"],"placetype":["aat:300006191"],"id":2250202,"name:xx":"Collins Lake Dam"}}
>>>>>>> 03f74aca74312dbeaf24d7e61306dd6a786dc3d0
