{
  "id": 2785150,
  "type": "Feature",
  "properties": {
    "tgn:hierarchy":[
        "tgn:2785150",
        "tgn:1000001",
        "tgn:2001410",
        "tgn:7012149",
        "tgn:7007526",
        "tgn:7029392"
    ],
    "tgn:id":2785150,
    "tgn:name":"Yellow Pine Mine",
    "tgn:placetype":[
        "aat:300000390"
    ]
},
  "bbox": [],
  "geometry": {"coordinates":[-115.4833,35.85],"type":"Point"}
}