{
  "id": 7526871,
  "type": "Feature",
  "properties": {
    "tgn:hierarchy":[
        "tgn:7526871",
        "tgn:7001242",
        "tgn:7016833",
        "tgn:1001091",
        "tgn:7029392"
    ],
    "tgn:id":7526871,
    "tgn:name":"Qal'at Mu\u1e29ammad 'Al\u012b",
    "tgn:placetype":[
        "aat:300000833"
    ]
},
  "bbox": [],
  "geometry": {"coordinates":[31.268555,30.024988],"type":"Point"}
}