{
  "id": 7236812,
  "type": "Feature",
  "properties": {
    "tgn:hierarchy":[
        "tgn:7236812",
        "tgn:7002690",
        "tgn:7012056",
        "tgn:1000003",
        "tgn:1000074",
        "tgn:7029392"
    ],
    "tgn:id":7236812,
    "tgn:name":"\u00c1yios Io\u00e1nnis",
    "tgn:placetype":[
        "aat:300008347"
    ]
},
  "bbox": [],
  "geometry": {"coordinates":[24.783333,35.333333],"type":"Point"}
}