{
  "id": 1106288,
  "type": "Feature",
  "properties": {
    "tgn:hierarchy":[
        "tgn:1106288",
        "tgn:1000004",
        "tgn:7000198",
        "tgn:1001895",
        "tgn:7029392"
    ],
    "tgn:id":1106288,
    "tgn:name":"Salher",
    "tgn:placetype":[
        "aat:300008795"
    ]
},
  "bbox": [],
  "geometry": {"coordinates":[73.95,20.916667],"type":"Point"}
}