{
  "id": 2316358,
  "type": "Feature",
  "properties": {
    "tgn:hierarchy":[
        "tgn:2316358",
        "tgn:1000001",
        "tgn:7014423",
        "tgn:7012149",
        "tgn:7007517",
        "tgn:7029392"
    ],
    "tgn:id":2316358,
    "tgn:name":"Elmwood Station",
    "tgn:placetype":[
        "aat:300008347"
    ]
},
  "bbox": [],
  "geometry": {"coordinates":[-70.9667,42.0167],"type":"Point"}
}