{
  "id": 7088840,
  "type": "Feature",
  "properties": {
    "tgn:hierarchy":[
        "tgn:7088840",
        "tgn:7003669",
        "tgn:1000003",
        "tgn:7000084",
        "tgn:7029392"
    ],
    "tgn:id":7088840,
    "tgn:name":"Wahl",
    "tgn:placetype":[
        "aat:300008347"
    ]
},
  "bbox": [],
  "geometry": {"coordinates":[11.616667,50.25],"type":"Point"}
}