{
  "id": 2079829,
  "type": "Feature",
  "properties": {
    "tgn:hierarchy":[
        "tgn:2079829",
        "tgn:1000001",
        "tgn:7012149",
        "tgn:1002470",
        "tgn:7007706",
        "tgn:7029392"
    ],
    "tgn:id":2079829,
    "tgn:name":"Grelton",
    "tgn:placetype":[
        "aat:300008347"
    ]
},
  "bbox": [],
  "geometry": {"coordinates":[-83.9833,41.3333],"type":"Point"}
}