{
  "id": 2340752,
  "type": "Feature",
  "properties": {
    "tgn:hierarchy":[
        "tgn:2340752",
        "tgn:1000001",
        "tgn:7012149",
        "tgn:1002767",
        "tgn:7007920",
        "tgn:7029392"
    ],
    "tgn:id":2340752,
    "tgn:name":"Freshwater Creek",
    "tgn:placetype":[
        "aat:300008706"
    ]
},
  "bbox": [],
  "geometry": {"coordinates":[-123.8333,46.4833],"type":"Point"}
}