{
  "id": 2696855,
  "type": "Feature",
  "properties": {
    "tgn:hierarchy":[
        "tgn:2696855",
        "tgn:1000001",
        "tgn:7012149",
        "tgn:1002913",
        "tgn:7007919",
        "tgn:7029392"
    ],
    "tgn:id":2696855,
    "tgn:name":"Stones Corner",
    "tgn:placetype":[
        "aat:300008347"
    ]
},
  "bbox": [],
  "geometry": {"coordinates":[-77.3833,38.3167],"type":"Point"}
}