{
  "id": 2519425,
  "type": "Feature",
  "properties": {
    "tgn:hierarchy":[
        "tgn:2519425",
        "tgn:1000001",
        "tgn:7012149",
        "tgn:2000216",
        "tgn:7007158",
        "tgn:7029392"
    ],
    "tgn:id":2519425,
    "tgn:name":"Modlin Creek",
    "tgn:placetype":[
        "aat:300008706"
    ]
},
  "bbox": [],
  "geometry": {"coordinates":[-106.5833,40.0333],"type":"Point"}
}