<<<<<<< HEAD
{
  "id": 2708986,
  "type": "Feature",
  "properties": {
    "tgn:hierarchy":[
        "tgn:2708986",
        "tgn:1000001",
        "tgn:7012149",
        "tgn:2001718",
        "tgn:7007708",
        "tgn:7029392"
    ],
    "tgn:id":2708986,
    "tgn:name":"T J Spring",
    "tgn:placetype":[
        "aat:300008697"
    ]
},
  "bbox": [],
  "geometry": {"coordinates":[-118.1167,43.8667],"type":"Point"}
}
=======
{"geometry":{"type":"Point","coordinates":[-118.116700,43.866700]},"type":"Feature","properties":{"hierarchy":["tgn:2708986","tgn:1000001","tgn:7012149","tgn:2001718","tgn:7007708","tgn:7029392"],"placetype":["aat:300008697"],"id":2708986,"name:xx":"T J Spring"}}
>>>>>>> 03f74aca74312dbeaf24d7e61306dd6a786dc3d0
