{
  "id": 7419362,
  "type": "Feature",
  "properties": {
    "tgn:hierarchy":[
        "tgn:7419362",
        "tgn:1000001",
        "tgn:7005589",
        "tgn:7005560",
        "tgn:7029392"
    ],
    "tgn:id":7419362,
    "tgn:name:es":"El Oc\u00e9ano, R\u00edo",
    "tgn:placetype":[
        "aat:300008699"
    ]
},
  "bbox": [],
  "geometry": {"coordinates":[-100.43,27.278333],"type":"Point"}
}