{
  "id": 2182755,
  "type": "Feature",
  "properties": {
    "tgn:hierarchy":[
        "tgn:2182755",
        "tgn:1000001",
        "tgn:7012149",
        "tgn:2002111",
        "tgn:7007827",
        "tgn:7029392"
    ],
    "tgn:id":2182755,
    "tgn:name":"Blue Spring Valley",
    "tgn:placetype":[
        "aat:300386845"
    ]
},
  "bbox": [],
  "geometry": {"coordinates":[-112.6667,37.6833],"type":"Point"}
}