{
  "id": 7570753,
  "type": "Feature",
  "properties": {
    "tgn:hierarchy":[
        "tgn:7570753",
        "tgn:1000004",
        "tgn:7000198",
        "tgn:7000799",
        "tgn:7029392"
    ],
    "tgn:id":7570753,
    "tgn:name:en":"H\u0101patkh\u0101i Nad\u012b",
    "tgn:placetype":[
        "aat:300008699"
    ]
},
  "bbox": [],
  "geometry": {"coordinates":[74.174111,34.139813],"type":"Point"}
}