{
  "id": 7383184,
  "type": "Feature",
  "properties": {
    "tgn:hierarchy":[
        "tgn:7383184",
        "tgn:7005581",
        "tgn:1000001",
        "tgn:7005560",
        "tgn:7029392"
    ],
    "tgn:id":7383184,
    "tgn:name":"Oro, Arroyo del",
    "tgn:placetype":[
        "aat:300266554",
        "aat:300008699"
    ]
},
  "bbox": [],
  "geometry": {"coordinates":[-108.516667,30.116667],"type":"Point"}
}