{
  "id": 2678467,
  "type": "Feature",
  "properties": {
    "tgn:hierarchy":[
        "tgn:2678467",
        "tgn:1000001",
        "tgn:7012149",
        "tgn:2002334",
        "tgn:7007922",
        "tgn:7029392"
    ],
    "tgn:id":2678467,
    "tgn:name":"South Fork Copper River",
    "tgn:placetype":[
        "aat:300008707"
    ]
},
  "bbox": [],
  "geometry": {"coordinates":[-89.9667,45.15],"type":"Point"}
}