{
  "id": 2205494,
  "type": "Feature",
  "properties": {
    "tgn:hierarchy":[
        "tgn:2205494",
        "tgn:1000001",
        "tgn:7012149",
        "tgn:2001722",
        "tgn:7007708",
        "tgn:7029392"
    ],
    "tgn:id":2205494,
    "tgn:name":"Bull Creek",
    "tgn:placetype":[
        "aat:300008706"
    ]
},
  "bbox": [],
  "geometry": {"coordinates":[-116.6833,45.35],"type":"Point"}
}