{
  "id": 2547082,
  "type": "Feature",
  "properties": {
    "tgn:hierarchy":[
        "tgn:2547082",
        "tgn:1000001",
        "tgn:7012149",
        "tgn:7029392"
    ],
    "tgn:id":2547082,
    "tgn:name":"North Fork Powder Wash",
    "tgn:placetype":[
        "aat:300008761"
    ]
},
  "bbox": [],
  "geometry": {"coordinates":[-108.2833,40.9667],"type":"Point"}
}