{
  "id": 7510902,
  "type": "Feature",
  "properties": {
    "tgn:hierarchy":[
        "tgn:7510902",
        "tgn:1009227",
        "tgn:1000226",
        "tgn:7016822",
        "tgn:1000006",
        "tgn:7029392"
    ],
    "tgn:id":7510902,
    "tgn:name:en":"Turner Pass",
    "tgn:placetype":[
        "aat:300259572"
    ]
},
  "bbox": [],
  "geometry": {"coordinates":[168.033333,-44.616667],"type":"Point"}
}