{
  "id": 2372175,
  "type": "Feature",
  "properties": {
    "tgn:hierarchy":[
        "tgn:2372175",
        "tgn:1000001",
        "tgn:7012149",
        "tgn:1003019",
        "tgn:7007826",
        "tgn:7029392"
    ],
    "tgn:id":2372175,
    "tgn:name":"Halfmoon Lake",
    "tgn:placetype":[
        "aat:300008680"
    ]
},
  "bbox": [],
  "geometry": {"coordinates":[-96.0333,29.2833],"type":"Point"}
}