{
  "id": 7152758,
  "type": "Feature",
  "properties": {
    "tgn:hierarchy":[
        "tgn:7152758",
        "tgn:7003669",
        "tgn:1000003",
        "tgn:7000084",
        "tgn:7029392"
    ],
    "tgn:id":7152758,
    "tgn:name":"Kalten Graben",
    "tgn:placetype":[
        "aat:300008699"
    ]
},
  "bbox": [],
  "geometry": {"coordinates":[12.433333,47.733333],"type":"Point"}
}