<<<<<<< HEAD
{
  "id": 7022955,
  "type": "Feature",
  "properties": {
    "tgn:hierarchy":[
        "tgn:7022955",
        "tgn:1000001",
        "tgn:2001266",
        "tgn:7012149",
        "tgn:7007524",
        "tgn:7029392"
    ],
    "tgn:id":7022955,
    "tgn:name":"Fair Haven Colony",
    "tgn:placetype":[
        "aat:300008347"
    ]
},
  "bbox": [],
  "geometry": {"coordinates":[-111.6167,47.4],"type":"Point"}
}
=======
{"geometry":{"type":"Point","coordinates":[-111.616700,47.400000]},"type":"Feature","properties":{"hierarchy":["tgn:7022955","tgn:1000001","tgn:2001266","tgn:7012149","tgn:7007524","tgn:7029392"],"placetype":["aat:300008347"],"id":7022955,"name:xx":"Fair Haven Colony"}}
>>>>>>> 03f74aca74312dbeaf24d7e61306dd6a786dc3d0
