{
  "id": 7559464,
  "type": "Feature",
  "properties": {
    "tgn:hierarchy":[
        "tgn:7559464",
        "tgn:1000004",
        "tgn:1001871",
        "tgn:7000198",
        "tgn:7029392"
    ],
    "tgn:id":7559464,
    "tgn:name:en":"R\u0101ipur",
    "tgn:placetype":[
        "aat:300008347"
    ]
},
  "bbox": [],
  "geometry": {"coordinates":[77.021551,30.584972],"type":"Point"}
}