{
  "id": 1029687,
  "type": "Feature",
  "properties": {
    "tgn:hierarchy":[
        "tgn:1029687",
        "tgn:7002445",
        "tgn:1000003",
        "tgn:7008131",
        "tgn:7008591",
        "tgn:7029392"
    ],
    "tgn:id":1029687,
    "tgn:name":"Jaywick",
    "tgn:placetype":[
        "aat:300008347"
    ]
},
  "bbox": [],
  "geometry": {"coordinates":[1.1333,51.7833],"type":"Point"}
}