{
  "id": 2531976,
  "type": "Feature",
  "properties": {
    "tgn:hierarchy":[
        "tgn:2531976",
        "tgn:1000001",
        "tgn:7012149",
        "tgn:2001237",
        "tgn:7007523",
        "tgn:7029392"
    ],
    "tgn:id":2531976,
    "tgn:name":"Mulvinia Hill",
    "tgn:placetype":[
        "aat:300008798"
    ]
},
  "bbox": [],
  "geometry": {"coordinates":[-91.0333,36.55],"type":"Point"}
}