{
  "id": 2751405,
  "type": "Feature",
  "properties": {
    "tgn:hierarchy":[
        "tgn:2751405",
        "tgn:1000001",
        "tgn:2002107",
        "tgn:7012149",
        "tgn:7007827",
        "tgn:7029392"
    ],
    "tgn:id":2751405,
    "tgn:name":"Warm Springs",
    "tgn:placetype":[
        "aat:300008697"
    ]
},
  "bbox": [],
  "geometry": {"coordinates":[-110.8167,40.4333],"type":"Point"}
}