<<<<<<< HEAD
{
  "id": 2769864,
  "type": "Feature",
  "properties": {
    "tgn:hierarchy":[
        "tgn:2769864",
        "tgn:1000001",
        "tgn:7012149",
        "tgn:1003018",
        "tgn:7007919",
        "tgn:7029392"
    ],
    "tgn:id":2769864,
    "tgn:name":"Wilberts Corner",
    "tgn:placetype":[
        "aat:300008347"
    ]
},
  "bbox": [],
  "geometry": {"coordinates":[-76.6333,37.9667],"type":"Point"}
}
=======
{"geometry":{"type":"Point","coordinates":[-76.633300,37.966700]},"type":"Feature","properties":{"hierarchy":["tgn:2769864","tgn:1000001","tgn:7012149","tgn:1003018","tgn:7007919","tgn:7029392"],"placetype":["aat:300008347"],"id":2769864,"name:xx":"Wilberts Corner"}}
>>>>>>> 03f74aca74312dbeaf24d7e61306dd6a786dc3d0
