{
  "id": 7427899,
  "type": "Feature",
  "properties": {
    "tgn:hierarchy":[
        "tgn:7427899",
        "tgn:1000001",
        "tgn:7005594",
        "tgn:7005560",
        "tgn:7029392"
    ],
    "tgn:id":7427899,
    "tgn:name":"Los Chilares",
    "tgn:placetype":[
        "aat:300008347"
    ]
},
  "bbox": [],
  "geometry": {"coordinates":[-100.75,23.516667],"type":"Point"}
}