{
  "id": 2347220,
  "type": "Feature",
  "properties": {
    "tgn:hierarchy":[
        "tgn:2347220",
        "tgn:1000001",
        "tgn:7012149",
        "tgn:2002084",
        "tgn:7007826",
        "tgn:7029392"
    ],
    "tgn:id":2347220,
    "tgn:name":"Gentry Crossing",
    "tgn:placetype":[
        "aat:300008347"
    ]
},
  "bbox": [],
  "geometry": {"coordinates":[-99.3333,33.05],"type":"Point"}
}