{
  "id": 2073439,
  "type": "Feature",
  "properties": {
    "tgn:hierarchy":[
        "tgn:2073439",
        "tgn:1000001",
        "tgn:7012149",
        "tgn:2001529",
        "tgn:7007709",
        "tgn:7029392"
    ],
    "tgn:id":2073439,
    "tgn:name":"Allensville",
    "tgn:placetype":[
        "aat:300008347"
    ]
},
  "bbox": [],
  "geometry": {"coordinates":[-78.8833,36.3833],"type":"Point"}
}