{
  "id": 7082461,
  "type": "Feature",
  "properties": {
    "tgn:hierarchy":[
        "tgn:7082461",
        "tgn:1000003",
        "tgn:7003677",
        "tgn:7000084",
        "tgn:7029392"
    ],
    "tgn:id":7082461,
    "tgn:name":"Wiesen-Berg",
    "tgn:placetype":[
        "aat:300008777"
    ]
},
  "bbox": [],
  "geometry": {"coordinates":[6.45,50.533333],"type":"Point"}
}