{
  "id": 7317001,
  "type": "Feature",
  "properties": {
    "tgn:hierarchy":[
        "tgn:7317001",
        "tgn:1001630",
        "tgn:1000049",
        "tgn:1000002",
        "tgn:7029392"
    ],
    "tgn:id":7317001,
    "tgn:name":"C\u00f3ndor, Portezuelo",
    "tgn:placetype":[
        "aat:300259572"
    ]
},
  "bbox": [],
  "geometry": {"coordinates":[-70.533333,-29.033333],"type":"Point"}
}