{
  "id": 2082997,
  "type": "Feature",
  "properties": {
    "tgn:hierarchy":[
        "tgn:2082997",
        "tgn:1000001",
        "tgn:7012149",
        "tgn:2001688",
        "tgn:7007707",
        "tgn:7029392"
    ],
    "tgn:id":2082997,
    "tgn:name":"Chelsea",
    "tgn:placetype":[
        "aat:300008347"
    ]
},
  "bbox": [],
  "geometry": {"coordinates":[-95.4167,36.5333],"type":"Point"}
}