{
  "id": 7043229,
  "type": "Feature",
  "properties": {
    "tgn:hierarchy":[
        "tgn:7043229",
        "tgn:7003158",
        "tgn:1000003",
        "tgn:7003124",
        "tgn:1000080",
        "tgn:7029392"
    ],
    "tgn:id":7043229,
    "tgn:name":"Rabbies, Torrente",
    "tgn:placetype":[
        "aat:300008699"
    ]
},
  "bbox": [],
  "geometry": {"coordinates":[10.916667,46.35],"type":"Point"}
}