{
  "id": 2274549,
  "type": "Feature",
  "properties": {
    "tgn:hierarchy":[
        "tgn:2274549",
        "tgn:1000001",
        "tgn:7012149",
        "tgn:2001307",
        "tgn:7007524",
        "tgn:7029392"
    ],
    "tgn:id":2274549,
    "tgn:name":"Dallmann Lake",
    "tgn:placetype":[
        "aat:300008680"
    ]
},
  "bbox": [],
  "geometry": {"coordinates":[-109.2333,45.95],"type":"Point"}
}