{
  "id": 2482690,
  "type": "Feature",
  "properties": {
    "tgn:hierarchy":[
        "tgn:2482690",
        "tgn:1000001",
        "tgn:1002466",
        "tgn:7012149",
        "tgn:7007240",
        "tgn:7029392"
    ],
    "tgn:id":2482690,
    "tgn:name":"Lard Can Slough",
    "tgn:placetype":[
        "aat:300008905"
    ]
},
  "bbox": [],
  "geometry": {"coordinates":[-81.0833,26.3167],"type":"Point"}
}