{
  "id": 2249748,
  "type": "Feature",
  "properties": {
    "tgn:hierarchy":[
        "tgn:2249748",
        "tgn:1000001",
        "tgn:7012149",
        "tgn:7007157",
        "tgn:7029392"
    ],
    "tgn:id":2249748,
    "tgn:name":"Collayomi Valley",
    "tgn:placetype":[
        "aat:300008761"
    ]
},
  "bbox": [],
  "geometry": {"coordinates":[-122.6333,38.75],"type":"Point"}
}