<<<<<<< HEAD
{
  "id": 2404577,
  "type": "Feature",
  "properties": {
    "tgn:hierarchy":[
        "tgn:2404577",
        "tgn:1000001",
        "tgn:7012149",
        "tgn:2000806",
        "tgn:7007255",
        "tgn:7029392"
    ],
    "tgn:id":2404577,
    "tgn:name":"Hubbs Creek",
    "tgn:placetype":[
        "aat:300008706"
    ]
},
  "bbox": [],
  "geometry": {"coordinates":[-83.8833,36.7667],"type":"Point"}
}
=======
{"geometry":{"type":"Point","coordinates":[-83.883300,36.766700]},"type":"Feature","properties":{"hierarchy":["tgn:2404577","tgn:1000001","tgn:7012149","tgn:2000806","tgn:7007255","tgn:7029392"],"placetype":["aat:300008706"],"id":2404577,"name:xx":"Hubbs Creek"}}
>>>>>>> 03f74aca74312dbeaf24d7e61306dd6a786dc3d0
