{
  "id": 7322731,
  "type": "Feature",
  "properties": {
    "tgn:hierarchy":[
        "tgn:7322731",
        "tgn:7002810",
        "tgn:7001158",
        "tgn:1000003",
        "tgn:1000095",
        "tgn:7029392"
    ],
    "tgn:id":7322731,
    "tgn:name":"Salinillas de Bureba",
    "tgn:placetype":[
        "aat:300008347"
    ]
},
  "bbox": [],
  "geometry": {"coordinates":[-3.383333,42.55],"type":"Point"}
}