<<<<<<< HEAD
{
  "id": 7470899,
  "type": "Feature",
  "properties": {
    "tgn:hierarchy":[
        "tgn:7470899",
        "tgn:1000004",
        "tgn:7001009",
        "tgn:1000141",
        "tgn:7029392"
    ],
    "tgn:id":7470899,
    "tgn:name":"Erke Shan",
    "tgn:placetype":[
        "aat:300008798"
    ]
},
  "bbox": [],
  "geometry": {"coordinates":[120.800205,24.188688],"type":"Point"}
}
=======
{"geometry":{"type":"Point","coordinates":[120.800205,24.188688]},"type":"Feature","properties":{"hierarchy":["tgn:7470899","tgn:1000004","tgn:7001009","tgn:1000141","tgn:7029392"],"placetype":["aat:300008798"],"id":7470899,"name:xx":"Erke Shan"}}
>>>>>>> 03f74aca74312dbeaf24d7e61306dd6a786dc3d0
