{
  "id": 2742999,
  "type": "Feature",
  "properties": {
    "tgn:hierarchy":[
        "tgn:2742999",
        "tgn:1000001",
        "tgn:7012149",
        "tgn:7007157",
        "tgn:2000190",
        "tgn:7029392"
    ],
    "tgn:id":2742999,
    "tgn:name":"Van Spring",
    "tgn:placetype":[
        "aat:300008697"
    ]
},
  "bbox": [],
  "geometry": {"coordinates":[-122.85,40.15],"type":"Point"}
}