{
  "id": 7440603,
  "type": "Feature",
  "properties": {
    "tgn:hierarchy":[
        "tgn:7440603",
        "tgn:1000001",
        "tgn:7005589",
        "tgn:7005560",
        "tgn:7029392"
    ],
    "tgn:id":7440603,
    "tgn:name":"San Manuel",
    "tgn:placetype":[
        "aat:300008347"
    ]
},
  "bbox": [],
  "geometry": {"coordinates":[-99.266667,24.933333],"type":"Point"}
}