{
  "id": 2674490,
  "type": "Feature",
  "properties": {
    "tgn:hierarchy":[
        "tgn:2674490",
        "tgn:1002143",
        "tgn:1000001",
        "tgn:7012149",
        "tgn:7007252",
        "tgn:7029392"
    ],
    "tgn:id":2674490,
    "tgn:name":"Snyder Ditch",
    "tgn:placetype":[
        "aat:300006075"
    ]
},
  "bbox": [],
  "geometry": {"coordinates":[-85.1167,40.95],"type":"Point"}
}