{
  "id": 7275832,
  "type": "Feature",
  "properties": {
    "tgn:hierarchy":[
        "tgn:7275832",
        "tgn:1001630",
        "tgn:1000049",
        "tgn:1000002",
        "tgn:7029392"
    ],
    "tgn:id":7275832,
    "tgn:name":"Totoralillo, Bah\u00eda",
    "tgn:placetype":[
        "aat:300132316"
    ]
},
  "bbox": [],
  "geometry": {"coordinates":[-70.816667,-26.866667],"type":"Point"}
}