{
  "id": 2333151,
  "type": "Feature",
  "properties": {
    "tgn:hierarchy":[
        "tgn:2333151",
        "tgn:1000001",
        "tgn:7006451",
        "tgn:7012149",
        "tgn:2000100",
        "tgn:7029392"
    ],
    "tgn:id":2333151,
    "tgn:name":"Flying V Tank",
    "tgn:placetype":[
        "aat:300006191"
    ]
},
  "bbox": [],
  "geometry": {"coordinates":[-110.85,32.3167],"type":"Point"}
}