{
  "id": 5004221,
  "type": "Feature",
  "properties": {
    "tgn:hierarchy":[
        "tgn:5004221",
        "tgn:7002692",
        "tgn:7012056",
        "tgn:1000003",
        "tgn:1000074",
        "tgn:7029392"
    ],
    "tgn:id":5004221,
    "tgn:name":"Akhl\u00e1dhia",
    "tgn:placetype":[
        "aat:300008347",
        "aat:300008372"
    ]
},
  "bbox": [],
  "geometry": {"coordinates":[26.05,35.166667],"type":"Point"}
}