{
  "id": 2635397,
  "type": "Feature",
  "properties": {
    "tgn:hierarchy":[
        "tgn:2635397",
        "tgn:1000001",
        "tgn:7012149",
        "tgn:2001284",
        "tgn:7007524",
        "tgn:7029392"
    ],
    "tgn:id":2635397,
    "tgn:name":"SE SE Section 19 Mine",
    "tgn:placetype":[
        "aat:300000390"
    ]
},
  "bbox": [],
  "geometry": {"coordinates":[-111.6333,46.6833],"type":"Point"}
}