{
  "id": 7215243,
  "type": "Feature",
  "properties": {
    "tgn:hierarchy":[
        "tgn:7215243",
        "tgn:1000003",
        "tgn:7003676",
        "tgn:7000084",
        "tgn:7029392"
    ],
    "tgn:id":7215243,
    "tgn:name":"Bleckede, Forst",
    "tgn:placetype":[
        "aat:300008863"
    ]
},
  "bbox": [],
  "geometry": {"coordinates":[10.75,53.25],"type":"Point"}
}