{
  "id": 7445769,
  "type": "Feature",
  "properties": {
    "tgn:hierarchy":[
        "tgn:7445769",
        "tgn:7002444",
        "tgn:1000003",
        "tgn:7008082",
        "tgn:7008591",
        "tgn:7029392"
    ],
    "tgn:id":7445769,
    "tgn:name:en":"Rispond",
    "tgn:placetype":[
        "aat:300008347"
    ]
},
  "bbox": [],
  "geometry": {"coordinates":[-4.65,58.533333],"type":"Point"}
}