{
  "id": 2616374,
  "type": "Feature",
  "properties": {
    "tgn:hierarchy":[
        "tgn:2616374",
        "tgn:1000001",
        "tgn:2001432",
        "tgn:7012149",
        "tgn:7007566",
        "tgn:7029392"
    ],
    "tgn:id":2616374,
    "tgn:name":"Rice Canyon",
    "tgn:placetype":[
        "aat:300008761"
    ]
},
  "bbox": [],
  "geometry": {"coordinates":[-104.5833,36.9167],"type":"Point"}
}