{
  "id": 7414791,
  "type": "Feature",
  "properties": {
    "tgn:hierarchy":[
        "tgn:7414791",
        "tgn:1000001",
        "tgn:7005591",
        "tgn:7005560",
        "tgn:7029392"
    ],
    "tgn:id":7414791,
    "tgn:name:es":"Pascual Fuentes",
    "tgn:placetype":[
        "aat:300008347"
    ]
},
  "bbox": [],
  "geometry": {"coordinates":[-94.265556,16.445833],"type":"Point"}
}