<<<<<<< HEAD
{
  "id": 2400273,
  "type": "Feature",
  "properties": {
    "tgn:hierarchy":[
        "tgn:2400273",
        "tgn:1000001",
        "tgn:7012149",
        "tgn:2002381",
        "tgn:7007923",
        "tgn:7029392"
    ],
    "tgn:id":2400273,
    "tgn:name":"Horse Creek Ridge",
    "tgn:placetype":[
        "aat:300266640"
    ]
},
  "bbox": [],
  "geometry": {"coordinates":[-107.4,44.8333],"type":"Point"}
}
=======
{"geometry":{"type":"Point","coordinates":[-107.400000,44.833300]},"type":"Feature","properties":{"hierarchy":["tgn:2400273","tgn:1000001","tgn:7012149","tgn:2002381","tgn:7007923","tgn:7029392"],"placetype":["aat:300266640"],"id":2400273,"name:xx":"Horse Creek Ridge"}}
>>>>>>> 03f74aca74312dbeaf24d7e61306dd6a786dc3d0
