{
  "id": 2125094,
  "type": "Feature",
  "properties": {
    "tgn:hierarchy":[
        "tgn:2125094",
        "tgn:1000001",
        "tgn:7012149",
        "tgn:1002924",
        "tgn:7007568",
        "tgn:7029392"
    ],
    "tgn:id":2125094,
    "tgn:name":"Acabonack Harbor",
    "tgn:placetype":[
        "aat:300132316"
    ]
},
  "bbox": [],
  "geometry": {"coordinates":[-72.1333,41.0167],"type":"Point"}
}