{
  "id": 7172118,
  "type": "Feature",
  "properties": {
    "tgn:hierarchy":[
        "tgn:7172118",
        "tgn:1000003",
        "tgn:7003685",
        "tgn:7000084",
        "tgn:7029392"
    ],
    "tgn:id":7172118,
    "tgn:name":"Herrenteiche",
    "tgn:placetype":[
        "aat:300008688"
    ]
},
  "bbox": [],
  "geometry": {"coordinates":[12.333333,50.383333],"type":"Point"}
}