{
  "id": 7574761,
  "type": "Feature",
  "properties": {
    "tgn:hierarchy":[
        "tgn:7574761",
        "tgn:1001828",
        "tgn:1000004",
        "tgn:7000198",
        "tgn:7029392"
    ],
    "tgn:id":7574761,
    "tgn:name:en":"Maddul\u016bru",
    "tgn:placetype":[
        "aat:300008347"
    ]
},
  "bbox": [],
  "geometry": {"coordinates":[79.866667,15.466667],"type":"Point"}
}