{
  "id": 7098239,
  "type": "Feature",
  "properties": {
    "tgn:hierarchy":[
        "tgn:7098239",
        "tgn:1000003",
        "tgn:7003682",
        "tgn:7000084",
        "tgn:7029392"
    ],
    "tgn:id":7098239,
    "tgn:name":"Silzer Linde",
    "tgn:placetype":[
        "aat:300387200"
    ]
},
  "bbox": [],
  "geometry": {"coordinates":[7.933333,49.133333],"type":"Point"}
}