{
  "id": 7234116,
  "type": "Feature",
  "properties": {
    "tgn:hierarchy":[
        "tgn:7234116",
        "tgn:7011330",
        "tgn:7002674",
        "tgn:1000003",
        "tgn:1000074",
        "tgn:7029392"
    ],
    "tgn:id":7234116,
    "tgn:name":"Ak\u00e1ndia, Lim\u00edn",
    "tgn:placetype":[
        "aat:300008678"
    ]
},
  "bbox": [],
  "geometry": {"coordinates":[28.25,36.433333],"type":"Point"}
}