{
  "id": 7552472,
  "type": "Feature",
  "properties": {
    "tgn:hierarchy":[
        "tgn:7552472",
        "tgn:1000004",
        "tgn:7000198",
        "tgn:1001996",
        "tgn:7029392"
    ],
    "tgn:id":7552472,
    "tgn:name:en":"Palch\u0101n",
    "tgn:placetype":[
        "aat:300008347"
    ]
},
  "bbox": [],
  "geometry": {"coordinates":[77.186641,32.314306],"type":"Point"}
}