{
  "id": 7512873,
  "type": "Feature",
  "properties": {
    "tgn:hierarchy":[
        "tgn:7512873",
        "tgn:1009227",
        "tgn:1000226",
        "tgn:1000006",
        "tgn:7016850",
        "tgn:7029392"
    ],
    "tgn:id":7512873,
    "tgn:name:en":"Hawks Crag",
    "tgn:placetype":[
        "aat:300008749"
    ]
},
  "bbox": [],
  "geometry": {"coordinates":[171.783333,-41.866667],"type":"Point"}
}