{
  "id": 7592065,
  "type": "Feature",
  "properties": {
    "tgn:hierarchy":[
        "tgn:7592065",
        "tgn:1000004",
        "tgn:7000198",
        "tgn:7000799",
        "tgn:7029392"
    ],
    "tgn:id":7592065,
    "tgn:name:en":"Kundanpur",
    "tgn:placetype":[
        "aat:300008347"
    ]
},
  "bbox": [],
  "geometry": {"coordinates":[74.956509,32.67139],"type":"Point"}
}