{
  "id": 2427418,
  "type": "Feature",
  "properties": {
    "tgn:hierarchy":[
        "tgn:2427418",
        "tgn:1000001",
        "tgn:7012149",
        "tgn:7007158",
        "tgn:2000251",
        "tgn:7029392"
    ],
    "tgn:id":2427418,
    "tgn:name":"Jordan Number 1 Reservoir",
    "tgn:placetype":[
        "aat:300006191"
    ]
},
  "bbox": [],
  "geometry": {"coordinates":[-105.2667,38.85],"type":"Point"}
}