{
  "id": 7335369,
  "type": "Feature",
  "properties": {
    "tgn:hierarchy":[
        "tgn:7335369",
        "tgn:7002832",
        "tgn:7001158",
        "tgn:1000003",
        "tgn:1000095",
        "tgn:7029392"
    ],
    "tgn:id":7335369,
    "tgn:name":"Fr\u00eda, Arroyo de la",
    "tgn:placetype":[
        "aat:300266554",
        "aat:300008699"
    ]
},
  "bbox": [],
  "geometry": {"coordinates":[-4.633333,42.283333],"type":"Point"}
}