{
  "id": 2106590,
  "type": "Feature",
  "properties": {
    "tgn:hierarchy":[
        "tgn:2106590",
        "tgn:1000001",
        "tgn:7012149",
        "tgn:1002533",
        "tgn:7007826",
        "tgn:7029392"
    ],
    "tgn:id":2106590,
    "tgn:name":"Panna Maria",
    "tgn:placetype":[
        "aat:300008347"
    ]
},
  "bbox": [],
  "geometry": {"coordinates":[-97.8833,28.95],"type":"Point"}
}