{
  "id": 2675832,
  "type": "Feature",
  "properties": {
    "tgn:hierarchy":[
        "tgn:2675832",
        "tgn:1000001",
        "tgn:2001481",
        "tgn:7012149",
        "tgn:7007709",
        "tgn:7029392"
    ],
    "tgn:id":2675832,
    "tgn:name":"Song Branch",
    "tgn:placetype":[
        "aat:300008699"
    ]
},
  "bbox": [],
  "geometry": {"coordinates":[-84.1167,35.1333],"type":"Point"}
}