<<<<<<< HEAD
{
  "id": 7483415,
  "type": "Feature",
  "properties": {
    "tgn:hierarchy":[
        "tgn:7483415",
        "tgn:7487020",
        "tgn:1000004",
        "tgn:1000141",
        "tgn:7029392"
    ],
    "tgn:id":7483415,
    "tgn:name":"Fuxing Er Qiao",
    "tgn:placetype":[
        "aat:300007836"
    ]
},
  "bbox": [],
  "geometry": {"coordinates":[120.728056,24.430833],"type":"Point"}
}
=======
{"geometry":{"type":"Point","coordinates":[120.728056,24.430833]},"type":"Feature","properties":{"hierarchy":["tgn:7483415","tgn:7487020","tgn:1000004","tgn:1000141","tgn:7029392"],"placetype":["aat:300007836"],"id":7483415,"name:xx":"Fuxing Er Qiao"}}
>>>>>>> 03f74aca74312dbeaf24d7e61306dd6a786dc3d0
