{
  "id": 7483415,
  "type": "Feature",
  "properties": {
    "tgn:hierarchy":[
        "tgn:7483415",
        "tgn:7487020",
        "tgn:1000004",
        "tgn:1000141",
        "tgn:7029392"
    ],
    "tgn:id":7483415,
    "tgn:name":"Fuxing Er Qiao",
    "tgn:placetype":[
        "aat:300007836"
    ]
},
  "bbox": [],
  "geometry": {"coordinates":[120.728056,24.430833],"type":"Point"}
}