{
  "id": 2380504,
  "type": "Feature",
  "properties": {
    "tgn:hierarchy":[
        "tgn:2380504",
        "tgn:1000001",
        "tgn:7012149",
        "tgn:2000479",
        "tgn:7007250",
        "tgn:7029392"
    ],
    "tgn:id":2380504,
    "tgn:name":"Hauser Lake",
    "tgn:placetype":[
        "aat:300008680"
    ]
},
  "bbox": [],
  "geometry": {"coordinates":[-117.0167,47.7667],"type":"Point"}
}