{
  "id": 1124990,
  "type": "Feature",
  "properties": {
    "tgn:hierarchy":[
        "tgn:1124990",
        "tgn:1000004",
        "tgn:7000896",
        "tgn:1000120",
        "tgn:7029392"
    ],
    "tgn:id":1124990,
    "tgn:name":"Ishi",
    "tgn:placetype":[
        "aat:300008707"
    ]
},
  "bbox": [],
  "geometry": {"coordinates":[135.6333,34.5833],"type":"Point"}
}