{
  "id": 1018408,
  "type": "Feature",
  "properties": {
    "tgn:hierarchy":[
        "tgn:1018408",
        "tgn:7005585",
        "tgn:1000001",
        "tgn:7005560",
        "tgn:7029392"
    ],
    "tgn:id":1018408,
    "tgn:name":"Tecpan de Galeana",
    "tgn:placetype":[
        "aat:300008347"
    ]
},
  "bbox": [],
  "geometry": {"coordinates":[-100.683333,17.25],"type":"Point"}
}