{
  "id": 7304524,
  "type": "Feature",
  "properties": {
    "tgn:hierarchy":[
        "tgn:7304524",
        "tgn:7001155",
        "tgn:1000003",
        "tgn:7002790",
        "tgn:1000095",
        "tgn:7029392"
    ],
    "tgn:id":7304524,
    "tgn:name":"Embalses de Leurza",
    "tgn:placetype":[
        "aat:300006191"
    ]
},
  "bbox": [],
  "geometry": {"coordinates":[-1.716667,43.066667],"type":"Point"}
}