{
  "id": 2262787,
  "type": "Feature",
  "properties": {
    "tgn:hierarchy":[
        "tgn:2262787",
        "tgn:1000001",
        "tgn:7012149",
        "tgn:2001513",
        "tgn:7007709",
        "tgn:7029392"
    ],
    "tgn:id":2262787,
    "tgn:name":"Cowans Ford",
    "tgn:placetype":[
        "aat:300008347"
    ]
},
  "bbox": [],
  "geometry": {"coordinates":[-80.95,35.4167],"type":"Point"}
}