{
  "id": 7572275,
  "type": "Feature",
  "properties": {
    "tgn:hierarchy":[
        "tgn:7572275",
        "tgn:1000004",
        "tgn:7000198",
        "tgn:7016788",
        "tgn:7029392"
    ],
    "tgn:id":7572275,
    "tgn:name:en":"Gamri",
    "tgn:placetype":[
        "aat:300008347"
    ]
},
  "bbox": [],
  "geometry": {"coordinates":[73.619625,23.76833],"type":"Point"}
}