{
  "id": 2544057,
  "type": "Feature",
  "properties": {
    "tgn:hierarchy":[
        "tgn:2544057",
        "tgn:1000001",
        "tgn:7012149",
        "tgn:1003002",
        "tgn:7007922",
        "tgn:7029392"
    ],
    "tgn:id":2544057,
    "tgn:name":"North Branch Genesee Creek",
    "tgn:placetype":[
        "aat:300008706"
    ]
},
  "bbox": [],
  "geometry": {"coordinates":[-88.3667,42.9667],"type":"Point"}
}