<<<<<<< HEAD
{
  "id": 2407378,
  "type": "Feature",
  "properties": {
    "tgn:hierarchy":[
        "tgn:2407378",
        "tgn:1002366",
        "tgn:1000001",
        "tgn:7012149",
        "tgn:7007159",
        "tgn:7029392"
    ],
    "tgn:id":2407378,
    "tgn:name":"Huntington Pond",
    "tgn:placetype":[
        "aat:300008680"
    ]
},
  "bbox": [],
  "geometry": {"coordinates":[-73.35,41.3333],"type":"Point"}
}
=======
{"geometry":{"type":"Point","coordinates":[-73.350000,41.333300]},"type":"Feature","properties":{"hierarchy":["tgn:2407378","tgn:1002366","tgn:1000001","tgn:7012149","tgn:7007159","tgn:7029392"],"placetype":["aat:300008680"],"id":2407378,"name:xx":"Huntington Pond"}}
>>>>>>> 03f74aca74312dbeaf24d7e61306dd6a786dc3d0
