{
  "id": 2407378,
  "type": "Feature",
  "properties": {
    "tgn:hierarchy":[
        "tgn:2407378",
        "tgn:1002366",
        "tgn:1000001",
        "tgn:7012149",
        "tgn:7007159",
        "tgn:7029392"
    ],
    "tgn:id":2407378,
    "tgn:name":"Huntington Pond",
    "tgn:placetype":[
        "aat:300008680"
    ]
},
  "bbox": [],
  "geometry": {"coordinates":[-73.35,41.3333],"type":"Point"}
}