{
  "id": 2600955,
  "type": "Feature",
  "properties": {
    "tgn:hierarchy":[
        "tgn:2600955",
        "tgn:1000001",
        "tgn:7012149",
        "tgn:2000876",
        "tgn:7007256",
        "tgn:7029392"
    ],
    "tgn:id":2600955,
    "tgn:name":"Pumpkin Point",
    "tgn:placetype":[
        "aat:300008850"
    ]
},
  "bbox": [],
  "geometry": {"coordinates":[-91.2667,30.05],"type":"Point"}
}