{
  "id": 7220612,
  "type": "Feature",
  "properties": {
    "tgn:hierarchy":[
        "tgn:7220612",
        "tgn:4003773",
        "tgn:7001395",
        "tgn:1000003",
        "tgn:1000074",
        "tgn:7029392"
    ],
    "tgn:id":7220612,
    "tgn:name":"Pl\u00e1tanoi",
    "tgn:placetype":[
        "aat:300008347"
    ]
},
  "bbox": [],
  "geometry": {"coordinates":[21.656667,39.001111],"type":"Point"}
}