{
  "id": 2456289,
  "type": "Feature",
  "properties": {
    "tgn:hierarchy":[
        "tgn:2456289",
        "tgn:1000001",
        "tgn:7012149",
        "tgn:2001722",
        "tgn:7007708",
        "tgn:7029392"
    ],
    "tgn:id":2456289,
    "tgn:name":"Little Horse Creek",
    "tgn:placetype":[
        "aat:300008706"
    ]
},
  "bbox": [],
  "geometry": {"coordinates":[-116.9833,45.4167],"type":"Point"}
}