<<<<<<< HEAD
{
  "id": 7174090,
  "type": "Feature",
  "properties": {
    "tgn:hierarchy":[
        "tgn:7174090",
        "tgn:7000096",
        "tgn:1000003",
        "tgn:7000084",
        "tgn:7029392"
    ],
    "tgn:id":7174090,
    "tgn:name":"Gro\u00df Leine",
    "tgn:placetype":[
        "aat:300008347"
    ]
},
  "bbox": [],
  "geometry": {"coordinates":[14.066667,52.0],"type":"Point"}
}
=======
{"geometry":{"type":"Point","coordinates":[14.066667,52.000000]},"type":"Feature","properties":{"hierarchy":["tgn:7174090","tgn:7000096","tgn:1000003","tgn:7000084","tgn:7029392"],"placetype":["aat:300008347"],"id":7174090,"name:xx":"Gro\u00df Leine"}}
>>>>>>> 03f74aca74312dbeaf24d7e61306dd6a786dc3d0
