{
  "id": 2248064,
  "type": "Feature",
  "properties": {
    "tgn:hierarchy":[
        "tgn:2248064",
        "tgn:7002659",
        "tgn:1000001",
        "tgn:7012149",
        "tgn:2000057",
        "tgn:7029392"
    ],
    "tgn:id":2248064,
    "tgn:name":"Cold Branch",
    "tgn:placetype":[
        "aat:300008699"
    ]
},
  "bbox": [],
  "geometry": {"coordinates":[-86.2833,33.6333],"type":"Point"}
}