{
  "id": 7530937,
  "type": "Feature",
  "properties": {
    "tgn:hierarchy":[
        "tgn:7530937",
        "tgn:7001242",
        "tgn:7016833",
        "tgn:1001083",
        "tgn:7029392"
    ],
    "tgn:id":7530937,
    "tgn:name":"Masjid \u0162\u0101riq Bin Ziy\u0101d",
    "tgn:placetype":[
        "aat:300007544"
    ]
},
  "bbox": [],
  "geometry": {"coordinates":[31.197469,30.054402],"type":"Point"}
}