{
  "id": 7324250,
  "type": "Feature",
  "properties": {
    "tgn:hierarchy":[
        "tgn:7324250",
        "tgn:7008912",
        "tgn:7030216",
        "tgn:1000003",
        "tgn:1000095",
        "tgn:7029392"
    ],
    "tgn:id":7324250,
    "tgn:name":"Sant Andreu",
    "tgn:placetype":[
        "aat:300008347"
    ]
},
  "bbox": [],
  "geometry": {"coordinates":[1.306816,42.395468],"type":"Point"}
}