{
  "id": 7257870,
  "type": "Feature",
  "properties": {
    "tgn:concordances":{
        "gn:id":"2759398"
    },
    "tgn:hierarchy":[
        "tgn:7257870",
        "tgn:1000003",
        "tgn:7003626",
        "tgn:7016845",
        "tgn:7029392"
    ],
    "tgn:id":7257870,
    "tgn:name:nl":"Barsbeek",
    "tgn:placetype":[
        "aat:300008347"
    ]
},
  "bbox": [],
  "geometry": {"coordinates":[6.016667,52.65],"type":"Point"}
}