<<<<<<< HEAD
{
  "id": 7175898,
  "type": "Feature",
  "properties": {
    "tgn:hierarchy":[
        "tgn:7175898",
        "tgn:1000003",
        "tgn:7003689",
        "tgn:7000084",
        "tgn:7029392"
    ],
    "tgn:id":7175898,
    "tgn:name":"Gro\u00dfer Zimmer-Berg",
    "tgn:placetype":[
        "aat:300008777"
    ]
},
  "bbox": [],
  "geometry": {"coordinates":[10.433333,51.066667],"type":"Point"}
}
=======
{"geometry":{"type":"Point","coordinates":[10.433333,51.066667]},"type":"Feature","properties":{"hierarchy":["tgn:7175898","tgn:1000003","tgn:7003689","tgn:7000084","tgn:7029392"],"placetype":["aat:300008777"],"id":7175898,"name:xx":"Gro\u00dfer Zimmer-Berg"}}
>>>>>>> 03f74aca74312dbeaf24d7e61306dd6a786dc3d0
