<<<<<<< HEAD
{
  "id": 2159965,
  "type": "Feature",
  "properties": {
    "tgn:hierarchy":[
        "tgn:2159965",
        "tgn:1000001",
        "tgn:7012149",
        "tgn:2000809",
        "tgn:7007255",
        "tgn:7029392"
    ],
    "tgn:id":2159965,
    "tgn:name":"Beech Hollow",
    "tgn:placetype":[
        "aat:300008761"
    ]
},
  "bbox": [],
  "geometry": {"coordinates":[-82.7,38.0333],"type":"Point"}
}
=======
{"geometry":{"type":"Point","coordinates":[-82.700000,38.033300]},"type":"Feature","properties":{"hierarchy":["tgn:2159965","tgn:1000001","tgn:7012149","tgn:2000809","tgn:7007255","tgn:7029392"],"placetype":["aat:300008761"],"id":2159965,"name:xx":"Beech Hollow"}}
>>>>>>> 03f74aca74312dbeaf24d7e61306dd6a786dc3d0
