{
  "id": 2580624,
  "type": "Feature",
  "properties": {
    "tgn:hierarchy":[
        "tgn:2580624",
        "tgn:1000001",
        "tgn:1002239",
        "tgn:7012149",
        "tgn:7007706",
        "tgn:7029392"
    ],
    "tgn:id":2580624,
    "tgn:name":"Pigeon Ridge",
    "tgn:placetype":[
        "aat:300266640"
    ]
},
  "bbox": [],
  "geometry": {"coordinates":[-80.9333,40.4833],"type":"Point"}
}