<<<<<<< HEAD
{
  "id": 2252070,
  "type": "Feature",
  "properties": {
    "tgn:hierarchy":[
        "tgn:2252070",
        "tgn:1000001",
        "tgn:7012149",
        "tgn:1002733",
        "tgn:7007919",
        "tgn:7029392"
    ],
    "tgn:id":2252070,
    "tgn:name":"Condit Pond",
    "tgn:placetype":[
        "aat:300008680"
    ]
},
  "bbox": [],
  "geometry": {"coordinates":[-76.3167,37.9333],"type":"Point"}
}
=======
{"geometry":{"type":"Point","coordinates":[-76.316700,37.933300]},"type":"Feature","properties":{"hierarchy":["tgn:2252070","tgn:1000001","tgn:7012149","tgn:1002733","tgn:7007919","tgn:7029392"],"placetype":["aat:300008680"],"id":2252070,"name:xx":"Condit Pond"}}
>>>>>>> 03f74aca74312dbeaf24d7e61306dd6a786dc3d0
