{
  "id": 7282680,
  "type": "Feature",
  "properties": {
    "tgn:hierarchy":[
        "tgn:7282680",
        "tgn:1001637",
        "tgn:1000049",
        "tgn:1000002",
        "tgn:7029392"
    ],
    "tgn:id":7282680,
    "tgn:name":"Pe\u00f1uelas, Cerro",
    "tgn:placetype":[
        "aat:300008777"
    ]
},
  "bbox": [],
  "geometry": {"coordinates":[-72.016667,-36.233333],"type":"Point"}
}