{
  "id": 2249430,
  "type": "Feature",
  "properties": {
    "tgn:hierarchy":[
        "tgn:2249430",
        "tgn:1000001",
        "tgn:7012149",
        "tgn:2001671",
        "tgn:7007707",
        "tgn:7029392"
    ],
    "tgn:id":2249430,
    "tgn:name":"Coleman Hollow",
    "tgn:placetype":[
        "aat:300008761"
    ]
},
  "bbox": [],
  "geometry": {"coordinates":[-95.1833,36.0833],"type":"Point"}
}