{
  "id": 1135822,
  "type": "Feature",
  "properties": {
    "tgn:hierarchy":[
        "tgn:1135822",
        "tgn:7001242",
        "tgn:7016833",
        "tgn:7029392"
    ],
    "tgn:id":1135822,
    "tgn:name":"Ar-Rayya\u0101\u1e25 at-Tawf\u012bq\u012b",
    "tgn:placetype":[
        "aat:300006075"
    ]
},
  "bbox": [],
  "geometry": {"coordinates":[31.1167,30.1833],"type":"Point"}
}