{
  "id": 2538354,
  "type": "Feature",
  "properties": {
    "tgn:hierarchy":[
        "tgn:2538354",
        "tgn:1000001",
        "tgn:7012149",
        "tgn:2002339",
        "tgn:7007922",
        "tgn:7029392"
    ],
    "tgn:id":2538354,
    "tgn:name":"Neopit Mill Pond",
    "tgn:placetype":[
        "aat:300006191"
    ]
},
  "bbox": [],
  "geometry": {"coordinates":[-88.8167,44.9667],"type":"Point"}
}