{
  "id": 7410416,
  "type": "Feature",
  "properties": {
    "tgn:hierarchy":[
        "tgn:7410416",
        "tgn:1000001",
        "tgn:7005590",
        "tgn:7005560",
        "tgn:7029392"
    ],
    "tgn:id":7410416,
    "tgn:name":"Tres Palos",
    "tgn:placetype":[
        "aat:300008347"
    ]
},
  "bbox": [],
  "geometry": {"coordinates":[-101.683333,18.983333],"type":"Point"}
}