<<<<<<< HEAD
{
  "id": 7177508,
  "type": "Feature",
  "properties": {
    "tgn:hierarchy":[
        "tgn:7177508",
        "tgn:1000003",
        "tgn:7003677",
        "tgn:7000084",
        "tgn:7029392"
    ],
    "tgn:id":7177508,
    "tgn:name":"Hanwieh",
    "tgn:placetype":[
        "aat:300000206"
    ]
},
  "bbox": [],
  "geometry": {"coordinates":[8.85,52.15],"type":"Point"}
}
=======
{"geometry":{"type":"Point","coordinates":[8.850000,52.150000]},"type":"Feature","properties":{"hierarchy":["tgn:7177508","tgn:1000003","tgn:7003677","tgn:7000084","tgn:7029392"],"placetype":["aat:300000206"],"id":7177508,"name:xx":"Hanwieh"}}
>>>>>>> 03f74aca74312dbeaf24d7e61306dd6a786dc3d0
