{
  "id": 2345087,
  "type": "Feature",
  "properties": {
    "tgn:hierarchy":[
        "tgn:2345087",
        "tgn:7002659",
        "tgn:1000001",
        "tgn:2000003",
        "tgn:7012149",
        "tgn:7029392"
    ],
    "tgn:id":2345087,
    "tgn:name":"Gardner Mine",
    "tgn:placetype":[
        "aat:300000390"
    ]
},
  "bbox": [],
  "geometry": {"coordinates":[-87.0667,33.0667],"type":"Point"}
}