{
  "id": 2130792,
  "type": "Feature",
  "properties": {
    "tgn:hierarchy":[
        "tgn:2130792",
        "tgn:1000001",
        "tgn:7012149",
        "tgn:2001852",
        "tgn:7007825",
        "tgn:7029392"
    ],
    "tgn:id":2130792,
    "tgn:name":"Allison Spring",
    "tgn:placetype":[
        "aat:300008697"
    ]
},
  "bbox": [],
  "geometry": {"coordinates":[-86.1167,35.4833],"type":"Point"}
}