{
  "id": 2540910,
  "type": "Feature",
  "properties": {
    "tgn:hierarchy":[
        "tgn:2540910",
        "tgn:1000001",
        "tgn:1002190",
        "tgn:7012149",
        "tgn:7007523",
        "tgn:7029392"
    ],
    "tgn:id":2540910,
    "tgn:name":"Nichols Branch",
    "tgn:placetype":[
        "aat:300008699"
    ]
},
  "bbox": [],
  "geometry": {"coordinates":[-92.25,38.7167],"type":"Point"}
}