{
  "id": 7515138,
  "type": "Feature",
  "properties": {
    "tgn:hierarchy":[
        "tgn:7515138",
        "tgn:1009227",
        "tgn:1000226",
        "tgn:7016822",
        "tgn:1000006",
        "tgn:7029392"
    ],
    "tgn:id":7515138,
    "tgn:name:en":"Crayfish Rock",
    "tgn:placetype":[
        "aat:300011692"
    ]
},
  "bbox": [],
  "geometry": {"coordinates":[168.066667,-44.283333],"type":"Point"}
}