{
  "id": 2138836,
  "type": "Feature",
  "properties": {
    "tgn:hierarchy":[
        "tgn:2138836",
        "tgn:1000001",
        "tgn:7012149",
        "tgn:2001161",
        "tgn:7007522",
        "tgn:7029392"
    ],
    "tgn:id":2138836,
    "tgn:name":"Ashbrook Neck",
    "tgn:placetype":[
        "aat:300008850"
    ]
},
  "bbox": [],
  "geometry": {"coordinates":[-91.1833,33.4833],"type":"Point"}
}