{
  "id": 2734901,
  "type": "Feature",
  "properties": {
    "tgn:hierarchy":[
        "tgn:2734901",
        "tgn:1000001",
        "tgn:7012149",
        "tgn:2001708",
        "tgn:7007708",
        "tgn:7029392"
    ],
    "tgn:id":2734901,
    "tgn:name":"Twelvemile Creek",
    "tgn:placetype":[
        "aat:300008706"
    ]
},
  "bbox": [],
  "geometry": {"coordinates":[-119.05,44.9167],"type":"Point"}
}