{
  "id": 1058979,
  "type": "Feature",
  "properties": {
    "tgn:hierarchy":[
        "tgn:1058979",
        "tgn:7013670",
        "tgn:1000004",
        "tgn:7018214",
        "tgn:7002435",
        "tgn:7029392"
    ],
    "tgn:id":1058979,
    "tgn:name":"Romanovo",
    "tgn:placetype":[
        "aat:300008347"
    ]
},
  "bbox": [],
  "geometry": {"coordinates":[81.2667,52.6333],"type":"Point"}
}