{
  "id": 2496679,
  "type": "Feature",
  "properties": {
    "tgn:hierarchy":[
        "tgn:2496679",
        "tgn:1000001",
        "tgn:7012149",
        "tgn:1002730",
        "tgn:7007919",
        "tgn:7029392"
    ],
    "tgn:id":2496679,
    "tgn:name":"Mattawoman Creek",
    "tgn:placetype":[
        "aat:300008706"
    ]
},
  "bbox": [],
  "geometry": {"coordinates":[-75.9333,37.3667],"type":"Point"}
}