{
  "id": 7063326,
  "type": "Feature",
  "properties": {
    "tgn:hierarchy":[
        "tgn:7063326",
        "tgn:7003692",
        "tgn:1000003",
        "tgn:7000084",
        "tgn:7029392"
    ],
    "tgn:id":7063326,
    "tgn:name":"Atzenweiler",
    "tgn:placetype":[
        "aat:300008347"
    ]
},
  "bbox": [],
  "geometry": {"coordinates":[9.666667,47.75],"type":"Point"}
}