{
  "id": 1132685,
  "type": "Feature",
  "properties": {
    "tgn:hierarchy":[
        "tgn:1132685",
        "tgn:1000001",
        "tgn:7012149",
        "tgn:1002945",
        "tgn:7007710",
        "tgn:7029392"
    ],
    "tgn:id":1132685,
    "tgn:name":"Campbells Run",
    "tgn:placetype":[
        "aat:300008706"
    ]
},
  "bbox": [],
  "geometry": {"coordinates":[-77.4167,41.6833],"type":"Point"}
}