{
  "id": 7276836,
  "type": "Feature",
  "properties": {
    "tgn:hierarchy":[
        "tgn:7276836",
        "tgn:1001699",
        "tgn:1000049",
        "tgn:1000002",
        "tgn:7029392"
    ],
    "tgn:id":7276836,
    "tgn:name":"Chipu\u00e9, Estero",
    "tgn:placetype":[
        "aat:300185707"
    ]
},
  "bbox": [],
  "geometry": {"coordinates":[-72.916667,-41.716667],"type":"Point"}
}