<<<<<<< HEAD
{
  "id": 7054459,
  "type": "Feature",
  "properties": {
    "tgn:hierarchy":[
        "tgn:7054459",
        "tgn:1000003",
        "tgn:7003142",
        "tgn:7003236",
        "tgn:1000080",
        "tgn:7029392"
    ],
    "tgn:id":7054459,
    "tgn:name":"Mongiardino Ligure",
    "tgn:placetype":[
        "aat:300008347"
    ]
},
  "bbox": [],
  "geometry": {"coordinates":[9.066667,44.633333],"type":"Point"}
}
=======
{"geometry":{"type":"Point","coordinates":[9.066667,44.633333]},"type":"Feature","properties":{"hierarchy":["tgn:7054459","tgn:1000003","tgn:7003142","tgn:7003236","tgn:1000080","tgn:7029392"],"placetype":["aat:300008347"],"id":7054459,"name:xx":"Mongiardino Ligure"}}
>>>>>>> 03f74aca74312dbeaf24d7e61306dd6a786dc3d0
