{
  "id": 7087412,
  "type": "Feature",
  "properties": {
    "tgn:hierarchy":[
        "tgn:7087412",
        "tgn:1000003",
        "tgn:7003688",
        "tgn:7000084",
        "tgn:7029392"
    ],
    "tgn:id":7087412,
    "tgn:name":"Wanratt",
    "tgn:placetype":[
        "aat:300000206"
    ]
},
  "bbox": [],
  "geometry": {"coordinates":[9.183333,54.716667],"type":"Point"}
}