{
  "id": 2661211,
  "type": "Feature",
  "properties": {
    "tgn:hierarchy":[
        "tgn:2661211",
        "tgn:7006450",
        "tgn:1000001",
        "tgn:7012149",
        "tgn:2000086",
        "tgn:7029392"
    ],
    "tgn:id":2661211,
    "tgn:name":"Short River",
    "tgn:placetype":[
        "aat:300008707"
    ]
},
  "bbox": [],
  "geometry": {"coordinates":[-141.8833,61.0833],"type":"Point"}
}