{
  "id": 2203290,
  "type": "Feature",
  "properties": {
    "tgn:hierarchy":[
        "tgn:2203290",
        "tgn:1000001",
        "tgn:7012149",
        "tgn:7007255",
        "tgn:7029392"
    ],
    "tgn:id":2203290,
    "tgn:name":"Buckhorn Lake",
    "tgn:placetype":[
        "aat:300006191"
    ]
},
  "bbox": [],
  "geometry": {"coordinates":[-83.4667,37.3333],"type":"Point"}
}