{
  "id": 7590533,
  "type": "Feature",
  "properties": {
    "tgn:hierarchy":[
        "tgn:7590533",
        "tgn:1000004",
        "tgn:7000198",
        "tgn:7016722",
        "tgn:7029392"
    ],
    "tgn:id":7590533,
    "tgn:name:en":"Nanauta",
    "tgn:placetype":[
        "aat:300007783"
    ]
},
  "bbox": [],
  "geometry": {"coordinates":[77.439747,29.703873],"type":"Point"}
}