{
  "id": 1084608,
  "type": "Feature",
  "properties": {
    "tgn:hierarchy":[
        "tgn:1084608",
        "tgn:1000004",
        "tgn:1009446",
        "tgn:1001419",
        "tgn:1000135",
        "tgn:7029392"
    ],
    "tgn:id":1084608,
    "tgn:name":"San Fernando",
    "tgn:placetype":[
        "aat:300008347"
    ]
},
  "bbox": [],
  "geometry": {"coordinates":[120.3167,16.65],"type":"Point"}
}