{
  "id": 2115869,
  "type": "Feature",
  "properties": {
    "tgn:hierarchy":[
        "tgn:2115869",
        "tgn:1000001",
        "tgn:7012149",
        "tgn:1002899",
        "tgn:7007920",
        "tgn:7029392"
    ],
    "tgn:id":2115869,
    "tgn:name":"Gold Bar",
    "tgn:placetype":[
        "aat:300008347"
    ]
},
  "bbox": [],
  "geometry": {"coordinates":[-121.6833,47.85],"type":"Point"}
}