{
  "id": 2540215,
  "type": "Feature",
  "properties": {
    "tgn:hierarchy":[
        "tgn:2540215",
        "tgn:1000001",
        "tgn:7012149",
        "tgn:2001289",
        "tgn:7007524",
        "tgn:7029392"
    ],
    "tgn:id":2540215,
    "tgn:name":"Newlan Creek Reservoir",
    "tgn:placetype":[
        "aat:300006191"
    ]
},
  "bbox": [],
  "geometry": {"coordinates":[-110.9333,46.6333],"type":"Point"}
}