{
  "id": 2110870,
  "type": "Feature",
  "properties": {
    "tgn:hierarchy":[
        "tgn:2110870",
        "tgn:1000001",
        "tgn:7012149",
        "tgn:1002911",
        "tgn:7007919",
        "tgn:7029392"
    ],
    "tgn:id":2110870,
    "tgn:name":"Burdette",
    "tgn:placetype":[
        "aat:300008347",
        "aat:300387210"
    ]
},
  "bbox": [],
  "geometry": {"coordinates":[-76.8833,36.7667],"type":"Point"}
}