{
  "id": 7435985,
  "type": "Feature",
  "properties": {
    "tgn:hierarchy":[
        "tgn:7435985",
        "tgn:7005581",
        "tgn:1000001",
        "tgn:7005560",
        "tgn:7029392"
    ],
    "tgn:id":7435985,
    "tgn:name":"T\u00e9chore",
    "tgn:placetype":[
        "aat:300008347"
    ]
},
  "bbox": [],
  "geometry": {"coordinates":[-107.25,28.65],"type":"Point"}
}