<<<<<<< HEAD
{
  "id": 2768494,
  "type": "Feature",
  "properties": {
    "tgn:hierarchy":[
        "tgn:2768494",
        "tgn:1000001",
        "tgn:2002136",
        "tgn:7012149",
        "tgn:7007828",
        "tgn:7029392"
    ],
    "tgn:id":2768494,
    "tgn:name":"Whitewater Brook",
    "tgn:placetype":[
        "aat:300008699"
    ]
},
  "bbox": [],
  "geometry": {"coordinates":[-72.4667,43.8333],"type":"Point"}
}
=======
{"geometry":{"type":"Point","coordinates":[-72.466700,43.833300]},"type":"Feature","properties":{"hierarchy":["tgn:2768494","tgn:1000001","tgn:2002136","tgn:7012149","tgn:7007828","tgn:7029392"],"placetype":["aat:300008699"],"id":2768494,"name:xx":"Whitewater Brook"}}
>>>>>>> 03f74aca74312dbeaf24d7e61306dd6a786dc3d0
