{
  "id": 7225296,
  "type": "Feature",
  "properties": {
    "tgn:hierarchy":[
        "tgn:7225296",
        "tgn:7002681",
        "tgn:7001395",
        "tgn:1000003",
        "tgn:1000074",
        "tgn:7029392"
    ],
    "tgn:id":7225296,
    "tgn:name":"N\u00e9dha, \u00c1kra",
    "tgn:placetype":[
        "aat:300008850"
    ]
},
  "bbox": [],
  "geometry": {"coordinates":[23.416667,37.516667],"type":"Point"}
}