{
  "id": 2485600,
  "type": "Feature",
  "properties": {
    "tgn:hierarchy":[
        "tgn:2485600",
        "tgn:1000001",
        "tgn:7012149",
        "tgn:1002545",
        "tgn:7007157",
        "tgn:7029392"
    ],
    "tgn:id":2485600,
    "tgn:name":"Layman Area",
    "tgn:placetype":[
        "aat:300055621"
    ]
},
  "bbox": [],
  "geometry": {"coordinates":[-119.85,35.4833],"type":"Point"}
}