{
  "id": 7172773,
  "type": "Feature",
  "properties": {
    "tgn:hierarchy":[
        "tgn:7172773",
        "tgn:1000003",
        "tgn:7003685",
        "tgn:7000084",
        "tgn:7029392"
    ],
    "tgn:id":7172773,
    "tgn:name":"Herold",
    "tgn:placetype":[
        "aat:300008347"
    ]
},
  "bbox": [],
  "geometry": {"coordinates":[12.983333,50.666667],"type":"Point"}
}