{
  "id": 7085543,
  "type": "Feature",
  "properties": {
    "tgn:hierarchy":[
        "tgn:7085543",
        "tgn:1000003",
        "tgn:7003685",
        "tgn:7000084",
        "tgn:7029392"
    ],
    "tgn:id":7085543,
    "tgn:name":"Werbrigs-Berg",
    "tgn:placetype":[
        "aat:300008777"
    ]
},
  "bbox": [],
  "geometry": {"coordinates":[13.783333,51.35],"type":"Point"}
}