{
  "id": 2137920,
  "type": "Feature",
  "properties": {
    "tgn:hierarchy":[
        "tgn:2137920",
        "tgn:1000001",
        "tgn:7012149",
        "tgn:1002570",
        "tgn:7007706",
        "tgn:7029392"
    ],
    "tgn:id":2137920,
    "tgn:name":"Arrowhead Beach",
    "tgn:placetype":[
        "aat:300008347"
    ]
},
  "bbox": [],
  "geometry": {"coordinates":[-81.3833,41.6833],"type":"Point"}
}