{
  "id": 2688345,
  "type": "Feature",
  "properties": {
    "tgn:hierarchy":[
        "tgn:2688345",
        "tgn:1000001",
        "tgn:7012149",
        "tgn:1003042",
        "tgn:7007920",
        "tgn:7029392"
    ],
    "tgn:id":2688345,
    "tgn:name":"Spruce Creek",
    "tgn:placetype":[
        "aat:300008706"
    ]
},
  "bbox": [],
  "geometry": {"coordinates":[-121.1667,46.55],"type":"Point"}
}