{
  "id": 2381425,
  "type": "Feature",
  "properties": {
    "tgn:hierarchy":[
        "tgn:2381425",
        "tgn:1000001",
        "tgn:2001262",
        "tgn:7012149",
        "tgn:7007524",
        "tgn:7029392"
    ],
    "tgn:id":2381425,
    "tgn:name":"Hay Coulee",
    "tgn:placetype":[
        "aat:300008761"
    ]
},
  "bbox": [],
  "geometry": {"coordinates":[-108.9833,47.9667],"type":"Point"}
}