<<<<<<< HEAD
{
  "id": 7178148,
  "type": "Feature",
  "properties": {
    "tgn:hierarchy":[
        "tgn:7178148",
        "tgn:7003669",
        "tgn:1000003",
        "tgn:7000084",
        "tgn:7029392"
    ],
    "tgn:id":7178148,
    "tgn:name":"Gunderding",
    "tgn:placetype":[
        "aat:300000206"
    ]
},
  "bbox": [],
  "geometry": {"coordinates":[12.966667,48.5],"type":"Point"}
}
=======
{"geometry":{"type":"Point","coordinates":[12.966667,48.500000]},"type":"Feature","properties":{"hierarchy":["tgn:7178148","tgn:7003669","tgn:1000003","tgn:7000084","tgn:7029392"],"placetype":["aat:300000206"],"id":7178148,"name:xx":"Gunderding"}}
>>>>>>> 03f74aca74312dbeaf24d7e61306dd6a786dc3d0
