{
  "id": 7322030,
  "type": "Feature",
  "properties": {
    "tgn:hierarchy":[
        "tgn:7322030",
        "tgn:1001702",
        "tgn:1000049",
        "tgn:1000002",
        "tgn:7029392"
    ],
    "tgn:id":7322030,
    "tgn:name":"Baupr\u00e9s, Isla",
    "tgn:placetype":[
        "aat:300008791"
    ]
},
  "bbox": [],
  "geometry": {"coordinates":[-74.25,-52.066667],"type":"Point"}
}