{
  "id": 7219120,
  "type": "Feature",
  "properties": {
    "tgn:hierarchy":[
        "tgn:7219120",
        "tgn:7011161",
        "tgn:7002674",
        "tgn:1000003",
        "tgn:1000074",
        "tgn:7029392"
    ],
    "tgn:id":7219120,
    "tgn:name":"Maragko\u00fa, Vrachonis\u00edda",
    "tgn:placetype":[
        "aat:300008791"
    ]
},
  "bbox": [],
  "geometry": {"coordinates":[25.602222,38.531944],"type":"Point"}
}