{
  "id": 7084155,
  "type": "Feature",
  "properties": {
    "tgn:hierarchy":[
        "tgn:7084155",
        "tgn:1000003",
        "tgn:7003677",
        "tgn:7000084",
        "tgn:7029392"
    ],
    "tgn:id":7084155,
    "tgn:name":"Wessel",
    "tgn:placetype":[
        "aat:300000206"
    ]
},
  "bbox": [],
  "geometry": {"coordinates":[8.283333,51.733333],"type":"Point"}
}