<<<<<<< HEAD
{
  "id": 2409147,
  "type": "Feature",
  "properties": {
    "tgn:hierarchy":[
        "tgn:2409147",
        "tgn:1000001",
        "tgn:7012149",
        "tgn:7007157",
        "tgn:1002675",
        "tgn:7029392"
    ],
    "tgn:id":2409147,
    "tgn:name":"Ice Lake",
    "tgn:placetype":[
        "aat:300008680"
    ]
},
  "bbox": [],
  "geometry": {"coordinates":[-119.4167,38.1],"type":"Point"}
}
=======
{"geometry":{"type":"Point","coordinates":[-119.416700,38.100000]},"type":"Feature","properties":{"hierarchy":["tgn:2409147","tgn:1000001","tgn:7012149","tgn:7007157","tgn:1002675","tgn:7029392"],"placetype":["aat:300008680"],"id":2409147,"name:xx":"Ice Lake"}}
>>>>>>> 03f74aca74312dbeaf24d7e61306dd6a786dc3d0
