{
  "id": 7291865,
  "type": "Feature",
  "properties": {
    "tgn:hierarchy":[
        "tgn:7291865",
        "tgn:7002464",
        "tgn:1000049",
        "tgn:1000002",
        "tgn:7029392"
    ],
    "tgn:id":7291865,
    "tgn:name":"Enga\u00f1adora, Pampa",
    "tgn:placetype":[
        "aat:300008805"
    ]
},
  "bbox": [],
  "geometry": {"coordinates":[-69.883333,-20.85],"type":"Point"}
}