{
  "id": 7206903,
  "type": "Feature",
  "properties": {
    "tgn:hierarchy":[
        "tgn:7206903",
        "tgn:7000096",
        "tgn:1000003",
        "tgn:7000084",
        "tgn:7029392"
    ],
    "tgn:id":7206903,
    "tgn:name":"B\u00fcrgerheide",
    "tgn:placetype":[
        "aat:300386887"
    ]
},
  "bbox": [],
  "geometry": {"coordinates":[13.55,53.15],"type":"Point"}
}