{
  "id": 2143971,
  "type": "Feature",
  "properties": {
    "tgn:hierarchy":[
        "tgn:2143971",
        "tgn:1000001",
        "tgn:7012149",
        "tgn:2001123",
        "tgn:7007522",
        "tgn:7029392"
    ],
    "tgn:id":2143971,
    "tgn:name":"Baker Creek",
    "tgn:placetype":[
        "aat:300008706"
    ]
},
  "bbox": [],
  "geometry": {"coordinates":[-88.6833,32.5667],"type":"Point"}
}