{
  "id": 7592510,
  "type": "Feature",
  "properties": {
    "tgn:hierarchy":[
        "tgn:7592510",
        "tgn:1000004",
        "tgn:7000198",
        "tgn:7000799",
        "tgn:7029392"
    ],
    "tgn:id":7592510,
    "tgn:name:en":"Pungali",
    "tgn:placetype":[
        "aat:300008347"
    ]
},
  "bbox": [],
  "geometry": {"coordinates":[74.886609,32.854843],"type":"Point"}
}