{
  "id": 2156195,
  "type": "Feature",
  "properties": {
    "tgn:hierarchy":[
        "tgn:2156195",
        "tgn:7014651",
        "tgn:1000001",
        "tgn:7012149",
        "tgn:7007516",
        "tgn:7029392"
    ],
    "tgn:id":2156195,
    "tgn:name":"Beards Point",
    "tgn:placetype":[
        "aat:300008850"
    ]
},
  "bbox": [],
  "geometry": {"coordinates":[-76.5833,38.95],"type":"Point"}
}