{
  "id": 7009223,
  "type": "Feature",
  "properties": {
    "tgn:hierarchy":[
        "tgn:7009223",
        "tgn:1000003",
        "tgn:7001095",
        "tgn:1000070",
        "tgn:7029392"
    ],
    "tgn:id":7009223,
    "tgn:name":"Gu\u00e9ret",
    "tgn:placetype":[
        "aat:300008347"
    ]
},
  "bbox": [],
  "geometry": {"coordinates":[1.8667,46.1667],"type":"Point"}
}