<<<<<<< HEAD
{
  "id": 2335203,
  "type": "Feature",
  "properties": {
    "tgn:hierarchy":[
        "tgn:2335203",
        "tgn:1000001",
        "tgn:1002310",
        "tgn:7012149",
        "tgn:7007710",
        "tgn:7029392"
    ],
    "tgn:id":2335203,
    "tgn:name":"Fort Couch",
    "tgn:placetype":[
        "aat:300008347"
    ]
},
  "bbox": [],
  "geometry": {"coordinates":[-76.9,40.2333],"type":"Point"}
}
=======
{"geometry":{"type":"Point","coordinates":[-76.900000,40.233300]},"type":"Feature","properties":{"hierarchy":["tgn:2335203","tgn:1000001","tgn:1002310","tgn:7012149","tgn:7007710","tgn:7029392"],"placetype":["aat:300008347"],"id":2335203,"name:xx":"Fort Couch"}}
>>>>>>> 03f74aca74312dbeaf24d7e61306dd6a786dc3d0
