{
  "id": 7331178,
  "type": "Feature",
  "properties": {
    "tgn:hierarchy":[
        "tgn:7331178",
        "tgn:7002758",
        "tgn:1001316",
        "tgn:1000003",
        "tgn:1000095",
        "tgn:7029392"
    ],
    "tgn:id":7331178,
    "tgn:name":"Grande, Pantano",
    "tgn:placetype":[
        "aat:300008680"
    ]
},
  "bbox": [],
  "geometry": {"coordinates":[-3.55,37.933333],"type":"Point"}
}