{
  "id": 2057779,
  "type": "Feature",
  "properties": {
    "tgn:hierarchy":[
        "tgn:2057779",
        "tgn:1000001",
        "tgn:7012149",
        "tgn:2001151",
        "tgn:7007522",
        "tgn:7029392"
    ],
    "tgn:id":2057779,
    "tgn:name":"Whites Crossing",
    "tgn:placetype":[
        "aat:300008347",
        "aat:300387210"
    ]
},
  "bbox": [],
  "geometry": {"coordinates":[-89.0333,30.8333],"type":"Point"}
}