{
  "id": 2266109,
  "type": "Feature",
  "properties": {
    "tgn:hierarchy":[
        "tgn:2266109",
        "tgn:1000001",
        "tgn:7012149",
        "tgn:2002328",
        "tgn:7007922",
        "tgn:7029392"
    ],
    "tgn:id":2266109,
    "tgn:name":"Crawford Hills",
    "tgn:placetype":[
        "aat:300266640"
    ]
},
  "bbox": [],
  "geometry": {"coordinates":[-90.5833,44.35],"type":"Point"}
}