{
  "id": 7050800,
  "type": "Feature",
  "properties": {
    "tgn:hierarchy":[
        "tgn:7050800",
        "tgn:1001730",
        "tgn:1000003",
        "tgn:7003121",
        "tgn:1000080",
        "tgn:7029392"
    ],
    "tgn:id":7050800,
    "tgn:name":"Massama",
    "tgn:placetype":[
        "aat:300008347"
    ]
},
  "bbox": [],
  "geometry": {"coordinates":[8.6025,39.943889],"type":"Point"}
}