{
  "id": 2593143,
  "type": "Feature",
  "properties": {
    "tgn:hierarchy":[
        "tgn:2593143",
        "tgn:1000001",
        "tgn:7012149",
        "tgn:2000812",
        "tgn:7007255",
        "tgn:7029392"
    ],
    "tgn:id":2593143,
    "tgn:name":"Poplar Log Hollow",
    "tgn:placetype":[
        "aat:300008761"
    ]
},
  "bbox": [],
  "geometry": {"coordinates":[-82.8667,37.0833],"type":"Point"}
}