{
  "id": 7364174,
  "type": "Feature",
  "properties": {
    "tgn:hierarchy":[
        "tgn:7364174",
        "tgn:1000001",
        "tgn:7005597",
        "tgn:7005560",
        "tgn:7029392"
    ],
    "tgn:id":7364174,
    "tgn:name":"El Guayabo",
    "tgn:placetype":[
        "aat:300008347"
    ]
},
  "bbox": [],
  "geometry": {"coordinates":[-98.283333,23.35],"type":"Point"}
}