{
  "id": 7275941,
  "type": "Feature",
  "properties": {
    "tgn:hierarchy":[
        "tgn:7275941",
        "tgn:1001623",
        "tgn:1000049",
        "tgn:1000002",
        "tgn:7029392"
    ],
    "tgn:id":7275941,
    "tgn:name":"T\u00e9rminus, Brazo",
    "tgn:placetype":[
        "aat:300008676"
    ]
},
  "bbox": [],
  "geometry": {"coordinates":[-74.233333,-48.233333],"type":"Point"}
}