{
  "id": 2215314,
  "type": "Feature",
  "properties": {
    "tgn:hierarchy":[
        "tgn:2215314",
        "tgn:1000001",
        "tgn:7012149",
        "tgn:2000432",
        "tgn:7007248",
        "tgn:7029392"
    ],
    "tgn:id":2215314,
    "tgn:name":"Callaway Lake",
    "tgn:placetype":[
        "aat:300006191"
    ]
},
  "bbox": [],
  "geometry": {"coordinates":[-85.0667,33.05],"type":"Point"}
}