{
  "id": 7161734,
  "type": "Feature",
  "properties": {
    "tgn:hierarchy":[
        "tgn:7161734",
        "tgn:7003669",
        "tgn:1000003",
        "tgn:7000084",
        "tgn:7029392"
    ],
    "tgn:id":7161734,
    "tgn:name":"Hohe-Berg",
    "tgn:placetype":[
        "aat:300008777"
    ]
},
  "bbox": [],
  "geometry": {"coordinates":[9.233333,50.133333],"type":"Point"}
}