{
  "id": 2587727,
  "type": "Feature",
  "properties": {
    "tgn:hierarchy":[
        "tgn:2587727",
        "tgn:1000001",
        "tgn:7012149",
        "tgn:7007157",
        "tgn:1002957",
        "tgn:7029392"
    ],
    "tgn:id":2587727,
    "tgn:name":"Pleasant Valley",
    "tgn:placetype":[
        "aat:300386845"
    ]
},
  "bbox": [],
  "geometry": {"coordinates":[-119.5667,37.9833],"type":"Point"}
}