{
  "id": 2396391,
  "type": "Feature",
  "properties": {
    "tgn:hierarchy":[
        "tgn:2396391",
        "tgn:1000001",
        "tgn:7012149",
        "tgn:2001709",
        "tgn:7007708",
        "tgn:7029392"
    ],
    "tgn:id":2396391,
    "tgn:name":"Holmes Spring",
    "tgn:placetype":[
        "aat:300008697"
    ]
},
  "bbox": [],
  "geometry": {"coordinates":[-118.9667,42.1333],"type":"Point"}
}