<<<<<<< HEAD
{
  "id": 2768837,
  "type": "Feature",
  "properties": {
    "tgn:hierarchy":[
        "tgn:2768837",
        "tgn:1000001",
        "tgn:2000923",
        "tgn:7012149",
        "tgn:7007515",
        "tgn:7029392"
    ],
    "tgn:id":2768837,
    "tgn:name":"Whitney Brook",
    "tgn:placetype":[
        "aat:300008699"
    ]
},
  "bbox": [],
  "geometry": {"coordinates":[-69.75,44.3],"type":"Point"}
}
=======
{"geometry":{"type":"Point","coordinates":[-69.750000,44.300000]},"type":"Feature","properties":{"hierarchy":["tgn:2768837","tgn:1000001","tgn:2000923","tgn:7012149","tgn:7007515","tgn:7029392"],"placetype":["aat:300008699"],"id":2768837,"name:xx":"Whitney Brook"}}
>>>>>>> 03f74aca74312dbeaf24d7e61306dd6a786dc3d0
