{
  "id": 2564228,
  "type": "Feature",
  "properties": {
    "tgn:hierarchy":[
        "tgn:2564228",
        "tgn:1000001",
        "tgn:7012149",
        "tgn:2001067",
        "tgn:7007521",
        "tgn:7029392"
    ],
    "tgn:id":2564228,
    "tgn:name":"Paavola Creek",
    "tgn:placetype":[
        "aat:300008706"
    ]
},
  "bbox": [],
  "geometry": {"coordinates":[-92.75,47.7167],"type":"Point"}
}