{
  "id": 7487469,
  "type": "Feature",
  "properties": {
    "tgn:hierarchy":[
        "tgn:7487469",
        "tgn:1000004",
        "tgn:1000454",
        "tgn:1000141",
        "tgn:7029392"
    ],
    "tgn:id":7487469,
    "tgn:name":"Mudan Xi",
    "tgn:placetype":[
        "aat:300008699"
    ]
},
  "bbox": [],
  "geometry": {"coordinates":[121.867734,25.045936],"type":"Point"}
}