{
  "id": 7425883,
  "type": "Feature",
  "properties": {
    "tgn:hierarchy":[
        "tgn:7425883",
        "tgn:1000001",
        "tgn:7005594",
        "tgn:7005560",
        "tgn:7029392"
    ],
    "tgn:id":7425883,
    "tgn:name":"Morelos",
    "tgn:placetype":[
        "aat:300008347"
    ]
},
  "bbox": [],
  "geometry": {"coordinates":[-101.283333,22.183333],"type":"Point"}
}