{
  "id": 2098733,
  "type": "Feature",
  "properties": {
    "tgn:hierarchy":[
        "tgn:2098733",
        "tgn:1000001",
        "tgn:7012149",
        "tgn:2001917",
        "tgn:7007825",
        "tgn:7029392"
    ],
    "tgn:id":2098733,
    "tgn:name":"Cumberland City",
    "tgn:placetype":[
        "aat:300008347"
    ]
},
  "bbox": [],
  "geometry": {"coordinates":[-87.6333,36.3833],"type":"Point"}
}