{
  "id": 7124085,
  "type": "Feature",
  "properties": {
    "tgn:hierarchy":[
        "tgn:7124085",
        "tgn:1000003",
        "tgn:7003676",
        "tgn:7000084",
        "tgn:7029392"
    ],
    "tgn:id":7124085,
    "tgn:name":"Niedergrafschaft Bentheim",
    "tgn:placetype":[
        "aat:300055621"
    ]
},
  "bbox": [],
  "geometry": {"coordinates":[6.85,52.55],"type":"Point"}
}