{
  "id": 1139375,
  "type": "Feature",
  "properties": {
    "tgn:hierarchy":[
        "tgn:1139375",
        "tgn:7002075",
        "tgn:1000004",
        "tgn:1000111",
        "tgn:7029392"
    ],
    "tgn:id":1139375,
    "tgn:name":"Meicun",
    "tgn:placetype":[
        "aat:300008347"
    ]
},
  "bbox": [],
  "geometry": {"coordinates":[119.0333,30.35],"type":"Point"}
}