{
  "id": 2500943,
  "type": "Feature",
  "properties": {
    "tgn:hierarchy":[
        "tgn:2500943",
        "tgn:7002659",
        "tgn:1000001",
        "tgn:7012149",
        "tgn:2000035",
        "tgn:7029392"
    ],
    "tgn:id":2500943,
    "tgn:name":"McFarland Hollow",
    "tgn:placetype":[
        "aat:300008761"
    ]
},
  "bbox": [],
  "geometry": {"coordinates":[-86.2667,34.7667],"type":"Point"}
}