{
  "id": 7121272,
  "type": "Feature",
  "properties": {
    "tgn:hierarchy":[
        "tgn:7121272",
        "tgn:1000003",
        "tgn:7000094",
        "tgn:7000084",
        "tgn:7029392"
    ],
    "tgn:id":7121272,
    "tgn:name":"Parper Tannen",
    "tgn:placetype":[
        "aat:300008863"
    ]
},
  "bbox": [],
  "geometry": {"coordinates":[12.383333,53.883333],"type":"Point"}
}