{
  "id": 2713452,
  "type": "Feature",
  "properties": {
    "tgn:hierarchy":[
        "tgn:2713452",
        "tgn:1000001",
        "tgn:7012149",
        "tgn:2000959",
        "tgn:7007520",
        "tgn:7029392"
    ],
    "tgn:id":2713452,
    "tgn:name":"Tea Creek",
    "tgn:placetype":[
        "aat:300008706"
    ]
},
  "bbox": [],
  "geometry": {"coordinates":[-84.2833,44.0667],"type":"Point"}
}