{
  "id": 2745334,
  "type": "Feature",
  "properties": {
    "tgn:hierarchy":[
        "tgn:2745334",
        "tgn:1000001",
        "tgn:7012149",
        "tgn:1002517",
        "tgn:7007523",
        "tgn:7029392"
    ],
    "tgn:id":2745334,
    "tgn:name":"Vinegar Hill",
    "tgn:placetype":[
        "aat:300008798"
    ]
},
  "bbox": [],
  "geometry": {"coordinates":[-90.5333,38.0167],"type":"Point"}
}