<<<<<<< HEAD
{
  "id": 2336415,
  "type": "Feature",
  "properties": {
    "tgn:hierarchy":[
        "tgn:2336415",
        "tgn:1000001",
        "tgn:2002241",
        "tgn:7012149",
        "tgn:7007920",
        "tgn:7029392"
    ],
    "tgn:id":2336415,
    "tgn:name":"Fountain Springs",
    "tgn:placetype":[
        "aat:300008697"
    ]
},
  "bbox": [],
  "geometry": {"coordinates":[-118.2167,46.3333],"type":"Point"}
}
=======
{"geometry":{"type":"Point","coordinates":[-118.216700,46.333300]},"type":"Feature","properties":{"hierarchy":["tgn:2336415","tgn:1000001","tgn:2002241","tgn:7012149","tgn:7007920","tgn:7029392"],"placetype":["aat:300008697"],"id":2336415,"name:xx":"Fountain Springs"}}
>>>>>>> 03f74aca74312dbeaf24d7e61306dd6a786dc3d0
