{
  "id": 2098365,
  "type": "Feature",
  "properties": {
    "tgn:hierarchy":[
        "tgn:2098365",
        "tgn:1000001",
        "tgn:7012149",
        "tgn:2001858",
        "tgn:7007825",
        "tgn:7029392"
    ],
    "tgn:id":2098365,
    "tgn:name":"Charlotte",
    "tgn:placetype":[
        "aat:300008347"
    ]
},
  "bbox": [],
  "geometry": {"coordinates":[-87.3333,36.1667],"type":"Point"}
}