{
  "id": 2109556,
  "type": "Feature",
  "properties": {
    "tgn:hierarchy":[
        "tgn:2109556",
        "tgn:1000001",
        "tgn:1002753",
        "tgn:7012149",
        "tgn:7007828",
        "tgn:7029392"
    ],
    "tgn:id":2109556,
    "tgn:name":"Derby Center",
    "tgn:placetype":[
        "aat:300008347"
    ]
},
  "bbox": [],
  "geometry": {"coordinates":[-72.1333,44.9333],"type":"Point"}
}