{
  "id": 7225011,
  "type": "Feature",
  "properties": {
    "tgn:hierarchy":[
        "tgn:7225011",
        "tgn:7011161",
        "tgn:7002674",
        "tgn:1000003",
        "tgn:1000074",
        "tgn:7029392"
    ],
    "tgn:id":7225011,
    "tgn:name":"Stok, \u00cdfalos",
    "tgn:placetype":[
        "aat:300386970"
    ]
},
  "bbox": [],
  "geometry": {"coordinates":[25.416667,38.883333],"type":"Point"}
}