{
  "id": 2031269,
  "type": "Feature",
  "properties": {
    "tgn:hierarchy":[
        "tgn:2031269",
        "tgn:1000001",
        "tgn:7012149",
        "tgn:2000546",
        "tgn:7007252",
        "tgn:7029392"
    ],
    "tgn:id":2031269,
    "tgn:name":"Cale",
    "tgn:placetype":[
        "aat:300008347"
    ]
},
  "bbox": [],
  "geometry": {"coordinates":[-86.75,38.7833],"type":"Point"}
}