{
  "id": 7137068,
  "type": "Feature",
  "properties": {
    "tgn:hierarchy":[
        "tgn:7137068",
        "tgn:7003669",
        "tgn:1000003",
        "tgn:7000084",
        "tgn:7029392"
    ],
    "tgn:id":7137068,
    "tgn:name":"Lerchenberg",
    "tgn:placetype":[
        "aat:300008777"
    ]
},
  "bbox": [],
  "geometry": {"coordinates":[10.583333,49.666667],"type":"Point"}
}