{
  "id": 1085228,
  "type": "Feature",
  "properties": {
    "tgn:hierarchy":[
        "tgn:1085228",
        "tgn:1002066",
        "tgn:1000004",
        "tgn:1000140",
        "tgn:7029392"
    ],
    "tgn:id":1085228,
    "tgn:name":"Ru\u1e0daymah Lio\u00fba",
    "tgn:placetype":[
        "aat:300008347"
    ]
},
  "bbox": [],
  "geometry": {"coordinates":[36.5833,33.0167],"type":"Point"}
}