{
  "id": 7111824,
  "type": "Feature",
  "properties": {
    "tgn:hierarchy":[
        "tgn:7111824",
        "tgn:7003669",
        "tgn:1000003",
        "tgn:7000084",
        "tgn:7029392"
    ],
    "tgn:id":7111824,
    "tgn:name":"Rohrb\u00fchl",
    "tgn:placetype":[
        "aat:300008777"
    ]
},
  "bbox": [],
  "geometry": {"coordinates":[12.366667,49.583333],"type":"Point"}
}