<<<<<<< HEAD
{
  "id": 7111824,
  "type": "Feature",
  "properties": {
    "tgn:hierarchy":[
        "tgn:7111824",
        "tgn:7003669",
        "tgn:1000003",
        "tgn:7000084",
        "tgn:7029392"
    ],
    "tgn:id":7111824,
    "tgn:name":"Rohrb\u00fchl",
    "tgn:placetype":[
        "aat:300008777"
    ]
},
  "bbox": [],
  "geometry": {"coordinates":[12.366667,49.583333],"type":"Point"}
}
=======
{"geometry":{"type":"Point","coordinates":[12.366667,49.583333]},"type":"Feature","properties":{"hierarchy":["tgn:7111824","tgn:7003669","tgn:1000003","tgn:7000084","tgn:7029392"],"placetype":["aat:300008777"],"id":7111824,"name:xx":"Rohrb\u00fchl"}}
>>>>>>> 03f74aca74312dbeaf24d7e61306dd6a786dc3d0
