{
  "id": 7534410,
  "type": "Feature",
  "properties": {
    "tgn:hierarchy":[
        "tgn:7534410",
        "tgn:7001242",
        "tgn:7016833",
        "tgn:1001092",
        "tgn:7029392"
    ],
    "tgn:id":7534410,
    "tgn:name":"Kafr \u0162i\u015ff\u0101",
    "tgn:placetype":[
        "aat:300008347"
    ]
},
  "bbox": [],
  "geometry": {"coordinates":[31.304199,30.568167],"type":"Point"}
}