{
  "id": 7488053,
  "type": "Feature",
  "properties": {
    "tgn:hierarchy":[
        "tgn:7488053",
        "tgn:1000004",
        "tgn:7004300",
        "tgn:1000141",
        "tgn:7029392"
    ],
    "tgn:id":7488053,
    "tgn:name":"Liyu Shan",
    "tgn:placetype":[
        "aat:300008777"
    ]
},
  "bbox": [],
  "geometry": {"coordinates":[119.510556,23.375278],"type":"Point"}
}