{
  "id": 7534814,
  "type": "Feature",
  "properties": {
    "tgn:hierarchy":[
        "tgn:7534814",
        "tgn:7001242",
        "tgn:7001311",
        "tgn:7016833",
        "tgn:7029392"
    ],
    "tgn:id":7534814,
    "tgn:name:en":"H\u00eer, W\u00e2di el-",
    "tgn:placetype":[
        "aat:300379998"
    ]
},
  "bbox": [],
  "geometry": {"coordinates":[33.366667,25.766667],"type":"Point"}
}