<<<<<<< HEAD
{
  "id": 2330570,
  "type": "Feature",
  "properties": {
    "tgn:hierarchy":[
        "tgn:2330570",
        "tgn:1000001",
        "tgn:7012149",
        "tgn:2001536",
        "tgn:7007709",
        "tgn:7029392"
    ],
    "tgn:id":2330570,
    "tgn:name":"Flat Creek",
    "tgn:placetype":[
        "aat:300008706"
    ]
},
  "bbox": [],
  "geometry": {"coordinates":[-80.2833,35.55],"type":"Point"}
}
=======
{"geometry":{"type":"Point","coordinates":[-80.283300,35.550000]},"type":"Feature","properties":{"hierarchy":["tgn:2330570","tgn:1000001","tgn:7012149","tgn:2001536","tgn:7007709","tgn:7029392"],"placetype":["aat:300008706"],"id":2330570,"name:xx":"Flat Creek"}}
>>>>>>> 03f74aca74312dbeaf24d7e61306dd6a786dc3d0
