<<<<<<< HEAD
{
  "id": 7354324,
  "type": "Feature",
  "properties": {
    "tgn:hierarchy":[
        "tgn:7354324",
        "tgn:1000001",
        "tgn:7005589",
        "tgn:7005560",
        "tgn:7029392"
    ],
    "tgn:id":7354324,
    "tgn:name":"Ca\u00f1ada Honda",
    "tgn:placetype":[
        "aat:300008347"
    ]
},
  "bbox": [],
  "geometry": {"coordinates":[-99.65,26.033333],"type":"Point"}
}
=======
{"geometry":{"type":"Point","coordinates":[-99.650000,26.033333]},"type":"Feature","properties":{"hierarchy":["tgn:7354324","tgn:1000001","tgn:7005589","tgn:7005560","tgn:7029392"],"placetype":["aat:300008347"],"id":7354324,"name:xx":"Ca\u00f1ada Honda"}}
>>>>>>> 03f74aca74312dbeaf24d7e61306dd6a786dc3d0
