{
  "id": 7354324,
  "type": "Feature",
  "properties": {
    "tgn:hierarchy":[
        "tgn:7354324",
        "tgn:1000001",
        "tgn:7005589",
        "tgn:7005560",
        "tgn:7029392"
    ],
    "tgn:id":7354324,
    "tgn:name":"Ca\u00f1ada Honda",
    "tgn:placetype":[
        "aat:300008347"
    ]
},
  "bbox": [],
  "geometry": {"coordinates":[-99.65,26.033333],"type":"Point"}
}