{
  "id": 2557122,
  "type": "Feature",
  "properties": {
    "tgn:hierarchy":[
        "tgn:2557122",
        "tgn:1000001",
        "tgn:1002369",
        "tgn:7012149",
        "tgn:7007251",
        "tgn:7029392"
    ],
    "tgn:id":2557122,
    "tgn:name":"Old Hickory Creek",
    "tgn:placetype":[
        "aat:300008706"
    ]
},
  "bbox": [],
  "geometry": {"coordinates":[-89.0333,38.9167],"type":"Point"}
}