{
  "id": 7310520,
  "type": "Feature",
  "properties": {
    "tgn:hierarchy":[
        "tgn:7310520",
        "tgn:1001702",
        "tgn:1000049",
        "tgn:1000002",
        "tgn:7029392"
    ],
    "tgn:id":7310520,
    "tgn:name":"Milne Edwards, Isla",
    "tgn:placetype":[
        "aat:300008791"
    ]
},
  "bbox": [],
  "geometry": {"coordinates":[-68.266667,-55.183333],"type":"Point"}
}