{
  "id": 7281272,
  "type": "Feature",
  "properties": {
    "tgn:hierarchy":[
        "tgn:7281272",
        "tgn:1001702",
        "tgn:1000049",
        "tgn:1000002",
        "tgn:7029392"
    ],
    "tgn:id":7281272,
    "tgn:name":"Senos, Islote",
    "tgn:placetype":[
        "aat:300008791"
    ]
},
  "bbox": [],
  "geometry": {"coordinates":[-75.516667,-50.65],"type":"Point"}
}