{
  "id": 2173950,
  "type": "Feature",
  "properties": {
    "tgn:hierarchy":[
        "tgn:2173950",
        "tgn:1000001",
        "tgn:7012149",
        "tgn:1002567",
        "tgn:7007240",
        "tgn:7029392"
    ],
    "tgn:id":2173950,
    "tgn:name":"Bird Lake",
    "tgn:placetype":[
        "aat:300008680"
    ]
},
  "bbox": [],
  "geometry": {"coordinates":[-81.85,28.6333],"type":"Point"}
}