{
  "id": 7442770,
  "type": "Feature",
  "properties": {
    "tgn:hierarchy":[
        "tgn:7442770",
        "tgn:7002445",
        "tgn:1000003",
        "tgn:7008165",
        "tgn:7008591",
        "tgn:7029392"
    ],
    "tgn:id":7442770,
    "tgn:name:en":"Tipalt Burn",
    "tgn:placetype":[
        "aat:300008699"
    ]
},
  "bbox": [],
  "geometry": {"coordinates":[-2.466667,54.966667],"type":"Point"}
}