{
  "id": 7317970,
  "type": "Feature",
  "properties": {
    "tgn:hierarchy":[
        "tgn:7317970",
        "tgn:7016598",
        "tgn:1000049",
        "tgn:1000002",
        "tgn:7029392"
    ],
    "tgn:id":7317970,
    "tgn:name":"Cifuncho, Aguada",
    "tgn:placetype":[
        "aat:300008697"
    ]
},
  "bbox": [],
  "geometry": {"coordinates":[-70.65,-25.716667],"type":"Point"}
}