{
  "id": 2742279,
  "type": "Feature",
  "properties": {
    "tgn:hierarchy":[
        "tgn:2742279",
        "tgn:1000001",
        "tgn:7012149",
        "tgn:2001449",
        "tgn:7007566",
        "tgn:7029392"
    ],
    "tgn:id":2742279,
    "tgn:name":"Vallecitos",
    "tgn:placetype":[
        "aat:300055621"
    ]
},
  "bbox": [],
  "geometry": {"coordinates":[-105.7333,36.0833],"type":"Point"}
}