{
  "id": 2687828,
  "type": "Feature",
  "properties": {
    "tgn:hierarchy":[
        "tgn:2687828",
        "tgn:1000001",
        "tgn:1002219",
        "tgn:7012149",
        "tgn:7007157",
        "tgn:7029392"
    ],
    "tgn:id":2687828,
    "tgn:name":"Spring Valley Creek",
    "tgn:placetype":[
        "aat:300008706"
    ]
},
  "bbox": [],
  "geometry": {"coordinates":[-120.75,38.2167],"type":"Point"}
}