<<<<<<< HEAD
{
  "id": 7028406,
  "type": "Feature",
  "properties": {
    "tgn:hierarchy":[
        "tgn:7028406",
        "tgn:7002445",
        "tgn:1000003",
        "tgn:7008160",
        "tgn:7008591",
        "tgn:7029392"
    ],
    "tgn:id":7028406,
    "tgn:name":"Godwick",
    "tgn:placetype":[
        "aat:300008347",
        "aat:300008372"
    ]
},
  "bbox": [],
  "geometry": {"coordinates":[0.83,52.766],"type":"Point"}
}
=======
{"geometry":{"type":"Point","coordinates":[0.830000,52.766000]},"type":"Feature","properties":{"hierarchy":["tgn:7028406","tgn:7002445","tgn:1000003","tgn:7008160","tgn:7008591","tgn:7029392"],"placetype":["aat:300008347","aat:300008372"],"id":7028406,"name:xx":"Godwick"}}
>>>>>>> 03f74aca74312dbeaf24d7e61306dd6a786dc3d0
