<<<<<<< HEAD
{
  "id": 7113310,
  "type": "Feature",
  "properties": {
    "tgn:hierarchy":[
        "tgn:7113310",
        "tgn:7003669",
        "tgn:1000003",
        "tgn:7000084",
        "tgn:7029392"
    ],
    "tgn:id":7113310,
    "tgn:name":"Reuschb\u00fchl",
    "tgn:placetype":[
        "aat:300008777"
    ]
},
  "bbox": [],
  "geometry": {"coordinates":[10.633333,48.133333],"type":"Point"}
}
=======
{"geometry":{"type":"Point","coordinates":[10.633333,48.133333]},"type":"Feature","properties":{"hierarchy":["tgn:7113310","tgn:7003669","tgn:1000003","tgn:7000084","tgn:7029392"],"placetype":["aat:300008777"],"id":7113310,"name:xx":"Reuschb\u00fchl"}}
>>>>>>> 03f74aca74312dbeaf24d7e61306dd6a786dc3d0
