{
  "id": 7357024,
  "type": "Feature",
  "properties": {
    "tgn:hierarchy":[
        "tgn:7357024",
        "tgn:1001853",
        "tgn:1000001",
        "tgn:7005560",
        "tgn:7029392"
    ],
    "tgn:id":7357024,
    "tgn:name":"Tanque Chiquito",
    "tgn:placetype":[
        "aat:300006191"
    ]
},
  "bbox": [],
  "geometry": {"coordinates":[-100.75,27.85],"type":"Point"}
}