{
  "id": 7583476,
  "type": "Feature",
  "properties": {
    "tgn:hierarchy":[
        "tgn:7583476",
        "tgn:1000004",
        "tgn:7000198",
        "tgn:7000799",
        "tgn:7029392"
    ],
    "tgn:id":7583476,
    "tgn:name:en":"Chumik",
    "tgn:placetype":[
        "aat:300008777"
    ]
},
  "bbox": [],
  "geometry": {"coordinates":[78.305381,32.732412],"type":"Point"}
}