{
  "id": 2000298,
  "type": "Feature",
  "properties": {
    "tgn:hierarchy":[
        "tgn:2000298",
        "tgn:1000001",
        "tgn:7012149",
        "tgn:7007248",
        "tgn:7029392"
    ],
    "tgn:id":2000298,
    "tgn:name":"Barrow",
    "tgn:placetype":[
        "aat:300387145",
        "aat:300000771"
    ]
},
  "bbox": [],
  "geometry": {"coordinates":[-83.7167,33.9833],"type":"Point"}
}