{
  "id": 1042161,
  "type": "Feature",
  "properties": {
    "tgn:hierarchy":[
        "tgn:1042161",
        "tgn:7002753",
        "tgn:7002756",
        "tgn:1000003",
        "tgn:1000074",
        "tgn:7029392"
    ],
    "tgn:id":1042161,
    "tgn:name":"Oresti\u00e1s",
    "tgn:placetype":[
        "aat:300008347"
    ]
},
  "bbox": [],
  "geometry": {"coordinates":[26.529722,41.503056],"type":"Point"}
}