{
  "id": 7149589,
  "type": "Feature",
  "properties": {
    "tgn:hierarchy":[
        "tgn:7149589",
        "tgn:1000003",
        "tgn:7003688",
        "tgn:7000084",
        "tgn:7029392"
    ],
    "tgn:id":7149589,
    "tgn:name":"Kr\u00f6ppelshausen",
    "tgn:placetype":[
        "aat:300008347"
    ]
},
  "bbox": [],
  "geometry": {"coordinates":[10.333333,53.483333],"type":"Point"}
}