{
  "id": 1118096,
  "type": "Feature",
  "properties": {
    "tgn:hierarchy":[
        "tgn:1118096",
        "tgn:1000001",
        "tgn:7012149",
        "tgn:7007568",
        "tgn:7029392"
    ],
    "tgn:id":1118096,
    "tgn:name":"Seneca Lake",
    "tgn:placetype":[
        "aat:300008680"
    ]
},
  "bbox": [],
  "geometry": {"coordinates":[-76.8667,42.6333],"type":"Point"}
}