{
  "id": 2587553,
  "type": "Feature",
  "properties": {
    "tgn:hierarchy":[
        "tgn:2587553",
        "tgn:1000001",
        "tgn:7012149",
        "tgn:2002327",
        "tgn:7007922",
        "tgn:7029392"
    ],
    "tgn:id":2587553,
    "tgn:name":"Pleasant Lake Outlet",
    "tgn:placetype":[
        "aat:300008699"
    ]
},
  "bbox": [],
  "geometry": {"coordinates":[-90.3333,46.25],"type":"Point"}
}