{
  "id": 1123240,
  "type": "Feature",
  "properties": {
    "tgn:hierarchy":[
        "tgn:1123240",
        "tgn:7001242",
        "tgn:1000149",
        "tgn:1000867",
        "tgn:7029392"
    ],
    "tgn:id":1123240,
    "tgn:name":"Cusso",
    "tgn:placetype":[
        "aat:300008707"
    ]
},
  "bbox": [],
  "geometry": {"coordinates":[15.5667,-14.3333],"type":"Point"}
}