{
  "id": 2191225,
  "type": "Feature",
  "properties": {
    "tgn:hierarchy":[
        "tgn:2191225",
        "tgn:1000001",
        "tgn:2000311",
        "tgn:7012149",
        "tgn:7007248",
        "tgn:7029392"
    ],
    "tgn:id":2191225,
    "tgn:name":"Boys Point",
    "tgn:placetype":[
        "aat:300008850"
    ]
},
  "bbox": [],
  "geometry": {"coordinates":[-81.5167,30.95],"type":"Point"}
}