{
  "id": 2639513,
  "type": "Feature",
  "properties": {
    "tgn:hierarchy":[
        "tgn:2639513",
        "tgn:2000768",
        "tgn:1000001",
        "tgn:7012149",
        "tgn:7007255",
        "tgn:7029392"
    ],
    "tgn:id":2639513,
    "tgn:name":"Saltpeter Cave",
    "tgn:placetype":[
        "aat:300008746"
    ]
},
  "bbox": [],
  "geometry": {"coordinates":[-85.85,36.8667],"type":"Point"}
}