<<<<<<< HEAD
{
  "id": 2154499,
  "type": "Feature",
  "properties": {
    "tgn:hierarchy":[
        "tgn:2154499",
        "tgn:1000001",
        "tgn:7012149",
        "tgn:2001508",
        "tgn:7007709",
        "tgn:7029392"
    ],
    "tgn:id":2154499,
    "tgn:name":"Bear Creek Lake",
    "tgn:placetype":[
        "aat:300006191"
    ]
},
  "bbox": [],
  "geometry": {"coordinates":[-83.0667,35.2333],"type":"Point"}
}
=======
{"geometry":{"type":"Point","coordinates":[-83.066700,35.233300]},"type":"Feature","properties":{"hierarchy":["tgn:2154499","tgn:1000001","tgn:7012149","tgn:2001508","tgn:7007709","tgn:7029392"],"placetype":["aat:300006191"],"id":2154499,"name:xx":"Bear Creek Lake"}}
>>>>>>> 03f74aca74312dbeaf24d7e61306dd6a786dc3d0
