{
  "id": 7431883,
  "type": "Feature",
  "properties": {
    "tgn:hierarchy":[
        "tgn:7431883",
        "tgn:7005583",
        "tgn:1000001",
        "tgn:7005560",
        "tgn:7029392"
    ],
    "tgn:id":7431883,
    "tgn:name":"Navarro, Mesa",
    "tgn:placetype":[
        "aat:300008811"
    ]
},
  "bbox": [],
  "geometry": {"coordinates":[-106.116667,26.516667],"type":"Point"}
}