{
  "id": 2683469,
  "type": "Feature",
  "properties": {
    "tgn:hierarchy":[
        "tgn:2683469",
        "tgn:1000001",
        "tgn:7012149",
        "tgn:2000927",
        "tgn:7007515",
        "tgn:7029392"
    ],
    "tgn:id":2683469,
    "tgn:name":"Spaulding Brook",
    "tgn:placetype":[
        "aat:300008699"
    ]
},
  "bbox": [],
  "geometry": {"coordinates":[-68.1167,45.35],"type":"Point"}
}