{
  "id": 7099170,
  "type": "Feature",
  "properties": {
    "tgn:hierarchy":[
        "tgn:7099170",
        "tgn:7000096",
        "tgn:1000003",
        "tgn:7000084",
        "tgn:7029392"
    ],
    "tgn:id":7099170,
    "tgn:name":"Sieversdorfer Heide",
    "tgn:placetype":[
        "aat:300386887"
    ]
},
  "bbox": [],
  "geometry": {"coordinates":[14.066667,52.533333],"type":"Point"}
}