{
  "id": 1051630,
  "type": "Feature",
  "properties": {
    "tgn:hierarchy":[
        "tgn:1051630",
        "tgn:1003351",
        "tgn:1000004",
        "tgn:7018214",
        "tgn:7002435",
        "tgn:7029392"
    ],
    "tgn:id":1051630,
    "tgn:name":"Sherlovaya Gora",
    "tgn:placetype":[
        "aat:300008347"
    ]
},
  "bbox": [],
  "geometry": {"coordinates":[116.25,50.5333],"type":"Point"}
}