{
  "id": 7390907,
  "type": "Feature",
  "properties": {
    "tgn:hierarchy":[
        "tgn:7390907",
        "tgn:1000001",
        "tgn:7005600",
        "tgn:7005560",
        "tgn:7029392"
    ],
    "tgn:id":7390907,
    "tgn:name":"Sanakt\u00e9",
    "tgn:placetype":[
        "aat:300008347"
    ]
},
  "bbox": [],
  "geometry": {"coordinates":[-89.716667,20.216667],"type":"Point"}
}