{
  "id": 7111663,
  "type": "Feature",
  "properties": {
    "tgn:hierarchy":[
        "tgn:7111663",
        "tgn:7003669",
        "tgn:1000003",
        "tgn:7000084",
        "tgn:7029392"
    ],
    "tgn:id":7111663,
    "tgn:name":"Richting",
    "tgn:placetype":[
        "aat:300008347"
    ]
},
  "bbox": [],
  "geometry": {"coordinates":[13.433333,48.683333],"type":"Point"}
}