{
  "id": 2336050,
  "type": "Feature",
  "properties": {
    "tgn:hierarchy":[
        "tgn:2336050",
        "tgn:1000001",
        "tgn:2001357",
        "tgn:7012149",
        "tgn:7007525",
        "tgn:7029392"
    ],
    "tgn:id":2336050,
    "tgn:name":"Foster Creek",
    "tgn:placetype":[
        "aat:300008706"
    ]
},
  "bbox": [],
  "geometry": {"coordinates":[-99.4833,40.3333],"type":"Point"}
}