{
  "id": 7500937,
  "type": "Feature",
  "properties": {
    "tgn:hierarchy":[
        "tgn:7500937",
        "tgn:7488858",
        "tgn:1000004",
        "tgn:1000141",
        "tgn:7029392"
    ],
    "tgn:id":7500937,
    "tgn:name":"Lele Shanwu",
    "tgn:placetype":[
        "aat:300005567"
    ]
},
  "bbox": [],
  "geometry": {"coordinates":[120.955,23.547778],"type":"Point"}
}