{
  "id": 7233268,
  "type": "Feature",
  "properties": {
    "tgn:hierarchy":[
        "tgn:7233268",
        "tgn:7011270",
        "tgn:7002674",
        "tgn:1000003",
        "tgn:1000074",
        "tgn:7029392"
    ],
    "tgn:id":7233268,
    "tgn:name":"Amar\u00eddes, Vr\u00e1choi",
    "tgn:placetype":[
        "aat:300011692"
    ]
},
  "bbox": [],
  "geometry": {"coordinates":[25.316667,37.05],"type":"Point"}
}