{
  "id": 7375658,
  "type": "Feature",
  "properties": {
    "tgn:hierarchy":[
        "tgn:7375658",
        "tgn:1000001",
        "tgn:1001960",
        "tgn:7005560",
        "tgn:7029392"
    ],
    "tgn:id":7375658,
    "tgn:name":"Las Flores",
    "tgn:placetype":[
        "aat:300008347"
    ]
},
  "bbox": [],
  "geometry": {"coordinates":[-110.85,30.833333],"type":"Point"}
}