<<<<<<< HEAD
{
  "id": 7362489,
  "type": "Feature",
  "properties": {
    "tgn:hierarchy":[
        "tgn:7362489",
        "tgn:7005584",
        "tgn:1000001",
        "tgn:7005560",
        "tgn:7029392"
    ],
    "tgn:id":7362489,
    "tgn:name":"El Patrocinio",
    "tgn:placetype":[
        "aat:300008347"
    ]
},
  "bbox": [],
  "geometry": {"coordinates":[-100.566667,21.183333],"type":"Point"}
}
=======
{"geometry":{"type":"Point","coordinates":[-100.566667,21.183333]},"type":"Feature","properties":{"hierarchy":["tgn:7362489","tgn:7005584","tgn:1000001","tgn:7005560","tgn:7029392"],"placetype":["aat:300008347"],"id":7362489,"name:xx":"El Patrocinio"}}
>>>>>>> 03f74aca74312dbeaf24d7e61306dd6a786dc3d0
