{
  "id": 2279062,
  "type": "Feature",
  "properties": {
    "tgn:hierarchy":[
        "tgn:2279062",
        "tgn:1000001",
        "tgn:1002284",
        "tgn:7012149",
        "tgn:7007568",
        "tgn:7029392"
    ],
    "tgn:id":2279062,
    "tgn:name":"Dead Sea",
    "tgn:placetype":[
        "aat:300008680"
    ]
},
  "bbox": [],
  "geometry": {"coordinates":[-73.6167,44.8667],"type":"Point"}
}