{
  "id": 2317299,
  "type": "Feature",
  "properties": {
    "tgn:hierarchy":[
        "tgn:2317299",
        "tgn:1000001",
        "tgn:7012149",
        "tgn:2000217",
        "tgn:7007158",
        "tgn:7029392"
    ],
    "tgn:id":2317299,
    "tgn:name":"Emmons, Mount",
    "tgn:placetype":[
        "aat:300008798"
    ]
},
  "bbox": [],
  "geometry": {"coordinates":[-107.05,38.8833],"type":"Point"}
}