{
  "id": 2411485,
  "type": "Feature",
  "properties": {
    "tgn:hierarchy":[
        "tgn:2411485",
        "tgn:1000001",
        "tgn:7006451",
        "tgn:7012149",
        "tgn:2000102",
        "tgn:7029392"
    ],
    "tgn:id":2411485,
    "tgn:name":"Indian Hills Tank",
    "tgn:placetype":[
        "aat:300006191"
    ]
},
  "bbox": [],
  "geometry": {"coordinates":[-111.1333,31.5833],"type":"Point"}
}