{
  "id": 2297852,
  "type": "Feature",
  "properties": {
    "tgn:hierarchy":[
        "tgn:2297852",
        "tgn:1000001",
        "tgn:7012149",
        "tgn:7007523",
        "tgn:7029392"
    ],
    "tgn:id":2297852,
    "tgn:name":"Dry Hollow",
    "tgn:placetype":[
        "aat:300008761"
    ]
},
  "bbox": [],
  "geometry": {"coordinates":[-93.5833,36.7833],"type":"Point"}
}