{
  "id": 7345508,
  "type": "Feature",
  "properties": {
    "tgn:hierarchy":[
        "tgn:7345508",
        "tgn:7002818",
        "tgn:1001647",
        "tgn:1000003",
        "tgn:1000095",
        "tgn:7029392"
    ],
    "tgn:id":7345508,
    "tgn:name":"Aldehuela, R\u00edo de la",
    "tgn:placetype":[
        "aat:300008699"
    ]
},
  "bbox": [],
  "geometry": {"coordinates":[-2.633333,40.15],"type":"Point"}
}