{
  "id": 7569876,
  "type": "Feature",
  "properties": {
    "tgn:hierarchy":[
        "tgn:7569876",
        "tgn:1000004",
        "tgn:7000198",
        "tgn:1001895",
        "tgn:7029392"
    ],
    "tgn:id":7569876,
    "tgn:name:en":"Velas",
    "tgn:placetype":[
        "aat:300008347"
    ]
},
  "bbox": [],
  "geometry": {"coordinates":[73.033333,17.966667],"type":"Point"}
}