{
  "id": 2050711,
  "type": "Feature",
  "properties": {
    "tgn:hierarchy":[
        "tgn:2050711",
        "tgn:1000001",
        "tgn:7013942",
        "tgn:7012149",
        "tgn:7007517",
        "tgn:7029392"
    ],
    "tgn:id":2050711,
    "tgn:name":"Stoneville",
    "tgn:placetype":[
        "aat:300008347",
        "aat:300387210"
    ]
},
  "bbox": [],
  "geometry": {"coordinates":[-72.3833,42.5833],"type":"Point"}
}