{
  "id": 7416648,
  "type": "Feature",
  "properties": {
    "tgn:hierarchy":[
        "tgn:7416648",
        "tgn:1000001",
        "tgn:7005591",
        "tgn:7005560",
        "tgn:7029392"
    ],
    "tgn:id":7416648,
    "tgn:name:es":"Monte Obscuro",
    "tgn:placetype":[
        "aat:300008347"
    ]
},
  "bbox": [],
  "geometry": {"coordinates":[-97.360278,15.9925],"type":"Point"}
}