{
  "id": 1093494,
  "type": "Feature",
  "properties": {
    "tgn:hierarchy":[
        "tgn:1093494",
        "tgn:7001242",
        "tgn:7017574",
        "tgn:1000193",
        "tgn:7029392"
    ],
    "tgn:id":1093494,
    "tgn:name":"Perdekop",
    "tgn:placetype":[
        "aat:300008347"
    ]
},
  "bbox": [],
  "geometry": {"coordinates":[29.6333,-27.1667],"type":"Point"}
}