{
  "id": 7478671,
  "type": "Feature",
  "properties": {
    "tgn:hierarchy":[
        "tgn:7478671",
        "tgn:1000004",
        "tgn:7489179",
        "tgn:1000141",
        "tgn:7029392"
    ],
    "tgn:id":7478671,
    "tgn:name":"Linheyuan Sihao Qiao",
    "tgn:placetype":[
        "aat:300007836"
    ]
},
  "bbox": [],
  "geometry": {"coordinates":[121.8116,24.651413],"type":"Point"}
}