{
  "id": 7228675,
  "type": "Feature",
  "properties": {
    "tgn:hierarchy":[
        "tgn:7228675",
        "tgn:7002715",
        "tgn:7002731",
        "tgn:1000003",
        "tgn:1000074",
        "tgn:7029392"
    ],
    "tgn:id":7228675,
    "tgn:name":"Koj\u00e1 R\u00e9ma",
    "tgn:placetype":[
        "aat:300008699"
    ]
},
  "bbox": [],
  "geometry": {"coordinates":[23.466667,40.666667],"type":"Point"}
}