{
  "id": 2455215,
  "type": "Feature",
  "properties": {
    "tgn:hierarchy":[
        "tgn:2455215",
        "tgn:1000001",
        "tgn:7016172",
        "tgn:7012149",
        "tgn:2000153",
        "tgn:7029392"
    ],
    "tgn:id":2455215,
    "tgn:name":"Little Fir Landing",
    "tgn:placetype":[
        "aat:300008347"
    ]
},
  "bbox": [],
  "geometry": {"coordinates":[-93.4667,34.6167],"type":"Point"}
}