{
  "id": 7286010,
  "type": "Feature",
  "properties": {
    "tgn:hierarchy":[
        "tgn:7286010",
        "tgn:7002464",
        "tgn:1000049",
        "tgn:1000002",
        "tgn:7029392"
    ],
    "tgn:id":7286010,
    "tgn:name":"La Escalera",
    "tgn:placetype":[
        "aat:300008347"
    ]
},
  "bbox": [],
  "geometry": {"coordinates":[-68.916667,-20.066667],"type":"Point"}
}