{
  "id": 7528335,
  "type": "Feature",
  "properties": {
    "tgn:hierarchy":[
        "tgn:7528335",
        "tgn:7001242",
        "tgn:7016833",
        "tgn:1001080",
        "tgn:7029392"
    ],
    "tgn:id":7528335,
    "tgn:name:en":"Subaytah, Tall as",
    "tgn:placetype":[
        "aat:300008777"
    ]
},
  "bbox": [],
  "geometry": {"coordinates":[32.25,30.816667],"type":"Point"}
}