{
  "id": 2437001,
  "type": "Feature",
  "properties": {
    "tgn:hierarchy":[
        "tgn:2437001",
        "tgn:1000001",
        "tgn:7012149",
        "tgn:2001502",
        "tgn:7007709",
        "tgn:7029392"
    ],
    "tgn:id":2437001,
    "tgn:name":"Killens Hill",
    "tgn:placetype":[
        "aat:300008798"
    ]
},
  "bbox": [],
  "geometry": {"coordinates":[-78.8167,35.2667],"type":"Point"}
}