{
  "id": 7490908,
  "type": "Feature",
  "properties": {
    "tgn:hierarchy":[
        "tgn:7490908",
        "tgn:1000004",
        "tgn:7490934",
        "tgn:1000141",
        "tgn:7029392"
    ],
    "tgn:id":7490908,
    "tgn:name":"Sanhezi",
    "tgn:placetype":[
        "aat:300008347"
    ]
},
  "bbox": [],
  "geometry": {"coordinates":[120.142778,23.144722],"type":"Point"}
}