{
  "id": 7366761,
  "type": "Feature",
  "properties": {
    "tgn:hierarchy":[
        "tgn:7366761",
        "tgn:1000001",
        "tgn:7005595",
        "tgn:7005560",
        "tgn:7029392"
    ],
    "tgn:id":7366761,
    "tgn:name":"El Rinc\u00f3n",
    "tgn:placetype":[
        "aat:300008347"
    ]
},
  "bbox": [],
  "geometry": {"coordinates":[-108.333333,25.766667],"type":"Point"}
}