{
  "id": 1130206,
  "type": "Feature",
  "properties": {
    "tgn:hierarchy":[
        "tgn:1130206",
        "tgn:7001242",
        "tgn:7029392"
    ],
    "tgn:id":1130206,
    "tgn:name":"Sourou",
    "tgn:placetype":[
        "aat:300008707"
    ]
},
  "bbox": [],
  "geometry": {"coordinates":[-3.4167,12.75],"type":"Point"}
}