{
  "id": 2342640,
  "type": "Feature",
  "properties": {
    "tgn:hierarchy":[
        "tgn:2342640",
        "tgn:1000001",
        "tgn:7012149",
        "tgn:1002517",
        "tgn:7007523",
        "tgn:7029392"
    ],
    "tgn:id":2342640,
    "tgn:name":"Fun Valley Lake",
    "tgn:placetype":[
        "aat:300006191"
    ]
},
  "bbox": [],
  "geometry": {"coordinates":[-90.7167,38.45],"type":"Point"}
}