{
  "id": 2471651,
  "type": "Feature",
  "properties": {
    "tgn:hierarchy":[
        "tgn:2471651",
        "tgn:1000001",
        "tgn:7012149",
        "tgn:2001866",
        "tgn:7007825",
        "tgn:7029392"
    ],
    "tgn:id":2471651,
    "tgn:name":"Lost Mountain",
    "tgn:placetype":[
        "aat:300008798"
    ]
},
  "bbox": [],
  "geometry": {"coordinates":[-82.7667,36.3333],"type":"Point"}
}