{
  "id": 7108712,
  "type": "Feature",
  "properties": {
    "tgn:hierarchy":[
        "tgn:7108712",
        "tgn:7003669",
        "tgn:1000003",
        "tgn:7000084",
        "tgn:7029392"
    ],
    "tgn:id":7108712,
    "tgn:name":"Bahnhof Regensburg-Pr\u00fcfening",
    "tgn:placetype":[
        "aat:300007783"
    ]
},
  "bbox": [],
  "geometry": {"coordinates":[12.046111,49.0125],"type":"Point"}
}