{
  "id": 2527957,
  "type": "Feature",
  "properties": {
    "tgn:hierarchy":[
        "tgn:2527957",
        "tgn:1000001",
        "tgn:7012149",
        "tgn:7007157",
        "tgn:2000184",
        "tgn:7029392"
    ],
    "tgn:id":2527957,
    "tgn:name":"Mountain Meadows Reservoir",
    "tgn:placetype":[
        "aat:300006191"
    ]
},
  "bbox": [],
  "geometry": {"coordinates":[-121.0167,40.2833],"type":"Point"}
}