{
  "id": 2480629,
  "type": "Feature",
  "properties": {
    "tgn:hierarchy":[
        "tgn:2480629",
        "tgn:1000001",
        "tgn:7012149",
        "tgn:7007157",
        "tgn:2000187",
        "tgn:7029392"
    ],
    "tgn:id":2480629,
    "tgn:name":"Lakes Basin",
    "tgn:placetype":[
        "aat:300386845"
    ]
},
  "bbox": [],
  "geometry": {"coordinates":[-120.6667,39.6833],"type":"Point"}
}