{
  "id": 2034255,
  "type": "Feature",
  "properties": {
    "tgn:hierarchy":[
        "tgn:2034255",
        "tgn:1000001",
        "tgn:2000572",
        "tgn:7012149",
        "tgn:7007253",
        "tgn:7029392"
    ],
    "tgn:id":2034255,
    "tgn:name":"Allison",
    "tgn:placetype":[
        "aat:300008347"
    ]
},
  "bbox": [],
  "geometry": {"coordinates":[-92.7833,42.75],"type":"Point"}
}