{
  "id": 7041777,
  "type": "Feature",
  "properties": {
    "tgn:hierarchy":[
        "tgn:7041777",
        "tgn:7003154",
        "tgn:1000003",
        "tgn:7003120",
        "tgn:1000080",
        "tgn:7029392"
    ],
    "tgn:id":7041777,
    "tgn:name":"San Francesco al Campo",
    "tgn:placetype":[
        "aat:300008347"
    ]
},
  "bbox": [],
  "geometry": {"coordinates":[7.666667,45.233333],"type":"Point"}
}