{
  "id": 2755269,
  "type": "Feature",
  "properties": {
    "tgn:hierarchy":[
        "tgn:2755269",
        "tgn:1000001",
        "tgn:7006451",
        "tgn:7012149",
        "tgn:7029392"
    ],
    "tgn:id":2755269,
    "tgn:name":"Webber Creek",
    "tgn:placetype":[
        "aat:300008706"
    ]
},
  "bbox": [],
  "geometry": {"coordinates":[-111.3333,34.4167],"type":"Point"}
}