{
  "id": 7563832,
  "type": "Feature",
  "properties": {
    "tgn:hierarchy":[
        "tgn:7563832",
        "tgn:1000004",
        "tgn:7000198",
        "tgn:1001894",
        "tgn:7029392"
    ],
    "tgn:id":7563832,
    "tgn:name:en":"Dadgaon",
    "tgn:placetype":[
        "aat:300008347"
    ]
},
  "bbox": [],
  "geometry": {"coordinates":[79.306602,24.947389],"type":"Point"}
}