{
  "id": 2661559,
  "type": "Feature",
  "properties": {
    "tgn:hierarchy":[
        "tgn:2661559",
        "tgn:1000001",
        "tgn:7006451",
        "tgn:7012149",
        "tgn:2000098",
        "tgn:7029392"
    ],
    "tgn:id":2661559,
    "tgn:name":"Showerbath Spring",
    "tgn:placetype":[
        "aat:300008697"
    ]
},
  "bbox": [],
  "geometry": {"coordinates":[-112.6333,36.45],"type":"Point"}
}