{
  "id": 7337112,
  "type": "Feature",
  "properties": {
    "tgn:hierarchy":[
        "tgn:7337112",
        "tgn:7002760",
        "tgn:1000003",
        "tgn:1000095",
        "tgn:7029392"
    ],
    "tgn:id":7337112,
    "tgn:name":"Cohi\u00f1o",
    "tgn:placetype":[
        "aat:300008347"
    ]
},
  "bbox": [],
  "geometry": {"coordinates":[-4.066667,43.183333],"type":"Point"}
}