{
  "id": 7352781,
  "type": "Feature",
  "properties": {
    "tgn:hierarchy":[
        "tgn:7352781",
        "tgn:1000001",
        "tgn:1001960",
        "tgn:7005560",
        "tgn:7029392"
    ],
    "tgn:id":7352781,
    "tgn:name":"Batamote",
    "tgn:placetype":[
        "aat:300008347"
    ]
},
  "bbox": [],
  "geometry": {"coordinates":[-110.083333,29.916667],"type":"Point"}
}