{
  "id": 2502977,
  "type": "Feature",
  "properties": {
    "tgn:hierarchy":[
        "tgn:2502977",
        "tgn:1000001",
        "tgn:7012149",
        "tgn:2001110",
        "tgn:7007522",
        "tgn:7029392"
    ],
    "tgn:id":2502977,
    "tgn:name":"McNair Branch",
    "tgn:placetype":[
        "aat:300008699"
    ]
},
  "bbox": [],
  "geometry": {"coordinates":[-90.5167,32.1667],"type":"Point"}
}