{
  "id": 1044364,
  "type": "Feature",
  "properties": {
    "tgn:hierarchy":[
        "tgn:1044364",
        "tgn:7002995",
        "tgn:1000003",
        "tgn:7002997",
        "tgn:1000080",
        "tgn:7029392"
    ],
    "tgn:id":1044364,
    "tgn:name":"Contarina",
    "tgn:placetype":[
        "aat:300008347"
    ]
},
  "bbox": [],
  "geometry": {"coordinates":[12.228611,45.027778],"type":"Point"}
}