{
  "id": 2407232,
  "type": "Feature",
  "properties": {
    "tgn:hierarchy":[
        "tgn:2407232",
        "tgn:1000001",
        "tgn:7012149",
        "tgn:1002456",
        "tgn:7007826",
        "tgn:7029392"
    ],
    "tgn:id":2407232,
    "tgn:name":"Hunting Bayou",
    "tgn:placetype":[
        "aat:300008699"
    ]
},
  "bbox": [],
  "geometry": {"coordinates":[-95.3333,29.7833],"type":"Point"}
}