{
  "id": 2205067,
  "type": "Feature",
  "properties": {
    "tgn:hierarchy":[
        "tgn:2205067",
        "tgn:1000001",
        "tgn:7012149",
        "tgn:2002053",
        "tgn:7007826",
        "tgn:7029392"
    ],
    "tgn:id":2205067,
    "tgn:name":"Bugle Mountain",
    "tgn:placetype":[
        "aat:300008798"
    ]
},
  "bbox": [],
  "geometry": {"coordinates":[-98.1667,32.55],"type":"Point"}
}