{
  "id": 2670417,
  "type": "Feature",
  "properties": {
    "tgn:hierarchy":[
        "tgn:2670417",
        "tgn:1000001",
        "tgn:7012149",
        "tgn:2000834",
        "tgn:7007255",
        "tgn:7029392"
    ],
    "tgn:id":2670417,
    "tgn:name":"Smallhous",
    "tgn:placetype":[
        "aat:300008347"
    ]
},
  "bbox": [],
  "geometry": {"coordinates":[-87.0833,37.3667],"type":"Point"}
}