{
  "id": 2748286,
  "type": "Feature",
  "properties": {
    "tgn:hierarchy":[
        "tgn:2748286",
        "tgn:7002659",
        "tgn:1000001",
        "tgn:7012149",
        "tgn:2000063",
        "tgn:7029392"
    ],
    "tgn:id":2748286,
    "tgn:name":"Walker County Lake",
    "tgn:placetype":[
        "aat:300006191"
    ]
},
  "bbox": [],
  "geometry": {"coordinates":[-87.2167,33.7833],"type":"Point"}
}