<<<<<<< HEAD
{
  "id": 7479736,
  "type": "Feature",
  "properties": {
    "tgn:hierarchy":[
        "tgn:7479736",
        "tgn:1000004",
        "tgn:7490934",
        "tgn:1000141",
        "tgn:7029392"
    ],
    "tgn:id":7479736,
    "tgn:name":"Sanxin Qiao",
    "tgn:placetype":[
        "aat:300007836"
    ]
},
  "bbox": [],
  "geometry": {"coordinates":[120.295007,23.085683],"type":"Point"}
}
=======
{"geometry":{"type":"Point","coordinates":[120.295007,23.085683]},"type":"Feature","properties":{"hierarchy":["tgn:7479736","tgn:1000004","tgn:7490934","tgn:1000141","tgn:7029392"],"placetype":["aat:300007836"],"id":7479736,"name:xx":"Sanxin Qiao"}}
>>>>>>> 03f74aca74312dbeaf24d7e61306dd6a786dc3d0
