{
  "id": 2431766,
  "type": "Feature",
  "properties": {
    "tgn:hierarchy":[
        "tgn:2431766",
        "tgn:1000001",
        "tgn:7012149",
        "tgn:7007568",
        "tgn:7029392"
    ],
    "tgn:id":2431766,
    "tgn:name":"Kattskill Bay",
    "tgn:placetype":[
        "aat:300132316"
    ]
},
  "bbox": [],
  "geometry": {"coordinates":[-73.6167,43.4667],"type":"Point"}
}