{
  "id": 1065292,
  "type": "Feature",
  "properties": {
    "tgn:hierarchy":[
        "tgn:1065292",
        "tgn:1000003",
        "tgn:7015141",
        "tgn:7006670",
        "tgn:7029392"
    ],
    "tgn:id":1065292,
    "tgn:name":"Tolmin",
    "tgn:placetype":[
        "aat:300008347",
        "aat:300387222",
        "aat:300008375"
    ]
},
  "bbox": [],
  "geometry": {"coordinates":[13.75,46.1833],"type":"Point"}
}