{
  "id": 2285376,
  "type": "Feature",
  "properties": {
    "tgn:hierarchy":[
        "tgn:2285376",
        "tgn:1000001",
        "tgn:7012149",
        "tgn:2002353",
        "tgn:7007922",
        "tgn:7029392"
    ],
    "tgn:id":2285376,
    "tgn:name":"Devils Creek",
    "tgn:placetype":[
        "aat:300008706"
    ]
},
  "bbox": [],
  "geometry": {"coordinates":[-91.3167,45.85],"type":"Point"}
}