{
  "id": 2535059,
  "type": "Feature",
  "properties": {
    "tgn:hierarchy":[
        "tgn:2535059",
        "tgn:7023902",
        "tgn:1000001",
        "tgn:7012149",
        "tgn:7007249",
        "tgn:7029392"
    ],
    "tgn:id":2535059,
    "tgn:name":"Nanawale Bay",
    "tgn:placetype":[
        "aat:300132316"
    ]
},
  "bbox": [],
  "geometry": {"coordinates":[-154.8667,19.55],"type":"Point"}
}