{
  "id": 2263266,
  "type": "Feature",
  "properties": {
    "tgn:hierarchy":[
        "tgn:2263266",
        "tgn:1000001",
        "tgn:2001429",
        "tgn:7012149",
        "tgn:7007566",
        "tgn:7029392"
    ],
    "tgn:id":2263266,
    "tgn:name":"Cox Canyon",
    "tgn:placetype":[
        "aat:300008761"
    ]
},
  "bbox": [],
  "geometry": {"coordinates":[-108.4333,33.7333],"type":"Point"}
}