{
  "id": 2708365,
  "type": "Feature",
  "properties": {
    "tgn:hierarchy":[
        "tgn:2708365",
        "tgn:1000001",
        "tgn:7006451",
        "tgn:7012149",
        "tgn:2000103",
        "tgn:7029392"
    ],
    "tgn:id":2708365,
    "tgn:name":"Sycamore Canyon",
    "tgn:placetype":[
        "aat:300008761"
    ]
},
  "bbox": [],
  "geometry": {"coordinates":[-111.6333,34.4667],"type":"Point"}
}