<<<<<<< HEAD
{
  "id": 7023803,
  "type": "Feature",
  "properties": {
    "tgn:hierarchy":[
        "tgn:7023803",
        "tgn:1000001",
        "tgn:2002259",
        "tgn:7012149",
        "tgn:7013961",
        "tgn:7029392"
    ],
    "tgn:id":7023803,
    "tgn:name":"Two Run",
    "tgn:placetype":[
        "aat:300008699"
    ]
},
  "bbox": [],
  "geometry": {"coordinates":[-81.0667,38.5167],"type":"Point"}
}
=======
{"geometry":{"type":"Point","coordinates":[-81.066700,38.516700]},"type":"Feature","properties":{"hierarchy":["tgn:7023803","tgn:1000001","tgn:2002259","tgn:7012149","tgn:7013961","tgn:7029392"],"placetype":["aat:300008699"],"id":7023803,"name:xx":"Two Run"}}
>>>>>>> 03f74aca74312dbeaf24d7e61306dd6a786dc3d0
