{
  "id": 2621677,
  "type": "Feature",
  "properties": {
    "tgn:hierarchy":[
        "tgn:2621677",
        "tgn:1000001",
        "tgn:2001350",
        "tgn:7012149",
        "tgn:7007525",
        "tgn:7029392"
    ],
    "tgn:id":2621677,
    "tgn:name":"Robb Valley",
    "tgn:placetype":[
        "aat:300386845"
    ]
},
  "bbox": [],
  "geometry": {"coordinates":[-102.15,41.75],"type":"Point"}
}