{
  "id": 1002811,
  "type": "Feature",
  "properties": {
    "tgn:hierarchy":[
        "tgn:1002811",
        "tgn:1000001",
        "tgn:7012149",
        "tgn:7007706",
        "tgn:7029392"
    ],
    "tgn:id":1002811,
    "tgn:name":"Putnam",
    "tgn:placetype":[
        "aat:300387145",
        "aat:300000771"
    ]
},
  "bbox": [],
  "geometry": {"coordinates":[-84.1333,41.0333],"type":"Point"}
}