<<<<<<< HEAD
{
  "id": 2156124,
  "type": "Feature",
  "properties": {
    "tgn:hierarchy":[
        "tgn:2156124",
        "tgn:1000001",
        "tgn:7012149",
        "tgn:2001532",
        "tgn:7007709",
        "tgn:7029392"
    ],
    "tgn:id":2156124,
    "tgn:name":"Beard Lake",
    "tgn:placetype":[
        "aat:300006191"
    ]
},
  "bbox": [],
  "geometry": {"coordinates":[-79.9333,35.8167],"type":"Point"}
}
=======
{"geometry":{"type":"Point","coordinates":[-79.933300,35.816700]},"type":"Feature","properties":{"hierarchy":["tgn:2156124","tgn:1000001","tgn:7012149","tgn:2001532","tgn:7007709","tgn:7029392"],"placetype":["aat:300006191"],"id":2156124,"name:xx":"Beard Lake"}}
>>>>>>> 03f74aca74312dbeaf24d7e61306dd6a786dc3d0
