{
  "id": 2156124,
  "type": "Feature",
  "properties": {
    "tgn:hierarchy":[
        "tgn:2156124",
        "tgn:1000001",
        "tgn:7012149",
        "tgn:2001532",
        "tgn:7007709",
        "tgn:7029392"
    ],
    "tgn:id":2156124,
    "tgn:name":"Beard Lake",
    "tgn:placetype":[
        "aat:300006191"
    ]
},
  "bbox": [],
  "geometry": {"coordinates":[-79.9333,35.8167],"type":"Point"}
}