{
  "id": 7527904,
  "type": "Feature",
  "properties": {
    "tgn:hierarchy":[
        "tgn:7527904",
        "tgn:7001242",
        "tgn:7001311",
        "tgn:7016833",
        "tgn:7029392"
    ],
    "tgn:id":7527904,
    "tgn:name:en":"Um Markh, W\u00e2di",
    "tgn:placetype":[
        "aat:300379998"
    ]
},
  "bbox": [],
  "geometry": {"coordinates":[35.440296,23.591246],"type":"Point"}
}