{
  "id": 7036011,
  "type": "Feature",
  "properties": {
    "tgn:hierarchy":[
        "tgn:7036011",
        "tgn:7002991",
        "tgn:1000003",
        "tgn:7002997",
        "tgn:1000080",
        "tgn:7029392"
    ],
    "tgn:id":7036011,
    "tgn:name":"Piz Popena",
    "tgn:placetype":[
        "aat:300008795"
    ]
},
  "bbox": [],
  "geometry": {"coordinates":[12.212222,46.583333],"type":"Point"}
}