{
  "id": 7150796,
  "type": "Feature",
  "properties": {
    "tgn:hierarchy":[
        "tgn:7150796",
        "tgn:1000003",
        "tgn:7003687",
        "tgn:7000084",
        "tgn:7029392"
    ],
    "tgn:id":7150796,
    "tgn:name":"Krakau Rathsbruch",
    "tgn:placetype":[
        "aat:300055621"
    ]
},
  "bbox": [],
  "geometry": {"coordinates":[12.283333,51.983333],"type":"Point"}
}