{
  "id": 7276273,
  "type": "Feature",
  "properties": {
    "tgn:hierarchy":[
        "tgn:7276273",
        "tgn:1001623",
        "tgn:1000049",
        "tgn:1000002",
        "tgn:7029392"
    ],
    "tgn:id":7276273,
    "tgn:name":"Tehuelche, Cerro",
    "tgn:placetype":[
        "aat:300008795"
    ]
},
  "bbox": [],
  "geometry": {"coordinates":[-71.733333,-46.55],"type":"Point"}
}