{
  "id": 2745814,
  "type": "Feature",
  "properties": {
    "tgn:hierarchy":[
        "tgn:2745814",
        "tgn:1000001",
        "tgn:7012149",
        "tgn:2002217",
        "tgn:7007919",
        "tgn:7029392"
    ],
    "tgn:id":2745814,
    "tgn:name":"Vista Acres",
    "tgn:placetype":[
        "aat:300008347"
    ]
},
  "bbox": [],
  "geometry": {"coordinates":[-79.1833,37.3333],"type":"Point"}
}