<<<<<<< HEAD
{
  "id": 7171286,
  "type": "Feature",
  "properties": {
    "tgn:hierarchy":[
        "tgn:7171286",
        "tgn:1000003",
        "tgn:7003685",
        "tgn:7000084",
        "tgn:7029392"
    ],
    "tgn:id":7171286,
    "tgn:name":"Hirschel-Berg",
    "tgn:placetype":[
        "aat:300008777"
    ]
},
  "bbox": [],
  "geometry": {"coordinates":[13.45,51.05],"type":"Point"}
}
=======
{"geometry":{"type":"Point","coordinates":[13.450000,51.050000]},"type":"Feature","properties":{"hierarchy":["tgn:7171286","tgn:1000003","tgn:7003685","tgn:7000084","tgn:7029392"],"placetype":["aat:300008777"],"id":7171286,"name:xx":"Hirschel-Berg"}}
>>>>>>> 03f74aca74312dbeaf24d7e61306dd6a786dc3d0
