{
  "id": 2293621,
  "type": "Feature",
  "properties": {
    "tgn:hierarchy":[
        "tgn:2293621",
        "tgn:1000001",
        "tgn:7016172",
        "tgn:7012149",
        "tgn:2000139",
        "tgn:7029392"
    ],
    "tgn:id":2293621,
    "tgn:name":"Double Wells",
    "tgn:placetype":[
        "aat:300008347"
    ]
},
  "bbox": [],
  "geometry": {"coordinates":[-92.1833,34.15],"type":"Point"}
}