{
  "id": 7268618,
  "type": "Feature",
  "properties": {
    "tgn:concordances":{
        "gn:id":"2747895"
    },
    "tgn:hierarchy":[
        "tgn:7268618",
        "tgn:1000003",
        "tgn:7003622",
        "tgn:7016845",
        "tgn:7029392"
    ],
    "tgn:id":7268618,
    "tgn:name:nl":"Rott",
    "tgn:placetype":[
        "aat:300008347"
    ]
},
  "bbox": [],
  "geometry": {"coordinates":[5.95,50.783333],"type":"Point"}
}