{
  "id": 7021469,
  "type": "Feature",
  "properties": {
    "tgn:hierarchy":[
        "tgn:7021469",
        "tgn:1000001",
        "tgn:7012149",
        "tgn:2002300",
        "tgn:7013961",
        "tgn:7029392"
    ],
    "tgn:id":7021469,
    "tgn:name":"Big Lick Fork",
    "tgn:placetype":[
        "aat:300008699"
    ]
},
  "bbox": [],
  "geometry": {"coordinates":[-80.3333,38.6167],"type":"Point"}
}