{
  "id": 7577358,
  "type": "Feature",
  "properties": {
    "tgn:hierarchy":[
        "tgn:7577358",
        "tgn:1000004",
        "tgn:7000198",
        "tgn:1001895",
        "tgn:7029392"
    ],
    "tgn:id":7577358,
    "tgn:name:en":"Kuchi",
    "tgn:placetype":[
        "aat:300008347"
    ]
},
  "bbox": [],
  "geometry": {"coordinates":[74.866667,17.066667],"type":"Point"}
}