{
  "id": 7027535,
  "type": "Feature",
  "properties": {
    "tgn:hierarchy":[
        "tgn:7027535",
        "tgn:7002445",
        "tgn:1000003",
        "tgn:7008155",
        "tgn:7008591",
        "tgn:7029392"
    ],
    "tgn:id":7027535,
    "tgn:name:en":"Buckminster",
    "tgn:placetype":[
        "aat:300008347",
        "aat:300008372"
    ]
},
  "bbox": [],
  "geometry": {"coordinates":[-0.683333,52.783333],"type":"Point"}
}