{
  "id": 7498997,
  "type": "Feature",
  "properties": {
    "tgn:hierarchy":[
        "tgn:7498997",
        "tgn:7488858",
        "tgn:1000004",
        "tgn:1000141",
        "tgn:7029392"
    ],
    "tgn:id":7498997,
    "tgn:name":"Fujin Gong",
    "tgn:placetype":[
        "aat:300007595"
    ]
},
  "bbox": [],
  "geometry": {"coordinates":[120.950196,24.029845],"type":"Point"}
}