{
  "id": 2020908,
  "type": "Feature",
  "properties": {
    "tgn:hierarchy":[
        "tgn:2020908",
        "tgn:1000001",
        "tgn:7012149",
        "tgn:1002567",
        "tgn:7007240",
        "tgn:7029392"
    ],
    "tgn:id":2020908,
    "tgn:name":"Pittman",
    "tgn:placetype":[
        "aat:300008347"
    ]
},
  "bbox": [],
  "geometry": {"coordinates":[-81.6333,28.9833],"type":"Point"}
}