{
  "id": 7317300,
  "type": "Feature",
  "properties": {
    "tgn:hierarchy":[
        "tgn:7317300",
        "tgn:1001768",
        "tgn:1000049",
        "tgn:1000002",
        "tgn:7029392"
    ],
    "tgn:id":7317300,
    "tgn:name":"Cochoa, Caleta",
    "tgn:placetype":[
        "aat:300132317"
    ]
},
  "bbox": [],
  "geometry": {"coordinates":[-71.55,-32.95],"type":"Point"}
}