{
  "id": 2533136,
  "type": "Feature",
  "properties": {
    "tgn:hierarchy":[
        "tgn:2533136",
        "tgn:1000001",
        "tgn:7012149",
        "tgn:2002326",
        "tgn:7007922",
        "tgn:7029392"
    ],
    "tgn:id":2533136,
    "tgn:name":"Muscoda Island",
    "tgn:placetype":[
        "aat:300008791"
    ]
},
  "bbox": [],
  "geometry": {"coordinates":[-90.4167,43.1833],"type":"Point"}
}