{
  "id": 7071880,
  "type": "Feature",
  "properties": {
    "tgn:hierarchy":[
        "tgn:7071880",
        "tgn:1000003",
        "tgn:7003687",
        "tgn:7000084",
        "tgn:7029392"
    ],
    "tgn:id":7071880,
    "tgn:name":"Thekenberge",
    "tgn:placetype":[
        "aat:300008777"
    ]
},
  "bbox": [],
  "geometry": {"coordinates":[11.033333,51.85],"type":"Point"}
}