{
  "id": 2002955,
  "type": "Feature",
  "properties": {
    "tgn:hierarchy":[
        "tgn:2002955",
        "tgn:7002659",
        "tgn:1000001",
        "tgn:7012149",
        "tgn:2000058",
        "tgn:7029392"
    ],
    "tgn:id":2002955,
    "tgn:name":"Cahaba River Estates",
    "tgn:placetype":[
        "aat:300008347"
    ]
},
  "bbox": [],
  "geometry": {"coordinates":[-86.8167,33.35],"type":"Point"}
}