{
  "id": 2667308,
  "type": "Feature",
  "properties": {
    "tgn:hierarchy":[
        "tgn:2667308",
        "tgn:1000001",
        "tgn:7012149",
        "tgn:2002290",
        "tgn:7013961",
        "tgn:7029392"
    ],
    "tgn:id":2667308,
    "tgn:name":"Skinner Fork",
    "tgn:placetype":[
        "aat:300008699"
    ]
},
  "bbox": [],
  "geometry": {"coordinates":[-81.3167,37.7167],"type":"Point"}
}