{
  "id": 7415344,
  "type": "Feature",
  "properties": {
    "tgn:hierarchy":[
        "tgn:7415344",
        "tgn:7005584",
        "tgn:1000001",
        "tgn:7005560",
        "tgn:7029392"
    ],
    "tgn:id":7415344,
    "tgn:name":"Victoria, R\u00edo",
    "tgn:placetype":[
        "aat:300008699"
    ]
},
  "bbox": [],
  "geometry": {"coordinates":[-100.093611,21.171667],"type":"Point"}
}