<<<<<<< HEAD
{
  "id": 2331397,
  "type": "Feature",
  "properties": {
    "tgn:hierarchy":[
        "tgn:2331397",
        "tgn:1000001",
        "tgn:7016172",
        "tgn:7012149",
        "tgn:2000155",
        "tgn:7029392"
    ],
    "tgn:id":2331397,
    "tgn:name":"Flatrock Creek",
    "tgn:placetype":[
        "aat:300008706"
    ]
},
  "bbox": [],
  "geometry": {"coordinates":[-93.05,36.1],"type":"Point"}
}
=======
{"geometry":{"type":"Point","coordinates":[-93.050000,36.100000]},"type":"Feature","properties":{"hierarchy":["tgn:2331397","tgn:1000001","tgn:7016172","tgn:7012149","tgn:2000155","tgn:7029392"],"placetype":["aat:300008706"],"id":2331397,"name:xx":"Flatrock Creek"}}
>>>>>>> 03f74aca74312dbeaf24d7e61306dd6a786dc3d0
