{
  "id": 2587236,
  "type": "Feature",
  "properties": {
    "tgn:hierarchy":[
        "tgn:2587236",
        "tgn:1000001",
        "tgn:7012149",
        "tgn:2000973",
        "tgn:7007520",
        "tgn:7029392"
    ],
    "tgn:id":2587236,
    "tgn:name":"Platz Lake",
    "tgn:placetype":[
        "aat:300008680"
    ]
},
  "bbox": [],
  "geometry": {"coordinates":[-84.6833,46.05],"type":"Point"}
}