{
  "id": 7485187,
  "type": "Feature",
  "properties": {
    "tgn:hierarchy":[
        "tgn:7485187",
        "tgn:1000004",
        "tgn:7491221",
        "tgn:1000141",
        "tgn:7029392"
    ],
    "tgn:id":7485187,
    "tgn:name":"Chaoyong Xikou",
    "tgn:placetype":[
        "aat:300387057"
    ]
},
  "bbox": [],
  "geometry": {"coordinates":[120.8975,22.339722],"type":"Point"}
}