<<<<<<< HEAD
{
  "id": 7485187,
  "type": "Feature",
  "properties": {
    "tgn:hierarchy":[
        "tgn:7485187",
        "tgn:1000004",
        "tgn:7491221",
        "tgn:1000141",
        "tgn:7029392"
    ],
    "tgn:id":7485187,
    "tgn:name":"Chaoyong Xikou",
    "tgn:placetype":[
        "aat:300387057"
    ]
},
  "bbox": [],
  "geometry": {"coordinates":[120.8975,22.339722],"type":"Point"}
}
=======
{"geometry":{"type":"Point","coordinates":[120.897500,22.339722]},"type":"Feature","properties":{"hierarchy":["tgn:7485187","tgn:1000004","tgn:7491221","tgn:1000141","tgn:7029392"],"placetype":["aat:300387057"],"id":7485187,"name:xx":"Chaoyong Xikou"}}
>>>>>>> 03f74aca74312dbeaf24d7e61306dd6a786dc3d0
