{
  "id": 7209164,
  "type": "Feature",
  "properties": {
    "tgn:hierarchy":[
        "tgn:7209164",
        "tgn:1000003",
        "tgn:7003688",
        "tgn:7000084",
        "tgn:7029392"
    ],
    "tgn:id":7209164,
    "tgn:name":"Beck",
    "tgn:placetype":[
        "aat:300008699"
    ]
},
  "bbox": [],
  "geometry": {"coordinates":[9.85,53.666667],"type":"Point"}
}