<<<<<<< HEAD
{
  "id": 2151213,
  "type": "Feature",
  "properties": {
    "tgn:hierarchy":[
        "tgn:2151213",
        "tgn:1000001",
        "tgn:1002480",
        "tgn:7012149",
        "tgn:7007564",
        "tgn:7029392"
    ],
    "tgn:id":2151213,
    "tgn:name":"Bate Pond",
    "tgn:placetype":[
        "aat:300008680"
    ]
},
  "bbox": [],
  "geometry": {"coordinates":[-71.6333,42.9],"type":"Point"}
}
=======
{"geometry":{"type":"Point","coordinates":[-71.633300,42.900000]},"type":"Feature","properties":{"hierarchy":["tgn:2151213","tgn:1000001","tgn:1002480","tgn:7012149","tgn:7007564","tgn:7029392"],"placetype":["aat:300008680"],"id":2151213,"name:xx":"Bate Pond"}}
>>>>>>> 03f74aca74312dbeaf24d7e61306dd6a786dc3d0
