{
  "id": 7280775,
  "type": "Feature",
  "properties": {
    "tgn:hierarchy":[
        "tgn:7280775",
        "tgn:1001702",
        "tgn:1000049",
        "tgn:1000002",
        "tgn:7029392"
    ],
    "tgn:id":7280775,
    "tgn:name":"Sim\u00f3n, Bah\u00eda",
    "tgn:placetype":[
        "aat:300132316"
    ]
},
  "bbox": [],
  "geometry": {"coordinates":[-72.033333,-53.883333],"type":"Point"}
}