<<<<<<< HEAD
{
  "id": 2150006,
  "type": "Feature",
  "properties": {
    "tgn:hierarchy":[
        "tgn:2150006",
        "tgn:1000001",
        "tgn:7006451",
        "tgn:7012149",
        "tgn:2000103",
        "tgn:7029392"
    ],
    "tgn:id":2150006,
    "tgn:name":"Bartol Spring",
    "tgn:placetype":[
        "aat:300008697"
    ]
},
  "bbox": [],
  "geometry": {"coordinates":[-112.3167,34.15],"type":"Point"}
}
=======
{"geometry":{"type":"Point","coordinates":[-112.316700,34.150000]},"type":"Feature","properties":{"hierarchy":["tgn:2150006","tgn:1000001","tgn:7006451","tgn:7012149","tgn:2000103","tgn:7029392"],"placetype":["aat:300008697"],"id":2150006,"name:xx":"Bartol Spring"}}
>>>>>>> 03f74aca74312dbeaf24d7e61306dd6a786dc3d0
