{
  "id": 1085450,
  "type": "Feature",
  "properties": {
    "tgn:hierarchy":[
        "tgn:1085450",
        "tgn:7000910",
        "tgn:7005193",
        "tgn:1000004",
        "tgn:1000142",
        "tgn:7029392"
    ],
    "tgn:id":1085450,
    "tgn:name":"Ban Kruat",
    "tgn:placetype":[
        "aat:300008347"
    ]
},
  "bbox": [],
  "geometry": {"coordinates":[103.1167,14.4167],"type":"Point"}
}