{
  "id": 7544231,
  "type": "Feature",
  "properties": {
    "tgn:hierarchy":[
        "tgn:7544231",
        "tgn:7001242",
        "tgn:7016833",
        "tgn:1001110",
        "tgn:7029392"
    ],
    "tgn:id":7544231,
    "tgn:name":"Ab\u016b S\u0101lah, W\u0101d\u012b",
    "tgn:placetype":[
        "aat:300379998"
    ]
},
  "bbox": [],
  "geometry": {"coordinates":[32.460278,29.905833],"type":"Point"}
}