{
  "id": 7132655,
  "type": "Feature",
  "properties": {
    "tgn:hierarchy":[
        "tgn:7132655",
        "tgn:1000003",
        "tgn:7003677",
        "tgn:7000084",
        "tgn:7029392"
    ],
    "tgn:id":7132655,
    "tgn:name":"Bahnhof Marbeck-Heiden",
    "tgn:placetype":[
        "aat:300007783"
    ]
},
  "bbox": [],
  "geometry": {"coordinates":[6.905278,51.810278],"type":"Point"}
}