{
  "id": 7559976,
  "type": "Feature",
  "properties": {
    "tgn:hierarchy":[
        "tgn:7559976",
        "tgn:1000004",
        "tgn:7000198",
        "tgn:7016722",
        "tgn:7029392"
    ],
    "tgn:id":7559976,
    "tgn:name:en":"Dhari\u0101n",
    "tgn:placetype":[
        "aat:300008347"
    ]
},
  "bbox": [],
  "geometry": {"coordinates":[79.704962,27.706493],"type":"Point"}
}