{
  "id": 2194950,
  "type": "Feature",
  "properties": {
    "tgn:hierarchy":[
        "tgn:2194950",
        "tgn:1000001",
        "tgn:2000954",
        "tgn:7012149",
        "tgn:7007520",
        "tgn:7029392"
    ],
    "tgn:id":2194950,
    "tgn:name":"Bright Lake",
    "tgn:placetype":[
        "aat:300008680"
    ]
},
  "bbox": [],
  "geometry": {"coordinates":[-84.6833,44.7167],"type":"Point"}
}