{
  "id": 7572577,
  "type": "Feature",
  "properties": {
    "tgn:hierarchy":[
        "tgn:7572577",
        "tgn:1000004",
        "tgn:7000198",
        "tgn:1001882",
        "tgn:7029392"
    ],
    "tgn:id":7572577,
    "tgn:name:en":"Hoshalli",
    "tgn:placetype":[
        "aat:300008347"
    ]
},
  "bbox": [],
  "geometry": {"coordinates":[77.444722,13.447222],"type":"Point"}
}