{
  "id": 2498993,
  "type": "Feature",
  "properties": {
    "tgn:hierarchy":[
        "tgn:2498993",
        "tgn:1000001",
        "tgn:7012149",
        "tgn:2002183",
        "tgn:7007919",
        "tgn:7029392"
    ],
    "tgn:id":2498993,
    "tgn:name":"McCarthy Camp Caves",
    "tgn:placetype":[
        "aat:300008746"
    ]
},
  "bbox": [],
  "geometry": {"coordinates":[-80.6667,37.0167],"type":"Point"}
}