{
  "id": 7439632,
  "type": "Feature",
  "properties": {
    "tgn:hierarchy":[
        "tgn:7439632",
        "tgn:1000001",
        "tgn:7005600",
        "tgn:7005560",
        "tgn:7029392"
    ],
    "tgn:id":7439632,
    "tgn:name":"Santa Cruz",
    "tgn:placetype":[
        "aat:300008347"
    ]
},
  "bbox": [],
  "geometry": {"coordinates":[-89.75,20.85],"type":"Point"}
}