{
  "id": 2750339,
  "type": "Feature",
  "properties": {
    "tgn:hierarchy":[
        "tgn:2750339",
        "tgn:1000001",
        "tgn:7012149",
        "tgn:1002555",
        "tgn:7007523",
        "tgn:7029392"
    ],
    "tgn:id":2750339,
    "tgn:name":"Wamsley Lake",
    "tgn:placetype":[
        "aat:300006191"
    ]
},
  "bbox": [],
  "geometry": {"coordinates":[-92.0667,40.0333],"type":"Point"}
}