{
  "id": 7490014,
  "type": "Feature",
  "properties": {
    "tgn:hierarchy":[
        "tgn:7490014",
        "tgn:1000004",
        "tgn:7004300",
        "tgn:1000141",
        "tgn:7029392"
    ],
    "tgn:id":7490014,
    "tgn:name":"Buchuan'an Yugang",
    "tgn:placetype":[
        "aat:300008678"
    ]
},
  "bbox": [],
  "geometry": {"coordinates":[119.495,23.3875],"type":"Point"}
}