{
  "id": 2305377,
  "type": "Feature",
  "properties": {
    "tgn:hierarchy":[
        "tgn:2305377",
        "tgn:1000001",
        "tgn:7012149",
        "tgn:7007520",
        "tgn:7029392"
    ],
    "tgn:id":2305377,
    "tgn:name":"East Branch Whitefish River",
    "tgn:placetype":[
        "aat:300008707"
    ]
},
  "bbox": [],
  "geometry": {"coordinates":[-86.85,46.2333],"type":"Point"}
}