{
  "id": 1047335,
  "type": "Feature",
  "properties": {
    "tgn:hierarchy":[
        "tgn:1047335",
        "tgn:7002996",
        "tgn:1000003",
        "tgn:7002997",
        "tgn:1000080",
        "tgn:7029392"
    ],
    "tgn:id":1047335,
    "tgn:name":"Vedelago",
    "tgn:placetype":[
        "aat:300008347"
    ]
},
  "bbox": [],
  "geometry": {"coordinates":[12.016389,45.687222],"type":"Point"}
}