{
  "id": 2221102,
  "type": "Feature",
  "properties": {
    "tgn:hierarchy":[
        "tgn:2221102",
        "tgn:1000001",
        "tgn:2001264",
        "tgn:7012149",
        "tgn:7007524",
        "tgn:7029392"
    ],
    "tgn:id":2221102,
    "tgn:name":"Carbonado Ditch",
    "tgn:placetype":[
        "aat:300006075"
    ]
},
  "bbox": [],
  "geometry": {"coordinates":[-109.0167,45.45],"type":"Point"}
}