{
  "id": 7353110,
  "type": "Feature",
  "properties": {
    "tgn:hierarchy":[
        "tgn:7353110",
        "tgn:1000001",
        "tgn:1001960",
        "tgn:7005560",
        "tgn:7029392"
    ],
    "tgn:id":7353110,
    "tgn:name":"Bayojori",
    "tgn:placetype":[
        "aat:300008347"
    ]
},
  "bbox": [],
  "geometry": {"coordinates":[-109.65,27.083333],"type":"Point"}
}