<<<<<<< HEAD
{
  "id": 2150893,
  "type": "Feature",
  "properties": {
    "tgn:hierarchy":[
        "tgn:2150893",
        "tgn:1000001",
        "tgn:7012149",
        "tgn:2000962",
        "tgn:7007520",
        "tgn:7029392"
    ],
    "tgn:id":2150893,
    "tgn:name":"Bass Lake Drain",
    "tgn:placetype":[
        "aat:300006075"
    ]
},
  "bbox": [],
  "geometry": {"coordinates":[-84.8,43.4333],"type":"Point"}
}
=======
{"geometry":{"type":"Point","coordinates":[-84.800000,43.433300]},"type":"Feature","properties":{"hierarchy":["tgn:2150893","tgn:1000001","tgn:7012149","tgn:2000962","tgn:7007520","tgn:7029392"],"placetype":["aat:300006075"],"id":2150893,"name:xx":"Bass Lake Drain"}}
>>>>>>> 03f74aca74312dbeaf24d7e61306dd6a786dc3d0
