<<<<<<< HEAD
{
  "id": 7240896,
  "type": "Feature",
  "properties": {
    "tgn:hierarchy":[
        "tgn:7240896",
        "tgn:7003466",
        "tgn:1000003",
        "tgn:1000063",
        "tgn:4012014",
        "tgn:7029392"
    ],
    "tgn:id":7240896,
    "tgn:name":"Forge du Prince, Ruisseau de la",
    "tgn:placetype":[
        "aat:300008699"
    ]
},
  "bbox": [],
  "geometry": {"coordinates":[4.516667,50.016667],"type":"Point"}
}
=======
{"geometry":{"type":"Point","coordinates":[4.516667,50.016667]},"type":"Feature","properties":{"hierarchy":["tgn:7240896","tgn:7003466","tgn:1000003","tgn:1000063","tgn:4012014","tgn:7029392"],"placetype":["aat:300008699"],"id":7240896,"name:xx":"Forge du Prince, Ruisseau de la"}}
>>>>>>> 03f74aca74312dbeaf24d7e61306dd6a786dc3d0
