{
  "id": 7493370,
  "type": "Feature",
  "properties": {
    "tgn:hierarchy":[
        "tgn:7493370",
        "tgn:1000004",
        "tgn:1000454",
        "tgn:1000141",
        "tgn:7029392"
    ],
    "tgn:id":7493370,
    "tgn:name":"Changshou Shan",
    "tgn:placetype":[
        "aat:300008777"
    ]
},
  "bbox": [],
  "geometry": {"coordinates":[121.407129,24.940477],"type":"Point"}
}