{
  "id": 2396976,
  "type": "Feature",
  "properties": {
    "tgn:hierarchy":[
        "tgn:2396976",
        "tgn:1000001",
        "tgn:7012149",
        "tgn:2001442",
        "tgn:7007566",
        "tgn:7029392"
    ],
    "tgn:id":2396976,
    "tgn:name":"Homestake Mine",
    "tgn:placetype":[
        "aat:300000390"
    ]
},
  "bbox": [],
  "geometry": {"coordinates":[-105.8167,33.55],"type":"Point"}
}