{
  "id": 2161238,
  "type": "Feature",
  "properties": {
    "tgn:hierarchy":[
        "tgn:2161238",
        "tgn:1000001",
        "tgn:7012149",
        "tgn:2001917",
        "tgn:7007825",
        "tgn:7029392"
    ],
    "tgn:id":2161238,
    "tgn:name":"Bell Hollow",
    "tgn:placetype":[
        "aat:300008761"
    ]
},
  "bbox": [],
  "geometry": {"coordinates":[-87.8667,36.4167],"type":"Point"}
}