{
  "id": 7039263,
  "type": "Feature",
  "properties": {
    "tgn:hierarchy":[
        "tgn:7039263",
        "tgn:7003248",
        "tgn:1000003",
        "tgn:7010380",
        "tgn:1000080",
        "tgn:7029392"
    ],
    "tgn:id":7039263,
    "tgn:name":"Sovereto",
    "tgn:placetype":[
        "aat:300008347"
    ]
},
  "bbox": [],
  "geometry": {"coordinates":[16.583333,41.116667],"type":"Point"}
}