{
  "id": 1030661,
  "type": "Feature",
  "properties": {
    "tgn:hierarchy":[
        "tgn:1030661",
        "tgn:7002445",
        "tgn:1000003",
        "tgn:7008154",
        "tgn:7008591",
        "tgn:7029392"
    ],
    "tgn:id":1030661,
    "tgn:name:en":"Sollom",
    "tgn:placetype":[
        "aat:300008347"
    ]
},
  "bbox": [],
  "geometry": {"coordinates":[-2.833333,53.65],"type":"Point"}
}