<<<<<<< HEAD
{
  "id": 2404441,
  "type": "Feature",
  "properties": {
    "tgn:hierarchy":[
        "tgn:2404441",
        "tgn:1000001",
        "tgn:7012149",
        "tgn:1003005",
        "tgn:7007520",
        "tgn:7029392"
    ],
    "tgn:id":2404441,
    "tgn:name":"Hubbard Drain",
    "tgn:placetype":[
        "aat:300008699"
    ]
},
  "bbox": [],
  "geometry": {"coordinates":[-83.4833,42.1833],"type":"Point"}
}
=======
{"geometry":{"type":"Point","coordinates":[-83.483300,42.183300]},"type":"Feature","properties":{"hierarchy":["tgn:2404441","tgn:1000001","tgn:7012149","tgn:1003005","tgn:7007520","tgn:7029392"],"placetype":["aat:300008699"],"id":2404441,"name:xx":"Hubbard Drain"}}
>>>>>>> 03f74aca74312dbeaf24d7e61306dd6a786dc3d0
