{
  "id": 2566662,
  "type": "Feature",
  "properties": {
    "tgn:hierarchy":[
        "tgn:2566662",
        "tgn:7006450",
        "tgn:1000001",
        "tgn:7012149",
        "tgn:2000082",
        "tgn:7029392"
    ],
    "tgn:id":2566662,
    "tgn:name":"Panhandle Island",
    "tgn:placetype":[
        "aat:300008791"
    ]
},
  "bbox": [],
  "geometry": {"coordinates":[-132.85,55.1833],"type":"Point"}
}