{
  "id": 1105683,
  "type": "Feature",
  "properties": {
    "tgn:hierarchy":[
        "tgn:1105683",
        "tgn:1000882",
        "tgn:1000003",
        "tgn:1000090",
        "tgn:7029392"
    ],
    "tgn:id":1105683,
    "tgn:name":"Montemor",
    "tgn:placetype":[
        "aat:300008795"
    ]
},
  "bbox": [],
  "geometry": {"coordinates":[-9.204,38.823],"type":"Point"}
}