{
  "id": 7227998,
  "type": "Feature",
  "properties": {
    "tgn:hierarchy":[
        "tgn:7227998",
        "tgn:7002681",
        "tgn:7001395",
        "tgn:1000003",
        "tgn:1000074",
        "tgn:7029392"
    ],
    "tgn:id":7227998,
    "tgn:name":"Katafyg\u00ed, \u00c1kra",
    "tgn:placetype":[
        "aat:300008850"
    ]
},
  "bbox": [],
  "geometry": {"coordinates":[23.937455,37.672546],"type":"Point"}
}