{
  "id": 7422801,
  "type": "Feature",
  "properties": {
    "tgn:hierarchy":[
        "tgn:7422801",
        "tgn:1000001",
        "tgn:7005601",
        "tgn:7005560",
        "tgn:7029392"
    ],
    "tgn:id":7422801,
    "tgn:name":"Las Vigas, Cerro",
    "tgn:placetype":[
        "aat:300008795"
    ]
},
  "bbox": [],
  "geometry": {"coordinates":[-103.166667,21.583333],"type":"Point"}
}