<<<<<<< HEAD
{
  "id": 2404996,
  "type": "Feature",
  "properties": {
    "tgn:hierarchy":[
        "tgn:2404996",
        "tgn:1000001",
        "tgn:7012149",
        "tgn:1002263",
        "tgn:7007826",
        "tgn:7029392"
    ],
    "tgn:id":2404996,
    "tgn:name":"Hudson Chapel",
    "tgn:placetype":[
        "aat:300008347"
    ]
},
  "bbox": [],
  "geometry": {"coordinates":[-95.15,31.7167],"type":"Point"}
}
=======
{"geometry":{"type":"Point","coordinates":[-95.150000,31.716700]},"type":"Feature","properties":{"hierarchy":["tgn:2404996","tgn:1000001","tgn:7012149","tgn:1002263","tgn:7007826","tgn:7029392"],"placetype":["aat:300008347"],"id":2404996,"name:xx":"Hudson Chapel"}}
>>>>>>> 03f74aca74312dbeaf24d7e61306dd6a786dc3d0
