{
  "id": 2163824,
  "type": "Feature",
  "properties": {
    "tgn:hierarchy":[
        "tgn:2163824",
        "tgn:2000090",
        "tgn:1000001",
        "tgn:7006451",
        "tgn:7012149",
        "tgn:7029392"
    ],
    "tgn:id":2163824,
    "tgn:name":"Benzes Draw",
    "tgn:placetype":[
        "aat:300008761"
    ]
},
  "bbox": [],
  "geometry": {"coordinates":[-109.8333,34.5833],"type":"Point"}
}