{
  "id": 2113129,
  "type": "Feature",
  "properties": {
    "tgn:hierarchy":[
        "tgn:2113129",
        "tgn:1000001",
        "tgn:7012149",
        "tgn:2002187",
        "tgn:7007919",
        "tgn:7029392"
    ],
    "tgn:id":2113129,
    "tgn:name":"Mount Clinton",
    "tgn:placetype":[
        "aat:300008347"
    ]
},
  "bbox": [],
  "geometry": {"coordinates":[-78.95,38.4833],"type":"Point"}
}