{
  "id": 7491360,
  "type": "Feature",
  "properties": {
    "tgn:hierarchy":[
        "tgn:7491360",
        "tgn:1000004",
        "tgn:7467799",
        "tgn:1000141",
        "tgn:7029392"
    ],
    "tgn:id":7491360,
    "tgn:name":"Sanmin Li",
    "tgn:placetype":[
        "aat:300387173"
    ]
},
  "bbox": [],
  "geometry": {"coordinates":[120.571,23.8592],"type":"Point"}
}