{
  "id": 7236574,
  "type": "Feature",
  "properties": {
    "tgn:hierarchy":[
        "tgn:7236574",
        "tgn:7002751",
        "tgn:7001399",
        "tgn:1000003",
        "tgn:1000074",
        "tgn:7029392"
    ],
    "tgn:id":7236574,
    "tgn:name":"\u00c1no \u00cdlia",
    "tgn:placetype":[
        "aat:300000745"
    ]
},
  "bbox": [],
  "geometry": {"coordinates":[23.116667,38.85],"type":"Point"}
}