{
  "id": 7409385,
  "type": "Feature",
  "properties": {
    "tgn:hierarchy":[
        "tgn:7409385",
        "tgn:1000001",
        "tgn:7005592",
        "tgn:7005560",
        "tgn:7029392"
    ],
    "tgn:id":7409385,
    "tgn:name":"Tepetzitzintla",
    "tgn:placetype":[
        "aat:300008347"
    ]
},
  "bbox": [],
  "geometry": {"coordinates":[-98.083333,18.683333],"type":"Point"}
}