{
  "id": 2674343,
  "type": "Feature",
  "properties": {
    "tgn:hierarchy":[
        "tgn:2674343",
        "tgn:1000001",
        "tgn:7012149",
        "tgn:2000494",
        "tgn:7007250",
        "tgn:7029392"
    ],
    "tgn:id":2674343,
    "tgn:name":"Snowslide Summit",
    "tgn:placetype":[
        "aat:300008798"
    ]
},
  "bbox": [],
  "geometry": {"coordinates":[-115.9167,44.9667],"type":"Point"}
}