{
  "id": 2135034,
  "type": "Feature",
  "properties": {
    "tgn:hierarchy":[
        "tgn:2135034",
        "tgn:1000001",
        "tgn:7012149",
        "tgn:2001718",
        "tgn:7007708",
        "tgn:7029392"
    ],
    "tgn:id":2135034,
    "tgn:name":"Antelope Swale Spring",
    "tgn:placetype":[
        "aat:300008697"
    ]
},
  "bbox": [],
  "geometry": {"coordinates":[-117.8333,43.7167],"type":"Point"}
}