<<<<<<< HEAD
{
  "id": 7245896,
  "type": "Feature",
  "properties": {
    "tgn:hierarchy":[
        "tgn:7245896",
        "tgn:7007877",
        "tgn:1000003",
        "tgn:1000063",
        "tgn:4012014",
        "tgn:7029392"
    ],
    "tgn:id":7245896,
    "tgn:name":"Dergneau",
    "tgn:placetype":[
        "aat:300008347"
    ]
},
  "bbox": [],
  "geometry": {"coordinates":[3.580039,50.713993],"type":"Point"}
}
=======
{"geometry":{"type":"Point","coordinates":[3.580039,50.713993]},"type":"Feature","properties":{"hierarchy":["tgn:7245896","tgn:7007877","tgn:1000003","tgn:1000063","tgn:4012014","tgn:7029392"],"placetype":["aat:300008347"],"id":7245896,"name:xx":"Dergneau"}}
>>>>>>> 03f74aca74312dbeaf24d7e61306dd6a786dc3d0
