{
  "id": 7432350,
  "type": "Feature",
  "properties": {
    "tgn:hierarchy":[
        "tgn:7432350",
        "tgn:7005583",
        "tgn:1000001",
        "tgn:7005560",
        "tgn:7029392"
    ],
    "tgn:id":7432350,
    "tgn:name":"Urbalejo",
    "tgn:placetype":[
        "aat:300008347"
    ]
},
  "bbox": [],
  "geometry": {"coordinates":[-106.116667,25.116667],"type":"Point"}
}