{
  "id": 7314782,
  "type": "Feature",
  "properties": {
    "tgn:hierarchy":[
        "tgn:7314782",
        "tgn:1001657",
        "tgn:1000049",
        "tgn:1000002",
        "tgn:7029392"
    ],
    "tgn:id":7314782,
    "tgn:name":"Las Tres Cruces, Portezuelo",
    "tgn:placetype":[
        "aat:300259572"
    ]
},
  "bbox": [],
  "geometry": {"coordinates":[-70.666667,-30.216667],"type":"Point"}
}