{
  "id": 2277717,
  "type": "Feature",
  "properties": {
    "tgn:hierarchy":[
        "tgn:2277717",
        "tgn:1000001",
        "tgn:7012149",
        "tgn:2001680",
        "tgn:7007707",
        "tgn:7029392"
    ],
    "tgn:id":2277717,
    "tgn:name":"Dawes",
    "tgn:placetype":[
        "aat:300008347"
    ]
},
  "bbox": [],
  "geometry": {"coordinates":[-94.9833,36.8667],"type":"Point"}
}