{
  "id": 2194426,
  "type": "Feature",
  "properties": {
    "tgn:hierarchy":[
        "tgn:2194426",
        "tgn:1000001",
        "tgn:7012149",
        "tgn:2002060",
        "tgn:7007826",
        "tgn:7029392"
    ],
    "tgn:id":2194426,
    "tgn:name":"Bridge Hollow",
    "tgn:placetype":[
        "aat:300008761"
    ]
},
  "bbox": [],
  "geometry": {"coordinates":[-99.6333,29.8333],"type":"Point"}
}