{
  "id": 7093559,
  "type": "Feature",
  "properties": {
    "tgn:hierarchy":[
        "tgn:7093559",
        "tgn:1000003",
        "tgn:7003687",
        "tgn:7000084",
        "tgn:7029392"
    ],
    "tgn:id":7093559,
    "tgn:name":"Sch\u00f6pp-Graben",
    "tgn:placetype":[
        "aat:300008699"
    ]
},
  "bbox": [],
  "geometry": {"coordinates":[11.783333,52.85],"type":"Point"}
}