{
  "id": 1003450,
  "type": "Feature",
  "properties": {
    "tgn:hierarchy":[
        "tgn:1003450",
        "tgn:7007850",
        "tgn:1000003",
        "tgn:1000080",
        "tgn:7029392"
    ],
    "tgn:id":1003450,
    "tgn:name":"Cosenza",
    "tgn:placetype":[
        "aat:300387145",
        "aat:300000774"
    ]
},
  "bbox": [],
  "geometry": {"coordinates":[16.416667,39.466667],"type":"Point"}
}