<<<<<<< HEAD
{
  "id": 2767616,
  "type": "Feature",
  "properties": {
    "tgn:hierarchy":[
        "tgn:2767616",
        "tgn:1000001",
        "tgn:7012149",
        "tgn:2001129",
        "tgn:7007522",
        "tgn:7029392"
    ],
    "tgn:id":2767616,
    "tgn:name":"Whitebury",
    "tgn:placetype":[
        "aat:300008347"
    ]
},
  "bbox": [],
  "geometry": {"coordinates":[-88.3667,33.4167],"type":"Point"}
}
=======
{"geometry":{"type":"Point","coordinates":[-88.366700,33.416700]},"type":"Feature","properties":{"hierarchy":["tgn:2767616","tgn:1000001","tgn:7012149","tgn:2001129","tgn:7007522","tgn:7029392"],"placetype":["aat:300008347"],"id":2767616,"name:xx":"Whitebury"}}
>>>>>>> 03f74aca74312dbeaf24d7e61306dd6a786dc3d0
