{
  "id": 2767616,
  "type": "Feature",
  "properties": {
    "tgn:hierarchy":[
        "tgn:2767616",
        "tgn:1000001",
        "tgn:7012149",
        "tgn:2001129",
        "tgn:7007522",
        "tgn:7029392"
    ],
    "tgn:id":2767616,
    "tgn:name":"Whitebury",
    "tgn:placetype":[
        "aat:300008347"
    ]
},
  "bbox": [],
  "geometry": {"coordinates":[-88.3667,33.4167],"type":"Point"}
}