<<<<<<< HEAD
{
  "id": 7372437,
  "type": "Feature",
  "properties": {
    "tgn:hierarchy":[
        "tgn:7372437",
        "tgn:7005581",
        "tgn:1000001",
        "tgn:7005560",
        "tgn:7029392"
    ],
    "tgn:id":7372437,
    "tgn:name":"La Estaci\u00f3n",
    "tgn:placetype":[
        "aat:300008347"
    ]
},
  "bbox": [],
  "geometry": {"coordinates":[-107.816667,27.133333],"type":"Point"}
}
=======
{"geometry":{"type":"Point","coordinates":[-107.816667,27.133333]},"type":"Feature","properties":{"hierarchy":["tgn:7372437","tgn:7005581","tgn:1000001","tgn:7005560","tgn:7029392"],"placetype":["aat:300008347"],"id":7372437,"name:xx":"La Estaci\u00f3n"}}
>>>>>>> 03f74aca74312dbeaf24d7e61306dd6a786dc3d0
