{
  "id": 7372437,
  "type": "Feature",
  "properties": {
    "tgn:hierarchy":[
        "tgn:7372437",
        "tgn:7005581",
        "tgn:1000001",
        "tgn:7005560",
        "tgn:7029392"
    ],
    "tgn:id":7372437,
    "tgn:name":"La Estaci\u00f3n",
    "tgn:placetype":[
        "aat:300008347"
    ]
},
  "bbox": [],
  "geometry": {"coordinates":[-107.816667,27.133333],"type":"Point"}
}