{
  "id": 2477561,
  "type": "Feature",
  "properties": {
    "tgn:hierarchy":[
        "tgn:2477561",
        "tgn:1000001",
        "tgn:7012149",
        "tgn:7007157",
        "tgn:7014516",
        "tgn:7029392"
    ],
    "tgn:id":2477561,
    "tgn:name":"Lytton Lake",
    "tgn:placetype":[
        "aat:300008680"
    ]
},
  "bbox": [],
  "geometry": {"coordinates":[-122.8667,38.65],"type":"Point"}
}