{
  "id": 2428865,
  "type": "Feature",
  "properties": {
    "tgn:hierarchy":[
        "tgn:2428865",
        "tgn:1000001",
        "tgn:7012149",
        "tgn:7014185",
        "tgn:7007710",
        "tgn:7029392"
    ],
    "tgn:id":2428865,
    "tgn:name":"Jumonville Cave",
    "tgn:placetype":[
        "aat:300008746"
    ]
},
  "bbox": [],
  "geometry": {"coordinates":[-79.6167,39.8833],"type":"Point"}
}