{
  "id": 7058732,
  "type": "Feature",
  "properties": {
    "tgn:hierarchy":[
        "tgn:7058732",
        "tgn:7003129",
        "tgn:1000003",
        "tgn:7008516",
        "tgn:1000080",
        "tgn:7029392"
    ],
    "tgn:id":7058732,
    "tgn:name":"Borello, Torrente",
    "tgn:placetype":[
        "aat:300008699"
    ]
},
  "bbox": [],
  "geometry": {"coordinates":[12.184444,44.053333],"type":"Point"}
}