{
  "id": 7237202,
  "type": "Feature",
  "properties": {
    "tgn:hierarchy":[
        "tgn:7237202",
        "tgn:7002748",
        "tgn:7001399",
        "tgn:1000003",
        "tgn:1000074",
        "tgn:7029392"
    ],
    "tgn:id":7237202,
    "tgn:name":"Tr\u00edlofon",
    "tgn:placetype":[
        "aat:300008347"
    ]
},
  "bbox": [],
  "geometry": {"coordinates":[21.41,39.332222],"type":"Point"}
}