{
  "id": 2208378,
  "type": "Feature",
  "properties": {
    "tgn:hierarchy":[
        "tgn:2208378",
        "tgn:1000001",
        "tgn:7013686",
        "tgn:7012149",
        "tgn:7007517",
        "tgn:7029392"
    ],
    "tgn:id":2208378,
    "tgn:name":"Burnell Hill",
    "tgn:placetype":[
        "aat:300008798"
    ]
},
  "bbox": [],
  "geometry": {"coordinates":[-72.8667,42.4667],"type":"Point"}
}