{
  "id": 1063618,
  "type": "Feature",
  "properties": {
    "tgn:hierarchy":[
        "tgn:1063618",
        "tgn:7003770",
        "tgn:7003769",
        "tgn:1000003",
        "tgn:1000097",
        "tgn:7029392"
    ],
    "tgn:id":1063618,
    "tgn:name":"Slite",
    "tgn:placetype":[
        "aat:300008347"
    ]
},
  "bbox": [],
  "geometry": {"coordinates":[18.8333,57.7167],"type":"Point"}
}