{
  "id": 7568257,
  "type": "Feature",
  "properties": {
    "tgn:hierarchy":[
        "tgn:7568257",
        "tgn:1000004",
        "tgn:7000198",
        "tgn:7016788",
        "tgn:7029392"
    ],
    "tgn:id":7568257,
    "tgn:name:en":"Das\u0101liya",
    "tgn:placetype":[
        "aat:300008347"
    ]
},
  "bbox": [],
  "geometry": {"coordinates":[75.530992,25.06143],"type":"Point"}
}