{
  "id": 1058582,
  "type": "Feature",
  "properties": {
    "tgn:hierarchy":[
        "tgn:1058582",
        "tgn:1000004",
        "tgn:1003398",
        "tgn:7018214",
        "tgn:7002435",
        "tgn:7029392"
    ],
    "tgn:id":1058582,
    "tgn:name":"Ponomarevka",
    "tgn:placetype":[
        "aat:300008347"
    ]
},
  "bbox": [],
  "geometry": {"coordinates":[54.0167,53.3333],"type":"Point"}
}