{
  "id": 7318765,
  "type": "Feature",
  "properties": {
    "tgn:hierarchy":[
        "tgn:7318765",
        "tgn:1001699",
        "tgn:1000049",
        "tgn:1000002",
        "tgn:7029392"
    ],
    "tgn:id":7318765,
    "tgn:name":"Bonita, Laguna",
    "tgn:placetype":[
        "aat:300008680"
    ]
},
  "bbox": [],
  "geometry": {"coordinates":[-72.583333,-40.883333],"type":"Point"}
}