{
  "id": 1045684,
  "type": "Feature",
  "properties": {
    "tgn:hierarchy":[
        "tgn:1045684",
        "tgn:7003248",
        "tgn:1000003",
        "tgn:7010380",
        "tgn:1000080",
        "tgn:7029392"
    ],
    "tgn:id":1045684,
    "tgn:name":"Noicattaro",
    "tgn:placetype":[
        "aat:300008347"
    ]
},
  "bbox": [],
  "geometry": {"coordinates":[16.983333,41.033333],"type":"Point"}
}