{
  "id": 7412751,
  "type": "Feature",
  "properties": {
    "tgn:hierarchy":[
        "tgn:7412751",
        "tgn:7005587",
        "tgn:1000001",
        "tgn:7005560",
        "tgn:7029392"
    ],
    "tgn:id":7412751,
    "tgn:name:es":"Puerto de Piedra",
    "tgn:placetype":[
        "aat:300008347"
    ]
},
  "bbox": [],
  "geometry": {"coordinates":[-99.113889,21.047222],"type":"Point"}
}