{
  "id": 1106471,
  "type": "Feature",
  "properties": {
    "tgn:hierarchy":[
        "tgn:1106471",
        "tgn:7005685",
        "tgn:1000001",
        "tgn:7029392"
    ],
    "tgn:id":1106471,
    "tgn:name":"Sir Douglas, Mount",
    "tgn:placetype":[
        "aat:300008795"
    ]
},
  "bbox": [],
  "geometry": {"coordinates":[-115.4167,50.7333],"type":"Point"}
}