{
  "id": 7416229,
  "type": "Feature",
  "properties": {
    "tgn:hierarchy":[
        "tgn:7416229",
        "tgn:1000001",
        "tgn:7005591",
        "tgn:7005560",
        "tgn:7029392"
    ],
    "tgn:id":7416229,
    "tgn:name:es":"Espinazo del Diablo",
    "tgn:placetype":[
        "aat:300008347"
    ]
},
  "bbox": [],
  "geometry": {"coordinates":[-96.499444,15.995833],"type":"Point"}
}