{
  "id": 7491081,
  "type": "Feature",
  "properties": {
    "tgn:hierarchy":[
        "tgn:7491081",
        "tgn:1000004",
        "tgn:7492971",
        "tgn:1000141",
        "tgn:7029392"
    ],
    "tgn:id":7491081,
    "tgn:name":"Sangoushui",
    "tgn:placetype":[
        "aat:300008347"
    ]
},
  "bbox": [],
  "geometry": {"coordinates":[120.584019,22.582081],"type":"Point"}
}