{
  "id": 7406600,
  "type": "Feature",
  "properties": {
    "tgn:hierarchy":[
        "tgn:7406600",
        "tgn:7005585",
        "tgn:1000001",
        "tgn:7005560",
        "tgn:7029392"
    ],
    "tgn:id":7406600,
    "tgn:name":"Tlalixtaquilla, R\u00edo",
    "tgn:placetype":[
        "aat:300008699"
    ]
},
  "bbox": [],
  "geometry": {"coordinates":[-98.45,17.433333],"type":"Point"}
}