{
  "id": 2505526,
  "type": "Feature",
  "properties": {
    "tgn:hierarchy":[
        "tgn:2505526",
        "tgn:1000001",
        "tgn:7012149",
        "tgn:7014600",
        "tgn:7007568",
        "tgn:7029392"
    ],
    "tgn:id":2505526,
    "tgn:name":"Melvin Brook",
    "tgn:placetype":[
        "aat:300008699"
    ]
},
  "bbox": [],
  "geometry": {"coordinates":[-76.9167,43.1333],"type":"Point"}
}