{
  "id": 2612336,
  "type": "Feature",
  "properties": {
    "tgn:hierarchy":[
        "tgn:2612336",
        "tgn:1000001",
        "tgn:7012149",
        "tgn:2002282",
        "tgn:7013961",
        "tgn:7029392"
    ],
    "tgn:id":2612336,
    "tgn:name":"Red Sulphur Spring",
    "tgn:placetype":[
        "aat:300008697"
    ]
},
  "bbox": [],
  "geometry": {"coordinates":[-80.7667,37.3833],"type":"Point"}
}