{
  "id": 2436446,
  "type": "Feature",
  "properties": {
    "tgn:hierarchy":[
        "tgn:2436446",
        "tgn:1000001",
        "tgn:7016172",
        "tgn:7012149",
        "tgn:7029392"
    ],
    "tgn:id":2436446,
    "tgn:name":"Kickback Hollow",
    "tgn:placetype":[
        "aat:300008761"
    ]
},
  "bbox": [],
  "geometry": {"coordinates":[-91.9833,35.35],"type":"Point"}
}