{
  "id": 2605713,
  "type": "Feature",
  "properties": {
    "tgn:hierarchy":[
        "tgn:2605713",
        "tgn:1000001",
        "tgn:7012149",
        "tgn:1002492",
        "tgn:7007826",
        "tgn:7029392"
    ],
    "tgn:id":2605713,
    "tgn:name":"Rain Point",
    "tgn:placetype":[
        "aat:300008850"
    ]
},
  "bbox": [],
  "geometry": {"coordinates":[-96.0333,32.9167],"type":"Point"}
}