<<<<<<< HEAD
{
  "id": 7378319,
  "type": "Feature",
  "properties": {
    "tgn:hierarchy":[
        "tgn:7378319",
        "tgn:1000001",
        "tgn:1001960",
        "tgn:7005560",
        "tgn:7029392"
    ],
    "tgn:id":7378319,
    "tgn:name":"Las Piedras, Arroyo",
    "tgn:placetype":[
        "aat:300266554",
        "aat:300008699"
    ]
},
  "bbox": [],
  "geometry": {"coordinates":[-110.166667,30.4],"type":"Point"}
}
=======
{"geometry":{"type":"Point","coordinates":[-110.166667,30.400000]},"type":"Feature","properties":{"hierarchy":["tgn:7378319","tgn:1000001","tgn:1001960","tgn:7005560","tgn:7029392"],"placetype":["aat:300266554","aat:300008699"],"id":7378319,"name:xx":"Las Piedras, Arroyo"}}
>>>>>>> 03f74aca74312dbeaf24d7e61306dd6a786dc3d0
