{
  "id": 2728466,
  "type": "Feature",
  "properties": {
    "tgn:hierarchy":[
        "tgn:2728466",
        "tgn:1000001",
        "tgn:7012149",
        "tgn:2001284",
        "tgn:7007524",
        "tgn:7029392"
    ],
    "tgn:id":2728466,
    "tgn:name":"Treasury Number 1  Mine",
    "tgn:placetype":[
        "aat:300000390"
    ]
},
  "bbox": [],
  "geometry": {"coordinates":[-112.2167,46.4167],"type":"Point"}
}