{
  "id": 2640601,
  "type": "Feature",
  "properties": {
    "tgn:hierarchy":[
        "tgn:2640601",
        "tgn:1000001",
        "tgn:7012149",
        "tgn:7019676",
        "tgn:7007566",
        "tgn:7029392"
    ],
    "tgn:id":2640601,
    "tgn:name":"San Lucas Valley",
    "tgn:placetype":[
        "aat:300008761"
    ]
},
  "bbox": [],
  "geometry": {"coordinates":[-107.5333,35.3167],"type":"Point"}
}