<<<<<<< HEAD
{
  "id": 2259370,
  "type": "Feature",
  "properties": {
    "tgn:hierarchy":[
        "tgn:2259370",
        "tgn:1000001",
        "tgn:7006451",
        "tgn:2000091",
        "tgn:7012149",
        "tgn:7029392"
    ],
    "tgn:id":2259370,
    "tgn:name":"Cottonwood Spring",
    "tgn:placetype":[
        "aat:300006191"
    ]
},
  "bbox": [],
  "geometry": {"coordinates":[-109.3,31.7333],"type":"Point"}
}
=======
{"geometry":{"type":"Point","coordinates":[-109.300000,31.733300]},"type":"Feature","properties":{"hierarchy":["tgn:2259370","tgn:1000001","tgn:7006451","tgn:2000091","tgn:7012149","tgn:7029392"],"placetype":["aat:300006191"],"id":2259370,"name:xx":"Cottonwood Spring"}}
>>>>>>> 03f74aca74312dbeaf24d7e61306dd6a786dc3d0
