{
  "id": 2625488,
  "type": "Feature",
  "properties": {
    "tgn:hierarchy":[
        "tgn:2625488",
        "tgn:1000001",
        "tgn:2000924",
        "tgn:7012149",
        "tgn:7007515",
        "tgn:7029392"
    ],
    "tgn:id":2625488,
    "tgn:name":"Rockport Harbor",
    "tgn:placetype":[
        "aat:300008678"
    ]
},
  "bbox": [],
  "geometry": {"coordinates":[-69.0667,44.1667],"type":"Point"}
}