{
  "id": 2024429,
  "type": "Feature",
  "properties": {
    "tgn:hierarchy":[
        "tgn:2024429",
        "tgn:1000001",
        "tgn:7012149",
        "tgn:2000435",
        "tgn:7007248",
        "tgn:7029392"
    ],
    "tgn:id":2024429,
    "tgn:name":"Suches",
    "tgn:placetype":[
        "aat:300008347"
    ]
},
  "bbox": [],
  "geometry": {"coordinates":[-84.0167,34.6833],"type":"Point"}
}