<<<<<<< HEAD
{
  "id": 7377495,
  "type": "Feature",
  "properties": {
    "tgn:hierarchy":[
        "tgn:7377495",
        "tgn:1000001",
        "tgn:7005595",
        "tgn:7005560",
        "tgn:7029392"
    ],
    "tgn:id":7377495,
    "tgn:name":"La Vainillita",
    "tgn:placetype":[
        "aat:300008347"
    ]
},
  "bbox": [],
  "geometry": {"coordinates":[-107.483333,25.7],"type":"Point"}
}
=======
{"geometry":{"type":"Point","coordinates":[-107.483333,25.700000]},"type":"Feature","properties":{"hierarchy":["tgn:7377495","tgn:1000001","tgn:7005595","tgn:7005560","tgn:7029392"],"placetype":["aat:300008347"],"id":7377495,"name:xx":"La Vainillita"}}
>>>>>>> 03f74aca74312dbeaf24d7e61306dd6a786dc3d0
