{
  "id": 7355254,
  "type": "Feature",
  "properties": {
    "tgn:hierarchy":[
        "tgn:7355254",
        "tgn:7005586",
        "tgn:1000001",
        "tgn:7005560",
        "tgn:7029392"
    ],
    "tgn:id":7355254,
    "tgn:name":"Ci\u00e9nega del Pastor",
    "tgn:placetype":[
        "aat:300008347"
    ]
},
  "bbox": [],
  "geometry": {"coordinates":[-102.666667,20.533333],"type":"Point"}
}