{
  "id": 2368204,
  "type": "Feature",
  "properties": {
    "tgn:hierarchy":[
        "tgn:2368204",
        "tgn:1000001",
        "tgn:7012149",
        "tgn:2001449",
        "tgn:7007566",
        "tgn:7029392"
    ],
    "tgn:id":2368204,
    "tgn:name":"Guardia Spring",
    "tgn:placetype":[
        "aat:300008697"
    ]
},
  "bbox": [],
  "geometry": {"coordinates":[-106.6833,36.05],"type":"Point"}
}