{
  "id": 7218132,
  "type": "Feature",
  "properties": {
    "tgn:hierarchy":[
        "tgn:7218132",
        "tgn:7002739",
        "tgn:7017076",
        "tgn:1000003",
        "tgn:1000074",
        "tgn:7029392"
    ],
    "tgn:id":7218132,
    "tgn:name":"Trakh\u00edli, Nis\u00eds",
    "tgn:placetype":[
        "aat:300008791"
    ]
},
  "bbox": [],
  "geometry": {"coordinates":[23.183333,37.716667],"type":"Point"}
}