{
  "id": 7522268,
  "type": "Feature",
  "properties": {
    "tgn:hierarchy":[
        "tgn:7522268",
        "tgn:7001242",
        "tgn:7016833",
        "tgn:7001335",
        "tgn:7029392"
    ],
    "tgn:id":7522268,
    "tgn:name":"Al \u1e28amz\u0327ah",
    "tgn:placetype":[
        "aat:300387200"
    ]
},
  "bbox": [],
  "geometry": {"coordinates":[33.911389,30.924444],"type":"Point"}
}