{
  "id": 1122320,
  "type": "Feature",
  "properties": {
    "tgn:hierarchy":[
        "tgn:1122320",
        "tgn:1000004",
        "tgn:7001745",
        "tgn:1000111",
        "tgn:7029392"
    ],
    "tgn:id":1122320,
    "tgn:name":"Burqin He",
    "tgn:placetype":[
        "aat:300008707"
    ]
},
  "bbox": [],
  "geometry": {"coordinates":[86.9167,47.6667],"type":"Point"}
}