{
  "id": 2110777,
  "type": "Feature",
  "properties": {
    "tgn:hierarchy":[
        "tgn:2110777",
        "tgn:1000001",
        "tgn:7012149",
        "tgn:2002164",
        "tgn:7007919",
        "tgn:7029392"
    ],
    "tgn:id":2110777,
    "tgn:name":"Bridle Creek",
    "tgn:placetype":[
        "aat:300008347",
        "aat:300387210"
    ]
},
  "bbox": [],
  "geometry": {"coordinates":[-81.2333,36.6167],"type":"Point"}
}