{
  "id": 7197993,
  "type": "Feature",
  "properties": {
    "tgn:hierarchy":[
        "tgn:7197993",
        "tgn:1000003",
        "tgn:7003682",
        "tgn:7000084",
        "tgn:7029392"
    ],
    "tgn:id":7197993,
    "tgn:name":"Echtersbach",
    "tgn:placetype":[
        "aat:300008699"
    ]
},
  "bbox": [],
  "geometry": {"coordinates":[6.433333,49.983333],"type":"Point"}
}