{
  "id": 2666382,
  "type": "Feature",
  "properties": {
    "tgn:hierarchy":[
        "tgn:2666382",
        "tgn:2000453",
        "tgn:1000001",
        "tgn:7012149",
        "tgn:7007250",
        "tgn:7029392"
    ],
    "tgn:id":2666382,
    "tgn:name":"Sixmile Creek",
    "tgn:placetype":[
        "aat:300008706"
    ]
},
  "bbox": [],
  "geometry": {"coordinates":[-116.1833,45.0667],"type":"Point"}
}