{
  "id": 2439348,
  "type": "Feature",
  "properties": {
    "tgn:hierarchy":[
        "tgn:2439348",
        "tgn:1000001",
        "tgn:7012149",
        "tgn:2002174",
        "tgn:7007919",
        "tgn:7029392"
    ],
    "tgn:id":2439348,
    "tgn:name":"Kirk Hollow",
    "tgn:placetype":[
        "aat:300008761"
    ]
},
  "bbox": [],
  "geometry": {"coordinates":[-80.2667,37.15],"type":"Point"}
}