{
  "id": 7230992,
  "type": "Feature",
  "properties": {
    "tgn:hierarchy":[
        "tgn:7230992",
        "tgn:7002721",
        "tgn:7002715",
        "tgn:1000003",
        "tgn:1000074",
        "tgn:7029392"
    ],
    "tgn:id":7230992,
    "tgn:name":"Kalon\u00e9rion",
    "tgn:placetype":[
        "aat:300008347"
    ]
},
  "bbox": [],
  "geometry": {"coordinates":[21.483333,40.283333],"type":"Point"}
}