{
  "id": 2751267,
  "type": "Feature",
  "properties": {
    "tgn:hierarchy":[
        "tgn:2751267",
        "tgn:1000001",
        "tgn:7012149",
        "tgn:2002113",
        "tgn:7007827",
        "tgn:7029392"
    ],
    "tgn:id":2751267,
    "tgn:name":"Warm Creek Bay",
    "tgn:placetype":[
        "aat:300132316"
    ]
},
  "bbox": [],
  "geometry": {"coordinates":[-111.45,37.0667],"type":"Point"}
}