{
  "id": 7553299,
  "type": "Feature",
  "properties": {
    "tgn:hierarchy":[
        "tgn:7553299",
        "tgn:1000004",
        "tgn:1001871",
        "tgn:7000198",
        "tgn:7029392"
    ],
    "tgn:id":7553299,
    "tgn:name:en":"M\u016bnak",
    "tgn:placetype":[
        "aat:300008347"
    ]
},
  "bbox": [],
  "geometry": {"coordinates":[76.848607,29.519686],"type":"Point"}
}