{
  "id": 2763939,
  "type": "Feature",
  "properties": {
    "tgn:hierarchy":[
        "tgn:2763939",
        "tgn:1000001",
        "tgn:7012149",
        "tgn:2000439",
        "tgn:7007248",
        "tgn:7029392"
    ],
    "tgn:id":2763939,
    "tgn:name":"Wheel of Fortune Island",
    "tgn:placetype":[
        "aat:300008791"
    ]
},
  "bbox": [],
  "geometry": {"coordinates":[-82.3333,31.0667],"type":"Point"}
}