{
  "id": 7589826,
  "type": "Feature",
  "properties": {
    "tgn:hierarchy":[
        "tgn:7589826",
        "tgn:1000004",
        "tgn:7000198",
        "tgn:7000799",
        "tgn:7029392"
    ],
    "tgn:id":7589826,
    "tgn:name:en":"Dudhi",
    "tgn:placetype":[
        "aat:300008347"
    ]
},
  "bbox": [],
  "geometry": {"coordinates":[73.971769,34.669997],"type":"Point"}
}