{
  "id": 2051020,
  "type": "Feature",
  "properties": {
    "tgn:hierarchy":[
        "tgn:2051020",
        "tgn:1000001",
        "tgn:7012149",
        "tgn:1003038",
        "tgn:7014647",
        "tgn:7007517",
        "tgn:7029392"
    ],
    "tgn:id":2051020,
    "tgn:name":"Columbus Park",
    "tgn:placetype":[
        "aat:300000745"
    ]
},
  "bbox": [],
  "geometry": {"coordinates":[-71.8333,42.25],"type":"Point"}
}