{
  "id": 7511934,
  "type": "Feature",
  "properties": {
    "tgn:hierarchy":[
        "tgn:7511934",
        "tgn:1008380",
        "tgn:7520093",
        "tgn:1000226",
        "tgn:1000006",
        "tgn:7029392"
    ],
    "tgn:id":7511934,
    "tgn:name:en":"Kairanga",
    "tgn:placetype":[
        "aat:300008347"
    ]
},
  "bbox": [],
  "geometry": {"coordinates":[175.533333,-40.35],"type":"Point"}
}