{
  "id": 2343125,
  "type": "Feature",
  "properties": {
    "tgn:hierarchy":[
        "tgn:2343125",
        "tgn:1000001",
        "tgn:7012149",
        "tgn:2001851",
        "tgn:7007825",
        "tgn:7029392"
    ],
    "tgn:id":2343125,
    "tgn:name":"Gabes Mountain",
    "tgn:placetype":[
        "aat:300008798"
    ]
},
  "bbox": [],
  "geometry": {"coordinates":[-83.2333,35.75],"type":"Point"}
}