{
  "id": 7532910,
  "type": "Feature",
  "properties": {
    "tgn:hierarchy":[
        "tgn:7532910",
        "tgn:7001242",
        "tgn:7016833",
        "tgn:1001091",
        "tgn:7029392"
    ],
    "tgn:id":7532910,
    "tgn:name":"Mu\u1e29ammad Naj\u012bb",
    "tgn:placetype":[
        "aat:300007780"
    ]
},
  "bbox": [],
  "geometry": {"coordinates":[31.243868,30.045053],"type":"Point"}
}