<<<<<<< HEAD
{
  "id": 7118863,
  "type": "Feature",
  "properties": {
    "tgn:hierarchy":[
        "tgn:7118863",
        "tgn:1000003",
        "tgn:7003689",
        "tgn:7000084",
        "tgn:7029392"
    ],
    "tgn:id":7118863,
    "tgn:name":"Der Polarsch",
    "tgn:placetype":[
        "aat:300008777"
    ]
},
  "bbox": [],
  "geometry": {"coordinates":[10.983333,51.266667],"type":"Point"}
}
=======
{"geometry":{"type":"Point","coordinates":[10.983333,51.266667]},"type":"Feature","properties":{"hierarchy":["tgn:7118863","tgn:1000003","tgn:7003689","tgn:7000084","tgn:7029392"],"placetype":["aat:300008777"],"id":7118863,"name:xx":"Der Polarsch"}}
>>>>>>> 03f74aca74312dbeaf24d7e61306dd6a786dc3d0
