{
  "id": 7207644,
  "type": "Feature",
  "properties": {
    "tgn:hierarchy":[
        "tgn:7207644",
        "tgn:7003669",
        "tgn:1000003",
        "tgn:7000084",
        "tgn:7029392"
    ],
    "tgn:id":7207644,
    "tgn:name":"Buchenrod",
    "tgn:placetype":[
        "aat:300008347"
    ]
},
  "bbox": [],
  "geometry": {"coordinates":[10.933333,50.183333],"type":"Point"}
}