{
  "id": 7286520,
  "type": "Feature",
  "properties": {
    "tgn:hierarchy":[
        "tgn:7286520",
        "tgn:1001702",
        "tgn:1000049",
        "tgn:1000002",
        "tgn:7029392"
    ],
    "tgn:id":7286520,
    "tgn:name":"Harris, Bah\u00eda",
    "tgn:placetype":[
        "aat:300132316"
    ]
},
  "bbox": [],
  "geometry": {"coordinates":[-70.433333,-53.833333],"type":"Point"}
}