{
  "id": 2366934,
  "type": "Feature",
  "properties": {
    "tgn:hierarchy":[
        "tgn:2366934",
        "tgn:1000001",
        "tgn:7012149",
        "tgn:2002384",
        "tgn:7007923",
        "tgn:7029392"
    ],
    "tgn:id":2366934,
    "tgn:name":"Grizzly Basin",
    "tgn:placetype":[
        "aat:300386845"
    ]
},
  "bbox": [],
  "geometry": {"coordinates":[-110.2667,43.3833],"type":"Point"}
}