{
  "id": 2303357,
  "type": "Feature",
  "properties": {
    "tgn:hierarchy":[
        "tgn:2303357",
        "tgn:1000001",
        "tgn:7012149",
        "tgn:2000730",
        "tgn:7007254",
        "tgn:7029392"
    ],
    "tgn:id":2303357,
    "tgn:name":"Eagle Creek",
    "tgn:placetype":[
        "aat:300008706"
    ]
},
  "bbox": [],
  "geometry": {"coordinates":[-99.0333,39.25],"type":"Point"}
}