{
  "id": 2251912,
  "type": "Feature",
  "properties": {
    "tgn:hierarchy":[
        "tgn:2251912",
        "tgn:1000001",
        "tgn:7012149",
        "tgn:2002002",
        "tgn:7007826",
        "tgn:7029392"
    ],
    "tgn:id":2251912,
    "tgn:name":"Conception, Lake",
    "tgn:placetype":[
        "aat:300008680"
    ]
},
  "bbox": [],
  "geometry": {"coordinates":[-98.2667,26.1667],"type":"Point"}
}