<<<<<<< HEAD
{
  "id": 2251912,
  "type": "Feature",
  "properties": {
    "tgn:hierarchy":[
        "tgn:2251912",
        "tgn:1000001",
        "tgn:7012149",
        "tgn:2002002",
        "tgn:7007826",
        "tgn:7029392"
    ],
    "tgn:id":2251912,
    "tgn:name":"Conception, Lake",
    "tgn:placetype":[
        "aat:300008680"
    ]
},
  "bbox": [],
  "geometry": {"coordinates":[-98.2667,26.1667],"type":"Point"}
}
=======
{"geometry":{"type":"Point","coordinates":[-98.266700,26.166700]},"type":"Feature","properties":{"hierarchy":["tgn:2251912","tgn:1000001","tgn:7012149","tgn:2002002","tgn:7007826","tgn:7029392"],"placetype":["aat:300008680"],"id":2251912,"name:xx":"Conception, Lake"}}
>>>>>>> 03f74aca74312dbeaf24d7e61306dd6a786dc3d0
