{
  "id": 1058445,
  "type": "Feature",
  "properties": {
    "tgn:hierarchy":[
        "tgn:1058445",
        "tgn:1000003",
        "tgn:7011662",
        "tgn:7006660",
        "tgn:7029392"
    ],
    "tgn:id":1058445,
    "tgn:name":"Pletnyy Tashlyk",
    "tgn:placetype":[
        "aat:300008347"
    ]
},
  "bbox": [],
  "geometry": {"coordinates":[31.6667,48.4833],"type":"Point"}
}