{
  "id": 2463029,
  "type": "Feature",
  "properties": {
    "tgn:hierarchy":[
        "tgn:2463029",
        "tgn:1000001",
        "tgn:7012149",
        "tgn:7007157",
        "tgn:1002857",
        "tgn:7029392"
    ],
    "tgn:id":2463029,
    "tgn:name":"Live Oak Spring",
    "tgn:placetype":[
        "aat:300008697"
    ]
},
  "bbox": [],
  "geometry": {"coordinates":[-115.4167,35.1833],"type":"Point"}
}