{
  "id": 7321234,
  "type": "Feature",
  "properties": {
    "tgn:hierarchy":[
        "tgn:7321234",
        "tgn:1001623",
        "tgn:1000049",
        "tgn:1000002",
        "tgn:7029392"
    ],
    "tgn:id":7321234,
    "tgn:name":"Camello, Cerro",
    "tgn:placetype":[
        "aat:300008795"
    ]
},
  "bbox": [],
  "geometry": {"coordinates":[-74.433333,-46.666667],"type":"Point"}
}