<<<<<<< HEAD
{
  "id": 7059826,
  "type": "Feature",
  "properties": {
    "tgn:hierarchy":[
        "tgn:7059826",
        "tgn:1000003",
        "tgn:7003688",
        "tgn:7000084",
        "tgn:7029392"
    ],
    "tgn:id":7059826,
    "tgn:name":"Altenkoog",
    "tgn:placetype":[
        "aat:300387200"
    ]
},
  "bbox": [],
  "geometry": {"coordinates":[9.2,53.9],"type":"Point"}
}
=======
{"geometry":{"type":"Point","coordinates":[9.200000,53.900000]},"type":"Feature","properties":{"hierarchy":["tgn:7059826","tgn:1000003","tgn:7003688","tgn:7000084","tgn:7029392"],"placetype":["aat:300387200"],"id":7059826,"name:xx":"Altenkoog"}}
>>>>>>> 03f74aca74312dbeaf24d7e61306dd6a786dc3d0
