{
  "id": 2375163,
  "type": "Feature",
  "properties": {
    "tgn:hierarchy":[
        "tgn:2375163",
        "tgn:1000001",
        "tgn:7012149",
        "tgn:2000233",
        "tgn:7007158",
        "tgn:7029392"
    ],
    "tgn:id":2375163,
    "tgn:name":"Hanna Spring",
    "tgn:placetype":[
        "aat:300008697"
    ]
},
  "bbox": [],
  "geometry": {"coordinates":[-108.75,37.2667],"type":"Point"}
}