{
  "id": 2520979,
  "type": "Feature",
  "properties": {
    "tgn:hierarchy":[
        "tgn:2520979",
        "tgn:1000001",
        "tgn:7006451",
        "tgn:2000093",
        "tgn:7012149",
        "tgn:7029392"
    ],
    "tgn:id":2520979,
    "tgn:name":"Montague Spring",
    "tgn:placetype":[
        "aat:300008697"
    ]
},
  "bbox": [],
  "geometry": {"coordinates":[-110.8167,33.7167],"type":"Point"}
}