{
  "id": 7216455,
  "type": "Feature",
  "properties": {
    "tgn:hierarchy":[
        "tgn:7216455",
        "tgn:1000003",
        "tgn:7000094",
        "tgn:7000084",
        "tgn:7029392"
    ],
    "tgn:id":7216455,
    "tgn:name":"Alt Gaarz",
    "tgn:placetype":[
        "aat:300008347"
    ]
},
  "bbox": [],
  "geometry": {"coordinates":[12.516667,53.583333],"type":"Point"}
}