{
  "id": 7507338,
  "type": "Feature",
  "properties": {
    "tgn:hierarchy":[
        "tgn:7507338",
        "tgn:1008380",
        "tgn:7000507",
        "tgn:1000226",
        "tgn:1000006",
        "tgn:7029392"
    ],
    "tgn:id":7507338,
    "tgn:name:en":"Pukenui",
    "tgn:placetype":[
        "aat:300008777"
    ]
},
  "bbox": [],
  "geometry": {"coordinates":[174.466667,-35.616667],"type":"Point"}
}