{
  "id": 2782758,
  "type": "Feature",
  "properties": {
    "tgn:hierarchy":[
        "tgn:2782758",
        "tgn:1000001",
        "tgn:2000467",
        "tgn:7012149",
        "tgn:7007250",
        "tgn:7029392"
    ],
    "tgn:id":2782758,
    "tgn:name":"Worm Corral Spring",
    "tgn:placetype":[
        "aat:300008697"
    ]
},
  "bbox": [],
  "geometry": {"coordinates":[-114.1167,42.1833],"type":"Point"}
}