{
  "id": 7442812,
  "type": "Feature",
  "properties": {
    "tgn:hierarchy":[
        "tgn:7442812",
        "tgn:7002445",
        "tgn:1000003",
        "tgn:7012077",
        "tgn:7008591",
        "tgn:7029392"
    ],
    "tgn:id":7442812,
    "tgn:name:en":"Black Stone",
    "tgn:placetype":[
        "aat:300011692"
    ]
},
  "bbox": [],
  "geometry": {"coordinates":[-3.633333,50.216667],"type":"Point"}
}