{
  "id": 7142335,
  "type": "Feature",
  "properties": {
    "tgn:hierarchy":[
        "tgn:7142335",
        "tgn:1000003",
        "tgn:7003677",
        "tgn:7000084",
        "tgn:7029392"
    ],
    "tgn:id":7142335,
    "tgn:name":"Loh-Kopf",
    "tgn:placetype":[
        "aat:300008777"
    ]
},
  "bbox": [],
  "geometry": {"coordinates":[8.35,51.25],"type":"Point"}
}