{
  "id": 2509957,
  "type": "Feature",
  "properties": {
    "tgn:hierarchy":[
        "tgn:2509957",
        "tgn:1000001",
        "tgn:7012149",
        "tgn:2002190",
        "tgn:7007919",
        "tgn:7029392"
    ],
    "tgn:id":2509957,
    "tgn:name":"Middle Mountain",
    "tgn:placetype":[
        "aat:300008798"
    ]
},
  "bbox": [],
  "geometry": {"coordinates":[-78.7167,38.8833],"type":"Point"}
}