{
  "id": 7518474,
  "type": "Feature",
  "properties": {
    "tgn:hierarchy":[
        "tgn:7518474",
        "tgn:1009227",
        "tgn:1000226",
        "tgn:7018437",
        "tgn:1000006",
        "tgn:7029392"
    ],
    "tgn:id":7518474,
    "tgn:name:en":"Macs Valley",
    "tgn:placetype":[
        "aat:300008761"
    ]
},
  "bbox": [],
  "geometry": {"coordinates":[170.083333,-46.066667],"type":"Point"}
}