{
  "id": 2126745,
  "type": "Feature",
  "properties": {
    "tgn:hierarchy":[
        "tgn:2126745",
        "tgn:7030516",
        "tgn:7006450",
        "tgn:1000001",
        "tgn:7012149",
        "tgn:7029392"
    ],
    "tgn:id":2126745,
    "tgn:name":"Agligadak Reefs",
    "tgn:placetype":[
        "aat:300132348"
    ]
},
  "bbox": [],
  "geometry": {"coordinates":[-172.9167,52.0833],"type":"Point"}
}