{
  "id": 7202700,
  "type": "Feature",
  "properties": {
    "tgn:hierarchy":[
        "tgn:7202700",
        "tgn:1000003",
        "tgn:7003682",
        "tgn:7000084",
        "tgn:7029392"
    ],
    "tgn:id":7202700,
    "tgn:name":"Broden Bach",
    "tgn:placetype":[
        "aat:300008699"
    ]
},
  "bbox": [],
  "geometry": {"coordinates":[7.45,50.233333],"type":"Point"}
}