{
  "id": 2002589,
  "type": "Feature",
  "properties": {
    "tgn:hierarchy":[
        "tgn:2002589",
        "tgn:7002659",
        "tgn:1000001",
        "tgn:7012149",
        "tgn:7021514",
        "tgn:7029392"
    ],
    "tgn:id":2002589,
    "tgn:name":"Battelle",
    "tgn:placetype":[
        "aat:300008347",
        "aat:300387210"
    ]
},
  "bbox": [],
  "geometry": {"coordinates":[-85.55,34.6333],"type":"Point"}
}