{
  "id": 2127143,
  "type": "Feature",
  "properties": {
    "tgn:hierarchy":[
        "tgn:2127143",
        "tgn:1000001",
        "tgn:7012149",
        "tgn:2001898",
        "tgn:7007825",
        "tgn:7029392"
    ],
    "tgn:id":2127143,
    "tgn:name":"Aiken Hollow",
    "tgn:placetype":[
        "aat:300008761"
    ]
},
  "bbox": [],
  "geometry": {"coordinates":[-84.2667,35.3667],"type":"Point"}
}