{
  "id": 2488404,
  "type": "Feature",
  "properties": {
    "tgn:hierarchy":[
        "tgn:2488404",
        "tgn:1000001",
        "tgn:2001267",
        "tgn:7012149",
        "tgn:7007524",
        "tgn:7029392"
    ],
    "tgn:id":2488404,
    "tgn:name":"Mahikahn Creek",
    "tgn:placetype":[
        "aat:300008706"
    ]
},
  "bbox": [],
  "geometry": {"coordinates":[-109.7333,48.1333],"type":"Point"}
}