<<<<<<< HEAD
{
  "id": 7116570,
  "type": "Feature",
  "properties": {
    "tgn:hierarchy":[
        "tgn:7116570",
        "tgn:1000003",
        "tgn:7003677",
        "tgn:7000084",
        "tgn:7029392"
    ],
    "tgn:id":7116570,
    "tgn:name":"Otters-Graben",
    "tgn:placetype":[
        "aat:300008699"
    ]
},
  "bbox": [],
  "geometry": {"coordinates":[6.2,51.65],"type":"Point"}
}
=======
{"geometry":{"type":"Point","coordinates":[6.200000,51.650000]},"type":"Feature","properties":{"hierarchy":["tgn:7116570","tgn:1000003","tgn:7003677","tgn:7000084","tgn:7029392"],"placetype":["aat:300008699"],"id":7116570,"name:xx":"Otters-Graben"}}
>>>>>>> 03f74aca74312dbeaf24d7e61306dd6a786dc3d0
