{
  "id": 2100938,
  "type": "Feature",
  "properties": {
    "tgn:hierarchy":[
        "tgn:2100938",
        "tgn:1000001",
        "tgn:7012149",
        "tgn:2001906",
        "tgn:7007825",
        "tgn:7029392"
    ],
    "tgn:id":2100938,
    "tgn:name":"Patty",
    "tgn:placetype":[
        "aat:300008347",
        "aat:300387210"
    ]
},
  "bbox": [],
  "geometry": {"coordinates":[-84.6333,35.2333],"type":"Point"}
}