{
  "id": 2779496,
  "type": "Feature",
  "properties": {
    "tgn:hierarchy":[
        "tgn:2779496",
        "tgn:1000001",
        "tgn:1002198",
        "tgn:7012149",
        "tgn:7007826",
        "tgn:7029392"
    ],
    "tgn:id":2779496,
    "tgn:name":"Wolf Lake",
    "tgn:placetype":[
        "aat:300008680"
    ]
},
  "bbox": [],
  "geometry": {"coordinates":[-95.2333,29.0333],"type":"Point"}
}