{
  "id": 7460418,
  "type": "Feature",
  "properties": {
    "tgn:hierarchy":[
        "tgn:7460418",
        "tgn:7002445",
        "tgn:1000003",
        "tgn:7012077",
        "tgn:7008591",
        "tgn:7029392"
    ],
    "tgn:id":7460418,
    "tgn:name:en":"Hope",
    "tgn:placetype":[
        "aat:300008347"
    ]
},
  "bbox": [],
  "geometry": {"coordinates":[-3.85,50.25],"type":"Point"}
}