<<<<<<< HEAD
{
  "id": 7361239,
  "type": "Feature",
  "properties": {
    "tgn:hierarchy":[
        "tgn:7361239",
        "tgn:7005581",
        "tgn:1000001",
        "tgn:7005560",
        "tgn:7029392"
    ],
    "tgn:id":7361239,
    "tgn:name":"El Caido, Cerro",
    "tgn:placetype":[
        "aat:300008777"
    ]
},
  "bbox": [],
  "geometry": {"coordinates":[-103.666667,29.083333],"type":"Point"}
}
=======
{"geometry":{"type":"Point","coordinates":[-103.666667,29.083333]},"type":"Feature","properties":{"hierarchy":["tgn:7361239","tgn:7005581","tgn:1000001","tgn:7005560","tgn:7029392"],"placetype":["aat:300008777"],"id":7361239,"name:xx":"El Caido, Cerro"}}
>>>>>>> 03f74aca74312dbeaf24d7e61306dd6a786dc3d0
