{
  "id": 7588157,
  "type": "Feature",
  "properties": {
    "tgn:hierarchy":[
        "tgn:7588157",
        "tgn:1000004",
        "tgn:7000198",
        "tgn:7000799",
        "tgn:7029392"
    ],
    "tgn:id":7588157,
    "tgn:name:en":"Kadalbal",
    "tgn:placetype":[
        "aat:300008347"
    ]
},
  "bbox": [],
  "geometry": {"coordinates":[74.913889,34.011111],"type":"Point"}
}