{
  "id": 1049908,
  "type": "Feature",
  "properties": {
    "tgn:hierarchy":[
        "tgn:1049908",
        "tgn:1000003",
        "tgn:1000929",
        "tgn:1000090",
        "tgn:7029392"
    ],
    "tgn:id":1049908,
    "tgn:name":"S\u00e3o Juli\u00e3o da Barra",
    "tgn:placetype":[
        "aat:300008347"
    ]
},
  "bbox": [],
  "geometry": {"coordinates":[-9.3333,38.683],"type":"Point"}
}