{
  "id": 7529278,
  "type": "Feature",
  "properties": {
    "tgn:hierarchy":[
        "tgn:7529278",
        "tgn:7001242",
        "tgn:7016833",
        "tgn:1001079",
        "tgn:7029392"
    ],
    "tgn:id":7529278,
    "tgn:name:en":"Umm \u015eughayw, Jaz\u012brat",
    "tgn:placetype":[
        "aat:300008791"
    ]
},
  "bbox": [],
  "geometry": {"coordinates":[29.715833,31.034167],"type":"Point"}
}