{
  "id": 2450333,
  "type": "Feature",
  "properties": {
    "tgn:hierarchy":[
        "tgn:2450333",
        "tgn:1000001",
        "tgn:7012149",
        "tgn:2000226",
        "tgn:7007158",
        "tgn:7029392"
    ],
    "tgn:id":2450333,
    "tgn:name":"Link Creek",
    "tgn:placetype":[
        "aat:300008706"
    ]
},
  "bbox": [],
  "geometry": {"coordinates":[-105.95,40.7333],"type":"Point"}
}