<<<<<<< HEAD
{
  "id": 2156004,
  "type": "Feature",
  "properties": {
    "tgn:hierarchy":[
        "tgn:2156004",
        "tgn:1000001",
        "tgn:7012149",
        "tgn:2001851",
        "tgn:7007825",
        "tgn:7029392"
    ],
    "tgn:id":2156004,
    "tgn:name":"Bear Wallow Hollow",
    "tgn:placetype":[
        "aat:300008761"
    ]
},
  "bbox": [],
  "geometry": {"coordinates":[-83.2667,35.9],"type":"Point"}
}
=======
{"geometry":{"type":"Point","coordinates":[-83.266700,35.900000]},"type":"Feature","properties":{"hierarchy":["tgn:2156004","tgn:1000001","tgn:7012149","tgn:2001851","tgn:7007825","tgn:7029392"],"placetype":["aat:300008761"],"id":2156004,"name:xx":"Bear Wallow Hollow"}}
>>>>>>> 03f74aca74312dbeaf24d7e61306dd6a786dc3d0
