{
  "id": 7354005,
  "type": "Feature",
  "properties": {
    "tgn:hierarchy":[
        "tgn:7354005",
        "tgn:7005583",
        "tgn:1000001",
        "tgn:7005560",
        "tgn:7029392"
    ],
    "tgn:id":7354005,
    "tgn:name":"Chancote, Sierra del",
    "tgn:placetype":[
        "aat:300008795"
    ]
},
  "bbox": [],
  "geometry": {"coordinates":[-106.833333,25.233333],"type":"Point"}
}