<<<<<<< HEAD
{
  "id": 2250203,
  "type": "Feature",
  "properties": {
    "tgn:hierarchy":[
        "tgn:2250203",
        "tgn:1000001",
        "tgn:7012149",
        "tgn:2001855",
        "tgn:7007825",
        "tgn:7029392"
    ],
    "tgn:id":2250203,
    "tgn:name":"Collins Lake Number Three",
    "tgn:placetype":[
        "aat:300006191"
    ]
},
  "bbox": [],
  "geometry": {"coordinates":[-86.9667,36.15],"type":"Point"}
}
=======
{"geometry":{"type":"Point","coordinates":[-86.966700,36.150000]},"type":"Feature","properties":{"hierarchy":["tgn:2250203","tgn:1000001","tgn:7012149","tgn:2001855","tgn:7007825","tgn:7029392"],"placetype":["aat:300006191"],"id":2250203,"name:xx":"Collins Lake Number Three"}}
>>>>>>> 03f74aca74312dbeaf24d7e61306dd6a786dc3d0
