{
  "id": 2754555,
  "type": "Feature",
  "properties": {
    "tgn:hierarchy":[
        "tgn:2754555",
        "tgn:1000001",
        "tgn:7012149",
        "tgn:2000287",
        "tgn:7007240",
        "tgn:7029392"
    ],
    "tgn:id":2754555,
    "tgn:name":"Waylonzo",
    "tgn:placetype":[
        "aat:300008347"
    ]
},
  "bbox": [],
  "geometry": {"coordinates":[-83.8167,30.1167],"type":"Point"}
}