{
  "id": 2416336,
  "type": "Feature",
  "properties": {
    "tgn:hierarchy":[
        "tgn:2416336",
        "tgn:1000001",
        "tgn:7012149",
        "tgn:2002082",
        "tgn:7007826",
        "tgn:7029392"
    ],
    "tgn:id":2416336,
    "tgn:name":"Jabalina Canyon",
    "tgn:placetype":[
        "aat:300008761"
    ]
},
  "bbox": [],
  "geometry": {"coordinates":[-102.1167,29.8667],"type":"Point"}
}