{
  "id": 7163018,
  "type": "Feature",
  "properties": {
    "tgn:hierarchy":[
        "tgn:7163018",
        "tgn:1000003",
        "tgn:7003677",
        "tgn:7000084",
        "tgn:7029392"
    ],
    "tgn:id":7163018,
    "tgn:name":"Horn-Bad Meinberg",
    "tgn:placetype":[
        "aat:300008347"
    ]
},
  "bbox": [],
  "geometry": {"coordinates":[8.966667,51.983333],"type":"Point"}
}