{
  "id": 2011930,
  "type": "Feature",
  "properties": {
    "tgn:hierarchy":[
        "tgn:2011930",
        "tgn:1000001",
        "tgn:7012149",
        "tgn:1002545",
        "tgn:7007157",
        "tgn:7029392"
    ],
    "tgn:id":2011930,
    "tgn:name":"Jastro",
    "tgn:placetype":[
        "aat:300387016"
    ]
},
  "bbox": [],
  "geometry": {"coordinates":[-119.0667,35.3667],"type":"Point"}
}