<<<<<<< HEAD
{
  "id": 2333623,
  "type": "Feature",
  "properties": {
    "tgn:hierarchy":[
        "tgn:2333623",
        "tgn:1000001",
        "tgn:7012149",
        "tgn:7007515",
        "tgn:7029392"
    ],
    "tgn:id":2333623,
    "tgn:name":"Fool Brook",
    "tgn:placetype":[
        "aat:300008699"
    ]
},
  "bbox": [],
  "geometry": {"coordinates":[-69.7333,46.5333],"type":"Point"}
}
=======
{"geometry":{"type":"Point","coordinates":[-69.733300,46.533300]},"type":"Feature","properties":{"hierarchy":["tgn:2333623","tgn:1000001","tgn:7012149","tgn:7007515","tgn:7029392"],"placetype":["aat:300008699"],"id":2333623,"name:xx":"Fool Brook"}}
>>>>>>> 03f74aca74312dbeaf24d7e61306dd6a786dc3d0
