{
  "id": 7360140,
  "type": "Feature",
  "properties": {
    "tgn:hierarchy":[
        "tgn:7360140",
        "tgn:7005584",
        "tgn:1000001",
        "tgn:7005560",
        "tgn:7029392"
    ],
    "tgn:id":7360140,
    "tgn:name":"Congregaci\u00f3n de la Cabra",
    "tgn:placetype":[
        "aat:300008347"
    ]
},
  "bbox": [],
  "geometry": {"coordinates":[-101.383333,21.133333],"type":"Point"}
}