{
  "id": 2635238,
  "type": "Feature",
  "properties": {
    "tgn:hierarchy":[
        "tgn:2635238",
        "tgn:1000001",
        "tgn:7012149",
        "tgn:2002371",
        "tgn:7007923",
        "tgn:7029392"
    ],
    "tgn:id":2635238,
    "tgn:name":"S G Drain",
    "tgn:placetype":[
        "aat:300006075"
    ]
},
  "bbox": [],
  "geometry": {"coordinates":[-108.45,43.1167],"type":"Point"}
}