{
  "id": 2311195,
  "type": "Feature",
  "properties": {
    "tgn:hierarchy":[
        "tgn:2311195",
        "tgn:7002659",
        "tgn:1000001",
        "tgn:7012149",
        "tgn:2000050",
        "tgn:7029392"
    ],
    "tgn:id":2311195,
    "tgn:name":"Edgemont Heights",
    "tgn:placetype":[
        "aat:300008347"
    ]
},
  "bbox": [],
  "geometry": {"coordinates":[-86.3167,32.3333],"type":"Point"}
}