{
  "id": 2314584,
  "type": "Feature",
  "properties": {
    "tgn:hierarchy":[
        "tgn:2314584",
        "tgn:1000001",
        "tgn:7012149",
        "tgn:2000181",
        "tgn:7007157",
        "tgn:7029392"
    ],
    "tgn:id":2314584,
    "tgn:name":"Elk Prairie",
    "tgn:placetype":[
        "aat:300055621"
    ]
},
  "bbox": [],
  "geometry": {"coordinates":[-124.0167,41.35],"type":"Point"}
}