{
  "id": 7474608,
  "type": "Feature",
  "properties": {
    "tgn:hierarchy":[
        "tgn:7474608",
        "tgn:1000004",
        "tgn:7467799",
        "tgn:1000141",
        "tgn:7029392"
    ],
    "tgn:id":7474608,
    "tgn:name":"Dingcuo Li",
    "tgn:placetype":[
        "aat:300387173"
    ]
},
  "bbox": [],
  "geometry": {"coordinates":[120.445278,24.060278],"type":"Point"}
}