{
  "id": 7342592,
  "type": "Feature",
  "properties": {
    "tgn:hierarchy":[
        "tgn:7342592",
        "tgn:7010420",
        "tgn:1000003",
        "tgn:7002795",
        "tgn:1000095",
        "tgn:7029392"
    ],
    "tgn:id":7342592,
    "tgn:name":"Carpetanos, Montes",
    "tgn:placetype":[
        "aat:300008795"
    ]
},
  "bbox": [],
  "geometry": {"coordinates":[-3.916667,40.916667],"type":"Point"}
}