<<<<<<< HEAD
{
  "id": 2252535,
  "type": "Feature",
  "properties": {
    "tgn:hierarchy":[
        "tgn:2252535",
        "tgn:1000001",
        "tgn:7012149",
        "tgn:2001721",
        "tgn:7007708",
        "tgn:7029392"
    ],
    "tgn:id":2252535,
    "tgn:name":"Conley Lake",
    "tgn:placetype":[
        "aat:300008680"
    ]
},
  "bbox": [],
  "geometry": {"coordinates":[-117.8833,45.3333],"type":"Point"}
}
=======
{"geometry":{"type":"Point","coordinates":[-117.883300,45.333300]},"type":"Feature","properties":{"hierarchy":["tgn:2252535","tgn:1000001","tgn:7012149","tgn:2001721","tgn:7007708","tgn:7029392"],"placetype":["aat:300008680"],"id":2252535,"name:xx":"Conley Lake"}}
>>>>>>> 03f74aca74312dbeaf24d7e61306dd6a786dc3d0
