{
  "id": 7510121,
  "type": "Feature",
  "properties": {
    "tgn:hierarchy":[
        "tgn:7510121",
        "tgn:1009227",
        "tgn:1000226",
        "tgn:1000006",
        "tgn:7016850",
        "tgn:7029392"
    ],
    "tgn:id":7510121,
    "tgn:name:en":"Steeples, The",
    "tgn:placetype":[
        "aat:300011692"
    ]
},
  "bbox": [],
  "geometry": {"coordinates":[171.466667,-41.716667],"type":"Point"}
}