{
  "id": 2333410,
  "type": "Feature",
  "properties": {
    "tgn:hierarchy":[
        "tgn:2333410",
        "tgn:1000001",
        "tgn:7012149",
        "tgn:2002187",
        "tgn:7007919",
        "tgn:7029392"
    ],
    "tgn:id":2333410,
    "tgn:name":"Foley Hill",
    "tgn:placetype":[
        "aat:300008798"
    ]
},
  "bbox": [],
  "geometry": {"coordinates":[-78.75,38.65],"type":"Point"}
}