<<<<<<< HEAD
{
  "id": 2333410,
  "type": "Feature",
  "properties": {
    "tgn:hierarchy":[
        "tgn:2333410",
        "tgn:1000001",
        "tgn:7012149",
        "tgn:2002187",
        "tgn:7007919",
        "tgn:7029392"
    ],
    "tgn:id":2333410,
    "tgn:name":"Foley Hill",
    "tgn:placetype":[
        "aat:300008798"
    ]
},
  "bbox": [],
  "geometry": {"coordinates":[-78.75,38.65],"type":"Point"}
}
=======
{"geometry":{"type":"Point","coordinates":[-78.750000,38.650000]},"type":"Feature","properties":{"hierarchy":["tgn:2333410","tgn:1000001","tgn:7012149","tgn:2002187","tgn:7007919","tgn:7029392"],"placetype":["aat:300008798"],"id":2333410,"name:xx":"Foley Hill"}}
>>>>>>> 03f74aca74312dbeaf24d7e61306dd6a786dc3d0
