{
  "id": 7486966,
  "type": "Feature",
  "properties": {
    "tgn:hierarchy":[
        "tgn:7486966",
        "tgn:1000004",
        "tgn:7490934",
        "tgn:1000141",
        "tgn:7029392"
    ],
    "tgn:id":7486966,
    "tgn:name":"Lingding",
    "tgn:placetype":[
        "aat:300008347"
    ]
},
  "bbox": [],
  "geometry": {"coordinates":[120.377778,22.981667],"type":"Point"}
}