{
  "id": 2368293,
  "type": "Feature",
  "properties": {
    "tgn:hierarchy":[
        "tgn:2368293",
        "tgn:2001730",
        "tgn:1000001",
        "tgn:7012149",
        "tgn:7007712",
        "tgn:7029392"
    ],
    "tgn:id":2368293,
    "tgn:name":"Guess Pond",
    "tgn:placetype":[
        "aat:300008680"
    ]
},
  "bbox": [],
  "geometry": {"coordinates":[-81.25,33.35],"type":"Point"}
}