{
  "id": 1077201,
  "type": "Feature",
  "properties": {
    "tgn:hierarchy":[
        "tgn:1077201",
        "tgn:1000004",
        "tgn:7000198",
        "tgn:7031783",
        "tgn:7029392"
    ],
    "tgn:id":1077201,
    "tgn:name:en":"Topch\u0101nchi",
    "tgn:placetype":[
        "aat:300008347"
    ]
},
  "bbox": [],
  "geometry": {"coordinates":[86.197916,23.903812],"type":"Point"}
}