{
  "id": 1035855,
  "type": "Feature",
  "properties": {
    "tgn:hierarchy":[
        "tgn:1035855",
        "tgn:1000003",
        "tgn:7002880",
        "tgn:1000070",
        "tgn:7029392"
    ],
    "tgn:id":1035855,
    "tgn:name":"Thilay",
    "tgn:placetype":[
        "aat:300008347"
    ]
},
  "bbox": [],
  "geometry": {"coordinates":[4.8167,49.8667],"type":"Point"}
}