{
  "id": 2756977,
  "type": "Feature",
  "properties": {
    "tgn:hierarchy":[
        "tgn:2756977",
        "tgn:1000001",
        "tgn:7012149",
        "tgn:7016056",
        "tgn:7007520",
        "tgn:7029392"
    ],
    "tgn:id":2756977,
    "tgn:name":"Wendt Drain",
    "tgn:placetype":[
        "aat:300006075"
    ]
},
  "bbox": [],
  "geometry": {"coordinates":[-82.9667,43.0333],"type":"Point"}
}