{
  "id": 7039360,
  "type": "Feature",
  "properties": {
    "tgn:hierarchy":[
        "tgn:7039360",
        "tgn:1001724",
        "tgn:1000003",
        "tgn:7003121",
        "tgn:1000080",
        "tgn:7029392"
    ],
    "tgn:id":7039360,
    "tgn:name":"Su Contu",
    "tgn:placetype":[
        "aat:300008795"
    ]
},
  "bbox": [],
  "geometry": {"coordinates":[9.583333,40.15],"type":"Point"}
}