{
  "id": 7218552,
  "type": "Feature",
  "properties": {
    "tgn:hierarchy":[
        "tgn:7218552",
        "tgn:7011171",
        "tgn:7001395",
        "tgn:1000003",
        "tgn:1000074",
        "tgn:7029392"
    ],
    "tgn:id":7218552,
    "tgn:name":"Sarakin\u00f3, Sten\u00f3",
    "tgn:placetype":[
        "aat:300266559"
    ]
},
  "bbox": [],
  "geometry": {"coordinates":[24.615278,38.760833],"type":"Point"}
}