{
  "id": 7398376,
  "type": "Feature",
  "properties": {
    "tgn:hierarchy":[
        "tgn:7398376",
        "tgn:1000001",
        "tgn:1001960",
        "tgn:7005560",
        "tgn:7029392"
    ],
    "tgn:id":7398376,
    "tgn:name":"Lizarraga",
    "tgn:placetype":[
        "aat:300008347"
    ]
},
  "bbox": [],
  "geometry": {"coordinates":[-111.959167,30.914722],"type":"Point"}
}