{
  "id": 2683279,
  "type": "Feature",
  "properties": {
    "tgn:hierarchy":[
        "tgn:2683279",
        "tgn:1000001",
        "tgn:7012149",
        "tgn:2001281",
        "tgn:7007524",
        "tgn:7029392"
    ],
    "tgn:id":2683279,
    "tgn:name":"Spar Mine",
    "tgn:placetype":[
        "aat:300000390"
    ]
},
  "bbox": [],
  "geometry": {"coordinates":[-111.7833,46.2167],"type":"Point"}
}