{
  "id": 2618651,
  "type": "Feature",
  "properties": {
    "tgn:hierarchy":[
        "tgn:2618651",
        "tgn:1000001",
        "tgn:7012149",
        "tgn:2002125",
        "tgn:7007827",
        "tgn:7029392"
    ],
    "tgn:id":2618651,
    "tgn:name":"Right Fork Mill",
    "tgn:placetype":[
        "aat:300008699"
    ]
},
  "bbox": [],
  "geometry": {"coordinates":[-111.3333,39.8667],"type":"Point"}
}