{
  "id": 2580198,
  "type": "Feature",
  "properties": {
    "tgn:hierarchy":[
        "tgn:2580198",
        "tgn:1000001",
        "tgn:7006451",
        "tgn:7012149",
        "tgn:2000099",
        "tgn:7029392"
    ],
    "tgn:id":2580198,
    "tgn:name":"Pierce Tank",
    "tgn:placetype":[
        "aat:300006191"
    ]
},
  "bbox": [],
  "geometry": {"coordinates":[-110.4833,34.45],"type":"Point"}
}