<<<<<<< HEAD
{
  "id": 7481428,
  "type": "Feature",
  "properties": {
    "tgn:hierarchy":[
        "tgn:7481428",
        "tgn:1000004",
        "tgn:7492971",
        "tgn:1000141",
        "tgn:7029392"
    ],
    "tgn:id":7481428,
    "tgn:name":"Longdong Qiao",
    "tgn:placetype":[
        "aat:300007836"
    ]
},
  "bbox": [],
  "geometry": {"coordinates":[120.582431,22.603082],"type":"Point"}
}
=======
{"geometry":{"type":"Point","coordinates":[120.582431,22.603082]},"type":"Feature","properties":{"hierarchy":["tgn:7481428","tgn:1000004","tgn:7492971","tgn:1000141","tgn:7029392"],"placetype":["aat:300007836"],"id":7481428,"name:xx":"Longdong Qiao"}}
>>>>>>> 03f74aca74312dbeaf24d7e61306dd6a786dc3d0
