{
  "id": 7481428,
  "type": "Feature",
  "properties": {
    "tgn:hierarchy":[
        "tgn:7481428",
        "tgn:1000004",
        "tgn:7492971",
        "tgn:1000141",
        "tgn:7029392"
    ],
    "tgn:id":7481428,
    "tgn:name":"Longdong Qiao",
    "tgn:placetype":[
        "aat:300007836"
    ]
},
  "bbox": [],
  "geometry": {"coordinates":[120.582431,22.603082],"type":"Point"}
}