{
  "id": 7100849,
  "type": "Feature",
  "properties": {
    "tgn:hierarchy":[
        "tgn:7100849",
        "tgn:1000003",
        "tgn:7003676",
        "tgn:7000084",
        "tgn:7029392"
    ],
    "tgn:id":7100849,
    "tgn:name":"Rott-Berg",
    "tgn:placetype":[
        "aat:300008777"
    ]
},
  "bbox": [],
  "geometry": {"coordinates":[9.933333,52.066667],"type":"Point"}
}