{
  "id": 2668716,
  "type": "Feature",
  "properties": {
    "tgn:hierarchy":[
        "tgn:2668716",
        "tgn:1000001",
        "tgn:1003028",
        "tgn:7012149",
        "tgn:7007159",
        "tgn:7029392"
    ],
    "tgn:id":2668716,
    "tgn:name":"Slater Hill",
    "tgn:placetype":[
        "aat:300008798"
    ]
},
  "bbox": [],
  "geometry": {"coordinates":[-71.8167,41.8167],"type":"Point"}
}