{
  "id": 7593252,
  "type": "Feature",
  "properties": {
    "tgn:hierarchy":[
        "tgn:7593252",
        "tgn:1001612",
        "tgn:7002559",
        "tgn:1000051",
        "tgn:1000002",
        "tgn:7029392"
    ],
    "tgn:id":7593252,
    "tgn:name":"El Pangui",
    "tgn:placetype":[
        "aat:300008347"
    ]
},
  "bbox": [],
  "geometry": {"coordinates":[-78.589,-3.627],"type":"Point"}
}