{
  "id": 7439334,
  "type": "Feature",
  "properties": {
    "tgn:hierarchy":[
        "tgn:7439334",
        "tgn:7005581",
        "tgn:1000001",
        "tgn:7005560",
        "tgn:7029392"
    ],
    "tgn:id":7439334,
    "tgn:name":"Tecolote",
    "tgn:placetype":[
        "aat:300008347"
    ]
},
  "bbox": [],
  "geometry": {"coordinates":[-105.866667,27.533333],"type":"Point"}
}