{
  "id": 2234858,
  "type": "Feature",
  "properties": {
    "tgn:hierarchy":[
        "tgn:2234858",
        "tgn:1000001",
        "tgn:7012149",
        "tgn:2002112",
        "tgn:7007827",
        "tgn:7029392"
    ],
    "tgn:id":2234858,
    "tgn:name":"Cherry Creek Reservoir",
    "tgn:placetype":[
        "aat:300006191"
    ]
},
  "bbox": [],
  "geometry": {"coordinates":[-112.3333,39.85],"type":"Point"}
}