{
  "id": 7511456,
  "type": "Feature",
  "properties": {
    "tgn:hierarchy":[
        "tgn:7511456",
        "tgn:1009227",
        "tgn:1000226",
        "tgn:7016822",
        "tgn:1000006",
        "tgn:7029392"
    ],
    "tgn:id":7511456,
    "tgn:name:en":"Mason Head",
    "tgn:placetype":[
        "aat:300008850"
    ]
},
  "bbox": [],
  "geometry": {"coordinates":[167.75,-46.883333],"type":"Point"}
}