{
  "id": 7510589,
  "type": "Feature",
  "properties": {
    "tgn:hierarchy":[
        "tgn:7510589",
        "tgn:1009227",
        "tgn:1000226",
        "tgn:1000006",
        "tgn:7016850",
        "tgn:7029392"
    ],
    "tgn:id":7510589,
    "tgn:name:en":"Tyndalls Knob",
    "tgn:placetype":[
        "aat:300008798"
    ]
},
  "bbox": [],
  "geometry": {"coordinates":[171.25,-42.916667],"type":"Point"}
}