{
  "id": 7500881,
  "type": "Feature",
  "properties": {
    "tgn:hierarchy":[
        "tgn:7500881",
        "tgn:7001004",
        "tgn:1000004",
        "tgn:1000141",
        "tgn:7029392"
    ],
    "tgn:id":7500881,
    "tgn:name":"Longfeng Si",
    "tgn:placetype":[
        "aat:300007595"
    ]
},
  "bbox": [],
  "geometry": {"coordinates":[120.370556,22.833333],"type":"Point"}
}