{
  "id": 2511221,
  "type": "Feature",
  "properties": {
    "tgn:hierarchy":[
        "tgn:2511221",
        "tgn:1000001",
        "tgn:7012149",
        "tgn:2001607",
        "tgn:7007705",
        "tgn:7029392"
    ],
    "tgn:id":2511221,
    "tgn:name":"Mike King Hill",
    "tgn:placetype":[
        "aat:300008798"
    ]
},
  "bbox": [],
  "geometry": {"coordinates":[-101.8667,48.5167],"type":"Point"}
}