{
  "id": 2198446,
  "type": "Feature",
  "properties": {
    "tgn:hierarchy":[
        "tgn:2198446",
        "tgn:1000001",
        "tgn:7012149",
        "tgn:7007157",
        "tgn:2000187",
        "tgn:7029392"
    ],
    "tgn:id":2198446,
    "tgn:name":"Browns Hill Ridge",
    "tgn:placetype":[
        "aat:300266640"
    ]
},
  "bbox": [],
  "geometry": {"coordinates":[-121.1333,39.7167],"type":"Point"}
}