{
  "id": 7558443,
  "type": "Feature",
  "properties": {
    "tgn:hierarchy":[
        "tgn:7558443",
        "tgn:1000004",
        "tgn:7000198",
        "tgn:1001895",
        "tgn:7029392"
    ],
    "tgn:id":7558443,
    "tgn:name:en":"Pathrot",
    "tgn:placetype":[
        "aat:300007783"
    ]
},
  "bbox": [],
  "geometry": {"coordinates":[77.397667,21.185804],"type":"Point"}
}