{
  "id": 2314531,
  "type": "Feature",
  "properties": {
    "tgn:hierarchy":[
        "tgn:2314531",
        "tgn:1000001",
        "tgn:7012149",
        "tgn:1002979",
        "tgn:7007920",
        "tgn:7029392"
    ],
    "tgn:id":2314531,
    "tgn:name":"Elk Mountain",
    "tgn:placetype":[
        "aat:300008798"
    ]
},
  "bbox": [],
  "geometry": {"coordinates":[-123.5333,46.3167],"type":"Point"}
}