{
  "id": 2495647,
  "type": "Feature",
  "properties": {
    "tgn:hierarchy":[
        "tgn:2495647",
        "tgn:1000001",
        "tgn:7006451",
        "tgn:7012149",
        "tgn:2000097",
        "tgn:7029392"
    ],
    "tgn:id":2495647,
    "tgn:name":"Mashakattee Spring",
    "tgn:placetype":[
        "aat:300008697"
    ]
},
  "bbox": [],
  "geometry": {"coordinates":[-111.85,33.9667],"type":"Point"}
}