{
  "id": 2047626,
  "type": "Feature",
  "properties": {
    "tgn:hierarchy":[
        "tgn:2047626",
        "tgn:1000001",
        "tgn:2000939",
        "tgn:7012149",
        "tgn:7007516",
        "tgn:7029392"
    ],
    "tgn:id":2047626,
    "tgn:name":"Kirkham",
    "tgn:placetype":[
        "aat:300008347",
        "aat:300387210"
    ]
},
  "bbox": [],
  "geometry": {"coordinates":[-76.1333,38.75],"type":"Point"}
}