{
  "id": 7504204,
  "type": "Feature",
  "properties": {
    "tgn:hierarchy":[
        "tgn:7504204",
        "tgn:1009227",
        "tgn:1000226",
        "tgn:7018437",
        "tgn:1000006",
        "tgn:7029392"
    ],
    "tgn:id":7504204,
    "tgn:name:en":"Wanbrow, Cape",
    "tgn:placetype":[
        "aat:300008850"
    ]
},
  "bbox": [],
  "geometry": {"coordinates":[170.983333,-45.116667],"type":"Point"}
}