{
  "id": 2220629,
  "type": "Feature",
  "properties": {
    "tgn:hierarchy":[
        "tgn:2220629",
        "tgn:7006450",
        "tgn:1000001",
        "tgn:7012149",
        "tgn:2000079",
        "tgn:7029392"
    ],
    "tgn:id":2220629,
    "tgn:name":"Cape Woolley",
    "tgn:placetype":[
        "aat:300008850"
    ]
},
  "bbox": [],
  "geometry": {"coordinates":[-166.4667,64.7833],"type":"Point"}
}