{
  "id": 2675719,
  "type": "Feature",
  "properties": {
    "tgn:hierarchy":[
        "tgn:2675719",
        "tgn:1000001",
        "tgn:2001336",
        "tgn:7012149",
        "tgn:7007525",
        "tgn:7029392"
    ],
    "tgn:id":2675719,
    "tgn:name":"Somerford Valley",
    "tgn:placetype":[
        "aat:300008761"
    ]
},
  "bbox": [],
  "geometry": {"coordinates":[-99.4167,41.5667],"type":"Point"}
}