{
  "id": 1112851,
  "type": "Feature",
  "properties": {
    "tgn:hierarchy":[
        "tgn:1112851",
        "tgn:1000004",
        "tgn:1001481",
        "tgn:1000135",
        "tgn:7029392"
    ],
    "tgn:id":1112851,
    "tgn:name":"Coral Bay",
    "tgn:placetype":[
        "aat:300132316"
    ]
},
  "bbox": [],
  "geometry": {"coordinates":[117.3333,8.4167],"type":"Point"}
}