{
  "id": 7262615,
  "type": "Feature",
  "properties": {
    "tgn:concordances":{
        "gn:id":"2758222"
    },
    "tgn:hierarchy":[
        "tgn:7262615",
        "tgn:7003614",
        "tgn:1000003",
        "tgn:7016845",
        "tgn:7029392"
    ],
    "tgn:id":7262615,
    "tgn:name:nl":"Bronneger",
    "tgn:placetype":[
        "aat:300008347"
    ]
},
  "bbox": [],
  "geometry": {"coordinates":[6.816667,52.95],"type":"Point"}
}