{
  "id": 2575172,
  "type": "Feature",
  "properties": {
    "tgn:hierarchy":[
        "tgn:2575172",
        "tgn:1000001",
        "tgn:7012149",
        "tgn:1002729",
        "tgn:7007710",
        "tgn:7029392"
    ],
    "tgn:id":2575172,
    "tgn:name":"Pennsylvania Canal",
    "tgn:placetype":[
        "aat:300006075"
    ]
},
  "bbox": [],
  "geometry": {"coordinates":[-75.1833,40.6667],"type":"Point"}
}