{
  "id": 2383660,
  "type": "Feature",
  "properties": {
    "tgn:hierarchy":[
        "tgn:2383660",
        "tgn:1000001",
        "tgn:7012149",
        "tgn:2001537",
        "tgn:7007709",
        "tgn:7029392"
    ],
    "tgn:id":2383660,
    "tgn:name":"Heaveners Creek",
    "tgn:placetype":[
        "aat:300008706"
    ]
},
  "bbox": [],
  "geometry": {"coordinates":[-81.7667,35.4167],"type":"Point"}
}