<<<<<<< HEAD
{
  "id": 2402078,
  "type": "Feature",
  "properties": {
    "tgn:hierarchy":[
        "tgn:2402078",
        "tgn:1000001",
        "tgn:2002102",
        "tgn:7012149",
        "tgn:7007827",
        "tgn:7029392"
    ],
    "tgn:id":2402078,
    "tgn:name":"Horseshoe Sloughs",
    "tgn:placetype":[
        "aat:300008680"
    ]
},
  "bbox": [],
  "geometry": {"coordinates":[-112.0833,41.5167],"type":"Point"}
}
=======
{"geometry":{"type":"Point","coordinates":[-112.083300,41.516700]},"type":"Feature","properties":{"hierarchy":["tgn:2402078","tgn:1000001","tgn:2002102","tgn:7012149","tgn:7007827","tgn:7029392"],"placetype":["aat:300008680"],"id":2402078,"name:xx":"Horseshoe Sloughs"}}
>>>>>>> 03f74aca74312dbeaf24d7e61306dd6a786dc3d0
