<<<<<<< HEAD
{
  "id": 7245857,
  "type": "Feature",
  "properties": {
    "tgn:hierarchy":[
        "tgn:7245857",
        "tgn:7003456",
        "tgn:1000003",
        "tgn:1000063",
        "tgn:7018236",
        "tgn:7029392"
    ],
    "tgn:id":7245857,
    "tgn:name":"Brusselsebossen",
    "tgn:placetype":[
        "aat:300008863"
    ]
},
  "bbox": [],
  "geometry": {"coordinates":[4.45,51.316667],"type":"Point"}
}
=======
{"geometry":{"type":"Point","coordinates":[4.450000,51.316667]},"type":"Feature","properties":{"hierarchy":["tgn:7245857","tgn:7003456","tgn:1000003","tgn:1000063","tgn:7018236","tgn:7029392"],"placetype":["aat:300008863"],"id":7245857,"name:xx":"Brusselsebossen"}}
>>>>>>> 03f74aca74312dbeaf24d7e61306dd6a786dc3d0
