{
  "id": 7580202,
  "type": "Feature",
  "properties": {
    "tgn:hierarchy":[
        "tgn:7580202",
        "tgn:1000004",
        "tgn:7000198",
        "tgn:1001996",
        "tgn:7029392"
    ],
    "tgn:id":7580202,
    "tgn:name:en":"Tharoch",
    "tgn:placetype":[
        "aat:300008347"
    ]
},
  "bbox": [],
  "geometry": {"coordinates":[77.692951,30.977715],"type":"Point"}
}