<<<<<<< HEAD
{
  "id": 2405373,
  "type": "Feature",
  "properties": {
    "tgn:hierarchy":[
        "tgn:2405373",
        "tgn:1000001",
        "tgn:1002184",
        "tgn:7012149",
        "tgn:7007252",
        "tgn:7029392"
    ],
    "tgn:id":2405373,
    "tgn:name":"Huggens Ditch",
    "tgn:placetype":[
        "aat:300006075"
    ]
},
  "bbox": [],
  "geometry": {"coordinates":[-85.3333,40.4833],"type":"Point"}
}
=======
{"geometry":{"type":"Point","coordinates":[-85.333300,40.483300]},"type":"Feature","properties":{"hierarchy":["tgn:2405373","tgn:1000001","tgn:1002184","tgn:7012149","tgn:7007252","tgn:7029392"],"placetype":["aat:300006075"],"id":2405373,"name:xx":"Huggens Ditch"}}
>>>>>>> 03f74aca74312dbeaf24d7e61306dd6a786dc3d0
