{
  "id": 2423450,
  "type": "Feature",
  "properties": {
    "tgn:hierarchy":[
        "tgn:2423450",
        "tgn:1000001",
        "tgn:2001411",
        "tgn:7012149",
        "tgn:7007526",
        "tgn:7029392"
    ],
    "tgn:id":2423450,
    "tgn:name":"John Day Creek",
    "tgn:placetype":[
        "aat:300008706"
    ]
},
  "bbox": [],
  "geometry": {"coordinates":[-115.3333,40.7667],"type":"Point"}
}