{
  "id": 7228533,
  "type": "Feature",
  "properties": {
    "tgn:hierarchy":[
        "tgn:7228533",
        "tgn:7011170",
        "tgn:7002715",
        "tgn:1000003",
        "tgn:1000074",
        "tgn:7029392"
    ],
    "tgn:id":7228533,
    "tgn:name":"G\u00e1zoros",
    "tgn:placetype":[
        "aat:300008347"
    ]
},
  "bbox": [],
  "geometry": {"coordinates":[23.766667,41.016667],"type":"Point"}
}