{
  "id": 2422304,
  "type": "Feature",
  "properties": {
    "tgn:hierarchy":[
        "tgn:2422304",
        "tgn:1000001",
        "tgn:7012149",
        "tgn:2001306",
        "tgn:7007524",
        "tgn:7029392"
    ],
    "tgn:id":2422304,
    "tgn:name":"Jimmie New Creek",
    "tgn:placetype":[
        "aat:300008706"
    ]
},
  "bbox": [],
  "geometry": {"coordinates":[-112.9333,45.8667],"type":"Point"}
}