<<<<<<< HEAD
{
  "id": 2253222,
  "type": "Feature",
  "properties": {
    "tgn:hierarchy":[
        "tgn:2253222",
        "tgn:1000001",
        "tgn:7012149",
        "tgn:7007826",
        "tgn:7029392"
    ],
    "tgn:id":2253222,
    "tgn:name":"Contrabando Mountain",
    "tgn:placetype":[
        "aat:300008798"
    ]
},
  "bbox": [],
  "geometry": {"coordinates":[-103.7833,29.3],"type":"Point"}
}
=======
{"geometry":{"type":"Point","coordinates":[-103.783300,29.300000]},"type":"Feature","properties":{"hierarchy":["tgn:2253222","tgn:1000001","tgn:7012149","tgn:7007826","tgn:7029392"],"placetype":["aat:300008798"],"id":2253222,"name:xx":"Contrabando Mountain"}}
>>>>>>> 03f74aca74312dbeaf24d7e61306dd6a786dc3d0
