<<<<<<< HEAD
{
  "id": 2258367,
  "type": "Feature",
  "properties": {
    "tgn:hierarchy":[
        "tgn:2258367",
        "tgn:1000001",
        "tgn:7012149",
        "tgn:7007828",
        "tgn:7029392"
    ],
    "tgn:id":2258367,
    "tgn:name":"Cotton Brook",
    "tgn:placetype":[
        "aat:300008699"
    ]
},
  "bbox": [],
  "geometry": {"coordinates":[-72.8333,44.4333],"type":"Point"}
}
=======
{"geometry":{"type":"Point","coordinates":[-72.833300,44.433300]},"type":"Feature","properties":{"hierarchy":["tgn:2258367","tgn:1000001","tgn:7012149","tgn:7007828","tgn:7029392"],"placetype":["aat:300008699"],"id":2258367,"name:xx":"Cotton Brook"}}
>>>>>>> 03f74aca74312dbeaf24d7e61306dd6a786dc3d0
