{
  "id": 2431062,
  "type": "Feature",
  "properties": {
    "tgn:hierarchy":[
        "tgn:2431062",
        "tgn:7006450",
        "tgn:1000001",
        "tgn:7012149",
        "tgn:2124002",
        "tgn:7029392"
    ],
    "tgn:id":2431062,
    "tgn:name":"Kanga Bay",
    "tgn:placetype":[
        "aat:300132316"
    ]
},
  "bbox": [],
  "geometry": {"coordinates":[-135.35,56.8833],"type":"Point"}
}