{
  "id": 2570191,
  "type": "Feature",
  "properties": {
    "tgn:hierarchy":[
        "tgn:2570191",
        "tgn:1000001",
        "tgn:7012149",
        "tgn:2002127",
        "tgn:7007827",
        "tgn:7029392"
    ],
    "tgn:id":2570191,
    "tgn:name":"Pastry Ridge",
    "tgn:placetype":[
        "aat:300266640"
    ]
},
  "bbox": [],
  "geometry": {"coordinates":[-113.1167,37.15],"type":"Point"}
}