{
  "id": 2035415,
  "type": "Feature",
  "properties": {
    "tgn:hierarchy":[
        "tgn:2035415",
        "tgn:1000001",
        "tgn:7012149",
        "tgn:2000612",
        "tgn:7007253",
        "tgn:7029392"
    ],
    "tgn:id":2035415,
    "tgn:name":"Oxford",
    "tgn:placetype":[
        "aat:300008347"
    ]
},
  "bbox": [],
  "geometry": {"coordinates":[-91.7833,41.7167],"type":"Point"}
}