{
  "id": 2776306,
  "type": "Feature",
  "properties": {
    "tgn:hierarchy":[
        "tgn:2776306",
        "tgn:1000001",
        "tgn:2000935",
        "tgn:7012149",
        "tgn:7007516",
        "tgn:7029392"
    ],
    "tgn:id":2776306,
    "tgn:name":"Winchester",
    "tgn:placetype":[
        "aat:300008347"
    ]
},
  "bbox": [],
  "geometry": {"coordinates":[-78.8333,39.6167],"type":"Point"}
}