{
  "id": 2116274,
  "type": "Feature",
  "properties": {
    "tgn:hierarchy":[
        "tgn:2116274",
        "tgn:1000001",
        "tgn:7012149",
        "tgn:1002418",
        "tgn:7007920",
        "tgn:7029392"
    ],
    "tgn:id":2116274,
    "tgn:name":"Melbourne",
    "tgn:placetype":[
        "aat:300008347"
    ]
},
  "bbox": [],
  "geometry": {"coordinates":[-123.6167,46.9333],"type":"Point"}
}