<<<<<<< HEAD
{
  "id": 2769391,
  "type": "Feature",
  "properties": {
    "tgn:hierarchy":[
        "tgn:2769391",
        "tgn:7002659",
        "tgn:1000001",
        "tgn:7012149",
        "tgn:2000035",
        "tgn:7029392"
    ],
    "tgn:id":2769391,
    "tgn:name":"Wicks Hollow",
    "tgn:placetype":[
        "aat:300008761"
    ]
},
  "bbox": [],
  "geometry": {"coordinates":[-85.8333,34.7],"type":"Point"}
}
=======
{"geometry":{"type":"Point","coordinates":[-85.833300,34.700000]},"type":"Feature","properties":{"hierarchy":["tgn:2769391","tgn:7002659","tgn:1000001","tgn:7012149","tgn:2000035","tgn:7029392"],"placetype":["aat:300008761"],"id":2769391,"name:xx":"Wicks Hollow"}}
>>>>>>> 03f74aca74312dbeaf24d7e61306dd6a786dc3d0
