<<<<<<< HEAD
{
  "id": 7059336,
  "type": "Feature",
  "properties": {
    "tgn:hierarchy":[
        "tgn:7059336",
        "tgn:7003669",
        "tgn:1000003",
        "tgn:7000084",
        "tgn:7029392"
    ],
    "tgn:id":7059336,
    "tgn:name":"Almbach",
    "tgn:placetype":[
        "aat:300000206"
    ]
},
  "bbox": [],
  "geometry": {"coordinates":[11.6,47.65],"type":"Point"}
}
=======
{"geometry":{"type":"Point","coordinates":[11.600000,47.650000]},"type":"Feature","properties":{"hierarchy":["tgn:7059336","tgn:7003669","tgn:1000003","tgn:7000084","tgn:7029392"],"placetype":["aat:300000206"],"id":7059336,"name:xx":"Almbach"}}
>>>>>>> 03f74aca74312dbeaf24d7e61306dd6a786dc3d0
