{
  "id": 2167394,
  "type": "Feature",
  "properties": {
    "tgn:hierarchy":[
        "tgn:2167394",
        "tgn:1000001",
        "tgn:7012149",
        "tgn:1002742",
        "tgn:7007920",
        "tgn:7029392"
    ],
    "tgn:id":2167394,
    "tgn:name":"Big Craggy Peak",
    "tgn:placetype":[
        "aat:300008798"
    ]
},
  "bbox": [],
  "geometry": {"coordinates":[-120.3167,48.75],"type":"Point"}
}