{
  "id": 7584173,
  "type": "Feature",
  "properties": {
    "tgn:hierarchy":[
        "tgn:7584173",
        "tgn:1000004",
        "tgn:7000198",
        "tgn:7016788",
        "tgn:7029392"
    ],
    "tgn:id":7584173,
    "tgn:name:en":"P\u012bp\u0101na Johra",
    "tgn:placetype":[
        "aat:300008688"
    ]
},
  "bbox": [],
  "geometry": {"coordinates":[75.1618,28.4102],"type":"Point"}
}