<<<<<<< HEAD
{
  "id": 2331957,
  "type": "Feature",
  "properties": {
    "tgn:hierarchy":[
        "tgn:2331957",
        "tgn:1000001",
        "tgn:7012149",
        "tgn:1002785",
        "tgn:7007920",
        "tgn:7029392"
    ],
    "tgn:id":2331957,
    "tgn:name":"Flett Creek",
    "tgn:placetype":[
        "aat:300008706"
    ]
},
  "bbox": [],
  "geometry": {"coordinates":[-122.4833,47.1833],"type":"Point"}
}
=======
{"geometry":{"type":"Point","coordinates":[-122.483300,47.183300]},"type":"Feature","properties":{"hierarchy":["tgn:2331957","tgn:1000001","tgn:7012149","tgn:1002785","tgn:7007920","tgn:7029392"],"placetype":["aat:300008706"],"id":2331957,"name:xx":"Flett Creek"}}
>>>>>>> 03f74aca74312dbeaf24d7e61306dd6a786dc3d0
