{
  "id": 2675380,
  "type": "Feature",
  "properties": {
    "tgn:hierarchy":[
        "tgn:2675380",
        "tgn:1000001",
        "tgn:7012149",
        "tgn:2001274",
        "tgn:7007524",
        "tgn:7029392"
    ],
    "tgn:id":2675380,
    "tgn:name":"Soldier Mountain",
    "tgn:placetype":[
        "aat:300008798"
    ]
},
  "bbox": [],
  "geometry": {"coordinates":[-113.6167,47.95],"type":"Point"}
}