{
  "id": 7346199,
  "type": "Feature",
  "properties": {
    "tgn:hierarchy":[
        "tgn:7346199",
        "tgn:7002832",
        "tgn:7001158",
        "tgn:1000003",
        "tgn:1000095",
        "tgn:7029392"
    ],
    "tgn:id":7346199,
    "tgn:name":"Arlanz\u00f3n, R\u00edo",
    "tgn:placetype":[
        "aat:300008699"
    ]
},
  "bbox": [],
  "geometry": {"coordinates":[-4.283333,42.05],"type":"Point"}
}