{
  "id": 7127642,
  "type": "Feature",
  "properties": {
    "tgn:hierarchy":[
        "tgn:7127642",
        "tgn:7003669",
        "tgn:1000003",
        "tgn:7000084",
        "tgn:7029392"
    ],
    "tgn:id":7127642,
    "tgn:name":"Oberndorf",
    "tgn:placetype":[
        "aat:300008347"
    ]
},
  "bbox": [],
  "geometry": {"coordinates":[12.85,47.883333],"type":"Point"}
}