{
  "id": 1080960,
  "type": "Feature",
  "properties": {
    "tgn:hierarchy":[
        "tgn:1080960",
        "tgn:7000895",
        "tgn:1000004",
        "tgn:1001010",
        "tgn:1000120",
        "tgn:7029392"
    ],
    "tgn:id":1080960,
    "tgn:name":"Namiai",
    "tgn:placetype":[
        "aat:300008347"
    ]
},
  "bbox": [],
  "geometry": {"coordinates":[137.6833,35.3667],"type":"Point"}
}