{
  "id": 2423823,
  "type": "Feature",
  "properties": {
    "tgn:hierarchy":[
        "tgn:2423823",
        "tgn:1000001",
        "tgn:7006451",
        "tgn:7012149",
        "tgn:2000099",
        "tgn:7029392"
    ],
    "tgn:id":2423823,
    "tgn:name":"Johnnie Tank",
    "tgn:placetype":[
        "aat:300006191"
    ]
},
  "bbox": [],
  "geometry": {"coordinates":[-110.0667,34.15],"type":"Point"}
}