{
  "id": 7041075,
  "type": "Feature",
  "properties": {
    "tgn:hierarchy":[
        "tgn:7041075",
        "tgn:7003163",
        "tgn:1000003",
        "tgn:7009760",
        "tgn:1000080",
        "tgn:7029392"
    ],
    "tgn:id":7041075,
    "tgn:name":"San Cerbone",
    "tgn:placetype":[
        "aat:300008347"
    ]
},
  "bbox": [],
  "geometry": {"coordinates":[11.383333,43.65],"type":"Point"}
}