{
  "id": 7055602,
  "type": "Feature",
  "properties": {
    "tgn:hierarchy":[
        "tgn:7055602",
        "tgn:7003154",
        "tgn:1000003",
        "tgn:7003120",
        "tgn:1000080",
        "tgn:7029392"
    ],
    "tgn:id":7055602,
    "tgn:name":"Orio Canavese",
    "tgn:placetype":[
        "aat:300008347"
    ]
},
  "bbox": [],
  "geometry": {"coordinates":[7.866667,45.333333],"type":"Point"}
}