{
  "id": 2040627,
  "type": "Feature",
  "properties": {
    "tgn:hierarchy":[
        "tgn:2040627",
        "tgn:1000001",
        "tgn:7012149",
        "tgn:2000801",
        "tgn:7007255",
        "tgn:7029392"
    ],
    "tgn:id":2040627,
    "tgn:name":"Oriole",
    "tgn:placetype":[
        "aat:300387016"
    ]
},
  "bbox": [],
  "geometry": {"coordinates":[-87.5667,37.2833],"type":"Point"}
}