{
  "id": 2213304,
  "type": "Feature",
  "properties": {
    "tgn:hierarchy":[
        "tgn:2213304",
        "tgn:1000001",
        "tgn:7012149",
        "tgn:7007919",
        "tgn:7029392"
    ],
    "tgn:id":2213304,
    "tgn:name":"Cabin Creek",
    "tgn:placetype":[
        "aat:300008706"
    ]
},
  "bbox": [],
  "geometry": {"coordinates":[-77.3333,37.25],"type":"Point"}
}