{
  "id": 2433106,
  "type": "Feature",
  "properties": {
    "tgn:hierarchy":[
        "tgn:2433106",
        "tgn:1002648",
        "tgn:1000001",
        "tgn:7019158",
        "tgn:7012149",
        "tgn:7007249",
        "tgn:7029392"
    ],
    "tgn:id":2433106,
    "tgn:name":"Kekaa Point",
    "tgn:placetype":[
        "aat:300008850"
    ]
},
  "bbox": [],
  "geometry": {"coordinates":[-156.6833,20.9167],"type":"Point"}
}