{
  "id": 7436141,
  "type": "Feature",
  "properties": {
    "tgn:hierarchy":[
        "tgn:7436141",
        "tgn:7005581",
        "tgn:1000001",
        "tgn:7005560",
        "tgn:7029392"
    ],
    "tgn:id":7436141,
    "tgn:name":"Santo Ni\u00f1o",
    "tgn:placetype":[
        "aat:300008347"
    ]
},
  "bbox": [],
  "geometry": {"coordinates":[-108.366667,27.066667],"type":"Point"}
}