<<<<<<< HEAD
{
  "id": 7358591,
  "type": "Feature",
  "properties": {
    "tgn:hierarchy":[
        "tgn:7358591",
        "tgn:7005583",
        "tgn:1000001",
        "tgn:7005560",
        "tgn:7029392"
    ],
    "tgn:id":7358591,
    "tgn:name":"Rancho El Aceteado",
    "tgn:placetype":[
        "aat:300000241"
    ]
},
  "bbox": [],
  "geometry": {"coordinates":[-105.59,24.15],"type":"Point"}
}
=======
{"geometry":{"type":"Point","coordinates":[-105.590000,24.150000]},"type":"Feature","properties":{"hierarchy":["tgn:7358591","tgn:7005583","tgn:1000001","tgn:7005560","tgn:7029392"],"placetype":["aat:300000241"],"id":7358591,"name:xx":"Rancho El Aceteado"}}
>>>>>>> 03f74aca74312dbeaf24d7e61306dd6a786dc3d0
