{
  "id": 7476136,
  "type": "Feature",
  "properties": {
    "tgn:hierarchy":[
        "tgn:7476136",
        "tgn:7488858",
        "tgn:1000004",
        "tgn:1000141",
        "tgn:7029392"
    ],
    "tgn:id":7476136,
    "tgn:name":"Xinshan Qiao",
    "tgn:placetype":[
        "aat:300007836"
    ]
},
  "bbox": [],
  "geometry": {"coordinates":[120.864232,23.761949],"type":"Point"}
}