{
  "id": 2449197,
  "type": "Feature",
  "properties": {
    "tgn:hierarchy":[
        "tgn:2449197",
        "tgn:1000001",
        "tgn:7012149",
        "tgn:2000549",
        "tgn:7007252",
        "tgn:7029392"
    ],
    "tgn:id":2449197,
    "tgn:name":"Limestone Branch",
    "tgn:placetype":[
        "aat:300008699"
    ]
},
  "bbox": [],
  "geometry": {"coordinates":[-87.0167,39.7333],"type":"Point"}
}