<<<<<<< HEAD
{
  "id": 7052950,
  "type": "Feature",
  "properties": {
    "tgn:hierarchy":[
        "tgn:7052950",
        "tgn:7003167",
        "tgn:1000003",
        "tgn:7009760",
        "tgn:1000080",
        "tgn:7029392"
    ],
    "tgn:id":7052950,
    "tgn:name":"Il Barba",
    "tgn:placetype":[
        "aat:300008347"
    ]
},
  "bbox": [],
  "geometry": {"coordinates":[10.966667,43.883333],"type":"Point"}
}
=======
{"geometry":{"type":"Point","coordinates":[10.966667,43.883333]},"type":"Feature","properties":{"hierarchy":["tgn:7052950","tgn:7003167","tgn:1000003","tgn:7009760","tgn:1000080","tgn:7029392"],"placetype":["aat:300008347"],"id":7052950,"name:xx":"Il Barba"}}
>>>>>>> 03f74aca74312dbeaf24d7e61306dd6a786dc3d0
