{
  "id": 2158802,
  "type": "Feature",
  "properties": {
    "tgn:hierarchy":[
        "tgn:2158802",
        "tgn:2002131",
        "tgn:1000001",
        "tgn:7012149",
        "tgn:7007828",
        "tgn:7029392"
    ],
    "tgn:id":2158802,
    "tgn:name":"Beck Pond",
    "tgn:placetype":[
        "aat:300008680"
    ]
},
  "bbox": [],
  "geometry": {"coordinates":[-71.9167,44.7167],"type":"Point"}
}