{
  "id": 1091877,
  "type": "Feature",
  "properties": {
    "tgn:hierarchy":[
        "tgn:1091877",
        "tgn:7001242",
        "tgn:1001874",
        "tgn:1000182",
        "tgn:7029392"
    ],
    "tgn:id":1091877,
    "tgn:name":"Awgu",
    "tgn:placetype":[
        "aat:300008347"
    ]
},
  "bbox": [],
  "geometry": {"coordinates":[7.4333,6.0833],"type":"Point"}
}