{
  "id": 7072374,
  "type": "Feature",
  "properties": {
    "tgn:hierarchy":[
        "tgn:7072374",
        "tgn:1000003",
        "tgn:7000094",
        "tgn:7000084",
        "tgn:7029392"
    ],
    "tgn:id":7072374,
    "tgn:name":"Thandorf",
    "tgn:placetype":[
        "aat:300008347"
    ]
},
  "bbox": [],
  "geometry": {"coordinates":[10.816667,53.766667],"type":"Point"}
}