{
  "id": 2557672,
  "type": "Feature",
  "properties": {
    "tgn:hierarchy":[
        "tgn:2557672",
        "tgn:1000001",
        "tgn:2001418",
        "tgn:7012149",
        "tgn:7007526",
        "tgn:7029392"
    ],
    "tgn:id":2557672,
    "tgn:name":"Old Reveille",
    "tgn:placetype":[
        "aat:300008347"
    ]
},
  "bbox": [],
  "geometry": {"coordinates":[-116.1667,38.0333],"type":"Point"}
}