{
  "id": 1029769,
  "type": "Feature",
  "properties": {
    "tgn:hierarchy":[
        "tgn:1029769",
        "tgn:7002445",
        "tgn:7008104",
        "tgn:1000003",
        "tgn:7008591",
        "tgn:7029392"
    ],
    "tgn:id":1029769,
    "tgn:name":"Knotty Green",
    "tgn:placetype":[
        "aat:300008347"
    ]
},
  "bbox": [],
  "geometry": {"coordinates":[-0.65,51.6167],"type":"Point"}
}