{
  "id": 2202802,
  "type": "Feature",
  "properties": {
    "tgn:hierarchy":[
        "tgn:2202802",
        "tgn:1000001",
        "tgn:7012149",
        "tgn:2001614",
        "tgn:7007706",
        "tgn:7029392"
    ],
    "tgn:id":2202802,
    "tgn:name":"Buckeye",
    "tgn:placetype":[
        "aat:300008347"
    ]
},
  "bbox": [],
  "geometry": {"coordinates":[-82.45,39.05],"type":"Point"}
}