{
  "id": 7036428,
  "type": "Feature",
  "properties": {
    "tgn:hierarchy":[
        "tgn:7036428",
        "tgn:1003459",
        "tgn:1000003",
        "tgn:7002993",
        "tgn:1000080",
        "tgn:7029392"
    ],
    "tgn:id":7036428,
    "tgn:name":"Vermegliano",
    "tgn:placetype":[
        "aat:300008347"
    ]
},
  "bbox": [],
  "geometry": {"coordinates":[13.5125,45.835278],"type":"Point"}
}