{
  "id": 2541592,
  "type": "Feature",
  "properties": {
    "tgn:hierarchy":[
        "tgn:2541592",
        "tgn:7006450",
        "tgn:1000001",
        "tgn:2124012",
        "tgn:7012149",
        "tgn:7029392"
    ],
    "tgn:id":2541592,
    "tgn:name":"Ninagiak Island",
    "tgn:placetype":[
        "aat:300008791"
    ]
},
  "bbox": [],
  "geometry": {"coordinates":[-153.9833,58.45],"type":"Point"}
}