{
  "id": 7368360,
  "type": "Feature",
  "properties": {
    "tgn:hierarchy":[
        "tgn:7368360",
        "tgn:1000001",
        "tgn:1001937",
        "tgn:7005560",
        "tgn:7029392"
    ],
    "tgn:id":7368360,
    "tgn:name":"Inna, Punta",
    "tgn:placetype":[
        "aat:300386846"
    ]
},
  "bbox": [],
  "geometry": {"coordinates":[-87.133333,20.566667],"type":"Point"}
}