{
  "id": 7304160,
  "type": "Feature",
  "properties": {
    "tgn:hierarchy":[
        "tgn:7304160",
        "tgn:7002810",
        "tgn:7001158",
        "tgn:1000003",
        "tgn:1000095",
        "tgn:7029392"
    ],
    "tgn:id":7304160,
    "tgn:name":"Marauri",
    "tgn:placetype":[
        "aat:300008347"
    ]
},
  "bbox": [],
  "geometry": {"coordinates":[-2.641391,42.7226],"type":"Point"}
}