{
  "id": 7057590,
  "type": "Feature",
  "properties": {
    "tgn:hierarchy":[
        "tgn:7057590",
        "tgn:7015163",
        "tgn:1000003",
        "tgn:7003121",
        "tgn:1000080",
        "tgn:7029392"
    ],
    "tgn:id":7057590,
    "tgn:name":"Aspiddarzu, Punta de s'",
    "tgn:placetype":[
        "aat:300008795"
    ]
},
  "bbox": [],
  "geometry": {"coordinates":[8.983333,40.366667],"type":"Point"}
}