{
  "id": 2622894,
  "type": "Feature",
  "properties": {
    "tgn:hierarchy":[
        "tgn:2622894",
        "tgn:7002659",
        "tgn:1000001",
        "tgn:2000013",
        "tgn:7012149",
        "tgn:7029392"
    ],
    "tgn:id":2622894,
    "tgn:name":"Robinson Prospect",
    "tgn:placetype":[
        "aat:300000390"
    ]
},
  "bbox": [],
  "geometry": {"coordinates":[-85.8167,33.35],"type":"Point"}
}