{
  "id": 7499996,
  "type": "Feature",
  "properties": {
    "tgn:hierarchy":[
        "tgn:7499996",
        "tgn:1000004",
        "tgn:1000959",
        "tgn:1000141",
        "tgn:7029392"
    ],
    "tgn:id":7499996,
    "tgn:name":"Guting Zhan",
    "tgn:placetype":[
        "aat:300007783"
    ]
},
  "bbox": [],
  "geometry": {"coordinates":[121.5228,25.0258],"type":"Point"}
}