{
  "id": 2525269,
  "type": "Feature",
  "properties": {
    "tgn:hierarchy":[
        "tgn:2525269",
        "tgn:1000001",
        "tgn:2002318",
        "tgn:7012149",
        "tgn:7007922",
        "tgn:7029392"
    ],
    "tgn:id":2525269,
    "tgn:name":"Morrison Creek",
    "tgn:placetype":[
        "aat:300008706"
    ]
},
  "bbox": [],
  "geometry": {"coordinates":[-91.9167,46.5833],"type":"Point"}
}