{
  "id": 7384746,
  "type": "Feature",
  "properties": {
    "tgn:hierarchy":[
        "tgn:7384746",
        "tgn:1000001",
        "tgn:7005595",
        "tgn:7005560",
        "tgn:7029392"
    ],
    "tgn:id":7384746,
    "tgn:name":"Navito",
    "tgn:placetype":[
        "aat:300008347"
    ]
},
  "bbox": [],
  "geometry": {"coordinates":[-107.341111,24.342778],"type":"Point"}
}