{
  "id": 2117887,
  "type": "Feature",
  "properties": {
    "tgn:hierarchy":[
        "tgn:2117887",
        "tgn:1000001",
        "tgn:7012149",
        "tgn:2002292",
        "tgn:7013961",
        "tgn:7029392"
    ],
    "tgn:id":2117887,
    "tgn:name":"Cornwallis",
    "tgn:placetype":[
        "aat:300008347",
        "aat:300387210"
    ]
},
  "bbox": [],
  "geometry": {"coordinates":[-81.1167,39.2167],"type":"Point"}
}