{
  "id": 2133446,
  "type": "Feature",
  "properties": {
    "tgn:hierarchy":[
        "tgn:2133446",
        "tgn:1000001",
        "tgn:7012149",
        "tgn:7007825",
        "tgn:7029392"
    ],
    "tgn:id":2133446,
    "tgn:name":"Andersons Shoals",
    "tgn:placetype":[
        "aat:300132348"
    ]
},
  "bbox": [],
  "geometry": {"coordinates":[-83.1833,36.15],"type":"Point"}
}