{
  "id": 2233867,
  "type": "Feature",
  "properties": {
    "tgn:hierarchy":[
        "tgn:2233867",
        "tgn:1000001",
        "tgn:7012149",
        "tgn:7007256",
        "tgn:7029392"
    ],
    "tgn:id":2233867,
    "tgn:name":"Chatlin Lake Canal",
    "tgn:placetype":[
        "aat:300006075"
    ]
},
  "bbox": [],
  "geometry": {"coordinates":[-92.3667,31.1667],"type":"Point"}
}