<<<<<<< HEAD
{
  "id": 7480474,
  "type": "Feature",
  "properties": {
    "tgn:hierarchy":[
        "tgn:7480474",
        "tgn:7468018",
        "tgn:1000004",
        "tgn:1000141",
        "tgn:7029392"
    ],
    "tgn:id":7480474,
    "tgn:name":"Yanbuzi",
    "tgn:placetype":[
        "aat:300008347"
    ]
},
  "bbox": [],
  "geometry": {"coordinates":[120.2323,23.4692],"type":"Point"}
}
=======
{"geometry":{"type":"Point","coordinates":[120.232300,23.469200]},"type":"Feature","properties":{"hierarchy":["tgn:7480474","tgn:7468018","tgn:1000004","tgn:1000141","tgn:7029392"],"placetype":["aat:300008347"],"id":7480474,"name:xx":"Yanbuzi"}}
>>>>>>> 03f74aca74312dbeaf24d7e61306dd6a786dc3d0
