<<<<<<< HEAD
{
  "id": 7172969,
  "type": "Feature",
  "properties": {
    "tgn:hierarchy":[
        "tgn:7172969",
        "tgn:7000096",
        "tgn:1000003",
        "tgn:7000084",
        "tgn:7029392"
    ],
    "tgn:id":7172969,
    "tgn:name":"Gro\u00df Sch\u00f6nebeck",
    "tgn:placetype":[
        "aat:300008347"
    ]
},
  "bbox": [],
  "geometry": {"coordinates":[13.516667,52.9],"type":"Point"}
}
=======
{"geometry":{"type":"Point","coordinates":[13.516667,52.900000]},"type":"Feature","properties":{"hierarchy":["tgn:7172969","tgn:7000096","tgn:1000003","tgn:7000084","tgn:7029392"],"placetype":["aat:300008347"],"id":7172969,"name:xx":"Gro\u00df Sch\u00f6nebeck"}}
>>>>>>> 03f74aca74312dbeaf24d7e61306dd6a786dc3d0
