{
  "id": 7524905,
  "type": "Feature",
  "properties": {
    "tgn:hierarchy":[
        "tgn:7524905",
        "tgn:7001242",
        "tgn:7016833",
        "tgn:1001088",
        "tgn:7029392"
    ],
    "tgn:id":7524905,
    "tgn:name:en":"Bur\u0163ub\u0101\u0163 al Jabal",
    "tgn:placetype":[
        "aat:300008347"
    ]
},
  "bbox": [],
  "geometry": {"coordinates":[30.681218,28.611793],"type":"Point"}
}