{
  "id": 2757531,
  "type": "Feature",
  "properties": {
    "tgn:hierarchy":[
        "tgn:2757531",
        "tgn:1000001",
        "tgn:7012149",
        "tgn:7007520",
        "tgn:7029392"
    ],
    "tgn:id":2757531,
    "tgn:name":"West Branch",
    "tgn:placetype":[
        "aat:300006075"
    ]
},
  "bbox": [],
  "geometry": {"coordinates":[-83.45,43.7167],"type":"Point"}
}