{
  "id": 2467654,
  "type": "Feature",
  "properties": {
    "tgn:hierarchy":[
        "tgn:2467654",
        "tgn:7002659",
        "tgn:1000001",
        "tgn:7012149",
        "tgn:2000035",
        "tgn:7029392"
    ],
    "tgn:id":2467654,
    "tgn:name":"Long Island",
    "tgn:placetype":[
        "aat:300008791"
    ]
},
  "bbox": [],
  "geometry": {"coordinates":[-85.6833,34.95],"type":"Point"}
}