<<<<<<< HEAD
{
  "id": 7481993,
  "type": "Feature",
  "properties": {
    "tgn:hierarchy":[
        "tgn:7481993",
        "tgn:1000004",
        "tgn:7490934",
        "tgn:1000141",
        "tgn:7029392"
    ],
    "tgn:id":7481993,
    "tgn:name":"Dongxing Guoxiao",
    "tgn:placetype":[
        "aat:300006495"
    ]
},
  "bbox": [],
  "geometry": {"coordinates":[120.26745,23.238885],"type":"Point"}
}
=======
{"geometry":{"type":"Point","coordinates":[120.267450,23.238885]},"type":"Feature","properties":{"hierarchy":["tgn:7481993","tgn:1000004","tgn:7490934","tgn:1000141","tgn:7029392"],"placetype":["aat:300006495"],"id":7481993,"name:xx":"Dongxing Guoxiao"}}
>>>>>>> 03f74aca74312dbeaf24d7e61306dd6a786dc3d0
