{
  "id": 1095686,
  "type": "Feature",
  "properties": {
    "tgn:hierarchy":[
        "tgn:1095686",
        "tgn:7001242",
        "tgn:7016833",
        "tgn:1001088",
        "tgn:7029392"
    ],
    "tgn:id":1095686,
    "tgn:name:en":"\u015eandaf\u0101 al F\u0101r",
    "tgn:placetype":[
        "aat:300008347"
    ]
},
  "bbox": [],
  "geometry": {"coordinates":[30.665492,28.534511],"type":"Point"}
}