{
  "id": 2584249,
  "type": "Feature",
  "properties": {
    "tgn:hierarchy":[
        "tgn:2584249",
        "tgn:1000001",
        "tgn:7012149",
        "tgn:2002129",
        "tgn:7007827",
        "tgn:7029392"
    ],
    "tgn:id":2584249,
    "tgn:name":"Pineview Reservoir",
    "tgn:placetype":[
        "aat:300006191"
    ]
},
  "bbox": [],
  "geometry": {"coordinates":[-111.8333,41.25],"type":"Point"}
}