{
  "id": 2009629,
  "type": "Feature",
  "properties": {
    "tgn:hierarchy":[
        "tgn:2009629",
        "tgn:1000001",
        "tgn:7016172",
        "tgn:7012149",
        "tgn:2000148",
        "tgn:7029392"
    ],
    "tgn:id":2009629,
    "tgn:name":"Thorney",
    "tgn:placetype":[
        "aat:300008347",
        "aat:300387210"
    ]
},
  "bbox": [],
  "geometry": {"coordinates":[-93.9167,35.9833],"type":"Point"}
}