{
  "id": 2044527,
  "type": "Feature",
  "properties": {
    "tgn:hierarchy":[
        "tgn:2044527",
        "tgn:1000001",
        "tgn:2000922",
        "tgn:7012149",
        "tgn:7007515",
        "tgn:7029392"
    ],
    "tgn:id":2044527,
    "tgn:name":"Bucksport",
    "tgn:placetype":[
        "aat:300008347"
    ]
},
  "bbox": [],
  "geometry": {"coordinates":[-68.7833,44.5667],"type":"Point"}
}