{
  "id": 2469158,
  "type": "Feature",
  "properties": {
    "tgn:hierarchy":[
        "tgn:2469158",
        "tgn:1000001",
        "tgn:2001473",
        "tgn:7012149",
        "tgn:7007709",
        "tgn:7029392"
    ],
    "tgn:id":2469158,
    "tgn:name":"Long Valley Lake",
    "tgn:placetype":[
        "aat:300006191"
    ]
},
  "bbox": [],
  "geometry": {"coordinates":[-82.5833,35.5333],"type":"Point"}
}