{
  "id": 2625811,
  "type": "Feature",
  "properties": {
    "tgn:hierarchy":[
        "tgn:2625811",
        "tgn:1000001",
        "tgn:7012149",
        "tgn:2001104",
        "tgn:7007522",
        "tgn:7029392"
    ],
    "tgn:id":2625811,
    "tgn:name":"Rocky Branch",
    "tgn:placetype":[
        "aat:300008699"
    ]
},
  "bbox": [],
  "geometry": {"coordinates":[-91.0333,31.4333],"type":"Point"}
}