{
  "id": 7454859,
  "type": "Feature",
  "properties": {
    "tgn:hierarchy":[
        "tgn:7454859",
        "tgn:5000432",
        "tgn:7002444",
        "tgn:1000003",
        "tgn:7008591",
        "tgn:7029392"
    ],
    "tgn:id":7454859,
    "tgn:name:en":"Comers",
    "tgn:placetype":[
        "aat:300008347"
    ]
},
  "bbox": [],
  "geometry": {"coordinates":[-2.533333,57.15],"type":"Point"}
}