{
  "id": 7520002,
  "type": "Feature",
  "properties": {
    "tgn:hierarchy":[
        "tgn:7520002",
        "tgn:1009227",
        "tgn:1000226",
        "tgn:1000006",
        "tgn:7016850",
        "tgn:7029392"
    ],
    "tgn:id":7520002,
    "tgn:name:en":"Baxter Creek",
    "tgn:placetype":[
        "aat:300008699"
    ]
},
  "bbox": [],
  "geometry": {"coordinates":[171.483333,-42.35],"type":"Point"}
}