<<<<<<< HEAD
{
  "id": 7246164,
  "type": "Feature",
  "properties": {
    "tgn:hierarchy":[
        "tgn:7246164",
        "tgn:7003465",
        "tgn:1000003",
        "tgn:1000063",
        "tgn:4012014",
        "tgn:7029392"
    ],
    "tgn:id":7246164,
    "tgn:name":"Devant la Het",
    "tgn:placetype":[
        "aat:300008347"
    ]
},
  "bbox": [],
  "geometry": {"coordinates":[5.283333,49.95],"type":"Point"}
}
=======
{"geometry":{"type":"Point","coordinates":[5.283333,49.950000]},"type":"Feature","properties":{"hierarchy":["tgn:7246164","tgn:7003465","tgn:1000003","tgn:1000063","tgn:4012014","tgn:7029392"],"placetype":["aat:300008347"],"id":7246164,"name:xx":"Devant la Het"}}
>>>>>>> 03f74aca74312dbeaf24d7e61306dd6a786dc3d0
