{
  "id": 2343151,
  "type": "Feature",
  "properties": {
    "tgn:hierarchy":[
        "tgn:2343151",
        "tgn:1000001",
        "tgn:7012149",
        "tgn:2000183",
        "tgn:7007157",
        "tgn:7029392"
    ],
    "tgn:id":2343151,
    "tgn:name":"Gable Lakes",
    "tgn:placetype":[
        "aat:300008680"
    ]
},
  "bbox": [],
  "geometry": {"coordinates":[-118.6833,37.3167],"type":"Point"}
}