{
  "id": 7496859,
  "type": "Feature",
  "properties": {
    "tgn:hierarchy":[
        "tgn:7496859",
        "tgn:7001004",
        "tgn:1000004",
        "tgn:1000141",
        "tgn:7029392"
    ],
    "tgn:id":7496859,
    "tgn:name":"Min'an Qiao",
    "tgn:placetype":[
        "aat:300007836"
    ]
},
  "bbox": [],
  "geometry": {"coordinates":[120.352857,22.590738],"type":"Point"}
}