{
  "id": 2068169,
  "type": "Feature",
  "properties": {
    "tgn:hierarchy":[
        "tgn:2068169",
        "tgn:1000001",
        "tgn:7012149",
        "tgn:1002593",
        "tgn:7007568",
        "tgn:7029392"
    ],
    "tgn:id":2068169,
    "tgn:name":"Brantingham",
    "tgn:placetype":[
        "aat:300008347"
    ]
},
  "bbox": [],
  "geometry": {"coordinates":[-75.2833,43.6833],"type":"Point"}
}