{
  "id": 7215475,
  "type": "Feature",
  "properties": {
    "tgn:hierarchy":[
        "tgn:7215475",
        "tgn:7003669",
        "tgn:1000003",
        "tgn:7000084",
        "tgn:7029392"
    ],
    "tgn:id":7215475,
    "tgn:name":"Albertshofen",
    "tgn:placetype":[
        "aat:300008347"
    ]
},
  "bbox": [],
  "geometry": {"coordinates":[11.666667,49.033333],"type":"Point"}
}