{
  "id": 2352389,
  "type": "Feature",
  "properties": {
    "tgn:hierarchy":[
        "tgn:2352389",
        "tgn:1000001",
        "tgn:7012149",
        "tgn:7007157",
        "tgn:1002864",
        "tgn:7029392"
    ],
    "tgn:id":2352389,
    "tgn:name":"Goat Hill",
    "tgn:placetype":[
        "aat:300008798"
    ]
},
  "bbox": [],
  "geometry": {"coordinates":[-122.3167,37.2667],"type":"Point"}
}