{
  "id": 2407455,
  "type": "Feature",
  "properties": {
    "tgn:hierarchy":[
        "tgn:2407455",
        "tgn:1000001",
        "tgn:2001417",
        "tgn:7012149",
        "tgn:7007526",
        "tgn:7029392"
    ],
    "tgn:id":2407455,
    "tgn:name":"Huntoon Valley",
    "tgn:placetype":[
        "aat:300386845"
    ]
},
  "bbox": [],
  "geometry": {"coordinates":[-118.5333,38.1333],"type":"Point"}
}