<<<<<<< HEAD
{
  "id": 7176676,
  "type": "Feature",
  "properties": {
    "tgn:hierarchy":[
        "tgn:7176676",
        "tgn:1000003",
        "tgn:7003688",
        "tgn:7000084",
        "tgn:7029392"
    ],
    "tgn:id":7176676,
    "tgn:name":"Halloh",
    "tgn:placetype":[
        "aat:300008347"
    ]
},
  "bbox": [],
  "geometry": {"coordinates":[10.033333,53.966667],"type":"Point"}
}
=======
{"geometry":{"type":"Point","coordinates":[10.033333,53.966667]},"type":"Feature","properties":{"hierarchy":["tgn:7176676","tgn:1000003","tgn:7003688","tgn:7000084","tgn:7029392"],"placetype":["aat:300008347"],"id":7176676,"name:xx":"Halloh"}}
>>>>>>> 03f74aca74312dbeaf24d7e61306dd6a786dc3d0
