{
  "id": 2251578,
  "type": "Feature",
  "properties": {
    "tgn:hierarchy":[
        "tgn:2251578",
        "tgn:1000001",
        "tgn:1002479",
        "tgn:7012149",
        "tgn:7007240",
        "tgn:7029392"
    ],
    "tgn:id":2251578,
    "tgn:name":"Commston Lake",
    "tgn:placetype":[
        "aat:300008680"
    ]
},
  "bbox": [],
  "geometry": {"coordinates":[-82.45,28.1333],"type":"Point"}
}