{
  "id": 1076171,
  "type": "Feature",
  "properties": {
    "tgn:hierarchy":[
        "tgn:1076171",
        "tgn:1000004",
        "tgn:7000198",
        "tgn:1001894",
        "tgn:7029392"
    ],
    "tgn:id":1076171,
    "tgn:name:en":"Mandsaur",
    "tgn:placetype":[
        "aat:300008347"
    ]
},
  "bbox": [],
  "geometry": {"coordinates":[75.06986,24.071841],"type":"Point"}
}