{
  "id": 7503396,
  "type": "Feature",
  "properties": {
    "tgn:hierarchy":[
        "tgn:7503396",
        "tgn:1000004",
        "tgn:7491221",
        "tgn:1000141",
        "tgn:7029392"
    ],
    "tgn:id":7503396,
    "tgn:name":"Foyuan Chansi",
    "tgn:placetype":[
        "aat:300007595"
    ]
},
  "bbox": [],
  "geometry": {"coordinates":[121.155278,23.076944],"type":"Point"}
}