{
  "id": 7034363,
  "type": "Feature",
  "properties": {
    "tgn:hierarchy":[
        "tgn:7034363",
        "tgn:1001641",
        "tgn:1000003",
        "tgn:7003121",
        "tgn:1000080",
        "tgn:7029392"
    ],
    "tgn:id":7034363,
    "tgn:name":"Burroni, Cala",
    "tgn:placetype":[
        "aat:300132317"
    ]
},
  "bbox": [],
  "geometry": {"coordinates":[9.513611,39.098889],"type":"Point"}
}