{
  "id": 7563947,
  "type": "Feature",
  "properties": {
    "tgn:hierarchy":[
        "tgn:7563947",
        "tgn:1000004",
        "tgn:7000198",
        "tgn:7016722",
        "tgn:7029392"
    ],
    "tgn:id":7563947,
    "tgn:name:en":"Madhpuri",
    "tgn:placetype":[
        "aat:300008347"
    ]
},
  "bbox": [],
  "geometry": {"coordinates":[79.598441,26.9854],"type":"Point"}
}