{
  "id": 2653508,
  "type": "Feature",
  "properties": {
    "tgn:hierarchy":[
        "tgn:2653508",
        "tgn:1000001",
        "tgn:2000461",
        "tgn:7012149",
        "tgn:7007250",
        "tgn:7029392"
    ],
    "tgn:id":2653508,
    "tgn:name":"Seventeenmile Cave",
    "tgn:placetype":[
        "aat:300008746"
    ]
},
  "bbox": [],
  "geometry": {"coordinates":[-112.35,43.5333],"type":"Point"}
}