{
  "id": 2630093,
  "type": "Feature",
  "properties": {
    "tgn:hierarchy":[
        "tgn:2630093",
        "tgn:1000001",
        "tgn:2001353",
        "tgn:7012149",
        "tgn:7007525",
        "tgn:7029392"
    ],
    "tgn:id":2630093,
    "tgn:name":"Rothwell Valley",
    "tgn:placetype":[
        "aat:300386845"
    ]
},
  "bbox": [],
  "geometry": {"coordinates":[-101.7333,41.7667],"type":"Point"}
}