{
  "id": 1029202,
  "type": "Feature",
  "properties": {
    "tgn:hierarchy":[
        "tgn:1029202",
        "tgn:7002445",
        "tgn:1000003",
        "tgn:7008153",
        "tgn:7008591",
        "tgn:7029392"
    ],
    "tgn:id":1029202,
    "tgn:name":"Eyhorne Street",
    "tgn:placetype":[
        "aat:300008347"
    ]
},
  "bbox": [],
  "geometry": {"coordinates":[0.6333,51.2667],"type":"Point"}
}