{
  "id": 7229251,
  "type": "Feature",
  "properties": {
    "tgn:hierarchy":[
        "tgn:7229251",
        "tgn:7002690",
        "tgn:7012056",
        "tgn:1000003",
        "tgn:1000074",
        "tgn:7029392"
    ],
    "tgn:id":7229251,
    "tgn:name":"Fter\u00f3lakas",
    "tgn:placetype":[
        "aat:300008347"
    ]
},
  "bbox": [],
  "geometry": {"coordinates":[23.633333,35.466667],"type":"Point"}
}