{
  "id": 7231447,
  "type": "Feature",
  "properties": {
    "tgn:hierarchy":[
        "tgn:7231447",
        "tgn:7002735",
        "tgn:7017076",
        "tgn:1000003",
        "tgn:1000074",
        "tgn:7029392"
    ],
    "tgn:id":7231447,
    "tgn:name":"Marath\u00e9as, R\u00e1khi",
    "tgn:placetype":[
        "aat:300266640"
    ]
},
  "bbox": [],
  "geometry": {"coordinates":[22.483333,36.733333],"type":"Point"}
}