<<<<<<< HEAD
{
  "id": 7111718,
  "type": "Feature",
  "properties": {
    "tgn:hierarchy":[
        "tgn:7111718",
        "tgn:1000003",
        "tgn:7003677",
        "tgn:7000084",
        "tgn:7029392"
    ],
    "tgn:id":7111718,
    "tgn:name":"Rosskothen",
    "tgn:placetype":[
        "aat:300000206"
    ]
},
  "bbox": [],
  "geometry": {"coordinates":[6.933333,51.4],"type":"Point"}
}
=======
{"geometry":{"type":"Point","coordinates":[6.933333,51.400000]},"type":"Feature","properties":{"hierarchy":["tgn:7111718","tgn:1000003","tgn:7003677","tgn:7000084","tgn:7029392"],"placetype":["aat:300000206"],"id":7111718,"name:xx":"Rosskothen"}}
>>>>>>> 03f74aca74312dbeaf24d7e61306dd6a786dc3d0
