{
  "id": 1122316,
  "type": "Feature",
  "properties": {
    "tgn:hierarchy":[
        "tgn:1122316",
        "tgn:7005685",
        "tgn:1000001",
        "tgn:7024197",
        "tgn:7029392"
    ],
    "tgn:id":1122316,
    "tgn:name":"Burnside",
    "tgn:placetype":[
        "aat:300008707"
    ]
},
  "bbox": [],
  "geometry": {"coordinates":[-108.0667,66.85],"type":"Point"}
}