{
  "id": 2617546,
  "type": "Feature",
  "properties": {
    "tgn:hierarchy":[
        "tgn:2617546",
        "tgn:1002176",
        "tgn:1000001",
        "tgn:7012149",
        "tgn:7007828",
        "tgn:7029392"
    ],
    "tgn:id":2617546,
    "tgn:name":"Richville",
    "tgn:placetype":[
        "aat:300008347"
    ]
},
  "bbox": [],
  "geometry": {"coordinates":[-73.05,43.15],"type":"Point"}
}