{
  "id": 2375936,
  "type": "Feature",
  "properties": {
    "tgn:hierarchy":[
        "tgn:2375936",
        "tgn:1000001",
        "tgn:7012149",
        "tgn:7007825",
        "tgn:7029392"
    ],
    "tgn:id":2375936,
    "tgn:name":"Happy Valley",
    "tgn:placetype":[
        "aat:300008761"
    ]
},
  "bbox": [],
  "geometry": {"coordinates":[-82.6667,36.2833],"type":"Point"}
}