{
  "id": 7568322,
  "type": "Feature",
  "properties": {
    "tgn:hierarchy":[
        "tgn:7568322",
        "tgn:1000004",
        "tgn:7000198",
        "tgn:1001996",
        "tgn:7029392"
    ],
    "tgn:id":7568322,
    "tgn:name:en":"Kothi Protected Forest",
    "tgn:placetype":[
        "aat:300008863"
    ]
},
  "bbox": [],
  "geometry": {"coordinates":[77.008611,31.171944],"type":"Point"}
}