{
  "id": 7582883,
  "type": "Feature",
  "properties": {
    "tgn:hierarchy":[
        "tgn:7582883",
        "tgn:1000004",
        "tgn:1001871",
        "tgn:7000198",
        "tgn:7029392"
    ],
    "tgn:id":7582883,
    "tgn:name:en":"Jharauli Khurd",
    "tgn:placetype":[
        "aat:300008347"
    ]
},
  "bbox": [],
  "geometry": {"coordinates":[76.784284,30.147923],"type":"Point"}
}