{
  "id": 7564775,
  "type": "Feature",
  "properties": {
    "tgn:hierarchy":[
        "tgn:7564775",
        "tgn:1000004",
        "tgn:7000198",
        "tgn:7016722",
        "tgn:7029392"
    ],
    "tgn:id":7564775,
    "tgn:name:en":"R\u0101jpura M\u0101dhogarh",
    "tgn:placetype":[
        "aat:300008347"
    ]
},
  "bbox": [],
  "geometry": {"coordinates":[79.301002,26.254277],"type":"Point"}
}