<<<<<<< HEAD
{
  "id": 2768372,
  "type": "Feature",
  "properties": {
    "tgn:hierarchy":[
        "tgn:2768372",
        "tgn:7006450",
        "tgn:1000001",
        "tgn:7012149",
        "tgn:2124002",
        "tgn:7029392"
    ],
    "tgn:id":2768372,
    "tgn:name":"Whitestone Cove",
    "tgn:placetype":[
        "aat:300132316"
    ]
},
  "bbox": [],
  "geometry": {"coordinates":[-135.55,57.2333],"type":"Point"}
}
=======
{"geometry":{"type":"Point","coordinates":[-135.550000,57.233300]},"type":"Feature","properties":{"hierarchy":["tgn:2768372","tgn:7006450","tgn:1000001","tgn:7012149","tgn:2124002","tgn:7029392"],"placetype":["aat:300132316"],"id":2768372,"name:xx":"Whitestone Cove"}}
>>>>>>> 03f74aca74312dbeaf24d7e61306dd6a786dc3d0
