{
  "id": 2268749,
  "type": "Feature",
  "properties": {
    "tgn:hierarchy":[
        "tgn:2268749",
        "tgn:1000001",
        "tgn:7012149",
        "tgn:1002999",
        "tgn:7007526",
        "tgn:7029392"
    ],
    "tgn:id":2268749,
    "tgn:name":"Cross Fence Spring",
    "tgn:placetype":[
        "aat:300008697"
    ]
},
  "bbox": [],
  "geometry": {"coordinates":[-119.6833,40.8667],"type":"Point"}
}