{
  "id": 1116863,
  "type": "Feature",
  "properties": {
    "tgn:hierarchy":[
        "tgn:1116863",
        "tgn:7005685",
        "tgn:1000001",
        "tgn:7005734",
        "tgn:7029392"
    ],
    "tgn:id":1116863,
    "tgn:name":"Kiski Lake",
    "tgn:placetype":[
        "aat:300008680"
    ]
},
  "bbox": [],
  "geometry": {"coordinates":[-98.9167,54.7667],"type":"Point"}
}