{
  "id": 7485934,
  "type": "Feature",
  "properties": {
    "tgn:hierarchy":[
        "tgn:7485934",
        "tgn:7488858",
        "tgn:1000004",
        "tgn:1000141",
        "tgn:7029392"
    ],
    "tgn:id":7485934,
    "tgn:name":"Gecaiyuan Yihao Qiao",
    "tgn:placetype":[
        "aat:300007836"
    ]
},
  "bbox": [],
  "geometry": {"coordinates":[120.646389,23.6425],"type":"Point"}
}