<<<<<<< HEAD
{
  "id": 7022187,
  "type": "Feature",
  "properties": {
    "tgn:hierarchy":[
        "tgn:7022187",
        "tgn:1000001",
        "tgn:7012149",
        "tgn:2001449",
        "tgn:7007566",
        "tgn:7029392"
    ],
    "tgn:id":7022187,
    "tgn:name":"Jicarilla Apache Indian Reservation",
    "tgn:placetype":[
        "aat:300008347",
        "aat:300387324"
    ]
},
  "bbox": [],
  "geometry": {"coordinates":[-107.0,36.6667],"type":"Point"}
}
=======
{"geometry":{"type":"Point","coordinates":[-107.000000,36.666700]},"type":"Feature","properties":{"hierarchy":["tgn:7022187","tgn:1000001","tgn:7012149","tgn:2001449","tgn:7007566","tgn:7029392"],"placetype":["aat:300008347","aat:300387324"],"id":7022187,"name:xx":"Jicarilla Apache Indian Reservation"}}
>>>>>>> 03f74aca74312dbeaf24d7e61306dd6a786dc3d0
