{
  "id": 7238520,
  "type": "Feature",
  "properties": {
    "tgn:hierarchy":[
        "tgn:7238520",
        "tgn:7003460",
        "tgn:1000003",
        "tgn:1000063",
        "tgn:4012014",
        "tgn:7029392"
    ],
    "tgn:id":7238520,
    "tgn:name":"Harz\u00e9",
    "tgn:placetype":[
        "aat:300008347"
    ]
},
  "bbox": [],
  "geometry": {"coordinates":[5.666667,50.433333],"type":"Point"}
}