{
  "id": 7256719,
  "type": "Feature",
  "properties": {
    "tgn:hierarchy":[
        "tgn:7256719",
        "tgn:7593113",
        "tgn:7016620",
        "tgn:7593112",
        "tgn:1000001",
        "tgn:7029392"
    ],
    "tgn:id":7256719,
    "tgn:name:nl":"Chikitu, Playa",
    "tgn:placetype":[
        "aat:300132317"
    ]
},
  "bbox": [],
  "geometry": {"coordinates":[-68.333333,12.283333],"type":"Point"}
}