{
  "id": 2578557,
  "type": "Feature",
  "properties": {
    "tgn:hierarchy":[
        "tgn:2578557",
        "tgn:1000001",
        "tgn:7012149",
        "tgn:2000379",
        "tgn:7007248",
        "tgn:7029392"
    ],
    "tgn:id":2578557,
    "tgn:name":"Philema Branch",
    "tgn:placetype":[
        "aat:300008699"
    ]
},
  "bbox": [],
  "geometry": {"coordinates":[-84.05,31.75],"type":"Point"}
}