{
  "id": 2724130,
  "type": "Feature",
  "properties": {
    "tgn:hierarchy":[
        "tgn:2724130",
        "tgn:1000001",
        "tgn:7012149",
        "tgn:7007157",
        "tgn:1002608",
        "tgn:7029392"
    ],
    "tgn:id":2724130,
    "tgn:name":"Toluca Lake",
    "tgn:placetype":[
        "aat:300008680"
    ]
},
  "bbox": [],
  "geometry": {"coordinates":[-118.3333,34.1333],"type":"Point"}
}