<<<<<<< HEAD
{
  "id": 2257853,
  "type": "Feature",
  "properties": {
    "tgn:hierarchy":[
        "tgn:2257853",
        "tgn:1000001",
        "tgn:7012149",
        "tgn:2001453",
        "tgn:7007566",
        "tgn:7029392"
    ],
    "tgn:id":2257853,
    "tgn:name":"Corrales Spring",
    "tgn:placetype":[
        "aat:300008697"
    ]
},
  "bbox": [],
  "geometry": {"coordinates":[-105.5333,35.5667],"type":"Point"}
}
=======
{"geometry":{"type":"Point","coordinates":[-105.533300,35.566700]},"type":"Feature","properties":{"hierarchy":["tgn:2257853","tgn:1000001","tgn:7012149","tgn:2001453","tgn:7007566","tgn:7029392"],"placetype":["aat:300008697"],"id":2257853,"name:xx":"Corrales Spring"}}
>>>>>>> 03f74aca74312dbeaf24d7e61306dd6a786dc3d0
