{
  "id": 2441092,
  "type": "Feature",
  "properties": {
    "tgn:hierarchy":[
        "tgn:2441092",
        "tgn:1000001",
        "tgn:7012149",
        "tgn:2002114",
        "tgn:7007827",
        "tgn:7029392"
    ],
    "tgn:id":2441092,
    "tgn:name":"Knoll Hollow",
    "tgn:placetype":[
        "aat:300008761"
    ]
},
  "bbox": [],
  "geometry": {"coordinates":[-112.2333,39.3833],"type":"Point"}
}