{
  "id": 2119958,
  "type": "Feature",
  "properties": {
    "tgn:hierarchy":[
        "tgn:2119958",
        "tgn:1000001",
        "tgn:7012149",
        "tgn:2002273",
        "tgn:7013961",
        "tgn:7029392"
    ],
    "tgn:id":2119958,
    "tgn:name":"Shively",
    "tgn:placetype":[
        "aat:300008347"
    ]
},
  "bbox": [],
  "geometry": {"coordinates":[-82.1167,37.95],"type":"Point"}
}