{
  "id": 2269318,
  "type": "Feature",
  "properties": {
    "tgn:hierarchy":[
        "tgn:2269318",
        "tgn:1000001",
        "tgn:2001703",
        "tgn:7012149",
        "tgn:7007708",
        "tgn:7029392"
    ],
    "tgn:id":2269318,
    "tgn:name":"Crow Foot Springs",
    "tgn:placetype":[
        "aat:300008697"
    ]
},
  "bbox": [],
  "geometry": {"coordinates":[-121.7833,44.2833],"type":"Point"}
}