<<<<<<< HEAD
{
  "id": 2257500,
  "type": "Feature",
  "properties": {
    "tgn:hierarchy":[
        "tgn:2257500",
        "tgn:1000001",
        "tgn:7012149",
        "tgn:7007157",
        "tgn:7014475",
        "tgn:7029392"
    ],
    "tgn:id":2257500,
    "tgn:name":"Corporal",
    "tgn:placetype":[
        "aat:300008347"
    ]
},
  "bbox": [],
  "geometry": {"coordinates":[-121.5333,36.9167],"type":"Point"}
}
=======
{"geometry":{"type":"Point","coordinates":[-121.533300,36.916700]},"type":"Feature","properties":{"hierarchy":["tgn:2257500","tgn:1000001","tgn:7012149","tgn:7007157","tgn:7014475","tgn:7029392"],"placetype":["aat:300008347"],"id":2257500,"name:xx":"Corporal"}}
>>>>>>> 03f74aca74312dbeaf24d7e61306dd6a786dc3d0
