{
  "id": 7517096,
  "type": "Feature",
  "properties": {
    "tgn:hierarchy":[
        "tgn:7517096",
        "tgn:1008380",
        "tgn:1000226",
        "tgn:7016827",
        "tgn:1000006",
        "tgn:7029392"
    ],
    "tgn:id":7517096,
    "tgn:name:en":"Mangamaio Stream",
    "tgn:placetype":[
        "aat:300008699"
    ]
},
  "bbox": [],
  "geometry": {"coordinates":[174.466667,-38.95],"type":"Point"}
}