{
  "id": 2331914,
  "type": "Feature",
  "properties": {
    "tgn:hierarchy":[
        "tgn:2331914",
        "tgn:1000001",
        "tgn:7012149",
        "tgn:2000933",
        "tgn:7007515",
        "tgn:7029392"
    ],
    "tgn:id":2331914,
    "tgn:name":"Fletcher Neck",
    "tgn:placetype":[
        "aat:300008850"
    ]
},
  "bbox": [],
  "geometry": {"coordinates":[-70.35,43.4333],"type":"Point"}
}