{
  "id": 2679164,
  "type": "Feature",
  "properties": {
    "tgn:hierarchy":[
        "tgn:2679164",
        "tgn:7006450",
        "tgn:1000001",
        "tgn:7012149",
        "tgn:2000085",
        "tgn:7029392"
    ],
    "tgn:id":2679164,
    "tgn:name":"South Fork Ladue River",
    "tgn:placetype":[
        "aat:300008707"
    ]
},
  "bbox": [],
  "geometry": {"coordinates":[-141.8667,63.1167],"type":"Point"}
}