{
  "id": 7299682,
  "type": "Feature",
  "properties": {
    "tgn:hierarchy":[
        "tgn:7299682",
        "tgn:7002849",
        "tgn:1000003",
        "tgn:7009604",
        "tgn:1000095",
        "tgn:7029392"
    ],
    "tgn:id":7299682,
    "tgn:name":"Ugarte de M\u00fagica",
    "tgn:placetype":[
        "aat:300008347"
    ]
},
  "bbox": [],
  "geometry": {"coordinates":[-2.708659,43.292768],"type":"Point"}
}