{
  "id": 7100210,
  "type": "Feature",
  "properties": {
    "tgn:hierarchy":[
        "tgn:7100210",
        "tgn:1000003",
        "tgn:7003685",
        "tgn:7000084",
        "tgn:7029392"
    ],
    "tgn:id":7100210,
    "tgn:name":"Rote Jahne",
    "tgn:placetype":[
        "aat:300008347"
    ]
},
  "bbox": [],
  "geometry": {"coordinates":[12.666667,51.516667],"type":"Point"}
}