{
  "id": 7545926,
  "type": "Feature",
  "properties": {
    "tgn:hierarchy":[
        "tgn:7545926",
        "tgn:1000004",
        "tgn:7000198",
        "tgn:1001895",
        "tgn:7029392"
    ],
    "tgn:id":7545926,
    "tgn:name:en":"B\u0101hre",
    "tgn:placetype":[
        "aat:300008347"
    ]
},
  "bbox": [],
  "geometry": {"coordinates":[73.516667,20.45],"type":"Point"}
}