{
  "id": 7440267,
  "type": "Feature",
  "properties": {
    "tgn:hierarchy":[
        "tgn:7440267",
        "tgn:1000001",
        "tgn:7005591",
        "tgn:7005560",
        "tgn:7029392"
    ],
    "tgn:id":7440267,
    "tgn:name":"Santa Catarina Quian\u00e9",
    "tgn:placetype":[
        "aat:300008347"
    ]
},
  "bbox": [],
  "geometry": {"coordinates":[-96.733333,16.883333],"type":"Point"}
}