{
  "id": 2408035,
  "type": "Feature",
  "properties": {
    "tgn:hierarchy":[
        "tgn:2408035",
        "tgn:1000001",
        "tgn:7012149",
        "tgn:2002273",
        "tgn:7013961",
        "tgn:7029392"
    ],
    "tgn:id":2408035,
    "tgn:name":"Hurricane Fork",
    "tgn:placetype":[
        "aat:300008699"
    ]
},
  "bbox": [],
  "geometry": {"coordinates":[-82.0333,37.9333],"type":"Point"}
}