<<<<<<< HEAD
{
  "id": 2408035,
  "type": "Feature",
  "properties": {
    "tgn:hierarchy":[
        "tgn:2408035",
        "tgn:1000001",
        "tgn:7012149",
        "tgn:2002273",
        "tgn:7013961",
        "tgn:7029392"
    ],
    "tgn:id":2408035,
    "tgn:name":"Hurricane Fork",
    "tgn:placetype":[
        "aat:300008699"
    ]
},
  "bbox": [],
  "geometry": {"coordinates":[-82.0333,37.9333],"type":"Point"}
}
=======
{"geometry":{"type":"Point","coordinates":[-82.033300,37.933300]},"type":"Feature","properties":{"hierarchy":["tgn:2408035","tgn:1000001","tgn:7012149","tgn:2002273","tgn:7013961","tgn:7029392"],"placetype":["aat:300008699"],"id":2408035,"name:xx":"Hurricane Fork"}}
>>>>>>> 03f74aca74312dbeaf24d7e61306dd6a786dc3d0
