{
  "id": 7383882,
  "type": "Feature",
  "properties": {
    "tgn:hierarchy":[
        "tgn:7383882",
        "tgn:7005586",
        "tgn:1000001",
        "tgn:7005560",
        "tgn:7029392"
    ],
    "tgn:id":7383882,
    "tgn:name":"Pabelo",
    "tgn:placetype":[
        "aat:300008347"
    ]
},
  "bbox": [],
  "geometry": {"coordinates":[-104.616667,19.883333],"type":"Point"}
}