{
  "id": 7035196,
  "type": "Feature",
  "properties": {
    "tgn:hierarchy":[
        "tgn:7035196",
        "tgn:1003506",
        "tgn:1000003",
        "tgn:7002993",
        "tgn:1000080",
        "tgn:7029392"
    ],
    "tgn:id":7035196,
    "tgn:name":"Spiz, Monte",
    "tgn:placetype":[
        "aat:300008795"
    ]
},
  "bbox": [],
  "geometry": {"coordinates":[13.236389,46.373889],"type":"Point"}
}