<<<<<<< HEAD
{
  "id": 7475339,
  "type": "Feature",
  "properties": {
    "tgn:hierarchy":[
        "tgn:7475339",
        "tgn:1000004",
        "tgn:7001014",
        "tgn:1000141",
        "tgn:7029392"
    ],
    "tgn:id":7475339,
    "tgn:name":"Caicuo",
    "tgn:placetype":[
        "aat:300008347"
    ]
},
  "bbox": [],
  "geometry": {"coordinates":[120.219444,23.61],"type":"Point"}
}
=======
{"geometry":{"type":"Point","coordinates":[120.219444,23.610000]},"type":"Feature","properties":{"hierarchy":["tgn:7475339","tgn:1000004","tgn:7001014","tgn:1000141","tgn:7029392"],"placetype":["aat:300008347"],"id":7475339,"name:xx":"Caicuo"}}
>>>>>>> 03f74aca74312dbeaf24d7e61306dd6a786dc3d0
