{
  "id": 7475339,
  "type": "Feature",
  "properties": {
    "tgn:hierarchy":[
        "tgn:7475339",
        "tgn:1000004",
        "tgn:7001014",
        "tgn:1000141",
        "tgn:7029392"
    ],
    "tgn:id":7475339,
    "tgn:name":"Caicuo",
    "tgn:placetype":[
        "aat:300008347"
    ]
},
  "bbox": [],
  "geometry": {"coordinates":[120.219444,23.61],"type":"Point"}
}