{
  "id": 7307912,
  "type": "Feature",
  "properties": {
    "tgn:hierarchy":[
        "tgn:7307912",
        "tgn:1001699",
        "tgn:1000049",
        "tgn:1000002",
        "tgn:7029392"
    ],
    "tgn:id":7307912,
    "tgn:name":"Negra, Cordillera",
    "tgn:placetype":[
        "aat:300008795"
    ]
},
  "bbox": [],
  "geometry": {"coordinates":[-71.933333,-40.366667],"type":"Point"}
}