{
  "id": 2290511,
  "type": "Feature",
  "properties": {
    "tgn:hierarchy":[
        "tgn:2290511",
        "tgn:1000001",
        "tgn:7012149",
        "tgn:2000481",
        "tgn:7007250",
        "tgn:7029392"
    ],
    "tgn:id":2290511,
    "tgn:name":"Doe Lake",
    "tgn:placetype":[
        "aat:300008680"
    ]
},
  "bbox": [],
  "geometry": {"coordinates":[-114.5833,45.0833],"type":"Point"}
}