{
  "id": 7492414,
  "type": "Feature",
  "properties": {
    "tgn:hierarchy":[
        "tgn:7492414",
        "tgn:7487020",
        "tgn:1000004",
        "tgn:1000141",
        "tgn:7029392"
    ],
    "tgn:id":7492414,
    "tgn:name":"Shangan",
    "tgn:placetype":[
        "aat:300008347"
    ]
},
  "bbox": [],
  "geometry": {"coordinates":[120.672222,24.395278],"type":"Point"}
}