{
  "id": 7277230,
  "type": "Feature",
  "properties": {
    "tgn:hierarchy":[
        "tgn:7277230",
        "tgn:1001623",
        "tgn:1000049",
        "tgn:1000002",
        "tgn:7029392"
    ],
    "tgn:id":7277230,
    "tgn:name":"R\u00edo Claro Solar",
    "tgn:placetype":[
        "aat:300008699"
    ]
},
  "bbox": [],
  "geometry": {"coordinates":[-72.368611,-43.945278],"type":"Point"}
}