{
  "id": 2697095,
  "type": "Feature",
  "properties": {
    "tgn:hierarchy":[
        "tgn:2697095",
        "tgn:7019618",
        "tgn:1000001",
        "tgn:7012149",
        "tgn:7007564",
        "tgn:7029392"
    ],
    "tgn:id":2697095,
    "tgn:name":"Stony Brook",
    "tgn:placetype":[
        "aat:300008699"
    ]
},
  "bbox": [],
  "geometry": {"coordinates":[-72.0833,42.85],"type":"Point"}
}