{
  "id": 1022754,
  "type": "Feature",
  "properties": {
    "tgn:hierarchy":[
        "tgn:1022754",
        "tgn:7006246",
        "tgn:1000047",
        "tgn:7002455",
        "tgn:1000002",
        "tgn:7029392"
    ],
    "tgn:id":1022754,
    "tgn:name":"S\u00e3o Benedito do Rio Pr\u00eato",
    "tgn:placetype":[
        "aat:300008347"
    ]
},
  "bbox": [],
  "geometry": {"coordinates":[-43.5833,-3.35],"type":"Point"}
}