{
  "id": 7441837,
  "type": "Feature",
  "properties": {
    "tgn:hierarchy":[
        "tgn:7441837",
        "tgn:7002444",
        "tgn:7019088",
        "tgn:1000003",
        "tgn:7008591",
        "tgn:7029392"
    ],
    "tgn:id":7441837,
    "tgn:name:en":"Waterside",
    "tgn:placetype":[
        "aat:300008347"
    ]
},
  "bbox": [],
  "geometry": {"coordinates":[-4.483333,55.333333],"type":"Point"}
}