{
  "id": 7536609,
  "type": "Feature",
  "properties": {
    "tgn:hierarchy":[
        "tgn:7536609",
        "tgn:7001242",
        "tgn:7001311",
        "tgn:7016833",
        "tgn:7029392"
    ],
    "tgn:id":7536609,
    "tgn:name:en":"Girfa, W\u00e2d\u00ee",
    "tgn:placetype":[
        "aat:300379998"
    ]
},
  "bbox": [],
  "geometry": {"coordinates":[31.380128,28.650428],"type":"Point"}
}