{
  "id": 2642280,
  "type": "Feature",
  "properties": {
    "tgn:hierarchy":[
        "tgn:2642280",
        "tgn:1000001",
        "tgn:7006451",
        "tgn:2000092",
        "tgn:7012149",
        "tgn:7029392"
    ],
    "tgn:id":2642280,
    "tgn:name":"Sand Spring",
    "tgn:placetype":[
        "aat:300008697"
    ]
},
  "bbox": [],
  "geometry": {"coordinates":[-110.9167,36.1667],"type":"Point"}
}