{
  "id": 2707881,
  "type": "Feature",
  "properties": {
    "tgn:hierarchy":[
        "tgn:2707881",
        "tgn:1000001",
        "tgn:7012149",
        "tgn:2001830",
        "tgn:7007713",
        "tgn:7029392"
    ],
    "tgn:id":2707881,
    "tgn:name":"Swift Bear Lake",
    "tgn:placetype":[
        "aat:300008680"
    ]
},
  "bbox": [],
  "geometry": {"coordinates":[-100.8167,43.2833],"type":"Point"}
}