<<<<<<< HEAD
{
  "id": 2158461,
  "type": "Feature",
  "properties": {
    "tgn:hierarchy":[
        "tgn:2158461",
        "tgn:1000001",
        "tgn:7012149",
        "tgn:2001503",
        "tgn:7007709",
        "tgn:7029392"
    ],
    "tgn:id":2158461,
    "tgn:name":"Beaverdam Creek",
    "tgn:placetype":[
        "aat:300008706"
    ]
},
  "bbox": [],
  "geometry": {"coordinates":[-82.8167,35.6167],"type":"Point"}
}
=======
{"geometry":{"type":"Point","coordinates":[-82.816700,35.616700]},"type":"Feature","properties":{"hierarchy":["tgn:2158461","tgn:1000001","tgn:7012149","tgn:2001503","tgn:7007709","tgn:7029392"],"placetype":["aat:300008706"],"id":2158461,"name:xx":"Beaverdam Creek"}}
>>>>>>> 03f74aca74312dbeaf24d7e61306dd6a786dc3d0
