{
  "id": 2261796,
  "type": "Feature",
  "properties": {
    "tgn:hierarchy":[
        "tgn:2261796",
        "tgn:1000001",
        "tgn:7012149",
        "tgn:7007157",
        "tgn:2000186",
        "tgn:7029392"
    ],
    "tgn:id":2261796,
    "tgn:name":"Cove Spring",
    "tgn:placetype":[
        "aat:300008697"
    ]
},
  "bbox": [],
  "geometry": {"coordinates":[-121.0667,41.3167],"type":"Point"}
}