{
  "id": 7350024,
  "type": "Feature",
  "properties": {
    "tgn:hierarchy":[
        "tgn:7350024",
        "tgn:7005581",
        "tgn:1000001",
        "tgn:7005560",
        "tgn:7029392"
    ],
    "tgn:id":7350024,
    "tgn:name":"Rancho Aguilar",
    "tgn:placetype":[
        "aat:300000241"
    ]
},
  "bbox": [],
  "geometry": {"coordinates":[-108.083333,29.666667],"type":"Point"}
}