<<<<<<< HEAD
{
  "id": 7350024,
  "type": "Feature",
  "properties": {
    "tgn:hierarchy":[
        "tgn:7350024",
        "tgn:7005581",
        "tgn:1000001",
        "tgn:7005560",
        "tgn:7029392"
    ],
    "tgn:id":7350024,
    "tgn:name":"Rancho Aguilar",
    "tgn:placetype":[
        "aat:300000241"
    ]
},
  "bbox": [],
  "geometry": {"coordinates":[-108.083333,29.666667],"type":"Point"}
}
=======
{"geometry":{"type":"Point","coordinates":[-108.083333,29.666667]},"type":"Feature","properties":{"hierarchy":["tgn:7350024","tgn:7005581","tgn:1000001","tgn:7005560","tgn:7029392"],"placetype":["aat:300000241"],"id":7350024,"name:xx":"Rancho Aguilar"}}
>>>>>>> 03f74aca74312dbeaf24d7e61306dd6a786dc3d0
