<<<<<<< HEAD
{
  "id": 7242380,
  "type": "Feature",
  "properties": {
    "tgn:hierarchy":[
        "tgn:7242380",
        "tgn:7003465",
        "tgn:1000003",
        "tgn:1000063",
        "tgn:4012014",
        "tgn:7029392"
    ],
    "tgn:id":7242380,
    "tgn:name":"Lomprez",
    "tgn:placetype":[
        "aat:300008347"
    ]
},
  "bbox": [],
  "geometry": {"coordinates":[5.1,50.083333],"type":"Point"}
}
=======
{"geometry":{"type":"Point","coordinates":[5.100000,50.083333]},"type":"Feature","properties":{"hierarchy":["tgn:7242380","tgn:7003465","tgn:1000003","tgn:1000063","tgn:4012014","tgn:7029392"],"placetype":["aat:300008347"],"id":7242380,"name:xx":"Lomprez"}}
>>>>>>> 03f74aca74312dbeaf24d7e61306dd6a786dc3d0
