{
  "id": 7395291,
  "type": "Feature",
  "properties": {
    "tgn:hierarchy":[
        "tgn:7395291",
        "tgn:1000001",
        "tgn:7005597",
        "tgn:7005560",
        "tgn:7029392"
    ],
    "tgn:id":7395291,
    "tgn:name":"San Jos\u00e9 del Pasito",
    "tgn:placetype":[
        "aat:300008347"
    ]
},
  "bbox": [],
  "geometry": {"coordinates":[-98.333333,26.083333],"type":"Point"}
}