<<<<<<< HEAD
{
  "id": 2409685,
  "type": "Feature",
  "properties": {
    "tgn:hierarchy":[
        "tgn:2409685",
        "tgn:1000001",
        "tgn:2001418",
        "tgn:7012149",
        "tgn:7007526",
        "tgn:7029392"
    ],
    "tgn:id":2409685,
    "tgn:name":"Ikes Canyon",
    "tgn:placetype":[
        "aat:300008761"
    ]
},
  "bbox": [],
  "geometry": {"coordinates":[-116.7833,39.0333],"type":"Point"}
}
=======
{"geometry":{"type":"Point","coordinates":[-116.783300,39.033300]},"type":"Feature","properties":{"hierarchy":["tgn:2409685","tgn:1000001","tgn:2001418","tgn:7012149","tgn:7007526","tgn:7029392"],"placetype":["aat:300008761"],"id":2409685,"name:xx":"Ikes Canyon"}}
>>>>>>> 03f74aca74312dbeaf24d7e61306dd6a786dc3d0
