{
  "id": 7443312,
  "type": "Feature",
  "properties": {
    "tgn:hierarchy":[
        "tgn:7443312",
        "tgn:7002445",
        "tgn:1000003",
        "tgn:7008153",
        "tgn:7008591",
        "tgn:7029392"
    ],
    "tgn:id":7443312,
    "tgn:name:en":"Walpole Rocks",
    "tgn:placetype":[
        "aat:300011692"
    ]
},
  "bbox": [],
  "geometry": {"coordinates":[1.408333,51.394444],"type":"Point"}
}