{
  "id": 2433182,
  "type": "Feature",
  "properties": {
    "tgn:hierarchy":[
        "tgn:2433182",
        "tgn:7002659",
        "tgn:1000001",
        "tgn:2000008",
        "tgn:7012149",
        "tgn:7029392"
    ],
    "tgn:id":2433182,
    "tgn:name":"Kellem Hill Creek",
    "tgn:placetype":[
        "aat:300008706"
    ]
},
  "bbox": [],
  "geometry": {"coordinates":[-85.3833,32.8833],"type":"Point"}
}