{
  "id": 7112365,
  "type": "Feature",
  "properties": {
    "tgn:hierarchy":[
        "tgn:7112365",
        "tgn:1000003",
        "tgn:7003682",
        "tgn:7000084",
        "tgn:7029392"
    ],
    "tgn:id":7112365,
    "tgn:name":"Rheinecker Berg",
    "tgn:placetype":[
        "aat:300008777"
    ]
},
  "bbox": [],
  "geometry": {"coordinates":[7.316667,50.483333],"type":"Point"}
}