<<<<<<< HEAD
{
  "id": 2150630,
  "type": "Feature",
  "properties": {
    "tgn:hierarchy":[
        "tgn:2150630",
        "tgn:1000001",
        "tgn:2000920",
        "tgn:7012149",
        "tgn:7007515",
        "tgn:7029392"
    ],
    "tgn:id":2150630,
    "tgn:name":"Basket Island",
    "tgn:placetype":[
        "aat:300008791"
    ]
},
  "bbox": [],
  "geometry": {"coordinates":[-70.1667,43.7333],"type":"Point"}
}
=======
{"geometry":{"type":"Point","coordinates":[-70.166700,43.733300]},"type":"Feature","properties":{"hierarchy":["tgn:2150630","tgn:1000001","tgn:2000920","tgn:7012149","tgn:7007515","tgn:7029392"],"placetype":["aat:300008791"],"id":2150630,"name:xx":"Basket Island"}}
>>>>>>> 03f74aca74312dbeaf24d7e61306dd6a786dc3d0
