{
  "id": 2150630,
  "type": "Feature",
  "properties": {
    "tgn:hierarchy":[
        "tgn:2150630",
        "tgn:1000001",
        "tgn:2000920",
        "tgn:7012149",
        "tgn:7007515",
        "tgn:7029392"
    ],
    "tgn:id":2150630,
    "tgn:name":"Basket Island",
    "tgn:placetype":[
        "aat:300008791"
    ]
},
  "bbox": [],
  "geometry": {"coordinates":[-70.1667,43.7333],"type":"Point"}
}