{
  "id": 2191452,
  "type": "Feature",
  "properties": {
    "tgn:hierarchy":[
        "tgn:2191452",
        "tgn:1002215",
        "tgn:1000001",
        "tgn:7012149",
        "tgn:7007565",
        "tgn:7029392"
    ],
    "tgn:id":2191452,
    "tgn:name":"Braddocks Mill",
    "tgn:placetype":[
        "aat:300008347"
    ]
},
  "bbox": [],
  "geometry": {"coordinates":[-74.8333,39.8167],"type":"Point"}
}