{
  "id": 7227578,
  "type": "Feature",
  "properties": {
    "tgn:hierarchy":[
        "tgn:7227578",
        "tgn:7002725",
        "tgn:7002715",
        "tgn:1000003",
        "tgn:1000074",
        "tgn:7029392"
    ],
    "tgn:id":7227578,
    "tgn:name":"Konstandin\u00e1ton",
    "tgn:placetype":[
        "aat:300008347"
    ]
},
  "bbox": [],
  "geometry": {"coordinates":[23.55,41.016667],"type":"Point"}
}