<<<<<<< HEAD
{
  "id": 7477738,
  "type": "Feature",
  "properties": {
    "tgn:hierarchy":[
        "tgn:7477738",
        "tgn:7488858",
        "tgn:1000004",
        "tgn:1000141",
        "tgn:7029392"
    ],
    "tgn:id":7477738,
    "tgn:name":"Yufeng Guoxiao",
    "tgn:placetype":[
        "aat:300006495"
    ]
},
  "bbox": [],
  "geometry": {"coordinates":[120.838174,23.805067],"type":"Point"}
}
=======
{"geometry":{"type":"Point","coordinates":[120.838174,23.805067]},"type":"Feature","properties":{"hierarchy":["tgn:7477738","tgn:7488858","tgn:1000004","tgn:1000141","tgn:7029392"],"placetype":["aat:300006495"],"id":7477738,"name:xx":"Yufeng Guoxiao"}}
>>>>>>> 03f74aca74312dbeaf24d7e61306dd6a786dc3d0
