{
  "id": 2551658,
  "type": "Feature",
  "properties": {
    "tgn:hierarchy":[
        "tgn:2551658",
        "tgn:1000001",
        "tgn:7016172",
        "tgn:7012149",
        "tgn:2000151",
        "tgn:7029392"
    ],
    "tgn:id":2551658,
    "tgn:name":"Number 39, Ditch",
    "tgn:placetype":[
        "aat:300006075"
    ]
},
  "bbox": [],
  "geometry": {"coordinates":[-89.75,35.9333],"type":"Point"}
}