{
  "id": 7279022,
  "type": "Feature",
  "properties": {
    "tgn:hierarchy":[
        "tgn:7279022",
        "tgn:1001702",
        "tgn:1000049",
        "tgn:1000002",
        "tgn:7029392"
    ],
    "tgn:id":7279022,
    "tgn:name":"Rys, Ensenada",
    "tgn:placetype":[
        "aat:300132316"
    ]
},
  "bbox": [],
  "geometry": {"coordinates":[-72.333333,-52.533333],"type":"Point"}
}