{
  "id": 2413256,
  "type": "Feature",
  "properties": {
    "tgn:hierarchy":[
        "tgn:2413256",
        "tgn:1000001",
        "tgn:7012149",
        "tgn:2000928",
        "tgn:7007515",
        "tgn:7029392"
    ],
    "tgn:id":2413256,
    "tgn:name":"Intake Pond",
    "tgn:placetype":[
        "aat:300008680"
    ]
},
  "bbox": [],
  "geometry": {"coordinates":[-69.6667,45.4667],"type":"Point"}
}