{
  "id": 7249379,
  "type": "Feature",
  "properties": {
    "tgn:hierarchy":[
        "tgn:7249379",
        "tgn:7007877",
        "tgn:1000003",
        "tgn:1000063",
        "tgn:4012014",
        "tgn:7029392"
    ],
    "tgn:id":7249379,
    "tgn:name":"Mon Souhait",
    "tgn:placetype":[
        "aat:300000206"
    ]
},
  "bbox": [],
  "geometry": {"coordinates":[4.383333,50.65],"type":"Point"}
}