{
  "id": 7582235,
  "type": "Feature",
  "properties": {
    "tgn:hierarchy":[
        "tgn:7582235",
        "tgn:1000004",
        "tgn:7000198",
        "tgn:7016722",
        "tgn:7029392"
    ],
    "tgn:id":7582235,
    "tgn:name:en":"Sondla T\u0101l",
    "tgn:placetype":[
        "aat:300008680"
    ]
},
  "bbox": [],
  "geometry": {"coordinates":[78.315007,24.821829],"type":"Point"}
}