{
  "id": 7582442,
  "type": "Feature",
  "properties": {
    "tgn:hierarchy":[
        "tgn:7582442",
        "tgn:1000004",
        "tgn:1001871",
        "tgn:7000198",
        "tgn:7029392"
    ],
    "tgn:id":7582442,
    "tgn:name:en":"Sy\u0101mtu",
    "tgn:placetype":[
        "aat:300008347"
    ]
},
  "bbox": [],
  "geometry": {"coordinates":[76.979814,30.624223],"type":"Point"}
}