{
  "id": 7304922,
  "type": "Feature",
  "properties": {
    "tgn:hierarchy":[
        "tgn:7304922",
        "tgn:7008911",
        "tgn:1000003",
        "tgn:7002763",
        "tgn:1000095",
        "tgn:7029392"
    ],
    "tgn:id":7304922,
    "tgn:name":"La Torre",
    "tgn:placetype":[
        "aat:300008347"
    ]
},
  "bbox": [],
  "geometry": {"coordinates":[-6.133333,43.166667],"type":"Point"}
}