{
  "id": 2643915,
  "type": "Feature",
  "properties": {
    "tgn:hierarchy":[
        "tgn:2643915",
        "tgn:1000001",
        "tgn:7012149",
        "tgn:1002576",
        "tgn:7007520",
        "tgn:7029392"
    ],
    "tgn:id":2643915,
    "tgn:name":"Sans Lake",
    "tgn:placetype":[
        "aat:300008680"
    ]
},
  "bbox": [],
  "geometry": {"coordinates":[-82.9833,43.0333],"type":"Point"}
}