{
  "id": 2079585,
  "type": "Feature",
  "properties": {
    "tgn:hierarchy":[
        "tgn:2079585",
        "tgn:1000001",
        "tgn:7012149",
        "tgn:1002784",
        "tgn:7007706",
        "tgn:7029392"
    ],
    "tgn:id":2079585,
    "tgn:name":"Five Points",
    "tgn:placetype":[
        "aat:300008347"
    ]
},
  "bbox": [],
  "geometry": {"coordinates":[-83.1667,39.6667],"type":"Point"}
}