{
  "id": 1052462,
  "type": "Feature",
  "properties": {
    "tgn:hierarchy":[
        "tgn:1052462",
        "tgn:1000004",
        "tgn:1003421",
        "tgn:7018214",
        "tgn:7002435",
        "tgn:7029392"
    ],
    "tgn:id":1052462,
    "tgn:name":"Bakino",
    "tgn:placetype":[
        "aat:300008347"
    ]
},
  "bbox": [],
  "geometry": {"coordinates":[38.9833,56.3333],"type":"Point"}
}