{
  "id": 7186040,
  "type": "Feature",
  "properties": {
    "tgn:hierarchy":[
        "tgn:7186040",
        "tgn:7000096",
        "tgn:1000003",
        "tgn:7000084",
        "tgn:7029392"
    ],
    "tgn:id":7186040,
    "tgn:name":"G\u00f6lsdorfer B\u00f6cke",
    "tgn:placetype":[
        "aat:300055621"
    ]
},
  "bbox": [],
  "geometry": {"coordinates":[12.983333,51.933333],"type":"Point"}
}