<<<<<<< HEAD
{
  "id": 7480848,
  "type": "Feature",
  "properties": {
    "tgn:hierarchy":[
        "tgn:7480848",
        "tgn:1000004",
        "tgn:7471332",
        "tgn:1000141",
        "tgn:7029392"
    ],
    "tgn:id":7480848,
    "tgn:name":"Yushan",
    "tgn:placetype":[
        "aat:300008347"
    ]
},
  "bbox": [],
  "geometry": {"coordinates":[121.208056,24.758889],"type":"Point"}
}
=======
{"geometry":{"type":"Point","coordinates":[121.208056,24.758889]},"type":"Feature","properties":{"hierarchy":["tgn:7480848","tgn:1000004","tgn:7471332","tgn:1000141","tgn:7029392"],"placetype":["aat:300008347"],"id":7480848,"name:xx":"Yushan"}}
>>>>>>> 03f74aca74312dbeaf24d7e61306dd6a786dc3d0
