{
  "id": 2537760,
  "type": "Feature",
  "properties": {
    "tgn:hierarchy":[
        "tgn:2537760",
        "tgn:7006450",
        "tgn:1000001",
        "tgn:7012149",
        "tgn:2000079",
        "tgn:7029392"
    ],
    "tgn:id":2537760,
    "tgn:name":"Nekeelit Point",
    "tgn:placetype":[
        "aat:300008850"
    ]
},
  "bbox": [],
  "geometry": {"coordinates":[-171.75,63.6833],"type":"Point"}
}