{
  "id": 2684578,
  "type": "Feature",
  "properties": {
    "tgn:hierarchy":[
        "tgn:2684578",
        "tgn:2002306",
        "tgn:1000001",
        "tgn:7012149",
        "tgn:7007922",
        "tgn:7029392"
    ],
    "tgn:id":2684578,
    "tgn:name":"Spillerberg Lake",
    "tgn:placetype":[
        "aat:300008680"
    ]
},
  "bbox": [],
  "geometry": {"coordinates":[-90.6667,46.1833],"type":"Point"}
}