{
  "id": 2361582,
  "type": "Feature",
  "properties": {
    "tgn:hierarchy":[
        "tgn:2361582",
        "tgn:1000001",
        "tgn:7012149",
        "tgn:2001872",
        "tgn:7007825",
        "tgn:7029392"
    ],
    "tgn:id":2361582,
    "tgn:name":"Gravett Branch",
    "tgn:placetype":[
        "aat:300008699"
    ]
},
  "bbox": [],
  "geometry": {"coordinates":[-88.1167,35.25],"type":"Point"}
}