{
  "id": 2768020,
  "type": "Feature",
  "properties": {
    "tgn:hierarchy":[
        "tgn:2768020",
        "tgn:1000001",
        "tgn:7012149",
        "tgn:2002187",
        "tgn:7007919",
        "tgn:7029392"
    ],
    "tgn:id":2768020,
    "tgn:name":"Whiteoak Run",
    "tgn:placetype":[
        "aat:300008699"
    ]
},
  "bbox": [],
  "geometry": {"coordinates":[-78.7167,38.2167],"type":"Point"}
}