<<<<<<< HEAD
{
  "id": 2768020,
  "type": "Feature",
  "properties": {
    "tgn:hierarchy":[
        "tgn:2768020",
        "tgn:1000001",
        "tgn:7012149",
        "tgn:2002187",
        "tgn:7007919",
        "tgn:7029392"
    ],
    "tgn:id":2768020,
    "tgn:name":"Whiteoak Run",
    "tgn:placetype":[
        "aat:300008699"
    ]
},
  "bbox": [],
  "geometry": {"coordinates":[-78.7167,38.2167],"type":"Point"}
}
=======
{"geometry":{"type":"Point","coordinates":[-78.716700,38.216700]},"type":"Feature","properties":{"hierarchy":["tgn:2768020","tgn:1000001","tgn:7012149","tgn:2002187","tgn:7007919","tgn:7029392"],"placetype":["aat:300008699"],"id":2768020,"name:xx":"Whiteoak Run"}}
>>>>>>> 03f74aca74312dbeaf24d7e61306dd6a786dc3d0
