{
  "id": 7404133,
  "type": "Feature",
  "properties": {
    "tgn:hierarchy":[
        "tgn:7404133",
        "tgn:7005585",
        "tgn:1000001",
        "tgn:7005560",
        "tgn:7029392"
    ],
    "tgn:id":7404133,
    "tgn:name":"Sulchuchio",
    "tgn:placetype":[
        "aat:300008347"
    ]
},
  "bbox": [],
  "geometry": {"coordinates":[-99.091667,17.616667],"type":"Point"}
}