{
  "id": 7529759,
  "type": "Feature",
  "properties": {
    "tgn:hierarchy":[
        "tgn:7529759",
        "tgn:7001242",
        "tgn:7016833",
        "tgn:7001336",
        "tgn:7029392"
    ],
    "tgn:id":7529759,
    "tgn:name:en":"Rumayth\u012b, W\u0101d\u012b ar",
    "tgn:placetype":[
        "aat:300379998"
    ]
},
  "bbox": [],
  "geometry": {"coordinates":[34.50352,29.376064],"type":"Point"}
}