{
  "id": 2244985,
  "type": "Feature",
  "properties": {
    "tgn:hierarchy":[
        "tgn:2244985",
        "tgn:1000001",
        "tgn:7012149",
        "tgn:2002287",
        "tgn:7013961",
        "tgn:7029392"
    ],
    "tgn:id":2244985,
    "tgn:name":"Clover Creek",
    "tgn:placetype":[
        "aat:300008706"
    ]
},
  "bbox": [],
  "geometry": {"coordinates":[-80.05,38.3167],"type":"Point"}
}