<<<<<<< HEAD
{
  "id": 2253917,
  "type": "Feature",
  "properties": {
    "tgn:hierarchy":[
        "tgn:2253917",
        "tgn:1002146",
        "tgn:1000001",
        "tgn:7012149",
        "tgn:7007157",
        "tgn:7029392"
    ],
    "tgn:id":2253917,
    "tgn:name":"Cooks Station Ridge",
    "tgn:placetype":[
        "aat:300266640"
    ]
},
  "bbox": [],
  "geometry": {"coordinates":[-120.45,38.5],"type":"Point"}
}
=======
{"geometry":{"type":"Point","coordinates":[-120.450000,38.500000]},"type":"Feature","properties":{"hierarchy":["tgn:2253917","tgn:1002146","tgn:1000001","tgn:7012149","tgn:7007157","tgn:7029392"],"placetype":["aat:300266640"],"id":2253917,"name:xx":"Cooks Station Ridge"}}
>>>>>>> 03f74aca74312dbeaf24d7e61306dd6a786dc3d0
