{
  "id": 7158100,
  "type": "Feature",
  "properties": {
    "tgn:hierarchy":[
        "tgn:7158100",
        "tgn:7000096",
        "tgn:1000003",
        "tgn:7000084",
        "tgn:7029392"
    ],
    "tgn:id":7158100,
    "tgn:name":"Katzenberge",
    "tgn:placetype":[
        "aat:300008777"
    ]
},
  "bbox": [],
  "geometry": {"coordinates":[12.383333,52.133333],"type":"Point"}
}