<<<<<<< HEAD
{
  "id": 2337902,
  "type": "Feature",
  "properties": {
    "tgn:hierarchy":[
        "tgn:2337902",
        "tgn:1000001",
        "tgn:7012149",
        "tgn:1002440",
        "tgn:7007568",
        "tgn:7029392"
    ],
    "tgn:id":2337902,
    "tgn:name":"Fox Hill",
    "tgn:placetype":[
        "aat:300008798"
    ]
},
  "bbox": [],
  "geometry": {"coordinates":[-74.05,43.7833],"type":"Point"}
}
=======
{"geometry":{"type":"Point","coordinates":[-74.050000,43.783300]},"type":"Feature","properties":{"hierarchy":["tgn:2337902","tgn:1000001","tgn:7012149","tgn:1002440","tgn:7007568","tgn:7029392"],"placetype":["aat:300008798"],"id":2337902,"name:xx":"Fox Hill"}}
>>>>>>> 03f74aca74312dbeaf24d7e61306dd6a786dc3d0
