{
  "id": 7262514,
  "type": "Feature",
  "properties": {
    "tgn:concordances":{
        "gn:id":"2758264"
    },
    "tgn:hierarchy":[
        "tgn:7262514",
        "tgn:1000003",
        "tgn:7003626",
        "tgn:7016845",
        "tgn:7029392"
    ],
    "tgn:id":7262514,
    "tgn:name:nl":"Broekhuizen",
    "tgn:placetype":[
        "aat:300008347"
    ]
},
  "bbox": [],
  "geometry": {"coordinates":[6.216667,52.516667],"type":"Point"}
}