{
  "id": 2275070,
  "type": "Feature",
  "properties": {
    "tgn:hierarchy":[
        "tgn:2275070",
        "tgn:1002175",
        "tgn:1000001",
        "tgn:7012149",
        "tgn:7007706",
        "tgn:7029392"
    ],
    "tgn:id":2275070,
    "tgn:name":"Dandelion Hollow",
    "tgn:placetype":[
        "aat:300008761"
    ]
},
  "bbox": [],
  "geometry": {"coordinates":[-80.75,40.0833],"type":"Point"}
}