{
  "id": 2079979,
  "type": "Feature",
  "properties": {
    "tgn:hierarchy":[
        "tgn:2079979",
        "tgn:1000001",
        "tgn:7012149",
        "tgn:1002386",
        "tgn:7007706",
        "tgn:7029392"
    ],
    "tgn:id":2079979,
    "tgn:name":"Hilliard",
    "tgn:placetype":[
        "aat:300008347"
    ]
},
  "bbox": [],
  "geometry": {"coordinates":[-83.15,40.0333],"type":"Point"}
}