{
  "id": 7206027,
  "type": "Feature",
  "properties": {
    "tgn:hierarchy":[
        "tgn:7206027",
        "tgn:1000003",
        "tgn:7003678",
        "tgn:7000084",
        "tgn:7029392"
    ],
    "tgn:id":7206027,
    "tgn:name":"B\u00fcdesheim",
    "tgn:placetype":[
        "aat:300008347"
    ]
},
  "bbox": [],
  "geometry": {"coordinates":[8.833333,50.216667],"type":"Point"}
}