{
  "id": 7341462,
  "type": "Feature",
  "properties": {
    "tgn:hierarchy":[
        "tgn:7341462",
        "tgn:7002824",
        "tgn:1000003",
        "tgn:7002786",
        "tgn:1000095",
        "tgn:7029392"
    ],
    "tgn:id":7341462,
    "tgn:name":"Berroge",
    "tgn:placetype":[
        "aat:300008347"
    ]
},
  "bbox": [],
  "geometry": {"coordinates":[-9.166667,42.95],"type":"Point"}
}