{
  "id": 7288353,
  "type": "Feature",
  "properties": {
    "tgn:hierarchy":[
        "tgn:7288353",
        "tgn:1001623",
        "tgn:1000049",
        "tgn:1000002",
        "tgn:7029392"
    ],
    "tgn:id":7288353,
    "tgn:name":"Seno Jesuitas",
    "tgn:placetype":[
        "aat:300006495"
    ]
},
  "bbox": [],
  "geometry": {"coordinates":[-74.25,-47.183333],"type":"Point"}
}