<<<<<<< HEAD
{
  "id": 7172548,
  "type": "Feature",
  "properties": {
    "tgn:hierarchy":[
        "tgn:7172548",
        "tgn:1000003",
        "tgn:7003687",
        "tgn:7000084",
        "tgn:7029392"
    ],
    "tgn:id":7172548,
    "tgn:name":"Herren-Berg",
    "tgn:placetype":[
        "aat:300008777"
    ]
},
  "bbox": [],
  "geometry": {"coordinates":[10.95,51.95],"type":"Point"}
}
=======
{"geometry":{"type":"Point","coordinates":[10.950000,51.950000]},"type":"Feature","properties":{"hierarchy":["tgn:7172548","tgn:1000003","tgn:7003687","tgn:7000084","tgn:7029392"],"placetype":["aat:300008777"],"id":7172548,"name:xx":"Herren-Berg"}}
>>>>>>> 03f74aca74312dbeaf24d7e61306dd6a786dc3d0
