<<<<<<< HEAD
{
  "id": 7023108,
  "type": "Feature",
  "properties": {
    "tgn:hierarchy":[
        "tgn:7023108",
        "tgn:1000001",
        "tgn:2002106",
        "tgn:7012149",
        "tgn:7007827",
        "tgn:7029392"
    ],
    "tgn:id":7023108,
    "tgn:name":"Heritage Square",
    "tgn:placetype":[
        "aat:300008347"
    ]
},
  "bbox": [],
  "geometry": {"coordinates":[-112.0333,41.15],"type":"Point"}
}
=======
{"geometry":{"type":"Point","coordinates":[-112.033300,41.150000]},"type":"Feature","properties":{"hierarchy":["tgn:7023108","tgn:1000001","tgn:2002106","tgn:7012149","tgn:7007827","tgn:7029392"],"placetype":["aat:300008347"],"id":7023108,"name:xx":"Heritage Square"}}
>>>>>>> 03f74aca74312dbeaf24d7e61306dd6a786dc3d0
