{
  "id": 7423010,
  "type": "Feature",
  "properties": {
    "tgn:hierarchy":[
        "tgn:7423010",
        "tgn:1000001",
        "tgn:7005601",
        "tgn:7005560",
        "tgn:7029392"
    ],
    "tgn:id":7423010,
    "tgn:name":"San Vicente",
    "tgn:placetype":[
        "aat:300008347"
    ]
},
  "bbox": [],
  "geometry": {"coordinates":[-103.366667,21.533333],"type":"Point"}
}