{
  "id": 2438513,
  "type": "Feature",
  "properties": {
    "tgn:hierarchy":[
        "tgn:2438513",
        "tgn:1000001",
        "tgn:2000202",
        "tgn:7012149",
        "tgn:7007158",
        "tgn:7029392"
    ],
    "tgn:id":2438513,
    "tgn:name":"Kings Turquoise Mines",
    "tgn:placetype":[
        "aat:300000390"
    ]
},
  "bbox": [],
  "geometry": {"coordinates":[-105.75,37.1667],"type":"Point"}
}