{
  "id": 2565317,
  "type": "Feature",
  "properties": {
    "tgn:hierarchy":[
        "tgn:2565317",
        "tgn:1000001",
        "tgn:7012149",
        "tgn:2001866",
        "tgn:7007825",
        "tgn:7029392"
    ],
    "tgn:id":2565317,
    "tgn:name":"Paint Creek",
    "tgn:placetype":[
        "aat:300008706"
    ]
},
  "bbox": [],
  "geometry": {"coordinates":[-82.8833,35.9333],"type":"Point"}
}