{
  "id": 7565570,
  "type": "Feature",
  "properties": {
    "tgn:hierarchy":[
        "tgn:7565570",
        "tgn:1000004",
        "tgn:7000198",
        "tgn:7016722",
        "tgn:7029392"
    ],
    "tgn:id":7565570,
    "tgn:name:en":"Bik\u016bpur",
    "tgn:placetype":[
        "aat:300008347"
    ]
},
  "bbox": [],
  "geometry": {"coordinates":[79.50957,26.775567],"type":"Point"}
}