{
  "id": 7273305,
  "type": "Feature",
  "properties": {
    "tgn:hierarchy":[
        "tgn:7273305",
        "tgn:7003616",
        "tgn:1000003",
        "tgn:7016845",
        "tgn:7029392"
    ],
    "tgn:id":7273305,
    "tgn:name:nl":"West Friese Eilanden",
    "tgn:placetype":[
        "aat:300008791"
    ]
},
  "bbox": [],
  "geometry": {"coordinates":[5.333333,53.366667],"type":"Point"}
}