{
  "id": 2248403,
  "type": "Feature",
  "properties": {
    "tgn:hierarchy":[
        "tgn:2248403",
        "tgn:1000001",
        "tgn:7012149",
        "tgn:2001281",
        "tgn:7007524",
        "tgn:7029392"
    ],
    "tgn:id":2248403,
    "tgn:name":"Cold Spring",
    "tgn:placetype":[
        "aat:300008697"
    ]
},
  "bbox": [],
  "geometry": {"coordinates":[-112.2667,45.85],"type":"Point"}
}