{
  "id": 2163970,
  "type": "Feature",
  "properties": {
    "tgn:hierarchy":[
        "tgn:2163970",
        "tgn:1000001",
        "tgn:7012149",
        "tgn:2002355",
        "tgn:7007922",
        "tgn:7029392"
    ],
    "tgn:id":2163970,
    "tgn:name":"Bergin Ditch",
    "tgn:placetype":[
        "aat:300006075"
    ]
},
  "bbox": [],
  "geometry": {"coordinates":[-88.0833,43.8167],"type":"Point"}
}