{
  "id": 2251597,
  "type": "Feature",
  "properties": {
    "tgn:hierarchy":[
        "tgn:2251597",
        "tgn:1000001",
        "tgn:1002246",
        "tgn:7012149",
        "tgn:7007568",
        "tgn:7029392"
    ],
    "tgn:id":2251597,
    "tgn:name":"Como",
    "tgn:placetype":[
        "aat:300008347"
    ]
},
  "bbox": [],
  "geometry": {"coordinates":[-76.2667,42.6667],"type":"Point"}
}