<<<<<<< HEAD
{
  "id": 2251597,
  "type": "Feature",
  "properties": {
    "tgn:hierarchy":[
        "tgn:2251597",
        "tgn:1000001",
        "tgn:1002246",
        "tgn:7012149",
        "tgn:7007568",
        "tgn:7029392"
    ],
    "tgn:id":2251597,
    "tgn:name":"Como",
    "tgn:placetype":[
        "aat:300008347"
    ]
},
  "bbox": [],
  "geometry": {"coordinates":[-76.2667,42.6667],"type":"Point"}
}
=======
{"geometry":{"type":"Point","coordinates":[-76.266700,42.666700]},"type":"Feature","properties":{"hierarchy":["tgn:2251597","tgn:1000001","tgn:1002246","tgn:7012149","tgn:7007568","tgn:7029392"],"placetype":["aat:300008347"],"id":2251597,"name:xx":"Como"}}
>>>>>>> 03f74aca74312dbeaf24d7e61306dd6a786dc3d0
