{
  "id": 7044532,
  "type": "Feature",
  "properties": {
    "tgn:hierarchy":[
        "tgn:7044532",
        "tgn:7003166",
        "tgn:1000003",
        "tgn:7009760",
        "tgn:1000080",
        "tgn:7029392"
    ],
    "tgn:id":7044532,
    "tgn:name":"Frassineta",
    "tgn:placetype":[
        "aat:300008347"
    ]
},
  "bbox": [],
  "geometry": {"coordinates":[10.633333,43.333333],"type":"Point"}
}