<<<<<<< HEAD
{
  "id": 2154498,
  "type": "Feature",
  "properties": {
    "tgn:hierarchy":[
        "tgn:2154498",
        "tgn:1000001",
        "tgn:2000470",
        "tgn:7012149",
        "tgn:7007250",
        "tgn:7029392"
    ],
    "tgn:id":2154498,
    "tgn:name":"Bear Creek Lake",
    "tgn:placetype":[
        "aat:300006191"
    ]
},
  "bbox": [],
  "geometry": {"coordinates":[-113.5,43.9833],"type":"Point"}
}
=======
{"geometry":{"type":"Point","coordinates":[-113.500000,43.983300]},"type":"Feature","properties":{"hierarchy":["tgn:2154498","tgn:1000001","tgn:2000470","tgn:7012149","tgn:7007250","tgn:7029392"],"placetype":["aat:300006191"],"id":2154498,"name:xx":"Bear Creek Lake"}}
>>>>>>> 03f74aca74312dbeaf24d7e61306dd6a786dc3d0
