<<<<<<< HEAD
{
  "id": 7485056,
  "type": "Feature",
  "properties": {
    "tgn:hierarchy":[
        "tgn:7485056",
        "tgn:1000004",
        "tgn:7001014",
        "tgn:1000141",
        "tgn:7029392"
    ],
    "tgn:id":7485056,
    "tgn:name":"Fangzilun",
    "tgn:placetype":[
        "aat:300008347"
    ]
},
  "bbox": [],
  "geometry": {"coordinates":[120.654167,23.575556],"type":"Point"}
}
=======
{"geometry":{"type":"Point","coordinates":[120.654167,23.575556]},"type":"Feature","properties":{"hierarchy":["tgn:7485056","tgn:1000004","tgn:7001014","tgn:1000141","tgn:7029392"],"placetype":["aat:300008347"],"id":7485056,"name:xx":"Fangzilun"}}
>>>>>>> 03f74aca74312dbeaf24d7e61306dd6a786dc3d0
