{
  "id": 7485056,
  "type": "Feature",
  "properties": {
    "tgn:hierarchy":[
        "tgn:7485056",
        "tgn:1000004",
        "tgn:7001014",
        "tgn:1000141",
        "tgn:7029392"
    ],
    "tgn:id":7485056,
    "tgn:name":"Fangzilun",
    "tgn:placetype":[
        "aat:300008347"
    ]
},
  "bbox": [],
  "geometry": {"coordinates":[120.654167,23.575556],"type":"Point"}
}