{
  "id": 2210309,
  "type": "Feature",
  "properties": {
    "tgn:hierarchy":[
        "tgn:2210309",
        "tgn:1000001",
        "tgn:2002152",
        "tgn:7012149",
        "tgn:7007919",
        "tgn:7029392"
    ],
    "tgn:id":2210309,
    "tgn:name":"Bush Ford Branch",
    "tgn:placetype":[
        "aat:300008699"
    ]
},
  "bbox": [],
  "geometry": {"coordinates":[-78.6333,37.05],"type":"Point"}
}