{
  "id": 2100466,
  "type": "Feature",
  "properties": {
    "tgn:hierarchy":[
        "tgn:2100466",
        "tgn:1000001",
        "tgn:7012149",
        "tgn:2001863",
        "tgn:7007825",
        "tgn:7029392"
    ],
    "tgn:id":2100466,
    "tgn:name":"Moores Chapel",
    "tgn:placetype":[
        "aat:300008347",
        "aat:300387210"
    ]
},
  "bbox": [],
  "geometry": {"coordinates":[-88.85,35.9333],"type":"Point"}
}