{
  "id": 2245902,
  "type": "Feature",
  "properties": {
    "tgn:hierarchy":[
        "tgn:2245902",
        "tgn:1000001",
        "tgn:7012149",
        "tgn:2002121",
        "tgn:7007827",
        "tgn:7029392"
    ],
    "tgn:id":2245902,
    "tgn:name":"Coal Hollow",
    "tgn:placetype":[
        "aat:300008761"
    ]
},
  "bbox": [],
  "geometry": {"coordinates":[-111.5833,38.9167],"type":"Point"}
}