{
  "id": 7527881,
  "type": "Feature",
  "properties": {
    "tgn:hierarchy":[
        "tgn:7527881",
        "tgn:7001242",
        "tgn:7001311",
        "tgn:7016833",
        "tgn:7029392"
    ],
    "tgn:id":7527881,
    "tgn:name:en":"Umm a\u0163 \u0162uy\u016br, Jabal",
    "tgn:placetype":[
        "aat:300008795"
    ]
},
  "bbox": [],
  "geometry": {"coordinates":[34.864616,24.17133],"type":"Point"}
}