{
  "id": 7029554,
  "type": "Feature",
  "properties": {
    "tgn:hierarchy":[
        "tgn:7029554",
        "tgn:1001311",
        "tgn:1000004",
        "tgn:1000118",
        "tgn:7001784",
        "tgn:7029392"
    ],
    "tgn:id":7029554,
    "tgn:name":"Harir",
    "tgn:placetype":[
        "aat:300008347"
    ]
},
  "bbox": [],
  "geometry": {"coordinates":[44.355,36.554],"type":"Point"}
}