{
  "id": 2015957,
  "type": "Feature",
  "properties": {
    "tgn:hierarchy":[
        "tgn:2015957",
        "tgn:1000001",
        "tgn:7012149",
        "tgn:2000216",
        "tgn:7007158",
        "tgn:7029392"
    ],
    "tgn:id":2015957,
    "tgn:name":"Maryvale",
    "tgn:placetype":[
        "aat:300008347"
    ]
},
  "bbox": [],
  "geometry": {"coordinates":[-105.7833,39.9167],"type":"Point"}
}