<<<<<<< HEAD
{
  "id": 2257234,
  "type": "Feature",
  "properties": {
    "tgn:hierarchy":[
        "tgn:2257234",
        "tgn:1000001",
        "tgn:7012149",
        "tgn:2002017",
        "tgn:7007826",
        "tgn:7029392"
    ],
    "tgn:id":2257234,
    "tgn:name":"Corner Tank",
    "tgn:placetype":[
        "aat:300006191"
    ]
},
  "bbox": [],
  "geometry": {"coordinates":[-101.0167,33.2167],"type":"Point"}
}
=======
{"geometry":{"type":"Point","coordinates":[-101.016700,33.216700]},"type":"Feature","properties":{"hierarchy":["tgn:2257234","tgn:1000001","tgn:7012149","tgn:2002017","tgn:7007826","tgn:7029392"],"placetype":["aat:300006191"],"id":2257234,"name:xx":"Corner Tank"}}
>>>>>>> 03f74aca74312dbeaf24d7e61306dd6a786dc3d0
