{
  "id": 2257234,
  "type": "Feature",
  "properties": {
    "tgn:hierarchy":[
        "tgn:2257234",
        "tgn:1000001",
        "tgn:7012149",
        "tgn:2002017",
        "tgn:7007826",
        "tgn:7029392"
    ],
    "tgn:id":2257234,
    "tgn:name":"Corner Tank",
    "tgn:placetype":[
        "aat:300006191"
    ]
},
  "bbox": [],
  "geometry": {"coordinates":[-101.0167,33.2167],"type":"Point"}
}