<<<<<<< HEAD
{
  "id": 2151080,
  "type": "Feature",
  "properties": {
    "tgn:hierarchy":[
        "tgn:2151080",
        "tgn:2000919",
        "tgn:1000001",
        "tgn:7012149",
        "tgn:7007515",
        "tgn:7029392"
    ],
    "tgn:id":2151080,
    "tgn:name":"Baston Brook",
    "tgn:placetype":[
        "aat:300008699"
    ]
},
  "bbox": [],
  "geometry": {"coordinates":[-68.3333,46.2],"type":"Point"}
}
=======
{"geometry":{"type":"Point","coordinates":[-68.333300,46.200000]},"type":"Feature","properties":{"hierarchy":["tgn:2151080","tgn:2000919","tgn:1000001","tgn:7012149","tgn:7007515","tgn:7029392"],"placetype":["aat:300008699"],"id":2151080,"name:xx":"Baston Brook"}}
>>>>>>> 03f74aca74312dbeaf24d7e61306dd6a786dc3d0
