<<<<<<< HEAD
{
  "id": 7119118,
  "type": "Feature",
  "properties": {
    "tgn:hierarchy":[
        "tgn:7119118",
        "tgn:1000003",
        "tgn:7003678",
        "tgn:7000084",
        "tgn:7029392"
    ],
    "tgn:id":7119118,
    "tgn:name":"Pickel-Berg",
    "tgn:placetype":[
        "aat:300008777"
    ]
},
  "bbox": [],
  "geometry": {"coordinates":[9.066667,51.033333],"type":"Point"}
}
=======
{"geometry":{"type":"Point","coordinates":[9.066667,51.033333]},"type":"Feature","properties":{"hierarchy":["tgn:7119118","tgn:1000003","tgn:7003678","tgn:7000084","tgn:7029392"],"placetype":["aat:300008777"],"id":7119118,"name:xx":"Pickel-Berg"}}
>>>>>>> 03f74aca74312dbeaf24d7e61306dd6a786dc3d0
