{
  "id": 2655439,
  "type": "Feature",
  "properties": {
    "tgn:hierarchy":[
        "tgn:2655439",
        "tgn:1002215",
        "tgn:1000001",
        "tgn:7012149",
        "tgn:7007565",
        "tgn:7029392"
    ],
    "tgn:id":2655439,
    "tgn:name":"Sharp",
    "tgn:placetype":[
        "aat:300008347"
    ]
},
  "bbox": [],
  "geometry": {"coordinates":[-74.7333,40.0833],"type":"Point"}
}