{
  "id": 2187330,
  "type": "Feature",
  "properties": {
    "tgn:hierarchy":[
        "tgn:2187330",
        "tgn:1000001",
        "tgn:1002259",
        "tgn:7012149",
        "tgn:7007568",
        "tgn:7029392"
    ],
    "tgn:id":2187330,
    "tgn:name":"Boomertown",
    "tgn:placetype":[
        "aat:300008347"
    ]
},
  "bbox": [],
  "geometry": {"coordinates":[-79.3667,42.0667],"type":"Point"}
}