<<<<<<< HEAD
{
  "id": 2763285,
  "type": "Feature",
  "properties": {
    "tgn:hierarchy":[
        "tgn:2763285",
        "tgn:1000001",
        "tgn:7012149",
        "tgn:7007157",
        "tgn:1002675",
        "tgn:7029392"
    ],
    "tgn:id":2763285,
    "tgn:name":"Wet Fork",
    "tgn:placetype":[
        "aat:300008699"
    ]
},
  "bbox": [],
  "geometry": {"coordinates":[-118.6667,37.75],"type":"Point"}
}
=======
{"geometry":{"type":"Point","coordinates":[-118.666700,37.750000]},"type":"Feature","properties":{"hierarchy":["tgn:2763285","tgn:1000001","tgn:7012149","tgn:7007157","tgn:1002675","tgn:7029392"],"placetype":["aat:300008699"],"id":2763285,"name:xx":"Wet Fork"}}
>>>>>>> 03f74aca74312dbeaf24d7e61306dd6a786dc3d0
