{
  "id": 7108752,
  "type": "Feature",
  "properties": {
    "tgn:hierarchy":[
        "tgn:7108752",
        "tgn:7003669",
        "tgn:1000003",
        "tgn:7000084",
        "tgn:7029392"
    ],
    "tgn:id":7108752,
    "tgn:name":"Rappers Berg",
    "tgn:placetype":[
        "aat:300008777"
    ]
},
  "bbox": [],
  "geometry": {"coordinates":[11.366667,49.933333],"type":"Point"}
}