{
  "id": 2168982,
  "type": "Feature",
  "properties": {
    "tgn:hierarchy":[
        "tgn:2168982",
        "tgn:7014651",
        "tgn:1000001",
        "tgn:7012149",
        "tgn:7007516",
        "tgn:7029392"
    ],
    "tgn:id":2168982,
    "tgn:name":"Big Island",
    "tgn:placetype":[
        "aat:300008791"
    ]
},
  "bbox": [],
  "geometry": {"coordinates":[-76.5333,38.8833],"type":"Point"}
}