{
  "id": 2298767,
  "type": "Feature",
  "properties": {
    "tgn:hierarchy":[
        "tgn:2298767",
        "tgn:1000001",
        "tgn:7012149",
        "tgn:2001237",
        "tgn:7007523",
        "tgn:7029392"
    ],
    "tgn:id":2298767,
    "tgn:name":"Dryden",
    "tgn:placetype":[
        "aat:300008347"
    ]
},
  "bbox": [],
  "geometry": {"coordinates":[-90.7333,36.6667],"type":"Point"}
}