{
  "id": 7511301,
  "type": "Feature",
  "properties": {
    "tgn:hierarchy":[
        "tgn:7511301",
        "tgn:7000508",
        "tgn:1008380",
        "tgn:1000226",
        "tgn:1000006",
        "tgn:7029392"
    ],
    "tgn:id":7511301,
    "tgn:name:en":"Tree Hill",
    "tgn:placetype":[
        "aat:300008777"
    ]
},
  "bbox": [],
  "geometry": {"coordinates":[174.55,-37.066667],"type":"Point"}
}