{
  "id": 2074504,
  "type": "Feature",
  "properties": {
    "tgn:hierarchy":[
        "tgn:2074504",
        "tgn:2001464",
        "tgn:1000001",
        "tgn:7012149",
        "tgn:7007709",
        "tgn:7029392"
    ],
    "tgn:id":2074504,
    "tgn:name":"Ellendale",
    "tgn:placetype":[
        "aat:300008347",
        "aat:300387210"
    ]
},
  "bbox": [],
  "geometry": {"coordinates":[-81.2667,35.9167],"type":"Point"}
}