{
  "id": 2664543,
  "type": "Feature",
  "properties": {
    "tgn:hierarchy":[
        "tgn:2664543",
        "tgn:1000001",
        "tgn:7012149",
        "tgn:2000904",
        "tgn:7007256",
        "tgn:7029392"
    ],
    "tgn:id":2664543,
    "tgn:name":"Simmons Bayou",
    "tgn:placetype":[
        "aat:300008699"
    ]
},
  "bbox": [],
  "geometry": {"coordinates":[-91.2333,29.6667],"type":"Point"}
}