<<<<<<< HEAD
{
  "id": 2763658,
  "type": "Feature",
  "properties": {
    "tgn:hierarchy":[
        "tgn:2763658",
        "tgn:1000001",
        "tgn:7012149",
        "tgn:7018871",
        "tgn:7007920",
        "tgn:7029392"
    ],
    "tgn:id":2763658,
    "tgn:name":"Whalers Cove",
    "tgn:placetype":[
        "aat:300132316"
    ]
},
  "bbox": [],
  "geometry": {"coordinates":[-122.2,47.6],"type":"Point"}
}
=======
{"geometry":{"type":"Point","coordinates":[-122.200000,47.600000]},"type":"Feature","properties":{"hierarchy":["tgn:2763658","tgn:1000001","tgn:7012149","tgn:7018871","tgn:7007920","tgn:7029392"],"placetype":["aat:300132316"],"id":2763658,"name:xx":"Whalers Cove"}}
>>>>>>> 03f74aca74312dbeaf24d7e61306dd6a786dc3d0
