{
  "id": 2683658,
  "type": "Feature",
  "properties": {
    "tgn:hierarchy":[
        "tgn:2683658",
        "tgn:1000001",
        "tgn:7012149",
        "tgn:2002068",
        "tgn:7007826",
        "tgn:7029392"
    ],
    "tgn:id":2683658,
    "tgn:name":"Spears Lake",
    "tgn:placetype":[
        "aat:300008680"
    ]
},
  "bbox": [],
  "geometry": {"coordinates":[-97.1833,27.9667],"type":"Point"}
}