{
  "id": 7545192,
  "type": "Feature",
  "properties": {
    "tgn:hierarchy":[
        "tgn:7545192",
        "tgn:1000004",
        "tgn:7000198",
        "tgn:7001797",
        "tgn:7029392"
    ],
    "tgn:id":7545192,
    "tgn:name:en":"Barg\u016bru",
    "tgn:placetype":[
        "aat:300008347"
    ]
},
  "bbox": [],
  "geometry": {"coordinates":[78.366667,12.55],"type":"Point"}
}