{
  "id": 7551425,
  "type": "Feature",
  "properties": {
    "tgn:hierarchy":[
        "tgn:7551425",
        "tgn:1000004",
        "tgn:7000198",
        "tgn:7000799",
        "tgn:7029392"
    ],
    "tgn:id":7551425,
    "tgn:name:en":"Boizardin La",
    "tgn:placetype":[
        "aat:300259572"
    ]
},
  "bbox": [],
  "geometry": {"coordinates":[79.087781,32.603116],"type":"Point"}
}