<<<<<<< HEAD
{
  "id": 2765745,
  "type": "Feature",
  "properties": {
    "tgn:hierarchy":[
        "tgn:2765745",
        "tgn:1000001",
        "tgn:7012149",
        "tgn:7007825",
        "tgn:7029392"
    ],
    "tgn:id":2765745,
    "tgn:name":"White Creek Shoals",
    "tgn:placetype":[
        "aat:300132348"
    ]
},
  "bbox": [],
  "geometry": {"coordinates":[-84.7,35.7333],"type":"Point"}
}
=======
{"geometry":{"type":"Point","coordinates":[-84.700000,35.733300]},"type":"Feature","properties":{"hierarchy":["tgn:2765745","tgn:1000001","tgn:7012149","tgn:7007825","tgn:7029392"],"placetype":["aat:300132348"],"id":2765745,"name:xx":"White Creek Shoals"}}
>>>>>>> 03f74aca74312dbeaf24d7e61306dd6a786dc3d0
