{
  "id": 2699786,
  "type": "Feature",
  "properties": {
    "tgn:hierarchy":[
        "tgn:2699786",
        "tgn:1000001",
        "tgn:7016172",
        "tgn:2000116",
        "tgn:7012149",
        "tgn:7029392"
    ],
    "tgn:id":2699786,
    "tgn:name":"Stubbs Point",
    "tgn:placetype":[
        "aat:300008850"
    ]
},
  "bbox": [],
  "geometry": {"coordinates":[-92.05,35.6833],"type":"Point"}
}