{
  "id": 2555637,
  "type": "Feature",
  "properties": {
    "tgn:hierarchy":[
        "tgn:2555637",
        "tgn:1000001",
        "tgn:7012149",
        "tgn:2001276",
        "tgn:7007524",
        "tgn:7029392"
    ],
    "tgn:id":2555637,
    "tgn:name":"Ogilvie Coulee",
    "tgn:placetype":[
        "aat:300008761"
    ]
},
  "bbox": [],
  "geometry": {"coordinates":[-106.4833,47.0333],"type":"Point"}
}