{
  "id": 2370905,
  "type": "Feature",
  "properties": {
    "tgn:hierarchy":[
        "tgn:2370905",
        "tgn:1000001",
        "tgn:7012149",
        "tgn:2000342",
        "tgn:7007248",
        "tgn:7029392"
    ],
    "tgn:id":2370905,
    "tgn:name":"Haddonville",
    "tgn:placetype":[
        "aat:300008347"
    ]
},
  "bbox": [],
  "geometry": {"coordinates":[-81.2167,32.4333],"type":"Point"}
}