{
  "id": 2255530,
  "type": "Feature",
  "properties": {
    "tgn:hierarchy":[
        "tgn:2255530",
        "tgn:1000001",
        "tgn:7012149",
        "tgn:7016056",
        "tgn:7007520",
        "tgn:7029392"
    ],
    "tgn:id":2255530,
    "tgn:name":"Copeland Corner",
    "tgn:placetype":[
        "aat:300008347"
    ]
},
  "bbox": [],
  "geometry": {"coordinates":[-82.6167,42.6667],"type":"Point"}
}