<<<<<<< HEAD
{
  "id": 2255530,
  "type": "Feature",
  "properties": {
    "tgn:hierarchy":[
        "tgn:2255530",
        "tgn:1000001",
        "tgn:7012149",
        "tgn:7016056",
        "tgn:7007520",
        "tgn:7029392"
    ],
    "tgn:id":2255530,
    "tgn:name":"Copeland Corner",
    "tgn:placetype":[
        "aat:300008347"
    ]
},
  "bbox": [],
  "geometry": {"coordinates":[-82.6167,42.6667],"type":"Point"}
}
=======
{"geometry":{"type":"Point","coordinates":[-82.616700,42.666700]},"type":"Feature","properties":{"hierarchy":["tgn:2255530","tgn:1000001","tgn:7012149","tgn:7016056","tgn:7007520","tgn:7029392"],"placetype":["aat:300008347"],"id":2255530,"name:xx":"Copeland Corner"}}
>>>>>>> 03f74aca74312dbeaf24d7e61306dd6a786dc3d0
