{
  "id": 2711677,
  "type": "Feature",
  "properties": {
    "tgn:hierarchy":[
        "tgn:2711677",
        "tgn:1000001",
        "tgn:7012149",
        "tgn:1002876",
        "tgn:7007710",
        "tgn:7029392"
    ],
    "tgn:id":2711677,
    "tgn:name":"Tar Run Reservoir",
    "tgn:placetype":[
        "aat:300006191"
    ]
},
  "bbox": [],
  "geometry": {"coordinates":[-76.2167,40.75],"type":"Point"}
}