<<<<<<< HEAD
{
  "id": 2259860,
  "type": "Feature",
  "properties": {
    "tgn:hierarchy":[
        "tgn:2259860",
        "tgn:1000001",
        "tgn:7012149",
        "tgn:2000909",
        "tgn:7007256",
        "tgn:7029392"
    ],
    "tgn:id":2259860,
    "tgn:name":"Coulee Creek",
    "tgn:placetype":[
        "aat:300008706"
    ]
},
  "bbox": [],
  "geometry": {"coordinates":[-92.15,32.65],"type":"Point"}
}
=======
{"geometry":{"type":"Point","coordinates":[-92.150000,32.650000]},"type":"Feature","properties":{"hierarchy":["tgn:2259860","tgn:1000001","tgn:7012149","tgn:2000909","tgn:7007256","tgn:7029392"],"placetype":["aat:300008706"],"id":2259860,"name:xx":"Coulee Creek"}}
>>>>>>> 03f74aca74312dbeaf24d7e61306dd6a786dc3d0
