{
  "id": 1067422,
  "type": "Feature",
  "properties": {
    "tgn:hierarchy":[
        "tgn:1067422",
        "tgn:1000004",
        "tgn:7002085",
        "tgn:1000111",
        "tgn:7029392"
    ],
    "tgn:id":1067422,
    "tgn:name":"Dakunlun",
    "tgn:placetype":[
        "aat:300008347"
    ]
},
  "bbox": [],
  "geometry": {"coordinates":[117.8833,36.5833],"type":"Point"}
}