{
  "id": 7214556,
  "type": "Feature",
  "properties": {
    "tgn:hierarchy":[
        "tgn:7214556",
        "tgn:1000003",
        "tgn:7003677",
        "tgn:7000084",
        "tgn:7029392"
    ],
    "tgn:id":7214556,
    "tgn:name":"Bohren",
    "tgn:placetype":[
        "aat:300000206"
    ]
},
  "bbox": [],
  "geometry": {"coordinates":[7.683333,51.033333],"type":"Point"}
}