{
  "id": 7490446,
  "type": "Feature",
  "properties": {
    "tgn:hierarchy":[
        "tgn:7490446",
        "tgn:1000004",
        "tgn:7489179",
        "tgn:1000141",
        "tgn:7029392"
    ],
    "tgn:id":7490446,
    "tgn:name":"Sanqi Cun",
    "tgn:placetype":[
        "aat:300387173"
    ]
},
  "bbox": [],
  "geometry": {"coordinates":[121.8099,24.6396],"type":"Point"}
}