<<<<<<< HEAD
{
  "id": 7475260,
  "type": "Feature",
  "properties": {
    "tgn:hierarchy":[
        "tgn:7475260",
        "tgn:1000004",
        "tgn:7467799",
        "tgn:1000141",
        "tgn:7029392"
    ],
    "tgn:id":7475260,
    "tgn:name":"Heliu San Qiao",
    "tgn:placetype":[
        "aat:300007836"
    ]
},
  "bbox": [],
  "geometry": {"coordinates":[120.40257,23.977812],"type":"Point"}
}
=======
{"geometry":{"type":"Point","coordinates":[120.402570,23.977812]},"type":"Feature","properties":{"hierarchy":["tgn:7475260","tgn:1000004","tgn:7467799","tgn:1000141","tgn:7029392"],"placetype":["aat:300007836"],"id":7475260,"name:xx":"Heliu San Qiao"}}
>>>>>>> 03f74aca74312dbeaf24d7e61306dd6a786dc3d0
