{
  "id": 7475260,
  "type": "Feature",
  "properties": {
    "tgn:hierarchy":[
        "tgn:7475260",
        "tgn:1000004",
        "tgn:7467799",
        "tgn:1000141",
        "tgn:7029392"
    ],
    "tgn:id":7475260,
    "tgn:name":"Heliu San Qiao",
    "tgn:placetype":[
        "aat:300007836"
    ]
},
  "bbox": [],
  "geometry": {"coordinates":[120.40257,23.977812],"type":"Point"}
}