{
  "id": 1076779,
  "type": "Feature",
  "properties": {
    "tgn:hierarchy":[
        "tgn:1076779",
        "tgn:1000004",
        "tgn:7000198",
        "tgn:7031786",
        "tgn:7029392"
    ],
    "tgn:id":1076779,
    "tgn:name:en":"Roorkee",
    "tgn:placetype":[
        "aat:300008347"
    ]
},
  "bbox": [],
  "geometry": {"coordinates":[77.891258,29.863132],"type":"Point"}
}