{
  "id": 1029713,
  "type": "Feature",
  "properties": {
    "tgn:hierarchy":[
        "tgn:1029713",
        "tgn:7002445",
        "tgn:1000003",
        "tgn:7008134",
        "tgn:7008591",
        "tgn:7029392"
    ],
    "tgn:id":1029713,
    "tgn:name":"Keymer",
    "tgn:placetype":[
        "aat:300008347"
    ]
},
  "bbox": [],
  "geometry": {"coordinates":[-0.1333,50.9167],"type":"Point"}
}