<<<<<<< HEAD
{
  "id": 2762338,
  "type": "Feature",
  "properties": {
    "tgn:hierarchy":[
        "tgn:2762338",
        "tgn:1000001",
        "tgn:7012149",
        "tgn:7007522",
        "tgn:7029392"
    ],
    "tgn:id":2762338,
    "tgn:name":"West Topisaw Creek",
    "tgn:placetype":[
        "aat:300008706"
    ]
},
  "bbox": [],
  "geometry": {"coordinates":[-90.2833,31.4667],"type":"Point"}
}
=======
{"geometry":{"type":"Point","coordinates":[-90.283300,31.466700]},"type":"Feature","properties":{"hierarchy":["tgn:2762338","tgn:1000001","tgn:7012149","tgn:7007522","tgn:7029392"],"placetype":["aat:300008706"],"id":2762338,"name:xx":"West Topisaw Creek"}}
>>>>>>> 03f74aca74312dbeaf24d7e61306dd6a786dc3d0
