{
  "id": 2762338,
  "type": "Feature",
  "properties": {
    "tgn:hierarchy":[
        "tgn:2762338",
        "tgn:1000001",
        "tgn:7012149",
        "tgn:7007522",
        "tgn:7029392"
    ],
    "tgn:id":2762338,
    "tgn:name":"West Topisaw Creek",
    "tgn:placetype":[
        "aat:300008706"
    ]
},
  "bbox": [],
  "geometry": {"coordinates":[-90.2833,31.4667],"type":"Point"}
}