<<<<<<< HEAD
{
  "id": 7369095,
  "type": "Feature",
  "properties": {
    "tgn:hierarchy":[
        "tgn:7369095",
        "tgn:7005587",
        "tgn:1000001",
        "tgn:7005560",
        "tgn:7029392"
    ],
    "tgn:id":7369095,
    "tgn:name":"Ixcatl\u00e1n",
    "tgn:placetype":[
        "aat:300008347"
    ]
},
  "bbox": [],
  "geometry": {"coordinates":[-98.8,20.95],"type":"Point"}
}
=======
{"geometry":{"type":"Point","coordinates":[-98.800000,20.950000]},"type":"Feature","properties":{"hierarchy":["tgn:7369095","tgn:7005587","tgn:1000001","tgn:7005560","tgn:7029392"],"placetype":["aat:300008347"],"id":7369095,"name:xx":"Ixcatl\u00e1n"}}
>>>>>>> 03f74aca74312dbeaf24d7e61306dd6a786dc3d0
