{
  "id": 7567555,
  "type": "Feature",
  "properties": {
    "tgn:hierarchy":[
        "tgn:7567555",
        "tgn:1001828",
        "tgn:1000004",
        "tgn:7000198",
        "tgn:7029392"
    ],
    "tgn:id":7567555,
    "tgn:name:en":"Pogilonpalli",
    "tgn:placetype":[
        "aat:300008347"
    ]
},
  "bbox": [],
  "geometry": {"coordinates":[78.013333,17.990833],"type":"Point"}
}