{
  "id": 2120638,
  "type": "Feature",
  "properties": {
    "tgn:hierarchy":[
        "tgn:2120638",
        "tgn:1000001",
        "tgn:7012149",
        "tgn:2002364",
        "tgn:7007922",
        "tgn:7029392"
    ],
    "tgn:id":2120638,
    "tgn:name":"Arpin",
    "tgn:placetype":[
        "aat:300008347"
    ]
},
  "bbox": [],
  "geometry": {"coordinates":[-90.0333,44.5333],"type":"Point"}
}