{
  "id": 7329961,
  "type": "Feature",
  "properties": {
    "tgn:hierarchy":[
        "tgn:7329961",
        "tgn:7002825",
        "tgn:7016622",
        "tgn:1000003",
        "tgn:1000095",
        "tgn:7029392"
    ],
    "tgn:id":7329961,
    "tgn:name":"Huertas del Palmar",
    "tgn:placetype":[
        "aat:300008347"
    ]
},
  "bbox": [],
  "geometry": {"coordinates":[-15.533333,28.083333],"type":"Point"}
}