{
  "id": 1023453,
  "type": "Feature",
  "properties": {
    "tgn:hierarchy":[
        "tgn:1023453",
        "tgn:1001708",
        "tgn:1000049",
        "tgn:1000002",
        "tgn:7029392"
    ],
    "tgn:id":1023453,
    "tgn:name":"El Peral",
    "tgn:placetype":[
        "aat:300008347"
    ]
},
  "bbox": [],
  "geometry": {"coordinates":[-70.566667,-33.583333],"type":"Point"}
}