<<<<<<< HEAD
{
  "id": 2255226,
  "type": "Feature",
  "properties": {
    "tgn:hierarchy":[
        "tgn:2255226",
        "tgn:1000001",
        "tgn:7016172",
        "tgn:2000123",
        "tgn:7012149",
        "tgn:7029392"
    ],
    "tgn:id":2255226,
    "tgn:name":"Cooper Pond",
    "tgn:placetype":[
        "aat:300006191"
    ]
},
  "bbox": [],
  "geometry": {"coordinates":[-90.9667,35.4],"type":"Point"}
}
=======
{"geometry":{"type":"Point","coordinates":[-90.966700,35.400000]},"type":"Feature","properties":{"hierarchy":["tgn:2255226","tgn:1000001","tgn:7016172","tgn:2000123","tgn:7012149","tgn:7029392"],"placetype":["aat:300006191"],"id":2255226,"name:xx":"Cooper Pond"}}
>>>>>>> 03f74aca74312dbeaf24d7e61306dd6a786dc3d0
