{
  "id": 7580662,
  "type": "Feature",
  "properties": {
    "tgn:hierarchy":[
        "tgn:7580662",
        "tgn:1000004",
        "tgn:7000198",
        "tgn:7031786",
        "tgn:7029392"
    ],
    "tgn:id":7580662,
    "tgn:name:en":"Sult\u0101npur",
    "tgn:placetype":[
        "aat:300008347"
    ]
},
  "bbox": [],
  "geometry": {"coordinates":[78.108937,29.756031],"type":"Point"}
}