{
  "id": 2174603,
  "type": "Feature",
  "properties": {
    "tgn:hierarchy":[
        "tgn:2174603",
        "tgn:1000001",
        "tgn:7022245",
        "tgn:7012149",
        "tgn:7007526",
        "tgn:7029392"
    ],
    "tgn:id":2174603,
    "tgn:name":"Bismark Peak",
    "tgn:placetype":[
        "aat:300008798"
    ]
},
  "bbox": [],
  "geometry": {"coordinates":[-119.5667,39.0833],"type":"Point"}
}