{
  "id": 7241721,
  "type": "Feature",
  "properties": {
    "tgn:hierarchy":[
        "tgn:7241721",
        "tgn:7003456",
        "tgn:1000003",
        "tgn:1000063",
        "tgn:7018236",
        "tgn:7029392"
    ],
    "tgn:id":7241721,
    "tgn:name":"Leemputten",
    "tgn:placetype":[
        "aat:300008347"
    ]
},
  "bbox": [],
  "geometry": {"coordinates":[4.667962,51.076859],"type":"Point"}
}