{
  "id": 2235455,
  "type": "Feature",
  "properties": {
    "tgn:hierarchy":[
        "tgn:2235455",
        "tgn:1000001",
        "tgn:7012149",
        "tgn:2001232",
        "tgn:7007523",
        "tgn:7029392"
    ],
    "tgn:id":2235455,
    "tgn:name":"Chester Jenkins Lake",
    "tgn:placetype":[
        "aat:300006191"
    ]
},
  "bbox": [],
  "geometry": {"coordinates":[-93.25,37.4333],"type":"Point"}
}