{
  "id": 2681013,
  "type": "Feature",
  "properties": {
    "tgn:hierarchy":[
        "tgn:2681013",
        "tgn:1000001",
        "tgn:2001842",
        "tgn:7012149",
        "tgn:7007825",
        "tgn:7029392"
    ],
    "tgn:id":2681013,
    "tgn:name":"South Mapleton Hills",
    "tgn:placetype":[
        "aat:300008347"
    ]
},
  "bbox": [],
  "geometry": {"coordinates":[-84.8333,35.2167],"type":"Point"}
}