{
  "id": 2535458,
  "type": "Feature",
  "properties": {
    "tgn:hierarchy":[
        "tgn:2535458",
        "tgn:1002808",
        "tgn:1000001",
        "tgn:7012149",
        "tgn:7007711",
        "tgn:7029392"
    ],
    "tgn:id":2535458,
    "tgn:name":"Narragansett Terrace",
    "tgn:placetype":[
        "aat:300008347"
    ]
},
  "bbox": [],
  "geometry": {"coordinates":[-71.3833,41.55],"type":"Point"}
}