{
  "id": 2219416,
  "type": "Feature",
  "properties": {
    "tgn:hierarchy":[
        "tgn:2219416",
        "tgn:7002659",
        "tgn:1000001",
        "tgn:7012149",
        "tgn:2000041",
        "tgn:7029392"
    ],
    "tgn:id":2219416,
    "tgn:name":"Cannon Hollow",
    "tgn:placetype":[
        "aat:300008761"
    ]
},
  "bbox": [],
  "geometry": {"coordinates":[-87.1833,34.8333],"type":"Point"}
}