{
  "id": 7584333,
  "type": "Feature",
  "properties": {
    "tgn:hierarchy":[
        "tgn:7584333",
        "tgn:1000004",
        "tgn:7000198",
        "tgn:1001894",
        "tgn:7029392"
    ],
    "tgn:id":7584333,
    "tgn:name:en":"N\u0101noti",
    "tgn:placetype":[
        "aat:300008347"
    ]
},
  "bbox": [],
  "geometry": {"coordinates":[78.011569,24.248768],"type":"Point"}
}