{
  "id": 2160538,
  "type": "Feature",
  "properties": {
    "tgn:hierarchy":[
        "tgn:2160538",
        "tgn:1000001",
        "tgn:7012149",
        "tgn:2002194",
        "tgn:7007919",
        "tgn:7029392"
    ],
    "tgn:id":2160538,
    "tgn:name":"Beetree Branch",
    "tgn:placetype":[
        "aat:300008699"
    ]
},
  "bbox": [],
  "geometry": {"coordinates":[-81.9167,36.8667],"type":"Point"}
}