{
  "id": 7073607,
  "type": "Feature",
  "properties": {
    "tgn:hierarchy":[
        "tgn:7073607",
        "tgn:1000003",
        "tgn:7003687",
        "tgn:7000084",
        "tgn:7029392"
    ],
    "tgn:id":7073607,
    "tgn:name":"Tangeln",
    "tgn:placetype":[
        "aat:300008347"
    ]
},
  "bbox": [],
  "geometry": {"coordinates":[11.016667,52.666667],"type":"Point"}
}