<<<<<<< HEAD
{
  "id": 2255277,
  "type": "Feature",
  "properties": {
    "tgn:hierarchy":[
        "tgn:2255277",
        "tgn:1000001",
        "tgn:7012149",
        "tgn:2001762",
        "tgn:7007712",
        "tgn:7029392"
    ],
    "tgn:id":2255277,
    "tgn:name":"Cooper Swamp",
    "tgn:placetype":[
        "aat:300008699"
    ]
},
  "bbox": [],
  "geometry": {"coordinates":[-80.95,33.45],"type":"Point"}
}
=======
{"geometry":{"type":"Point","coordinates":[-80.950000,33.450000]},"type":"Feature","properties":{"hierarchy":["tgn:2255277","tgn:1000001","tgn:7012149","tgn:2001762","tgn:7007712","tgn:7029392"],"placetype":["aat:300008699"],"id":2255277,"name:xx":"Cooper Swamp"}}
>>>>>>> 03f74aca74312dbeaf24d7e61306dd6a786dc3d0
