{
  "id": 2255277,
  "type": "Feature",
  "properties": {
    "tgn:hierarchy":[
        "tgn:2255277",
        "tgn:1000001",
        "tgn:7012149",
        "tgn:2001762",
        "tgn:7007712",
        "tgn:7029392"
    ],
    "tgn:id":2255277,
    "tgn:name":"Cooper Swamp",
    "tgn:placetype":[
        "aat:300008699"
    ]
},
  "bbox": [],
  "geometry": {"coordinates":[-80.95,33.45],"type":"Point"}
}