{
  "id": 2784530,
  "type": "Feature",
  "properties": {
    "tgn:hierarchy":[
        "tgn:2784530",
        "tgn:1000001",
        "tgn:7012149",
        "tgn:1002860",
        "tgn:7007826",
        "tgn:7029392"
    ],
    "tgn:id":2784530,
    "tgn:name":"Yates Creek",
    "tgn:placetype":[
        "aat:300008706"
    ]
},
  "bbox": [],
  "geometry": {"coordinates":[-95.05,30.5167],"type":"Point"}
}