{
  "id": 2530672,
  "type": "Feature",
  "properties": {
    "tgn:hierarchy":[
        "tgn:2530672",
        "tgn:1000001",
        "tgn:7012149",
        "tgn:7007157",
        "tgn:7014005",
        "tgn:7029392"
    ],
    "tgn:id":2530672,
    "tgn:name":"Muddy Hollow",
    "tgn:placetype":[
        "aat:300386845"
    ]
},
  "bbox": [],
  "geometry": {"coordinates":[-122.8667,38.0333],"type":"Point"}
}