{
  "id": 2664162,
  "type": "Feature",
  "properties": {
    "tgn:hierarchy":[
        "tgn:2664162",
        "tgn:7013388",
        "tgn:1000001",
        "tgn:7012149",
        "tgn:7007517",
        "tgn:7029392"
    ],
    "tgn:id":2664162,
    "tgn:name":"Silver Shield Lake",
    "tgn:placetype":[
        "aat:300006191"
    ]
},
  "bbox": [],
  "geometry": {"coordinates":[-73.0833,42.2333],"type":"Point"}
}