{
  "id": 2520621,
  "type": "Feature",
  "properties": {
    "tgn:hierarchy":[
        "tgn:2520621",
        "tgn:1000001",
        "tgn:7012149",
        "tgn:7007157",
        "tgn:2000185",
        "tgn:7029392"
    ],
    "tgn:id":2520621,
    "tgn:name":"Monkey Rock",
    "tgn:placetype":[
        "aat:300008798"
    ]
},
  "bbox": [],
  "geometry": {"coordinates":[-122.95,39.5333],"type":"Point"}
}