{
  "id": 7041790,
  "type": "Feature",
  "properties": {
    "tgn:hierarchy":[
        "tgn:7041790",
        "tgn:1003459",
        "tgn:1000003",
        "tgn:7002993",
        "tgn:1000080",
        "tgn:7029392"
    ],
    "tgn:id":7041790,
    "tgn:name":"San Floriano del C\u00f3llio",
    "tgn:placetype":[
        "aat:300008347"
    ]
},
  "bbox": [],
  "geometry": {"coordinates":[13.586389,45.982222],"type":"Point"}
}