{
  "id": 2202930,
  "type": "Feature",
  "properties": {
    "tgn:hierarchy":[
        "tgn:2202930",
        "tgn:1000001",
        "tgn:7012149",
        "tgn:2001900",
        "tgn:7007825",
        "tgn:7029392"
    ],
    "tgn:id":2202930,
    "tgn:name":"Buckeye Hollow",
    "tgn:placetype":[
        "aat:300008761"
    ]
},
  "bbox": [],
  "geometry": {"coordinates":[-86.4167,35.3167],"type":"Point"}
}