{
  "id": 2444692,
  "type": "Feature",
  "properties": {
    "tgn:hierarchy":[
        "tgn:2444692",
        "tgn:1000001",
        "tgn:7012149",
        "tgn:2001506",
        "tgn:7007709",
        "tgn:7029392"
    ],
    "tgn:id":2444692,
    "tgn:name":"Legged Lump",
    "tgn:placetype":[
        "aat:300132348"
    ]
},
  "bbox": [],
  "geometry": {"coordinates":[-75.8333,35.1833],"type":"Point"}
}