<<<<<<< HEAD
{
  "id": 2150271,
  "type": "Feature",
  "properties": {
    "tgn:hierarchy":[
        "tgn:2150271",
        "tgn:1000001",
        "tgn:7012149",
        "tgn:7019676",
        "tgn:7007566",
        "tgn:7029392"
    ],
    "tgn:id":2150271,
    "tgn:name":"Basgal Tank",
    "tgn:placetype":[
        "aat:300006191"
    ]
},
  "bbox": [],
  "geometry": {"coordinates":[-108.45,35.3667],"type":"Point"}
}
=======
{"geometry":{"type":"Point","coordinates":[-108.450000,35.366700]},"type":"Feature","properties":{"hierarchy":["tgn:2150271","tgn:1000001","tgn:7012149","tgn:7019676","tgn:7007566","tgn:7029392"],"placetype":["aat:300006191"],"id":2150271,"name:xx":"Basgal Tank"}}
>>>>>>> 03f74aca74312dbeaf24d7e61306dd6a786dc3d0
