{
  "id": 2150271,
  "type": "Feature",
  "properties": {
    "tgn:hierarchy":[
        "tgn:2150271",
        "tgn:1000001",
        "tgn:7012149",
        "tgn:7019676",
        "tgn:7007566",
        "tgn:7029392"
    ],
    "tgn:id":2150271,
    "tgn:name":"Basgal Tank",
    "tgn:placetype":[
        "aat:300006191"
    ]
},
  "bbox": [],
  "geometry": {"coordinates":[-108.45,35.3667],"type":"Point"}
}