{
  "id": 7351814,
  "type": "Feature",
  "properties": {
    "tgn:hierarchy":[
        "tgn:7351814",
        "tgn:1000001",
        "tgn:1001893",
        "tgn:7005560",
        "tgn:7029392"
    ],
    "tgn:id":7351814,
    "tgn:name":"Baromico, Cerro",
    "tgn:placetype":[
        "aat:300008795"
    ]
},
  "bbox": [],
  "geometry": {"coordinates":[-108.533333,27.016667],"type":"Point"}
}