<<<<<<< HEAD
{
  "id": 7351814,
  "type": "Feature",
  "properties": {
    "tgn:hierarchy":[
        "tgn:7351814",
        "tgn:1000001",
        "tgn:1001893",
        "tgn:7005560",
        "tgn:7029392"
    ],
    "tgn:id":7351814,
    "tgn:name":"Baromico, Cerro",
    "tgn:placetype":[
        "aat:300008795"
    ]
},
  "bbox": [],
  "geometry": {"coordinates":[-108.533333,27.016667],"type":"Point"}
}
=======
{"geometry":{"type":"Point","coordinates":[-108.533333,27.016667]},"type":"Feature","properties":{"hierarchy":["tgn:7351814","tgn:1000001","tgn:1001893","tgn:7005560","tgn:7029392"],"placetype":["aat:300008795"],"id":7351814,"name:xx":"Baromico, Cerro"}}
>>>>>>> 03f74aca74312dbeaf24d7e61306dd6a786dc3d0
