{
  "id": 1116925,
  "type": "Feature",
  "properties": {
    "tgn:hierarchy":[
        "tgn:1116925",
        "tgn:1000004",
        "tgn:7002081",
        "tgn:1000111",
        "tgn:7029392"
    ],
    "tgn:id":1116925,
    "tgn:name":"Kuncheng Hu",
    "tgn:placetype":[
        "aat:300008680"
    ]
},
  "bbox": [],
  "geometry": {"coordinates":[120.75,31.5833],"type":"Point"}
}