{
  "id": 2070210,
  "type": "Feature",
  "properties": {
    "tgn:hierarchy":[
        "tgn:2070210",
        "tgn:1000001",
        "tgn:7012149",
        "tgn:1002604",
        "tgn:7007568",
        "tgn:7029392"
    ],
    "tgn:id":2070210,
    "tgn:name":"Libertypole",
    "tgn:placetype":[
        "aat:300008347",
        "aat:300387210"
    ]
},
  "bbox": [],
  "geometry": {"coordinates":[-77.6333,42.6333],"type":"Point"}
}