{
  "id": 7269131,
  "type": "Feature",
  "properties": {
    "tgn:hierarchy":[
        "tgn:7269131",
        "tgn:7003616",
        "tgn:1000003",
        "tgn:7016845",
        "tgn:7029392"
    ],
    "tgn:id":7269131,
    "tgn:name:nl":"Prinsenwijk",
    "tgn:placetype":[
        "aat:300006075"
    ]
},
  "bbox": [],
  "geometry": {"coordinates":[5.983333,52.933333],"type":"Point"}
}