{
  "id": 1074229,
  "type": "Feature",
  "properties": {
    "tgn:hierarchy":[
        "tgn:1074229",
        "tgn:1000004",
        "tgn:7001745",
        "tgn:1000111",
        "tgn:7029392"
    ],
    "tgn:id":1074229,
    "tgn:name":"Zuotema",
    "tgn:placetype":[
        "aat:300008347"
    ]
},
  "bbox": [],
  "geometry": {"coordinates":[80.75,35.8333],"type":"Point"}
}