{
  "id": 2436347,
  "type": "Feature",
  "properties": {
    "tgn:hierarchy":[
        "tgn:2436347",
        "tgn:1000001",
        "tgn:7012149",
        "tgn:2000896",
        "tgn:7007256",
        "tgn:7029392"
    ],
    "tgn:id":2436347,
    "tgn:name":"Kib Bayou",
    "tgn:placetype":[
        "aat:300008699"
    ]
},
  "bbox": [],
  "geometry": {"coordinates":[-93.2833,31.3833],"type":"Point"}
}