{
  "id": 2652814,
  "type": "Feature",
  "properties": {
    "tgn:hierarchy":[
        "tgn:2652814",
        "tgn:1000001",
        "tgn:7012149",
        "tgn:2000709",
        "tgn:7007254",
        "tgn:7029392"
    ],
    "tgn:id":2652814,
    "tgn:name":"Service Lake",
    "tgn:placetype":[
        "aat:300006191"
    ]
},
  "bbox": [],
  "geometry": {"coordinates":[-95.0833,37.2833],"type":"Point"}
}