{
  "id": 1051772,
  "type": "Feature",
  "properties": {
    "tgn:hierarchy":[
        "tgn:1051772",
        "tgn:1000004",
        "tgn:7011457",
        "tgn:7014786",
        "tgn:7029392"
    ],
    "tgn:id":1051772,
    "tgn:name":"Zhamankak",
    "tgn:placetype":[
        "aat:300008347"
    ]
},
  "bbox": [],
  "geometry": {"coordinates":[48.8167,48.9667],"type":"Point"}
}