{
  "id": 7334886,
  "type": "Feature",
  "properties": {
    "tgn:hierarchy":[
        "tgn:7334886",
        "tgn:1001439",
        "tgn:1000003",
        "tgn:7002797",
        "tgn:1000095",
        "tgn:7029392"
    ],
    "tgn:id":7334886,
    "tgn:name":"Garabitos, Morra de los",
    "tgn:placetype":[
        "aat:300266640"
    ]
},
  "bbox": [],
  "geometry": {"coordinates":[-1.116667,37.583333],"type":"Point"}
}