<<<<<<< HEAD
{
  "id": 7246833,
  "type": "Feature",
  "properties": {
    "tgn:hierarchy":[
        "tgn:7246833",
        "tgn:7018238",
        "tgn:1000003",
        "tgn:1000063",
        "tgn:4012014",
        "tgn:7029392"
    ],
    "tgn:id":7246833,
    "tgn:name":"Ferme Croissant",
    "tgn:placetype":[
        "aat:300000206"
    ]
},
  "bbox": [],
  "geometry": {"coordinates":[4.45,50.65],"type":"Point"}
}
=======
{"geometry":{"type":"Point","coordinates":[4.450000,50.650000]},"type":"Feature","properties":{"hierarchy":["tgn:7246833","tgn:7018238","tgn:1000003","tgn:1000063","tgn:4012014","tgn:7029392"],"placetype":["aat:300000206"],"id":7246833,"name:xx":"Ferme Croissant"}}
>>>>>>> 03f74aca74312dbeaf24d7e61306dd6a786dc3d0
