<<<<<<< HEAD
{
  "id": 7055494,
  "type": "Feature",
  "properties": {
    "tgn:hierarchy":[
        "tgn:7055494",
        "tgn:7003166",
        "tgn:1000003",
        "tgn:7009760",
        "tgn:1000080",
        "tgn:7029392"
    ],
    "tgn:id":7055494,
    "tgn:name":"Podere Dottrina",
    "tgn:placetype":[
        "aat:300008347"
    ]
},
  "bbox": [],
  "geometry": {"coordinates":[10.6,43.383333],"type":"Point"}
}
=======
{"geometry":{"type":"Point","coordinates":[10.600000,43.383333]},"type":"Feature","properties":{"hierarchy":["tgn:7055494","tgn:7003166","tgn:1000003","tgn:7009760","tgn:1000080","tgn:7029392"],"placetype":["aat:300008347"],"id":7055494,"name:xx":"Podere Dottrina"}}
>>>>>>> 03f74aca74312dbeaf24d7e61306dd6a786dc3d0
