{
  "id": 2476877,
  "type": "Feature",
  "properties": {
    "tgn:hierarchy":[
        "tgn:2476877",
        "tgn:1000001",
        "tgn:2001812",
        "tgn:7012149",
        "tgn:7007713",
        "tgn:7029392"
    ],
    "tgn:id":2476877,
    "tgn:name":"Lyman",
    "tgn:placetype":[
        "aat:300008347"
    ]
},
  "bbox": [],
  "geometry": {"coordinates":[-99.7333,43.8667],"type":"Point"}
}