{
  "id": 1044113,
  "type": "Feature",
  "properties": {
    "tgn:hierarchy":[
        "tgn:1044113",
        "tgn:7005126",
        "tgn:1000003",
        "tgn:7003120",
        "tgn:1000080",
        "tgn:7029392"
    ],
    "tgn:id":1044113,
    "tgn:name":"Cavallermaggiore",
    "tgn:placetype":[
        "aat:300008347"
    ]
},
  "bbox": [],
  "geometry": {"coordinates":[7.683333,44.716667],"type":"Point"}
}