{
  "id": 7358826,
  "type": "Feature",
  "properties": {
    "tgn:hierarchy":[
        "tgn:7358826",
        "tgn:1000001",
        "tgn:1001960",
        "tgn:7005560",
        "tgn:7029392"
    ],
    "tgn:id":7358826,
    "tgn:name":"Colorado, Cerro",
    "tgn:placetype":[
        "aat:300008795"
    ]
},
  "bbox": [],
  "geometry": {"coordinates":[-109.916667,28.416667],"type":"Point"}
}