<<<<<<< HEAD
{
  "id": 2768475,
  "type": "Feature",
  "properties": {
    "tgn:hierarchy":[
        "tgn:2768475",
        "tgn:1000001",
        "tgn:7012149",
        "tgn:2001770",
        "tgn:7007712",
        "tgn:7029392"
    ],
    "tgn:id":2768475,
    "tgn:name":"Whiteville Park",
    "tgn:placetype":[
        "aat:300008347"
    ]
},
  "bbox": [],
  "geometry": {"coordinates":[-80.9333,35.0],"type":"Point"}
}
=======
{"geometry":{"type":"Point","coordinates":[-80.933300,35.000000]},"type":"Feature","properties":{"hierarchy":["tgn:2768475","tgn:1000001","tgn:7012149","tgn:2001770","tgn:7007712","tgn:7029392"],"placetype":["aat:300008347"],"id":2768475,"name:xx":"Whiteville Park"}}
>>>>>>> 03f74aca74312dbeaf24d7e61306dd6a786dc3d0
