{
  "id": 7422469,
  "type": "Feature",
  "properties": {
    "tgn:hierarchy":[
        "tgn:7422469",
        "tgn:1000001",
        "tgn:1001960",
        "tgn:7005560",
        "tgn:7029392"
    ],
    "tgn:id":7422469,
    "tgn:name":"San Lazaro",
    "tgn:placetype":[
        "aat:300008347"
    ]
},
  "bbox": [],
  "geometry": {"coordinates":[-110.466667,27.733333],"type":"Point"}
}