{
  "id": 1004176,
  "type": "Feature",
  "properties": {
    "tgn:hierarchy":[
        "tgn:1004176",
        "tgn:7013962",
        "tgn:1000001",
        "tgn:7012149",
        "tgn:7015717",
        "tgn:7029392"
    ],
    "tgn:id":1004176,
    "tgn:name":"Brookland",
    "tgn:placetype":[
        "aat:300000745"
    ]
},
  "bbox": [],
  "geometry": {"coordinates":[-76.9833,38.9167],"type":"Point"}
}