{
  "id": 2755343,
  "type": "Feature",
  "properties": {
    "tgn:hierarchy":[
        "tgn:2755343",
        "tgn:2000856",
        "tgn:1000001",
        "tgn:7012149",
        "tgn:7007256",
        "tgn:7029392"
    ],
    "tgn:id":2755343,
    "tgn:name":"Weber City",
    "tgn:placetype":[
        "aat:300008347"
    ]
},
  "bbox": [],
  "geometry": {"coordinates":[-90.8833,30.2167],"type":"Point"}
}