{
  "id": 7469459,
  "type": "Feature",
  "properties": {
    "tgn:hierarchy":[
        "tgn:7469459",
        "tgn:1000004",
        "tgn:7001009",
        "tgn:1000141",
        "tgn:7029392"
    ],
    "tgn:id":7469459,
    "tgn:name":"Fushou Shanzhuang",
    "tgn:placetype":[
        "aat:300008347"
    ]
},
  "bbox": [],
  "geometry": {"coordinates":[121.233333,24.233333],"type":"Point"}
}