{
  "id": 7521896,
  "type": "Feature",
  "properties": {
    "tgn:hierarchy":[
        "tgn:7521896",
        "tgn:7001242",
        "tgn:7001311",
        "tgn:7016833",
        "tgn:7029392"
    ],
    "tgn:id":7521896,
    "tgn:name:en":"Abu Maraw\u00e2t",
    "tgn:placetype":[
        "aat:300055621"
    ]
},
  "bbox": [],
  "geometry": {"coordinates":[33.666667,26.566667],"type":"Point"}
}