{
  "id": 2552157,
  "type": "Feature",
  "properties": {
    "tgn:hierarchy":[
        "tgn:2552157",
        "tgn:1002933",
        "tgn:1000001",
        "tgn:7012149",
        "tgn:7007239",
        "tgn:7029392"
    ],
    "tgn:id":2552157,
    "tgn:name":"Number One, Prong",
    "tgn:placetype":[
        "aat:300008699"
    ]
},
  "bbox": [],
  "geometry": {"coordinates":[-75.4667,38.7833],"type":"Point"}
}