{
  "id": 2519062,
  "type": "Feature",
  "properties": {
    "tgn:hierarchy":[
        "tgn:2519062",
        "tgn:1000001",
        "tgn:1002326",
        "tgn:7012149",
        "tgn:7007706",
        "tgn:7029392"
    ],
    "tgn:id":2519062,
    "tgn:name":"Moats",
    "tgn:placetype":[
        "aat:300008347"
    ]
},
  "bbox": [],
  "geometry": {"coordinates":[-84.5167,41.3167],"type":"Point"}
}