{
  "id": 2480012,
  "type": "Feature",
  "properties": {
    "tgn:hierarchy":[
        "tgn:2480012",
        "tgn:2002365",
        "tgn:1000001",
        "tgn:7012149",
        "tgn:7007923",
        "tgn:7029392"
    ],
    "tgn:id":2480012,
    "tgn:name":"Lake Hattie Supply Ditch Number 2",
    "tgn:placetype":[
        "aat:300006075"
    ]
},
  "bbox": [],
  "geometry": {"coordinates":[-105.95,41.25],"type":"Point"}
}