<<<<<<< HEAD
{
  "id": 7029037,
  "type": "Feature",
  "properties": {
    "tgn:hierarchy":[
        "tgn:7029037",
        "tgn:7002445",
        "tgn:1000003",
        "tgn:7019057",
        "tgn:7008591",
        "tgn:7029392"
    ],
    "tgn:id":7029037,
    "tgn:name":"Kiplingcotes",
    "tgn:placetype":[
        "aat:300020756",
        "aat:300008347",
        "aat:300167671",
        "aat:300008372"
    ]
},
  "bbox": [],
  "geometry": {"coordinates":[-0.585,53.885],"type":"Point"}
}
=======
{"geometry":{"type":"Point","coordinates":[-0.585000,53.885000]},"type":"Feature","properties":{"hierarchy":["tgn:7029037","tgn:7002445","tgn:1000003","tgn:7019057","tgn:7008591","tgn:7029392"],"placetype":["aat:300020756","aat:300008347","aat:300167671","aat:300008372"],"id":7029037,"name:xx":"Kiplingcotes"}}
>>>>>>> 03f74aca74312dbeaf24d7e61306dd6a786dc3d0
