{
  "id": 2199577,
  "type": "Feature",
  "properties": {
    "tgn:hierarchy":[
        "tgn:2199577",
        "tgn:1000001",
        "tgn:7012149",
        "tgn:1003042",
        "tgn:7007920",
        "tgn:7029392"
    ],
    "tgn:id":2199577,
    "tgn:name":"Brush Creek",
    "tgn:placetype":[
        "aat:300008706"
    ]
},
  "bbox": [],
  "geometry": {"coordinates":[-120.9167,46.1833],"type":"Point"}
}