{
  "id": 7454042,
  "type": "Feature",
  "properties": {
    "tgn:hierarchy":[
        "tgn:7454042",
        "tgn:7002445",
        "tgn:1000003",
        "tgn:7008145",
        "tgn:7008591",
        "tgn:7029392"
    ],
    "tgn:id":7454042,
    "tgn:name:en":"Bushey Hall",
    "tgn:placetype":[
        "aat:300004792"
    ]
},
  "bbox": [],
  "geometry": {"coordinates":[-0.383333,51.666667],"type":"Point"}
}