{
  "id": 7090039,
  "type": "Feature",
  "properties": {
    "tgn:hierarchy":[
        "tgn:7090039",
        "tgn:1000003",
        "tgn:7003676",
        "tgn:7000084",
        "tgn:7029392"
    ],
    "tgn:id":7090039,
    "tgn:name":"Verbindungshafen",
    "tgn:placetype":[
        "aat:300008678"
    ]
},
  "bbox": [],
  "geometry": {"coordinates":[8.55,53.566667],"type":"Point"}
}