{
  "id": 7497519,
  "type": "Feature",
  "properties": {
    "tgn:hierarchy":[
        "tgn:7497519",
        "tgn:1000004",
        "tgn:7001009",
        "tgn:1000141",
        "tgn:7029392"
    ],
    "tgn:id":7497519,
    "tgn:name":"Taiyu Qiao",
    "tgn:placetype":[
        "aat:300007836"
    ]
},
  "bbox": [],
  "geometry": {"coordinates":[120.6607,24.2005],"type":"Point"}
}