{
  "id": 2692460,
  "type": "Feature",
  "properties": {
    "tgn:hierarchy":[
        "tgn:2692460",
        "tgn:1000001",
        "tgn:7012149",
        "tgn:7007250",
        "tgn:7029392"
    ],
    "tgn:id":2692460,
    "tgn:name":"Steamboat Creek",
    "tgn:placetype":[
        "aat:300008706"
    ]
},
  "bbox": [],
  "geometry": {"coordinates":[-115.7167,45.1667],"type":"Point"}
}