{
  "id": 2368355,
  "type": "Feature",
  "properties": {
    "tgn:hierarchy":[
        "tgn:2368355",
        "tgn:1000001",
        "tgn:2001485",
        "tgn:7012149",
        "tgn:7007709",
        "tgn:7029392"
    ],
    "tgn:id":2368355,
    "tgn:name":"Guide",
    "tgn:placetype":[
        "aat:300008347"
    ]
},
  "bbox": [],
  "geometry": {"coordinates":[-78.7333,34.0667],"type":"Point"}
}