{
  "id": 2171149,
  "type": "Feature",
  "properties": {
    "tgn:hierarchy":[
        "tgn:2171149",
        "tgn:1000001",
        "tgn:7012149",
        "tgn:2001868",
        "tgn:7007825",
        "tgn:7029392"
    ],
    "tgn:id":2171149,
    "tgn:name":"Big Spring",
    "tgn:placetype":[
        "aat:300008697"
    ]
},
  "bbox": [],
  "geometry": {"coordinates":[-83.1333,36.2333],"type":"Point"}
}