{
  "id": 2592655,
  "type": "Feature",
  "properties": {
    "tgn:hierarchy":[
        "tgn:2592655",
        "tgn:1000001",
        "tgn:7012149",
        "tgn:2001286",
        "tgn:7007524",
        "tgn:7029392"
    ],
    "tgn:id":2592655,
    "tgn:name":"Poorman Basin",
    "tgn:placetype":[
        "aat:300386845"
    ]
},
  "bbox": [],
  "geometry": {"coordinates":[-114.9333,48.95],"type":"Point"}
}