{
  "id": 2240325,
  "type": "Feature",
  "properties": {
    "tgn:hierarchy":[
        "tgn:2240325",
        "tgn:1000001",
        "tgn:7006451",
        "tgn:2000095",
        "tgn:7012149",
        "tgn:7029392"
    ],
    "tgn:id":2240325,
    "tgn:name":"Cistern Tank",
    "tgn:placetype":[
        "aat:300006191"
    ]
},
  "bbox": [],
  "geometry": {"coordinates":[-109.45,33.1833],"type":"Point"}
}