{
  "id": 2611363,
  "type": "Feature",
  "properties": {
    "tgn:hierarchy":[
        "tgn:2611363",
        "tgn:1000001",
        "tgn:2001810",
        "tgn:7012149",
        "tgn:7007713",
        "tgn:7029392"
    ],
    "tgn:id":2611363,
    "tgn:name":"Red Lake",
    "tgn:placetype":[
        "aat:300008680"
    ]
},
  "bbox": [],
  "geometry": {"coordinates":[-103.95,44.35],"type":"Point"}
}