{
  "id": 1103056,
  "type": "Feature",
  "properties": {
    "tgn:hierarchy":[
        "tgn:1103056",
        "tgn:1000001",
        "tgn:7012149",
        "tgn:1002298",
        "tgn:7007157",
        "tgn:7029392"
    ],
    "tgn:id":1103056,
    "tgn:name":"Round Top Regional Park",
    "tgn:placetype":[
        "aat:300008187"
    ]
},
  "bbox": [],
  "geometry": {"coordinates":[-122.1833,37.8333],"type":"Point"}
}