{
  "id": 2671606,
  "type": "Feature",
  "properties": {
    "tgn:hierarchy":[
        "tgn:2671606",
        "tgn:2001563",
        "tgn:1000001",
        "tgn:7012149",
        "tgn:7007705",
        "tgn:7029392"
    ],
    "tgn:id":2671606,
    "tgn:name":"Smith Lake",
    "tgn:placetype":[
        "aat:300008680"
    ]
},
  "bbox": [],
  "geometry": {"coordinates":[-102.3833,48.55],"type":"Point"}
}