{
  "id": 2680307,
  "type": "Feature",
  "properties": {
    "tgn:hierarchy":[
        "tgn:2680307",
        "tgn:1000001",
        "tgn:7012149",
        "tgn:7007157",
        "tgn:7029392"
    ],
    "tgn:id":2680307,
    "tgn:name":"South Fork Valley",
    "tgn:placetype":[
        "aat:300008761"
    ]
},
  "bbox": [],
  "geometry": {"coordinates":[-118.1667,35.7167],"type":"Point"}
}