{
  "id": 2636229,
  "type": "Feature",
  "properties": {
    "tgn:hierarchy":[
        "tgn:2636229",
        "tgn:1000001",
        "tgn:7006451",
        "tgn:7012149",
        "tgn:2000099",
        "tgn:7029392"
    ],
    "tgn:id":2636229,
    "tgn:name":"Saddle Tank",
    "tgn:placetype":[
        "aat:300006191"
    ]
},
  "bbox": [],
  "geometry": {"coordinates":[-110.7333,34.2833],"type":"Point"}
}