{
  "id": 7332610,
  "type": "Feature",
  "properties": {
    "tgn:hierarchy":[
        "tgn:7332610",
        "tgn:7002810",
        "tgn:7001158",
        "tgn:1000003",
        "tgn:1000095",
        "tgn:7029392"
    ],
    "tgn:id":7332610,
    "tgn:name":"La Nave",
    "tgn:placetype":[
        "aat:300008347"
    ]
},
  "bbox": [],
  "geometry": {"coordinates":[-2.973067,42.693601],"type":"Point"}
}