{
  "id": 2556496,
  "type": "Feature",
  "properties": {
    "tgn:hierarchy":[
        "tgn:2556496",
        "tgn:1000001",
        "tgn:7012149",
        "tgn:2002250",
        "tgn:7007920",
        "tgn:7029392"
    ],
    "tgn:id":2556496,
    "tgn:name":"Old Baldy",
    "tgn:placetype":[
        "aat:300008798"
    ]
},
  "bbox": [],
  "geometry": {"coordinates":[-118.0333,48.35],"type":"Point"}
}