<<<<<<< HEAD
{
  "id": 2337742,
  "type": "Feature",
  "properties": {
    "tgn:hierarchy":[
        "tgn:2337742",
        "tgn:1000001",
        "tgn:2001009",
        "tgn:7012149",
        "tgn:7007521",
        "tgn:7029392"
    ],
    "tgn:id":2337742,
    "tgn:name":"Fox Creek",
    "tgn:placetype":[
        "aat:300008706"
    ]
},
  "bbox": [],
  "geometry": {"coordinates":[-94.6167,47.3667],"type":"Point"}
}
=======
{"geometry":{"type":"Point","coordinates":[-94.616700,47.366700]},"type":"Feature","properties":{"hierarchy":["tgn:2337742","tgn:1000001","tgn:2001009","tgn:7012149","tgn:7007521","tgn:7029392"],"placetype":["aat:300008706"],"id":2337742,"name:xx":"Fox Creek"}}
>>>>>>> 03f74aca74312dbeaf24d7e61306dd6a786dc3d0
