{
  "id": 1113342,
  "type": "Feature",
  "properties": {
    "tgn:hierarchy":[
        "tgn:1113342",
        "tgn:7018590",
        "tgn:7005559",
        "tgn:1000001",
        "tgn:7005556",
        "tgn:7029392"
    ],
    "tgn:id":1113342,
    "tgn:name":"Long Bay",
    "tgn:placetype":[
        "aat:300132316"
    ]
},
  "bbox": [],
  "geometry": {"coordinates":[-76.316,18.108],"type":"Point"}
}