{
  "id": 1073459,
  "type": "Feature",
  "properties": {
    "tgn:hierarchy":[
        "tgn:1073459",
        "tgn:1000004",
        "tgn:1001390",
        "tgn:1000111",
        "tgn:7029392"
    ],
    "tgn:id":1073459,
    "tgn:name":"Yaojiawopeng",
    "tgn:placetype":[
        "aat:300008347"
    ]
},
  "bbox": [],
  "geometry": {"coordinates":[122.4167,41.7833],"type":"Point"}
}