{
  "id": 2005403,
  "type": "Feature",
  "properties": {
    "tgn:hierarchy":[
        "tgn:2005403",
        "tgn:7002659",
        "tgn:1000001",
        "tgn:7012149",
        "tgn:7021514",
        "tgn:7029392"
    ],
    "tgn:id":2005403,
    "tgn:name":"Sulphur Springs",
    "tgn:placetype":[
        "aat:300008347",
        "aat:300387210"
    ]
},
  "bbox": [],
  "geometry": {"coordinates":[-85.5667,34.6833],"type":"Point"}
}