{
  "id": 7311384,
  "type": "Feature",
  "properties": {
    "tgn:hierarchy":[
        "tgn:7311384",
        "tgn:1001708",
        "tgn:1000049",
        "tgn:1000002",
        "tgn:7029392"
    ],
    "tgn:id":7311384,
    "tgn:name":"Monserrat",
    "tgn:placetype":[
        "aat:300000745"
    ]
},
  "bbox": [],
  "geometry": {"coordinates":[-70.633333,-33.416667],"type":"Point"}
}