{
  "id": 2513423,
  "type": "Feature",
  "properties": {
    "tgn:hierarchy":[
        "tgn:2513423",
        "tgn:7002659",
        "tgn:1000001",
        "tgn:7012149",
        "tgn:2000047",
        "tgn:7029392"
    ],
    "tgn:id":2513423,
    "tgn:name":"Mill Hollow Cave",
    "tgn:placetype":[
        "aat:300008746"
    ]
},
  "bbox": [],
  "geometry": {"coordinates":[-86.25,34.4667],"type":"Point"}
}