{
  "id": 7458111,
  "type": "Feature",
  "properties": {
    "tgn:hierarchy":[
        "tgn:7458111",
        "tgn:7002444",
        "tgn:1000003",
        "tgn:7008082",
        "tgn:7008591",
        "tgn:7029392"
    ],
    "tgn:id":7458111,
    "tgn:name:en":"Nigg Bay",
    "tgn:placetype":[
        "aat:300132316"
    ]
},
  "bbox": [],
  "geometry": {"coordinates":[-4.05,57.716667],"type":"Point"}
}