{
  "id": 2377968,
  "type": "Feature",
  "properties": {
    "tgn:hierarchy":[
        "tgn:2377968",
        "tgn:2000919",
        "tgn:1000001",
        "tgn:7012149",
        "tgn:7007515",
        "tgn:7029392"
    ],
    "tgn:id":2377968,
    "tgn:name":"Harris Brook",
    "tgn:placetype":[
        "aat:300008699"
    ]
},
  "bbox": [],
  "geometry": {"coordinates":[-68.3333,47.1667],"type":"Point"}
}