{
  "id": 2758625,
  "type": "Feature",
  "properties": {
    "tgn:hierarchy":[
        "tgn:2758625",
        "tgn:1000001",
        "tgn:7012149",
        "tgn:2000209",
        "tgn:7007158",
        "tgn:7029392"
    ],
    "tgn:id":2758625,
    "tgn:name":"West Creek",
    "tgn:placetype":[
        "aat:300008347"
    ]
},
  "bbox": [],
  "geometry": {"coordinates":[-105.15,39.15],"type":"Point"}
}