{
  "id": 2677417,
  "type": "Feature",
  "properties": {
    "tgn:hierarchy":[
        "tgn:2677417",
        "tgn:1000001",
        "tgn:7012149",
        "tgn:7007708",
        "tgn:7029392"
    ],
    "tgn:id":2677417,
    "tgn:name":"South Canyon",
    "tgn:placetype":[
        "aat:300008761"
    ]
},
  "bbox": [],
  "geometry": {"coordinates":[-118.6667,45.3167],"type":"Point"}
}