{
  "id": 2455353,
  "type": "Feature",
  "properties": {
    "tgn:hierarchy":[
        "tgn:2455353",
        "tgn:1000001",
        "tgn:2001473",
        "tgn:7012149",
        "tgn:7007709",
        "tgn:7029392"
    ],
    "tgn:id":2455353,
    "tgn:name":"Little Fork",
    "tgn:placetype":[
        "aat:300008699"
    ]
},
  "bbox": [],
  "geometry": {"coordinates":[-82.2833,35.6833],"type":"Point"}
}