{
  "id": 2460510,
  "type": "Feature",
  "properties": {
    "tgn:hierarchy":[
        "tgn:2460510",
        "tgn:1000001",
        "tgn:7012149",
        "tgn:7007709",
        "tgn:7029392"
    ],
    "tgn:id":2460510,
    "tgn:name":"Little Sandy Creek",
    "tgn:placetype":[
        "aat:300008706"
    ]
},
  "bbox": [],
  "geometry": {"coordinates":[-81.0167,36.3667],"type":"Point"}
}