<<<<<<< HEAD
{
  "id": 7059044,
  "type": "Feature",
  "properties": {
    "tgn:hierarchy":[
        "tgn:7059044",
        "tgn:7003005",
        "tgn:7003014",
        "tgn:1000003",
        "tgn:1000080",
        "tgn:7029392"
    ],
    "tgn:id":7059044,
    "tgn:name":"Stazione di Albanella",
    "tgn:placetype":[
        "aat:300007783"
    ]
},
  "bbox": [],
  "geometry": {"coordinates":[15.0,40.5],"type":"Point"}
}
=======
{"geometry":{"type":"Point","coordinates":[15.000000,40.500000]},"type":"Feature","properties":{"hierarchy":["tgn:7059044","tgn:7003005","tgn:7003014","tgn:1000003","tgn:1000080","tgn:7029392"],"placetype":["aat:300007783"],"id":7059044,"name:xx":"Stazione di Albanella"}}
>>>>>>> 03f74aca74312dbeaf24d7e61306dd6a786dc3d0
