{
  "id": 7078969,
  "type": "Feature",
  "properties": {
    "tgn:hierarchy":[
        "tgn:7078969",
        "tgn:7003692",
        "tgn:1000003",
        "tgn:7000084",
        "tgn:7029392"
    ],
    "tgn:id":7078969,
    "tgn:name":"Wolfskreut",
    "tgn:placetype":[
        "aat:300008347"
    ]
},
  "bbox": [],
  "geometry": {"coordinates":[10.066667,49.333333],"type":"Point"}
}