<<<<<<< HEAD
{
  "id": 7026150,
  "type": "Feature",
  "properties": {
    "tgn:hierarchy":[
        "tgn:7026150",
        "tgn:1000773",
        "tgn:1000002",
        "tgn:1000056",
        "tgn:7029392"
    ],
    "tgn:id":7026150,
    "tgn:name":"Tacahuay, Quebrada",
    "tgn:placetype":[
        "aat:300266554"
    ]
},
  "bbox": [],
  "geometry": {"coordinates":[-71.1167,-17.8167],"type":"Point"}
}
=======
{"geometry":{"type":"Point","coordinates":[-71.116700,-17.816700]},"type":"Feature","properties":{"hierarchy":["tgn:7026150","tgn:1000773","tgn:1000002","tgn:1000056","tgn:7029392"],"placetype":["aat:300266554"],"id":7026150,"name:xx":"Tacahuay, Quebrada"}}
>>>>>>> 03f74aca74312dbeaf24d7e61306dd6a786dc3d0
