{
  "id": 2127164,
  "type": "Feature",
  "properties": {
    "tgn:hierarchy":[
        "tgn:2127164",
        "tgn:1000001",
        "tgn:7012149",
        "tgn:2002061",
        "tgn:7007826",
        "tgn:7029392"
    ],
    "tgn:id":2127164,
    "tgn:name":"Aikin Grove",
    "tgn:placetype":[
        "aat:300008347"
    ]
},
  "bbox": [],
  "geometry": {"coordinates":[-95.0333,33.55],"type":"Point"}
}