{
  "id": 7184111,
  "type": "Feature",
  "properties": {
    "tgn:hierarchy":[
        "tgn:7184111",
        "tgn:1000003",
        "tgn:7003677",
        "tgn:7000084",
        "tgn:7029392"
    ],
    "tgn:id":7184111,
    "tgn:name":"Gie\u00dfelbach",
    "tgn:placetype":[
        "aat:300008347"
    ]
},
  "bbox": [],
  "geometry": {"coordinates":[7.45,50.85],"type":"Point"}
}