{
  "id": 7506597,
  "type": "Feature",
  "properties": {
    "tgn:hierarchy":[
        "tgn:7506597",
        "tgn:1009227",
        "tgn:1000226",
        "tgn:7016822",
        "tgn:1000006",
        "tgn:7029392"
    ],
    "tgn:id":7506597,
    "tgn:name:en":"Roa Stream",
    "tgn:placetype":[
        "aat:300008699"
    ]
},
  "bbox": [],
  "geometry": {"coordinates":[167.033333,-45.716667],"type":"Point"}
}