{
  "id": 2482988,
  "type": "Feature",
  "properties": {
    "tgn:hierarchy":[
        "tgn:2482988",
        "tgn:1000001",
        "tgn:7012149",
        "tgn:2002124",
        "tgn:7007827",
        "tgn:7029392"
    ],
    "tgn:id":2482988,
    "tgn:name":"Larsen Ditch",
    "tgn:placetype":[
        "aat:300006075"
    ]
},
  "bbox": [],
  "geometry": {"coordinates":[-109.9667,40.4667],"type":"Point"}
}