{
  "id": 2063299,
  "type": "Feature",
  "properties": {
    "tgn:hierarchy":[
        "tgn:2063299",
        "tgn:1000001",
        "tgn:2001426",
        "tgn:7012149",
        "tgn:7007564",
        "tgn:7029392"
    ],
    "tgn:id":2063299,
    "tgn:name":"Center Strafford",
    "tgn:placetype":[
        "aat:300008347"
    ]
},
  "bbox": [],
  "geometry": {"coordinates":[-71.1167,43.2667],"type":"Point"}
}