{
  "id": 2117422,
  "type": "Feature",
  "properties": {
    "tgn:hierarchy":[
        "tgn:2117422",
        "tgn:1000001",
        "tgn:7012149",
        "tgn:2002283",
        "tgn:7013961",
        "tgn:7029392"
    ],
    "tgn:id":2117422,
    "tgn:name":"Berkeley Springs",
    "tgn:placetype":[
        "aat:300008347"
    ]
},
  "bbox": [],
  "geometry": {"coordinates":[-78.2167,39.6167],"type":"Point"}
}