{
  "id": 1002903,
  "type": "Feature",
  "properties": {
    "tgn:hierarchy":[
        "tgn:1002903",
        "tgn:1000001",
        "tgn:7012149",
        "tgn:7007565",
        "tgn:7029392"
    ],
    "tgn:id":1002903,
    "tgn:name":"Somerset",
    "tgn:placetype":[
        "aat:300387145",
        "aat:300000771"
    ]
},
  "bbox": [],
  "geometry": {"coordinates":[-74.55,40.5667],"type":"Point"}
}