{
  "id": 7471929,
  "type": "Feature",
  "properties": {
    "tgn:hierarchy":[
        "tgn:7471929",
        "tgn:7001010",
        "tgn:1000004",
        "tgn:1000141",
        "tgn:7029392"
    ],
    "tgn:id":7471929,
    "tgn:name":"Fuxing",
    "tgn:placetype":[
        "aat:300008347"
    ]
},
  "bbox": [],
  "geometry": {"coordinates":[121.628466,24.155731],"type":"Point"}
}