{
  "id": 2668459,
  "type": "Feature",
  "properties": {
    "tgn:hierarchy":[
        "tgn:2668459",
        "tgn:1000001",
        "tgn:7012149",
        "tgn:2002125",
        "tgn:7007827",
        "tgn:7029392"
    ],
    "tgn:id":2668459,
    "tgn:name":"Slate Canyon",
    "tgn:placetype":[
        "aat:300008761"
    ]
},
  "bbox": [],
  "geometry": {"coordinates":[-111.55,40.2333],"type":"Point"}
}