<<<<<<< HEAD
{
  "id": 2251395,
  "type": "Feature",
  "properties": {
    "tgn:hierarchy":[
        "tgn:2251395",
        "tgn:1000001",
        "tgn:7012149",
        "tgn:7007157",
        "tgn:1002857",
        "tgn:7029392"
    ],
    "tgn:id":2251395,
    "tgn:name":"Comet Mine",
    "tgn:placetype":[
        "aat:300000390"
    ]
},
  "bbox": [],
  "geometry": {"coordinates":[-117.3,34.6],"type":"Point"}
}
=======
{"geometry":{"type":"Point","coordinates":[-117.300000,34.600000]},"type":"Feature","properties":{"hierarchy":["tgn:2251395","tgn:1000001","tgn:7012149","tgn:7007157","tgn:1002857","tgn:7029392"],"placetype":["aat:300000390"],"id":2251395,"name:xx":"Comet Mine"}}
>>>>>>> 03f74aca74312dbeaf24d7e61306dd6a786dc3d0
