<<<<<<< HEAD
{
  "id": 7374192,
  "type": "Feature",
  "properties": {
    "tgn:hierarchy":[
        "tgn:7374192",
        "tgn:7005583",
        "tgn:1000001",
        "tgn:7005560",
        "tgn:7029392"
    ],
    "tgn:id":7374192,
    "tgn:name":"Laguna Colorada",
    "tgn:placetype":[
        "aat:300008347"
    ]
},
  "bbox": [],
  "geometry": {"coordinates":[-105.139444,24.177222],"type":"Point"}
}
=======
{"geometry":{"type":"Point","coordinates":[-105.139444,24.177222]},"type":"Feature","properties":{"hierarchy":["tgn:7374192","tgn:7005583","tgn:1000001","tgn:7005560","tgn:7029392"],"placetype":["aat:300008347"],"id":7374192,"name:xx":"Laguna Colorada"}}
>>>>>>> 03f74aca74312dbeaf24d7e61306dd6a786dc3d0
