{
  "id": 1044554,
  "type": "Feature",
  "properties": {
    "tgn:hierarchy":[
        "tgn:1044554",
        "tgn:7002991",
        "tgn:1000003",
        "tgn:7002997",
        "tgn:1000080",
        "tgn:7029392"
    ],
    "tgn:id":1044554,
    "tgn:name":"Falcade",
    "tgn:placetype":[
        "aat:300008347"
    ]
},
  "bbox": [],
  "geometry": {"coordinates":[11.85,46.35],"type":"Point"}
}