{
  "id": 2647768,
  "type": "Feature",
  "properties": {
    "tgn:hierarchy":[
        "tgn:2647768",
        "tgn:1000001",
        "tgn:2000199",
        "tgn:7012149",
        "tgn:7007158",
        "tgn:7029392"
    ],
    "tgn:id":2647768,
    "tgn:name":"School Section Spring",
    "tgn:placetype":[
        "aat:300008697"
    ]
},
  "bbox": [],
  "geometry": {"coordinates":[-105.9167,38.6167],"type":"Point"}
}