<<<<<<< HEAD
{
  "id": 2409580,
  "type": "Feature",
  "properties": {
    "tgn:hierarchy":[
        "tgn:2409580",
        "tgn:1000001",
        "tgn:2001793",
        "tgn:7012149",
        "tgn:7007713",
        "tgn:7029392"
    ],
    "tgn:id":2409580,
    "tgn:name":"Igloo",
    "tgn:placetype":[
        "aat:300008347"
    ]
},
  "bbox": [],
  "geometry": {"coordinates":[-103.85,43.2],"type":"Point"}
}
=======
{"geometry":{"type":"Point","coordinates":[-103.850000,43.200000]},"type":"Feature","properties":{"hierarchy":["tgn:2409580","tgn:1000001","tgn:2001793","tgn:7012149","tgn:7007713","tgn:7029392"],"placetype":["aat:300008347"],"id":2409580,"name:xx":"Igloo"}}
>>>>>>> 03f74aca74312dbeaf24d7e61306dd6a786dc3d0
