<<<<<<< HEAD
{
  "id": 2153508,
  "type": "Feature",
  "properties": {
    "tgn:hierarchy":[
        "tgn:2153508",
        "tgn:1000001",
        "tgn:7012149",
        "tgn:2000476",
        "tgn:7007250",
        "tgn:7029392"
    ],
    "tgn:id":2153508,
    "tgn:name":"Bear Bar",
    "tgn:placetype":[
        "aat:300132348"
    ]
},
  "bbox": [],
  "geometry": {"coordinates":[-115.0833,45.5167],"type":"Point"}
}
=======
{"geometry":{"type":"Point","coordinates":[-115.083300,45.516700]},"type":"Feature","properties":{"hierarchy":["tgn:2153508","tgn:1000001","tgn:7012149","tgn:2000476","tgn:7007250","tgn:7029392"],"placetype":["aat:300132348"],"id":2153508,"name:xx":"Bear Bar"}}
>>>>>>> 03f74aca74312dbeaf24d7e61306dd6a786dc3d0
