{
  "id": 7530204,
  "type": "Feature",
  "properties": {
    "tgn:hierarchy":[
        "tgn:7530204",
        "tgn:7001242",
        "tgn:7016833",
        "tgn:7001335",
        "tgn:7029392"
    ],
    "tgn:id":7530204,
    "tgn:name:en":"Merahil, W\u00e2di",
    "tgn:placetype":[
        "aat:300379998"
    ]
},
  "bbox": [],
  "geometry": {"coordinates":[34.149722,30.746667],"type":"Point"}
}