{
  "id": 2719970,
  "type": "Feature",
  "properties": {
    "tgn:hierarchy":[
        "tgn:2719970",
        "tgn:1000001",
        "tgn:2719640",
        "tgn:7012149",
        "tgn:2002350",
        "tgn:7007922",
        "tgn:7029392"
    ],
    "tgn:id":2719970,
    "tgn:name":"Three, Lake",
    "tgn:placetype":[
        "aat:300008680"
    ]
},
  "bbox": [],
  "geometry": {"coordinates":[-91.4333,45.3167],"type":"Point"}
}