{
  "id": 7038206,
  "type": "Feature",
  "properties": {
    "tgn:hierarchy":[
        "tgn:7038206",
        "tgn:7003162",
        "tgn:1000003",
        "tgn:7009760",
        "tgn:1000080",
        "tgn:7029392"
    ],
    "tgn:id":7038206,
    "tgn:name":"Torriola",
    "tgn:placetype":[
        "aat:300008347"
    ]
},
  "bbox": [],
  "geometry": {"coordinates":[12.35,43.733333],"type":"Point"}
}