{
  "id": 7550625,
  "type": "Feature",
  "properties": {
    "tgn:hierarchy":[
        "tgn:7550625",
        "tgn:1000004",
        "tgn:7000198",
        "tgn:7016722",
        "tgn:7029392"
    ],
    "tgn:id":7550625,
    "tgn:name:en":"D\u012bd\u0101rganj",
    "tgn:placetype":[
        "aat:300008347"
    ]
},
  "bbox": [],
  "geometry": {"coordinates":[82.764982,25.997683],"type":"Point"}
}