{
  "id": 2343087,
  "type": "Feature",
  "properties": {
    "tgn:hierarchy":[
        "tgn:2343087",
        "tgn:1000001",
        "tgn:7012149",
        "tgn:2000966",
        "tgn:7007520",
        "tgn:7029392"
    ],
    "tgn:id":2343087,
    "tgn:name":"Gabbit Lake",
    "tgn:placetype":[
        "aat:300008680"
    ]
},
  "bbox": [],
  "geometry": {"coordinates":[-88.8167,46.3833],"type":"Point"}
}