<<<<<<< HEAD
{
  "id": 2403635,
  "type": "Feature",
  "properties": {
    "tgn:hierarchy":[
        "tgn:2403635",
        "tgn:1000001",
        "tgn:7012149",
        "tgn:2000226",
        "tgn:7007158",
        "tgn:7029392"
    ],
    "tgn:id":2403635,
    "tgn:name":"Howard Gulch",
    "tgn:placetype":[
        "aat:300008761"
    ]
},
  "bbox": [],
  "geometry": {"coordinates":[-105.3333,40.3167],"type":"Point"}
}
=======
{"geometry":{"type":"Point","coordinates":[-105.333300,40.316700]},"type":"Feature","properties":{"hierarchy":["tgn:2403635","tgn:1000001","tgn:7012149","tgn:2000226","tgn:7007158","tgn:7029392"],"placetype":["aat:300008761"],"id":2403635,"name:xx":"Howard Gulch"}}
>>>>>>> 03f74aca74312dbeaf24d7e61306dd6a786dc3d0
