{
  "id": 2635019,
  "type": "Feature",
  "properties": {
    "tgn:hierarchy":[
        "tgn:2635019",
        "tgn:1000001",
        "tgn:7012149",
        "tgn:1002830",
        "tgn:7007826",
        "tgn:7029392"
    ],
    "tgn:id":2635019,
    "tgn:name":"Rye",
    "tgn:placetype":[
        "aat:300008347"
    ]
},
  "bbox": [],
  "geometry": {"coordinates":[-96.4833,30.7167],"type":"Point"}
}