<<<<<<< HEAD
{
  "id": 7057785,
  "type": "Feature",
  "properties": {
    "tgn:hierarchy":[
        "tgn:7057785",
        "tgn:7003171",
        "tgn:1000003",
        "tgn:7003125",
        "tgn:1000080",
        "tgn:7029392"
    ],
    "tgn:id":7057785,
    "tgn:name":"Arnata, Monte",
    "tgn:placetype":[
        "aat:300008795"
    ]
},
  "bbox": [],
  "geometry": {"coordinates":[12.466667,42.55],"type":"Point"}
}
=======
{"geometry":{"type":"Point","coordinates":[12.466667,42.550000]},"type":"Feature","properties":{"hierarchy":["tgn:7057785","tgn:7003171","tgn:1000003","tgn:7003125","tgn:1000080","tgn:7029392"],"placetype":["aat:300008795"],"id":7057785,"name:xx":"Arnata, Monte"}}
>>>>>>> 03f74aca74312dbeaf24d7e61306dd6a786dc3d0
