{
  "id": 7591765,
  "type": "Feature",
  "properties": {
    "tgn:hierarchy":[
        "tgn:7591765",
        "tgn:1000004",
        "tgn:7000198",
        "tgn:7000799",
        "tgn:7029392"
    ],
    "tgn:id":7591765,
    "tgn:name:en":"Kathl\u0101la",
    "tgn:placetype":[
        "aat:300008347"
    ]
},
  "bbox": [],
  "geometry": {"coordinates":[74.027107,33.230816],"type":"Point"}
}