{
  "id": 2095134,
  "type": "Feature",
  "properties": {
    "tgn:hierarchy":[
        "tgn:2095134",
        "tgn:1002541",
        "tgn:1000001",
        "tgn:7012149",
        "tgn:7007711",
        "tgn:7029392"
    ],
    "tgn:id":2095134,
    "tgn:name":"Vaughn Hollow",
    "tgn:placetype":[
        "aat:300008347",
        "aat:300387210"
    ]
},
  "bbox": [],
  "geometry": {"coordinates":[-71.75,41.7167],"type":"Point"}
}