{
  "id": 2280635,
  "type": "Feature",
  "properties": {
    "tgn:hierarchy":[
        "tgn:2280635",
        "tgn:1000001",
        "tgn:7012149",
        "tgn:2000740",
        "tgn:7007254",
        "tgn:7029392"
    ],
    "tgn:id":2280635,
    "tgn:name":"Deep Canyon",
    "tgn:placetype":[
        "aat:300008761"
    ]
},
  "bbox": [],
  "geometry": {"coordinates":[-96.7667,39.1167],"type":"Point"}
}