{
  "id": 2679216,
  "type": "Feature",
  "properties": {
    "tgn:hierarchy":[
        "tgn:2679216",
        "tgn:1000001",
        "tgn:7012149",
        "tgn:2001930",
        "tgn:7007825",
        "tgn:7029392"
    ],
    "tgn:id":2679216,
    "tgn:name":"South Fork Lick Creek",
    "tgn:placetype":[
        "aat:300008706"
    ]
},
  "bbox": [],
  "geometry": {"coordinates":[-87.0667,35.8167],"type":"Point"}
}