{
  "id": 2756361,
  "type": "Feature",
  "properties": {
    "tgn:hierarchy":[
        "tgn:2756361",
        "tgn:1000001",
        "tgn:7012149",
        "tgn:2000364",
        "tgn:7007248",
        "tgn:7029392"
    ],
    "tgn:id":2756361,
    "tgn:name":"Weldon Island",
    "tgn:placetype":[
        "aat:300386851",
        "aat:300008791"
    ]
},
  "bbox": [],
  "geometry": {"coordinates":[-82.8667,34.4667],"type":"Point"}
}