{
  "id": 7425271,
  "type": "Feature",
  "properties": {
    "tgn:hierarchy":[
        "tgn:7425271",
        "tgn:7005581",
        "tgn:1000001",
        "tgn:7005560",
        "tgn:7029392"
    ],
    "tgn:id":7425271,
    "tgn:name":"Santa Clara",
    "tgn:placetype":[
        "aat:300008347"
    ]
},
  "bbox": [],
  "geometry": {"coordinates":[-105.516667,27.716667],"type":"Point"}
}