{
  "id": 2464210,
  "type": "Feature",
  "properties": {
    "tgn:hierarchy":[
        "tgn:2464210",
        "tgn:1000001",
        "tgn:7012149",
        "tgn:2002194",
        "tgn:7007919",
        "tgn:7029392"
    ],
    "tgn:id":2464210,
    "tgn:name":"Locust Ridge",
    "tgn:placetype":[
        "aat:300266640"
    ]
},
  "bbox": [],
  "geometry": {"coordinates":[-81.6333,36.65],"type":"Point"}
}