{
  "id": 2245235,
  "type": "Feature",
  "properties": {
    "tgn:hierarchy":[
        "tgn:2245235",
        "tgn:1000001",
        "tgn:2001174",
        "tgn:7012149",
        "tgn:7007523",
        "tgn:7029392"
    ],
    "tgn:id":2245235,
    "tgn:name":"Club Creek State Forest",
    "tgn:placetype":[
        "aat:300008863"
    ]
},
  "bbox": [],
  "geometry": {"coordinates":[-90.0167,37.15],"type":"Point"}
}