{
  "id": 2471369,
  "type": "Feature",
  "properties": {
    "tgn:hierarchy":[
        "tgn:2471369",
        "tgn:1000001",
        "tgn:7012149",
        "tgn:2000537",
        "tgn:7007251",
        "tgn:7029392"
    ],
    "tgn:id":2471369,
    "tgn:name":"Lost Lake",
    "tgn:placetype":[
        "aat:300008680"
    ]
},
  "bbox": [],
  "geometry": {"coordinates":[-87.9167,38.15],"type":"Point"}
}