{
  "id": 7303430,
  "type": "Feature",
  "properties": {
    "tgn:hierarchy":[
        "tgn:7303430",
        "tgn:7002839",
        "tgn:7001158",
        "tgn:1000003",
        "tgn:1000095",
        "tgn:7029392"
    ],
    "tgn:id":7303430,
    "tgn:name":"Navares de Enmedio",
    "tgn:placetype":[
        "aat:300008347"
    ]
},
  "bbox": [],
  "geometry": {"coordinates":[-3.716667,41.383333],"type":"Point"}
}