{
  "id": 2656487,
  "type": "Feature",
  "properties": {
    "tgn:hierarchy":[
        "tgn:2656487",
        "tgn:1000001",
        "tgn:2001410",
        "tgn:7012149",
        "tgn:7007526",
        "tgn:7029392"
    ],
    "tgn:id":2656487,
    "tgn:name":"Sheep Basin",
    "tgn:placetype":[
        "aat:300386845"
    ]
},
  "bbox": [],
  "geometry": {"coordinates":[-115.15,36.7333],"type":"Point"}
}