{
  "id": 7350723,
  "type": "Feature",
  "properties": {
    "tgn:hierarchy":[
        "tgn:7350723",
        "tgn:1000001",
        "tgn:1001906",
        "tgn:7005560",
        "tgn:7029392"
    ],
    "tgn:id":7350723,
    "tgn:name":"Blas",
    "tgn:placetype":[
        "aat:300008347"
    ]
},
  "bbox": [],
  "geometry": {"coordinates":[-104.933333,21.533333],"type":"Point"}
}