{
  "id": 2519763,
  "type": "Feature",
  "properties": {
    "tgn:hierarchy":[
        "tgn:2519763",
        "tgn:1002648",
        "tgn:1000001",
        "tgn:7019158",
        "tgn:7012149",
        "tgn:7007249",
        "tgn:7029392"
    ],
    "tgn:id":2519763,
    "tgn:name":"Moho",
    "tgn:placetype":[
        "aat:300008850"
    ]
},
  "bbox": [],
  "geometry": {"coordinates":[-156.5167,20.9667],"type":"Point"}
}