{
  "id": 7583486,
  "type": "Feature",
  "properties": {
    "tgn:hierarchy":[
        "tgn:7583486",
        "tgn:1000004",
        "tgn:7000198",
        "tgn:7016722",
        "tgn:7029392"
    ],
    "tgn:id":7583486,
    "tgn:name:en":"Parw\u0101n Minor",
    "tgn:placetype":[
        "aat:300006075"
    ]
},
  "bbox": [],
  "geometry": {"coordinates":[78.725653,24.627188],"type":"Point"}
}