{
  "id": 2161050,
  "type": "Feature",
  "properties": {
    "tgn:hierarchy":[
        "tgn:2161050",
        "tgn:1000001",
        "tgn:7012149",
        "tgn:2001447",
        "tgn:7007566",
        "tgn:7029392"
    ],
    "tgn:id":2161050,
    "tgn:name":"Bell Canyon",
    "tgn:placetype":[
        "aat:300008761"
    ]
},
  "bbox": [],
  "geometry": {"coordinates":[-105.5833,32.95],"type":"Point"}
}