<<<<<<< HEAD
{
  "id": 7022674,
  "type": "Feature",
  "properties": {
    "tgn:hierarchy":[
        "tgn:7022674",
        "tgn:1000001",
        "tgn:7012149",
        "tgn:7007248",
        "tgn:7029392"
    ],
    "tgn:id":7022674,
    "tgn:name":"Walthour Swamp",
    "tgn:placetype":[
        "aat:300008905"
    ]
},
  "bbox": [],
  "geometry": {"coordinates":[-81.2667,32.1333],"type":"Point"}
}
=======
{"geometry":{"type":"Point","coordinates":[-81.266700,32.133300]},"type":"Feature","properties":{"hierarchy":["tgn:7022674","tgn:1000001","tgn:7012149","tgn:7007248","tgn:7029392"],"placetype":["aat:300008905"],"id":7022674,"name:xx":"Walthour Swamp"}}
>>>>>>> 03f74aca74312dbeaf24d7e61306dd6a786dc3d0
