{
  "id": 2394601,
  "type": "Feature",
  "properties": {
    "tgn:hierarchy":[
        "tgn:2394601",
        "tgn:1000001",
        "tgn:7016172",
        "tgn:2000112",
        "tgn:7012149",
        "tgn:7029392"
    ],
    "tgn:id":2394601,
    "tgn:name":"Hogscald Hollow",
    "tgn:placetype":[
        "aat:300008761"
    ]
},
  "bbox": [],
  "geometry": {"coordinates":[-93.7833,36.3167],"type":"Point"}
}