{
  "id": 7361793,
  "type": "Feature",
  "properties": {
    "tgn:hierarchy":[
        "tgn:7361793",
        "tgn:7005586",
        "tgn:1000001",
        "tgn:7005560",
        "tgn:7029392"
    ],
    "tgn:id":7361793,
    "tgn:name":"El Padre",
    "tgn:placetype":[
        "aat:300008699"
    ]
},
  "bbox": [],
  "geometry": {"coordinates":[-104.483333,20.383333],"type":"Point"}
}