{
  "id": 7590151,
  "type": "Feature",
  "properties": {
    "tgn:hierarchy":[
        "tgn:7590151",
        "tgn:1000004",
        "tgn:7000198",
        "tgn:7000799",
        "tgn:7029392"
    ],
    "tgn:id":7590151,
    "tgn:name:en":"Chapri",
    "tgn:placetype":[
        "aat:300008347"
    ]
},
  "bbox": [],
  "geometry": {"coordinates":[74.27614,33.875492],"type":"Point"}
}