{
  "id": 1076603,
  "type": "Feature",
  "properties": {
    "tgn:hierarchy":[
        "tgn:1076603",
        "tgn:1000004",
        "tgn:7000198",
        "tgn:7016722",
        "tgn:7029392"
    ],
    "tgn:id":1076603,
    "tgn:name:en":"Pih\u0101ni",
    "tgn:placetype":[
        "aat:300008347"
    ]
},
  "bbox": [],
  "geometry": {"coordinates":[80.199856,27.623323],"type":"Point"}
}