{
  "id": 2530971,
  "type": "Feature",
  "properties": {
    "tgn:hierarchy":[
        "tgn:2530971",
        "tgn:1000001",
        "tgn:1002271",
        "tgn:7012149",
        "tgn:7007920",
        "tgn:7029392"
    ],
    "tgn:id":2530971,
    "tgn:name":"Mueller Creek",
    "tgn:placetype":[
        "aat:300008706"
    ]
},
  "bbox": [],
  "geometry": {"coordinates":[-123.15,47.8833],"type":"Point"}
}