{
  "id": 2424141,
  "type": "Feature",
  "properties": {
    "tgn:hierarchy":[
        "tgn:2424141",
        "tgn:1000001",
        "tgn:7012149",
        "tgn:7007248",
        "tgn:7029392"
    ],
    "tgn:id":2424141,
    "tgn:name":"Johns Mountain",
    "tgn:placetype":[
        "aat:300008798"
    ]
},
  "bbox": [],
  "geometry": {"coordinates":[-85.1333,34.5167],"type":"Point"}
}