{
  "id": 7143109,
  "type": "Feature",
  "properties": {
    "tgn:hierarchy":[
        "tgn:7143109",
        "tgn:1000003",
        "tgn:7003682",
        "tgn:7000084",
        "tgn:7029392"
    ],
    "tgn:id":7143109,
    "tgn:name":"Ruine Madenburg",
    "tgn:placetype":[
        "aat:300008057"
    ]
},
  "bbox": [],
  "geometry": {"coordinates":[8.016667,49.166667],"type":"Point"}
}