{
  "id": 1028129,
  "type": "Feature",
  "properties": {
    "tgn:hierarchy":[
        "tgn:1028129",
        "tgn:1000003",
        "tgn:7594009",
        "tgn:1000066",
        "tgn:7029392"
    ],
    "tgn:id":1028129,
    "tgn:name":"Skrydstrup",
    "tgn:placetype":[
        "aat:300008347"
    ]
},
  "bbox": [],
  "geometry": {"coordinates":[9.25,55.2333],"type":"Point"}
}