{
  "id": 7086227,
  "type": "Feature",
  "properties": {
    "tgn:hierarchy":[
        "tgn:7086227",
        "tgn:1000003",
        "tgn:7003678",
        "tgn:7000084",
        "tgn:7029392"
    ],
    "tgn:id":7086227,
    "tgn:name":"F\u00f6rsterei Warzenbach",
    "tgn:placetype":[
        "aat:300004792"
    ]
},
  "bbox": [],
  "geometry": {"coordinates":[8.65,50.866667],"type":"Point"}
}