{
  "id": 2503624,
  "type": "Feature",
  "properties": {
    "tgn:hierarchy":[
        "tgn:2503624",
        "tgn:1000001",
        "tgn:1002328",
        "tgn:7012149",
        "tgn:7007568",
        "tgn:7029392"
    ],
    "tgn:id":2503624,
    "tgn:name":"Meade Hill",
    "tgn:placetype":[
        "aat:300008798"
    ]
},
  "bbox": [],
  "geometry": {"coordinates":[-74.5833,42.1333],"type":"Point"}
}