{
  "id": 7316675,
  "type": "Feature",
  "properties": {
    "tgn:hierarchy":[
        "tgn:7316675",
        "tgn:1001630",
        "tgn:1000049",
        "tgn:1000002",
        "tgn:7029392"
    ],
    "tgn:id":7316675,
    "tgn:name":"Cuesta la Arena, Quebrada",
    "tgn:placetype":[
        "aat:300266554",
        "aat:300008699"
    ]
},
  "bbox": [],
  "geometry": {"coordinates":[-71.283333,-28.633333],"type":"Point"}
}