{
  "id": 2582867,
  "type": "Feature",
  "properties": {
    "tgn:hierarchy":[
        "tgn:2582867",
        "tgn:1000001",
        "tgn:7014423",
        "tgn:7012149",
        "tgn:7007517",
        "tgn:7029392"
    ],
    "tgn:id":2582867,
    "tgn:name":"Pine Island Brook",
    "tgn:placetype":[
        "aat:300008699"
    ]
},
  "bbox": [],
  "geometry": {"coordinates":[-70.7667,41.65],"type":"Point"}
}