{
  "id": 2526118,
  "type": "Feature",
  "properties": {
    "tgn:hierarchy":[
        "tgn:2526118",
        "tgn:1000001",
        "tgn:7012149",
        "tgn:2000908",
        "tgn:7007256",
        "tgn:7029392"
    ],
    "tgn:id":2526118,
    "tgn:name":"Mosquito Island",
    "tgn:placetype":[
        "aat:300008791"
    ]
},
  "bbox": [],
  "geometry": {"coordinates":[-91.15,29.3167],"type":"Point"}
}