{
  "id": 7221304,
  "type": "Feature",
  "properties": {
    "tgn:hierarchy":[
        "tgn:7221304",
        "tgn:7002715",
        "tgn:7002731",
        "tgn:1000003",
        "tgn:1000074",
        "tgn:7029392"
    ],
    "tgn:id":7221304,
    "tgn:name":"Trim\u00edvi",
    "tgn:placetype":[
        "aat:300008347"
    ]
},
  "bbox": [],
  "geometry": {"coordinates":[22.993757,40.526111],"type":"Point"}
}