{
  "id": 2030439,
  "type": "Feature",
  "properties": {
    "tgn:hierarchy":[
        "tgn:2030439",
        "tgn:1000001",
        "tgn:7012149",
        "tgn:1002622",
        "tgn:7007251",
        "tgn:7029392"
    ],
    "tgn:id":2030439,
    "tgn:name":"Troy",
    "tgn:placetype":[
        "aat:300008347"
    ]
},
  "bbox": [],
  "geometry": {"coordinates":[-89.8667,38.7167],"type":"Point"}
}