{
  "id": 7452404,
  "type": "Feature",
  "properties": {
    "tgn:hierarchy":[
        "tgn:7452404",
        "tgn:7002444",
        "tgn:1000003",
        "tgn:7019152",
        "tgn:7008591",
        "tgn:7029392"
    ],
    "tgn:id":7452404,
    "tgn:name:en":"Fortingall",
    "tgn:placetype":[
        "aat:300008347"
    ]
},
  "bbox": [],
  "geometry": {"coordinates":[-4.05,56.583333],"type":"Point"}
}