{
  "id": 2334895,
  "type": "Feature",
  "properties": {
    "tgn:hierarchy":[
        "tgn:2334895",
        "tgn:1000001",
        "tgn:7012149",
        "tgn:2001667",
        "tgn:7007707",
        "tgn:7029392"
    ],
    "tgn:id":2334895,
    "tgn:name":"Forked Lake",
    "tgn:placetype":[
        "aat:300008680"
    ]
},
  "bbox": [],
  "geometry": {"coordinates":[-94.5333,33.9667],"type":"Point"}
}