{
  "id": 7429213,
  "type": "Feature",
  "properties": {
    "tgn:hierarchy":[
        "tgn:7429213",
        "tgn:7005583",
        "tgn:1000001",
        "tgn:7005560",
        "tgn:7029392"
    ],
    "tgn:id":7429213,
    "tgn:name":"Parque Natural Puerto de los Angeles",
    "tgn:placetype":[
        "aat:300008187"
    ]
},
  "bbox": [],
  "geometry": {"coordinates":[-105.75,23.65],"type":"Point"}
}