<<<<<<< HEAD
{
  "id": 2702769,
  "type": "Feature",
  "properties": {
    "tgn:hierarchy":[
        "tgn:2702769",
        "tgn:1000001",
        "tgn:7012149",
        "tgn:1002749",
        "tgn:7007240",
        "tgn:7029392"
    ],
    "tgn:id":2702769,
    "tgn:name":"Sulphur Spring",
    "tgn:placetype":[
        "aat:300008697"
    ]
},
  "bbox": [],
  "geometry": {"coordinates":[-81.5,28.7667],"type":"Point"}
}
=======
{"geometry":{"type":"Point","coordinates":[-81.500000,28.766700]},"type":"Feature","properties":{"hierarchy":["tgn:2702769","tgn:1000001","tgn:7012149","tgn:1002749","tgn:7007240","tgn:7029392"],"placetype":["aat:300008697"],"id":2702769,"name:xx":"Sulphur Spring"}}
>>>>>>> 03f74aca74312dbeaf24d7e61306dd6a786dc3d0
