{
  "id": 2619213,
  "type": "Feature",
  "properties": {
    "tgn:hierarchy":[
        "tgn:2619213",
        "tgn:1000001",
        "tgn:7012149",
        "tgn:2002348",
        "tgn:7007922",
        "tgn:7029392"
    ],
    "tgn:id":2619213,
    "tgn:name":"Riley Lake",
    "tgn:placetype":[
        "aat:300008680"
    ]
},
  "bbox": [],
  "geometry": {"coordinates":[-90.15,45.85],"type":"Point"}
}