<<<<<<< HEAD
{
  "id": 7170769,
  "type": "Feature",
  "properties": {
    "tgn:hierarchy":[
        "tgn:7170769",
        "tgn:1000003",
        "tgn:7003676",
        "tgn:7000084",
        "tgn:7029392"
    ],
    "tgn:id":7170769,
    "tgn:name":"Hennenk\u00f6pfe",
    "tgn:placetype":[
        "aat:300008777"
    ]
},
  "bbox": [],
  "geometry": {"coordinates":[9.7,51.7],"type":"Point"}
}
=======
{"geometry":{"type":"Point","coordinates":[9.700000,51.700000]},"type":"Feature","properties":{"hierarchy":["tgn:7170769","tgn:1000003","tgn:7003676","tgn:7000084","tgn:7029392"],"placetype":["aat:300008777"],"id":7170769,"name:xx":"Hennenk\u00f6pfe"}}
>>>>>>> 03f74aca74312dbeaf24d7e61306dd6a786dc3d0
