{
  "id": 7468032,
  "type": "Feature",
  "properties": {
    "tgn:hierarchy":[
        "tgn:7468032",
        "tgn:1000004",
        "tgn:7471332",
        "tgn:1000141",
        "tgn:7029392"
    ],
    "tgn:id":7468032,
    "tgn:name":"Jiaxin Daqiao",
    "tgn:placetype":[
        "aat:300007836"
    ]
},
  "bbox": [],
  "geometry": {"coordinates":[121.214722,24.701667],"type":"Point"}
}