{
  "id": 2585293,
  "type": "Feature",
  "properties": {
    "tgn:hierarchy":[
        "tgn:2585293",
        "tgn:1000001",
        "tgn:7012149",
        "tgn:2001446",
        "tgn:7007566",
        "tgn:7029392"
    ],
    "tgn:id":2585293,
    "tgn:name":"Pinos Altos",
    "tgn:placetype":[
        "aat:300055621"
    ]
},
  "bbox": [],
  "geometry": {"coordinates":[-104.6833,35.7833],"type":"Point"}
}