{
  "id": 7388310,
  "type": "Feature",
  "properties": {
    "tgn:hierarchy":[
        "tgn:7388310",
        "tgn:1000001",
        "tgn:7005595",
        "tgn:7005560",
        "tgn:7029392"
    ],
    "tgn:id":7388310,
    "tgn:name":"Potrero de los Fierros",
    "tgn:placetype":[
        "aat:300008347"
    ]
},
  "bbox": [],
  "geometry": {"coordinates":[-108.233333,26.266667],"type":"Point"}
}