{
  "id": 2174387,
  "type": "Feature",
  "properties": {
    "tgn:hierarchy":[
        "tgn:2174387",
        "tgn:7002659",
        "tgn:1000001",
        "tgn:7012149",
        "tgn:2000047",
        "tgn:7029392"
    ],
    "tgn:id":2174387,
    "tgn:name":"Bishop Cave",
    "tgn:placetype":[
        "aat:300008746"
    ]
},
  "bbox": [],
  "geometry": {"coordinates":[-86.35,34.45],"type":"Point"}
}