{
  "id": 7563469,
  "type": "Feature",
  "properties": {
    "tgn:hierarchy":[
        "tgn:7563469",
        "tgn:1000004",
        "tgn:7000198",
        "tgn:7016788",
        "tgn:7029392"
    ],
    "tgn:id":7563469,
    "tgn:name":"Bh\u0101ni Singh ki Dh\u0101ni",
    "tgn:placetype":[
        "aat:300008347"
    ]
},
  "bbox": [],
  "geometry": {"coordinates":[74.739176,28.904032],"type":"Point"}
}