{
  "id": 2042463,
  "type": "Feature",
  "properties": {
    "tgn:hierarchy":[
        "tgn:2042463",
        "tgn:1000001",
        "tgn:2000861",
        "tgn:7012149",
        "tgn:7007256",
        "tgn:7029392"
    ],
    "tgn:id":2042463,
    "tgn:name":"Carterville",
    "tgn:placetype":[
        "aat:300008347",
        "aat:300387210"
    ]
},
  "bbox": [],
  "geometry": {"coordinates":[-93.5833,32.9667],"type":"Point"}
}