<<<<<<< HEAD
{
  "id": 7354619,
  "type": "Feature",
  "properties": {
    "tgn:hierarchy":[
        "tgn:7354619",
        "tgn:1000001",
        "tgn:7005589",
        "tgn:7005560",
        "tgn:7029392"
    ],
    "tgn:id":7354619,
    "tgn:name":"Rancho Canapo",
    "tgn:placetype":[
        "aat:300000241"
    ]
},
  "bbox": [],
  "geometry": {"coordinates":[-99.733333,27.2],"type":"Point"}
}
=======
{"geometry":{"type":"Point","coordinates":[-99.733333,27.200000]},"type":"Feature","properties":{"hierarchy":["tgn:7354619","tgn:1000001","tgn:7005589","tgn:7005560","tgn:7029392"],"placetype":["aat:300000241"],"id":7354619,"name:xx":"Rancho Canapo"}}
>>>>>>> 03f74aca74312dbeaf24d7e61306dd6a786dc3d0
