<<<<<<< HEAD
{
  "id": 2334281,
  "type": "Feature",
  "properties": {
    "tgn:hierarchy":[
        "tgn:2334281",
        "tgn:1000001",
        "tgn:2000867",
        "tgn:7012149",
        "tgn:7007256",
        "tgn:7029392"
    ],
    "tgn:id":2334281,
    "tgn:name":"Forest Grove",
    "tgn:placetype":[
        "aat:300008347"
    ]
},
  "bbox": [],
  "geometry": {"coordinates":[-92.9667,32.8167],"type":"Point"}
}
=======
{"geometry":{"type":"Point","coordinates":[-92.966700,32.816700]},"type":"Feature","properties":{"hierarchy":["tgn:2334281","tgn:1000001","tgn:2000867","tgn:7012149","tgn:7007256","tgn:7029392"],"placetype":["aat:300008347"],"id":2334281,"name:xx":"Forest Grove"}}
>>>>>>> 03f74aca74312dbeaf24d7e61306dd6a786dc3d0
