{
  "id": 7592332,
  "type": "Feature",
  "properties": {
    "tgn:hierarchy":[
        "tgn:7592332",
        "tgn:1000004",
        "tgn:7000198",
        "tgn:7000799",
        "tgn:7029392"
    ],
    "tgn:id":7592332,
    "tgn:name:en":"Pur\u0101ni Nandni",
    "tgn:placetype":[
        "aat:300008347"
    ]
},
  "bbox": [],
  "geometry": {"coordinates":[74.812977,32.707333],"type":"Point"}
}