{
  "id": 2531046,
  "type": "Feature",
  "properties": {
    "tgn:hierarchy":[
        "tgn:2531046",
        "tgn:2000001",
        "tgn:7002659",
        "tgn:1000001",
        "tgn:7012149",
        "tgn:7029392"
    ],
    "tgn:id":2531046,
    "tgn:name":"Muiel Lake",
    "tgn:placetype":[
        "aat:300006191"
    ]
},
  "bbox": [],
  "geometry": {"coordinates":[-87.6167,30.35],"type":"Point"}
}