{
  "id": 2198186,
  "type": "Feature",
  "properties": {
    "tgn:hierarchy":[
        "tgn:2198186",
        "tgn:1000001",
        "tgn:7012149",
        "tgn:1002350",
        "tgn:7007157",
        "tgn:7029392"
    ],
    "tgn:id":2198186,
    "tgn:name":"Browns Bar",
    "tgn:placetype":[
        "aat:300132348"
    ]
},
  "bbox": [],
  "geometry": {"coordinates":[-120.9833,38.9167],"type":"Point"}
}