{
  "id": 2543159,
  "type": "Feature",
  "properties": {
    "tgn:hierarchy":[
        "tgn:2543159",
        "tgn:1000001",
        "tgn:2000457",
        "tgn:7012149",
        "tgn:7007250",
        "tgn:7029392"
    ],
    "tgn:id":2543159,
    "tgn:name":"Nora Lateral",
    "tgn:placetype":[
        "aat:300006075"
    ]
},
  "bbox": [],
  "geometry": {"coordinates":[-112.4333,43.1167],"type":"Point"}
}