{
  "id": 7583094,
  "type": "Feature",
  "properties": {
    "tgn:hierarchy":[
        "tgn:7583094",
        "tgn:1000004",
        "tgn:7000198",
        "tgn:7016788",
        "tgn:7029392"
    ],
    "tgn:id":7583094,
    "tgn:name:en":"Sun\u0101rli ki Dh\u0101ni",
    "tgn:placetype":[
        "aat:300008347"
    ]
},
  "bbox": [],
  "geometry": {"coordinates":[75.63503,28.052291],"type":"Point"}
}