{
  "id": 1115565,
  "type": "Feature",
  "properties": {
    "tgn:hierarchy":[
        "tgn:1115565",
        "tgn:7005694",
        "tgn:7005685",
        "tgn:1000001",
        "tgn:7029392"
    ],
    "tgn:id":1115565,
    "tgn:name":"Beaver Lake",
    "tgn:placetype":[
        "aat:300008680"
    ]
},
  "bbox": [],
  "geometry": {"coordinates":[-111.8333,54.7167],"type":"Point"}
}