{
  "id": 2560866,
  "type": "Feature",
  "properties": {
    "tgn:hierarchy":[
        "tgn:2560866",
        "tgn:1000001",
        "tgn:7012149",
        "tgn:1002977",
        "tgn:7007240",
        "tgn:7029392"
    ],
    "tgn:id":2560866,
    "tgn:name":"Ormond-by-the-Sea",
    "tgn:placetype":[
        "aat:300008347"
    ]
},
  "bbox": [],
  "geometry": {"coordinates":[-81.0667,29.3333],"type":"Point"}
}