{
  "id": 7177933,
  "type": "Feature",
  "properties": {
    "tgn:hierarchy":[
        "tgn:7177933",
        "tgn:1000003",
        "tgn:7003676",
        "tgn:7000084",
        "tgn:7029392"
    ],
    "tgn:id":7177933,
    "tgn:name":"G\u00fcnne-Moor",
    "tgn:placetype":[
        "aat:300386886"
    ]
},
  "bbox": [],
  "geometry": {"coordinates":[8.916667,53.283333],"type":"Point"}
}