{
  "id": 7289052,
  "type": "Feature",
  "properties": {
    "tgn:hierarchy":[
        "tgn:7289052",
        "tgn:7016598",
        "tgn:1000049",
        "tgn:1000002",
        "tgn:7029392"
    ],
    "tgn:id":7289052,
    "tgn:name":"Iscu\u00f1a, Aguada",
    "tgn:placetype":[
        "aat:300008697"
    ]
},
  "bbox": [],
  "geometry": {"coordinates":[-70.55,-24.566667],"type":"Point"}
}