{
  "id": 2031794,
  "type": "Feature",
  "properties": {
    "tgn:hierarchy":[
        "tgn:2031794",
        "tgn:1000001",
        "tgn:7012149",
        "tgn:2000559",
        "tgn:7007252",
        "tgn:7029392"
    ],
    "tgn:id":2031794,
    "tgn:name":"Ferguson Hill",
    "tgn:placetype":[
        "aat:300008347"
    ]
},
  "bbox": [],
  "geometry": {"coordinates":[-87.45,39.4667],"type":"Point"}
}