{
  "id": 2325037,
  "type": "Feature",
  "properties": {
    "tgn:hierarchy":[
        "tgn:2325037",
        "tgn:1000001",
        "tgn:7012149",
        "tgn:1002749",
        "tgn:7007240",
        "tgn:7029392"
    ],
    "tgn:id":2325037,
    "tgn:name":"Fern Creek",
    "tgn:placetype":[
        "aat:300008706"
    ]
},
  "bbox": [],
  "geometry": {"coordinates":[-81.35,28.5333],"type":"Point"}
}