{
  "id": 2782215,
  "type": "Feature",
  "properties": {
    "tgn:hierarchy":[
        "tgn:2782215",
        "tgn:1000001",
        "tgn:7012149",
        "tgn:2001298",
        "tgn:7007524",
        "tgn:7029392"
    ],
    "tgn:id":2782215,
    "tgn:name":"Woodtick Mountain",
    "tgn:placetype":[
        "aat:300008798"
    ]
},
  "bbox": [],
  "geometry": {"coordinates":[-113.1167,47.3833],"type":"Point"}
}