{
  "id": 7153919,
  "type": "Feature",
  "properties": {
    "tgn:hierarchy":[
        "tgn:7153919",
        "tgn:1000003",
        "tgn:7003677",
        "tgn:7000084",
        "tgn:7029392"
    ],
    "tgn:id":7153919,
    "tgn:name":"Kalen-Berg",
    "tgn:placetype":[
        "aat:300008777"
    ]
},
  "bbox": [],
  "geometry": {"coordinates":[9.166667,51.916667],"type":"Point"}
}