<<<<<<< HEAD
{
  "id": 7026219,
  "type": "Feature",
  "properties": {
    "tgn:hierarchy":[
        "tgn:7026219",
        "tgn:7002445",
        "tgn:1000003",
        "tgn:1003654",
        "tgn:7008591",
        "tgn:7029392"
    ],
    "tgn:id":7026219,
    "tgn:name":"Lakeside",
    "tgn:placetype":[
        "aat:300008347"
    ]
},
  "bbox": [],
  "geometry": {"coordinates":[0.2833,51.4833],"type":"Point"}
}
=======
{"geometry":{"type":"Point","coordinates":[0.283300,51.483300]},"type":"Feature","properties":{"hierarchy":["tgn:7026219","tgn:7002445","tgn:1000003","tgn:1003654","tgn:7008591","tgn:7029392"],"placetype":["aat:300008347"],"id":7026219,"name:xx":"Lakeside"}}
>>>>>>> 03f74aca74312dbeaf24d7e61306dd6a786dc3d0
