{
  "id": 2203477,
  "type": "Feature",
  "properties": {
    "tgn:hierarchy":[
        "tgn:2203477",
        "tgn:1000001",
        "tgn:7012149",
        "tgn:2001914",
        "tgn:7007825",
        "tgn:7029392"
    ],
    "tgn:id":2203477,
    "tgn:name":"Buckingham Island",
    "tgn:placetype":[
        "aat:300008791"
    ]
},
  "bbox": [],
  "geometry": {"coordinates":[-83.6333,35.9167],"type":"Point"}
}