{
  "id": 7334092,
  "type": "Feature",
  "properties": {
    "tgn:hierarchy":[
        "tgn:7334092",
        "tgn:7002815",
        "tgn:1000003",
        "tgn:7002793",
        "tgn:1000095",
        "tgn:7029392"
    ],
    "tgn:id":7334092,
    "tgn:name":"El Toro",
    "tgn:placetype":[
        "aat:300008347"
    ]
},
  "bbox": [],
  "geometry": {"coordinates":[-0.75,39.983333],"type":"Point"}
}