{
  "id": 2283879,
  "type": "Feature",
  "properties": {
    "tgn:hierarchy":[
        "tgn:2283879",
        "tgn:1000001",
        "tgn:7012149",
        "tgn:2000441",
        "tgn:7007248",
        "tgn:7029392"
    ],
    "tgn:id":2283879,
    "tgn:name":"Dennard Branch",
    "tgn:placetype":[
        "aat:300008699"
    ]
},
  "bbox": [],
  "geometry": {"coordinates":[-82.8667,32.9167],"type":"Point"}
}