<<<<<<< HEAD
{
  "id": 7026217,
  "type": "Feature",
  "properties": {
    "tgn:hierarchy":[
        "tgn:7026217",
        "tgn:1002215",
        "tgn:1000001",
        "tgn:7012149",
        "tgn:7007565",
        "tgn:7029392"
    ],
    "tgn:id":7026217,
    "tgn:name":"Westampton",
    "tgn:placetype":[
        "aat:300008347",
        "aat:300000792"
    ]
},
  "bbox": [],
  "geometry": {"coordinates":[-74.8333,40.0167],"type":"Point"}
}
=======
{"geometry":{"type":"Point","coordinates":[-74.833300,40.016700]},"type":"Feature","properties":{"hierarchy":["tgn:7026217","tgn:1002215","tgn:1000001","tgn:7012149","tgn:7007565","tgn:7029392"],"placetype":["aat:300008347","aat:300000792"],"id":7026217,"name:xx":"Westampton"}}
>>>>>>> 03f74aca74312dbeaf24d7e61306dd6a786dc3d0
