{
  "id": 2497985,
  "type": "Feature",
  "properties": {
    "tgn:hierarchy":[
        "tgn:2497985",
        "tgn:1000001",
        "tgn:1002328",
        "tgn:7012149",
        "tgn:7007568",
        "tgn:7029392"
    ],
    "tgn:id":2497985,
    "tgn:name":"Maynard Hollow",
    "tgn:placetype":[
        "aat:300008761"
    ]
},
  "bbox": [],
  "geometry": {"coordinates":[-75.1667,41.9333],"type":"Point"}
}