{
  "id": 2603585,
  "type": "Feature",
  "properties": {
    "tgn:hierarchy":[
        "tgn:2603585",
        "tgn:1000001",
        "tgn:7012149",
        "tgn:7014021",
        "tgn:7007709",
        "tgn:7029392"
    ],
    "tgn:id":2603585,
    "tgn:name":"Queens Grant",
    "tgn:placetype":[
        "aat:300008347"
    ]
},
  "bbox": [],
  "geometry": {"coordinates":[-80.75,35.15],"type":"Point"}
}