{
  "id": 2614139,
  "type": "Feature",
  "properties": {
    "tgn:hierarchy":[
        "tgn:2614139",
        "tgn:2001001",
        "tgn:1000001",
        "tgn:7012149",
        "tgn:7007521",
        "tgn:7029392"
    ],
    "tgn:id":2614139,
    "tgn:name":"Reeves Lake",
    "tgn:placetype":[
        "aat:300008680"
    ]
},
  "bbox": [],
  "geometry": {"coordinates":[-95.8333,46.7333],"type":"Point"}
}