{
  "id": 7500240,
  "type": "Feature",
  "properties": {
    "tgn:hierarchy":[
        "tgn:7500240",
        "tgn:1000004",
        "tgn:7491221",
        "tgn:1000141",
        "tgn:7029392"
    ],
    "tgn:id":7500240,
    "tgn:name":"Rongmin Nongchang",
    "tgn:placetype":[
        "aat:300000206"
    ]
},
  "bbox": [],
  "geometry": {"coordinates":[120.958889,22.562778],"type":"Point"}
}