{
  "id": 1073175,
  "type": "Feature",
  "properties": {
    "tgn:hierarchy":[
        "tgn:1073175",
        "tgn:1000004",
        "tgn:7002081",
        "tgn:1000111",
        "tgn:7029392"
    ],
    "tgn:id":1073175,
    "tgn:name":"Xishiqiao",
    "tgn:placetype":[
        "aat:300008347"
    ]
},
  "bbox": [],
  "geometry": {"coordinates":[120.0833,31.8667],"type":"Point"}
}