{
  "id": 7031920,
  "type": "Feature",
  "properties": {
    "tgn:hierarchy":[
        "tgn:7031920",
        "tgn:1000004",
        "tgn:7005019",
        "tgn:7029392"
    ],
    "tgn:id":7031920,
    "tgn:name":"Exterior, Porto",
    "tgn:placetype":[
        "aat:300008678"
    ]
},
  "bbox": [],
  "geometry": {"coordinates":[113.558,22.193],"type":"Point"}
}