{
  "id": 2201219,
  "type": "Feature",
  "properties": {
    "tgn:hierarchy":[
        "tgn:2201219",
        "tgn:1000001",
        "tgn:1002276",
        "tgn:7012149",
        "tgn:7007708",
        "tgn:7029392"
    ],
    "tgn:id":2201219,
    "tgn:name":"Buchanan Creek",
    "tgn:placetype":[
        "aat:300008706"
    ]
},
  "bbox": [],
  "geometry": {"coordinates":[-123.8167,45.8333],"type":"Point"}
}