{
  "id": 2644896,
  "type": "Feature",
  "properties": {
    "tgn:hierarchy":[
        "tgn:2644896",
        "tgn:1000001",
        "tgn:7006451",
        "tgn:7012149",
        "tgn:2000099",
        "tgn:7029392"
    ],
    "tgn:id":2644896,
    "tgn:name":"Satan Butte",
    "tgn:placetype":[
        "aat:300008798"
    ]
},
  "bbox": [],
  "geometry": {"coordinates":[-109.9167,35.5167],"type":"Point"}
}