<<<<<<< HEAD
{
  "id": 2400772,
  "type": "Feature",
  "properties": {
    "tgn:hierarchy":[
        "tgn:2400772",
        "tgn:1000001",
        "tgn:7012149",
        "tgn:7007712",
        "tgn:7029392"
    ],
    "tgn:id":2400772,
    "tgn:name":"Horse Pen Swamp",
    "tgn:placetype":[
        "aat:300008699"
    ]
},
  "bbox": [],
  "geometry": {"coordinates":[-79.5667,33.4667],"type":"Point"}
}
=======
{"geometry":{"type":"Point","coordinates":[-79.566700,33.466700]},"type":"Feature","properties":{"hierarchy":["tgn:2400772","tgn:1000001","tgn:7012149","tgn:7007712","tgn:7029392"],"placetype":["aat:300008699"],"id":2400772,"name:xx":"Horse Pen Swamp"}}
>>>>>>> 03f74aca74312dbeaf24d7e61306dd6a786dc3d0
