{
  "id": 2400772,
  "type": "Feature",
  "properties": {
    "tgn:hierarchy":[
        "tgn:2400772",
        "tgn:1000001",
        "tgn:7012149",
        "tgn:7007712",
        "tgn:7029392"
    ],
    "tgn:id":2400772,
    "tgn:name":"Horse Pen Swamp",
    "tgn:placetype":[
        "aat:300008699"
    ]
},
  "bbox": [],
  "geometry": {"coordinates":[-79.5667,33.4667],"type":"Point"}
}