{
  "id": 2719299,
  "type": "Feature",
  "properties": {
    "tgn:hierarchy":[
        "tgn:2719299",
        "tgn:1000001",
        "tgn:7012149",
        "tgn:2000926",
        "tgn:7007515",
        "tgn:7029392"
    ],
    "tgn:id":2719299,
    "tgn:name":"Thrasher Peaks",
    "tgn:placetype":[
        "aat:300008798"
    ]
},
  "bbox": [],
  "geometry": {"coordinates":[-70.9833,45.2333],"type":"Point"}
}