{
  "id": 2735842,
  "type": "Feature",
  "properties": {
    "tgn:hierarchy":[
        "tgn:2735842",
        "tgn:1000001",
        "tgn:7012149",
        "tgn:7007157",
        "tgn:1002858",
        "tgn:7029392"
    ],
    "tgn:id":2735842,
    "tgn:name":"Twin Lakes",
    "tgn:placetype":[
        "aat:300008680"
    ]
},
  "bbox": [],
  "geometry": {"coordinates":[-116.65,33.4167],"type":"Point"}
}