<<<<<<< HEAD
{
  "id": 7115036,
  "type": "Feature",
  "properties": {
    "tgn:hierarchy":[
        "tgn:7115036",
        "tgn:1000003",
        "tgn:7003688",
        "tgn:7000084",
        "tgn:7029392"
    ],
    "tgn:id":7115036,
    "tgn:name":"Osterhever",
    "tgn:placetype":[
        "aat:300008347"
    ]
},
  "bbox": [],
  "geometry": {"coordinates":[8.783333,54.383333],"type":"Point"}
}
=======
{"geometry":{"type":"Point","coordinates":[8.783333,54.383333]},"type":"Feature","properties":{"hierarchy":["tgn:7115036","tgn:1000003","tgn:7003688","tgn:7000084","tgn:7029392"],"placetype":["aat:300008347"],"id":7115036,"name:xx":"Osterhever"}}
>>>>>>> 03f74aca74312dbeaf24d7e61306dd6a786dc3d0
