{
  "id": 7122765,
  "type": "Feature",
  "properties": {
    "tgn:hierarchy":[
        "tgn:7122765",
        "tgn:7003669",
        "tgn:1000003",
        "tgn:7000084",
        "tgn:7029392"
    ],
    "tgn:id":7122765,
    "tgn:name":"Neuteichhof",
    "tgn:placetype":[
        "aat:300000206"
    ]
},
  "bbox": [],
  "geometry": {"coordinates":[12.35,49.833333],"type":"Point"}
}