{
  "id": 7102280,
  "type": "Feature",
  "properties": {
    "tgn:hierarchy":[
        "tgn:7102280",
        "tgn:1000003",
        "tgn:7003688",
        "tgn:7000084",
        "tgn:7029392"
    ],
    "tgn:id":7102280,
    "tgn:name":"Sarau",
    "tgn:placetype":[
        "aat:300008347"
    ]
},
  "bbox": [],
  "geometry": {"coordinates":[10.533333,54.05],"type":"Point"}
}