{
  "id": 2398342,
  "type": "Feature",
  "properties": {
    "tgn:hierarchy":[
        "tgn:2398342",
        "tgn:1000001",
        "tgn:7012149",
        "tgn:7007157",
        "tgn:2000189",
        "tgn:7029392"
    ],
    "tgn:id":2398342,
    "tgn:name":"Hooper Spring",
    "tgn:placetype":[
        "aat:300008697"
    ]
},
  "bbox": [],
  "geometry": {"coordinates":[-122.1667,41.25],"type":"Point"}
}