{
  "id": 7193144,
  "type": "Feature",
  "properties": {
    "tgn:hierarchy":[
        "tgn:7193144",
        "tgn:7003669",
        "tgn:1000003",
        "tgn:7000084",
        "tgn:7029392"
    ],
    "tgn:id":7193144,
    "tgn:name":"Fleck",
    "tgn:placetype":[
        "aat:300000206"
    ]
},
  "bbox": [],
  "geometry": {"coordinates":[12.583333,48.15],"type":"Point"}
}