{
  "id": 2432248,
  "type": "Feature",
  "properties": {
    "tgn:hierarchy":[
        "tgn:2432248",
        "tgn:1002483",
        "tgn:7019080",
        "tgn:1000001",
        "tgn:7012149",
        "tgn:7007249",
        "tgn:7029392"
    ],
    "tgn:id":2432248,
    "tgn:name":"Keahi Point",
    "tgn:placetype":[
        "aat:300008850"
    ]
},
  "bbox": [],
  "geometry": {"coordinates":[-157.9667,21.3167],"type":"Point"}
}