{
  "id": 7418434,
  "type": "Feature",
  "properties": {
    "tgn:hierarchy":[
        "tgn:7418434",
        "tgn:7005584",
        "tgn:1000001",
        "tgn:7005560",
        "tgn:7029392"
    ],
    "tgn:id":7418434,
    "tgn:name":"Los Arcos",
    "tgn:placetype":[
        "aat:300008347"
    ]
},
  "bbox": [],
  "geometry": {"coordinates":[-100.9375,21.228333],"type":"Point"}
}