<<<<<<< HEAD
{
  "id": 2336471,
  "type": "Feature",
  "properties": {
    "tgn:hierarchy":[
        "tgn:2336471",
        "tgn:1000001",
        "tgn:7012149",
        "tgn:7007157",
        "tgn:2000187",
        "tgn:7029392"
    ],
    "tgn:id":2336471,
    "tgn:name":"Four Bits Creek",
    "tgn:placetype":[
        "aat:300008706"
    ]
},
  "bbox": [],
  "geometry": {"coordinates":[-120.75,39.7667],"type":"Point"}
}
=======
{"geometry":{"type":"Point","coordinates":[-120.750000,39.766700]},"type":"Feature","properties":{"hierarchy":["tgn:2336471","tgn:1000001","tgn:7012149","tgn:7007157","tgn:2000187","tgn:7029392"],"placetype":["aat:300008706"],"id":2336471,"name:xx":"Four Bits Creek"}}
>>>>>>> 03f74aca74312dbeaf24d7e61306dd6a786dc3d0
