{
  "id": 2662910,
  "type": "Feature",
  "properties": {
    "tgn:hierarchy":[
        "tgn:2662910",
        "tgn:1000001",
        "tgn:2001098",
        "tgn:7012149",
        "tgn:7007522",
        "tgn:7029392"
    ],
    "tgn:id":2662910,
    "tgn:name":"Siloam",
    "tgn:placetype":[
        "aat:300008347"
    ]
},
  "bbox": [],
  "geometry": {"coordinates":[-88.75,33.6333],"type":"Point"}
}