{
  "id": 2001224,
  "type": "Feature",
  "properties": {
    "tgn:hierarchy":[
        "tgn:2001224",
        "tgn:1000001",
        "tgn:7012149",
        "tgn:7007523",
        "tgn:7029392"
    ],
    "tgn:id":2001224,
    "tgn:name":"Nodaway",
    "tgn:placetype":[
        "aat:300387145",
        "aat:300000771"
    ]
},
  "bbox": [],
  "geometry": {"coordinates":[-94.8667,40.35],"type":"Point"}
}