{
  "id": 2673690,
  "type": "Feature",
  "properties": {
    "tgn:hierarchy":[
        "tgn:2673690",
        "tgn:1000001",
        "tgn:7012149",
        "tgn:7007157",
        "tgn:1002972",
        "tgn:7029392"
    ],
    "tgn:id":2673690,
    "tgn:name":"Snow Canyon",
    "tgn:placetype":[
        "aat:300008761"
    ]
},
  "bbox": [],
  "geometry": {"coordinates":[-118.9667,34.4333],"type":"Point"}
}