<<<<<<< HEAD
{
  "id": 2769451,
  "type": "Feature",
  "properties": {
    "tgn:hierarchy":[
        "tgn:2769451",
        "tgn:1000001",
        "tgn:7012149",
        "tgn:2002121",
        "tgn:7007827",
        "tgn:7029392"
    ],
    "tgn:id":2769451,
    "tgn:name":"Wide Hollow",
    "tgn:placetype":[
        "aat:300008761"
    ]
},
  "bbox": [],
  "geometry": {"coordinates":[-111.5,38.8167],"type":"Point"}
}
=======
{"geometry":{"type":"Point","coordinates":[-111.500000,38.816700]},"type":"Feature","properties":{"hierarchy":["tgn:2769451","tgn:1000001","tgn:7012149","tgn:2002121","tgn:7007827","tgn:7029392"],"placetype":["aat:300008761"],"id":2769451,"name:xx":"Wide Hollow"}}
>>>>>>> 03f74aca74312dbeaf24d7e61306dd6a786dc3d0
