{
  "id": 7016994,
  "type": "Feature",
  "properties": {
    "tgn:hierarchy":[
        "tgn:7016994",
        "tgn:7007877",
        "tgn:1000003",
        "tgn:1000063",
        "tgn:4012014",
        "tgn:7029392"
    ],
    "tgn:id":7016994,
    "tgn:name":"Bouvignes",
    "tgn:placetype":[
        "aat:300008347",
        "aat:300008375"
    ]
},
  "bbox": [],
  "geometry": {"coordinates":[3.7667,50.6333],"type":"Point"}
}