{
  "id": 2179072,
  "type": "Feature",
  "properties": {
    "tgn:hierarchy":[
        "tgn:2179072",
        "tgn:1002135",
        "tgn:1000001",
        "tgn:7012149",
        "tgn:7007252",
        "tgn:7029392"
    ],
    "tgn:id":2179072,
    "tgn:name":"Blair Ditch",
    "tgn:placetype":[
        "aat:300006075"
    ]
},
  "bbox": [],
  "geometry": {"coordinates":[-84.9833,40.75],"type":"Point"}
}