{
  "id": 7492768,
  "type": "Feature",
  "properties": {
    "tgn:hierarchy":[
        "tgn:7492768",
        "tgn:1000004",
        "tgn:7471332",
        "tgn:1000141",
        "tgn:7029392"
    ],
    "tgn:id":7492768,
    "tgn:name":"Sizuowu",
    "tgn:placetype":[
        "aat:300008347"
    ]
},
  "bbox": [],
  "geometry": {"coordinates":[121.083333,24.827222],"type":"Point"}
}