{
  "id": 7394033,
  "type": "Feature",
  "properties": {
    "tgn:hierarchy":[
        "tgn:7394033",
        "tgn:1000001",
        "tgn:7005591",
        "tgn:7005560",
        "tgn:7029392"
    ],
    "tgn:id":7394033,
    "tgn:name:es":"San Bernardo",
    "tgn:placetype":[
        "aat:300008347"
    ]
},
  "bbox": [],
  "geometry": {"coordinates":[-96.718611,16.382778],"type":"Point"}
}