{
  "id": 7265189,
  "type": "Feature",
  "properties": {
    "tgn:concordances":{
        "gn:id":"2752812"
    },
    "tgn:hierarchy":[
        "tgn:7265189",
        "tgn:1000003",
        "tgn:7003624",
        "tgn:7016845",
        "tgn:7029392"
    ],
    "tgn:id":7265189,
    "tgn:name:nl":"Kladde",
    "tgn:placetype":[
        "aat:300008347"
    ]
},
  "bbox": [],
  "geometry": {"coordinates":[4.266667,51.55],"type":"Point"}
}