{
  "id": 2310836,
  "type": "Feature",
  "properties": {
    "tgn:hierarchy":[
        "tgn:2310836",
        "tgn:2000090",
        "tgn:1000001",
        "tgn:7006451",
        "tgn:7012149",
        "tgn:7029392"
    ],
    "tgn:id":2310836,
    "tgn:name":"Ed Walker Tank",
    "tgn:placetype":[
        "aat:300006191"
    ]
},
  "bbox": [],
  "geometry": {"coordinates":[-109.5833,34.05],"type":"Point"}
}