{
  "id": 7563436,
  "type": "Feature",
  "properties": {
    "tgn:hierarchy":[
        "tgn:7563436",
        "tgn:1000004",
        "tgn:7000198",
        "tgn:7016788",
        "tgn:7029392"
    ],
    "tgn:id":7563436,
    "tgn:name":"Ghur\u0101la Johra",
    "tgn:placetype":[
        "aat:300008688"
    ]
},
  "bbox": [],
  "geometry": {"coordinates":[74.568502,28.754932],"type":"Point"}
}