{
  "id": 7228849,
  "type": "Feature",
  "properties": {
    "tgn:hierarchy":[
        "tgn:7228849",
        "tgn:7002690",
        "tgn:7012056",
        "tgn:1000003",
        "tgn:1000074",
        "tgn:7029392"
    ],
    "tgn:id":7228849,
    "tgn:name":"Gavalokh\u00f3rion",
    "tgn:placetype":[
        "aat:300008347"
    ]
},
  "bbox": [],
  "geometry": {"coordinates":[24.216667,35.416667],"type":"Point"}
}