{
  "id": 7487544,
  "type": "Feature",
  "properties": {
    "tgn:hierarchy":[
        "tgn:7487544",
        "tgn:7487020",
        "tgn:1000004",
        "tgn:1000141",
        "tgn:7029392"
    ],
    "tgn:id":7487544,
    "tgn:name":"Huangmayuan",
    "tgn:placetype":[
        "aat:300008347"
    ]
},
  "bbox": [],
  "geometry": {"coordinates":[120.829346,24.42082],"type":"Point"}
}