{
  "id": 2776341,
  "type": "Feature",
  "properties": {
    "tgn:hierarchy":[
        "tgn:2776341",
        "tgn:1000001",
        "tgn:7012149",
        "tgn:7007157",
        "tgn:1003046",
        "tgn:7029392"
    ],
    "tgn:id":2776341,
    "tgn:name":"Winchester Lake",
    "tgn:placetype":[
        "aat:300008680"
    ]
},
  "bbox": [],
  "geometry": {"coordinates":[-121.55,38.4333],"type":"Point"}
}