{
  "id": 7409558,
  "type": "Feature",
  "properties": {
    "tgn:hierarchy":[
        "tgn:7409558",
        "tgn:1000001",
        "tgn:7005590",
        "tgn:7005560",
        "tgn:7029392"
    ],
    "tgn:id":7409558,
    "tgn:name":"San Mart\u00edn",
    "tgn:placetype":[
        "aat:300008347"
    ]
},
  "bbox": [],
  "geometry": {"coordinates":[-101.627778,20.216667],"type":"Point"}
}