{
  "id": 2642714,
  "type": "Feature",
  "properties": {
    "tgn:hierarchy":[
        "tgn:2642714",
        "tgn:1000001",
        "tgn:7012149",
        "tgn:2000986",
        "tgn:7007520",
        "tgn:7029392"
    ],
    "tgn:id":2642714,
    "tgn:name":"Sandhill Creek",
    "tgn:placetype":[
        "aat:300008706"
    ]
},
  "bbox": [],
  "geometry": {"coordinates":[-89.5167,46.6667],"type":"Point"}
}