{
  "id": 1114718,
  "type": "Feature",
  "properties": {
    "tgn:hierarchy":[
        "tgn:1114718",
        "tgn:1000617",
        "tgn:1000001",
        "tgn:7005554",
        "tgn:7029392"
    ],
    "tgn:id":1114718,
    "tgn:name":"Brus, Laguna de",
    "tgn:placetype":[
        "aat:300008679"
    ]
},
  "bbox": [],
  "geometry": {"coordinates":[-84.55,15.8167],"type":"Point"}
}