{
  "id": 2414311,
  "type": "Feature",
  "properties": {
    "tgn:hierarchy":[
        "tgn:2414311",
        "tgn:1000001",
        "tgn:7012149",
        "tgn:2001828",
        "tgn:7007713",
        "tgn:7029392"
    ],
    "tgn:id":2414311,
    "tgn:name":"Iron Post Buttes",
    "tgn:placetype":[
        "aat:300386831"
    ]
},
  "bbox": [],
  "geometry": {"coordinates":[-100.6833,44.6833],"type":"Point"}
}