{
  "id": 7591896,
  "type": "Feature",
  "properties": {
    "tgn:hierarchy":[
        "tgn:7591896",
        "tgn:1000004",
        "tgn:7000198",
        "tgn:7000799",
        "tgn:7029392"
    ],
    "tgn:id":7591896,
    "tgn:name:en":"N\u0101nakpur",
    "tgn:placetype":[
        "aat:300008347"
    ]
},
  "bbox": [],
  "geometry": {"coordinates":[74.866667,32.691667],"type":"Point"}
}