{
  "id": 2089758,
  "type": "Feature",
  "properties": {
    "tgn:hierarchy":[
        "tgn:2089758",
        "tgn:1000001",
        "tgn:7012149",
        "tgn:1002352",
        "tgn:7007710",
        "tgn:7029392"
    ],
    "tgn:id":2089758,
    "tgn:name":"Kersey",
    "tgn:placetype":[
        "aat:300008347"
    ]
},
  "bbox": [],
  "geometry": {"coordinates":[-78.5833,41.35],"type":"Point"}
}