{
  "id": 7129390,
  "type": "Feature",
  "properties": {
    "tgn:hierarchy":[
        "tgn:7129390",
        "tgn:7000096",
        "tgn:1000003",
        "tgn:7000084",
        "tgn:7029392"
    ],
    "tgn:id":7129390,
    "tgn:name":"Mellnsee",
    "tgn:placetype":[
        "aat:300008903"
    ]
},
  "bbox": [],
  "geometry": {"coordinates":[13.783333,53.016667],"type":"Point"}
}