{
  "id": 7091597,
  "type": "Feature",
  "properties": {
    "tgn:hierarchy":[
        "tgn:7091597",
        "tgn:1000003",
        "tgn:7003678",
        "tgn:7000084",
        "tgn:7029392"
    ],
    "tgn:id":7091597,
    "tgn:name":"Vockenrod",
    "tgn:placetype":[
        "aat:300008347"
    ]
},
  "bbox": [],
  "geometry": {"coordinates":[9.216667,50.766667],"type":"Point"}
}