<<<<<<< HEAD
{
  "id": 7368822,
  "type": "Feature",
  "properties": {
    "tgn:hierarchy":[
        "tgn:7368822",
        "tgn:1000001",
        "tgn:7005600",
        "tgn:7005560",
        "tgn:7029392"
    ],
    "tgn:id":7368822,
    "tgn:name":"Hoct\u00fan",
    "tgn:placetype":[
        "aat:300008347"
    ]
},
  "bbox": [],
  "geometry": {"coordinates":[-89.2,20.866667],"type":"Point"}
}
=======
{"geometry":{"type":"Point","coordinates":[-89.200000,20.866667]},"type":"Feature","properties":{"hierarchy":["tgn:7368822","tgn:1000001","tgn:7005600","tgn:7005560","tgn:7029392"],"placetype":["aat:300008347"],"id":7368822,"name:xx":"Hoct\u00fan"}}
>>>>>>> 03f74aca74312dbeaf24d7e61306dd6a786dc3d0
