{
  "id": 2138633,
  "type": "Feature",
  "properties": {
    "tgn:hierarchy":[
        "tgn:2138633",
        "tgn:1000001",
        "tgn:2002370",
        "tgn:7012149",
        "tgn:7007923",
        "tgn:7029392"
    ],
    "tgn:id":2138633,
    "tgn:name":"Ash Draw",
    "tgn:placetype":[
        "aat:300008761"
    ]
},
  "bbox": [],
  "geometry": {"coordinates":[-104.9667,44.6167],"type":"Point"}
}