{
  "id": 1022083,
  "type": "Feature",
  "properties": {
    "tgn:hierarchy":[
        "tgn:1022083",
        "tgn:1001834",
        "tgn:1000047",
        "tgn:7002455",
        "tgn:1000002",
        "tgn:7029392"
    ],
    "tgn:id":1022083,
    "tgn:name":"Medeiros Neto",
    "tgn:placetype":[
        "aat:300008347"
    ]
},
  "bbox": [],
  "geometry": {"coordinates":[-40.2333,-17.3333],"type":"Point"}
}