{
  "id": 2444088,
  "type": "Feature",
  "properties": {
    "tgn:hierarchy":[
        "tgn:2444088",
        "tgn:1000001",
        "tgn:2001790",
        "tgn:7012149",
        "tgn:7007713",
        "tgn:7029392"
    ],
    "tgn:id":2444088,
    "tgn:name":"LaPlant",
    "tgn:placetype":[
        "aat:300008347"
    ]
},
  "bbox": [],
  "geometry": {"coordinates":[-100.65,45.1333],"type":"Point"}
}