<<<<<<< HEAD
{
  "id": 2157932,
  "type": "Feature",
  "properties": {
    "tgn:hierarchy":[
        "tgn:2157932",
        "tgn:1000001",
        "tgn:7012149",
        "tgn:7007158",
        "tgn:2000243",
        "tgn:7029392"
    ],
    "tgn:id":2157932,
    "tgn:name":"Beaver Lake Reservoir",
    "tgn:placetype":[
        "aat:300006191"
    ]
},
  "bbox": [],
  "geometry": {"coordinates":[-107.6333,39.9],"type":"Point"}
}
=======
{"geometry":{"type":"Point","coordinates":[-107.633300,39.900000]},"type":"Feature","properties":{"hierarchy":["tgn:2157932","tgn:1000001","tgn:7012149","tgn:7007158","tgn:2000243","tgn:7029392"],"placetype":["aat:300006191"],"id":2157932,"name:xx":"Beaver Lake Reservoir"}}
>>>>>>> 03f74aca74312dbeaf24d7e61306dd6a786dc3d0
