{
  "id": 7144502,
  "type": "Feature",
  "properties": {
    "tgn:hierarchy":[
        "tgn:7144502",
        "tgn:1000003",
        "tgn:7000094",
        "tgn:7000084",
        "tgn:7029392"
    ],
    "tgn:id":7144502,
    "tgn:name":"Kotzen-See",
    "tgn:placetype":[
        "aat:300008688"
    ]
},
  "bbox": [],
  "geometry": {"coordinates":[14.316667,53.316667],"type":"Point"}
}