{
  "id": 2629733,
  "type": "Feature",
  "properties": {
    "tgn:hierarchy":[
        "tgn:2629733",
        "tgn:1000001",
        "tgn:2001173",
        "tgn:7012149",
        "tgn:7007523",
        "tgn:7029392"
    ],
    "tgn:id":2629733,
    "tgn:name":"Ross Creek",
    "tgn:placetype":[
        "aat:300008706"
    ]
},
  "bbox": [],
  "geometry": {"coordinates":[-93.1333,38.3167],"type":"Point"}
}