{
  "id": 7563274,
  "type": "Feature",
  "properties": {
    "tgn:hierarchy":[
        "tgn:7563274",
        "tgn:1000004",
        "tgn:7000198",
        "tgn:7016722",
        "tgn:7029392"
    ],
    "tgn:id":7563274,
    "tgn:name:en":"Salempur T\u0101ra",
    "tgn:placetype":[
        "aat:300008347"
    ]
},
  "bbox": [],
  "geometry": {"coordinates":[79.9526,27.0313],"type":"Point"}
}