<<<<<<< HEAD
{
  "id": 2760143,
  "type": "Feature",
  "properties": {
    "tgn:hierarchy":[
        "tgn:2760143",
        "tgn:1000001",
        "tgn:7016172",
        "tgn:2000119",
        "tgn:7012149",
        "tgn:7029392"
    ],
    "tgn:id":2760143,
    "tgn:name":"West Fork Point Remove Creek Site Five Reservoir",
    "tgn:placetype":[
        "aat:300006191"
    ]
},
  "bbox": [],
  "geometry": {"coordinates":[-92.75,35.45],"type":"Point"}
}
=======
{"geometry":{"type":"Point","coordinates":[-92.750000,35.450000]},"type":"Feature","properties":{"hierarchy":["tgn:2760143","tgn:1000001","tgn:7016172","tgn:2000119","tgn:7012149","tgn:7029392"],"placetype":["aat:300006191"],"id":2760143,"name:xx":"West Fork Point Remove Creek Site Five Reservoir"}}
>>>>>>> 03f74aca74312dbeaf24d7e61306dd6a786dc3d0
