{
  "id": 2758297,
  "type": "Feature",
  "properties": {
    "tgn:hierarchy":[
        "tgn:2758297",
        "tgn:1000001",
        "tgn:7012149",
        "tgn:2000926",
        "tgn:7007515",
        "tgn:7029392"
    ],
    "tgn:id":2758297,
    "tgn:name":"West Brownfield",
    "tgn:placetype":[
        "aat:300008347"
    ]
},
  "bbox": [],
  "geometry": {"coordinates":[-70.9667,43.9167],"type":"Point"}
}