{
  "id": 1018763,
  "type": "Feature",
  "properties": {
    "tgn:hierarchy":[
        "tgn:1018763",
        "tgn:1000570",
        "tgn:1000001",
        "tgn:7005562",
        "tgn:7029392"
    ],
    "tgn:id":1018763,
    "tgn:name":"Morrito",
    "tgn:placetype":[
        "aat:300008347"
    ]
},
  "bbox": [],
  "geometry": {"coordinates":[-85.0833,11.6167],"type":"Point"}
}