{
  "id": 1131493,
  "type": "Feature",
  "properties": {
    "tgn:hierarchy":[
        "tgn:1131493",
        "tgn:1000003",
        "tgn:7006542",
        "tgn:7029392"
    ],
    "tgn:id":1131493,
    "tgn:name":"Virvy\u010dia",
    "tgn:placetype":[
        "aat:300008707"
    ]
},
  "bbox": [],
  "geometry": {"coordinates":[22.5667,56.2167],"type":"Point"}
}