{
  "id": 7409071,
  "type": "Feature",
  "properties": {
    "tgn:hierarchy":[
        "tgn:7409071",
        "tgn:1000001",
        "tgn:7005590",
        "tgn:7005560",
        "tgn:7029392"
    ],
    "tgn:id":7409071,
    "tgn:name":"Capullo",
    "tgn:placetype":[
        "aat:300008347"
    ]
},
  "bbox": [],
  "geometry": {"coordinates":[-100.9375,19.498611],"type":"Point"}
}