{
  "id": 2197528,
  "type": "Feature",
  "properties": {
    "tgn:hierarchy":[
        "tgn:2197528",
        "tgn:1000001",
        "tgn:7012149",
        "tgn:7007255",
        "tgn:7029392"
    ],
    "tgn:id":2197528,
    "tgn:name":"Brown Fork",
    "tgn:placetype":[
        "aat:300008699"
    ]
},
  "bbox": [],
  "geometry": {"coordinates":[-83.25,38.1167],"type":"Point"}
}