{
  "id": 7593577,
  "type": "Feature",
  "properties": {
    "tgn:hierarchy":[
        "tgn:7593577",
        "tgn:7005510",
        "tgn:1000001",
        "tgn:7005502",
        "tgn:7029392"
    ],
    "tgn:id":7593577,
    "tgn:name":"Mirebalais",
    "tgn:placetype":[
        "aat:300008347"
    ]
},
  "bbox": [],
  "geometry": {"coordinates":[-72.105,18.833],"type":"Point"}
}