{
  "id": 2591848,
  "type": "Feature",
  "properties": {
    "tgn:hierarchy":[
        "tgn:2591848",
        "tgn:1000001",
        "tgn:1002664",
        "tgn:7012149",
        "tgn:7007159",
        "tgn:7029392"
    ],
    "tgn:id":2591848,
    "tgn:name":"Pond Meadow",
    "tgn:placetype":[
        "aat:300008905"
    ]
},
  "bbox": [],
  "geometry": {"coordinates":[-72.45,41.3167],"type":"Point"}
}