{
  "id": 2518352,
  "type": "Feature",
  "properties": {
    "tgn:hierarchy":[
        "tgn:2518352",
        "tgn:1000001",
        "tgn:7012149",
        "tgn:7007520",
        "tgn:7029392"
    ],
    "tgn:id":2518352,
    "tgn:name":"Misteguay Creek",
    "tgn:placetype":[
        "aat:300008706"
    ]
},
  "bbox": [],
  "geometry": {"coordinates":[-83.8833,42.9667],"type":"Point"}
}