{
  "id": 7572889,
  "type": "Feature",
  "properties": {
    "tgn:hierarchy":[
        "tgn:7572889",
        "tgn:1000004",
        "tgn:7000198",
        "tgn:7016788",
        "tgn:7029392"
    ],
    "tgn:id":7572889,
    "tgn:name:en":"Gubrend\u0101",
    "tgn:placetype":[
        "aat:300008347"
    ]
},
  "bbox": [],
  "geometry": {"coordinates":[77.200863,26.589393],"type":"Point"}
}