{
  "id": 1062462,
  "type": "Feature",
  "properties": {
    "tgn:hierarchy":[
        "tgn:1062462",
        "tgn:7002808",
        "tgn:7030216",
        "tgn:1000003",
        "tgn:1000095",
        "tgn:7029392"
    ],
    "tgn:id":1062462,
    "tgn:name":"San Pedro de Premi\u00e1",
    "tgn:placetype":[
        "aat:300008347"
    ]
},
  "bbox": [],
  "geometry": {"coordinates":[2.343718,41.507424],"type":"Point"}
}