<<<<<<< HEAD
{
  "id": 2338995,
  "type": "Feature",
  "properties": {
    "tgn:hierarchy":[
        "tgn:2338995",
        "tgn:1000001",
        "tgn:7012149",
        "tgn:2001879",
        "tgn:7007825",
        "tgn:7029392"
    ],
    "tgn:id":2338995,
    "tgn:name":"Franklin Hollow",
    "tgn:placetype":[
        "aat:300008761"
    ]
},
  "bbox": [],
  "geometry": {"coordinates":[-87.5333,35.9667],"type":"Point"}
}
=======
{"geometry":{"type":"Point","coordinates":[-87.533300,35.966700]},"type":"Feature","properties":{"hierarchy":["tgn:2338995","tgn:1000001","tgn:7012149","tgn:2001879","tgn:7007825","tgn:7029392"],"placetype":["aat:300008761"],"id":2338995,"name:xx":"Franklin Hollow"}}
>>>>>>> 03f74aca74312dbeaf24d7e61306dd6a786dc3d0
