{
  "id": 2519073,
  "type": "Feature",
  "properties": {
    "tgn:hierarchy":[
        "tgn:2519073",
        "tgn:1000001",
        "tgn:2001483",
        "tgn:7012149",
        "tgn:7007709",
        "tgn:7029392"
    ],
    "tgn:id":2519073,
    "tgn:name":"Mob Branch",
    "tgn:placetype":[
        "aat:300008699"
    ]
},
  "bbox": [],
  "geometry": {"coordinates":[-83.85,35.0833],"type":"Point"}
}