{
  "id": 7090981,
  "type": "Feature",
  "properties": {
    "tgn:hierarchy":[
        "tgn:7090981",
        "tgn:1000003",
        "tgn:7003677",
        "tgn:7000084",
        "tgn:7029392"
    ],
    "tgn:id":7090981,
    "tgn:name":"Varler Wald",
    "tgn:placetype":[
        "aat:300055621"
    ]
},
  "bbox": [],
  "geometry": {"coordinates":[8.55,52.416667],"type":"Point"}
}