{
  "id": 2772680,
  "type": "Feature",
  "properties": {
    "tgn:hierarchy":[
        "tgn:2772680",
        "tgn:1000001",
        "tgn:7012149",
        "tgn:7007826",
        "tgn:7029392"
    ],
    "tgn:id":2772680,
    "tgn:name":"Williams Creek",
    "tgn:placetype":[
        "aat:300008706"
    ]
},
  "bbox": [],
  "geometry": {"coordinates":[-98.5833,30.1667],"type":"Point"}
}