{
  "id": 2045173,
  "type": "Feature",
  "properties": {
    "tgn:hierarchy":[
        "tgn:2045173",
        "tgn:1000001",
        "tgn:2000925",
        "tgn:7012149",
        "tgn:7007515",
        "tgn:7029392"
    ],
    "tgn:id":2045173,
    "tgn:name":"Monhegan",
    "tgn:placetype":[
        "aat:300008347"
    ]
},
  "bbox": [],
  "geometry": {"coordinates":[-69.3167,43.75],"type":"Point"}
}