{
  "id": 2161489,
  "type": "Feature",
  "properties": {
    "tgn:hierarchy":[
        "tgn:2161489",
        "tgn:1000001",
        "tgn:7012149",
        "tgn:7007157",
        "tgn:2000185",
        "tgn:7029392"
    ],
    "tgn:id":2161489,
    "tgn:name":"Bell Springs Creek",
    "tgn:placetype":[
        "aat:300008706"
    ]
},
  "bbox": [],
  "geometry": {"coordinates":[-123.5833,39.95],"type":"Point"}
}