{
  "id": 2586464,
  "type": "Feature",
  "properties": {
    "tgn:hierarchy":[
        "tgn:2586464",
        "tgn:1000001",
        "tgn:7012149",
        "tgn:1002350",
        "tgn:7007157",
        "tgn:7029392"
    ],
    "tgn:id":2586464,
    "tgn:name":"Pitt Lake",
    "tgn:placetype":[
        "aat:300008680"
    ]
},
  "bbox": [],
  "geometry": {"coordinates":[-120.1167,38.8333],"type":"Point"}
}