{
  "id": 7276532,
  "type": "Feature",
  "properties": {
    "tgn:hierarchy":[
        "tgn:7276532",
        "tgn:1001702",
        "tgn:1000049",
        "tgn:1000002",
        "tgn:7029392"
    ],
    "tgn:id":7276532,
    "tgn:name":"El Quince, Punta",
    "tgn:placetype":[
        "aat:300386846"
    ]
},
  "bbox": [],
  "geometry": {"coordinates":[-70.941667,-53.216667],"type":"Point"}
}