{
  "id": 2265519,
  "type": "Feature",
  "properties": {
    "tgn:hierarchy":[
        "tgn:2265519",
        "tgn:1008304",
        "tgn:1009982",
        "tgn:1000001",
        "tgn:1002344",
        "tgn:7012149",
        "tgn:7007517",
        "tgn:7029392"
    ],
    "tgn:id":2265519,
    "tgn:name":"Crane Pond",
    "tgn:placetype":[
        "aat:300008680"
    ]
},
  "bbox": [],
  "geometry": {"coordinates":[-70.7333,41.4833],"type":"Point"}
}