{
  "id": 2112151,
  "type": "Feature",
  "properties": {
    "tgn:hierarchy":[
        "tgn:2112151",
        "tgn:1000001",
        "tgn:7012149",
        "tgn:2002193",
        "tgn:7007919",
        "tgn:7029392"
    ],
    "tgn:id":2112151,
    "tgn:name":"Happy Creek",
    "tgn:placetype":[
        "aat:300008347"
    ]
},
  "bbox": [],
  "geometry": {"coordinates":[-78.1333,38.9167],"type":"Point"}
}