{
  "id": 7427093,
  "type": "Feature",
  "properties": {
    "tgn:hierarchy":[
        "tgn:7427093",
        "tgn:7005581",
        "tgn:1000001",
        "tgn:7005560",
        "tgn:7029392"
    ],
    "tgn:id":7427093,
    "tgn:name":"Las Mesas",
    "tgn:placetype":[
        "aat:300008347"
    ]
},
  "bbox": [],
  "geometry": {"coordinates":[-106.583333,27.683333],"type":"Point"}
}