<<<<<<< HEAD
{
  "id": 7368246,
  "type": "Feature",
  "properties": {
    "tgn:hierarchy":[
        "tgn:7368246",
        "tgn:1001835",
        "tgn:1000001",
        "tgn:7005560",
        "tgn:7029392"
    ],
    "tgn:id":7368246,
    "tgn:name":"Escuela Jos\u00e9 Maria Morelos",
    "tgn:placetype":[
        "aat:300006495"
    ]
},
  "bbox": [],
  "geometry": {"coordinates":[-114.966667,32.633333],"type":"Point"}
}
=======
{"geometry":{"type":"Point","coordinates":[-114.966667,32.633333]},"type":"Feature","properties":{"hierarchy":["tgn:7368246","tgn:1001835","tgn:1000001","tgn:7005560","tgn:7029392"],"placetype":["aat:300006495"],"id":7368246,"name:xx":"Escuela Jos\u00e9 Maria Morelos"}}
>>>>>>> 03f74aca74312dbeaf24d7e61306dd6a786dc3d0
