{
  "id": 7201967,
  "type": "Feature",
  "properties": {
    "tgn:hierarchy":[
        "tgn:7201967",
        "tgn:7003692",
        "tgn:1000003",
        "tgn:7000084",
        "tgn:7029392"
    ],
    "tgn:id":7201967,
    "tgn:name":"Buch",
    "tgn:placetype":[
        "aat:300008347"
    ]
},
  "bbox": [],
  "geometry": {"coordinates":[9.966944,49.163333],"type":"Point"}
}