<<<<<<< HEAD
{
  "id": 7021359,
  "type": "Feature",
  "properties": {
    "tgn:hierarchy":[
        "tgn:7021359",
        "tgn:1000001",
        "tgn:7012149",
        "tgn:2001067",
        "tgn:7007521",
        "tgn:7029392"
    ],
    "tgn:id":7021359,
    "tgn:name":"Boulder Lake Reservoir",
    "tgn:placetype":[
        "aat:300006191"
    ]
},
  "bbox": [],
  "geometry": {"coordinates":[-92.1833,47.05],"type":"Point"}
}
=======
{"geometry":{"type":"Point","coordinates":[-92.183300,47.050000]},"type":"Feature","properties":{"hierarchy":["tgn:7021359","tgn:1000001","tgn:7012149","tgn:2001067","tgn:7007521","tgn:7029392"],"placetype":["aat:300006191"],"id":7021359,"name:xx":"Boulder Lake Reservoir"}}
>>>>>>> 03f74aca74312dbeaf24d7e61306dd6a786dc3d0
