{
  "id": 7354227,
  "type": "Feature",
  "properties": {
    "tgn:hierarchy":[
        "tgn:7354227",
        "tgn:7005584",
        "tgn:1000001",
        "tgn:7005560",
        "tgn:7029392"
    ],
    "tgn:id":7354227,
    "tgn:name":"Casas Blancas",
    "tgn:placetype":[
        "aat:300008347"
    ]
},
  "bbox": [],
  "geometry": {"coordinates":[-101.216667,21.383333],"type":"Point"}
}