{
  "id": 2255205,
  "type": "Feature",
  "properties": {
    "tgn:hierarchy":[
        "tgn:2255205",
        "tgn:1000001",
        "tgn:7012149",
        "tgn:2002265",
        "tgn:7013961",
        "tgn:7029392"
    ],
    "tgn:id":2255205,
    "tgn:name":"Cooper Mountain",
    "tgn:placetype":[
        "aat:300008798"
    ]
},
  "bbox": [],
  "geometry": {"coordinates":[-78.5167,39.25],"type":"Point"}
}