{
  "id": 2476996,
  "type": "Feature",
  "properties": {
    "tgn:hierarchy":[
        "tgn:2476996",
        "tgn:1000001",
        "tgn:2001704",
        "tgn:7012149",
        "tgn:7007708",
        "tgn:7029392"
    ],
    "tgn:id":2476996,
    "tgn:name":"Lynch Creek",
    "tgn:placetype":[
        "aat:300008706"
    ]
},
  "bbox": [],
  "geometry": {"coordinates":[-124.3667,42.4167],"type":"Point"}
}