{
  "id": 7036144,
  "type": "Feature",
  "properties": {
    "tgn:hierarchy":[
        "tgn:7036144",
        "tgn:7002996",
        "tgn:1000003",
        "tgn:7002997",
        "tgn:1000080",
        "tgn:7029392"
    ],
    "tgn:id":7036144,
    "tgn:name":"Rolle",
    "tgn:placetype":[
        "aat:300008347"
    ]
},
  "bbox": [],
  "geometry": {"coordinates":[12.165833,45.953056],"type":"Point"}
}