<<<<<<< HEAD
{
  "id": 2335409,
  "type": "Feature",
  "properties": {
    "tgn:hierarchy":[
        "tgn:2335409",
        "tgn:1000001",
        "tgn:2001734",
        "tgn:7012149",
        "tgn:7007712",
        "tgn:7029392"
    ],
    "tgn:id":2335409,
    "tgn:name":"Fort Moultrie",
    "tgn:placetype":[
        "aat:300008347"
    ]
},
  "bbox": [],
  "geometry": {"coordinates":[-79.85,32.75],"type":"Point"}
}
=======
{"geometry":{"type":"Point","coordinates":[-79.850000,32.750000]},"type":"Feature","properties":{"hierarchy":["tgn:2335409","tgn:1000001","tgn:2001734","tgn:7012149","tgn:7007712","tgn:7029392"],"placetype":["aat:300008347"],"id":2335409,"name:xx":"Fort Moultrie"}}
>>>>>>> 03f74aca74312dbeaf24d7e61306dd6a786dc3d0
