{
  "id": 7392421,
  "type": "Feature",
  "properties": {
    "tgn:hierarchy":[
        "tgn:7392421",
        "tgn:7005581",
        "tgn:1000001",
        "tgn:7005560",
        "tgn:7029392"
    ],
    "tgn:id":7392421,
    "tgn:name":"Rancho El Lucero",
    "tgn:placetype":[
        "aat:300008347"
    ]
},
  "bbox": [],
  "geometry": {"coordinates":[-104.933333,27.166667],"type":"Point"}
}