<<<<<<< HEAD
{
  "id": 7487958,
  "type": "Feature",
  "properties": {
    "tgn:hierarchy":[
        "tgn:7487958",
        "tgn:1000004",
        "tgn:7467799",
        "tgn:1000141",
        "tgn:7029392"
    ],
    "tgn:id":7487958,
    "tgn:name":"Nanfengliao",
    "tgn:placetype":[
        "aat:300008347"
    ]
},
  "bbox": [],
  "geometry": {"coordinates":[120.6032,24.00831],"type":"Point"}
}
=======
{"geometry":{"type":"Point","coordinates":[120.603200,24.008310]},"type":"Feature","properties":{"hierarchy":["tgn:7487958","tgn:1000004","tgn:7467799","tgn:1000141","tgn:7029392"],"placetype":["aat:300008347"],"id":7487958,"name:xx":"Nanfengliao"}}
>>>>>>> 03f74aca74312dbeaf24d7e61306dd6a786dc3d0
