{
  "id": 7559883,
  "type": "Feature",
  "properties": {
    "tgn:hierarchy":[
        "tgn:7559883",
        "tgn:1000004",
        "tgn:7000198",
        "tgn:7016722",
        "tgn:7029392"
    ],
    "tgn:id":7559883,
    "tgn:name:en":"Gup\u0101lpur",
    "tgn:placetype":[
        "aat:300008347"
    ]
},
  "bbox": [],
  "geometry": {"coordinates":[79.184484,26.991589],"type":"Point"}
}