{
  "id": 1002624,
  "type": "Feature",
  "properties": {
    "tgn:hierarchy":[
        "tgn:1002624",
        "tgn:1000001",
        "tgn:7012149",
        "tgn:7007568",
        "tgn:7029392"
    ],
    "tgn:id":1002624,
    "tgn:name":"Madison",
    "tgn:placetype":[
        "aat:300387145",
        "aat:300000771"
    ]
},
  "bbox": [],
  "geometry": {"coordinates":[-75.65,42.9333],"type":"Point"}
}