{
  "id": 2266866,
  "type": "Feature",
  "properties": {
    "tgn:hierarchy":[
        "tgn:2266866",
        "tgn:1000001",
        "tgn:7012149",
        "tgn:2002122",
        "tgn:7007827",
        "tgn:7029392"
    ],
    "tgn:id":2266866,
    "tgn:name":"Crescent Ridge",
    "tgn:placetype":[
        "aat:300266640"
    ]
},
  "bbox": [],
  "geometry": {"coordinates":[-111.5167,40.6333],"type":"Point"}
}