<<<<<<< HEAD
{
  "id": 7244808,
  "type": "Feature",
  "properties": {
    "tgn:hierarchy":[
        "tgn:7244808",
        "tgn:7003465",
        "tgn:1000003",
        "tgn:1000063",
        "tgn:4012014",
        "tgn:7029392"
    ],
    "tgn:id":7244808,
    "tgn:name":"Au del\u00e0 de l'Eau",
    "tgn:placetype":[
        "aat:300008347"
    ]
},
  "bbox": [],
  "geometry": {"coordinates":[5.416667,50.166667],"type":"Point"}
}
=======
{"geometry":{"type":"Point","coordinates":[5.416667,50.166667]},"type":"Feature","properties":{"hierarchy":["tgn:7244808","tgn:7003465","tgn:1000003","tgn:1000063","tgn:4012014","tgn:7029392"],"placetype":["aat:300008347"],"id":7244808,"name:xx":"Au del\u00e0 de l'Eau"}}
>>>>>>> 03f74aca74312dbeaf24d7e61306dd6a786dc3d0
