<<<<<<< HEAD
{
  "id": 2253511,
  "type": "Feature",
  "properties": {
    "tgn:hierarchy":[
        "tgn:2253511",
        "tgn:1000001",
        "tgn:2002243",
        "tgn:7012149",
        "tgn:7007920",
        "tgn:7029392"
    ],
    "tgn:id":2253511,
    "tgn:name":"Cook Creek",
    "tgn:placetype":[
        "aat:300008706"
    ]
},
  "bbox": [],
  "geometry": {"coordinates":[-118.6,48.1167],"type":"Point"}
}
=======
{"geometry":{"type":"Point","coordinates":[-118.600000,48.116700]},"type":"Feature","properties":{"hierarchy":["tgn:2253511","tgn:1000001","tgn:2002243","tgn:7012149","tgn:7007920","tgn:7029392"],"placetype":["aat:300008706"],"id":2253511,"name:xx":"Cook Creek"}}
>>>>>>> 03f74aca74312dbeaf24d7e61306dd6a786dc3d0
