{
  "id": 7340411,
  "type": "Feature",
  "properties": {
    "tgn:hierarchy":[
        "tgn:7340411",
        "tgn:7002847",
        "tgn:1001647",
        "tgn:1000003",
        "tgn:1000095",
        "tgn:7029392"
    ],
    "tgn:id":7340411,
    "tgn:name":"Cuevas, Arroyo de las",
    "tgn:placetype":[
        "aat:300008699"
    ]
},
  "bbox": [],
  "geometry": {"coordinates":[-4.366667,39.816667],"type":"Point"}
}