{
  "id": 7550666,
  "type": "Feature",
  "properties": {
    "tgn:hierarchy":[
        "tgn:7550666",
        "tgn:1000004",
        "tgn:7000198",
        "tgn:1001895",
        "tgn:7029392"
    ],
    "tgn:id":7550666,
    "tgn:name:en":"Dhulpimpri",
    "tgn:placetype":[
        "aat:300008347"
    ]
},
  "bbox": [],
  "geometry": {"coordinates":[75.225324,20.818202],"type":"Point"}
}