{
  "id": 7559334,
  "type": "Feature",
  "properties": {
    "tgn:hierarchy":[
        "tgn:7559334",
        "tgn:1000004",
        "tgn:7031781",
        "tgn:7000198",
        "tgn:7029392"
    ],
    "tgn:id":7559334,
    "tgn:name:en":"Sarsonpuri",
    "tgn:placetype":[
        "aat:300007783"
    ]
},
  "bbox": [],
  "geometry": {"coordinates":[81.638213,20.781134],"type":"Point"}
}