{
  "id": 2441249,
  "type": "Feature",
  "properties": {
    "tgn:hierarchy":[
        "tgn:2441249",
        "tgn:1000001",
        "tgn:2001786",
        "tgn:7012149",
        "tgn:7007713",
        "tgn:7029392"
    ],
    "tgn:id":2441249,
    "tgn:name":"Knowles Lode Claim Mine",
    "tgn:placetype":[
        "aat:300000390"
    ]
},
  "bbox": [],
  "geometry": {"coordinates":[-103.5833,43.7667],"type":"Point"}
}