{
  "id": 7075625,
  "type": "Feature",
  "properties": {
    "tgn:hierarchy":[
        "tgn:7075625",
        "tgn:7003692",
        "tgn:1000003",
        "tgn:7000084",
        "tgn:7029392"
    ],
    "tgn:id":7075625,
    "tgn:name":"Ufgau",
    "tgn:placetype":[
        "aat:300055621"
    ]
},
  "bbox": [],
  "geometry": {"coordinates":[8.333333,48.883333],"type":"Point"}
}