{
  "id": 2006448,
  "type": "Feature",
  "properties": {
    "tgn:hierarchy":[
        "tgn:2006448",
        "tgn:7006450",
        "tgn:1000001",
        "tgn:2000071",
        "tgn:7012149",
        "tgn:7029392"
    ],
    "tgn:id":2006448,
    "tgn:name":"Twin Hills",
    "tgn:placetype":[
        "aat:300008347"
    ]
},
  "bbox": [],
  "geometry": {"coordinates":[-160.2667,59.0667],"type":"Point"}
}