{
  "id": 7345293,
  "type": "Feature",
  "properties": {
    "tgn:hierarchy":[
        "tgn:7345293",
        "tgn:7001122",
        "tgn:1000003",
        "tgn:7002765",
        "tgn:1000095",
        "tgn:7029392"
    ],
    "tgn:id":7345293,
    "tgn:name":"Algaida",
    "tgn:placetype":[
        "aat:300008347"
    ]
},
  "bbox": [],
  "geometry": {"coordinates":[2.866667,39.55],"type":"Point"}
}