{
  "id": 7507588,
  "type": "Feature",
  "properties": {
    "tgn:hierarchy":[
        "tgn:7507588",
        "tgn:1009227",
        "tgn:1000226",
        "tgn:7520095",
        "tgn:1000006",
        "tgn:7029392"
    ],
    "tgn:id":7507588,
    "tgn:name:en":"Porters Rock",
    "tgn:placetype":[
        "aat:300008795"
    ]
},
  "bbox": [],
  "geometry": {"coordinates":[172.95,-40.933333],"type":"Point"}
}