{
  "id": 2038844,
  "type": "Feature",
  "properties": {
    "tgn:hierarchy":[
        "tgn:2038844",
        "tgn:1000001",
        "tgn:1002240",
        "tgn:7012149",
        "tgn:7007255",
        "tgn:7029392"
    ],
    "tgn:id":2038844,
    "tgn:name":"Fitch",
    "tgn:placetype":[
        "aat:300008347",
        "aat:300387210"
    ]
},
  "bbox": [],
  "geometry": {"coordinates":[-83.3333,38.3167],"type":"Point"}
}