{
  "id": 2220061,
  "type": "Feature",
  "properties": {
    "tgn:hierarchy":[
        "tgn:2220061",
        "tgn:1000001",
        "tgn:2002366",
        "tgn:7012149",
        "tgn:7007923",
        "tgn:7029392"
    ],
    "tgn:id":2220061,
    "tgn:name":"Canyon Creek",
    "tgn:placetype":[
        "aat:300008706"
    ]
},
  "bbox": [],
  "geometry": {"coordinates":[-107.2167,44.3833],"type":"Point"}
}