<<<<<<< HEAD
{
  "id": 2406185,
  "type": "Feature",
  "properties": {
    "tgn:hierarchy":[
        "tgn:2406185",
        "tgn:1000001",
        "tgn:7012149",
        "tgn:2000180",
        "tgn:7007157",
        "tgn:7029392"
    ],
    "tgn:id":2406185,
    "tgn:name":"Hump Rock",
    "tgn:placetype":[
        "aat:300008791"
    ]
},
  "bbox": [],
  "geometry": {"coordinates":[-124.3,41.7667],"type":"Point"}
}
=======
{"geometry":{"type":"Point","coordinates":[-124.300000,41.766700]},"type":"Feature","properties":{"hierarchy":["tgn:2406185","tgn:1000001","tgn:7012149","tgn:2000180","tgn:7007157","tgn:7029392"],"placetype":["aat:300008791"],"id":2406185,"name:xx":"Hump Rock"}}
>>>>>>> 03f74aca74312dbeaf24d7e61306dd6a786dc3d0
