{
  "id": 7537458,
  "type": "Feature",
  "properties": {
    "tgn:hierarchy":[
        "tgn:7537458",
        "tgn:7001242",
        "tgn:7016833",
        "tgn:1001335",
        "tgn:7029392"
    ],
    "tgn:id":7537458,
    "tgn:name:en":"Naqb, Q\u0101'an",
    "tgn:placetype":[
        "aat:300132350"
    ]
},
  "bbox": [],
  "geometry": {"coordinates":[34.849787,29.613099],"type":"Point"}
}