{
  "id": 2202019,
  "type": "Feature",
  "properties": {
    "tgn:hierarchy":[
        "tgn:2202019",
        "tgn:1000001",
        "tgn:7012149",
        "tgn:2001164",
        "tgn:7007522",
        "tgn:7029392"
    ],
    "tgn:id":2202019,
    "tgn:name":"Buck Island",
    "tgn:placetype":[
        "aat:300008791"
    ]
},
  "bbox": [],
  "geometry": {"coordinates":[-91.45,31.2667],"type":"Point"}
}