{
  "id": 2377654,
  "type": "Feature",
  "properties": {
    "tgn:hierarchy":[
        "tgn:2377654",
        "tgn:1000001",
        "tgn:7012149",
        "tgn:1002368",
        "tgn:7007919",
        "tgn:7029392"
    ],
    "tgn:id":2377654,
    "tgn:name":"Harpers Run",
    "tgn:placetype":[
        "aat:300008699"
    ]
},
  "bbox": [],
  "geometry": {"coordinates":[-77.6833,38.5167],"type":"Point"}
}