{
  "id": 2300600,
  "type": "Feature",
  "properties": {
    "tgn:hierarchy":[
        "tgn:2300600",
        "tgn:1000001",
        "tgn:2001419",
        "tgn:7012149",
        "tgn:7007526",
        "tgn:7029392"
    ],
    "tgn:id":2300600,
    "tgn:name":"Dun Glen Mine",
    "tgn:placetype":[
        "aat:300000390"
    ]
},
  "bbox": [],
  "geometry": {"coordinates":[-117.9167,40.7333],"type":"Point"}
}