{
  "id": 7376895,
  "type": "Feature",
  "properties": {
    "tgn:hierarchy":[
        "tgn:7376895",
        "tgn:7005585",
        "tgn:1000001",
        "tgn:7005560",
        "tgn:7029392"
    ],
    "tgn:id":7376895,
    "tgn:name":"Las \u00c1nimas",
    "tgn:placetype":[
        "aat:300008347"
    ]
},
  "bbox": [],
  "geometry": {"coordinates":[-101.516667,18.066667],"type":"Point"}
}