{
  "id": 2338283,
  "type": "Feature",
  "properties": {
    "tgn:hierarchy":[
        "tgn:2338283",
        "tgn:2000455",
        "tgn:1000001",
        "tgn:7012149",
        "tgn:7007250",
        "tgn:7029392"
    ],
    "tgn:id":2338283,
    "tgn:name":"Fox Spring",
    "tgn:placetype":[
        "aat:300008697"
    ]
},
  "bbox": [],
  "geometry": {"coordinates":[-111.2167,42.3667],"type":"Point"}
}