<<<<<<< HEAD
{
  "id": 2338283,
  "type": "Feature",
  "properties": {
    "tgn:hierarchy":[
        "tgn:2338283",
        "tgn:2000455",
        "tgn:1000001",
        "tgn:7012149",
        "tgn:7007250",
        "tgn:7029392"
    ],
    "tgn:id":2338283,
    "tgn:name":"Fox Spring",
    "tgn:placetype":[
        "aat:300008697"
    ]
},
  "bbox": [],
  "geometry": {"coordinates":[-111.2167,42.3667],"type":"Point"}
}
=======
{"geometry":{"type":"Point","coordinates":[-111.216700,42.366700]},"type":"Feature","properties":{"hierarchy":["tgn:2338283","tgn:2000455","tgn:1000001","tgn:7012149","tgn:7007250","tgn:7029392"],"placetype":["aat:300008697"],"id":2338283,"name:xx":"Fox Spring"}}
>>>>>>> 03f74aca74312dbeaf24d7e61306dd6a786dc3d0
