{
  "id": 2446611,
  "type": "Feature",
  "properties": {
    "tgn:hierarchy":[
        "tgn:2446611",
        "tgn:1000001",
        "tgn:7012149",
        "tgn:1002767",
        "tgn:7007920",
        "tgn:7029392"
    ],
    "tgn:id":2446611,
    "tgn:name":"Lewis Slough",
    "tgn:placetype":[
        "aat:300008699"
    ]
},
  "bbox": [],
  "geometry": {"coordinates":[-123.9667,46.45],"type":"Point"}
}