{
  "id": 7113953,
  "type": "Feature",
  "properties": {
    "tgn:hierarchy":[
        "tgn:7113953",
        "tgn:7003669",
        "tgn:1000003",
        "tgn:7000084",
        "tgn:7029392"
    ],
    "tgn:id":7113953,
    "tgn:name":"Riedler Graben",
    "tgn:placetype":[
        "aat:300008699"
    ]
},
  "bbox": [],
  "geometry": {"coordinates":[11.75,47.633333],"type":"Point"}
}