{
  "id": 2341619,
  "type": "Feature",
  "properties": {
    "tgn:hierarchy":[
        "tgn:2341619",
        "tgn:1000001",
        "tgn:7012149",
        "tgn:1002387",
        "tgn:7007710",
        "tgn:7029392"
    ],
    "tgn:id":2341619,
    "tgn:name":"Front Mountain",
    "tgn:placetype":[
        "aat:300008798"
    ]
},
  "bbox": [],
  "geometry": {"coordinates":[-77.8167,39.95],"type":"Point"}
}