{
  "id": 2774691,
  "type": "Feature",
  "properties": {
    "tgn:hierarchy":[
        "tgn:2774691",
        "tgn:1000001",
        "tgn:7012149",
        "tgn:2001455",
        "tgn:7007566",
        "tgn:7029392"
    ],
    "tgn:id":2774691,
    "tgn:name":"Willow Spring",
    "tgn:placetype":[
        "aat:300008697"
    ]
},
  "bbox": [],
  "geometry": {"coordinates":[-107.8333,33.1167],"type":"Point"}
}