{
  "id": 7167053,
  "type": "Feature",
  "properties": {
    "tgn:hierarchy":[
        "tgn:7167053",
        "tgn:1000003",
        "tgn:7003689",
        "tgn:7000084",
        "tgn:7029392"
    ],
    "tgn:id":7167053,
    "tgn:name":"Heid-Berg",
    "tgn:placetype":[
        "aat:300008777"
    ]
},
  "bbox": [],
  "geometry": {"coordinates":[10.333333,51.416667],"type":"Point"}
}