{
  "id": 7042513,
  "type": "Feature",
  "properties": {
    "tgn:hierarchy":[
        "tgn:7042513",
        "tgn:7003164",
        "tgn:1000003",
        "tgn:7009760",
        "tgn:1000080",
        "tgn:7029392"
    ],
    "tgn:id":7042513,
    "tgn:name":"Salviano",
    "tgn:placetype":[
        "aat:300008347"
    ]
},
  "bbox": [],
  "geometry": {"coordinates":[10.35,43.533333],"type":"Point"}
}