{
  "id": 2652249,
  "type": "Feature",
  "properties": {
    "tgn:hierarchy":[
        "tgn:2652249",
        "tgn:1000001",
        "tgn:2001260",
        "tgn:7012149",
        "tgn:7007524",
        "tgn:7029392"
    ],
    "tgn:id":2652249,
    "tgn:name":"Selway Lake",
    "tgn:placetype":[
        "aat:300008680"
    ]
},
  "bbox": [],
  "geometry": {"coordinates":[-113.35,45.15],"type":"Point"}
}