{
  "id": 2106073,
  "type": "Feature",
  "properties": {
    "tgn:hierarchy":[
        "tgn:2106073",
        "tgn:1000001",
        "tgn:7012149",
        "tgn:1002595",
        "tgn:7007826",
        "tgn:7029392"
    ],
    "tgn:id":2106073,
    "tgn:name":"Milvid",
    "tgn:placetype":[
        "aat:300387016"
    ]
},
  "bbox": [],
  "geometry": {"coordinates":[-94.7833,30.45],"type":"Point"}
}