<<<<<<< HEAD
{
  "id": 7355191,
  "type": "Feature",
  "properties": {
    "tgn:hierarchy":[
        "tgn:7355191",
        "tgn:7005581",
        "tgn:1000001",
        "tgn:7005560",
        "tgn:7029392"
    ],
    "tgn:id":7355191,
    "tgn:name":"Chayote, Puerto del",
    "tgn:placetype":[
        "aat:300259572"
    ]
},
  "bbox": [],
  "geometry": {"coordinates":[-107.25,30.0],"type":"Point"}
}
=======
{"geometry":{"type":"Point","coordinates":[-107.250000,30.000000]},"type":"Feature","properties":{"hierarchy":["tgn:7355191","tgn:7005581","tgn:1000001","tgn:7005560","tgn:7029392"],"placetype":["aat:300259572"],"id":7355191,"name:xx":"Chayote, Puerto del"}}
>>>>>>> 03f74aca74312dbeaf24d7e61306dd6a786dc3d0
