{
  "id": 2095480,
  "type": "Feature",
  "properties": {
    "tgn:hierarchy":[
        "tgn:2095480",
        "tgn:2001727",
        "tgn:1000001",
        "tgn:7012149",
        "tgn:7007712",
        "tgn:7029392"
    ],
    "tgn:id":2095480,
    "tgn:name":"Cave",
    "tgn:placetype":[
        "aat:300008347",
        "aat:300387210"
    ]
},
  "bbox": [],
  "geometry": {"coordinates":[-81.3333,33.0833],"type":"Point"}
}