<<<<<<< HEAD
{
  "id": 7029525,
  "type": "Feature",
  "properties": {
    "tgn:concordances":{
        "gn:id":"2752581"
    },
    "tgn:hierarchy":[
        "tgn:7029525",
        "tgn:1000003",
        "tgn:7003627",
        "tgn:7016845",
        "tgn:7029392"
    ],
    "tgn:id":7029525,
    "tgn:name:nl":"Kockengen",
    "tgn:placetype":[
        "aat:300008347"
    ]
},
  "bbox": [],
  "geometry": {"coordinates":[4.966667,52.166667],"type":"Point"}
}
=======
{"geometry":{"type":"Point","coordinates":[4.966667,52.166667]},"type":"Feature","properties":{"hierarchy":["tgn:7029525","tgn:1000003","tgn:7003627","tgn:7016845","tgn:7029392"],"placetype":["aat:300008347"],"name:nl":"Kockengen","id":7029525}}
>>>>>>> 03f74aca74312dbeaf24d7e61306dd6a786dc3d0
