{
  "id": 2069145,
  "type": "Feature",
  "properties": {
    "tgn:hierarchy":[
        "tgn:2069145",
        "tgn:1000001",
        "tgn:7012149",
        "tgn:7014612",
        "tgn:7007568",
        "tgn:7029392"
    ],
    "tgn:id":2069145,
    "tgn:name":"Fairview",
    "tgn:placetype":[
        "aat:300008347"
    ]
},
  "bbox": [],
  "geometry": {"coordinates":[-73.7833,41.0333],"type":"Point"}
}