{
  "id": 2318676,
  "type": "Feature",
  "properties": {
    "tgn:hierarchy":[
        "tgn:2318676",
        "tgn:1000001",
        "tgn:7012149",
        "tgn:2001309",
        "tgn:7007524",
        "tgn:7029392"
    ],
    "tgn:id":2318676,
    "tgn:name":"Erosion Creek",
    "tgn:placetype":[
        "aat:300008706"
    ]
},
  "bbox": [],
  "geometry": {"coordinates":[-112.75,47.75],"type":"Point"}
}