{
  "id": 2205033,
  "type": "Feature",
  "properties": {
    "tgn:hierarchy":[
        "tgn:2205033",
        "tgn:1000001",
        "tgn:2000274",
        "tgn:7012149",
        "tgn:7007240",
        "tgn:7029392"
    ],
    "tgn:id":2205033,
    "tgn:name":"Buggs Creek",
    "tgn:placetype":[
        "aat:300008706"
    ]
},
  "bbox": [],
  "geometry": {"coordinates":[-83.85,30.4833],"type":"Point"}
}