{
  "id": 2398866,
  "type": "Feature",
  "properties": {
    "tgn:hierarchy":[
        "tgn:2398866",
        "tgn:1000001",
        "tgn:7016172",
        "tgn:7012149",
        "tgn:2000159",
        "tgn:7029392"
    ],
    "tgn:id":2398866,
    "tgn:name":"Hopewell",
    "tgn:placetype":[
        "aat:300008347"
    ]
},
  "bbox": [],
  "geometry": {"coordinates":[-93.5333,34.05],"type":"Point"}
}