{
  "id": 7303100,
  "type": "Feature",
  "properties": {
    "tgn:hierarchy":[
        "tgn:7303100",
        "tgn:7001155",
        "tgn:1000003",
        "tgn:7002790",
        "tgn:1000095",
        "tgn:7029392"
    ],
    "tgn:id":7303100,
    "tgn:name":"Ozc\u00e1riz",
    "tgn:placetype":[
        "aat:300008347"
    ]
},
  "bbox": [],
  "geometry": {"coordinates":[-1.45,42.816667],"type":"Point"}
}