<<<<<<< HEAD
{
  "id": 7050784,
  "type": "Feature",
  "properties": {
    "tgn:hierarchy":[
        "tgn:7050784",
        "tgn:7003137",
        "tgn:1000003",
        "tgn:7003080",
        "tgn:1000080",
        "tgn:7029392"
    ],
    "tgn:id":7050784,
    "tgn:name":"Nespolo",
    "tgn:placetype":[
        "aat:300008347"
    ]
},
  "bbox": [],
  "geometry": {"coordinates":[13.066667,42.15],"type":"Point"}
}
=======
{"geometry":{"type":"Point","coordinates":[13.066667,42.150000]},"type":"Feature","properties":{"hierarchy":["tgn:7050784","tgn:7003137","tgn:1000003","tgn:7003080","tgn:1000080","tgn:7029392"],"placetype":["aat:300008347"],"id":7050784,"name:xx":"Nespolo"}}
>>>>>>> 03f74aca74312dbeaf24d7e61306dd6a786dc3d0
