<<<<<<< HEAD
{
  "id": 2259529,
  "type": "Feature",
  "properties": {
    "tgn:hierarchy":[
        "tgn:2259529",
        "tgn:2000454",
        "tgn:1000001",
        "tgn:7012149",
        "tgn:7007250",
        "tgn:7029392"
    ],
    "tgn:id":2259529,
    "tgn:name":"Cottonwood Valley",
    "tgn:placetype":[
        "aat:300008761"
    ]
},
  "bbox": [],
  "geometry": {"coordinates":[-111.9167,42.4167],"type":"Point"}
}
=======
{"geometry":{"type":"Point","coordinates":[-111.916700,42.416700]},"type":"Feature","properties":{"hierarchy":["tgn:2259529","tgn:2000454","tgn:1000001","tgn:7012149","tgn:7007250","tgn:7029392"],"placetype":["aat:300008761"],"id":2259529,"name:xx":"Cottonwood Valley"}}
>>>>>>> 03f74aca74312dbeaf24d7e61306dd6a786dc3d0
