{
  "id": 2169580,
  "type": "Feature",
  "properties": {
    "tgn:hierarchy":[
        "tgn:2169580",
        "tgn:1000001",
        "tgn:7012149",
        "tgn:7007157",
        "tgn:1002957",
        "tgn:7029392"
    ],
    "tgn:id":2169580,
    "tgn:name":"Big Meadow Creek",
    "tgn:placetype":[
        "aat:300008706"
    ]
},
  "bbox": [],
  "geometry": {"coordinates":[-119.4167,38.0667],"type":"Point"}
}