{
  "id": 2550859,
  "type": "Feature",
  "properties": {
    "tgn:hierarchy":[
        "tgn:2550859",
        "tgn:1000001",
        "tgn:7012149",
        "tgn:2000637",
        "tgn:7007253",
        "tgn:7029392"
    ],
    "tgn:id":2550859,
    "tgn:name":"Norwoodville Norwood State",
    "tgn:placetype":[
        "aat:300008347"
    ]
},
  "bbox": [],
  "geometry": {"coordinates":[-93.55,41.6333],"type":"Point"}
}