{
  "id": 2367880,
  "type": "Feature",
  "properties": {
    "tgn:hierarchy":[
        "tgn:2367880",
        "tgn:1000001",
        "tgn:7006451",
        "tgn:7012149",
        "tgn:2000099",
        "tgn:7029392"
    ],
    "tgn:id":2367880,
    "tgn:name":"Grover Spring",
    "tgn:placetype":[
        "aat:300008697"
    ]
},
  "bbox": [],
  "geometry": {"coordinates":[-110.35,34.3167],"type":"Point"}
}