{
  "id": 1122182,
  "type": "Feature",
  "properties": {
    "tgn:hierarchy":[
        "tgn:1122182",
        "tgn:1000003",
        "tgn:1000070",
        "tgn:7002897",
        "tgn:7029392"
    ],
    "tgn:id":1122182,
    "tgn:name":"Br\u00e9venne",
    "tgn:placetype":[
        "aat:300008707"
    ]
},
  "bbox": [],
  "geometry": {"coordinates":[4.6667,45.85],"type":"Point"}
}