{
  "id": 7398342,
  "type": "Feature",
  "properties": {
    "tgn:hierarchy":[
        "tgn:7398342",
        "tgn:1000001",
        "tgn:1001960",
        "tgn:7005560",
        "tgn:7029392"
    ],
    "tgn:id":7398342,
    "tgn:name":"El Guacomea, Ca\u00f1\u00f3n",
    "tgn:placetype":[
        "aat:300008763"
    ]
},
  "bbox": [],
  "geometry": {"coordinates":[-111.006944,30.993333],"type":"Point"}
}