{
  "id": 2600972,
  "type": "Feature",
  "properties": {
    "tgn:hierarchy":[
        "tgn:2600972",
        "tgn:1000001",
        "tgn:7012149",
        "tgn:2000627",
        "tgn:7007253",
        "tgn:7029392"
    ],
    "tgn:id":2600972,
    "tgn:name":"Pumpkin Run",
    "tgn:placetype":[
        "aat:300008699"
    ]
},
  "bbox": [],
  "geometry": {"coordinates":[-95.85,42.1833],"type":"Point"}
}