{
  "id": 7567977,
  "type": "Feature",
  "properties": {
    "tgn:hierarchy":[
        "tgn:7567977",
        "tgn:1000004",
        "tgn:7000198",
        "tgn:7000799",
        "tgn:7029392"
    ],
    "tgn:id":7567977,
    "tgn:name:en":"B\u0101targ\u0101m",
    "tgn:placetype":[
        "aat:300008347"
    ]
},
  "bbox": [],
  "geometry": {"coordinates":[74.223979,34.529456],"type":"Point"}
}