{
  "id": 7320618,
  "type": "Feature",
  "properties": {
    "tgn:hierarchy":[
        "tgn:7320618",
        "tgn:1001699",
        "tgn:1000049",
        "tgn:1000002",
        "tgn:7029392"
    ],
    "tgn:id":7320618,
    "tgn:name":"Blanco, R\u00edo",
    "tgn:placetype":[
        "aat:300008699"
    ]
},
  "bbox": [],
  "geometry": {"coordinates":[-72.133333,-41.233333],"type":"Point"}
}