{
  "id": 2395793,
  "type": "Feature",
  "properties": {
    "tgn:hierarchy":[
        "tgn:2395793",
        "tgn:1000001",
        "tgn:7012149",
        "tgn:1002519",
        "tgn:7007706",
        "tgn:7029392"
    ],
    "tgn:id":2395793,
    "tgn:name":"Hollow Rock Run",
    "tgn:placetype":[
        "aat:300008699"
    ]
},
  "bbox": [],
  "geometry": {"coordinates":[-80.6667,40.4833],"type":"Point"}
}