{
  "id": 2230086,
  "type": "Feature",
  "properties": {
    "tgn:hierarchy":[
        "tgn:2230086",
        "tgn:1000001",
        "tgn:7012149",
        "tgn:2001850",
        "tgn:7007825",
        "tgn:7029392"
    ],
    "tgn:id":2230086,
    "tgn:name":"Celina Bar",
    "tgn:placetype":[
        "aat:300132348"
    ]
},
  "bbox": [],
  "geometry": {"coordinates":[-85.5167,36.5333],"type":"Point"}
}