{
  "id": 1030002,
  "type": "Feature",
  "properties": {
    "tgn:hierarchy":[
        "tgn:1030002",
        "tgn:7002445",
        "tgn:1000003",
        "tgn:7008131",
        "tgn:7008591",
        "tgn:7029392"
    ],
    "tgn:id":1030002,
    "tgn:name:en":"Matching",
    "tgn:placetype":[
        "aat:300008347",
        "aat:300008372"
    ]
},
  "bbox": [],
  "geometry": {"coordinates":[0.216667,51.783333],"type":"Point"}
}