{
  "id": 7560372,
  "type": "Feature",
  "properties": {
    "tgn:hierarchy":[
        "tgn:7560372",
        "tgn:1000004",
        "tgn:7000198",
        "tgn:7016788",
        "tgn:7029392"
    ],
    "tgn:id":7560372,
    "tgn:name:en":"\u0100vaniya",
    "tgn:placetype":[
        "aat:300008347"
    ]
},
  "bbox": [],
  "geometry": {"coordinates":[75.516975,26.828729],"type":"Point"}
}