{
  "id": 7250696,
  "type": "Feature",
  "properties": {
    "tgn:hierarchy":[
        "tgn:7250696",
        "tgn:7003458",
        "tgn:1000003",
        "tgn:1000063",
        "tgn:7018236",
        "tgn:7029392"
    ],
    "tgn:id":7250696,
    "tgn:name":"Nachtegaal",
    "tgn:placetype":[
        "aat:300008347"
    ]
},
  "bbox": [],
  "geometry": {"coordinates":[2.901274,50.964402],"type":"Point"}
}