{
  "id": 7301085,
  "type": "Feature",
  "properties": {
    "tgn:hierarchy":[
        "tgn:7301085",
        "tgn:7002758",
        "tgn:7002830",
        "tgn:1000003",
        "tgn:1000095",
        "tgn:7029392"
    ],
    "tgn:id":7301085,
    "tgn:name":"Montejaque",
    "tgn:placetype":[
        "aat:300008347"
    ]
},
  "bbox": [],
  "geometry": {"coordinates":[-5.266667,36.716667],"type":"Point"}
}