{
  "id": 7396818,
  "type": "Feature",
  "properties": {
    "tgn:hierarchy":[
        "tgn:7396818",
        "tgn:7005583",
        "tgn:1000001",
        "tgn:7005560",
        "tgn:7029392"
    ],
    "tgn:id":7396818,
    "tgn:name":"San Rafael, Sierra de",
    "tgn:placetype":[
        "aat:300008795"
    ]
},
  "bbox": [],
  "geometry": {"coordinates":[-104.783333,24.216667],"type":"Point"}
}