{
  "id": 2702460,
  "type": "Feature",
  "properties": {
    "tgn:hierarchy":[
        "tgn:2702460",
        "tgn:1000001",
        "tgn:7012149",
        "tgn:7007157",
        "tgn:1002857",
        "tgn:7029392"
    ],
    "tgn:id":2702460,
    "tgn:name":"Sulphide Queen Mine",
    "tgn:placetype":[
        "aat:300000390"
    ]
},
  "bbox": [],
  "geometry": {"coordinates":[-115.5167,35.4667],"type":"Point"}
}