{
  "id": 7316664,
  "type": "Feature",
  "properties": {
    "tgn:hierarchy":[
        "tgn:7316664",
        "tgn:1001705",
        "tgn:1000049",
        "tgn:1000002",
        "tgn:7029392"
    ],
    "tgn:id":7316664,
    "tgn:name":"Capellan\u00eda",
    "tgn:placetype":[
        "aat:300000206"
    ]
},
  "bbox": [],
  "geometry": {"coordinates":[-72.083333,-35.933333],"type":"Point"}
}