{
  "id": 7278676,
  "type": "Feature",
  "properties": {
    "tgn:hierarchy":[
        "tgn:7278676",
        "tgn:1001699",
        "tgn:1000049",
        "tgn:1000002",
        "tgn:7029392"
    ],
    "tgn:id":7278676,
    "tgn:name":"Arenas, Punta",
    "tgn:placetype":[
        "aat:300386846"
    ]
},
  "bbox": [],
  "geometry": {"coordinates":[-73.889167,-41.858333],"type":"Point"}
}