{
  "id": 1116844,
  "type": "Feature",
  "properties": {
    "tgn:hierarchy":[
        "tgn:1116844",
        "tgn:7006450",
        "tgn:1000001",
        "tgn:7012149",
        "tgn:2000087",
        "tgn:7029392"
    ],
    "tgn:id":1116844,
    "tgn:name":"Kgun Lake",
    "tgn:placetype":[
        "aat:300008680"
    ]
},
  "bbox": [],
  "geometry": {"coordinates":[-163.7333,61.5333],"type":"Point"}
}