{
  "id": 7500499,
  "type": "Feature",
  "properties": {
    "tgn:hierarchy":[
        "tgn:7500499",
        "tgn:7488858",
        "tgn:1000004",
        "tgn:1000141",
        "tgn:7029392"
    ],
    "tgn:id":7500499,
    "tgn:name":"Tianliao",
    "tgn:placetype":[
        "aat:300008347"
    ]
},
  "bbox": [],
  "geometry": {"coordinates":[120.776111,23.726111],"type":"Point"}
}