<<<<<<< HEAD
{
  "id": 2404013,
  "type": "Feature",
  "properties": {
    "tgn:hierarchy":[
        "tgn:2404013",
        "tgn:1000001",
        "tgn:7012149",
        "tgn:2124023",
        "tgn:7007248",
        "tgn:7029392"
    ],
    "tgn:id":2404013,
    "tgn:name":"Howell Lake",
    "tgn:placetype":[
        "aat:300008680"
    ]
},
  "bbox": [],
  "geometry": {"coordinates":[-84.15,33.8],"type":"Point"}
}
=======
{"geometry":{"type":"Point","coordinates":[-84.150000,33.800000]},"type":"Feature","properties":{"hierarchy":["tgn:2404013","tgn:1000001","tgn:7012149","tgn:2124023","tgn:7007248","tgn:7029392"],"placetype":["aat:300008680"],"id":2404013,"name:xx":"Howell Lake"}}
>>>>>>> 03f74aca74312dbeaf24d7e61306dd6a786dc3d0
