{
  "id": 2046842,
  "type": "Feature",
  "properties": {
    "tgn:hierarchy":[
        "tgn:2046842",
        "tgn:7014651",
        "tgn:1000001",
        "tgn:7012149",
        "tgn:7007516",
        "tgn:7029392"
    ],
    "tgn:id":2046842,
    "tgn:name":"Deale",
    "tgn:placetype":[
        "aat:300008347"
    ]
},
  "bbox": [],
  "geometry": {"coordinates":[-76.55,38.7667],"type":"Point"}
}