{
  "id": 7288875,
  "type": "Feature",
  "properties": {
    "tgn:hierarchy":[
        "tgn:7288875",
        "tgn:1001699",
        "tgn:1000049",
        "tgn:1000002",
        "tgn:7029392"
    ],
    "tgn:id":7288875,
    "tgn:name":"Huequi, Pen\u00ednsula",
    "tgn:placetype":[
        "aat:300008804"
    ]
},
  "bbox": [],
  "geometry": {"coordinates":[-72.65,-42.366667],"type":"Point"}
}