<<<<<<< HEAD
{
  "id": 2330637,
  "type": "Feature",
  "properties": {
    "tgn:hierarchy":[
        "tgn:2330637",
        "tgn:1000001",
        "tgn:2001414",
        "tgn:7012149",
        "tgn:7007526",
        "tgn:7029392"
    ],
    "tgn:id":2330637,
    "tgn:name":"Flat Creek Spring",
    "tgn:placetype":[
        "aat:300008697"
    ]
},
  "bbox": [],
  "geometry": {"coordinates":[-118.2,41.8833],"type":"Point"}
}
=======
{"geometry":{"type":"Point","coordinates":[-118.200000,41.883300]},"type":"Feature","properties":{"hierarchy":["tgn:2330637","tgn:1000001","tgn:2001414","tgn:7012149","tgn:7007526","tgn:7029392"],"placetype":["aat:300008697"],"id":2330637,"name:xx":"Flat Creek Spring"}}
>>>>>>> 03f74aca74312dbeaf24d7e61306dd6a786dc3d0
