{
  "id": 7333312,
  "type": "Feature",
  "properties": {
    "tgn:hierarchy":[
        "tgn:7333312",
        "tgn:7002803",
        "tgn:1001647",
        "tgn:1000003",
        "tgn:1000095",
        "tgn:7029392"
    ],
    "tgn:id":7333312,
    "tgn:name":"Fuente del Espino",
    "tgn:placetype":[
        "aat:300008347"
    ]
},
  "bbox": [],
  "geometry": {"coordinates":[-2.583333,38.566667],"type":"Point"}
}