{
  "id": 7503457,
  "type": "Feature",
  "properties": {
    "tgn:hierarchy":[
        "tgn:7503457",
        "tgn:7487020",
        "tgn:1000004",
        "tgn:1000141",
        "tgn:7029392"
    ],
    "tgn:id":7503457,
    "tgn:name":"Donghe Huguansuo",
    "tgn:placetype":[
        "aat:300387503"
    ]
},
  "bbox": [],
  "geometry": {"coordinates":[121.048889,24.583056],"type":"Point"}
}