{
  "id": 2546899,
  "type": "Feature",
  "properties": {
    "tgn:hierarchy":[
        "tgn:2546899",
        "tgn:1000001",
        "tgn:7012149",
        "tgn:7007826",
        "tgn:7029392"
    ],
    "tgn:id":2546899,
    "tgn:name":"North Fork Neils Creek",
    "tgn:placetype":[
        "aat:300008706"
    ]
},
  "bbox": [],
  "geometry": {"coordinates":[-97.9167,31.75],"type":"Point"}
}