{
  "id": 2634142,
  "type": "Feature",
  "properties": {
    "tgn:hierarchy":[
        "tgn:2634142",
        "tgn:1000001",
        "tgn:7012149",
        "tgn:2001706",
        "tgn:7007708",
        "tgn:7029392"
    ],
    "tgn:id":2634142,
    "tgn:name":"Russell Creek",
    "tgn:placetype":[
        "aat:300008706"
    ]
},
  "bbox": [],
  "geometry": {"coordinates":[-123.3667,42.85],"type":"Point"}
}