<<<<<<< HEAD
{
  "id": 7374152,
  "type": "Feature",
  "properties": {
    "tgn:hierarchy":[
        "tgn:7374152",
        "tgn:1000001",
        "tgn:7005599",
        "tgn:7005560",
        "tgn:7029392"
    ],
    "tgn:id":7374152,
    "tgn:name":"La Angostura",
    "tgn:placetype":[
        "aat:300000241"
    ]
},
  "bbox": [],
  "geometry": {"coordinates":[-96.35,18.65],"type":"Point"}
}
=======
{"geometry":{"type":"Point","coordinates":[-96.350000,18.650000]},"type":"Feature","properties":{"hierarchy":["tgn:7374152","tgn:1000001","tgn:7005599","tgn:7005560","tgn:7029392"],"placetype":["aat:300000241"],"id":7374152,"name:xx":"La Angostura"}}
>>>>>>> 03f74aca74312dbeaf24d7e61306dd6a786dc3d0
