{
  "id": 7374152,
  "type": "Feature",
  "properties": {
    "tgn:hierarchy":[
        "tgn:7374152",
        "tgn:1000001",
        "tgn:7005599",
        "tgn:7005560",
        "tgn:7029392"
    ],
    "tgn:id":7374152,
    "tgn:name":"La Angostura",
    "tgn:placetype":[
        "aat:300000241"
    ]
},
  "bbox": [],
  "geometry": {"coordinates":[-96.35,18.65],"type":"Point"}
}