{
  "id": 2022268,
  "type": "Feature",
  "properties": {
    "tgn:hierarchy":[
        "tgn:2022268",
        "tgn:1000001",
        "tgn:2000322",
        "tgn:7012149",
        "tgn:7007248",
        "tgn:7029392"
    ],
    "tgn:id":2022268,
    "tgn:name":"Brooks",
    "tgn:placetype":[
        "aat:300008347"
    ]
},
  "bbox": [],
  "geometry": {"coordinates":[-84.45,33.2833],"type":"Point"}
}