<<<<<<< HEAD
{
  "id": 7365188,
  "type": "Feature",
  "properties": {
    "tgn:hierarchy":[
        "tgn:7365188",
        "tgn:7005581",
        "tgn:1000001",
        "tgn:7005560",
        "tgn:7029392"
    ],
    "tgn:id":7365188,
    "tgn:name":"Francisco I. Madero",
    "tgn:placetype":[
        "aat:300006495"
    ]
},
  "bbox": [],
  "geometry": {"coordinates":[-104.866667,27.183333],"type":"Point"}
}
=======
{"geometry":{"type":"Point","coordinates":[-104.866667,27.183333]},"type":"Feature","properties":{"hierarchy":["tgn:7365188","tgn:7005581","tgn:1000001","tgn:7005560","tgn:7029392"],"placetype":["aat:300006495"],"id":7365188,"name:xx":"Francisco I. Madero"}}
>>>>>>> 03f74aca74312dbeaf24d7e61306dd6a786dc3d0
