{
  "id": 2570138,
  "type": "Feature",
  "properties": {
    "tgn:hierarchy":[
        "tgn:2570138",
        "tgn:1000001",
        "tgn:7012149",
        "tgn:7007919",
        "tgn:7029392"
    ],
    "tgn:id":2570138,
    "tgn:name":"Passage Creek",
    "tgn:placetype":[
        "aat:300008706"
    ]
},
  "bbox": [],
  "geometry": {"coordinates":[-78.5833,38.65],"type":"Point"}
}