{
  "id": 2720427,
  "type": "Feature",
  "properties": {
    "tgn:hierarchy":[
        "tgn:2720427",
        "tgn:1000001",
        "tgn:7012149",
        "tgn:2000933",
        "tgn:7007515",
        "tgn:7029392"
    ],
    "tgn:id":2720427,
    "tgn:name":"Thunder Island",
    "tgn:placetype":[
        "aat:300008850"
    ]
},
  "bbox": [],
  "geometry": {"coordinates":[-70.4167,43.4833],"type":"Point"}
}