{
  "id": 7504683,
  "type": "Feature",
  "properties": {
    "tgn:hierarchy":[
        "tgn:7504683",
        "tgn:7000508",
        "tgn:1008380",
        "tgn:1000226",
        "tgn:1000006",
        "tgn:7029392"
    ],
    "tgn:id":7504683,
    "tgn:name:en":"Narrow Neck Beach",
    "tgn:placetype":[
        "aat:300008816"
    ]
},
  "bbox": [],
  "geometry": {"coordinates":[174.802222,-36.812222],"type":"Point"}
}