<<<<<<< HEAD
{
  "id": 7246165,
  "type": "Feature",
  "properties": {
    "tgn:hierarchy":[
        "tgn:7246165",
        "tgn:7003465",
        "tgn:1000003",
        "tgn:1000063",
        "tgn:4012014",
        "tgn:7029392"
    ],
    "tgn:id":7246165,
    "tgn:name":"Devant la Fange",
    "tgn:placetype":[
        "aat:300008863"
    ]
},
  "bbox": [],
  "geometry": {"coordinates":[5.1,50.05],"type":"Point"}
}
=======
{"geometry":{"type":"Point","coordinates":[5.100000,50.050000]},"type":"Feature","properties":{"hierarchy":["tgn:7246165","tgn:7003465","tgn:1000003","tgn:1000063","tgn:4012014","tgn:7029392"],"placetype":["aat:300008863"],"id":7246165,"name:xx":"Devant la Fange"}}
>>>>>>> 03f74aca74312dbeaf24d7e61306dd6a786dc3d0
