{
  "id": 2510189,
  "type": "Feature",
  "properties": {
    "tgn:hierarchy":[
        "tgn:2510189",
        "tgn:1000001",
        "tgn:7012149",
        "tgn:2000214",
        "tgn:7007158",
        "tgn:7029392"
    ],
    "tgn:id":2510189,
    "tgn:name":"Middle Ranch Canyon",
    "tgn:placetype":[
        "aat:300008761"
    ]
},
  "bbox": [],
  "geometry": {"coordinates":[-108.6167,39.5167],"type":"Point"}
}