{
  "id": 7187289,
  "type": "Feature",
  "properties": {
    "tgn:hierarchy":[
        "tgn:7187289",
        "tgn:7003669",
        "tgn:1000003",
        "tgn:7000084",
        "tgn:7029392"
    ],
    "tgn:id":7187289,
    "tgn:name":"Ellenbach",
    "tgn:placetype":[
        "aat:300008347"
    ]
},
  "bbox": [],
  "geometry": {"coordinates":[11.383333,48.55],"type":"Point"}
}