{
  "id": 7344519,
  "type": "Feature",
  "properties": {
    "tgn:hierarchy":[
        "tgn:7344519",
        "tgn:7002803",
        "tgn:1001647",
        "tgn:1000003",
        "tgn:1000095",
        "tgn:7029392"
    ],
    "tgn:id":7344519,
    "tgn:name":"Antonete, Llanos de",
    "tgn:placetype":[
        "aat:300008805"
    ]
},
  "bbox": [],
  "geometry": {"coordinates":[-1.983333,39.266667],"type":"Point"}
}