{
  "id": 2720239,
  "type": "Feature",
  "properties": {
    "tgn:hierarchy":[
        "tgn:2720239",
        "tgn:1000001",
        "tgn:7012149",
        "tgn:2001969",
        "tgn:7007826",
        "tgn:7029392"
    ],
    "tgn:id":2720239,
    "tgn:name":"Threemile Tank",
    "tgn:placetype":[
        "aat:300006191"
    ]
},
  "bbox": [],
  "geometry": {"coordinates":[-104.55,31.1833],"type":"Point"}
}