{
  "id": 2505076,
  "type": "Feature",
  "properties": {
    "tgn:hierarchy":[
        "tgn:2505076",
        "tgn:1000001",
        "tgn:7012149",
        "tgn:2000383",
        "tgn:7007248",
        "tgn:7029392"
    ],
    "tgn:id":2505076,
    "tgn:name":"Meetinghouse Branch",
    "tgn:placetype":[
        "aat:300008699"
    ]
},
  "bbox": [],
  "geometry": {"coordinates":[-83.4167,31.0167],"type":"Point"}
}