{
  "id": 7533860,
  "type": "Feature",
  "properties": {
    "tgn:hierarchy":[
        "tgn:7533860",
        "tgn:7001242",
        "tgn:7016833",
        "tgn:1001418",
        "tgn:7029392"
    ],
    "tgn:id":7533860,
    "tgn:name:en":"\u1e28amrah, Sa\u0163\u1e29 al",
    "tgn:placetype":[
        "aat:300008777"
    ]
},
  "bbox": [],
  "geometry": {"coordinates":[27.481511,28.697366],"type":"Point"}
}