{
  "id": 1036127,
  "type": "Feature",
  "properties": {
    "tgn:hierarchy":[
        "tgn:1036127",
        "tgn:1000003",
        "tgn:1000070",
        "tgn:7002895",
        "tgn:7029392"
    ],
    "tgn:id":1036127,
    "tgn:name":"Villars-Colmars",
    "tgn:placetype":[
        "aat:300008347"
    ]
},
  "bbox": [],
  "geometry": {"coordinates":[6.6167,44.1667],"type":"Point"}
}