<<<<<<< HEAD
{
  "id": 7244541,
  "type": "Feature",
  "properties": {
    "tgn:hierarchy":[
        "tgn:7244541",
        "tgn:7003457",
        "tgn:1000003",
        "tgn:1000063",
        "tgn:7018236",
        "tgn:7029392"
    ],
    "tgn:id":7244541,
    "tgn:name":"Kruisweg",
    "tgn:placetype":[
        "aat:300008347"
    ]
},
  "bbox": [],
  "geometry": {"coordinates":[3.504358,51.01538],"type":"Point"}
}
=======
{"geometry":{"type":"Point","coordinates":[3.504358,51.015380]},"type":"Feature","properties":{"hierarchy":["tgn:7244541","tgn:7003457","tgn:1000003","tgn:1000063","tgn:7018236","tgn:7029392"],"placetype":["aat:300008347"],"id":7244541,"name:xx":"Kruisweg"}}
>>>>>>> 03f74aca74312dbeaf24d7e61306dd6a786dc3d0
