{
  "id": 7206960,
  "type": "Feature",
  "properties": {
    "tgn:hierarchy":[
        "tgn:7206960",
        "tgn:1000003",
        "tgn:7003677",
        "tgn:7000084",
        "tgn:7029392"
    ],
    "tgn:id":7206960,
    "tgn:name":"F\u00f6rsterei Buchholz",
    "tgn:placetype":[
        "aat:300004792"
    ]
},
  "bbox": [],
  "geometry": {"coordinates":[8.816667,51.483333],"type":"Point"}
}