{
  "id": 7438736,
  "type": "Feature",
  "properties": {
    "tgn:hierarchy":[
        "tgn:7438736",
        "tgn:1000001",
        "tgn:1001906",
        "tgn:7005560",
        "tgn:7029392"
    ],
    "tgn:id":7438736,
    "tgn:name":"Sauces",
    "tgn:placetype":[
        "aat:300008347"
    ]
},
  "bbox": [],
  "geometry": {"coordinates":[-105.116667,20.916667],"type":"Point"}
}