{
  "id": 7278856,
  "type": "Feature",
  "properties": {
    "tgn:hierarchy":[
        "tgn:7278856",
        "tgn:1001695",
        "tgn:1000049",
        "tgn:1000002",
        "tgn:7029392"
    ],
    "tgn:id":7278856,
    "tgn:name":"San Luis",
    "tgn:placetype":[
        "aat:300004792"
    ]
},
  "bbox": [],
  "geometry": {"coordinates":[-71.266667,-34.733333],"type":"Point"}
}