{
  "id": 2712849,
  "type": "Feature",
  "properties": {
    "tgn:hierarchy":[
        "tgn:2712849",
        "tgn:1000001",
        "tgn:2001802",
        "tgn:7012149",
        "tgn:7007713",
        "tgn:7029392"
    ],
    "tgn:id":2712849,
    "tgn:name":"Taylor Draw",
    "tgn:placetype":[
        "aat:300008761"
    ]
},
  "bbox": [],
  "geometry": {"coordinates":[-100.1667,44.3333],"type":"Point"}
}