{
  "id": 2756460,
  "type": "Feature",
  "properties": {
    "tgn:hierarchy":[
        "tgn:2756460",
        "tgn:1000001",
        "tgn:7014423",
        "tgn:7012149",
        "tgn:7007517",
        "tgn:7029392"
    ],
    "tgn:id":2756460,
    "tgn:name":"Well Rock",
    "tgn:placetype":[
        "aat:300011692"
    ]
},
  "bbox": [],
  "geometry": {"coordinates":[-70.75,42.2333],"type":"Point"}
}