{
  "id": 7033429,
  "type": "Feature",
  "properties": {
    "tgn:hierarchy":[
        "tgn:7033429",
        "tgn:7002996",
        "tgn:1000003",
        "tgn:7002997",
        "tgn:1000080",
        "tgn:7029392"
    ],
    "tgn:id":7033429,
    "tgn:name":"Meduna di Livenza",
    "tgn:placetype":[
        "aat:300008347"
    ]
},
  "bbox": [],
  "geometry": {"coordinates":[12.611944,45.806667],"type":"Point"}
}