{
  "id": 7232832,
  "type": "Feature",
  "properties": {
    "tgn:hierarchy":[
        "tgn:7232832",
        "tgn:7002725",
        "tgn:7002715",
        "tgn:1000003",
        "tgn:1000074",
        "tgn:7029392"
    ],
    "tgn:id":7232832,
    "tgn:name":"K\u00e1to Theodor\u00e1kion",
    "tgn:placetype":[
        "aat:300008347"
    ]
},
  "bbox": [],
  "geometry": {"coordinates":[23.004167,41.141111],"type":"Point"}
}