{
  "id": 2355029,
  "type": "Feature",
  "properties": {
    "tgn:hierarchy":[
        "tgn:2355029",
        "tgn:1000001",
        "tgn:7012149",
        "tgn:2001905",
        "tgn:7007825",
        "tgn:7029392"
    ],
    "tgn:id":2355029,
    "tgn:name":"Goodman Ridge",
    "tgn:placetype":[
        "aat:300266640"
    ]
},
  "bbox": [],
  "geometry": {"coordinates":[-84.9667,36.5833],"type":"Point"}
}