{
  "id": 2165440,
  "type": "Feature",
  "properties": {
    "tgn:hierarchy":[
        "tgn:2165440",
        "tgn:1000001",
        "tgn:7012149",
        "tgn:2000488",
        "tgn:7007250",
        "tgn:7029392"
    ],
    "tgn:id":2165440,
    "tgn:name":"Between The Fields Spring",
    "tgn:placetype":[
        "aat:300008697"
    ]
},
  "bbox": [],
  "geometry": {"coordinates":[-116.9667,42.5167],"type":"Point"}
}