{
  "id": 2662898,
  "type": "Feature",
  "properties": {
    "tgn:hierarchy":[
        "tgn:2662898",
        "tgn:1000001",
        "tgn:2001430",
        "tgn:7012149",
        "tgn:7007566",
        "tgn:7029392"
    ],
    "tgn:id":2662898,
    "tgn:name":"Silman Lake",
    "tgn:placetype":[
        "aat:300008680"
    ]
},
  "bbox": [],
  "geometry": {"coordinates":[-104.0667,33.4667],"type":"Point"}
}