{
  "id": 2573200,
  "type": "Feature",
  "properties": {
    "tgn:hierarchy":[
        "tgn:2573200",
        "tgn:1000001",
        "tgn:7012149",
        "tgn:2000216",
        "tgn:7007158",
        "tgn:7029392"
    ],
    "tgn:id":2573200,
    "tgn:name":"Pease Gulch",
    "tgn:placetype":[
        "aat:300008761"
    ]
},
  "bbox": [],
  "geometry": {"coordinates":[-106.1167,39.8667],"type":"Point"}
}