{
  "id": 7571923,
  "type": "Feature",
  "properties": {
    "tgn:hierarchy":[
        "tgn:7571923",
        "tgn:1000004",
        "tgn:1001832",
        "tgn:7000198",
        "tgn:7029392"
    ],
    "tgn:id":7571923,
    "tgn:name:en":"Gokulk\u0101ta",
    "tgn:placetype":[
        "aat:300008347"
    ]
},
  "bbox": [],
  "geometry": {"coordinates":[89.877739,26.477436],"type":"Point"}
}