{
  "id": 2443640,
  "type": "Feature",
  "properties": {
    "tgn:hierarchy":[
        "tgn:2443640",
        "tgn:7006450",
        "tgn:1000001",
        "tgn:7030517",
        "tgn:7012149",
        "tgn:7029392"
    ],
    "tgn:id":2443640,
    "tgn:name":"La Gorce, Mount",
    "tgn:placetype":[
        "aat:300008798"
    ]
},
  "bbox": [],
  "geometry": {"coordinates":[-155.4833,58.55],"type":"Point"}
}