{
  "id": 2716894,
  "type": "Feature",
  "properties": {
    "tgn:hierarchy":[
        "tgn:2716894",
        "tgn:1000001",
        "tgn:2001262",
        "tgn:7012149",
        "tgn:7007524",
        "tgn:7029392"
    ],
    "tgn:id":2716894,
    "tgn:name":"Thibadeau Coulee",
    "tgn:placetype":[
        "aat:300008761"
    ]
},
  "bbox": [],
  "geometry": {"coordinates":[-109.35,48.6667],"type":"Point"}
}