{
  "id": 2739691,
  "type": "Feature",
  "properties": {
    "tgn:hierarchy":[
        "tgn:2739691",
        "tgn:1000001",
        "tgn:7012149",
        "tgn:2001544",
        "tgn:7007709",
        "tgn:7029392"
    ],
    "tgn:id":2739691,
    "tgn:name":"Upper Creek",
    "tgn:placetype":[
        "aat:300008706"
    ]
},
  "bbox": [],
  "geometry": {"coordinates":[-82.7333,35.15],"type":"Point"}
}