<<<<<<< HEAD
{
  "id": 7377343,
  "type": "Feature",
  "properties": {
    "tgn:hierarchy":[
        "tgn:7377343",
        "tgn:1000001",
        "tgn:7005599",
        "tgn:7005560",
        "tgn:7029392"
    ],
    "tgn:id":7377343,
    "tgn:name":"Las Bajadas",
    "tgn:placetype":[
        "aat:300008347"
    ]
},
  "bbox": [],
  "geometry": {"coordinates":[-96.166667,19.166667],"type":"Point"}
}
=======
{"geometry":{"type":"Point","coordinates":[-96.166667,19.166667]},"type":"Feature","properties":{"hierarchy":["tgn:7377343","tgn:1000001","tgn:7005599","tgn:7005560","tgn:7029392"],"placetype":["aat:300008347"],"id":7377343,"name:xx":"Las Bajadas"}}
>>>>>>> 03f74aca74312dbeaf24d7e61306dd6a786dc3d0
