{
  "id": 7590824,
  "type": "Feature",
  "properties": {
    "tgn:hierarchy":[
        "tgn:7590824",
        "tgn:1000004",
        "tgn:7000198",
        "tgn:7000799",
        "tgn:7029392"
    ],
    "tgn:id":7590824,
    "tgn:name:en":"Chak M\u0101jra",
    "tgn:placetype":[
        "aat:300008347"
    ]
},
  "bbox": [],
  "geometry": {"coordinates":[74.839083,32.542966],"type":"Point"}
}