{
  "id": 2000238,
  "type": "Feature",
  "properties": {
    "tgn:hierarchy":[
        "tgn:2000238",
        "tgn:1000001",
        "tgn:7012149",
        "tgn:7007158",
        "tgn:7029392"
    ],
    "tgn:id":2000238,
    "tgn:name":"Park",
    "tgn:placetype":[
        "aat:300387145",
        "aat:300000771"
    ]
},
  "bbox": [],
  "geometry": {"coordinates":[-105.7667,39.15],"type":"Point"}
}