{
  "id": 2423151,
  "type": "Feature",
  "properties": {
    "tgn:hierarchy":[
        "tgn:2423151",
        "tgn:1000001",
        "tgn:7012149",
        "tgn:7007256",
        "tgn:7029392"
    ],
    "tgn:id":2423151,
    "tgn:name":"Joes Bayou",
    "tgn:placetype":[
        "aat:300008699"
    ]
},
  "bbox": [],
  "geometry": {"coordinates":[-91.2667,32.7167],"type":"Point"}
}