{
  "id": 2109361,
  "type": "Feature",
  "properties": {
    "tgn:hierarchy":[
        "tgn:2109361",
        "tgn:1000001",
        "tgn:7012149",
        "tgn:2002126",
        "tgn:7007827",
        "tgn:7029392"
    ],
    "tgn:id":2109361,
    "tgn:name":"Wallsburg",
    "tgn:placetype":[
        "aat:300008347"
    ]
},
  "bbox": [],
  "geometry": {"coordinates":[-111.4167,40.3833],"type":"Point"}
}