{
  "id": 7469972,
  "type": "Feature",
  "properties": {
    "tgn:hierarchy":[
        "tgn:7469972",
        "tgn:1000957",
        "tgn:1000004",
        "tgn:1000141",
        "tgn:7029392"
    ],
    "tgn:id":7469972,
    "tgn:name":"Jilong Yu",
    "tgn:placetype":[
        "aat:300008791"
    ]
},
  "bbox": [],
  "geometry": {"coordinates":[121.786934,25.193404],"type":"Point"}
}