{
  "id": 2251451,
  "type": "Feature",
  "properties": {
    "tgn:hierarchy":[
        "tgn:2251451",
        "tgn:7006450",
        "tgn:1000001",
        "tgn:7012149",
        "tgn:2000089",
        "tgn:7029392"
    ],
    "tgn:id":2251451,
    "tgn:name":"Coming Portage Lake",
    "tgn:placetype":[
        "aat:300008680"
    ]
},
  "bbox": [],
  "geometry": {"coordinates":[-145.3167,68.1333],"type":"Point"}
}