{
  "id": 1079477,
  "type": "Feature",
  "properties": {
    "tgn:hierarchy":[
        "tgn:1079477",
        "tgn:7000249",
        "tgn:1000004",
        "tgn:1000119",
        "tgn:7029392"
    ],
    "tgn:id":1079477,
    "tgn:name":"Ashmura",
    "tgn:placetype":[
        "aat:300008347"
    ]
},
  "bbox": [],
  "geometry": {"coordinates":[35.65,33.05],"type":"Point"}
}