{
  "id": 2609302,
  "type": "Feature",
  "properties": {
    "tgn:hierarchy":[
        "tgn:2609302",
        "tgn:1000001",
        "tgn:7012149",
        "tgn:2000930",
        "tgn:7007515",
        "tgn:7029392"
    ],
    "tgn:id":2609302,
    "tgn:name":"Ray Brook",
    "tgn:placetype":[
        "aat:300008699"
    ]
},
  "bbox": [],
  "geometry": {"coordinates":[-69.4333,44.9333],"type":"Point"}
}