{
  "id": 2720185,
  "type": "Feature",
  "properties": {
    "tgn:hierarchy":[
        "tgn:2720185",
        "tgn:1000001",
        "tgn:7012149",
        "tgn:1002967",
        "tgn:7007520",
        "tgn:7029392"
    ],
    "tgn:id":2720185,
    "tgn:name":"Threemile Lake",
    "tgn:placetype":[
        "aat:300008680"
    ]
},
  "bbox": [],
  "geometry": {"coordinates":[-85.95,42.1833],"type":"Point"}
}