{
  "id": 7536460,
  "type": "Feature",
  "properties": {
    "tgn:hierarchy":[
        "tgn:7536460",
        "tgn:7001242",
        "tgn:7016833",
        "tgn:7001312",
        "tgn:7029392"
    ],
    "tgn:id":7536460,
    "tgn:name:en":"Kafr ash Sh\u016brbaj\u012b",
    "tgn:placetype":[
        "aat:300008347"
    ]
},
  "bbox": [],
  "geometry": {"coordinates":[30.899397,30.80715],"type":"Point"}
}