{
  "id": 7282711,
  "type": "Feature",
  "properties": {
    "tgn:hierarchy":[
        "tgn:7282711",
        "tgn:7002464",
        "tgn:1000049",
        "tgn:1000002",
        "tgn:7029392"
    ],
    "tgn:id":7282711,
    "tgn:name":"P\u00e9njamo",
    "tgn:placetype":[
        "aat:300004792"
    ]
},
  "bbox": [],
  "geometry": {"coordinates":[-68.833333,-19.85],"type":"Point"}
}