{
  "id": 7588442,
  "type": "Feature",
  "properties": {
    "tgn:hierarchy":[
        "tgn:7588442",
        "tgn:1000004",
        "tgn:7000198",
        "tgn:1001977",
        "tgn:7029392"
    ],
    "tgn:id":7588442,
    "tgn:name:en":"Bebangheri",
    "tgn:placetype":[
        "aat:300008347"
    ]
},
  "bbox": [],
  "geometry": {"coordinates":[88.780495,22.453257],"type":"Point"}
}