{
  "id": 7438506,
  "type": "Feature",
  "properties": {
    "tgn:hierarchy":[
        "tgn:7438506",
        "tgn:1000001",
        "tgn:1001960",
        "tgn:7005560",
        "tgn:7029392"
    ],
    "tgn:id":7438506,
    "tgn:name":"Tacuachi",
    "tgn:placetype":[
        "aat:300008347"
    ]
},
  "bbox": [],
  "geometry": {"coordinates":[-108.824167,26.846944],"type":"Point"}
}