{
  "id": 2723443,
  "type": "Feature",
  "properties": {
    "tgn:hierarchy":[
        "tgn:2723443",
        "tgn:1000001",
        "tgn:1002272",
        "tgn:7012149",
        "tgn:7007710",
        "tgn:7029392"
    ],
    "tgn:id":2723443,
    "tgn:name":"Toby Creek",
    "tgn:placetype":[
        "aat:300008706"
    ]
},
  "bbox": [],
  "geometry": {"coordinates":[-79.2667,41.3833],"type":"Point"}
}