<<<<<<< HEAD
{
  "id": 2151873,
  "type": "Feature",
  "properties": {
    "tgn:hierarchy":[
        "tgn:2151873",
        "tgn:1000001",
        "tgn:7012149",
        "tgn:2000230",
        "tgn:7007158",
        "tgn:7029392"
    ],
    "tgn:id":2151873,
    "tgn:name":"Battleship Rock",
    "tgn:placetype":[
        "aat:300008798"
    ]
},
  "bbox": [],
  "geometry": {"coordinates":[-108.85,39.0333],"type":"Point"}
}
=======
{"geometry":{"type":"Point","coordinates":[-108.850000,39.033300]},"type":"Feature","properties":{"hierarchy":["tgn:2151873","tgn:1000001","tgn:7012149","tgn:2000230","tgn:7007158","tgn:7029392"],"placetype":["aat:300008798"],"id":2151873,"name:xx":"Battleship Rock"}}
>>>>>>> 03f74aca74312dbeaf24d7e61306dd6a786dc3d0
