{
  "id": 7342873,
  "type": "Feature",
  "properties": {
    "tgn:hierarchy":[
        "tgn:7342873",
        "tgn:7002811",
        "tgn:1000003",
        "tgn:7003837",
        "tgn:1000095",
        "tgn:7029392"
    ],
    "tgn:id":7342873,
    "tgn:name":"Ca\u00f1amero",
    "tgn:placetype":[
        "aat:300008347"
    ]
},
  "bbox": [],
  "geometry": {"coordinates":[-5.383333,39.383333],"type":"Point"}
}