{
  "id": 2027486,
  "type": "Feature",
  "properties": {
    "tgn:hierarchy":[
        "tgn:2027486",
        "tgn:1000001",
        "tgn:7012149",
        "tgn:1002430",
        "tgn:7007251",
        "tgn:7029392"
    ],
    "tgn:id":2027486,
    "tgn:name":"Diamond",
    "tgn:placetype":[
        "aat:300008347"
    ]
},
  "bbox": [],
  "geometry": {"coordinates":[-88.25,41.2833],"type":"Point"}
}