{
  "id": 7135841,
  "type": "Feature",
  "properties": {
    "tgn:hierarchy":[
        "tgn:7135841",
        "tgn:1000003",
        "tgn:7003676",
        "tgn:7000084",
        "tgn:7029392"
    ],
    "tgn:id":7135841,
    "tgn:name":"Nackenberg",
    "tgn:placetype":[
        "aat:300008347"
    ]
},
  "bbox": [],
  "geometry": {"coordinates":[9.816667,52.383333],"type":"Point"}
}