{
  "id": 7088759,
  "type": "Feature",
  "properties": {
    "tgn:hierarchy":[
        "tgn:7088759",
        "tgn:1000003",
        "tgn:7003676",
        "tgn:7000084",
        "tgn:7029392"
    ],
    "tgn:id":7088759,
    "tgn:name":"Walmstorf",
    "tgn:placetype":[
        "aat:300008347"
    ]
},
  "bbox": [],
  "geometry": {"coordinates":[10.583333,53.033333],"type":"Point"}
}