{
  "id": 7286488,
  "type": "Feature",
  "properties": {
    "tgn:hierarchy":[
        "tgn:7286488",
        "tgn:1001702",
        "tgn:1000049",
        "tgn:1000002",
        "tgn:7029392"
    ],
    "tgn:id":7286488,
    "tgn:name":"H\u00e9ctor, Isla",
    "tgn:placetype":[
        "aat:300008791"
    ]
},
  "bbox": [],
  "geometry": {"coordinates":[-75.466667,-48.783333],"type":"Point"}
}