{
  "id": 7391341,
  "type": "Feature",
  "properties": {
    "tgn:hierarchy":[
        "tgn:7391341",
        "tgn:1000001",
        "tgn:1001960",
        "tgn:7005560",
        "tgn:7029392"
    ],
    "tgn:id":7391341,
    "tgn:name":"Rancho El Alamo",
    "tgn:placetype":[
        "aat:300008347"
    ]
},
  "bbox": [],
  "geometry": {"coordinates":[-112.533333,30.75],"type":"Point"}
}