{
  "id": 2183043,
  "type": "Feature",
  "properties": {
    "tgn:hierarchy":[
        "tgn:2183043",
        "tgn:1000001",
        "tgn:7012149",
        "tgn:7007157",
        "tgn:1002748",
        "tgn:7029392"
    ],
    "tgn:id":2183043,
    "tgn:name":"Bluebird Canyon",
    "tgn:placetype":[
        "aat:300008761"
    ]
},
  "bbox": [],
  "geometry": {"coordinates":[-117.75,33.5167],"type":"Point"}
}