{
  "id": 2377775,
  "type": "Feature",
  "properties": {
    "tgn:hierarchy":[
        "tgn:2377775",
        "tgn:1000001",
        "tgn:2002318",
        "tgn:7012149",
        "tgn:7007922",
        "tgn:7029392"
    ],
    "tgn:id":2377775,
    "tgn:name":"Harriet Lake",
    "tgn:placetype":[
        "aat:300008680"
    ]
},
  "bbox": [],
  "geometry": {"coordinates":[-91.7833,46.2167],"type":"Point"}
}