{
  "id": 7479194,
  "type": "Feature",
  "properties": {
    "tgn:hierarchy":[
        "tgn:7479194",
        "tgn:1000004",
        "tgn:7490934",
        "tgn:1000141",
        "tgn:7029392"
    ],
    "tgn:id":7479194,
    "tgn:name":"Hainan Qiao",
    "tgn:placetype":[
        "aat:300007836"
    ]
},
  "bbox": [],
  "geometry": {"coordinates":[120.188056,23.038889],"type":"Point"}
}