{
  "id": 1041066,
  "type": "Feature",
  "properties": {
    "tgn:hierarchy":[
        "tgn:1041066",
        "tgn:1000003",
        "tgn:7003688",
        "tgn:7000084",
        "tgn:7029392"
    ],
    "tgn:id":1041066,
    "tgn:name":"Sch\u00f6nwalde",
    "tgn:placetype":[
        "aat:300008347"
    ]
},
  "bbox": [],
  "geometry": {"coordinates":[10.75,54.183333],"type":"Point"}
}