{
  "id": 7542084,
  "type": "Feature",
  "properties": {
    "tgn:hierarchy":[
        "tgn:7542084",
        "tgn:7001242",
        "tgn:7016833",
        "tgn:7029392"
    ],
    "tgn:id":7542084,
    "tgn:name":"El-Haf\u00eera",
    "tgn:placetype":[
        "aat:300055621"
    ]
},
  "bbox": [],
  "geometry": {"coordinates":[33.406939,28.957998],"type":"Point"}
}