{
  "id": 2161536,
  "type": "Feature",
  "properties": {
    "tgn:hierarchy":[
        "tgn:2161536",
        "tgn:1000001",
        "tgn:7012149",
        "tgn:1002314",
        "tgn:7007240",
        "tgn:7029392"
    ],
    "tgn:id":2161536,
    "tgn:name":"Bella Vista Bay",
    "tgn:placetype":[
        "aat:300132316"
    ]
},
  "bbox": [],
  "geometry": {"coordinates":[-80.1167,25.9167],"type":"Point"}
}