{
  "id": 1061891,
  "type": "Feature",
  "properties": {
    "tgn:hierarchy":[
        "tgn:1061891",
        "tgn:7002844",
        "tgn:7030216",
        "tgn:1000003",
        "tgn:1000095",
        "tgn:7029392"
    ],
    "tgn:id":1061891,
    "tgn:name":"Cambrils",
    "tgn:placetype":[
        "aat:300008347"
    ]
},
  "bbox": [],
  "geometry": {"coordinates":[1.05,41.066667],"type":"Point"}
}