{
  "id": 7122196,
  "type": "Feature",
  "properties": {
    "tgn:hierarchy":[
        "tgn:7122196",
        "tgn:1000003",
        "tgn:7003688",
        "tgn:7000084",
        "tgn:7029392"
    ],
    "tgn:id":7122196,
    "tgn:name":"Neuenkoog",
    "tgn:placetype":[
        "aat:300000206"
    ]
},
  "bbox": [],
  "geometry": {"coordinates":[8.833333,54.15],"type":"Point"}
}