{
  "id": 2693653,
  "type": "Feature",
  "properties": {
    "tgn:hierarchy":[
        "tgn:2693653",
        "tgn:1000001",
        "tgn:7012149",
        "tgn:2001226",
        "tgn:7007523",
        "tgn:7029392"
    ],
    "tgn:id":2693653,
    "tgn:name":"Stephens Hollow",
    "tgn:placetype":[
        "aat:300008761"
    ]
},
  "bbox": [],
  "geometry": {"coordinates":[-92.2833,36.7833],"type":"Point"}
}