{
  "id": 7027019,
  "type": "Feature",
  "properties": {
    "tgn:hierarchy":[
        "tgn:7027019",
        "tgn:7002445",
        "tgn:1000003",
        "tgn:7008143",
        "tgn:7008591",
        "tgn:7029392"
    ],
    "tgn:id":7027019,
    "tgn:name:en":"Canon Frome",
    "tgn:placetype":[
        "aat:300008347",
        "aat:300008372"
    ]
},
  "bbox": [],
  "geometry": {"coordinates":[-2.516667,52.083333],"type":"Point"}
}