{
  "id": 1124046,
  "type": "Feature",
  "properties": {
    "tgn:hierarchy":[
        "tgn:1124046",
        "tgn:1001945",
        "tgn:1000047",
        "tgn:7002457",
        "tgn:1000002",
        "tgn:7029392"
    ],
    "tgn:id":1124046,
    "tgn:name":"Funil, Rio do",
    "tgn:placetype":[
        "aat:300008707"
    ]
},
  "bbox": [],
  "geometry": {"coordinates":[-44.5667,-22.9667],"type":"Point"}
}