{
  "id": 1098325,
  "type": "Feature",
  "properties": {
    "tgn:hierarchy":[
        "tgn:1098325",
        "tgn:7000490",
        "tgn:1000006",
        "tgn:7001834",
        "tgn:7029392"
    ],
    "tgn:id":1098325,
    "tgn:name":"Three Springs",
    "tgn:placetype":[
        "aat:300008347"
    ]
},
  "bbox": [],
  "geometry": {"coordinates":[119.15,-25.1167],"type":"Point"}
}