<<<<<<< HEAD
{
  "id": 7378988,
  "type": "Feature",
  "properties": {
    "tgn:hierarchy":[
        "tgn:7378988",
        "tgn:7005586",
        "tgn:1000001",
        "tgn:7005560",
        "tgn:7029392"
    ],
    "tgn:id":7378988,
    "tgn:name":"Los Rucios",
    "tgn:placetype":[
        "aat:300008347"
    ]
},
  "bbox": [],
  "geometry": {"coordinates":[-103.15,19.6],"type":"Point"}
}
=======
{"geometry":{"type":"Point","coordinates":[-103.150000,19.600000]},"type":"Feature","properties":{"hierarchy":["tgn:7378988","tgn:7005586","tgn:1000001","tgn:7005560","tgn:7029392"],"placetype":["aat:300008347"],"id":7378988,"name:xx":"Los Rucios"}}
>>>>>>> 03f74aca74312dbeaf24d7e61306dd6a786dc3d0
