{
  "id": 7565420,
  "type": "Feature",
  "properties": {
    "tgn:hierarchy":[
        "tgn:7565420",
        "tgn:1000004",
        "tgn:7000198",
        "tgn:7016788",
        "tgn:7029392"
    ],
    "tgn:id":7565420,
    "tgn:name:en":"Aeta",
    "tgn:placetype":[
        "aat:300008347"
    ]
},
  "bbox": [],
  "geometry": {"coordinates":[71.643876,27.182462],"type":"Point"}
}