{
  "id": 2036462,
  "type": "Feature",
  "properties": {
    "tgn:hierarchy":[
        "tgn:2036462",
        "tgn:1000001",
        "tgn:2000675",
        "tgn:7012149",
        "tgn:7007254",
        "tgn:7029392"
    ],
    "tgn:id":2036462,
    "tgn:name":"Halls Summit",
    "tgn:placetype":[
        "aat:300008347",
        "aat:300387210"
    ]
},
  "bbox": [],
  "geometry": {"coordinates":[-95.6667,38.3333],"type":"Point"}
}