{
  "id": 2142091,
  "type": "Feature",
  "properties": {
    "tgn:hierarchy":[
        "tgn:2142091",
        "tgn:1000001",
        "tgn:1003037",
        "tgn:7012149",
        "tgn:7007516",
        "tgn:7029392"
    ],
    "tgn:id":2142091,
    "tgn:name":"Back Creek",
    "tgn:placetype":[
        "aat:300008706"
    ]
},
  "bbox": [],
  "geometry": {"coordinates":[-75.15,38.4167],"type":"Point"}
}