{
  "id": 7518769,
  "type": "Feature",
  "properties": {
    "tgn:hierarchy":[
        "tgn:7518769",
        "tgn:1009227",
        "tgn:1000226",
        "tgn:7520095",
        "tgn:1000006",
        "tgn:7029392"
    ],
    "tgn:id":7518769,
    "tgn:name:en":"Cairn Hill",
    "tgn:placetype":[
        "aat:300008777"
    ]
},
  "bbox": [],
  "geometry": {"coordinates":[173.066667,-40.966667],"type":"Point"}
}