<<<<<<< HEAD
{
  "id": 7029887,
  "type": "Feature",
  "properties": {
    "tgn:hierarchy":[
        "tgn:7029887",
        "tgn:7019049",
        "tgn:7002445",
        "tgn:1000003",
        "tgn:7029505",
        "tgn:7008591",
        "tgn:7029392"
    ],
    "tgn:id":7029887,
    "tgn:name":"Bramley",
    "tgn:name:ang":"Bramelei",
    "tgn:placetype":[
        "aat:300008347"
    ]
},
  "bbox": [],
  "geometry": {"coordinates":[-1.266667,53.416667],"type":"Point"}
}
=======
{"geometry":{"type":"Point","coordinates":[-1.266667,53.416667]},"type":"Feature","properties":{"hierarchy":["tgn:7029887","tgn:7019049","tgn:7002445","tgn:1000003","tgn:7029505","tgn:7008591","tgn:7029392"],"placetype":["aat:300008347"],"id":7029887,"name:xx":"Bramley","name:ang":"Bramelei"}}
>>>>>>> 03f74aca74312dbeaf24d7e61306dd6a786dc3d0
