{
  "id": 7370417,
  "type": "Feature",
  "properties": {
    "tgn:hierarchy":[
        "tgn:7370417",
        "tgn:1000001",
        "tgn:7005601",
        "tgn:7005560",
        "tgn:7029392"
    ],
    "tgn:id":7370417,
    "tgn:name":"Huerta de Enciso",
    "tgn:placetype":[
        "aat:300008347"
    ]
},
  "bbox": [],
  "geometry": {"coordinates":[-102.633333,22.783333],"type":"Point"}
}