{
  "id": 2291008,
  "type": "Feature",
  "properties": {
    "tgn:hierarchy":[
        "tgn:2291008",
        "tgn:1000001",
        "tgn:2002259",
        "tgn:7012149",
        "tgn:7013961",
        "tgn:7029392"
    ],
    "tgn:id":2291008,
    "tgn:name":"Dog Run",
    "tgn:placetype":[
        "aat:300008699"
    ]
},
  "bbox": [],
  "geometry": {"coordinates":[-80.9167,38.4167],"type":"Point"}
}