{
  "id": 7132973,
  "type": "Feature",
  "properties": {
    "tgn:hierarchy":[
        "tgn:7132973",
        "tgn:1000003",
        "tgn:7003688",
        "tgn:7000084",
        "tgn:7029392"
    ],
    "tgn:id":7132973,
    "tgn:name":"M\u00fchlenbach",
    "tgn:placetype":[
        "aat:300008699"
    ]
},
  "bbox": [],
  "geometry": {"coordinates":[9.916667,54.183333],"type":"Point"}
}