{
  "id": 7274246,
  "type": "Feature",
  "properties": {
    "tgn:hierarchy":[
        "tgn:7274246",
        "tgn:1000003",
        "tgn:7003632",
        "tgn:7016845",
        "tgn:7029392"
    ],
    "tgn:id":7274246,
    "tgn:name:nl":"Zuidbroek, Polder",
    "tgn:placetype":[
        "aat:300006163"
    ]
},
  "bbox": [],
  "geometry": {"coordinates":[4.733333,51.933333],"type":"Point"}
}