{
  "id": 2361095,
  "type": "Feature",
  "properties": {
    "tgn:hierarchy":[
        "tgn:2361095",
        "tgn:1000001",
        "tgn:7012149",
        "tgn:7007157",
        "tgn:2000191",
        "tgn:7029392"
    ],
    "tgn:id":2361095,
    "tgn:name":"Gratten Creek",
    "tgn:placetype":[
        "aat:300008706"
    ]
},
  "bbox": [],
  "geometry": {"coordinates":[-122.7333,40.9667],"type":"Point"}
}