{
  "id": 7412139,
  "type": "Feature",
  "properties": {
    "tgn:hierarchy":[
        "tgn:7412139",
        "tgn:1000001",
        "tgn:7005596",
        "tgn:7005560",
        "tgn:7029392"
    ],
    "tgn:id":7412139,
    "tgn:name:es":"Cucuyulapa",
    "tgn:placetype":[
        "aat:300008347"
    ]
},
  "bbox": [],
  "geometry": {"coordinates":[-93.291667,17.9875],"type":"Point"}
}