{
  "id": 7099944,
  "type": "Feature",
  "properties": {
    "tgn:hierarchy":[
        "tgn:7099944",
        "tgn:7003669",
        "tgn:1000003",
        "tgn:7000084",
        "tgn:7029392"
    ],
    "tgn:id":7099944,
    "tgn:name":"Sperlbrunn",
    "tgn:placetype":[
        "aat:300000206"
    ]
},
  "bbox": [],
  "geometry": {"coordinates":[13.75,48.65],"type":"Point"}
}