{
  "id": 2284165,
  "type": "Feature",
  "properties": {
    "tgn:hierarchy":[
        "tgn:2284165",
        "tgn:7002659",
        "tgn:1000001",
        "tgn:7012149",
        "tgn:2000034",
        "tgn:7029392"
    ],
    "tgn:id":2284165,
    "tgn:name":"Denton Acres",
    "tgn:placetype":[
        "aat:300008347"
    ]
},
  "bbox": [],
  "geometry": {"coordinates":[-85.4167,31.2667],"type":"Point"}
}