{
  "id": 7225532,
  "type": "Feature",
  "properties": {
    "tgn:hierarchy":[
        "tgn:7225532",
        "tgn:7002681",
        "tgn:7001395",
        "tgn:1000003",
        "tgn:1000074",
        "tgn:7029392"
    ],
    "tgn:id":7225532,
    "tgn:name":"P\u00e9rvelos, \u00c1kra",
    "tgn:placetype":[
        "aat:300008850"
    ]
},
  "bbox": [],
  "geometry": {"coordinates":[24.35,37.683333],"type":"Point"}
}