<<<<<<< HEAD
{
  "id": 2153893,
  "type": "Feature",
  "properties": {
    "tgn:hierarchy":[
        "tgn:2153893",
        "tgn:1000001",
        "tgn:7006451",
        "tgn:2000093",
        "tgn:7012149",
        "tgn:7029392"
    ],
    "tgn:id":2153893,
    "tgn:name":"Bear Canyon Spring",
    "tgn:placetype":[
        "aat:300008697"
    ]
},
  "bbox": [],
  "geometry": {"coordinates":[-110.5333,33.6333],"type":"Point"}
}
=======
{"geometry":{"type":"Point","coordinates":[-110.533300,33.633300]},"type":"Feature","properties":{"hierarchy":["tgn:2153893","tgn:1000001","tgn:7006451","tgn:2000093","tgn:7012149","tgn:7029392"],"placetype":["aat:300008697"],"id":2153893,"name:xx":"Bear Canyon Spring"}}
>>>>>>> 03f74aca74312dbeaf24d7e61306dd6a786dc3d0
