<<<<<<< HEAD
{
  "id": 2761965,
  "type": "Feature",
  "properties": {
    "tgn:hierarchy":[
        "tgn:2761965",
        "tgn:1000001",
        "tgn:7012149",
        "tgn:2001307",
        "tgn:7007524",
        "tgn:7029392"
    ],
    "tgn:id":2761965,
    "tgn:name":"West Rosebud Lake",
    "tgn:placetype":[
        "aat:300008680"
    ]
},
  "bbox": [],
  "geometry": {"coordinates":[-109.7,45.25],"type":"Point"}
}
=======
{"geometry":{"type":"Point","coordinates":[-109.700000,45.250000]},"type":"Feature","properties":{"hierarchy":["tgn:2761965","tgn:1000001","tgn:7012149","tgn:2001307","tgn:7007524","tgn:7029392"],"placetype":["aat:300008680"],"id":2761965,"name:xx":"West Rosebud Lake"}}
>>>>>>> 03f74aca74312dbeaf24d7e61306dd6a786dc3d0
