{
  "id": 4008633,
  "type": "Feature",
  "properties": {
    "tgn:hierarchy":[
        "tgn:4008633",
        "tgn:7003167",
        "tgn:1000003",
        "tgn:7009760",
        "tgn:1000080",
        "tgn:7029392"
    ],
    "tgn:id":4008633,
    "tgn:name":"Piazza",
    "tgn:placetype":[
        "aat:300008347"
    ]
},
  "bbox": [],
  "geometry": {"coordinates":[11.15,45.883333],"type":"Point"}
}