{
  "id": 2309814,
  "type": "Feature",
  "properties": {
    "tgn:hierarchy":[
        "tgn:2309814",
        "tgn:1000001",
        "tgn:1003023",
        "tgn:7012149",
        "tgn:7007516",
        "tgn:7029392"
    ],
    "tgn:id":2309814,
    "tgn:name":"Eastern Shore Expermintal Forest",
    "tgn:placetype":[
        "aat:300008863"
    ]
},
  "bbox": [],
  "geometry": {"coordinates":[-75.4167,38.35],"type":"Point"}
}