{
  "id": 2146991,
  "type": "Feature",
  "properties": {
    "tgn:hierarchy":[
        "tgn:2146991",
        "tgn:1000001",
        "tgn:7012149",
        "tgn:7007157",
        "tgn:1002608",
        "tgn:1008999",
        "tgn:7029392"
    ],
    "tgn:id":2146991,
    "tgn:name":"Banning, Mount",
    "tgn:placetype":[
        "aat:300008798"
    ]
},
  "bbox": [],
  "geometry": {"coordinates":[-118.4333,33.3667],"type":"Point"}
}