{
  "id": 7297967,
  "type": "Feature",
  "properties": {
    "tgn:hierarchy":[
        "tgn:7297967",
        "tgn:7002758",
        "tgn:7002821",
        "tgn:1000003",
        "tgn:1000095",
        "tgn:7029392"
    ],
    "tgn:id":7297967,
    "tgn:name":"Sillar Alta",
    "tgn:placetype":[
        "aat:300008347"
    ]
},
  "bbox": [],
  "geometry": {"coordinates":[-3.416667,37.35],"type":"Point"}
}