{
  "id": 7082436,
  "type": "Feature",
  "properties": {
    "tgn:hierarchy":[
        "tgn:7082436",
        "tgn:7003669",
        "tgn:1000003",
        "tgn:7000084",
        "tgn:7029392"
    ],
    "tgn:id":7082436,
    "tgn:name":"Wimm",
    "tgn:placetype":[
        "aat:300000206"
    ]
},
  "bbox": [],
  "geometry": {"coordinates":[12.483333,48.166667],"type":"Point"}
}