{
  "id": 2098200,
  "type": "Feature",
  "properties": {
    "tgn:hierarchy":[
        "tgn:2098200",
        "tgn:1000001",
        "tgn:7012149",
        "tgn:2001880",
        "tgn:7007825",
        "tgn:7029392"
    ],
    "tgn:id":2098200,
    "tgn:name":"Burristown",
    "tgn:placetype":[
        "aat:300008347",
        "aat:300387210"
    ]
},
  "bbox": [],
  "geometry": {"coordinates":[-85.5333,36.3833],"type":"Point"}
}