{
  "id": 1055464,
  "type": "Feature",
  "properties": {
    "tgn:hierarchy":[
        "tgn:1055464",
        "tgn:7006633",
        "tgn:1000003",
        "tgn:7006540",
        "tgn:7029392"
    ],
    "tgn:id":1055464,
    "tgn:name":"Kohtla-J\u00e4rve",
    "tgn:placetype":[
        "aat:300008347",
        "aat:300008389",
        "aat:300387270",
        "aat:300387302"
    ]
},
  "bbox": [],
  "geometry": {"coordinates":[27.271,59.398],"type":"Point"}
}