<<<<<<< HEAD
{
  "id": 7023472,
  "type": "Feature",
  "properties": {
    "tgn:hierarchy":[
        "tgn:7023472",
        "tgn:1000001",
        "tgn:7012149",
        "tgn:7007157",
        "tgn:7029392"
    ],
    "tgn:id":7023472,
    "tgn:name":"Mormon Ravine",
    "tgn:placetype":[
        "aat:300008761"
    ]
},
  "bbox": [],
  "geometry": {"coordinates":[-121.0,38.7333],"type":"Point"}
}
=======
{"geometry":{"type":"Point","coordinates":[-121.000000,38.733300]},"type":"Feature","properties":{"hierarchy":["tgn:7023472","tgn:1000001","tgn:7012149","tgn:7007157","tgn:7029392"],"placetype":["aat:300008761"],"id":7023472,"name:xx":"Mormon Ravine"}}
>>>>>>> 03f74aca74312dbeaf24d7e61306dd6a786dc3d0
