{
  "id": 2437338,
  "type": "Feature",
  "properties": {
    "tgn:hierarchy":[
        "tgn:2437338",
        "tgn:1000001",
        "tgn:7012149",
        "tgn:2001615",
        "tgn:7007706",
        "tgn:7029392"
    ],
    "tgn:id":2437338,
    "tgn:name":"Kimble Creek",
    "tgn:placetype":[
        "aat:300008706"
    ]
},
  "bbox": [],
  "geometry": {"coordinates":[-82.5833,38.7667],"type":"Point"}
}