{
  "id": 2191703,
  "type": "Feature",
  "properties": {
    "tgn:hierarchy":[
        "tgn:2191703",
        "tgn:1000001",
        "tgn:7012149",
        "tgn:2001892",
        "tgn:7007825",
        "tgn:7029392"
    ],
    "tgn:id":2191703,
    "tgn:name":"Bradley Hollow",
    "tgn:placetype":[
        "aat:300008761"
    ]
},
  "bbox": [],
  "geometry": {"coordinates":[-86.0167,36.5167],"type":"Point"}
}