{
  "id": 2217448,
  "type": "Feature",
  "properties": {
    "tgn:hierarchy":[
        "tgn:2217448",
        "tgn:1000001",
        "tgn:1002231",
        "tgn:7012149",
        "tgn:7007255",
        "tgn:7029392"
    ],
    "tgn:id":2217448,
    "tgn:name":"Campbell County Lake",
    "tgn:placetype":[
        "aat:300008680"
    ]
},
  "bbox": [],
  "geometry": {"coordinates":[-84.3667,38.8833],"type":"Point"}
}