{
  "id": 2204985,
  "type": "Feature",
  "properties": {
    "tgn:hierarchy":[
        "tgn:2204985",
        "tgn:1000001",
        "tgn:7012149",
        "tgn:2001447",
        "tgn:7007566",
        "tgn:7029392"
    ],
    "tgn:id":2204985,
    "tgn:name":"Bug Scuffle Canyon",
    "tgn:placetype":[
        "aat:300008761"
    ]
},
  "bbox": [],
  "geometry": {"coordinates":[-105.7667,32.7167],"type":"Point"}
}