{
  "id": 7579513,
  "type": "Feature",
  "properties": {
    "tgn:hierarchy":[
        "tgn:7579513",
        "tgn:1000004",
        "tgn:7000198",
        "tgn:1001894",
        "tgn:7029392"
    ],
    "tgn:id":7579513,
    "tgn:name:en":"Umr\u0101oganj",
    "tgn:placetype":[
        "aat:300008347"
    ]
},
  "bbox": [],
  "geometry": {"coordinates":[77.603695,23.192808],"type":"Point"}
}