{
  "id": 7204758,
  "type": "Feature",
  "properties": {
    "tgn:hierarchy":[
        "tgn:7204758",
        "tgn:7003669",
        "tgn:1000003",
        "tgn:7000084",
        "tgn:7029392"
    ],
    "tgn:id":7204758,
    "tgn:name":"B\u00fcchel-Berg",
    "tgn:placetype":[
        "aat:300008777"
    ]
},
  "bbox": [],
  "geometry": {"coordinates":[10.033333,50.116667],"type":"Point"}
}