{
  "id": 7468085,
  "type": "Feature",
  "properties": {
    "tgn:hierarchy":[
        "tgn:7468085",
        "tgn:7001010",
        "tgn:1000004",
        "tgn:1000141",
        "tgn:7029392"
    ],
    "tgn:id":7468085,
    "tgn:name":"Qianagangxi Kou",
    "tgn:placetype":[
        "aat:300387057"
    ]
},
  "bbox": [],
  "geometry": {"coordinates":[121.716667,24.25],"type":"Point"}
}