{
  "id": 1015157,
  "type": "Feature",
  "properties": {
    "tgn:hierarchy":[
        "tgn:1015157",
        "tgn:7005685",
        "tgn:1000001",
        "tgn:7013154",
        "tgn:7029392"
    ],
    "tgn:id":1015157,
    "tgn:name":"Thessalon",
    "tgn:placetype":[
        "aat:300008347"
    ]
},
  "bbox": [],
  "geometry": {"coordinates":[-83.5667,46.25],"type":"Point"}
}