{
  "id": 7440961,
  "type": "Feature",
  "properties": {
    "tgn:hierarchy":[
        "tgn:7440961",
        "tgn:7005586",
        "tgn:1000001",
        "tgn:7005560",
        "tgn:7029392"
    ],
    "tgn:id":7440961,
    "tgn:name":"Santa Ana Tepetitl\u00e1n",
    "tgn:placetype":[
        "aat:300008347"
    ]
},
  "bbox": [],
  "geometry": {"coordinates":[-103.45,20.616667],"type":"Point"}
}