{
  "id": 7462439,
  "type": "Feature",
  "properties": {
    "tgn:hierarchy":[
        "tgn:7462439",
        "tgn:7002445",
        "tgn:1000003",
        "tgn:7008157",
        "tgn:7008591",
        "tgn:7029392"
    ],
    "tgn:id":7462439,
    "tgn:name:en":"Inner Knock",
    "tgn:placetype":[
        "aat:300386970"
    ]
},
  "bbox": [],
  "geometry": {"coordinates":[0.35,53.083333],"type":"Point"}
}