{
  "id": 2381179,
  "type": "Feature",
  "properties": {
    "tgn:hierarchy":[
        "tgn:2381179",
        "tgn:1000001",
        "tgn:1002664",
        "tgn:7012149",
        "tgn:7007159",
        "tgn:7029392"
    ],
    "tgn:id":2381179,
    "tgn:name":"Hawks Nest",
    "tgn:placetype":[
        "aat:300008347"
    ]
},
  "bbox": [],
  "geometry": {"coordinates":[-72.4667,41.2667],"type":"Point"}
}