<<<<<<< HEAD
{
  "id": 2761036,
  "type": "Feature",
  "properties": {
    "tgn:hierarchy":[
        "tgn:2761036",
        "tgn:1000001",
        "tgn:7012149",
        "tgn:1002873",
        "tgn:7007568",
        "tgn:7029392"
    ],
    "tgn:id":2761036,
    "tgn:name":"West Kill",
    "tgn:placetype":[
        "aat:300008699"
    ]
},
  "bbox": [],
  "geometry": {"coordinates":[-74.6,42.5],"type":"Point"}
}
=======
{"geometry":{"type":"Point","coordinates":[-74.600000,42.500000]},"type":"Feature","properties":{"hierarchy":["tgn:2761036","tgn:1000001","tgn:7012149","tgn:1002873","tgn:7007568","tgn:7029392"],"placetype":["aat:300008699"],"id":2761036,"name:xx":"West Kill"}}
>>>>>>> 03f74aca74312dbeaf24d7e61306dd6a786dc3d0
