{
  "id": 1088423,
  "type": "Feature",
  "properties": {
    "tgn:hierarchy":[
        "tgn:1088423",
        "tgn:7001242",
        "tgn:1000982",
        "tgn:1000155",
        "tgn:7029392"
    ],
    "tgn:id":1088423,
    "tgn:name":"Ouadda",
    "tgn:placetype":[
        "aat:300008347"
    ]
},
  "bbox": [],
  "geometry": {"coordinates":[22.3333,8.15],"type":"Point"}
}