{
  "id": 2344822,
  "type": "Feature",
  "properties": {
    "tgn:hierarchy":[
        "tgn:2344822",
        "tgn:1000001",
        "tgn:7012149",
        "tgn:2001036",
        "tgn:7007521",
        "tgn:7029392"
    ],
    "tgn:id":2344822,
    "tgn:name":"Garden Lake",
    "tgn:placetype":[
        "aat:300008680"
    ]
},
  "bbox": [],
  "geometry": {"coordinates":[-91.75,47.9167],"type":"Point"}
}