{
  "id": 2187706,
  "type": "Feature",
  "properties": {
    "tgn:hierarchy":[
        "tgn:2187706",
        "tgn:1000001",
        "tgn:7016102",
        "tgn:7012149",
        "tgn:7007516",
        "tgn:7029392"
    ],
    "tgn:id":2187706,
    "tgn:name":"Boothby Hill",
    "tgn:placetype":[
        "aat:300008798"
    ]
},
  "bbox": [],
  "geometry": {"coordinates":[-76.15,39.4667],"type":"Point"}
}