{
  "id": 7110305,
  "type": "Feature",
  "properties": {
    "tgn:hierarchy":[
        "tgn:7110305",
        "tgn:7003669",
        "tgn:1000003",
        "tgn:7000084",
        "tgn:7029392"
    ],
    "tgn:id":7110305,
    "tgn:name":"Rauschensteig",
    "tgn:placetype":[
        "aat:300008347"
    ]
},
  "bbox": [],
  "geometry": {"coordinates":[12.016667,50.083333],"type":"Point"}
}