{
  "id": 7452228,
  "type": "Feature",
  "properties": {
    "tgn:hierarchy":[
        "tgn:7452228",
        "tgn:7002444",
        "tgn:7008074",
        "tgn:1000003",
        "tgn:7008591",
        "tgn:7029392"
    ],
    "tgn:id":7452228,
    "tgn:name:en":"Enoch",
    "tgn:placetype":[
        "aat:300008347"
    ]
},
  "bbox": [],
  "geometry": {"coordinates":[-5.116667,54.85],"type":"Point"}
}