{
  "id": 7192569,
  "type": "Feature",
  "properties": {
    "tgn:hierarchy":[
        "tgn:7192569",
        "tgn:1000003",
        "tgn:7003678",
        "tgn:7000084",
        "tgn:7029392"
    ],
    "tgn:id":7192569,
    "tgn:name":"F\u00f6rsterei Falkenbach",
    "tgn:placetype":[
        "aat:300004792"
    ]
},
  "bbox": [],
  "geometry": {"coordinates":[9.633333,50.816667],"type":"Point"}
}