{
  "id": 7384001,
  "type": "Feature",
  "properties": {
    "tgn:hierarchy":[
        "tgn:7384001",
        "tgn:1000001",
        "tgn:1001960",
        "tgn:7005560",
        "tgn:7029392"
    ],
    "tgn:id":7384001,
    "tgn:name":"Obenala",
    "tgn:placetype":[
        "aat:300008347"
    ]
},
  "bbox": [],
  "geometry": {"coordinates":[-110.483333,29.366667],"type":"Point"}
}