{
  "id": 2759020,
  "type": "Feature",
  "properties": {
    "tgn:hierarchy":[
        "tgn:2759020",
        "tgn:1000001",
        "tgn:7012149",
        "tgn:7007252",
        "tgn:7029392"
    ],
    "tgn:id":2759020,
    "tgn:name":"West Fork Bear Creek",
    "tgn:placetype":[
        "aat:300008706"
    ]
},
  "bbox": [],
  "geometry": {"coordinates":[-85.9333,40.2167],"type":"Point"}
}