<<<<<<< HEAD
{
  "id": 2156625,
  "type": "Feature",
  "properties": {
    "tgn:hierarchy":[
        "tgn:2156625",
        "tgn:1000001",
        "tgn:7012149",
        "tgn:2001722",
        "tgn:7007708",
        "tgn:7029392"
    ],
    "tgn:id":2156625,
    "tgn:name":"Bearwallow Spring",
    "tgn:placetype":[
        "aat:300008697"
    ]
},
  "bbox": [],
  "geometry": {"coordinates":[-117.5833,45.4333],"type":"Point"}
}
=======
{"geometry":{"type":"Point","coordinates":[-117.583300,45.433300]},"type":"Feature","properties":{"hierarchy":["tgn:2156625","tgn:1000001","tgn:7012149","tgn:2001722","tgn:7007708","tgn:7029392"],"placetype":["aat:300008697"],"id":2156625,"name:xx":"Bearwallow Spring"}}
>>>>>>> 03f74aca74312dbeaf24d7e61306dd6a786dc3d0
