{
  "id": 7552963,
  "type": "Feature",
  "properties": {
    "tgn:hierarchy":[
        "tgn:7552963",
        "tgn:1000004",
        "tgn:1001832",
        "tgn:7000198",
        "tgn:7029392"
    ],
    "tgn:id":7552963,
    "tgn:name:en":"M\u0101ranj\u0101n",
    "tgn:placetype":[
        "aat:300008347"
    ]
},
  "bbox": [],
  "geometry": {"coordinates":[94.916667,27.083333],"type":"Point"}
}