{
  "id": 7190195,
  "type": "Feature",
  "properties": {
    "tgn:hierarchy":[
        "tgn:7190195",
        "tgn:1000003",
        "tgn:7003682",
        "tgn:7000084",
        "tgn:7029392"
    ],
    "tgn:id":7190195,
    "tgn:name":"Eimsheim",
    "tgn:placetype":[
        "aat:300008347"
    ]
},
  "bbox": [],
  "geometry": {"coordinates":[8.289444,49.795833],"type":"Point"}
}