<<<<<<< HEAD
{
  "id": 7360915,
  "type": "Feature",
  "properties": {
    "tgn:hierarchy":[
        "tgn:7360915",
        "tgn:7005587",
        "tgn:1000001",
        "tgn:7005560",
        "tgn:7029392"
    ],
    "tgn:id":7360915,
    "tgn:name:es":"El Nith",
    "tgn:placetype":[
        "aat:300008347"
    ]
},
  "bbox": [],
  "geometry": {"coordinates":[-99.191667,20.491667],"type":"Point"}
}
=======
{"geometry":{"type":"Point","coordinates":[-99.191667,20.491667]},"type":"Feature","properties":{"hierarchy":["tgn:7360915","tgn:7005587","tgn:1000001","tgn:7005560","tgn:7029392"],"placetype":["aat:300008347"],"id":7360915,"name:es":"El Nith"}}
>>>>>>> 03f74aca74312dbeaf24d7e61306dd6a786dc3d0
