{
  "id": 2383142,
  "type": "Feature",
  "properties": {
    "tgn:hierarchy":[
        "tgn:2383142",
        "tgn:1000001",
        "tgn:2000311",
        "tgn:7012149",
        "tgn:7007248",
        "tgn:7029392"
    ],
    "tgn:id":2383142,
    "tgn:name":"Heads Creek",
    "tgn:placetype":[
        "aat:300008706"
    ]
},
  "bbox": [],
  "geometry": {"coordinates":[-81.6167,31.0333],"type":"Point"}
}