{
  "id": 2296999,
  "type": "Feature",
  "properties": {
    "tgn:hierarchy":[
        "tgn:2296999",
        "tgn:1000001",
        "tgn:7012149",
        "tgn:1002932",
        "tgn:7007710",
        "tgn:7029392"
    ],
    "tgn:id":2296999,
    "tgn:name":"Dry Creek",
    "tgn:placetype":[
        "aat:300008706"
    ]
},
  "bbox": [],
  "geometry": {"coordinates":[-75.7833,41.7667],"type":"Point"}
}