{
  "id": 7527067,
  "type": "Feature",
  "properties": {
    "tgn:hierarchy":[
        "tgn:7527067",
        "tgn:7001242",
        "tgn:7016833",
        "tgn:1001091",
        "tgn:7029392"
    ],
    "tgn:id":7527067,
    "tgn:name":"K\u016bbr\u012b at T\u016bnis\u012b Ut\u016bstr\u0101d",
    "tgn:placetype":[
        "aat:300007836"
    ]
},
  "bbox": [],
  "geometry": {"coordinates":[31.269684,30.008306],"type":"Point"}
}