{
  "id": 2491102,
  "type": "Feature",
  "properties": {
    "tgn:hierarchy":[
        "tgn:2491102",
        "tgn:1000001",
        "tgn:7012149",
        "tgn:1002742",
        "tgn:7007920",
        "tgn:7029392"
    ],
    "tgn:id":2491102,
    "tgn:name":"Many Trails Peak",
    "tgn:placetype":[
        "aat:300008798"
    ]
},
  "bbox": [],
  "geometry": {"coordinates":[-120.4667,48.85],"type":"Point"}
}