{
  "id": 7562182,
  "type": "Feature",
  "properties": {
    "tgn:hierarchy":[
        "tgn:7562182",
        "tgn:1000004",
        "tgn:7000198",
        "tgn:1001894",
        "tgn:7029392"
    ],
    "tgn:id":7562182,
    "tgn:name:en":"Iswari",
    "tgn:placetype":[
        "aat:300008347"
    ]
},
  "bbox": [],
  "geometry": {"coordinates":[79.022108,26.491069],"type":"Point"}
}