{
  "id": 2758395,
  "type": "Feature",
  "properties": {
    "tgn:hierarchy":[
        "tgn:2758395",
        "tgn:1000001",
        "tgn:7012149",
        "tgn:1002747",
        "tgn:7007568",
        "tgn:7029392"
    ],
    "tgn:id":2758395,
    "tgn:name":"West Canadice Corners",
    "tgn:placetype":[
        "aat:300008347"
    ]
},
  "bbox": [],
  "geometry": {"coordinates":[-77.55,42.7333],"type":"Point"}
}