{
  "id": 2360217,
  "type": "Feature",
  "properties": {
    "tgn:hierarchy":[
        "tgn:2360217",
        "tgn:1000001",
        "tgn:7012149",
        "tgn:7007240",
        "tgn:7029392"
    ],
    "tgn:id":2360217,
    "tgn:name":"Grass Pond",
    "tgn:placetype":[
        "aat:300008905"
    ]
},
  "bbox": [],
  "geometry": {"coordinates":[-81.6167,28.7833],"type":"Point"}
}