{
  "id": 7206260,
  "type": "Feature",
  "properties": {
    "tgn:hierarchy":[
        "tgn:7206260",
        "tgn:1000003",
        "tgn:7003685",
        "tgn:7000084",
        "tgn:7029392"
    ],
    "tgn:id":7206260,
    "tgn:name":"Bucker Berg",
    "tgn:placetype":[
        "aat:300008795"
    ]
},
  "bbox": [],
  "geometry": {"coordinates":[12.633333,50.483333],"type":"Point"}
}