{
  "id": 2348784,
  "type": "Feature",
  "properties": {
    "tgn:hierarchy":[
        "tgn:2348784",
        "tgn:1000001",
        "tgn:2002151",
        "tgn:7012149",
        "tgn:7007919",
        "tgn:7029392"
    ],
    "tgn:id":2348784,
    "tgn:name":"Gibson Knob",
    "tgn:placetype":[
        "aat:300008798"
    ]
},
  "bbox": [],
  "geometry": {"coordinates":[-80.5167,36.7167],"type":"Point"}
}