{
  "id": 2048908,
  "type": "Feature",
  "properties": {
    "tgn:hierarchy":[
        "tgn:2048908",
        "tgn:1000001",
        "tgn:7016098",
        "tgn:7012149",
        "tgn:7007516",
        "tgn:7029392"
    ],
    "tgn:id":2048908,
    "tgn:name":"Tall Timbers",
    "tgn:placetype":[
        "aat:300008347"
    ]
},
  "bbox": [],
  "geometry": {"coordinates":[-76.5333,38.1667],"type":"Point"}
}