<<<<<<< HEAD
{
  "id": 7022695,
  "type": "Feature",
  "properties": {
    "tgn:hierarchy":[
        "tgn:7022695",
        "tgn:1000001",
        "tgn:7012149",
        "tgn:7029392"
    ],
    "tgn:id":7022695,
    "tgn:name":"West Fork Medicine Creek",
    "tgn:placetype":[
        "aat:300008706"
    ]
},
  "bbox": [],
  "geometry": {"coordinates":[-93.3,40.5167],"type":"Point"}
}
=======
{"geometry":{"type":"Point","coordinates":[-93.300000,40.516700]},"type":"Feature","properties":{"hierarchy":["tgn:7022695","tgn:1000001","tgn:7012149","tgn:7029392"],"placetype":["aat:300008706"],"id":7022695,"name:xx":"West Fork Medicine Creek"}}
>>>>>>> 03f74aca74312dbeaf24d7e61306dd6a786dc3d0
