{
  "id": 2560923,
  "type": "Feature",
  "properties": {
    "tgn:hierarchy":[
        "tgn:2560923",
        "tgn:1000001",
        "tgn:7006451",
        "tgn:7012149",
        "tgn:2000103",
        "tgn:7029392"
    ],
    "tgn:id":2560923,
    "tgn:name":"Oro Grande Mine",
    "tgn:placetype":[
        "aat:300000390"
    ]
},
  "bbox": [],
  "geometry": {"coordinates":[-112.7167,34.0167],"type":"Point"}
}