{
  "id": 7430100,
  "type": "Feature",
  "properties": {
    "tgn:hierarchy":[
        "tgn:7430100",
        "tgn:7005583",
        "tgn:1000001",
        "tgn:7005560",
        "tgn:7029392"
    ],
    "tgn:id":7430100,
    "tgn:name":"Campo Alto",
    "tgn:placetype":[
        "aat:300008347"
    ]
},
  "bbox": [],
  "geometry": {"coordinates":[-105.05,24.966667],"type":"Point"}
}