<<<<<<< HEAD
{
  "id": 7119923,
  "type": "Feature",
  "properties": {
    "tgn:hierarchy":[
        "tgn:7119923",
        "tgn:7003692",
        "tgn:1000003",
        "tgn:7000084",
        "tgn:7029392"
    ],
    "tgn:id":7119923,
    "tgn:name":"Premer Weiher",
    "tgn:placetype":[
        "aat:300008688"
    ]
},
  "bbox": [],
  "geometry": {"coordinates":[9.816667,47.783333],"type":"Point"}
}
=======
{"geometry":{"type":"Point","coordinates":[9.816667,47.783333]},"type":"Feature","properties":{"hierarchy":["tgn:7119923","tgn:7003692","tgn:1000003","tgn:7000084","tgn:7029392"],"placetype":["aat:300008688"],"id":7119923,"name:xx":"Premer Weiher"}}
>>>>>>> 03f74aca74312dbeaf24d7e61306dd6a786dc3d0
