{
  "id": 1137652,
  "type": "Feature",
  "properties": {
    "tgn:hierarchy":[
        "tgn:1137652",
        "tgn:7012076",
        "tgn:1000003",
        "tgn:7006660",
        "tgn:7029392"
    ],
    "tgn:id":1137652,
    "tgn:name":"Kirovo",
    "tgn:placetype":[
        "aat:300008347",
        "aat:300008375"
    ]
},
  "bbox": [],
  "geometry": {"coordinates":[38.05,48.8333],"type":"Point"}
}