{
  "id": 2191055,
  "type": "Feature",
  "properties": {
    "tgn:hierarchy":[
        "tgn:2191055",
        "tgn:1000001",
        "tgn:7012149",
        "tgn:7007157",
        "tgn:1002869",
        "tgn:7029392"
    ],
    "tgn:id":2191055,
    "tgn:name":"Boyer Creek",
    "tgn:placetype":[
        "aat:300008706"
    ]
},
  "bbox": [],
  "geometry": {"coordinates":[-122.1833,37.1167],"type":"Point"}
}