{
  "id": 7250365,
  "type": "Feature",
  "properties": {
    "tgn:hierarchy":[
        "tgn:7250365",
        "tgn:7003460",
        "tgn:1000003",
        "tgn:1000063",
        "tgn:4012014",
        "tgn:7029392"
    ],
    "tgn:id":7250365,
    "tgn:name":"Oborne",
    "tgn:placetype":[
        "aat:300008347"
    ]
},
  "bbox": [],
  "geometry": {"coordinates":[5.538365,50.755458],"type":"Point"}
}