{
  "id": 7280968,
  "type": "Feature",
  "properties": {
    "tgn:hierarchy":[
        "tgn:7280968",
        "tgn:1001637",
        "tgn:1000049",
        "tgn:1000002",
        "tgn:7029392"
    ],
    "tgn:id":7280968,
    "tgn:name":"Tagua, Cerro",
    "tgn:placetype":[
        "aat:300008795"
    ]
},
  "bbox": [],
  "geometry": {"coordinates":[-71.15,-36.683333],"type":"Point"}
}