{
  "id": 7495122,
  "type": "Feature",
  "properties": {
    "tgn:hierarchy":[
        "tgn:7495122",
        "tgn:1000004",
        "tgn:7001013",
        "tgn:1000141",
        "tgn:7029392"
    ],
    "tgn:id":7495122,
    "tgn:name":"Zhongxing Guozhong",
    "tgn:placetype":[
        "aat:300006495"
    ]
},
  "bbox": [],
  "geometry": {"coordinates":[121.289395,24.99777],"type":"Point"}
}