{
  "id": 1075209,
  "type": "Feature",
  "properties": {
    "tgn:hierarchy":[
        "tgn:1075209",
        "tgn:1000004",
        "tgn:7000198",
        "tgn:7000799",
        "tgn:7029392"
    ],
    "tgn:id":1075209,
    "tgn:name:en":"Doda",
    "tgn:placetype":[
        "aat:300008347"
    ]
},
  "bbox": [],
  "geometry": {"coordinates":[75.546,33.148],"type":"Point"}
}