{
  "id": 2410411,
  "type": "Feature",
  "properties": {
    "tgn:hierarchy":[
        "tgn:2410411",
        "tgn:1000001",
        "tgn:2001411",
        "tgn:7012149",
        "tgn:7007526",
        "tgn:7029392"
    ],
    "tgn:id":2410411,
    "tgn:name":"Indian Buttes",
    "tgn:placetype":[
        "aat:300008798"
    ]
},
  "bbox": [],
  "geometry": {"coordinates":[-116.9167,41.8833],"type":"Point"}
}