<<<<<<< HEAD
{
  "id": 2150625,
  "type": "Feature",
  "properties": {
    "tgn:hierarchy":[
        "tgn:2150625",
        "tgn:1000001",
        "tgn:1002275",
        "tgn:7012149",
        "tgn:7007920",
        "tgn:7029392"
    ],
    "tgn:id":2150625,
    "tgn:name":"Basket Creek",
    "tgn:placetype":[
        "aat:300008706"
    ]
},
  "bbox": [],
  "geometry": {"coordinates":[-122.4167,45.8167],"type":"Point"}
}
=======
{"geometry":{"type":"Point","coordinates":[-122.416700,45.816700]},"type":"Feature","properties":{"hierarchy":["tgn:2150625","tgn:1000001","tgn:1002275","tgn:7012149","tgn:7007920","tgn:7029392"],"placetype":["aat:300008706"],"id":2150625,"name:xx":"Basket Creek"}}
>>>>>>> 03f74aca74312dbeaf24d7e61306dd6a786dc3d0
