{
  "id": 2779976,
  "type": "Feature",
  "properties": {
    "tgn:hierarchy":[
        "tgn:2779976",
        "tgn:1000001",
        "tgn:7012149",
        "tgn:2001067",
        "tgn:7007521",
        "tgn:7029392"
    ],
    "tgn:id":2779976,
    "tgn:name":"Wolfpack Lake",
    "tgn:placetype":[
        "aat:300008680"
    ]
},
  "bbox": [],
  "geometry": {"coordinates":[-92.2833,48.1833],"type":"Point"}
}