{
  "id": 2752317,
  "type": "Feature",
  "properties": {
    "tgn:hierarchy":[
        "tgn:2752317",
        "tgn:1000001",
        "tgn:7012149",
        "tgn:2001442",
        "tgn:7007566",
        "tgn:7029392"
    ],
    "tgn:id":2752317,
    "tgn:name":"Washington",
    "tgn:placetype":[
        "aat:300000390"
    ]
},
  "bbox": [],
  "geometry": {"coordinates":[-105.7667,33.4667],"type":"Point"}
}