{
  "id": 1114874,
  "type": "Feature",
  "properties": {
    "tgn:hierarchy":[
        "tgn:1114874",
        "tgn:7005735",
        "tgn:7005685",
        "tgn:1000001",
        "tgn:7029392"
    ],
    "tgn:id":1114874,
    "tgn:name":"Discovery Passage",
    "tgn:placetype":[
        "aat:300387217"
    ]
},
  "bbox": [],
  "geometry": {"coordinates":[-125.25,50.0667],"type":"Point"}
}