{
  "id": 1025020,
  "type": "Feature",
  "properties": {
    "tgn:hierarchy":[
        "tgn:1025020",
        "tgn:1001963",
        "tgn:1000002",
        "tgn:1000059",
        "tgn:7029392"
    ],
    "tgn:id":1025020,
    "tgn:name":"Araya",
    "tgn:placetype":[
        "aat:300008347"
    ]
},
  "bbox": [],
  "geometry": {"coordinates":[-64.25,10.5667],"type":"Point"}
}