{
  "id": 1026117,
  "type": "Feature",
  "properties": {
    "tgn:hierarchy":[
        "tgn:1026117",
        "tgn:7003023",
        "tgn:1000003",
        "tgn:1000062",
        "tgn:7029392"
    ],
    "tgn:id":1026117,
    "tgn:name":"Stegersbach",
    "tgn:placetype":[
        "aat:300008347"
    ]
},
  "bbox": [],
  "geometry": {"coordinates":[16.1667,47.1667],"type":"Point"}
}