<<<<<<< HEAD
{
  "id": 2339530,
  "type": "Feature",
  "properties": {
    "tgn:hierarchy":[
        "tgn:2339530",
        "tgn:1000001",
        "tgn:7012149",
        "tgn:2000393",
        "tgn:7007248",
        "tgn:7029392"
    ],
    "tgn:id":2339530,
    "tgn:name":"Fred Vaughn Lake",
    "tgn:placetype":[
        "aat:300006191"
    ]
},
  "bbox": [],
  "geometry": {"coordinates":[-84.0,33.0333],"type":"Point"}
}
=======
{"geometry":{"type":"Point","coordinates":[-84.000000,33.033300]},"type":"Feature","properties":{"hierarchy":["tgn:2339530","tgn:1000001","tgn:7012149","tgn:2000393","tgn:7007248","tgn:7029392"],"placetype":["aat:300006191"],"id":2339530,"name:xx":"Fred Vaughn Lake"}}
>>>>>>> 03f74aca74312dbeaf24d7e61306dd6a786dc3d0
