{
  "id": 1131760,
  "type": "Feature",
  "properties": {
    "tgn:hierarchy":[
        "tgn:1131760",
        "tgn:1000001",
        "tgn:7012149",
        "tgn:7007709",
        "tgn:7029392"
    ],
    "tgn:id":1131760,
    "tgn:name":"White Oak",
    "tgn:placetype":[
        "aat:300008707"
    ]
},
  "bbox": [],
  "geometry": {"coordinates":[-78.2833,34.4167],"type":"Point"}
}