{
  "id": 1086366,
  "type": "Feature",
  "properties": {
    "tgn:hierarchy":[
        "tgn:1086366",
        "tgn:1001127",
        "tgn:1000004",
        "tgn:7018455",
        "tgn:1000144",
        "tgn:7029392"
    ],
    "tgn:id":1086366,
    "tgn:name":"Simek",
    "tgn:placetype":[
        "aat:300008347"
    ]
},
  "bbox": [],
  "geometry": {"coordinates":[42.1167,38.3167],"type":"Point"}
}