{
  "id": 7034639,
  "type": "Feature",
  "properties": {
    "tgn:hierarchy":[
        "tgn:7034639",
        "tgn:7003006",
        "tgn:1000003",
        "tgn:7002997",
        "tgn:1000080",
        "tgn:7029392"
    ],
    "tgn:id":7034639,
    "tgn:name":"Canale Malamocco Marghera",
    "tgn:placetype":[
        "aat:300006075"
    ]
},
  "bbox": [],
  "geometry": {"coordinates":[12.256667,45.441667],"type":"Point"}
}