<<<<<<< HEAD
{
  "id": 7356671,
  "type": "Feature",
  "properties": {
    "tgn:hierarchy":[
        "tgn:7356671",
        "tgn:1000001",
        "tgn:7005599",
        "tgn:7005560",
        "tgn:7029392"
    ],
    "tgn:id":7356671,
    "tgn:name":"Chacalapan",
    "tgn:placetype":[
        "aat:300008347"
    ]
},
  "bbox": [],
  "geometry": {"coordinates":[-95.2,18.35],"type":"Point"}
}
=======
{"geometry":{"type":"Point","coordinates":[-95.200000,18.350000]},"type":"Feature","properties":{"hierarchy":["tgn:7356671","tgn:1000001","tgn:7005599","tgn:7005560","tgn:7029392"],"placetype":["aat:300008347"],"id":7356671,"name:xx":"Chacalapan"}}
>>>>>>> 03f74aca74312dbeaf24d7e61306dd6a786dc3d0
