<<<<<<< HEAD
{
  "id": 2405508,
  "type": "Feature",
  "properties": {
    "tgn:hierarchy":[
        "tgn:2405508",
        "tgn:1000001",
        "tgn:7012149",
        "tgn:2001300",
        "tgn:7007524",
        "tgn:7029392"
    ],
    "tgn:id":2405508,
    "tgn:name":"Hughes Creek",
    "tgn:placetype":[
        "aat:300008706"
    ]
},
  "bbox": [],
  "geometry": {"coordinates":[-114.0333,45.6667],"type":"Point"}
}
=======
{"geometry":{"type":"Point","coordinates":[-114.033300,45.666700]},"type":"Feature","properties":{"hierarchy":["tgn:2405508","tgn:1000001","tgn:7012149","tgn:2001300","tgn:7007524","tgn:7029392"],"placetype":["aat:300008706"],"id":2405508,"name:xx":"Hughes Creek"}}
>>>>>>> 03f74aca74312dbeaf24d7e61306dd6a786dc3d0
