{
  "id": 1130939,
  "type": "Feature",
  "properties": {
    "tgn:hierarchy":[
        "tgn:1130939",
        "tgn:1000001",
        "tgn:7005599",
        "tgn:7005560",
        "tgn:7029392"
    ],
    "tgn:id":1130939,
    "tgn:name":"Tonal\u00e1, R\u00edo",
    "tgn:placetype":[
        "aat:300008707",
        "aat:300008699"
    ]
},
  "bbox": [],
  "geometry": {"coordinates":[-94.070833,17.980556],"type":"Point"}
}