{
  "id": 1118529,
  "type": "Feature",
  "properties": {
    "tgn:hierarchy":[
        "tgn:1118529",
        "tgn:1000003",
        "tgn:7594273",
        "tgn:1000070",
        "tgn:7029392"
    ],
    "tgn:id":1118529,
    "tgn:name":"Urbino, \u00c9tang d'",
    "tgn:placetype":[
        "aat:300008680"
    ]
},
  "bbox": [],
  "geometry": {"coordinates":[9.4667,42.0333],"type":"Point"}
}