{
  "id": 7165171,
  "type": "Feature",
  "properties": {
    "tgn:hierarchy":[
        "tgn:7165171",
        "tgn:7003692",
        "tgn:1000003",
        "tgn:7000084",
        "tgn:7029392"
    ],
    "tgn:id":7165171,
    "tgn:name":"Ihlingen",
    "tgn:placetype":[
        "aat:300008347"
    ]
},
  "bbox": [],
  "geometry": {"coordinates":[8.666667,48.433333],"type":"Point"}
}