{
  "id": 2383283,
  "type": "Feature",
  "properties": {
    "tgn:hierarchy":[
        "tgn:2383283",
        "tgn:1000001",
        "tgn:7012149",
        "tgn:2001533",
        "tgn:7007709",
        "tgn:7029392"
    ],
    "tgn:id":2383283,
    "tgn:name":"Hearne Pond",
    "tgn:placetype":[
        "aat:300006191"
    ]
},
  "bbox": [],
  "geometry": {"coordinates":[-79.7167,34.9333],"type":"Point"}
}