{
  "id": 2477540,
  "type": "Feature",
  "properties": {
    "tgn:hierarchy":[
        "tgn:2477540",
        "tgn:1000001",
        "tgn:7012149",
        "tgn:2001911",
        "tgn:7007825",
        "tgn:7029392"
    ],
    "tgn:id":2477540,
    "tgn:name":"Lytle Creek",
    "tgn:placetype":[
        "aat:300008706"
    ]
},
  "bbox": [],
  "geometry": {"coordinates":[-86.3833,35.7167],"type":"Point"}
}