{
  "id": 1079647,
  "type": "Feature",
  "properties": {
    "tgn:hierarchy":[
        "tgn:1079647",
        "tgn:1000861",
        "tgn:1000004",
        "tgn:1000119",
        "tgn:7029392"
    ],
    "tgn:id":1079647,
    "tgn:name":"Yero\u1e96am",
    "tgn:placetype":[
        "aat:300008347"
    ]
},
  "bbox": [],
  "geometry": {"coordinates":[34.9167,30.9833],"type":"Point"}
}