<<<<<<< HEAD
{
  "id": 2151815,
  "type": "Feature",
  "properties": {
    "tgn:hierarchy":[
        "tgn:2151815",
        "tgn:1000001",
        "tgn:7016172",
        "tgn:7012149",
        "tgn:2000128",
        "tgn:7029392"
    ],
    "tgn:id":2151815,
    "tgn:name":"Battle Springs",
    "tgn:placetype":[
        "aat:300008697"
    ]
},
  "bbox": [],
  "geometry": {"coordinates":[-93.7833,35.6],"type":"Point"}
}
=======
{"geometry":{"type":"Point","coordinates":[-93.783300,35.600000]},"type":"Feature","properties":{"hierarchy":["tgn:2151815","tgn:1000001","tgn:7016172","tgn:7012149","tgn:2000128","tgn:7029392"],"placetype":["aat:300008697"],"id":2151815,"name:xx":"Battle Springs"}}
>>>>>>> 03f74aca74312dbeaf24d7e61306dd6a786dc3d0
