{
  "id": 7210208,
  "type": "Feature",
  "properties": {
    "tgn:hierarchy":[
        "tgn:7210208",
        "tgn:7003692",
        "tgn:1000003",
        "tgn:7000084",
        "tgn:7029392"
    ],
    "tgn:id":7210208,
    "tgn:name":"Belzenhofen",
    "tgn:placetype":[
        "aat:300000206"
    ]
},
  "bbox": [],
  "geometry": {"coordinates":[9.566667,47.816667],"type":"Point"}
}