<<<<<<< HEAD
{
  "id": 2152954,
  "type": "Feature",
  "properties": {
    "tgn:hierarchy":[
        "tgn:2152954",
        "tgn:2124017",
        "tgn:7006450",
        "tgn:1000001",
        "tgn:7012149",
        "tgn:7029392"
    ],
    "tgn:id":2152954,
    "tgn:name":"Beach Lake",
    "tgn:placetype":[
        "aat:300008680"
    ]
},
  "bbox": [],
  "geometry": {"coordinates":[-149.55,61.4],"type":"Point"}
}
=======
{"geometry":{"type":"Point","coordinates":[-149.550000,61.400000]},"type":"Feature","properties":{"hierarchy":["tgn:2152954","tgn:2124017","tgn:7006450","tgn:1000001","tgn:7012149","tgn:7029392"],"placetype":["aat:300008680"],"id":2152954,"name:xx":"Beach Lake"}}
>>>>>>> 03f74aca74312dbeaf24d7e61306dd6a786dc3d0
