{
  "id": 2614479,
  "type": "Feature",
  "properties": {
    "tgn:hierarchy":[
        "tgn:2614479",
        "tgn:1000001",
        "tgn:7006451",
        "tgn:7012149",
        "tgn:7029392"
    ],
    "tgn:id":2614479,
    "tgn:name":"Reiley Creek",
    "tgn:placetype":[
        "aat:300008706"
    ]
},
  "bbox": [],
  "geometry": {"coordinates":[-110.0667,32.3667],"type":"Point"}
}