{
  "id": 2525564,
  "type": "Feature",
  "properties": {
    "tgn:hierarchy":[
        "tgn:2525564",
        "tgn:1000001",
        "tgn:1002242",
        "tgn:7012149",
        "tgn:7007252",
        "tgn:7029392"
    ],
    "tgn:id":2525564,
    "tgn:name":"Mortgage Trust Ditch",
    "tgn:placetype":[
        "aat:300006075"
    ]
},
  "bbox": [],
  "geometry": {"coordinates":[-86.5333,40.7833],"type":"Point"}
}