{
  "id": 2547729,
  "type": "Feature",
  "properties": {
    "tgn:hierarchy":[
        "tgn:2547729",
        "tgn:1000001",
        "tgn:7006451",
        "tgn:7012149",
        "tgn:2000103",
        "tgn:7029392"
    ],
    "tgn:id":2547729,
    "tgn:name":"North Fork Walnut Creek",
    "tgn:placetype":[
        "aat:300008706"
    ]
},
  "bbox": [],
  "geometry": {"coordinates":[-112.95,34.9333],"type":"Point"}
}