{
  "id": 2393575,
  "type": "Feature",
  "properties": {
    "tgn:hierarchy":[
        "tgn:2393575",
        "tgn:2001626",
        "tgn:1000001",
        "tgn:7012149",
        "tgn:7007707",
        "tgn:7029392"
    ],
    "tgn:id":2393575,
    "tgn:name":"Hog Creek",
    "tgn:placetype":[
        "aat:300008706"
    ]
},
  "bbox": [],
  "geometry": {"coordinates":[-100.1167,36.8167],"type":"Point"}
}