{
  "id": 2299333,
  "type": "Feature",
  "properties": {
    "tgn:hierarchy":[
        "tgn:2299333",
        "tgn:2000946",
        "tgn:1000001",
        "tgn:7012149",
        "tgn:7007520",
        "tgn:7029392"
    ],
    "tgn:id":2299333,
    "tgn:name":"Duck Lake",
    "tgn:placetype":[
        "aat:300008680"
    ]
},
  "bbox": [],
  "geometry": {"coordinates":[-83.7167,44.0333],"type":"Point"}
}