{
  "id": 7309304,
  "type": "Feature",
  "properties": {
    "tgn:hierarchy":[
        "tgn:7309304",
        "tgn:1001623",
        "tgn:1000049",
        "tgn:1000002",
        "tgn:7029392"
    ],
    "tgn:id":7309304,
    "tgn:name":"Luis Soto",
    "tgn:placetype":[
        "aat:300008347"
    ]
},
  "bbox": [],
  "geometry": {"coordinates":[-72.783333,-46.85],"type":"Point"}
}