{
  "id": 7095673,
  "type": "Feature",
  "properties": {
    "tgn:hierarchy":[
        "tgn:7095673",
        "tgn:1000003",
        "tgn:7000094",
        "tgn:7000084",
        "tgn:7029392"
    ],
    "tgn:id":7095673,
    "tgn:name":"Schwiggerow",
    "tgn:placetype":[
        "aat:300008347"
    ]
},
  "bbox": [],
  "geometry": {"coordinates":[12.316667,53.733333],"type":"Point"}
}