{
  "id": 2663431,
  "type": "Feature",
  "properties": {
    "tgn:hierarchy":[
        "tgn:2663431",
        "tgn:1000001",
        "tgn:7012149",
        "tgn:2001437",
        "tgn:7007566",
        "tgn:7029392"
    ],
    "tgn:id":2663431,
    "tgn:name":"Silver Dale Spring",
    "tgn:placetype":[
        "aat:300008697"
    ]
},
  "bbox": [],
  "geometry": {"coordinates":[-108.4667,32.7167],"type":"Point"}
}