{
  "id": 2592923,
  "type": "Feature",
  "properties": {
    "tgn:hierarchy":[
        "tgn:2592923",
        "tgn:1000001",
        "tgn:7014090",
        "tgn:7012149",
        "tgn:7007565",
        "tgn:7029392"
    ],
    "tgn:id":2592923,
    "tgn:name":"Poplar Brook",
    "tgn:placetype":[
        "aat:300008699"
    ]
},
  "bbox": [],
  "geometry": {"coordinates":[-74.05,40.25],"type":"Point"}
}