{
  "id": 2043019,
  "type": "Feature",
  "properties": {
    "tgn:hierarchy":[
        "tgn:2043019",
        "tgn:1000001",
        "tgn:7020676",
        "tgn:7012149",
        "tgn:7007256",
        "tgn:7029392"
    ],
    "tgn:id":2043019,
    "tgn:name":"Holly Beach",
    "tgn:placetype":[
        "aat:300008347"
    ]
},
  "bbox": [],
  "geometry": {"coordinates":[-93.45,29.7667],"type":"Point"}
}