{
  "id": 7346491,
  "type": "Feature",
  "properties": {
    "tgn:hierarchy":[
        "tgn:7346491",
        "tgn:7008912",
        "tgn:7030216",
        "tgn:1000003",
        "tgn:1000095",
        "tgn:7029392"
    ],
    "tgn:id":7346491,
    "tgn:name":"Bellpuig",
    "tgn:placetype":[
        "aat:300008347"
    ]
},
  "bbox": [],
  "geometry": {"coordinates":[1.011437,41.625954],"type":"Point"}
}