{
  "id": 7583380,
  "type": "Feature",
  "properties": {
    "tgn:hierarchy":[
        "tgn:7583380",
        "tgn:1000004",
        "tgn:7000198",
        "tgn:7016883",
        "tgn:7029392"
    ],
    "tgn:id":7583380,
    "tgn:name:en":"Pati\u0101la Branch First Feeder",
    "tgn:placetype":[
        "aat:300006075"
    ]
},
  "bbox": [],
  "geometry": {"coordinates":[76.068776,30.576496],"type":"Point"}
}