{
  "id": 7168554,
  "type": "Feature",
  "properties": {
    "tgn:hierarchy":[
        "tgn:7168554",
        "tgn:7003669",
        "tgn:1000003",
        "tgn:7000084",
        "tgn:7029392"
    ],
    "tgn:id":7168554,
    "tgn:name":"Harsdorf",
    "tgn:placetype":[
        "aat:300008347"
    ]
},
  "bbox": [],
  "geometry": {"coordinates":[11.566667,50.033333],"type":"Point"}
}