<<<<<<< HEAD
{
  "id": 2408417,
  "type": "Feature",
  "properties": {
    "tgn:hierarchy":[
        "tgn:2408417",
        "tgn:1000001",
        "tgn:7012149",
        "tgn:1002392",
        "tgn:7007157",
        "tgn:7029392"
    ],
    "tgn:id":2408417,
    "tgn:name":"Hutchings, Mount",
    "tgn:placetype":[
        "aat:300008798"
    ]
},
  "bbox": [],
  "geometry": {"coordinates":[-118.6,36.8167],"type":"Point"}
}
=======
{"geometry":{"type":"Point","coordinates":[-118.600000,36.816700]},"type":"Feature","properties":{"hierarchy":["tgn:2408417","tgn:1000001","tgn:7012149","tgn:1002392","tgn:7007157","tgn:7029392"],"placetype":["aat:300008798"],"id":2408417,"name:xx":"Hutchings, Mount"}}
>>>>>>> 03f74aca74312dbeaf24d7e61306dd6a786dc3d0
