{
  "id": 7524778,
  "type": "Feature",
  "properties": {
    "tgn:hierarchy":[
        "tgn:7524778",
        "tgn:7001242",
        "tgn:1001059",
        "tgn:7016833",
        "tgn:7029392"
    ],
    "tgn:id":7524778,
    "tgn:name:en":"Al Matwah",
    "tgn:placetype":[
        "aat:300008347"
    ]
},
  "bbox": [],
  "geometry": {"coordinates":[31.452722,30.954247],"type":"Point"}
}