{
  "id": 2078293,
  "type": "Feature",
  "properties": {
    "tgn:hierarchy":[
        "tgn:2078293",
        "tgn:1000001",
        "tgn:1002307",
        "tgn:7012149",
        "tgn:7007706",
        "tgn:7029392"
    ],
    "tgn:id":2078293,
    "tgn:name":"Auburn Center",
    "tgn:placetype":[
        "aat:300008347",
        "aat:300387210"
    ]
},
  "bbox": [],
  "geometry": {"coordinates":[-82.7333,40.9333],"type":"Point"}
}