{
  "id": 2537775,
  "type": "Feature",
  "properties": {
    "tgn:hierarchy":[
        "tgn:2537775",
        "tgn:1000001",
        "tgn:7012149",
        "tgn:1002942",
        "tgn:7007920",
        "tgn:7029392"
    ],
    "tgn:id":2537775,
    "tgn:name":"Nelda Lake",
    "tgn:placetype":[
        "aat:300006191"
    ]
},
  "bbox": [],
  "geometry": {"coordinates":[-122.5333,46.8167],"type":"Point"}
}