{
  "id": 2450878,
  "type": "Feature",
  "properties": {
    "tgn:hierarchy":[
        "tgn:2450878",
        "tgn:1000001",
        "tgn:7012149",
        "tgn:2001516",
        "tgn:7007709",
        "tgn:7029392"
    ],
    "tgn:id":2450878,
    "tgn:name":"Lisenbee Branch",
    "tgn:placetype":[
        "aat:300008699"
    ]
},
  "bbox": [],
  "geometry": {"coordinates":[-82.6333,35.9667],"type":"Point"}
}