{
  "id": 2228175,
  "type": "Feature",
  "properties": {
    "tgn:hierarchy":[
        "tgn:2228175",
        "tgn:1000001",
        "tgn:2001179",
        "tgn:7012149",
        "tgn:7007523",
        "tgn:7029392"
    ],
    "tgn:id":2228175,
    "tgn:name":"Cedar Cliffs",
    "tgn:placetype":[
        "aat:300008347"
    ]
},
  "bbox": [],
  "geometry": {"coordinates":[-89.65,37.2333],"type":"Point"}
}