{
  "id": 2607526,
  "type": "Feature",
  "properties": {
    "tgn:hierarchy":[
        "tgn:2607526",
        "tgn:1000001",
        "tgn:2001597",
        "tgn:7012149",
        "tgn:7007705",
        "tgn:7029392"
    ],
    "tgn:id":2607526,
    "tgn:name":"Ransom City",
    "tgn:placetype":[
        "aat:300008347"
    ]
},
  "bbox": [],
  "geometry": {"coordinates":[-97.3833,46.0833],"type":"Point"}
}