{
  "id": 7063513,
  "type": "Feature",
  "properties": {
    "tgn:hierarchy":[
        "tgn:7063513",
        "tgn:7003669",
        "tgn:1000003",
        "tgn:7000084",
        "tgn:7029392"
    ],
    "tgn:id":7063513,
    "tgn:name":"Aunham",
    "tgn:placetype":[
        "aat:300008347"
    ]
},
  "bbox": [],
  "geometry": {"coordinates":[13.083333,48.45],"type":"Point"}
}