{
  "id": 7097496,
  "type": "Feature",
  "properties": {
    "tgn:hierarchy":[
        "tgn:7097496",
        "tgn:7003669",
        "tgn:1000003",
        "tgn:7000084",
        "tgn:7029392"
    ],
    "tgn:id":7097496,
    "tgn:name":"Sorig",
    "tgn:placetype":[
        "aat:300008863"
    ]
},
  "bbox": [],
  "geometry": {"coordinates":[10.616667,48.683333],"type":"Point"}
}