{
  "id": 7299122,
  "type": "Feature",
  "properties": {
    "tgn:hierarchy":[
        "tgn:7299122",
        "tgn:7002816",
        "tgn:1001647",
        "tgn:1000003",
        "tgn:1000095",
        "tgn:7029392"
    ],
    "tgn:id":7299122,
    "tgn:name":"Toledano, Puerto del",
    "tgn:placetype":[
        "aat:300259572"
    ]
},
  "bbox": [],
  "geometry": {"coordinates":[-3.983333,38.45],"type":"Point"}
}