<<<<<<< HEAD
{
  "id": 2150182,
  "type": "Feature",
  "properties": {
    "tgn:hierarchy":[
        "tgn:2150182",
        "tgn:1000001",
        "tgn:7012149",
        "tgn:7007256",
        "tgn:7029392"
    ],
    "tgn:id":2150182,
    "tgn:name":"Barwick, Bayou",
    "tgn:placetype":[
        "aat:300008699"
    ]
},
  "bbox": [],
  "geometry": {"coordinates":[-92.5333,30.5],"type":"Point"}
}
=======
{"geometry":{"type":"Point","coordinates":[-92.533300,30.500000]},"type":"Feature","properties":{"hierarchy":["tgn:2150182","tgn:1000001","tgn:7012149","tgn:7007256","tgn:7029392"],"placetype":["aat:300008699"],"id":2150182,"name:xx":"Barwick, Bayou"}}
>>>>>>> 03f74aca74312dbeaf24d7e61306dd6a786dc3d0
