{
  "id": 2627175,
  "type": "Feature",
  "properties": {
    "tgn:hierarchy":[
        "tgn:2627175",
        "tgn:1000001",
        "tgn:7012149",
        "tgn:1002898",
        "tgn:7007826",
        "tgn:7029392"
    ],
    "tgn:id":2627175,
    "tgn:name":"Roddy Branch",
    "tgn:placetype":[
        "aat:300008699"
    ]
},
  "bbox": [],
  "geometry": {"coordinates":[-95.2667,32.2167],"type":"Point"}
}