{
  "id": 2146478,
  "type": "Feature",
  "properties": {
    "tgn:hierarchy":[
        "tgn:2146478",
        "tgn:1000001",
        "tgn:1002714",
        "tgn:7012149",
        "tgn:7007159",
        "tgn:7029392"
    ],
    "tgn:id":2146478,
    "tgn:name":"Baltic Reservoir",
    "tgn:placetype":[
        "aat:300006191"
    ]
},
  "bbox": [],
  "geometry": {"coordinates":[-72.0667,41.6167],"type":"Point"}
}