{
  "id": 2356008,
  "type": "Feature",
  "properties": {
    "tgn:hierarchy":[
        "tgn:2356008",
        "tgn:1000001",
        "tgn:7012149",
        "tgn:2000543",
        "tgn:7007252",
        "tgn:7029392"
    ],
    "tgn:id":2356008,
    "tgn:name":"Goose Pond",
    "tgn:placetype":[
        "aat:300008680"
    ]
},
  "bbox": [],
  "geometry": {"coordinates":[-87.9167,38.2333],"type":"Point"}
}