{
  "id": 2014374,
  "type": "Feature",
  "properties": {
    "tgn:hierarchy":[
        "tgn:2014374",
        "tgn:1000001",
        "tgn:7012149",
        "tgn:7007157",
        "tgn:1002608",
        "tgn:7029392"
    ],
    "tgn:id":2014374,
    "tgn:name":"South San Gabriel",
    "tgn:placetype":[
        "aat:300008347"
    ]
},
  "bbox": [],
  "geometry": {"coordinates":[-118.0833,34.05],"type":"Point"}
}