<<<<<<< HEAD
{
  "id": 7365055,
  "type": "Feature",
  "properties": {
    "tgn:hierarchy":[
        "tgn:7365055",
        "tgn:1001836",
        "tgn:1000001",
        "tgn:7005560",
        "tgn:7029392"
    ],
    "tgn:id":7365055,
    "tgn:name":"El Sauzal",
    "tgn:placetype":[
        "aat:300008347"
    ]
},
  "bbox": [],
  "geometry": {"coordinates":[-112.4,27.133333],"type":"Point"}
}
=======
{"geometry":{"type":"Point","coordinates":[-112.400000,27.133333]},"type":"Feature","properties":{"hierarchy":["tgn:7365055","tgn:1001836","tgn:1000001","tgn:7005560","tgn:7029392"],"placetype":["aat:300008347"],"id":7365055,"name:xx":"El Sauzal"}}
>>>>>>> 03f74aca74312dbeaf24d7e61306dd6a786dc3d0
