{
  "id": 2472448,
  "type": "Feature",
  "properties": {
    "tgn:hierarchy":[
        "tgn:2472448",
        "tgn:1000001",
        "tgn:7012149",
        "tgn:1002924",
        "tgn:7007568",
        "tgn:7029392"
    ],
    "tgn:id":2472448,
    "tgn:name":"Louse Point",
    "tgn:placetype":[
        "aat:300008850"
    ]
},
  "bbox": [],
  "geometry": {"coordinates":[-72.1333,41.0167],"type":"Point"}
}