{
  "id": 2029882,
  "type": "Feature",
  "properties": {
    "tgn:hierarchy":[
        "tgn:2029882",
        "tgn:1000001",
        "tgn:7012149",
        "tgn:1002866",
        "tgn:7007251",
        "tgn:7029392"
    ],
    "tgn:id":2029882,
    "tgn:name":"Riverton",
    "tgn:placetype":[
        "aat:300008347"
    ]
},
  "bbox": [],
  "geometry": {"coordinates":[-89.5333,39.8333],"type":"Point"}
}