{
  "id": 2213375,
  "type": "Feature",
  "properties": {
    "tgn:hierarchy":[
        "tgn:2213375",
        "tgn:1000001",
        "tgn:7012149",
        "tgn:2001882",
        "tgn:7007825",
        "tgn:7029392"
    ],
    "tgn:id":2213375,
    "tgn:name":"Cabin Hill",
    "tgn:placetype":[
        "aat:300008798"
    ]
},
  "bbox": [],
  "geometry": {"coordinates":[-81.7167,36.5667],"type":"Point"}
}