{
  "id": 2369200,
  "type": "Feature",
  "properties": {
    "tgn:hierarchy":[
        "tgn:2369200",
        "tgn:1000001",
        "tgn:2000859",
        "tgn:7012149",
        "tgn:7007256",
        "tgn:7029392"
    ],
    "tgn:id":2369200,
    "tgn:name":"Gum Slough",
    "tgn:placetype":[
        "aat:300008699"
    ]
},
  "bbox": [],
  "geometry": {"coordinates":[-93.4167,30.65],"type":"Point"}
}