{
  "id": 7079394,
  "type": "Feature",
  "properties": {
    "tgn:hierarchy":[
        "tgn:7079394",
        "tgn:1000003",
        "tgn:7003673",
        "tgn:7000084",
        "tgn:7029392"
    ],
    "tgn:id":7079394,
    "tgn:name":"Wulms-Berg",
    "tgn:placetype":[
        "aat:300008777"
    ]
},
  "bbox": [],
  "geometry": {"coordinates":[9.883333,53.466667],"type":"Point"}
}