{
  "id": 2164804,
  "type": "Feature",
  "properties": {
    "tgn:hierarchy":[
        "tgn:2164804",
        "tgn:1000001",
        "tgn:2001095",
        "tgn:7012149",
        "tgn:7007522",
        "tgn:7029392"
    ],
    "tgn:id":2164804,
    "tgn:name":"Besa Chitto Creek",
    "tgn:placetype":[
        "aat:300008706"
    ]
},
  "bbox": [],
  "geometry": {"coordinates":[-89.1667,33.3667],"type":"Point"}
}