{
  "id": 1110793,
  "type": "Feature",
  "properties": {
    "tgn:hierarchy":[
        "tgn:1110793",
        "tgn:7006260",
        "tgn:7002454",
        "tgn:1000047",
        "tgn:1000002",
        "tgn:7029392"
    ],
    "tgn:id":1110793,
    "tgn:name":"Azul, Serra",
    "tgn:placetype":[
        "aat:300386856"
    ]
},
  "bbox": [],
  "geometry": {"coordinates":[-54.8333,-14.8333],"type":"Point"}
}