{
  "id": 2300859,
  "type": "Feature",
  "properties": {
    "tgn:hierarchy":[
        "tgn:2300859",
        "tgn:1000001",
        "tgn:7012149",
        "tgn:2001283",
        "tgn:7007524",
        "tgn:7029392"
    ],
    "tgn:id":2300859,
    "tgn:name":"Duncan Lake",
    "tgn:placetype":[
        "aat:300008680"
    ]
},
  "bbox": [],
  "geometry": {"coordinates":[-113.9333,47.3667],"type":"Point"}
}