{
  "id": 7013839,
  "type": "Feature",
  "properties": {
    "tgn:hierarchy":[
        "tgn:7013839",
        "tgn:7021537",
        "tgn:1000001",
        "tgn:7021534",
        "tgn:7012149",
        "tgn:1002676",
        "tgn:7007240",
        "tgn:7029392"
    ],
    "tgn:id":7013839,
    "tgn:name":"Key West",
    "tgn:placetype":[
        "aat:300008347",
        "aat:300008416",
        "aat:300008389",
        "aat:300000467",
        "aat:300387512",
        "aat:300000547"
    ]
},
  "bbox": [],
  "geometry": {"coordinates":[-81.7667,24.55],"type":"Point"}
}