{
  "id": 7593266,
  "type": "Feature",
  "properties": {
    "tgn:hierarchy":[
        "tgn:7593266",
        "tgn:1001612",
        "tgn:7002559",
        "tgn:1000051",
        "tgn:1000002",
        "tgn:7029392"
    ],
    "tgn:id":7593266,
    "tgn:name":"Yantzaza",
    "tgn:placetype":[
        "aat:300008347"
    ]
},
  "bbox": [],
  "geometry": {"coordinates":[-78.76,-3.832],"type":"Point"}
}