{
  "id": 2102476,
  "type": "Feature",
  "properties": {
    "tgn:hierarchy":[
        "tgn:2102476",
        "tgn:1000001",
        "tgn:7012149",
        "tgn:2001951",
        "tgn:7007826",
        "tgn:7029392"
    ],
    "tgn:id":2102476,
    "tgn:name":"Atwell",
    "tgn:placetype":[
        "aat:300008347",
        "aat:300387210"
    ]
},
  "bbox": [],
  "geometry": {"coordinates":[-99.1333,32.25],"type":"Point"}
}