{
  "id": 7447255,
  "type": "Feature",
  "properties": {
    "tgn:hierarchy":[
        "tgn:7447255",
        "tgn:7002444",
        "tgn:1000003",
        "tgn:7008072",
        "tgn:7008591",
        "tgn:7029392"
    ],
    "tgn:id":7447255,
    "tgn:name:en":"Stobs Station",
    "tgn:placetype":[
        "aat:300007783"
    ]
},
  "bbox": [],
  "geometry": {"coordinates":[-2.783333,55.366667],"type":"Point"}
}