{
  "id": 7516834,
  "type": "Feature",
  "properties": {
    "tgn:hierarchy":[
        "tgn:7516834",
        "tgn:1008380",
        "tgn:7520093",
        "tgn:1000226",
        "tgn:1000006",
        "tgn:7029392"
    ],
    "tgn:id":7516834,
    "tgn:name:en":"Koukoupo Stream",
    "tgn:placetype":[
        "aat:300008699"
    ]
},
  "bbox": [],
  "geometry": {"coordinates":[175.433333,-39.65],"type":"Point"}
}