{
  "id": 2663595,
  "type": "Feature",
  "properties": {
    "tgn:hierarchy":[
        "tgn:2663595",
        "tgn:1000001",
        "tgn:7012149",
        "tgn:7007157",
        "tgn:1002857",
        "tgn:7029392"
    ],
    "tgn:id":2663595,
    "tgn:name":"Silver King Mine",
    "tgn:placetype":[
        "aat:300000390"
    ]
},
  "bbox": [],
  "geometry": {"coordinates":[-115.4833,34.9833],"type":"Point"}
}