{
  "id": 7216703,
  "type": "Feature",
  "properties": {
    "tgn:hierarchy":[
        "tgn:7216703",
        "tgn:7000096",
        "tgn:1000003",
        "tgn:7000084",
        "tgn:7029392"
    ],
    "tgn:id":7216703,
    "tgn:name":"Alsenhof",
    "tgn:placetype":[
        "aat:300000206"
    ]
},
  "bbox": [],
  "geometry": {"coordinates":[13.45,53.083333],"type":"Point"}
}