{
  "id": 2717799,
  "type": "Feature",
  "properties": {
    "tgn:hierarchy":[
        "tgn:2717799",
        "tgn:1000001",
        "tgn:7012149",
        "tgn:2000287",
        "tgn:7007240",
        "tgn:7029392"
    ],
    "tgn:id":2717799,
    "tgn:name":"Thomas Mill Island",
    "tgn:placetype":[
        "aat:300008791"
    ]
},
  "bbox": [],
  "geometry": {"coordinates":[-83.7667,30.0167],"type":"Point"}
}