{
  "id": 7300640,
  "type": "Feature",
  "properties": {
    "tgn:hierarchy":[
        "tgn:7300640",
        "tgn:7002824",
        "tgn:1000003",
        "tgn:7002786",
        "tgn:1000095",
        "tgn:7029392"
    ],
    "tgn:id":7300640,
    "tgn:name":"Nos",
    "tgn:placetype":[
        "aat:300008347"
    ]
},
  "bbox": [],
  "geometry": {"coordinates":[-8.333333,43.316667],"type":"Point"}
}