{
  "id": 7002211,
  "type": "Feature",
  "properties": {
    "tgn:hierarchy":[
        "tgn:7002211",
        "tgn:1000004",
        "tgn:7029392"
    ],
    "tgn:id":7002211,
    "tgn:name":"Makran Coast",
    "tgn:placetype":[
        "aat:300008734"
    ]
},
  "bbox": [],
  "geometry": {"coordinates":[60.0833,25.3333],"type":"Point"}
}