{
  "id": 7391535,
  "type": "Feature",
  "properties": {
    "tgn:hierarchy":[
        "tgn:7391535",
        "tgn:1001853",
        "tgn:1000001",
        "tgn:7005560",
        "tgn:7029392"
    ],
    "tgn:id":7391535,
    "tgn:name":"Rancho El Azutejo",
    "tgn:placetype":[
        "aat:300008347"
    ]
},
  "bbox": [],
  "geometry": {"coordinates":[-100.366667,27.983333],"type":"Point"}
}