<<<<<<< HEAD
{
  "id": 7479765,
  "type": "Feature",
  "properties": {
    "tgn:hierarchy":[
        "tgn:7479765",
        "tgn:1000004",
        "tgn:7490934",
        "tgn:1000141",
        "tgn:7029392"
    ],
    "tgn:id":7479765,
    "tgn:name":"Bitan Guoxiao",
    "tgn:placetype":[
        "aat:300006495"
    ]
},
  "bbox": [],
  "geometry": {"coordinates":[120.300278,23.386667],"type":"Point"}
}
=======
{"geometry":{"type":"Point","coordinates":[120.300278,23.386667]},"type":"Feature","properties":{"hierarchy":["tgn:7479765","tgn:1000004","tgn:7490934","tgn:1000141","tgn:7029392"],"placetype":["aat:300006495"],"id":7479765,"name:xx":"Bitan Guoxiao"}}
>>>>>>> 03f74aca74312dbeaf24d7e61306dd6a786dc3d0
