{
  "id": 7479765,
  "type": "Feature",
  "properties": {
    "tgn:hierarchy":[
        "tgn:7479765",
        "tgn:1000004",
        "tgn:7490934",
        "tgn:1000141",
        "tgn:7029392"
    ],
    "tgn:id":7479765,
    "tgn:name":"Bitan Guoxiao",
    "tgn:placetype":[
        "aat:300006495"
    ]
},
  "bbox": [],
  "geometry": {"coordinates":[120.300278,23.386667],"type":"Point"}
}