{
  "id": 7224682,
  "type": "Feature",
  "properties": {
    "tgn:hierarchy":[
        "tgn:7224682",
        "tgn:7002680",
        "tgn:7001395",
        "tgn:1000003",
        "tgn:1000074",
        "tgn:7029392"
    ],
    "tgn:id":7224682,
    "tgn:name":"Strongila\u00edika",
    "tgn:placetype":[
        "aat:300008347"
    ]
},
  "bbox": [],
  "geometry": {"coordinates":[21.366667,38.683333],"type":"Point"}
}