<<<<<<< HEAD
{
  "id": 7378782,
  "type": "Feature",
  "properties": {
    "tgn:hierarchy":[
        "tgn:7378782",
        "tgn:1000001",
        "tgn:7005589",
        "tgn:7005560",
        "tgn:7029392"
    ],
    "tgn:id":7378782,
    "tgn:name":"Rancho Los Cavazos",
    "tgn:placetype":[
        "aat:300000241"
    ]
},
  "bbox": [],
  "geometry": {"coordinates":[-99.916667,26.516667],"type":"Point"}
}
=======
{"geometry":{"type":"Point","coordinates":[-99.916667,26.516667]},"type":"Feature","properties":{"hierarchy":["tgn:7378782","tgn:1000001","tgn:7005589","tgn:7005560","tgn:7029392"],"placetype":["aat:300000241"],"id":7378782,"name:xx":"Rancho Los Cavazos"}}
>>>>>>> 03f74aca74312dbeaf24d7e61306dd6a786dc3d0
