<<<<<<< HEAD
{
  "id": 7352709,
  "type": "Feature",
  "properties": {
    "tgn:hierarchy":[
        "tgn:7352709",
        "tgn:7005581",
        "tgn:1000001",
        "tgn:7005560",
        "tgn:7029392"
    ],
    "tgn:id":7352709,
    "tgn:name":"Rancho Basigochito",
    "tgn:placetype":[
        "aat:300000241"
    ]
},
  "bbox": [],
  "geometry": {"coordinates":[-107.533333,27.25],"type":"Point"}
}
=======
{"geometry":{"type":"Point","coordinates":[-107.533333,27.250000]},"type":"Feature","properties":{"hierarchy":["tgn:7352709","tgn:7005581","tgn:1000001","tgn:7005560","tgn:7029392"],"placetype":["aat:300000241"],"id":7352709,"name:xx":"Rancho Basigochito"}}
>>>>>>> 03f74aca74312dbeaf24d7e61306dd6a786dc3d0
