{
  "id": 2647267,
  "type": "Feature",
  "properties": {
    "tgn:hierarchy":[
        "tgn:2647267",
        "tgn:1000001",
        "tgn:7012149",
        "tgn:2000968",
        "tgn:7007520",
        "tgn:7029392"
    ],
    "tgn:id":2647267,
    "tgn:name":"Schlemmer Swamp",
    "tgn:placetype":[
        "aat:300008905"
    ]
},
  "bbox": [],
  "geometry": {"coordinates":[-85.0667,44.6833],"type":"Point"}
}