{
  "id": 2606724,
  "type": "Feature",
  "properties": {
    "tgn:hierarchy":[
        "tgn:2606724",
        "tgn:1000001",
        "tgn:7012149",
        "tgn:2001532",
        "tgn:7007709",
        "tgn:7029392"
    ],
    "tgn:id":2606724,
    "tgn:name":"Ramseur Lake",
    "tgn:placetype":[
        "aat:300006191"
    ]
},
  "bbox": [],
  "geometry": {"coordinates":[-79.65,35.7333],"type":"Point"}
}