<<<<<<< HEAD
{
  "id": 7115785,
  "type": "Feature",
  "properties": {
    "tgn:hierarchy":[
        "tgn:7115785",
        "tgn:1000003",
        "tgn:7003689",
        "tgn:7000084",
        "tgn:7029392"
    ],
    "tgn:id":7115785,
    "tgn:name":"Ohrdruf",
    "tgn:placetype":[
        "aat:300008347"
    ]
},
  "bbox": [],
  "geometry": {"coordinates":[10.816667,50.833333],"type":"Point"}
}
=======
{"geometry":{"type":"Point","coordinates":[10.816667,50.833333]},"type":"Feature","properties":{"hierarchy":["tgn:7115785","tgn:1000003","tgn:7003689","tgn:7000084","tgn:7029392"],"placetype":["aat:300008347"],"id":7115785,"name:xx":"Ohrdruf"}}
>>>>>>> 03f74aca74312dbeaf24d7e61306dd6a786dc3d0
