{
  "id": 7541230,
  "type": "Feature",
  "properties": {
    "tgn:hierarchy":[
        "tgn:7541230",
        "tgn:7001242",
        "tgn:7016833",
        "tgn:7001336",
        "tgn:7029392"
    ],
    "tgn:id":7541230,
    "tgn:name:en":"Thaalbi, Gebel",
    "tgn:placetype":[
        "aat:300008795"
    ]
},
  "bbox": [],
  "geometry": {"coordinates":[34.156758,28.421814],"type":"Point"}
}