{
  "id": 2142574,
  "type": "Feature",
  "properties": {
    "tgn:hierarchy":[
        "tgn:2142574",
        "tgn:1000001",
        "tgn:2001643",
        "tgn:7012149",
        "tgn:7007707",
        "tgn:7029392"
    ],
    "tgn:id":2142574,
    "tgn:name":"Bad Island",
    "tgn:placetype":[
        "aat:300008791"
    ]
},
  "bbox": [],
  "geometry": {"coordinates":[-94.8333,36.6167],"type":"Point"}
}