{
  "id": 7377911,
  "type": "Feature",
  "properties": {
    "tgn:hierarchy":[
        "tgn:7377911",
        "tgn:1001836",
        "tgn:1000001",
        "tgn:7005560",
        "tgn:7029392"
    ],
    "tgn:id":7377911,
    "tgn:name":"Las Casitas",
    "tgn:placetype":[
        "aat:300008347"
    ]
},
  "bbox": [],
  "geometry": {"coordinates":[-109.733333,23.266667],"type":"Point"}
}