{
  "id": 2735044,
  "type": "Feature",
  "properties": {
    "tgn:hierarchy":[
        "tgn:2735044",
        "tgn:1000001",
        "tgn:7012149",
        "tgn:1002441",
        "tgn:7007706",
        "tgn:7029392"
    ],
    "tgn:id":2735044,
    "tgn:name":"Twentyfirst Century Boat Harbor",
    "tgn:placetype":[
        "aat:300008678"
    ]
},
  "bbox": [],
  "geometry": {"coordinates":[-84.5833,39.0667],"type":"Point"}
}