{
  "id": 7585755,
  "type": "Feature",
  "properties": {
    "tgn:hierarchy":[
        "tgn:7585755",
        "tgn:1000004",
        "tgn:7000198",
        "tgn:7000799",
        "tgn:7029392"
    ],
    "tgn:id":7585755,
    "tgn:name:en":"R\u0101jba Kol",
    "tgn:placetype":[
        "aat:300008699"
    ]
},
  "bbox": [],
  "geometry": {"coordinates":[74.458333,34.333333],"type":"Point"}
}