{
  "id": 7263199,
  "type": "Feature",
  "properties": {
    "tgn:hierarchy":[
        "tgn:7263199",
        "tgn:7003616",
        "tgn:1000003",
        "tgn:7016845",
        "tgn:7029392"
    ],
    "tgn:id":7263199,
    "tgn:name:nl":"De Hammen",
    "tgn:placetype":[
        "aat:300387200"
    ]
},
  "bbox": [],
  "geometry": {"coordinates":[5.966667,53.183333],"type":"Point"}
}