<<<<<<< HEAD
{
  "id": 7245222,
  "type": "Feature",
  "properties": {
    "tgn:hierarchy":[
        "tgn:7245222",
        "tgn:7003460",
        "tgn:1000003",
        "tgn:1000063",
        "tgn:4012014",
        "tgn:7029392"
    ],
    "tgn:id":7245222,
    "tgn:name":"Abolens",
    "tgn:placetype":[
        "aat:300008347"
    ]
},
  "bbox": [],
  "geometry": {"coordinates":[5.150072,50.670835],"type":"Point"}
}
=======
{"geometry":{"type":"Point","coordinates":[5.150072,50.670835]},"type":"Feature","properties":{"hierarchy":["tgn:7245222","tgn:7003460","tgn:1000003","tgn:1000063","tgn:4012014","tgn:7029392"],"placetype":["aat:300008347"],"id":7245222,"name:xx":"Abolens"}}
>>>>>>> 03f74aca74312dbeaf24d7e61306dd6a786dc3d0
