{
  "id": 2540952,
  "type": "Feature",
  "properties": {
    "tgn:hierarchy":[
        "tgn:2540952",
        "tgn:1000001",
        "tgn:7012149",
        "tgn:7007826",
        "tgn:7029392"
    ],
    "tgn:id":2540952,
    "tgn:name":"Nichols Creek",
    "tgn:placetype":[
        "aat:300008706"
    ]
},
  "bbox": [],
  "geometry": {"coordinates":[-93.9833,30.6833],"type":"Point"}
}