<<<<<<< HEAD
{
  "id": 2707477,
  "type": "Feature",
  "properties": {
    "tgn:hierarchy":[
        "tgn:2707477",
        "tgn:1000001",
        "tgn:7012149",
        "tgn:7029392"
    ],
    "tgn:id":2707477,
    "tgn:name":"Sweet Springs Valley",
    "tgn:placetype":[
        "aat:300008761"
    ]
},
  "bbox": [],
  "geometry": {"coordinates":[-80.4,37.55],"type":"Point"}
}
=======
{"geometry":{"type":"Point","coordinates":[-80.400000,37.550000]},"type":"Feature","properties":{"hierarchy":["tgn:2707477","tgn:1000001","tgn:7012149","tgn:7029392"],"placetype":["aat:300008761"],"id":2707477,"name:xx":"Sweet Springs Valley"}}
>>>>>>> 03f74aca74312dbeaf24d7e61306dd6a786dc3d0
