{
  "id": 7144985,
  "type": "Feature",
  "properties": {
    "tgn:hierarchy":[
        "tgn:7144985",
        "tgn:1000003",
        "tgn:7003676",
        "tgn:7000084",
        "tgn:7029392"
    ],
    "tgn:id":7144985,
    "tgn:name":"K\u00f6therbusch",
    "tgn:placetype":[
        "aat:300055621"
    ]
},
  "bbox": [],
  "geometry": {"coordinates":[10.616667,52.566667],"type":"Point"}
}