{
  "id": 2066727,
  "type": "Feature",
  "properties": {
    "tgn:hierarchy":[
        "tgn:2066727",
        "tgn:1000001",
        "tgn:7012149",
        "tgn:2001442",
        "tgn:7007566",
        "tgn:7029392"
    ],
    "tgn:id":2066727,
    "tgn:name":"Bluewater",
    "tgn:placetype":[
        "aat:300008347",
        "aat:300387210"
    ]
},
  "bbox": [],
  "geometry": {"coordinates":[-105.1833,33.55],"type":"Point"}
}