{
  "id": 2377216,
  "type": "Feature",
  "properties": {
    "tgn:hierarchy":[
        "tgn:2377216",
        "tgn:1000001",
        "tgn:7012149",
        "tgn:2000997",
        "tgn:7007520",
        "tgn:7029392"
    ],
    "tgn:id":2377216,
    "tgn:name":"Harmon Lake",
    "tgn:placetype":[
        "aat:300008680"
    ]
},
  "bbox": [],
  "geometry": {"coordinates":[-83.3167,43.3833],"type":"Point"}
}