{
  "id": 2432108,
  "type": "Feature",
  "properties": {
    "tgn:hierarchy":[
        "tgn:2432108",
        "tgn:7023902",
        "tgn:1000001",
        "tgn:7012149",
        "tgn:7007249",
        "tgn:7029392"
    ],
    "tgn:id":2432108,
    "tgn:name":"Kawela Loa",
    "tgn:placetype":[
        "aat:300008798"
    ]
},
  "bbox": [],
  "geometry": {"coordinates":[-155.5167,20.05],"type":"Point"}
}