{
  "id": 2422324,
  "type": "Feature",
  "properties": {
    "tgn:hierarchy":[
        "tgn:2422324",
        "tgn:1000001",
        "tgn:7012149",
        "tgn:7007515",
        "tgn:7029392"
    ],
    "tgn:id":2422324,
    "tgn:name":"Jimmy Brook",
    "tgn:placetype":[
        "aat:300008699"
    ]
},
  "bbox": [],
  "geometry": {"coordinates":[-69.4667,45.0667],"type":"Point"}
}