<<<<<<< HEAD
{
  "id": 2250533,
  "type": "Feature",
  "properties": {
    "tgn:hierarchy":[
        "tgn:2250533",
        "tgn:2124017",
        "tgn:7006450",
        "tgn:1000001",
        "tgn:7012149",
        "tgn:7029392"
    ],
    "tgn:id":2250533,
    "tgn:name":"Colony Glacier",
    "tgn:placetype":[
        "aat:300008835"
    ]
},
  "bbox": [],
  "geometry": {"coordinates":[-148.5,61.2333],"type":"Point"}
}
=======
{"geometry":{"type":"Point","coordinates":[-148.500000,61.233300]},"type":"Feature","properties":{"hierarchy":["tgn:2250533","tgn:2124017","tgn:7006450","tgn:1000001","tgn:7012149","tgn:7029392"],"placetype":["aat:300008835"],"id":2250533,"name:xx":"Colony Glacier"}}
>>>>>>> 03f74aca74312dbeaf24d7e61306dd6a786dc3d0
