{
  "id": 2750656,
  "type": "Feature",
  "properties": {
    "tgn:hierarchy":[
        "tgn:2750656",
        "tgn:1000001",
        "tgn:7016172",
        "tgn:7012149",
        "tgn:2000139",
        "tgn:7029392"
    ],
    "tgn:id":2750656,
    "tgn:name":"Warbritton",
    "tgn:placetype":[
        "aat:300008347"
    ]
},
  "bbox": [],
  "geometry": {"coordinates":[-92.0167,34.2667],"type":"Point"}
}