{
  "id": 7482832,
  "type": "Feature",
  "properties": {
    "tgn:hierarchy":[
        "tgn:7482832",
        "tgn:1000004",
        "tgn:7001014",
        "tgn:1000141",
        "tgn:7029392"
    ],
    "tgn:id":7482832,
    "tgn:name":"Boziliao Paishuigou",
    "tgn:placetype":[
        "aat:300006075"
    ]
},
  "bbox": [],
  "geometry": {"coordinates":[120.145278,23.599722],"type":"Point"}
}