<<<<<<< HEAD
{
  "id": 7482832,
  "type": "Feature",
  "properties": {
    "tgn:hierarchy":[
        "tgn:7482832",
        "tgn:1000004",
        "tgn:7001014",
        "tgn:1000141",
        "tgn:7029392"
    ],
    "tgn:id":7482832,
    "tgn:name":"Boziliao Paishuigou",
    "tgn:placetype":[
        "aat:300006075"
    ]
},
  "bbox": [],
  "geometry": {"coordinates":[120.145278,23.599722],"type":"Point"}
}
=======
{"geometry":{"type":"Point","coordinates":[120.145278,23.599722]},"type":"Feature","properties":{"hierarchy":["tgn:7482832","tgn:1000004","tgn:7001014","tgn:1000141","tgn:7029392"],"placetype":["aat:300006075"],"id":7482832,"name:xx":"Boziliao Paishuigou"}}
>>>>>>> 03f74aca74312dbeaf24d7e61306dd6a786dc3d0
