{
  "id": 2452636,
  "type": "Feature",
  "properties": {
    "tgn:hierarchy":[
        "tgn:2452636",
        "tgn:1000001",
        "tgn:2001435",
        "tgn:7012149",
        "tgn:7007566",
        "tgn:7029392"
    ],
    "tgn:id":2452636,
    "tgn:name":"Little Buck",
    "tgn:placetype":[
        "aat:300000390"
    ]
},
  "bbox": [],
  "geometry": {"coordinates":[-106.55,32.45],"type":"Point"}
}