{
  "id": 2495172,
  "type": "Feature",
  "properties": {
    "tgn:hierarchy":[
        "tgn:2495172",
        "tgn:7002659",
        "tgn:1000001",
        "tgn:7012149",
        "tgn:2000021",
        "tgn:7029392"
    ],
    "tgn:id":2495172,
    "tgn:name":"Mary Ann Hollow",
    "tgn:placetype":[
        "aat:300008761"
    ]
},
  "bbox": [],
  "geometry": {"coordinates":[-87.0333,33.9167],"type":"Point"}
}