{
  "id": 2162635,
  "type": "Feature",
  "properties": {
    "tgn:hierarchy":[
        "tgn:2162635",
        "tgn:1000001",
        "tgn:7012149",
        "tgn:2002183",
        "tgn:7007919",
        "tgn:7029392"
    ],
    "tgn:id":2162635,
    "tgn:name":"Bench Mountain",
    "tgn:placetype":[
        "aat:300008798"
    ]
},
  "bbox": [],
  "geometry": {"coordinates":[-80.5833,36.9667],"type":"Point"}
}