{
  "id": 7224987,
  "type": "Feature",
  "properties": {
    "tgn:hierarchy":[
        "tgn:7224987",
        "tgn:7002707",
        "tgn:7002705",
        "tgn:1000003",
        "tgn:1000074",
        "tgn:7029392"
    ],
    "tgn:id":7224987,
    "tgn:name":"Strat\u00ednista",
    "tgn:placetype":[
        "aat:300008347"
    ]
},
  "bbox": [],
  "geometry": {"coordinates":[20.483056,39.855556],"type":"Point"}
}