{
  "id": 2036258,
  "type": "Feature",
  "properties": {
    "tgn:hierarchy":[
        "tgn:2036258",
        "tgn:1000001",
        "tgn:2000702",
        "tgn:7012149",
        "tgn:7007254",
        "tgn:7029392"
    ],
    "tgn:id":2036258,
    "tgn:name":"Delia",
    "tgn:placetype":[
        "aat:300008347"
    ]
},
  "bbox": [],
  "geometry": {"coordinates":[-95.9667,39.2333],"type":"Point"}
}