{
  "id": 7359614,
  "type": "Feature",
  "properties": {
    "tgn:hierarchy":[
        "tgn:7359614",
        "tgn:7005581",
        "tgn:1000001",
        "tgn:7005560",
        "tgn:7029392"
    ],
    "tgn:id":7359614,
    "tgn:name":"Cuatas, Lagunas",
    "tgn:placetype":[
        "aat:300008680"
    ]
},
  "bbox": [],
  "geometry": {"coordinates":[-106.666667,26.716667],"type":"Point"}
}