{
  "id": 7220085,
  "type": "Feature",
  "properties": {
    "tgn:hierarchy":[
        "tgn:7220085",
        "tgn:7002707",
        "tgn:7002705",
        "tgn:1000003",
        "tgn:1000074",
        "tgn:7029392"
    ],
    "tgn:id":7220085,
    "tgn:name":"Amp\u00e9lia",
    "tgn:placetype":[
        "aat:300008347"
    ]
},
  "bbox": [],
  "geometry": {"coordinates":[21.056389,39.763056],"type":"Point"}
}