{
  "id": 7329286,
  "type": "Feature",
  "properties": {
    "tgn:hierarchy":[
        "tgn:7329286",
        "tgn:7002806",
        "tgn:7001158",
        "tgn:1000003",
        "tgn:1000095",
        "tgn:7029392"
    ],
    "tgn:id":7329286,
    "tgn:name":"Poveda",
    "tgn:placetype":[
        "aat:300008347"
    ]
},
  "bbox": [],
  "geometry": {"coordinates":[-5.083333,40.566667],"type":"Point"}
}