{
  "id": 2450479,
  "type": "Feature",
  "properties": {
    "tgn:hierarchy":[
        "tgn:2450479",
        "tgn:1000001",
        "tgn:7012149",
        "tgn:2000495",
        "tgn:7007250",
        "tgn:7029392"
    ],
    "tgn:id":2450479,
    "tgn:name":"Linson Creek",
    "tgn:placetype":[
        "aat:300008706"
    ]
},
  "bbox": [],
  "geometry": {"coordinates":[-116.65,44.2167],"type":"Point"}
}