{
  "id": 1115984,
  "type": "Feature",
  "properties": {
    "tgn:hierarchy":[
        "tgn:1115984",
        "tgn:7005685",
        "tgn:1000001",
        "tgn:7005734",
        "tgn:7029392"
    ],
    "tgn:id":1115984,
    "tgn:name":"Cormorant Lake",
    "tgn:placetype":[
        "aat:300008680"
    ]
},
  "bbox": [],
  "geometry": {"coordinates":[-100.75,54.25],"type":"Point"}
}