{
  "id": 1009655,
  "type": "Feature",
  "properties": {
    "tgn:hierarchy":[
        "tgn:1009655",
        "tgn:7005153",
        "tgn:1010312",
        "tgn:7005152",
        "tgn:1000002",
        "tgn:7029392"
    ],
    "tgn:id":1009655,
    "tgn:name":"Visokoi Island",
    "tgn:placetype":[
        "aat:300008791"
    ]
},
  "bbox": [],
  "geometry": {"coordinates":[-27.25,-56.7167],"type":"Point"}
}