{
  "id": 2613789,
  "type": "Feature",
  "properties": {
    "tgn:hierarchy":[
        "tgn:2613789",
        "tgn:1000001",
        "tgn:7012149",
        "tgn:2000291",
        "tgn:7007240",
        "tgn:7029392"
    ],
    "tgn:id":2613789,
    "tgn:name":"Reedy Creek",
    "tgn:placetype":[
        "aat:300008706"
    ]
},
  "bbox": [],
  "geometry": {"coordinates":[-85.5667,30.5833],"type":"Point"}
}