{
  "id": 7256964,
  "type": "Feature",
  "properties": {
    "tgn:hierarchy":[
        "tgn:7256964",
        "tgn:1000003",
        "tgn:7006951",
        "tgn:7016845",
        "tgn:7029392"
    ],
    "tgn:id":7256964,
    "tgn:name:nl":"Binnen Breesem",
    "tgn:placetype":[
        "aat:300132350"
    ]
},
  "bbox": [],
  "geometry": {"coordinates":[5.033333,53.116667],"type":"Point"}
}