{
  "id": 7437678,
  "type": "Feature",
  "properties": {
    "tgn:hierarchy":[
        "tgn:7437678",
        "tgn:1001836",
        "tgn:1000001",
        "tgn:7005560",
        "tgn:7029392"
    ],
    "tgn:id":7437678,
    "tgn:name":"Tintorera, Punta",
    "tgn:placetype":[
        "aat:300386846"
    ]
},
  "bbox": [],
  "geometry": {"coordinates":[-111.166667,26.066667],"type":"Point"}
}