{
  "id": 2463842,
  "type": "Feature",
  "properties": {
    "tgn:hierarchy":[
        "tgn:2463842",
        "tgn:1000001",
        "tgn:7012149",
        "tgn:7007712",
        "tgn:7029392"
    ],
    "tgn:id":2463842,
    "tgn:name":"Lockhart Lower Shoals",
    "tgn:placetype":[
        "aat:300132348"
    ]
},
  "bbox": [],
  "geometry": {"coordinates":[-81.45,34.75],"type":"Point"}
}