{
  "id": 2212727,
  "type": "Feature",
  "properties": {
    "tgn:hierarchy":[
        "tgn:2212727",
        "tgn:1000001",
        "tgn:7012149",
        "tgn:2000488",
        "tgn:7007250",
        "tgn:7029392"
    ],
    "tgn:id":2212727,
    "tgn:name":"C C C Spring",
    "tgn:placetype":[
        "aat:300008697"
    ]
},
  "bbox": [],
  "geometry": {"coordinates":[-116.95,42.4333],"type":"Point"}
}