{
  "id": 7510094,
  "type": "Feature",
  "properties": {
    "tgn:hierarchy":[
        "tgn:7510094",
        "tgn:1009227",
        "tgn:1000226",
        "tgn:7018437",
        "tgn:1000006",
        "tgn:7029392"
    ],
    "tgn:id":7510094,
    "tgn:name:en":"Stewart Pass",
    "tgn:placetype":[
        "aat:300259572"
    ]
},
  "bbox": [],
  "geometry": {"coordinates":[169.016667,-44.116667],"type":"Point"}
}