{
  "id": 2392493,
  "type": "Feature",
  "properties": {
    "tgn:hierarchy":[
        "tgn:2392493",
        "tgn:1000001",
        "tgn:2001417",
        "tgn:7012149",
        "tgn:7007526",
        "tgn:7029392"
    ],
    "tgn:id":2392493,
    "tgn:name":"Hitt Mine",
    "tgn:placetype":[
        "aat:300000390"
    ]
},
  "bbox": [],
  "geometry": {"coordinates":[-117.9833,38.35],"type":"Point"}
}