<<<<<<< HEAD
{
  "id": 7021377,
  "type": "Feature",
  "properties": {
    "tgn:hierarchy":[
        "tgn:7021377",
        "tgn:1000001",
        "tgn:7012149",
        "tgn:2001067",
        "tgn:7007521",
        "tgn:7029392"
    ],
    "tgn:id":7021377,
    "tgn:name":"Pine Islands",
    "tgn:placetype":[
        "aat:300386853"
    ]
},
  "bbox": [],
  "geometry": {"coordinates":[-92.85,48.55],"type":"Point"}
}
=======
{"geometry":{"type":"Point","coordinates":[-92.850000,48.550000]},"type":"Feature","properties":{"hierarchy":["tgn:7021377","tgn:1000001","tgn:7012149","tgn:2001067","tgn:7007521","tgn:7029392"],"placetype":["aat:300386853"],"id":7021377,"name:xx":"Pine Islands"}}
>>>>>>> 03f74aca74312dbeaf24d7e61306dd6a786dc3d0
