{
  "id": 7021377,
  "type": "Feature",
  "properties": {
    "tgn:hierarchy":[
        "tgn:7021377",
        "tgn:1000001",
        "tgn:7012149",
        "tgn:2001067",
        "tgn:7007521",
        "tgn:7029392"
    ],
    "tgn:id":7021377,
    "tgn:name":"Pine Islands",
    "tgn:placetype":[
        "aat:300386853"
    ]
},
  "bbox": [],
  "geometry": {"coordinates":[-92.85,48.55],"type":"Point"}
}