{
  "id": 2608009,
  "type": "Feature",
  "properties": {
    "tgn:hierarchy":[
        "tgn:2608009",
        "tgn:1000001",
        "tgn:7012149",
        "tgn:2001752",
        "tgn:7007712",
        "tgn:7029392"
    ],
    "tgn:id":2608009,
    "tgn:name":"Ratliff Millpond",
    "tgn:placetype":[
        "aat:300006191"
    ]
},
  "bbox": [],
  "geometry": {"coordinates":[-80.3833,34.3333],"type":"Point"}
}