{
  "id": 7562516,
  "type": "Feature",
  "properties": {
    "tgn:hierarchy":[
        "tgn:7562516",
        "tgn:1000004",
        "tgn:7000198",
        "tgn:7016722",
        "tgn:7029392"
    ],
    "tgn:id":7562516,
    "tgn:name:en":"Nagla Dinu",
    "tgn:placetype":[
        "aat:300008347"
    ]
},
  "bbox": [],
  "geometry": {"coordinates":[79.347147,27.008967],"type":"Point"}
}