{
  "id": 1107449,
  "type": "Feature",
  "properties": {
    "tgn:hierarchy":[
        "tgn:1107449",
        "tgn:1000001",
        "tgn:7012149",
        "tgn:7007158",
        "tgn:2000243",
        "tgn:7029392"
    ],
    "tgn:id":1107449,
    "tgn:name":"Pagoda Peak",
    "tgn:placetype":[
        "aat:300008798"
    ]
},
  "bbox": [],
  "geometry": {"coordinates":[-107.3167,40.1333],"type":"Point"}
}