{
  "id": 2315524,
  "type": "Feature",
  "properties": {
    "tgn:hierarchy":[
        "tgn:2315524",
        "tgn:1000001",
        "tgn:7012149",
        "tgn:1002942",
        "tgn:7007920",
        "tgn:7029392"
    ],
    "tgn:id":2315524,
    "tgn:name":"Ellis Cove",
    "tgn:placetype":[
        "aat:300132316"
    ]
},
  "bbox": [],
  "geometry": {"coordinates":[-122.8833,47.0667],"type":"Point"}
}