{
  "id": 2598760,
  "type": "Feature",
  "properties": {
    "tgn:hierarchy":[
        "tgn:2598760",
        "tgn:1000001",
        "tgn:7012149",
        "tgn:1002899",
        "tgn:7007920",
        "tgn:7029392"
    ],
    "tgn:id":2598760,
    "tgn:name":"Priest Point",
    "tgn:placetype":[
        "aat:300008850"
    ]
},
  "bbox": [],
  "geometry": {"coordinates":[-122.2167,48.0167],"type":"Point"}
}