{
  "id": 7042807,
  "type": "Feature",
  "properties": {
    "tgn:hierarchy":[
        "tgn:7042807",
        "tgn:1000003",
        "tgn:7003141",
        "tgn:7003236",
        "tgn:1000080",
        "tgn:7029392"
    ],
    "tgn:id":7042807,
    "tgn:name":"Riva",
    "tgn:placetype":[
        "aat:300008347"
    ]
},
  "bbox": [],
  "geometry": {"coordinates":[9.416667,44.25],"type":"Point"}
}