{
  "id": 2403934,
  "type": "Feature",
  "properties": {
    "tgn:hierarchy":[
        "tgn:2403934",
        "tgn:1000001",
        "tgn:2000459",
        "tgn:7012149",
        "tgn:7007250",
        "tgn:7029392"
    ],
    "tgn:id":2403934,
    "tgn:name":"Howell",
    "tgn:placetype":[
        "aat:300008347"
    ]
},
  "bbox": [],
  "geometry": {"coordinates":[-116.25,43.7833],"type":"Point"}
}