<<<<<<< HEAD
{
  "id": 2403934,
  "type": "Feature",
  "properties": {
    "tgn:hierarchy":[
        "tgn:2403934",
        "tgn:1000001",
        "tgn:2000459",
        "tgn:7012149",
        "tgn:7007250",
        "tgn:7029392"
    ],
    "tgn:id":2403934,
    "tgn:name":"Howell",
    "tgn:placetype":[
        "aat:300008347"
    ]
},
  "bbox": [],
  "geometry": {"coordinates":[-116.25,43.7833],"type":"Point"}
}
=======
{"geometry":{"type":"Point","coordinates":[-116.250000,43.783300]},"type":"Feature","properties":{"hierarchy":["tgn:2403934","tgn:1000001","tgn:2000459","tgn:7012149","tgn:7007250","tgn:7029392"],"placetype":["aat:300008347"],"id":2403934,"name:xx":"Howell"}}
>>>>>>> 03f74aca74312dbeaf24d7e61306dd6a786dc3d0
