{
  "id": 2699386,
  "type": "Feature",
  "properties": {
    "tgn:hierarchy":[
        "tgn:2699386",
        "tgn:1000001",
        "tgn:7012149",
        "tgn:1002658",
        "tgn:7007706",
        "tgn:7029392"
    ],
    "tgn:id":2699386,
    "tgn:name":"Striptown",
    "tgn:placetype":[
        "aat:300008347"
    ]
},
  "bbox": [],
  "geometry": {"coordinates":[-84.6833,40.5833],"type":"Point"}
}