{
  "id": 1068896,
  "type": "Feature",
  "properties": {
    "tgn:hierarchy":[
        "tgn:1068896",
        "tgn:1000004",
        "tgn:7002077",
        "tgn:1000111",
        "tgn:7029392"
    ],
    "tgn:id":1068896,
    "tgn:name":"Huanghua",
    "tgn:placetype":[
        "aat:300008347"
    ]
},
  "bbox": [],
  "geometry": {"coordinates":[117.3333,38.3667],"type":"Point"}
}