{
  "id": 1067430,
  "type": "Feature",
  "properties": {
    "tgn:hierarchy":[
        "tgn:1067430",
        "tgn:1000004",
        "tgn:7001838",
        "tgn:1000111",
        "tgn:7029392"
    ],
    "tgn:id":1067430,
    "tgn:name":"Dalengtu",
    "tgn:placetype":[
        "aat:300008347"
    ]
},
  "bbox": [],
  "geometry": {"coordinates":[113.75,41.1833],"type":"Point"}
}