{
  "id": 7212180,
  "type": "Feature",
  "properties": {
    "tgn:hierarchy":[
        "tgn:7212180",
        "tgn:1000003",
        "tgn:7000094",
        "tgn:7000084",
        "tgn:7029392"
    ],
    "tgn:id":7212180,
    "tgn:name":"Blankensee",
    "tgn:placetype":[
        "aat:300008347"
    ]
},
  "bbox": [],
  "geometry": {"coordinates":[14.316667,53.516667],"type":"Point"}
}