{
  "id": 7465835,
  "type": "Feature",
  "properties": {
    "tgn:hierarchy":[
        "tgn:7465835",
        "tgn:7002445",
        "tgn:1000003",
        "tgn:7008174",
        "tgn:7008591",
        "tgn:7029392"
    ],
    "tgn:id":7465835,
    "tgn:name:en":"Blymhill",
    "tgn:placetype":[
        "aat:300008347"
    ]
},
  "bbox": [],
  "geometry": {"coordinates":[-2.283333,52.716667],"type":"Point"}
}