{
  "id": 1088695,
  "type": "Feature",
  "properties": {
    "tgn:hierarchy":[
        "tgn:1088695",
        "tgn:7001242",
        "tgn:1001023",
        "tgn:1000158",
        "tgn:7029392"
    ],
    "tgn:id":1088695,
    "tgn:name":"Mindouli",
    "tgn:placetype":[
        "aat:300008347"
    ]
},
  "bbox": [],
  "geometry": {"coordinates":[14.3833,-4.2333],"type":"Point"}
}