{
  "id": 1009960,
  "type": "Feature",
  "properties": {
    "tgn:hierarchy":[
        "tgn:1009960",
        "tgn:1000004",
        "tgn:1000958",
        "tgn:1000111",
        "tgn:7029392"
    ],
    "tgn:id":1009960,
    "tgn:name":"Dajin Shan",
    "tgn:placetype":[
        "aat:300008791"
    ]
},
  "bbox": [],
  "geometry": {"coordinates":[121.4167,30.6833],"type":"Point"}
}