{
  "id": 2785531,
  "type": "Feature",
  "properties": {
    "tgn:hierarchy":[
        "tgn:2785531",
        "tgn:1000001",
        "tgn:7012149",
        "tgn:2000476",
        "tgn:7007250",
        "tgn:7029392"
    ],
    "tgn:id":2785531,
    "tgn:name":"Yew Ridge",
    "tgn:placetype":[
        "aat:300266640"
    ]
},
  "bbox": [],
  "geometry": {"coordinates":[-115.8333,45.9167],"type":"Point"}
}