{
  "id": 2778529,
  "type": "Feature",
  "properties": {
    "tgn:hierarchy":[
        "tgn:2778529",
        "tgn:1000001",
        "tgn:7012149",
        "tgn:2002192",
        "tgn:7007919",
        "tgn:7029392"
    ],
    "tgn:id":2778529,
    "tgn:name":"Witten Valley",
    "tgn:placetype":[
        "aat:300008761"
    ]
},
  "bbox": [],
  "geometry": {"coordinates":[-81.6167,37.0667],"type":"Point"}
}