{
  "id": 7048017,
  "type": "Feature",
  "properties": {
    "tgn:hierarchy":[
        "tgn:7048017",
        "tgn:7003131",
        "tgn:1000003",
        "tgn:7008516",
        "tgn:1000080",
        "tgn:7029392"
    ],
    "tgn:id":7048017,
    "tgn:name":"Cingia de' Botti",
    "tgn:placetype":[
        "aat:300008347"
    ]
},
  "bbox": [],
  "geometry": {"coordinates":[10.266667,45.083333],"type":"Point"}
}