{
  "id": 2354449,
  "type": "Feature",
  "properties": {
    "tgn:hierarchy":[
        "tgn:2354449",
        "tgn:1000001",
        "tgn:1002359",
        "tgn:7012149",
        "tgn:7007517",
        "tgn:7029392"
    ],
    "tgn:id":2354449,
    "tgn:name":"Goldthwait Brook",
    "tgn:placetype":[
        "aat:300008699"
    ]
},
  "bbox": [],
  "geometry": {"coordinates":[-70.9833,42.5167],"type":"Point"}
}