<<<<<<< HEAD
{
  "id": 2337908,
  "type": "Feature",
  "properties": {
    "tgn:hierarchy":[
        "tgn:2337908",
        "tgn:1002137",
        "tgn:1000001",
        "tgn:7012149",
        "tgn:7007710",
        "tgn:7029392"
    ],
    "tgn:id":2337908,
    "tgn:name":"Fox Hill",
    "tgn:placetype":[
        "aat:300008798"
    ]
},
  "bbox": [],
  "geometry": {"coordinates":[-77.3167,39.8833],"type":"Point"}
}
=======
{"geometry":{"type":"Point","coordinates":[-77.316700,39.883300]},"type":"Feature","properties":{"hierarchy":["tgn:2337908","tgn:1002137","tgn:1000001","tgn:7012149","tgn:7007710","tgn:7029392"],"placetype":["aat:300008798"],"id":2337908,"name:xx":"Fox Hill"}}
>>>>>>> 03f74aca74312dbeaf24d7e61306dd6a786dc3d0
