{
  "id": 2741511,
  "type": "Feature",
  "properties": {
    "tgn:hierarchy":[
        "tgn:2741511",
        "tgn:1000001",
        "tgn:7012149",
        "tgn:2001718",
        "tgn:7007708",
        "tgn:7029392"
    ],
    "tgn:id":2741511,
    "tgn:name":"Urlezaga Ditch",
    "tgn:placetype":[
        "aat:300006075"
    ]
},
  "bbox": [],
  "geometry": {"coordinates":[-117.15,42.9833],"type":"Point"}
}