{
  "id": 7272282,
  "type": "Feature",
  "properties": {
    "tgn:concordances":{
        "gn:id":"2745694"
    },
    "tgn:hierarchy":[
        "tgn:7272282",
        "tgn:1000003",
        "tgn:7003626",
        "tgn:7016845",
        "tgn:7029392"
    ],
    "tgn:id":7272282,
    "tgn:name:nl":"Veldmaat",
    "tgn:placetype":[
        "aat:300008347"
    ]
},
  "bbox": [],
  "geometry": {"coordinates":[6.75,52.183333],"type":"Point"}
}