{
  "id": 7304729,
  "type": "Feature",
  "properties": {
    "tgn:hierarchy":[
        "tgn:7304729",
        "tgn:7001155",
        "tgn:1000003",
        "tgn:7002790",
        "tgn:1000095",
        "tgn:7029392"
    ],
    "tgn:id":7304729,
    "tgn:name":"Lazar, Portillo de",
    "tgn:placetype":[
        "aat:300259572"
    ]
},
  "bbox": [],
  "geometry": {"coordinates":[-0.983333,42.916667],"type":"Point"}
}