{
  "id": 7401035,
  "type": "Feature",
  "properties": {
    "tgn:hierarchy":[
        "tgn:7401035",
        "tgn:1000001",
        "tgn:7005599",
        "tgn:7005560",
        "tgn:7029392"
    ],
    "tgn:id":7401035,
    "tgn:name":"Las Puentes",
    "tgn:placetype":[
        "aat:300008347"
    ]
},
  "bbox": [],
  "geometry": {"coordinates":[-97.55,20.766667],"type":"Point"}
}