{
  "id": 1044885,
  "type": "Feature",
  "properties": {
    "tgn:hierarchy":[
        "tgn:1044885",
        "tgn:7003007",
        "tgn:1000003",
        "tgn:7002997",
        "tgn:1000080",
        "tgn:7029392"
    ],
    "tgn:id":1044885,
    "tgn:name":"Grezzana",
    "tgn:placetype":[
        "aat:300008347"
    ]
},
  "bbox": [],
  "geometry": {"coordinates":[11.016667,45.516667],"type":"Point"}
}