{
  "id": 2435517,
  "type": "Feature",
  "properties": {
    "tgn:hierarchy":[
        "tgn:2435517",
        "tgn:1000001",
        "tgn:7012149",
        "tgn:2001914",
        "tgn:7007825",
        "tgn:7029392"
    ],
    "tgn:id":2435517,
    "tgn:name":"Kerr Knob",
    "tgn:placetype":[
        "aat:300008798"
    ]
},
  "bbox": [],
  "geometry": {"coordinates":[-83.5167,35.9333],"type":"Point"}
}