{
  "id": 2187332,
  "type": "Feature",
  "properties": {
    "tgn:hierarchy":[
        "tgn:2187332",
        "tgn:1000001",
        "tgn:1002328",
        "tgn:7012149",
        "tgn:7007568",
        "tgn:7029392"
    ],
    "tgn:id":2187332,
    "tgn:name":"Boomhower Hill",
    "tgn:placetype":[
        "aat:300008798"
    ]
},
  "bbox": [],
  "geometry": {"coordinates":[-74.85,42.2833],"type":"Point"}
}