{
  "id": 2292882,
  "type": "Feature",
  "properties": {
    "tgn:hierarchy":[
        "tgn:2292882",
        "tgn:1000001",
        "tgn:7012149",
        "tgn:2002284",
        "tgn:7013961",
        "tgn:7029392"
    ],
    "tgn:id":2292882,
    "tgn:name":"Dorsey Branch",
    "tgn:placetype":[
        "aat:300008699"
    ]
},
  "bbox": [],
  "geometry": {"coordinates":[-80.7833,38.15],"type":"Point"}
}