{
  "id": 7305958,
  "type": "Feature",
  "properties": {
    "tgn:hierarchy":[
        "tgn:7305958",
        "tgn:7002825",
        "tgn:7016622",
        "tgn:1000003",
        "tgn:1000095",
        "tgn:7029392"
    ],
    "tgn:id":7305958,
    "tgn:name":"Matos, Playa de los",
    "tgn:placetype":[
        "aat:300008816"
    ]
},
  "bbox": [],
  "geometry": {"coordinates":[-13.833333,28.683333],"type":"Point"}
}