{
  "id": 7387150,
  "type": "Feature",
  "properties": {
    "tgn:hierarchy":[
        "tgn:7387150",
        "tgn:1000001",
        "tgn:1001960",
        "tgn:7005560",
        "tgn:7029392"
    ],
    "tgn:id":7387150,
    "tgn:name":"Rancho Arroyo Seco",
    "tgn:placetype":[
        "aat:300008347"
    ]
},
  "bbox": [],
  "geometry": {"coordinates":[-109.85,29.683333],"type":"Point"}
}