{
  "id": 2464524,
  "type": "Feature",
  "properties": {
    "tgn:hierarchy":[
        "tgn:2464524",
        "tgn:1000001",
        "tgn:7012149",
        "tgn:7007157",
        "tgn:2000186",
        "tgn:7029392"
    ],
    "tgn:id":2464524,
    "tgn:name":"Log Corral Spring",
    "tgn:placetype":[
        "aat:300008697"
    ]
},
  "bbox": [],
  "geometry": {"coordinates":[-121.0667,41.4333],"type":"Point"}
}