{
  "id": 2059722,
  "type": "Feature",
  "properties": {
    "tgn:hierarchy":[
        "tgn:2059722",
        "tgn:1000001",
        "tgn:7012149",
        "tgn:2001243",
        "tgn:7007523",
        "tgn:7029392"
    ],
    "tgn:id":2059722,
    "tgn:name":"Miami",
    "tgn:placetype":[
        "aat:300008347"
    ]
},
  "bbox": [],
  "geometry": {"coordinates":[-93.2167,39.3167],"type":"Point"}
}