<<<<<<< HEAD
{
  "id": 7240809,
  "type": "Feature",
  "properties": {
    "tgn:hierarchy":[
        "tgn:7240809",
        "tgn:7003460",
        "tgn:1000003",
        "tgn:1000063",
        "tgn:4012014",
        "tgn:7029392"
    ],
    "tgn:id":7240809,
    "tgn:name":"Fl\u00e9ron",
    "tgn:placetype":[
        "aat:300008347"
    ]
},
  "bbox": [],
  "geometry": {"coordinates":[5.683333,50.616667],"type":"Point"}
}
=======
{"geometry":{"type":"Point","coordinates":[5.683333,50.616667]},"type":"Feature","properties":{"hierarchy":["tgn:7240809","tgn:7003460","tgn:1000003","tgn:1000063","tgn:4012014","tgn:7029392"],"placetype":["aat:300008347"],"id":7240809,"name:xx":"Fl\u00e9ron"}}
>>>>>>> 03f74aca74312dbeaf24d7e61306dd6a786dc3d0
