{
  "id": 7478875,
  "type": "Feature",
  "properties": {
    "tgn:hierarchy":[
        "tgn:7478875",
        "tgn:7487020",
        "tgn:1000004",
        "tgn:1000141",
        "tgn:7029392"
    ],
    "tgn:id":7478875,
    "tgn:name":"Lingdong Gong",
    "tgn:placetype":[
        "aat:300007595"
    ]
},
  "bbox": [],
  "geometry": {"coordinates":[120.948394,24.542064],"type":"Point"}
}