{
  "id": 2446644,
  "type": "Feature",
  "properties": {
    "tgn:hierarchy":[
        "tgn:2446644",
        "tgn:1000001",
        "tgn:7012149",
        "tgn:7007922",
        "tgn:7029392"
    ],
    "tgn:id":2446644,
    "tgn:name":"Lewis Valley",
    "tgn:placetype":[
        "aat:300008761"
    ]
},
  "bbox": [],
  "geometry": {"coordinates":[-91.5333,42.35],"type":"Point"}
}