{
  "id": 7499531,
  "type": "Feature",
  "properties": {
    "tgn:hierarchy":[
        "tgn:7499531",
        "tgn:1000004",
        "tgn:7491221",
        "tgn:1000141",
        "tgn:7029392"
    ],
    "tgn:id":7499531,
    "tgn:name":"Shimenxiang",
    "tgn:placetype":[
        "aat:300008347"
    ]
},
  "bbox": [],
  "geometry": {"coordinates":[121.409481,23.271834],"type":"Point"}
}