{
  "id": 7515103,
  "type": "Feature",
  "properties": {
    "tgn:hierarchy":[
        "tgn:7515103",
        "tgn:1009227",
        "tgn:1000226",
        "tgn:7018437",
        "tgn:1000006",
        "tgn:7029392"
    ],
    "tgn:id":7515103,
    "tgn:name:en":"Crow Creek",
    "tgn:placetype":[
        "aat:300008699"
    ]
},
  "bbox": [],
  "geometry": {"coordinates":[169.25,-43.95],"type":"Point"}
}