{
  "id": 2572017,
  "type": "Feature",
  "properties": {
    "tgn:hierarchy":[
        "tgn:2572017",
        "tgn:1000001",
        "tgn:7012149",
        "tgn:1002955",
        "tgn:7007706",
        "tgn:7029392"
    ],
    "tgn:id":2572017,
    "tgn:name":"Paynes Corner",
    "tgn:placetype":[
        "aat:300008347"
    ]
},
  "bbox": [],
  "geometry": {"coordinates":[-80.6167,41.2333],"type":"Point"}
}