{
  "id": 2613377,
  "type": "Feature",
  "properties": {
    "tgn:hierarchy":[
        "tgn:2613377",
        "tgn:1000001",
        "tgn:7012149",
        "tgn:2001273",
        "tgn:7007524",
        "tgn:7029392"
    ],
    "tgn:id":2613377,
    "tgn:name":"Reed Hill",
    "tgn:placetype":[
        "aat:300008798"
    ]
},
  "bbox": [],
  "geometry": {"coordinates":[-109.6333,47.6667],"type":"Point"}
}