{
  "id": 7042388,
  "type": "Feature",
  "properties": {
    "tgn:hierarchy":[
        "tgn:7042388",
        "tgn:7002995",
        "tgn:1000003",
        "tgn:7002997",
        "tgn:1000080",
        "tgn:7029392"
    ],
    "tgn:id":7042388,
    "tgn:name":"Roverdicr\u00e8",
    "tgn:placetype":[
        "aat:300008347"
    ]
},
  "bbox": [],
  "geometry": {"coordinates":[11.75,45.066667],"type":"Point"}
}