{
  "id": 7064372,
  "type": "Feature",
  "properties": {
    "tgn:hierarchy":[
        "tgn:7064372",
        "tgn:1000003",
        "tgn:7003677",
        "tgn:7000084",
        "tgn:7029392"
    ],
    "tgn:id":7064372,
    "tgn:name":"Unterboschbach",
    "tgn:placetype":[
        "aat:300008347"
    ]
},
  "bbox": [],
  "geometry": {"coordinates":[7.133333,51.016667],"type":"Point"}
}