{
  "id": 2744625,
  "type": "Feature",
  "properties": {
    "tgn:hierarchy":[
        "tgn:2744625",
        "tgn:1000001",
        "tgn:7012149",
        "tgn:2002123",
        "tgn:7007827",
        "tgn:7029392"
    ],
    "tgn:id":2744625,
    "tgn:name":"Vickory Mountain",
    "tgn:placetype":[
        "aat:300008798"
    ]
},
  "bbox": [],
  "geometry": {"coordinates":[-112.5833,40.3833],"type":"Point"}
}