{
  "id": 2177179,
  "type": "Feature",
  "properties": {
    "tgn:hierarchy":[
        "tgn:2177179",
        "tgn:1000001",
        "tgn:1003028",
        "tgn:7012149",
        "tgn:7007159",
        "tgn:7029392"
    ],
    "tgn:id":2177179,
    "tgn:name":"Black Pond",
    "tgn:placetype":[
        "aat:300006191"
    ]
},
  "bbox": [],
  "geometry": {"coordinates":[-72.05,41.9667],"type":"Point"}
}