{
  "id": 2564115,
  "type": "Feature",
  "properties": {
    "tgn:hierarchy":[
        "tgn:2564115",
        "tgn:1000001",
        "tgn:7006451",
        "tgn:2000093",
        "tgn:7012149",
        "tgn:7029392"
    ],
    "tgn:id":2564115,
    "tgn:name":"P B Spring",
    "tgn:placetype":[
        "aat:300008697"
    ]
},
  "bbox": [],
  "geometry": {"coordinates":[-110.9167,33.9333],"type":"Point"}
}