{
  "id": 7307779,
  "type": "Feature",
  "properties": {
    "tgn:hierarchy":[
        "tgn:7307779",
        "tgn:7002824",
        "tgn:1000003",
        "tgn:7002786",
        "tgn:1000095",
        "tgn:7029392"
    ],
    "tgn:id":7307779,
    "tgn:name":"Margarida",
    "tgn:placetype":[
        "aat:300008347"
    ]
},
  "bbox": [],
  "geometry": {"coordinates":[-8.883333,43.183333],"type":"Point"}
}