{
  "id": 2736359,
  "type": "Feature",
  "properties": {
    "tgn:hierarchy":[
        "tgn:2736359",
        "tgn:1000001",
        "tgn:2002102",
        "tgn:7012149",
        "tgn:7007827",
        "tgn:7029392"
    ],
    "tgn:id":2736359,
    "tgn:name":"Twin Peaks",
    "tgn:placetype":[
        "aat:300008798"
    ]
},
  "bbox": [],
  "geometry": {"coordinates":[-113.85,41.9167],"type":"Point"}
}