{
  "id": 7481716,
  "type": "Feature",
  "properties": {
    "tgn:hierarchy":[
        "tgn:7481716",
        "tgn:7468018",
        "tgn:1000004",
        "tgn:1000141",
        "tgn:7029392"
    ],
    "tgn:id":7481716,
    "tgn:name":"Wengang",
    "tgn:placetype":[
        "aat:300008347"
    ]
},
  "bbox": [],
  "geometry": {"coordinates":[120.145793,23.469123],"type":"Point"}
}