{
  "id": 2757721,
  "type": "Feature",
  "properties": {
    "tgn:hierarchy":[
        "tgn:2757721",
        "tgn:1000001",
        "tgn:7012149",
        "tgn:2002333",
        "tgn:7007922",
        "tgn:7029392"
    ],
    "tgn:id":2757721,
    "tgn:name":"West Branch Eau Claire River",
    "tgn:placetype":[
        "aat:300008707"
    ]
},
  "bbox": [],
  "geometry": {"coordinates":[-89.2667,45.35],"type":"Point"}
}