{
  "id": 1059331,
  "type": "Feature",
  "properties": {
    "tgn:hierarchy":[
        "tgn:1059331",
        "tgn:1000004",
        "tgn:7013412",
        "tgn:7018214",
        "tgn:7002435",
        "tgn:7029392"
    ],
    "tgn:id":1059331,
    "tgn:name":"Sepych",
    "tgn:placetype":[
        "aat:300008347"
    ]
},
  "bbox": [],
  "geometry": {"coordinates":[54.1333,58.1833],"type":"Point"}
}