<<<<<<< HEAD
{
  "id": 2764538,
  "type": "Feature",
  "properties": {
    "tgn:hierarchy":[
        "tgn:2764538",
        "tgn:1000001",
        "tgn:7006451",
        "tgn:7012149",
        "tgn:2000099",
        "tgn:7029392"
    ],
    "tgn:id":2764538,
    "tgn:name":"Whipple Lake",
    "tgn:placetype":[
        "aat:300008680"
    ]
},
  "bbox": [],
  "geometry": {"coordinates":[-109.9667,34.2667],"type":"Point"}
}
=======
{"geometry":{"type":"Point","coordinates":[-109.966700,34.266700]},"type":"Feature","properties":{"hierarchy":["tgn:2764538","tgn:1000001","tgn:7006451","tgn:7012149","tgn:2000099","tgn:7029392"],"placetype":["aat:300008680"],"id":2764538,"name:xx":"Whipple Lake"}}
>>>>>>> 03f74aca74312dbeaf24d7e61306dd6a786dc3d0
