{
  "id": 7435980,
  "type": "Feature",
  "properties": {
    "tgn:hierarchy":[
        "tgn:7435980",
        "tgn:7005585",
        "tgn:1000001",
        "tgn:7005560",
        "tgn:7029392"
    ],
    "tgn:id":7435980,
    "tgn:name":"Tecoanapa, Barra",
    "tgn:placetype":[
        "aat:300386885"
    ]
},
  "bbox": [],
  "geometry": {"coordinates":[-98.783333,16.516667],"type":"Point"}
}