{
  "id": 2501216,
  "type": "Feature",
  "properties": {
    "tgn:hierarchy":[
        "tgn:2501216",
        "tgn:1000001",
        "tgn:7012149",
        "tgn:7007709",
        "tgn:7029392"
    ],
    "tgn:id":2501216,
    "tgn:name":"McGill Creek",
    "tgn:placetype":[
        "aat:300008706"
    ]
},
  "bbox": [],
  "geometry": {"coordinates":[-81.3333,35.2333],"type":"Point"}
}