<<<<<<< HEAD
{
  "id": 2257635,
  "type": "Feature",
  "properties": {
    "tgn:hierarchy":[
        "tgn:2257635",
        "tgn:1000001",
        "tgn:2001264",
        "tgn:7012149",
        "tgn:7007524",
        "tgn:7029392"
    ],
    "tgn:id":2257635,
    "tgn:name":"Corral Creek",
    "tgn:placetype":[
        "aat:300008706"
    ]
},
  "bbox": [],
  "geometry": {"coordinates":[-109.3,45.0333],"type":"Point"}
}
=======
{"geometry":{"type":"Point","coordinates":[-109.300000,45.033300]},"type":"Feature","properties":{"hierarchy":["tgn:2257635","tgn:1000001","tgn:2001264","tgn:7012149","tgn:7007524","tgn:7029392"],"placetype":["aat:300008706"],"id":2257635,"name:xx":"Corral Creek"}}
>>>>>>> 03f74aca74312dbeaf24d7e61306dd6a786dc3d0
