{
  "id": 7162636,
  "type": "Feature",
  "properties": {
    "tgn:hierarchy":[
        "tgn:7162636",
        "tgn:1000003",
        "tgn:7003682",
        "tgn:7000084",
        "tgn:7029392"
    ],
    "tgn:id":7162636,
    "tgn:name":"Ingelheim-S\u00fcd",
    "tgn:placetype":[
        "aat:300000745"
    ]
},
  "bbox": [],
  "geometry": {"coordinates":[8.05,49.966667],"type":"Point"}
}