{
  "id": 2549135,
  "type": "Feature",
  "properties": {
    "tgn:hierarchy":[
        "tgn:2549135",
        "tgn:1000001",
        "tgn:7019560",
        "tgn:7012149",
        "tgn:7007566",
        "tgn:7029392"
    ],
    "tgn:id":2549135,
    "tgn:name":"North Ragland Tank",
    "tgn:placetype":[
        "aat:300006191"
    ]
},
  "bbox": [],
  "geometry": {"coordinates":[-104.7333,34.2333],"type":"Point"}
}