{
  "id": 1030100,
  "type": "Feature",
  "properties": {
    "tgn:hierarchy":[
        "tgn:1030100",
        "tgn:7002445",
        "tgn:7008114",
        "tgn:1000003",
        "tgn:7008591",
        "tgn:7029392"
    ],
    "tgn:id":1030100,
    "tgn:name:ang":"Moletune",
    "tgn:placetype":[
        "aat:300008347"
    ]
},
  "bbox": [],
  "geometry": {"coordinates":[-2.5167,53.2167],"type":"Point"}
}