{
  "id": 2558828,
  "type": "Feature",
  "properties": {
    "tgn:hierarchy":[
        "tgn:2558828",
        "tgn:1000001",
        "tgn:7012149",
        "tgn:1002599",
        "tgn:7007708",
        "tgn:7029392"
    ],
    "tgn:id":2558828,
    "tgn:name":"Olson Creek",
    "tgn:placetype":[
        "aat:300008706"
    ]
},
  "bbox": [],
  "geometry": {"coordinates":[-124.0333,44.6333],"type":"Point"}
}