{
  "id": 2695046,
  "type": "Feature",
  "properties": {
    "tgn:hierarchy":[
        "tgn:2695046",
        "tgn:1000001",
        "tgn:7012149",
        "tgn:1003038",
        "tgn:7007517",
        "tgn:7029392"
    ],
    "tgn:id":2695046,
    "tgn:name":"Still River",
    "tgn:placetype":[
        "aat:300008707"
    ]
},
  "bbox": [],
  "geometry": {"coordinates":[-71.6167,42.4333],"type":"Point"}
}