{
  "id": 2470393,
  "type": "Feature",
  "properties": {
    "tgn:hierarchy":[
        "tgn:2470393",
        "tgn:1000001",
        "tgn:7012149",
        "tgn:7007826",
        "tgn:7029392"
    ],
    "tgn:id":2470393,
    "tgn:name":"Loring Creek",
    "tgn:placetype":[
        "aat:300008706"
    ]
},
  "bbox": [],
  "geometry": {"coordinates":[-96.1667,33.4167],"type":"Point"}
}