<<<<<<< HEAD
{
  "id": 2768211,
  "type": "Feature",
  "properties": {
    "tgn:hierarchy":[
        "tgn:2768211",
        "tgn:2000918",
        "tgn:1000001",
        "tgn:7012149",
        "tgn:7007515",
        "tgn:7029392"
    ],
    "tgn:id":2768211,
    "tgn:name":"Whites Hill",
    "tgn:placetype":[
        "aat:300008798"
    ]
},
  "bbox": [],
  "geometry": {"coordinates":[-70.1,44.0333],"type":"Point"}
}
=======
{"geometry":{"type":"Point","coordinates":[-70.100000,44.033300]},"type":"Feature","properties":{"hierarchy":["tgn:2768211","tgn:2000918","tgn:1000001","tgn:7012149","tgn:7007515","tgn:7029392"],"placetype":["aat:300008798"],"id":2768211,"name:xx":"Whites Hill"}}
>>>>>>> 03f74aca74312dbeaf24d7e61306dd6a786dc3d0
