<<<<<<< HEAD
{
  "id": 7245353,
  "type": "Feature",
  "properties": {
    "tgn:hierarchy":[
        "tgn:7245353",
        "tgn:7003466",
        "tgn:1000003",
        "tgn:1000063",
        "tgn:4012014",
        "tgn:7029392"
    ],
    "tgn:id":7245353,
    "tgn:name":"Aische-en-Refail",
    "tgn:placetype":[
        "aat:300008347"
    ]
},
  "bbox": [],
  "geometry": {"coordinates":[4.83775,50.600089],"type":"Point"}
}
=======
{"geometry":{"type":"Point","coordinates":[4.837750,50.600089]},"type":"Feature","properties":{"hierarchy":["tgn:7245353","tgn:7003466","tgn:1000003","tgn:1000063","tgn:4012014","tgn:7029392"],"placetype":["aat:300008347"],"id":7245353,"name:xx":"Aische-en-Refail"}}
>>>>>>> 03f74aca74312dbeaf24d7e61306dd6a786dc3d0
