{
  "id": 7417147,
  "type": "Feature",
  "properties": {
    "tgn:hierarchy":[
        "tgn:7417147",
        "tgn:1000001",
        "tgn:7005591",
        "tgn:7005560",
        "tgn:7029392"
    ],
    "tgn:id":7417147,
    "tgn:name:es":"La Humedad",
    "tgn:placetype":[
        "aat:300008347"
    ]
},
  "bbox": [],
  "geometry": {"coordinates":[-97.762222,16.218611],"type":"Point"}
}