{
  "id": 2457895,
  "type": "Feature",
  "properties": {
    "tgn:hierarchy":[
        "tgn:2457895",
        "tgn:1000001",
        "tgn:1002539",
        "tgn:7012149",
        "tgn:7007516",
        "tgn:7029392"
    ],
    "tgn:id":2457895,
    "tgn:name":"Little Mill Pond",
    "tgn:placetype":[
        "aat:300006191"
    ]
},
  "bbox": [],
  "geometry": {"coordinates":[-75.8167,39.25],"type":"Point"}
}