{
  "id": 7257080,
  "type": "Feature",
  "properties": {
    "tgn:hierarchy":[
        "tgn:7257080",
        "tgn:7593113",
        "tgn:7016620",
        "tgn:7593112",
        "tgn:1000001",
        "tgn:7029392"
    ],
    "tgn:id":7257080,
    "tgn:name:nl":"Kibra Hacha",
    "tgn:placetype":[
        "aat:300387200"
    ]
},
  "bbox": [],
  "geometry": {"coordinates":[-68.266667,12.166667],"type":"Point"}
}