{
  "id": 2675279,
  "type": "Feature",
  "properties": {
    "tgn:hierarchy":[
        "tgn:2675279",
        "tgn:1000001",
        "tgn:7012149",
        "tgn:7007157",
        "tgn:2000189",
        "tgn:7029392"
    ],
    "tgn:id":2675279,
    "tgn:name":"Soldier Creek",
    "tgn:placetype":[
        "aat:300008706"
    ]
},
  "bbox": [],
  "geometry": {"coordinates":[-123.5333,41.55],"type":"Point"}
}