{
  "id": 7359624,
  "type": "Feature",
  "properties": {
    "tgn:hierarchy":[
        "tgn:7359624",
        "tgn:7005586",
        "tgn:1000001",
        "tgn:7005560",
        "tgn:7029392"
    ],
    "tgn:id":7359624,
    "tgn:name":"Cuastecomate",
    "tgn:placetype":[
        "aat:300008347"
    ]
},
  "bbox": [],
  "geometry": {"coordinates":[-104.716667,19.216667],"type":"Point"}
}