{
  "id": 7229657,
  "type": "Feature",
  "properties": {
    "tgn:hierarchy":[
        "tgn:7229657",
        "tgn:7002681",
        "tgn:7001395",
        "tgn:1000003",
        "tgn:1000074",
        "tgn:7029392"
    ],
    "tgn:id":7229657,
    "tgn:name":"Lago\u00fases, Nis\u00eddes",
    "tgn:placetype":[
        "aat:300008791"
    ]
},
  "bbox": [],
  "geometry": {"coordinates":[23.468957,37.815139],"type":"Point"}
}