{
  "id": 2192470,
  "type": "Feature",
  "properties": {
    "tgn:hierarchy":[
        "tgn:2192470",
        "tgn:1000001",
        "tgn:7012149",
        "tgn:7014589",
        "tgn:7007515",
        "tgn:7029392"
    ],
    "tgn:id":2192470,
    "tgn:name":"Brandy Heath",
    "tgn:placetype":[
        "aat:300008905"
    ]
},
  "bbox": [],
  "geometry": {"coordinates":[-67.8333,44.7833],"type":"Point"}
}