{
  "id": 2273203,
  "type": "Feature",
  "properties": {
    "tgn:hierarchy":[
        "tgn:2273203",
        "tgn:1000001",
        "tgn:7012149",
        "tgn:2000887",
        "tgn:7007256",
        "tgn:7029392"
    ],
    "tgn:id":2273203,
    "tgn:name":"Cypress Bayou",
    "tgn:placetype":[
        "aat:300008699"
    ]
},
  "bbox": [],
  "geometry": {"coordinates":[-91.6167,32.8333],"type":"Point"}
}