<<<<<<< HEAD
{
  "id": 2155855,
  "type": "Feature",
  "properties": {
    "tgn:hierarchy":[
        "tgn:2155855",
        "tgn:1000001",
        "tgn:7012149",
        "tgn:2001711",
        "tgn:7007708",
        "tgn:7029392"
    ],
    "tgn:id":2155855,
    "tgn:name":"Bear Trap Gulch",
    "tgn:placetype":[
        "aat:300008761"
    ]
},
  "bbox": [],
  "geometry": {"coordinates":[-123.1,42.6167],"type":"Point"}
}
=======
{"geometry":{"type":"Point","coordinates":[-123.100000,42.616700]},"type":"Feature","properties":{"hierarchy":["tgn:2155855","tgn:1000001","tgn:7012149","tgn:2001711","tgn:7007708","tgn:7029392"],"placetype":["aat:300008761"],"id":2155855,"name:xx":"Bear Trap Gulch"}}
>>>>>>> 03f74aca74312dbeaf24d7e61306dd6a786dc3d0
