{
  "id": 7099262,
  "type": "Feature",
  "properties": {
    "tgn:hierarchy":[
        "tgn:7099262",
        "tgn:7003669",
        "tgn:1000003",
        "tgn:7000084",
        "tgn:7029392"
    ],
    "tgn:id":7099262,
    "tgn:name":"Spiesbrunn",
    "tgn:placetype":[
        "aat:300387200"
    ]
},
  "bbox": [],
  "geometry": {"coordinates":[13.783333,48.683333],"type":"Point"}
}