{
  "id": 1016118,
  "type": "Feature",
  "properties": {
    "tgn:hierarchy":[
        "tgn:1016118",
        "tgn:7005685",
        "tgn:1000001",
        "tgn:7005805",
        "tgn:7029392"
    ],
    "tgn:id":1016118,
    "tgn:name":"Southey",
    "tgn:placetype":[
        "aat:300008347"
    ]
},
  "bbox": [],
  "geometry": {"coordinates":[-104.55,50.95],"type":"Point"}
}