{
  "id": 2464694,
  "type": "Feature",
  "properties": {
    "tgn:hierarchy":[
        "tgn:2464694",
        "tgn:1000001",
        "tgn:7012149",
        "tgn:2000928",
        "tgn:7007515",
        "tgn:7029392"
    ],
    "tgn:id":2464694,
    "tgn:name":"Logan Bog",
    "tgn:placetype":[
        "aat:300008905"
    ]
},
  "bbox": [],
  "geometry": {"coordinates":[-69.2667,46.05],"type":"Point"}
}