{
  "id": 1033996,
  "type": "Feature",
  "properties": {
    "tgn:hierarchy":[
        "tgn:1033996",
        "tgn:1000003",
        "tgn:7002883",
        "tgn:1000070",
        "tgn:7029392"
    ],
    "tgn:id":1033996,
    "tgn:name":"Lilas, les",
    "tgn:placetype":[
        "aat:300008347"
    ]
},
  "bbox": [],
  "geometry": {"coordinates":[2.4167,48.8833],"type":"Point"}
}