{
  "id": 7566590,
  "type": "Feature",
  "properties": {
    "tgn:hierarchy":[
        "tgn:7566590",
        "tgn:1000004",
        "tgn:1001832",
        "tgn:7000198",
        "tgn:7029392"
    ],
    "tgn:id":7566590,
    "tgn:name:en":"Chakma Nadi",
    "tgn:placetype":[
        "aat:300008699"
    ]
},
  "bbox": [],
  "geometry": {"coordinates":[89.96696,26.413982],"type":"Point"}
}