{
  "id": 7314529,
  "type": "Feature",
  "properties": {
    "tgn:hierarchy":[
        "tgn:7314529",
        "tgn:1001705",
        "tgn:1000049",
        "tgn:1000002",
        "tgn:7029392"
    ],
    "tgn:id":7314529,
    "tgn:name":"Limpia, Loma",
    "tgn:placetype":[
        "aat:300387002"
    ]
},
  "bbox": [],
  "geometry": {"coordinates":[-72.15,-35.25],"type":"Point"}
}