{
  "id": 7277441,
  "type": "Feature",
  "properties": {
    "tgn:hierarchy":[
        "tgn:7277441",
        "tgn:1001623",
        "tgn:1000049",
        "tgn:1000002",
        "tgn:7029392"
    ],
    "tgn:id":7277441,
    "tgn:name":"Vergara, Isla",
    "tgn:placetype":[
        "aat:300008791"
    ]
},
  "bbox": [],
  "geometry": {"coordinates":[-73.533333,-45.183333],"type":"Point"}
}