{
  "id": 7593787,
  "type": "Feature",
  "properties": {
    "tgn:hierarchy":[
        "tgn:7593787",
        "tgn:7001242",
        "tgn:1000169",
        "tgn:7029392"
    ],
    "tgn:id":7593787,
    "tgn:name":"Nakuru",
    "tgn:placetype":[
        "aat:300387064",
        "aat:300000771"
    ]
},
  "bbox": [],
  "geometry": {"coordinates":[36.083,-0.466],"type":"Point"}
}