{
  "id": 2570099,
  "type": "Feature",
  "properties": {
    "tgn:hierarchy":[
        "tgn:2570099",
        "tgn:1000001",
        "tgn:7012149",
        "tgn:1002676",
        "tgn:7007240",
        "tgn:7029392"
    ],
    "tgn:id":2570099,
    "tgn:name":"Pass Key",
    "tgn:placetype":[
        "aat:300008791"
    ]
},
  "bbox": [],
  "geometry": {"coordinates":[-80.5667,25.15],"type":"Point"}
}