{
  "id": 2586941,
  "type": "Feature",
  "properties": {
    "tgn:hierarchy":[
        "tgn:2586941",
        "tgn:2000090",
        "tgn:1000001",
        "tgn:7006451",
        "tgn:7012149",
        "tgn:7029392"
    ],
    "tgn:id":2586941,
    "tgn:name":"Plane Rock",
    "tgn:placetype":[
        "aat:300008798"
    ]
},
  "bbox": [],
  "geometry": {"coordinates":[-109.6667,36.65],"type":"Point"}
}