<<<<<<< HEAD
{
  "id": 2708608,
  "type": "Feature",
  "properties": {
    "tgn:hierarchy":[
        "tgn:2708608",
        "tgn:1000001",
        "tgn:7012149",
        "tgn:7007708",
        "tgn:7029392"
    ],
    "tgn:id":2708608,
    "tgn:name":"Sycan Marsh",
    "tgn:placetype":[
        "aat:300008905"
    ]
},
  "bbox": [],
  "geometry": {"coordinates":[-121.1,42.8],"type":"Point"}
}
=======
{"geometry":{"type":"Point","coordinates":[-121.100000,42.800000]},"type":"Feature","properties":{"hierarchy":["tgn:2708608","tgn:1000001","tgn:7012149","tgn:7007708","tgn:7029392"],"placetype":["aat:300008905"],"id":2708608,"name:xx":"Sycan Marsh"}}
>>>>>>> 03f74aca74312dbeaf24d7e61306dd6a786dc3d0
