{
  "id": 2619355,
  "type": "Feature",
  "properties": {
    "tgn:hierarchy":[
        "tgn:2619355",
        "tgn:1000001",
        "tgn:7012149",
        "tgn:2001449",
        "tgn:7007566",
        "tgn:7029392"
    ],
    "tgn:id":2619355,
    "tgn:name":"Rim Rock Tank",
    "tgn:placetype":[
        "aat:300006191"
    ]
},
  "bbox": [],
  "geometry": {"coordinates":[-106.2167,36.8667],"type":"Point"}
}