{
  "id": 7150467,
  "type": "Feature",
  "properties": {
    "tgn:hierarchy":[
        "tgn:7150467",
        "tgn:7000096",
        "tgn:1000003",
        "tgn:7000084",
        "tgn:7029392"
    ],
    "tgn:id":7150467,
    "tgn:name":"Kuhblank",
    "tgn:placetype":[
        "aat:300008347"
    ]
},
  "bbox": [],
  "geometry": {"coordinates":[11.85,52.983333],"type":"Point"}
}