{
  "id": 2060126,
  "type": "Feature",
  "properties": {
    "tgn:hierarchy":[
        "tgn:2060126",
        "tgn:1000001",
        "tgn:7012149",
        "tgn:2001209",
        "tgn:7007523",
        "tgn:7029392"
    ],
    "tgn:id":2060126,
    "tgn:name":"Pleasant Valley",
    "tgn:placetype":[
        "aat:300008347"
    ]
},
  "bbox": [],
  "geometry": {"coordinates":[-94.3333,37.15],"type":"Point"}
}