<<<<<<< HEAD
{
  "id": 2151818,
  "type": "Feature",
  "properties": {
    "tgn:hierarchy":[
        "tgn:2151818",
        "tgn:1000001",
        "tgn:7006451",
        "tgn:2000092",
        "tgn:7012149",
        "tgn:7029392"
    ],
    "tgn:id":2151818,
    "tgn:name":"Battle Tank",
    "tgn:placetype":[
        "aat:300006191"
    ]
},
  "bbox": [],
  "geometry": {"coordinates":[-110.9167,34.7333],"type":"Point"}
}
=======
{"geometry":{"type":"Point","coordinates":[-110.916700,34.733300]},"type":"Feature","properties":{"hierarchy":["tgn:2151818","tgn:1000001","tgn:7006451","tgn:2000092","tgn:7012149","tgn:7029392"],"placetype":["aat:300006191"],"id":2151818,"name:xx":"Battle Tank"}}
>>>>>>> 03f74aca74312dbeaf24d7e61306dd6a786dc3d0
