{
  "id": 1103812,
  "type": "Feature",
  "properties": {
    "tgn:hierarchy":[
        "tgn:1103812",
        "tgn:1001274",
        "tgn:1000001",
        "tgn:7005364",
        "tgn:7029392"
    ],
    "tgn:id":1103812,
    "tgn:name":"Azul, Cerro",
    "tgn:placetype":[
        "aat:300008795"
    ]
},
  "bbox": [],
  "geometry": {"coordinates":[-85.2833,9.95],"type":"Point"}
}