<<<<<<< HEAD
{
  "id": 2407238,
  "type": "Feature",
  "properties": {
    "tgn:hierarchy":[
        "tgn:2407238",
        "tgn:1000001",
        "tgn:7012149",
        "tgn:2001722",
        "tgn:7007708",
        "tgn:7029392"
    ],
    "tgn:id":2407238,
    "tgn:name":"Hunting Camp Ridge",
    "tgn:placetype":[
        "aat:300266640"
    ]
},
  "bbox": [],
  "geometry": {"coordinates":[-117.1,45.9],"type":"Point"}
}
=======
{"geometry":{"type":"Point","coordinates":[-117.100000,45.900000]},"type":"Feature","properties":{"hierarchy":["tgn:2407238","tgn:1000001","tgn:7012149","tgn:2001722","tgn:7007708","tgn:7029392"],"placetype":["aat:300266640"],"id":2407238,"name:xx":"Hunting Camp Ridge"}}
>>>>>>> 03f74aca74312dbeaf24d7e61306dd6a786dc3d0
