{
  "id": 7378039,
  "type": "Feature",
  "properties": {
    "tgn:hierarchy":[
        "tgn:7378039",
        "tgn:7005581",
        "tgn:1000001",
        "tgn:7005560",
        "tgn:7029392"
    ],
    "tgn:id":7378039,
    "tgn:name":"La Vinata",
    "tgn:placetype":[
        "aat:300008347"
    ]
},
  "bbox": [],
  "geometry": {"coordinates":[-104.883333,27.416667],"type":"Point"}
}