{
  "id": 2665889,
  "type": "Feature",
  "properties": {
    "tgn:hierarchy":[
        "tgn:2665889",
        "tgn:1000001",
        "tgn:7012149",
        "tgn:2001851",
        "tgn:7007825",
        "tgn:7029392"
    ],
    "tgn:id":2665889,
    "tgn:name":"Sisk Island",
    "tgn:placetype":[
        "aat:300008791"
    ]
},
  "bbox": [],
  "geometry": {"coordinates":[-83.1667,35.9167],"type":"Point"}
}