{
  "id": 2028203,
  "type": "Feature",
  "properties": {
    "tgn:hierarchy":[
        "tgn:2028203",
        "tgn:1000001",
        "tgn:7012149",
        "tgn:1003030",
        "tgn:7007251",
        "tgn:7029392"
    ],
    "tgn:id":2028203,
    "tgn:name":"Harlem",
    "tgn:placetype":[
        "aat:300008347"
    ]
},
  "bbox": [],
  "geometry": {"coordinates":[-89.0167,42.3333],"type":"Point"}
}