{
  "id": 2255890,
  "type": "Feature",
  "properties": {
    "tgn:hierarchy":[
        "tgn:2255890",
        "tgn:1000001",
        "tgn:7012149",
        "tgn:1002897",
        "tgn:7007920",
        "tgn:7029392"
    ],
    "tgn:id":2255890,
    "tgn:name":"Copper Creek",
    "tgn:placetype":[
        "aat:300008706"
    ]
},
  "bbox": [],
  "geometry": {"coordinates":[-121.8833,46.1833],"type":"Point"}
}