{
  "id": 7187021,
  "type": "Feature",
  "properties": {
    "tgn:hierarchy":[
        "tgn:7187021",
        "tgn:1000003",
        "tgn:7003677",
        "tgn:7000084",
        "tgn:7029392"
    ],
    "tgn:id":7187021,
    "tgn:name":"Hof Ginsberg",
    "tgn:placetype":[
        "aat:300000206"
    ]
},
  "bbox": [],
  "geometry": {"coordinates":[8.15,50.966667],"type":"Point"}
}