{
  "id": 7086553,
  "type": "Feature",
  "properties": {
    "tgn:hierarchy":[
        "tgn:7086553",
        "tgn:7003692",
        "tgn:1000003",
        "tgn:7000084",
        "tgn:7029392"
    ],
    "tgn:id":7086553,
    "tgn:name":"Waldhuterhof",
    "tgn:placetype":[
        "aat:300000206"
    ]
},
  "bbox": [],
  "geometry": {"coordinates":[9.366667,47.783333],"type":"Point"}
}