{
  "id": 2214414,
  "type": "Feature",
  "properties": {
    "tgn:hierarchy":[
        "tgn:2214414",
        "tgn:1000001",
        "tgn:7012149",
        "tgn:7007157",
        "tgn:1002858",
        "tgn:7029392"
    ],
    "tgn:id":2214414,
    "tgn:name":"Calavera, Cerro de la",
    "tgn:placetype":[
        "aat:300008798"
    ]
},
  "bbox": [],
  "geometry": {"coordinates":[-117.2667,33.1667],"type":"Point"}
}