{
  "id": 2488846,
  "type": "Feature",
  "properties": {
    "tgn:hierarchy":[
        "tgn:2488846",
        "tgn:1000001",
        "tgn:2001262",
        "tgn:7012149",
        "tgn:7007524",
        "tgn:7029392"
    ],
    "tgn:id":2488846,
    "tgn:name":"Main Canal A",
    "tgn:placetype":[
        "aat:300006075"
    ]
},
  "bbox": [],
  "geometry": {"coordinates":[-108.65,48.45],"type":"Point"}
}