{
  "id": 7546113,
  "type": "Feature",
  "properties": {
    "tgn:hierarchy":[
        "tgn:7546113",
        "tgn:1000004",
        "tgn:7000198",
        "tgn:1001996",
        "tgn:7029392"
    ],
    "tgn:id":7546113,
    "tgn:name:en":"Baijn\u0101th",
    "tgn:placetype":[
        "aat:300008347"
    ]
},
  "bbox": [],
  "geometry": {"coordinates":[76.64381,32.051075],"type":"Point"}
}