<<<<<<< HEAD
{
  "id": 7352169,
  "type": "Feature",
  "properties": {
    "tgn:hierarchy":[
        "tgn:7352169",
        "tgn:1000001",
        "tgn:7005594",
        "tgn:7005560",
        "tgn:7029392"
    ],
    "tgn:id":7352169,
    "tgn:name":"Bozal, Sierra",
    "tgn:placetype":[
        "aat:300008795"
    ]
},
  "bbox": [],
  "geometry": {"coordinates":[-101.5,23.7],"type":"Point"}
}
=======
{"geometry":{"type":"Point","coordinates":[-101.500000,23.700000]},"type":"Feature","properties":{"hierarchy":["tgn:7352169","tgn:1000001","tgn:7005594","tgn:7005560","tgn:7029392"],"placetype":["aat:300008795"],"id":7352169,"name:xx":"Bozal, Sierra"}}
>>>>>>> 03f74aca74312dbeaf24d7e61306dd6a786dc3d0
