{
  "id": 7549290,
  "type": "Feature",
  "properties": {
    "tgn:hierarchy":[
        "tgn:7549290",
        "tgn:1000004",
        "tgn:7000198",
        "tgn:7000799",
        "tgn:7029392"
    ],
    "tgn:id":7549290,
    "tgn:name:en":"Chak Bow\u0101l",
    "tgn:placetype":[
        "aat:300008347"
    ]
},
  "bbox": [],
  "geometry": {"coordinates":[74.807039,32.86282],"type":"Point"}
}