{
  "id": 7407771,
  "type": "Feature",
  "properties": {
    "tgn:hierarchy":[
        "tgn:7407771",
        "tgn:7005580",
        "tgn:1000001",
        "tgn:7005560",
        "tgn:7029392"
    ],
    "tgn:id":7407771,
    "tgn:name":"Nueva Libertad",
    "tgn:placetype":[
        "aat:300008347"
    ]
},
  "bbox": [],
  "geometry": {"coordinates":[-92.806944,16.091667],"type":"Point"}
}