<<<<<<< HEAD
{
  "id": 2400540,
  "type": "Feature",
  "properties": {
    "tgn:hierarchy":[
        "tgn:2400540",
        "tgn:1000001",
        "tgn:7012149",
        "tgn:2001277",
        "tgn:7007524",
        "tgn:7029392"
    ],
    "tgn:id":2400540,
    "tgn:name":"Horse Lake",
    "tgn:placetype":[
        "aat:300008680"
    ]
},
  "bbox": [],
  "geometry": {"coordinates":[-113.2167,48.7167],"type":"Point"}
}
=======
{"geometry":{"type":"Point","coordinates":[-113.216700,48.716700]},"type":"Feature","properties":{"hierarchy":["tgn:2400540","tgn:1000001","tgn:7012149","tgn:2001277","tgn:7007524","tgn:7029392"],"placetype":["aat:300008680"],"id":2400540,"name:xx":"Horse Lake"}}
>>>>>>> 03f74aca74312dbeaf24d7e61306dd6a786dc3d0
