{
  "id": 2400540,
  "type": "Feature",
  "properties": {
    "tgn:hierarchy":[
        "tgn:2400540",
        "tgn:1000001",
        "tgn:7012149",
        "tgn:2001277",
        "tgn:7007524",
        "tgn:7029392"
    ],
    "tgn:id":2400540,
    "tgn:name":"Horse Lake",
    "tgn:placetype":[
        "aat:300008680"
    ]
},
  "bbox": [],
  "geometry": {"coordinates":[-113.2167,48.7167],"type":"Point"}
}