{
  "id": 7293038,
  "type": "Feature",
  "properties": {
    "tgn:hierarchy":[
        "tgn:7293038",
        "tgn:1001699",
        "tgn:1000049",
        "tgn:1000002",
        "tgn:7029392"
    ],
    "tgn:id":7293038,
    "tgn:name":"El Salto Chico",
    "tgn:placetype":[
        "aat:300008347"
    ]
},
  "bbox": [],
  "geometry": {"coordinates":[-73.316667,-41.483333],"type":"Point"}
}