{
  "id": 2637254,
  "type": "Feature",
  "properties": {
    "tgn:hierarchy":[
        "tgn:2637254",
        "tgn:7006450",
        "tgn:1000001",
        "tgn:2124077",
        "tgn:7012149",
        "tgn:7029392"
    ],
    "tgn:id":2637254,
    "tgn:name":"Saint James Bay",
    "tgn:placetype":[
        "aat:300132316"
    ]
},
  "bbox": [],
  "geometry": {"coordinates":[-135.1667,58.5833],"type":"Point"}
}