{
  "id": 7452379,
  "type": "Feature",
  "properties": {
    "tgn:hierarchy":[
        "tgn:7452379",
        "tgn:7002444",
        "tgn:1000003",
        "tgn:7029508",
        "tgn:7008591",
        "tgn:7029392"
    ],
    "tgn:id":7452379,
    "tgn:name:en":"Foul Baa",
    "tgn:placetype":[
        "aat:300008808"
    ]
},
  "bbox": [],
  "geometry": {"coordinates":[-1.333333,60.15],"type":"Point"}
}