<<<<<<< HEAD
{
  "id": 7476909,
  "type": "Feature",
  "properties": {
    "tgn:hierarchy":[
        "tgn:7476909",
        "tgn:7488858",
        "tgn:1000004",
        "tgn:1000141",
        "tgn:7029392"
    ],
    "tgn:id":7476909,
    "tgn:name":"Kengkoupi",
    "tgn:placetype":[
        "aat:300008699"
    ]
},
  "bbox": [],
  "geometry": {"coordinates":[120.7671,23.821664],"type":"Point"}
}
=======
{"geometry":{"type":"Point","coordinates":[120.767100,23.821664]},"type":"Feature","properties":{"hierarchy":["tgn:7476909","tgn:7488858","tgn:1000004","tgn:1000141","tgn:7029392"],"placetype":["aat:300008699"],"id":7476909,"name:xx":"Kengkoupi"}}
>>>>>>> 03f74aca74312dbeaf24d7e61306dd6a786dc3d0
