{
  "id": 7476909,
  "type": "Feature",
  "properties": {
    "tgn:hierarchy":[
        "tgn:7476909",
        "tgn:7488858",
        "tgn:1000004",
        "tgn:1000141",
        "tgn:7029392"
    ],
    "tgn:id":7476909,
    "tgn:name":"Kengkoupi",
    "tgn:placetype":[
        "aat:300008699"
    ]
},
  "bbox": [],
  "geometry": {"coordinates":[120.7671,23.821664],"type":"Point"}
}