{
  "id": 7433179,
  "type": "Feature",
  "properties": {
    "tgn:hierarchy":[
        "tgn:7433179",
        "tgn:1000001",
        "tgn:7005599",
        "tgn:7005560",
        "tgn:7029392"
    ],
    "tgn:id":7433179,
    "tgn:name":"Vieja, Barra",
    "tgn:placetype":[
        "aat:300386885"
    ]
},
  "bbox": [],
  "geometry": {"coordinates":[-96.766667,20.25],"type":"Point"}
}