{
  "id": 2603481,
  "type": "Feature",
  "properties": {
    "tgn:hierarchy":[
        "tgn:2603481",
        "tgn:1000001",
        "tgn:7012149",
        "tgn:1003026",
        "tgn:7007826",
        "tgn:7029392"
    ],
    "tgn:id":2603481,
    "tgn:name":"Queen Hill",
    "tgn:placetype":[
        "aat:300008798"
    ]
},
  "bbox": [],
  "geometry": {"coordinates":[-97.5333,30.6667],"type":"Point"}
}