{
  "id": 1084355,
  "type": "Feature",
  "properties": {
    "tgn:hierarchy":[
        "tgn:1084355",
        "tgn:1000004",
        "tgn:1001551",
        "tgn:1000135",
        "tgn:7029392"
    ],
    "tgn:id":1084355,
    "tgn:name":"Ligao",
    "tgn:placetype":[
        "aat:300008347"
    ]
},
  "bbox": [],
  "geometry": {"coordinates":[124.15,6.2833],"type":"Point"}
}