{
  "id": 1105593,
  "type": "Feature",
  "properties": {
    "tgn:hierarchy":[
        "tgn:1105593",
        "tgn:7593919",
        "tgn:1000003",
        "tgn:1001780",
        "tgn:7029392"
    ],
    "tgn:id":1105593,
    "tgn:name":"Medv\u011bd\u00ed hora",
    "tgn:placetype":[
        "aat:300008795"
    ]
},
  "bbox": [],
  "geometry": {"coordinates":[13.416,48.983],"type":"Point"}
}