{
  "id": 7175525,
  "type": "Feature",
  "properties": {
    "tgn:hierarchy":[
        "tgn:7175525",
        "tgn:7003669",
        "tgn:1000003",
        "tgn:7000084",
        "tgn:7029392"
    ],
    "tgn:id":7175525,
    "tgn:name":"Grieshof",
    "tgn:placetype":[
        "aat:300000206"
    ]
},
  "bbox": [],
  "geometry": {"coordinates":[13.283333,48.683333],"type":"Point"}
}