{
  "id": 2366609,
  "type": "Feature",
  "properties": {
    "tgn:hierarchy":[
        "tgn:2366609",
        "tgn:1000001",
        "tgn:7012149",
        "tgn:2002341",
        "tgn:7007922",
        "tgn:7029392"
    ],
    "tgn:id":2366609,
    "tgn:name":"Grindle Lake",
    "tgn:placetype":[
        "aat:300008680"
    ]
},
  "bbox": [],
  "geometry": {"coordinates":[-88.3667,45.2167],"type":"Point"}
}