{
  "id": 2441111,
  "type": "Feature",
  "properties": {
    "tgn:hierarchy":[
        "tgn:2441111",
        "tgn:1000001",
        "tgn:7012149",
        "tgn:2001109",
        "tgn:7007522",
        "tgn:7029392"
    ],
    "tgn:id":2441111,
    "tgn:name":"Knoll, The",
    "tgn:placetype":[
        "aat:300132348"
    ]
},
  "bbox": [],
  "geometry": {"coordinates":[-88.9833,30.1833],"type":"Point"}
}