{
  "id": 2486047,
  "type": "Feature",
  "properties": {
    "tgn:hierarchy":[
        "tgn:2486047",
        "tgn:1000001",
        "tgn:2002102",
        "tgn:7012149",
        "tgn:7007827",
        "tgn:7029392"
    ],
    "tgn:id":2486047,
    "tgn:name":"Lead Mountain",
    "tgn:placetype":[
        "aat:300008798"
    ]
},
  "bbox": [],
  "geometry": {"coordinates":[-112.45,41.25],"type":"Point"}
}