{
  "id": 7333295,
  "type": "Feature",
  "properties": {
    "tgn:hierarchy":[
        "tgn:7333295",
        "tgn:7002758",
        "tgn:7002830",
        "tgn:1000003",
        "tgn:1000095",
        "tgn:7029392"
    ],
    "tgn:id":7333295,
    "tgn:name":"Fuente de Piedra",
    "tgn:placetype":[
        "aat:300008347"
    ]
},
  "bbox": [],
  "geometry": {"coordinates":[-4.716667,37.133333],"type":"Point"}
}