{
  "id": 2393344,
  "type": "Feature",
  "properties": {
    "tgn:hierarchy":[
        "tgn:2393344",
        "tgn:1000001",
        "tgn:7006451",
        "tgn:7012149",
        "tgn:2000103",
        "tgn:7029392"
    ],
    "tgn:id":2393344,
    "tgn:name":"Hoffman Tank",
    "tgn:placetype":[
        "aat:300006191"
    ]
},
  "bbox": [],
  "geometry": {"coordinates":[-112.8167,35.3167],"type":"Point"}
}