{
  "id": 1036390,
  "type": "Feature",
  "properties": {
    "tgn:hierarchy":[
        "tgn:1036390",
        "tgn:1000003",
        "tgn:7003689",
        "tgn:7000084",
        "tgn:7029392"
    ],
    "tgn:id":1036390,
    "tgn:name":"Bad K\u00f6stritz",
    "tgn:placetype":[
        "aat:300008347"
    ]
},
  "bbox": [],
  "geometry": {"coordinates":[12.016667,50.933333],"type":"Point"}
}