{
  "id": 7506465,
  "type": "Feature",
  "properties": {
    "tgn:hierarchy":[
        "tgn:7506465",
        "tgn:7000509",
        "tgn:1008380",
        "tgn:1000226",
        "tgn:1000006",
        "tgn:7029392"
    ],
    "tgn:id":7506465,
    "tgn:name:en":"Rotokakahi, Lake",
    "tgn:placetype":[
        "aat:300008680"
    ]
},
  "bbox": [],
  "geometry": {"coordinates":[176.333333,-38.216667],"type":"Point"}
}