{
  "id": 7579392,
  "type": "Feature",
  "properties": {
    "tgn:hierarchy":[
        "tgn:7579392",
        "tgn:1009838",
        "tgn:7000204",
        "tgn:1000004",
        "tgn:7000198",
        "tgn:7029392"
    ],
    "tgn:id":7579392,
    "tgn:name:en":"Wilson Island",
    "tgn:placetype":[
        "aat:300008791"
    ]
},
  "bbox": [],
  "geometry": {"coordinates":[92.983333,12.133333],"type":"Point"}
}