{
  "id": 2715589,
  "type": "Feature",
  "properties": {
    "tgn:hierarchy":[
        "tgn:2715589",
        "tgn:1000001",
        "tgn:7012149",
        "tgn:2000206",
        "tgn:7007158",
        "tgn:7029392"
    ],
    "tgn:id":2715589,
    "tgn:name":"Terror Ditch",
    "tgn:placetype":[
        "aat:300008699"
    ]
},
  "bbox": [],
  "geometry": {"coordinates":[-107.5833,39.0167],"type":"Point"}
}