{
  "id": 2661584,
  "type": "Feature",
  "properties": {
    "tgn:hierarchy":[
        "tgn:2661584",
        "tgn:1000001",
        "tgn:7012149",
        "tgn:2002252",
        "tgn:7007920",
        "tgn:7029392"
    ],
    "tgn:id":2661584,
    "tgn:name":"Shreck",
    "tgn:placetype":[
        "aat:300008347"
    ]
},
  "bbox": [],
  "geometry": {"coordinates":[-117.8833,46.6833],"type":"Point"}
}