{
  "id": 2197165,
  "type": "Feature",
  "properties": {
    "tgn:hierarchy":[
        "tgn:2197165",
        "tgn:1000001",
        "tgn:1002361",
        "tgn:7012149",
        "tgn:7007828",
        "tgn:7029392"
    ],
    "tgn:id":2197165,
    "tgn:name":"Brousseau Mountain",
    "tgn:placetype":[
        "aat:300008798"
    ]
},
  "bbox": [],
  "geometry": {"coordinates":[-71.7333,44.9667],"type":"Point"}
}