<<<<<<< HEAD
{
  "id": 2401904,
  "type": "Feature",
  "properties": {
    "tgn:hierarchy":[
        "tgn:2401904",
        "tgn:1000001",
        "tgn:7012149",
        "tgn:2002249",
        "tgn:7007920",
        "tgn:7029392"
    ],
    "tgn:id":2401904,
    "tgn:name":"Horseshoe Lake",
    "tgn:placetype":[
        "aat:300008680"
    ]
},
  "bbox": [],
  "geometry": {"coordinates":[-117.75,47.75],"type":"Point"}
}
=======
{"geometry":{"type":"Point","coordinates":[-117.750000,47.750000]},"type":"Feature","properties":{"hierarchy":["tgn:2401904","tgn:1000001","tgn:7012149","tgn:2002249","tgn:7007920","tgn:7029392"],"placetype":["aat:300008680"],"id":2401904,"name:xx":"Horseshoe Lake"}}
>>>>>>> 03f74aca74312dbeaf24d7e61306dd6a786dc3d0
