{
  "id": 2178154,
  "type": "Feature",
  "properties": {
    "tgn:hierarchy":[
        "tgn:2178154",
        "tgn:1000001",
        "tgn:7012149",
        "tgn:2000916",
        "tgn:7007256",
        "tgn:7029392"
    ],
    "tgn:id":2178154,
    "tgn:name":"Blackfork Bayou",
    "tgn:placetype":[
        "aat:300008699"
    ]
},
  "bbox": [],
  "geometry": {"coordinates":[-91.4667,30.7833],"type":"Point"}
}