{
  "id": 7046230,
  "type": "Feature",
  "properties": {
    "tgn:hierarchy":[
        "tgn:7046230",
        "tgn:7003138",
        "tgn:1000003",
        "tgn:7003080",
        "tgn:1000080",
        "tgn:7029392"
    ],
    "tgn:id":7046230,
    "tgn:name":"Fiore, Monte",
    "tgn:placetype":[
        "aat:300008795"
    ]
},
  "bbox": [],
  "geometry": {"coordinates":[12.766667,41.766667],"type":"Point"}
}