{
  "id": 7046085,
  "type": "Feature",
  "properties": {
    "tgn:hierarchy":[
        "tgn:7046085",
        "tgn:7003164",
        "tgn:1000003",
        "tgn:7009760",
        "tgn:1000080",
        "tgn:7029392"
    ],
    "tgn:id":7046085,
    "tgn:name":"Stazione Campiglia Marittima",
    "tgn:placetype":[
        "aat:300007783"
    ]
},
  "bbox": [],
  "geometry": {"coordinates":[10.566667,43.016667],"type":"Point"}
}