{
  "id": 7317018,
  "type": "Feature",
  "properties": {
    "tgn:hierarchy":[
        "tgn:7317018",
        "tgn:1001692",
        "tgn:1000049",
        "tgn:1000002",
        "tgn:7029392"
    ],
    "tgn:id":7317018,
    "tgn:name":"Coilico, Estero",
    "tgn:placetype":[
        "aat:300008699"
    ]
},
  "bbox": [],
  "geometry": {"coordinates":[-73.133333,-38.683333],"type":"Point"}
}