{
  "id": 7472820,
  "type": "Feature",
  "properties": {
    "tgn:hierarchy":[
        "tgn:7472820",
        "tgn:1000004",
        "tgn:1000454",
        "tgn:1000141",
        "tgn:7029392"
    ],
    "tgn:id":7472820,
    "tgn:name":"Pinglin Guoxiao Jianshanhu Fenxiao",
    "tgn:placetype":[
        "aat:300006495"
    ]
},
  "bbox": [],
  "geometry": {"coordinates":[121.753397,24.89632],"type":"Point"}
}