{
  "id": 7233543,
  "type": "Feature",
  "properties": {
    "tgn:hierarchy":[
        "tgn:7233543",
        "tgn:7011270",
        "tgn:7002674",
        "tgn:1000003",
        "tgn:1000074",
        "tgn:7029392"
    ],
    "tgn:id":7233543,
    "tgn:name":"Alimni\u00e1, \u00c1kra",
    "tgn:placetype":[
        "aat:300008850"
    ]
},
  "bbox": [],
  "geometry": {"coordinates":[25.416667,36.816667],"type":"Point"}
}