{
  "id": 2314026,
  "type": "Feature",
  "properties": {
    "tgn:hierarchy":[
        "tgn:2314026",
        "tgn:1000001",
        "tgn:7012149",
        "tgn:2002382",
        "tgn:7007923",
        "tgn:7029392"
    ],
    "tgn:id":2314026,
    "tgn:name":"Elizabeth Lake",
    "tgn:placetype":[
        "aat:300008680"
    ]
},
  "bbox": [],
  "geometry": {"coordinates":[-109.2833,42.7667],"type":"Point"}
}