{
  "id": 7455278,
  "type": "Feature",
  "properties": {
    "tgn:hierarchy":[
        "tgn:7455278",
        "tgn:7002444",
        "tgn:1000003",
        "tgn:7019152",
        "tgn:7008591",
        "tgn:7029392"
    ],
    "tgn:id":7455278,
    "tgn:name:en":"Collace",
    "tgn:placetype":[
        "aat:300008347"
    ]
},
  "bbox": [],
  "geometry": {"coordinates":[-3.283333,56.466667],"type":"Point"}
}