{
  "id": 7319526,
  "type": "Feature",
  "properties": {
    "tgn:hierarchy":[
        "tgn:7319526",
        "tgn:1001708",
        "tgn:1000049",
        "tgn:1000002",
        "tgn:7029392"
    ],
    "tgn:id":7319526,
    "tgn:name":"Altar, Cerro",
    "tgn:placetype":[
        "aat:300008795"
    ]
},
  "bbox": [],
  "geometry": {"coordinates":[-70.25,-33.183333],"type":"Point"}
}