{
  "id": 2756575,
  "type": "Feature",
  "properties": {
    "tgn:hierarchy":[
        "tgn:2756575",
        "tgn:1000001",
        "tgn:7012149",
        "tgn:2001494",
        "tgn:7007709",
        "tgn:7029392"
    ],
    "tgn:id":2756575,
    "tgn:name":"Wellington Way",
    "tgn:placetype":[
        "aat:300008347"
    ]
},
  "bbox": [],
  "geometry": {"coordinates":[-80.1167,36.1167],"type":"Point"}
}