{
  "id": 2304155,
  "type": "Feature",
  "properties": {
    "tgn:hierarchy":[
        "tgn:2304155",
        "tgn:1000001",
        "tgn:2001801",
        "tgn:7012149",
        "tgn:7007713",
        "tgn:7029392"
    ],
    "tgn:id":2304155,
    "tgn:name":"Eagles Nest Butte",
    "tgn:placetype":[
        "aat:300008798"
    ]
},
  "bbox": [],
  "geometry": {"coordinates":[-103.4833,45.9167],"type":"Point"}
}