{
  "id": 7410605,
  "type": "Feature",
  "properties": {
    "tgn:hierarchy":[
        "tgn:7410605",
        "tgn:1000001",
        "tgn:7005590",
        "tgn:7005560",
        "tgn:7029392"
    ],
    "tgn:id":7410605,
    "tgn:name":"Atijo",
    "tgn:placetype":[
        "aat:300008347"
    ]
},
  "bbox": [],
  "geometry": {"coordinates":[-101.420833,18.708333],"type":"Point"}
}