{
  "id": 7398420,
  "type": "Feature",
  "properties": {
    "tgn:hierarchy":[
        "tgn:7398420",
        "tgn:1000001",
        "tgn:1001960",
        "tgn:7005560",
        "tgn:7029392"
    ],
    "tgn:id":7398420,
    "tgn:name":"El Corral, Cerro",
    "tgn:placetype":[
        "aat:300008777"
    ]
},
  "bbox": [],
  "geometry": {"coordinates":[-111.838889,31.204444],"type":"Point"}
}