{
  "id": 7460028,
  "type": "Feature",
  "properties": {
    "tgn:hierarchy":[
        "tgn:7460028",
        "tgn:7002445",
        "tgn:7027477",
        "tgn:1000003",
        "tgn:7026570",
        "tgn:7008591",
        "tgn:7029392"
    ],
    "tgn:id":7460028,
    "tgn:name:en":"Medlock, River",
    "tgn:placetype":[
        "aat:300008699"
    ]
},
  "bbox": [],
  "geometry": {"coordinates":[-2.283333,53.45],"type":"Point"}
}