{
  "id": 7308025,
  "type": "Feature",
  "properties": {
    "tgn:hierarchy":[
        "tgn:7308025",
        "tgn:1001708",
        "tgn:1000049",
        "tgn:1000002",
        "tgn:7029392"
    ],
    "tgn:id":7308025,
    "tgn:name":"Melocot\u00f3n Alto",
    "tgn:placetype":[
        "aat:300008347"
    ]
},
  "bbox": [],
  "geometry": {"coordinates":[-70.35,-33.716667],"type":"Point"}
}