{
  "id": 2270966,
  "type": "Feature",
  "properties": {
    "tgn:hierarchy":[
        "tgn:2270966",
        "tgn:1000001",
        "tgn:7012149",
        "tgn:2000817",
        "tgn:7007255",
        "tgn:7029392"
    ],
    "tgn:id":2270966,
    "tgn:name":"Cuba Towhead",
    "tgn:placetype":[
        "aat:300008791"
    ]
},
  "bbox": [],
  "geometry": {"coordinates":[-88.5667,37.05],"type":"Point"}
}