{
  "id": 7563477,
  "type": "Feature",
  "properties": {
    "tgn:hierarchy":[
        "tgn:7563477",
        "tgn:1000004",
        "tgn:7000198",
        "tgn:7016788",
        "tgn:7029392"
    ],
    "tgn:id":7563477,
    "tgn:name:en":"L\u0101khera",
    "tgn:placetype":[
        "aat:300008347"
    ]
},
  "bbox": [],
  "geometry": {"coordinates":[74.287489,28.975088],"type":"Point"}
}