{
  "id": 2693196,
  "type": "Feature",
  "properties": {
    "tgn:hierarchy":[
        "tgn:2693196",
        "tgn:1000001",
        "tgn:7012149",
        "tgn:7007157",
        "tgn:1002867",
        "tgn:7029392"
    ],
    "tgn:id":2693196,
    "tgn:name":"Steer Creek",
    "tgn:placetype":[
        "aat:300008706"
    ]
},
  "bbox": [],
  "geometry": {"coordinates":[-119.45,34.4667],"type":"Point"}
}