<<<<<<< HEAD
{
  "id": 2152302,
  "type": "Feature",
  "properties": {
    "tgn:hierarchy":[
        "tgn:2152302",
        "tgn:1000001",
        "tgn:7012149",
        "tgn:2000386",
        "tgn:7007248",
        "tgn:7029392"
    ],
    "tgn:id":2152302,
    "tgn:name":"Bay Hammock",
    "tgn:placetype":[
        "aat:300008791"
    ]
},
  "bbox": [],
  "geometry": {"coordinates":[-81.2,31.5167],"type":"Point"}
}
=======
{"geometry":{"type":"Point","coordinates":[-81.200000,31.516700]},"type":"Feature","properties":{"hierarchy":["tgn:2152302","tgn:1000001","tgn:7012149","tgn:2000386","tgn:7007248","tgn:7029392"],"placetype":["aat:300008791"],"id":2152302,"name:xx":"Bay Hammock"}}
>>>>>>> 03f74aca74312dbeaf24d7e61306dd6a786dc3d0
