{
  "id": 2347993,
  "type": "Feature",
  "properties": {
    "tgn:hierarchy":[
        "tgn:2347993",
        "tgn:2000192",
        "tgn:1000001",
        "tgn:7012149",
        "tgn:7007158",
        "tgn:7029392"
    ],
    "tgn:id":2347993,
    "tgn:name":"German Reservoir Number 2",
    "tgn:placetype":[
        "aat:300006191"
    ]
},
  "bbox": [],
  "geometry": {"coordinates":[-104.9167,39.9833],"type":"Point"}
}