{
  "id": 2302790,
  "type": "Feature",
  "properties": {
    "tgn:hierarchy":[
        "tgn:2302790",
        "tgn:1000001",
        "tgn:2002242",
        "tgn:7012149",
        "tgn:7007920",
        "tgn:7029392"
    ],
    "tgn:id":2302790,
    "tgn:name":"Dyer",
    "tgn:placetype":[
        "aat:300008347"
    ]
},
  "bbox": [],
  "geometry": {"coordinates":[-119.7667,47.9667],"type":"Point"}
}