{
  "id": 2341445,
  "type": "Feature",
  "properties": {
    "tgn:hierarchy":[
        "tgn:2341445",
        "tgn:1000001",
        "tgn:7012149",
        "tgn:2002341",
        "tgn:7007922",
        "tgn:7029392"
    ],
    "tgn:id":2341445,
    "tgn:name":"Frog Lake",
    "tgn:placetype":[
        "aat:300008680"
    ]
},
  "bbox": [],
  "geometry": {"coordinates":[-88.1833,45.1833],"type":"Point"}
}