{
  "id": 7001323,
  "type": "Feature",
  "properties": {
    "tgn:hierarchy":[
        "tgn:7001323",
        "tgn:1000004",
        "tgn:7000299",
        "tgn:7029392"
    ],
    "tgn:id":7001323,
    "tgn:name":"Kwangju-si",
    "tgn:placetype":[
        "aat:300387064",
        "aat:300387067"
    ]
},
  "bbox": [],
  "geometry": {"coordinates":[126.9167,35.1667],"type":"Point"}
}