{
  "id": 2734272,
  "type": "Feature",
  "properties": {
    "tgn:hierarchy":[
        "tgn:2734272",
        "tgn:1000001",
        "tgn:7012149",
        "tgn:2000928",
        "tgn:7007515",
        "tgn:7029392"
    ],
    "tgn:id":2734272,
    "tgn:name":"Turtle Cove",
    "tgn:placetype":[
        "aat:300132316"
    ]
},
  "bbox": [],
  "geometry": {"coordinates":[-69.15,45.25],"type":"Point"}
}