{
  "id": 2288781,
  "type": "Feature",
  "properties": {
    "tgn:hierarchy":[
        "tgn:2288781",
        "tgn:1000001",
        "tgn:7012149",
        "tgn:7007523",
        "tgn:7029392"
    ],
    "tgn:id":2288781,
    "tgn:name":"Ditch Number 251",
    "tgn:placetype":[
        "aat:300006075"
    ]
},
  "bbox": [],
  "geometry": {"coordinates":[-89.9167,36.3167],"type":"Point"}
}