{
  "id": 2239399,
  "type": "Feature",
  "properties": {
    "tgn:hierarchy":[
        "tgn:2239399",
        "tgn:1000001",
        "tgn:7012149",
        "tgn:2001536",
        "tgn:7007709",
        "tgn:7029392"
    ],
    "tgn:id":2239399,
    "tgn:name":"Church Creek",
    "tgn:placetype":[
        "aat:300008706"
    ]
},
  "bbox": [],
  "geometry": {"coordinates":[-80.45,35.5833],"type":"Point"}
}