{
  "id": 2764023,
  "type": "Feature",
  "properties": {
    "tgn:hierarchy":[
        "tgn:2764023",
        "tgn:1000001",
        "tgn:7012149",
        "tgn:2000220",
        "tgn:7007158",
        "tgn:7029392"
    ],
    "tgn:id":2764023,
    "tgn:name":"Wheeler Creek",
    "tgn:placetype":[
        "aat:300008706"
    ]
},
  "bbox": [],
  "geometry": {"coordinates":[-106.4667,40.9333],"type":"Point"}
}