{
  "id": 7391699,
  "type": "Feature",
  "properties": {
    "tgn:hierarchy":[
        "tgn:7391699",
        "tgn:1001853",
        "tgn:1000001",
        "tgn:7005560",
        "tgn:7029392"
    ],
    "tgn:id":7391699,
    "tgn:name":"Rancho Cuba",
    "tgn:placetype":[
        "aat:300008347"
    ]
},
  "bbox": [],
  "geometry": {"coordinates":[-103.45,25.25],"type":"Point"}
}