{
  "id": 2744209,
  "type": "Feature",
  "properties": {
    "tgn:hierarchy":[
        "tgn:2744209",
        "tgn:1000001",
        "tgn:7012149",
        "tgn:2002119",
        "tgn:7007827",
        "tgn:7029392"
    ],
    "tgn:id":2744209,
    "tgn:name":"Verdure",
    "tgn:placetype":[
        "aat:300008347"
    ]
},
  "bbox": [],
  "geometry": {"coordinates":[-109.3333,37.7833],"type":"Point"}
}