{
  "id": 2213409,
  "type": "Feature",
  "properties": {
    "tgn:hierarchy":[
        "tgn:2213409",
        "tgn:1000001",
        "tgn:7012149",
        "tgn:2002011",
        "tgn:7007826",
        "tgn:7029392"
    ],
    "tgn:id":2213409,
    "tgn:name":"Cabin Lake",
    "tgn:placetype":[
        "aat:300008680"
    ]
},
  "bbox": [],
  "geometry": {"coordinates":[-94.05,29.7667],"type":"Point"}
}