{
  "id": 2519684,
  "type": "Feature",
  "properties": {
    "tgn:hierarchy":[
        "tgn:2519684",
        "tgn:1000001",
        "tgn:7012149",
        "tgn:1002737",
        "tgn:7007520",
        "tgn:7029392"
    ],
    "tgn:id":2519684,
    "tgn:name":"Mohawk Lake",
    "tgn:placetype":[
        "aat:300008680"
    ]
},
  "bbox": [],
  "geometry": {"coordinates":[-83.3333,42.6833],"type":"Point"}
}