{
  "id": 2560777,
  "type": "Feature",
  "properties": {
    "tgn:hierarchy":[
        "tgn:2560777",
        "tgn:1000001",
        "tgn:7012149",
        "tgn:7014371",
        "tgn:7007248",
        "tgn:7029392"
    ],
    "tgn:id":2560777,
    "tgn:name":"Original Pond",
    "tgn:placetype":[
        "aat:300008680"
    ]
},
  "bbox": [],
  "geometry": {"coordinates":[-84.0333,30.6833],"type":"Point"}
}