{
  "id": 2303145,
  "type": "Feature",
  "properties": {
    "tgn:hierarchy":[
        "tgn:2303145",
        "tgn:1000001",
        "tgn:7012149",
        "tgn:2001449",
        "tgn:7007566",
        "tgn:7029392"
    ],
    "tgn:id":2303145,
    "tgn:name":"ET Tank",
    "tgn:placetype":[
        "aat:300006191"
    ]
},
  "bbox": [],
  "geometry": {"coordinates":[-106.85,36.4833],"type":"Point"}
}