{
  "id": 7328508,
  "type": "Feature",
  "properties": {
    "tgn:hierarchy":[
        "tgn:7328508",
        "tgn:7002810",
        "tgn:7001158",
        "tgn:1000003",
        "tgn:1000095",
        "tgn:7029392"
    ],
    "tgn:id":7328508,
    "tgn:name":"Quintanadue\u00f1as",
    "tgn:placetype":[
        "aat:300008347"
    ]
},
  "bbox": [],
  "geometry": {"coordinates":[-3.733333,42.383333],"type":"Point"}
}