{
  "id": 2348950,
  "type": "Feature",
  "properties": {
    "tgn:hierarchy":[
        "tgn:2348950",
        "tgn:1000001",
        "tgn:7012149",
        "tgn:2000996",
        "tgn:7007520",
        "tgn:7029392"
    ],
    "tgn:id":2348950,
    "tgn:name":"Gierke Creek",
    "tgn:placetype":[
        "aat:300008706"
    ]
},
  "bbox": [],
  "geometry": {"coordinates":[-86.3667,45.85],"type":"Point"}
}