{
  "id": 7325197,
  "type": "Feature",
  "properties": {
    "tgn:hierarchy":[
        "tgn:7325197",
        "tgn:7002807",
        "tgn:1000003",
        "tgn:7003837",
        "tgn:1000095",
        "tgn:7029392"
    ],
    "tgn:id":7325197,
    "tgn:name":"Santa Engracia",
    "tgn:placetype":[
        "aat:300008347"
    ]
},
  "bbox": [],
  "geometry": {"coordinates":[-6.966667,38.916667],"type":"Point"}
}