{
  "id": 2428765,
  "type": "Feature",
  "properties": {
    "tgn:hierarchy":[
        "tgn:2428765",
        "tgn:1000001",
        "tgn:7012149",
        "tgn:2001506",
        "tgn:7007709",
        "tgn:7029392"
    ],
    "tgn:id":2428765,
    "tgn:name":"July Point",
    "tgn:placetype":[
        "aat:300008850"
    ]
},
  "bbox": [],
  "geometry": {"coordinates":[-76.55,35.45],"type":"Point"}
}