{
  "id": 7137403,
  "type": "Feature",
  "properties": {
    "tgn:hierarchy":[
        "tgn:7137403",
        "tgn:7003669",
        "tgn:1000003",
        "tgn:7000084",
        "tgn:7029392"
    ],
    "tgn:id":7137403,
    "tgn:name":"Lanzenreuth",
    "tgn:placetype":[
        "aat:300008347"
    ]
},
  "bbox": [],
  "geometry": {"coordinates":[11.45,50.066667],"type":"Point"}
}