{
  "id": 7277530,
  "type": "Feature",
  "properties": {
    "tgn:hierarchy":[
        "tgn:7277530",
        "tgn:1001637",
        "tgn:1000049",
        "tgn:1000002",
        "tgn:7029392"
    ],
    "tgn:id":7277530,
    "tgn:name":"Lirqu\u00e9n, Estero",
    "tgn:placetype":[
        "aat:300008699"
    ]
},
  "bbox": [],
  "geometry": {"coordinates":[-72.975,-36.708333],"type":"Point"}
}