{
  "id": 7416165,
  "type": "Feature",
  "properties": {
    "tgn:hierarchy":[
        "tgn:7416165",
        "tgn:1000001",
        "tgn:7005591",
        "tgn:7005560",
        "tgn:7029392"
    ],
    "tgn:id":7416165,
    "tgn:name:es":"R\u00edo Verde",
    "tgn:placetype":[
        "aat:300008347"
    ]
},
  "bbox": [],
  "geometry": {"coordinates":[-94.751389,17.056944],"type":"Point"}
}