{
  "id": 1068515,
  "type": "Feature",
  "properties": {
    "tgn:hierarchy":[
        "tgn:1068515",
        "tgn:1000004",
        "tgn:7002077",
        "tgn:1000111",
        "tgn:7029392"
    ],
    "tgn:id":1068515,
    "tgn:name":"Guye",
    "tgn:placetype":[
        "aat:300008347"
    ]
},
  "bbox": [],
  "geometry": {"coordinates":[118.4167,39.7333],"type":"Point"}
}