{
  "id": 7474156,
  "type": "Feature",
  "properties": {
    "tgn:hierarchy":[
        "tgn:7474156",
        "tgn:1000004",
        "tgn:1000959",
        "tgn:1000141",
        "tgn:7029392"
    ],
    "tgn:id":7474156,
    "tgn:name":"Dingbeitou",
    "tgn:placetype":[
        "aat:300008347"
    ]
},
  "bbox": [],
  "geometry": {"coordinates":[121.483333,25.15],"type":"Point"}
}