<<<<<<< HEAD
{
  "id": 2339787,
  "type": "Feature",
  "properties": {
    "tgn:hierarchy":[
        "tgn:2339787",
        "tgn:1000001",
        "tgn:7006451",
        "tgn:7012149",
        "tgn:2000097",
        "tgn:7029392"
    ],
    "tgn:id":2339787,
    "tgn:name":"Freeman",
    "tgn:placetype":[
        "aat:300008347"
    ]
},
  "bbox": [],
  "geometry": {"coordinates":[-112.2833,32.8333],"type":"Point"}
}
=======
{"geometry":{"type":"Point","coordinates":[-112.283300,32.833300]},"type":"Feature","properties":{"hierarchy":["tgn:2339787","tgn:1000001","tgn:7006451","tgn:7012149","tgn:2000097","tgn:7029392"],"placetype":["aat:300008347"],"id":2339787,"name:xx":"Freeman"}}
>>>>>>> 03f74aca74312dbeaf24d7e61306dd6a786dc3d0
