{
  "id": 2781751,
  "type": "Feature",
  "properties": {
    "tgn:hierarchy":[
        "tgn:2781751",
        "tgn:1000001",
        "tgn:2001425",
        "tgn:7012149",
        "tgn:7007564",
        "tgn:7029392"
    ],
    "tgn:id":2781751,
    "tgn:name":"Woods Brook",
    "tgn:placetype":[
        "aat:300008699"
    ]
},
  "bbox": [],
  "geometry": {"coordinates":[-71.5667,43.2167],"type":"Point"}
}