{
  "id": 7237495,
  "type": "Feature",
  "properties": {
    "tgn:hierarchy":[
        "tgn:7237495",
        "tgn:1042193",
        "tgn:7002705",
        "tgn:1000003",
        "tgn:1000074",
        "tgn:7029392"
    ],
    "tgn:id":7237495,
    "tgn:name":"Dr\u00e9panou, \u00d3rmos",
    "tgn:placetype":[
        "aat:300132316"
    ]
},
  "bbox": [],
  "geometry": {"coordinates":[20.733333,38.766667],"type":"Point"}
}