{
  "id": 7457780,
  "type": "Feature",
  "properties": {
    "tgn:hierarchy":[
        "tgn:7457780",
        "tgn:7002443",
        "tgn:1000003",
        "tgn:7029493",
        "tgn:7008591",
        "tgn:7029392"
    ],
    "tgn:id":7457780,
    "tgn:name:en":"Penllech",
    "tgn:placetype":[
        "aat:300008347"
    ]
},
  "bbox": [],
  "geometry": {"coordinates":[-4.65,52.883333],"type":"Point"}
}