{
  "id": 7575611,
  "type": "Feature",
  "properties": {
    "tgn:hierarchy":[
        "tgn:7575611",
        "tgn:1000004",
        "tgn:1001869",
        "tgn:7000198",
        "tgn:7029392"
    ],
    "tgn:id":7575611,
    "tgn:name:en":"Koliy\u0101k",
    "tgn:placetype":[
        "aat:300008347"
    ]
},
  "bbox": [],
  "geometry": {"coordinates":[72.266667,21.616667],"type":"Point"}
}