{
  "id": 2031866,
  "type": "Feature",
  "properties": {
    "tgn:hierarchy":[
        "tgn:2031866",
        "tgn:1002143",
        "tgn:1000001",
        "tgn:7013933",
        "tgn:7012149",
        "tgn:7007252",
        "tgn:7029392"
    ],
    "tgn:id":2031866,
    "tgn:name":"Waynedale",
    "tgn:placetype":[
        "aat:300000745"
    ]
},
  "bbox": [],
  "geometry": {"coordinates":[-85.1667,41.0167],"type":"Point"}
}