{
  "id": 2171037,
  "type": "Feature",
  "properties": {
    "tgn:hierarchy":[
        "tgn:2171037",
        "tgn:1000001",
        "tgn:7012149",
        "tgn:7007157",
        "tgn:1002972",
        "tgn:7029392"
    ],
    "tgn:id":2171037,
    "tgn:name":"Big Spring",
    "tgn:placetype":[
        "aat:300008697"
    ]
},
  "bbox": [],
  "geometry": {"coordinates":[-118.9333,34.6667],"type":"Point"}
}