{
  "id": 2585549,
  "type": "Feature",
  "properties": {
    "tgn:hierarchy":[
        "tgn:2585549",
        "tgn:1000001",
        "tgn:7012149",
        "tgn:1002545",
        "tgn:7007157",
        "tgn:7029392"
    ],
    "tgn:id":2585549,
    "tgn:name":"Piojo Spring",
    "tgn:placetype":[
        "aat:300008697"
    ]
},
  "bbox": [],
  "geometry": {"coordinates":[-118.6167,35.4333],"type":"Point"}
}