{
  "id": 2542493,
  "type": "Feature",
  "properties": {
    "tgn:hierarchy":[
        "tgn:2542493",
        "tgn:1000001",
        "tgn:7012149",
        "tgn:2000476",
        "tgn:7007250",
        "tgn:7029392"
    ],
    "tgn:id":2542493,
    "tgn:name":"No-see-um Creek",
    "tgn:placetype":[
        "aat:300008706"
    ]
},
  "bbox": [],
  "geometry": {"coordinates":[-115.2667,46.3833],"type":"Point"}
}