{
  "id": 7532057,
  "type": "Feature",
  "properties": {
    "tgn:hierarchy":[
        "tgn:7532057",
        "tgn:7001242",
        "tgn:7016833",
        "tgn:1001335",
        "tgn:7029392"
    ],
    "tgn:id":7532057,
    "tgn:name:en":"Aul\u00e2d el-Q\u00e2\u1e0di",
    "tgn:placetype":[
        "aat:300008347"
    ]
},
  "bbox": [],
  "geometry": {"coordinates":[31.012578,31.5786],"type":"Point"}
}