{
  "id": 7301565,
  "type": "Feature",
  "properties": {
    "tgn:hierarchy":[
        "tgn:7301565",
        "tgn:7001122",
        "tgn:1000003",
        "tgn:7002765",
        "tgn:1000095",
        "tgn:7029392"
    ],
    "tgn:id":7301565,
    "tgn:name":"Menorca, Cabo",
    "tgn:placetype":[
        "aat:300008850"
    ]
},
  "bbox": [],
  "geometry": {"coordinates":[3.75,40.033333],"type":"Point"}
}