<<<<<<< HEAD
{
  "id": 7020485,
  "type": "Feature",
  "properties": {
    "tgn:hierarchy":[
        "tgn:7020485",
        "tgn:1000001",
        "tgn:7012149",
        "tgn:2001538",
        "tgn:7007709",
        "tgn:7029392"
    ],
    "tgn:id":7020485,
    "tgn:name":"Suttentown",
    "tgn:placetype":[
        "aat:300008347",
        "aat:300387210"
    ]
},
  "bbox": [],
  "geometry": {"coordinates":[-78.25,35.2],"type":"Point"}
}
=======
{"geometry":{"type":"Point","coordinates":[-78.250000,35.200000]},"type":"Feature","properties":{"hierarchy":["tgn:7020485","tgn:1000001","tgn:7012149","tgn:2001538","tgn:7007709","tgn:7029392"],"placetype":["aat:300008347","aat:300387210"],"id":7020485,"name:xx":"Suttentown"}}
>>>>>>> 03f74aca74312dbeaf24d7e61306dd6a786dc3d0
