{
  "id": 7224781,
  "type": "Feature",
  "properties": {
    "tgn:hierarchy":[
        "tgn:7224781",
        "tgn:7002680",
        "tgn:7001395",
        "tgn:1000003",
        "tgn:1000074",
        "tgn:7029392"
    ],
    "tgn:id":7224781,
    "tgn:name":"R\u00edon, \u00c1kra",
    "tgn:placetype":[
        "aat:300386846"
    ]
},
  "bbox": [],
  "geometry": {"coordinates":[21.783333,38.316667],"type":"Point"}
}