{
  "id": 1135060,
  "type": "Feature",
  "properties": {
    "tgn:hierarchy":[
        "tgn:1135060",
        "tgn:1000001",
        "tgn:7012149",
        "tgn:7007157",
        "tgn:1002656",
        "tgn:7029392"
    ],
    "tgn:id":1135060,
    "tgn:name":"Wildcat Creek",
    "tgn:placetype":[
        "aat:300008706"
    ]
},
  "bbox": [],
  "geometry": {"coordinates":[-121.0667,36.9167],"type":"Point"}
}