{
  "id": 7535269,
  "type": "Feature",
  "properties": {
    "tgn:hierarchy":[
        "tgn:7535269",
        "tgn:7001242",
        "tgn:7016833",
        "tgn:7001335",
        "tgn:7029392"
    ],
    "tgn:id":7535269,
    "tgn:name:en":"\u1e28amz\u0327, W\u0101d\u012b al",
    "tgn:placetype":[
        "aat:300379998"
    ]
},
  "bbox": [],
  "geometry": {"coordinates":[33.755206,30.099628],"type":"Point"}
}