{
  "id": 2752664,
  "type": "Feature",
  "properties": {
    "tgn:hierarchy":[
        "tgn:2752664",
        "tgn:1000001",
        "tgn:7012149",
        "tgn:1002990",
        "tgn:7007708",
        "tgn:7029392"
    ],
    "tgn:id":2752664,
    "tgn:name":"Wassen Pond",
    "tgn:placetype":[
        "aat:300008680"
    ]
},
  "bbox": [],
  "geometry": {"coordinates":[-121.2667,45.5833],"type":"Point"}
}