{
  "id": 7592362,
  "type": "Feature",
  "properties": {
    "tgn:hierarchy":[
        "tgn:7592362",
        "tgn:1000004",
        "tgn:7000198",
        "tgn:7016722",
        "tgn:7029392"
    ],
    "tgn:id":7592362,
    "tgn:name:en":"Th\u0101pal D\u0101ndi Protected Forest",
    "tgn:placetype":[
        "aat:300008865"
    ]
},
  "bbox": [],
  "geometry": {"coordinates":[77.829406,30.116518],"type":"Point"}
}