{
  "id": 2530772,
  "type": "Feature",
  "properties": {
    "tgn:hierarchy":[
        "tgn:2530772",
        "tgn:1000001",
        "tgn:7012149",
        "tgn:1002732",
        "tgn:7007710",
        "tgn:7029392"
    ],
    "tgn:id":2530772,
    "tgn:name":"Muddy Run",
    "tgn:placetype":[
        "aat:300008699"
    ]
},
  "bbox": [],
  "geometry": {"coordinates":[-76.7667,41.05],"type":"Point"}
}