{
  "id": 2199461,
  "type": "Feature",
  "properties": {
    "tgn:hierarchy":[
        "tgn:2199461",
        "tgn:1000001",
        "tgn:7012149",
        "tgn:2001139",
        "tgn:7007522",
        "tgn:7029392"
    ],
    "tgn:id":2199461,
    "tgn:name":"Brush Creek",
    "tgn:placetype":[
        "aat:300008706"
    ]
},
  "bbox": [],
  "geometry": {"coordinates":[-89.8667,34.3833],"type":"Point"}
}