{
  "id": 7402484,
  "type": "Feature",
  "properties": {
    "tgn:hierarchy":[
        "tgn:7402484",
        "tgn:1000001",
        "tgn:1001937",
        "tgn:7005560",
        "tgn:7029392"
    ],
    "tgn:id":7402484,
    "tgn:name":"Ziquipal",
    "tgn:placetype":[
        "aat:300008347"
    ]
},
  "bbox": [],
  "geometry": {"coordinates":[-87.4375,19.316667],"type":"Point"}
}