{
  "id": 7008936,
  "type": "Feature",
  "properties": {
    "tgn:hierarchy":[
        "tgn:7008936",
        "tgn:1000003",
        "tgn:7001097",
        "tgn:1000070",
        "tgn:7029392"
    ],
    "tgn:id":7008936,
    "tgn:name":"Bailleul",
    "tgn:placetype":[
        "aat:300008347"
    ]
},
  "bbox": [],
  "geometry": {"coordinates":[2.7333,50.7333],"type":"Point"}
}