{
  "id": 2700958,
  "type": "Feature",
  "properties": {
    "tgn:hierarchy":[
        "tgn:2700958",
        "tgn:1000001",
        "tgn:7012149",
        "tgn:1002991",
        "tgn:7007251",
        "tgn:7029392"
    ],
    "tgn:id":2700958,
    "tgn:name":"Sugar Creek",
    "tgn:placetype":[
        "aat:300008706"
    ]
},
  "bbox": [],
  "geometry": {"coordinates":[-89.4167,38.2333],"type":"Point"}
}