{
  "id": 1121598,
  "type": "Feature",
  "properties": {
    "tgn:hierarchy":[
        "tgn:1121598",
        "tgn:7001242",
        "tgn:7029392"
    ],
    "tgn:id":1121598,
    "tgn:name":"Bafing",
    "tgn:placetype":[
        "aat:300008707"
    ]
},
  "bbox": [],
  "geometry": {"coordinates":[-10.8333,13.8167],"type":"Point"}
}