{
  "id": 7458987,
  "type": "Feature",
  "properties": {
    "tgn:hierarchy":[
        "tgn:7458987",
        "tgn:7019182",
        "tgn:7002448",
        "tgn:1000003",
        "tgn:7008591",
        "tgn:7029392"
    ],
    "tgn:id":7458987,
    "tgn:name:en":"Newcastle",
    "tgn:placetype":[
        "aat:300008347"
    ]
},
  "bbox": [],
  "geometry": {"coordinates":[-5.466667,54.383333],"type":"Point"}
}