{
  "id": 7535053,
  "type": "Feature",
  "properties": {
    "tgn:hierarchy":[
        "tgn:7535053",
        "tgn:7001242",
        "tgn:7016833",
        "tgn:1001113",
        "tgn:7029392"
    ],
    "tgn:id":7535053,
    "tgn:name":"Kafr Ab\u016b Q\u016brah",
    "tgn:placetype":[
        "aat:300008347"
    ]
},
  "bbox": [],
  "geometry": {"coordinates":[31.716667,30.716667],"type":"Point"}
}