{
  "id": 2397797,
  "type": "Feature",
  "properties": {
    "tgn:hierarchy":[
        "tgn:2397797",
        "tgn:1000001",
        "tgn:7012149",
        "tgn:1002870",
        "tgn:7007240",
        "tgn:7029392"
    ],
    "tgn:id":2397797,
    "tgn:name":"Honore",
    "tgn:placetype":[
        "aat:300008347"
    ]
},
  "bbox": [],
  "geometry": {"coordinates":[-82.25,27.2333],"type":"Point"}
}