{
  "id": 2237902,
  "type": "Feature",
  "properties": {
    "tgn:hierarchy":[
        "tgn:2237902",
        "tgn:1000001",
        "tgn:7012149",
        "tgn:2002358",
        "tgn:7007922",
        "tgn:7029392"
    ],
    "tgn:id":2237902,
    "tgn:name":"Chipmunk Ridge",
    "tgn:placetype":[
        "aat:300266640"
    ]
},
  "bbox": [],
  "geometry": {"coordinates":[-91.1667,43.6833],"type":"Point"}
}