<<<<<<< HEAD
{
  "id": 7366335,
  "type": "Feature",
  "properties": {
    "tgn:hierarchy":[
        "tgn:7366335",
        "tgn:1000001",
        "tgn:1001960",
        "tgn:7005560",
        "tgn:7029392"
    ],
    "tgn:id":7366335,
    "tgn:name":"Rancho El Pe\u00f1asco",
    "tgn:placetype":[
        "aat:300000241"
    ]
},
  "bbox": [],
  "geometry": {"coordinates":[-109.433333,29.816667],"type":"Point"}
}
=======
{"geometry":{"type":"Point","coordinates":[-109.433333,29.816667]},"type":"Feature","properties":{"hierarchy":["tgn:7366335","tgn:1000001","tgn:1001960","tgn:7005560","tgn:7029392"],"placetype":["aat:300000241"],"id":7366335,"name:xx":"Rancho El Pe\u00f1asco"}}
>>>>>>> 03f74aca74312dbeaf24d7e61306dd6a786dc3d0
