{
  "id": 2161681,
  "type": "Feature",
  "properties": {
    "tgn:hierarchy":[
        "tgn:2161681",
        "tgn:1000001",
        "tgn:2001748",
        "tgn:7012149",
        "tgn:7007712",
        "tgn:7029392"
    ],
    "tgn:id":2161681,
    "tgn:name":"Belle Meade",
    "tgn:placetype":[
        "aat:300008347"
    ]
},
  "bbox": [],
  "geometry": {"coordinates":[-82.1667,34.2167],"type":"Point"}
}