<<<<<<< HEAD
{
  "id": 7477075,
  "type": "Feature",
  "properties": {
    "tgn:hierarchy":[
        "tgn:7477075",
        "tgn:1000004",
        "tgn:7004300",
        "tgn:1000141",
        "tgn:7029392"
    ],
    "tgn:id":7477075,
    "tgn:name":"Dong'an Gong",
    "tgn:placetype":[
        "aat:300007595"
    ]
},
  "bbox": [],
  "geometry": {"coordinates":[119.594916,23.551484],"type":"Point"}
}
=======
{"geometry":{"type":"Point","coordinates":[119.594916,23.551484]},"type":"Feature","properties":{"hierarchy":["tgn:7477075","tgn:1000004","tgn:7004300","tgn:1000141","tgn:7029392"],"placetype":["aat:300007595"],"id":7477075,"name:xx":"Dong'an Gong"}}
>>>>>>> 03f74aca74312dbeaf24d7e61306dd6a786dc3d0
