{
  "id": 7477075,
  "type": "Feature",
  "properties": {
    "tgn:hierarchy":[
        "tgn:7477075",
        "tgn:1000004",
        "tgn:7004300",
        "tgn:1000141",
        "tgn:7029392"
    ],
    "tgn:id":7477075,
    "tgn:name":"Dong'an Gong",
    "tgn:placetype":[
        "aat:300007595"
    ]
},
  "bbox": [],
  "geometry": {"coordinates":[119.594916,23.551484],"type":"Point"}
}