{
  "id": 2455358,
  "type": "Feature",
  "properties": {
    "tgn:hierarchy":[
        "tgn:2455358",
        "tgn:1000001",
        "tgn:7012149",
        "tgn:2002264",
        "tgn:7013961",
        "tgn:7029392"
    ],
    "tgn:id":2455358,
    "tgn:name":"Little Fork",
    "tgn:placetype":[
        "aat:300008699"
    ]
},
  "bbox": [],
  "geometry": {"coordinates":[-80.6833,38.0333],"type":"Point"}
}