{
  "id": 7219787,
  "type": "Feature",
  "properties": {
    "tgn:hierarchy":[
        "tgn:7219787",
        "tgn:7002711",
        "tgn:7001338",
        "tgn:1000003",
        "tgn:1000074",
        "tgn:7029392"
    ],
    "tgn:id":7219787,
    "tgn:name":"V\u00edngla",
    "tgn:placetype":[
        "aat:300008347"
    ]
},
  "bbox": [],
  "geometry": {"coordinates":[19.933333,39.75],"type":"Point"}
}