{
  "id": 2409641,
  "type": "Feature",
  "properties": {
    "tgn:hierarchy":[
        "tgn:2409641",
        "tgn:1000001",
        "tgn:7012149",
        "tgn:2000812",
        "tgn:7007255",
        "tgn:7029392"
    ],
    "tgn:id":2409641,
    "tgn:name":"Ike Branch",
    "tgn:placetype":[
        "aat:300008699"
    ]
},
  "bbox": [],
  "geometry": {"coordinates":[-82.9167,37.05],"type":"Point"}
}