{
  "id": 7473537,
  "type": "Feature",
  "properties": {
    "tgn:hierarchy":[
        "tgn:7473537",
        "tgn:1000004",
        "tgn:7001009",
        "tgn:1000141",
        "tgn:7029392"
    ],
    "tgn:id":7473537,
    "tgn:name":"Dinglaoxu",
    "tgn:placetype":[
        "aat:300008347"
    ]
},
  "bbox": [],
  "geometry": {"coordinates":[120.606542,24.119442],"type":"Point"}
}