{
  "id": 7322890,
  "type": "Feature",
  "properties": {
    "tgn:hierarchy":[
        "tgn:7322890",
        "tgn:7002758",
        "tgn:7002841",
        "tgn:1000003",
        "tgn:1000095",
        "tgn:7029392"
    ],
    "tgn:id":7322890,
    "tgn:name":"Salado, Arroyo del",
    "tgn:placetype":[
        "aat:300008699"
    ]
},
  "bbox": [],
  "geometry": {"coordinates":[-5.433333,37.383333],"type":"Point"}
}