{
  "id": 7041049,
  "type": "Feature",
  "properties": {
    "tgn:hierarchy":[
        "tgn:7041049",
        "tgn:1000003",
        "tgn:7003122",
        "tgn:7003157",
        "tgn:1000080",
        "tgn:7029392"
    ],
    "tgn:id":7041049,
    "tgn:name":"San Como",
    "tgn:placetype":[
        "aat:300008347"
    ]
},
  "bbox": [],
  "geometry": {"coordinates":[15.416667,38.166667],"type":"Point"}
}