{
  "id": 7106571,
  "type": "Feature",
  "properties": {
    "tgn:hierarchy":[
        "tgn:7106571",
        "tgn:7003669",
        "tgn:1000003",
        "tgn:7000084",
        "tgn:7029392"
    ],
    "tgn:id":7106571,
    "tgn:name":"Schmidhausen",
    "tgn:placetype":[
        "aat:300008347"
    ]
},
  "bbox": [],
  "geometry": {"coordinates":[11.433333,48.516667],"type":"Point"}
}