{
  "id": 7497676,
  "type": "Feature",
  "properties": {
    "tgn:hierarchy":[
        "tgn:7497676",
        "tgn:1000004",
        "tgn:1000454",
        "tgn:1000141",
        "tgn:7029392"
    ],
    "tgn:id":7497676,
    "tgn:name":"Nanshi",
    "tgn:placetype":[
        "aat:300008347"
    ]
},
  "bbox": [],
  "geometry": {"coordinates":[121.364896,25.07136],"type":"Point"}
}