{
  "id": 1117932,
  "type": "Feature",
  "properties": {
    "tgn:hierarchy":[
        "tgn:1117932",
        "tgn:7002445",
        "tgn:7008114",
        "tgn:1000003",
        "tgn:7008591",
        "tgn:7029392"
    ],
    "tgn:id":1117932,
    "tgn:name":"Rostherne Mere",
    "tgn:placetype":[
        "aat:300008680"
    ]
},
  "bbox": [],
  "geometry": {"coordinates":[-2.3833,53.35],"type":"Point"}
}