{
  "id": 2732965,
  "type": "Feature",
  "properties": {
    "tgn:hierarchy":[
        "tgn:2732965",
        "tgn:1000001",
        "tgn:7012149",
        "tgn:7007157",
        "tgn:1002791",
        "tgn:7029392"
    ],
    "tgn:id":2732965,
    "tgn:name":"Turkey Hill Mine",
    "tgn:placetype":[
        "aat:300000390"
    ]
},
  "bbox": [],
  "geometry": {"coordinates":[-120.7167,39.05],"type":"Point"}
}