{
  "id": 7470051,
  "type": "Feature",
  "properties": {
    "tgn:hierarchy":[
        "tgn:7470051",
        "tgn:1000004",
        "tgn:7491221",
        "tgn:1000141",
        "tgn:7029392"
    ],
    "tgn:id":7470051,
    "tgn:name":"Qingfeng",
    "tgn:placetype":[
        "aat:300008347"
    ]
},
  "bbox": [],
  "geometry": {"coordinates":[121.230556,23.129444],"type":"Point"}
}