<<<<<<< HEAD
{
  "id": 2401844,
  "type": "Feature",
  "properties": {
    "tgn:hierarchy":[
        "tgn:2401844",
        "tgn:1000001",
        "tgn:7012149",
        "tgn:2001712",
        "tgn:7007708",
        "tgn:7029392"
    ],
    "tgn:id":2401844,
    "tgn:name":"Horseshoe Lake",
    "tgn:placetype":[
        "aat:300008680"
    ]
},
  "bbox": [],
  "geometry": {"coordinates":[-121.7833,44.7667],"type":"Point"}
}
=======
{"geometry":{"type":"Point","coordinates":[-121.783300,44.766700]},"type":"Feature","properties":{"hierarchy":["tgn:2401844","tgn:1000001","tgn:7012149","tgn:2001712","tgn:7007708","tgn:7029392"],"placetype":["aat:300008680"],"id":2401844,"name:xx":"Horseshoe Lake"}}
>>>>>>> 03f74aca74312dbeaf24d7e61306dd6a786dc3d0
