{
  "id": 7029395,
  "type": "Feature",
  "properties": {
    "tgn:hierarchy":[
        "tgn:7029395",
        "tgn:7002445",
        "tgn:1000003",
        "tgn:7019057",
        "tgn:7008591",
        "tgn:7029392"
    ],
    "tgn:id":7029395,
    "tgn:name":"Sunderlandwick",
    "tgn:placetype":[
        "aat:300020756",
        "aat:300008347",
        "aat:300167671",
        "aat:300008372"
    ]
},
  "bbox": [],
  "geometry": {"coordinates":[-0.457,53.983],"type":"Point"}
}