{
  "id": 2310320,
  "type": "Feature",
  "properties": {
    "tgn:hierarchy":[
        "tgn:2310320",
        "tgn:1000001",
        "tgn:7012149",
        "tgn:2002055",
        "tgn:7007826",
        "tgn:7029392"
    ],
    "tgn:id":2310320,
    "tgn:name":"Ebers Tank",
    "tgn:placetype":[
        "aat:300006191"
    ]
},
  "bbox": [],
  "geometry": {"coordinates":[-102.65,30.4167],"type":"Point"}
}