{
  "id": 2030552,
  "type": "Feature",
  "properties": {
    "tgn:hierarchy":[
        "tgn:2030552",
        "tgn:1000001",
        "tgn:7012149",
        "tgn:1002632",
        "tgn:7007251",
        "tgn:7029392"
    ],
    "tgn:id":2030552,
    "tgn:name":"Walnut Hill",
    "tgn:placetype":[
        "aat:300008347"
    ]
},
  "bbox": [],
  "geometry": {"coordinates":[-89.0333,38.4667],"type":"Point"}
}