{
  "id": 2414440,
  "type": "Feature",
  "properties": {
    "tgn:hierarchy":[
        "tgn:2414440",
        "tgn:1000001",
        "tgn:7012149",
        "tgn:7007158",
        "tgn:2000248",
        "tgn:7029392"
    ],
    "tgn:id":2414440,
    "tgn:name":"Iron Springs Mesa",
    "tgn:placetype":[
        "aat:300008798"
    ]
},
  "bbox": [],
  "geometry": {"coordinates":[-108.0833,38.0333],"type":"Point"}
}