<<<<<<< HEAD
{
  "id": 2762504,
  "type": "Feature",
  "properties": {
    "tgn:hierarchy":[
        "tgn:2762504",
        "tgn:1000001",
        "tgn:7012149",
        "tgn:1003038",
        "tgn:7007517",
        "tgn:7029392"
    ],
    "tgn:id":2762504,
    "tgn:name":"West Waushacum Pond",
    "tgn:placetype":[
        "aat:300008680"
    ]
},
  "bbox": [],
  "geometry": {"coordinates":[-71.75,42.4],"type":"Point"}
}
=======
{"geometry":{"type":"Point","coordinates":[-71.750000,42.400000]},"type":"Feature","properties":{"hierarchy":["tgn:2762504","tgn:1000001","tgn:7012149","tgn:1003038","tgn:7007517","tgn:7029392"],"placetype":["aat:300008680"],"id":2762504,"name:xx":"West Waushacum Pond"}}
>>>>>>> 03f74aca74312dbeaf24d7e61306dd6a786dc3d0
