{
  "id": 2673937,
  "type": "Feature",
  "properties": {
    "tgn:hierarchy":[
        "tgn:2673937",
        "tgn:1000001",
        "tgn:7012149",
        "tgn:2000931",
        "tgn:7007515",
        "tgn:7029392"
    ],
    "tgn:id":2673937,
    "tgn:name":"Snow Mountain",
    "tgn:placetype":[
        "aat:300008798"
    ]
},
  "bbox": [],
  "geometry": {"coordinates":[-68.9333,44.65],"type":"Point"}
}