{
  "id": 7383796,
  "type": "Feature",
  "properties": {
    "tgn:hierarchy":[
        "tgn:7383796",
        "tgn:1000001",
        "tgn:7005600",
        "tgn:7005560",
        "tgn:7029392"
    ],
    "tgn:id":7383796,
    "tgn:name":"Para\u00edso",
    "tgn:placetype":[
        "aat:300008347"
    ]
},
  "bbox": [],
  "geometry": {"coordinates":[-103.033333,24.366667],"type":"Point"}
}