<<<<<<< HEAD
{
  "id": 7359061,
  "type": "Feature",
  "properties": {
    "tgn:hierarchy":[
        "tgn:7359061",
        "tgn:1000001",
        "tgn:7005595",
        "tgn:7005560",
        "tgn:7029392"
    ],
    "tgn:id":7359061,
    "tgn:name":"El Aguajito",
    "tgn:placetype":[
        "aat:300008347"
    ]
},
  "bbox": [],
  "geometry": {"coordinates":[-107.666667,25.55],"type":"Point"}
}
=======
{"geometry":{"type":"Point","coordinates":[-107.666667,25.550000]},"type":"Feature","properties":{"hierarchy":["tgn:7359061","tgn:1000001","tgn:7005595","tgn:7005560","tgn:7029392"],"placetype":["aat:300008347"],"id":7359061,"name:xx":"El Aguajito"}}
>>>>>>> 03f74aca74312dbeaf24d7e61306dd6a786dc3d0
