{
  "id": 7359061,
  "type": "Feature",
  "properties": {
    "tgn:hierarchy":[
        "tgn:7359061",
        "tgn:1000001",
        "tgn:7005595",
        "tgn:7005560",
        "tgn:7029392"
    ],
    "tgn:id":7359061,
    "tgn:name":"El Aguajito",
    "tgn:placetype":[
        "aat:300008347"
    ]
},
  "bbox": [],
  "geometry": {"coordinates":[-107.666667,25.55],"type":"Point"}
}