{
  "id": 2754355,
  "type": "Feature",
  "properties": {
    "tgn:hierarchy":[
        "tgn:2754355",
        "tgn:1000001",
        "tgn:7012149",
        "tgn:7013855",
        "tgn:7007251",
        "tgn:7029392"
    ],
    "tgn:id":2754355,
    "tgn:name":"Waukegan River",
    "tgn:placetype":[
        "aat:300008707"
    ]
},
  "bbox": [],
  "geometry": {"coordinates":[-87.8333,42.3333],"type":"Point"}
}