<<<<<<< HEAD
{
  "id": 2256432,
  "type": "Feature",
  "properties": {
    "tgn:hierarchy":[
        "tgn:2256432",
        "tgn:1000001",
        "tgn:7012149",
        "tgn:2000363",
        "tgn:7007248",
        "tgn:7029392"
    ],
    "tgn:id":2256432,
    "tgn:name":"Cora, Lake",
    "tgn:placetype":[
        "aat:300006191"
    ]
},
  "bbox": [],
  "geometry": {"coordinates":[-84.85,32.5833],"type":"Point"}
}
=======
{"geometry":{"type":"Point","coordinates":[-84.850000,32.583300]},"type":"Feature","properties":{"hierarchy":["tgn:2256432","tgn:1000001","tgn:7012149","tgn:2000363","tgn:7007248","tgn:7029392"],"placetype":["aat:300006191"],"id":2256432,"name:xx":"Cora, Lake"}}
>>>>>>> 03f74aca74312dbeaf24d7e61306dd6a786dc3d0
