{
  "id": 2706152,
  "type": "Feature",
  "properties": {
    "tgn:hierarchy":[
        "tgn:2706152",
        "tgn:1000001",
        "tgn:2000780",
        "tgn:7012149",
        "tgn:7007255",
        "tgn:7029392"
    ],
    "tgn:id":2706152,
    "tgn:name":"Swallow Spring Pond",
    "tgn:placetype":[
        "aat:300008680"
    ]
},
  "bbox": [],
  "geometry": {"coordinates":[-87.5167,36.7667],"type":"Point"}
}