{
  "id": 2744284,
  "type": "Feature",
  "properties": {
    "tgn:hierarchy":[
        "tgn:2744284",
        "tgn:7006450",
        "tgn:1000001",
        "tgn:7012149",
        "tgn:2000089",
        "tgn:7029392"
    ],
    "tgn:id":2744284,
    "tgn:name":"Vermont Creek",
    "tgn:placetype":[
        "aat:300008706"
    ]
},
  "bbox": [],
  "geometry": {"coordinates":[-150.2167,67.5167],"type":"Point"}
}