{
  "id": 1073812,
  "type": "Feature",
  "properties": {
    "tgn:hierarchy":[
        "tgn:1073812",
        "tgn:1000004",
        "tgn:7002077",
        "tgn:1000111",
        "tgn:7029392"
    ],
    "tgn:id":1073812,
    "tgn:name":"Zengjiawan",
    "tgn:placetype":[
        "aat:300008347"
    ]
},
  "bbox": [],
  "geometry": {"coordinates":[118.3833,39.3667],"type":"Point"}
}