{
  "id": 7000395,
  "type": "Feature",
  "properties": {
    "tgn:hierarchy":[
        "tgn:7000395",
        "tgn:7001242",
        "tgn:1000955",
        "tgn:1000180",
        "tgn:7029392"
    ],
    "tgn:id":7000395,
    "tgn:name":"Quelimane",
    "tgn:placetype":[
        "aat:300008347",
        "aat:300387223",
        "aat:300008375",
        "aat:300120599"
    ]
},
  "bbox": [],
  "geometry": {"coordinates":[36.85,-17.8833],"type":"Point"}
}