{
  "id": 1056972,
  "type": "Feature",
  "properties": {
    "tgn:hierarchy":[
        "tgn:1056972",
        "tgn:1000004",
        "tgn:7012215",
        "tgn:7006653",
        "tgn:7029392"
    ],
    "tgn:id":1056972,
    "tgn:name":"Senaki",
    "tgn:placetype":[
        "aat:300008347"
    ]
},
  "bbox": [],
  "geometry": {"coordinates":[42.0667,42.2833],"type":"Point"}
}