{
  "id": 7246905,
  "type": "Feature",
  "properties": {
    "tgn:hierarchy":[
        "tgn:7246905",
        "tgn:7003456",
        "tgn:1000003",
        "tgn:1000063",
        "tgn:7018236",
        "tgn:7029392"
    ],
    "tgn:id":7246905,
    "tgn:name":"Donk",
    "tgn:placetype":[
        "aat:300008347"
    ]
},
  "bbox": [],
  "geometry": {"coordinates":[4.542957,51.13714],"type":"Point"}
}