{
  "id": 7034020,
  "type": "Feature",
  "properties": {
    "tgn:hierarchy":[
        "tgn:7034020",
        "tgn:1001641",
        "tgn:1000003",
        "tgn:7003121",
        "tgn:1000080",
        "tgn:7029392"
    ],
    "tgn:id":7034020,
    "tgn:name":"Ella, Cuccuru",
    "tgn:placetype":[
        "aat:300008798"
    ]
},
  "bbox": [],
  "geometry": {"coordinates":[9.406111,39.204722],"type":"Point"}
}