{
  "id": 7492366,
  "type": "Feature",
  "properties": {
    "tgn:hierarchy":[
        "tgn:7492366",
        "tgn:1000004",
        "tgn:7004300",
        "tgn:1000141",
        "tgn:7029392"
    ],
    "tgn:id":7492366,
    "tgn:name":"Penghu'ercun",
    "tgn:placetype":[
        "aat:300008347"
    ]
},
  "bbox": [],
  "geometry": {"coordinates":[119.566667,23.566667],"type":"Point"}
}