{
  "id": 7221532,
  "type": "Feature",
  "properties": {
    "tgn:hierarchy":[
        "tgn:7221532",
        "tgn:7002711",
        "tgn:7001338",
        "tgn:1000003",
        "tgn:1000074",
        "tgn:7029392"
    ],
    "tgn:id":7221532,
    "tgn:name":"Pax\u00f3n, Th\u00e1lassa",
    "tgn:placetype":[
        "aat:300266559"
    ]
},
  "bbox": [],
  "geometry": {"coordinates":[20.286667,39.238611],"type":"Point"}
}