{
  "id": 2304591,
  "type": "Feature",
  "properties": {
    "tgn:hierarchy":[
        "tgn:2304591",
        "tgn:1000001",
        "tgn:1002313",
        "tgn:7012149",
        "tgn:7007706",
        "tgn:7029392"
    ],
    "tgn:id":2304591,
    "tgn:name":"East Basin",
    "tgn:placetype":[
        "aat:300386845"
    ]
},
  "bbox": [],
  "geometry": {"coordinates":[-81.6667,41.5167],"type":"Point"}
}