{
  "id": 1060042,
  "type": "Feature",
  "properties": {
    "tgn:hierarchy":[
        "tgn:1060042",
        "tgn:1000004",
        "tgn:1003398",
        "tgn:7018214",
        "tgn:7002435",
        "tgn:7029392"
    ],
    "tgn:id":1060042,
    "tgn:name":"Tyul'gan",
    "tgn:placetype":[
        "aat:300008347"
    ]
},
  "bbox": [],
  "geometry": {"coordinates":[56.15,52.3833],"type":"Point"}
}