<<<<<<< HEAD
{
  "id": 7354476,
  "type": "Feature",
  "properties": {
    "tgn:hierarchy":[
        "tgn:7354476",
        "tgn:1000001",
        "tgn:7005595",
        "tgn:7005560",
        "tgn:7029392"
    ],
    "tgn:id":7354476,
    "tgn:name":"Chapote",
    "tgn:placetype":[
        "aat:300008347"
    ]
},
  "bbox": [],
  "geometry": {"coordinates":[-107.75,25.2],"type":"Point"}
}
=======
{"geometry":{"type":"Point","coordinates":[-107.750000,25.200000]},"type":"Feature","properties":{"hierarchy":["tgn:7354476","tgn:1000001","tgn:7005595","tgn:7005560","tgn:7029392"],"placetype":["aat:300008347"],"id":7354476,"name:xx":"Chapote"}}
>>>>>>> 03f74aca74312dbeaf24d7e61306dd6a786dc3d0
