{
  "id": 1111355,
  "type": "Feature",
  "properties": {
    "tgn:hierarchy":[
        "tgn:1111355",
        "tgn:7005735",
        "tgn:7005685",
        "tgn:1000001",
        "tgn:7029392"
    ],
    "tgn:id":1111355,
    "tgn:name":"Hells Gate",
    "tgn:placetype":[
        "aat:300008763"
    ]
},
  "bbox": [],
  "geometry": {"coordinates":[-121.45,49.7833],"type":"Point"}
}