{
  "id": 7341496,
  "type": "Feature",
  "properties": {
    "tgn:hierarchy":[
        "tgn:7341496",
        "tgn:7002758",
        "tgn:7002817",
        "tgn:1000003",
        "tgn:1000095",
        "tgn:7029392"
    ],
    "tgn:id":7341496,
    "tgn:name":"Boquinete, Arroyo de",
    "tgn:placetype":[
        "aat:300266554",
        "aat:300008699"
    ]
},
  "bbox": [],
  "geometry": {"coordinates":[-5.35,37.85],"type":"Point"}
}