<<<<<<< HEAD
{
  "id": 7365831,
  "type": "Feature",
  "properties": {
    "tgn:hierarchy":[
        "tgn:7365831",
        "tgn:1000001",
        "tgn:7005597",
        "tgn:7005560",
        "tgn:7029392"
    ],
    "tgn:id":7365831,
    "tgn:name":"Ensenada Ferrocarril",
    "tgn:placetype":[
        "aat:300007783"
    ]
},
  "bbox": [],
  "geometry": {"coordinates":[-97.85,25.966667],"type":"Point"}
}
=======
{"geometry":{"type":"Point","coordinates":[-97.850000,25.966667]},"type":"Feature","properties":{"hierarchy":["tgn:7365831","tgn:1000001","tgn:7005597","tgn:7005560","tgn:7029392"],"placetype":["aat:300007783"],"id":7365831,"name:xx":"Ensenada Ferrocarril"}}
>>>>>>> 03f74aca74312dbeaf24d7e61306dd6a786dc3d0
