{
  "id": 7297317,
  "type": "Feature",
  "properties": {
    "tgn:hierarchy":[
        "tgn:7297317",
        "tgn:7008912",
        "tgn:7030216",
        "tgn:1000003",
        "tgn:1000095",
        "tgn:7029392"
    ],
    "tgn:id":7297317,
    "tgn:name":"Talladell",
    "tgn:placetype":[
        "aat:300008347"
    ]
},
  "bbox": [],
  "geometry": {"coordinates":[1.166667,41.65],"type":"Point"}
}