{
  "id": 7587523,
  "type": "Feature",
  "properties": {
    "tgn:hierarchy":[
        "tgn:7587523",
        "tgn:1000004",
        "tgn:7000198",
        "tgn:7000799",
        "tgn:7029392"
    ],
    "tgn:id":7587523,
    "tgn:name:en":"Agar",
    "tgn:placetype":[
        "aat:300008347"
    ]
},
  "bbox": [],
  "geometry": {"coordinates":[74.602433,34.099632],"type":"Point"}
}