{
  "id": 7577295,
  "type": "Feature",
  "properties": {
    "tgn:hierarchy":[
        "tgn:7577295",
        "tgn:1000004",
        "tgn:7000198",
        "tgn:7000799",
        "tgn:7029392"
    ],
    "tgn:id":7577295,
    "tgn:name:en":"Khelanmarg",
    "tgn:placetype":[
        "aat:300132356"
    ]
},
  "bbox": [],
  "geometry": {"coordinates":[74.35,34.033333],"type":"Point"}
}