{
  "id": 2289010,
  "type": "Feature",
  "properties": {
    "tgn:hierarchy":[
        "tgn:2289010",
        "tgn:1000001",
        "tgn:7012149",
        "tgn:7007707",
        "tgn:7029392"
    ],
    "tgn:id":2289010,
    "tgn:name":"Diver Creek",
    "tgn:placetype":[
        "aat:300008706"
    ]
},
  "bbox": [],
  "geometry": {"coordinates":[-95.4667,36.4833],"type":"Point"}
}