<<<<<<< HEAD
{
  "id": 7481023,
  "type": "Feature",
  "properties": {
    "tgn:hierarchy":[
        "tgn:7481023",
        "tgn:1000004",
        "tgn:7471332",
        "tgn:1000141",
        "tgn:7029392"
    ],
    "tgn:id":7481023,
    "tgn:name":"Aikou Yihao Ti",
    "tgn:placetype":[
        "aat:300006156"
    ]
},
  "bbox": [],
  "geometry": {"coordinates":[121.046389,24.795833],"type":"Point"}
}
=======
{"geometry":{"type":"Point","coordinates":[121.046389,24.795833]},"type":"Feature","properties":{"hierarchy":["tgn:7481023","tgn:1000004","tgn:7471332","tgn:1000141","tgn:7029392"],"placetype":["aat:300006156"],"id":7481023,"name:xx":"Aikou Yihao Ti"}}
>>>>>>> 03f74aca74312dbeaf24d7e61306dd6a786dc3d0
