{
  "id": 7481023,
  "type": "Feature",
  "properties": {
    "tgn:hierarchy":[
        "tgn:7481023",
        "tgn:1000004",
        "tgn:7471332",
        "tgn:1000141",
        "tgn:7029392"
    ],
    "tgn:id":7481023,
    "tgn:name":"Aikou Yihao Ti",
    "tgn:placetype":[
        "aat:300006156"
    ]
},
  "bbox": [],
  "geometry": {"coordinates":[121.046389,24.795833],"type":"Point"}
}