{
  "id": 7007999,
  "type": "Feature",
  "properties": {
    "tgn:hierarchy":[
        "tgn:7007999",
        "tgn:1000003",
        "tgn:7002883",
        "tgn:1000070",
        "tgn:7029392"
    ],
    "tgn:id":7007999,
    "tgn:name":"S\u00e8vres",
    "tgn:placetype":[
        "aat:300008347",
        "aat:300008389",
        "aat:300387308",
        "aat:300387330",
        "aat:300000874"
    ]
},
  "bbox": [],
  "geometry": {"coordinates":[2.2167,48.8167],"type":"Point"}
}