<<<<<<< HEAD
{
  "id": 7358837,
  "type": "Feature",
  "properties": {
    "tgn:hierarchy":[
        "tgn:7358837",
        "tgn:1001836",
        "tgn:1000001",
        "tgn:7005560",
        "tgn:7029392"
    ],
    "tgn:id":7358837,
    "tgn:name":"Colorado, Cerro",
    "tgn:placetype":[
        "aat:300008795"
    ]
},
  "bbox": [],
  "geometry": {"coordinates":[-111.733333,26.733333],"type":"Point"}
}
=======
{"geometry":{"type":"Point","coordinates":[-111.733333,26.733333]},"type":"Feature","properties":{"hierarchy":["tgn:7358837","tgn:1001836","tgn:1000001","tgn:7005560","tgn:7029392"],"placetype":["aat:300008795"],"id":7358837,"name:xx":"Colorado, Cerro"}}
>>>>>>> 03f74aca74312dbeaf24d7e61306dd6a786dc3d0
