<<<<<<< HEAD
{
  "id": 7359176,
  "type": "Feature",
  "properties": {
    "tgn:hierarchy":[
        "tgn:7359176",
        "tgn:1000001",
        "tgn:7005599",
        "tgn:7005560",
        "tgn:7029392"
    ],
    "tgn:id":7359176,
    "tgn:name":"Cruz Blanca",
    "tgn:placetype":[
        "aat:300007783"
    ]
},
  "bbox": [],
  "geometry": {"coordinates":[-97.166667,19.633333],"type":"Point"}
}
=======
{"geometry":{"type":"Point","coordinates":[-97.166667,19.633333]},"type":"Feature","properties":{"hierarchy":["tgn:7359176","tgn:1000001","tgn:7005599","tgn:7005560","tgn:7029392"],"placetype":["aat:300007783"],"id":7359176,"name:xx":"Cruz Blanca"}}
>>>>>>> 03f74aca74312dbeaf24d7e61306dd6a786dc3d0
