<<<<<<< HEAD
{
  "id": 2250013,
  "type": "Feature",
  "properties": {
    "tgn:hierarchy":[
        "tgn:2250013",
        "tgn:2002365",
        "tgn:1000001",
        "tgn:7012149",
        "tgn:7007923",
        "tgn:7029392"
    ],
    "tgn:id":2250013,
    "tgn:name":"Collins",
    "tgn:placetype":[
        "aat:300008347"
    ]
},
  "bbox": [],
  "geometry": {"coordinates":[-106.15,41.1],"type":"Point"}
}
=======
{"geometry":{"type":"Point","coordinates":[-106.150000,41.100000]},"type":"Feature","properties":{"hierarchy":["tgn:2250013","tgn:2002365","tgn:1000001","tgn:7012149","tgn:7007923","tgn:7029392"],"placetype":["aat:300008347"],"id":2250013,"name:xx":"Collins"}}
>>>>>>> 03f74aca74312dbeaf24d7e61306dd6a786dc3d0
