{
  "id": 7326243,
  "type": "Feature",
  "properties": {
    "tgn:hierarchy":[
        "tgn:7326243",
        "tgn:7002836",
        "tgn:7016622",
        "tgn:1000003",
        "tgn:1000095",
        "tgn:7029392"
    ],
    "tgn:id":7326243,
    "tgn:name":"Piedras Ca\u00eddas, Punta de las",
    "tgn:placetype":[
        "aat:300386846"
    ]
},
  "bbox": [],
  "geometry": {"coordinates":[-17.233333,28.016667],"type":"Point"}
}