{
  "id": 2633532,
  "type": "Feature",
  "properties": {
    "tgn:hierarchy":[
        "tgn:2633532",
        "tgn:7002659",
        "tgn:1000001",
        "tgn:7012149",
        "tgn:2000031",
        "tgn:7029392"
    ],
    "tgn:id":2633532,
    "tgn:name":"Runway Branch",
    "tgn:placetype":[
        "aat:300008699"
    ]
},
  "bbox": [],
  "geometry": {"coordinates":[-87.85,32.5833],"type":"Point"}
}