{
  "id": 2249380,
  "type": "Feature",
  "properties": {
    "tgn:hierarchy":[
        "tgn:2249380",
        "tgn:1000001",
        "tgn:7012149",
        "tgn:2001166",
        "tgn:7007522",
        "tgn:7029392"
    ],
    "tgn:id":2249380,
    "tgn:name":"Coleman Creek",
    "tgn:placetype":[
        "aat:300008706"
    ]
},
  "bbox": [],
  "geometry": {"coordinates":[-89.6167,34.0667],"type":"Point"}
}