{
  "id": 1031248,
  "type": "Feature",
  "properties": {
    "tgn:hierarchy":[
        "tgn:1031248",
        "tgn:7002445",
        "tgn:1000003",
        "tgn:7019017",
        "tgn:7008591",
        "tgn:7029392"
    ],
    "tgn:id":1031248,
    "tgn:name:en":"Yatton",
    "tgn:placetype":[
        "aat:300008347"
    ]
},
  "bbox": [],
  "geometry": {"coordinates":[-2.816667,51.383333],"type":"Point"}
}