{
  "id": 7498221,
  "type": "Feature",
  "properties": {
    "tgn:hierarchy":[
        "tgn:7498221",
        "tgn:1000004",
        "tgn:7467799",
        "tgn:1000141",
        "tgn:7029392"
    ],
    "tgn:id":7498221,
    "tgn:name":"Huanan Guoxiao",
    "tgn:placetype":[
        "aat:300006495"
    ]
},
  "bbox": [],
  "geometry": {"coordinates":[120.5523,24.0162],"type":"Point"}
}