{
  "id": 2161935,
  "type": "Feature",
  "properties": {
    "tgn:hierarchy":[
        "tgn:2161935",
        "tgn:1000001",
        "tgn:7012149",
        "tgn:1002474",
        "tgn:7007709",
        "tgn:7029392"
    ],
    "tgn:id":2161935,
    "tgn:name":"Bells Branch",
    "tgn:placetype":[
        "aat:300008699"
    ]
},
  "bbox": [],
  "geometry": {"coordinates":[-77.0333,36.3833],"type":"Point"}
}