{
  "id": 1130399,
  "type": "Feature",
  "properties": {
    "tgn:hierarchy":[
        "tgn:1130399",
        "tgn:7005694",
        "tgn:7005685",
        "tgn:1000001",
        "tgn:7029392"
    ],
    "tgn:id":1130399,
    "tgn:name":"Sulphur",
    "tgn:placetype":[
        "aat:300008707"
    ]
},
  "bbox": [],
  "geometry": {"coordinates":[-119.1833,53.8667],"type":"Point"}
}