{
  "id": 7079023,
  "type": "Feature",
  "properties": {
    "tgn:hierarchy":[
        "tgn:7079023",
        "tgn:1000003",
        "tgn:7003676",
        "tgn:7000084",
        "tgn:7029392"
    ],
    "tgn:id":7079023,
    "tgn:name":"Wischer Schloot",
    "tgn:placetype":[
        "aat:300008699"
    ]
},
  "bbox": [],
  "geometry": {"coordinates":[7.233333,53.616667],"type":"Point"}
}