{
  "id": 7417860,
  "type": "Feature",
  "properties": {
    "tgn:hierarchy":[
        "tgn:7417860",
        "tgn:7005584",
        "tgn:1000001",
        "tgn:7005560",
        "tgn:7029392"
    ],
    "tgn:id":7417860,
    "tgn:name":"El Espejo",
    "tgn:placetype":[
        "aat:300008347"
    ]
},
  "bbox": [],
  "geometry": {"coordinates":[-100.547778,20.441111],"type":"Point"}
}