{
  "id": 7420742,
  "type": "Feature",
  "properties": {
    "tgn:hierarchy":[
        "tgn:7420742",
        "tgn:1000001",
        "tgn:7005589",
        "tgn:7005560",
        "tgn:7029392"
    ],
    "tgn:id":7420742,
    "tgn:name:es":"El Saucito",
    "tgn:placetype":[
        "aat:300008347"
    ]
},
  "bbox": [],
  "geometry": {"coordinates":[-99.660556,25.890278],"type":"Point"}
}