{
  "id": 2606805,
  "type": "Feature",
  "properties": {
    "tgn:hierarchy":[
        "tgn:2606805",
        "tgn:7002659",
        "tgn:1000001",
        "tgn:2000007",
        "tgn:7012149",
        "tgn:7029392"
    ],
    "tgn:id":2606805,
    "tgn:name":"Ramsey Hill",
    "tgn:placetype":[
        "aat:300008798"
    ]
},
  "bbox": [],
  "geometry": {"coordinates":[-85.7833,33.6833],"type":"Point"}
}