{
  "id": 7226115,
  "type": "Feature",
  "properties": {
    "tgn:hierarchy":[
        "tgn:7226115",
        "tgn:7002739",
        "tgn:7017076",
        "tgn:1000003",
        "tgn:1000074",
        "tgn:7029392"
    ],
    "tgn:id":7226115,
    "tgn:name":"Spalathron\u00edsi, Vrakhonis\u00eds",
    "tgn:placetype":[
        "aat:300008791"
    ]
},
  "bbox": [],
  "geometry": {"coordinates":[23.237227,37.703283],"type":"Point"}
}