{
  "id": 1082546,
  "type": "Feature",
  "properties": {
    "tgn:hierarchy":[
        "tgn:1082546",
        "tgn:1000004",
        "tgn:7000848",
        "tgn:1000125",
        "tgn:7029392"
    ],
    "tgn:id":1082546,
    "tgn:name":"Pak Ban",
    "tgn:placetype":[
        "aat:300008347"
    ]
},
  "bbox": [],
  "geometry": {"coordinates":[102.4667,21.2333],"type":"Point"}
}