{
  "id": 7300683,
  "type": "Feature",
  "properties": {
    "tgn:hierarchy":[
        "tgn:7300683",
        "tgn:7008912",
        "tgn:7030216",
        "tgn:1000003",
        "tgn:1000095",
        "tgn:7029392"
    ],
    "tgn:id":7300683,
    "tgn:name":"Noguera de Tor, R\u00edo",
    "tgn:placetype":[
        "aat:300008699"
    ]
},
  "bbox": [],
  "geometry": {"coordinates":[0.735998,42.418915],"type":"Point"}
}