{
  "id": 2783423,
  "type": "Feature",
  "properties": {
    "tgn:hierarchy":[
        "tgn:2783423",
        "tgn:1000001",
        "tgn:7012149",
        "tgn:7007157",
        "tgn:1002858",
        "tgn:7029392"
    ],
    "tgn:id":2783423,
    "tgn:name":"Wruck Canyon",
    "tgn:placetype":[
        "aat:300008761"
    ]
},
  "bbox": [],
  "geometry": {"coordinates":[-116.9833,32.55],"type":"Point"}
}