{
  "id": 7484233,
  "type": "Feature",
  "properties": {
    "tgn:hierarchy":[
        "tgn:7484233",
        "tgn:7001004",
        "tgn:1000004",
        "tgn:1000141",
        "tgn:7029392"
    ],
    "tgn:id":7484233,
    "tgn:name":"Guanshan Sanhao Qiao",
    "tgn:placetype":[
        "aat:300007836"
    ]
},
  "bbox": [],
  "geometry": {"coordinates":[120.565833,23.101389],"type":"Point"}
}