<<<<<<< HEAD
{
  "id": 7484233,
  "type": "Feature",
  "properties": {
    "tgn:hierarchy":[
        "tgn:7484233",
        "tgn:7001004",
        "tgn:1000004",
        "tgn:1000141",
        "tgn:7029392"
    ],
    "tgn:id":7484233,
    "tgn:name":"Guanshan Sanhao Qiao",
    "tgn:placetype":[
        "aat:300007836"
    ]
},
  "bbox": [],
  "geometry": {"coordinates":[120.565833,23.101389],"type":"Point"}
}
=======
{"geometry":{"type":"Point","coordinates":[120.565833,23.101389]},"type":"Feature","properties":{"hierarchy":["tgn:7484233","tgn:7001004","tgn:1000004","tgn:1000141","tgn:7029392"],"placetype":["aat:300007836"],"id":7484233,"name:xx":"Guanshan Sanhao Qiao"}}
>>>>>>> 03f74aca74312dbeaf24d7e61306dd6a786dc3d0
