{
  "id": 1116619,
  "type": "Feature",
  "properties": {
    "tgn:hierarchy":[
        "tgn:1116619",
        "tgn:1000004",
        "tgn:7002081",
        "tgn:1000111",
        "tgn:7029392"
    ],
    "tgn:id":1116619,
    "tgn:name":"Hongze Hu",
    "tgn:placetype":[
        "aat:300008680"
    ]
},
  "bbox": [],
  "geometry": {"coordinates":[118.5833,33.2833],"type":"Point"}
}