{
  "id": 2117319,
  "type": "Feature",
  "properties": {
    "tgn:hierarchy":[
        "tgn:2117319",
        "tgn:1000001",
        "tgn:2002261",
        "tgn:7012149",
        "tgn:7013961",
        "tgn:7029392"
    ],
    "tgn:id":2117319,
    "tgn:name":"Backus",
    "tgn:placetype":[
        "aat:300008347",
        "aat:300387210"
    ]
},
  "bbox": [],
  "geometry": {"coordinates":[-80.9667,37.85],"type":"Point"}
}