{
  "id": 2499976,
  "type": "Feature",
  "properties": {
    "tgn:hierarchy":[
        "tgn:2499976",
        "tgn:1000001",
        "tgn:7012149",
        "tgn:7007919",
        "tgn:7029392"
    ],
    "tgn:id":2499976,
    "tgn:name":"McCracken Creek",
    "tgn:placetype":[
        "aat:300008706"
    ]
},
  "bbox": [],
  "geometry": {"coordinates":[-77.8333,38.2333],"type":"Point"}
}