{
  "id": 2704954,
  "type": "Feature",
  "properties": {
    "tgn:hierarchy":[
        "tgn:2704954",
        "tgn:1000001",
        "tgn:7012149",
        "tgn:2002363",
        "tgn:7007922",
        "tgn:7029392"
    ],
    "tgn:id":2704954,
    "tgn:name":"Sunset Point",
    "tgn:placetype":[
        "aat:300008347"
    ]
},
  "bbox": [],
  "geometry": {"coordinates":[-88.5833,44.05],"type":"Point"}
}