{
  "id": 2381941,
  "type": "Feature",
  "properties": {
    "tgn:hierarchy":[
        "tgn:2381941",
        "tgn:1000001",
        "tgn:7012149",
        "tgn:7029392"
    ],
    "tgn:id":2381941,
    "tgn:name":"Hayes Creek",
    "tgn:placetype":[
        "aat:300008706"
    ]
},
  "bbox": [],
  "geometry": {"coordinates":[-115.1167,41.95],"type":"Point"}
}