{
  "id": 7210713,
  "type": "Feature",
  "properties": {
    "tgn:hierarchy":[
        "tgn:7210713",
        "tgn:7000096",
        "tgn:1000003",
        "tgn:7000084",
        "tgn:7029392"
    ],
    "tgn:id":7210713,
    "tgn:name":"Bauernsee",
    "tgn:placetype":[
        "aat:300008680"
    ]
},
  "bbox": [],
  "geometry": {"coordinates":[13.933333,52.466667],"type":"Point"}
}