{
  "id": 7537193,
  "type": "Feature",
  "properties": {
    "tgn:hierarchy":[
        "tgn:7537193",
        "tgn:7001242",
        "tgn:7016833",
        "tgn:7001335",
        "tgn:7029392"
    ],
    "tgn:id":7537193,
    "tgn:name":"Qurray\u015f, W\u0101d\u012b al",
    "tgn:placetype":[
        "aat:300379998"
    ]
},
  "bbox": [],
  "geometry": {"coordinates":[34.213634,29.742806],"type":"Point"}
}