{
  "id": 2479855,
  "type": "Feature",
  "properties": {
    "tgn:hierarchy":[
        "tgn:2479855",
        "tgn:1000001",
        "tgn:2000198",
        "tgn:7012149",
        "tgn:7007158",
        "tgn:7029392"
    ],
    "tgn:id":2479855,
    "tgn:name":"Lake Ditch",
    "tgn:placetype":[
        "aat:300006075"
    ]
},
  "bbox": [],
  "geometry": {"coordinates":[-105.2667,40.15],"type":"Point"}
}