{
  "id": 2254905,
  "type": "Feature",
  "properties": {
    "tgn:hierarchy":[
        "tgn:2254905",
        "tgn:1000001",
        "tgn:7016102",
        "tgn:7012149",
        "tgn:7007516",
        "tgn:7029392"
    ],
    "tgn:id":2254905,
    "tgn:name":"Cooper",
    "tgn:placetype":[
        "aat:300008347"
    ]
},
  "bbox": [],
  "geometry": {"coordinates":[-76.2833,39.6833],"type":"Point"}
}