{
  "id": 2751693,
  "type": "Feature",
  "properties": {
    "tgn:hierarchy":[
        "tgn:2751693",
        "tgn:2000258",
        "tgn:1000001",
        "tgn:7012149",
        "tgn:7007240",
        "tgn:7029392"
    ],
    "tgn:id":2751693,
    "tgn:name":"Warren Bayou",
    "tgn:placetype":[
        "aat:300132316"
    ]
},
  "bbox": [],
  "geometry": {"coordinates":[-85.7167,30.2667],"type":"Point"}
}