<<<<<<< HEAD
{
  "id": 2403266,
  "type": "Feature",
  "properties": {
    "tgn:hierarchy":[
        "tgn:2403266",
        "tgn:1000001",
        "tgn:7012149",
        "tgn:2002010",
        "tgn:7007826",
        "tgn:7029392"
    ],
    "tgn:id":2403266,
    "tgn:name":"House Spring",
    "tgn:placetype":[
        "aat:300008697"
    ]
},
  "bbox": [],
  "geometry": {"coordinates":[-104.0333,31.0],"type":"Point"}
}
=======
{"geometry":{"type":"Point","coordinates":[-104.033300,31.000000]},"type":"Feature","properties":{"hierarchy":["tgn:2403266","tgn:1000001","tgn:7012149","tgn:2002010","tgn:7007826","tgn:7029392"],"placetype":["aat:300008697"],"id":2403266,"name:xx":"House Spring"}}
>>>>>>> 03f74aca74312dbeaf24d7e61306dd6a786dc3d0
