{
  "id": 7055041,
  "type": "Feature",
  "properties": {
    "tgn:hierarchy":[
        "tgn:7055041",
        "tgn:7003135",
        "tgn:1000003",
        "tgn:7003080",
        "tgn:1000080",
        "tgn:7029392"
    ],
    "tgn:id":7055041,
    "tgn:name":"Polleca, Rio",
    "tgn:placetype":[
        "aat:300008699"
    ]
},
  "bbox": [],
  "geometry": {"coordinates":[13.666667,41.383333],"type":"Point"}
}