{
  "id": 7161196,
  "type": "Feature",
  "properties": {
    "tgn:hierarchy":[
        "tgn:7161196",
        "tgn:7003669",
        "tgn:1000003",
        "tgn:7000084",
        "tgn:7029392"
    ],
    "tgn:id":7161196,
    "tgn:name":"Hoher Rainstein",
    "tgn:placetype":[
        "aat:300008795"
    ]
},
  "bbox": [],
  "geometry": {"coordinates":[12.416667,49.533333],"type":"Point"}
}