<<<<<<< HEAD
{
  "id": 7059504,
  "type": "Feature",
  "properties": {
    "tgn:hierarchy":[
        "tgn:7059504",
        "tgn:7003669",
        "tgn:1000003",
        "tgn:7000084",
        "tgn:7029392"
    ],
    "tgn:id":7059504,
    "tgn:name":"Allmannshausner Filz",
    "tgn:placetype":[
        "aat:300386886"
    ]
},
  "bbox": [],
  "geometry": {"coordinates":[11.366667,47.933333],"type":"Point"}
}
=======
{"geometry":{"type":"Point","coordinates":[11.366667,47.933333]},"type":"Feature","properties":{"hierarchy":["tgn:7059504","tgn:7003669","tgn:1000003","tgn:7000084","tgn:7029392"],"placetype":["aat:300386886"],"id":7059504,"name:xx":"Allmannshausner Filz"}}
>>>>>>> 03f74aca74312dbeaf24d7e61306dd6a786dc3d0
