{
  "id": 5001928,
  "type": "Feature",
  "properties": {
    "tgn:hierarchy":[
        "tgn:5001928",
        "tgn:7002692",
        "tgn:7012056",
        "tgn:1000003",
        "tgn:1000074",
        "tgn:7029392"
    ],
    "tgn:id":5001928,
    "tgn:name":"Khama\u00edzi",
    "tgn:placetype":[
        "aat:300008347",
        "aat:300000810",
        "aat:300008372"
    ]
},
  "bbox": [],
  "geometry": {"coordinates":[26.016667,35.166667],"type":"Point"}
}