{
  "id": 7475797,
  "type": "Feature",
  "properties": {
    "tgn:hierarchy":[
        "tgn:7475797",
        "tgn:7487020",
        "tgn:1000004",
        "tgn:1000141",
        "tgn:7029392"
    ],
    "tgn:id":7475797,
    "tgn:name":"Zhangwu",
    "tgn:placetype":[
        "aat:300008347"
    ]
},
  "bbox": [],
  "geometry": {"coordinates":[120.771864,24.546018],"type":"Point"}
}