{
  "id": 2762316,
  "type": "Feature",
  "properties": {
    "tgn:hierarchy":[
        "tgn:2762316",
        "tgn:1000001",
        "tgn:7012149",
        "tgn:2002384",
        "tgn:7007923",
        "tgn:7029392"
    ],
    "tgn:id":2762316,
    "tgn:name":"West Thumb",
    "tgn:placetype":[
        "aat:300132316"
    ]
},
  "bbox": [],
  "geometry": {"coordinates":[-110.5167,44.4167],"type":"Point"}
}