{
  "id": 7351546,
  "type": "Feature",
  "properties": {
    "tgn:hierarchy":[
        "tgn:7351546",
        "tgn:7005581",
        "tgn:1000001",
        "tgn:7005560",
        "tgn:7029392"
    ],
    "tgn:id":7351546,
    "tgn:name":"Ba\u00f1os de San Diego",
    "tgn:placetype":[
        "aat:300008347"
    ]
},
  "bbox": [],
  "geometry": {"coordinates":[-105.533333,28.583333],"type":"Point"}
}