{
  "id": 2400293,
  "type": "Feature",
  "properties": {
    "tgn:hierarchy":[
        "tgn:2400293",
        "tgn:1000001",
        "tgn:7012149",
        "tgn:7007158",
        "tgn:2000243",
        "tgn:7029392"
    ],
    "tgn:id":2400293,
    "tgn:name":"Horse Draw",
    "tgn:placetype":[
        "aat:300008761"
    ]
},
  "bbox": [],
  "geometry": {"coordinates":[-108.3333,39.9333],"type":"Point"}
}