<<<<<<< HEAD
{
  "id": 2400293,
  "type": "Feature",
  "properties": {
    "tgn:hierarchy":[
        "tgn:2400293",
        "tgn:1000001",
        "tgn:7012149",
        "tgn:7007158",
        "tgn:2000243",
        "tgn:7029392"
    ],
    "tgn:id":2400293,
    "tgn:name":"Horse Draw",
    "tgn:placetype":[
        "aat:300008761"
    ]
},
  "bbox": [],
  "geometry": {"coordinates":[-108.3333,39.9333],"type":"Point"}
}
=======
{"geometry":{"type":"Point","coordinates":[-108.333300,39.933300]},"type":"Feature","properties":{"hierarchy":["tgn:2400293","tgn:1000001","tgn:7012149","tgn:7007158","tgn:2000243","tgn:7029392"],"placetype":["aat:300008761"],"id":2400293,"name:xx":"Horse Draw"}}
>>>>>>> 03f74aca74312dbeaf24d7e61306dd6a786dc3d0
