{
  "id": 2250283,
  "type": "Feature",
  "properties": {
    "tgn:hierarchy":[
        "tgn:2250283",
        "tgn:1000001",
        "tgn:7012149",
        "tgn:2001226",
        "tgn:7007523",
        "tgn:7029392"
    ],
    "tgn:id":2250283,
    "tgn:name":"Collins Spring",
    "tgn:placetype":[
        "aat:300008697"
    ]
},
  "bbox": [],
  "geometry": {"coordinates":[-92.1833,36.7333],"type":"Point"}
}