{
  "id": 7588501,
  "type": "Feature",
  "properties": {
    "tgn:hierarchy":[
        "tgn:7588501",
        "tgn:1000004",
        "tgn:7000198",
        "tgn:7000799",
        "tgn:7029392"
    ],
    "tgn:id":7588501,
    "tgn:name:en":"Dheri",
    "tgn:placetype":[
        "aat:300008347"
    ]
},
  "bbox": [],
  "geometry": {"coordinates":[74.072222,33.770833],"type":"Point"}
}