{
  "id": 7550436,
  "type": "Feature",
  "properties": {
    "tgn:hierarchy":[
        "tgn:7550436",
        "tgn:1000004",
        "tgn:7000198",
        "tgn:1001895",
        "tgn:7029392"
    ],
    "tgn:id":7550436,
    "tgn:name:en":"B\u012bbi",
    "tgn:placetype":[
        "aat:300008347"
    ]
},
  "bbox": [],
  "geometry": {"coordinates":[76.366667,20.016667],"type":"Point"}
}