{
  "id": 7430583,
  "type": "Feature",
  "properties": {
    "tgn:hierarchy":[
        "tgn:7430583",
        "tgn:7005581",
        "tgn:1000001",
        "tgn:7005560",
        "tgn:7029392"
    ],
    "tgn:id":7430583,
    "tgn:name":"Ci\u00e9naga de Loya",
    "tgn:placetype":[
        "aat:300008347"
    ]
},
  "bbox": [],
  "geometry": {"coordinates":[-106.35,28.183333],"type":"Point"}
}