{
  "id": 2253357,
  "type": "Feature",
  "properties": {
    "tgn:hierarchy":[
        "tgn:2253357",
        "tgn:1000001",
        "tgn:7013942",
        "tgn:7012149",
        "tgn:7007517",
        "tgn:7029392"
    ],
    "tgn:id":2253357,
    "tgn:name":"Conway State Forest",
    "tgn:placetype":[
        "aat:300008863"
    ]
},
  "bbox": [],
  "geometry": {"coordinates":[-72.7167,42.4667],"type":"Point"}
}