{
  "id": 7503418,
  "type": "Feature",
  "properties": {
    "tgn:hierarchy":[
        "tgn:7503418",
        "tgn:1000004",
        "tgn:7471332",
        "tgn:1000141",
        "tgn:7029392"
    ],
    "tgn:id":7503418,
    "tgn:name":"Gaoqiao Shan",
    "tgn:placetype":[
        "aat:300008795"
    ]
},
  "bbox": [],
  "geometry": {"coordinates":[121.171111,24.566111],"type":"Point"}
}