<<<<<<< HEAD
{
  "id": 7023536,
  "type": "Feature",
  "properties": {
    "tgn:hierarchy":[
        "tgn:7023536",
        "tgn:1000001",
        "tgn:7012149",
        "tgn:1002591",
        "tgn:7007255",
        "tgn:7029392"
    ],
    "tgn:id":7023536,
    "tgn:name":"Sugar Tree Branch",
    "tgn:placetype":[
        "aat:300008699"
    ]
},
  "bbox": [],
  "geometry": {"coordinates":[-83.3667,38.5167],"type":"Point"}
}
=======
{"geometry":{"type":"Point","coordinates":[-83.366700,38.516700]},"type":"Feature","properties":{"hierarchy":["tgn:7023536","tgn:1000001","tgn:7012149","tgn:1002591","tgn:7007255","tgn:7029392"],"placetype":["aat:300008699"],"id":7023536,"name:xx":"Sugar Tree Branch"}}
>>>>>>> 03f74aca74312dbeaf24d7e61306dd6a786dc3d0
