{
  "id": 7023536,
  "type": "Feature",
  "properties": {
    "tgn:hierarchy":[
        "tgn:7023536",
        "tgn:1000001",
        "tgn:7012149",
        "tgn:1002591",
        "tgn:7007255",
        "tgn:7029392"
    ],
    "tgn:id":7023536,
    "tgn:name":"Sugar Tree Branch",
    "tgn:placetype":[
        "aat:300008699"
    ]
},
  "bbox": [],
  "geometry": {"coordinates":[-83.3667,38.5167],"type":"Point"}
}