{
  "id": 7279712,
  "type": "Feature",
  "properties": {
    "tgn:hierarchy":[
        "tgn:7279712",
        "tgn:1001695",
        "tgn:1000049",
        "tgn:1000002",
        "tgn:7029392"
    ],
    "tgn:id":7279712,
    "tgn:name":"Ranchillo, Cerro",
    "tgn:placetype":[
        "aat:300008795"
    ]
},
  "bbox": [],
  "geometry": {"coordinates":[-71.583333,-34.75],"type":"Point"}
}