{
  "id": 7001267,
  "type": "Feature",
  "properties": {
    "tgn:hierarchy":[
        "tgn:7001267",
        "tgn:7001242",
        "tgn:7016833",
        "tgn:1001088",
        "tgn:7029392"
    ],
    "tgn:id":7001267,
    "tgn:name:en":"Al Bahnas\u0101",
    "tgn:placetype":[
        "aat:300008347",
        "aat:300000810"
    ]
},
  "bbox": [],
  "geometry": {"coordinates":[30.659546,28.53564],"type":"Point"}
}