{
  "id": 2531855,
  "type": "Feature",
  "properties": {
    "tgn:hierarchy":[
        "tgn:2531855",
        "tgn:1000001",
        "tgn:7012149",
        "tgn:7007157",
        "tgn:1002684",
        "tgn:7029392"
    ],
    "tgn:id":2531855,
    "tgn:name":"Mulligan Hill",
    "tgn:placetype":[
        "aat:300008798"
    ]
},
  "bbox": [],
  "geometry": {"coordinates":[-121.7833,36.7333],"type":"Point"}
}