{
  "id": 2756561,
  "type": "Feature",
  "properties": {
    "tgn:hierarchy":[
        "tgn:2756561",
        "tgn:1000001",
        "tgn:7012149",
        "tgn:1002730",
        "tgn:7007919",
        "tgn:7029392"
    ],
    "tgn:id":2756561,
    "tgn:name":"Wellington Neck",
    "tgn:placetype":[
        "aat:300008850"
    ]
},
  "bbox": [],
  "geometry": {"coordinates":[-75.8833,37.4833],"type":"Point"}
}