{
  "id": 2026095,
  "type": "Feature",
  "properties": {
    "tgn:hierarchy":[
        "tgn:2026095",
        "tgn:1000001",
        "tgn:7012149",
        "tgn:2000473",
        "tgn:7007250",
        "tgn:7029392"
    ],
    "tgn:id":2026095,
    "tgn:name":"Saint Anthony",
    "tgn:placetype":[
        "aat:300008347"
    ]
},
  "bbox": [],
  "geometry": {"coordinates":[-111.6667,43.95],"type":"Point"}
}