{
  "id": 7455450,
  "type": "Feature",
  "properties": {
    "tgn:hierarchy":[
        "tgn:7455450",
        "tgn:7002445",
        "tgn:1000003",
        "tgn:7008117",
        "tgn:7008591",
        "tgn:7029392"
    ],
    "tgn:id":7455450,
    "tgn:name:en":"Cumwhitton",
    "tgn:placetype":[
        "aat:300008347"
    ]
},
  "bbox": [],
  "geometry": {"coordinates":[-2.766667,54.85],"type":"Point"}
}