{
  "id": 7217958,
  "type": "Feature",
  "properties": {
    "tgn:hierarchy":[
        "tgn:7217958",
        "tgn:7002728",
        "tgn:7002715",
        "tgn:1000003",
        "tgn:1000074",
        "tgn:7029392"
    ],
    "tgn:id":7217958,
    "tgn:name":"Psil\u00f3 Liv\u00e1di",
    "tgn:placetype":[
        "aat:300266640"
    ]
},
  "bbox": [],
  "geometry": {"coordinates":[22.204167,41.0025],"type":"Point"}
}