{
  "id": 2511876,
  "type": "Feature",
  "properties": {
    "tgn:hierarchy":[
        "tgn:2511876",
        "tgn:1000001",
        "tgn:7012149",
        "tgn:1002999",
        "tgn:7007526",
        "tgn:7029392"
    ],
    "tgn:id":2511876,
    "tgn:name":"Milk Ranch Reservoir",
    "tgn:placetype":[
        "aat:300006191"
    ]
},
  "bbox": [],
  "geometry": {"coordinates":[-119.8167,39.9667],"type":"Point"}
}