{
  "id": 2755944,
  "type": "Feature",
  "properties": {
    "tgn:hierarchy":[
        "tgn:2755944",
        "tgn:7002659",
        "tgn:1000001",
        "tgn:2000005",
        "tgn:7012149",
        "tgn:7029392"
    ],
    "tgn:id":2755944,
    "tgn:name":"Wehle Lake",
    "tgn:placetype":[
        "aat:300006191"
    ]
},
  "bbox": [],
  "geometry": {"coordinates":[-85.4667,32.0333],"type":"Point"}
}