{
  "id": 7157084,
  "type": "Feature",
  "properties": {
    "tgn:hierarchy":[
        "tgn:7157084",
        "tgn:1000003",
        "tgn:7000094",
        "tgn:7000084",
        "tgn:7029392"
    ],
    "tgn:id":7157084,
    "tgn:name":"Kietz \u00fcber Lenzen",
    "tgn:placetype":[
        "aat:300008347"
    ]
},
  "bbox": [],
  "geometry": {"coordinates":[11.333333,53.083333],"type":"Point"}
}