{
  "id": 7342184,
  "type": "Feature",
  "properties": {
    "tgn:hierarchy":[
        "tgn:7342184",
        "tgn:7002835",
        "tgn:7001158",
        "tgn:1000003",
        "tgn:1000095",
        "tgn:7029392"
    ],
    "tgn:id":7342184,
    "tgn:name":"Canillas de Torneros",
    "tgn:placetype":[
        "aat:300008347"
    ]
},
  "bbox": [],
  "geometry": {"coordinates":[-5.883333,40.833333],"type":"Point"}
}