{
  "id": 2322878,
  "type": "Feature",
  "properties": {
    "tgn:hierarchy":[
        "tgn:2322878",
        "tgn:1000001",
        "tgn:7012149",
        "tgn:2001111",
        "tgn:7007522",
        "tgn:7029392"
    ],
    "tgn:id":2322878,
    "tgn:name":"Fannegusha Ditch",
    "tgn:placetype":[
        "aat:300006075"
    ]
},
  "bbox": [],
  "geometry": {"coordinates":[-90.2833,33.0667],"type":"Point"}
}