{
  "id": 2297597,
  "type": "Feature",
  "properties": {
    "tgn:hierarchy":[
        "tgn:2297597",
        "tgn:1000001",
        "tgn:2002369",
        "tgn:7012149",
        "tgn:7007923",
        "tgn:7029392"
    ],
    "tgn:id":2297597,
    "tgn:name":"Dry Fork La Prele Creek",
    "tgn:placetype":[
        "aat:300008706"
    ]
},
  "bbox": [],
  "geometry": {"coordinates":[-105.7667,42.5667],"type":"Point"}
}