{
  "id": 7587295,
  "type": "Feature",
  "properties": {
    "tgn:hierarchy":[
        "tgn:7587295",
        "tgn:1000004",
        "tgn:7000198",
        "tgn:1001977",
        "tgn:7029392"
    ],
    "tgn:id":7587295,
    "tgn:name:en":"Iswaripur",
    "tgn:placetype":[
        "aat:300008347"
    ]
},
  "bbox": [],
  "geometry": {"coordinates":[88.402014,22.200854],"type":"Point"}
}