{
  "id": 7528569,
  "type": "Feature",
  "properties": {
    "tgn:hierarchy":[
        "tgn:7528569",
        "tgn:7001242",
        "tgn:7016833",
        "tgn:1001080",
        "tgn:7029392"
    ],
    "tgn:id":7528569,
    "tgn:name:en":"Umm Khalaf, Ba\u1e29r",
    "tgn:placetype":[
        "aat:300008680"
    ]
},
  "bbox": [],
  "geometry": {"coordinates":[32.266667,30.966667],"type":"Point"}
}