<<<<<<< HEAD
{
  "id": 7110498,
  "type": "Feature",
  "properties": {
    "tgn:hierarchy":[
        "tgn:7110498",
        "tgn:7003669",
        "tgn:1000003",
        "tgn:7000084",
        "tgn:7029392"
    ],
    "tgn:id":7110498,
    "tgn:name":"Reichertsried",
    "tgn:placetype":[
        "aat:300008347"
    ]
},
  "bbox": [],
  "geometry": {"coordinates":[10.483333,48.316667],"type":"Point"}
}
=======
{"geometry":{"type":"Point","coordinates":[10.483333,48.316667]},"type":"Feature","properties":{"hierarchy":["tgn:7110498","tgn:7003669","tgn:1000003","tgn:7000084","tgn:7029392"],"placetype":["aat:300008347"],"id":7110498,"name:xx":"Reichertsried"}}
>>>>>>> 03f74aca74312dbeaf24d7e61306dd6a786dc3d0
