{
  "id": 7108897,
  "type": "Feature",
  "properties": {
    "tgn:hierarchy":[
        "tgn:7108897",
        "tgn:1000003",
        "tgn:7003689",
        "tgn:7000084",
        "tgn:7029392"
    ],
    "tgn:id":7108897,
    "tgn:name":"Regen-Berg",
    "tgn:placetype":[
        "aat:300008777"
    ]
},
  "bbox": [],
  "geometry": {"coordinates":[10.533333,50.833333],"type":"Point"}
}