{
  "id": 7176105,
  "type": "Feature",
  "properties": {
    "tgn:hierarchy":[
        "tgn:7176105",
        "tgn:7000096",
        "tgn:1000003",
        "tgn:7000084",
        "tgn:7029392"
    ],
    "tgn:id":7176105,
    "tgn:name":"Gro\u00dfer Wentowsee",
    "tgn:placetype":[
        "aat:300008680"
    ]
},
  "bbox": [],
  "geometry": {"coordinates":[13.233333,53.05],"type":"Point"}
}