{
  "id": 7485778,
  "type": "Feature",
  "properties": {
    "tgn:hierarchy":[
        "tgn:7485778",
        "tgn:1000004",
        "tgn:7001014",
        "tgn:1000141",
        "tgn:7029392"
    ],
    "tgn:id":7485778,
    "tgn:name":"Kandeng Shan",
    "tgn:placetype":[
        "aat:300008777"
    ]
},
  "bbox": [],
  "geometry": {"coordinates":[120.576389,23.630556],"type":"Point"}
}