<<<<<<< HEAD
{
  "id": 7485778,
  "type": "Feature",
  "properties": {
    "tgn:hierarchy":[
        "tgn:7485778",
        "tgn:1000004",
        "tgn:7001014",
        "tgn:1000141",
        "tgn:7029392"
    ],
    "tgn:id":7485778,
    "tgn:name":"Kandeng Shan",
    "tgn:placetype":[
        "aat:300008777"
    ]
},
  "bbox": [],
  "geometry": {"coordinates":[120.576389,23.630556],"type":"Point"}
}
=======
{"geometry":{"type":"Point","coordinates":[120.576389,23.630556]},"type":"Feature","properties":{"hierarchy":["tgn:7485778","tgn:1000004","tgn:7001014","tgn:1000141","tgn:7029392"],"placetype":["aat:300008777"],"id":7485778,"name:xx":"Kandeng Shan"}}
>>>>>>> 03f74aca74312dbeaf24d7e61306dd6a786dc3d0
