{
  "id": 7582026,
  "type": "Feature",
  "properties": {
    "tgn:hierarchy":[
        "tgn:7582026",
        "tgn:1000004",
        "tgn:7000198",
        "tgn:7016788",
        "tgn:7029392"
    ],
    "tgn:id":7582026,
    "tgn:name:en":"R\u0101md\u012bs\u0101n Johra",
    "tgn:placetype":[
        "aat:300008688"
    ]
},
  "bbox": [],
  "geometry": {"coordinates":[75.504539,28.495274],"type":"Point"}
}