<<<<<<< HEAD
{
  "id": 7486832,
  "type": "Feature",
  "properties": {
    "tgn:hierarchy":[
        "tgn:7486832",
        "tgn:1000004",
        "tgn:7490934",
        "tgn:1000141",
        "tgn:7029392"
    ],
    "tgn:id":7486832,
    "tgn:name":"Dabaimi",
    "tgn:placetype":[
        "aat:300008347"
    ]
},
  "bbox": [],
  "geometry": {"coordinates":[120.1721,23.2857],"type":"Point"}
}
=======
{"geometry":{"type":"Point","coordinates":[120.172100,23.285700]},"type":"Feature","properties":{"hierarchy":["tgn:7486832","tgn:1000004","tgn:7490934","tgn:1000141","tgn:7029392"],"placetype":["aat:300008347"],"id":7486832,"name:xx":"Dabaimi"}}
>>>>>>> 03f74aca74312dbeaf24d7e61306dd6a786dc3d0
