{
  "id": 7486832,
  "type": "Feature",
  "properties": {
    "tgn:hierarchy":[
        "tgn:7486832",
        "tgn:1000004",
        "tgn:7490934",
        "tgn:1000141",
        "tgn:7029392"
    ],
    "tgn:id":7486832,
    "tgn:name":"Dabaimi",
    "tgn:placetype":[
        "aat:300008347"
    ]
},
  "bbox": [],
  "geometry": {"coordinates":[120.1721,23.2857],"type":"Point"}
}