<<<<<<< HEAD
{
  "id": 2157330,
  "type": "Feature",
  "properties": {
    "tgn:hierarchy":[
        "tgn:2157330",
        "tgn:1000001",
        "tgn:7012149",
        "tgn:2001150",
        "tgn:7007522",
        "tgn:7029392"
    ],
    "tgn:id":2157330,
    "tgn:name":"Beaver Creek",
    "tgn:placetype":[
        "aat:300008706"
    ]
},
  "bbox": [],
  "geometry": {"coordinates":[-89.5167,32.0],"type":"Point"}
}
=======
{"geometry":{"type":"Point","coordinates":[-89.516700,32.000000]},"type":"Feature","properties":{"hierarchy":["tgn:2157330","tgn:1000001","tgn:7012149","tgn:2001150","tgn:7007522","tgn:7029392"],"placetype":["aat:300008706"],"id":2157330,"name:xx":"Beaver Creek"}}
>>>>>>> 03f74aca74312dbeaf24d7e61306dd6a786dc3d0
