{
  "id": 7342983,
  "type": "Feature",
  "properties": {
    "tgn:hierarchy":[
        "tgn:7342983",
        "tgn:7002758",
        "tgn:7002821",
        "tgn:1000003",
        "tgn:1000095",
        "tgn:7029392"
    ],
    "tgn:id":7342983,
    "tgn:name":"Caser\u00edo Prado Negro",
    "tgn:placetype":[
        "aat:300008347"
    ]
},
  "bbox": [],
  "geometry": {"coordinates":[-3.45,37.333333],"type":"Point"}
}