{
  "id": 7395562,
  "type": "Feature",
  "properties": {
    "tgn:hierarchy":[
        "tgn:7395562",
        "tgn:1000001",
        "tgn:7005601",
        "tgn:7005560",
        "tgn:7029392"
    ],
    "tgn:id":7395562,
    "tgn:name":"San Jos\u00e9 Llamas",
    "tgn:placetype":[
        "aat:300008347"
    ]
},
  "bbox": [],
  "geometry": {"coordinates":[-102.166667,22.533333],"type":"Point"}
}