{
  "id": 2702189,
  "type": "Feature",
  "properties": {
    "tgn:hierarchy":[
        "tgn:2702189",
        "tgn:1000001",
        "tgn:7012149",
        "tgn:2001217",
        "tgn:7007523",
        "tgn:7029392"
    ],
    "tgn:id":2702189,
    "tgn:name":"Sulfur Hollow",
    "tgn:placetype":[
        "aat:300008761"
    ]
},
  "bbox": [],
  "geometry": {"coordinates":[-90.35,37.4167],"type":"Point"}
}