{
  "id": 2654192,
  "type": "Feature",
  "properties": {
    "tgn:hierarchy":[
        "tgn:2654192",
        "tgn:1000001",
        "tgn:7012149",
        "tgn:2001911",
        "tgn:7007825",
        "tgn:7029392"
    ],
    "tgn:id":2654192,
    "tgn:name":"Shadowbrook",
    "tgn:placetype":[
        "aat:300008347"
    ]
},
  "bbox": [],
  "geometry": {"coordinates":[-86.5167,35.9167],"type":"Point"}
}