<<<<<<< HEAD
{
  "id": 2407749,
  "type": "Feature",
  "properties": {
    "tgn:hierarchy":[
        "tgn:2407749",
        "tgn:2000105",
        "tgn:1000001",
        "tgn:7016172",
        "tgn:7012149",
        "tgn:7029392"
    ],
    "tgn:id":2407749,
    "tgn:name":"Hurricane Bayou",
    "tgn:placetype":[
        "aat:300008699"
    ]
},
  "bbox": [],
  "geometry": {"coordinates":[-91.4833,34.35],"type":"Point"}
}
=======
{"geometry":{"type":"Point","coordinates":[-91.483300,34.350000]},"type":"Feature","properties":{"hierarchy":["tgn:2407749","tgn:2000105","tgn:1000001","tgn:7016172","tgn:7012149","tgn:7029392"],"placetype":["aat:300008699"],"id":2407749,"name:xx":"Hurricane Bayou"}}
>>>>>>> 03f74aca74312dbeaf24d7e61306dd6a786dc3d0
