{
  "id": 2407749,
  "type": "Feature",
  "properties": {
    "tgn:hierarchy":[
        "tgn:2407749",
        "tgn:2000105",
        "tgn:1000001",
        "tgn:7016172",
        "tgn:7012149",
        "tgn:7029392"
    ],
    "tgn:id":2407749,
    "tgn:name":"Hurricane Bayou",
    "tgn:placetype":[
        "aat:300008699"
    ]
},
  "bbox": [],
  "geometry": {"coordinates":[-91.4833,34.35],"type":"Point"}
}