{
  "id": 7390990,
  "type": "Feature",
  "properties": {
    "tgn:hierarchy":[
        "tgn:7390990",
        "tgn:7005581",
        "tgn:1000001",
        "tgn:7005560",
        "tgn:7029392"
    ],
    "tgn:id":7390990,
    "tgn:name":"R\u00edo Verde",
    "tgn:placetype":[
        "aat:300008347"
    ]
},
  "bbox": [],
  "geometry": {"coordinates":[-107.766667,28.383333],"type":"Point"}
}