{
  "id": 7000537,
  "type": "Feature",
  "properties": {
    "tgn:hierarchy":[
        "tgn:7000537",
        "tgn:7001242",
        "tgn:1001921",
        "tgn:1000182",
        "tgn:7029392"
    ],
    "tgn:id":7000537,
    "tgn:name":"Ibadan",
    "tgn:placetype":[
        "aat:300387277",
        "aat:300008347",
        "aat:300008389",
        "aat:300387512",
        "aat:300387221",
        "aat:300387270",
        "aat:300387285",
        "aat:300387296"
    ]
},
  "bbox": [],
  "geometry": {"coordinates":[3.9333,7.3833],"type":"Point"}
}