{
  "id": 2180673,
  "type": "Feature",
  "properties": {
    "tgn:hierarchy":[
        "tgn:2180673",
        "tgn:1000001",
        "tgn:7012149",
        "tgn:1002920",
        "tgn:7007568",
        "tgn:7029392"
    ],
    "tgn:id":2180673,
    "tgn:name":"Bloomerville",
    "tgn:placetype":[
        "aat:300008347"
    ]
},
  "bbox": [],
  "geometry": {"coordinates":[-77.45,42.4167],"type":"Point"}
}