{
  "id": 2118236,
  "type": "Feature",
  "properties": {
    "tgn:hierarchy":[
        "tgn:2118236",
        "tgn:1000001",
        "tgn:7012149",
        "tgn:2002298",
        "tgn:7013961",
        "tgn:7029392"
    ],
    "tgn:id":2118236,
    "tgn:name":"Fishing Camp",
    "tgn:placetype":[
        "aat:300387016"
    ]
},
  "bbox": [],
  "geometry": {"coordinates":[-80.1667,39.0167],"type":"Point"}
}