{
  "id": 2570615,
  "type": "Feature",
  "properties": {
    "tgn:hierarchy":[
        "tgn:2570615",
        "tgn:1000001",
        "tgn:2002152",
        "tgn:7012149",
        "tgn:7007919",
        "tgn:7029392"
    ],
    "tgn:id":2570615,
    "tgn:name":"Patrick Henry",
    "tgn:placetype":[
        "aat:300008347"
    ]
},
  "bbox": [],
  "geometry": {"coordinates":[-78.8833,37.0167],"type":"Point"}
}