{
  "id": 2675893,
  "type": "Feature",
  "properties": {
    "tgn:hierarchy":[
        "tgn:2675893",
        "tgn:1000001",
        "tgn:2001595",
        "tgn:7012149",
        "tgn:7007705",
        "tgn:7029392"
    ],
    "tgn:id":2675893,
    "tgn:name":"Sonora",
    "tgn:placetype":[
        "aat:300008347"
    ]
},
  "bbox": [],
  "geometry": {"coordinates":[-96.7333,46.0667],"type":"Point"}
}