{
  "id": 7154242,
  "type": "Feature",
  "properties": {
    "tgn:hierarchy":[
        "tgn:7154242",
        "tgn:1000003",
        "tgn:7003676",
        "tgn:7000084",
        "tgn:7029392"
    ],
    "tgn:id":7154242,
    "tgn:name":"Iseler",
    "tgn:placetype":[
        "aat:300000206"
    ]
},
  "bbox": [],
  "geometry": {"coordinates":[9.116667,53.55],"type":"Point"}
}