{
  "id": 7572678,
  "type": "Feature",
  "properties": {
    "tgn:hierarchy":[
        "tgn:7572678",
        "tgn:1000004",
        "tgn:7000198",
        "tgn:1001882",
        "tgn:7029392"
    ],
    "tgn:id":7572678,
    "tgn:name:en":"Hudukula",
    "tgn:placetype":[
        "aat:300007783"
    ]
},
  "bbox": [],
  "geometry": {"coordinates":[78.166667,13.066667],"type":"Point"}
}