<<<<<<< HEAD
{
  "id": 2154835,
  "type": "Feature",
  "properties": {
    "tgn:hierarchy":[
        "tgn:2154835",
        "tgn:1000001",
        "tgn:7012149",
        "tgn:2001923",
        "tgn:7007825",
        "tgn:7029392"
    ],
    "tgn:id":2154835,
    "tgn:name":"Bear Hole Island",
    "tgn:placetype":[
        "aat:300008791"
    ]
},
  "bbox": [],
  "geometry": {"coordinates":[-83.9167,36.2833],"type":"Point"}
}
=======
{"geometry":{"type":"Point","coordinates":[-83.916700,36.283300]},"type":"Feature","properties":{"hierarchy":["tgn:2154835","tgn:1000001","tgn:7012149","tgn:2001923","tgn:7007825","tgn:7029392"],"placetype":["aat:300008791"],"id":2154835,"name:xx":"Bear Hole Island"}}
>>>>>>> 03f74aca74312dbeaf24d7e61306dd6a786dc3d0
