{
  "id": 1140378,
  "type": "Feature",
  "properties": {
    "tgn:hierarchy":[
        "tgn:1140378",
        "tgn:7016808",
        "tgn:7000897",
        "tgn:1000004",
        "tgn:1000120",
        "tgn:7029392"
    ],
    "tgn:id":1140378,
    "tgn:name":"Hirata",
    "tgn:placetype":[
        "aat:300008347"
    ]
},
  "bbox": [],
  "geometry": {"coordinates":[132.75,35.4167],"type":"Point"}
}