{
  "id": 2705643,
  "type": "Feature",
  "properties": {
    "tgn:hierarchy":[
        "tgn:2705643",
        "tgn:1000001",
        "tgn:7012149",
        "tgn:2001708",
        "tgn:7007708",
        "tgn:7029392"
    ],
    "tgn:id":2705643,
    "tgn:name":"Susie Creek",
    "tgn:placetype":[
        "aat:300008706"
    ]
},
  "bbox": [],
  "geometry": {"coordinates":[-118.7167,44.45],"type":"Point"}
}