{
  "id": 7525266,
  "type": "Feature",
  "properties": {
    "tgn:hierarchy":[
        "tgn:7525266",
        "tgn:7001242",
        "tgn:7001311",
        "tgn:7016833",
        "tgn:7029392"
    ],
    "tgn:id":7525266,
    "tgn:name:en":"Baghd\u0101d\u012b, Ra's",
    "tgn:placetype":[
        "aat:300386846"
    ]
},
  "bbox": [],
  "geometry": {"coordinates":[35.109712,24.664842],"type":"Point"}
}