{
  "id": 2279735,
  "type": "Feature",
  "properties": {
    "tgn:hierarchy":[
        "tgn:2279735",
        "tgn:7014651",
        "tgn:1000001",
        "tgn:7012149",
        "tgn:7007516",
        "tgn:7029392"
    ],
    "tgn:id":2279735,
    "tgn:name":"Deadwood Cove",
    "tgn:placetype":[
        "aat:300132316"
    ]
},
  "bbox": [],
  "geometry": {"coordinates":[-76.5167,38.85],"type":"Point"}
}