<<<<<<< HEAD
{
  "id": 7482819,
  "type": "Feature",
  "properties": {
    "tgn:hierarchy":[
        "tgn:7482819",
        "tgn:7488858",
        "tgn:1000004",
        "tgn:1000141",
        "tgn:7029392"
    ],
    "tgn:id":7482819,
    "tgn:name":"Baizhou Shan",
    "tgn:placetype":[
        "aat:300387002"
    ]
},
  "bbox": [],
  "geometry": {"coordinates":[120.674444,23.714167],"type":"Point"}
}
=======
{"geometry":{"type":"Point","coordinates":[120.674444,23.714167]},"type":"Feature","properties":{"hierarchy":["tgn:7482819","tgn:7488858","tgn:1000004","tgn:1000141","tgn:7029392"],"placetype":["aat:300387002"],"id":7482819,"name:xx":"Baizhou Shan"}}
>>>>>>> 03f74aca74312dbeaf24d7e61306dd6a786dc3d0
