{
  "id": 2213471,
  "type": "Feature",
  "properties": {
    "tgn:hierarchy":[
        "tgn:2213471",
        "tgn:1000001",
        "tgn:7006451",
        "tgn:7012149",
        "tgn:2000103",
        "tgn:7029392"
    ],
    "tgn:id":2213471,
    "tgn:name":"Cabin Spring",
    "tgn:placetype":[
        "aat:300008697"
    ]
},
  "bbox": [],
  "geometry": {"coordinates":[-111.8667,34.2833],"type":"Point"}
}