{
  "id": 7149942,
  "type": "Feature",
  "properties": {
    "tgn:hierarchy":[
        "tgn:7149942",
        "tgn:7003669",
        "tgn:1000003",
        "tgn:7000084",
        "tgn:7029392"
    ],
    "tgn:id":7149942,
    "tgn:name":"Laimering",
    "tgn:placetype":[
        "aat:300008347"
    ]
},
  "bbox": [],
  "geometry": {"coordinates":[11.083333,48.383333],"type":"Point"}
}