{
  "id": 7415340,
  "type": "Feature",
  "properties": {
    "tgn:hierarchy":[
        "tgn:7415340",
        "tgn:7005584",
        "tgn:1000001",
        "tgn:7005560",
        "tgn:7029392"
    ],
    "tgn:id":7415340,
    "tgn:name":"Estaci\u00f3n San Francisco del Rinc\u00f3n",
    "tgn:placetype":[
        "aat:300007783"
    ]
},
  "bbox": [],
  "geometry": {"coordinates":[-101.820278,21.035],"type":"Point"}
}