{
  "id": 7325716,
  "type": "Feature",
  "properties": {
    "tgn:hierarchy":[
        "tgn:7325716",
        "tgn:7002836",
        "tgn:7016622",
        "tgn:1000003",
        "tgn:1000095",
        "tgn:7029392"
    ],
    "tgn:id":7325716,
    "tgn:name":"San Lorenzo, Punta de",
    "tgn:placetype":[
        "aat:300386846"
    ]
},
  "bbox": [],
  "geometry": {"coordinates":[-17.133333,28.15],"type":"Point"}
}