{
  "id": 1049639,
  "type": "Feature",
  "properties": {
    "tgn:hierarchy":[
        "tgn:1049639",
        "tgn:1000003",
        "tgn:7024124",
        "tgn:7006366",
        "tgn:7029392"
    ],
    "tgn:id":1049639,
    "tgn:name":"Zawadzkie",
    "tgn:placetype":[
        "aat:300008347"
    ]
},
  "bbox": [],
  "geometry": {"coordinates":[18.4667,50.6167],"type":"Point"}
}