{
  "id": 2559532,
  "type": "Feature",
  "properties": {
    "tgn:hierarchy":[
        "tgn:2559532",
        "tgn:1000001",
        "tgn:7012149",
        "tgn:7007157",
        "tgn:1002857",
        "tgn:7029392"
    ],
    "tgn:id":2559532,
    "tgn:name":"Ontario Peak",
    "tgn:placetype":[
        "aat:300008798"
    ]
},
  "bbox": [],
  "geometry": {"coordinates":[-117.6167,34.2167],"type":"Point"}
}