{
  "id": 1122901,
  "type": "Feature",
  "properties": {
    "tgn:hierarchy":[
        "tgn:1122901",
        "tgn:1009227",
        "tgn:1000226",
        "tgn:1000006",
        "tgn:7029392"
    ],
    "tgn:id":1122901,
    "tgn:name":"Clarence",
    "tgn:placetype":[
        "aat:300008707",
        "aat:300008699"
    ]
},
  "bbox": [],
  "geometry": {"coordinates":[173.95,-42.166667],"type":"Point"}
}