{
  "id": 2482296,
  "type": "Feature",
  "properties": {
    "tgn:hierarchy":[
        "tgn:2482296",
        "tgn:1000001",
        "tgn:7012149",
        "tgn:2000489",
        "tgn:7007250",
        "tgn:7029392"
    ],
    "tgn:id":2482296,
    "tgn:name":"Langley Gulch",
    "tgn:placetype":[
        "aat:300008761"
    ]
},
  "bbox": [],
  "geometry": {"coordinates":[-116.8333,43.8833],"type":"Point"}
}