{
  "id": 7227407,
  "type": "Feature",
  "properties": {
    "tgn:hierarchy":[
        "tgn:7227407",
        "tgn:7002681",
        "tgn:7001395",
        "tgn:1000003",
        "tgn:1000074",
        "tgn:7029392"
    ],
    "tgn:id":7227407,
    "tgn:name":"\u00dddras, K\u00f3lpos",
    "tgn:placetype":[
        "aat:300132315"
    ]
},
  "bbox": [],
  "geometry": {"coordinates":[23.451037,37.376987],"type":"Point"}
}