{
  "id": 7327799,
  "type": "Feature",
  "properties": {
    "tgn:hierarchy":[
        "tgn:7327799",
        "tgn:7002829",
        "tgn:1000003",
        "tgn:7002786",
        "tgn:1000095",
        "tgn:7029392"
    ],
    "tgn:id":7327799,
    "tgn:name":"Retorta",
    "tgn:placetype":[
        "aat:300008347"
    ]
},
  "bbox": [],
  "geometry": {"coordinates":[-7.733333,42.95],"type":"Point"}
}