{
  "id": 7221710,
  "type": "Feature",
  "properties": {
    "tgn:hierarchy":[
        "tgn:7221710",
        "tgn:7011170",
        "tgn:7002715",
        "tgn:1000003",
        "tgn:1000074",
        "tgn:7029392"
    ],
    "tgn:id":7221710,
    "tgn:name":"Milop\u00f3tamos",
    "tgn:placetype":[
        "aat:300008347"
    ]
},
  "bbox": [],
  "geometry": {"coordinates":[24.066667,41.15],"type":"Point"}
}