<<<<<<< HEAD
{
  "id": 7172597,
  "type": "Feature",
  "properties": {
    "tgn:hierarchy":[
        "tgn:7172597",
        "tgn:7003712",
        "tgn:7032547",
        "tgn:7003670",
        "tgn:1000003",
        "tgn:7000084",
        "tgn:7029392"
    ],
    "tgn:id":7172597,
    "tgn:name":"Hellersdorf",
    "tgn:placetype":[
        "aat:300000745",
        "aat:300387340"
    ]
},
  "bbox": [],
  "geometry": {"coordinates":[13.6,52.533333],"type":"Point"}
}
=======
{"geometry":{"type":"Point","coordinates":[13.600000,52.533333]},"type":"Feature","properties":{"hierarchy":["tgn:7172597","tgn:7003712","tgn:7032547","tgn:7003670","tgn:1000003","tgn:7000084","tgn:7029392"],"placetype":["aat:300000745","aat:300387340"],"id":7172597,"name:xx":"Hellersdorf"}}
>>>>>>> 03f74aca74312dbeaf24d7e61306dd6a786dc3d0
