{
  "id": 2750351,
  "type": "Feature",
  "properties": {
    "tgn:hierarchy":[
        "tgn:2750351",
        "tgn:1000001",
        "tgn:2001777",
        "tgn:7012149",
        "tgn:7007713",
        "tgn:7029392"
    ],
    "tgn:id":2750351,
    "tgn:name":"Wanalain, Lake",
    "tgn:placetype":[
        "aat:300006191"
    ]
},
  "bbox": [],
  "geometry": {"coordinates":[-99.25,43.6333],"type":"Point"}
}