{
  "id": 2040200,
  "type": "Feature",
  "properties": {
    "tgn:hierarchy":[
        "tgn:2040200",
        "tgn:1000001",
        "tgn:7012149",
        "tgn:2000786",
        "tgn:7007255",
        "tgn:7029392"
    ],
    "tgn:id":2040200,
    "tgn:name":"Masonville",
    "tgn:placetype":[
        "aat:300008347"
    ]
},
  "bbox": [],
  "geometry": {"coordinates":[-87.0333,37.6667],"type":"Point"}
}