{
  "id": 2203902,
  "type": "Feature",
  "properties": {
    "tgn:hierarchy":[
        "tgn:2203902",
        "tgn:1000001",
        "tgn:2000457",
        "tgn:7012149",
        "tgn:7007250",
        "tgn:7029392"
    ],
    "tgn:id":2203902,
    "tgn:name":"Buckskin Spring",
    "tgn:placetype":[
        "aat:300008697"
    ]
},
  "bbox": [],
  "geometry": {"coordinates":[-112.2333,43.0833],"type":"Point"}
}