{
  "id": 7527804,
  "type": "Feature",
  "properties": {
    "tgn:hierarchy":[
        "tgn:7527804",
        "tgn:7001242",
        "tgn:7001311",
        "tgn:7016833",
        "tgn:7029392"
    ],
    "tgn:id":7527804,
    "tgn:name:en":"Sifein, W\u00e2di",
    "tgn:placetype":[
        "aat:300379998"
    ]
},
  "bbox": [],
  "geometry": {"coordinates":[34.879619,25.100808],"type":"Point"}
}