{
  "id": 2340354,
  "type": "Feature",
  "properties": {
    "tgn:hierarchy":[
        "tgn:2340354",
        "tgn:1000001",
        "tgn:7012149",
        "tgn:2001711",
        "tgn:7007708",
        "tgn:7029392"
    ],
    "tgn:id":2340354,
    "tgn:name":"French Gulch",
    "tgn:placetype":[
        "aat:300008761"
    ]
},
  "bbox": [],
  "geometry": {"coordinates":[-123.0667,42.05],"type":"Point"}
}