<<<<<<< HEAD
{
  "id": 2257719,
  "type": "Feature",
  "properties": {
    "tgn:hierarchy":[
        "tgn:2257719",
        "tgn:1000001",
        "tgn:7012149",
        "tgn:7007158",
        "tgn:7029392"
    ],
    "tgn:id":2257719,
    "tgn:name":"Corral Gulch",
    "tgn:placetype":[
        "aat:300008761"
    ]
},
  "bbox": [],
  "geometry": {"coordinates":[-107.45,38.5167],"type":"Point"}
}
=======
{"geometry":{"type":"Point","coordinates":[-107.450000,38.516700]},"type":"Feature","properties":{"hierarchy":["tgn:2257719","tgn:1000001","tgn:7012149","tgn:7007158","tgn:7029392"],"placetype":["aat:300008761"],"id":2257719,"name:xx":"Corral Gulch"}}
>>>>>>> 03f74aca74312dbeaf24d7e61306dd6a786dc3d0
