{
  "id": 2702553,
  "type": "Feature",
  "properties": {
    "tgn:hierarchy":[
        "tgn:2702553",
        "tgn:1000001",
        "tgn:7012149",
        "tgn:7007157",
        "tgn:7029392"
    ],
    "tgn:id":2702553,
    "tgn:name":"Sulphur Creek",
    "tgn:placetype":[
        "aat:300008706"
    ]
},
  "bbox": [],
  "geometry": {"coordinates":[-120.4833,39.65],"type":"Point"}
}