{
  "id": 7192009,
  "type": "Feature",
  "properties": {
    "tgn:hierarchy":[
        "tgn:7192009",
        "tgn:7003669",
        "tgn:1000003",
        "tgn:7000084",
        "tgn:7029392"
    ],
    "tgn:id":7192009,
    "tgn:name":"Fl\u00fcssen",
    "tgn:placetype":[
        "aat:300008347"
    ]
},
  "bbox": [],
  "geometry": {"coordinates":[10.283333,48.216667],"type":"Point"}
}