<<<<<<< HEAD
{
  "id": 7372670,
  "type": "Feature",
  "properties": {
    "tgn:hierarchy":[
        "tgn:7372670",
        "tgn:7005584",
        "tgn:1000001",
        "tgn:7005560",
        "tgn:7029392"
    ],
    "tgn:id":7372670,
    "tgn:name":"La Laborcita",
    "tgn:placetype":[
        "aat:300008347"
    ]
},
  "bbox": [],
  "geometry": {"coordinates":[-101.55,21.1],"type":"Point"}
}
=======
{"geometry":{"type":"Point","coordinates":[-101.550000,21.100000]},"type":"Feature","properties":{"hierarchy":["tgn:7372670","tgn:7005584","tgn:1000001","tgn:7005560","tgn:7029392"],"placetype":["aat:300008347"],"id":7372670,"name:xx":"La Laborcita"}}
>>>>>>> 03f74aca74312dbeaf24d7e61306dd6a786dc3d0
