{
  "id": 7092873,
  "type": "Feature",
  "properties": {
    "tgn:hierarchy":[
        "tgn:7092873",
        "tgn:1000003",
        "tgn:7003677",
        "tgn:7000084",
        "tgn:7029392"
    ],
    "tgn:id":7092873,
    "tgn:name":"Schraberg",
    "tgn:placetype":[
        "aat:300008347"
    ]
},
  "bbox": [],
  "geometry": {"coordinates":[7.416667,51.416667],"type":"Point"}
}