{
  "id": 7439017,
  "type": "Feature",
  "properties": {
    "tgn:hierarchy":[
        "tgn:7439017",
        "tgn:7005575",
        "tgn:1000001",
        "tgn:7005560",
        "tgn:7029392"
    ],
    "tgn:id":7439017,
    "tgn:name":"Tezontle",
    "tgn:placetype":[
        "aat:300007783"
    ]
},
  "bbox": [],
  "geometry": {"coordinates":[-99.033333,19.383333],"type":"Point"}
}