{
  "id": 2650001,
  "type": "Feature",
  "properties": {
    "tgn:hierarchy":[
        "tgn:2650001",
        "tgn:1000001",
        "tgn:2002106",
        "tgn:7012149",
        "tgn:7007827",
        "tgn:7029392"
    ],
    "tgn:id":2650001,
    "tgn:name":"Sea Gull Point",
    "tgn:placetype":[
        "aat:300008850"
    ]
},
  "bbox": [],
  "geometry": {"coordinates":[-112.15,40.9333],"type":"Point"}
}