{
  "id": 7036113,
  "type": "Feature",
  "properties": {
    "tgn:hierarchy":[
        "tgn:7036113",
        "tgn:7002996",
        "tgn:1000003",
        "tgn:7002997",
        "tgn:1000080",
        "tgn:7029392"
    ],
    "tgn:id":7036113,
    "tgn:name":"Barriera",
    "tgn:placetype":[
        "aat:300008347"
    ]
},
  "bbox": [],
  "geometry": {"coordinates":[12.250833,45.863611],"type":"Point"}
}