{
  "id": 7150359,
  "type": "Feature",
  "properties": {
    "tgn:hierarchy":[
        "tgn:7150359",
        "tgn:7000096",
        "tgn:1000003",
        "tgn:7000084",
        "tgn:7029392"
    ],
    "tgn:id":7150359,
    "tgn:name":"Krangen",
    "tgn:placetype":[
        "aat:300008347"
    ]
},
  "bbox": [],
  "geometry": {"coordinates":[12.85,52.983333],"type":"Point"}
}