{
  "id": 7093534,
  "type": "Feature",
  "properties": {
    "tgn:hierarchy":[
        "tgn:7093534",
        "tgn:1000003",
        "tgn:7003678",
        "tgn:7000084",
        "tgn:7029392"
    ],
    "tgn:id":7093534,
    "tgn:name":"Schoren",
    "tgn:placetype":[
        "aat:300008777"
    ]
},
  "bbox": [],
  "geometry": {"coordinates":[9.166667,51.416667],"type":"Point"}
}