<<<<<<< HEAD
{
  "id": 2764465,
  "type": "Feature",
  "properties": {
    "tgn:hierarchy":[
        "tgn:2764465",
        "tgn:1000001",
        "tgn:2001173",
        "tgn:7012149",
        "tgn:7007523",
        "tgn:7029392"
    ],
    "tgn:id":2764465,
    "tgn:name":"Whig Creek",
    "tgn:placetype":[
        "aat:300008706"
    ]
},
  "bbox": [],
  "geometry": {"coordinates":[-93.2833,38.1],"type":"Point"}
}
=======
{"geometry":{"type":"Point","coordinates":[-93.283300,38.100000]},"type":"Feature","properties":{"hierarchy":["tgn:2764465","tgn:1000001","tgn:2001173","tgn:7012149","tgn:7007523","tgn:7029392"],"placetype":["aat:300008706"],"id":2764465,"name:xx":"Whig Creek"}}
>>>>>>> 03f74aca74312dbeaf24d7e61306dd6a786dc3d0
