{
  "id": 7232806,
  "type": "Feature",
  "properties": {
    "tgn:hierarchy":[
        "tgn:7232806",
        "tgn:7002707",
        "tgn:7002705",
        "tgn:1000003",
        "tgn:1000074",
        "tgn:7029392"
    ],
    "tgn:id":7232806,
    "tgn:name":"K\u00e1to V\u00edtsa",
    "tgn:placetype":[
        "aat:300008347"
    ]
},
  "bbox": [],
  "geometry": {"coordinates":[20.75,39.866667],"type":"Point"}
}