<<<<<<< HEAD
{
  "id": 7174958,
  "type": "Feature",
  "properties": {
    "tgn:hierarchy":[
        "tgn:7174958",
        "tgn:1000003",
        "tgn:7003677",
        "tgn:7000084",
        "tgn:7029392"
    ],
    "tgn:id":7174958,
    "tgn:name":"Gro\u00dfheide",
    "tgn:placetype":[
        "aat:300008347"
    ]
},
  "bbox": [],
  "geometry": {"coordinates":[6.4,51.216667],"type":"Point"}
}
=======
{"geometry":{"type":"Point","coordinates":[6.400000,51.216667]},"type":"Feature","properties":{"hierarchy":["tgn:7174958","tgn:1000003","tgn:7003677","tgn:7000084","tgn:7029392"],"placetype":["aat:300008347"],"id":7174958,"name:xx":"Gro\u00dfheide"}}
>>>>>>> 03f74aca74312dbeaf24d7e61306dd6a786dc3d0
