{
  "id": 2738132,
  "type": "Feature",
  "properties": {
    "tgn:hierarchy":[
        "tgn:2738132",
        "tgn:1000001",
        "tgn:2000922",
        "tgn:7012149",
        "tgn:7007515",
        "tgn:7029392"
    ],
    "tgn:id":2738132,
    "tgn:name":"Ulmer Brook",
    "tgn:placetype":[
        "aat:300008699"
    ]
},
  "bbox": [],
  "geometry": {"coordinates":[-68.7833,44.5333],"type":"Point"}
}