{
  "id": 2412984,
  "type": "Feature",
  "properties": {
    "tgn:hierarchy":[
        "tgn:2412984",
        "tgn:1000001",
        "tgn:7012149",
        "tgn:2001247",
        "tgn:7007523",
        "tgn:7029392"
    ],
    "tgn:id":2412984,
    "tgn:name":"Ink Hollow",
    "tgn:placetype":[
        "aat:300008761"
    ]
},
  "bbox": [],
  "geometry": {"coordinates":[-91.4833,37.25],"type":"Point"}
}