<<<<<<< HEAD
{
  "id": 7059892,
  "type": "Feature",
  "properties": {
    "tgn:hierarchy":[
        "tgn:7059892",
        "tgn:1000003",
        "tgn:7003677",
        "tgn:7000084",
        "tgn:7029392"
    ],
    "tgn:id":7059892,
    "tgn:name":"Ahe",
    "tgn:placetype":[
        "aat:300008347"
    ]
},
  "bbox": [],
  "geometry": {"coordinates":[7.433333,51.2],"type":"Point"}
}
=======
{"geometry":{"type":"Point","coordinates":[7.433333,51.200000]},"type":"Feature","properties":{"hierarchy":["tgn:7059892","tgn:1000003","tgn:7003677","tgn:7000084","tgn:7029392"],"placetype":["aat:300008347"],"id":7059892,"name:xx":"Ahe"}}
>>>>>>> 03f74aca74312dbeaf24d7e61306dd6a786dc3d0
