{
  "id": 2264416,
  "type": "Feature",
  "properties": {
    "tgn:hierarchy":[
        "tgn:2264416",
        "tgn:1000001",
        "tgn:7012149",
        "tgn:2001201",
        "tgn:7007523",
        "tgn:7029392"
    ],
    "tgn:id":2264416,
    "tgn:name":"Crabapple Branch",
    "tgn:placetype":[
        "aat:300008699"
    ]
},
  "bbox": [],
  "geometry": {"coordinates":[-94.0167,40.25],"type":"Point"}
}