{
  "id": 7046788,
  "type": "Feature",
  "properties": {
    "tgn:hierarchy":[
        "tgn:7046788",
        "tgn:7003135",
        "tgn:1000003",
        "tgn:7003080",
        "tgn:1000080",
        "tgn:7029392"
    ],
    "tgn:id":7046788,
    "tgn:name":"Colle Alto",
    "tgn:placetype":[
        "aat:300008347"
    ]
},
  "bbox": [],
  "geometry": {"coordinates":[13.566667,41.566667],"type":"Point"}
}