{
  "id": 2140572,
  "type": "Feature",
  "properties": {
    "tgn:hierarchy":[
        "tgn:2140572",
        "tgn:1002134",
        "tgn:1000001",
        "tgn:7012149",
        "tgn:7007251",
        "tgn:7029392"
    ],
    "tgn:id":2140572,
    "tgn:name":"Austin Creek Settling Basin",
    "tgn:placetype":[
        "aat:300386845"
    ]
},
  "bbox": [],
  "geometry": {"coordinates":[-91.3167,39.7667],"type":"Point"}
}