{
  "id": 2281842,
  "type": "Feature",
  "properties": {
    "tgn:hierarchy":[
        "tgn:2281842",
        "tgn:1000001",
        "tgn:7012149",
        "tgn:2002284",
        "tgn:7013961",
        "tgn:7029392"
    ],
    "tgn:id":2281842,
    "tgn:name":"Deer Creek",
    "tgn:placetype":[
        "aat:300008706"
    ]
},
  "bbox": [],
  "geometry": {"coordinates":[-80.6833,38.25],"type":"Point"}
}