{
  "id": 2436855,
  "type": "Feature",
  "properties": {
    "tgn:hierarchy":[
        "tgn:2436855",
        "tgn:1002648",
        "tgn:1000001",
        "tgn:7019158",
        "tgn:7012149",
        "tgn:7007249",
        "tgn:7029392"
    ],
    "tgn:id":2436855,
    "tgn:name":"Kilea",
    "tgn:placetype":[
        "aat:300008798"
    ]
},
  "bbox": [],
  "geometry": {"coordinates":[-156.6167,20.8167],"type":"Point"}
}