{
  "id": 7285930,
  "type": "Feature",
  "properties": {
    "tgn:hierarchy":[
        "tgn:7285930",
        "tgn:1001705",
        "tgn:1000049",
        "tgn:1000002",
        "tgn:7029392"
    ],
    "tgn:id":7285930,
    "tgn:name":"Quebrada de Canales",
    "tgn:placetype":[
        "aat:300387200"
    ]
},
  "bbox": [],
  "geometry": {"coordinates":[-71.883333,-34.766667],"type":"Point"}
}