{
  "id": 7532984,
  "type": "Feature",
  "properties": {
    "tgn:hierarchy":[
        "tgn:7532984",
        "tgn:7001242",
        "tgn:7016833",
        "tgn:1001335",
        "tgn:7029392"
    ],
    "tgn:id":7532984,
    "tgn:name:en":"Ma\u015frif Shin\u016b",
    "tgn:placetype":[
        "aat:300006075"
    ]
},
  "bbox": [],
  "geometry": {"coordinates":[30.921155,31.012418],"type":"Point"}
}