{
  "id": 1087111,
  "type": "Feature",
  "properties": {
    "tgn:hierarchy":[
        "tgn:1087111",
        "tgn:1000004",
        "tgn:7001055",
        "tgn:1000145",
        "tgn:7029392"
    ],
    "tgn:id":1087111,
    "tgn:name":"\u0110\u00f4ng Hai",
    "tgn:placetype":[
        "aat:300008347"
    ]
},
  "bbox": [],
  "geometry": {"coordinates":[109.2333,12.5667],"type":"Point"}
}