{
  "id": 1117704,
  "type": "Feature",
  "properties": {
    "tgn:hierarchy":[
        "tgn:1117704",
        "tgn:1000001",
        "tgn:7012149",
        "tgn:7007250",
        "tgn:7029392"
    ],
    "tgn:id":1117704,
    "tgn:name":"Pend Oreille, Lake",
    "tgn:placetype":[
        "aat:300008680"
    ]
},
  "bbox": [],
  "geometry": {"coordinates":[-116.3333,48.15],"type":"Point"}
}