{
  "id": 2037103,
  "type": "Feature",
  "properties": {
    "tgn:hierarchy":[
        "tgn:2037103",
        "tgn:1000001",
        "tgn:2000670",
        "tgn:7012149",
        "tgn:7007254",
        "tgn:7029392"
    ],
    "tgn:id":2037103,
    "tgn:name":"Scammon",
    "tgn:placetype":[
        "aat:300008347"
    ]
},
  "bbox": [],
  "geometry": {"coordinates":[-94.8167,37.2667],"type":"Point"}
}