{
  "id": 2272009,
  "type": "Feature",
  "properties": {
    "tgn:hierarchy":[
        "tgn:2272009",
        "tgn:1000001",
        "tgn:2002243",
        "tgn:7012149",
        "tgn:7007920",
        "tgn:7029392"
    ],
    "tgn:id":2272009,
    "tgn:name":"Curlew Creek",
    "tgn:placetype":[
        "aat:300008706"
    ]
},
  "bbox": [],
  "geometry": {"coordinates":[-118.65,48.7667],"type":"Point"}
}