{
  "id": 7322301,
  "type": "Feature",
  "properties": {
    "tgn:hierarchy":[
        "tgn:7322301",
        "tgn:1001630",
        "tgn:1000049",
        "tgn:1000002",
        "tgn:7029392"
    ],
    "tgn:id":7322301,
    "tgn:name":"\u00c1spera, Quebrada",
    "tgn:placetype":[
        "aat:300008699"
    ]
},
  "bbox": [],
  "geometry": {"coordinates":[-69.816667,-28.383333],"type":"Point"}
}