{
  "id": 7439234,
  "type": "Feature",
  "properties": {
    "tgn:hierarchy":[
        "tgn:7439234",
        "tgn:7005583",
        "tgn:1000001",
        "tgn:7005560",
        "tgn:7029392"
    ],
    "tgn:id":7439234,
    "tgn:name":"San Vicente",
    "tgn:placetype":[
        "aat:300008347"
    ]
},
  "bbox": [],
  "geometry": {"coordinates":[-105.677778,24.353333],"type":"Point"}
}