{
  "id": 2437165,
  "type": "Feature",
  "properties": {
    "tgn:hierarchy":[
        "tgn:2437165",
        "tgn:1000001",
        "tgn:7006451",
        "tgn:2000094",
        "tgn:7012149",
        "tgn:7029392"
    ],
    "tgn:id":2437165,
    "tgn:name":"Kimball",
    "tgn:placetype":[
        "aat:300008347"
    ]
},
  "bbox": [],
  "geometry": {"coordinates":[-109.7667,32.8833],"type":"Point"}
}