{
  "id": 2481915,
  "type": "Feature",
  "properties": {
    "tgn:hierarchy":[
        "tgn:2481915",
        "tgn:1000001",
        "tgn:2001091",
        "tgn:7012149",
        "tgn:7007522",
        "tgn:7029392"
    ],
    "tgn:id":2481915,
    "tgn:name":"Lane Bayou",
    "tgn:placetype":[
        "aat:300008699"
    ]
},
  "bbox": [],
  "geometry": {"coordinates":[-91.0167,33.85],"type":"Point"}
}