{
  "id": 2189149,
  "type": "Feature",
  "properties": {
    "tgn:hierarchy":[
        "tgn:2189149",
        "tgn:1000001",
        "tgn:1002260",
        "tgn:7012149",
        "tgn:7007920",
        "tgn:7029392"
    ],
    "tgn:id":2189149,
    "tgn:name":"Boundary Butte",
    "tgn:placetype":[
        "aat:300008798"
    ]
},
  "bbox": [],
  "geometry": {"coordinates":[-120.6333,47.5333],"type":"Point"}
}