<<<<<<< HEAD
{
  "id": 7363382,
  "type": "Feature",
  "properties": {
    "tgn:hierarchy":[
        "tgn:7363382",
        "tgn:7005585",
        "tgn:1000001",
        "tgn:7005560",
        "tgn:7029392"
    ],
    "tgn:id":7363382,
    "tgn:name":"El Algod\u00f3n",
    "tgn:placetype":[
        "aat:300008347"
    ]
},
  "bbox": [],
  "geometry": {"coordinates":[-101.5,18.333333],"type":"Point"}
}
=======
{"geometry":{"type":"Point","coordinates":[-101.500000,18.333333]},"type":"Feature","properties":{"hierarchy":["tgn:7363382","tgn:7005585","tgn:1000001","tgn:7005560","tgn:7029392"],"placetype":["aat:300008347"],"id":7363382,"name:xx":"El Algod\u00f3n"}}
>>>>>>> 03f74aca74312dbeaf24d7e61306dd6a786dc3d0
