{
  "id": 7159988,
  "type": "Feature",
  "properties": {
    "tgn:hierarchy":[
        "tgn:7159988",
        "tgn:7003669",
        "tgn:1000003",
        "tgn:7000084",
        "tgn:7029392"
    ],
    "tgn:id":7159988,
    "tgn:name":"Holzbuch",
    "tgn:placetype":[
        "aat:300008347"
    ]
},
  "bbox": [],
  "geometry": {"coordinates":[12.533333,48.716667],"type":"Point"}
}