{
  "id": 7474252,
  "type": "Feature",
  "properties": {
    "tgn:hierarchy":[
        "tgn:7474252",
        "tgn:1000004",
        "tgn:7001014",
        "tgn:1000141",
        "tgn:7029392"
    ],
    "tgn:id":7474252,
    "tgn:name":"Dinglulitan",
    "tgn:placetype":[
        "aat:300008347"
    ]
},
  "bbox": [],
  "geometry": {"coordinates":[120.236944,23.695],"type":"Point"}
}