{
  "id": 7319511,
  "type": "Feature",
  "properties": {
    "tgn:hierarchy":[
        "tgn:7319511",
        "tgn:1001657",
        "tgn:1000049",
        "tgn:1000002",
        "tgn:7029392"
    ],
    "tgn:id":7319511,
    "tgn:name":"Alto, Cerro",
    "tgn:placetype":[
        "aat:300008795"
    ]
},
  "bbox": [],
  "geometry": {"coordinates":[-70.45,-32.016667],"type":"Point"}
}