{
  "id": 2090349,
  "type": "Feature",
  "properties": {
    "tgn:hierarchy":[
        "tgn:2090349",
        "tgn:1000001",
        "tgn:7012149",
        "tgn:7014185",
        "tgn:7007710",
        "tgn:7029392"
    ],
    "tgn:id":2090349,
    "tgn:name":"Lower Peanut",
    "tgn:placetype":[
        "aat:300008347"
    ]
},
  "bbox": [],
  "geometry": {"coordinates":[-79.75,39.9667],"type":"Point"}
}