{
  "id": 7507167,
  "type": "Feature",
  "properties": {
    "tgn:hierarchy":[
        "tgn:7507167",
        "tgn:1009227",
        "tgn:1000226",
        "tgn:1000006",
        "tgn:7016850",
        "tgn:7029392"
    ],
    "tgn:id":7507167,
    "tgn:name:en":"Purple Hill",
    "tgn:placetype":[
        "aat:300008777"
    ]
},
  "bbox": [],
  "geometry": {"coordinates":[169.45,-43.916667],"type":"Point"}
}