{
  "id": 2410693,
  "type": "Feature",
  "properties": {
    "tgn:hierarchy":[
        "tgn:2410693",
        "tgn:1000001",
        "tgn:7012149",
        "tgn:2000400",
        "tgn:7007248",
        "tgn:7029392"
    ],
    "tgn:id":2410693,
    "tgn:name":"Indian Creek",
    "tgn:placetype":[
        "aat:300008706"
    ]
},
  "bbox": [],
  "geometry": {"coordinates":[-83.0833,33.9167],"type":"Point"}
}