<<<<<<< HEAD
{
  "id": 2766686,
  "type": "Feature",
  "properties": {
    "tgn:hierarchy":[
        "tgn:2766686",
        "tgn:1000001",
        "tgn:7012149",
        "tgn:1002548",
        "tgn:7007919",
        "tgn:7029392"
    ],
    "tgn:id":2766686,
    "tgn:name":"White Oak Landing",
    "tgn:placetype":[
        "aat:300008347"
    ]
},
  "bbox": [],
  "geometry": {"coordinates":[-76.9667,37.6833],"type":"Point"}
}
=======
{"geometry":{"type":"Point","coordinates":[-76.966700,37.683300]},"type":"Feature","properties":{"hierarchy":["tgn:2766686","tgn:1000001","tgn:7012149","tgn:1002548","tgn:7007919","tgn:7029392"],"placetype":["aat:300008347"],"id":2766686,"name:xx":"White Oak Landing"}}
>>>>>>> 03f74aca74312dbeaf24d7e61306dd6a786dc3d0
