{
  "id": 2701507,
  "type": "Feature",
  "properties": {
    "tgn:hierarchy":[
        "tgn:2701507",
        "tgn:1000001",
        "tgn:7012149",
        "tgn:2001222",
        "tgn:7007523",
        "tgn:7029392"
    ],
    "tgn:id":2701507,
    "tgn:name":"Sugar Tree Ridge",
    "tgn:placetype":[
        "aat:300266640"
    ]
},
  "bbox": [],
  "geometry": {"coordinates":[-89.35,36.6333],"type":"Point"}
}