{
  "id": 7561065,
  "type": "Feature",
  "properties": {
    "tgn:hierarchy":[
        "tgn:7561065",
        "tgn:1000004",
        "tgn:7000198",
        "tgn:7016722",
        "tgn:7029392"
    ],
    "tgn:id":7561065,
    "tgn:name:en":"Malpura",
    "tgn:placetype":[
        "aat:300008347"
    ]
},
  "bbox": [],
  "geometry": {"coordinates":[79.466767,27.09655],"type":"Point"}
}