<<<<<<< HEAD
{
  "id": 2257533,
  "type": "Feature",
  "properties": {
    "tgn:hierarchy":[
        "tgn:2257533",
        "tgn:1000001",
        "tgn:7012149",
        "tgn:7007157",
        "tgn:1002972",
        "tgn:7029392"
    ],
    "tgn:id":2257533,
    "tgn:name":"Corral Canyon",
    "tgn:placetype":[
        "aat:300008761"
    ]
},
  "bbox": [],
  "geometry": {"coordinates":[-119.3,34.75],"type":"Point"}
}
=======
{"geometry":{"type":"Point","coordinates":[-119.300000,34.750000]},"type":"Feature","properties":{"hierarchy":["tgn:2257533","tgn:1000001","tgn:7012149","tgn:7007157","tgn:1002972","tgn:7029392"],"placetype":["aat:300008761"],"id":2257533,"name:xx":"Corral Canyon"}}
>>>>>>> 03f74aca74312dbeaf24d7e61306dd6a786dc3d0
