<<<<<<< HEAD
{
  "id": 2250237,
  "type": "Feature",
  "properties": {
    "tgn:hierarchy":[
        "tgn:2250237",
        "tgn:1000001",
        "tgn:7012149",
        "tgn:1002733",
        "tgn:7007919",
        "tgn:7029392"
    ],
    "tgn:id":2250237,
    "tgn:name":"Collins Point",
    "tgn:placetype":[
        "aat:300008850"
    ]
},
  "bbox": [],
  "geometry": {"coordinates":[-76.3167,37.8333],"type":"Point"}
}
=======
{"geometry":{"type":"Point","coordinates":[-76.316700,37.833300]},"type":"Feature","properties":{"hierarchy":["tgn:2250237","tgn:1000001","tgn:7012149","tgn:1002733","tgn:7007919","tgn:7029392"],"placetype":["aat:300008850"],"id":2250237,"name:xx":"Collins Point"}}
>>>>>>> 03f74aca74312dbeaf24d7e61306dd6a786dc3d0
