{
  "id": 2537327,
  "type": "Feature",
  "properties": {
    "tgn:hierarchy":[
        "tgn:2537327",
        "tgn:1000001",
        "tgn:7012149",
        "tgn:2001447",
        "tgn:7007566",
        "tgn:7029392"
    ],
    "tgn:id":2537327,
    "tgn:name":"Negro Ed Canyon",
    "tgn:placetype":[
        "aat:300008761"
    ]
},
  "bbox": [],
  "geometry": {"coordinates":[-105.85,32.6667],"type":"Point"}
}