<<<<<<< HEAD
{
  "id": 2150039,
  "type": "Feature",
  "properties": {
    "tgn:hierarchy":[
        "tgn:2150039",
        "tgn:1000001",
        "tgn:7012149",
        "tgn:7007827",
        "tgn:7029392"
    ],
    "tgn:id":2150039,
    "tgn:name":"Barton Canyon",
    "tgn:placetype":[
        "aat:300008761"
    ]
},
  "bbox": [],
  "geometry": {"coordinates":[-110.1833,39.4667],"type":"Point"}
}
=======
{"geometry":{"type":"Point","coordinates":[-110.183300,39.466700]},"type":"Feature","properties":{"hierarchy":["tgn:2150039","tgn:1000001","tgn:7012149","tgn:7007827","tgn:7029392"],"placetype":["aat:300008761"],"id":2150039,"name:xx":"Barton Canyon"}}
>>>>>>> 03f74aca74312dbeaf24d7e61306dd6a786dc3d0
