{
  "id": 2150039,
  "type": "Feature",
  "properties": {
    "tgn:hierarchy":[
        "tgn:2150039",
        "tgn:1000001",
        "tgn:7012149",
        "tgn:7007827",
        "tgn:7029392"
    ],
    "tgn:id":2150039,
    "tgn:name":"Barton Canyon",
    "tgn:placetype":[
        "aat:300008761"
    ]
},
  "bbox": [],
  "geometry": {"coordinates":[-110.1833,39.4667],"type":"Point"}
}