<<<<<<< HEAD
{
  "id": 7359998,
  "type": "Feature",
  "properties": {
    "tgn:hierarchy":[
        "tgn:7359998",
        "tgn:7005581",
        "tgn:1000001",
        "tgn:7005560",
        "tgn:7029392"
    ],
    "tgn:id":7359998,
    "tgn:name":"Conchos",
    "tgn:placetype":[
        "aat:300008347"
    ]
},
  "bbox": [],
  "geometry": {"coordinates":[-105.25,28.0],"type":"Point"}
}
=======
{"geometry":{"type":"Point","coordinates":[-105.250000,28.000000]},"type":"Feature","properties":{"hierarchy":["tgn:7359998","tgn:7005581","tgn:1000001","tgn:7005560","tgn:7029392"],"placetype":["aat:300008347"],"id":7359998,"name:xx":"Conchos"}}
>>>>>>> 03f74aca74312dbeaf24d7e61306dd6a786dc3d0
