{
  "id": 7590030,
  "type": "Feature",
  "properties": {
    "tgn:hierarchy":[
        "tgn:7590030",
        "tgn:1000004",
        "tgn:7000198",
        "tgn:7000799",
        "tgn:7029392"
    ],
    "tgn:id":7590030,
    "tgn:name:en":"Khori\u0101n",
    "tgn:placetype":[
        "aat:300008347"
    ]
},
  "bbox": [],
  "geometry": {"coordinates":[73.987536,34.613549],"type":"Point"}
}