{
  "id": 2184315,
  "type": "Feature",
  "properties": {
    "tgn:hierarchy":[
        "tgn:2184315",
        "tgn:1000001",
        "tgn:7012149",
        "tgn:7007157",
        "tgn:2000185",
        "tgn:7029392"
    ],
    "tgn:id":2184315,
    "tgn:name":"Bobcat Canyon",
    "tgn:placetype":[
        "aat:300008761"
    ]
},
  "bbox": [],
  "geometry": {"coordinates":[-123.4167,38.95],"type":"Point"}
}