{
  "id": 7062098,
  "type": "Feature",
  "properties": {
    "tgn:hierarchy":[
        "tgn:7062098",
        "tgn:7000096",
        "tgn:1000003",
        "tgn:7000084",
        "tgn:7029392"
    ],
    "tgn:id":7062098,
    "tgn:name":"Amor-Teich",
    "tgn:placetype":[
        "aat:300008688"
    ]
},
  "bbox": [],
  "geometry": {"coordinates":[13.15,51.966667],"type":"Point"}
}