{
  "id": 1129462,
  "type": "Feature",
  "properties": {
    "tgn:hierarchy":[
        "tgn:1129462",
        "tgn:1000001",
        "tgn:7012149",
        "tgn:7007250",
        "tgn:7029392"
    ],
    "tgn:id":1129462,
    "tgn:name":"Salmon",
    "tgn:placetype":[
        "aat:300008707"
    ]
},
  "bbox": [],
  "geometry": {"coordinates":[-114.7667,43.7833],"type":"Point"}
}