{
  "id": 2588942,
  "type": "Feature",
  "properties": {
    "tgn:hierarchy":[
        "tgn:2588942",
        "tgn:1000001",
        "tgn:2001734",
        "tgn:7012149",
        "tgn:7007712",
        "tgn:7029392"
    ],
    "tgn:id":2588942,
    "tgn:name":"Pockoy Island",
    "tgn:placetype":[
        "aat:300008791"
    ]
},
  "bbox": [],
  "geometry": {"coordinates":[-80.2333,32.5333],"type":"Point"}
}