{
  "id": 1104354,
  "type": "Feature",
  "properties": {
    "tgn:hierarchy":[
        "tgn:1104354",
        "tgn:1000001",
        "tgn:7012149",
        "tgn:1002545",
        "tgn:7007157",
        "tgn:7029392"
    ],
    "tgn:id":1104354,
    "tgn:name":"Cummings Mountain",
    "tgn:placetype":[
        "aat:300008795"
    ]
},
  "bbox": [],
  "geometry": {"coordinates":[-118.5667,35.0333],"type":"Point"}
}