<<<<<<< HEAD
{
  "id": 2760375,
  "type": "Feature",
  "properties": {
    "tgn:hierarchy":[
        "tgn:2760375",
        "tgn:1000001",
        "tgn:7012149",
        "tgn:2002371",
        "tgn:7007923",
        "tgn:7029392"
    ],
    "tgn:id":2760375,
    "tgn:name":"West Fork Sixmile Creek",
    "tgn:placetype":[
        "aat:300008706"
    ]
},
  "bbox": [],
  "geometry": {"coordinates":[-109.75,43.75],"type":"Point"}
}
=======
{"geometry":{"type":"Point","coordinates":[-109.750000,43.750000]},"type":"Feature","properties":{"hierarchy":["tgn:2760375","tgn:1000001","tgn:7012149","tgn:2002371","tgn:7007923","tgn:7029392"],"placetype":["aat:300008706"],"id":2760375,"name:xx":"West Fork Sixmile Creek"}}
>>>>>>> 03f74aca74312dbeaf24d7e61306dd6a786dc3d0
