{
  "id": 2688003,
  "type": "Feature",
  "properties": {
    "tgn:hierarchy":[
        "tgn:2688003",
        "tgn:1000001",
        "tgn:7012149",
        "tgn:2001539",
        "tgn:7007709",
        "tgn:7029392"
    ],
    "tgn:id":2688003,
    "tgn:name":"Springfield",
    "tgn:placetype":[
        "aat:300008347"
    ]
},
  "bbox": [],
  "geometry": {"coordinates":[-79.5167,34.7667],"type":"Point"}
}