<<<<<<< HEAD
{
  "id": 7477100,
  "type": "Feature",
  "properties": {
    "tgn:hierarchy":[
        "tgn:7477100",
        "tgn:1000004",
        "tgn:1000454",
        "tgn:1000141",
        "tgn:7029392"
    ],
    "tgn:id":7477100,
    "tgn:name":"Panshankeng Xi",
    "tgn:placetype":[
        "aat:300008699"
    ]
},
  "bbox": [],
  "geometry": {"coordinates":[121.793467,25.002442],"type":"Point"}
}
=======
{"geometry":{"type":"Point","coordinates":[121.793467,25.002442]},"type":"Feature","properties":{"hierarchy":["tgn:7477100","tgn:1000004","tgn:1000454","tgn:1000141","tgn:7029392"],"placetype":["aat:300008699"],"id":7477100,"name:xx":"Panshankeng Xi"}}
>>>>>>> 03f74aca74312dbeaf24d7e61306dd6a786dc3d0
