{
  "id": 7477100,
  "type": "Feature",
  "properties": {
    "tgn:hierarchy":[
        "tgn:7477100",
        "tgn:1000004",
        "tgn:1000454",
        "tgn:1000141",
        "tgn:7029392"
    ],
    "tgn:id":7477100,
    "tgn:name":"Panshankeng Xi",
    "tgn:placetype":[
        "aat:300008699"
    ]
},
  "bbox": [],
  "geometry": {"coordinates":[121.793467,25.002442],"type":"Point"}
}