{
  "id": 2067284,
  "type": "Feature",
  "properties": {
    "tgn:hierarchy":[
        "tgn:2067284",
        "tgn:1000001",
        "tgn:7012149",
        "tgn:2001449",
        "tgn:7007566",
        "tgn:7029392"
    ],
    "tgn:id":2067284,
    "tgn:name":"Ojo Sarco",
    "tgn:placetype":[
        "aat:300008347"
    ]
},
  "bbox": [],
  "geometry": {"coordinates":[-105.7667,36.1167],"type":"Point"}
}