{
  "id": 2038705,
  "type": "Feature",
  "properties": {
    "tgn:hierarchy":[
        "tgn:2038705",
        "tgn:1000001",
        "tgn:7012149",
        "tgn:2000797",
        "tgn:7007255",
        "tgn:7029392"
    ],
    "tgn:id":2038705,
    "tgn:name":"Rio Vista",
    "tgn:placetype":[
        "aat:300008347"
    ]
},
  "bbox": [],
  "geometry": {"coordinates":[-83.35,36.8333],"type":"Point"}
}