<<<<<<< HEAD
{
  "id": 2255228,
  "type": "Feature",
  "properties": {
    "tgn:hierarchy":[
        "tgn:2255228",
        "tgn:1000001",
        "tgn:7014423",
        "tgn:7012149",
        "tgn:7007517",
        "tgn:7029392"
    ],
    "tgn:id":2255228,
    "tgn:name":"Cooper Pond",
    "tgn:placetype":[
        "aat:300008680"
    ]
},
  "bbox": [],
  "geometry": {"coordinates":[-70.7833,41.9167],"type":"Point"}
}
=======
{"geometry":{"type":"Point","coordinates":[-70.783300,41.916700]},"type":"Feature","properties":{"hierarchy":["tgn:2255228","tgn:1000001","tgn:7014423","tgn:7012149","tgn:7007517","tgn:7029392"],"placetype":["aat:300008680"],"id":2255228,"name:xx":"Cooper Pond"}}
>>>>>>> 03f74aca74312dbeaf24d7e61306dd6a786dc3d0
