{
  "id": 2369227,
  "type": "Feature",
  "properties": {
    "tgn:hierarchy":[
        "tgn:2369227",
        "tgn:1000001",
        "tgn:7012149",
        "tgn:1002399",
        "tgn:7007710",
        "tgn:7029392"
    ],
    "tgn:id":2369227,
    "tgn:name":"Gum Spring",
    "tgn:placetype":[
        "aat:300008697"
    ]
},
  "bbox": [],
  "geometry": {"coordinates":[-77.9167,39.9833],"type":"Point"}
}