{
  "id": 1078001,
  "type": "Feature",
  "properties": {
    "tgn:hierarchy":[
        "tgn:1078001",
        "tgn:1001321",
        "tgn:1000004",
        "tgn:1000116",
        "tgn:7029392"
    ],
    "tgn:id":1078001,
    "tgn:name":"Leuwiliang",
    "tgn:placetype":[
        "aat:300008347"
    ]
},
  "bbox": [],
  "geometry": {"coordinates":[106.6167,-6.5667],"type":"Point"}
}