{
  "id": 7103619,
  "type": "Feature",
  "properties": {
    "tgn:hierarchy":[
        "tgn:7103619",
        "tgn:7003669",
        "tgn:1000003",
        "tgn:7000084",
        "tgn:7029392"
    ],
    "tgn:id":7103619,
    "tgn:name":"Rotenberg",
    "tgn:placetype":[
        "aat:300008777"
    ]
},
  "bbox": [],
  "geometry": {"coordinates":[11.016667,49.366667],"type":"Point"}
}