{
  "id": 1113734,
  "type": "Feature",
  "properties": {
    "tgn:hierarchy":[
        "tgn:1113734",
        "tgn:1000003",
        "tgn:1000070",
        "tgn:7002895",
        "tgn:7029392"
    ],
    "tgn:id":1113734,
    "tgn:name":"Saintes-Maries, Golfe des",
    "tgn:placetype":[
        "aat:300132316"
    ]
},
  "bbox": [],
  "geometry": {"coordinates":[4.5167,43.4167],"type":"Point"}
}