{
  "id": 7110028,
  "type": "Feature",
  "properties": {
    "tgn:hierarchy":[
        "tgn:7110028",
        "tgn:7000096",
        "tgn:1000003",
        "tgn:7000084",
        "tgn:7029392"
    ],
    "tgn:id":7110028,
    "tgn:name":"Reiherheide",
    "tgn:placetype":[
        "aat:300008863"
    ]
},
  "bbox": [],
  "geometry": {"coordinates":[12.716667,52.333333],"type":"Point"}
}