{
  "id": 2733833,
  "type": "Feature",
  "properties": {
    "tgn:hierarchy":[
        "tgn:2733833",
        "tgn:1000001",
        "tgn:7012149",
        "tgn:2002371",
        "tgn:7007923",
        "tgn:7029392"
    ],
    "tgn:id":2733833,
    "tgn:name":"Turner Fork",
    "tgn:placetype":[
        "aat:300008699"
    ]
},
  "bbox": [],
  "geometry": {"coordinates":[-109.85,43.9167],"type":"Point"}
}