{
  "id": 2006697,
  "type": "Feature",
  "properties": {
    "tgn:hierarchy":[
        "tgn:2006697",
        "tgn:1000001",
        "tgn:7006451",
        "tgn:2000094",
        "tgn:7012149",
        "tgn:7029392"
    ],
    "tgn:id":2006697,
    "tgn:name":"Cork",
    "tgn:placetype":[
        "aat:300008347",
        "aat:300387210"
    ]
},
  "bbox": [],
  "geometry": {"coordinates":[-109.9167,32.95],"type":"Point"}
}