{
  "id": 7373437,
  "type": "Feature",
  "properties": {
    "tgn:hierarchy":[
        "tgn:7373437",
        "tgn:1000001",
        "tgn:1001960",
        "tgn:7005560",
        "tgn:7029392"
    ],
    "tgn:id":7373437,
    "tgn:name":"Rancho La Agua Nueva",
    "tgn:placetype":[
        "aat:300000241"
    ]
},
  "bbox": [],
  "geometry": {"coordinates":[-109.033333,29.783333],"type":"Point"}
}