{
  "id": 7370202,
  "type": "Feature",
  "properties": {
    "tgn:hierarchy":[
        "tgn:7370202",
        "tgn:1000001",
        "tgn:7005599",
        "tgn:7005560",
        "tgn:7029392"
    ],
    "tgn:id":7370202,
    "tgn:name":"Jamapa",
    "tgn:placetype":[
        "aat:300008347"
    ]
},
  "bbox": [],
  "geometry": {"coordinates":[-96.233333,19.033333],"type":"Point"}
}