{
  "id": 2031059,
  "type": "Feature",
  "properties": {
    "tgn:hierarchy":[
        "tgn:2031059",
        "tgn:1000001",
        "tgn:7012149",
        "tgn:1002557",
        "tgn:7007252",
        "tgn:7029392"
    ],
    "tgn:id":2031059,
    "tgn:name":"Bell Rohr Park",
    "tgn:placetype":[
        "aat:300008347",
        "aat:300387247"
    ]
},
  "bbox": [],
  "geometry": {"coordinates":[-85.7667,41.3167],"type":"Point"}
}