{
  "id": 7453485,
  "type": "Feature",
  "properties": {
    "tgn:hierarchy":[
        "tgn:7453485",
        "tgn:7002445",
        "tgn:1000003",
        "tgn:7008118",
        "tgn:7008591",
        "tgn:7029392"
    ],
    "tgn:id":7453485,
    "tgn:name:en":"Church Gresley",
    "tgn:placetype":[
        "aat:300008347"
    ]
},
  "bbox": [],
  "geometry": {"coordinates":[-1.566667,52.75],"type":"Point"}
}