{
  "id": 7569308,
  "type": "Feature",
  "properties": {
    "tgn:hierarchy":[
        "tgn:7569308",
        "tgn:1000004",
        "tgn:7000198",
        "tgn:7016883",
        "tgn:7029392"
    ],
    "tgn:id":7569308,
    "tgn:name:en":"Bor\u0101s",
    "tgn:placetype":[
        "aat:300008347"
    ]
},
  "bbox": [],
  "geometry": {"coordinates":[76.531238,30.598299],"type":"Point"}
}