{
  "id": 2576984,
  "type": "Feature",
  "properties": {
    "tgn:hierarchy":[
        "tgn:2576984",
        "tgn:1000001",
        "tgn:7012149",
        "tgn:7007255",
        "tgn:7029392"
    ],
    "tgn:id":2576984,
    "tgn:name":"Peter Branch",
    "tgn:placetype":[
        "aat:300008699"
    ]
},
  "bbox": [],
  "geometry": {"coordinates":[-82.8167,38.2167],"type":"Point"}
}