{
  "id": 7313006,
  "type": "Feature",
  "properties": {
    "tgn:hierarchy":[
        "tgn:7313006",
        "tgn:1001708",
        "tgn:1000049",
        "tgn:1000002",
        "tgn:7029392"
    ],
    "tgn:id":7313006,
    "tgn:name":"Los Pirques, Cerro",
    "tgn:placetype":[
        "aat:300008777"
    ]
},
  "bbox": [],
  "geometry": {"coordinates":[-70.533333,-33.383333],"type":"Point"}
}