{
  "id": 2401076,
  "type": "Feature",
  "properties": {
    "tgn:hierarchy":[
        "tgn:2401076",
        "tgn:1000001",
        "tgn:7012149",
        "tgn:1002779",
        "tgn:7007710",
        "tgn:7029392"
    ],
    "tgn:id":2401076,
    "tgn:name":"Horse Valley",
    "tgn:placetype":[
        "aat:300008761"
    ]
},
  "bbox": [],
  "geometry": {"coordinates":[-77.65,40.2833],"type":"Point"}
}