{
  "id": 2296354,
  "type": "Feature",
  "properties": {
    "tgn:hierarchy":[
        "tgn:2296354",
        "tgn:1000001",
        "tgn:7012149",
        "tgn:2000821",
        "tgn:7007255",
        "tgn:7029392"
    ],
    "tgn:id":2296354,
    "tgn:name":"Dry Bread Fork",
    "tgn:placetype":[
        "aat:300008699"
    ]
},
  "bbox": [],
  "geometry": {"coordinates":[-82.95,37.7333],"type":"Point"}
}