{
  "id": 1076540,
  "type": "Feature",
  "properties": {
    "tgn:hierarchy":[
        "tgn:1076540",
        "tgn:1000004",
        "tgn:7000198",
        "tgn:1001977",
        "tgn:7029392"
    ],
    "tgn:id":1076540,
    "tgn:name:en":"Pandua",
    "tgn:placetype":[
        "aat:300008347"
    ]
},
  "bbox": [],
  "geometry": {"coordinates":[88.286374,23.074917],"type":"Point"}
}