{
  "id": 7224566,
  "type": "Feature",
  "properties": {
    "tgn:hierarchy":[
        "tgn:7224566",
        "tgn:4003773",
        "tgn:7001395",
        "tgn:1000003",
        "tgn:1000074",
        "tgn:7029392"
    ],
    "tgn:id":7224566,
    "tgn:name":"Neros\u00edrtis",
    "tgn:placetype":[
        "aat:300008347"
    ]
},
  "bbox": [],
  "geometry": {"coordinates":[21.666667,38.683333],"type":"Point"}
}