{
  "id": 7428571,
  "type": "Feature",
  "properties": {
    "tgn:hierarchy":[
        "tgn:7428571",
        "tgn:7005581",
        "tgn:1000001",
        "tgn:7005560",
        "tgn:7029392"
    ],
    "tgn:id":7428571,
    "tgn:name":"Tehuerichi",
    "tgn:placetype":[
        "aat:300008347"
    ]
},
  "bbox": [],
  "geometry": {"coordinates":[-107.216667,27.616667],"type":"Point"}
}