{
  "id": 2201773,
  "type": "Feature",
  "properties": {
    "tgn:hierarchy":[
        "tgn:2201773",
        "tgn:1000001",
        "tgn:7012149",
        "tgn:2001929",
        "tgn:7007825",
        "tgn:7029392"
    ],
    "tgn:id":2201773,
    "tgn:name":"Buck Creek Lake",
    "tgn:placetype":[
        "aat:300006191"
    ]
},
  "bbox": [],
  "geometry": {"coordinates":[-85.2667,35.9667],"type":"Point"}
}