<<<<<<< HEAD
{
  "id": 2158892,
  "type": "Feature",
  "properties": {
    "tgn:hierarchy":[
        "tgn:2158892",
        "tgn:1000001",
        "tgn:7012149",
        "tgn:2001952",
        "tgn:7007826",
        "tgn:7029392"
    ],
    "tgn:id":2158892,
    "tgn:name":"Beckham Reservoir",
    "tgn:placetype":[
        "aat:300006191"
    ]
},
  "bbox": [],
  "geometry": {"coordinates":[-97.6333,26.2167],"type":"Point"}
}
=======
{"geometry":{"type":"Point","coordinates":[-97.633300,26.216700]},"type":"Feature","properties":{"hierarchy":["tgn:2158892","tgn:1000001","tgn:7012149","tgn:2001952","tgn:7007826","tgn:7029392"],"placetype":["aat:300006191"],"id":2158892,"name:xx":"Beckham Reservoir"}}
>>>>>>> 03f74aca74312dbeaf24d7e61306dd6a786dc3d0
