{
  "id": 1096402,
  "type": "Feature",
  "properties": {
    "tgn:hierarchy":[
        "tgn:1096402",
        "tgn:7000490",
        "tgn:1000006",
        "tgn:7001828",
        "tgn:7029392"
    ],
    "tgn:id":1096402,
    "tgn:name":"Bulga",
    "tgn:placetype":[
        "aat:300008347"
    ]
},
  "bbox": [],
  "geometry": {"coordinates":[151.0167,-32.6667],"type":"Point"}
}