{
  "id": 7503108,
  "type": "Feature",
  "properties": {
    "tgn:hierarchy":[
        "tgn:7503108",
        "tgn:7001010",
        "tgn:1000004",
        "tgn:1000141",
        "tgn:7029392"
    ],
    "tgn:id":7503108,
    "tgn:name":"Wule Shan",
    "tgn:placetype":[
        "aat:300008795"
    ]
},
  "bbox": [],
  "geometry": {"coordinates":[121.091667,23.233889],"type":"Point"}
}