{
  "id": 7589954,
  "type": "Feature",
  "properties": {
    "tgn:hierarchy":[
        "tgn:7589954",
        "tgn:1000004",
        "tgn:7000198",
        "tgn:7016883",
        "tgn:7029392"
    ],
    "tgn:id":7589954,
    "tgn:name:en":"Taunsa",
    "tgn:placetype":[
        "aat:300008347"
    ]
},
  "bbox": [],
  "geometry": {"coordinates":[76.115865,30.630303],"type":"Point"}
}