{
  "id": 2523906,
  "type": "Feature",
  "properties": {
    "tgn:hierarchy":[
        "tgn:2523906",
        "tgn:1002366",
        "tgn:1000001",
        "tgn:7012149",
        "tgn:7007159",
        "tgn:7029392"
    ],
    "tgn:id":2523906,
    "tgn:name":"Morehouse Brook",
    "tgn:placetype":[
        "aat:300008699"
    ]
},
  "bbox": [],
  "geometry": {"coordinates":[-73.2667,41.25],"type":"Point"}
}