{
  "id": 2477476,
  "type": "Feature",
  "properties": {
    "tgn:hierarchy":[
        "tgn:2477476",
        "tgn:1000001",
        "tgn:7012149",
        "tgn:2001717",
        "tgn:7007708",
        "tgn:7029392"
    ],
    "tgn:id":2477476,
    "tgn:name":"Lyons Log Pond",
    "tgn:placetype":[
        "aat:300006191"
    ]
},
  "bbox": [],
  "geometry": {"coordinates":[-122.5833,44.7667],"type":"Point"}
}