{
  "id": 1088313,
  "type": "Feature",
  "properties": {
    "tgn:hierarchy":[
        "tgn:1088313",
        "tgn:1000965",
        "tgn:7001242",
        "tgn:1000155",
        "tgn:7029392"
    ],
    "tgn:id":1088313,
    "tgn:name":"Alindao",
    "tgn:placetype":[
        "aat:300008347"
    ]
},
  "bbox": [],
  "geometry": {"coordinates":[21.1833,5.0167],"type":"Point"}
}