{
  "id": 7026992,
  "type": "Feature",
  "properties": {
    "tgn:hierarchy":[
        "tgn:7026992",
        "tgn:7002445",
        "tgn:1000003",
        "tgn:7008143",
        "tgn:7008591",
        "tgn:7029392"
    ],
    "tgn:id":7026992,
    "tgn:name:en":"Adforton",
    "tgn:placetype":[
        "aat:300008347",
        "aat:300008372"
    ]
},
  "bbox": [],
  "geometry": {"coordinates":[-2.866667,52.333333],"type":"Point"}
}