{
  "id": 7431769,
  "type": "Feature",
  "properties": {
    "tgn:hierarchy":[
        "tgn:7431769",
        "tgn:7005586",
        "tgn:1000001",
        "tgn:7005560",
        "tgn:7029392"
    ],
    "tgn:id":7431769,
    "tgn:name":"Rinc\u00f3n de San Lorenzo",
    "tgn:placetype":[
        "aat:300008347"
    ]
},
  "bbox": [],
  "geometry": {"coordinates":[-102.833333,21.183333],"type":"Point"}
}