{
  "id": 2156383,
  "type": "Feature",
  "properties": {
    "tgn:hierarchy":[
        "tgn:2156383",
        "tgn:1000001",
        "tgn:7012149",
        "tgn:2001212",
        "tgn:7007523",
        "tgn:7029392"
    ],
    "tgn:id":2156383,
    "tgn:name":"Bears Grove",
    "tgn:placetype":[
        "aat:300132451"
    ]
},
  "bbox": [],
  "geometry": {"coordinates":[-93.7167,39.0333],"type":"Point"}
}