{
  "id": 2224391,
  "type": "Feature",
  "properties": {
    "tgn:hierarchy":[
        "tgn:2224391",
        "tgn:1000001",
        "tgn:7012149",
        "tgn:1003042",
        "tgn:7007920",
        "tgn:7029392"
    ],
    "tgn:id":2224391,
    "tgn:name":"Cascade Mill Pond",
    "tgn:placetype":[
        "aat:300006191"
    ]
},
  "bbox": [],
  "geometry": {"coordinates":[-120.4833,46.6167],"type":"Point"}
}