{
  "id": 2306128,
  "type": "Feature",
  "properties": {
    "tgn:hierarchy":[
        "tgn:2306128",
        "tgn:7002659",
        "tgn:1000001",
        "tgn:7012149",
        "tgn:7029392"
    ],
    "tgn:id":2306128,
    "tgn:name":"East Fork Beech Creek",
    "tgn:placetype":[
        "aat:300008706"
    ]
},
  "bbox": [],
  "geometry": {"coordinates":[-87.3167,34.3667],"type":"Point"}
}