{
  "id": 2405160,
  "type": "Feature",
  "properties": {
    "tgn:hierarchy":[
        "tgn:2405160",
        "tgn:1000001",
        "tgn:7012149",
        "tgn:7007158",
        "tgn:2000242",
        "tgn:7029392"
    ],
    "tgn:id":2405160,
    "tgn:name":"Huerfano Lake",
    "tgn:placetype":[
        "aat:300006191"
    ]
},
  "bbox": [],
  "geometry": {"coordinates":[-104.3833,38.1333],"type":"Point"}
}