<<<<<<< HEAD
{
  "id": 2405160,
  "type": "Feature",
  "properties": {
    "tgn:hierarchy":[
        "tgn:2405160",
        "tgn:1000001",
        "tgn:7012149",
        "tgn:7007158",
        "tgn:2000242",
        "tgn:7029392"
    ],
    "tgn:id":2405160,
    "tgn:name":"Huerfano Lake",
    "tgn:placetype":[
        "aat:300006191"
    ]
},
  "bbox": [],
  "geometry": {"coordinates":[-104.3833,38.1333],"type":"Point"}
}
=======
{"geometry":{"type":"Point","coordinates":[-104.383300,38.133300]},"type":"Feature","properties":{"hierarchy":["tgn:2405160","tgn:1000001","tgn:7012149","tgn:7007158","tgn:2000242","tgn:7029392"],"placetype":["aat:300006191"],"id":2405160,"name:xx":"Huerfano Lake"}}
>>>>>>> 03f74aca74312dbeaf24d7e61306dd6a786dc3d0
