{
  "id": 7099076,
  "type": "Feature",
  "properties": {
    "tgn:hierarchy":[
        "tgn:7099076",
        "tgn:7003692",
        "tgn:1000003",
        "tgn:7000084",
        "tgn:7029392"
    ],
    "tgn:id":7099076,
    "tgn:name":"Sondelfingen",
    "tgn:placetype":[
        "aat:300008347"
    ]
},
  "bbox": [],
  "geometry": {"coordinates":[9.233333,48.516667],"type":"Point"}
}