{
  "id": 7535891,
  "type": "Feature",
  "properties": {
    "tgn:hierarchy":[
        "tgn:7535891",
        "tgn:7001242",
        "tgn:7016833",
        "tgn:7001335",
        "tgn:7029392"
    ],
    "tgn:id":7535891,
    "tgn:name:en":"Quday'\u012b, W\u0101d\u012b al",
    "tgn:placetype":[
        "aat:300379998"
    ]
},
  "bbox": [],
  "geometry": {"coordinates":[33.60392,30.207823],"type":"Point"}
}