{
  "id": 2141795,
  "type": "Feature",
  "properties": {
    "tgn:hierarchy":[
        "tgn:2141795",
        "tgn:1000001",
        "tgn:7012149",
        "tgn:2000183",
        "tgn:7007157",
        "tgn:7029392"
    ],
    "tgn:id":2141795,
    "tgn:name":"Baboon Lakes",
    "tgn:placetype":[
        "aat:300008680"
    ]
},
  "bbox": [],
  "geometry": {"coordinates":[-118.6167,37.1667],"type":"Point"}
}