{
  "id": 2725472,
  "type": "Feature",
  "properties": {
    "tgn:hierarchy":[
        "tgn:2725472",
        "tgn:1000001",
        "tgn:7012149",
        "tgn:2002126",
        "tgn:7007827",
        "tgn:7029392"
    ],
    "tgn:id":2725472,
    "tgn:name":"Tooth Spring",
    "tgn:placetype":[
        "aat:300008697"
    ]
},
  "bbox": [],
  "geometry": {"coordinates":[-111.5667,40.45],"type":"Point"}
}