{
  "id": 2414182,
  "type": "Feature",
  "properties": {
    "tgn:hierarchy":[
        "tgn:2414182",
        "tgn:1000001",
        "tgn:7012149",
        "tgn:2000495",
        "tgn:7007250",
        "tgn:7029392"
    ],
    "tgn:id":2414182,
    "tgn:name":"Iron Mountain",
    "tgn:placetype":[
        "aat:300008798"
    ]
},
  "bbox": [],
  "geometry": {"coordinates":[-117.0167,44.55],"type":"Point"}
}