{
  "id": 2095274,
  "type": "Feature",
  "properties": {
    "tgn:hierarchy":[
        "tgn:2095274",
        "tgn:1000001",
        "tgn:2001734",
        "tgn:7012149",
        "tgn:7007712",
        "tgn:7029392"
    ],
    "tgn:id":2095274,
    "tgn:name":"Ashley Heights",
    "tgn:placetype":[
        "aat:300008347"
    ]
},
  "bbox": [],
  "geometry": {"coordinates":[-80.05,32.9167],"type":"Point"}
}