{
  "id": 2309257,
  "type": "Feature",
  "properties": {
    "tgn:hierarchy":[
        "tgn:2309257",
        "tgn:1000001",
        "tgn:7012149",
        "tgn:2001303",
        "tgn:7007524",
        "tgn:7029392"
    ],
    "tgn:id":2309257,
    "tgn:name":"East Spring Coulee",
    "tgn:placetype":[
        "aat:300008761"
    ]
},
  "bbox": [],
  "geometry": {"coordinates":[-106.8167,46.35],"type":"Point"}
}