{
  "id": 7351925,
  "type": "Feature",
  "properties": {
    "tgn:hierarchy":[
        "tgn:7351925",
        "tgn:1000001",
        "tgn:7005591",
        "tgn:7005560",
        "tgn:7029392"
    ],
    "tgn:id":7351925,
    "tgn:name":"Arroyo Perro",
    "tgn:placetype":[
        "aat:300008347"
    ]
},
  "bbox": [],
  "geometry": {"coordinates":[-95.083333,16.933333],"type":"Point"}
}