<<<<<<< HEAD
{
  "id": 2155911,
  "type": "Feature",
  "properties": {
    "tgn:hierarchy":[
        "tgn:2155911",
        "tgn:1000001",
        "tgn:7012149",
        "tgn:1002387",
        "tgn:7007710",
        "tgn:7029392"
    ],
    "tgn:id":2155911,
    "tgn:name":"Bear Valley",
    "tgn:placetype":[
        "aat:300008761"
    ]
},
  "bbox": [],
  "geometry": {"coordinates":[-77.7667,40.0333],"type":"Point"}
}
=======
{"geometry":{"type":"Point","coordinates":[-77.766700,40.033300]},"type":"Feature","properties":{"hierarchy":["tgn:2155911","tgn:1000001","tgn:7012149","tgn:1002387","tgn:7007710","tgn:7029392"],"placetype":["aat:300008761"],"id":2155911,"name:xx":"Bear Valley"}}
>>>>>>> 03f74aca74312dbeaf24d7e61306dd6a786dc3d0
