{
  "id": 2169207,
  "type": "Feature",
  "properties": {
    "tgn:hierarchy":[
        "tgn:2169207",
        "tgn:1000001",
        "tgn:7006451",
        "tgn:2000092",
        "tgn:7012149",
        "tgn:7029392"
    ],
    "tgn:id":2169207,
    "tgn:name":"Big Knoll, The",
    "tgn:placetype":[
        "aat:300008798"
    ]
},
  "bbox": [],
  "geometry": {"coordinates":[-111.85,36.8333],"type":"Point"}
}