{
  "id": 2314094,
  "type": "Feature",
  "properties": {
    "tgn:hierarchy":[
        "tgn:2314094",
        "tgn:1000001",
        "tgn:7012149",
        "tgn:2002379",
        "tgn:7007923",
        "tgn:7029392"
    ],
    "tgn:id":2314094,
    "tgn:name":"Elk Basin",
    "tgn:placetype":[
        "aat:300008347"
    ]
},
  "bbox": [],
  "geometry": {"coordinates":[-108.85,44.9833],"type":"Point"}
}