{
  "id": 2414682,
  "type": "Feature",
  "properties": {
    "tgn:hierarchy":[
        "tgn:2414682",
        "tgn:1000001",
        "tgn:7012149",
        "tgn:2002249",
        "tgn:7007920",
        "tgn:7029392"
    ],
    "tgn:id":2414682,
    "tgn:name":"Irwin",
    "tgn:placetype":[
        "aat:300008347"
    ]
},
  "bbox": [],
  "geometry": {"coordinates":[-117.2333,47.6833],"type":"Point"}
}