{
  "id": 7286258,
  "type": "Feature",
  "properties": {
    "tgn:hierarchy":[
        "tgn:7286258",
        "tgn:1001623",
        "tgn:1000049",
        "tgn:1000002",
        "tgn:7029392"
    ],
    "tgn:id":7286258,
    "tgn:name":"Seno Hoppner",
    "tgn:placetype":[
        "aat:300006495"
    ]
},
  "bbox": [],
  "geometry": {"coordinates":[-75.466667,-46.683333],"type":"Point"}
}