{
  "id": 1018316,
  "type": "Feature",
  "properties": {
    "tgn:hierarchy":[
        "tgn:1018316",
        "tgn:1000001",
        "tgn:7005593",
        "tgn:7005560",
        "tgn:7029392"
    ],
    "tgn:id":1018316,
    "tgn:name":"Santa Rosa J\u00e1uregui",
    "tgn:placetype":[
        "aat:300008347"
    ]
},
  "bbox": [],
  "geometry": {"coordinates":[-100.45,20.733333],"type":"Point"}
}