{
  "id": 7297865,
  "type": "Feature",
  "properties": {
    "tgn:hierarchy":[
        "tgn:7297865",
        "tgn:7002825",
        "tgn:7016622",
        "tgn:1000003",
        "tgn:1000095",
        "tgn:7029392"
    ],
    "tgn:id":7297865,
    "tgn:name":"Sombrero, Punta",
    "tgn:placetype":[
        "aat:300386846"
    ]
},
  "bbox": [],
  "geometry": {"coordinates":[-15.533333,28.15],"type":"Point"}
}