{
  "id": 2162478,
  "type": "Feature",
  "properties": {
    "tgn:hierarchy":[
        "tgn:2162478",
        "tgn:1000001",
        "tgn:7012149",
        "tgn:7007157",
        "tgn:1002869",
        "tgn:7029392"
    ],
    "tgn:id":2162478,
    "tgn:name":"Ben Lomond Mountain",
    "tgn:placetype":[
        "aat:300008798"
    ]
},
  "bbox": [],
  "geometry": {"coordinates":[-122.1667,37.1167],"type":"Point"}
}