{
  "id": 1028956,
  "type": "Feature",
  "properties": {
    "tgn:hierarchy":[
        "tgn:1028956",
        "tgn:7002445",
        "tgn:1000003",
        "tgn:7008168",
        "tgn:7008591",
        "tgn:7029392"
    ],
    "tgn:id":1028956,
    "tgn:name:en":"Cowley",
    "tgn:placetype":[
        "aat:300008347",
        "aat:300008372"
    ]
},
  "bbox": [],
  "geometry": {"coordinates":[-1.216667,51.716667],"type":"Point"}
}