{
  "id": 2614597,
  "type": "Feature",
  "properties": {
    "tgn:hierarchy":[
        "tgn:2614597",
        "tgn:1000001",
        "tgn:7012149",
        "tgn:7007157",
        "tgn:1002566",
        "tgn:7029392"
    ],
    "tgn:id":2614597,
    "tgn:name":"Reister Knoll",
    "tgn:placetype":[
        "aat:300008798"
    ]
},
  "bbox": [],
  "geometry": {"coordinates":[-122.6167,39.1167],"type":"Point"}
}