{
  "id": 7512770,
  "type": "Feature",
  "properties": {
    "tgn:hierarchy":[
        "tgn:7512770",
        "tgn:1009227",
        "tgn:1000226",
        "tgn:1000006",
        "tgn:7016850",
        "tgn:7029392"
    ],
    "tgn:id":7512770,
    "tgn:name:en":"Heretaniwha Point",
    "tgn:placetype":[
        "aat:300386846"
    ]
},
  "bbox": [],
  "geometry": {"coordinates":[169.55,-43.583333],"type":"Point"}
}