{
  "id": 2484826,
  "type": "Feature",
  "properties": {
    "tgn:hierarchy":[
        "tgn:2484826",
        "tgn:1000001",
        "tgn:7012149",
        "tgn:2000333",
        "tgn:7007248",
        "tgn:7029392"
    ],
    "tgn:id":2484826,
    "tgn:name":"Laurel, Lake",
    "tgn:placetype":[
        "aat:300006191"
    ]
},
  "bbox": [],
  "geometry": {"coordinates":[-84.2333,34.5167],"type":"Point"}
}