{
  "id": 2392733,
  "type": "Feature",
  "properties": {
    "tgn:hierarchy":[
        "tgn:2392733",
        "tgn:1000001",
        "tgn:2000920",
        "tgn:7012149",
        "tgn:7007515",
        "tgn:7029392"
    ],
    "tgn:id":2392733,
    "tgn:name":"Hobbs Brook",
    "tgn:placetype":[
        "aat:300008699"
    ]
},
  "bbox": [],
  "geometry": {"coordinates":[-70.2833,43.7833],"type":"Point"}
}