{
  "id": 1128121,
  "type": "Feature",
  "properties": {
    "tgn:hierarchy":[
        "tgn:1128121",
        "tgn:7001242",
        "tgn:7017582",
        "tgn:1000193",
        "tgn:7029392"
    ],
    "tgn:id":1128121,
    "tgn:name":"Oorlogskloof",
    "tgn:placetype":[
        "aat:300008707"
    ]
},
  "bbox": [],
  "geometry": {"coordinates":[19.14,-31.424],"type":"Point"}
}