{
  "id": 2484005,
  "type": "Feature",
  "properties": {
    "tgn:hierarchy":[
        "tgn:2484005",
        "tgn:1000001",
        "tgn:7012149",
        "tgn:2001456",
        "tgn:7007566",
        "tgn:7029392"
    ],
    "tgn:id":2484005,
    "tgn:name":"Latta Tanks",
    "tgn:placetype":[
        "aat:300006191"
    ]
},
  "bbox": [],
  "geometry": {"coordinates":[-107.65,34.5333],"type":"Point"}
}