{
  "id": 2120786,
  "type": "Feature",
  "properties": {
    "tgn:hierarchy":[
        "tgn:2120786",
        "tgn:1000001",
        "tgn:7012149",
        "tgn:1002982",
        "tgn:7007922",
        "tgn:7029392"
    ],
    "tgn:id":2120786,
    "tgn:name":"Bowers",
    "tgn:placetype":[
        "aat:300008347"
    ]
},
  "bbox": [],
  "geometry": {"coordinates":[-88.4333,42.6833],"type":"Point"}
}