{
  "id": 2601969,
  "type": "Feature",
  "properties": {
    "tgn:hierarchy":[
        "tgn:2601969",
        "tgn:1002648",
        "tgn:1000001",
        "tgn:7019158",
        "tgn:7012149",
        "tgn:7007249",
        "tgn:7029392"
    ],
    "tgn:id":2601969,
    "tgn:name":"Puu Laina",
    "tgn:placetype":[
        "aat:300008798"
    ]
},
  "bbox": [],
  "geometry": {"coordinates":[-156.6667,20.8833],"type":"Point"}
}