<<<<<<< HEAD
{
  "id": 7357176,
  "type": "Feature",
  "properties": {
    "tgn:hierarchy":[
        "tgn:7357176",
        "tgn:1000001",
        "tgn:7005591",
        "tgn:7005560",
        "tgn:7029392"
    ],
    "tgn:id":7357176,
    "tgn:name":"Chivo, Punta",
    "tgn:placetype":[
        "aat:300386846"
    ]
},
  "bbox": [],
  "geometry": {"coordinates":[-95.283333,16.1],"type":"Point"}
}
=======
{"geometry":{"type":"Point","coordinates":[-95.283333,16.100000]},"type":"Feature","properties":{"hierarchy":["tgn:7357176","tgn:1000001","tgn:7005591","tgn:7005560","tgn:7029392"],"placetype":["aat:300386846"],"id":7357176,"name:xx":"Chivo, Punta"}}
>>>>>>> 03f74aca74312dbeaf24d7e61306dd6a786dc3d0
