{
  "id": 7361385,
  "type": "Feature",
  "properties": {
    "tgn:hierarchy":[
        "tgn:7361385",
        "tgn:1000001",
        "tgn:7005593",
        "tgn:7005560",
        "tgn:7029392"
    ],
    "tgn:id":7361385,
    "tgn:name":"El Jacal",
    "tgn:placetype":[
        "aat:300008347"
    ]
},
  "bbox": [],
  "geometry": {"coordinates":[-100.416667,20.566667],"type":"Point"}
}