{
  "id": 7402296,
  "type": "Feature",
  "properties": {
    "tgn:hierarchy":[
        "tgn:7402296",
        "tgn:1000001",
        "tgn:7005599",
        "tgn:7005560",
        "tgn:7029392"
    ],
    "tgn:id":7402296,
    "tgn:name":"Pueblo Viejo",
    "tgn:placetype":[
        "aat:300008347"
    ]
},
  "bbox": [],
  "geometry": {"coordinates":[-97.055556,19.541667],"type":"Point"}
}