{
  "id": 7074673,
  "type": "Feature",
  "properties": {
    "tgn:hierarchy":[
        "tgn:7074673",
        "tgn:7003669",
        "tgn:1000003",
        "tgn:7000084",
        "tgn:7029392"
    ],
    "tgn:id":7074673,
    "tgn:name":"Serlbach",
    "tgn:placetype":[
        "aat:300008347"
    ]
},
  "bbox": [],
  "geometry": {"coordinates":[11.083333,49.733333],"type":"Point"}
}