{
  "id": 2548659,
  "type": "Feature",
  "properties": {
    "tgn:hierarchy":[
        "tgn:2548659",
        "tgn:1000001",
        "tgn:7012149",
        "tgn:2002123",
        "tgn:7007827",
        "tgn:7029392"
    ],
    "tgn:id":2548659,
    "tgn:name":"North Oak Brush Creek",
    "tgn:placetype":[
        "aat:300008706"
    ]
},
  "bbox": [],
  "geometry": {"coordinates":[-112.5167,39.9667],"type":"Point"}
}