{
  "id": 2700521,
  "type": "Feature",
  "properties": {
    "tgn:hierarchy":[
        "tgn:2700521",
        "tgn:1000001",
        "tgn:7012149",
        "tgn:2001718",
        "tgn:7007708",
        "tgn:7029392"
    ],
    "tgn:id":2700521,
    "tgn:name":"Sucker",
    "tgn:placetype":[
        "aat:300008347"
    ]
},
  "bbox": [],
  "geometry": {"coordinates":[-117.0167,43.5833],"type":"Point"}
}