{
  "id": 7402520,
  "type": "Feature",
  "properties": {
    "tgn:hierarchy":[
        "tgn:7402520",
        "tgn:1000001",
        "tgn:1001937",
        "tgn:7005560",
        "tgn:7029392"
    ],
    "tgn:id":7402520,
    "tgn:name":"Santa Luc\u00eda",
    "tgn:placetype":[
        "aat:300008347"
    ]
},
  "bbox": [],
  "geometry": {"coordinates":[-88.641667,19.383333],"type":"Point"}
}