{
  "id": 2652963,
  "type": "Feature",
  "properties": {
    "tgn:hierarchy":[
        "tgn:2652963",
        "tgn:1000001",
        "tgn:1002276",
        "tgn:7012149",
        "tgn:7007708",
        "tgn:7029392"
    ],
    "tgn:id":2652963,
    "tgn:name":"Settler Point",
    "tgn:placetype":[
        "aat:300008850"
    ]
},
  "bbox": [],
  "geometry": {"coordinates":[-123.6667,46.1667],"type":"Point"}
}