{
  "id": 7394131,
  "type": "Feature",
  "properties": {
    "tgn:hierarchy":[
        "tgn:7394131",
        "tgn:1000001",
        "tgn:7005599",
        "tgn:7005560",
        "tgn:7029392"
    ],
    "tgn:id":7394131,
    "tgn:name":"San Juli\u00e1n",
    "tgn:placetype":[
        "aat:300008347"
    ]
},
  "bbox": [],
  "geometry": {"coordinates":[-96.25,19.25],"type":"Point"}
}