{
  "id": 2318139,
  "type": "Feature",
  "properties": {
    "tgn:hierarchy":[
        "tgn:2318139",
        "tgn:1000001",
        "tgn:7012149",
        "tgn:2001761",
        "tgn:7007712",
        "tgn:7029392"
    ],
    "tgn:id":2318139,
    "tgn:name":"Ensenaka",
    "tgn:placetype":[
        "aat:300008347"
    ]
},
  "bbox": [],
  "geometry": {"coordinates":[-82.85,34.6667],"type":"Point"}
}