{
  "id": 7239491,
  "type": "Feature",
  "properties": {
    "tgn:hierarchy":[
        "tgn:7239491",
        "tgn:7003456",
        "tgn:1000003",
        "tgn:1000063",
        "tgn:7018236",
        "tgn:7029392"
    ],
    "tgn:id":7239491,
    "tgn:name":"Heibraek",
    "tgn:placetype":[
        "aat:300008347"
    ]
},
  "bbox": [],
  "geometry": {"coordinates":[5.033333,51.416667],"type":"Point"}
}