{
  "id": 2194722,
  "type": "Feature",
  "properties": {
    "tgn:hierarchy":[
        "tgn:2194722",
        "tgn:2001468",
        "tgn:1000001",
        "tgn:7012149",
        "tgn:7007709",
        "tgn:7029392"
    ],
    "tgn:id":2194722,
    "tgn:name":"Brier Knob",
    "tgn:placetype":[
        "aat:300008798"
    ]
},
  "bbox": [],
  "geometry": {"coordinates":[-81.8667,36.0667],"type":"Point"}
}