{
  "id": 7404266,
  "type": "Feature",
  "properties": {
    "tgn:hierarchy":[
        "tgn:7404266",
        "tgn:7005578",
        "tgn:1000001",
        "tgn:7005560",
        "tgn:7029392"
    ],
    "tgn:id":7404266,
    "tgn:name":"Independencia",
    "tgn:placetype":[
        "aat:300008347"
    ]
},
  "bbox": [],
  "geometry": {"coordinates":[-90.975,18.683333],"type":"Point"}
}