{
  "id": 2611212,
  "type": "Feature",
  "properties": {
    "tgn:hierarchy":[
        "tgn:2611212",
        "tgn:1000001",
        "tgn:7012149",
        "tgn:2000476",
        "tgn:7007250",
        "tgn:7029392"
    ],
    "tgn:id":2611212,
    "tgn:name":"Red Horse Ridge",
    "tgn:placetype":[
        "aat:300266640"
    ]
},
  "bbox": [],
  "geometry": {"coordinates":[-115.3833,45.8167],"type":"Point"}
}