{
  "id": 7478356,
  "type": "Feature",
  "properties": {
    "tgn:hierarchy":[
        "tgn:7478356",
        "tgn:1000004",
        "tgn:7467799",
        "tgn:1000141",
        "tgn:7029392"
    ],
    "tgn:id":7478356,
    "tgn:name":"Rongxing",
    "tgn:placetype":[
        "aat:300008347"
    ]
},
  "bbox": [],
  "geometry": {"coordinates":[120.612,23.7759],"type":"Point"}
}