{
  "id": 2780127,
  "type": "Feature",
  "properties": {
    "tgn:hierarchy":[
        "tgn:2780127",
        "tgn:1000001",
        "tgn:7012149",
        "tgn:2002194",
        "tgn:7007919",
        "tgn:7029392"
    ],
    "tgn:id":2780127,
    "tgn:name":"Wolfrun",
    "tgn:placetype":[
        "aat:300008347"
    ]
},
  "bbox": [],
  "geometry": {"coordinates":[-82.2333,36.6833],"type":"Point"}
}