{
  "id": 2297336,
  "type": "Feature",
  "properties": {
    "tgn:hierarchy":[
        "tgn:2297336",
        "tgn:7002659",
        "tgn:1000001",
        "tgn:2000003",
        "tgn:7012149",
        "tgn:7029392"
    ],
    "tgn:id":2297336,
    "tgn:name":"Dry Ford Branch",
    "tgn:placetype":[
        "aat:300008699"
    ]
},
  "bbox": [],
  "geometry": {"coordinates":[-87.1167,33.1833],"type":"Point"}
}