{
  "id": 7579974,
  "type": "Feature",
  "properties": {
    "tgn:hierarchy":[
        "tgn:7579974",
        "tgn:1000004",
        "tgn:7000198",
        "tgn:1001894",
        "tgn:7029392"
    ],
    "tgn:id":7579974,
    "tgn:name:en":"Teonda",
    "tgn:placetype":[
        "aat:300008347"
    ]
},
  "bbox": [],
  "geometry": {"coordinates":[78.195774,23.805256],"type":"Point"}
}