{
  "id": 2735365,
  "type": "Feature",
  "properties": {
    "tgn:hierarchy":[
        "tgn:2735365",
        "tgn:1000001",
        "tgn:7012149",
        "tgn:2000225",
        "tgn:7007158",
        "tgn:7029392"
    ],
    "tgn:id":2735365,
    "tgn:name":"Twin Buttes",
    "tgn:placetype":[
        "aat:300008798"
    ]
},
  "bbox": [],
  "geometry": {"coordinates":[-107.9167,37.2667],"type":"Point"}
}