{
  "id": 7415447,
  "type": "Feature",
  "properties": {
    "tgn:hierarchy":[
        "tgn:7415447",
        "tgn:7005584",
        "tgn:1000001",
        "tgn:7005560",
        "tgn:7029392"
    ],
    "tgn:id":7415447,
    "tgn:name":"Ca\u00f1aditas",
    "tgn:placetype":[
        "aat:300008347"
    ]
},
  "bbox": [],
  "geometry": {"coordinates":[-101.265,21.523333],"type":"Point"}
}