<<<<<<< HEAD
{
  "id": 7481523,
  "type": "Feature",
  "properties": {
    "tgn:hierarchy":[
        "tgn:7481523",
        "tgn:1000004",
        "tgn:7489179",
        "tgn:1000141",
        "tgn:7029392"
    ],
    "tgn:id":7481523,
    "tgn:name":"Shuangzi Shan",
    "tgn:placetype":[
        "aat:300008798"
    ]
},
  "bbox": [],
  "geometry": {"coordinates":[121.698167,24.444427],"type":"Point"}
}
=======
{"geometry":{"type":"Point","coordinates":[121.698167,24.444427]},"type":"Feature","properties":{"hierarchy":["tgn:7481523","tgn:1000004","tgn:7489179","tgn:1000141","tgn:7029392"],"placetype":["aat:300008798"],"id":7481523,"name:xx":"Shuangzi Shan"}}
>>>>>>> 03f74aca74312dbeaf24d7e61306dd6a786dc3d0
