{
  "id": 7481523,
  "type": "Feature",
  "properties": {
    "tgn:hierarchy":[
        "tgn:7481523",
        "tgn:1000004",
        "tgn:7489179",
        "tgn:1000141",
        "tgn:7029392"
    ],
    "tgn:id":7481523,
    "tgn:name":"Shuangzi Shan",
    "tgn:placetype":[
        "aat:300008798"
    ]
},
  "bbox": [],
  "geometry": {"coordinates":[121.698167,24.444427],"type":"Point"}
}