<<<<<<< HEAD
{
  "id": 7352248,
  "type": "Feature",
  "properties": {
    "tgn:hierarchy":[
        "tgn:7352248",
        "tgn:1000001",
        "tgn:1001906",
        "tgn:7005560",
        "tgn:7029392"
    ],
    "tgn:id":7352248,
    "tgn:name":"Barreteros",
    "tgn:placetype":[
        "aat:300008347"
    ]
},
  "bbox": [],
  "geometry": {"coordinates":[-105.133333,22.1],"type":"Point"}
}
=======
{"geometry":{"type":"Point","coordinates":[-105.133333,22.100000]},"type":"Feature","properties":{"hierarchy":["tgn:7352248","tgn:1000001","tgn:1001906","tgn:7005560","tgn:7029392"],"placetype":["aat:300008347"],"id":7352248,"name:xx":"Barreteros"}}
>>>>>>> 03f74aca74312dbeaf24d7e61306dd6a786dc3d0
