<<<<<<< HEAD
{
  "id": 2331211,
  "type": "Feature",
  "properties": {
    "tgn:hierarchy":[
        "tgn:2331211",
        "tgn:1000001",
        "tgn:2001424",
        "tgn:7012149",
        "tgn:7007564",
        "tgn:7029392"
    ],
    "tgn:id":2331211,
    "tgn:name":"Flat Top Mountain",
    "tgn:placetype":[
        "aat:300008798"
    ]
},
  "bbox": [],
  "geometry": {"coordinates":[-71.6,44.2],"type":"Point"}
}
=======
{"geometry":{"type":"Point","coordinates":[-71.600000,44.200000]},"type":"Feature","properties":{"hierarchy":["tgn:2331211","tgn:1000001","tgn:2001424","tgn:7012149","tgn:7007564","tgn:7029392"],"placetype":["aat:300008798"],"id":2331211,"name:xx":"Flat Top Mountain"}}
>>>>>>> 03f74aca74312dbeaf24d7e61306dd6a786dc3d0
