{
  "id": 7290275,
  "type": "Feature",
  "properties": {
    "tgn:hierarchy":[
        "tgn:7290275",
        "tgn:1001702",
        "tgn:1000049",
        "tgn:1000002",
        "tgn:7029392"
    ],
    "tgn:id":7290275,
    "tgn:name":"Don Pedro, Punta",
    "tgn:placetype":[
        "aat:300386846"
    ]
},
  "bbox": [],
  "geometry": {"coordinates":[-74.083333,-51.45],"type":"Point"}
}