{
  "id": 2709597,
  "type": "Feature",
  "properties": {
    "tgn:hierarchy":[
        "tgn:2709597",
        "tgn:1000001",
        "tgn:7012149",
        "tgn:2001461",
        "tgn:7007568",
        "tgn:7029392"
    ],
    "tgn:id":2709597,
    "tgn:name":"Tadds Bay",
    "tgn:placetype":[
        "aat:300132316"
    ]
},
  "bbox": [],
  "geometry": {"coordinates":[-74.0833,44.3167],"type":"Point"}
}