{
  "id": 1137651,
  "type": "Feature",
  "properties": {
    "tgn:hierarchy":[
        "tgn:1137651",
        "tgn:7012076",
        "tgn:1000003",
        "tgn:7006660",
        "tgn:7029392"
    ],
    "tgn:id":1137651,
    "tgn:name":"Kirovo",
    "tgn:placetype":[
        "aat:300008347",
        "aat:300008375"
    ]
},
  "bbox": [],
  "geometry": {"coordinates":[37.9167,48.3833],"type":"Point"}
}