<<<<<<< HEAD
{
  "id": 2765712,
  "type": "Feature",
  "properties": {
    "tgn:hierarchy":[
        "tgn:2765712",
        "tgn:1000001",
        "tgn:7012149",
        "tgn:2001713",
        "tgn:7007708",
        "tgn:7029392"
    ],
    "tgn:id":2765712,
    "tgn:name":"White Creek",
    "tgn:placetype":[
        "aat:300008706"
    ]
},
  "bbox": [],
  "geometry": {"coordinates":[-123.4667,42.2167],"type":"Point"}
}
=======
{"geometry":{"type":"Point","coordinates":[-123.466700,42.216700]},"type":"Feature","properties":{"hierarchy":["tgn:2765712","tgn:1000001","tgn:7012149","tgn:2001713","tgn:7007708","tgn:7029392"],"placetype":["aat:300008706"],"id":2765712,"name:xx":"White Creek"}}
>>>>>>> 03f74aca74312dbeaf24d7e61306dd6a786dc3d0
