{
  "id": 2756125,
  "type": "Feature",
  "properties": {
    "tgn:hierarchy":[
        "tgn:2756125",
        "tgn:1000001",
        "tgn:7012149",
        "tgn:2001036",
        "tgn:7007521",
        "tgn:7029392"
    ],
    "tgn:id":2756125,
    "tgn:name":"Weiss Creek",
    "tgn:placetype":[
        "aat:300008706"
    ]
},
  "bbox": [],
  "geometry": {"coordinates":[-91.4167,47.6167],"type":"Point"}
}