{
  "id": 7586708,
  "type": "Feature",
  "properties": {
    "tgn:hierarchy":[
        "tgn:7586708",
        "tgn:1000004",
        "tgn:7000198",
        "tgn:7000799",
        "tgn:7029392"
    ],
    "tgn:id":7586708,
    "tgn:name:en":"S\u0101lnai",
    "tgn:placetype":[
        "aat:300387200"
    ]
},
  "bbox": [],
  "geometry": {"coordinates":[74.875,34.479167],"type":"Point"}
}