<<<<<<< HEAD
{
  "id": 7246759,
  "type": "Feature",
  "properties": {
    "tgn:hierarchy":[
        "tgn:7246759",
        "tgn:7007877",
        "tgn:1000003",
        "tgn:1000063",
        "tgn:4012014",
        "tgn:7029392"
    ],
    "tgn:id":7246759,
    "tgn:name":"Camus, Bois du",
    "tgn:placetype":[
        "aat:300008863"
    ]
},
  "bbox": [],
  "geometry": {"coordinates":[4.416667,50.3],"type":"Point"}
}
=======
{"geometry":{"type":"Point","coordinates":[4.416667,50.300000]},"type":"Feature","properties":{"hierarchy":["tgn:7246759","tgn:7007877","tgn:1000003","tgn:1000063","tgn:4012014","tgn:7029392"],"placetype":["aat:300008863"],"id":7246759,"name:xx":"Camus, Bois du"}}
>>>>>>> 03f74aca74312dbeaf24d7e61306dd6a786dc3d0
