{
  "id": 7165926,
  "type": "Feature",
  "properties": {
    "tgn:hierarchy":[
        "tgn:7165926",
        "tgn:7003692",
        "tgn:1000003",
        "tgn:7000084",
        "tgn:7029392"
    ],
    "tgn:id":7165926,
    "tgn:name":"Heidenbuckel",
    "tgn:placetype":[
        "aat:300008777"
    ]
},
  "bbox": [],
  "geometry": {"coordinates":[9.583333,49.033333],"type":"Point"}
}