{
  "id": 2771490,
  "type": "Feature",
  "properties": {
    "tgn:hierarchy":[
        "tgn:2771490",
        "tgn:1000001",
        "tgn:7012149",
        "tgn:2001454",
        "tgn:7007566",
        "tgn:7029392"
    ],
    "tgn:id":2771490,
    "tgn:name":"Wildhorse Mesa",
    "tgn:placetype":[
        "aat:300008798"
    ]
},
  "bbox": [],
  "geometry": {"coordinates":[-105.7667,35.3167],"type":"Point"}
}