{
  "id": 2531102,
  "type": "Feature",
  "properties": {
    "tgn:hierarchy":[
        "tgn:2531102",
        "tgn:1000001",
        "tgn:7012149",
        "tgn:2002353",
        "tgn:7007922",
        "tgn:7029392"
    ],
    "tgn:id":2531102,
    "tgn:name":"Mukwonago Lake",
    "tgn:placetype":[
        "aat:300008680"
    ]
},
  "bbox": [],
  "geometry": {"coordinates":[-91.1333,46.05],"type":"Point"}
}