{
  "id": 2480451,
  "type": "Feature",
  "properties": {
    "tgn:hierarchy":[
        "tgn:2480451",
        "tgn:1000001",
        "tgn:7012149",
        "tgn:1002381",
        "tgn:7007252",
        "tgn:7029392"
    ],
    "tgn:id":2480451,
    "tgn:name":"Lake View",
    "tgn:placetype":[
        "aat:300008347"
    ]
},
  "bbox": [],
  "geometry": {"coordinates":[-85.2333,39.4833],"type":"Point"}
}