{
  "id": 2192068,
  "type": "Feature",
  "properties": {
    "tgn:hierarchy":[
        "tgn:2192068",
        "tgn:1000001",
        "tgn:7012149",
        "tgn:2001103",
        "tgn:7007522",
        "tgn:7029392"
    ],
    "tgn:id":2192068,
    "tgn:name":"Braiden Creek",
    "tgn:placetype":[
        "aat:300008706"
    ]
},
  "bbox": [],
  "geometry": {"coordinates":[-89.25,31.1833],"type":"Point"}
}