{
  "id": 7559395,
  "type": "Feature",
  "properties": {
    "tgn:hierarchy":[
        "tgn:7559395",
        "tgn:1000004",
        "tgn:7000198",
        "tgn:1001895",
        "tgn:7029392"
    ],
    "tgn:id":7559395,
    "tgn:name:en":"Pendra",
    "tgn:placetype":[
        "aat:300008347"
    ]
},
  "bbox": [],
  "geometry": {"coordinates":[74.151387,21.946826],"type":"Point"}
}