{
  "id": 2301000,
  "type": "Feature",
  "properties": {
    "tgn:hierarchy":[
        "tgn:2301000",
        "tgn:1000001",
        "tgn:2001413",
        "tgn:7012149",
        "tgn:7007526",
        "tgn:7029392"
    ],
    "tgn:id":2301000,
    "tgn:name":"Dunderberg Mine",
    "tgn:placetype":[
        "aat:300000390"
    ]
},
  "bbox": [],
  "geometry": {"coordinates":[-115.9667,39.4667],"type":"Point"}
}