<<<<<<< HEAD
{
  "id": 7356503,
  "type": "Feature",
  "properties": {
    "tgn:hierarchy":[
        "tgn:7356503",
        "tgn:1001853",
        "tgn:1000001",
        "tgn:7005560",
        "tgn:7029392"
    ],
    "tgn:id":7356503,
    "tgn:name":"Chiltipiqu\u00edn, Ca\u00f1\u00f3n del",
    "tgn:placetype":[
        "aat:300008763"
    ]
},
  "bbox": [],
  "geometry": {"coordinates":[-101.5,26.45],"type":"Point"}
}
=======
{"geometry":{"type":"Point","coordinates":[-101.500000,26.450000]},"type":"Feature","properties":{"hierarchy":["tgn:7356503","tgn:1001853","tgn:1000001","tgn:7005560","tgn:7029392"],"placetype":["aat:300008763"],"id":7356503,"name:xx":"Chiltipiqu\u00edn, Ca\u00f1\u00f3n del"}}
>>>>>>> 03f74aca74312dbeaf24d7e61306dd6a786dc3d0
