{
  "id": 2024496,
  "type": "Feature",
  "properties": {
    "tgn:hierarchy":[
        "tgn:2024496",
        "tgn:1000001",
        "tgn:7012149",
        "tgn:2000354",
        "tgn:7007248",
        "tgn:7029392"
    ],
    "tgn:id":2024496,
    "tgn:name":"Thalmann",
    "tgn:placetype":[
        "aat:300008347"
    ]
},
  "bbox": [],
  "geometry": {"coordinates":[-81.6833,31.2833],"type":"Point"}
}