<<<<<<< HEAD
{
  "id": 2251639,
  "type": "Feature",
  "properties": {
    "tgn:hierarchy":[
        "tgn:2251639",
        "tgn:1000001",
        "tgn:7006451",
        "tgn:7012149",
        "tgn:2000100",
        "tgn:7029392"
    ],
    "tgn:id":2251639,
    "tgn:name":"Comobari Mountains",
    "tgn:placetype":[
        "aat:300386831"
    ]
},
  "bbox": [],
  "geometry": {"coordinates":[-111.7833,32.1167],"type":"Point"}
}
=======
{"geometry":{"type":"Point","coordinates":[-111.783300,32.116700]},"type":"Feature","properties":{"hierarchy":["tgn:2251639","tgn:1000001","tgn:7006451","tgn:7012149","tgn:2000100","tgn:7029392"],"placetype":["aat:300386831"],"id":2251639,"name:xx":"Comobari Mountains"}}
>>>>>>> 03f74aca74312dbeaf24d7e61306dd6a786dc3d0
