{
  "id": 2088438,
  "type": "Feature",
  "properties": {
    "tgn:hierarchy":[
        "tgn:2088438",
        "tgn:1000001",
        "tgn:1002278",
        "tgn:7012149",
        "tgn:7007710",
        "tgn:7029392"
    ],
    "tgn:id":2088438,
    "tgn:name":"Fernwood",
    "tgn:placetype":[
        "aat:300008347",
        "aat:300387210"
    ]
},
  "bbox": [],
  "geometry": {"coordinates":[-78.3833,40.7667],"type":"Point"}
}