{
  "id": 7437218,
  "type": "Feature",
  "properties": {
    "tgn:hierarchy":[
        "tgn:7437218",
        "tgn:7005585",
        "tgn:1000001",
        "tgn:7005560",
        "tgn:7029392"
    ],
    "tgn:id":7437218,
    "tgn:name":"Santiago Salinas",
    "tgn:placetype":[
        "aat:300008347"
    ]
},
  "bbox": [],
  "geometry": {"coordinates":[-99.833333,18.583333],"type":"Point"}
}