{
  "id": 7548959,
  "type": "Feature",
  "properties": {
    "tgn:hierarchy":[
        "tgn:7548959",
        "tgn:1000004",
        "tgn:7000198",
        "tgn:7000799",
        "tgn:7029392"
    ],
    "tgn:id":7548959,
    "tgn:name:en":"Durgu",
    "tgn:placetype":[
        "aat:300008347"
    ]
},
  "bbox": [],
  "geometry": {"coordinates":[78.121761,34.101505],"type":"Point"}
}