{
  "id": 7291643,
  "type": "Feature",
  "properties": {
    "tgn:hierarchy":[
        "tgn:7291643",
        "tgn:1001702",
        "tgn:1000049",
        "tgn:1000002",
        "tgn:7029392"
    ],
    "tgn:id":7291643,
    "tgn:name":"Entrada, Punta",
    "tgn:placetype":[
        "aat:300386846"
    ]
},
  "bbox": [],
  "geometry": {"coordinates":[-71.75,-53.216667],"type":"Point"}
}