{
  "id": 2300158,
  "type": "Feature",
  "properties": {
    "tgn:hierarchy":[
        "tgn:2300158",
        "tgn:1000001",
        "tgn:7012149",
        "tgn:7029392"
    ],
    "tgn:id":2300158,
    "tgn:name":"Dughill Ridge",
    "tgn:placetype":[
        "aat:300266640"
    ]
},
  "bbox": [],
  "geometry": {"coordinates":[-82.25,35.1833],"type":"Point"}
}