{
  "id": 7318920,
  "type": "Feature",
  "properties": {
    "tgn:hierarchy":[
        "tgn:7318920",
        "tgn:7002464",
        "tgn:1000049",
        "tgn:1000002",
        "tgn:7029392"
    ],
    "tgn:id":7318920,
    "tgn:name":"Aroma",
    "tgn:placetype":[
        "aat:300008347"
    ]
},
  "bbox": [],
  "geometry": {"coordinates":[-69.366667,-19.566667],"type":"Point"}
}