{
  "id": 7220813,
  "type": "Feature",
  "properties": {
    "tgn:hierarchy":[
        "tgn:7220813",
        "tgn:7002741",
        "tgn:7017076",
        "tgn:1000003",
        "tgn:1000074",
        "tgn:7029392"
    ],
    "tgn:id":7220813,
    "tgn:name":"Varv\u00e1s",
    "tgn:placetype":[
        "aat:300008795"
    ]
},
  "bbox": [],
  "geometry": {"coordinates":[22.833333,38.65],"type":"Point"}
}