{
  "id": 2234112,
  "type": "Feature",
  "properties": {
    "tgn:hierarchy":[
        "tgn:2234112",
        "tgn:1000001",
        "tgn:7012149",
        "tgn:2002113",
        "tgn:7007827",
        "tgn:7029392"
    ],
    "tgn:id":2234112,
    "tgn:name":"Checkerboard Mesa",
    "tgn:placetype":[
        "aat:300008798"
    ]
},
  "bbox": [],
  "geometry": {"coordinates":[-112.8667,37.2167],"type":"Point"}
}