{
  "id": 2729019,
  "type": "Feature",
  "properties": {
    "tgn:hierarchy":[
        "tgn:2729019",
        "tgn:1000001",
        "tgn:2000589",
        "tgn:7012149",
        "tgn:7007253",
        "tgn:7029392"
    ],
    "tgn:id":2729019,
    "tgn:name":"Trienes Bay",
    "tgn:placetype":[
        "aat:300132316"
    ]
},
  "bbox": [],
  "geometry": {"coordinates":[-91.0333,40.8667],"type":"Point"}
}