<<<<<<< HEAD
{
  "id": 2158563,
  "type": "Feature",
  "properties": {
    "tgn:hierarchy":[
        "tgn:2158563",
        "tgn:1000001",
        "tgn:7012149",
        "tgn:1002440",
        "tgn:7007568",
        "tgn:7029392"
    ],
    "tgn:id":2158563,
    "tgn:name":"Beaverdam Pond",
    "tgn:placetype":[
        "aat:300008680"
    ]
},
  "bbox": [],
  "geometry": {"coordinates":[-74.7667,43.4667],"type":"Point"}
}
=======
{"geometry":{"type":"Point","coordinates":[-74.766700,43.466700]},"type":"Feature","properties":{"hierarchy":["tgn:2158563","tgn:1000001","tgn:7012149","tgn:1002440","tgn:7007568","tgn:7029392"],"placetype":["aat:300008680"],"id":2158563,"name:xx":"Beaverdam Pond"}}
>>>>>>> 03f74aca74312dbeaf24d7e61306dd6a786dc3d0
