{
  "id": 2697753,
  "type": "Feature",
  "properties": {
    "tgn:hierarchy":[
        "tgn:2697753",
        "tgn:1000001",
        "tgn:7012149",
        "tgn:2001275",
        "tgn:7007524",
        "tgn:7029392"
    ],
    "tgn:id":2697753,
    "tgn:name":"Storm Castle",
    "tgn:placetype":[
        "aat:300008798"
    ]
},
  "bbox": [],
  "geometry": {"coordinates":[-111.2167,45.45],"type":"Point"}
}