<<<<<<< HEAD
{
  "id": 7353594,
  "type": "Feature",
  "properties": {
    "tgn:hierarchy":[
        "tgn:7353594",
        "tgn:1000001",
        "tgn:7005592",
        "tgn:7005560",
        "tgn:7029392"
    ],
    "tgn:id":7353594,
    "tgn:name":"Ayutla",
    "tgn:placetype":[
        "aat:300008347"
    ]
},
  "bbox": [],
  "geometry": {"coordinates":[-98.5,18.55],"type":"Point"}
}
=======
{"geometry":{"type":"Point","coordinates":[-98.500000,18.550000]},"type":"Feature","properties":{"hierarchy":["tgn:7353594","tgn:1000001","tgn:7005592","tgn:7005560","tgn:7029392"],"placetype":["aat:300008347"],"id":7353594,"name:xx":"Ayutla"}}
>>>>>>> 03f74aca74312dbeaf24d7e61306dd6a786dc3d0
