{
  "id": 1129324,
  "type": "Feature",
  "properties": {
    "tgn:hierarchy":[
        "tgn:1129324",
        "tgn:1000004",
        "tgn:7000894",
        "tgn:1001034",
        "tgn:1000120",
        "tgn:7029392"
    ],
    "tgn:id":1129324,
    "tgn:name":"Sabi-gawa",
    "tgn:placetype":[
        "aat:300008707"
    ]
},
  "bbox": [],
  "geometry": {"coordinates":[140.05,36.8167],"type":"Point"}
}