{
  "id": 7217426,
  "type": "Feature",
  "properties": {
    "tgn:hierarchy":[
        "tgn:7217426",
        "tgn:7002707",
        "tgn:7002705",
        "tgn:1000003",
        "tgn:1000074",
        "tgn:7029392"
    ],
    "tgn:id":7217426,
    "tgn:name":"Y\u00edftissa",
    "tgn:placetype":[
        "aat:300008798"
    ]
},
  "bbox": [],
  "geometry": {"coordinates":[20.866667,40.183333],"type":"Point"}
}