<<<<<<< HEAD
{
  "id": 2765537,
  "type": "Feature",
  "properties": {
    "tgn:hierarchy":[
        "tgn:2765537",
        "tgn:1000001",
        "tgn:7012149",
        "tgn:7019676",
        "tgn:7007566",
        "tgn:7029392"
    ],
    "tgn:id":2765537,
    "tgn:name":"White Canyon",
    "tgn:placetype":[
        "aat:300008761"
    ]
},
  "bbox": [],
  "geometry": {"coordinates":[-108.7833,35.15],"type":"Point"}
}
=======
{"geometry":{"type":"Point","coordinates":[-108.783300,35.150000]},"type":"Feature","properties":{"hierarchy":["tgn:2765537","tgn:1000001","tgn:7012149","tgn:7019676","tgn:7007566","tgn:7029392"],"placetype":["aat:300008761"],"id":2765537,"name:xx":"White Canyon"}}
>>>>>>> 03f74aca74312dbeaf24d7e61306dd6a786dc3d0
