{
  "id": 2455988,
  "type": "Feature",
  "properties": {
    "tgn:hierarchy":[
        "tgn:2455988",
        "tgn:1000001",
        "tgn:2002146",
        "tgn:7012149",
        "tgn:7007919",
        "tgn:7029392"
    ],
    "tgn:id":2455988,
    "tgn:name":"Little Harkening Hill",
    "tgn:placetype":[
        "aat:300008798"
    ]
},
  "bbox": [],
  "geometry": {"coordinates":[-79.6167,37.4667],"type":"Point"}
}