<<<<<<< HEAD
{
  "id": 2709885,
  "type": "Feature",
  "properties": {
    "tgn:hierarchy":[
        "tgn:2709885",
        "tgn:1000001",
        "tgn:7012149",
        "tgn:7016020",
        "tgn:7007710",
        "tgn:7029392"
    ],
    "tgn:id":2709885,
    "tgn:name":"Taintor",
    "tgn:placetype":[
        "aat:300008347"
    ]
},
  "bbox": [],
  "geometry": {"coordinates":[-78.65,41.8],"type":"Point"}
}
=======
{"geometry":{"type":"Point","coordinates":[-78.650000,41.800000]},"type":"Feature","properties":{"hierarchy":["tgn:2709885","tgn:1000001","tgn:7012149","tgn:7016020","tgn:7007710","tgn:7029392"],"placetype":["aat:300008347"],"id":2709885,"name:xx":"Taintor"}}
>>>>>>> 03f74aca74312dbeaf24d7e61306dd6a786dc3d0
