<<<<<<< HEAD
{
  "id": 2403632,
  "type": "Feature",
  "properties": {
    "tgn:hierarchy":[
        "tgn:2403632",
        "tgn:1000001",
        "tgn:2000772",
        "tgn:7012149",
        "tgn:7007255",
        "tgn:7029392"
    ],
    "tgn:id":2403632,
    "tgn:name":"Howard Fork",
    "tgn:placetype":[
        "aat:300008699"
    ]
},
  "bbox": [],
  "geometry": {"coordinates":[-83.4167,37.4833],"type":"Point"}
}
=======
{"geometry":{"type":"Point","coordinates":[-83.416700,37.483300]},"type":"Feature","properties":{"hierarchy":["tgn:2403632","tgn:1000001","tgn:2000772","tgn:7012149","tgn:7007255","tgn:7029392"],"placetype":["aat:300008699"],"id":2403632,"name:xx":"Howard Fork"}}
>>>>>>> 03f74aca74312dbeaf24d7e61306dd6a786dc3d0
