<<<<<<< HEAD
{
  "id": 7477867,
  "type": "Feature",
  "properties": {
    "tgn:hierarchy":[
        "tgn:7477867",
        "tgn:7001010",
        "tgn:1000004",
        "tgn:1000141",
        "tgn:7029392"
    ],
    "tgn:id":7477867,
    "tgn:name":"Lintian Qiao",
    "tgn:placetype":[
        "aat:300007836"
    ]
},
  "bbox": [],
  "geometry": {"coordinates":[121.472206,23.76257],"type":"Point"}
}
=======
{"geometry":{"type":"Point","coordinates":[121.472206,23.762570]},"type":"Feature","properties":{"hierarchy":["tgn:7477867","tgn:7001010","tgn:1000004","tgn:1000141","tgn:7029392"],"placetype":["aat:300007836"],"id":7477867,"name:xx":"Lintian Qiao"}}
>>>>>>> 03f74aca74312dbeaf24d7e61306dd6a786dc3d0
