{
  "id": 7373298,
  "type": "Feature",
  "properties": {
    "tgn:hierarchy":[
        "tgn:7373298",
        "tgn:7005583",
        "tgn:1000001",
        "tgn:7005560",
        "tgn:7029392"
    ],
    "tgn:id":7373298,
    "tgn:name":"Rancho La Garrapata",
    "tgn:placetype":[
        "aat:300000241"
    ]
},
  "bbox": [],
  "geometry": {"coordinates":[-106.016667,26.733333],"type":"Point"}
}