{
  "id": 7436293,
  "type": "Feature",
  "properties": {
    "tgn:hierarchy":[
        "tgn:7436293",
        "tgn:7005585",
        "tgn:1000001",
        "tgn:7005560",
        "tgn:7029392"
    ],
    "tgn:id":7436293,
    "tgn:name":"Soledad, Cerro",
    "tgn:placetype":[
        "aat:300008795"
    ]
},
  "bbox": [],
  "geometry": {"coordinates":[-100.116667,17.35],"type":"Point"}
}