{
  "id": 7328606,
  "type": "Feature",
  "properties": {
    "tgn:hierarchy":[
        "tgn:7328606",
        "tgn:7002759",
        "tgn:7002845",
        "tgn:1000003",
        "tgn:1000095",
        "tgn:7029392"
    ],
    "tgn:id":7328606,
    "tgn:name":"Pradilla de Ebro",
    "tgn:placetype":[
        "aat:300008347"
    ]
},
  "bbox": [],
  "geometry": {"coordinates":[-1.25,41.866667],"type":"Point"}
}