<<<<<<< HEAD
{
  "id": 7170890,
  "type": "Feature",
  "properties": {
    "tgn:hierarchy":[
        "tgn:7170890",
        "tgn:7003692",
        "tgn:1000003",
        "tgn:7000084",
        "tgn:7029392"
    ],
    "tgn:id":7170890,
    "tgn:name":"Himmelsberg",
    "tgn:placetype":[
        "aat:300008777"
    ]
},
  "bbox": [],
  "geometry": {"coordinates":[7.983333,48.25],"type":"Point"}
}
=======
{"geometry":{"type":"Point","coordinates":[7.983333,48.250000]},"type":"Feature","properties":{"hierarchy":["tgn:7170890","tgn:7003692","tgn:1000003","tgn:7000084","tgn:7029392"],"placetype":["aat:300008777"],"id":7170890,"name:xx":"Himmelsberg"}}
>>>>>>> 03f74aca74312dbeaf24d7e61306dd6a786dc3d0
