{
  "id": 2567742,
  "type": "Feature",
  "properties": {
    "tgn:hierarchy":[
        "tgn:2567742",
        "tgn:1000001",
        "tgn:7012149",
        "tgn:7007157",
        "tgn:2000187",
        "tgn:7029392"
    ],
    "tgn:id":2567742,
    "tgn:name":"Paradise Creek",
    "tgn:placetype":[
        "aat:300008706"
    ]
},
  "bbox": [],
  "geometry": {"coordinates":[-120.65,39.9167],"type":"Point"}
}