<<<<<<< HEAD
{
  "id": 2406103,
  "type": "Feature",
  "properties": {
    "tgn:hierarchy":[
        "tgn:2406103",
        "tgn:7002659",
        "tgn:1000001",
        "tgn:7012149",
        "tgn:2000044",
        "tgn:7029392"
    ],
    "tgn:id":2406103,
    "tgn:name":"Hummel Cave",
    "tgn:placetype":[
        "aat:300008746"
    ]
},
  "bbox": [],
  "geometry": {"coordinates":[-86.5333,34.7167],"type":"Point"}
}
=======
{"geometry":{"type":"Point","coordinates":[-86.533300,34.716700]},"type":"Feature","properties":{"hierarchy":["tgn:2406103","tgn:7002659","tgn:1000001","tgn:7012149","tgn:2000044","tgn:7029392"],"placetype":["aat:300008746"],"id":2406103,"name:xx":"Hummel Cave"}}
>>>>>>> 03f74aca74312dbeaf24d7e61306dd6a786dc3d0
