{
  "id": 2074295,
  "type": "Feature",
  "properties": {
    "tgn:hierarchy":[
        "tgn:2074295",
        "tgn:1000001",
        "tgn:7012149",
        "tgn:2001516",
        "tgn:7007709",
        "tgn:7029392"
    ],
    "tgn:id":2074295,
    "tgn:name":"Cutshalltown",
    "tgn:placetype":[
        "aat:300008347",
        "aat:300387210"
    ]
},
  "bbox": [],
  "geometry": {"coordinates":[-82.6833,35.95],"type":"Point"}
}