{
  "id": 2484230,
  "type": "Feature",
  "properties": {
    "tgn:hierarchy":[
        "tgn:2484230",
        "tgn:1000001",
        "tgn:7012149",
        "tgn:2000808",
        "tgn:7007255",
        "tgn:7029392"
    ],
    "tgn:id":2484230,
    "tgn:name":"Laurel Branch",
    "tgn:placetype":[
        "aat:300008699"
    ]
},
  "bbox": [],
  "geometry": {"coordinates":[-84.25,37.0667],"type":"Point"}
}