{
  "id": 2394445,
  "type": "Feature",
  "properties": {
    "tgn:hierarchy":[
        "tgn:2394445",
        "tgn:2001086",
        "tgn:1000001",
        "tgn:7012149",
        "tgn:7007522",
        "tgn:7029392"
    ],
    "tgn:id":2394445,
    "tgn:name":"Hoggatt Branch",
    "tgn:placetype":[
        "aat:300008699"
    ]
},
  "bbox": [],
  "geometry": {"coordinates":[-91.2167,31.4833],"type":"Point"}
}