{
  "id": 2043411,
  "type": "Feature",
  "properties": {
    "tgn:hierarchy":[
        "tgn:2043411",
        "tgn:1000001",
        "tgn:7012149",
        "tgn:2000885",
        "tgn:7007256",
        "tgn:7029392"
    ],
    "tgn:id":2043411,
    "tgn:name":"Maurepas",
    "tgn:placetype":[
        "aat:300008347"
    ]
},
  "bbox": [],
  "geometry": {"coordinates":[-90.65,30.2833],"type":"Point"}
}