{
  "id": 1129565,
  "type": "Feature",
  "properties": {
    "tgn:hierarchy":[
        "tgn:1129565",
        "tgn:1000002",
        "tgn:7029392"
    ],
    "tgn:id":1129565,
    "tgn:name":"San Juan",
    "tgn:placetype":[
        "aat:300008707"
    ]
},
  "bbox": [],
  "geometry": {"coordinates":[-78.55,1.1833],"type":"Point"}
}