{
  "id": 2481056,
  "type": "Feature",
  "properties": {
    "tgn:hierarchy":[
        "tgn:2481056",
        "tgn:1000001",
        "tgn:7012149",
        "tgn:1002544",
        "tgn:7007255",
        "tgn:7029392"
    ],
    "tgn:id":2481056,
    "tgn:name":"Lamb",
    "tgn:placetype":[
        "aat:300008347"
    ]
},
  "bbox": [],
  "geometry": {"coordinates":[-84.4333,38.95],"type":"Point"}
}