{
  "id": 7302617,
  "type": "Feature",
  "properties": {
    "tgn:hierarchy":[
        "tgn:7302617",
        "tgn:7002810",
        "tgn:7001158",
        "tgn:1000003",
        "tgn:1000095",
        "tgn:7029392"
    ],
    "tgn:id":7302617,
    "tgn:name":"Palacios de la Sierra",
    "tgn:placetype":[
        "aat:300008347"
    ]
},
  "bbox": [],
  "geometry": {"coordinates":[-3.133333,41.966667],"type":"Point"}
}