<<<<<<< HEAD
{
  "id": 2408708,
  "type": "Feature",
  "properties": {
    "tgn:hierarchy":[
        "tgn:2408708",
        "tgn:7002659",
        "tgn:1000001",
        "tgn:7012149",
        "tgn:2000063",
        "tgn:7029392"
    ],
    "tgn:id":2408708,
    "tgn:name":"Hyche Mine",
    "tgn:placetype":[
        "aat:300000390"
    ]
},
  "bbox": [],
  "geometry": {"coordinates":[-87.2167,33.7],"type":"Point"}
}
=======
{"geometry":{"type":"Point","coordinates":[-87.216700,33.700000]},"type":"Feature","properties":{"hierarchy":["tgn:2408708","tgn:7002659","tgn:1000001","tgn:7012149","tgn:2000063","tgn:7029392"],"placetype":["aat:300000390"],"id":2408708,"name:xx":"Hyche Mine"}}
>>>>>>> 03f74aca74312dbeaf24d7e61306dd6a786dc3d0
