{
  "id": 2746303,
  "type": "Feature",
  "properties": {
    "tgn:hierarchy":[
        "tgn:2746303",
        "tgn:1000001",
        "tgn:7012149",
        "tgn:7007157",
        "tgn:1002863",
        "tgn:7029392"
    ],
    "tgn:id":2746303,
    "tgn:name":"Vulture Rock",
    "tgn:placetype":[
        "aat:300008798"
    ]
},
  "bbox": [],
  "geometry": {"coordinates":[-121.0167,35.6333],"type":"Point"}
}