{
  "id": 1110005,
  "type": "Feature",
  "properties": {
    "tgn:hierarchy":[
        "tgn:1110005",
        "tgn:1000001",
        "tgn:2001418",
        "tgn:7012149",
        "tgn:7007526",
        "tgn:7029392"
    ],
    "tgn:id":1110005,
    "tgn:name":"Hot Creek Range",
    "tgn:placetype":[
        "aat:300386831"
    ]
},
  "bbox": [],
  "geometry": {"coordinates":[-116.4167,38.55],"type":"Point"}
}