{
  "id": 7520657,
  "type": "Feature",
  "properties": {
    "tgn:hierarchy":[
        "tgn:7520657",
        "tgn:7001242",
        "tgn:7016833",
        "tgn:1001335",
        "tgn:7029392"
    ],
    "tgn:id":7520657,
    "tgn:name:en":"Ab\u016b adh Dhahab, Mall\u0101\u1e29at",
    "tgn:placetype":[
        "aat:300266556"
    ]
},
  "bbox": [],
  "geometry": {"coordinates":[31.088611,31.570833],"type":"Point"}
}