{
  "id": 2354226,
  "type": "Feature",
  "properties": {
    "tgn:hierarchy":[
        "tgn:2354226",
        "tgn:1000001",
        "tgn:7012149",
        "tgn:2002125",
        "tgn:7007827",
        "tgn:7029392"
    ],
    "tgn:id":2354226,
    "tgn:name":"Golden Ridge",
    "tgn:placetype":[
        "aat:300266640"
    ]
},
  "bbox": [],
  "geometry": {"coordinates":[-111.6333,39.8167],"type":"Point"}
}