{
  "id": 2785586,
  "type": "Feature",
  "properties": {
    "tgn:hierarchy":[
        "tgn:2785586",
        "tgn:1000001",
        "tgn:7016172",
        "tgn:7012149",
        "tgn:2000149",
        "tgn:7029392"
    ],
    "tgn:id":2785586,
    "tgn:name":"Yocum Cove",
    "tgn:placetype":[
        "aat:300008699"
    ]
},
  "bbox": [],
  "geometry": {"coordinates":[-92.6667,36.4667],"type":"Point"}
}