{
  "id": 7577343,
  "type": "Feature",
  "properties": {
    "tgn:hierarchy":[
        "tgn:7577343",
        "tgn:1000004",
        "tgn:7000198",
        "tgn:7016722",
        "tgn:7029392"
    ],
    "tgn:id":7577343,
    "tgn:name:en":"Kudarkot",
    "tgn:placetype":[
        "aat:300008347"
    ]
},
  "bbox": [],
  "geometry": {"coordinates":[79.393077,26.811423],"type":"Point"}
}