{
  "id": 4000853,
  "type": "Feature",
  "properties": {
    "tgn:hierarchy":[
        "tgn:4000853",
        "tgn:7007088",
        "tgn:1000003",
        "tgn:7009604",
        "tgn:1000095",
        "tgn:7029392"
    ],
    "tgn:id":4000853,
    "tgn:name":"Arriola",
    "tgn:placetype":[
        "aat:300008347"
    ]
},
  "bbox": [],
  "geometry": {"coordinates":[-2.39085,42.912005],"type":"Point"}
}