{
  "id": 7438480,
  "type": "Feature",
  "properties": {
    "tgn:hierarchy":[
        "tgn:7438480",
        "tgn:7005583",
        "tgn:1000001",
        "tgn:7005560",
        "tgn:7029392"
    ],
    "tgn:id":7438480,
    "tgn:name":"Tagarete, Cerro",
    "tgn:placetype":[
        "aat:300008795"
    ]
},
  "bbox": [],
  "geometry": {"coordinates":[-105.883333,26.516667],"type":"Point"}
}