{
  "id": 7123565,
  "type": "Feature",
  "properties": {
    "tgn:hierarchy":[
        "tgn:7123565",
        "tgn:7000096",
        "tgn:1000003",
        "tgn:7000084",
        "tgn:7029392"
    ],
    "tgn:id":7123565,
    "tgn:name":"Neudorf",
    "tgn:placetype":[
        "aat:300008347"
    ]
},
  "bbox": [],
  "geometry": {"coordinates":[14.066667,51.666667],"type":"Point"}
}