{
  "id": 2783496,
  "type": "Feature",
  "properties": {
    "tgn:hierarchy":[
        "tgn:2783496",
        "tgn:1000001",
        "tgn:7012149",
        "tgn:2000476",
        "tgn:7007250",
        "tgn:7029392"
    ],
    "tgn:id":2783496,
    "tgn:name":"Wyant Creek",
    "tgn:placetype":[
        "aat:300008706"
    ]
},
  "bbox": [],
  "geometry": {"coordinates":[-116.4667,45.2667],"type":"Point"}
}