{
  "id": 1070175,
  "type": "Feature",
  "properties": {
    "tgn:hierarchy":[
        "tgn:1070175",
        "tgn:1000004",
        "tgn:7002081",
        "tgn:1000111",
        "tgn:7029392"
    ],
    "tgn:id":1070175,
    "tgn:name":"Lumu",
    "tgn:placetype":[
        "aat:300008347"
    ]
},
  "bbox": [],
  "geometry": {"coordinates":[120.6167,31.35],"type":"Point"}
}