{
  "id": 2651701,
  "type": "Feature",
  "properties": {
    "tgn:hierarchy":[
        "tgn:2651701",
        "tgn:1000001",
        "tgn:7012149",
        "tgn:2000483",
        "tgn:7007250",
        "tgn:7029392"
    ],
    "tgn:id":2651701,
    "tgn:name":"Seep Reservoir",
    "tgn:placetype":[
        "aat:300008680"
    ]
},
  "bbox": [],
  "geometry": {"coordinates":[-114.4333,43.0833],"type":"Point"}
}