{
  "id": 2033556,
  "type": "Feature",
  "properties": {
    "tgn:hierarchy":[
        "tgn:2033556",
        "tgn:1000001",
        "tgn:1002325",
        "tgn:7012149",
        "tgn:7007252",
        "tgn:7029392"
    ],
    "tgn:id":2033556,
    "tgn:name":"Saint Paul",
    "tgn:placetype":[
        "aat:300008347"
    ]
},
  "bbox": [],
  "geometry": {"coordinates":[-85.6167,39.4167],"type":"Point"}
}