{
  "id": 2473279,
  "type": "Feature",
  "properties": {
    "tgn:hierarchy":[
        "tgn:2473279",
        "tgn:1000001",
        "tgn:7012149",
        "tgn:2002018",
        "tgn:7007826",
        "tgn:7029392"
    ],
    "tgn:id":2473279,
    "tgn:name":"Lower Bee Caves Spring",
    "tgn:placetype":[
        "aat:300008697"
    ]
},
  "bbox": [],
  "geometry": {"coordinates":[-99.4333,30.05],"type":"Point"}
}