<<<<<<< HEAD
{
  "id": 7372322,
  "type": "Feature",
  "properties": {
    "tgn:hierarchy":[
        "tgn:7372322",
        "tgn:1000001",
        "tgn:1001960",
        "tgn:7005560",
        "tgn:7029392"
    ],
    "tgn:id":7372322,
    "tgn:name":"Rancho La Nopalera",
    "tgn:placetype":[
        "aat:300000241"
    ]
},
  "bbox": [],
  "geometry": {"coordinates":[-111.533333,29.7],"type":"Point"}
}
=======
{"geometry":{"type":"Point","coordinates":[-111.533333,29.700000]},"type":"Feature","properties":{"hierarchy":["tgn:7372322","tgn:1000001","tgn:1001960","tgn:7005560","tgn:7029392"],"placetype":["aat:300000241"],"id":7372322,"name:xx":"Rancho La Nopalera"}}
>>>>>>> 03f74aca74312dbeaf24d7e61306dd6a786dc3d0
