{
  "id": 7415533,
  "type": "Feature",
  "properties": {
    "tgn:hierarchy":[
        "tgn:7415533",
        "tgn:1000001",
        "tgn:7005591",
        "tgn:7005560",
        "tgn:7029392"
    ],
    "tgn:id":7415533,
    "tgn:name:es":"Santa Mar\u00eda Yucuhiti",
    "tgn:placetype":[
        "aat:300008347"
    ]
},
  "bbox": [],
  "geometry": {"coordinates":[-97.765556,17.011389],"type":"Point"}
}