{
  "id": 2640259,
  "type": "Feature",
  "properties": {
    "tgn:hierarchy":[
        "tgn:2640259",
        "tgn:1000001",
        "tgn:7012149",
        "tgn:2002099",
        "tgn:7007826",
        "tgn:7029392"
    ],
    "tgn:id":2640259,
    "tgn:name":"San Bartolo, Arroyo",
    "tgn:placetype":[
        "aat:300008761"
    ]
},
  "bbox": [],
  "geometry": {"coordinates":[-99.2667,26.9333],"type":"Point"}
}