{
  "id": 1047545,
  "type": "Feature",
  "properties": {
    "tgn:hierarchy":[
        "tgn:1047545",
        "tgn:7003531",
        "tgn:1000003",
        "tgn:7003514",
        "tgn:7029392"
    ],
    "tgn:id":1047545,
    "tgn:name":"Bourscheid",
    "tgn:placetype":[
        "aat:300008347"
    ]
},
  "bbox": [],
  "geometry": {"coordinates":[6.0667,49.9167],"type":"Point"}
}