{
  "id": 7384889,
  "type": "Feature",
  "properties": {
    "tgn:hierarchy":[
        "tgn:7384889",
        "tgn:1000001",
        "tgn:7005588",
        "tgn:7005560",
        "tgn:7029392"
    ],
    "tgn:id":7384889,
    "tgn:name":"Nepopualco",
    "tgn:placetype":[
        "aat:300008347"
    ]
},
  "bbox": [],
  "geometry": {"coordinates":[-98.933333,18.983333],"type":"Point"}
}