{
  "id": 7393046,
  "type": "Feature",
  "properties": {
    "tgn:hierarchy":[
        "tgn:7393046",
        "tgn:1000001",
        "tgn:7005589",
        "tgn:7005560",
        "tgn:7029392"
    ],
    "tgn:id":7393046,
    "tgn:name":"San Joaqu\u00edn",
    "tgn:placetype":[
        "aat:300008347"
    ]
},
  "bbox": [],
  "geometry": {"coordinates":[-99.65,25.266667],"type":"Point"}
}