{
  "id": 1026622,
  "type": "Feature",
  "properties": {
    "tgn:hierarchy":[
        "tgn:1026622",
        "tgn:7003460",
        "tgn:1000003",
        "tgn:1000063",
        "tgn:4012014",
        "tgn:7029392"
    ],
    "tgn:id":1026622,
    "tgn:name":"Moxhe",
    "tgn:placetype":[
        "aat:300008347"
    ]
},
  "bbox": [],
  "geometry": {"coordinates":[5.091775,50.631765],"type":"Point"}
}