{
  "id": 7168305,
  "type": "Feature",
  "properties": {
    "tgn:hierarchy":[
        "tgn:7168305",
        "tgn:1000003",
        "tgn:7003687",
        "tgn:7000084",
        "tgn:7029392"
    ],
    "tgn:id":7168305,
    "tgn:name":"Hasserode",
    "tgn:placetype":[
        "aat:300000745"
    ]
},
  "bbox": [],
  "geometry": {"coordinates":[10.75,51.816667],"type":"Point"}
}