{
  "id": 7403312,
  "type": "Feature",
  "properties": {
    "tgn:hierarchy":[
        "tgn:7403312",
        "tgn:1000001",
        "tgn:7005600",
        "tgn:7005560",
        "tgn:7029392"
    ],
    "tgn:id":7403312,
    "tgn:name":"Yalkubul, Punta",
    "tgn:placetype":[
        "aat:300386846"
    ]
},
  "bbox": [],
  "geometry": {"coordinates":[-88.616667,21.533333],"type":"Point"}
}