{
  "id": 7277063,
  "type": "Feature",
  "properties": {
    "tgn:hierarchy":[
        "tgn:7277063",
        "tgn:7002464",
        "tgn:1000049",
        "tgn:1000002",
        "tgn:7029392"
    ],
    "tgn:id":7277063,
    "tgn:name":"Palcota, Cerro",
    "tgn:placetype":[
        "aat:300008795"
    ]
},
  "bbox": [],
  "geometry": {"coordinates":[-69.965278,-17.869167],"type":"Point"}
}