{
  "id": 1022232,
  "type": "Feature",
  "properties": {
    "tgn:hierarchy":[
        "tgn:1022232",
        "tgn:1001942",
        "tgn:1000047",
        "tgn:7002457",
        "tgn:1000002",
        "tgn:7029392"
    ],
    "tgn:id":1022232,
    "tgn:name":"Nova Friburgo",
    "tgn:placetype":[
        "aat:300008347",
        "aat:300008389",
        "aat:300000547"
    ]
},
  "bbox": [],
  "geometry": {"coordinates":[-42.5667,-22.2667],"type":"Point"}
}