{
  "id": 2706835,
  "type": "Feature",
  "properties": {
    "tgn:hierarchy":[
        "tgn:2706835",
        "tgn:1000001",
        "tgn:7012149",
        "tgn:2000978",
        "tgn:7007520",
        "tgn:7029392"
    ],
    "tgn:id":2706835,
    "tgn:name":"Swanson Creek",
    "tgn:placetype":[
        "aat:300008706"
    ]
},
  "bbox": [],
  "geometry": {"coordinates":[-87.7167,45.4667],"type":"Point"}
}