{
  "id": 7259790,
  "type": "Feature",
  "properties": {
    "tgn:hierarchy":[
        "tgn:7259790",
        "tgn:7003461",
        "tgn:1000003",
        "tgn:1000063",
        "tgn:7018236",
        "tgn:7029392"
    ],
    "tgn:id":7259790,
    "tgn:name":"Zutendaal",
    "tgn:placetype":[
        "aat:300387173"
    ]
},
  "bbox": [],
  "geometry": {"coordinates":[5.566667,50.933333],"type":"Point"}
}