{
  "id": 7223678,
  "type": "Feature",
  "properties": {
    "tgn:hierarchy":[
        "tgn:7223678",
        "tgn:7002715",
        "tgn:7002731",
        "tgn:1000003",
        "tgn:1000074",
        "tgn:7029392"
    ],
    "tgn:id":7223678,
    "tgn:name":"Sarak\u00edna",
    "tgn:placetype":[
        "aat:300008347"
    ]
},
  "bbox": [],
  "geometry": {"coordinates":[23.216667,40.583333],"type":"Point"}
}