<<<<<<< HEAD
{
  "id": 7053949,
  "type": "Feature",
  "properties": {
    "tgn:hierarchy":[
        "tgn:7053949",
        "tgn:7003005",
        "tgn:7003014",
        "tgn:1000003",
        "tgn:1000080",
        "tgn:7029392"
    ],
    "tgn:id":7053949,
    "tgn:name":"Palistro, Fiume",
    "tgn:placetype":[
        "aat:300008699"
    ]
},
  "bbox": [],
  "geometry": {"coordinates":[15.15,40.183333],"type":"Point"}
}
=======
{"geometry":{"type":"Point","coordinates":[15.150000,40.183333]},"type":"Feature","properties":{"hierarchy":["tgn:7053949","tgn:7003005","tgn:7003014","tgn:1000003","tgn:1000080","tgn:7029392"],"placetype":["aat:300008699"],"id":7053949,"name:xx":"Palistro, Fiume"}}
>>>>>>> 03f74aca74312dbeaf24d7e61306dd6a786dc3d0
