{
  "id": 2563201,
  "type": "Feature",
  "properties": {
    "tgn:hierarchy":[
        "tgn:2563201",
        "tgn:1000001",
        "tgn:7006451",
        "tgn:7012149",
        "tgn:2000099",
        "tgn:7029392"
    ],
    "tgn:id":2563201,
    "tgn:name":"Owens Tank",
    "tgn:placetype":[
        "aat:300006191"
    ]
},
  "bbox": [],
  "geometry": {"coordinates":[-110.2167,34.3333],"type":"Point"}
}