{
  "id": 7256841,
  "type": "Feature",
  "properties": {
    "tgn:hierarchy":[
        "tgn:7256841",
        "tgn:7004783",
        "tgn:7593114",
        "tgn:7593112",
        "tgn:1000001",
        "tgn:7029392"
    ],
    "tgn:id":7256841,
    "tgn:name:nl":"Compagnie",
    "tgn:placetype":[
        "aat:300387200"
    ]
},
  "bbox": [],
  "geometry": {"coordinates":[-62.95,17.466667],"type":"Point"}
}