{
  "id": 2098572,
  "type": "Feature",
  "properties": {
    "tgn:hierarchy":[
        "tgn:2098572",
        "tgn:1000001",
        "tgn:2001841",
        "tgn:7012149",
        "tgn:7007825",
        "tgn:7029392"
    ],
    "tgn:id":2098572,
    "tgn:name":"College Park Estates",
    "tgn:placetype":[
        "aat:300008347"
    ]
},
  "bbox": [],
  "geometry": {"coordinates":[-83.9333,35.7167],"type":"Point"}
}