{
  "id": 7335065,
  "type": "Feature",
  "properties": {
    "tgn:hierarchy":[
        "tgn:7335065",
        "tgn:7002844",
        "tgn:7030216",
        "tgn:1000003",
        "tgn:1000095",
        "tgn:7029392"
    ],
    "tgn:id":7335065,
    "tgn:name":"Gos, Morro de",
    "tgn:placetype":[
        "aat:300387499"
    ]
},
  "bbox": [],
  "geometry": {"coordinates":[0.75,40.816667],"type":"Point"}
}