{
  "id": 2601044,
  "type": "Feature",
  "properties": {
    "tgn:hierarchy":[
        "tgn:2601044",
        "tgn:1000001",
        "tgn:7012149",
        "tgn:2001119",
        "tgn:7007522",
        "tgn:7029392"
    ],
    "tgn:id":2601044,
    "tgn:name":"Punch Branch",
    "tgn:placetype":[
        "aat:300008699"
    ]
},
  "bbox": [],
  "geometry": {"coordinates":[-89.3333,31.45],"type":"Point"}
}