{
  "id": 2622735,
  "type": "Feature",
  "properties": {
    "tgn:hierarchy":[
        "tgn:2622735",
        "tgn:1000001",
        "tgn:7012149",
        "tgn:7007157",
        "tgn:2000185",
        "tgn:7029392"
    ],
    "tgn:id":2622735,
    "tgn:name":"Robinson Gulch",
    "tgn:placetype":[
        "aat:300008761"
    ]
},
  "bbox": [],
  "geometry": {"coordinates":[-123.5167,38.7833],"type":"Point"}
}