{
  "id": 7493730,
  "type": "Feature",
  "properties": {
    "tgn:hierarchy":[
        "tgn:7493730",
        "tgn:7468018",
        "tgn:1000004",
        "tgn:1000141",
        "tgn:7029392"
    ],
    "tgn:id":7493730,
    "tgn:name":"Shengyuan Qiao",
    "tgn:placetype":[
        "aat:300007836"
    ]
},
  "bbox": [],
  "geometry": {"coordinates":[120.585918,23.482659],"type":"Point"}
}