{
  "id": 7158069,
  "type": "Feature",
  "properties": {
    "tgn:hierarchy":[
        "tgn:7158069",
        "tgn:7003669",
        "tgn:1000003",
        "tgn:7000084",
        "tgn:7029392"
    ],
    "tgn:id":7158069,
    "tgn:name":"Katzenlohe",
    "tgn:placetype":[
        "aat:300000206"
    ]
},
  "bbox": [],
  "geometry": {"coordinates":[11.433333,50.033333],"type":"Point"}
}