<<<<<<< HEAD
{
  "id": 7487162,
  "type": "Feature",
  "properties": {
    "tgn:hierarchy":[
        "tgn:7487162",
        "tgn:1000004",
        "tgn:7001013",
        "tgn:1000141",
        "tgn:7029392"
    ],
    "tgn:id":7487162,
    "tgn:name":"Gaoshanxia",
    "tgn:placetype":[
        "aat:300008347"
    ]
},
  "bbox": [],
  "geometry": {"coordinates":[121.189167,24.940278],"type":"Point"}
}
=======
{"geometry":{"type":"Point","coordinates":[121.189167,24.940278]},"type":"Feature","properties":{"hierarchy":["tgn:7487162","tgn:1000004","tgn:7001013","tgn:1000141","tgn:7029392"],"placetype":["aat:300008347"],"id":7487162,"name:xx":"Gaoshanxia"}}
>>>>>>> 03f74aca74312dbeaf24d7e61306dd6a786dc3d0
