{
  "id": 2574995,
  "type": "Feature",
  "properties": {
    "tgn:hierarchy":[
        "tgn:2574995",
        "tgn:1000001",
        "tgn:7012149",
        "tgn:7007710",
        "tgn:7029392"
    ],
    "tgn:id":2574995,
    "tgn:name":"Penn Forest Reservoir",
    "tgn:placetype":[
        "aat:300006191"
    ]
},
  "bbox": [],
  "geometry": {"coordinates":[-75.55,40.9167],"type":"Point"}
}