{
  "id": 7398975,
  "type": "Feature",
  "properties": {
    "tgn:hierarchy":[
        "tgn:7398975",
        "tgn:1000001",
        "tgn:1001893",
        "tgn:7005560",
        "tgn:7029392"
    ],
    "tgn:id":7398975,
    "tgn:name":"Tierras Blancas",
    "tgn:placetype":[
        "aat:300008347"
    ]
},
  "bbox": [],
  "geometry": {"coordinates":[-99.860833,19.8675],"type":"Point"}
}