{
  "id": 7488569,
  "type": "Feature",
  "properties": {
    "tgn:hierarchy":[
        "tgn:7488569",
        "tgn:1000004",
        "tgn:7467799",
        "tgn:1000141",
        "tgn:7029392"
    ],
    "tgn:id":7488569,
    "tgn:name":"Nanshi",
    "tgn:placetype":[
        "aat:300008347"
    ]
},
  "bbox": [],
  "geometry": {"coordinates":[120.455,24.090278],"type":"Point"}
}