{
  "id": 1068433,
  "type": "Feature",
  "properties": {
    "tgn:hierarchy":[
        "tgn:1068433",
        "tgn:1000004",
        "tgn:1001390",
        "tgn:1000111",
        "tgn:7029392"
    ],
    "tgn:id":1068433,
    "tgn:name":"Guchengzi",
    "tgn:placetype":[
        "aat:300008347"
    ]
},
  "bbox": [],
  "geometry": {"coordinates":[120.5167,40.6667],"type":"Point"}
}