{
  "id": 2470624,
  "type": "Feature",
  "properties": {
    "tgn:hierarchy":[
        "tgn:2470624",
        "tgn:1000001",
        "tgn:7012149",
        "tgn:7007826",
        "tgn:7029392"
    ],
    "tgn:id":2470624,
    "tgn:name":"Los Tanques Creek",
    "tgn:placetype":[
        "aat:300008706"
    ]
},
  "bbox": [],
  "geometry": {"coordinates":[-98.8667,27.1167],"type":"Point"}
}