{
  "id": 2624030,
  "type": "Feature",
  "properties": {
    "tgn:hierarchy":[
        "tgn:2624030",
        "tgn:1000001",
        "tgn:1002840",
        "tgn:7012149",
        "tgn:7007828",
        "tgn:7029392"
    ],
    "tgn:id":2624030,
    "tgn:name":"Rock Hill",
    "tgn:placetype":[
        "aat:300008798"
    ]
},
  "bbox": [],
  "geometry": {"coordinates":[-73.2167,43.3167],"type":"Point"}
}