{
  "id": 7327427,
  "type": "Feature",
  "properties": {
    "tgn:hierarchy":[
        "tgn:7327427",
        "tgn:7002844",
        "tgn:7030216",
        "tgn:1000003",
        "tgn:1000095",
        "tgn:7029392"
    ],
    "tgn:id":7327427,
    "tgn:name":"Pe\u00f1als, Punta dels",
    "tgn:placetype":[
        "aat:300386846"
    ]
},
  "bbox": [],
  "geometry": {"coordinates":[0.95,41.016667],"type":"Point"}
}