<<<<<<< HEAD
{
  "id": 7350733,
  "type": "Feature",
  "properties": {
    "tgn:hierarchy":[
        "tgn:7350733",
        "tgn:1000001",
        "tgn:1001893",
        "tgn:7005560",
        "tgn:7029392"
    ],
    "tgn:id":7350733,
    "tgn:name":"Blanco, R\u00edo",
    "tgn:placetype":[
        "aat:300008699"
    ]
},
  "bbox": [],
  "geometry": {"coordinates":[-99.392222,24.147778],"type":"Point"}
}
=======
{"geometry":{"type":"Point","coordinates":[-99.392222,24.147778]},"type":"Feature","properties":{"hierarchy":["tgn:7350733","tgn:1000001","tgn:1001893","tgn:7005560","tgn:7029392"],"placetype":["aat:300008699"],"id":7350733,"name:xx":"Blanco, R\u00edo"}}
>>>>>>> 03f74aca74312dbeaf24d7e61306dd6a786dc3d0
