{
  "id": 1043153,
  "type": "Feature",
  "properties": {
    "tgn:hierarchy":[
        "tgn:1043153",
        "tgn:1003455",
        "tgn:1000003",
        "tgn:7010380",
        "tgn:1000080",
        "tgn:7029392"
    ],
    "tgn:id":1043153,
    "tgn:name":"Alberona",
    "tgn:placetype":[
        "aat:300008347"
    ]
},
  "bbox": [],
  "geometry": {"coordinates":[15.116667,41.433333],"type":"Point"}
}