{
  "id": 2496248,
  "type": "Feature",
  "properties": {
    "tgn:hierarchy":[
        "tgn:2496248",
        "tgn:1000001",
        "tgn:7012149",
        "tgn:7007158",
        "tgn:2000245",
        "tgn:7029392"
    ],
    "tgn:id":2496248,
    "tgn:name":"Mat Gulch",
    "tgn:placetype":[
        "aat:300008761"
    ]
},
  "bbox": [],
  "geometry": {"coordinates":[-107.1667,40.5667],"type":"Point"}
}