<<<<<<< HEAD
{
  "id": 2159732,
  "type": "Feature",
  "properties": {
    "tgn:hierarchy":[
        "tgn:2159732",
        "tgn:1000001",
        "tgn:1002260",
        "tgn:7012149",
        "tgn:7007920",
        "tgn:7029392"
    ],
    "tgn:id":2159732,
    "tgn:name":"Beebe Springs",
    "tgn:placetype":[
        "aat:300008697"
    ]
},
  "bbox": [],
  "geometry": {"coordinates":[-119.9667,47.8167],"type":"Point"}
}
=======
{"geometry":{"type":"Point","coordinates":[-119.966700,47.816700]},"type":"Feature","properties":{"hierarchy":["tgn:2159732","tgn:1000001","tgn:1002260","tgn:7012149","tgn:7007920","tgn:7029392"],"placetype":["aat:300008697"],"id":2159732,"name:xx":"Beebe Springs"}}
>>>>>>> 03f74aca74312dbeaf24d7e61306dd6a786dc3d0
