{
  "id": 2115450,
  "type": "Feature",
  "properties": {
    "tgn:hierarchy":[
        "tgn:2115450",
        "tgn:1000001",
        "tgn:7012149",
        "tgn:1002897",
        "tgn:7007920",
        "tgn:7029392"
    ],
    "tgn:id":2115450,
    "tgn:name":"Carson",
    "tgn:placetype":[
        "aat:300008347"
    ]
},
  "bbox": [],
  "geometry": {"coordinates":[-121.8167,45.7167],"type":"Point"}
}