{
  "id": 1086223,
  "type": "Feature",
  "properties": {
    "tgn:hierarchy":[
        "tgn:1086223",
        "tgn:7000420",
        "tgn:7018452",
        "tgn:1000004",
        "tgn:1000144",
        "tgn:7029392"
    ],
    "tgn:id":1086223,
    "tgn:name":"E\u011fridir",
    "tgn:placetype":[
        "aat:300008347"
    ]
},
  "bbox": [],
  "geometry": {"coordinates":[30.85,37.8667],"type":"Point"}
}