{
  "id": 7484683,
  "type": "Feature",
  "properties": {
    "tgn:hierarchy":[
        "tgn:7484683",
        "tgn:7001004",
        "tgn:1000004",
        "tgn:1000141",
        "tgn:7029392"
    ],
    "tgn:id":7484683,
    "tgn:name":"Xiakan",
    "tgn:placetype":[
        "aat:300008347"
    ]
},
  "bbox": [],
  "geometry": {"coordinates":[120.685278,23.084167],"type":"Point"}
}