<<<<<<< HEAD
{
  "id": 7484683,
  "type": "Feature",
  "properties": {
    "tgn:hierarchy":[
        "tgn:7484683",
        "tgn:7001004",
        "tgn:1000004",
        "tgn:1000141",
        "tgn:7029392"
    ],
    "tgn:id":7484683,
    "tgn:name":"Xiakan",
    "tgn:placetype":[
        "aat:300008347"
    ]
},
  "bbox": [],
  "geometry": {"coordinates":[120.685278,23.084167],"type":"Point"}
}
=======
{"geometry":{"type":"Point","coordinates":[120.685278,23.084167]},"type":"Feature","properties":{"hierarchy":["tgn:7484683","tgn:7001004","tgn:1000004","tgn:1000141","tgn:7029392"],"placetype":["aat:300008347"],"id":7484683,"name:xx":"Xiakan"}}
>>>>>>> 03f74aca74312dbeaf24d7e61306dd6a786dc3d0
