{
  "id": 7096972,
  "type": "Feature",
  "properties": {
    "tgn:hierarchy":[
        "tgn:7096972",
        "tgn:7003669",
        "tgn:1000003",
        "tgn:7000084",
        "tgn:7029392"
    ],
    "tgn:id":7096972,
    "tgn:name":"Stadel",
    "tgn:placetype":[
        "aat:300008347"
    ]
},
  "bbox": [],
  "geometry": {"coordinates":[10.95,50.133333],"type":"Point"}
}