{
  "id": 2331096,
  "type": "Feature",
  "properties": {
    "tgn:hierarchy":[
        "tgn:2331096",
        "tgn:1000001",
        "tgn:2001436",
        "tgn:7012149",
        "tgn:7007566",
        "tgn:7029392"
    ],
    "tgn:id":2331096,
    "tgn:name":"Flat Tank",
    "tgn:placetype":[
        "aat:300006191"
    ]
},
  "bbox": [],
  "geometry": {"coordinates":[-104.3833,32.2667],"type":"Point"}
}