{
  "id": 2752705,
  "type": "Feature",
  "properties": {
    "tgn:hierarchy":[
        "tgn:2752705",
        "tgn:1000001",
        "tgn:7012149",
        "tgn:1002876",
        "tgn:7007710",
        "tgn:7029392"
    ],
    "tgn:id":2752705,
    "tgn:name":"Waste House Run Reservoir Number Three",
    "tgn:placetype":[
        "aat:300006191"
    ]
},
  "bbox": [],
  "geometry": {"coordinates":[-76.15,40.8333],"type":"Point"}
}