{
  "id": 7583044,
  "type": "Feature",
  "properties": {
    "tgn:hierarchy":[
        "tgn:7583044",
        "tgn:1000004",
        "tgn:7000198",
        "tgn:1001894",
        "tgn:7029392"
    ],
    "tgn:id":7583044,
    "tgn:name:en":"B\u016bdho",
    "tgn:placetype":[
        "aat:300008347"
    ]
},
  "bbox": [],
  "geometry": {"coordinates":[78.481587,24.048162],"type":"Point"}
}