<<<<<<< HEAD
{
  "id": 2767005,
  "type": "Feature",
  "properties": {
    "tgn:hierarchy":[
        "tgn:2767005",
        "tgn:1000001",
        "tgn:7012149",
        "tgn:2001284",
        "tgn:7007524",
        "tgn:7029392"
    ],
    "tgn:id":2767005,
    "tgn:name":"White Ridge",
    "tgn:placetype":[
        "aat:300266640"
    ]
},
  "bbox": [],
  "geometry": {"coordinates":[-113.0,47.6667],"type":"Point"}
}
=======
{"geometry":{"type":"Point","coordinates":[-113.000000,47.666700]},"type":"Feature","properties":{"hierarchy":["tgn:2767005","tgn:1000001","tgn:7012149","tgn:2001284","tgn:7007524","tgn:7029392"],"placetype":["aat:300266640"],"id":2767005,"name:xx":"White Ridge"}}
>>>>>>> 03f74aca74312dbeaf24d7e61306dd6a786dc3d0
