{
  "id": 2095842,
  "type": "Feature",
  "properties": {
    "tgn:hierarchy":[
        "tgn:2095842",
        "tgn:1000001",
        "tgn:2001735",
        "tgn:7012149",
        "tgn:7007712",
        "tgn:7029392"
    ],
    "tgn:id":2095842,
    "tgn:name":"Gaffney",
    "tgn:placetype":[
        "aat:300008347"
    ]
},
  "bbox": [],
  "geometry": {"coordinates":[-81.65,35.0667],"type":"Point"}
}