{
  "id": 2681796,
  "type": "Feature",
  "properties": {
    "tgn:hierarchy":[
        "tgn:2681796",
        "tgn:1000001",
        "tgn:7012149",
        "tgn:7007712",
        "tgn:7029392"
    ],
    "tgn:id":2681796,
    "tgn:name":"South Saluda River",
    "tgn:placetype":[
        "aat:300008707"
    ]
},
  "bbox": [],
  "geometry": {"coordinates":[-82.75,35.05],"type":"Point"}
}