{
  "id": 2740519,
  "type": "Feature",
  "properties": {
    "tgn:hierarchy":[
        "tgn:2740519",
        "tgn:1000001",
        "tgn:7012149",
        "tgn:7007923",
        "tgn:7029392"
    ],
    "tgn:id":2740519,
    "tgn:name":"Upper North Crow Reservoir",
    "tgn:placetype":[
        "aat:300006191"
    ]
},
  "bbox": [],
  "geometry": {"coordinates":[-105.2667,41.2333],"type":"Point"}
}