<<<<<<< HEAD
{
  "id": 7023698,
  "type": "Feature",
  "properties": {
    "tgn:hierarchy":[
        "tgn:7023698",
        "tgn:1000001",
        "tgn:7012149",
        "tgn:7007710",
        "tgn:7029392"
    ],
    "tgn:id":7023698,
    "tgn:name":"Potter Run",
    "tgn:placetype":[
        "aat:300008699"
    ]
},
  "bbox": [],
  "geometry": {"coordinates":[-78.15,41.0833],"type":"Point"}
}
=======
{"geometry":{"type":"Point","coordinates":[-78.150000,41.083300]},"type":"Feature","properties":{"hierarchy":["tgn:7023698","tgn:1000001","tgn:7012149","tgn:7007710","tgn:7029392"],"placetype":["aat:300008699"],"id":7023698,"name:xx":"Potter Run"}}
>>>>>>> 03f74aca74312dbeaf24d7e61306dd6a786dc3d0
