{
  "id": 7023698,
  "type": "Feature",
  "properties": {
    "tgn:hierarchy":[
        "tgn:7023698",
        "tgn:1000001",
        "tgn:7012149",
        "tgn:7007710",
        "tgn:7029392"
    ],
    "tgn:id":7023698,
    "tgn:name":"Potter Run",
    "tgn:placetype":[
        "aat:300008699"
    ]
},
  "bbox": [],
  "geometry": {"coordinates":[-78.15,41.0833],"type":"Point"}
}