{
  "id": 7399795,
  "type": "Feature",
  "properties": {
    "tgn:hierarchy":[
        "tgn:7399795",
        "tgn:1000001",
        "tgn:7005593",
        "tgn:7005560",
        "tgn:7029392"
    ],
    "tgn:id":7399795,
    "tgn:name":"Jag\u00fcey Colorado",
    "tgn:placetype":[
        "aat:300008347"
    ]
},
  "bbox": [],
  "geometry": {"coordinates":[-99.091667,21.175],"type":"Point"}
}