{
  "id": 2346152,
  "type": "Feature",
  "properties": {
    "tgn:hierarchy":[
        "tgn:2346152",
        "tgn:1000001",
        "tgn:7012149",
        "tgn:7013961",
        "tgn:7029392"
    ],
    "tgn:id":2346152,
    "tgn:name":"Gate Fork",
    "tgn:placetype":[
        "aat:300008699"
    ]
},
  "bbox": [],
  "geometry": {"coordinates":[-80.75,38.8333],"type":"Point"}
}