{
  "id": 2509223,
  "type": "Feature",
  "properties": {
    "tgn:hierarchy":[
        "tgn:2509223",
        "tgn:1000001",
        "tgn:7012149",
        "tgn:2001706",
        "tgn:7007708",
        "tgn:7029392"
    ],
    "tgn:id":2509223,
    "tgn:name":"Middle Fork North Fork Smith River",
    "tgn:placetype":[
        "aat:300008707"
    ]
},
  "bbox": [],
  "geometry": {"coordinates":[-123.75,43.8833],"type":"Point"}
}