{
  "id": 1121626,
  "type": "Feature",
  "properties": {
    "tgn:hierarchy":[
        "tgn:1121626",
        "tgn:1000051",
        "tgn:1000002",
        "tgn:7029392"
    ],
    "tgn:id":1121626,
    "tgn:name":"Balao Grande, R\u00edo",
    "tgn:placetype":[
        "aat:300008707"
    ]
},
  "bbox": [],
  "geometry": {"coordinates":[-79.845,-2.879],"type":"Point"}
}