{
  "id": 2566305,
  "type": "Feature",
  "properties": {
    "tgn:hierarchy":[
        "tgn:2566305",
        "tgn:1000001",
        "tgn:7006451",
        "tgn:7012149",
        "tgn:2000098",
        "tgn:7029392"
    ],
    "tgn:id":2566305,
    "tgn:name":"Palmtree Wash",
    "tgn:placetype":[
        "aat:300008699"
    ]
},
  "bbox": [],
  "geometry": {"coordinates":[-114.2667,34.5167],"type":"Point"}
}