{
  "id": 7142846,
  "type": "Feature",
  "properties": {
    "tgn:hierarchy":[
        "tgn:7142846",
        "tgn:1000003",
        "tgn:7003687",
        "tgn:7000084",
        "tgn:7029392"
    ],
    "tgn:id":7142846,
    "tgn:name":"Vorwerk Lindenberg",
    "tgn:placetype":[
        "aat:300000206"
    ]
},
  "bbox": [],
  "geometry": {"coordinates":[11.566667,51.15],"type":"Point"}
}