{
  "id": 2432043,
  "type": "Feature",
  "properties": {
    "tgn:hierarchy":[
        "tgn:2432043",
        "tgn:7023902",
        "tgn:1000001",
        "tgn:7012149",
        "tgn:7007249",
        "tgn:7029392"
    ],
    "tgn:id":2432043,
    "tgn:name":"Kawaikalia Gulch",
    "tgn:placetype":[
        "aat:300008761"
    ]
},
  "bbox": [],
  "geometry": {"coordinates":[-155.5333,20.0667],"type":"Point"}
}