{
  "id": 1096571,
  "type": "Feature",
  "properties": {
    "tgn:hierarchy":[
        "tgn:1096571",
        "tgn:7000490",
        "tgn:1000006",
        "tgn:7006238",
        "tgn:7029392"
    ],
    "tgn:id":1096571,
    "tgn:name":"Clunes",
    "tgn:placetype":[
        "aat:300008347"
    ]
},
  "bbox": [],
  "geometry": {"coordinates":[143.85,-37.3333],"type":"Point"}
}