{
  "id": 7231708,
  "type": "Feature",
  "properties": {
    "tgn:hierarchy":[
        "tgn:7231708",
        "tgn:7011163",
        "tgn:7002674",
        "tgn:1000003",
        "tgn:1000074",
        "tgn:7029392"
    ],
    "tgn:id":7231708,
    "tgn:name":"Kerame\u00eda",
    "tgn:placetype":[
        "aat:300008347"
    ]
},
  "bbox": [],
  "geometry": {"coordinates":[26.416667,39.133333],"type":"Point"}
}