{
  "id": 2053039,
  "type": "Feature",
  "properties": {
    "tgn:hierarchy":[
        "tgn:2053039",
        "tgn:1000001",
        "tgn:7012149",
        "tgn:2000963",
        "tgn:7007520",
        "tgn:7029392"
    ],
    "tgn:id":2053039,
    "tgn:name":"Pori",
    "tgn:placetype":[
        "aat:300387016"
    ]
},
  "bbox": [],
  "geometry": {"coordinates":[-88.95,46.6667],"type":"Point"}
}