{
  "id": 7272764,
  "type": "Feature",
  "properties": {
    "tgn:hierarchy":[
        "tgn:7272764",
        "tgn:7003619",
        "tgn:1000003",
        "tgn:7016845",
        "tgn:7029392"
    ],
    "tgn:id":7272764,
    "tgn:name:nl":"Voorstondensche Beek",
    "tgn:placetype":[
        "aat:300008699"
    ]
},
  "bbox": [],
  "geometry": {"coordinates":[6.166667,52.133333],"type":"Point"}
}