{
  "id": 2243847,
  "type": "Feature",
  "properties": {
    "tgn:hierarchy":[
        "tgn:2243847",
        "tgn:1000001",
        "tgn:7012149",
        "tgn:2000472",
        "tgn:7007250",
        "tgn:7029392"
    ],
    "tgn:id":2243847,
    "tgn:name":"Cleveland Irrigation Canal",
    "tgn:placetype":[
        "aat:300006075"
    ]
},
  "bbox": [],
  "geometry": {"coordinates":[-111.7333,42.3333],"type":"Point"}
}