{
  "id": 2708304,
  "type": "Feature",
  "properties": {
    "tgn:hierarchy":[
        "tgn:2708304",
        "tgn:2001168",
        "tgn:1000001",
        "tgn:7012149",
        "tgn:7007523",
        "tgn:7029392"
    ],
    "tgn:id":2708304,
    "tgn:name":"Sybert Lake - Lower",
    "tgn:placetype":[
        "aat:300006191"
    ]
},
  "bbox": [],
  "geometry": {"coordinates":[-94.8333,40.0667],"type":"Point"}
}