{
  "id": 1044669,
  "type": "Feature",
  "properties": {
    "tgn:hierarchy":[
        "tgn:1044669",
        "tgn:7003163",
        "tgn:1000003",
        "tgn:7009760",
        "tgn:1000080",
        "tgn:7029392"
    ],
    "tgn:id":1044669,
    "tgn:name":"Fornacelle",
    "tgn:placetype":[
        "aat:300008347"
    ]
},
  "bbox": [],
  "geometry": {"coordinates":[11.033333,43.933333],"type":"Point"}
}