{
  "id": 1101144,
  "type": "Feature",
  "properties": {
    "tgn:hierarchy":[
        "tgn:1101144",
        "tgn:7005685",
        "tgn:1000001",
        "tgn:7005734",
        "tgn:7029392"
    ],
    "tgn:id":1101144,
    "tgn:name":"Jenpeg Dam",
    "tgn:placetype":[
        "aat:300006084"
    ]
},
  "bbox": [],
  "geometry": {"coordinates":[-98.0333,54.55],"type":"Point"}
}