{
  "id": 2555926,
  "type": "Feature",
  "properties": {
    "tgn:hierarchy":[
        "tgn:2555926",
        "tgn:1000001",
        "tgn:7012149",
        "tgn:2001691",
        "tgn:7007707",
        "tgn:7029392"
    ],
    "tgn:id":2555926,
    "tgn:name":"Oil City",
    "tgn:placetype":[
        "aat:300008347"
    ]
},
  "bbox": [],
  "geometry": {"coordinates":[-98.0667,34.5167],"type":"Point"}
}