{
  "id": 2336592,
  "type": "Feature",
  "properties": {
    "tgn:hierarchy":[
        "tgn:2336592",
        "tgn:1000001",
        "tgn:2001746",
        "tgn:7012149",
        "tgn:7007712",
        "tgn:7029392"
    ],
    "tgn:id":2336592,
    "tgn:name":"Four Mile Creek",
    "tgn:placetype":[
        "aat:300008706"
    ]
},
  "bbox": [],
  "geometry": {"coordinates":[-79.2833,33.4333],"type":"Point"}
}