{
  "id": 2371030,
  "type": "Feature",
  "properties": {
    "tgn:hierarchy":[
        "tgn:2371030",
        "tgn:7006450",
        "tgn:1000001",
        "tgn:7012149",
        "tgn:7030574",
        "tgn:7029392"
    ],
    "tgn:id":2371030,
    "tgn:name":"Haenke Glacier",
    "tgn:placetype":[
        "aat:300008835"
    ]
},
  "bbox": [],
  "geometry": {"coordinates":[-139.6333,60.0667],"type":"Point"}
}