<<<<<<< HEAD
{
  "id": 2331265,
  "type": "Feature",
  "properties": {
    "tgn:hierarchy":[
        "tgn:2331265",
        "tgn:1000001",
        "tgn:7012149",
        "tgn:2001887",
        "tgn:7007825",
        "tgn:7029392"
    ],
    "tgn:id":2331265,
    "tgn:name":"Flat Woods",
    "tgn:placetype":[
        "aat:300055621"
    ]
},
  "bbox": [],
  "geometry": {"coordinates":[-87.4833,35.5167],"type":"Point"}
}
=======
{"geometry":{"type":"Point","coordinates":[-87.483300,35.516700]},"type":"Feature","properties":{"hierarchy":["tgn:2331265","tgn:1000001","tgn:7012149","tgn:2001887","tgn:7007825","tgn:7029392"],"placetype":["aat:300055621"],"id":2331265,"name:xx":"Flat Woods"}}
>>>>>>> 03f74aca74312dbeaf24d7e61306dd6a786dc3d0
