{
  "id": 2297948,
  "type": "Feature",
  "properties": {
    "tgn:hierarchy":[
        "tgn:2297948",
        "tgn:1000001",
        "tgn:7012149",
        "tgn:2002129",
        "tgn:7007827",
        "tgn:7029392"
    ],
    "tgn:id":2297948,
    "tgn:name":"Dry Hollow Creek",
    "tgn:placetype":[
        "aat:300008706"
    ]
},
  "bbox": [],
  "geometry": {"coordinates":[-111.75,41.2833],"type":"Point"}
}