{
  "id": 7315767,
  "type": "Feature",
  "properties": {
    "tgn:hierarchy":[
        "tgn:7315767",
        "tgn:1001708",
        "tgn:1000049",
        "tgn:1000002",
        "tgn:7029392"
    ],
    "tgn:id":7315767,
    "tgn:name":"Cepo, Quebrada del",
    "tgn:placetype":[
        "aat:300008699"
    ]
},
  "bbox": [],
  "geometry": {"coordinates":[-70.916667,-33.233333],"type":"Point"}
}