{
  "id": 2258419,
  "type": "Feature",
  "properties": {
    "tgn:hierarchy":[
        "tgn:2258419",
        "tgn:1000001",
        "tgn:7012149",
        "tgn:1002877",
        "tgn:7007706",
        "tgn:7029392"
    ],
    "tgn:id":2258419,
    "tgn:name":"Cotton Eye Hollow",
    "tgn:placetype":[
        "aat:300008761"
    ]
},
  "bbox": [],
  "geometry": {"coordinates":[-83.2167,38.7167],"type":"Point"}
}