{
  "id": 7260806,
  "type": "Feature",
  "properties": {
    "tgn:concordances":{
        "gn:id":"2755936"
    },
    "tgn:hierarchy":[
        "tgn:7260806",
        "tgn:7003616",
        "tgn:1000003",
        "tgn:7016845",
        "tgn:7029392"
    ],
    "tgn:id":7260806,
    "tgn:name:nl":"Ezumazijl",
    "tgn:placetype":[
        "aat:300008347"
    ]
},
  "bbox": [],
  "geometry": {"coordinates":[6.15,53.366667],"type":"Point"}
}