{
  "id": 7529300,
  "type": "Feature",
  "properties": {
    "tgn:hierarchy":[
        "tgn:7529300",
        "tgn:7001242",
        "tgn:7016833",
        "tgn:7001336",
        "tgn:7029392"
    ],
    "tgn:id":7529300,
    "tgn:name:en":"Umm Sar\u012br, W\u0101d\u012b",
    "tgn:placetype":[
        "aat:300379998"
    ]
},
  "bbox": [],
  "geometry": {"coordinates":[34.160567,29.398968],"type":"Point"}
}