{
  "id": 2604077,
  "type": "Feature",
  "properties": {
    "tgn:hierarchy":[
        "tgn:2604077",
        "tgn:1002134",
        "tgn:1000001",
        "tgn:7012149",
        "tgn:7007251",
        "tgn:7029392"
    ],
    "tgn:id":2604077,
    "tgn:name":"Quinsippi Island",
    "tgn:placetype":[
        "aat:300008791"
    ]
},
  "bbox": [],
  "geometry": {"coordinates":[-91.4167,39.9333],"type":"Point"}
}