{
  "id": 1004701,
  "type": "Feature",
  "properties": {
    "tgn:hierarchy":[
        "tgn:1004701",
        "tgn:7010420",
        "tgn:1000003",
        "tgn:7002795",
        "tgn:1000095",
        "tgn:7010413",
        "tgn:7029392"
    ],
    "tgn:id":1004701,
    "tgn:name":"Hortaleza",
    "tgn:placetype":[
        "aat:300000745"
    ]
},
  "bbox": [],
  "geometry": {"coordinates":[-3.6333,40.4667],"type":"Point"}
}