{
  "id": 7118911,
  "type": "Feature",
  "properties": {
    "tgn:hierarchy":[
        "tgn:7118911",
        "tgn:1000003",
        "tgn:7003688",
        "tgn:7000084",
        "tgn:7029392"
    ],
    "tgn:id":7118911,
    "tgn:name":"Pielstoft",
    "tgn:placetype":[
        "aat:300000206"
    ]
},
  "bbox": [],
  "geometry": {"coordinates":[9.95,54.766667],"type":"Point"}
}