<<<<<<< HEAD
{
  "id": 7118911,
  "type": "Feature",
  "properties": {
    "tgn:hierarchy":[
        "tgn:7118911",
        "tgn:1000003",
        "tgn:7003688",
        "tgn:7000084",
        "tgn:7029392"
    ],
    "tgn:id":7118911,
    "tgn:name":"Pielstoft",
    "tgn:placetype":[
        "aat:300000206"
    ]
},
  "bbox": [],
  "geometry": {"coordinates":[9.95,54.766667],"type":"Point"}
}
=======
{"geometry":{"type":"Point","coordinates":[9.950000,54.766667]},"type":"Feature","properties":{"hierarchy":["tgn:7118911","tgn:1000003","tgn:7003688","tgn:7000084","tgn:7029392"],"placetype":["aat:300000206"],"id":7118911,"name:xx":"Pielstoft"}}
>>>>>>> 03f74aca74312dbeaf24d7e61306dd6a786dc3d0
