{
  "id": 7351377,
  "type": "Feature",
  "properties": {
    "tgn:hierarchy":[
        "tgn:7351377",
        "tgn:1000001",
        "tgn:7005589",
        "tgn:7005560",
        "tgn:7029392"
    ],
    "tgn:id":7351377,
    "tgn:name":"Banco, Sierra del",
    "tgn:placetype":[
        "aat:300266640"
    ]
},
  "bbox": [],
  "geometry": {"coordinates":[-100.25,25.133333],"type":"Point"}
}