{
  "id": 2457377,
  "type": "Feature",
  "properties": {
    "tgn:hierarchy":[
        "tgn:2457377",
        "tgn:1000001",
        "tgn:7012149",
        "tgn:2000841",
        "tgn:7007255",
        "tgn:7029392"
    ],
    "tgn:id":2457377,
    "tgn:name":"Little Lily Creek",
    "tgn:placetype":[
        "aat:300008706"
    ]
},
  "bbox": [],
  "geometry": {"coordinates":[-85.05,37.0333],"type":"Point"}
}