{
  "id": 2674815,
  "type": "Feature",
  "properties": {
    "tgn:hierarchy":[
        "tgn:2674815",
        "tgn:1000001",
        "tgn:7012149",
        "tgn:2001719",
        "tgn:7007708",
        "tgn:7029392"
    ],
    "tgn:id":2674815,
    "tgn:name":"Social Ridge",
    "tgn:placetype":[
        "aat:300266640"
    ]
},
  "bbox": [],
  "geometry": {"coordinates":[-119.65,45.2667],"type":"Point"}
}