{
  "id": 7088827,
  "type": "Feature",
  "properties": {
    "tgn:hierarchy":[
        "tgn:7088827",
        "tgn:1000003",
        "tgn:7003676",
        "tgn:7000084",
        "tgn:7029392"
    ],
    "tgn:id":7088827,
    "tgn:name":"Wahlde",
    "tgn:placetype":[
        "aat:300008347"
    ]
},
  "bbox": [],
  "geometry": {"coordinates":[8.116667,52.533333],"type":"Point"}
}