<<<<<<< HEAD
{
  "id": 2402662,
  "type": "Feature",
  "properties": {
    "tgn:hierarchy":[
        "tgn:2402662",
        "tgn:1000001",
        "tgn:2001786",
        "tgn:7012149",
        "tgn:7007713",
        "tgn:7029392"
    ],
    "tgn:id":2402662,
    "tgn:name":"Hot Shot Mine",
    "tgn:placetype":[
        "aat:300000390"
    ]
},
  "bbox": [],
  "geometry": {"coordinates":[-103.5,43.7333],"type":"Point"}
}
=======
{"geometry":{"type":"Point","coordinates":[-103.500000,43.733300]},"type":"Feature","properties":{"hierarchy":["tgn:2402662","tgn:1000001","tgn:2001786","tgn:7012149","tgn:7007713","tgn:7029392"],"placetype":["aat:300000390"],"id":2402662,"name:xx":"Hot Shot Mine"}}
>>>>>>> 03f74aca74312dbeaf24d7e61306dd6a786dc3d0
