{
  "id": 1122246,
  "type": "Feature",
  "properties": {
    "tgn:hierarchy":[
        "tgn:1122246",
        "tgn:7001199",
        "tgn:7003492",
        "tgn:1000003",
        "tgn:1000078",
        "tgn:7029392"
    ],
    "tgn:id":1122246,
    "tgn:name":"Brosna, River",
    "tgn:placetype":[
        "aat:300008707"
    ]
},
  "bbox": [],
  "geometry": {"coordinates":[-7.966,53.217],"type":"Point"}
}