{
  "id": 2616379,
  "type": "Feature",
  "properties": {
    "tgn:hierarchy":[
        "tgn:2616379",
        "tgn:1000001",
        "tgn:7012149",
        "tgn:1003038",
        "tgn:7007517",
        "tgn:7029392"
    ],
    "tgn:id":2616379,
    "tgn:name":"Rice City Pond",
    "tgn:placetype":[
        "aat:300006191"
    ]
},
  "bbox": [],
  "geometry": {"coordinates":[-71.6167,42.0833],"type":"Point"}
}