{
  "id": 7467098,
  "type": "Feature",
  "properties": {
    "tgn:hierarchy":[
        "tgn:7467098",
        "tgn:7002444",
        "tgn:1000003",
        "tgn:7008082",
        "tgn:7008591",
        "tgn:7029392"
    ],
    "tgn:id":7467098,
    "tgn:name:en":"Alvie",
    "tgn:placetype":[
        "aat:300008347"
    ]
},
  "bbox": [],
  "geometry": {"coordinates":[-3.866667,57.15],"type":"Point"}
}