{
  "id": 2310117,
  "type": "Feature",
  "properties": {
    "tgn:hierarchy":[
        "tgn:2310117",
        "tgn:1000001",
        "tgn:7012149",
        "tgn:1002597",
        "tgn:7007826",
        "tgn:7029392"
    ],
    "tgn:id":2310117,
    "tgn:name":"Eaton Branch",
    "tgn:placetype":[
        "aat:300008699"
    ]
},
  "bbox": [],
  "geometry": {"coordinates":[-96.5667,31.4333],"type":"Point"}
}