{
  "id": 7275922,
  "type": "Feature",
  "properties": {
    "tgn:hierarchy":[
        "tgn:7275922",
        "tgn:7016598",
        "tgn:1000049",
        "tgn:1000002",
        "tgn:7029392"
    ],
    "tgn:id":7275922,
    "tgn:name":"Tetas, Cerro",
    "tgn:placetype":[
        "aat:300008795"
    ]
},
  "bbox": [],
  "geometry": {"coordinates":[-69.833333,-21.733333],"type":"Point"}
}