{
  "id": 7522074,
  "type": "Feature",
  "properties": {
    "tgn:hierarchy":[
        "tgn:7522074",
        "tgn:7001242",
        "tgn:7016833",
        "tgn:1001225",
        "tgn:7029392"
    ],
    "tgn:id":7522074,
    "tgn:name:en":"Al Ghaww\u0101b\u012bn",
    "tgn:placetype":[
        "aat:300008347"
    ]
},
  "bbox": [],
  "geometry": {"coordinates":[31.759522,31.331115],"type":"Point"}
}