{
  "id": 7500383,
  "type": "Feature",
  "properties": {
    "tgn:hierarchy":[
        "tgn:7500383",
        "tgn:1000004",
        "tgn:7001009",
        "tgn:1000141",
        "tgn:7029392"
    ],
    "tgn:id":7500383,
    "tgn:name":"Xiaxincuo",
    "tgn:placetype":[
        "aat:300008347"
    ]
},
  "bbox": [],
  "geometry": {"coordinates":[120.621328,24.2112],"type":"Point"}
}