{
  "id": 1070299,
  "type": "Feature",
  "properties": {
    "tgn:hierarchy":[
        "tgn:1070299",
        "tgn:1000004",
        "tgn:1000960",
        "tgn:1000111",
        "tgn:7029392"
    ],
    "tgn:id":1070299,
    "tgn:name":"Majiasi",
    "tgn:placetype":[
        "aat:300008347"
    ]
},
  "bbox": [],
  "geometry": {"coordinates":[117.0833,39.05],"type":"Point"}
}