{
  "id": 2161441,
  "type": "Feature",
  "properties": {
    "tgn:hierarchy":[
        "tgn:2161441",
        "tgn:1000001",
        "tgn:7006451",
        "tgn:7012149",
        "tgn:2000103",
        "tgn:7029392"
    ],
    "tgn:id":2161441,
    "tgn:name":"Bell Rock Spring",
    "tgn:placetype":[
        "aat:300008697"
    ]
},
  "bbox": [],
  "geometry": {"coordinates":[-111.75,34.7833],"type":"Point"}
}