{
  "id": 7003394,
  "type": "Feature",
  "properties": {
    "tgn:hierarchy":[
        "tgn:7003394",
        "tgn:7003025",
        "tgn:1000003",
        "tgn:1000062",
        "tgn:7029392"
    ],
    "tgn:id":7003394,
    "tgn:name":"Gm\u00fcnd",
    "tgn:placetype":[
        "aat:300008347"
    ]
},
  "bbox": [],
  "geometry": {"coordinates":[14.9833,48.7833],"type":"Point"}
}