{
  "id": 2725755,
  "type": "Feature",
  "properties": {
    "tgn:hierarchy":[
        "tgn:2725755",
        "tgn:1000001",
        "tgn:2001810",
        "tgn:7012149",
        "tgn:7007713",
        "tgn:7029392"
    ],
    "tgn:id":2725755,
    "tgn:name":"Tornado Mine",
    "tgn:placetype":[
        "aat:300000390"
    ]
},
  "bbox": [],
  "geometry": {"coordinates":[-103.8167,44.3333],"type":"Point"}
}