<<<<<<< HEAD
{
  "id": 7176646,
  "type": "Feature",
  "properties": {
    "tgn:hierarchy":[
        "tgn:7176646",
        "tgn:1000003",
        "tgn:7003685",
        "tgn:7000084",
        "tgn:7029392"
    ],
    "tgn:id":7176646,
    "tgn:name":"Hals-Bach",
    "tgn:placetype":[
        "aat:300008699"
    ]
},
  "bbox": [],
  "geometry": {"coordinates":[12.766667,50.5],"type":"Point"}
}
=======
{"geometry":{"type":"Point","coordinates":[12.766667,50.500000]},"type":"Feature","properties":{"hierarchy":["tgn:7176646","tgn:1000003","tgn:7003685","tgn:7000084","tgn:7029392"],"placetype":["aat:300008699"],"id":7176646,"name:xx":"Hals-Bach"}}
>>>>>>> 03f74aca74312dbeaf24d7e61306dd6a786dc3d0
