{
  "id": 7553452,
  "type": "Feature",
  "properties": {
    "tgn:hierarchy":[
        "tgn:7553452",
        "tgn:1000004",
        "tgn:7000198",
        "tgn:1001895",
        "tgn:7029392"
    ],
    "tgn:id":7553452,
    "tgn:name:en":"Municipal Colony",
    "tgn:placetype":[
        "aat:300055621"
    ]
},
  "bbox": [],
  "geometry": {"coordinates":[72.916667,19.05],"type":"Point"}
}