{
  "id": 2555798,
  "type": "Feature",
  "properties": {
    "tgn:hierarchy":[
        "tgn:2555798",
        "tgn:1000001",
        "tgn:7021626",
        "tgn:7012149",
        "tgn:2001618",
        "tgn:7007706",
        "tgn:7029392"
    ],
    "tgn:id":2555798,
    "tgn:name":"Ohio Power Company Pond 9515-019",
    "tgn:placetype":[
        "aat:300006191"
    ]
},
  "bbox": [],
  "geometry": {"coordinates":[-81.7333,39.7333],"type":"Point"}
}