{
  "id": 7334806,
  "type": "Feature",
  "properties": {
    "tgn:hierarchy":[
        "tgn:7334806",
        "tgn:7002829",
        "tgn:1000003",
        "tgn:7002786",
        "tgn:1000095",
        "tgn:7029392"
    ],
    "tgn:id":7334806,
    "tgn:name":"Gra\u00f1anova",
    "tgn:placetype":[
        "aat:300008347"
    ]
},
  "bbox": [],
  "geometry": {"coordinates":[-7.266667,43.216667],"type":"Point"}
}