{
  "id": 2511985,
  "type": "Feature",
  "properties": {
    "tgn:hierarchy":[
        "tgn:2511985",
        "tgn:1000001",
        "tgn:7012149",
        "tgn:2000905",
        "tgn:7007256",
        "tgn:7029392"
    ],
    "tgn:id":2511985,
    "tgn:name":"Mill Bayou",
    "tgn:placetype":[
        "aat:300008699"
    ]
},
  "bbox": [],
  "geometry": {"coordinates":[-89.6667,30.25],"type":"Point"}
}