{
  "id": 7592693,
  "type": "Feature",
  "properties": {
    "tgn:hierarchy":[
        "tgn:7592693",
        "tgn:1000004",
        "tgn:7000198",
        "tgn:7000799",
        "tgn:7029392"
    ],
    "tgn:id":7592693,
    "tgn:name:en":"T\u0101nda",
    "tgn:placetype":[
        "aat:300008347"
    ]
},
  "bbox": [],
  "geometry": {"coordinates":[74.86348,32.899288],"type":"Point"}
}