{
  "id": 1042621,
  "type": "Feature",
  "properties": {
    "tgn:hierarchy":[
        "tgn:1042621",
        "tgn:7003501",
        "tgn:7003478",
        "tgn:1000003",
        "tgn:1000078",
        "tgn:7029392"
    ],
    "tgn:id":1042621,
    "tgn:name":"Ballyhaise",
    "tgn:placetype":[
        "aat:300008347"
    ]
},
  "bbox": [],
  "geometry": {"coordinates":[-7.3167,54.05],"type":"Point"}
}