{
  "id": 2073120,
  "type": "Feature",
  "properties": {
    "tgn:hierarchy":[
        "tgn:2073120",
        "tgn:1000001",
        "tgn:7012149",
        "tgn:1002423",
        "tgn:7007568",
        "tgn:7029392"
    ],
    "tgn:id":2073120,
    "tgn:name":"West Jewett",
    "tgn:placetype":[
        "aat:300008347",
        "aat:300387210"
    ]
},
  "bbox": [],
  "geometry": {"coordinates":[-74.3167,42.25],"type":"Point"}
}