{
  "id": 7593161,
  "type": "Feature",
  "properties": {
    "tgn:hierarchy":[
        "tgn:7593161",
        "tgn:1000003",
        "tgn:7003142",
        "tgn:7003236",
        "tgn:1000080",
        "tgn:7029392"
    ],
    "tgn:id":7593161,
    "tgn:name":"Coreglia Ligure",
    "tgn:placetype":[
        "aat:300008347"
    ]
},
  "bbox": [],
  "geometry": {"coordinates":[9.267,44.391],"type":"Point"}
}