<<<<<<< HEAD
{
  "id": 2409849,
  "type": "Feature",
  "properties": {
    "tgn:hierarchy":[
        "tgn:2409849",
        "tgn:1000001",
        "tgn:7012149",
        "tgn:2001420",
        "tgn:7007526",
        "tgn:7029392"
    ],
    "tgn:id":2409849,
    "tgn:name":"Illipah",
    "tgn:placetype":[
        "aat:300008347"
    ]
},
  "bbox": [],
  "geometry": {"coordinates":[-115.3167,39.35],"type":"Point"}
}
=======
{"geometry":{"type":"Point","coordinates":[-115.316700,39.350000]},"type":"Feature","properties":{"hierarchy":["tgn:2409849","tgn:1000001","tgn:7012149","tgn:2001420","tgn:7007526","tgn:7029392"],"placetype":["aat:300008347"],"id":2409849,"name:xx":"Illipah"}}
>>>>>>> 03f74aca74312dbeaf24d7e61306dd6a786dc3d0
