{
  "id": 1053883,
  "type": "Feature",
  "properties": {
    "tgn:hierarchy":[
        "tgn:1053883",
        "tgn:1000004",
        "tgn:7011590",
        "tgn:7018214",
        "tgn:7002435",
        "tgn:7029392"
    ],
    "tgn:id":1053883,
    "tgn:name":"Filatova Gora",
    "tgn:placetype":[
        "aat:300008347"
    ]
},
  "bbox": [],
  "geometry": {"coordinates":[28.1667,57.6667],"type":"Point"}
}