{
  "id": 2526414,
  "type": "Feature",
  "properties": {
    "tgn:hierarchy":[
        "tgn:2526414",
        "tgn:1000001",
        "tgn:1002235",
        "tgn:7012149",
        "tgn:7007919",
        "tgn:7029392"
    ],
    "tgn:id":2526414,
    "tgn:name":"Moss Neck",
    "tgn:placetype":[
        "aat:300008850"
    ]
},
  "bbox": [],
  "geometry": {"coordinates":[-77.2833,38.2333],"type":"Point"}
}