{
  "id": 2117857,
  "type": "Feature",
  "properties": {
    "tgn:hierarchy":[
        "tgn:2117857",
        "tgn:1000001",
        "tgn:2002261",
        "tgn:7012149",
        "tgn:7013961",
        "tgn:7029392"
    ],
    "tgn:id":2117857,
    "tgn:name":"Collinsdale",
    "tgn:placetype":[
        "aat:300008347",
        "aat:300387210"
    ]
},
  "bbox": [],
  "geometry": {"coordinates":[-81.35,38.0333],"type":"Point"}
}