{
  "id": 2770848,
  "type": "Feature",
  "properties": {
    "tgn:hierarchy":[
        "tgn:2770848",
        "tgn:1000001",
        "tgn:7012149",
        "tgn:2001716",
        "tgn:7007708",
        "tgn:7029392"
    ],
    "tgn:id":2770848,
    "tgn:name":"Wildcat Creek",
    "tgn:placetype":[
        "aat:300008706"
    ]
},
  "bbox": [],
  "geometry": {"coordinates":[-123.9667,44.2333],"type":"Point"}
}