{
  "id": 7053487,
  "type": "Feature",
  "properties": {
    "tgn:hierarchy":[
        "tgn:7053487",
        "tgn:1003432",
        "tgn:1000003",
        "tgn:7003240",
        "tgn:1000080",
        "tgn:7029392"
    ],
    "tgn:id":7053487,
    "tgn:name":"Paradisi",
    "tgn:placetype":[
        "aat:300008347"
    ]
},
  "bbox": [],
  "geometry": {"coordinates":[13.35,42.966667],"type":"Point"}
}