<<<<<<< HEAD
{
  "id": 7053487,
  "type": "Feature",
  "properties": {
    "tgn:hierarchy":[
        "tgn:7053487",
        "tgn:1003432",
        "tgn:1000003",
        "tgn:7003240",
        "tgn:1000080",
        "tgn:7029392"
    ],
    "tgn:id":7053487,
    "tgn:name":"Paradisi",
    "tgn:placetype":[
        "aat:300008347"
    ]
},
  "bbox": [],
  "geometry": {"coordinates":[13.35,42.966667],"type":"Point"}
}
=======
{"geometry":{"type":"Point","coordinates":[13.350000,42.966667]},"type":"Feature","properties":{"hierarchy":["tgn:7053487","tgn:1003432","tgn:1000003","tgn:7003240","tgn:1000080","tgn:7029392"],"placetype":["aat:300008347"],"id":7053487,"name:xx":"Paradisi"}}
>>>>>>> 03f74aca74312dbeaf24d7e61306dd6a786dc3d0
