{
  "id": 1077738,
  "type": "Feature",
  "properties": {
    "tgn:hierarchy":[
        "tgn:1077738",
        "tgn:1000004",
        "tgn:1001339",
        "tgn:1000116",
        "tgn:7029392"
    ],
    "tgn:id":1077738,
    "tgn:name":"Janlohong",
    "tgn:placetype":[
        "aat:300008347"
    ]
},
  "bbox": [],
  "geometry": {"coordinates":[117.05,2.25],"type":"Point"}
}