{
  "id": 7310400,
  "type": "Feature",
  "properties": {
    "tgn:hierarchy":[
        "tgn:7310400",
        "tgn:1001699",
        "tgn:1000049",
        "tgn:1000002",
        "tgn:7029392"
    ],
    "tgn:id":7310400,
    "tgn:name":"Nihuel, Islote",
    "tgn:placetype":[
        "aat:300008791"
    ]
},
  "bbox": [],
  "geometry": {"coordinates":[-72.925833,-42.615833],"type":"Point"}
}