{
  "id": 2550353,
  "type": "Feature",
  "properties": {
    "tgn:hierarchy":[
        "tgn:2550353",
        "tgn:1000001",
        "tgn:7012149",
        "tgn:7021313",
        "tgn:7007521",
        "tgn:7029392"
    ],
    "tgn:id":2550353,
    "tgn:name":"Northwest Angle Inlet",
    "tgn:placetype":[
        "aat:300132316"
    ]
},
  "bbox": [],
  "geometry": {"coordinates":[-95.05,49.35],"type":"Point"}
}