{
  "id": 2772596,
  "type": "Feature",
  "properties": {
    "tgn:hierarchy":[
        "tgn:2772596",
        "tgn:1000001",
        "tgn:7012149",
        "tgn:7007248",
        "tgn:7029392"
    ],
    "tgn:id":2772596,
    "tgn:name":"Williams Creek",
    "tgn:placetype":[
        "aat:300008706"
    ]
},
  "bbox": [],
  "geometry": {"coordinates":[-84.7833,31.55],"type":"Point"}
}