{
  "id": 7299695,
  "type": "Feature",
  "properties": {
    "tgn:hierarchy":[
        "tgn:7299695",
        "tgn:7002849",
        "tgn:1000003",
        "tgn:7009604",
        "tgn:1000095",
        "tgn:7029392"
    ],
    "tgn:id":7299695,
    "tgn:name":"Udondo, R\u00edo",
    "tgn:placetype":[
        "aat:300008699"
    ]
},
  "bbox": [],
  "geometry": {"coordinates":[-2.981909,43.320467],"type":"Point"}
}