<<<<<<< HEAD
{
  "id": 2256599,
  "type": "Feature",
  "properties": {
    "tgn:hierarchy":[
        "tgn:2256599",
        "tgn:1000001",
        "tgn:7012149",
        "tgn:2000230",
        "tgn:7007158",
        "tgn:7029392"
    ],
    "tgn:id":2256599,
    "tgn:name":"Corcoran Peak",
    "tgn:placetype":[
        "aat:300008798"
    ]
},
  "bbox": [],
  "geometry": {"coordinates":[-108.5,39.3],"type":"Point"}
}
=======
{"geometry":{"type":"Point","coordinates":[-108.500000,39.300000]},"type":"Feature","properties":{"hierarchy":["tgn:2256599","tgn:1000001","tgn:7012149","tgn:2000230","tgn:7007158","tgn:7029392"],"placetype":["aat:300008798"],"id":2256599,"name:xx":"Corcoran Peak"}}
>>>>>>> 03f74aca74312dbeaf24d7e61306dd6a786dc3d0
