{
  "id": 2496924,
  "type": "Feature",
  "properties": {
    "tgn:hierarchy":[
        "tgn:2496924",
        "tgn:1000001",
        "tgn:7012149",
        "tgn:2000960",
        "tgn:7007520",
        "tgn:7029392"
    ],
    "tgn:id":2496924,
    "tgn:name":"Maud Lake",
    "tgn:placetype":[
        "aat:300008680"
    ]
},
  "bbox": [],
  "geometry": {"coordinates":[-89.3667,46.25],"type":"Point"}
}