{
  "id": 2125725,
  "type": "Feature",
  "properties": {
    "tgn:hierarchy":[
        "tgn:2125725",
        "tgn:7002659",
        "tgn:1000001",
        "tgn:7012149",
        "tgn:2000059",
        "tgn:7029392"
    ],
    "tgn:id":2125725,
    "tgn:name":"Adams Creek",
    "tgn:placetype":[
        "aat:300008706"
    ]
},
  "bbox": [],
  "geometry": {"coordinates":[-88.0167,32.4833],"type":"Point"}
}