{
  "id": 7568991,
  "type": "Feature",
  "properties": {
    "tgn:hierarchy":[
        "tgn:7568991",
        "tgn:1000004",
        "tgn:7000198",
        "tgn:1001996",
        "tgn:7029392"
    ],
    "tgn:id":7568991,
    "tgn:name:en":"Nay\u0101wag Protected Forest",
    "tgn:placetype":[
        "aat:300008863"
    ]
},
  "bbox": [],
  "geometry": {"coordinates":[77.102222,31.148611],"type":"Point"}
}