<<<<<<< HEAD
{
  "id": 7054146,
  "type": "Feature",
  "properties": {
    "tgn:hierarchy":[
        "tgn:7054146",
        "tgn:7003163",
        "tgn:1000003",
        "tgn:7009760",
        "tgn:1000080",
        "tgn:7029392"
    ],
    "tgn:id":7054146,
    "tgn:name":"Luia",
    "tgn:placetype":[
        "aat:300008347"
    ]
},
  "bbox": [],
  "geometry": {"coordinates":[11.1,43.583333],"type":"Point"}
}
=======
{"geometry":{"type":"Point","coordinates":[11.100000,43.583333]},"type":"Feature","properties":{"hierarchy":["tgn:7054146","tgn:7003163","tgn:1000003","tgn:7009760","tgn:1000080","tgn:7029392"],"placetype":["aat:300008347"],"id":7054146,"name:xx":"Luia"}}
>>>>>>> 03f74aca74312dbeaf24d7e61306dd6a786dc3d0
