{
  "id": 2564955,
  "type": "Feature",
  "properties": {
    "tgn:hierarchy":[
        "tgn:2564955",
        "tgn:1000001",
        "tgn:7012149",
        "tgn:2000853",
        "tgn:7007255",
        "tgn:7029392"
    ],
    "tgn:id":2564955,
    "tgn:name":"Page Branch",
    "tgn:placetype":[
        "aat:300008699"
    ]
},
  "bbox": [],
  "geometry": {"coordinates":[-83.5833,37.7333],"type":"Point"}
}