{
  "id": 2117361,
  "type": "Feature",
  "properties": {
    "tgn:hierarchy":[
        "tgn:2117361",
        "tgn:1000001",
        "tgn:7012149",
        "tgn:2002266",
        "tgn:7013961",
        "tgn:7029392"
    ],
    "tgn:id":2117361,
    "tgn:name":"Basore",
    "tgn:placetype":[
        "aat:300008347",
        "aat:300387210"
    ]
},
  "bbox": [],
  "geometry": {"coordinates":[-78.8167,38.85],"type":"Point"}
}