{
  "id": 2045527,
  "type": "Feature",
  "properties": {
    "tgn:hierarchy":[
        "tgn:2045527",
        "tgn:2000919",
        "tgn:1000001",
        "tgn:7012149",
        "tgn:7007515",
        "tgn:7029392"
    ],
    "tgn:id":2045527,
    "tgn:name":"Saint David",
    "tgn:placetype":[
        "aat:300008347"
    ]
},
  "bbox": [],
  "geometry": {"coordinates":[-68.2167,47.3333],"type":"Point"}
}