{
  "id": 2157070,
  "type": "Feature",
  "properties": {
    "tgn:hierarchy":[
        "tgn:2157070",
        "tgn:1000001",
        "tgn:2002147",
        "tgn:7012149",
        "tgn:7007919",
        "tgn:7029392"
    ],
    "tgn:id":2157070,
    "tgn:name":"Beaver Branch",
    "tgn:placetype":[
        "aat:300008699"
    ]
},
  "bbox": [],
  "geometry": {"coordinates":[-77.7833,36.8833],"type":"Point"}
}