<<<<<<< HEAD
{
  "id": 2157070,
  "type": "Feature",
  "properties": {
    "tgn:hierarchy":[
        "tgn:2157070",
        "tgn:1000001",
        "tgn:2002147",
        "tgn:7012149",
        "tgn:7007919",
        "tgn:7029392"
    ],
    "tgn:id":2157070,
    "tgn:name":"Beaver Branch",
    "tgn:placetype":[
        "aat:300008699"
    ]
},
  "bbox": [],
  "geometry": {"coordinates":[-77.7833,36.8833],"type":"Point"}
}
=======
{"geometry":{"type":"Point","coordinates":[-77.783300,36.883300]},"type":"Feature","properties":{"hierarchy":["tgn:2157070","tgn:1000001","tgn:2002147","tgn:7012149","tgn:7007919","tgn:7029392"],"placetype":["aat:300008699"],"id":2157070,"name:xx":"Beaver Branch"}}
>>>>>>> 03f74aca74312dbeaf24d7e61306dd6a786dc3d0
