{
  "id": 2510170,
  "type": "Feature",
  "properties": {
    "tgn:hierarchy":[
        "tgn:2510170",
        "tgn:1000001",
        "tgn:7012149",
        "tgn:2002382",
        "tgn:7007923",
        "tgn:7029392"
    ],
    "tgn:id":2510170,
    "tgn:name":"Middle Prong Reservoir",
    "tgn:placetype":[
        "aat:300006191"
    ]
},
  "bbox": [],
  "geometry": {"coordinates":[-109.7167,42.5167],"type":"Point"}
}