{
  "id": 7587790,
  "type": "Feature",
  "properties": {
    "tgn:hierarchy":[
        "tgn:7587790",
        "tgn:1000004",
        "tgn:1001832",
        "tgn:7000198",
        "tgn:7029392"
    ],
    "tgn:id":7587790,
    "tgn:name:en":"Son\u0101rihola",
    "tgn:placetype":[
        "aat:300008347"
    ]
},
  "bbox": [],
  "geometry": {"coordinates":[92.880726,26.548381],"type":"Point"}
}