{
  "id": 7443718,
  "type": "Feature",
  "properties": {
    "tgn:hierarchy":[
        "tgn:7443718",
        "tgn:7002445",
        "tgn:1000003",
        "tgn:7012032",
        "tgn:7008591",
        "tgn:7029392"
    ],
    "tgn:id":7443718,
    "tgn:name:en":"Upton",
    "tgn:placetype":[
        "aat:300008347"
    ]
},
  "bbox": [],
  "geometry": {"coordinates":[-3.437222,51.050278],"type":"Point"}
}