<<<<<<< HEAD
{
  "id": 2406416,
  "type": "Feature",
  "properties": {
    "tgn:hierarchy":[
        "tgn:2406416",
        "tgn:7006450",
        "tgn:1000001",
        "tgn:7019698",
        "tgn:7012149",
        "tgn:7029392"
    ],
    "tgn:id":2406416,
    "tgn:name":"Hungry Creek",
    "tgn:placetype":[
        "aat:300008706"
    ]
},
  "bbox": [],
  "geometry": {"coordinates":[-149.85,60.6833],"type":"Point"}
}
=======
{"geometry":{"type":"Point","coordinates":[-149.850000,60.683300]},"type":"Feature","properties":{"hierarchy":["tgn:2406416","tgn:7006450","tgn:1000001","tgn:7019698","tgn:7012149","tgn:7029392"],"placetype":["aat:300008706"],"id":2406416,"name:xx":"Hungry Creek"}}
>>>>>>> 03f74aca74312dbeaf24d7e61306dd6a786dc3d0
