{
  "id": 2501800,
  "type": "Feature",
  "properties": {
    "tgn:hierarchy":[
        "tgn:2501800",
        "tgn:1000001",
        "tgn:2001436",
        "tgn:7012149",
        "tgn:7007566",
        "tgn:7029392"
    ],
    "tgn:id":2501800,
    "tgn:name":"McIver Tank",
    "tgn:placetype":[
        "aat:300006191"
    ]
},
  "bbox": [],
  "geometry": {"coordinates":[-104.4167,32.3333],"type":"Point"}
}