<<<<<<< HEAD
{
  "id": 7359140,
  "type": "Feature",
  "properties": {
    "tgn:hierarchy":[
        "tgn:7359140",
        "tgn:1000001",
        "tgn:7005595",
        "tgn:7005560",
        "tgn:7029392"
    ],
    "tgn:id":7359140,
    "tgn:name":"Divisadero",
    "tgn:placetype":[
        "aat:300008347"
    ]
},
  "bbox": [],
  "geometry": {"coordinates":[-107.7,25.283333],"type":"Point"}
}
=======
{"geometry":{"type":"Point","coordinates":[-107.700000,25.283333]},"type":"Feature","properties":{"hierarchy":["tgn:7359140","tgn:1000001","tgn:7005595","tgn:7005560","tgn:7029392"],"placetype":["aat:300008347"],"id":7359140,"name:xx":"Divisadero"}}
>>>>>>> 03f74aca74312dbeaf24d7e61306dd6a786dc3d0
