{
  "id": 7318600,
  "type": "Feature",
  "properties": {
    "tgn:hierarchy":[
        "tgn:7318600",
        "tgn:1001692",
        "tgn:1000049",
        "tgn:1000002",
        "tgn:7029392"
    ],
    "tgn:id":7318600,
    "tgn:name":"Collanco, Estero",
    "tgn:placetype":[
        "aat:300008699"
    ]
},
  "bbox": [],
  "geometry": {"coordinates":[-72.583333,-38.466667],"type":"Point"}
}