{
  "id": 7406608,
  "type": "Feature",
  "properties": {
    "tgn:hierarchy":[
        "tgn:7406608",
        "tgn:7005585",
        "tgn:1000001",
        "tgn:7005560",
        "tgn:7029392"
    ],
    "tgn:id":7406608,
    "tgn:name":"Chuatepec",
    "tgn:placetype":[
        "aat:300008347"
    ]
},
  "bbox": [],
  "geometry": {"coordinates":[-98.566667,17.616667],"type":"Point"}
}