{
  "id": 7417761,
  "type": "Feature",
  "properties": {
    "tgn:hierarchy":[
        "tgn:7417761",
        "tgn:1000001",
        "tgn:7005591",
        "tgn:7005560",
        "tgn:7029392"
    ],
    "tgn:id":7417761,
    "tgn:name:es":"La Uni\u00f3n",
    "tgn:placetype":[
        "aat:300008347"
    ]
},
  "bbox": [],
  "geometry": {"coordinates":[-97.358333,17.925],"type":"Point"}
}