{
  "id": 2771196,
  "type": "Feature",
  "properties": {
    "tgn:hierarchy":[
        "tgn:2771196",
        "tgn:1000001",
        "tgn:7012149",
        "tgn:2002011",
        "tgn:7007826",
        "tgn:7029392"
    ],
    "tgn:id":2771196,
    "tgn:name":"Wildcat Ridge",
    "tgn:placetype":[
        "aat:300266640"
    ]
},
  "bbox": [],
  "geometry": {"coordinates":[-93.9333,29.7333],"type":"Point"}
}