{
  "id": 2571129,
  "type": "Feature",
  "properties": {
    "tgn:hierarchy":[
        "tgn:2571129",
        "tgn:1000001",
        "tgn:7012149",
        "tgn:1002891",
        "tgn:7007708",
        "tgn:7029392"
    ],
    "tgn:id":2571129,
    "tgn:name":"Pattlesnake Canyon",
    "tgn:placetype":[
        "aat:300008761"
    ]
},
  "bbox": [],
  "geometry": {"coordinates":[-120.8667,45.3167],"type":"Point"}
}