<<<<<<< HEAD
{
  "id": 2333115,
  "type": "Feature",
  "properties": {
    "tgn:hierarchy":[
        "tgn:2333115",
        "tgn:1000001",
        "tgn:7012149",
        "tgn:2002374",
        "tgn:7007923",
        "tgn:7029392"
    ],
    "tgn:id":2333115,
    "tgn:name":"Flying E Creek",
    "tgn:placetype":[
        "aat:300008706"
    ]
},
  "bbox": [],
  "geometry": {"coordinates":[-106.3,44.2167],"type":"Point"}
}
=======
{"geometry":{"type":"Point","coordinates":[-106.300000,44.216700]},"type":"Feature","properties":{"hierarchy":["tgn:2333115","tgn:1000001","tgn:7012149","tgn:2002374","tgn:7007923","tgn:7029392"],"placetype":["aat:300008706"],"id":2333115,"name:xx":"Flying E Creek"}}
>>>>>>> 03f74aca74312dbeaf24d7e61306dd6a786dc3d0
