{
  "id": 7277691,
  "type": "Feature",
  "properties": {
    "tgn:hierarchy":[
        "tgn:7277691",
        "tgn:1001699",
        "tgn:1000049",
        "tgn:1000002",
        "tgn:7029392"
    ],
    "tgn:id":7277691,
    "tgn:name":"Metahue",
    "tgn:placetype":[
        "aat:300008347"
    ]
},
  "bbox": [],
  "geometry": {"coordinates":[-73.099444,-42.287222],"type":"Point"}
}