{
  "id": 7564177,
  "type": "Feature",
  "properties": {
    "tgn:hierarchy":[
        "tgn:7564177",
        "tgn:1000004",
        "tgn:7000198",
        "tgn:7016788",
        "tgn:7029392"
    ],
    "tgn:id":7564177,
    "tgn:name:en":"S\u0101dhu ka Dhora",
    "tgn:placetype":[
        "aat:300008750"
    ]
},
  "bbox": [],
  "geometry": {"coordinates":[74.36938,28.272496],"type":"Point"}
}