{
  "id": 2558115,
  "type": "Feature",
  "properties": {
    "tgn:hierarchy":[
        "tgn:2558115",
        "tgn:7006450",
        "tgn:1000001",
        "tgn:7012149",
        "tgn:7029392"
    ],
    "tgn:id":2558115,
    "tgn:name":"Old Woman Creek",
    "tgn:placetype":[
        "aat:300008706"
    ]
},
  "bbox": [],
  "geometry": {"coordinates":[-144.4167,68.6167],"type":"Point"}
}