{
  "id": 1021790,
  "type": "Feature",
  "properties": {
    "tgn:hierarchy":[
        "tgn:1021790",
        "tgn:7006247",
        "tgn:1000047",
        "tgn:7002456",
        "tgn:1000002",
        "tgn:7029392"
    ],
    "tgn:id":1021790,
    "tgn:name":"Itupiranga",
    "tgn:placetype":[
        "aat:300008347"
    ]
},
  "bbox": [],
  "geometry": {"coordinates":[-49.3333,-5.1667],"type":"Point"}
}