{
  "id": 7579161,
  "type": "Feature",
  "properties": {
    "tgn:hierarchy":[
        "tgn:7579161",
        "tgn:1000004",
        "tgn:1001869",
        "tgn:7000198",
        "tgn:7029392"
    ],
    "tgn:id":7579161,
    "tgn:name:en":"Wanthali",
    "tgn:placetype":[
        "aat:300008347"
    ]
},
  "bbox": [],
  "geometry": {"coordinates":[70.333333,22.45],"type":"Point"}
}