{
  "id": 2711104,
  "type": "Feature",
  "properties": {
    "tgn:hierarchy":[
        "tgn:2711104",
        "tgn:1000001",
        "tgn:7012149",
        "tgn:7022544",
        "tgn:7007825",
        "tgn:7029392"
    ],
    "tgn:id":2711104,
    "tgn:name":"Tanner Branch",
    "tgn:placetype":[
        "aat:300008699"
    ]
},
  "bbox": [],
  "geometry": {"coordinates":[-88.45,35.15],"type":"Point"}
}