{
  "id": 7575812,
  "type": "Feature",
  "properties": {
    "tgn:hierarchy":[
        "tgn:7575812",
        "tgn:1000004",
        "tgn:7000198",
        "tgn:7016694",
        "tgn:7029392"
    ],
    "tgn:id":7575812,
    "tgn:name:en":"Khaira",
    "tgn:placetype":[
        "aat:300008347"
    ]
},
  "bbox": [],
  "geometry": {"coordinates":[86.454591,21.27714],"type":"Point"}
}