{
  "id": 2554070,
  "type": "Feature",
  "properties": {
    "tgn:hierarchy":[
        "tgn:2554070",
        "tgn:1000001",
        "tgn:7012149",
        "tgn:7014589",
        "tgn:7007515",
        "tgn:7029392"
    ],
    "tgn:id":2554070,
    "tgn:name":"Oak Pond",
    "tgn:placetype":[
        "aat:300008680"
    ]
},
  "bbox": [],
  "geometry": {"coordinates":[-67.9333,44.75],"type":"Point"}
}