{
  "id": 7456998,
  "type": "Feature",
  "properties": {
    "tgn:hierarchy":[
        "tgn:7456998",
        "tgn:7002448",
        "tgn:1000003",
        "tgn:7019206",
        "tgn:7008591",
        "tgn:7029392"
    ],
    "tgn:id":7456998,
    "tgn:name:en":"Moyle",
    "tgn:placetype":[
        "aat:300008347"
    ]
},
  "bbox": [],
  "geometry": {"coordinates":[-7.366667,54.716667],"type":"Point"}
}