{
  "id": 7430646,
  "type": "Feature",
  "properties": {
    "tgn:hierarchy":[
        "tgn:7430646",
        "tgn:1000001",
        "tgn:7005595",
        "tgn:7005560",
        "tgn:7029392"
    ],
    "tgn:id":7430646,
    "tgn:name":"Los Cevallos",
    "tgn:placetype":[
        "aat:300008347"
    ]
},
  "bbox": [],
  "geometry": {"coordinates":[-107.816667,25.75],"type":"Point"}
}