{
  "id": 1128534,
  "type": "Feature",
  "properties": {
    "tgn:hierarchy":[
        "tgn:1128534",
        "tgn:7005685",
        "tgn:1000001",
        "tgn:7005805",
        "tgn:7029392"
    ],
    "tgn:id":1128534,
    "tgn:name":"Pepaw",
    "tgn:placetype":[
        "aat:300008707"
    ]
},
  "bbox": [],
  "geometry": {"coordinates":[-102.3833,52.6667],"type":"Point"}
}