{
  "id": 1040509,
  "type": "Feature",
  "properties": {
    "tgn:hierarchy":[
        "tgn:1040509",
        "tgn:7003669",
        "tgn:1000003",
        "tgn:7000084",
        "tgn:7029392"
    ],
    "tgn:id":1040509,
    "tgn:name":"Niedersonthofen",
    "tgn:placetype":[
        "aat:300008347"
    ]
},
  "bbox": [],
  "geometry": {"coordinates":[10.233333,47.633333],"type":"Point"}
}