{
  "id": 2355067,
  "type": "Feature",
  "properties": {
    "tgn:hierarchy":[
        "tgn:2355067",
        "tgn:1000001",
        "tgn:7012149",
        "tgn:2002034",
        "tgn:7007826",
        "tgn:7029392"
    ],
    "tgn:id":2355067,
    "tgn:name":"Goodnight Tank",
    "tgn:placetype":[
        "aat:300006191"
    ]
},
  "bbox": [],
  "geometry": {"coordinates":[-99.2167,31.3667],"type":"Point"}
}