<<<<<<< HEAD
{
  "id": 2257123,
  "type": "Feature",
  "properties": {
    "tgn:hierarchy":[
        "tgn:2257123",
        "tgn:1000001",
        "tgn:1002198",
        "tgn:7012149",
        "tgn:7007826",
        "tgn:7029392"
    ],
    "tgn:id":2257123,
    "tgn:name":"Corner Bayou",
    "tgn:placetype":[
        "aat:300008699"
    ]
},
  "bbox": [],
  "geometry": {"coordinates":[-95.2833,29.3],"type":"Point"}
}
=======
{"geometry":{"type":"Point","coordinates":[-95.283300,29.300000]},"type":"Feature","properties":{"hierarchy":["tgn:2257123","tgn:1000001","tgn:1002198","tgn:7012149","tgn:7007826","tgn:7029392"],"placetype":["aat:300008699"],"id":2257123,"name:xx":"Corner Bayou"}}
>>>>>>> 03f74aca74312dbeaf24d7e61306dd6a786dc3d0
