{
  "id": 7319184,
  "type": "Feature",
  "properties": {
    "tgn:hierarchy":[
        "tgn:7319184",
        "tgn:7002464",
        "tgn:1000049",
        "tgn:1000002",
        "tgn:7029392"
    ],
    "tgn:id":7319184,
    "tgn:name":"Angostura",
    "tgn:placetype":[
        "aat:300387033"
    ]
},
  "bbox": [],
  "geometry": {"coordinates":[-69.983333,-19.116667],"type":"Point"}
}