{
  "id": 2561654,
  "type": "Feature",
  "properties": {
    "tgn:hierarchy":[
        "tgn:2561654",
        "tgn:7006450",
        "tgn:1000001",
        "tgn:7012149",
        "tgn:2124002",
        "tgn:7029392"
    ],
    "tgn:id":2561654,
    "tgn:name":"Osprey, Lake",
    "tgn:placetype":[
        "aat:300008680"
    ]
},
  "bbox": [],
  "geometry": {"coordinates":[-134.6667,56.3833],"type":"Point"}
}