{
  "id": 7077136,
  "type": "Feature",
  "properties": {
    "tgn:hierarchy":[
        "tgn:7077136",
        "tgn:7003692",
        "tgn:1000003",
        "tgn:7000084",
        "tgn:7029392"
    ],
    "tgn:id":7077136,
    "tgn:name":"Ziegerhof",
    "tgn:placetype":[
        "aat:300008347"
    ]
},
  "bbox": [],
  "geometry": {"coordinates":[9.75,48.766667],"type":"Point"}
}