{
  "id": 1083442,
  "type": "Feature",
  "properties": {
    "tgn:hierarchy":[
        "tgn:1083442",
        "tgn:1000004",
        "tgn:1001490",
        "tgn:1000133",
        "tgn:7029392"
    ],
    "tgn:id":1083442,
    "tgn:name":"Faisalabad",
    "tgn:placetype":[
        "aat:300008347",
        "aat:300008375",
        "aat:300387302",
        "aat:300387286",
        "aat:300387296"
    ]
},
  "bbox": [],
  "geometry": {"coordinates":[73.15,31.4167],"type":"Point"}
}