{
  "id": 7509460,
  "type": "Feature",
  "properties": {
    "tgn:hierarchy":[
        "tgn:7509460",
        "tgn:1009227",
        "tgn:1000226",
        "tgn:1000006",
        "tgn:7016850",
        "tgn:7029392"
    ],
    "tgn:id":7509460,
    "tgn:name:en":"Supply Creek",
    "tgn:placetype":[
        "aat:300008699"
    ]
},
  "bbox": [],
  "geometry": {"coordinates":[170.95,-42.883333],"type":"Point"}
}