{
  "id": 1076373,
  "type": "Feature",
  "properties": {
    "tgn:hierarchy":[
        "tgn:1076373",
        "tgn:1000004",
        "tgn:7000198",
        "tgn:1001977",
        "tgn:7029392"
    ],
    "tgn:id":1076373,
    "tgn:name":"Naopukuria",
    "tgn:placetype":[
        "aat:300008347"
    ]
},
  "bbox": [],
  "geometry": {"coordinates":[88.2667,22.9167],"type":"Point"}
}