{
  "id": 7069704,
  "type": "Feature",
  "properties": {
    "tgn:hierarchy":[
        "tgn:7069704",
        "tgn:7003692",
        "tgn:1000003",
        "tgn:7000084",
        "tgn:7029392"
    ],
    "tgn:id":7069704,
    "tgn:name":"Tonenberg",
    "tgn:placetype":[
        "aat:300008777"
    ]
},
  "bbox": [],
  "geometry": {"coordinates":[10.166667,48.866667],"type":"Point"}
}