{
  "id": 7493384,
  "type": "Feature",
  "properties": {
    "tgn:hierarchy":[
        "tgn:7493384",
        "tgn:1000004",
        "tgn:1000454",
        "tgn:1000141",
        "tgn:7029392"
    ],
    "tgn:id":7493384,
    "tgn:name":"Liuliaolun Shan",
    "tgn:placetype":[
        "aat:300008798"
    ]
},
  "bbox": [],
  "geometry": {"coordinates":[121.456229,24.908431],"type":"Point"}
}