{
  "id": 2310524,
  "type": "Feature",
  "properties": {
    "tgn:hierarchy":[
        "tgn:2310524",
        "tgn:1000001",
        "tgn:7012149",
        "tgn:7007157",
        "tgn:2000191",
        "tgn:7029392"
    ],
    "tgn:id":2310524,
    "tgn:name":"Echo Lake",
    "tgn:placetype":[
        "aat:300008680"
    ]
},
  "bbox": [],
  "geometry": {"coordinates":[-122.8667,40.9167],"type":"Point"}
}