<<<<<<< HEAD
{
  "id": 2157831,
  "type": "Feature",
  "properties": {
    "tgn:hierarchy":[
        "tgn:2157831",
        "tgn:1000001",
        "tgn:7013686",
        "tgn:7012149",
        "tgn:7007517",
        "tgn:7029392"
    ],
    "tgn:id":2157831,
    "tgn:name":"Beaver Lake",
    "tgn:placetype":[
        "aat:300006191"
    ]
},
  "bbox": [],
  "geometry": {"coordinates":[-72.3,42.25],"type":"Point"}
}
=======
{"geometry":{"type":"Point","coordinates":[-72.300000,42.250000]},"type":"Feature","properties":{"hierarchy":["tgn:2157831","tgn:1000001","tgn:7013686","tgn:7012149","tgn:7007517","tgn:7029392"],"placetype":["aat:300006191"],"id":2157831,"name:xx":"Beaver Lake"}}
>>>>>>> 03f74aca74312dbeaf24d7e61306dd6a786dc3d0
