{
  "id": 2355745,
  "type": "Feature",
  "properties": {
    "tgn:hierarchy":[
        "tgn:2355745",
        "tgn:7006450",
        "tgn:1000001",
        "tgn:7012149",
        "tgn:7019760",
        "tgn:7029392"
    ],
    "tgn:id":2355745,
    "tgn:name":"Goose Lake",
    "tgn:placetype":[
        "aat:300008680"
    ]
},
  "bbox": [],
  "geometry": {"coordinates":[-136.2167,57.9167],"type":"Point"}
}