{
  "id": 2128716,
  "type": "Feature",
  "properties": {
    "tgn:hierarchy":[
        "tgn:2128716",
        "tgn:1000001",
        "tgn:7012149",
        "tgn:7007158",
        "tgn:2000243",
        "tgn:7029392"
    ],
    "tgn:id":2128716,
    "tgn:name":"Aldrich Lakes",
    "tgn:placetype":[
        "aat:300008680"
    ]
},
  "bbox": [],
  "geometry": {"coordinates":[-107.6833,40.1667],"type":"Point"}
}