{
  "id": 2373538,
  "type": "Feature",
  "properties": {
    "tgn:hierarchy":[
        "tgn:2373538",
        "tgn:1000001",
        "tgn:7012149",
        "tgn:2000346",
        "tgn:7007248",
        "tgn:7029392"
    ],
    "tgn:id":2373538,
    "tgn:name":"Hamestring Valley",
    "tgn:placetype":[
        "aat:300008761"
    ]
},
  "bbox": [],
  "geometry": {"coordinates":[-84.1833,34.95],"type":"Point"}
}