{
  "id": 2483158,
  "type": "Feature",
  "properties": {
    "tgn:hierarchy":[
        "tgn:2483158",
        "tgn:1000001",
        "tgn:7012149",
        "tgn:7007157",
        "tgn:1002867",
        "tgn:7029392"
    ],
    "tgn:id":2483158,
    "tgn:name":"Las Animas Spring",
    "tgn:placetype":[
        "aat:300008697"
    ]
},
  "bbox": [],
  "geometry": {"coordinates":[-120.45,34.4833],"type":"Point"}
}