{
  "id": 2206213,
  "type": "Feature",
  "properties": {
    "tgn:hierarchy":[
        "tgn:2206213",
        "tgn:1000001",
        "tgn:7012149",
        "tgn:7029392"
    ],
    "tgn:id":2206213,
    "tgn:name":"Bullard Branch",
    "tgn:placetype":[
        "aat:300008699"
    ]
},
  "bbox": [],
  "geometry": {"coordinates":[-85.55,34.85],"type":"Point"}
}