<<<<<<< HEAD
{
  "id": 7357956,
  "type": "Feature",
  "properties": {
    "tgn:hierarchy":[
        "tgn:7357956",
        "tgn:1000001",
        "tgn:7005589",
        "tgn:7005560",
        "tgn:7029392"
    ],
    "tgn:id":7357956,
    "tgn:name":"Colonia Francisco G Sada",
    "tgn:placetype":[
        "aat:300008347"
    ]
},
  "bbox": [],
  "geometry": {"coordinates":[-100.25,25.7],"type":"Point"}
}
=======
{"geometry":{"type":"Point","coordinates":[-100.250000,25.700000]},"type":"Feature","properties":{"hierarchy":["tgn:7357956","tgn:1000001","tgn:7005589","tgn:7005560","tgn:7029392"],"placetype":["aat:300008347"],"id":7357956,"name:xx":"Colonia Francisco G Sada"}}
>>>>>>> 03f74aca74312dbeaf24d7e61306dd6a786dc3d0
