{
  "id": 7285288,
  "type": "Feature",
  "properties": {
    "tgn:hierarchy":[
        "tgn:7285288",
        "tgn:1001623",
        "tgn:1000049",
        "tgn:1000002",
        "tgn:7029392"
    ],
    "tgn:id":7285288,
    "tgn:name":"Puerto Bertrand",
    "tgn:placetype":[
        "aat:300008347"
    ]
},
  "bbox": [],
  "geometry": {"coordinates":[-72.816667,-47.033333],"type":"Point"}
}