{
  "id": 2380934,
  "type": "Feature",
  "properties": {
    "tgn:hierarchy":[
        "tgn:2380934",
        "tgn:1000001",
        "tgn:2002370",
        "tgn:7012149",
        "tgn:7007923",
        "tgn:7029392"
    ],
    "tgn:id":2380934,
    "tgn:name":"Hawkensmith Reservoir",
    "tgn:placetype":[
        "aat:300006191"
    ]
},
  "bbox": [],
  "geometry": {"coordinates":[-104.25,44.85],"type":"Point"}
}