{
  "id": 2222564,
  "type": "Feature",
  "properties": {
    "tgn:hierarchy":[
        "tgn:2222564",
        "tgn:1000001",
        "tgn:7012149",
        "tgn:7029392"
    ],
    "tgn:id":2222564,
    "tgn:name":"Carpenter Ridge",
    "tgn:placetype":[
        "aat:300266640"
    ]
},
  "bbox": [],
  "geometry": {"coordinates":[-108.9667,38.4167],"type":"Point"}
}