{
  "id": 7553260,
  "type": "Feature",
  "properties": {
    "tgn:hierarchy":[
        "tgn:7553260",
        "tgn:1000004",
        "tgn:7000198",
        "tgn:1001895",
        "tgn:7029392"
    ],
    "tgn:id":7553260,
    "tgn:name:en":"Neral",
    "tgn:placetype":[
        "aat:300008347"
    ]
},
  "bbox": [],
  "geometry": {"coordinates":[73.316667,19.033333],"type":"Point"}
}