{
  "id": 2527865,
  "type": "Feature",
  "properties": {
    "tgn:hierarchy":[
        "tgn:2527865",
        "tgn:1000001",
        "tgn:7012149",
        "tgn:7007157",
        "tgn:7014004",
        "tgn:7029392"
    ],
    "tgn:id":2527865,
    "tgn:name":"Mountain King Mine",
    "tgn:placetype":[
        "aat:300000390"
    ]
},
  "bbox": [],
  "geometry": {"coordinates":[-120.0167,37.6167],"type":"Point"}
}