{
  "id": 7471507,
  "type": "Feature",
  "properties": {
    "tgn:hierarchy":[
        "tgn:7471507",
        "tgn:1000004",
        "tgn:7492971",
        "tgn:1000141",
        "tgn:7029392"
    ],
    "tgn:id":7471507,
    "tgn:name":"Xinghuapou",
    "tgn:placetype":[
        "aat:300008347"
    ]
},
  "bbox": [],
  "geometry": {"coordinates":[120.444222,22.728278],"type":"Point"}
}