<<<<<<< HEAD
{
  "id": 7471507,
  "type": "Feature",
  "properties": {
    "tgn:hierarchy":[
        "tgn:7471507",
        "tgn:1000004",
        "tgn:7492971",
        "tgn:1000141",
        "tgn:7029392"
    ],
    "tgn:id":7471507,
    "tgn:name":"Xinghuapou",
    "tgn:placetype":[
        "aat:300008347"
    ]
},
  "bbox": [],
  "geometry": {"coordinates":[120.444222,22.728278],"type":"Point"}
}
=======
{"geometry":{"type":"Point","coordinates":[120.444222,22.728278]},"type":"Feature","properties":{"hierarchy":["tgn:7471507","tgn:1000004","tgn:7492971","tgn:1000141","tgn:7029392"],"placetype":["aat:300008347"],"id":7471507,"name:xx":"Xinghuapou"}}
>>>>>>> 03f74aca74312dbeaf24d7e61306dd6a786dc3d0
