{
  "id": 2561109,
  "type": "Feature",
  "properties": {
    "tgn:hierarchy":[
        "tgn:2561109",
        "tgn:1000001",
        "tgn:7012149",
        "tgn:2000348",
        "tgn:7007248",
        "tgn:7029392"
    ],
    "tgn:id":2561109,
    "tgn:name":"Orsman",
    "tgn:placetype":[
        "aat:300008347"
    ]
},
  "bbox": [],
  "geometry": {"coordinates":[-85.2333,34.3667],"type":"Point"}
}