{
  "id": 2071922,
  "type": "Feature",
  "properties": {
    "tgn:hierarchy":[
        "tgn:2071922",
        "tgn:1000001",
        "tgn:7012149",
        "tgn:1002718",
        "tgn:7007568",
        "tgn:7029392"
    ],
    "tgn:id":2071922,
    "tgn:name":"Ridgewood",
    "tgn:placetype":[
        "aat:300008347"
    ]
},
  "bbox": [],
  "geometry": {"coordinates":[-78.6333,43.25],"type":"Point"}
}