{
  "id": 7288405,
  "type": "Feature",
  "properties": {
    "tgn:hierarchy":[
        "tgn:7288405",
        "tgn:1001705",
        "tgn:1000049",
        "tgn:1000002",
        "tgn:7029392"
    ],
    "tgn:id":7288405,
    "tgn:name":"Huinganes, Estero",
    "tgn:placetype":[
        "aat:300008699"
    ]
},
  "bbox": [],
  "geometry": {"coordinates":[-72.016667,-35.866667],"type":"Point"}
}