<<<<<<< HEAD
{
  "id": 7356694,
  "type": "Feature",
  "properties": {
    "tgn:hierarchy":[
        "tgn:7356694",
        "tgn:7005586",
        "tgn:1000001",
        "tgn:7005560",
        "tgn:7029392"
    ],
    "tgn:id":7356694,
    "tgn:name":"Chacala",
    "tgn:placetype":[
        "aat:300008347"
    ]
},
  "bbox": [],
  "geometry": {"coordinates":[-104.283333,19.316667],"type":"Point"}
}
=======
{"geometry":{"type":"Point","coordinates":[-104.283333,19.316667]},"type":"Feature","properties":{"hierarchy":["tgn:7356694","tgn:7005586","tgn:1000001","tgn:7005560","tgn:7029392"],"placetype":["aat:300008347"],"id":7356694,"name:xx":"Chacala"}}
>>>>>>> 03f74aca74312dbeaf24d7e61306dd6a786dc3d0
