{
  "id": 7338533,
  "type": "Feature",
  "properties": {
    "tgn:hierarchy":[
        "tgn:7338533",
        "tgn:7002758",
        "tgn:7002841",
        "tgn:1000003",
        "tgn:1000095",
        "tgn:7029392"
    ],
    "tgn:id":7338533,
    "tgn:name":"El Coronil",
    "tgn:placetype":[
        "aat:300008347"
    ]
},
  "bbox": [],
  "geometry": {"coordinates":[-5.633333,37.083333],"type":"Point"}
}