{
  "id": 2044596,
  "type": "Feature",
  "properties": {
    "tgn:hierarchy":[
        "tgn:2044596",
        "tgn:1000001",
        "tgn:2000921",
        "tgn:7012149",
        "tgn:7007515",
        "tgn:7029392"
    ],
    "tgn:id":2044596,
    "tgn:name":"Carthage",
    "tgn:placetype":[
        "aat:300008347"
    ]
},
  "bbox": [],
  "geometry": {"coordinates":[-70.4667,44.6167],"type":"Point"}
}