{
  "id": 2130666,
  "type": "Feature",
  "properties": {
    "tgn:hierarchy":[
        "tgn:2130666",
        "tgn:1000001",
        "tgn:7012149",
        "tgn:2000928",
        "tgn:7007515",
        "tgn:7029392"
    ],
    "tgn:id":2130666,
    "tgn:name":"Alligator Pond",
    "tgn:placetype":[
        "aat:300008680"
    ]
},
  "bbox": [],
  "geometry": {"coordinates":[-69.1833,45.6167],"type":"Point"}
}