{
  "id": 7400160,
  "type": "Feature",
  "properties": {
    "tgn:hierarchy":[
        "tgn:7400160",
        "tgn:1000001",
        "tgn:7005599",
        "tgn:7005560",
        "tgn:7029392"
    ],
    "tgn:id":7400160,
    "tgn:name":"Las Conchas",
    "tgn:placetype":[
        "aat:300008347"
    ]
},
  "bbox": [],
  "geometry": {"coordinates":[-94.822222,17.458333],"type":"Point"}
}