{
  "id": 2315955,
  "type": "Feature",
  "properties": {
    "tgn:hierarchy":[
        "tgn:2315955",
        "tgn:1000001",
        "tgn:7012149",
        "tgn:2001654",
        "tgn:7007707",
        "tgn:7029392"
    ],
    "tgn:id":2315955,
    "tgn:name":"Elm Creek",
    "tgn:placetype":[
        "aat:300008706"
    ]
},
  "bbox": [],
  "geometry": {"coordinates":[-96.3167,35.0667],"type":"Point"}
}