{
  "id": 2280210,
  "type": "Feature",
  "properties": {
    "tgn:hierarchy":[
        "tgn:2280210",
        "tgn:1000001",
        "tgn:7012149",
        "tgn:2002127",
        "tgn:7007827",
        "tgn:7029392"
    ],
    "tgn:id":2280210,
    "tgn:name":"Death Valley Wash",
    "tgn:placetype":[
        "aat:300008761"
    ]
},
  "bbox": [],
  "geometry": {"coordinates":[-113.3167,37.4333],"type":"Point"}
}