{
  "id": 2370226,
  "type": "Feature",
  "properties": {
    "tgn:hierarchy":[
        "tgn:2370226",
        "tgn:1000001",
        "tgn:7012149",
        "tgn:2001455",
        "tgn:7007566",
        "tgn:7029392"
    ],
    "tgn:id":2370226,
    "tgn:name":"Gyp Hills",
    "tgn:placetype":[
        "aat:300386831"
    ]
},
  "bbox": [],
  "geometry": {"coordinates":[-106.75,33.25],"type":"Point"}
}