{
  "id": 7228392,
  "type": "Feature",
  "properties": {
    "tgn:hierarchy":[
        "tgn:7228392",
        "tgn:7002681",
        "tgn:7001395",
        "tgn:1000003",
        "tgn:1000074",
        "tgn:7029392"
    ],
    "tgn:id":7228392,
    "tgn:name":"Kast\u00e9lla",
    "tgn:placetype":[
        "aat:300008347"
    ]
},
  "bbox": [],
  "geometry": {"coordinates":[23.633333,38.566667],"type":"Point"}
}