{
  "id": 7349502,
  "type": "Feature",
  "properties": {
    "tgn:hierarchy":[
        "tgn:7349502",
        "tgn:1001853",
        "tgn:1000001",
        "tgn:7005560",
        "tgn:7029392"
    ],
    "tgn:id":7349502,
    "tgn:name":"Agua Grande, Arroyo",
    "tgn:placetype":[
        "aat:300266554",
        "aat:300008699"
    ]
},
  "bbox": [],
  "geometry": {"coordinates":[-101.016667,24.766667],"type":"Point"}
}