{
  "id": 2699843,
  "type": "Feature",
  "properties": {
    "tgn:hierarchy":[
        "tgn:2699843",
        "tgn:1000001",
        "tgn:2002109",
        "tgn:7012149",
        "tgn:7007827",
        "tgn:7029392"
    ],
    "tgn:id":2699843,
    "tgn:name":"Stud Knoll",
    "tgn:placetype":[
        "aat:300008798"
    ]
},
  "bbox": [],
  "geometry": {"coordinates":[-112.55,37.65],"type":"Point"}
}