{
  "id": 2463058,
  "type": "Feature",
  "properties": {
    "tgn:hierarchy":[
        "tgn:2463058",
        "tgn:1000001",
        "tgn:7012149",
        "tgn:1002882",
        "tgn:7007568",
        "tgn:7029392"
    ],
    "tgn:id":2463058,
    "tgn:name":"Lively Run",
    "tgn:placetype":[
        "aat:300008699"
    ]
},
  "bbox": [],
  "geometry": {"coordinates":[-76.75,42.6167],"type":"Point"}
}