{
  "id": 7002318,
  "type": "Feature",
  "properties": {
    "tgn:hierarchy":[
        "tgn:7002318",
        "tgn:1001232",
        "tgn:1000004",
        "tgn:7018450",
        "tgn:1000144",
        "tgn:7029392"
    ],
    "tgn:id":7002318,
    "tgn:name":"Enez",
    "tgn:placetype":[
        "aat:300008347",
        "aat:300008372"
    ]
},
  "bbox": [],
  "geometry": {"coordinates":[26.0833,40.7333],"type":"Point"}
}