{
  "id": 2392031,
  "type": "Feature",
  "properties": {
    "tgn:hierarchy":[
        "tgn:2392031",
        "tgn:7002659",
        "tgn:1000001",
        "tgn:2000008",
        "tgn:7012149",
        "tgn:7029392"
    ],
    "tgn:id":2392031,
    "tgn:name":"Hincle Lake",
    "tgn:placetype":[
        "aat:300006191"
    ]
},
  "bbox": [],
  "geometry": {"coordinates":[-85.3833,32.7333],"type":"Point"}
}