{
  "id": 7396692,
  "type": "Feature",
  "properties": {
    "tgn:hierarchy":[
        "tgn:7396692",
        "tgn:1000001",
        "tgn:7005601",
        "tgn:7005560",
        "tgn:7029392"
    ],
    "tgn:id":7396692,
    "tgn:name":"Santa Efigenia",
    "tgn:placetype":[
        "aat:300008347"
    ]
},
  "bbox": [],
  "geometry": {"coordinates":[-101.883333,23.716667],"type":"Point"}
}