{
  "id": 7554460,
  "type": "Feature",
  "properties": {
    "tgn:hierarchy":[
        "tgn:7554460",
        "tgn:1006247",
        "tgn:7001559",
        "tgn:1000004",
        "tgn:7000198",
        "tgn:1001890",
        "tgn:7029392"
    ],
    "tgn:id":7554460,
    "tgn:name:en":"North West Point",
    "tgn:placetype":[
        "aat:300386846"
    ]
},
  "bbox": [],
  "geometry": {"coordinates":[72.983333,11.483333],"type":"Point"}
}