{
  "id": 7103365,
  "type": "Feature",
  "properties": {
    "tgn:hierarchy":[
        "tgn:7103365",
        "tgn:7003669",
        "tgn:1000003",
        "tgn:7000084",
        "tgn:7029392"
    ],
    "tgn:id":7103365,
    "tgn:name":"Roter Berg",
    "tgn:placetype":[
        "aat:300008777"
    ]
},
  "bbox": [],
  "geometry": {"coordinates":[9.75,50.183333],"type":"Point"}
}