{
  "id": 7284564,
  "type": "Feature",
  "properties": {
    "tgn:hierarchy":[
        "tgn:7284564",
        "tgn:1001657",
        "tgn:1000049",
        "tgn:1000002",
        "tgn:7029392"
    ],
    "tgn:id":7284564,
    "tgn:name":"Quillaicillo",
    "tgn:placetype":[
        "aat:300008347"
    ]
},
  "bbox": [],
  "geometry": {"coordinates":[-71.572778,-31.414722],"type":"Point"}
}