{
  "id": 7509689,
  "type": "Feature",
  "properties": {
    "tgn:hierarchy":[
        "tgn:7509689",
        "tgn:1008380",
        "tgn:7000507",
        "tgn:1000226",
        "tgn:1000006",
        "tgn:7029392"
    ],
    "tgn:id":7509689,
    "tgn:name:en":"Te Ramanuka",
    "tgn:placetype":[
        "aat:300008777"
    ]
},
  "bbox": [],
  "geometry": {"coordinates":[173.016667,-34.733333],"type":"Point"}
}