{
  "id": 2498466,
  "type": "Feature",
  "properties": {
    "tgn:hierarchy":[
        "tgn:2498466",
        "tgn:1000001",
        "tgn:2002107",
        "tgn:7012149",
        "tgn:7007827",
        "tgn:7029392"
    ],
    "tgn:id":2498466,
    "tgn:name":"McAfee Basin",
    "tgn:placetype":[
        "aat:300386845"
    ]
},
  "bbox": [],
  "geometry": {"coordinates":[-110.6167,40.4667],"type":"Point"}
}