{
  "id": 1002389,
  "type": "Feature",
  "properties": {
    "tgn:hierarchy":[
        "tgn:1002389",
        "tgn:1000001",
        "tgn:7012149",
        "tgn:7007828",
        "tgn:7029392"
    ],
    "tgn:id":1002389,
    "tgn:name":"Franklin",
    "tgn:placetype":[
        "aat:300387145",
        "aat:300000771"
    ]
},
  "bbox": [],
  "geometry": {"coordinates":[-72.8667,44.85],"type":"Point"}
}