{
  "id": 7277050,
  "type": "Feature",
  "properties": {
    "tgn:hierarchy":[
        "tgn:7277050",
        "tgn:7002464",
        "tgn:1000049",
        "tgn:1000002",
        "tgn:7029392"
    ],
    "tgn:id":7277050,
    "tgn:name":"Titinepena, Cerro",
    "tgn:placetype":[
        "aat:300008795"
    ]
},
  "bbox": [],
  "geometry": {"coordinates":[-69.816111,-17.835556],"type":"Point"}
}