{
  "id": 4008462,
  "type": "Feature",
  "properties": {
    "tgn:hierarchy":[
        "tgn:4008462",
        "tgn:7019038",
        "tgn:7002445",
        "tgn:1000003",
        "tgn:7029507",
        "tgn:7008591",
        "tgn:7029392"
    ],
    "tgn:id":4008462,
    "tgn:name":"Parlington",
    "tgn:placetype":[
        "aat:300008347"
    ]
},
  "bbox": [],
  "geometry": {"coordinates":[-1.355,53.802],"type":"Point"}
}