{
  "id": 7568067,
  "type": "Feature",
  "properties": {
    "tgn:hierarchy":[
        "tgn:7568067",
        "tgn:1000004",
        "tgn:1001869",
        "tgn:7000198",
        "tgn:7029392"
    ],
    "tgn:id":7568067,
    "tgn:name:en":"Mojap",
    "tgn:placetype":[
        "aat:300008347"
    ]
},
  "bbox": [],
  "geometry": {"coordinates":[68.977222,22.366667],"type":"Point"}
}