{
  "id": 7512134,
  "type": "Feature",
  "properties": {
    "tgn:hierarchy":[
        "tgn:7512134",
        "tgn:1009227",
        "tgn:1000226",
        "tgn:7016822",
        "tgn:1000006",
        "tgn:7029392"
    ],
    "tgn:id":7512134,
    "tgn:name:en":"John Point",
    "tgn:placetype":[
        "aat:300386846"
    ]
},
  "bbox": [],
  "geometry": {"coordinates":[168.15,-47.116667],"type":"Point"}
}