{
  "id": 2725897,
  "type": "Feature",
  "properties": {
    "tgn:hierarchy":[
        "tgn:2725897",
        "tgn:1000001",
        "tgn:7012149",
        "tgn:7019676",
        "tgn:7007566",
        "tgn:7029392"
    ],
    "tgn:id":2725897,
    "tgn:name":"Torrivio Ridge",
    "tgn:placetype":[
        "aat:300266640"
    ]
},
  "bbox": [],
  "geometry": {"coordinates":[-108.9667,35.5833],"type":"Point"}
}