{
  "id": 2723917,
  "type": "Feature",
  "properties": {
    "tgn:hierarchy":[
        "tgn:2723917",
        "tgn:1000001",
        "tgn:7012149",
        "tgn:7029392"
    ],
    "tgn:id":2723917,
    "tgn:name":"Toledo Bend Reservoir",
    "tgn:placetype":[
        "aat:300006191"
    ]
},
  "bbox": [],
  "geometry": {"coordinates":[-93.5667,31.1833],"type":"Point"}
}