{
  "id": 2056147,
  "type": "Feature",
  "properties": {
    "tgn:hierarchy":[
        "tgn:2056147",
        "tgn:1000001",
        "tgn:7012149",
        "tgn:2001131",
        "tgn:7007522",
        "tgn:7029392"
    ],
    "tgn:id":2056147,
    "tgn:name":"Cheraw",
    "tgn:placetype":[
        "aat:300008347",
        "aat:300387210"
    ]
},
  "bbox": [],
  "geometry": {"coordinates":[-89.8333,31.15],"type":"Point"}
}