{
  "id": 7327712,
  "type": "Feature",
  "properties": {
    "tgn:hierarchy":[
        "tgn:7327712",
        "tgn:7002807",
        "tgn:1000003",
        "tgn:7003837",
        "tgn:1000095",
        "tgn:7029392"
    ],
    "tgn:id":7327712,
    "tgn:name":"Porras",
    "tgn:placetype":[
        "aat:300008347"
    ]
},
  "bbox": [],
  "geometry": {"coordinates":[-5.716667,38.45],"type":"Point"}
}