{
  "id": 2220956,
  "type": "Feature",
  "properties": {
    "tgn:hierarchy":[
        "tgn:2220956",
        "tgn:1000001",
        "tgn:7012149",
        "tgn:2001449",
        "tgn:7007566",
        "tgn:7029392"
    ],
    "tgn:id":2220956,
    "tgn:name":"Capulin, Ca\u00f1on",
    "tgn:placetype":[
        "aat:300008761"
    ]
},
  "bbox": [],
  "geometry": {"coordinates":[-106.8167,36.2167],"type":"Point"}
}