{
  "id": 7293964,
  "type": "Feature",
  "properties": {
    "tgn:hierarchy":[
        "tgn:7293964",
        "tgn:7002835",
        "tgn:7001158",
        "tgn:1000003",
        "tgn:1000095",
        "tgn:7029392"
    ],
    "tgn:id":7293964,
    "tgn:name":"Viejo, Puerto",
    "tgn:placetype":[
        "aat:300259572"
    ]
},
  "bbox": [],
  "geometry": {"coordinates":[-6.85,40.266667],"type":"Point"}
}