{
  "id": 7531971,
  "type": "Feature",
  "properties": {
    "tgn:hierarchy":[
        "tgn:7531971",
        "tgn:7001242",
        "tgn:7016833",
        "tgn:7001335",
        "tgn:7029392"
    ],
    "tgn:id":7531971,
    "tgn:name:en":"El-Sher\u00eef",
    "tgn:placetype":[
        "aat:300008884"
    ]
},
  "bbox": [],
  "geometry": {"coordinates":[33.681944,31.091389],"type":"Point"}
}