{
  "id": 1066609,
  "type": "Feature",
  "properties": {
    "tgn:hierarchy":[
        "tgn:1066609",
        "tgn:1000004",
        "tgn:7002088",
        "tgn:1000111",
        "tgn:7029392"
    ],
    "tgn:id":1066609,
    "tgn:name":"Bag Narin",
    "tgn:placetype":[
        "aat:300008347"
    ]
},
  "bbox": [],
  "geometry": {"coordinates":[94.3167,38.9667],"type":"Point"}
}