{
  "id": 7415392,
  "type": "Feature",
  "properties": {
    "tgn:hierarchy":[
        "tgn:7415392",
        "tgn:7005584",
        "tgn:1000001",
        "tgn:7005560",
        "tgn:7029392"
    ],
    "tgn:id":7415392,
    "tgn:name":"San Vicente",
    "tgn:placetype":[
        "aat:300008347"
    ]
},
  "bbox": [],
  "geometry": {"coordinates":[-100.654722,20.969167],"type":"Point"}
}