{
  "id": 7074785,
  "type": "Feature",
  "properties": {
    "tgn:hierarchy":[
        "tgn:7074785",
        "tgn:1000003",
        "tgn:7003689",
        "tgn:7000084",
        "tgn:7029392"
    ],
    "tgn:id":7074785,
    "tgn:name":"Zettel-Berg",
    "tgn:placetype":[
        "aat:300008777"
    ]
},
  "bbox": [],
  "geometry": {"coordinates":[10.916667,50.866667],"type":"Point"}
}