{
  "id": 7563289,
  "type": "Feature",
  "properties": {
    "tgn:hierarchy":[
        "tgn:7563289",
        "tgn:1000004",
        "tgn:7000198",
        "tgn:7016722",
        "tgn:7029392"
    ],
    "tgn:id":7563289,
    "tgn:name:en":"Chint\u0101man Purwa",
    "tgn:placetype":[
        "aat:300008347"
    ]
},
  "bbox": [],
  "geometry": {"coordinates":[79.9172,27.0767],"type":"Point"}
}