{
  "id": 2241607,
  "type": "Feature",
  "properties": {
    "tgn:hierarchy":[
        "tgn:2241607",
        "tgn:1000001",
        "tgn:7012149",
        "tgn:7014021",
        "tgn:7007709",
        "tgn:7029392"
    ],
    "tgn:id":2241607,
    "tgn:name":"Clarks Creek",
    "tgn:placetype":[
        "aat:300008706"
    ]
},
  "bbox": [],
  "geometry": {"coordinates":[-80.7833,35.3667],"type":"Point"}
}