{
  "id": 1081823,
  "type": "Feature",
  "properties": {
    "tgn:hierarchy":[
        "tgn:1081823",
        "tgn:1000975",
        "tgn:1000004",
        "tgn:7000901",
        "tgn:1000120",
        "tgn:7029392"
    ],
    "tgn:id":1081823,
    "tgn:name":"Yukuhashi",
    "tgn:placetype":[
        "aat:300008347"
    ]
},
  "bbox": [],
  "geometry": {"coordinates":[130.9833,33.75],"type":"Point"}
}