{
  "id": 7461363,
  "type": "Feature",
  "properties": {
    "tgn:hierarchy":[
        "tgn:7461363",
        "tgn:7002443",
        "tgn:1000003",
        "tgn:7029493",
        "tgn:7008591",
        "tgn:7029392"
    ],
    "tgn:id":7461363,
    "tgn:name:en":"Llanfor",
    "tgn:placetype":[
        "aat:300008347"
    ]
},
  "bbox": [],
  "geometry": {"coordinates":[-3.583333,52.916667],"type":"Point"}
}