<<<<<<< HEAD
{
  "id": 7179168,
  "type": "Feature",
  "properties": {
    "tgn:hierarchy":[
        "tgn:7179168",
        "tgn:7003669",
        "tgn:1000003",
        "tgn:7000084",
        "tgn:7029392"
    ],
    "tgn:id":7179168,
    "tgn:name":"Haidberg",
    "tgn:placetype":[
        "aat:300008777"
    ]
},
  "bbox": [],
  "geometry": {"coordinates":[12.65,49.4],"type":"Point"}
}
=======
{"geometry":{"type":"Point","coordinates":[12.650000,49.400000]},"type":"Feature","properties":{"hierarchy":["tgn:7179168","tgn:7003669","tgn:1000003","tgn:7000084","tgn:7029392"],"placetype":["aat:300008777"],"id":7179168,"name:xx":"Haidberg"}}
>>>>>>> 03f74aca74312dbeaf24d7e61306dd6a786dc3d0
