{
  "id": 2031279,
  "type": "Feature",
  "properties": {
    "tgn:hierarchy":[
        "tgn:2031279",
        "tgn:1000001",
        "tgn:7012149",
        "tgn:1002886",
        "tgn:7007252",
        "tgn:7029392"
    ],
    "tgn:id":2031279,
    "tgn:name":"Candleglo Village",
    "tgn:placetype":[
        "aat:300008347"
    ]
},
  "bbox": [],
  "geometry": {"coordinates":[-85.7833,39.55],"type":"Point"}
}