{
  "id": 7319572,
  "type": "Feature",
  "properties": {
    "tgn:hierarchy":[
        "tgn:7319572",
        "tgn:7002464",
        "tgn:1000049",
        "tgn:1000002",
        "tgn:7029392"
    ],
    "tgn:id":7319572,
    "tgn:name":"Alpajere, Llano",
    "tgn:placetype":[
        "aat:300008805"
    ]
},
  "bbox": [],
  "geometry": {"coordinates":[-69.283333,-19.166667],"type":"Point"}
}