{
  "id": 7504952,
  "type": "Feature",
  "properties": {
    "tgn:hierarchy":[
        "tgn:7504952",
        "tgn:1009227",
        "tgn:1000226",
        "tgn:1000006",
        "tgn:7016850",
        "tgn:7029392"
    ],
    "tgn:id":7504952,
    "tgn:name:en":"Otumotu Point",
    "tgn:placetype":[
        "aat:300386846"
    ]
},
  "bbox": [],
  "geometry": {"coordinates":[169.25,-43.683333],"type":"Point"}
}