{
  "id": 7335698,
  "type": "Feature",
  "properties": {
    "tgn:hierarchy":[
        "tgn:7335698",
        "tgn:7008912",
        "tgn:7030216",
        "tgn:1000003",
        "tgn:1000095",
        "tgn:7029392"
    ],
    "tgn:id":7335698,
    "tgn:name":"Femosa, Arroyo de la",
    "tgn:placetype":[
        "aat:300008699"
    ]
},
  "bbox": [],
  "geometry": {"coordinates":[0.625591,41.589198],"type":"Point"}
}