{
  "id": 2357643,
  "type": "Feature",
  "properties": {
    "tgn:hierarchy":[
        "tgn:2357643",
        "tgn:1000001",
        "tgn:7012149",
        "tgn:2000381",
        "tgn:7007248",
        "tgn:7029392"
    ],
    "tgn:id":2357643,
    "tgn:name":"Graball",
    "tgn:placetype":[
        "aat:300008347"
    ]
},
  "bbox": [],
  "geometry": {"coordinates":[-82.55,33.9167],"type":"Point"}
}