{
  "id": 7313402,
  "type": "Feature",
  "properties": {
    "tgn:hierarchy":[
        "tgn:7313402",
        "tgn:1001702",
        "tgn:1000049",
        "tgn:1000002",
        "tgn:7029392"
    ],
    "tgn:id":7313402,
    "tgn:name":"Lecky Retreat",
    "tgn:placetype":[
        "aat:300008678"
    ]
},
  "bbox": [],
  "geometry": {"coordinates":[-73.983333,-51.733333],"type":"Point"}
}