{
  "id": 7227486,
  "type": "Feature",
  "properties": {
    "tgn:hierarchy":[
        "tgn:7227486",
        "tgn:7002706",
        "tgn:7002705",
        "tgn:1000003",
        "tgn:1000074",
        "tgn:7029392"
    ],
    "tgn:id":7227486,
    "tgn:name":"Logaro\u00fa, Ichthyotrofe\u00edon",
    "tgn:placetype":[
        "aat:300008688"
    ]
},
  "bbox": [],
  "geometry": {"coordinates":[20.908056,39.046667],"type":"Point"}
}