<<<<<<< HEAD
{
  "id": 7361389,
  "type": "Feature",
  "properties": {
    "tgn:hierarchy":[
        "tgn:7361389",
        "tgn:1001853",
        "tgn:1000001",
        "tgn:7005560",
        "tgn:7029392"
    ],
    "tgn:id":7361389,
    "tgn:name":"Rancho El Jabal\u00ed",
    "tgn:placetype":[
        "aat:300000241"
    ]
},
  "bbox": [],
  "geometry": {"coordinates":[-102.916667,27.5],"type":"Point"}
}
=======
{"geometry":{"type":"Point","coordinates":[-102.916667,27.500000]},"type":"Feature","properties":{"hierarchy":["tgn:7361389","tgn:1001853","tgn:1000001","tgn:7005560","tgn:7029392"],"placetype":["aat:300000241"],"id":7361389,"name:xx":"Rancho El Jabal\u00ed"}}
>>>>>>> 03f74aca74312dbeaf24d7e61306dd6a786dc3d0
