{
  "id": 7418958,
  "type": "Feature",
  "properties": {
    "tgn:hierarchy":[
        "tgn:7418958",
        "tgn:1000001",
        "tgn:7005589",
        "tgn:7005560",
        "tgn:7029392"
    ],
    "tgn:id":7418958,
    "tgn:name:es":"San Jos\u00e9 del Sitio",
    "tgn:placetype":[
        "aat:300008347"
    ]
},
  "bbox": [],
  "geometry": {"coordinates":[-100.243056,24.232778],"type":"Point"}
}