{
  "id": 2104814,
  "type": "Feature",
  "properties": {
    "tgn:hierarchy":[
        "tgn:2104814",
        "tgn:1000001",
        "tgn:7012149",
        "tgn:1002331",
        "tgn:7007826",
        "tgn:7029392"
    ],
    "tgn:id":2104814,
    "tgn:name":"Highland Village",
    "tgn:placetype":[
        "aat:300008347"
    ]
},
  "bbox": [],
  "geometry": {"coordinates":[-97.0333,33.0833],"type":"Point"}
}