{
  "id": 2097293,
  "type": "Feature",
  "properties": {
    "tgn:hierarchy":[
        "tgn:2097293",
        "tgn:1000001",
        "tgn:2001785",
        "tgn:7012149",
        "tgn:7007713",
        "tgn:7029392"
    ],
    "tgn:id":2097293,
    "tgn:name":"Kenel",
    "tgn:placetype":[
        "aat:300008347"
    ]
},
  "bbox": [],
  "geometry": {"coordinates":[-100.45,45.85],"type":"Point"}
}