<<<<<<< HEAD
{
  "id": 7368907,
  "type": "Feature",
  "properties": {
    "tgn:hierarchy":[
        "tgn:7368907",
        "tgn:1000001",
        "tgn:7005588",
        "tgn:7005560",
        "tgn:7029392"
    ],
    "tgn:id":7368907,
    "tgn:name":"Itzamatitl\u00e1n",
    "tgn:placetype":[
        "aat:300008347"
    ]
},
  "bbox": [],
  "geometry": {"coordinates":[-99.033333,18.9],"type":"Point"}
}
=======
{"geometry":{"type":"Point","coordinates":[-99.033333,18.900000]},"type":"Feature","properties":{"hierarchy":["tgn:7368907","tgn:1000001","tgn:7005588","tgn:7005560","tgn:7029392"],"placetype":["aat:300008347"],"id":7368907,"name:xx":"Itzamatitl\u00e1n"}}
>>>>>>> 03f74aca74312dbeaf24d7e61306dd6a786dc3d0
