{
  "id": 1133949,
  "type": "Feature",
  "properties": {
    "tgn:hierarchy":[
        "tgn:1133949",
        "tgn:1000001",
        "tgn:7012149",
        "tgn:7007568",
        "tgn:7029392"
    ],
    "tgn:id":1133949,
    "tgn:name":"Murder Creek",
    "tgn:placetype":[
        "aat:300008706"
    ]
},
  "bbox": [],
  "geometry": {"coordinates":[-78.35,42.8667],"type":"Point"}
}