{
  "id": 2163973,
  "type": "Feature",
  "properties": {
    "tgn:hierarchy":[
        "tgn:2163973",
        "tgn:1000001",
        "tgn:7012149",
        "tgn:2000986",
        "tgn:7007520",
        "tgn:7029392"
    ],
    "tgn:id":2163973,
    "tgn:name":"Bergland Bay",
    "tgn:placetype":[
        "aat:300132316"
    ]
},
  "bbox": [],
  "geometry": {"coordinates":[-89.5667,46.5667],"type":"Point"}
}