{
  "id": 7079124,
  "type": "Feature",
  "properties": {
    "tgn:hierarchy":[
        "tgn:7079124",
        "tgn:1000003",
        "tgn:7003677",
        "tgn:7000084",
        "tgn:7029392"
    ],
    "tgn:id":7079124,
    "tgn:name":"Bahnhof Wuppertal-Varresbeck",
    "tgn:placetype":[
        "aat:300007783"
    ]
},
  "bbox": [],
  "geometry": {"coordinates":[7.0975,51.253333],"type":"Point"}
}