{
  "id": 7522277,
  "type": "Feature",
  "properties": {
    "tgn:hierarchy":[
        "tgn:7522277",
        "tgn:7001242",
        "tgn:7001311",
        "tgn:7016833",
        "tgn:7029392"
    ],
    "tgn:id":7522277,
    "tgn:name:en":"Ab\u016b Sawmah, Ra's",
    "tgn:placetype":[
        "aat:300386846"
    ]
},
  "bbox": [],
  "geometry": {"coordinates":[33.985785,26.846896],"type":"Point"}
}