{
  "id": 7033252,
  "type": "Feature",
  "properties": {
    "tgn:hierarchy":[
        "tgn:7033252",
        "tgn:7002995",
        "tgn:1000003",
        "tgn:7002997",
        "tgn:1000080",
        "tgn:7029392"
    ],
    "tgn:id":7033252,
    "tgn:name":"Borgo",
    "tgn:placetype":[
        "aat:300008347"
    ]
},
  "bbox": [],
  "geometry": {"coordinates":[12.017778,44.988889],"type":"Point"}
}