{
  "id": 1101983,
  "type": "Feature",
  "properties": {
    "tgn:hierarchy":[
        "tgn:1101983",
        "tgn:7005685",
        "tgn:1000001",
        "tgn:7005802",
        "tgn:7029392"
    ],
    "tgn:id":1101983,
    "tgn:name":"Fort Anne National Historic Park",
    "tgn:placetype":[
        "aat:300386977"
    ]
},
  "bbox": [],
  "geometry": {"coordinates":[-65.4333,44.7333],"type":"Point"}
}