{
  "id": 2577339,
  "type": "Feature",
  "properties": {
    "tgn:hierarchy":[
        "tgn:2577339",
        "tgn:1000001",
        "tgn:7012149",
        "tgn:2001523",
        "tgn:7007709",
        "tgn:7029392"
    ],
    "tgn:id":2577339,
    "tgn:name":"Peters Point",
    "tgn:placetype":[
        "aat:300008850"
    ]
},
  "bbox": [],
  "geometry": {"coordinates":[-77.9167,33.9833],"type":"Point"}
}