{
  "id": 2727451,
  "type": "Feature",
  "properties": {
    "tgn:hierarchy":[
        "tgn:2727451",
        "tgn:1000001",
        "tgn:7012149",
        "tgn:2000181",
        "tgn:7007157",
        "tgn:7029392"
    ],
    "tgn:id":2727451,
    "tgn:name":"Trail Creek",
    "tgn:placetype":[
        "aat:300008706"
    ]
},
  "bbox": [],
  "geometry": {"coordinates":[-123.5167,41.2333],"type":"Point"}
}