{
  "id": 2746526,
  "type": "Feature",
  "properties": {
    "tgn:hierarchy":[
        "tgn:2746526",
        "tgn:1000001",
        "tgn:7012149",
        "tgn:1002557",
        "tgn:7007252",
        "tgn:7029392"
    ],
    "tgn:id":2746526,
    "tgn:name":"Wabee Lake",
    "tgn:placetype":[
        "aat:300008680"
    ]
},
  "bbox": [],
  "geometry": {"coordinates":[-85.8167,41.3833],"type":"Point"}
}