<<<<<<< HEAD
{
  "id": 7358933,
  "type": "Feature",
  "properties": {
    "tgn:hierarchy":[
        "tgn:7358933",
        "tgn:1000001",
        "tgn:1001960",
        "tgn:7005560",
        "tgn:7029392"
    ],
    "tgn:id":7358933,
    "tgn:name":"Colorado, Cerro",
    "tgn:placetype":[
        "aat:300008795"
    ]
},
  "bbox": [],
  "geometry": {"coordinates":[-111.588056,30.781389],"type":"Point"}
}
=======
{"geometry":{"type":"Point","coordinates":[-111.588056,30.781389]},"type":"Feature","properties":{"hierarchy":["tgn:7358933","tgn:1000001","tgn:1001960","tgn:7005560","tgn:7029392"],"placetype":["aat:300008795"],"id":7358933,"name:xx":"Colorado, Cerro"}}
>>>>>>> 03f74aca74312dbeaf24d7e61306dd6a786dc3d0
