<<<<<<< HEAD
{
  "id": 2154840,
  "type": "Feature",
  "properties": {
    "tgn:hierarchy":[
        "tgn:2154840",
        "tgn:7002659",
        "tgn:1000001",
        "tgn:7012149",
        "tgn:7029392"
    ],
    "tgn:id":2154840,
    "tgn:name":"Bear Hollow",
    "tgn:placetype":[
        "aat:300008761"
    ]
},
  "bbox": [],
  "geometry": {"coordinates":[-86.9,34.3167],"type":"Point"}
}
=======
{"geometry":{"type":"Point","coordinates":[-86.900000,34.316700]},"type":"Feature","properties":{"hierarchy":["tgn:2154840","tgn:7002659","tgn:1000001","tgn:7012149","tgn:7029392"],"placetype":["aat:300008761"],"id":2154840,"name:xx":"Bear Hollow"}}
>>>>>>> 03f74aca74312dbeaf24d7e61306dd6a786dc3d0
