{
  "id": 2549812,
  "type": "Feature",
  "properties": {
    "tgn:hierarchy":[
        "tgn:2549812",
        "tgn:1000001",
        "tgn:7006451",
        "tgn:7012149",
        "tgn:2000099",
        "tgn:7029392"
    ],
    "tgn:id":2549812,
    "tgn:name":"North Trick Tank",
    "tgn:placetype":[
        "aat:300006191"
    ]
},
  "bbox": [],
  "geometry": {"coordinates":[-110.4833,34.5167],"type":"Point"}
}