{
  "id": 7034488,
  "type": "Feature",
  "properties": {
    "tgn:hierarchy":[
        "tgn:7034488",
        "tgn:1003442",
        "tgn:1000003",
        "tgn:7010380",
        "tgn:1000080",
        "tgn:7029392"
    ],
    "tgn:id":7034488,
    "tgn:name":"Masseria Villanova Gattini",
    "tgn:placetype":[
        "aat:300000206"
    ]
},
  "bbox": [],
  "geometry": {"coordinates":[18.017222,40.5925],"type":"Point"}
}