{
  "id": 7183905,
  "type": "Feature",
  "properties": {
    "tgn:hierarchy":[
        "tgn:7183905",
        "tgn:1000003",
        "tgn:7003676",
        "tgn:7000084",
        "tgn:7029392"
    ],
    "tgn:id":7183905,
    "tgn:name":"Landkreis Gifhorn",
    "tgn:placetype":[
        "aat:300387198"
    ]
},
  "bbox": [],
  "geometry": {"coordinates":[10.630556,52.59],"type":"Point"}
}