{
  "id": 2213494,
  "type": "Feature",
  "properties": {
    "tgn:hierarchy":[
        "tgn:2213494",
        "tgn:1000001",
        "tgn:7012149",
        "tgn:2001715",
        "tgn:7007708",
        "tgn:7029392"
    ],
    "tgn:id":2213494,
    "tgn:name":"Cabin Spring",
    "tgn:placetype":[
        "aat:300008697"
    ]
},
  "bbox": [],
  "geometry": {"coordinates":[-120.05,43.5333],"type":"Point"}
}