{
  "id": 7035170,
  "type": "Feature",
  "properties": {
    "tgn:hierarchy":[
        "tgn:7035170",
        "tgn:1003506",
        "tgn:1000003",
        "tgn:7002993",
        "tgn:1000080",
        "tgn:7029392"
    ],
    "tgn:id":7035170,
    "tgn:name":"Vallemontana",
    "tgn:placetype":[
        "aat:300008347"
    ]
},
  "bbox": [],
  "geometry": {"coordinates":[13.282778,46.220833],"type":"Point"}
}