{
  "id": 7221454,
  "type": "Feature",
  "properties": {
    "tgn:hierarchy":[
        "tgn:7221454",
        "tgn:7011161",
        "tgn:7002674",
        "tgn:1000003",
        "tgn:1000074",
        "tgn:7029392"
    ],
    "tgn:id":7221454,
    "tgn:name":"Sim\u00f3krino",
    "tgn:placetype":[
        "aat:300387200"
    ]
},
  "bbox": [],
  "geometry": {"coordinates":[25.864444,38.550833],"type":"Point"}
}