{
  "id": 7141235,
  "type": "Feature",
  "properties": {
    "tgn:hierarchy":[
        "tgn:7141235",
        "tgn:1000003",
        "tgn:7003677",
        "tgn:7000084",
        "tgn:7029392"
    ],
    "tgn:id":7141235,
    "tgn:name":"Lipp",
    "tgn:placetype":[
        "aat:300008347"
    ]
},
  "bbox": [],
  "geometry": {"coordinates":[6.566667,50.983333],"type":"Point"}
}