{
  "id": 1033191,
  "type": "Feature",
  "properties": {
    "tgn:hierarchy":[
        "tgn:1033191",
        "tgn:1000003",
        "tgn:7002881",
        "tgn:1000070",
        "tgn:7029392"
    ],
    "tgn:id":1033191,
    "tgn:name":"Fresne-Saint-Mam\u00e8s",
    "tgn:placetype":[
        "aat:300008347"
    ]
},
  "bbox": [],
  "geometry": {"coordinates":[5.8667,47.55],"type":"Point"}
}