{
  "id": 2532765,
  "type": "Feature",
  "properties": {
    "tgn:hierarchy":[
        "tgn:2532765",
        "tgn:1000001",
        "tgn:7012149",
        "tgn:2001487",
        "tgn:7007709",
        "tgn:7029392"
    ],
    "tgn:id":2532765,
    "tgn:name":"Murphy Swamp",
    "tgn:placetype":[
        "aat:300008905"
    ]
},
  "bbox": [],
  "geometry": {"coordinates":[-78.8167,34.9333],"type":"Point"}
}