{
  "id": 7405800,
  "type": "Feature",
  "properties": {
    "tgn:hierarchy":[
        "tgn:7405800",
        "tgn:7005585",
        "tgn:1000001",
        "tgn:7005560",
        "tgn:7029392"
    ],
    "tgn:id":7405800,
    "tgn:name":"El \u00c1guila, Cerro",
    "tgn:placetype":[
        "aat:300008795"
    ]
},
  "bbox": [],
  "geometry": {"coordinates":[-101.616667,18.083333],"type":"Point"}
}