{
  "id": 2418156,
  "type": "Feature",
  "properties": {
    "tgn:hierarchy":[
        "tgn:2418156",
        "tgn:1000001",
        "tgn:1002198",
        "tgn:7012149",
        "tgn:7007826",
        "tgn:7029392"
    ],
    "tgn:id":2418156,
    "tgn:name":"Jackson, Lake",
    "tgn:placetype":[
        "aat:300008680"
    ]
},
  "bbox": [],
  "geometry": {"coordinates":[-95.4667,29.05],"type":"Point"}
}