<<<<<<< HEAD
{
  "id": 7023653,
  "type": "Feature",
  "properties": {
    "tgn:hierarchy":[
        "tgn:7023653",
        "tgn:1000001",
        "tgn:7012149",
        "tgn:7007520",
        "tgn:7029392"
    ],
    "tgn:id":7023653,
    "tgn:name":"Pendock Pond",
    "tgn:placetype":[
        "aat:300008680"
    ]
},
  "bbox": [],
  "geometry": {"coordinates":[-89.6333,46.5667],"type":"Point"}
}
=======
{"geometry":{"type":"Point","coordinates":[-89.633300,46.566700]},"type":"Feature","properties":{"hierarchy":["tgn:7023653","tgn:1000001","tgn:7012149","tgn:7007520","tgn:7029392"],"placetype":["aat:300008680"],"id":7023653,"name:xx":"Pendock Pond"}}
>>>>>>> 03f74aca74312dbeaf24d7e61306dd6a786dc3d0
