{
  "id": 7023653,
  "type": "Feature",
  "properties": {
    "tgn:hierarchy":[
        "tgn:7023653",
        "tgn:1000001",
        "tgn:7012149",
        "tgn:7007520",
        "tgn:7029392"
    ],
    "tgn:id":7023653,
    "tgn:name":"Pendock Pond",
    "tgn:placetype":[
        "aat:300008680"
    ]
},
  "bbox": [],
  "geometry": {"coordinates":[-89.6333,46.5667],"type":"Point"}
}