{
  "id": 7050384,
  "type": "Feature",
  "properties": {
    "tgn:hierarchy":[
        "tgn:7050384",
        "tgn:1001730",
        "tgn:1000003",
        "tgn:7003121",
        "tgn:1000080",
        "tgn:7029392"
    ],
    "tgn:id":7050384,
    "tgn:name":"Norbello",
    "tgn:placetype":[
        "aat:300008347"
    ]
},
  "bbox": [],
  "geometry": {"coordinates":[8.833333,40.133333],"type":"Point"}
}