{
  "id": 7590995,
  "type": "Feature",
  "properties": {
    "tgn:hierarchy":[
        "tgn:7590995",
        "tgn:1000004",
        "tgn:7000198",
        "tgn:7031786",
        "tgn:7029392"
    ],
    "tgn:id":7590995,
    "tgn:name:en":"Sart\u0101ll",
    "tgn:placetype":[
        "aat:300008347"
    ]
},
  "bbox": [],
  "geometry": {"coordinates":[77.980278,30.4875],"type":"Point"}
}