{
  "id": 7443573,
  "type": "Feature",
  "properties": {
    "tgn:hierarchy":[
        "tgn:7443573",
        "tgn:7002445",
        "tgn:1000003",
        "tgn:7008166",
        "tgn:7008591",
        "tgn:7029392"
    ],
    "tgn:id":7443573,
    "tgn:name:en":"Old Horse Rocks",
    "tgn:placetype":[
        "aat:300011692"
    ]
},
  "bbox": [],
  "geometry": {"coordinates":[-0.3125,54.236111],"type":"Point"}
}