{
  "id": 2466179,
  "type": "Feature",
  "properties": {
    "tgn:hierarchy":[
        "tgn:2466179",
        "tgn:1000001",
        "tgn:7012149",
        "tgn:1002515",
        "tgn:7007252",
        "tgn:7029392"
    ],
    "tgn:id":2466179,
    "tgn:name":"Lonesome Hollow",
    "tgn:placetype":[
        "aat:300008761"
    ]
},
  "bbox": [],
  "geometry": {"coordinates":[-85.35,38.7333],"type":"Point"}
}