{
  "id": 7225249,
  "type": "Feature",
  "properties": {
    "tgn:hierarchy":[
        "tgn:7225249",
        "tgn:7011270",
        "tgn:7002674",
        "tgn:1000003",
        "tgn:1000074",
        "tgn:7029392"
    ],
    "tgn:id":7225249,
    "tgn:name":"Petal\u00eddes, Vr\u00e1choi",
    "tgn:placetype":[
        "aat:300011692"
    ]
},
  "bbox": [],
  "geometry": {"coordinates":[25.074444,36.950833],"type":"Point"}
}