{
  "id": 2747899,
  "type": "Feature",
  "properties": {
    "tgn:hierarchy":[
        "tgn:2747899",
        "tgn:1000001",
        "tgn:7012149",
        "tgn:2001295",
        "tgn:7007524",
        "tgn:7029392"
    ],
    "tgn:id":2747899,
    "tgn:name":"Walchuk Spring",
    "tgn:placetype":[
        "aat:300008697"
    ]
},
  "bbox": [],
  "geometry": {"coordinates":[-107.6667,48.9833],"type":"Point"}
}