{
  "id": 2687305,
  "type": "Feature",
  "properties": {
    "tgn:hierarchy":[
        "tgn:2687305",
        "tgn:1000001",
        "tgn:7012149",
        "tgn:2000930",
        "tgn:7007515",
        "tgn:7029392"
    ],
    "tgn:id":2687305,
    "tgn:name":"Spring Lake",
    "tgn:placetype":[
        "aat:300008347"
    ]
},
  "bbox": [],
  "geometry": {"coordinates":[-70.2833,45.2167],"type":"Point"}
}