<<<<<<< HEAD
{
  "id": 2707470,
  "type": "Feature",
  "properties": {
    "tgn:hierarchy":[
        "tgn:2707470",
        "tgn:2002142",
        "tgn:1000001",
        "tgn:7012149",
        "tgn:7007919",
        "tgn:7029392"
    ],
    "tgn:id":2707470,
    "tgn:name":"Sweet Spring Hollow",
    "tgn:placetype":[
        "aat:300008761"
    ]
},
  "bbox": [],
  "geometry": {"coordinates":[-79.3667,38.1],"type":"Point"}
}
=======
{"geometry":{"type":"Point","coordinates":[-79.366700,38.100000]},"type":"Feature","properties":{"hierarchy":["tgn:2707470","tgn:2002142","tgn:1000001","tgn:7012149","tgn:7007919","tgn:7029392"],"placetype":["aat:300008761"],"id":2707470,"name:xx":"Sweet Spring Hollow"}}
>>>>>>> 03f74aca74312dbeaf24d7e61306dd6a786dc3d0
