{
  "id": 7550993,
  "type": "Feature",
  "properties": {
    "tgn:hierarchy":[
        "tgn:7550993",
        "tgn:1000004",
        "tgn:1001869",
        "tgn:7000198",
        "tgn:7029392"
    ],
    "tgn:id":7550993,
    "tgn:name:en":"Blunt Channel",
    "tgn:placetype":[
        "aat:300008713"
    ]
},
  "bbox": [],
  "geometry": {"coordinates":[69.653333,22.407778],"type":"Point"}
}