{
  "id": 7218208,
  "type": "Feature",
  "properties": {
    "tgn:hierarchy":[
        "tgn:7218208",
        "tgn:7011161",
        "tgn:7002674",
        "tgn:1000003",
        "tgn:1000074",
        "tgn:7029392"
    ],
    "tgn:id":7218208,
    "tgn:name":"Tr\u00fdpanos",
    "tgn:placetype":[
        "aat:300008798"
    ]
},
  "bbox": [],
  "geometry": {"coordinates":[25.923611,38.252222],"type":"Point"}
}