{
  "id": 7584753,
  "type": "Feature",
  "properties": {
    "tgn:hierarchy":[
        "tgn:7584753",
        "tgn:1000004",
        "tgn:7000198",
        "tgn:1001894",
        "tgn:7029392"
    ],
    "tgn:id":7584753,
    "tgn:name:en":"Baretha",
    "tgn:placetype":[
        "aat:300008347"
    ]
},
  "bbox": [],
  "geometry": {"coordinates":[78.062706,24.088004],"type":"Point"}
}