{
  "id": 2317921,
  "type": "Feature",
  "properties": {
    "tgn:hierarchy":[
        "tgn:2317921",
        "tgn:1000001",
        "tgn:1002275",
        "tgn:7012149",
        "tgn:7007920",
        "tgn:7029392"
    ],
    "tgn:id":2317921,
    "tgn:name":"English Pit",
    "tgn:placetype":[
        "aat:300386845"
    ]
},
  "bbox": [],
  "geometry": {"coordinates":[-122.4667,45.6167],"type":"Point"}
}