{
  "id": 7363121,
  "type": "Feature",
  "properties": {
    "tgn:hierarchy":[
        "tgn:7363121",
        "tgn:1000001",
        "tgn:7005591",
        "tgn:7005560",
        "tgn:7029392"
    ],
    "tgn:id":7363121,
    "tgn:name":"El Espinal",
    "tgn:placetype":[
        "aat:300008347"
    ]
},
  "bbox": [],
  "geometry": {"coordinates":[-94.066667,16.333333],"type":"Point"}
}