{
  "id": 2066292,
  "type": "Feature",
  "properties": {
    "tgn:hierarchy":[
        "tgn:2066292",
        "tgn:1000001",
        "tgn:1002934",
        "tgn:7012149",
        "tgn:7007565",
        "tgn:7029392"
    ],
    "tgn:id":2066292,
    "tgn:name":"Swartswood",
    "tgn:placetype":[
        "aat:300008347"
    ]
},
  "bbox": [],
  "geometry": {"coordinates":[-74.8167,41.0833],"type":"Point"}
}