{
  "id": 1032759,
  "type": "Feature",
  "properties": {
    "tgn:hierarchy":[
        "tgn:1032759",
        "tgn:1000003",
        "tgn:7002890",
        "tgn:1000070",
        "tgn:7029392"
    ],
    "tgn:id":1032759,
    "tgn:name":"Corbeny",
    "tgn:placetype":[
        "aat:300008347"
    ]
},
  "bbox": [],
  "geometry": {"coordinates":[3.8333,49.4667],"type":"Point"}
}