{
  "id": 7396826,
  "type": "Feature",
  "properties": {
    "tgn:hierarchy":[
        "tgn:7396826",
        "tgn:7005581",
        "tgn:1000001",
        "tgn:7005560",
        "tgn:7029392"
    ],
    "tgn:id":7396826,
    "tgn:name":"Rancho San Rafael",
    "tgn:placetype":[
        "aat:300000241"
    ]
},
  "bbox": [],
  "geometry": {"coordinates":[-105.716667,28.15],"type":"Point"}
}