{
  "id": 7236350,
  "type": "Feature",
  "properties": {
    "tgn:hierarchy":[
        "tgn:7236350",
        "tgn:7011163",
        "tgn:7002674",
        "tgn:1000003",
        "tgn:1000074",
        "tgn:7029392"
    ],
    "tgn:id":7236350,
    "tgn:name":"\u00c1no Ch\u00e1likas",
    "tgn:placetype":[
        "aat:300008347"
    ]
},
  "bbox": [],
  "geometry": {"coordinates":[26.55,39.083333],"type":"Point"}
}