{
  "id": 7257840,
  "type": "Feature",
  "properties": {
    "tgn:hierarchy":[
        "tgn:7257840",
        "tgn:7003458",
        "tgn:1000003",
        "tgn:1000063",
        "tgn:7018236",
        "tgn:7029392"
    ],
    "tgn:id":7257840,
    "tgn:name":"Wulvergem",
    "tgn:placetype":[
        "aat:300008347"
    ]
},
  "bbox": [],
  "geometry": {"coordinates":[2.852427,50.760208],"type":"Point"}
}