{
  "id": 1119428,
  "type": "Feature",
  "properties": {
    "tgn:hierarchy":[
        "tgn:1119428",
        "tgn:1000001",
        "tgn:7012149",
        "tgn:7014160",
        "tgn:7007919",
        "tgn:7029392"
    ],
    "tgn:id":1119428,
    "tgn:name":"Barcroft, Lake",
    "tgn:placetype":[
        "aat:300006191"
    ]
},
  "bbox": [],
  "geometry": {"coordinates":[-77.1333,38.8333],"type":"Point"}
}