{
  "id": 7366754,
  "type": "Feature",
  "properties": {
    "tgn:hierarchy":[
        "tgn:7366754",
        "tgn:7005586",
        "tgn:1000001",
        "tgn:7005560",
        "tgn:7029392"
    ],
    "tgn:id":7366754,
    "tgn:name":"El Rinc\u00f3n",
    "tgn:placetype":[
        "aat:300006191"
    ]
},
  "bbox": [],
  "geometry": {"coordinates":[-103.483333,20.216667],"type":"Point"}
}