{
  "id": 2516195,
  "type": "Feature",
  "properties": {
    "tgn:hierarchy":[
        "tgn:2516195",
        "tgn:1000001",
        "tgn:7012149",
        "tgn:2002125",
        "tgn:7007827",
        "tgn:7029392"
    ],
    "tgn:id":2516195,
    "tgn:name":"Mine Hollow",
    "tgn:placetype":[
        "aat:300008761"
    ]
},
  "bbox": [],
  "geometry": {"coordinates":[-111.1833,40.0167],"type":"Point"}
}