{
  "id": 2499865,
  "type": "Feature",
  "properties": {
    "tgn:hierarchy":[
        "tgn:2499865",
        "tgn:7006450",
        "tgn:1000001",
        "tgn:7019674",
        "tgn:7012149",
        "tgn:7029392"
    ],
    "tgn:id":2499865,
    "tgn:name":"McCoy Creek",
    "tgn:placetype":[
        "aat:300008706"
    ]
},
  "bbox": [],
  "geometry": {"coordinates":[-145.9167,64.4167],"type":"Point"}
}