{
  "id": 7538777,
  "type": "Feature",
  "properties": {
    "tgn:hierarchy":[
        "tgn:7538777",
        "tgn:7001242",
        "tgn:7016833",
        "tgn:7001336",
        "tgn:7029392"
    ],
    "tgn:id":7538777,
    "tgn:name":"Ruwaykinah, W\u0101d\u012b",
    "tgn:placetype":[
        "aat:300379998"
    ]
},
  "bbox": [],
  "geometry": {"coordinates":[33.40754,29.12078],"type":"Point"}
}