{
  "id": 2159813,
  "type": "Feature",
  "properties": {
    "tgn:hierarchy":[
        "tgn:2159813",
        "tgn:1000001",
        "tgn:7012149",
        "tgn:2000548",
        "tgn:7007252",
        "tgn:7029392"
    ],
    "tgn:id":2159813,
    "tgn:name":"Beech Creek",
    "tgn:placetype":[
        "aat:300008706"
    ]
},
  "bbox": [],
  "geometry": {"coordinates":[-86.9333,39.2333],"type":"Point"}
}