{
  "id": 7494456,
  "type": "Feature",
  "properties": {
    "tgn:hierarchy":[
        "tgn:7494456",
        "tgn:1000004",
        "tgn:7001014",
        "tgn:1000141",
        "tgn:7029392"
    ],
    "tgn:id":7494456,
    "tgn:name":"Renwang Qiao",
    "tgn:placetype":[
        "aat:300007836"
    ]
},
  "bbox": [],
  "geometry": {"coordinates":[120.493015,23.693509],"type":"Point"}
}