{
  "id": 2642671,
  "type": "Feature",
  "properties": {
    "tgn:hierarchy":[
        "tgn:2642671",
        "tgn:1000001",
        "tgn:2002242",
        "tgn:7012149",
        "tgn:7007920",
        "tgn:7029392"
    ],
    "tgn:id":2642671,
    "tgn:name":"Sanderson Creek",
    "tgn:placetype":[
        "aat:300008706"
    ]
},
  "bbox": [],
  "geometry": {"coordinates":[-119.0833,48.0167],"type":"Point"}
}