{
  "id": 7451106,
  "type": "Feature",
  "properties": {
    "tgn:hierarchy":[
        "tgn:7451106",
        "tgn:7002445",
        "tgn:1000003",
        "tgn:7008165",
        "tgn:7008591",
        "tgn:7029392"
    ],
    "tgn:id":7451106,
    "tgn:name:en":"Dunstanburgh Castle",
    "tgn:placetype":[
        "aat:300387007"
    ]
},
  "bbox": [],
  "geometry": {"coordinates":[-1.583333,55.483333],"type":"Point"}
}