{
  "id": 2777093,
  "type": "Feature",
  "properties": {
    "tgn:hierarchy":[
        "tgn:2777093",
        "tgn:1000001",
        "tgn:2001472",
        "tgn:7012149",
        "tgn:7007709",
        "tgn:7029392"
    ],
    "tgn:id":2777093,
    "tgn:name":"Windy Point",
    "tgn:placetype":[
        "aat:300008850"
    ]
},
  "bbox": [],
  "geometry": {"coordinates":[-78.35,33.9167],"type":"Point"}
}