<<<<<<< HEAD
{
  "id": 2151979,
  "type": "Feature",
  "properties": {
    "tgn:hierarchy":[
        "tgn:2151979",
        "tgn:1000001",
        "tgn:7012149",
        "tgn:1002904",
        "tgn:7007710",
        "tgn:7029392"
    ],
    "tgn:id":2151979,
    "tgn:name":"Baughman Rocks",
    "tgn:placetype":[
        "aat:300008798"
    ]
},
  "bbox": [],
  "geometry": {"coordinates":[-79.1667,39.7833],"type":"Point"}
}
=======
{"geometry":{"type":"Point","coordinates":[-79.166700,39.783300]},"type":"Feature","properties":{"hierarchy":["tgn:2151979","tgn:1000001","tgn:7012149","tgn:1002904","tgn:7007710","tgn:7029392"],"placetype":["aat:300008798"],"id":2151979,"name:xx":"Baughman Rocks"}}
>>>>>>> 03f74aca74312dbeaf24d7e61306dd6a786dc3d0
