{
  "id": 2151979,
  "type": "Feature",
  "properties": {
    "tgn:hierarchy":[
        "tgn:2151979",
        "tgn:1000001",
        "tgn:7012149",
        "tgn:1002904",
        "tgn:7007710",
        "tgn:7029392"
    ],
    "tgn:id":2151979,
    "tgn:name":"Baughman Rocks",
    "tgn:placetype":[
        "aat:300008798"
    ]
},
  "bbox": [],
  "geometry": {"coordinates":[-79.1667,39.7833],"type":"Point"}
}