{
  "id": 1073480,
  "type": "Feature",
  "properties": {
    "tgn:hierarchy":[
        "tgn:1073480",
        "tgn:1000004",
        "tgn:7002081",
        "tgn:1000111",
        "tgn:7029392"
    ],
    "tgn:id":1073480,
    "tgn:name":"Yaxigang",
    "tgn:placetype":[
        "aat:300008347"
    ]
},
  "bbox": [],
  "geometry": {"coordinates":[119.1667,31.3667],"type":"Point"}
}