{
  "id": 2203036,
  "type": "Feature",
  "properties": {
    "tgn:hierarchy":[
        "tgn:2203036",
        "tgn:1000001",
        "tgn:7016101",
        "tgn:7012149",
        "tgn:7007516",
        "tgn:7029392"
    ],
    "tgn:id":2203036,
    "tgn:name":"Buckeystown Station",
    "tgn:placetype":[
        "aat:300008347"
    ]
},
  "bbox": [],
  "geometry": {"coordinates":[-77.4333,39.3167],"type":"Point"}
}