{
  "id": 2612579,
  "type": "Feature",
  "properties": {
    "tgn:hierarchy":[
        "tgn:2612579",
        "tgn:1000001",
        "tgn:7012149",
        "tgn:2000960",
        "tgn:7007520",
        "tgn:7029392"
    ],
    "tgn:id":2612579,
    "tgn:name":"Redboat Lake",
    "tgn:placetype":[
        "aat:300008680"
    ]
},
  "bbox": [],
  "geometry": {"coordinates":[-89.7667,46.3333],"type":"Point"}
}