{
  "id": 7591773,
  "type": "Feature",
  "properties": {
    "tgn:hierarchy":[
        "tgn:7591773",
        "tgn:1000004",
        "tgn:7000198",
        "tgn:7000799",
        "tgn:7029392"
    ],
    "tgn:id":7591773,
    "tgn:name:en":"Dang\u012b\u0101na Camp",
    "tgn:placetype":[
        "aat:300000517"
    ]
},
  "bbox": [],
  "geometry": {"coordinates":[74.863889,32.677778],"type":"Point"}
}