{
  "id": 7333753,
  "type": "Feature",
  "properties": {
    "tgn:hierarchy":[
        "tgn:7333753",
        "tgn:7002759",
        "tgn:7008909",
        "tgn:1000003",
        "tgn:1000095",
        "tgn:7029392"
    ],
    "tgn:id":7333753,
    "tgn:name":"Escan\u00e9",
    "tgn:placetype":[
        "aat:300008347"
    ]
},
  "bbox": [],
  "geometry": {"coordinates":[0.676267,42.455652],"type":"Point"}
}