{
  "id": 7294575,
  "type": "Feature",
  "properties": {
    "tgn:hierarchy":[
        "tgn:7294575",
        "tgn:7002844",
        "tgn:7030216",
        "tgn:1000003",
        "tgn:1000095",
        "tgn:7029392"
    ],
    "tgn:id":7294575,
    "tgn:name":"Vallplana, Sierra de",
    "tgn:placetype":[
        "aat:300266640"
    ]
},
  "bbox": [],
  "geometry": {"coordinates":[0.516667,40.983333],"type":"Point"}
}