{
  "id": 2439911,
  "type": "Feature",
  "properties": {
    "tgn:hierarchy":[
        "tgn:2439911",
        "tgn:1000001",
        "tgn:7012149",
        "tgn:2001106",
        "tgn:7007522",
        "tgn:7029392"
    ],
    "tgn:id":2439911,
    "tgn:name":"Kittrell Mill Creek",
    "tgn:placetype":[
        "aat:300008706"
    ]
},
  "bbox": [],
  "geometry": {"coordinates":[-88.7167,31.2833],"type":"Point"}
}