{
  "id": 2497888,
  "type": "Feature",
  "properties": {
    "tgn:hierarchy":[
        "tgn:2497888",
        "tgn:1000001",
        "tgn:2000459",
        "tgn:7012149",
        "tgn:7007250",
        "tgn:7029392"
    ],
    "tgn:id":2497888,
    "tgn:name":"Mayflower Mine",
    "tgn:placetype":[
        "aat:300000390"
    ]
},
  "bbox": [],
  "geometry": {"coordinates":[-115.9833,43.95],"type":"Point"}
}