{
  "id": 2120507,
  "type": "Feature",
  "properties": {
    "tgn:hierarchy":[
        "tgn:2120507",
        "tgn:1000001",
        "tgn:2002256",
        "tgn:7012149",
        "tgn:7013961",
        "tgn:7029392"
    ],
    "tgn:id":2120507,
    "tgn:name":"Wilsie",
    "tgn:placetype":[
        "aat:300008347"
    ]
},
  "bbox": [],
  "geometry": {"coordinates":[-80.8833,38.6833],"type":"Point"}
}