{
  "id": 2242877,
  "type": "Feature",
  "properties": {
    "tgn:hierarchy":[
        "tgn:2242877",
        "tgn:1000001",
        "tgn:7006451",
        "tgn:2000095",
        "tgn:7012149",
        "tgn:7029392"
    ],
    "tgn:id":2242877,
    "tgn:name":"Clear Creek Ridge Tank",
    "tgn:placetype":[
        "aat:300006191"
    ]
},
  "bbox": [],
  "geometry": {"coordinates":[-109.2167,33.3167],"type":"Point"}
}