<<<<<<< HEAD
{
  "id": 7485633,
  "type": "Feature",
  "properties": {
    "tgn:hierarchy":[
        "tgn:7485633",
        "tgn:1000004",
        "tgn:7490934",
        "tgn:1000141",
        "tgn:7029392"
    ],
    "tgn:id":7485633,
    "tgn:name":"Nanning Guozhong",
    "tgn:placetype":[
        "aat:300006495"
    ]
},
  "bbox": [],
  "geometry": {"coordinates":[120.187778,22.936389],"type":"Point"}
}
=======
{"geometry":{"type":"Point","coordinates":[120.187778,22.936389]},"type":"Feature","properties":{"hierarchy":["tgn:7485633","tgn:1000004","tgn:7490934","tgn:1000141","tgn:7029392"],"placetype":["aat:300006495"],"id":7485633,"name:xx":"Nanning Guozhong"}}
>>>>>>> 03f74aca74312dbeaf24d7e61306dd6a786dc3d0
