{
  "id": 2160232,
  "type": "Feature",
  "properties": {
    "tgn:hierarchy":[
        "tgn:2160232",
        "tgn:1000001",
        "tgn:7012149",
        "tgn:2002119",
        "tgn:7007827",
        "tgn:7029392"
    ],
    "tgn:id":2160232,
    "tgn:name":"Beef Basin",
    "tgn:placetype":[
        "aat:300386845"
    ]
},
  "bbox": [],
  "geometry": {"coordinates":[-109.9167,37.9667],"type":"Point"}
}