{
  "id": 2776851,
  "type": "Feature",
  "properties": {
    "tgn:hierarchy":[
        "tgn:2776851",
        "tgn:1000001",
        "tgn:7012149",
        "tgn:7007158",
        "tgn:2000253",
        "tgn:7029392"
    ],
    "tgn:id":2776851,
    "tgn:name":"Windsor Lake Reservoir",
    "tgn:placetype":[
        "aat:300006191"
    ]
},
  "bbox": [],
  "geometry": {"coordinates":[-104.8833,40.4833],"type":"Point"}
}