{
  "id": 7493649,
  "type": "Feature",
  "properties": {
    "tgn:hierarchy":[
        "tgn:7493649",
        "tgn:1000004",
        "tgn:1000454",
        "tgn:1000141",
        "tgn:7029392"
    ],
    "tgn:id":7493649,
    "tgn:name":"Huyi Yikeng",
    "tgn:placetype":[
        "aat:300008347"
    ]
},
  "bbox": [],
  "geometry": {"coordinates":[121.358915,24.962689],"type":"Point"}
}