{
  "id": 2067000,
  "type": "Feature",
  "properties": {
    "tgn:hierarchy":[
        "tgn:2067000",
        "tgn:1000001",
        "tgn:7012149",
        "tgn:2001454",
        "tgn:7007566",
        "tgn:7029392"
    ],
    "tgn:id":2067000,
    "tgn:name":"Glorieta",
    "tgn:placetype":[
        "aat:300008347"
    ]
},
  "bbox": [],
  "geometry": {"coordinates":[-105.7667,35.5667],"type":"Point"}
}