{
  "id": 1010257,
  "type": "Feature",
  "properties": {
    "tgn:hierarchy":[
        "tgn:1010257",
        "tgn:7018312",
        "tgn:1000001",
        "tgn:7004545",
        "tgn:7029392"
    ],
    "tgn:id":1010257,
    "tgn:name":"Saintes, \u00celes des",
    "tgn:placetype":[
        "aat:300386853"
    ]
},
  "bbox": [],
  "geometry": {"coordinates":[-61.6167,15.8667],"type":"Point"}
}