{
  "id": 2024037,
  "type": "Feature",
  "properties": {
    "tgn:hierarchy":[
        "tgn:2024037",
        "tgn:1000001",
        "tgn:7012149",
        "tgn:2000405",
        "tgn:7007248",
        "tgn:7029392"
    ],
    "tgn:id":2024037,
    "tgn:name":"Reidsboro",
    "tgn:placetype":[
        "aat:300008347",
        "aat:300387210"
    ]
},
  "bbox": [],
  "geometry": {"coordinates":[-84.3833,33.1333],"type":"Point"}
}