{
  "id": 2735524,
  "type": "Feature",
  "properties": {
    "tgn:hierarchy":[
        "tgn:2735524",
        "tgn:1000001",
        "tgn:7012149",
        "tgn:2001275",
        "tgn:7007524",
        "tgn:7029392"
    ],
    "tgn:id":2735524,
    "tgn:name":"Twin Creek",
    "tgn:placetype":[
        "aat:300008706"
    ]
},
  "bbox": [],
  "geometry": {"coordinates":[-111.2833,45.4333],"type":"Point"}
}