{
  "id": 7507002,
  "type": "Feature",
  "properties": {
    "tgn:hierarchy":[
        "tgn:7507002",
        "tgn:1009227",
        "tgn:1000226",
        "tgn:1000006",
        "tgn:7016850",
        "tgn:7029392"
    ],
    "tgn:id":7507002,
    "tgn:name:en":"Rameses, Mount",
    "tgn:placetype":[
        "aat:300008795"
    ]
},
  "bbox": [],
  "geometry": {"coordinates":[171.95,-42.45],"type":"Point"}
}