{
  "id": 2412410,
  "type": "Feature",
  "properties": {
    "tgn:hierarchy":[
        "tgn:2412410",
        "tgn:1000001",
        "tgn:7012149",
        "tgn:2001458",
        "tgn:7007566",
        "tgn:7029392"
    ],
    "tgn:id":2412410,
    "tgn:name":"Indian Tank",
    "tgn:placetype":[
        "aat:300006191"
    ]
},
  "bbox": [],
  "geometry": {"coordinates":[-106.0333,34.4833],"type":"Point"}
}