{
  "id": 1068988,
  "type": "Feature",
  "properties": {
    "tgn:hierarchy":[
        "tgn:1068988",
        "tgn:1000004",
        "tgn:7002079",
        "tgn:1000111",
        "tgn:7029392"
    ],
    "tgn:id":1068988,
    "tgn:name":"Huayuan",
    "tgn:placetype":[
        "aat:300008347"
    ]
},
  "bbox": [],
  "geometry": {"coordinates":[109.2167,28.5667],"type":"Point"}
}