{
  "id": 2417031,
  "type": "Feature",
  "properties": {
    "tgn:hierarchy":[
        "tgn:2417031",
        "tgn:1000001",
        "tgn:2000506",
        "tgn:7012149",
        "tgn:7007251",
        "tgn:7029392"
    ],
    "tgn:id":2417031,
    "tgn:name":"Jackie Branch",
    "tgn:placetype":[
        "aat:300008699"
    ]
},
  "bbox": [],
  "geometry": {"coordinates":[-89.0333,38.1167],"type":"Point"}
}