{
  "id": 7048101,
  "type": "Feature",
  "properties": {
    "tgn:hierarchy":[
        "tgn:7048101",
        "tgn:7003006",
        "tgn:1000003",
        "tgn:7002997",
        "tgn:1000080",
        "tgn:7029392"
    ],
    "tgn:id":7048101,
    "tgn:name":"Casa Martinuzzi",
    "tgn:placetype":[
        "aat:300008347"
    ]
},
  "bbox": [],
  "geometry": {"coordinates":[12.383333,45.45],"type":"Point"}
}