{
  "id": 7077540,
  "type": "Feature",
  "properties": {
    "tgn:hierarchy":[
        "tgn:7077540",
        "tgn:1000003",
        "tgn:7003676",
        "tgn:7000084",
        "tgn:7029392"
    ],
    "tgn:id":7077540,
    "tgn:name":"Reede von Freiburg",
    "tgn:placetype":[
        "aat:300008217"
    ]
},
  "bbox": [],
  "geometry": {"coordinates":[9.333333,53.833333],"type":"Point"}
}