{
  "id": 2663017,
  "type": "Feature",
  "properties": {
    "tgn:hierarchy":[
        "tgn:2663017",
        "tgn:1000001",
        "tgn:7012149",
        "tgn:2001440",
        "tgn:7007566",
        "tgn:7029392"
    ],
    "tgn:id":2663017,
    "tgn:name":"Silver Bell Mine",
    "tgn:placetype":[
        "aat:300000390"
    ]
},
  "bbox": [],
  "geometry": {"coordinates":[-108.75,32.2333],"type":"Point"}
}