{
  "id": 2077174,
  "type": "Feature",
  "properties": {
    "tgn:hierarchy":[
        "tgn:2077174",
        "tgn:1000001",
        "tgn:7012149",
        "tgn:2001521",
        "tgn:7007709",
        "tgn:7029392"
    ],
    "tgn:id":2077174,
    "tgn:name":"Whispering Pines",
    "tgn:placetype":[
        "aat:300008347"
    ]
},
  "bbox": [],
  "geometry": {"coordinates":[-79.3667,35.25],"type":"Point"}
}