{
  "id": 2415251,
  "type": "Feature",
  "properties": {
    "tgn:hierarchy":[
        "tgn:2415251",
        "tgn:1000001",
        "tgn:2002107",
        "tgn:7012149",
        "tgn:7007827",
        "tgn:7029392"
    ],
    "tgn:id":2415251,
    "tgn:name":"Island Lake",
    "tgn:placetype":[
        "aat:300008680"
    ]
},
  "bbox": [],
  "geometry": {"coordinates":[-110.2333,40.6833],"type":"Point"}
}