{
  "id": 7423211,
  "type": "Feature",
  "properties": {
    "tgn:hierarchy":[
        "tgn:7423211",
        "tgn:1000001",
        "tgn:1001960",
        "tgn:7005560",
        "tgn:7029392"
    ],
    "tgn:id":7423211,
    "tgn:name":"Salina, Bah\u00eda",
    "tgn:placetype":[
        "aat:300132316"
    ]
},
  "bbox": [],
  "geometry": {"coordinates":[-113.083333,31.033333],"type":"Point"}
}