{
  "id": 1015769,
  "type": "Feature",
  "properties": {
    "tgn:hierarchy":[
        "tgn:1015769",
        "tgn:7005685",
        "tgn:1000001",
        "tgn:7005804",
        "tgn:7029392"
    ],
    "tgn:id":1015769,
    "tgn:name":"Shawinigan-Sud",
    "tgn:placetype":[
        "aat:300008347"
    ]
},
  "bbox": [],
  "geometry": {"coordinates":[-72.75,46.5333],"type":"Point"}
}