<<<<<<< HEAD
{
  "id": 7050841,
  "type": "Feature",
  "properties": {
    "tgn:hierarchy":[
        "tgn:7050841",
        "tgn:1003489",
        "tgn:7004610",
        "tgn:1000003",
        "tgn:1000080",
        "tgn:7029392"
    ],
    "tgn:id":7050841,
    "tgn:name":"Masi",
    "tgn:placetype":[
        "aat:300008347"
    ]
},
  "bbox": [],
  "geometry": {"coordinates":[15.716667,40.8],"type":"Point"}
}
=======
{"geometry":{"type":"Point","coordinates":[15.716667,40.800000]},"type":"Feature","properties":{"hierarchy":["tgn:7050841","tgn:1003489","tgn:7004610","tgn:1000003","tgn:1000080","tgn:7029392"],"placetype":["aat:300008347"],"id":7050841,"name:xx":"Masi"}}
>>>>>>> 03f74aca74312dbeaf24d7e61306dd6a786dc3d0
