{
  "id": 2659601,
  "type": "Feature",
  "properties": {
    "tgn:hierarchy":[
        "tgn:2659601",
        "tgn:1000001",
        "tgn:7012149",
        "tgn:2001029",
        "tgn:7007521",
        "tgn:7029392"
    ],
    "tgn:id":2659601,
    "tgn:name":"Shingle Mill Lake",
    "tgn:placetype":[
        "aat:300008680"
    ]
},
  "bbox": [],
  "geometry": {"coordinates":[-93.75,47.0667],"type":"Point"}
}