{
  "id": 2650414,
  "type": "Feature",
  "properties": {
    "tgn:hierarchy":[
        "tgn:2650414",
        "tgn:1000001",
        "tgn:7012149",
        "tgn:2000450",
        "tgn:7007248",
        "tgn:7029392"
    ],
    "tgn:id":2650414,
    "tgn:name":"Sears Lake",
    "tgn:placetype":[
        "aat:300006191"
    ]
},
  "bbox": [],
  "geometry": {"coordinates":[-83.95,31.4667],"type":"Point"}
}