{
  "id": 7531382,
  "type": "Feature",
  "properties": {
    "tgn:hierarchy":[
        "tgn:7531382",
        "tgn:7001242",
        "tgn:7016833",
        "tgn:1001091",
        "tgn:7029392"
    ],
    "tgn:id":7531382,
    "tgn:name":"Jam'\u012byat \u015ead\u012bq\u0101t al Kit\u0101b al Muqaddas",
    "tgn:placetype":[
        "aat:300004792"
    ]
},
  "bbox": [],
  "geometry": {"coordinates":[31.279322,30.087516],"type":"Point"}
}