{
  "id": 7371097,
  "type": "Feature",
  "properties": {
    "tgn:hierarchy":[
        "tgn:7371097",
        "tgn:7005583",
        "tgn:1000001",
        "tgn:7005560",
        "tgn:7029392"
    ],
    "tgn:id":7371097,
    "tgn:name":"Huizquelite",
    "tgn:placetype":[
        "aat:300008347"
    ]
},
  "bbox": [],
  "geometry": {"coordinates":[-106.333333,24.566667],"type":"Point"}
}