{
  "id": 2573455,
  "type": "Feature",
  "properties": {
    "tgn:hierarchy":[
        "tgn:2573455",
        "tgn:1000001",
        "tgn:7012149",
        "tgn:7007707",
        "tgn:7029392"
    ],
    "tgn:id":2573455,
    "tgn:name":"Pecan Creek",
    "tgn:placetype":[
        "aat:300008706"
    ]
},
  "bbox": [],
  "geometry": {"coordinates":[-98.5167,34.6667],"type":"Point"}
}