{
  "id": 2670475,
  "type": "Feature",
  "properties": {
    "tgn:hierarchy":[
        "tgn:2670475",
        "tgn:1000001",
        "tgn:7012149",
        "tgn:2000221",
        "tgn:7007158",
        "tgn:7029392"
    ],
    "tgn:id":2670475,
    "tgn:name":"Smart Ditch",
    "tgn:placetype":[
        "aat:300006075"
    ]
},
  "bbox": [],
  "geometry": {"coordinates":[-105.2167,39.8667],"type":"Point"}
}