{
  "id": 7368584,
  "type": "Feature",
  "properties": {
    "tgn:hierarchy":[
        "tgn:7368584",
        "tgn:1000001",
        "tgn:7005599",
        "tgn:7005560",
        "tgn:7029392"
    ],
    "tgn:id":7368584,
    "tgn:name":"Hidalgo",
    "tgn:placetype":[
        "aat:300008347"
    ]
},
  "bbox": [],
  "geometry": {"coordinates":[-96.866667,19.966667],"type":"Point"}
}