{
  "id": 7593957,
  "type": "Feature",
  "properties": {
    "tgn:hierarchy":[
        "tgn:7593957",
        "tgn:7017309",
        "tgn:1000003",
        "tgn:7006663",
        "tgn:7029392"
    ],
    "tgn:id":7593957,
    "tgn:name":"Valtura",
    "tgn:placetype":[
        "aat:300008347",
        "aat:300008372"
    ]
},
  "bbox": [],
  "geometry": {"coordinates":[13.957778,44.905278],"type":"Point"}
}