{
  "id": 1073457,
  "type": "Feature",
  "properties": {
    "tgn:hierarchy":[
        "tgn:1073457",
        "tgn:1000004",
        "tgn:7002081",
        "tgn:1000111",
        "tgn:7029392"
    ],
    "tgn:id":1073457,
    "tgn:name":"Yaojiaqiao",
    "tgn:placetype":[
        "aat:300008347"
    ]
},
  "bbox": [],
  "geometry": {"coordinates":[119.7667,32.1667],"type":"Point"}
}