{
  "id": 2613673,
  "type": "Feature",
  "properties": {
    "tgn:hierarchy":[
        "tgn:2613673",
        "tgn:1000001",
        "tgn:7012149",
        "tgn:1002877",
        "tgn:7007706",
        "tgn:7029392"
    ],
    "tgn:id":2613673,
    "tgn:name":"Reeds Run",
    "tgn:placetype":[
        "aat:300008699"
    ]
},
  "bbox": [],
  "geometry": {"coordinates":[-83.0333,38.8667],"type":"Point"}
}