<<<<<<< HEAD
{
  "id": 7055820,
  "type": "Feature",
  "properties": {
    "tgn:hierarchy":[
        "tgn:7055820",
        "tgn:1003440",
        "tgn:1000003",
        "tgn:7003124",
        "tgn:1000080",
        "tgn:7029392"
    ],
    "tgn:id":7055820,
    "tgn:name":"Plata",
    "tgn:placetype":[
        "aat:300008347"
    ]
},
  "bbox": [],
  "geometry": {"coordinates":[11.166667,46.833333],"type":"Point"}
}
=======
{"geometry":{"type":"Point","coordinates":[11.166667,46.833333]},"type":"Feature","properties":{"hierarchy":["tgn:7055820","tgn:1003440","tgn:1000003","tgn:7003124","tgn:1000080","tgn:7029392"],"placetype":["aat:300008347"],"id":7055820,"name:xx":"Plata"}}
>>>>>>> 03f74aca74312dbeaf24d7e61306dd6a786dc3d0
