{
  "id": 7423127,
  "type": "Feature",
  "properties": {
    "tgn:hierarchy":[
        "tgn:7423127",
        "tgn:1000001",
        "tgn:1001960",
        "tgn:7005560",
        "tgn:7029392"
    ],
    "tgn:id":7423127,
    "tgn:name":"La Tinaja, R\u00edo",
    "tgn:placetype":[
        "aat:300008699"
    ]
},
  "bbox": [],
  "geometry": {"coordinates":[-111.133333,28.25],"type":"Point"}
}