{
  "id": 2661409,
  "type": "Feature",
  "properties": {
    "tgn:hierarchy":[
        "tgn:2661409",
        "tgn:7006450",
        "tgn:1000001",
        "tgn:7012149",
        "tgn:2000086",
        "tgn:7029392"
    ],
    "tgn:id":2661409,
    "tgn:name":"Shotgold Creek",
    "tgn:placetype":[
        "aat:300008706"
    ]
},
  "bbox": [],
  "geometry": {"coordinates":[-141.5167,61.8333],"type":"Point"}
}