{
  "id": 2503686,
  "type": "Feature",
  "properties": {
    "tgn:hierarchy":[
        "tgn:2503686",
        "tgn:1000001",
        "tgn:7012149",
        "tgn:1002354",
        "tgn:7007255",
        "tgn:7029392"
    ],
    "tgn:id":2503686,
    "tgn:name":"Meadow Branch",
    "tgn:placetype":[
        "aat:300008699"
    ]
},
  "bbox": [],
  "geometry": {"coordinates":[-82.9667,38.05],"type":"Point"}
}