{
  "id": 7166201,
  "type": "Feature",
  "properties": {
    "tgn:hierarchy":[
        "tgn:7166201",
        "tgn:1000003",
        "tgn:7003676",
        "tgn:7000084",
        "tgn:7029392"
    ],
    "tgn:id":7166201,
    "tgn:name":"Hausherzberger Teich",
    "tgn:placetype":[
        "aat:300008688"
    ]
},
  "bbox": [],
  "geometry": {"coordinates":[10.366667,51.816667],"type":"Point"}
}