{
  "id": 7358693,
  "type": "Feature",
  "properties": {
    "tgn:hierarchy":[
        "tgn:7358693",
        "tgn:7005583",
        "tgn:1000001",
        "tgn:7005560",
        "tgn:7029392"
    ],
    "tgn:id":7358693,
    "tgn:name":"Desechos",
    "tgn:placetype":[
        "aat:300008347"
    ]
},
  "bbox": [],
  "geometry": {"coordinates":[-106.183333,25.683333],"type":"Point"}
}