{
  "id": 2746123,
  "type": "Feature",
  "properties": {
    "tgn:hierarchy":[
        "tgn:2746123",
        "tgn:1000001",
        "tgn:7012149",
        "tgn:2001396",
        "tgn:7007525",
        "tgn:7029392"
    ],
    "tgn:id":2746123,
    "tgn:name":"Von Krosigh Lake",
    "tgn:placetype":[
        "aat:300008680"
    ]
},
  "bbox": [],
  "geometry": {"coordinates":[-102.1667,42.0667],"type":"Point"}
}