{
  "id": 7381062,
  "type": "Feature",
  "properties": {
    "tgn:hierarchy":[
        "tgn:7381062",
        "tgn:7005587",
        "tgn:1000001",
        "tgn:7005560",
        "tgn:7029392"
    ],
    "tgn:id":7381062,
    "tgn:name":"Maguey Blanco",
    "tgn:placetype":[
        "aat:300008347"
    ]
},
  "bbox": [],
  "geometry": {"coordinates":[-99.15,20.416667],"type":"Point"}
}