{
  "id": 7057624,
  "type": "Feature",
  "properties": {
    "tgn:hierarchy":[
        "tgn:7057624",
        "tgn:7002994",
        "tgn:1000003",
        "tgn:7002997",
        "tgn:1000080",
        "tgn:7029392"
    ],
    "tgn:id":7057624,
    "tgn:name":"Arzercavalli",
    "tgn:placetype":[
        "aat:300008347"
    ]
},
  "bbox": [],
  "geometry": {"coordinates":[11.933333,45.25],"type":"Point"}
}