{
  "id": 1030991,
  "type": "Feature",
  "properties": {
    "tgn:hierarchy":[
        "tgn:1030991",
        "tgn:7002445",
        "tgn:1000003",
        "tgn:7008131",
        "tgn:7008591",
        "tgn:7029392"
    ],
    "tgn:id":1030991,
    "tgn:name:en":"Walton-on-the-Naze",
    "tgn:placetype":[
        "aat:300008347",
        "aat:300008375"
    ]
},
  "bbox": [],
  "geometry": {"coordinates":[1.283333,51.85],"type":"Point"}
}