{
  "id": 2076468,
  "type": "Feature",
  "properties": {
    "tgn:hierarchy":[
        "tgn:2076468",
        "tgn:1000001",
        "tgn:7012149",
        "tgn:2001551",
        "tgn:7007709",
        "tgn:7029392"
    ],
    "tgn:id":2076468,
    "tgn:name":"Rutherwood",
    "tgn:placetype":[
        "aat:300008347"
    ]
},
  "bbox": [],
  "geometry": {"coordinates":[-81.5833,36.2167],"type":"Point"}
}