<<<<<<< HEAD
{
  "id": 7115691,
  "type": "Feature",
  "properties": {
    "tgn:hierarchy":[
        "tgn:7115691",
        "tgn:1000003",
        "tgn:7000094",
        "tgn:7000084",
        "tgn:7029392"
    ],
    "tgn:id":7115691,
    "tgn:name":"Owstin",
    "tgn:placetype":[
        "aat:300008347"
    ]
},
  "bbox": [],
  "geometry": {"coordinates":[13.466667,53.933333],"type":"Point"}
}
=======
{"geometry":{"type":"Point","coordinates":[13.466667,53.933333]},"type":"Feature","properties":{"hierarchy":["tgn:7115691","tgn:1000003","tgn:7000094","tgn:7000084","tgn:7029392"],"placetype":["aat:300008347"],"id":7115691,"name:xx":"Owstin"}}
>>>>>>> 03f74aca74312dbeaf24d7e61306dd6a786dc3d0
