{
  "id": 2415241,
  "type": "Feature",
  "properties": {
    "tgn:hierarchy":[
        "tgn:2415241",
        "tgn:1000001",
        "tgn:2001580",
        "tgn:7012149",
        "tgn:7007705",
        "tgn:7029392"
    ],
    "tgn:id":2415241,
    "tgn:name":"Island Lake",
    "tgn:placetype":[
        "aat:300008680"
    ]
},
  "bbox": [],
  "geometry": {"coordinates":[-99.5833,46.3667],"type":"Point"}
}