<<<<<<< HEAD
{
  "id": 2257815,
  "type": "Feature",
  "properties": {
    "tgn:hierarchy":[
        "tgn:2257815",
        "tgn:1000001",
        "tgn:7006451",
        "tgn:2000094",
        "tgn:7012149",
        "tgn:7029392"
    ],
    "tgn:id":2257815,
    "tgn:name":"Corral Tank",
    "tgn:placetype":[
        "aat:300006191"
    ]
},
  "bbox": [],
  "geometry": {"coordinates":[-110.3,32.6167],"type":"Point"}
}
=======
{"geometry":{"type":"Point","coordinates":[-110.300000,32.616700]},"type":"Feature","properties":{"hierarchy":["tgn:2257815","tgn:1000001","tgn:7006451","tgn:2000094","tgn:7012149","tgn:7029392"],"placetype":["aat:300006191"],"id":2257815,"name:xx":"Corral Tank"}}
>>>>>>> 03f74aca74312dbeaf24d7e61306dd6a786dc3d0
