{
  "id": 2630776,
  "type": "Feature",
  "properties": {
    "tgn:hierarchy":[
        "tgn:2630776",
        "tgn:1000001",
        "tgn:2000318",
        "tgn:7012149",
        "tgn:7007248",
        "tgn:7029392"
    ],
    "tgn:id":2630776,
    "tgn:name":"Round Lake",
    "tgn:placetype":[
        "aat:300008680"
    ]
},
  "bbox": [],
  "geometry": {"coordinates":[-85.3167,34.5333],"type":"Point"}
}