<<<<<<< HEAD
{
  "id": 2707461,
  "type": "Feature",
  "properties": {
    "tgn:hierarchy":[
        "tgn:2707461",
        "tgn:1000001",
        "tgn:7006451",
        "tgn:2000095",
        "tgn:7012149",
        "tgn:7029392"
    ],
    "tgn:id":2707461,
    "tgn:name":"Sweet Spring",
    "tgn:placetype":[
        "aat:300008697"
    ]
},
  "bbox": [],
  "geometry": {"coordinates":[-109.2333,33.2667],"type":"Point"}
}
=======
{"geometry":{"type":"Point","coordinates":[-109.233300,33.266700]},"type":"Feature","properties":{"hierarchy":["tgn:2707461","tgn:1000001","tgn:7006451","tgn:2000095","tgn:7012149","tgn:7029392"],"placetype":["aat:300008697"],"id":2707461,"name:xx":"Sweet Spring"}}
>>>>>>> 03f74aca74312dbeaf24d7e61306dd6a786dc3d0
