{
  "id": 7544333,
  "type": "Feature",
  "properties": {
    "tgn:hierarchy":[
        "tgn:7544333",
        "tgn:7001242",
        "tgn:1001075",
        "tgn:7016833",
        "tgn:7029392"
    ],
    "tgn:id":7544333,
    "tgn:name:en":"Naj' al Khi\u015fmah",
    "tgn:placetype":[
        "aat:300008347"
    ]
},
  "bbox": [],
  "geometry": {"coordinates":[30.120927,30.856582],"type":"Point"}
}