{
  "id": 7524429,
  "type": "Feature",
  "properties": {
    "tgn:hierarchy":[
        "tgn:7524429",
        "tgn:7001242",
        "tgn:7016833",
        "tgn:1001418",
        "tgn:7029392"
    ],
    "tgn:id":7524429,
    "tgn:name:en":"B\u00eer Emtiha",
    "tgn:placetype":[
        "aat:300006207"
    ]
},
  "bbox": [],
  "geometry": {"coordinates":[26.750302,30.924079],"type":"Point"}
}