{
  "id": 2462942,
  "type": "Feature",
  "properties": {
    "tgn:hierarchy":[
        "tgn:2462942",
        "tgn:1000001",
        "tgn:7012149",
        "tgn:2001959",
        "tgn:7007826",
        "tgn:7029392"
    ],
    "tgn:id":2462942,
    "tgn:name":"Live Oak Branch",
    "tgn:placetype":[
        "aat:300008699"
    ]
},
  "bbox": [],
  "geometry": {"coordinates":[-99.3833,32.0333],"type":"Point"}
}