{
  "id": 2036507,
  "type": "Feature",
  "properties": {
    "tgn:hierarchy":[
        "tgn:2036507",
        "tgn:1000001",
        "tgn:2000692",
        "tgn:7012149",
        "tgn:7007254",
        "tgn:7029392"
    ],
    "tgn:id":2036507,
    "tgn:name":"Hill City",
    "tgn:placetype":[
        "aat:300008347"
    ]
},
  "bbox": [],
  "geometry": {"coordinates":[-99.8333,39.35],"type":"Point"}
}