{
  "id": 2545369,
  "type": "Feature",
  "properties": {
    "tgn:hierarchy":[
        "tgn:2545369",
        "tgn:1000001",
        "tgn:7012149",
        "tgn:2001873",
        "tgn:7007825",
        "tgn:7029392"
    ],
    "tgn:id":2545369,
    "tgn:name":"North Fork Beech Creek",
    "tgn:placetype":[
        "aat:300008706"
    ]
},
  "bbox": [],
  "geometry": {"coordinates":[-82.7667,36.45],"type":"Point"}
}