<<<<<<< HEAD
{
  "id": 2409919,
  "type": "Feature",
  "properties": {
    "tgn:hierarchy":[
        "tgn:2409919",
        "tgn:1000001",
        "tgn:2001416",
        "tgn:7012149",
        "tgn:7007526",
        "tgn:7029392"
    ],
    "tgn:id":2409919,
    "tgn:name":"Immigration Wash",
    "tgn:placetype":[
        "aat:300008699"
    ]
},
  "bbox": [],
  "geometry": {"coordinates":[-114.1,37.9333],"type":"Point"}
}
=======
{"geometry":{"type":"Point","coordinates":[-114.100000,37.933300]},"type":"Feature","properties":{"hierarchy":["tgn:2409919","tgn:1000001","tgn:2001416","tgn:7012149","tgn:7007526","tgn:7029392"],"placetype":["aat:300008699"],"id":2409919,"name:xx":"Immigration Wash"}}
>>>>>>> 03f74aca74312dbeaf24d7e61306dd6a786dc3d0
