{
  "id": 7460528,
  "type": "Feature",
  "properties": {
    "tgn:hierarchy":[
        "tgn:7460528",
        "tgn:7002444",
        "tgn:1000003",
        "tgn:7008094",
        "tgn:7008591",
        "tgn:7029392"
    ],
    "tgn:id":7460528,
    "tgn:name:en":"Laxdale, River",
    "tgn:placetype":[
        "aat:300008699"
    ]
},
  "bbox": [],
  "geometry": {"coordinates":[-6.366667,58.216667],"type":"Point"}
}