{
  "id": 2104444,
  "type": "Feature",
  "properties": {
    "tgn:hierarchy":[
        "tgn:2104444",
        "tgn:1000001",
        "tgn:7012149",
        "tgn:2002056",
        "tgn:7007826",
        "tgn:7029392"
    ],
    "tgn:id":2104444,
    "tgn:name":"Gentry",
    "tgn:placetype":[
        "aat:300387016"
    ]
},
  "bbox": [],
  "geometry": {"coordinates":[-101.9833,35.2833],"type":"Point"}
}