{
  "id": 7491035,
  "type": "Feature",
  "properties": {
    "tgn:hierarchy":[
        "tgn:7491035",
        "tgn:1000004",
        "tgn:1000454",
        "tgn:1000141",
        "tgn:7029392"
    ],
    "tgn:id":7491035,
    "tgn:name":"Taipingling",
    "tgn:placetype":[
        "aat:300008347"
    ]
},
  "bbox": [],
  "geometry": {"coordinates":[121.378307,25.115019],"type":"Point"}
}