{
  "id": 7154726,
  "type": "Feature",
  "properties": {
    "tgn:hierarchy":[
        "tgn:7154726",
        "tgn:1000003",
        "tgn:7003676",
        "tgn:7000084",
        "tgn:7029392"
    ],
    "tgn:id":7154726,
    "tgn:name":"Kleinendorf",
    "tgn:placetype":[
        "aat:300000206"
    ]
},
  "bbox": [],
  "geometry": {"coordinates":[8.85,52.416667],"type":"Point"}
}