{
  "id": 7479688,
  "type": "Feature",
  "properties": {
    "tgn:hierarchy":[
        "tgn:7479688",
        "tgn:1000004",
        "tgn:7001013",
        "tgn:1000141",
        "tgn:7029392"
    ],
    "tgn:id":7479688,
    "tgn:name":"Disihao Qiao",
    "tgn:placetype":[
        "aat:300007836"
    ]
},
  "bbox": [],
  "geometry": {"coordinates":[121.120556,24.944722],"type":"Point"}
}