{
  "id": 7237373,
  "type": "Feature",
  "properties": {
    "tgn:hierarchy":[
        "tgn:7237373",
        "tgn:4003773",
        "tgn:7001395",
        "tgn:1000003",
        "tgn:1000074",
        "tgn:7029392"
    ],
    "tgn:id":7237373,
    "tgn:name":"An\u00e1lipsis",
    "tgn:placetype":[
        "aat:300008798"
    ]
},
  "bbox": [],
  "geometry": {"coordinates":[21.464444,39.134167],"type":"Point"}
}