{
  "id": 7479926,
  "type": "Feature",
  "properties": {
    "tgn:hierarchy":[
        "tgn:7479926",
        "tgn:1000004",
        "tgn:7490934",
        "tgn:1000141",
        "tgn:7029392"
    ],
    "tgn:id":7479926,
    "tgn:name":"Tuku Guoxiao",
    "tgn:placetype":[
        "aat:300006495"
    ]
},
  "bbox": [],
  "geometry": {"coordinates":[120.344722,23.318889],"type":"Point"}
}