{
  "id": 2421107,
  "type": "Feature",
  "properties": {
    "tgn:hierarchy":[
        "tgn:2421107",
        "tgn:1002172",
        "tgn:1000001",
        "tgn:7012149",
        "tgn:7007710",
        "tgn:7029392"
    ],
    "tgn:id":2421107,
    "tgn:name":"Jerkwater",
    "tgn:placetype":[
        "aat:300008347"
    ]
},
  "bbox": [],
  "geometry": {"coordinates":[-78.2333,40.1167],"type":"Point"}
}