{
  "id": 7434665,
  "type": "Feature",
  "properties": {
    "tgn:hierarchy":[
        "tgn:7434665",
        "tgn:7005580",
        "tgn:1000001",
        "tgn:7005560",
        "tgn:7029392"
    ],
    "tgn:id":7434665,
    "tgn:name":"Zona Marques de Comillas",
    "tgn:placetype":[
        "aat:300387200"
    ]
},
  "bbox": [],
  "geometry": {"coordinates":[-90.65,16.266667],"type":"Point"}
}