{
  "id": 2664834,
  "type": "Feature",
  "properties": {
    "tgn:hierarchy":[
        "tgn:2664834",
        "tgn:1000001",
        "tgn:7012149",
        "tgn:2001059",
        "tgn:7007521",
        "tgn:7029392"
    ],
    "tgn:id":2664834,
    "tgn:name":"Simon, Lake",
    "tgn:placetype":[
        "aat:300008680"
    ]
},
  "bbox": [],
  "geometry": {"coordinates":[-95.3167,45.4167],"type":"Point"}
}