{
  "id": 2481023,
  "type": "Feature",
  "properties": {
    "tgn:hierarchy":[
        "tgn:2481023",
        "tgn:1000001",
        "tgn:7012149",
        "tgn:2002024",
        "tgn:7007826",
        "tgn:7029392"
    ],
    "tgn:id":2481023,
    "tgn:name":"Lamar Lake",
    "tgn:placetype":[
        "aat:300006191"
    ]
},
  "bbox": [],
  "geometry": {"coordinates":[-95.5333,33.7667],"type":"Point"}
}