{
  "id": 7573953,
  "type": "Feature",
  "properties": {
    "tgn:hierarchy":[
        "tgn:7573953",
        "tgn:1000004",
        "tgn:7000198",
        "tgn:7016883",
        "tgn:7029392"
    ],
    "tgn:id":7573953,
    "tgn:name:en":"Garna S\u0101hib",
    "tgn:placetype":[
        "aat:300007783"
    ]
},
  "bbox": [],
  "geometry": {"coordinates":[75.653731,31.780773],"type":"Point"}
}