{
  "id": 7116150,
  "type": "Feature",
  "properties": {
    "tgn:hierarchy":[
        "tgn:7116150",
        "tgn:7003669",
        "tgn:1000003",
        "tgn:7000084",
        "tgn:7029392"
    ],
    "tgn:id":7116150,
    "tgn:name":"Ottosau",
    "tgn:placetype":[
        "aat:300008347"
    ]
},
  "bbox": [],
  "geometry": {"coordinates":[11.516667,49.283333],"type":"Point"}
}