{
  "id": 7480090,
  "type": "Feature",
  "properties": {
    "tgn:hierarchy":[
        "tgn:7480090",
        "tgn:1000004",
        "tgn:7490934",
        "tgn:1000141",
        "tgn:7029392"
    ],
    "tgn:id":7480090,
    "tgn:name":"Annan Guozhong",
    "tgn:placetype":[
        "aat:300006495"
    ]
},
  "bbox": [],
  "geometry": {"coordinates":[120.178611,23.049167],"type":"Point"}
}