{
  "id": 7320349,
  "type": "Feature",
  "properties": {
    "tgn:hierarchy":[
        "tgn:7320349",
        "tgn:1001657",
        "tgn:1000049",
        "tgn:1000002",
        "tgn:7029392"
    ],
    "tgn:id":7320349,
    "tgn:name":"Cabrer\u00edas, Quebrada",
    "tgn:placetype":[
        "aat:300008699"
    ]
},
  "bbox": [],
  "geometry": {"coordinates":[-70.733333,-30.766667],"type":"Point"}
}