{
  "id": 2335498,
  "type": "Feature",
  "properties": {
    "tgn:hierarchy":[
        "tgn:2335498",
        "tgn:2124017",
        "tgn:7006450",
        "tgn:1000001",
        "tgn:7012149",
        "tgn:7029392"
    ],
    "tgn:id":2335498,
    "tgn:name":"Fort Richardson",
    "tgn:placetype":[
        "aat:300008347"
    ]
},
  "bbox": [],
  "geometry": {"coordinates":[-149.6833,61.25],"type":"Point"}
}