{
  "id": 7158335,
  "type": "Feature",
  "properties": {
    "tgn:hierarchy":[
        "tgn:7158335",
        "tgn:1000003",
        "tgn:7003678",
        "tgn:7000084",
        "tgn:7029392"
    ],
    "tgn:id":7158335,
    "tgn:name":"Hoh-Berg",
    "tgn:placetype":[
        "aat:300008777"
    ]
},
  "bbox": [],
  "geometry": {"coordinates":[9.583333,50.933333],"type":"Point"}
}