{
  "id": 2607199,
  "type": "Feature",
  "properties": {
    "tgn:hierarchy":[
        "tgn:2607199",
        "tgn:1000001",
        "tgn:1002601",
        "tgn:7012149",
        "tgn:7007159",
        "tgn:7029392"
    ],
    "tgn:id":2607199,
    "tgn:name":"Randalls Point",
    "tgn:placetype":[
        "aat:300008850"
    ]
},
  "bbox": [],
  "geometry": {"coordinates":[-73.35,41.6833],"type":"Point"}
}