{
  "id": 7290195,
  "type": "Feature",
  "properties": {
    "tgn:hierarchy":[
        "tgn:7290195",
        "tgn:7016598",
        "tgn:1000049",
        "tgn:1000002",
        "tgn:7029392"
    ],
    "tgn:id":7290195,
    "tgn:name":"Dulce, Aguada",
    "tgn:placetype":[
        "aat:300008697"
    ]
},
  "bbox": [],
  "geometry": {"coordinates":[-70.233333,-22.216667],"type":"Point"}
}