{
  "id": 7335182,
  "type": "Feature",
  "properties": {
    "tgn:hierarchy":[
        "tgn:7335182",
        "tgn:7002758",
        "tgn:1001316",
        "tgn:1000003",
        "tgn:1000095",
        "tgn:7029392"
    ],
    "tgn:id":7335182,
    "tgn:name":"Fr\u00edo, Arroyo",
    "tgn:placetype":[
        "aat:300008699"
    ]
},
  "bbox": [],
  "geometry": {"coordinates":[-3.616667,37.833333],"type":"Point"}
}