{
  "id": 2460795,
  "type": "Feature",
  "properties": {
    "tgn:hierarchy":[
        "tgn:2460795",
        "tgn:1000001",
        "tgn:7012149",
        "tgn:7007706",
        "tgn:7029392"
    ],
    "tgn:id":2460795,
    "tgn:name":"Little Short Creek",
    "tgn:placetype":[
        "aat:300008706"
    ]
},
  "bbox": [],
  "geometry": {"coordinates":[-80.85,40.1667],"type":"Point"}
}