{
  "id": 7455677,
  "type": "Feature",
  "properties": {
    "tgn:hierarchy":[
        "tgn:7455677",
        "tgn:7002444",
        "tgn:1000003",
        "tgn:7008082",
        "tgn:7008591",
        "tgn:7029392"
    ],
    "tgn:id":7455677,
    "tgn:name:en":"Culkein",
    "tgn:placetype":[
        "aat:300008347"
    ]
},
  "bbox": [],
  "geometry": {"coordinates":[-5.35,58.233333],"type":"Point"}
}