{
  "id": 7410220,
  "type": "Feature",
  "properties": {
    "tgn:hierarchy":[
        "tgn:7410220",
        "tgn:7005580",
        "tgn:1000001",
        "tgn:7005560",
        "tgn:7029392"
    ],
    "tgn:id":7410220,
    "tgn:name":"Miguel Alem\u00e1n V.",
    "tgn:placetype":[
        "aat:300008347"
    ]
},
  "bbox": [],
  "geometry": {"coordinates":[-93.516667,15.541667],"type":"Point"}
}