{
  "id": 2461647,
  "type": "Feature",
  "properties": {
    "tgn:hierarchy":[
        "tgn:2461647",
        "tgn:1000001",
        "tgn:7012149",
        "tgn:1002417",
        "tgn:7007255",
        "tgn:7029392"
    ],
    "tgn:id":2461647,
    "tgn:name":"Little Ten Mile Creek",
    "tgn:placetype":[
        "aat:300008706"
    ]
},
  "bbox": [],
  "geometry": {"coordinates":[-84.65,38.7333],"type":"Point"}
}