{
  "id": 2256380,
  "type": "Feature",
  "properties": {
    "tgn:hierarchy":[
        "tgn:2256380",
        "tgn:2001423",
        "tgn:1000001",
        "tgn:7012149",
        "tgn:7007564",
        "tgn:7029392"
    ],
    "tgn:id":2256380,
    "tgn:name":"Copps Pond",
    "tgn:placetype":[
        "aat:300008680"
    ]
},
  "bbox": [],
  "geometry": {"coordinates":[-71.2667,43.6667],"type":"Point"}
}