{
  "id": 2043844,
  "type": "Feature",
  "properties": {
    "tgn:hierarchy":[
        "tgn:2043844",
        "tgn:1000001",
        "tgn:7012149",
        "tgn:2000900",
        "tgn:7007256",
        "tgn:7029392"
    ],
    "tgn:id":2043844,
    "tgn:name":"Remy",
    "tgn:placetype":[
        "aat:300008347"
    ]
},
  "bbox": [],
  "geometry": {"coordinates":[-90.7333,30.0167],"type":"Point"}
}