{
  "id": 1051099,
  "type": "Feature",
  "properties": {
    "tgn:hierarchy":[
        "tgn:1051099",
        "tgn:7002444",
        "tgn:1000003",
        "tgn:7008082",
        "tgn:7008591",
        "tgn:7008959",
        "tgn:7029392"
    ],
    "tgn:id":1051099,
    "tgn:name:en":"Talisker",
    "tgn:placetype":[
        "aat:300008347"
    ]
},
  "bbox": [],
  "geometry": {"coordinates":[-6.45,57.283333],"type":"Point"}
}