<<<<<<< HEAD
{
  "id": 7051563,
  "type": "Feature",
  "properties": {
    "tgn:hierarchy":[
        "tgn:7051563",
        "tgn:7002994",
        "tgn:1000003",
        "tgn:7002997",
        "tgn:1000080",
        "tgn:7029392"
    ],
    "tgn:id":7051563,
    "tgn:name":"Musone dei Sassi, Torrente",
    "tgn:placetype":[
        "aat:300008699"
    ]
},
  "bbox": [],
  "geometry": {"coordinates":[11.9,45.45],"type":"Point"}
}
=======
{"geometry":{"type":"Point","coordinates":[11.900000,45.450000]},"type":"Feature","properties":{"hierarchy":["tgn:7051563","tgn:7002994","tgn:1000003","tgn:7002997","tgn:1000080","tgn:7029392"],"placetype":["aat:300008699"],"id":7051563,"name:xx":"Musone dei Sassi, Torrente"}}
>>>>>>> 03f74aca74312dbeaf24d7e61306dd6a786dc3d0
