<<<<<<< HEAD
{
  "id": 2407618,
  "type": "Feature",
  "properties": {
    "tgn:hierarchy":[
        "tgn:2407618",
        "tgn:7002659",
        "tgn:1000001",
        "tgn:2000016",
        "tgn:7012149",
        "tgn:7029392"
    ],
    "tgn:id":2407618,
    "tgn:name":"Hurd Spring",
    "tgn:placetype":[
        "aat:300008697"
    ]
},
  "bbox": [],
  "geometry": {"coordinates":[-88.0667,34.7833],"type":"Point"}
}
=======
{"geometry":{"type":"Point","coordinates":[-88.066700,34.783300]},"type":"Feature","properties":{"hierarchy":["tgn:2407618","tgn:7002659","tgn:1000001","tgn:2000016","tgn:7012149","tgn:7029392"],"placetype":["aat:300008697"],"id":2407618,"name:xx":"Hurd Spring"}}
>>>>>>> 03f74aca74312dbeaf24d7e61306dd6a786dc3d0
