{
  "id": 2685951,
  "type": "Feature",
  "properties": {
    "tgn:hierarchy":[
        "tgn:2685951",
        "tgn:1000001",
        "tgn:7012149",
        "tgn:2000521",
        "tgn:7007251",
        "tgn:7029392"
    ],
    "tgn:id":2685951,
    "tgn:name":"Spring Branch State Conservation Area",
    "tgn:placetype":[
        "aat:300008863"
    ]
},
  "bbox": [],
  "geometry": {"coordinates":[-89.45,40.9333],"type":"Point"}
}