{
  "id": 7397246,
  "type": "Feature",
  "properties": {
    "tgn:hierarchy":[
        "tgn:7397246",
        "tgn:1000001",
        "tgn:7005595",
        "tgn:7005560",
        "tgn:7029392"
    ],
    "tgn:id":7397246,
    "tgn:name":"Santa Rosa",
    "tgn:placetype":[
        "aat:300008347"
    ]
},
  "bbox": [],
  "geometry": {"coordinates":[-108.033333,25.533333],"type":"Point"}
}