{
  "id": 2480292,
  "type": "Feature",
  "properties": {
    "tgn:hierarchy":[
        "tgn:2480292",
        "tgn:1000001",
        "tgn:7012149",
        "tgn:2002117",
        "tgn:7007827",
        "tgn:7029392"
    ],
    "tgn:id":2480292,
    "tgn:name":"Lake Ridge",
    "tgn:placetype":[
        "aat:300266640"
    ]
},
  "bbox": [],
  "geometry": {"coordinates":[-111.0833,41.95],"type":"Point"}
}