{
  "id": 1073523,
  "type": "Feature",
  "properties": {
    "tgn:hierarchy":[
        "tgn:1073523",
        "tgn:1000004",
        "tgn:1001390",
        "tgn:1000111",
        "tgn:7029392"
    ],
    "tgn:id":1073523,
    "tgn:name":"Yijiazi",
    "tgn:placetype":[
        "aat:300008347"
    ]
},
  "bbox": [],
  "geometry": {"coordinates":[122.6833,42.4833],"type":"Point"}
}