<<<<<<< HEAD
{
  "id": 2331879,
  "type": "Feature",
  "properties": {
    "tgn:hierarchy":[
        "tgn:2331879",
        "tgn:1000001",
        "tgn:7012149",
        "tgn:7007157",
        "tgn:1002858",
        "tgn:7029392"
    ],
    "tgn:id":2331879,
    "tgn:name":"Fletcher Hills",
    "tgn:placetype":[
        "aat:300386831"
    ]
},
  "bbox": [],
  "geometry": {"coordinates":[-116.9833,32.8],"type":"Point"}
}
=======
{"geometry":{"type":"Point","coordinates":[-116.983300,32.800000]},"type":"Feature","properties":{"hierarchy":["tgn:2331879","tgn:1000001","tgn:7012149","tgn:7007157","tgn:1002858","tgn:7029392"],"placetype":["aat:300386831"],"id":2331879,"name:xx":"Fletcher Hills"}}
>>>>>>> 03f74aca74312dbeaf24d7e61306dd6a786dc3d0
