{
  "id": 7548042,
  "type": "Feature",
  "properties": {
    "tgn:hierarchy":[
        "tgn:7548042",
        "tgn:1000004",
        "tgn:1001842",
        "tgn:7000198",
        "tgn:7029392"
    ],
    "tgn:id":7548042,
    "tgn:name:en":"Aurahi",
    "tgn:placetype":[
        "aat:300007783"
    ]
},
  "bbox": [],
  "geometry": {"coordinates":[87.135076,25.820448],"type":"Point"}
}