{
  "id": 7496054,
  "type": "Feature",
  "properties": {
    "tgn:hierarchy":[
        "tgn:7496054",
        "tgn:1000004",
        "tgn:7001014",
        "tgn:1000141",
        "tgn:7029392"
    ],
    "tgn:id":7496054,
    "tgn:name":"Shanzinei Qiao",
    "tgn:placetype":[
        "aat:300007836"
    ]
},
  "bbox": [],
  "geometry": {"coordinates":[120.313214,23.683593],"type":"Point"}
}