{
  "id": 7571500,
  "type": "Feature",
  "properties": {
    "tgn:hierarchy":[
        "tgn:7571500",
        "tgn:1000004",
        "tgn:1001842",
        "tgn:7000198",
        "tgn:7029392"
    ],
    "tgn:id":7571500,
    "tgn:name:en":"Kam\u0101lpur",
    "tgn:placetype":[
        "aat:300008347"
    ]
},
  "bbox": [],
  "geometry": {"coordinates":[87.295307,26.092445],"type":"Point"}
}