{
  "id": 2675746,
  "type": "Feature",
  "properties": {
    "tgn:hierarchy":[
        "tgn:2675746",
        "tgn:1000001",
        "tgn:7012149",
        "tgn:2002118",
        "tgn:7007827",
        "tgn:7029392"
    ],
    "tgn:id":2675746,
    "tgn:name":"Somerset Estates Place",
    "tgn:placetype":[
        "aat:300008347"
    ]
},
  "bbox": [],
  "geometry": {"coordinates":[-111.8167,40.6167],"type":"Point"}
}