{
  "id": 2437568,
  "type": "Feature",
  "properties": {
    "tgn:hierarchy":[
        "tgn:2437568",
        "tgn:1000001",
        "tgn:7012149",
        "tgn:2002194",
        "tgn:7007919",
        "tgn:7029392"
    ],
    "tgn:id":2437568,
    "tgn:name":"Kinets Cave",
    "tgn:placetype":[
        "aat:300008746"
    ]
},
  "bbox": [],
  "geometry": {"coordinates":[-81.85,36.6167],"type":"Point"}
}