{
  "id": 2696074,
  "type": "Feature",
  "properties": {
    "tgn:hierarchy":[
        "tgn:2696074",
        "tgn:1000001",
        "tgn:7012149",
        "tgn:2000388",
        "tgn:7007248",
        "tgn:7029392"
    ],
    "tgn:id":2696074,
    "tgn:name":"Stoehr Lake",
    "tgn:placetype":[
        "aat:300006191"
    ]
},
  "bbox": [],
  "geometry": {"coordinates":[-83.15,34.1167],"type":"Point"}
}