<<<<<<< HEAD
{
  "id": 7174206,
  "type": "Feature",
  "properties": {
    "tgn:hierarchy":[
        "tgn:7174206",
        "tgn:1000003",
        "tgn:7003688",
        "tgn:7000084",
        "tgn:7029392"
    ],
    "tgn:id":7174206,
    "tgn:name":"Gr\u00f6nland",
    "tgn:placetype":[
        "aat:300000206"
    ]
},
  "bbox": [],
  "geometry": {"coordinates":[10.366667,54.083333],"type":"Point"}
}
=======
{"geometry":{"type":"Point","coordinates":[10.366667,54.083333]},"type":"Feature","properties":{"hierarchy":["tgn:7174206","tgn:1000003","tgn:7003688","tgn:7000084","tgn:7029392"],"placetype":["aat:300000206"],"id":7174206,"name:xx":"Gr\u00f6nland"}}
>>>>>>> 03f74aca74312dbeaf24d7e61306dd6a786dc3d0
