{
  "id": 2573962,
  "type": "Feature",
  "properties": {
    "tgn:hierarchy":[
        "tgn:2573962",
        "tgn:1000001",
        "tgn:7012149",
        "tgn:2001762",
        "tgn:7007712",
        "tgn:7029392"
    ],
    "tgn:id":2573962,
    "tgn:name":"Peedee Lake",
    "tgn:placetype":[
        "aat:300008680"
    ]
},
  "bbox": [],
  "geometry": {"coordinates":[-80.4333,33.2667],"type":"Point"}
}