{
  "id": 2447079,
  "type": "Feature",
  "properties": {
    "tgn:hierarchy":[
        "tgn:2447079",
        "tgn:1000001",
        "tgn:7012149",
        "tgn:2002129",
        "tgn:7007827",
        "tgn:7029392"
    ],
    "tgn:id":2447079,
    "tgn:name":"Liberty Spring Creek",
    "tgn:placetype":[
        "aat:300008706"
    ]
},
  "bbox": [],
  "geometry": {"coordinates":[-111.8667,41.3167],"type":"Point"}
}