{
  "id": 2755601,
  "type": "Feature",
  "properties": {
    "tgn:hierarchy":[
        "tgn:2755601",
        "tgn:1000001",
        "tgn:7012149",
        "tgn:2001723",
        "tgn:7007708",
        "tgn:7029392"
    ],
    "tgn:id":2755601,
    "tgn:name":"Weddle Creek",
    "tgn:placetype":[
        "aat:300008706"
    ]
},
  "bbox": [],
  "geometry": {"coordinates":[-120.25,44.5333],"type":"Point"}
}