{
  "id": 7007452,
  "type": "Feature",
  "properties": {
    "tgn:hierarchy":[
        "tgn:7007452",
        "tgn:1000003",
        "tgn:7004723",
        "tgn:7011731",
        "tgn:7029392"
    ],
    "tgn:id":7007452,
    "tgn:name":"Ronco",
    "tgn:placetype":[
        "aat:300008347"
    ]
},
  "bbox": [],
  "geometry": {"coordinates":[8.7333,46.15],"type":"Point"}
}