{
  "id": 7119402,
  "type": "Feature",
  "properties": {
    "tgn:hierarchy":[
        "tgn:7119402",
        "tgn:1000003",
        "tgn:7000094",
        "tgn:7000084",
        "tgn:7029392"
    ],
    "tgn:id":7119402,
    "tgn:name":"Penzlin",
    "tgn:placetype":[
        "aat:300008347"
    ]
},
  "bbox": [],
  "geometry": {"coordinates":[12.166667,53.516667],"type":"Point"}
}