{
  "id": 2238589,
  "type": "Feature",
  "properties": {
    "tgn:hierarchy":[
        "tgn:2238589",
        "tgn:1000001",
        "tgn:7012149",
        "tgn:2001679",
        "tgn:7007707",
        "tgn:7029392"
    ],
    "tgn:id":2238589,
    "tgn:name":"Choteau Creek",
    "tgn:placetype":[
        "aat:300008706"
    ]
},
  "bbox": [],
  "geometry": {"coordinates":[-96.15,36.65],"type":"Point"}
}