{
  "id": 7468758,
  "type": "Feature",
  "properties": {
    "tgn:hierarchy":[
        "tgn:7468758",
        "tgn:1000004",
        "tgn:7471332",
        "tgn:1000141",
        "tgn:7029392"
    ],
    "tgn:id":7468758,
    "tgn:name":"Fengshan Xi Zhixian",
    "tgn:placetype":[
        "aat:300266560"
    ]
},
  "bbox": [],
  "geometry": {"coordinates":[121.041111,24.831389],"type":"Point"}
}