{
  "id": 7230415,
  "type": "Feature",
  "properties": {
    "tgn:hierarchy":[
        "tgn:7230415",
        "tgn:7002748",
        "tgn:7001399",
        "tgn:1000003",
        "tgn:1000074",
        "tgn:7029392"
    ],
    "tgn:id":7230415,
    "tgn:name":"Krits\u00e1rion",
    "tgn:placetype":[
        "aat:300008347"
    ]
},
  "bbox": [],
  "geometry": {"coordinates":[21.475,39.323333],"type":"Point"}
}