{
  "id": 7525714,
  "type": "Feature",
  "properties": {
    "tgn:hierarchy":[
        "tgn:7525714",
        "tgn:7001242",
        "tgn:7001311",
        "tgn:7016833",
        "tgn:7029392"
    ],
    "tgn:id":7525714,
    "tgn:name:en":"Bal\u012b', W\u0101d\u012b",
    "tgn:placetype":[
        "aat:300379998"
    ]
},
  "bbox": [],
  "geometry": {"coordinates":[33.645634,27.442382],"type":"Point"}
}