{
  "id": 2135965,
  "type": "Feature",
  "properties": {
    "tgn:hierarchy":[
        "tgn:2135965",
        "tgn:7006450",
        "tgn:1000001",
        "tgn:7012149",
        "tgn:2000089",
        "tgn:7029392"
    ],
    "tgn:id":2135965,
    "tgn:name":"Applegate Creek",
    "tgn:placetype":[
        "aat:300008706"
    ]
},
  "bbox": [],
  "geometry": {"coordinates":[-149.7833,65.25],"type":"Point"}
}