{
  "id": 2367850,
  "type": "Feature",
  "properties": {
    "tgn:hierarchy":[
        "tgn:2367850",
        "tgn:1000001",
        "tgn:2000682",
        "tgn:7012149",
        "tgn:7007254",
        "tgn:7029392"
    ],
    "tgn:id":2367850,
    "tgn:name":"Grover",
    "tgn:placetype":[
        "aat:300008347"
    ]
},
  "bbox": [],
  "geometry": {"coordinates":[-95.45,39.05],"type":"Point"}
}