{
  "id": 2748843,
  "type": "Feature",
  "properties": {
    "tgn:hierarchy":[
        "tgn:2748843",
        "tgn:7030516",
        "tgn:7006450",
        "tgn:1000001",
        "tgn:7012149",
        "tgn:7029392"
    ],
    "tgn:id":2748843,
    "tgn:name":"Wall Bay",
    "tgn:placetype":[
        "aat:300132316"
    ]
},
  "bbox": [],
  "geometry": {"coordinates":[-174.8833,52.0833],"type":"Point"}
}