{
  "id": 7110264,
  "type": "Feature",
  "properties": {
    "tgn:hierarchy":[
        "tgn:7110264",
        "tgn:1000003",
        "tgn:7000094",
        "tgn:7000084",
        "tgn:7029392"
    ],
    "tgn:id":7110264,
    "tgn:name":"Reidervitz",
    "tgn:placetype":[
        "aat:300008347"
    ]
},
  "bbox": [],
  "geometry": {"coordinates":[13.366667,54.633333],"type":"Point"}
}