{
  "id": 2682786,
  "type": "Feature",
  "properties": {
    "tgn:hierarchy":[
        "tgn:2682786",
        "tgn:1000001",
        "tgn:7012149",
        "tgn:2001512",
        "tgn:7007709",
        "tgn:7029392"
    ],
    "tgn:id":2682786,
    "tgn:name":"Southwest Creek",
    "tgn:placetype":[
        "aat:300008706"
    ]
},
  "bbox": [],
  "geometry": {"coordinates":[-77.75,35.1167],"type":"Point"}
}