{
  "id": 2612108,
  "type": "Feature",
  "properties": {
    "tgn:hierarchy":[
        "tgn:2612108",
        "tgn:1000001",
        "tgn:7012149",
        "tgn:7007157",
        "tgn:2000185",
        "tgn:7029392"
    ],
    "tgn:id":2612108,
    "tgn:name":"Red Rock Ridge",
    "tgn:placetype":[
        "aat:300266640"
    ]
},
  "bbox": [],
  "geometry": {"coordinates":[-122.9167,39.55],"type":"Point"}
}