<<<<<<< HEAD
{
  "id": 2250658,
  "type": "Feature",
  "properties": {
    "tgn:hierarchy":[
        "tgn:2250658",
        "tgn:1000001",
        "tgn:7012149",
        "tgn:2001451",
        "tgn:7007566",
        "tgn:7029392"
    ],
    "tgn:id":2250658,
    "tgn:name":"Colorado de Abajo, Loma",
    "tgn:placetype":[
        "aat:300008798"
    ]
},
  "bbox": [],
  "geometry": {"coordinates":[-106.65,35.2667],"type":"Point"}
}
=======
{"geometry":{"type":"Point","coordinates":[-106.650000,35.266700]},"type":"Feature","properties":{"hierarchy":["tgn:2250658","tgn:1000001","tgn:7012149","tgn:2001451","tgn:7007566","tgn:7029392"],"placetype":["aat:300008798"],"id":2250658,"name:xx":"Colorado de Abajo, Loma"}}
>>>>>>> 03f74aca74312dbeaf24d7e61306dd6a786dc3d0
