{
  "id": 2558579,
  "type": "Feature",
  "properties": {
    "tgn:hierarchy":[
        "tgn:2558579",
        "tgn:1000001",
        "tgn:7012149",
        "tgn:7016021",
        "tgn:7007568",
        "tgn:7029392"
    ],
    "tgn:id":2558579,
    "tgn:name":"Oliver Island",
    "tgn:placetype":[
        "aat:300008791"
    ]
},
  "bbox": [],
  "geometry": {"coordinates":[-75.7833,44.45],"type":"Point"}
}