{
  "id": 2195309,
  "type": "Feature",
  "properties": {
    "tgn:hierarchy":[
        "tgn:2195309",
        "tgn:1000001",
        "tgn:7012149",
        "tgn:2001440",
        "tgn:7007566",
        "tgn:7029392"
    ],
    "tgn:id":2195309,
    "tgn:name":"Brister Tank",
    "tgn:placetype":[
        "aat:300006191"
    ]
},
  "bbox": [],
  "geometry": {"coordinates":[-108.9833,32.3667],"type":"Point"}
}