{
  "id": 7514030,
  "type": "Feature",
  "properties": {
    "tgn:hierarchy":[
        "tgn:7514030",
        "tgn:1009227",
        "tgn:1000226",
        "tgn:1000006",
        "tgn:7016850",
        "tgn:7029392"
    ],
    "tgn:id":7514030,
    "tgn:name:en":"Eureka",
    "tgn:placetype":[
        "aat:300008798"
    ]
},
  "bbox": [],
  "geometry": {"coordinates":[169.483333,-43.85],"type":"Point"}
}