{
  "id": 2199170,
  "type": "Feature",
  "properties": {
    "tgn:hierarchy":[
        "tgn:2199170",
        "tgn:1000001",
        "tgn:2001418",
        "tgn:7012149",
        "tgn:7007526",
        "tgn:7029392"
    ],
    "tgn:id":2199170,
    "tgn:name":"Bruner Mine",
    "tgn:placetype":[
        "aat:300000390"
    ]
},
  "bbox": [],
  "geometry": {"coordinates":[-117.75,39.0667],"type":"Point"}
}