{
  "id": 2710778,
  "type": "Feature",
  "properties": {
    "tgn:hierarchy":[
        "tgn:2710778",
        "tgn:1000001",
        "tgn:7012149",
        "tgn:2001307",
        "tgn:7007524",
        "tgn:7029392"
    ],
    "tgn:id":2710778,
    "tgn:name":"Tandy 6 Coal Mine",
    "tgn:placetype":[
        "aat:300000390"
    ]
},
  "bbox": [],
  "geometry": {"coordinates":[-109.7667,45.45],"type":"Point"}
}