{
  "id": 2178374,
  "type": "Feature",
  "properties": {
    "tgn:hierarchy":[
        "tgn:2178374",
        "tgn:1000001",
        "tgn:2000935",
        "tgn:7012149",
        "tgn:7007516",
        "tgn:7029392"
    ],
    "tgn:id":2178374,
    "tgn:name":"Blacklick Run",
    "tgn:placetype":[
        "aat:300008699"
    ]
},
  "bbox": [],
  "geometry": {"coordinates":[-79.0833,39.6333],"type":"Point"}
}