{
  "id": 2550608,
  "type": "Feature",
  "properties": {
    "tgn:hierarchy":[
        "tgn:2550608",
        "tgn:1000001",
        "tgn:7012149",
        "tgn:2001893",
        "tgn:7007825",
        "tgn:7029392"
    ],
    "tgn:id":2550608,
    "tgn:name":"Norton Hill",
    "tgn:placetype":[
        "aat:300008798"
    ]
},
  "bbox": [],
  "geometry": {"coordinates":[-88.7667,35.5167],"type":"Point"}
}