{
  "id": 2692897,
  "type": "Feature",
  "properties": {
    "tgn:hierarchy":[
        "tgn:2692897",
        "tgn:1000001",
        "tgn:7012149",
        "tgn:1002871",
        "tgn:7007568",
        "tgn:7029392"
    ],
    "tgn:id":2692897,
    "tgn:name":"Steele Reservoir",
    "tgn:placetype":[
        "aat:300006191"
    ]
},
  "bbox": [],
  "geometry": {"coordinates":[-74.05,43.15],"type":"Point"}
}