{
  "id": 7051505,
  "type": "Feature",
  "properties": {
    "tgn:hierarchy":[
        "tgn:7051505",
        "tgn:7003170",
        "tgn:1000003",
        "tgn:7003125",
        "tgn:1000080",
        "tgn:7029392"
    ],
    "tgn:id":7051505,
    "tgn:name":"Petroro",
    "tgn:placetype":[
        "aat:300008347"
    ]
},
  "bbox": [],
  "geometry": {"coordinates":[12.466667,42.816667],"type":"Point"}
}