{
  "id": 7591196,
  "type": "Feature",
  "properties": {
    "tgn:hierarchy":[
        "tgn:7591196",
        "tgn:1000004",
        "tgn:7000198",
        "tgn:7000799",
        "tgn:7029392"
    ],
    "tgn:id":7591196,
    "tgn:name:en":"Gora",
    "tgn:placetype":[
        "aat:300008347"
    ]
},
  "bbox": [],
  "geometry": {"coordinates":[74.144444,33.175],"type":"Point"}
}