{
  "id": 7414113,
  "type": "Feature",
  "properties": {
    "tgn:hierarchy":[
        "tgn:7414113",
        "tgn:1000001",
        "tgn:7005596",
        "tgn:7005560",
        "tgn:7029392"
    ],
    "tgn:id":7414113,
    "tgn:name:es":"La Cueja",
    "tgn:placetype":[
        "aat:300008347"
    ]
},
  "bbox": [],
  "geometry": {"coordinates":[-91.25,17.85],"type":"Point"}
}