{
  "id": 7517279,
  "type": "Feature",
  "properties": {
    "tgn:hierarchy":[
        "tgn:7517279",
        "tgn:7016670",
        "tgn:1008380",
        "tgn:1000226",
        "tgn:1000006",
        "tgn:7029392"
    ],
    "tgn:id":7517279,
    "tgn:name:en":"Kokomoka",
    "tgn:placetype":[
        "aat:300008795"
    ]
},
  "bbox": [],
  "geometry": {"coordinates":[176.516667,-38.833333],"type":"Point"}
}