<<<<<<< HEAD
{
  "id": 7051481,
  "type": "Feature",
  "properties": {
    "tgn:hierarchy":[
        "tgn:7051481",
        "tgn:7003134",
        "tgn:1000003",
        "tgn:7008516",
        "tgn:1000080",
        "tgn:7029392"
    ],
    "tgn:id":7051481,
    "tgn:name":"Pezzano",
    "tgn:placetype":[
        "aat:300008347"
    ]
},
  "bbox": [],
  "geometry": {"coordinates":[10.433333,44.616667],"type":"Point"}
}
=======
{"geometry":{"type":"Point","coordinates":[10.433333,44.616667]},"type":"Feature","properties":{"hierarchy":["tgn:7051481","tgn:7003134","tgn:1000003","tgn:7008516","tgn:1000080","tgn:7029392"],"placetype":["aat:300008347"],"id":7051481,"name:xx":"Pezzano"}}
>>>>>>> 03f74aca74312dbeaf24d7e61306dd6a786dc3d0
