{
  "id": 2776396,
  "type": "Feature",
  "properties": {
    "tgn:hierarchy":[
        "tgn:2776396",
        "tgn:7002659",
        "tgn:1000001",
        "tgn:7012149",
        "tgn:7029392"
    ],
    "tgn:id":2776396,
    "tgn:name":"Wind Creek",
    "tgn:placetype":[
        "aat:300008706"
    ]
},
  "bbox": [],
  "geometry": {"coordinates":[-85.65,32.6833],"type":"Point"}
}