{
  "id": 1019160,
  "type": "Feature",
  "properties": {
    "tgn:hierarchy":[
        "tgn:1019160",
        "tgn:1001160",
        "tgn:7006477",
        "tgn:1000002",
        "tgn:7029392"
    ],
    "tgn:id":1019160,
    "tgn:name":"\u00c1ngel Etcheverry",
    "tgn:placetype":[
        "aat:300008347"
    ]
},
  "bbox": [],
  "geometry": {"coordinates":[-58.0667,-35.0333],"type":"Point"}
}