{
  "id": 2705638,
  "type": "Feature",
  "properties": {
    "tgn:hierarchy":[
        "tgn:2705638",
        "tgn:7006450",
        "tgn:2000069",
        "tgn:1000001",
        "tgn:7012149",
        "tgn:7029392"
    ],
    "tgn:id":2705638,
    "tgn:name":"Susie Creek",
    "tgn:placetype":[
        "aat:300008706"
    ]
},
  "bbox": [],
  "geometry": {"coordinates":[-161.6333,58.95],"type":"Point"}
}