{
  "id": 7467076,
  "type": "Feature",
  "properties": {
    "tgn:hierarchy":[
        "tgn:7467076",
        "tgn:7019094",
        "tgn:7002444",
        "tgn:1000003",
        "tgn:7008591",
        "tgn:7029392"
    ],
    "tgn:id":7467076,
    "tgn:name:en":"Ballimore",
    "tgn:placetype":[
        "aat:300008347"
    ]
},
  "bbox": [],
  "geometry": {"coordinates":[-5.066667,56.15],"type":"Point"}
}