{
  "id": 7154476,
  "type": "Feature",
  "properties": {
    "tgn:hierarchy":[
        "tgn:7154476",
        "tgn:1000003",
        "tgn:7003677",
        "tgn:7000084",
        "tgn:7029392"
    ],
    "tgn:id":7154476,
    "tgn:name":"Irresheim",
    "tgn:placetype":[
        "aat:300008347"
    ]
},
  "bbox": [],
  "geometry": {"coordinates":[6.616667,50.783333],"type":"Point"}
}