{
  "id": 2420158,
  "type": "Feature",
  "properties": {
    "tgn:hierarchy":[
        "tgn:2420158",
        "tgn:1000001",
        "tgn:7012149",
        "tgn:2001500",
        "tgn:7007709",
        "tgn:7029392"
    ],
    "tgn:id":2420158,
    "tgn:name":"Jefferson Club Lake",
    "tgn:placetype":[
        "aat:300006191"
    ]
},
  "bbox": [],
  "geometry": {"coordinates":[-79.8667,36.1333],"type":"Point"}
}