{
  "id": 2212534,
  "type": "Feature",
  "properties": {
    "tgn:hierarchy":[
        "tgn:2212534",
        "tgn:1000001",
        "tgn:7012149",
        "tgn:2001917",
        "tgn:7007825",
        "tgn:7029392"
    ],
    "tgn:id":2212534,
    "tgn:name":"Byrd Bay",
    "tgn:placetype":[
        "aat:300008905"
    ]
},
  "bbox": [],
  "geometry": {"coordinates":[-88.0167,36.5667],"type":"Point"}
}