<<<<<<< HEAD
{
  "id": 7472274,
  "type": "Feature",
  "properties": {
    "tgn:hierarchy":[
        "tgn:7472274",
        "tgn:1000004",
        "tgn:1000454",
        "tgn:1000141",
        "tgn:7029392"
    ],
    "tgn:id":7472274,
    "tgn:name":"Couhe",
    "tgn:placetype":[
        "aat:300008347"
    ]
},
  "bbox": [],
  "geometry": {"coordinates":[121.381935,24.880257],"type":"Point"}
}
=======
{"geometry":{"type":"Point","coordinates":[121.381935,24.880257]},"type":"Feature","properties":{"hierarchy":["tgn:7472274","tgn:1000004","tgn:1000454","tgn:1000141","tgn:7029392"],"placetype":["aat:300008347"],"id":7472274,"name:xx":"Couhe"}}
>>>>>>> 03f74aca74312dbeaf24d7e61306dd6a786dc3d0
