{
  "id": 2713651,
  "type": "Feature",
  "properties": {
    "tgn:hierarchy":[
        "tgn:2713651",
        "tgn:7030516",
        "tgn:7006450",
        "tgn:1000001",
        "tgn:7012149",
        "tgn:7029392"
    ],
    "tgn:id":2713651,
    "tgn:name":"Teapot Hill",
    "tgn:placetype":[
        "aat:300008798"
    ]
},
  "bbox": [],
  "geometry": {"coordinates":[-168.7833,53.1333],"type":"Point"}
}