{
  "id": 7044272,
  "type": "Feature",
  "properties": {
    "tgn:hierarchy":[
        "tgn:7044272",
        "tgn:7003139",
        "tgn:1000003",
        "tgn:7003080",
        "tgn:1000080",
        "tgn:7029392"
    ],
    "tgn:id":7044272,
    "tgn:name":"Crapina, Fosso",
    "tgn:placetype":[
        "aat:300008699"
    ]
},
  "bbox": [],
  "geometry": {"coordinates":[11.95,42.416667],"type":"Point"}
}