{
  "id": 2528860,
  "type": "Feature",
  "properties": {
    "tgn:hierarchy":[
        "tgn:2528860",
        "tgn:1000001",
        "tgn:7012149",
        "tgn:2000734",
        "tgn:7007254",
        "tgn:7029392"
    ],
    "tgn:id":2528860,
    "tgn:name":"Mud Creek",
    "tgn:placetype":[
        "aat:300008706"
    ]
},
  "bbox": [],
  "geometry": {"coordinates":[-96.2667,39.5667],"type":"Point"}
}