{
  "id": 2640293,
  "type": "Feature",
  "properties": {
    "tgn:hierarchy":[
        "tgn:2640293",
        "tgn:1000001",
        "tgn:7006451",
        "tgn:7012149",
        "tgn:7029392"
    ],
    "tgn:id":2640293,
    "tgn:name":"San Carlos Reservoir",
    "tgn:placetype":[
        "aat:300006191"
    ]
},
  "bbox": [],
  "geometry": {"coordinates":[-110.5167,33.1667],"type":"Point"}
}