{
  "id": 2729204,
  "type": "Feature",
  "properties": {
    "tgn:hierarchy":[
        "tgn:2729204",
        "tgn:1000001",
        "tgn:7012149",
        "tgn:2001879",
        "tgn:7007825",
        "tgn:7029392"
    ],
    "tgn:id":2729204,
    "tgn:name":"Trinity",
    "tgn:placetype":[
        "aat:300008347"
    ]
},
  "bbox": [],
  "geometry": {"coordinates":[-87.8167,36.15],"type":"Point"}
}