{
  "id": 7551495,
  "type": "Feature",
  "properties": {
    "tgn:hierarchy":[
        "tgn:7551495",
        "tgn:1000004",
        "tgn:7000198",
        "tgn:7001797",
        "tgn:7029392"
    ],
    "tgn:id":7551495,
    "tgn:name:en":"Chettin\u0101d",
    "tgn:placetype":[
        "aat:300007783"
    ]
},
  "bbox": [],
  "geometry": {"coordinates":[78.783333,10.166667],"type":"Point"}
}