{
  "id": 1019004,
  "type": "Feature",
  "properties": {
    "tgn:hierarchy":[
        "tgn:1019004",
        "tgn:7017438",
        "tgn:1000001",
        "tgn:7004643",
        "tgn:7029392"
    ],
    "tgn:id":1019004,
    "tgn:name":"Perchas",
    "tgn:placetype":[
        "aat:300008347"
    ]
},
  "bbox": [],
  "geometry": {"coordinates":[-66.9833,18.3167],"type":"Point"}
}