{
  "id": 2550786,
  "type": "Feature",
  "properties": {
    "tgn:hierarchy":[
        "tgn:2550786",
        "tgn:1000001",
        "tgn:7012149",
        "tgn:2002363",
        "tgn:7007922",
        "tgn:7029392"
    ],
    "tgn:id":2550786,
    "tgn:name":"Norwegian Bay",
    "tgn:placetype":[
        "aat:300132316"
    ]
},
  "bbox": [],
  "geometry": {"coordinates":[-88.85,44.1667],"type":"Point"}
}