{
  "id": 2623167,
  "type": "Feature",
  "properties": {
    "tgn:hierarchy":[
        "tgn:2623167",
        "tgn:1000001",
        "tgn:2001426",
        "tgn:7012149",
        "tgn:7007564",
        "tgn:7029392"
    ],
    "tgn:id":2623167,
    "tgn:name":"Rochester Reservoir",
    "tgn:placetype":[
        "aat:300006191"
    ]
},
  "bbox": [],
  "geometry": {"coordinates":[-71.0333,43.2833],"type":"Point"}
}