{
  "id": 2215991,
  "type": "Feature",
  "properties": {
    "tgn:hierarchy":[
        "tgn:2215991",
        "tgn:1000001",
        "tgn:7012149",
        "tgn:2001029",
        "tgn:7007521",
        "tgn:7029392"
    ],
    "tgn:id":2215991,
    "tgn:name":"Cameron Lake",
    "tgn:placetype":[
        "aat:300008680"
    ]
},
  "bbox": [],
  "geometry": {"coordinates":[-93.5667,47.65],"type":"Point"}
}