<<<<<<< HEAD
{
  "id": 7027680,
  "type": "Feature",
  "properties": {
    "tgn:hierarchy":[
        "tgn:7027680",
        "tgn:7002445",
        "tgn:1000003",
        "tgn:7008155",
        "tgn:7008591",
        "tgn:7029392"
    ],
    "tgn:id":7027680,
    "tgn:name":"Stoughton",
    "tgn:placetype":[
        "aat:300008347",
        "aat:300008372"
    ]
},
  "bbox": [],
  "geometry": {"coordinates":[-1.05,52.6167],"type":"Point"}
}
=======
{"geometry":{"type":"Point","coordinates":[-1.050000,52.616700]},"type":"Feature","properties":{"hierarchy":["tgn:7027680","tgn:7002445","tgn:1000003","tgn:7008155","tgn:7008591","tgn:7029392"],"placetype":["aat:300008347","aat:300008372"],"id":7027680,"name:xx":"Stoughton"}}
>>>>>>> 03f74aca74312dbeaf24d7e61306dd6a786dc3d0
