{
  "id": 2102809,
  "type": "Feature",
  "properties": {
    "tgn:hierarchy":[
        "tgn:2102809",
        "tgn:1000001",
        "tgn:7012149",
        "tgn:1002315",
        "tgn:7007826",
        "tgn:7029392"
    ],
    "tgn:id":2102809,
    "tgn:name":"Bobwyn",
    "tgn:placetype":[
        "aat:300387016"
    ]
},
  "bbox": [],
  "geometry": {"coordinates":[-96.5833,32.65],"type":"Point"}
}