{
  "id": 2072102,
  "type": "Feature",
  "properties": {
    "tgn:hierarchy":[
        "tgn:2072102",
        "tgn:1000001",
        "tgn:7012149",
        "tgn:1002688",
        "tgn:7007568",
        "tgn:7029392"
    ],
    "tgn:id":2072102,
    "tgn:name":"Saint Johnsville",
    "tgn:placetype":[
        "aat:300008347"
    ]
},
  "bbox": [],
  "geometry": {"coordinates":[-74.6833,42.9833],"type":"Point"}
}