{
  "id": 7272216,
  "type": "Feature",
  "properties": {
    "tgn:concordances":{
        "gn:id":"2746603"
    },
    "tgn:hierarchy":[
        "tgn:7272216",
        "tgn:1000003",
        "tgn:7003627",
        "tgn:7016845",
        "tgn:7029392"
    ],
    "tgn:id":7272216,
    "tgn:name:nl":"Strijkviertel",
    "tgn:placetype":[
        "aat:300008347"
    ]
},
  "bbox": [],
  "geometry": {"coordinates":[5.05,52.083333],"type":"Point"}
}