{
  "id": 2129263,
  "type": "Feature",
  "properties": {
    "tgn:hierarchy":[
        "tgn:2129263",
        "tgn:7006450",
        "tgn:1000001",
        "tgn:7012149",
        "tgn:2124005",
        "tgn:7029392"
    ],
    "tgn:id":2129263,
    "tgn:name":"Alice Creek",
    "tgn:placetype":[
        "aat:300008706"
    ]
},
  "bbox": [],
  "geometry": {"coordinates":[-154.1333,69.3667],"type":"Point"}
}