{
  "id": 7304915,
  "type": "Feature",
  "properties": {
    "tgn:hierarchy":[
        "tgn:7304915",
        "tgn:7002758",
        "tgn:7002821",
        "tgn:1000003",
        "tgn:1000095",
        "tgn:7029392"
    ],
    "tgn:id":7304915,
    "tgn:name":"La Torrecilla",
    "tgn:placetype":[
        "aat:300008795"
    ]
},
  "bbox": [],
  "geometry": {"coordinates":[-4.083333,36.966667],"type":"Point"}
}