{
  "id": 7570710,
  "type": "Feature",
  "properties": {
    "tgn:hierarchy":[
        "tgn:7570710",
        "tgn:1000004",
        "tgn:7000198",
        "tgn:1001895",
        "tgn:7029392"
    ],
    "tgn:id":7570710,
    "tgn:name:en":"Ghanbi",
    "tgn:placetype":[
        "aat:300008347"
    ]
},
  "bbox": [],
  "geometry": {"coordinates":[73.833333,17.433333],"type":"Point"}
}