{
  "id": 2579301,
  "type": "Feature",
  "properties": {
    "tgn:hierarchy":[
        "tgn:2579301",
        "tgn:1000001",
        "tgn:7012149",
        "tgn:2002359",
        "tgn:7007922",
        "tgn:7029392"
    ],
    "tgn:id":2579301,
    "tgn:name":"Pickel Lake",
    "tgn:placetype":[
        "aat:300008680"
    ]
},
  "bbox": [],
  "geometry": {"coordinates":[-88.9833,46.0333],"type":"Point"}
}