{
  "id": 7341085,
  "type": "Feature",
  "properties": {
    "tgn:hierarchy":[
        "tgn:7341085",
        "tgn:7002836",
        "tgn:7016622",
        "tgn:1000003",
        "tgn:1000095",
        "tgn:7029392"
    ],
    "tgn:id":7341085,
    "tgn:name":"Buenavista, Punta",
    "tgn:placetype":[
        "aat:300386846"
    ]
},
  "bbox": [],
  "geometry": {"coordinates":[-16.816667,28.383333],"type":"Point"}
}