{
  "id": 2355976,
  "type": "Feature",
  "properties": {
    "tgn:hierarchy":[
        "tgn:2355976",
        "tgn:7002659",
        "tgn:1000001",
        "tgn:7012149",
        "tgn:2000062",
        "tgn:7029392"
    ],
    "tgn:id":2355976,
    "tgn:name":"Goose Pond",
    "tgn:placetype":[
        "aat:300008680"
    ]
},
  "bbox": [],
  "geometry": {"coordinates":[-87.65,33.15],"type":"Point"}
}