{
  "id": 7197549,
  "type": "Feature",
  "properties": {
    "tgn:hierarchy":[
        "tgn:7197549",
        "tgn:1000003",
        "tgn:7003682",
        "tgn:7000084",
        "tgn:7029392"
    ],
    "tgn:id":7197549,
    "tgn:name":"Doll-Berg",
    "tgn:placetype":[
        "aat:300008777"
    ]
},
  "bbox": [],
  "geometry": {"coordinates":[7.416667,49.733333],"type":"Point"}
}