{
  "id": 2659686,
  "type": "Feature",
  "properties": {
    "tgn:hierarchy":[
        "tgn:2659686",
        "tgn:1000001",
        "tgn:2001009",
        "tgn:7012149",
        "tgn:7007521",
        "tgn:7029392"
    ],
    "tgn:id":2659686,
    "tgn:name":"Shingobee Bay",
    "tgn:placetype":[
        "aat:300132316"
    ]
},
  "bbox": [],
  "geometry": {"coordinates":[-94.55,47.05],"type":"Point"}
}