{
  "id": 7194008,
  "type": "Feature",
  "properties": {
    "tgn:hierarchy":[
        "tgn:7194008",
        "tgn:1000003",
        "tgn:7003688",
        "tgn:7000084",
        "tgn:7029392"
    ],
    "tgn:id":7194008,
    "tgn:name":"Fischerh\u00e4user",
    "tgn:placetype":[
        "aat:300008347"
    ]
},
  "bbox": [],
  "geometry": {"coordinates":[8.766667,54.883333],"type":"Point"}
}