{
  "id": 7120228,
  "type": "Feature",
  "properties": {
    "tgn:hierarchy":[
        "tgn:7120228",
        "tgn:7003669",
        "tgn:1000003",
        "tgn:7000084",
        "tgn:7029392"
    ],
    "tgn:id":7120228,
    "tgn:name":"Pleitmannswang",
    "tgn:placetype":[
        "aat:300008347"
    ]
},
  "bbox": [],
  "geometry": {"coordinates":[11.116667,48.116667],"type":"Point"}
}