{
  "id": 7167688,
  "type": "Feature",
  "properties": {
    "tgn:hierarchy":[
        "tgn:7167688",
        "tgn:7003669",
        "tgn:1000003",
        "tgn:7000084",
        "tgn:7029392"
    ],
    "tgn:id":7167688,
    "tgn:name":"Heimhof",
    "tgn:placetype":[
        "aat:300008347"
    ]
},
  "bbox": [],
  "geometry": {"coordinates":[11.766667,49.35],"type":"Point"}
}