{
  "id": 7281077,
  "type": "Feature",
  "properties": {
    "tgn:hierarchy":[
        "tgn:7281077",
        "tgn:1001699",
        "tgn:1000049",
        "tgn:1000002",
        "tgn:7029392"
    ],
    "tgn:id":7281077,
    "tgn:name":"Santa Gertrudis",
    "tgn:placetype":[
        "aat:300387200"
    ]
},
  "bbox": [],
  "geometry": {"coordinates":[-73.116667,-40.35],"type":"Point"}
}