{
  "id": 2649177,
  "type": "Feature",
  "properties": {
    "tgn:hierarchy":[
        "tgn:2649177",
        "tgn:1000001",
        "tgn:7012149",
        "tgn:2001848",
        "tgn:7007825",
        "tgn:7029392"
    ],
    "tgn:id":2649177,
    "tgn:name":"Scott Lake",
    "tgn:placetype":[
        "aat:300006191"
    ]
},
  "bbox": [],
  "geometry": {"coordinates":[-88.7833,35.4167],"type":"Point"}
}