{
  "id": 2604008,
  "type": "Feature",
  "properties": {
    "tgn:hierarchy":[
        "tgn:2604008",
        "tgn:1000001",
        "tgn:2001324",
        "tgn:7012149",
        "tgn:7007525",
        "tgn:7029392"
    ],
    "tgn:id":2604008,
    "tgn:name":"Quinn Canyon",
    "tgn:placetype":[
        "aat:300008761"
    ]
},
  "bbox": [],
  "geometry": {"coordinates":[-99.9167,42.6667],"type":"Point"}
}