{
  "id": 7281021,
  "type": "Feature",
  "properties": {
    "tgn:hierarchy":[
        "tgn:7281021",
        "tgn:1001623",
        "tgn:1000049",
        "tgn:1000002",
        "tgn:7029392"
    ],
    "tgn:id":7281021,
    "tgn:name":"Sibbald, Paso",
    "tgn:placetype":[
        "aat:300387026"
    ]
},
  "bbox": [],
  "geometry": {"coordinates":[-72.733056,-44.478333],"type":"Point"}
}