{
  "id": 2711384,
  "type": "Feature",
  "properties": {
    "tgn:hierarchy":[
        "tgn:2711384",
        "tgn:1000001",
        "tgn:7012149",
        "tgn:2001156",
        "tgn:7007522",
        "tgn:7029392"
    ],
    "tgn:id":2711384,
    "tgn:name":"Tanyard Branch",
    "tgn:placetype":[
        "aat:300008699"
    ]
},
  "bbox": [],
  "geometry": {"coordinates":[-88.25,34.9667],"type":"Point"}
}