{
  "id": 7373674,
  "type": "Feature",
  "properties": {
    "tgn:hierarchy":[
        "tgn:7373674",
        "tgn:7005581",
        "tgn:1000001",
        "tgn:7005560",
        "tgn:7029392"
    ],
    "tgn:id":7373674,
    "tgn:name":"La Cieneguita",
    "tgn:placetype":[
        "aat:300008347"
    ]
},
  "bbox": [],
  "geometry": {"coordinates":[-106.65,27.95],"type":"Point"}
}