<<<<<<< HEAD
{
  "id": 7373674,
  "type": "Feature",
  "properties": {
    "tgn:hierarchy":[
        "tgn:7373674",
        "tgn:7005581",
        "tgn:1000001",
        "tgn:7005560",
        "tgn:7029392"
    ],
    "tgn:id":7373674,
    "tgn:name":"La Cieneguita",
    "tgn:placetype":[
        "aat:300008347"
    ]
},
  "bbox": [],
  "geometry": {"coordinates":[-106.65,27.95],"type":"Point"}
}
=======
{"geometry":{"type":"Point","coordinates":[-106.650000,27.950000]},"type":"Feature","properties":{"hierarchy":["tgn:7373674","tgn:7005581","tgn:1000001","tgn:7005560","tgn:7029392"],"placetype":["aat:300008347"],"id":7373674,"name:xx":"La Cieneguita"}}
>>>>>>> 03f74aca74312dbeaf24d7e61306dd6a786dc3d0
