{
  "id": 7410627,
  "type": "Feature",
  "properties": {
    "tgn:hierarchy":[
        "tgn:7410627",
        "tgn:1000001",
        "tgn:7005590",
        "tgn:7005560",
        "tgn:7029392"
    ],
    "tgn:id":7410627,
    "tgn:name":"El Lim\u00f3n",
    "tgn:placetype":[
        "aat:300008347"
    ]
},
  "bbox": [],
  "geometry": {"coordinates":[-101.256944,18.741667],"type":"Point"}
}