{
  "id": 7559192,
  "type": "Feature",
  "properties": {
    "tgn:hierarchy":[
        "tgn:7559192",
        "tgn:1000004",
        "tgn:7000198",
        "tgn:1001977",
        "tgn:7029392"
    ],
    "tgn:id":7559192,
    "tgn:name:en":"S\u0101rgachhi",
    "tgn:placetype":[
        "aat:300007783"
    ]
},
  "bbox": [],
  "geometry": {"coordinates":[88.25,24.016667],"type":"Point"}
}