<<<<<<< HEAD
{
  "id": 7481143,
  "type": "Feature",
  "properties": {
    "tgn:hierarchy":[
        "tgn:7481143",
        "tgn:1000004",
        "tgn:7492971",
        "tgn:1000141",
        "tgn:7029392"
    ],
    "tgn:id":7481143,
    "tgn:name":"Guoli Pingdong Keji Daxue",
    "tgn:placetype":[
        "aat:300006610"
    ]
},
  "bbox": [],
  "geometry": {"coordinates":[120.607933,22.645485],"type":"Point"}
}
=======
{"geometry":{"type":"Point","coordinates":[120.607933,22.645485]},"type":"Feature","properties":{"hierarchy":["tgn:7481143","tgn:1000004","tgn:7492971","tgn:1000141","tgn:7029392"],"placetype":["aat:300006610"],"id":7481143,"name:xx":"Guoli Pingdong Keji Daxue"}}
>>>>>>> 03f74aca74312dbeaf24d7e61306dd6a786dc3d0
