{
  "id": 7310967,
  "type": "Feature",
  "properties": {
    "tgn:hierarchy":[
        "tgn:7310967",
        "tgn:1001699",
        "tgn:1000049",
        "tgn:1000002",
        "tgn:7029392"
    ],
    "tgn:id":7310967,
    "tgn:name":"Meul\u00edn",
    "tgn:placetype":[
        "aat:300008347"
    ]
},
  "bbox": [],
  "geometry": {"coordinates":[-73.316667,-42.416667],"type":"Point"}
}