{
  "id": 7103723,
  "type": "Feature",
  "properties": {
    "tgn:hierarchy":[
        "tgn:7103723",
        "tgn:1000003",
        "tgn:7003688",
        "tgn:7000084",
        "tgn:7029392"
    ],
    "tgn:id":7103723,
    "tgn:name":"Scheidekrug",
    "tgn:placetype":[
        "aat:300000206"
    ]
},
  "bbox": [],
  "geometry": {"coordinates":[10.35,53.933333],"type":"Point"}
}