{
  "id": 7231596,
  "type": "Feature",
  "properties": {
    "tgn:hierarchy":[
        "tgn:7231596",
        "tgn:7002735",
        "tgn:7017076",
        "tgn:1000003",
        "tgn:1000074",
        "tgn:7029392"
    ],
    "tgn:id":7231596,
    "tgn:name":"Kourko\u00fala",
    "tgn:placetype":[
        "aat:300008795"
    ]
},
  "bbox": [],
  "geometry": {"coordinates":[22.433333,36.966667],"type":"Point"}
}