{
  "id": 7214159,
  "type": "Feature",
  "properties": {
    "tgn:hierarchy":[
        "tgn:7214159",
        "tgn:1000003",
        "tgn:7003677",
        "tgn:7000084",
        "tgn:7029392"
    ],
    "tgn:id":7214159,
    "tgn:name":"Schlo\u00df Bloemersheim",
    "tgn:placetype":[
        "aat:300006891"
    ]
},
  "bbox": [],
  "geometry": {"coordinates":[6.516667,51.45],"type":"Point"}
}