{
  "id": 1014431,
  "type": "Feature",
  "properties": {
    "tgn:hierarchy":[
        "tgn:1014431",
        "tgn:7013022",
        "tgn:7005685",
        "tgn:1000001",
        "tgn:7005802",
        "tgn:7029392"
    ],
    "tgn:id":1014431,
    "tgn:name":"Gabarus",
    "tgn:placetype":[
        "aat:300008347"
    ]
},
  "bbox": [],
  "geometry": {"coordinates":[-60.15,45.8333],"type":"Point"}
}