{
  "id": 2082300,
  "type": "Feature",
  "properties": {
    "tgn:hierarchy":[
        "tgn:2082300",
        "tgn:1000001",
        "tgn:7012149",
        "tgn:2001613",
        "tgn:7007706",
        "tgn:7029392"
    ],
    "tgn:id":2082300,
    "tgn:name":"Union Furnace",
    "tgn:placetype":[
        "aat:300008347"
    ]
},
  "bbox": [],
  "geometry": {"coordinates":[-82.35,39.45],"type":"Point"}
}