{
  "id": 2193663,
  "type": "Feature",
  "properties": {
    "tgn:hierarchy":[
        "tgn:2193663",
        "tgn:1000001",
        "tgn:2000307",
        "tgn:7012149",
        "tgn:7007248",
        "tgn:7029392"
    ],
    "tgn:id":2193663,
    "tgn:name":"Brewer Pond",
    "tgn:placetype":[
        "aat:300008680"
    ]
},
  "bbox": [],
  "geometry": {"coordinates":[-81.8833,32.3667],"type":"Point"}
}