<<<<<<< HEAD
{
  "id": 7367856,
  "type": "Feature",
  "properties": {
    "tgn:hierarchy":[
        "tgn:7367856",
        "tgn:7005581",
        "tgn:1000001",
        "tgn:7005560",
        "tgn:7029392"
    ],
    "tgn:id":7367856,
    "tgn:name":"El Potrero",
    "tgn:placetype":[
        "aat:300008347"
    ]
},
  "bbox": [],
  "geometry": {"coordinates":[-107.766667,26.9],"type":"Point"}
}
=======
{"geometry":{"type":"Point","coordinates":[-107.766667,26.900000]},"type":"Feature","properties":{"hierarchy":["tgn:7367856","tgn:7005581","tgn:1000001","tgn:7005560","tgn:7029392"],"placetype":["aat:300008347"],"id":7367856,"name:xx":"El Potrero"}}
>>>>>>> 03f74aca74312dbeaf24d7e61306dd6a786dc3d0
