{
  "id": 1071558,
  "type": "Feature",
  "properties": {
    "tgn:hierarchy":[
        "tgn:1071558",
        "tgn:1000004",
        "tgn:7002087",
        "tgn:1000111",
        "tgn:7029392"
    ],
    "tgn:id":1071558,
    "tgn:name":"Shaquzhen",
    "tgn:placetype":[
        "aat:300008347"
    ]
},
  "bbox": [],
  "geometry": {"coordinates":[103.75,30.55],"type":"Point"}
}