{
  "id": 2176474,
  "type": "Feature",
  "properties": {
    "tgn:hierarchy":[
        "tgn:2176474",
        "tgn:1000001",
        "tgn:7012149",
        "tgn:1002773",
        "tgn:7007240",
        "tgn:7029392"
    ],
    "tgn:id":2176474,
    "tgn:name":"Black Lake",
    "tgn:placetype":[
        "aat:300008680"
    ]
},
  "bbox": [],
  "geometry": {"coordinates":[-82.5667,28.1833],"type":"Point"}
}