{
  "id": 7007550,
  "type": "Feature",
  "properties": {
    "tgn:hierarchy":[
        "tgn:7007550",
        "tgn:1003500",
        "tgn:1000003",
        "tgn:7010380",
        "tgn:1000080",
        "tgn:7029392"
    ],
    "tgn:id":7007550,
    "tgn:name":"Castellaneta",
    "tgn:placetype":[
        "aat:300008347"
    ]
},
  "bbox": [],
  "geometry": {"coordinates":[16.933333,40.633333],"type":"Point"}
}