{
  "id": 2771646,
  "type": "Feature",
  "properties": {
    "tgn:hierarchy":[
        "tgn:2771646",
        "tgn:1000001",
        "tgn:7012149",
        "tgn:2000966",
        "tgn:7007520",
        "tgn:7029392"
    ],
    "tgn:id":2771646,
    "tgn:name":"Wildwood Lake",
    "tgn:placetype":[
        "aat:300008680"
    ]
},
  "bbox": [],
  "geometry": {"coordinates":[-88.55,46.0833],"type":"Point"}
}