{
  "id": 2286124,
  "type": "Feature",
  "properties": {
    "tgn:hierarchy":[
        "tgn:2286124",
        "tgn:1000001",
        "tgn:7012149",
        "tgn:2001251",
        "tgn:7007523",
        "tgn:7029392"
    ],
    "tgn:id":2286124,
    "tgn:name":"Dewey Bald",
    "tgn:placetype":[
        "aat:300008798"
    ]
},
  "bbox": [],
  "geometry": {"coordinates":[-93.2833,36.65],"type":"Point"}
}