{
  "id": 7286803,
  "type": "Feature",
  "properties": {
    "tgn:hierarchy":[
        "tgn:7286803",
        "tgn:1001702",
        "tgn:1000049",
        "tgn:1000002",
        "tgn:7029392"
    ],
    "tgn:id":7286803,
    "tgn:name":"G\u00f3mez, Banco",
    "tgn:placetype":[
        "aat:300387036"
    ]
},
  "bbox": [],
  "geometry": {"coordinates":[-70.45,-53.316667],"type":"Point"}
}