{
  "id": 7370191,
  "type": "Feature",
  "properties": {
    "tgn:hierarchy":[
        "tgn:7370191",
        "tgn:7005581",
        "tgn:1000001",
        "tgn:7005560",
        "tgn:7029392"
    ],
    "tgn:id":7370191,
    "tgn:name":"Janos",
    "tgn:placetype":[
        "aat:300008347"
    ]
},
  "bbox": [],
  "geometry": {"coordinates":[-106.866667,28.266667],"type":"Point"}
}