{
  "id": 7585814,
  "type": "Feature",
  "properties": {
    "tgn:hierarchy":[
        "tgn:7585814",
        "tgn:1000004",
        "tgn:7000198",
        "tgn:7000799",
        "tgn:7029392"
    ],
    "tgn:id":7585814,
    "tgn:name:en":"Kainyar Forest",
    "tgn:placetype":[
        "aat:300008863"
    ]
},
  "bbox": [],
  "geometry": {"coordinates":[74.166667,34.35],"type":"Point"}
}