{
  "id": 1105594,
  "type": "Feature",
  "properties": {
    "tgn:hierarchy":[
        "tgn:1105594",
        "tgn:1000004",
        "tgn:7000198",
        "tgn:7016694",
        "tgn:7029392"
    ],
    "tgn:id":1105594,
    "tgn:name:en":"Megasini",
    "tgn:placetype":[
        "aat:300008795"
    ]
},
  "bbox": [],
  "geometry": {"coordinates":[86.348,21.632],"type":"Point"}
}