{
  "id": 7263609,
  "type": "Feature",
  "properties": {
    "tgn:concordances":{
        "gn:id":"2753879"
    },
    "tgn:hierarchy":[
        "tgn:7263609",
        "tgn:1000003",
        "tgn:7003622",
        "tgn:7016845",
        "tgn:7029392"
    ],
    "tgn:id":7263609,
    "tgn:name:nl":"Holst",
    "tgn:placetype":[
        "aat:300008347"
    ]
},
  "bbox": [],
  "geometry": {"coordinates":[6.05,51.133333],"type":"Point"}
}