{
  "id": 2457630,
  "type": "Feature",
  "properties": {
    "tgn:hierarchy":[
        "tgn:2457630",
        "tgn:1000001",
        "tgn:1002289",
        "tgn:7012149",
        "tgn:7007240",
        "tgn:7029392"
    ],
    "tgn:id":2457630,
    "tgn:name":"Little Marsh",
    "tgn:placetype":[
        "aat:300008905"
    ]
},
  "bbox": [],
  "geometry": {"coordinates":[-81.1667,26.1833],"type":"Point"}
}