{
  "id": 7533613,
  "type": "Feature",
  "properties": {
    "tgn:hierarchy":[
        "tgn:7533613",
        "tgn:7001242",
        "tgn:7001105",
        "tgn:7016833",
        "tgn:7029392"
    ],
    "tgn:id":7533613,
    "tgn:name:en":"Lus\u0101t\u016b, Ba\u1e29r",
    "tgn:placetype":[
        "aat:300387086"
    ]
},
  "bbox": [],
  "geometry": {"coordinates":[31.016667,29.316667],"type":"Point"}
}