{
  "id": 2400513,
  "type": "Feature",
  "properties": {
    "tgn:hierarchy":[
        "tgn:2400513",
        "tgn:1000001",
        "tgn:7012149",
        "tgn:2001544",
        "tgn:7007709",
        "tgn:7029392"
    ],
    "tgn:id":2400513,
    "tgn:name":"Horse Knob",
    "tgn:placetype":[
        "aat:300008798"
    ]
},
  "bbox": [],
  "geometry": {"coordinates":[-82.7167,35.3167],"type":"Point"}
}