<<<<<<< HEAD
{
  "id": 2400513,
  "type": "Feature",
  "properties": {
    "tgn:hierarchy":[
        "tgn:2400513",
        "tgn:1000001",
        "tgn:7012149",
        "tgn:2001544",
        "tgn:7007709",
        "tgn:7029392"
    ],
    "tgn:id":2400513,
    "tgn:name":"Horse Knob",
    "tgn:placetype":[
        "aat:300008798"
    ]
},
  "bbox": [],
  "geometry": {"coordinates":[-82.7167,35.3167],"type":"Point"}
}
=======
{"geometry":{"type":"Point","coordinates":[-82.716700,35.316700]},"type":"Feature","properties":{"hierarchy":["tgn:2400513","tgn:1000001","tgn:7012149","tgn:2001544","tgn:7007709","tgn:7029392"],"placetype":["aat:300008798"],"id":2400513,"name:xx":"Horse Knob"}}
>>>>>>> 03f74aca74312dbeaf24d7e61306dd6a786dc3d0
