{
  "id": 7299686,
  "type": "Feature",
  "properties": {
    "tgn:hierarchy":[
        "tgn:7299686",
        "tgn:7002849",
        "tgn:1000003",
        "tgn:7009604",
        "tgn:1000095",
        "tgn:7029392"
    ],
    "tgn:id":7299686,
    "tgn:name":"Ugarana",
    "tgn:placetype":[
        "aat:300008347"
    ]
},
  "bbox": [],
  "geometry": {"coordinates":[-2.75157,43.143292],"type":"Point"}
}