{
  "id": 2134647,
  "type": "Feature",
  "properties": {
    "tgn:hierarchy":[
        "tgn:2134647",
        "tgn:1000001",
        "tgn:7012149",
        "tgn:2001273",
        "tgn:7007524",
        "tgn:7029392"
    ],
    "tgn:id":2134647,
    "tgn:name":"Antelope Coulee",
    "tgn:placetype":[
        "aat:300008761"
    ]
},
  "bbox": [],
  "geometry": {"coordinates":[-108.8833,47.4667],"type":"Point"}
}