<<<<<<< HEAD
{
  "id": 2330041,
  "type": "Feature",
  "properties": {
    "tgn:hierarchy":[
        "tgn:2330041",
        "tgn:2002143",
        "tgn:1000001",
        "tgn:7012149",
        "tgn:7007919",
        "tgn:7029392"
    ],
    "tgn:id":2330041,
    "tgn:name":"Flagg Knob",
    "tgn:placetype":[
        "aat:300008798"
    ]
},
  "bbox": [],
  "geometry": {"coordinates":[-79.8833,38.1],"type":"Point"}
}
=======
{"geometry":{"type":"Point","coordinates":[-79.883300,38.100000]},"type":"Feature","properties":{"hierarchy":["tgn:2330041","tgn:2002143","tgn:1000001","tgn:7012149","tgn:7007919","tgn:7029392"],"placetype":["aat:300008798"],"id":2330041,"name:xx":"Flagg Knob"}}
>>>>>>> 03f74aca74312dbeaf24d7e61306dd6a786dc3d0
