{
  "id": 2506146,
  "type": "Feature",
  "properties": {
    "tgn:hierarchy":[
        "tgn:2506146",
        "tgn:1000001",
        "tgn:7012149",
        "tgn:2002359",
        "tgn:7007922",
        "tgn:7029392"
    ],
    "tgn:id":2506146,
    "tgn:name":"Mermaid Lake",
    "tgn:placetype":[
        "aat:300008680"
    ]
},
  "bbox": [],
  "geometry": {"coordinates":[-89.7333,46.2167],"type":"Point"}
}