{
  "id": 7424527,
  "type": "Feature",
  "properties": {
    "tgn:hierarchy":[
        "tgn:7424527",
        "tgn:1000001",
        "tgn:7005597",
        "tgn:7005560",
        "tgn:7029392"
    ],
    "tgn:id":7424527,
    "tgn:name":"Guadalupe Victoria",
    "tgn:placetype":[
        "aat:300008347"
    ]
},
  "bbox": [],
  "geometry": {"coordinates":[-98.233333,24.083333],"type":"Point"}
}