{
  "id": 7321485,
  "type": "Feature",
  "properties": {
    "tgn:hierarchy":[
        "tgn:7321485",
        "tgn:7016598",
        "tgn:1000049",
        "tgn:1000002",
        "tgn:7029392"
    ],
    "tgn:id":7321485,
    "tgn:name":"Buena, Caleta",
    "tgn:placetype":[
        "aat:300132317"
    ]
},
  "bbox": [],
  "geometry": {"coordinates":[-70.516667,-25.433333],"type":"Point"}
}