{
  "id": 7315506,
  "type": "Feature",
  "properties": {
    "tgn:hierarchy":[
        "tgn:7315506",
        "tgn:7016598",
        "tgn:1000049",
        "tgn:1000002",
        "tgn:7029392"
    ],
    "tgn:id":7315506,
    "tgn:name":"Chajagua, Pampa",
    "tgn:placetype":[
        "aat:300008805"
    ]
},
  "bbox": [],
  "geometry": {"coordinates":[-68.766667,-21.85],"type":"Point"}
}