<<<<<<< HEAD
{
  "id": 7475821,
  "type": "Feature",
  "properties": {
    "tgn:hierarchy":[
        "tgn:7475821",
        "tgn:7488858",
        "tgn:1000004",
        "tgn:1000141",
        "tgn:7029392"
    ],
    "tgn:id":7475821,
    "tgn:name":"Shuangshi Diaoqiao",
    "tgn:placetype":[
        "aat:300007836"
    ]
},
  "bbox": [],
  "geometry": {"coordinates":[120.780995,23.984354],"type":"Point"}
}
=======
{"geometry":{"type":"Point","coordinates":[120.780995,23.984354]},"type":"Feature","properties":{"hierarchy":["tgn:7475821","tgn:7488858","tgn:1000004","tgn:1000141","tgn:7029392"],"placetype":["aat:300007836"],"id":7475821,"name:xx":"Shuangshi Diaoqiao"}}
>>>>>>> 03f74aca74312dbeaf24d7e61306dd6a786dc3d0
