{
  "id": 7219756,
  "type": "Feature",
  "properties": {
    "tgn:hierarchy":[
        "tgn:7219756",
        "tgn:7002681",
        "tgn:7001395",
        "tgn:1000003",
        "tgn:1000074",
        "tgn:7029392"
    ],
    "tgn:id":7219756,
    "tgn:name":"Vit\u00e1li, Orm\u00edskos",
    "tgn:placetype":[
        "aat:300132316"
    ]
},
  "bbox": [],
  "geometry": {"coordinates":[24.833333,37.933333],"type":"Point"}
}