{
  "id": 1117833,
  "type": "Feature",
  "properties": {
    "tgn:hierarchy":[
        "tgn:1117833",
        "tgn:7005685",
        "tgn:1000001",
        "tgn:7013154",
        "tgn:7029392"
    ],
    "tgn:id":1117833,
    "tgn:name":"Quetico Lake",
    "tgn:placetype":[
        "aat:300008680"
    ]
},
  "bbox": [],
  "geometry": {"coordinates":[-91.9667,48.5833],"type":"Point"}
}