{
  "id": 2110702,
  "type": "Feature",
  "properties": {
    "tgn:hierarchy":[
        "tgn:2110702",
        "tgn:1000001",
        "tgn:7012149",
        "tgn:1002368",
        "tgn:7007919",
        "tgn:7029392"
    ],
    "tgn:id":2110702,
    "tgn:name":"Bleak",
    "tgn:placetype":[
        "aat:300008347",
        "aat:300387210"
    ]
},
  "bbox": [],
  "geometry": {"coordinates":[-77.6667,38.5167],"type":"Point"}
}