{
  "id": 7413849,
  "type": "Feature",
  "properties": {
    "tgn:hierarchy":[
        "tgn:7413849",
        "tgn:7005587",
        "tgn:1000001",
        "tgn:7005560",
        "tgn:7029392"
    ],
    "tgn:id":7413849,
    "tgn:name:es":"El Enzuelado",
    "tgn:placetype":[
        "aat:300008347"
    ]
},
  "bbox": [],
  "geometry": {"coordinates":[-98.615278,20.588889],"type":"Point"}
}