{
  "id": 1017641,
  "type": "Feature",
  "properties": {
    "tgn:hierarchy":[
        "tgn:1017641",
        "tgn:7005586",
        "tgn:1000001",
        "tgn:7005560",
        "tgn:7029392"
    ],
    "tgn:id":1017641,
    "tgn:name":"Jilotl\u00e1n de los Dolores",
    "tgn:placetype":[
        "aat:300008347"
    ]
},
  "bbox": [],
  "geometry": {"coordinates":[-103.016667,19.366667],"type":"Point"}
}