{
  "id": 2291877,
  "type": "Feature",
  "properties": {
    "tgn:hierarchy":[
        "tgn:2291877",
        "tgn:1000001",
        "tgn:7006451",
        "tgn:7012149",
        "tgn:2000104",
        "tgn:7029392"
    ],
    "tgn:id":2291877,
    "tgn:name":"Dome Protective Channel",
    "tgn:placetype":[
        "aat:300006075"
    ]
},
  "bbox": [],
  "geometry": {"coordinates":[-114.2833,32.7167],"type":"Point"}
}