{
  "id": 7023407,
  "type": "Feature",
  "properties": {
    "tgn:hierarchy":[
        "tgn:7023407",
        "tgn:1000001",
        "tgn:7012149",
        "tgn:7029392"
    ],
    "tgn:id":7023407,
    "tgn:name":"Meeks Cabin Reservoir",
    "tgn:placetype":[
        "aat:300006191"
    ]
},
  "bbox": [],
  "geometry": {"coordinates":[-110.5667,40.9833],"type":"Point"}
}