<<<<<<< HEAD
{
  "id": 7023407,
  "type": "Feature",
  "properties": {
    "tgn:hierarchy":[
        "tgn:7023407",
        "tgn:1000001",
        "tgn:7012149",
        "tgn:7029392"
    ],
    "tgn:id":7023407,
    "tgn:name":"Meeks Cabin Reservoir",
    "tgn:placetype":[
        "aat:300006191"
    ]
},
  "bbox": [],
  "geometry": {"coordinates":[-110.5667,40.9833],"type":"Point"}
}
=======
{"geometry":{"type":"Point","coordinates":[-110.566700,40.983300]},"type":"Feature","properties":{"hierarchy":["tgn:7023407","tgn:1000001","tgn:7012149","tgn:7029392"],"placetype":["aat:300006191"],"id":7023407,"name:xx":"Meeks Cabin Reservoir"}}
>>>>>>> 03f74aca74312dbeaf24d7e61306dd6a786dc3d0
