{
  "id": 7241256,
  "type": "Feature",
  "properties": {
    "tgn:hierarchy":[
        "tgn:7241256",
        "tgn:7003466",
        "tgn:1000003",
        "tgn:1000063",
        "tgn:4012014",
        "tgn:7029392"
    ],
    "tgn:id":7241256,
    "tgn:name":"Le Berceau",
    "tgn:placetype":[
        "aat:300008347"
    ]
},
  "bbox": [],
  "geometry": {"coordinates":[4.633333,50.066667],"type":"Point"}
}