{
  "id": 2588929,
  "type": "Feature",
  "properties": {
    "tgn:hierarchy":[
        "tgn:2588929",
        "tgn:1000001",
        "tgn:1002269",
        "tgn:7012149",
        "tgn:7007240",
        "tgn:7029392"
    ],
    "tgn:id":2588929,
    "tgn:name":"Pocket, The",
    "tgn:placetype":[
        "aat:300008791"
    ]
},
  "bbox": [],
  "geometry": {"coordinates":[-82.35,28.95],"type":"Point"}
}