{
  "id": 2628140,
  "type": "Feature",
  "properties": {
    "tgn:hierarchy":[
        "tgn:2628140",
        "tgn:1000001",
        "tgn:7012149",
        "tgn:2002268",
        "tgn:7013961",
        "tgn:7029392"
    ],
    "tgn:id":2628140,
    "tgn:name":"Rollins Lake",
    "tgn:placetype":[
        "aat:300006191"
    ]
},
  "bbox": [],
  "geometry": {"coordinates":[-81.75,38.8167],"type":"Point"}
}