{
  "id": 2260749,
  "type": "Feature",
  "properties": {
    "tgn:hierarchy":[
        "tgn:2260749",
        "tgn:1000001",
        "tgn:7012149",
        "tgn:2001063",
        "tgn:7007521",
        "tgn:7029392"
    ],
    "tgn:id":2260749,
    "tgn:name":"County Ditch Number One Hundred Three",
    "tgn:placetype":[
        "aat:300006075"
    ]
},
  "bbox": [],
  "geometry": {"coordinates":[-94.6833,44.65],"type":"Point"}
}