{
  "id": 2713337,
  "type": "Feature",
  "properties": {
    "tgn:hierarchy":[
        "tgn:2713337",
        "tgn:1000001",
        "tgn:7012149",
        "tgn:2002264",
        "tgn:7013961",
        "tgn:7029392"
    ],
    "tgn:id":2713337,
    "tgn:name":"Taylors Falls Cave",
    "tgn:placetype":[
        "aat:300008746"
    ]
},
  "bbox": [],
  "geometry": {"coordinates":[-80.4667,37.8167],"type":"Point"}
}