{
  "id": 2134221,
  "type": "Feature",
  "properties": {
    "tgn:hierarchy":[
        "tgn:2134221",
        "tgn:2000195",
        "tgn:1000001",
        "tgn:7012149",
        "tgn:7007158",
        "tgn:7029392"
    ],
    "tgn:id":2134221,
    "tgn:name":"Ann, Lake",
    "tgn:placetype":[
        "aat:300008680"
    ]
},
  "bbox": [],
  "geometry": {"coordinates":[-106.6833,37.2667],"type":"Point"}
}