{
  "id": 2345180,
  "type": "Feature",
  "properties": {
    "tgn:hierarchy":[
        "tgn:2345180",
        "tgn:1000001",
        "tgn:7012149",
        "tgn:2001536",
        "tgn:7007709",
        "tgn:7029392"
    ],
    "tgn:id":2345180,
    "tgn:name":"Garfield",
    "tgn:placetype":[
        "aat:300008347"
    ]
},
  "bbox": [],
  "geometry": {"coordinates":[-80.3667,35.5333],"type":"Point"}
}