{
  "id": 2595701,
  "type": "Feature",
  "properties": {
    "tgn:hierarchy":[
        "tgn:2595701",
        "tgn:1000001",
        "tgn:7012149",
        "tgn:7007157",
        "tgn:1002957",
        "tgn:7029392"
    ],
    "tgn:id":2595701,
    "tgn:name":"Pothole Dome",
    "tgn:placetype":[
        "aat:300008798"
    ]
},
  "bbox": [],
  "geometry": {"coordinates":[-119.3833,37.8667],"type":"Point"}
}