{
  "id": 7467088,
  "type": "Feature",
  "properties": {
    "tgn:hierarchy":[
        "tgn:7467088",
        "tgn:7002445",
        "tgn:1000003",
        "tgn:7008165",
        "tgn:7008591",
        "tgn:7029392"
    ],
    "tgn:id":7467088,
    "tgn:name:en":"Alwinton",
    "tgn:placetype":[
        "aat:300008347"
    ]
},
  "bbox": [],
  "geometry": {"coordinates":[-2.116667,55.333333],"type":"Point"}
}