{
  "id": 7019485,
  "type": "Feature",
  "properties": {
    "tgn:hierarchy":[
        "tgn:7019485",
        "tgn:1000001",
        "tgn:7012149",
        "tgn:2001440",
        "tgn:7007566",
        "tgn:7029392"
    ],
    "tgn:id":7019485,
    "tgn:name":"Nellie Gray Mine",
    "tgn:placetype":[
        "aat:300000390"
    ]
},
  "bbox": [],
  "geometry": {"coordinates":[-108.7667,32.2833],"type":"Point"}
}