{
  "id": 7404273,
  "type": "Feature",
  "properties": {
    "tgn:hierarchy":[
        "tgn:7404273",
        "tgn:7005578",
        "tgn:1000001",
        "tgn:7005560",
        "tgn:7029392"
    ],
    "tgn:id":7404273,
    "tgn:name":"La Cristalina",
    "tgn:placetype":[
        "aat:300008347"
    ]
},
  "bbox": [],
  "geometry": {"coordinates":[-91.05,18.716667],"type":"Point"}
}