{
  "id": 7546433,
  "type": "Feature",
  "properties": {
    "tgn:hierarchy":[
        "tgn:7546433",
        "tgn:1000004",
        "tgn:7000198",
        "tgn:7016788",
        "tgn:7029392"
    ],
    "tgn:id":7546433,
    "tgn:name:en":"Ada",
    "tgn:placetype":[
        "aat:300008347"
    ]
},
  "bbox": [],
  "geometry": {"coordinates":[72.233333,25.75],"type":"Point"}
}