{
  "id": 2420166,
  "type": "Feature",
  "properties": {
    "tgn:hierarchy":[
        "tgn:2420166",
        "tgn:1000001",
        "tgn:7012149",
        "tgn:2000238",
        "tgn:7007158",
        "tgn:7029392"
    ],
    "tgn:id":2420166,
    "tgn:name":"Jefferson Creek",
    "tgn:placetype":[
        "aat:300008706"
    ]
},
  "bbox": [],
  "geometry": {"coordinates":[-105.85,39.4833],"type":"Point"}
}