<<<<<<< HEAD
{
  "id": 7021029,
  "type": "Feature",
  "properties": {
    "tgn:hierarchy":[
        "tgn:7021029",
        "tgn:1000001",
        "tgn:7012149",
        "tgn:7029392"
    ],
    "tgn:id":7021029,
    "tgn:name":"Pearl River",
    "tgn:placetype":[
        "aat:300008707"
    ]
},
  "bbox": [],
  "geometry": {"coordinates":[-89.0,32.8833],"type":"Point"}
}
=======
{"geometry":{"type":"Point","coordinates":[-89.000000,32.883300]},"type":"Feature","properties":{"hierarchy":["tgn:7021029","tgn:1000001","tgn:7012149","tgn:7029392"],"placetype":["aat:300008707"],"id":7021029,"name:xx":"Pearl River"}}
>>>>>>> 03f74aca74312dbeaf24d7e61306dd6a786dc3d0
