{
  "id": 7062356,
  "type": "Feature",
  "properties": {
    "tgn:hierarchy":[
        "tgn:7062356",
        "tgn:7003692",
        "tgn:1000003",
        "tgn:7000084",
        "tgn:7029392"
    ],
    "tgn:id":7062356,
    "tgn:name":"Bach",
    "tgn:placetype":[
        "aat:300008347"
    ]
},
  "bbox": [],
  "geometry": {"coordinates":[9.85,48.333333],"type":"Point"}
}