{
  "id": 2449633,
  "type": "Feature",
  "properties": {
    "tgn:hierarchy":[
        "tgn:2449633",
        "tgn:1000001",
        "tgn:2001416",
        "tgn:7012149",
        "tgn:7007526",
        "tgn:7029392"
    ],
    "tgn:id":2449633,
    "tgn:name":"Lincoln Mine",
    "tgn:placetype":[
        "aat:300000390"
    ]
},
  "bbox": [],
  "geometry": {"coordinates":[-115.6167,37.6333],"type":"Point"}
}