{
  "id": 2347109,
  "type": "Feature",
  "properties": {
    "tgn:hierarchy":[
        "tgn:2347109",
        "tgn:7002659",
        "tgn:1000001",
        "tgn:7012149",
        "tgn:2000030",
        "tgn:7029392"
    ],
    "tgn:id":2347109,
    "tgn:name":"Geneva State Forest",
    "tgn:placetype":[
        "aat:300008863"
    ]
},
  "bbox": [],
  "geometry": {"coordinates":[-86.1667,31.1333],"type":"Point"}
}