{
  "id": 7560754,
  "type": "Feature",
  "properties": {
    "tgn:hierarchy":[
        "tgn:7560754",
        "tgn:1000004",
        "tgn:7000198",
        "tgn:7016722",
        "tgn:7029392"
    ],
    "tgn:id":7560754,
    "tgn:name:en":"Adda Nih\u0101l",
    "tgn:placetype":[
        "aat:300008347"
    ]
},
  "bbox": [],
  "geometry": {"coordinates":[79.052046,26.764031],"type":"Point"}
}