{
  "id": 7384259,
  "type": "Feature",
  "properties": {
    "tgn:hierarchy":[
        "tgn:7384259",
        "tgn:1000001",
        "tgn:7005591",
        "tgn:7005560",
        "tgn:7029392"
    ],
    "tgn:id":7384259,
    "tgn:name:es":"Ocotepec",
    "tgn:placetype":[
        "aat:300008347"
    ]
},
  "bbox": [],
  "geometry": {"coordinates":[-97.760833,17.141667],"type":"Point"}
}