{
  "id": 7006251,
  "type": "Feature",
  "properties": {
    "tgn:hierarchy":[
        "tgn:7006251",
        "tgn:7018204",
        "tgn:1000061",
        "tgn:1000003",
        "tgn:7029392"
    ],
    "tgn:id":7006251,
    "tgn:name":"Les Escaldes",
    "tgn:placetype":[
        "aat:300008347",
        "aat:300008375"
    ]
},
  "bbox": [],
  "geometry": {"coordinates":[1.5333,42.5167],"type":"Point"}
}