{
  "id": 2284029,
  "type": "Feature",
  "properties": {
    "tgn:hierarchy":[
        "tgn:2284029",
        "tgn:7013349",
        "tgn:1000001",
        "tgn:7012149",
        "tgn:7007708",
        "tgn:7029392"
    ],
    "tgn:id":2284029,
    "tgn:name":"Denny",
    "tgn:placetype":[
        "aat:300008347"
    ]
},
  "bbox": [],
  "geometry": {"coordinates":[-117.8833,44.65],"type":"Point"}
}