{
  "id": 2451119,
  "type": "Feature",
  "properties": {
    "tgn:hierarchy":[
        "tgn:2451119",
        "tgn:1000001",
        "tgn:7012149",
        "tgn:2001718",
        "tgn:7007708",
        "tgn:7029392"
    ],
    "tgn:id":2451119,
    "tgn:name":"Little Antelope Creek",
    "tgn:placetype":[
        "aat:300008706"
    ]
},
  "bbox": [],
  "geometry": {"coordinates":[-117.5833,42.2167],"type":"Point"}
}