{
  "id": 7011711,
  "type": "Feature",
  "properties": {
    "tgn:hierarchy":[
        "tgn:7011711",
        "tgn:7593921",
        "tgn:1000003",
        "tgn:1001780",
        "tgn:7029392"
    ],
    "tgn:id":7011711,
    "tgn:name":"Moravsk\u00e9 Bud\u011bjovice",
    "tgn:placetype":[
        "aat:300008347"
    ]
},
  "bbox": [],
  "geometry": {"coordinates":[15.8167,49.0667],"type":"Point"}
}