{
  "id": 7493855,
  "type": "Feature",
  "properties": {
    "tgn:hierarchy":[
        "tgn:7493855",
        "tgn:1000004",
        "tgn:7491221",
        "tgn:1000141",
        "tgn:7029392"
    ],
    "tgn:id":7493855,
    "tgn:name":"Beiyuan Guoxiao",
    "tgn:placetype":[
        "aat:300006495"
    ]
},
  "bbox": [],
  "geometry": {"coordinates":[121.293403,23.04029],"type":"Point"}
}