{
  "id": 2024698,
  "type": "Feature",
  "properties": {
    "tgn:hierarchy":[
        "tgn:2024698",
        "tgn:1000001",
        "tgn:7012149",
        "tgn:2000434",
        "tgn:7007248",
        "tgn:7029392"
    ],
    "tgn:id":2024698,
    "tgn:name":"Westlake",
    "tgn:placetype":[
        "aat:300387016"
    ]
},
  "bbox": [],
  "geometry": {"coordinates":[-83.4833,32.4833],"type":"Point"}
}