{
  "id": 2591344,
  "type": "Feature",
  "properties": {
    "tgn:hierarchy":[
        "tgn:2591344",
        "tgn:1000001",
        "tgn:7012149",
        "tgn:2000789",
        "tgn:7007255",
        "tgn:7029392"
    ],
    "tgn:id":2591344,
    "tgn:name":"Polly Spencer Branch",
    "tgn:placetype":[
        "aat:300008699"
    ]
},
  "bbox": [],
  "geometry": {"coordinates":[-82.7167,37.4667],"type":"Point"}
}