{
  "id": 2528597,
  "type": "Feature",
  "properties": {
    "tgn:hierarchy":[
        "tgn:2528597",
        "tgn:1000001",
        "tgn:2001014",
        "tgn:7012149",
        "tgn:7007521",
        "tgn:7029392"
    ],
    "tgn:id":2528597,
    "tgn:name":"Mucker Lake",
    "tgn:placetype":[
        "aat:300008680"
    ]
},
  "bbox": [],
  "geometry": {"coordinates":[-90.5167,48.0833],"type":"Point"}
}