{
  "id": 2127858,
  "type": "Feature",
  "properties": {
    "tgn:hierarchy":[
        "tgn:2127858",
        "tgn:1000001",
        "tgn:7012149",
        "tgn:7029392"
    ],
    "tgn:id":2127858,
    "tgn:name":"Alamuchee Creek",
    "tgn:placetype":[
        "aat:300008706"
    ]
},
  "bbox": [],
  "geometry": {"coordinates":[-88.1667,32.4833],"type":"Point"}
}