{
  "id": 2038729,
  "type": "Feature",
  "properties": {
    "tgn:hierarchy":[
        "tgn:2038729",
        "tgn:1000001",
        "tgn:7012149",
        "tgn:2000812",
        "tgn:7007255",
        "tgn:7029392"
    ],
    "tgn:id":2038729,
    "tgn:name":"Ermine",
    "tgn:placetype":[
        "aat:300008347"
    ]
},
  "bbox": [],
  "geometry": {"coordinates":[-82.7833,37.1167],"type":"Point"}
}