{
  "id": 2740098,
  "type": "Feature",
  "properties": {
    "tgn:hierarchy":[
        "tgn:2740098",
        "tgn:1000001",
        "tgn:7006451",
        "tgn:7012149",
        "tgn:2000099",
        "tgn:7029392"
    ],
    "tgn:id":2740098,
    "tgn:name":"Upper Hole Tank",
    "tgn:placetype":[
        "aat:300006191"
    ]
},
  "bbox": [],
  "geometry": {"coordinates":[-109.9167,33.8333],"type":"Point"}
}