{
  "id": 2586097,
  "type": "Feature",
  "properties": {
    "tgn:hierarchy":[
        "tgn:2586097",
        "tgn:1000001",
        "tgn:7012149",
        "tgn:2000848",
        "tgn:7007255",
        "tgn:7029392"
    ],
    "tgn:id":2586097,
    "tgn:name":"Pisgah Ridge",
    "tgn:placetype":[
        "aat:300266640"
    ]
},
  "bbox": [],
  "geometry": {"coordinates":[-86.5833,37.15],"type":"Point"}
}