{
  "id": 7057008,
  "type": "Feature",
  "properties": {
    "tgn:hierarchy":[
        "tgn:7057008",
        "tgn:1003506",
        "tgn:1000003",
        "tgn:7002993",
        "tgn:1000080",
        "tgn:7029392"
    ],
    "tgn:id":7057008,
    "tgn:name":"Basagliapenta",
    "tgn:placetype":[
        "aat:300008347"
    ]
},
  "bbox": [],
  "geometry": {"coordinates":[13.079444,45.997778],"type":"Point"}
}