{
  "id": 7335590,
  "type": "Feature",
  "properties": {
    "tgn:hierarchy":[
        "tgn:7335590",
        "tgn:7001122",
        "tgn:1000003",
        "tgn:7002765",
        "tgn:1000095",
        "tgn:7029392"
    ],
    "tgn:id":7335590,
    "tgn:name":"Galera, Punta",
    "tgn:placetype":[
        "aat:300386846"
    ]
},
  "bbox": [],
  "geometry": {"coordinates":[3.233333,39.366667],"type":"Point"}
}