{
  "id": 1018243,
  "type": "Feature",
  "properties": {
    "tgn:hierarchy":[
        "tgn:1018243",
        "tgn:1000001",
        "tgn:7005597",
        "tgn:7005560",
        "tgn:7029392"
    ],
    "tgn:id":1018243,
    "tgn:name":"San Miguel",
    "tgn:placetype":[
        "aat:300008347"
    ]
},
  "bbox": [],
  "geometry": {"coordinates":[-98.166667,23.383333],"type":"Point"}
}