{
  "id": 2619269,
  "type": "Feature",
  "properties": {
    "tgn:hierarchy":[
        "tgn:2619269",
        "tgn:1000001",
        "tgn:2001801",
        "tgn:7012149",
        "tgn:7007713",
        "tgn:7029392"
    ],
    "tgn:id":2619269,
    "tgn:name":"Riley Spring",
    "tgn:placetype":[
        "aat:300008697"
    ]
},
  "bbox": [],
  "geometry": {"coordinates":[-103.4333,45.8167],"type":"Point"}
}