{
  "id": 2752377,
  "type": "Feature",
  "properties": {
    "tgn:hierarchy":[
        "tgn:2752377",
        "tgn:1000001",
        "tgn:7012149",
        "tgn:2000986",
        "tgn:7007520",
        "tgn:7029392"
    ],
    "tgn:id":2752377,
    "tgn:name":"Washington Creek",
    "tgn:placetype":[
        "aat:300008706"
    ]
},
  "bbox": [],
  "geometry": {"coordinates":[-89.8167,46.7833],"type":"Point"}
}