{
  "id": 2215101,
  "type": "Feature",
  "properties": {
    "tgn:hierarchy":[
        "tgn:2215101",
        "tgn:7013272",
        "tgn:1000001",
        "tgn:7012149",
        "tgn:7007710",
        "tgn:7029392"
    ],
    "tgn:id":2215101,
    "tgn:name":"California Kirkbride",
    "tgn:placetype":[
        "aat:300008347"
    ]
},
  "bbox": [],
  "geometry": {"coordinates":[-80.0167,40.45],"type":"Point"}
}