{
  "id": 2564580,
  "type": "Feature",
  "properties": {
    "tgn:hierarchy":[
        "tgn:2564580",
        "tgn:1000001",
        "tgn:7012149",
        "tgn:2001717",
        "tgn:7007708",
        "tgn:7029392"
    ],
    "tgn:id":2564580,
    "tgn:name":"Packers Gulch",
    "tgn:placetype":[
        "aat:300008761"
    ]
},
  "bbox": [],
  "geometry": {"coordinates":[-122.35,44.6167],"type":"Point"}
}