{
  "id": 2140771,
  "type": "Feature",
  "properties": {
    "tgn:hierarchy":[
        "tgn:2140771",
        "tgn:1000001",
        "tgn:7012149",
        "tgn:7007524",
        "tgn:7029392"
    ],
    "tgn:id":2140771,
    "tgn:name":"Avalanche Creek",
    "tgn:placetype":[
        "aat:300008706"
    ]
},
  "bbox": [],
  "geometry": {"coordinates":[-111.5333,46.75],"type":"Point"}
}