{
  "id": 2229116,
  "type": "Feature",
  "properties": {
    "tgn:hierarchy":[
        "tgn:2229116",
        "tgn:7002659",
        "tgn:1000001",
        "tgn:7012149",
        "tgn:2000058",
        "tgn:7029392"
    ],
    "tgn:id":2229116,
    "tgn:name":"Cedar Lake",
    "tgn:placetype":[
        "aat:300008680"
    ]
},
  "bbox": [],
  "geometry": {"coordinates":[-86.55,33.4667],"type":"Point"}
}