{
  "id": 2102051,
  "type": "Feature",
  "properties": {
    "tgn:hierarchy":[
        "tgn:2102051",
        "tgn:1000001",
        "tgn:7012149",
        "tgn:2001883",
        "tgn:7007825",
        "tgn:7029392"
    ],
    "tgn:id":2102051,
    "tgn:name":"West Emory",
    "tgn:placetype":[
        "aat:300008347",
        "aat:300387210"
    ]
},
  "bbox": [],
  "geometry": {"coordinates":[-84.0833,35.8667],"type":"Point"}
}