<<<<<<< HEAD
{
  "id": 2253529,
  "type": "Feature",
  "properties": {
    "tgn:hierarchy":[
        "tgn:2253529",
        "tgn:1000001",
        "tgn:7012149",
        "tgn:2000964",
        "tgn:7007520",
        "tgn:7029392"
    ],
    "tgn:id":2253529,
    "tgn:name":"Cook Drain",
    "tgn:placetype":[
        "aat:300006075"
    ]
},
  "bbox": [],
  "geometry": {"coordinates":[-82.75,43.7333],"type":"Point"}
}
=======
{"geometry":{"type":"Point","coordinates":[-82.750000,43.733300]},"type":"Feature","properties":{"hierarchy":["tgn:2253529","tgn:1000001","tgn:7012149","tgn:2000964","tgn:7007520","tgn:7029392"],"placetype":["aat:300006075"],"id":2253529,"name:xx":"Cook Drain"}}
>>>>>>> 03f74aca74312dbeaf24d7e61306dd6a786dc3d0
