{
  "id": 2209843,
  "type": "Feature",
  "properties": {
    "tgn:hierarchy":[
        "tgn:2209843",
        "tgn:1000001",
        "tgn:7012149",
        "tgn:2000182",
        "tgn:7007157",
        "tgn:7029392"
    ],
    "tgn:id":2209843,
    "tgn:name":"Burro Wash",
    "tgn:placetype":[
        "aat:300008699"
    ]
},
  "bbox": [],
  "geometry": {"coordinates":[-114.6333,32.95],"type":"Point"}
}