{
  "id": 1118117,
  "type": "Feature",
  "properties": {
    "tgn:hierarchy":[
        "tgn:1118117",
        "tgn:1000004",
        "tgn:7002081",
        "tgn:1000111",
        "tgn:7029392"
    ],
    "tgn:id":1118117,
    "tgn:name":"Shang Hu",
    "tgn:placetype":[
        "aat:300008680"
    ]
},
  "bbox": [],
  "geometry": {"coordinates":[120.6833,31.65],"type":"Point"}
}