{
  "id": 7481168,
  "type": "Feature",
  "properties": {
    "tgn:hierarchy":[
        "tgn:7481168",
        "tgn:1000004",
        "tgn:7492971",
        "tgn:1000141",
        "tgn:7029392"
    ],
    "tgn:id":7481168,
    "tgn:name":"Bailu",
    "tgn:placetype":[
        "aat:300008347"
    ]
},
  "bbox": [],
  "geometry": {"coordinates":[120.688004,22.682308],"type":"Point"}
}