{
  "id": 7207878,
  "type": "Feature",
  "properties": {
    "tgn:hierarchy":[
        "tgn:7207878",
        "tgn:1000003",
        "tgn:7003687",
        "tgn:7000084",
        "tgn:7029392"
    ],
    "tgn:id":7207878,
    "tgn:name":"Coswig, Forst",
    "tgn:placetype":[
        "aat:300008863"
    ]
},
  "bbox": [],
  "geometry": {"coordinates":[12.466667,51.933333],"type":"Point"}
}