{
  "id": 2757599,
  "type": "Feature",
  "properties": {
    "tgn:hierarchy":[
        "tgn:2757599",
        "tgn:2000919",
        "tgn:1000001",
        "tgn:7012149",
        "tgn:7007515",
        "tgn:7029392"
    ],
    "tgn:id":2757599,
    "tgn:name":"West Branch Brandy Brook",
    "tgn:placetype":[
        "aat:300008699"
    ]
},
  "bbox": [],
  "geometry": {"coordinates":[-68.2333,46.25],"type":"Point"}
}