{
  "id": 2172519,
  "type": "Feature",
  "properties": {
    "tgn:hierarchy":[
        "tgn:2172519",
        "tgn:2001468",
        "tgn:1000001",
        "tgn:7012149",
        "tgn:7007709",
        "tgn:7029392"
    ],
    "tgn:id":2172519,
    "tgn:name":"Bill White Creek",
    "tgn:placetype":[
        "aat:300008706"
    ]
},
  "bbox": [],
  "geometry": {"coordinates":[-81.9333,36.0333],"type":"Point"}
}