{
  "id": 2661933,
  "type": "Feature",
  "properties": {
    "tgn:hierarchy":[
        "tgn:2661933",
        "tgn:1000001",
        "tgn:7012149",
        "tgn:2001544",
        "tgn:7007709",
        "tgn:7029392"
    ],
    "tgn:id":2661933,
    "tgn:name":"Shut-in Ridge",
    "tgn:placetype":[
        "aat:300266640"
    ]
},
  "bbox": [],
  "geometry": {"coordinates":[-82.7333,35.2667],"type":"Point"}
}