{
  "id": 7565368,
  "type": "Feature",
  "properties": {
    "tgn:hierarchy":[
        "tgn:7565368",
        "tgn:1000004",
        "tgn:7000198",
        "tgn:1001894",
        "tgn:7029392"
    ],
    "tgn:id":7565368,
    "tgn:name:en":"Tamora",
    "tgn:placetype":[
        "aat:300008347"
    ]
},
  "bbox": [],
  "geometry": {"coordinates":[79.100935,24.765255],"type":"Point"}
}