{
  "id": 2716093,
  "type": "Feature",
  "properties": {
    "tgn:hierarchy":[
        "tgn:2716093",
        "tgn:1000001",
        "tgn:7012149",
        "tgn:1002979",
        "tgn:7007920",
        "tgn:7029392"
    ],
    "tgn:id":2716093,
    "tgn:name":"Thadbar Creek",
    "tgn:placetype":[
        "aat:300008706"
    ]
},
  "bbox": [],
  "geometry": {"coordinates":[-123.5833,46.3167],"type":"Point"}
}