{
  "id": 7503089,
  "type": "Feature",
  "properties": {
    "tgn:hierarchy":[
        "tgn:7503089",
        "tgn:7001010",
        "tgn:1000004",
        "tgn:1000141",
        "tgn:7029392"
    ],
    "tgn:id":7503089,
    "tgn:name":"Zhongxing Qiao",
    "tgn:placetype":[
        "aat:300007836"
    ]
},
  "bbox": [],
  "geometry": {"coordinates":[121.256389,23.185278],"type":"Point"}
}