{
  "id": 2128207,
  "type": "Feature",
  "properties": {
    "tgn:hierarchy":[
        "tgn:2128207",
        "tgn:1000001",
        "tgn:7012149",
        "tgn:7013941",
        "tgn:7007568",
        "tgn:7029392"
    ],
    "tgn:id":2128207,
    "tgn:name":"Alburg Brook",
    "tgn:placetype":[
        "aat:300008699"
    ]
},
  "bbox": [],
  "geometry": {"coordinates":[-74.5167,44.7333],"type":"Point"}
}