{
  "id": 2510520,
  "type": "Feature",
  "properties": {
    "tgn:hierarchy":[
        "tgn:2510520",
        "tgn:1000001",
        "tgn:7012149",
        "tgn:2001449",
        "tgn:7007566",
        "tgn:7029392"
    ],
    "tgn:id":2510520,
    "tgn:name":"Middle Tank",
    "tgn:placetype":[
        "aat:300006191"
    ]
},
  "bbox": [],
  "geometry": {"coordinates":[-106.8167,36.4167],"type":"Point"}
}