<<<<<<< HEAD
{
  "id": 7355682,
  "type": "Feature",
  "properties": {
    "tgn:hierarchy":[
        "tgn:7355682",
        "tgn:1000001",
        "tgn:1001937",
        "tgn:7005560",
        "tgn:7029392"
    ],
    "tgn:id":7355682,
    "tgn:name":"Calderas",
    "tgn:placetype":[
        "aat:300387007"
    ]
},
  "bbox": [],
  "geometry": {"coordinates":[-88.85,18.133333],"type":"Point"}
}
=======
{"geometry":{"type":"Point","coordinates":[-88.850000,18.133333]},"type":"Feature","properties":{"hierarchy":["tgn:7355682","tgn:1000001","tgn:1001937","tgn:7005560","tgn:7029392"],"placetype":["aat:300387007"],"id":7355682,"name:xx":"Calderas"}}
>>>>>>> 03f74aca74312dbeaf24d7e61306dd6a786dc3d0
