{
  "id": 2310746,
  "type": "Feature",
  "properties": {
    "tgn:hierarchy":[
        "tgn:2310746",
        "tgn:1000001",
        "tgn:7006451",
        "tgn:2000092",
        "tgn:7012149",
        "tgn:7029392"
    ],
    "tgn:id":2310746,
    "tgn:name":"Eckles Tank",
    "tgn:placetype":[
        "aat:300006191"
    ]
},
  "bbox": [],
  "geometry": {"coordinates":[-110.9167,34.8167],"type":"Point"}
}