{
  "id": 7575608,
  "type": "Feature",
  "properties": {
    "tgn:hierarchy":[
        "tgn:7575608",
        "tgn:1000004",
        "tgn:7000198",
        "tgn:7031783",
        "tgn:7029392"
    ],
    "tgn:id":7575608,
    "tgn:name:en":"Kolkole Kal\u0101n",
    "tgn:placetype":[
        "aat:300008347"
    ]
},
  "bbox": [],
  "geometry": {"coordinates":[84.726078,24.154943],"type":"Point"}
}