<<<<<<< HEAD
{
  "id": 7482373,
  "type": "Feature",
  "properties": {
    "tgn:hierarchy":[
        "tgn:7482373",
        "tgn:7468018",
        "tgn:1000004",
        "tgn:1000141",
        "tgn:7029392"
    ],
    "tgn:id":7482373,
    "tgn:name":"Xizidi",
    "tgn:placetype":[
        "aat:300008347"
    ]
},
  "bbox": [],
  "geometry": {"coordinates":[120.426389,23.438056],"type":"Point"}
}
=======
{"geometry":{"type":"Point","coordinates":[120.426389,23.438056]},"type":"Feature","properties":{"hierarchy":["tgn:7482373","tgn:7468018","tgn:1000004","tgn:1000141","tgn:7029392"],"placetype":["aat:300008347"],"id":7482373,"name:xx":"Xizidi"}}
>>>>>>> 03f74aca74312dbeaf24d7e61306dd6a786dc3d0
