{
  "id": 2312196,
  "type": "Feature",
  "properties": {
    "tgn:hierarchy":[
        "tgn:2312196",
        "tgn:1000001",
        "tgn:1002310",
        "tgn:7012149",
        "tgn:7007710",
        "tgn:7029392"
    ],
    "tgn:id":2312196,
    "tgn:name":"Eichelberger Spring",
    "tgn:placetype":[
        "aat:300008697"
    ]
},
  "bbox": [],
  "geometry": {"coordinates":[-76.9167,40.2167],"type":"Point"}
}