{
  "id": 7283210,
  "type": "Feature",
  "properties": {
    "tgn:hierarchy":[
        "tgn:7283210",
        "tgn:1001657",
        "tgn:1000049",
        "tgn:1000002",
        "tgn:7029392"
    ],
    "tgn:id":7283210,
    "tgn:name":"Palo Colorado, Cerro",
    "tgn:placetype":[
        "aat:300008795"
    ]
},
  "bbox": [],
  "geometry": {"coordinates":[-71.45,-31.983333],"type":"Point"}
}