{
  "id": 1034377,
  "type": "Feature",
  "properties": {
    "tgn:hierarchy":[
        "tgn:1034377",
        "tgn:1000003",
        "tgn:7002885",
        "tgn:1000070",
        "tgn:7029392"
    ],
    "tgn:id":1034377,
    "tgn:name":"Meyrueis",
    "tgn:placetype":[
        "aat:300008347"
    ]
},
  "bbox": [],
  "geometry": {"coordinates":[3.4333,44.1833],"type":"Point"}
}