{
  "id": 2459086,
  "type": "Feature",
  "properties": {
    "tgn:hierarchy":[
        "tgn:2459086",
        "tgn:1000001",
        "tgn:7012149",
        "tgn:2002115",
        "tgn:7007827",
        "tgn:7029392"
    ],
    "tgn:id":2459086,
    "tgn:name":"Little Pine Fork",
    "tgn:placetype":[
        "aat:300008699"
    ]
},
  "bbox": [],
  "geometry": {"coordinates":[-111.4167,41.0833],"type":"Point"}
}