{
  "id": 7444833,
  "type": "Feature",
  "properties": {
    "tgn:hierarchy":[
        "tgn:7444833",
        "tgn:7002444",
        "tgn:7008074",
        "tgn:1000003",
        "tgn:7008591",
        "tgn:7029392"
    ],
    "tgn:id":7444833,
    "tgn:name:en":"West Barcloy",
    "tgn:placetype":[
        "aat:300008347"
    ]
},
  "bbox": [],
  "geometry": {"coordinates":[-3.783333,54.85],"type":"Point"}
}