{
  "id": 7578873,
  "type": "Feature",
  "properties": {
    "tgn:hierarchy":[
        "tgn:7578873",
        "tgn:1000004",
        "tgn:1001869",
        "tgn:7000198",
        "tgn:7029392"
    ],
    "tgn:id":7578873,
    "tgn:name:en":"Walan",
    "tgn:placetype":[
        "aat:300008347"
    ]
},
  "bbox": [],
  "geometry": {"coordinates":[73.083333,21.95],"type":"Point"}
}