{
  "id": 2493693,
  "type": "Feature",
  "properties": {
    "tgn:hierarchy":[
        "tgn:2493693",
        "tgn:1000001",
        "tgn:7012149",
        "tgn:1002593",
        "tgn:7007568",
        "tgn:7029392"
    ],
    "tgn:id":2493693,
    "tgn:name":"Marsh Pond",
    "tgn:placetype":[
        "aat:300008680"
    ]
},
  "bbox": [],
  "geometry": {"coordinates":[-75.4167,44.15],"type":"Point"}
}