{
  "id": 2633402,
  "type": "Feature",
  "properties": {
    "tgn:hierarchy":[
        "tgn:2633402",
        "tgn:1000001",
        "tgn:1002308",
        "tgn:7012149",
        "tgn:7007710",
        "tgn:7029392"
    ],
    "tgn:id":2633402,
    "tgn:name":"Rundelltown Creek",
    "tgn:placetype":[
        "aat:300008706"
    ]
},
  "bbox": [],
  "geometry": {"coordinates":[-80.2667,41.7167],"type":"Point"}
}