{
  "id": 1034150,
  "type": "Feature",
  "properties": {
    "tgn:hierarchy":[
        "tgn:1034150",
        "tgn:7002870",
        "tgn:1000003",
        "tgn:1000070",
        "tgn:7029392"
    ],
    "tgn:id":1034150,
    "tgn:name":"Lutterbach",
    "tgn:placetype":[
        "aat:300008347"
    ]
},
  "bbox": [],
  "geometry": {"coordinates":[7.2833,47.7667],"type":"Point"}
}