{
  "id": 7484486,
  "type": "Feature",
  "properties": {
    "tgn:hierarchy":[
        "tgn:7484486",
        "tgn:7487020",
        "tgn:1000004",
        "tgn:1000141",
        "tgn:7029392"
    ],
    "tgn:id":7484486,
    "tgn:name":"Zhonglu",
    "tgn:placetype":[
        "aat:300008347"
    ]
},
  "bbox": [],
  "geometry": {"coordinates":[120.711667,24.469444],"type":"Point"}
}