{
  "id": 2497133,
  "type": "Feature",
  "properties": {
    "tgn:hierarchy":[
        "tgn:2497133",
        "tgn:1000001",
        "tgn:2001592",
        "tgn:7012149",
        "tgn:7007705",
        "tgn:7029392"
    ],
    "tgn:id":2497133,
    "tgn:name":"Mauvais Coulee",
    "tgn:placetype":[
        "aat:300008701"
    ]
},
  "bbox": [],
  "geometry": {"coordinates":[-99.25,48.8667],"type":"Point"}
}