{
  "id": 2244208,
  "type": "Feature",
  "properties": {
    "tgn:hierarchy":[
        "tgn:2244208",
        "tgn:1000001",
        "tgn:7012149",
        "tgn:1002633",
        "tgn:7007252",
        "tgn:7029392"
    ],
    "tgn:id":2244208,
    "tgn:name":"Clifford Park",
    "tgn:placetype":[
        "aat:300008347"
    ]
},
  "bbox": [],
  "geometry": {"coordinates":[-87.0833,39.7833],"type":"Point"}
}