{
  "id": 2675265,
  "type": "Feature",
  "properties": {
    "tgn:hierarchy":[
        "tgn:2675265",
        "tgn:1000001",
        "tgn:7012149",
        "tgn:2000488",
        "tgn:7007250",
        "tgn:7029392"
    ],
    "tgn:id":2675265,
    "tgn:name":"Soldier Cap",
    "tgn:placetype":[
        "aat:300008798"
    ]
},
  "bbox": [],
  "geometry": {"coordinates":[-116.75,43.2833],"type":"Point"}
}