{
  "id": 2279497,
  "type": "Feature",
  "properties": {
    "tgn:hierarchy":[
        "tgn:2279497",
        "tgn:1002134",
        "tgn:1000001",
        "tgn:7012149",
        "tgn:7007251",
        "tgn:7029392"
    ],
    "tgn:id":2279497,
    "tgn:name":"Deadman Island",
    "tgn:placetype":[
        "aat:300008791"
    ]
},
  "bbox": [],
  "geometry": {"coordinates":[-91.45,39.9833],"type":"Point"}
}