{
  "id": 7259721,
  "type": "Feature",
  "properties": {
    "tgn:hierarchy":[
        "tgn:7259721",
        "tgn:7003465",
        "tgn:1000003",
        "tgn:1000063",
        "tgn:4012014",
        "tgn:7029392"
    ],
    "tgn:id":7259721,
    "tgn:name":"Watinsart, Bois de",
    "tgn:placetype":[
        "aat:300008863"
    ]
},
  "bbox": [],
  "geometry": {"coordinates":[5.35,49.666667],"type":"Point"}
}