{
  "id": 7417775,
  "type": "Feature",
  "properties": {
    "tgn:hierarchy":[
        "tgn:7417775",
        "tgn:1000001",
        "tgn:7005591",
        "tgn:7005560",
        "tgn:7029392"
    ],
    "tgn:id":7417775,
    "tgn:name:es":"Santiago Viejo",
    "tgn:placetype":[
        "aat:300008347"
    ]
},
  "bbox": [],
  "geometry": {"coordinates":[-96.999167,17.976944],"type":"Point"}
}