{
  "id": 2552670,
  "type": "Feature",
  "properties": {
    "tgn:hierarchy":[
        "tgn:2552670",
        "tgn:1000001",
        "tgn:7012149",
        "tgn:2000627",
        "tgn:7007253",
        "tgn:7029392"
    ],
    "tgn:id":2552670,
    "tgn:name":"Nutt Hollow",
    "tgn:placetype":[
        "aat:300008761"
    ]
},
  "bbox": [],
  "geometry": {"coordinates":[-95.9167,42.1333],"type":"Point"}
}