{
  "id": 2202718,
  "type": "Feature",
  "properties": {
    "tgn:hierarchy":[
        "tgn:2202718",
        "tgn:1000001",
        "tgn:2001481",
        "tgn:7012149",
        "tgn:7007709",
        "tgn:7029392"
    ],
    "tgn:id":2202718,
    "tgn:name":"Buckberry Branch",
    "tgn:placetype":[
        "aat:300008699"
    ]
},
  "bbox": [],
  "geometry": {"coordinates":[-84.2333,35.2167],"type":"Point"}
}