{
  "id": 7031783,
  "type": "Feature",
  "properties": {
    "tgn:hierarchy":[
        "tgn:7031783",
        "tgn:1000004",
        "tgn:7000198",
        "tgn:7029392"
    ],
    "tgn:id":7031783,
    "tgn:name":"Jharkhand",
    "tgn:placetype":[
        "aat:300387064",
        "aat:300000776"
    ]
},
  "bbox": [],
  "geometry": {"coordinates":[85.508,23.75],"type":"Point"}
}