{
  "id": 2410551,
  "type": "Feature",
  "properties": {
    "tgn:hierarchy":[
        "tgn:2410551",
        "tgn:1000001",
        "tgn:7012149",
        "tgn:2002188",
        "tgn:7007919",
        "tgn:7029392"
    ],
    "tgn:id":2410551,
    "tgn:name":"Indian Cave",
    "tgn:placetype":[
        "aat:300008746"
    ]
},
  "bbox": [],
  "geometry": {"coordinates":[-82.3167,36.8667],"type":"Point"}
}