<<<<<<< HEAD
{
  "id": 2251576,
  "type": "Feature",
  "properties": {
    "tgn:hierarchy":[
        "tgn:2251576",
        "tgn:1000001",
        "tgn:2002106",
        "tgn:7012149",
        "tgn:7007827",
        "tgn:7029392"
    ],
    "tgn:id":2251576,
    "tgn:name":"Commonwealth Square Condominium",
    "tgn:placetype":[
        "aat:300008347"
    ]
},
  "bbox": [],
  "geometry": {"coordinates":[-112.0167,41.15],"type":"Point"}
}
=======
{"geometry":{"type":"Point","coordinates":[-112.016700,41.150000]},"type":"Feature","properties":{"hierarchy":["tgn:2251576","tgn:1000001","tgn:2002106","tgn:7012149","tgn:7007827","tgn:7029392"],"placetype":["aat:300008347"],"id":2251576,"name:xx":"Commonwealth Square Condominium"}}
>>>>>>> 03f74aca74312dbeaf24d7e61306dd6a786dc3d0
