{
  "id": 2180905,
  "type": "Feature",
  "properties": {
    "tgn:hierarchy":[
        "tgn:2180905",
        "tgn:7002659",
        "tgn:1000001",
        "tgn:7012149",
        "tgn:2000039",
        "tgn:7029392"
    ],
    "tgn:id":2180905,
    "tgn:name":"Blowing Spring Branch",
    "tgn:placetype":[
        "aat:300008699"
    ]
},
  "bbox": [],
  "geometry": {"coordinates":[-87.2333,34.5833],"type":"Point"}
}