{
  "id": 2598822,
  "type": "Feature",
  "properties": {
    "tgn:hierarchy":[
        "tgn:2598822",
        "tgn:2000854",
        "tgn:1000001",
        "tgn:7012149",
        "tgn:7007256",
        "tgn:7029392"
    ],
    "tgn:id":2598822,
    "tgn:name":"Prime Gully",
    "tgn:placetype":[
        "aat:300008699"
    ]
},
  "bbox": [],
  "geometry": {"coordinates":[-92.3333,30.1167],"type":"Point"}
}