{
  "id": 2588884,
  "type": "Feature",
  "properties": {
    "tgn:hierarchy":[
        "tgn:2588884",
        "tgn:1000001",
        "tgn:2002150",
        "tgn:7012149",
        "tgn:7007919",
        "tgn:7029392"
    ],
    "tgn:id":2588884,
    "tgn:name":"Pocket Creek",
    "tgn:placetype":[
        "aat:300008706"
    ]
},
  "bbox": [],
  "geometry": {"coordinates":[-79.3333,37.1667],"type":"Point"}
}