<<<<<<< HEAD
{
  "id": 2257214,
  "type": "Feature",
  "properties": {
    "tgn:hierarchy":[
        "tgn:2257214",
        "tgn:1000001",
        "tgn:7006451",
        "tgn:2000095",
        "tgn:7012149",
        "tgn:7029392"
    ],
    "tgn:id":2257214,
    "tgn:name":"Corner Tank",
    "tgn:placetype":[
        "aat:300006191"
    ]
},
  "bbox": [],
  "geometry": {"coordinates":[-109.2833,33.3],"type":"Point"}
}
=======
{"geometry":{"type":"Point","coordinates":[-109.283300,33.300000]},"type":"Feature","properties":{"hierarchy":["tgn:2257214","tgn:1000001","tgn:7006451","tgn:2000095","tgn:7012149","tgn:7029392"],"placetype":["aat:300006191"],"id":2257214,"name:xx":"Corner Tank"}}
>>>>>>> 03f74aca74312dbeaf24d7e61306dd6a786dc3d0
