{
  "id": 2235560,
  "type": "Feature",
  "properties": {
    "tgn:hierarchy":[
        "tgn:2235560",
        "tgn:1000001",
        "tgn:7012149",
        "tgn:1002399",
        "tgn:7007710",
        "tgn:7029392"
    ],
    "tgn:id":2235560,
    "tgn:name":"Chestnut Flat",
    "tgn:placetype":[
        "aat:300266640"
    ]
},
  "bbox": [],
  "geometry": {"coordinates":[-78.0667,39.8667],"type":"Point"}
}