{
  "id": 7412129,
  "type": "Feature",
  "properties": {
    "tgn:hierarchy":[
        "tgn:7412129",
        "tgn:1000001",
        "tgn:7005596",
        "tgn:7005560",
        "tgn:7029392"
    ],
    "tgn:id":7412129,
    "tgn:name:es":"Carlos Madrazo",
    "tgn:placetype":[
        "aat:300008347"
    ]
},
  "bbox": [],
  "geometry": {"coordinates":[-93.445833,17.925],"type":"Point"}
}