{
  "id": 2622896,
  "type": "Feature",
  "properties": {
    "tgn:hierarchy":[
        "tgn:2622896",
        "tgn:1000001",
        "tgn:7012149",
        "tgn:7007157",
        "tgn:2000185",
        "tgn:7029392"
    ],
    "tgn:id":2622896,
    "tgn:name":"Robinson Reef",
    "tgn:placetype":[
        "aat:300132348"
    ]
},
  "bbox": [],
  "geometry": {"coordinates":[-123.5333,38.7667],"type":"Point"}
}