{
  "id": 2220446,
  "type": "Feature",
  "properties": {
    "tgn:hierarchy":[
        "tgn:2220446",
        "tgn:1000001",
        "tgn:2001734",
        "tgn:7012149",
        "tgn:7007712",
        "tgn:7029392"
    ],
    "tgn:id":2220446,
    "tgn:name":"Cape Island Point",
    "tgn:placetype":[
        "aat:300008850"
    ]
},
  "bbox": [],
  "geometry": {"coordinates":[-79.3333,33.0667],"type":"Point"}
}