<<<<<<< HEAD
{
  "id": 7175932,
  "type": "Feature",
  "properties": {
    "tgn:hierarchy":[
        "tgn:7175932",
        "tgn:1000003",
        "tgn:7003689",
        "tgn:7000084",
        "tgn:7029392"
    ],
    "tgn:id":7175932,
    "tgn:name":"Gro\u00dfengotternsches Ried",
    "tgn:placetype":[
        "aat:300055621"
    ]
},
  "bbox": [],
  "geometry": {"coordinates":[10.583333,51.15],"type":"Point"}
}
=======
{"geometry":{"type":"Point","coordinates":[10.583333,51.150000]},"type":"Feature","properties":{"hierarchy":["tgn:7175932","tgn:1000003","tgn:7003689","tgn:7000084","tgn:7029392"],"placetype":["aat:300055621"],"id":7175932,"name:xx":"Gro\u00dfengotternsches Ried"}}
>>>>>>> 03f74aca74312dbeaf24d7e61306dd6a786dc3d0
