{
  "id": 7063639,
  "type": "Feature",
  "properties": {
    "tgn:hierarchy":[
        "tgn:7063639",
        "tgn:7003669",
        "tgn:1000003",
        "tgn:7000084",
        "tgn:7029392"
    ],
    "tgn:id":7063639,
    "tgn:name":"Anzenberg",
    "tgn:placetype":[
        "aat:300000206"
    ]
},
  "bbox": [],
  "geometry": {"coordinates":[12.933333,48.366667],"type":"Point"}
}