{
  "id": 2149922,
  "type": "Feature",
  "properties": {
    "tgn:hierarchy":[
        "tgn:2149922",
        "tgn:1000001",
        "tgn:7012149",
        "tgn:1002699",
        "tgn:7007708",
        "tgn:7029392"
    ],
    "tgn:id":2149922,
    "tgn:name":"Bartlett Landing",
    "tgn:placetype":[
        "aat:300008347"
    ]
},
  "bbox": [],
  "geometry": {"coordinates":[-122.4667,45.5667],"type":"Point"}
}