{
  "id": 2105205,
  "type": "Feature",
  "properties": {
    "tgn:hierarchy":[
        "tgn:2105205",
        "tgn:1000001",
        "tgn:7012149",
        "tgn:1002637",
        "tgn:7007826",
        "tgn:7029392"
    ],
    "tgn:id":2105205,
    "tgn:name":"Jackson",
    "tgn:placetype":[
        "aat:300008347",
        "aat:300387210"
    ]
},
  "bbox": [],
  "geometry": {"coordinates":[-94.5667,32.7333],"type":"Point"}
}