{
  "id": 2459818,
  "type": "Feature",
  "properties": {
    "tgn:hierarchy":[
        "tgn:2459818",
        "tgn:2000919",
        "tgn:1000001",
        "tgn:7012149",
        "tgn:7007515",
        "tgn:7029392"
    ],
    "tgn:id":2459818,
    "tgn:name":"Little River",
    "tgn:placetype":[
        "aat:300008707"
    ]
},
  "bbox": [],
  "geometry": {"coordinates":[-68.1833,47.25],"type":"Point"}
}