{
  "id": 2009504,
  "type": "Feature",
  "properties": {
    "tgn:hierarchy":[
        "tgn:2009504",
        "tgn:1000001",
        "tgn:7016172",
        "tgn:7012149",
        "tgn:2000133",
        "tgn:7029392"
    ],
    "tgn:id":2009504,
    "tgn:name":"Shover Springs",
    "tgn:placetype":[
        "aat:300008347",
        "aat:300387210"
    ]
},
  "bbox": [],
  "geometry": {"coordinates":[-93.5167,33.6167],"type":"Point"}
}