{
  "id": 2393909,
  "type": "Feature",
  "properties": {
    "tgn:hierarchy":[
        "tgn:2393909",
        "tgn:1000001",
        "tgn:7012149",
        "tgn:1002511",
        "tgn:7007919",
        "tgn:7029392"
    ],
    "tgn:id":2393909,
    "tgn:name":"Hog Neck Creek",
    "tgn:placetype":[
        "aat:300008706"
    ]
},
  "bbox": [],
  "geometry": {"coordinates":[-76.85,37.3667],"type":"Point"}
}