{
  "id": 7128836,
  "type": "Feature",
  "properties": {
    "tgn:hierarchy":[
        "tgn:7128836",
        "tgn:1000003",
        "tgn:7003688",
        "tgn:7000084",
        "tgn:7029392"
    ],
    "tgn:id":7128836,
    "tgn:name":"Oberland",
    "tgn:placetype":[
        "aat:300055621"
    ]
},
  "bbox": [],
  "geometry": {"coordinates":[7.883333,54.183333],"type":"Point"}
}