{
  "id": 7125797,
  "type": "Feature",
  "properties": {
    "tgn:hierarchy":[
        "tgn:7125797",
        "tgn:1000003",
        "tgn:7003677",
        "tgn:7000084",
        "tgn:7029392"
    ],
    "tgn:id":7125797,
    "tgn:name":"Niedersaurenbach",
    "tgn:placetype":[
        "aat:300000206"
    ]
},
  "bbox": [],
  "geometry": {"coordinates":[7.45,50.85],"type":"Point"}
}