{
  "id": 2338923,
  "type": "Feature",
  "properties": {
    "tgn:hierarchy":[
        "tgn:2338923",
        "tgn:1000001",
        "tgn:7012149",
        "tgn:1002298",
        "tgn:7007157",
        "tgn:7029392"
    ],
    "tgn:id":2338923,
    "tgn:name":"Franklin Canyon",
    "tgn:placetype":[
        "aat:300008761"
    ]
},
  "bbox": [],
  "geometry": {"coordinates":[-122.1833,38.0167],"type":"Point"}
}