<<<<<<< HEAD
{
  "id": 2258441,
  "type": "Feature",
  "properties": {
    "tgn:hierarchy":[
        "tgn:2258441",
        "tgn:1000001",
        "tgn:7012149",
        "tgn:1002671",
        "tgn:7007523",
        "tgn:7029392"
    ],
    "tgn:id":2258441,
    "tgn:name":"Cotton Hollow",
    "tgn:placetype":[
        "aat:300008761"
    ]
},
  "bbox": [],
  "geometry": {"coordinates":[-92.6667,38.25],"type":"Point"}
}
=======
{"geometry":{"type":"Point","coordinates":[-92.666700,38.250000]},"type":"Feature","properties":{"hierarchy":["tgn:2258441","tgn:1000001","tgn:7012149","tgn:1002671","tgn:7007523","tgn:7029392"],"placetype":["aat:300008761"],"id":2258441,"name:xx":"Cotton Hollow"}}
>>>>>>> 03f74aca74312dbeaf24d7e61306dd6a786dc3d0
