{
  "id": 7143947,
  "type": "Feature",
  "properties": {
    "tgn:hierarchy":[
        "tgn:7143947",
        "tgn:1000003",
        "tgn:7003685",
        "tgn:7000084",
        "tgn:7029392"
    ],
    "tgn:id":7143947,
    "tgn:name":"Kohl-Berg",
    "tgn:placetype":[
        "aat:300008777"
    ]
},
  "bbox": [],
  "geometry": {"coordinates":[13.933333,50.95],"type":"Point"}
}