{
  "id": 7550494,
  "type": "Feature",
  "properties": {
    "tgn:hierarchy":[
        "tgn:7550494",
        "tgn:1000004",
        "tgn:7000198",
        "tgn:7000799",
        "tgn:7029392"
    ],
    "tgn:id":7550494,
    "tgn:name:en":"Char\u0101sa",
    "tgn:placetype":[
        "aat:300008347"
    ]
},
  "bbox": [],
  "geometry": {"coordinates":[77.566667,34.683333],"type":"Point"}
}