{
  "id": 2089681,
  "type": "Feature",
  "properties": {
    "tgn:hierarchy":[
        "tgn:2089681",
        "tgn:1000001",
        "tgn:7012149",
        "tgn:1002995",
        "tgn:7007710",
        "tgn:7029392"
    ],
    "tgn:id":2089681,
    "tgn:name":"Kammerer",
    "tgn:placetype":[
        "aat:300008347",
        "aat:300387210"
    ]
},
  "bbox": [],
  "geometry": {"coordinates":[-80.0333,40.1833],"type":"Point"}
}