{
  "id": 7535260,
  "type": "Feature",
  "properties": {
    "tgn:hierarchy":[
        "tgn:7535260",
        "tgn:7001242",
        "tgn:7016833",
        "tgn:1001079",
        "tgn:7029392"
    ],
    "tgn:id":7535260,
    "tgn:name:en":"S\u0101niyat \u1e28unaysh",
    "tgn:placetype":[
        "aat:300006207"
    ]
},
  "bbox": [],
  "geometry": {"coordinates":[29.833333,30.95],"type":"Point"}
}