{
  "id": 7583707,
  "type": "Feature",
  "properties": {
    "tgn:hierarchy":[
        "tgn:7583707",
        "tgn:1000004",
        "tgn:7000198",
        "tgn:7016788",
        "tgn:7029392"
    ],
    "tgn:id":7583707,
    "tgn:name:en":"Nyola",
    "tgn:placetype":[
        "aat:300008347"
    ]
},
  "bbox": [],
  "geometry": {"coordinates":[75.277047,28.306957],"type":"Point"}
}