{
  "id": 2712188,
  "type": "Feature",
  "properties": {
    "tgn:hierarchy":[
        "tgn:2712188",
        "tgn:1000001",
        "tgn:7012149",
        "tgn:1002599",
        "tgn:7007708",
        "tgn:7029392"
    ],
    "tgn:id":2712188,
    "tgn:name":"Tater Hill",
    "tgn:placetype":[
        "aat:300008798"
    ]
},
  "bbox": [],
  "geometry": {"coordinates":[-123.7167,44.6667],"type":"Point"}
}