<<<<<<< HEAD
{
  "id": 7482401,
  "type": "Feature",
  "properties": {
    "tgn:hierarchy":[
        "tgn:7482401",
        "tgn:1000004",
        "tgn:7001009",
        "tgn:1000141",
        "tgn:7029392"
    ],
    "tgn:id":7482401,
    "tgn:name":"Gaoshan Xi",
    "tgn:placetype":[
        "aat:300008699"
    ]
},
  "bbox": [],
  "geometry": {"coordinates":[121.312778,24.356111],"type":"Point"}
}
=======
{"geometry":{"type":"Point","coordinates":[121.312778,24.356111]},"type":"Feature","properties":{"hierarchy":["tgn:7482401","tgn:1000004","tgn:7001009","tgn:1000141","tgn:7029392"],"placetype":["aat:300008699"],"id":7482401,"name:xx":"Gaoshan Xi"}}
>>>>>>> 03f74aca74312dbeaf24d7e61306dd6a786dc3d0
