<<<<<<< HEAD
{
  "id": 7025167,
  "type": "Feature",
  "properties": {
    "tgn:hierarchy":[
        "tgn:7025167",
        "tgn:7002445",
        "tgn:1000003",
        "tgn:7008118",
        "tgn:7008591",
        "tgn:7029392"
    ],
    "tgn:id":7025167,
    "tgn:name:ang":"Estune",
    "tgn:placetype":[
        "aat:300008347"
    ]
},
  "bbox": [],
  "geometry": {"coordinates":[-1.45,53.3],"type":"Point"}
}
=======
{"geometry":{"type":"Point","coordinates":[-1.450000,53.300000]},"type":"Feature","properties":{"hierarchy":["tgn:7025167","tgn:7002445","tgn:1000003","tgn:7008118","tgn:7008591","tgn:7029392"],"placetype":["aat:300008347"],"id":7025167,"name:ang":"Estune"}}
>>>>>>> 03f74aca74312dbeaf24d7e61306dd6a786dc3d0
