{
  "id": 7414963,
  "type": "Feature",
  "properties": {
    "tgn:hierarchy":[
        "tgn:7414963",
        "tgn:7005584",
        "tgn:1000001",
        "tgn:7005560",
        "tgn:7029392"
    ],
    "tgn:id":7414963,
    "tgn:name":"Santo Domingo",
    "tgn:placetype":[
        "aat:300008347"
    ]
},
  "bbox": [],
  "geometry": {"coordinates":[-101.945278,20.443056],"type":"Point"}
}