{
  "id": 1091640,
  "type": "Feature",
  "properties": {
    "tgn:hierarchy":[
        "tgn:1091640",
        "tgn:7001242",
        "tgn:1000902",
        "tgn:1000180",
        "tgn:7029392"
    ],
    "tgn:id":1091640,
    "tgn:name":"Murrupula",
    "tgn:placetype":[
        "aat:300008347"
    ]
},
  "bbox": [],
  "geometry": {"coordinates":[38.7833,-15.4333],"type":"Point"}
}