{
  "id": 2238349,
  "type": "Feature",
  "properties": {
    "tgn:hierarchy":[
        "tgn:2238349",
        "tgn:1000001",
        "tgn:7012149",
        "tgn:2001109",
        "tgn:7007522",
        "tgn:7029392"
    ],
    "tgn:id":2238349,
    "tgn:name":"Choctaw Creek",
    "tgn:placetype":[
        "aat:300008706"
    ]
},
  "bbox": [],
  "geometry": {"coordinates":[-89.05,30.6167],"type":"Point"}
}