{
  "id": 2283345,
  "type": "Feature",
  "properties": {
    "tgn:hierarchy":[
        "tgn:2283345",
        "tgn:1000001",
        "tgn:7012149",
        "tgn:7007157",
        "tgn:1002828",
        "tgn:7029392"
    ],
    "tgn:id":2283345,
    "tgn:name":"Dellamont",
    "tgn:placetype":[
        "aat:300008798"
    ]
},
  "bbox": [],
  "geometry": {"coordinates":[-116.9167,33.8167],"type":"Point"}
}