{
  "id": 7319514,
  "type": "Feature",
  "properties": {
    "tgn:hierarchy":[
        "tgn:7319514",
        "tgn:1001637",
        "tgn:1000049",
        "tgn:1000002",
        "tgn:7029392"
    ],
    "tgn:id":7319514,
    "tgn:name":"Alto, Cerro",
    "tgn:placetype":[
        "aat:300008777"
    ]
},
  "bbox": [],
  "geometry": {"coordinates":[-72.716667,-37.416667],"type":"Point"}
}