{
  "id": 2590756,
  "type": "Feature",
  "properties": {
    "tgn:hierarchy":[
        "tgn:2590756",
        "tgn:1000001",
        "tgn:7012149",
        "tgn:2002009",
        "tgn:7007826",
        "tgn:7029392"
    ],
    "tgn:id":2590756,
    "tgn:name":"Pole Ridge Branch",
    "tgn:placetype":[
        "aat:300008699"
    ]
},
  "bbox": [],
  "geometry": {"coordinates":[-94.25,31.0333],"type":"Point"}
}