{
  "id": 2606328,
  "type": "Feature",
  "properties": {
    "tgn:hierarchy":[
        "tgn:2606328",
        "tgn:1000001",
        "tgn:7006451",
        "tgn:7012149",
        "tgn:2000102",
        "tgn:7029392"
    ],
    "tgn:id":2606328,
    "tgn:name":"Ralph Tank",
    "tgn:placetype":[
        "aat:300006191"
    ]
},
  "bbox": [],
  "geometry": {"coordinates":[-110.55,31.55],"type":"Point"}
}