{
  "id": 1108665,
  "type": "Feature",
  "properties": {
    "tgn:hierarchy":[
        "tgn:1108665",
        "tgn:1000003",
        "tgn:1000080",
        "tgn:7029392"
    ],
    "tgn:id":1108665,
    "tgn:name:it":"Adamello",
    "tgn:placetype":[
        "aat:300008795"
    ]
},
  "bbox": [],
  "geometry": {"coordinates":[10.5833,46.1667],"type":"Point"}
}