{
  "id": 7458463,
  "type": "Feature",
  "properties": {
    "tgn:hierarchy":[
        "tgn:7458463",
        "tgn:7002444",
        "tgn:1000003",
        "tgn:7008072",
        "tgn:7008591",
        "tgn:7029392"
    ],
    "tgn:id":7458463,
    "tgn:name:en":"Lugate Water",
    "tgn:placetype":[
        "aat:300008699"
    ]
},
  "bbox": [],
  "geometry": {"coordinates":[-2.866667,55.666667],"type":"Point"}
}