{
  "id": 7418192,
  "type": "Feature",
  "properties": {
    "tgn:hierarchy":[
        "tgn:7418192",
        "tgn:7005584",
        "tgn:1000001",
        "tgn:7005560",
        "tgn:7029392"
    ],
    "tgn:id":7418192,
    "tgn:name":"Santana",
    "tgn:placetype":[
        "aat:300008347"
    ]
},
  "bbox": [],
  "geometry": {"coordinates":[-101.269444,21.046667],"type":"Point"}
}