{
  "id": 2139873,
  "type": "Feature",
  "properties": {
    "tgn:hierarchy":[
        "tgn:2139873",
        "tgn:1000001",
        "tgn:7012149",
        "tgn:1002406",
        "tgn:7007520",
        "tgn:7029392"
    ],
    "tgn:id":2139873,
    "tgn:name":"Atlas Millpond",
    "tgn:placetype":[
        "aat:300006191"
    ]
},
  "bbox": [],
  "geometry": {"coordinates":[-83.5333,42.9333],"type":"Point"}
}