{
  "id": 2361149,
  "type": "Feature",
  "properties": {
    "tgn:hierarchy":[
        "tgn:2361149",
        "tgn:1000001",
        "tgn:7012149",
        "tgn:7007516",
        "tgn:7029392"
    ],
    "tgn:id":2361149,
    "tgn:name":"Grave Run",
    "tgn:placetype":[
        "aat:300008699"
    ]
},
  "bbox": [],
  "geometry": {"coordinates":[-76.8667,39.65],"type":"Point"}
}