{
  "id": 7366963,
  "type": "Feature",
  "properties": {
    "tgn:hierarchy":[
        "tgn:7366963",
        "tgn:1000001",
        "tgn:7005597",
        "tgn:7005560",
        "tgn:7029392"
    ],
    "tgn:id":7366963,
    "tgn:name":"El Perote",
    "tgn:placetype":[
        "aat:300008347"
    ]
},
  "bbox": [],
  "geometry": {"coordinates":[-97.683333,25.916667],"type":"Point"}
}