{
  "id": 2488785,
  "type": "Feature",
  "properties": {
    "tgn:hierarchy":[
        "tgn:2488785",
        "tgn:1000001",
        "tgn:7006451",
        "tgn:2000093",
        "tgn:7012149",
        "tgn:7029392"
    ],
    "tgn:id":2488785,
    "tgn:name":"Mailbox Mesa",
    "tgn:placetype":[
        "aat:300008798"
    ]
},
  "bbox": [],
  "geometry": {"coordinates":[-111.05,34.0833],"type":"Point"}
}