{
  "id": 7267801,
  "type": "Feature",
  "properties": {
    "tgn:hierarchy":[
        "tgn:7267801",
        "tgn:7003615",
        "tgn:1000003",
        "tgn:7016845",
        "tgn:7029392"
    ],
    "tgn:id":7267801,
    "tgn:name:nl":"Paardentocht",
    "tgn:placetype":[
        "aat:300006075"
    ]
},
  "bbox": [],
  "geometry": {"coordinates":[5.916667,52.633333],"type":"Point"}
}