{
  "id": 2052507,
  "type": "Feature",
  "properties": {
    "tgn:hierarchy":[
        "tgn:2052507",
        "tgn:1000001",
        "tgn:7012149",
        "tgn:2000968",
        "tgn:7007520",
        "tgn:7029392"
    ],
    "tgn:id":2052507,
    "tgn:name":"Lodi",
    "tgn:placetype":[
        "aat:300008347"
    ]
},
  "bbox": [],
  "geometry": {"coordinates":[-85.1667,44.6333],"type":"Point"}
}