{
  "id": 2374346,
  "type": "Feature",
  "properties": {
    "tgn:hierarchy":[
        "tgn:2374346",
        "tgn:1000001",
        "tgn:7012149",
        "tgn:2002272",
        "tgn:7013961",
        "tgn:7029392"
    ],
    "tgn:id":2374346,
    "tgn:name":"Hampton Creek",
    "tgn:placetype":[
        "aat:300008706"
    ]
},
  "bbox": [],
  "geometry": {"coordinates":[-82.15,38.0833],"type":"Point"}
}