{
  "id": 2394585,
  "type": "Feature",
  "properties": {
    "tgn:hierarchy":[
        "tgn:2394585",
        "tgn:1000001",
        "tgn:7012149",
        "tgn:2000655",
        "tgn:7007253",
        "tgn:7029392"
    ],
    "tgn:id":2394585,
    "tgn:name":"Hogsback Marsh Public Hunting Area",
    "tgn:placetype":[
        "aat:300055621"
    ]
},
  "bbox": [],
  "geometry": {"coordinates":[-93.55,43.45],"type":"Point"}
}