{
  "id": 2348670,
  "type": "Feature",
  "properties": {
    "tgn:hierarchy":[
        "tgn:2348670",
        "tgn:1000001",
        "tgn:7012149",
        "tgn:2002157",
        "tgn:7007919",
        "tgn:7029392"
    ],
    "tgn:id":2348670,
    "tgn:name":"Gibson Branch",
    "tgn:placetype":[
        "aat:300008699"
    ]
},
  "bbox": [],
  "geometry": {"coordinates":[-82.2833,37.0333],"type":"Point"}
}