{
  "id": 2266869,
  "type": "Feature",
  "properties": {
    "tgn:hierarchy":[
        "tgn:2266869",
        "tgn:7006450",
        "tgn:1000001",
        "tgn:7019698",
        "tgn:7012149",
        "tgn:7029392"
    ],
    "tgn:id":2266869,
    "tgn:name":"Crescent River",
    "tgn:placetype":[
        "aat:300008707"
    ]
},
  "bbox": [],
  "geometry": {"coordinates":[-152.7333,60.35],"type":"Point"}
}