{
  "id": 1060684,
  "type": "Feature",
  "properties": {
    "tgn:hierarchy":[
        "tgn:1060684",
        "tgn:1000004",
        "tgn:1003421",
        "tgn:7018214",
        "tgn:7002435",
        "tgn:7029392"
    ],
    "tgn:id":1060684,
    "tgn:name":"Urshel'skiy",
    "tgn:placetype":[
        "aat:300008347"
    ]
},
  "bbox": [],
  "geometry": {"coordinates":[40.2167,55.6833],"type":"Point"}
}