{
  "id": 7588006,
  "type": "Feature",
  "properties": {
    "tgn:hierarchy":[
        "tgn:7588006",
        "tgn:1000004",
        "tgn:7000198",
        "tgn:1001905",
        "tgn:7029392"
    ],
    "tgn:id":7588006,
    "tgn:name:en":"Rishetsu",
    "tgn:placetype":[
        "aat:300008347"
    ]
},
  "bbox": [],
  "geometry": {"coordinates":[94.75028,25.959376],"type":"Point"}
}