{
  "id": 2400643,
  "type": "Feature",
  "properties": {
    "tgn:hierarchy":[
        "tgn:2400643",
        "tgn:1000001",
        "tgn:2001411",
        "tgn:7012149",
        "tgn:7007526",
        "tgn:7029392"
    ],
    "tgn:id":2400643,
    "tgn:name":"Horse Mountain",
    "tgn:placetype":[
        "aat:300008798"
    ]
},
  "bbox": [],
  "geometry": {"coordinates":[-115.3333,40.7167],"type":"Point"}
}