{
  "id": 2171524,
  "type": "Feature",
  "properties": {
    "tgn:hierarchy":[
        "tgn:2171524",
        "tgn:1000001",
        "tgn:7012149",
        "tgn:2000380",
        "tgn:7007248",
        "tgn:7029392"
    ],
    "tgn:id":2171524,
    "tgn:name":"Big Swamp",
    "tgn:placetype":[
        "aat:300008905"
    ]
},
  "bbox": [],
  "geometry": {"coordinates":[-81.5333,31.9167],"type":"Point"}
}