{
  "id": 2068205,
  "type": "Feature",
  "properties": {
    "tgn:hierarchy":[
        "tgn:2068205",
        "tgn:1000001",
        "tgn:7012149",
        "tgn:1002926",
        "tgn:7007568",
        "tgn:7029392"
    ],
    "tgn:id":2068205,
    "tgn:name":"Briscoe",
    "tgn:placetype":[
        "aat:300008347",
        "aat:300387210"
    ]
},
  "bbox": [],
  "geometry": {"coordinates":[-74.8667,41.75],"type":"Point"}
}