{
  "id": 2393781,
  "type": "Feature",
  "properties": {
    "tgn:hierarchy":[
        "tgn:2393781",
        "tgn:1000001",
        "tgn:1002246",
        "tgn:7012149",
        "tgn:7007568",
        "tgn:7029392"
    ],
    "tgn:id":2393781,
    "tgn:name":"Hog Island",
    "tgn:placetype":[
        "aat:300008791"
    ]
},
  "bbox": [],
  "geometry": {"coordinates":[-76.6833,43.05],"type":"Point"}
}