{
  "id": 2364268,
  "type": "Feature",
  "properties": {
    "tgn:hierarchy":[
        "tgn:2364268",
        "tgn:1000001",
        "tgn:7012149",
        "tgn:2001516",
        "tgn:7007709",
        "tgn:7029392"
    ],
    "tgn:id":2364268,
    "tgn:name":"Green Ridge Knob",
    "tgn:placetype":[
        "aat:300008798"
    ]
},
  "bbox": [],
  "geometry": {"coordinates":[-82.6167,36.0333],"type":"Point"}
}