{
  "id": 7592543,
  "type": "Feature",
  "properties": {
    "tgn:hierarchy":[
        "tgn:7592543",
        "tgn:1000004",
        "tgn:7000198",
        "tgn:7016722",
        "tgn:7029392"
    ],
    "tgn:id":7592543,
    "tgn:name:en":"Telpura",
    "tgn:placetype":[
        "aat:300008347"
    ]
},
  "bbox": [],
  "geometry": {"coordinates":[77.841045,30.098801],"type":"Point"}
}