{
  "id": 7315416,
  "type": "Feature",
  "properties": {
    "tgn:hierarchy":[
        "tgn:7315416",
        "tgn:1001630",
        "tgn:1000049",
        "tgn:1000002",
        "tgn:7029392"
    ],
    "tgn:id":7315416,
    "tgn:name":"Cha\u00f1aral de Aceituna",
    "tgn:placetype":[
        "aat:300008347"
    ]
},
  "bbox": [],
  "geometry": {"coordinates":[-71.433333,-29.05],"type":"Point"}
}