{
  "id": 2327998,
  "type": "Feature",
  "properties": {
    "tgn:hierarchy":[
        "tgn:2327998",
        "tgn:1000001",
        "tgn:7012149",
        "tgn:2001300",
        "tgn:7007524",
        "tgn:7029392"
    ],
    "tgn:id":2327998,
    "tgn:name":"Fish Lake",
    "tgn:placetype":[
        "aat:300006191"
    ]
},
  "bbox": [],
  "geometry": {"coordinates":[-114.45,46.0833],"type":"Point"}
}