{
  "id": 2728343,
  "type": "Feature",
  "properties": {
    "tgn:hierarchy":[
        "tgn:2728343",
        "tgn:1000001",
        "tgn:7012149",
        "tgn:2001230",
        "tgn:7007523",
        "tgn:7029392"
    ],
    "tgn:id":2728343,
    "tgn:name":"Treable Creek",
    "tgn:placetype":[
        "aat:300008706"
    ]
},
  "bbox": [],
  "geometry": {"coordinates":[-91.8167,37.85],"type":"Point"}
}