{
  "id": 7134716,
  "type": "Feature",
  "properties": {
    "tgn:hierarchy":[
        "tgn:7134716",
        "tgn:1000003",
        "tgn:7003687",
        "tgn:7000084",
        "tgn:7029392"
    ],
    "tgn:id":7134716,
    "tgn:name":"Natho",
    "tgn:placetype":[
        "aat:300008347"
    ]
},
  "bbox": [],
  "geometry": {"coordinates":[12.216667,51.95],"type":"Point"}
}