{
  "id": 7013483,
  "type": "Feature",
  "properties": {
    "tgn:hierarchy":[
        "tgn:7013483",
        "tgn:1002215",
        "tgn:1000001",
        "tgn:7012149",
        "tgn:7007565",
        "tgn:7029392"
    ],
    "tgn:id":7013483,
    "tgn:name":"Burlington",
    "tgn:placetype":[
        "aat:300387277",
        "aat:300008347",
        "aat:300387308",
        "aat:300005135",
        "aat:300008375"
    ]
},
  "bbox": [],
  "geometry": {"coordinates":[-74.85,40.0667],"type":"Point"}
}