{
  "id": 1115723,
  "type": "Feature",
  "properties": {
    "tgn:hierarchy":[
        "tgn:1115723",
        "tgn:1000004",
        "tgn:1001175",
        "tgn:1000135",
        "tgn:7029392"
    ],
    "tgn:id":1115723,
    "tgn:name":"Buhi, Lake",
    "tgn:placetype":[
        "aat:300008680"
    ]
},
  "bbox": [],
  "geometry": {"coordinates":[123.5167,13.4333],"type":"Point"}
}