{
  "id": 7422028,
  "type": "Feature",
  "properties": {
    "tgn:hierarchy":[
        "tgn:7422028",
        "tgn:1000001",
        "tgn:1001960",
        "tgn:7005560",
        "tgn:7029392"
    ],
    "tgn:id":7422028,
    "tgn:name":"Joaquin Amaro",
    "tgn:placetype":[
        "aat:300008347"
    ]
},
  "bbox": [],
  "geometry": {"coordinates":[-109.783333,27.25],"type":"Point"}
}