{
  "id": 2558980,
  "type": "Feature",
  "properties": {
    "tgn:hierarchy":[
        "tgn:2558980",
        "tgn:7006450",
        "tgn:1000001",
        "tgn:7012149",
        "tgn:2124014",
        "tgn:7029392"
    ],
    "tgn:id":2558980,
    "tgn:name":"Omar River",
    "tgn:placetype":[
        "aat:300008707"
    ]
},
  "bbox": [],
  "geometry": {"coordinates":[-160.6333,67.6167],"type":"Point"}
}