{
  "id": 2603595,
  "type": "Feature",
  "properties": {
    "tgn:hierarchy":[
        "tgn:2603595",
        "tgn:1000001",
        "tgn:1002281",
        "tgn:7012149",
        "tgn:7007251",
        "tgn:7029392"
    ],
    "tgn:id":2603595,
    "tgn:name":"Queens Lake",
    "tgn:placetype":[
        "aat:300008680"
    ]
},
  "bbox": [],
  "geometry": {"coordinates":[-89.65,38.4333],"type":"Point"}
}