{
  "id": 2460183,
  "type": "Feature",
  "properties": {
    "tgn:hierarchy":[
        "tgn:2460183",
        "tgn:2000090",
        "tgn:1000001",
        "tgn:7006451",
        "tgn:7012149",
        "tgn:7029392"
    ],
    "tgn:id":2460183,
    "tgn:name":"Little Round Rock",
    "tgn:placetype":[
        "aat:300008798"
    ]
},
  "bbox": [],
  "geometry": {"coordinates":[-109.5333,36.5167],"type":"Point"}
}