<<<<<<< HEAD
{
  "id": 2338669,
  "type": "Feature",
  "properties": {
    "tgn:hierarchy":[
        "tgn:2338669",
        "tgn:1000001",
        "tgn:2001470",
        "tgn:7012149",
        "tgn:7007709",
        "tgn:7029392"
    ],
    "tgn:id":2338669,
    "tgn:name":"Francis Mill",
    "tgn:placetype":[
        "aat:300008347"
    ]
},
  "bbox": [],
  "geometry": {"coordinates":[-77.1,36.1333],"type":"Point"}
}
=======
{"geometry":{"type":"Point","coordinates":[-77.100000,36.133300]},"type":"Feature","properties":{"hierarchy":["tgn:2338669","tgn:1000001","tgn:2001470","tgn:7012149","tgn:7007709","tgn:7029392"],"placetype":["aat:300008347"],"id":2338669,"name:xx":"Francis Mill"}}
>>>>>>> 03f74aca74312dbeaf24d7e61306dd6a786dc3d0
