{
  "id": 7121025,
  "type": "Feature",
  "properties": {
    "tgn:hierarchy":[
        "tgn:7121025",
        "tgn:1000003",
        "tgn:7003685",
        "tgn:7000084",
        "tgn:7029392"
    ],
    "tgn:id":7121025,
    "tgn:name":"Pa\u00dfditz",
    "tgn:placetype":[
        "aat:300008347"
    ]
},
  "bbox": [],
  "geometry": {"coordinates":[14.283333,51.216667],"type":"Point"}
}