{
  "id": 7311763,
  "type": "Feature",
  "properties": {
    "tgn:hierarchy":[
        "tgn:7311763",
        "tgn:1001708",
        "tgn:1000049",
        "tgn:1000002",
        "tgn:7029392"
    ],
    "tgn:id":7311763,
    "tgn:name":"Las Ovejas, Morro",
    "tgn:placetype":[
        "aat:300008795"
    ]
},
  "bbox": [],
  "geometry": {"coordinates":[-71.033333,-33.766667],"type":"Point"}
}