{
  "id": 2417977,
  "type": "Feature",
  "properties": {
    "tgn:hierarchy":[
        "tgn:2417977",
        "tgn:1000001",
        "tgn:7012149",
        "tgn:2001926",
        "tgn:7007825",
        "tgn:7029392"
    ],
    "tgn:id":2417977,
    "tgn:name":"Jackson Mountain",
    "tgn:placetype":[
        "aat:300008798"
    ]
},
  "bbox": [],
  "geometry": {"coordinates":[-82.5167,36.15],"type":"Point"}
}