{
  "id": 2463312,
  "type": "Feature",
  "properties": {
    "tgn:hierarchy":[
        "tgn:2463312",
        "tgn:1000001",
        "tgn:7012149",
        "tgn:1002756",
        "tgn:7007240",
        "tgn:7029392"
    ],
    "tgn:id":2463312,
    "tgn:name":"Lizzie, Lake",
    "tgn:placetype":[
        "aat:300008680"
    ]
},
  "bbox": [],
  "geometry": {"coordinates":[-81.1833,28.2333],"type":"Point"}
}