{
  "id": 2300058,
  "type": "Feature",
  "properties": {
    "tgn:hierarchy":[
        "tgn:2300058",
        "tgn:1000001",
        "tgn:7012149",
        "tgn:2002048",
        "tgn:7007826",
        "tgn:7029392"
    ],
    "tgn:id":2300058,
    "tgn:name":"Dug Spring",
    "tgn:placetype":[
        "aat:300008697"
    ]
},
  "bbox": [],
  "geometry": {"coordinates":[-100.25,32.4333],"type":"Point"}
}