{
  "id": 2132762,
  "type": "Feature",
  "properties": {
    "tgn:hierarchy":[
        "tgn:2132762",
        "tgn:7006450",
        "tgn:1000001",
        "tgn:7012149",
        "tgn:2000088",
        "tgn:7029392"
    ],
    "tgn:id":2132762,
    "tgn:name":"Ancon Peak",
    "tgn:placetype":[
        "aat:300008798"
    ]
},
  "bbox": [],
  "geometry": {"coordinates":[-132.5333,56.3833],"type":"Point"}
}