{
  "id": 7141039,
  "type": "Feature",
  "properties": {
    "tgn:hierarchy":[
        "tgn:7141039",
        "tgn:7003669",
        "tgn:1000003",
        "tgn:7000084",
        "tgn:7029392"
    ],
    "tgn:id":7141039,
    "tgn:name":"Malmersdorf",
    "tgn:placetype":[
        "aat:300008347"
    ]
},
  "bbox": [],
  "geometry": {"coordinates":[10.683333,49.283333],"type":"Point"}
}