{
  "id": 7408157,
  "type": "Feature",
  "properties": {
    "tgn:hierarchy":[
        "tgn:7408157",
        "tgn:1000001",
        "tgn:7005590",
        "tgn:7005560",
        "tgn:7029392"
    ],
    "tgn:id":7408157,
    "tgn:name":"Santa Juana",
    "tgn:placetype":[
        "aat:300008347"
    ]
},
  "bbox": [],
  "geometry": {"coordinates":[-101.566667,19.425],"type":"Point"}
}