{
  "id": 2756383,
  "type": "Feature",
  "properties": {
    "tgn:hierarchy":[
        "tgn:2756383",
        "tgn:1007657",
        "tgn:1002534",
        "tgn:1000001",
        "tgn:7012149",
        "tgn:7007249",
        "tgn:7029392"
    ],
    "tgn:id":2756383,
    "tgn:name":"Weli Point",
    "tgn:placetype":[
        "aat:300008850"
    ]
},
  "bbox": [],
  "geometry": {"coordinates":[-159.5667,21.8833],"type":"Point"}
}