{
  "id": 2532235,
  "type": "Feature",
  "properties": {
    "tgn:hierarchy":[
        "tgn:2532235",
        "tgn:1000001",
        "tgn:7012149",
        "tgn:7007525",
        "tgn:7029392"
    ],
    "tgn:id":2532235,
    "tgn:name":"Munson Creek",
    "tgn:placetype":[
        "aat:300008706"
    ]
},
  "bbox": [],
  "geometry": {"coordinates":[-98.75,41.3333],"type":"Point"}
}