{
  "id": 7548005,
  "type": "Feature",
  "properties": {
    "tgn:hierarchy":[
        "tgn:7548005",
        "tgn:1000004",
        "tgn:7000198",
        "tgn:7016788",
        "tgn:7029392"
    ],
    "tgn:id":7548005,
    "tgn:name:en":"B\u0101nsur",
    "tgn:placetype":[
        "aat:300008347"
    ]
},
  "bbox": [],
  "geometry": {"coordinates":[76.353549,27.683322],"type":"Point"}
}