{
  "id": 2480419,
  "type": "Feature",
  "properties": {
    "tgn:hierarchy":[
        "tgn:2480419",
        "tgn:1000001",
        "tgn:7012149",
        "tgn:2000889",
        "tgn:7007256",
        "tgn:7029392"
    ],
    "tgn:id":2480419,
    "tgn:name":"Lake Terrace",
    "tgn:placetype":[
        "aat:300008347"
    ]
},
  "bbox": [],
  "geometry": {"coordinates":[-90.0667,30.0167],"type":"Point"}
}