{
  "id": 2176183,
  "type": "Feature",
  "properties": {
    "tgn:hierarchy":[
        "tgn:2176183",
        "tgn:1000001",
        "tgn:7012149",
        "tgn:2001455",
        "tgn:7007566",
        "tgn:7029392"
    ],
    "tgn:id":2176183,
    "tgn:name":"Black Hill",
    "tgn:placetype":[
        "aat:300008798"
    ]
},
  "bbox": [],
  "geometry": {"coordinates":[-107.0167,33.05],"type":"Point"}
}