{
  "id": 2125488,
  "type": "Feature",
  "properties": {
    "tgn:hierarchy":[
        "tgn:2125488",
        "tgn:1000001",
        "tgn:7012149",
        "tgn:2001719",
        "tgn:7007708",
        "tgn:7029392"
    ],
    "tgn:id":2125488,
    "tgn:name":"Acton",
    "tgn:placetype":[
        "aat:300008347"
    ]
},
  "bbox": [],
  "geometry": {"coordinates":[-119.4167,45.5833],"type":"Point"}
}