{
  "id": 2498488,
  "type": "Feature",
  "properties": {
    "tgn:hierarchy":[
        "tgn:2498488",
        "tgn:1000001",
        "tgn:1002260",
        "tgn:7012149",
        "tgn:7007920",
        "tgn:7029392"
    ],
    "tgn:id":2498488,
    "tgn:name":"McAlester Mountain",
    "tgn:placetype":[
        "aat:300008798"
    ]
},
  "bbox": [],
  "geometry": {"coordinates":[-120.65,48.3833],"type":"Point"}
}