{
  "id": 7254684,
  "type": "Feature",
  "properties": {
    "tgn:hierarchy":[
        "tgn:7254684",
        "tgn:7003456",
        "tgn:1000003",
        "tgn:1000063",
        "tgn:7018236",
        "tgn:7029392"
    ],
    "tgn:id":7254684,
    "tgn:name":"Steeghoven",
    "tgn:placetype":[
        "aat:300008347"
    ]
},
  "bbox": [],
  "geometry": {"coordinates":[4.633333,51.35],"type":"Point"}
}