<<<<<<< HEAD
{
  "id": 7362096,
  "type": "Feature",
  "properties": {
    "tgn:hierarchy":[
        "tgn:7362096",
        "tgn:1000001",
        "tgn:7005599",
        "tgn:7005560",
        "tgn:7029392"
    ],
    "tgn:id":7362096,
    "tgn:name":"El Palmar",
    "tgn:placetype":[
        "aat:300008347"
    ]
},
  "bbox": [],
  "geometry": {"coordinates":[-97.466667,20.966667],"type":"Point"}
}
=======
{"geometry":{"type":"Point","coordinates":[-97.466667,20.966667]},"type":"Feature","properties":{"hierarchy":["tgn:7362096","tgn:1000001","tgn:7005599","tgn:7005560","tgn:7029392"],"placetype":["aat:300008347"],"id":7362096,"name:xx":"El Palmar"}}
>>>>>>> 03f74aca74312dbeaf24d7e61306dd6a786dc3d0
