{
  "id": 2507035,
  "type": "Feature",
  "properties": {
    "tgn:hierarchy":[
        "tgn:2507035",
        "tgn:1000001",
        "tgn:7012149",
        "tgn:7007566",
        "tgn:7029392"
    ],
    "tgn:id":2507035,
    "tgn:name":"Mesteno, Ca\u00f1on",
    "tgn:placetype":[
        "aat:300008761"
    ]
},
  "bbox": [],
  "geometry": {"coordinates":[-104.25,36.0667],"type":"Point"}
}