{
  "id": 7140906,
  "type": "Feature",
  "properties": {
    "tgn:hierarchy":[
        "tgn:7140906",
        "tgn:1000003",
        "tgn:7003676",
        "tgn:7000084",
        "tgn:7029392"
    ],
    "tgn:id":7140906,
    "tgn:name":"Lust",
    "tgn:placetype":[
        "aat:300008347"
    ]
},
  "bbox": [],
  "geometry": {"coordinates":[9.683333,52.616667],"type":"Point"}
}