<<<<<<< HEAD
{
  "id": 7173227,
  "type": "Feature",
  "properties": {
    "tgn:hierarchy":[
        "tgn:7173227",
        "tgn:1000003",
        "tgn:7003676",
        "tgn:7000084",
        "tgn:7029392"
    ],
    "tgn:id":7173227,
    "tgn:name":"Gro\u00dfer Tannenkamp",
    "tgn:placetype":[
        "aat:300008863"
    ]
},
  "bbox": [],
  "geometry": {"coordinates":[7.3,52.816667],"type":"Point"}
}
=======
{"geometry":{"type":"Point","coordinates":[7.300000,52.816667]},"type":"Feature","properties":{"hierarchy":["tgn:7173227","tgn:1000003","tgn:7003676","tgn:7000084","tgn:7029392"],"placetype":["aat:300008863"],"id":7173227,"name:xx":"Gro\u00dfer Tannenkamp"}}
>>>>>>> 03f74aca74312dbeaf24d7e61306dd6a786dc3d0
