{
  "id": 7195190,
  "type": "Feature",
  "properties": {
    "tgn:hierarchy":[
        "tgn:7195190",
        "tgn:1000003",
        "tgn:7000094",
        "tgn:7000084",
        "tgn:7029392"
    ],
    "tgn:id":7195190,
    "tgn:name":"Granitz",
    "tgn:placetype":[
        "aat:300055621"
    ]
},
  "bbox": [],
  "geometry": {"coordinates":[13.666667,54.383333],"type":"Point"}
}