<<<<<<< HEAD
{
  "id": 2254806,
  "type": "Feature",
  "properties": {
    "tgn:hierarchy":[
        "tgn:2254806",
        "tgn:1000001",
        "tgn:7012149",
        "tgn:7007923",
        "tgn:7029392"
    ],
    "tgn:id":2254806,
    "tgn:name":"Cooney Hills",
    "tgn:placetype":[
        "aat:300266640"
    ]
},
  "bbox": [],
  "geometry": {"coordinates":[-105.1,41.9667],"type":"Point"}
}
=======
{"geometry":{"type":"Point","coordinates":[-105.100000,41.966700]},"type":"Feature","properties":{"hierarchy":["tgn:2254806","tgn:1000001","tgn:7012149","tgn:7007923","tgn:7029392"],"placetype":["aat:300266640"],"id":2254806,"name:xx":"Cooney Hills"}}
>>>>>>> 03f74aca74312dbeaf24d7e61306dd6a786dc3d0
