{
  "id": 2275679,
  "type": "Feature",
  "properties": {
    "tgn:hierarchy":[
        "tgn:2275679",
        "tgn:1000001",
        "tgn:2000922",
        "tgn:7012149",
        "tgn:7007515",
        "tgn:7029392"
    ],
    "tgn:id":2275679,
    "tgn:name":"Dark Brook",
    "tgn:placetype":[
        "aat:300008699"
    ]
},
  "bbox": [],
  "geometry": {"coordinates":[-68.1167,44.7667],"type":"Point"}
}