{
  "id": 7208124,
  "type": "Feature",
  "properties": {
    "tgn:hierarchy":[
        "tgn:7208124",
        "tgn:1000003",
        "tgn:7000094",
        "tgn:7000084",
        "tgn:7029392"
    ],
    "tgn:id":7208124,
    "tgn:name":"C\u00f6lpin",
    "tgn:placetype":[
        "aat:300008347"
    ]
},
  "bbox": [],
  "geometry": {"coordinates":[13.433333,53.516667],"type":"Point"}
}