{
  "id": 1053974,
  "type": "Feature",
  "properties": {
    "tgn:hierarchy":[
        "tgn:1053974",
        "tgn:1000004",
        "tgn:7011531",
        "tgn:7018214",
        "tgn:7002435",
        "tgn:7029392"
    ],
    "tgn:id":1053974,
    "tgn:name":"Gelendzhik",
    "tgn:placetype":[
        "aat:300008347"
    ]
},
  "bbox": [],
  "geometry": {"coordinates":[38.1167,44.5667],"type":"Point"}
}