{
  "id": 2521550,
  "type": "Feature",
  "properties": {
    "tgn:hierarchy":[
        "tgn:2521550",
        "tgn:1000001",
        "tgn:2001431",
        "tgn:7012149",
        "tgn:7007566",
        "tgn:7029392"
    ],
    "tgn:id":2521550,
    "tgn:name":"Montoso Tank",
    "tgn:placetype":[
        "aat:300006191"
    ]
},
  "bbox": [],
  "geometry": {"coordinates":[-108.2333,34.6667],"type":"Point"}
}