<<<<<<< HEAD
{
  "id": 2156284,
  "type": "Feature",
  "properties": {
    "tgn:hierarchy":[
        "tgn:2156284",
        "tgn:7006450",
        "tgn:1000001",
        "tgn:7012149",
        "tgn:2124005",
        "tgn:7029392"
    ],
    "tgn:id":2156284,
    "tgn:name":"Bearpaw Creek",
    "tgn:placetype":[
        "aat:300008706"
    ]
},
  "bbox": [],
  "geometry": {"coordinates":[-152.1667,69.4],"type":"Point"}
}
=======
{"geometry":{"type":"Point","coordinates":[-152.166700,69.400000]},"type":"Feature","properties":{"hierarchy":["tgn:2156284","tgn:7006450","tgn:1000001","tgn:7012149","tgn:2124005","tgn:7029392"],"placetype":["aat:300008706"],"id":2156284,"name:xx":"Bearpaw Creek"}}
>>>>>>> 03f74aca74312dbeaf24d7e61306dd6a786dc3d0
