{
  "id": 1028311,
  "type": "Feature",
  "properties": {
    "tgn:hierarchy":[
        "tgn:1028311",
        "tgn:7002445",
        "tgn:7008114",
        "tgn:1000003",
        "tgn:7008591",
        "tgn:7029392"
    ],
    "tgn:id":1028311,
    "tgn:name:en":"Anderton",
    "tgn:placetype":[
        "aat:300008347"
    ]
},
  "bbox": [],
  "geometry": {"coordinates":[-2.533333,53.266667],"type":"Point"}
}