{
  "id": 1076902,
  "type": "Feature",
  "properties": {
    "tgn:hierarchy":[
        "tgn:1076902",
        "tgn:1000004",
        "tgn:7031781",
        "tgn:7000198",
        "tgn:7029392"
    ],
    "tgn:id":1076902,
    "tgn:name:en":"Semaria",
    "tgn:placetype":[
        "aat:300008347"
    ]
},
  "bbox": [],
  "geometry": {"coordinates":[82.55999,23.718203],"type":"Point"}
}