{
  "id": 7359702,
  "type": "Feature",
  "properties": {
    "tgn:hierarchy":[
        "tgn:7359702",
        "tgn:1000001",
        "tgn:7005597",
        "tgn:7005560",
        "tgn:7029392"
    ],
    "tgn:id":7359702,
    "tgn:name":"Concepci\u00f3n",
    "tgn:placetype":[
        "aat:300008347"
    ]
},
  "bbox": [],
  "geometry": {"coordinates":[-99.533333,27.583333],"type":"Point"}
}