{
  "id": 2009686,
  "type": "Feature",
  "properties": {
    "tgn:hierarchy":[
        "tgn:2009686",
        "tgn:1000001",
        "tgn:7016172",
        "tgn:2000121",
        "tgn:7012149",
        "tgn:7029392"
    ],
    "tgn:id":2009686,
    "tgn:name":"Uniontown",
    "tgn:placetype":[
        "aat:300008347"
    ]
},
  "bbox": [],
  "geometry": {"coordinates":[-94.4333,35.5833],"type":"Point"}
}