{
  "id": 2163371,
  "type": "Feature",
  "properties": {
    "tgn:hierarchy":[
        "tgn:2163371",
        "tgn:2002143",
        "tgn:1000001",
        "tgn:7012149",
        "tgn:7007919",
        "tgn:7029392"
    ],
    "tgn:id":2163371,
    "tgn:name":"Bennys Cave",
    "tgn:placetype":[
        "aat:300008746"
    ]
},
  "bbox": [],
  "geometry": {"coordinates":[-79.65,38.0667],"type":"Point"}
}