{
  "id": 2115718,
  "type": "Feature",
  "properties": {
    "tgn:hierarchy":[
        "tgn:2115718",
        "tgn:1000001",
        "tgn:7012149",
        "tgn:2002252",
        "tgn:7007920",
        "tgn:7029392"
    ],
    "tgn:id":2115718,
    "tgn:name":"Endicott",
    "tgn:placetype":[
        "aat:300008347"
    ]
},
  "bbox": [],
  "geometry": {"coordinates":[-117.6667,46.9167],"type":"Point"}
}