{
  "id": 7306104,
  "type": "Feature",
  "properties": {
    "tgn:hierarchy":[
        "tgn:7306104",
        "tgn:7002758",
        "tgn:7002821",
        "tgn:1000003",
        "tgn:1000095",
        "tgn:7029392"
    ],
    "tgn:id":7306104,
    "tgn:name":"Los Ba\u00f1uelos",
    "tgn:placetype":[
        "aat:300008347"
    ]
},
  "bbox": [],
  "geometry": {"coordinates":[-3.683333,36.783333],"type":"Point"}
}