<<<<<<< HEAD
{
  "id": 7111308,
  "type": "Feature",
  "properties": {
    "tgn:hierarchy":[
        "tgn:7111308",
        "tgn:1000003",
        "tgn:7003678",
        "tgn:7000084",
        "tgn:7029392"
    ],
    "tgn:id":7111308,
    "tgn:name":"Remerz",
    "tgn:placetype":[
        "aat:300008347"
    ]
},
  "bbox": [],
  "geometry": {"coordinates":[9.833333,50.5],"type":"Point"}
}
=======
{"geometry":{"type":"Point","coordinates":[9.833333,50.500000]},"type":"Feature","properties":{"hierarchy":["tgn:7111308","tgn:1000003","tgn:7003678","tgn:7000084","tgn:7029392"],"placetype":["aat:300008347"],"id":7111308,"name:xx":"Remerz"}}
>>>>>>> 03f74aca74312dbeaf24d7e61306dd6a786dc3d0
