{
  "id": 2428120,
  "type": "Feature",
  "properties": {
    "tgn:hierarchy":[
        "tgn:2428120",
        "tgn:1000001",
        "tgn:2002109",
        "tgn:7012149",
        "tgn:7007827",
        "tgn:7029392"
    ],
    "tgn:id":2428120,
    "tgn:name":"Judd Creek",
    "tgn:placetype":[
        "aat:300008706"
    ]
},
  "bbox": [],
  "geometry": {"coordinates":[-112.2333,37.85],"type":"Point"}
}