{
  "id": 7041442,
  "type": "Feature",
  "properties": {
    "tgn:hierarchy":[
        "tgn:7041442",
        "tgn:7003127",
        "tgn:1000003",
        "tgn:7008516",
        "tgn:1000080",
        "tgn:7029392"
    ],
    "tgn:id":7041442,
    "tgn:name":"San Marco",
    "tgn:placetype":[
        "aat:300008347"
    ]
},
  "bbox": [],
  "geometry": {"coordinates":[12.178889,44.374722],"type":"Point"}
}