{
  "id": 2448841,
  "type": "Feature",
  "properties": {
    "tgn:hierarchy":[
        "tgn:2448841",
        "tgn:1000001",
        "tgn:2002370",
        "tgn:7012149",
        "tgn:7007923",
        "tgn:7029392"
    ],
    "tgn:id":2448841,
    "tgn:name":"Lime Buttes",
    "tgn:placetype":[
        "aat:300008798"
    ]
},
  "bbox": [],
  "geometry": {"coordinates":[-104.3667,44.3333],"type":"Point"}
}