{
  "id": 2479108,
  "type": "Feature",
  "properties": {
    "tgn:hierarchy":[
        "tgn:2479108",
        "tgn:1000001",
        "tgn:7012149",
        "tgn:2000342",
        "tgn:7007248",
        "tgn:7029392"
    ],
    "tgn:id":2479108,
    "tgn:name":"Lady Washington Point",
    "tgn:placetype":[
        "aat:300008850"
    ]
},
  "bbox": [],
  "geometry": {"coordinates":[-81.1167,32.2667],"type":"Point"}
}