{
  "id": 2517980,
  "type": "Feature",
  "properties": {
    "tgn:hierarchy":[
        "tgn:2517980",
        "tgn:1000001",
        "tgn:7012149",
        "tgn:1002924",
        "tgn:7007568",
        "tgn:7029392"
    ],
    "tgn:id":2517980,
    "tgn:name":"Misery, Mount",
    "tgn:placetype":[
        "aat:300008798"
    ]
},
  "bbox": [],
  "geometry": {"coordinates":[-73.05,40.95],"type":"Point"}
}