{
  "id": 2328811,
  "type": "Feature",
  "properties": {
    "tgn:hierarchy":[
        "tgn:2328811",
        "tgn:1000001",
        "tgn:7012149",
        "tgn:2001202",
        "tgn:7007523",
        "tgn:7029392"
    ],
    "tgn:id":2328811,
    "tgn:name":"Fishing Creek",
    "tgn:placetype":[
        "aat:300008706"
    ]
},
  "bbox": [],
  "geometry": {"coordinates":[-93.9333,38.35],"type":"Point"}
}