<<<<<<< HEAD
{
  "id": 2159001,
  "type": "Feature",
  "properties": {
    "tgn:hierarchy":[
        "tgn:2159001",
        "tgn:1000001",
        "tgn:7012149",
        "tgn:2001706",
        "tgn:7007708",
        "tgn:7029392"
    ],
    "tgn:id":2159001,
    "tgn:name":"Beckworth Creek",
    "tgn:placetype":[
        "aat:300008706"
    ]
},
  "bbox": [],
  "geometry": {"coordinates":[-123.2,42.9833],"type":"Point"}
}
=======
{"geometry":{"type":"Point","coordinates":[-123.200000,42.983300]},"type":"Feature","properties":{"hierarchy":["tgn:2159001","tgn:1000001","tgn:7012149","tgn:2001706","tgn:7007708","tgn:7029392"],"placetype":["aat:300008706"],"id":2159001,"name:xx":"Beckworth Creek"}}
>>>>>>> 03f74aca74312dbeaf24d7e61306dd6a786dc3d0
