{
  "id": 7270849,
  "type": "Feature",
  "properties": {
    "tgn:hierarchy":[
        "tgn:7270849",
        "tgn:1000003",
        "tgn:7003635",
        "tgn:7016845",
        "tgn:7029392"
    ],
    "tgn:id":7270849,
    "tgn:name:nl":"Sint Pieterspolder",
    "tgn:placetype":[
        "aat:300006163"
    ]
},
  "bbox": [],
  "geometry": {"coordinates":[4.066667,51.466667],"type":"Point"}
}