{
  "id": 7155993,
  "type": "Feature",
  "properties": {
    "tgn:hierarchy":[
        "tgn:7155993",
        "tgn:7000096",
        "tgn:1000003",
        "tgn:7000084",
        "tgn:7029392"
    ],
    "tgn:id":7155993,
    "tgn:name":"Kemnitz",
    "tgn:placetype":[
        "aat:300008347"
    ]
},
  "bbox": [],
  "geometry": {"coordinates":[12.233333,53.133333],"type":"Point"}
}