{
  "id": 2713650,
  "type": "Feature",
  "properties": {
    "tgn:hierarchy":[
        "tgn:2713650",
        "tgn:1000001",
        "tgn:7012149",
        "tgn:2000234",
        "tgn:7007158",
        "tgn:7029392"
    ],
    "tgn:id":2713650,
    "tgn:name":"Teapot Dome Number 2 Mine",
    "tgn:placetype":[
        "aat:300000390"
    ]
},
  "bbox": [],
  "geometry": {"coordinates":[-108.7833,38.1833],"type":"Point"}
}