{
  "id": 2613261,
  "type": "Feature",
  "properties": {
    "tgn:hierarchy":[
        "tgn:2613261",
        "tgn:1000001",
        "tgn:7012149",
        "tgn:2000930",
        "tgn:7007515",
        "tgn:7029392"
    ],
    "tgn:id":2613261,
    "tgn:name":"Reed Brook",
    "tgn:placetype":[
        "aat:300008699"
    ]
},
  "bbox": [],
  "geometry": {"coordinates":[-69.8167,46.1333],"type":"Point"}
}