{
  "id": 2128062,
  "type": "Feature",
  "properties": {
    "tgn:hierarchy":[
        "tgn:2128062",
        "tgn:1000001",
        "tgn:7012149",
        "tgn:2001449",
        "tgn:7007566",
        "tgn:7029392"
    ],
    "tgn:id":2128062,
    "tgn:name":"Albert Mesa",
    "tgn:placetype":[
        "aat:300008798"
    ]
},
  "bbox": [],
  "geometry": {"coordinates":[-107.4167,36.5167],"type":"Point"}
}