{
  "id": 2403155,
  "type": "Feature",
  "properties": {
    "tgn:hierarchy":[
        "tgn:2403155",
        "tgn:1000001",
        "tgn:7012149",
        "tgn:7007826",
        "tgn:7029392"
    ],
    "tgn:id":2403155,
    "tgn:name":"House Draw",
    "tgn:placetype":[
        "aat:300008761"
    ]
},
  "bbox": [],
  "geometry": {"coordinates":[-100.95,30.35],"type":"Point"}
}