{
  "id": 7292547,
  "type": "Feature",
  "properties": {
    "tgn:hierarchy":[
        "tgn:7292547",
        "tgn:1001657",
        "tgn:1000049",
        "tgn:1000002",
        "tgn:7029392"
    ],
    "tgn:id":7292547,
    "tgn:name":"El Toro, Cerro",
    "tgn:placetype":[
        "aat:300008795"
    ]
},
  "bbox": [],
  "geometry": {"coordinates":[-71.166667,-30.233333],"type":"Point"}
}