{
  "id": 7446002,
  "type": "Feature",
  "properties": {
    "tgn:hierarchy":[
        "tgn:7446002",
        "tgn:7002444",
        "tgn:7008074",
        "tgn:1000003",
        "tgn:7008591",
        "tgn:7029392"
    ],
    "tgn:id":7446002,
    "tgn:name:en":"Rigg",
    "tgn:placetype":[
        "aat:300008347"
    ]
},
  "bbox": [],
  "geometry": {"coordinates":[-3.116667,54.983333],"type":"Point"}
}