{
  "id": 2522740,
  "type": "Feature",
  "properties": {
    "tgn:hierarchy":[
        "tgn:2522740",
        "tgn:1000001",
        "tgn:7012149",
        "tgn:2001929",
        "tgn:7007825",
        "tgn:7029392"
    ],
    "tgn:id":2522740,
    "tgn:name":"Moore Cave",
    "tgn:placetype":[
        "aat:300008746"
    ]
},
  "bbox": [],
  "geometry": {"coordinates":[-85.6167,35.9833],"type":"Point"}
}