{
  "id": 2452448,
  "type": "Feature",
  "properties": {
    "tgn:hierarchy":[
        "tgn:2452448",
        "tgn:1000001",
        "tgn:7012149",
        "tgn:2001918",
        "tgn:7007825",
        "tgn:7029392"
    ],
    "tgn:id":2452448,
    "tgn:name":"Little Branch",
    "tgn:placetype":[
        "aat:300008699"
    ]
},
  "bbox": [],
  "geometry": {"coordinates":[-82.1167,36.4333],"type":"Point"}
}