<<<<<<< HEAD
{
  "id": 7351588,
  "type": "Feature",
  "properties": {
    "tgn:hierarchy":[
        "tgn:7351588",
        "tgn:1000001",
        "tgn:7005591",
        "tgn:7005560",
        "tgn:7029392"
    ],
    "tgn:id":7351588,
    "tgn:name":"Arroyo",
    "tgn:placetype":[
        "aat:300008347"
    ]
},
  "bbox": [],
  "geometry": {"coordinates":[-96.45,15.85],"type":"Point"}
}
=======
{"geometry":{"type":"Point","coordinates":[-96.450000,15.850000]},"type":"Feature","properties":{"hierarchy":["tgn:7351588","tgn:1000001","tgn:7005591","tgn:7005560","tgn:7029392"],"placetype":["aat:300008347"],"id":7351588,"name:xx":"Arroyo"}}
>>>>>>> 03f74aca74312dbeaf24d7e61306dd6a786dc3d0
