{
  "id": 2418984,
  "type": "Feature",
  "properties": {
    "tgn:hierarchy":[
        "tgn:2418984",
        "tgn:1000001",
        "tgn:7012149",
        "tgn:7007158",
        "tgn:7029392"
    ],
    "tgn:id":2418984,
    "tgn:name":"James Peak",
    "tgn:placetype":[
        "aat:300008798"
    ]
},
  "bbox": [],
  "geometry": {"coordinates":[-105.6833,39.85],"type":"Point"}
}