<<<<<<< HEAD
{
  "id": 7353427,
  "type": "Feature",
  "properties": {
    "tgn:hierarchy":[
        "tgn:7353427",
        "tgn:7005578",
        "tgn:1000001",
        "tgn:7005560",
        "tgn:7029392"
    ],
    "tgn:id":7353427,
    "tgn:name":"Buenos Aires",
    "tgn:placetype":[
        "aat:300008347"
    ]
},
  "bbox": [],
  "geometry": {"coordinates":[-90.916667,18.316667],"type":"Point"}
}
=======
{"geometry":{"type":"Point","coordinates":[-90.916667,18.316667]},"type":"Feature","properties":{"hierarchy":["tgn:7353427","tgn:7005578","tgn:1000001","tgn:7005560","tgn:7029392"],"placetype":["aat:300008347"],"id":7353427,"name:xx":"Buenos Aires"}}
>>>>>>> 03f74aca74312dbeaf24d7e61306dd6a786dc3d0
