{
  "id": 7353427,
  "type": "Feature",
  "properties": {
    "tgn:hierarchy":[
        "tgn:7353427",
        "tgn:7005578",
        "tgn:1000001",
        "tgn:7005560",
        "tgn:7029392"
    ],
    "tgn:id":7353427,
    "tgn:name":"Buenos Aires",
    "tgn:placetype":[
        "aat:300008347"
    ]
},
  "bbox": [],
  "geometry": {"coordinates":[-90.916667,18.316667],"type":"Point"}
}