{
  "id": 2184281,
  "type": "Feature",
  "properties": {
    "tgn:hierarchy":[
        "tgn:2184281",
        "tgn:1000001",
        "tgn:7012149",
        "tgn:7007710",
        "tgn:7029392"
    ],
    "tgn:id":2184281,
    "tgn:name":"Bobbs Creek",
    "tgn:placetype":[
        "aat:300008706"
    ]
},
  "bbox": [],
  "geometry": {"coordinates":[-79.2167,41.65],"type":"Point"}
}