{
  "id": 2574919,
  "type": "Feature",
  "properties": {
    "tgn:hierarchy":[
        "tgn:2574919",
        "tgn:1000001",
        "tgn:7012149",
        "tgn:2000329",
        "tgn:7007248",
        "tgn:7029392"
    ],
    "tgn:id":2574919,
    "tgn:name":"Peniston Lake",
    "tgn:placetype":[
        "aat:300006191"
    ]
},
  "bbox": [],
  "geometry": {"coordinates":[-84.6333,33.3833],"type":"Point"}
}