{
  "id": 7520013,
  "type": "Feature",
  "properties": {
    "tgn:hierarchy":[
        "tgn:7520013",
        "tgn:1009227",
        "tgn:1000226",
        "tgn:7016822",
        "tgn:1000006",
        "tgn:7029392"
    ],
    "tgn:id":7520013,
    "tgn:name:en":"Basin Creek",
    "tgn:placetype":[
        "aat:300008699"
    ]
},
  "bbox": [],
  "geometry": {"coordinates":[167.666667,-47.166667],"type":"Point"}
}