{
  "id": 7202802,
  "type": "Feature",
  "properties": {
    "tgn:hierarchy":[
        "tgn:7202802",
        "tgn:1000003",
        "tgn:7003688",
        "tgn:7000084",
        "tgn:7029392"
    ],
    "tgn:id":7202802,
    "tgn:name":"Braak",
    "tgn:placetype":[
        "aat:300008347"
    ]
},
  "bbox": [],
  "geometry": {"coordinates":[10.25,53.616667],"type":"Point"}
}