{
  "id": 1113576,
  "type": "Feature",
  "properties": {
    "tgn:hierarchy":[
        "tgn:1113576",
        "tgn:1000004",
        "tgn:7016744",
        "tgn:1000135",
        "tgn:7029392"
    ],
    "tgn:id":1113576,
    "tgn:name":"Panguil Bay",
    "tgn:placetype":[
        "aat:300132316"
    ]
},
  "bbox": [],
  "geometry": {"coordinates":[123.7167,8.0167],"type":"Point"}
}