{
  "id": 2429212,
  "type": "Feature",
  "properties": {
    "tgn:hierarchy":[
        "tgn:2429212",
        "tgn:1000001",
        "tgn:7012149",
        "tgn:2001715",
        "tgn:7007708",
        "tgn:7029392"
    ],
    "tgn:id":2429212,
    "tgn:name":"June Reservoir",
    "tgn:placetype":[
        "aat:300006191"
    ]
},
  "bbox": [],
  "geometry": {"coordinates":[-119.6667,42.25],"type":"Point"}
}