{
  "id": 1136400,
  "type": "Feature",
  "properties": {
    "tgn:hierarchy":[
        "tgn:1136400",
        "tgn:7005586",
        "tgn:1000001",
        "tgn:7005560",
        "tgn:7029392"
    ],
    "tgn:id":1136400,
    "tgn:name":"Tuxpan",
    "tgn:placetype":[
        "aat:300008347",
        "aat:300008375"
    ]
},
  "bbox": [],
  "geometry": {"coordinates":[-104.116667,21.616667],"type":"Point"}
}