{
  "id": 7375929,
  "type": "Feature",
  "properties": {
    "tgn:hierarchy":[
        "tgn:7375929",
        "tgn:7005586",
        "tgn:1000001",
        "tgn:7005560",
        "tgn:7029392"
    ],
    "tgn:id":7375929,
    "tgn:name":"Las Habas",
    "tgn:placetype":[
        "aat:300008347"
    ]
},
  "bbox": [],
  "geometry": {"coordinates":[-105.116667,19.65],"type":"Point"}
}