{
  "id": 2116262,
  "type": "Feature",
  "properties": {
    "tgn:hierarchy":[
        "tgn:2116262",
        "tgn:1000001",
        "tgn:7012149",
        "tgn:1002521",
        "tgn:7007920",
        "tgn:7029392"
    ],
    "tgn:id":2116262,
    "tgn:name":"Maynard",
    "tgn:placetype":[
        "aat:300387016"
    ]
},
  "bbox": [],
  "geometry": {"coordinates":[-122.8667,47.9833],"type":"Point"}
}