{
  "id": 7104441,
  "type": "Feature",
  "properties": {
    "tgn:hierarchy":[
        "tgn:7104441",
        "tgn:1000003",
        "tgn:7003689",
        "tgn:7000084",
        "tgn:7029392"
    ],
    "tgn:id":7104441,
    "tgn:name":"Schnetter Berg",
    "tgn:placetype":[
        "aat:300008777"
    ]
},
  "bbox": [],
  "geometry": {"coordinates":[10.883333,50.516667],"type":"Point"}
}