{
  "id": 2282126,
  "type": "Feature",
  "properties": {
    "tgn:hierarchy":[
        "tgn:2282126",
        "tgn:2000942",
        "tgn:1000001",
        "tgn:7012149",
        "tgn:7007520",
        "tgn:7029392"
    ],
    "tgn:id":2282126,
    "tgn:name":"Deer Lake",
    "tgn:placetype":[
        "aat:300008680"
    ]
},
  "bbox": [],
  "geometry": {"coordinates":[-83.4667,44.7667],"type":"Point"}
}