<<<<<<< HEAD
{
  "id": 7020703,
  "type": "Feature",
  "properties": {
    "tgn:hierarchy":[
        "tgn:7020703",
        "tgn:2000934",
        "tgn:1000001",
        "tgn:7012149",
        "tgn:7007516",
        "tgn:7029392"
    ],
    "tgn:id":7020703,
    "tgn:name":"Pine Ridge",
    "tgn:placetype":[
        "aat:300266640"
    ]
},
  "bbox": [],
  "geometry": {"coordinates":[-78.5833,39.5833],"type":"Point"}
}
=======
{"geometry":{"type":"Point","coordinates":[-78.583300,39.583300]},"type":"Feature","properties":{"hierarchy":["tgn:7020703","tgn:2000934","tgn:1000001","tgn:7012149","tgn:7007516","tgn:7029392"],"placetype":["aat:300266640"],"id":7020703,"name:xx":"Pine Ridge"}}
>>>>>>> 03f74aca74312dbeaf24d7e61306dd6a786dc3d0
