{
  "id": 7329556,
  "type": "Feature",
  "properties": {
    "tgn:hierarchy":[
        "tgn:7329556",
        "tgn:7002834",
        "tgn:1000003",
        "tgn:7002786",
        "tgn:1000095",
        "tgn:7029392"
    ],
    "tgn:id":7329556,
    "tgn:name":"Pi\u00f1eiro, R\u00edo",
    "tgn:placetype":[
        "aat:300008699"
    ]
},
  "bbox": [],
  "geometry": {"coordinates":[-8.383333,42.283333],"type":"Point"}
}