{
  "id": 7324971,
  "type": "Feature",
  "properties": {
    "tgn:hierarchy":[
        "tgn:7324971",
        "tgn:7002808",
        "tgn:7030216",
        "tgn:1000003",
        "tgn:1000095",
        "tgn:7029392"
    ],
    "tgn:id":7324971,
    "tgn:name":"Santa Fe",
    "tgn:placetype":[
        "aat:300008347"
    ]
},
  "bbox": [],
  "geometry": {"coordinates":[2.466667,41.783333],"type":"Point"}
}