{
  "id": 7008371,
  "type": "Feature",
  "properties": {
    "tgn:hierarchy":[
        "tgn:7008371",
        "tgn:1000003",
        "tgn:7002885",
        "tgn:1000070",
        "tgn:7029392"
    ],
    "tgn:id":7008371,
    "tgn:name:fr":"N\u00eemes",
    "tgn:placetype":[
        "aat:300008347",
        "aat:300000810",
        "aat:300387218",
        "aat:300387225",
        "aat:300008389",
        "aat:300387512",
        "aat:300387302",
        "aat:300387286"
    ]
},
  "bbox": [],
  "geometry": {"coordinates":[4.35,43.8333],"type":"Point"}
}