{
  "id": 2436263,
  "type": "Feature",
  "properties": {
    "tgn:hierarchy":[
        "tgn:2436263",
        "tgn:1000001",
        "tgn:7012149",
        "tgn:2002349",
        "tgn:7007922",
        "tgn:7029392"
    ],
    "tgn:id":2436263,
    "tgn:name":"Keysville",
    "tgn:placetype":[
        "aat:300008347"
    ]
},
  "bbox": [],
  "geometry": {"coordinates":[-90.2167,43.3333],"type":"Point"}
}