{
  "id": 7559942,
  "type": "Feature",
  "properties": {
    "tgn:hierarchy":[
        "tgn:7559942",
        "tgn:1000004",
        "tgn:7000198",
        "tgn:7016788",
        "tgn:7029392"
    ],
    "tgn:id":7559942,
    "tgn:name:en":"Bh\u0101mori",
    "tgn:placetype":[
        "aat:300008347"
    ]
},
  "bbox": [],
  "geometry": {"coordinates":[75.616047,26.960408],"type":"Point"}
}