{
  "id": 1004646,
  "type": "Feature",
  "properties": {
    "tgn:hierarchy":[
        "tgn:1004646",
        "tgn:7003712",
        "tgn:1005422",
        "tgn:7003670",
        "tgn:1000003",
        "tgn:7000084",
        "tgn:7029392"
    ],
    "tgn:id":1004646,
    "tgn:name":"Hermsdorf",
    "tgn:placetype":[
        "aat:300000745",
        "aat:300387340"
    ]
},
  "bbox": [],
  "geometry": {"coordinates":[13.316667,52.616667],"type":"Point"}
}