{
  "id": 7069528,
  "type": "Feature",
  "properties": {
    "tgn:hierarchy":[
        "tgn:7069528",
        "tgn:1000003",
        "tgn:7003677",
        "tgn:7000084",
        "tgn:7029392"
    ],
    "tgn:id":7069528,
    "tgn:name":"Th\u00fcle",
    "tgn:placetype":[
        "aat:300008347"
    ]
},
  "bbox": [],
  "geometry": {"coordinates":[8.583333,51.716667],"type":"Point"}
}