{
  "id": 7333880,
  "type": "Feature",
  "properties": {
    "tgn:hierarchy":[
        "tgn:7333880",
        "tgn:7002807",
        "tgn:1000003",
        "tgn:7003837",
        "tgn:1000095",
        "tgn:7029392"
    ],
    "tgn:id":7333880,
    "tgn:name":"Entr\u00edn Bajo",
    "tgn:placetype":[
        "aat:300008347"
    ]
},
  "bbox": [],
  "geometry": {"coordinates":[-6.716667,38.716667],"type":"Point"}
}