{
  "id": 2156925,
  "type": "Feature",
  "properties": {
    "tgn:hierarchy":[
        "tgn:2156925",
        "tgn:1002156",
        "tgn:1000001",
        "tgn:7012149",
        "tgn:7007706",
        "tgn:7029392"
    ],
    "tgn:id":2156925,
    "tgn:name":"Beaumont, Lake",
    "tgn:placetype":[
        "aat:300006191"
    ]
},
  "bbox": [],
  "geometry": {"coordinates":[-80.8667,41.6833],"type":"Point"}
}