{
  "id": 5002494,
  "type": "Feature",
  "properties": {
    "tgn:hierarchy":[
        "tgn:5002494",
        "tgn:1000003",
        "tgn:7003143",
        "tgn:7003236",
        "tgn:1000080",
        "tgn:7029392"
    ],
    "tgn:id":5002494,
    "tgn:name":"Baccano",
    "tgn:placetype":[
        "aat:300008347"
    ]
},
  "bbox": [],
  "geometry": {"coordinates":[121.6667,42.4167],"type":"Point"}
}