{
  "id": 7020862,
  "type": "Feature",
  "properties": {
    "tgn:hierarchy":[
        "tgn:7020862",
        "tgn:1000001",
        "tgn:7012149",
        "tgn:7029392"
    ],
    "tgn:id":7020862,
    "tgn:name":"Little Cumberland Mountain",
    "tgn:placetype":[
        "aat:300266640"
    ]
},
  "bbox": [],
  "geometry": {"coordinates":[-86.1167,34.9833],"type":"Point"}
}