<<<<<<< HEAD
{
  "id": 7020862,
  "type": "Feature",
  "properties": {
    "tgn:hierarchy":[
        "tgn:7020862",
        "tgn:1000001",
        "tgn:7012149",
        "tgn:7029392"
    ],
    "tgn:id":7020862,
    "tgn:name":"Little Cumberland Mountain",
    "tgn:placetype":[
        "aat:300266640"
    ]
},
  "bbox": [],
  "geometry": {"coordinates":[-86.1167,34.9833],"type":"Point"}
}
=======
{"geometry":{"type":"Point","coordinates":[-86.116700,34.983300]},"type":"Feature","properties":{"hierarchy":["tgn:7020862","tgn:1000001","tgn:7012149","tgn:7029392"],"placetype":["aat:300266640"],"id":7020862,"name:xx":"Little Cumberland Mountain"}}
>>>>>>> 03f74aca74312dbeaf24d7e61306dd6a786dc3d0
