{
  "id": 7406046,
  "type": "Feature",
  "properties": {
    "tgn:hierarchy":[
        "tgn:7406046",
        "tgn:1000001",
        "tgn:1001906",
        "tgn:7005560",
        "tgn:7029392"
    ],
    "tgn:id":7406046,
    "tgn:name":"Chimaltit\u00e1n",
    "tgn:placetype":[
        "aat:300008347"
    ]
},
  "bbox": [],
  "geometry": {"coordinates":[-104.825,22.108333],"type":"Point"}
}