{
  "id": 7254298,
  "type": "Feature",
  "properties": {
    "tgn:hierarchy":[
        "tgn:7254298",
        "tgn:7003461",
        "tgn:1000003",
        "tgn:1000063",
        "tgn:7018236",
        "tgn:7029392"
    ],
    "tgn:id":7254298,
    "tgn:name":"Teuven",
    "tgn:placetype":[
        "aat:300008347"
    ]
},
  "bbox": [],
  "geometry": {"coordinates":[5.866667,50.75],"type":"Point"}
}