{
  "id": 2255116,
  "type": "Feature",
  "properties": {
    "tgn:hierarchy":[
        "tgn:2255116",
        "tgn:1002808",
        "tgn:1000001",
        "tgn:7012149",
        "tgn:7007711",
        "tgn:7029392"
    ],
    "tgn:id":2255116,
    "tgn:name":"Cooper Hill",
    "tgn:placetype":[
        "aat:300008798"
    ]
},
  "bbox": [],
  "geometry": {"coordinates":[-71.6333,41.9333],"type":"Point"}
}