<<<<<<< HEAD
{
  "id": 7376269,
  "type": "Feature",
  "properties": {
    "tgn:hierarchy":[
        "tgn:7376269",
        "tgn:1000001",
        "tgn:1001960",
        "tgn:7005560",
        "tgn:7029392"
    ],
    "tgn:id":7376269,
    "tgn:name":"Rancho Las Jarillas",
    "tgn:placetype":[
        "aat:300000241"
    ]
},
  "bbox": [],
  "geometry": {"coordinates":[-111.283333,30.733333],"type":"Point"}
}
=======
{"geometry":{"type":"Point","coordinates":[-111.283333,30.733333]},"type":"Feature","properties":{"hierarchy":["tgn:7376269","tgn:1000001","tgn:1001960","tgn:7005560","tgn:7029392"],"placetype":["aat:300000241"],"id":7376269,"name:xx":"Rancho Las Jarillas"}}
>>>>>>> 03f74aca74312dbeaf24d7e61306dd6a786dc3d0
