{
  "id": 7276852,
  "type": "Feature",
  "properties": {
    "tgn:hierarchy":[
        "tgn:7276852",
        "tgn:1001705",
        "tgn:1000049",
        "tgn:1000002",
        "tgn:7029392"
    ],
    "tgn:id":7276852,
    "tgn:name":"Punta de la Silla, Cerro",
    "tgn:placetype":[
        "aat:300008795"
    ]
},
  "bbox": [],
  "geometry": {"coordinates":[-71.45,-34.641667],"type":"Point"}
}