{
  "id": 7003443,
  "type": "Feature",
  "properties": {
    "tgn:hierarchy":[
        "tgn:7003443",
        "tgn:7594006",
        "tgn:1000003",
        "tgn:1000066",
        "tgn:7029392"
    ],
    "tgn:id":7003443,
    "tgn:name":"Silkeborg",
    "tgn:placetype":[
        "aat:300008347"
    ]
},
  "bbox": [],
  "geometry": {"coordinates":[9.5667,56.1667],"type":"Point"}
}