{
  "id": 2465984,
  "type": "Feature",
  "properties": {
    "tgn:hierarchy":[
        "tgn:2465984",
        "tgn:1000001",
        "tgn:7012149",
        "tgn:1002545",
        "tgn:7007157",
        "tgn:7029392"
    ],
    "tgn:id":2465984,
    "tgn:name":"Lone Tree Hill",
    "tgn:placetype":[
        "aat:300008798"
    ]
},
  "bbox": [],
  "geometry": {"coordinates":[-121.1667,35.6833],"type":"Point"}
}