{
  "id": 7580359,
  "type": "Feature",
  "properties": {
    "tgn:hierarchy":[
        "tgn:7580359",
        "tgn:1000004",
        "tgn:7000198",
        "tgn:7016788",
        "tgn:7029392"
    ],
    "tgn:id":7580359,
    "tgn:name:en":"Sheriala",
    "tgn:placetype":[
        "aat:300008347"
    ]
},
  "bbox": [],
  "geometry": {"coordinates":[73.671207,27.734348],"type":"Point"}
}