{
  "id": 1018767,
  "type": "Feature",
  "properties": {
    "tgn:hierarchy":[
        "tgn:1018767",
        "tgn:7593359",
        "tgn:1000001",
        "tgn:7005562",
        "tgn:7029392"
    ],
    "tgn:id":1018767,
    "tgn:name":"Rama",
    "tgn:placetype":[
        "aat:300008347"
    ]
},
  "bbox": [],
  "geometry": {"coordinates":[-84.25,12.15],"type":"Point"}
}