{
  "id": 7259598,
  "type": "Feature",
  "properties": {
    "tgn:hierarchy":[
        "tgn:7259598",
        "tgn:7003461",
        "tgn:1000003",
        "tgn:1000063",
        "tgn:7018236",
        "tgn:7029392"
    ],
    "tgn:id":7259598,
    "tgn:name":"Waterval",
    "tgn:placetype":[
        "aat:300008347"
    ]
},
  "bbox": [],
  "geometry": {"coordinates":[5.816667,50.733333],"type":"Point"}
}