{
  "id": 1077039,
  "type": "Feature",
  "properties": {
    "tgn:hierarchy":[
        "tgn:1077039",
        "tgn:1000004",
        "tgn:7000198",
        "tgn:7000799",
        "tgn:7029392"
    ],
    "tgn:id":1077039,
    "tgn:name:en":"Sopur",
    "tgn:placetype":[
        "aat:300008347"
    ]
},
  "bbox": [],
  "geometry": {"coordinates":[74.472188,34.287874],"type":"Point"}
}