{
  "id": 2247264,
  "type": "Feature",
  "properties": {
    "tgn:hierarchy":[
        "tgn:2247264",
        "tgn:1000001",
        "tgn:7012149",
        "tgn:7007157",
        "tgn:7014004",
        "tgn:7029392"
    ],
    "tgn:id":2247264,
    "tgn:name":"Coe Gulch",
    "tgn:placetype":[
        "aat:300008761"
    ]
},
  "bbox": [],
  "geometry": {"coordinates":[-120.15,37.6667],"type":"Point"}
}