{
  "id": 2590133,
  "type": "Feature",
  "properties": {
    "tgn:hierarchy":[
        "tgn:2590133",
        "tgn:1000001",
        "tgn:7012149",
        "tgn:2000181",
        "tgn:7007157",
        "tgn:7029392"
    ],
    "tgn:id":2590133,
    "tgn:name":"Poison Spring",
    "tgn:placetype":[
        "aat:300008697"
    ]
},
  "bbox": [],
  "geometry": {"coordinates":[-123.6167,40.5667],"type":"Point"}
}