{
  "id": 7410647,
  "type": "Feature",
  "properties": {
    "tgn:hierarchy":[
        "tgn:7410647",
        "tgn:1000001",
        "tgn:7005590",
        "tgn:7005560",
        "tgn:7029392"
    ],
    "tgn:id":7410647,
    "tgn:name":"Acuyo",
    "tgn:placetype":[
        "aat:300008347"
    ]
},
  "bbox": [],
  "geometry": {"coordinates":[-101.181944,18.875],"type":"Point"}
}