{
  "id": 1093650,
  "type": "Feature",
  "properties": {
    "tgn:hierarchy":[
        "tgn:1093650",
        "tgn:7001242",
        "tgn:7017582",
        "tgn:1000193",
        "tgn:7029392"
    ],
    "tgn:id":1093650,
    "tgn:name":"Springbok",
    "tgn:placetype":[
        "aat:300008347"
    ]
},
  "bbox": [],
  "geometry": {"coordinates":[17.9333,-29.7333],"type":"Point"}
}