{
  "id": 1010989,
  "type": "Feature",
  "properties": {
    "tgn:hierarchy":[
        "tgn:1010989",
        "tgn:1001986",
        "tgn:1000047",
        "tgn:7002456",
        "tgn:1000002",
        "tgn:7029392"
    ],
    "tgn:id":1010989,
    "tgn:name":"Norte, Cabo",
    "tgn:placetype":[
        "aat:300008850"
    ]
},
  "bbox": [],
  "geometry": {"coordinates":[-49.9167,1.7167],"type":"Point"}
}