{
  "id": 7546192,
  "type": "Feature",
  "properties": {
    "tgn:hierarchy":[
        "tgn:7546192",
        "tgn:1000004",
        "tgn:1001871",
        "tgn:7000198",
        "tgn:7029392"
    ],
    "tgn:id":7546192,
    "tgn:name:en":"Basai",
    "tgn:placetype":[
        "aat:300008347"
    ]
},
  "bbox": [],
  "geometry": {"coordinates":[75.963021,27.966875],"type":"Point"}
}