{
  "id": 2400898,
  "type": "Feature",
  "properties": {
    "tgn:hierarchy":[
        "tgn:2400898",
        "tgn:2000934",
        "tgn:1000001",
        "tgn:7012149",
        "tgn:7007516",
        "tgn:7029392"
    ],
    "tgn:id":2400898,
    "tgn:name":"Horse Rock Hill",
    "tgn:placetype":[
        "aat:300008798"
    ]
},
  "bbox": [],
  "geometry": {"coordinates":[-79.0167,39.4833],"type":"Point"}
}