<<<<<<< HEAD
{
  "id": 2400898,
  "type": "Feature",
  "properties": {
    "tgn:hierarchy":[
        "tgn:2400898",
        "tgn:2000934",
        "tgn:1000001",
        "tgn:7012149",
        "tgn:7007516",
        "tgn:7029392"
    ],
    "tgn:id":2400898,
    "tgn:name":"Horse Rock Hill",
    "tgn:placetype":[
        "aat:300008798"
    ]
},
  "bbox": [],
  "geometry": {"coordinates":[-79.0167,39.4833],"type":"Point"}
}
=======
{"geometry":{"type":"Point","coordinates":[-79.016700,39.483300]},"type":"Feature","properties":{"hierarchy":["tgn:2400898","tgn:2000934","tgn:1000001","tgn:7012149","tgn:7007516","tgn:7029392"],"placetype":["aat:300008798"],"id":2400898,"name:xx":"Horse Rock Hill"}}
>>>>>>> 03f74aca74312dbeaf24d7e61306dd6a786dc3d0
