<<<<<<< HEAD
{
  "id": 2159621,
  "type": "Feature",
  "properties": {
    "tgn:hierarchy":[
        "tgn:2159621",
        "tgn:7002659",
        "tgn:1000001",
        "tgn:7012149",
        "tgn:2000035",
        "tgn:7029392"
    ],
    "tgn:id":2159621,
    "tgn:name":"Bee Sting Cave",
    "tgn:placetype":[
        "aat:300008746"
    ]
},
  "bbox": [],
  "geometry": {"coordinates":[-86.0833,34.95],"type":"Point"}
}
=======
{"geometry":{"type":"Point","coordinates":[-86.083300,34.950000]},"type":"Feature","properties":{"hierarchy":["tgn:2159621","tgn:7002659","tgn:1000001","tgn:7012149","tgn:2000035","tgn:7029392"],"placetype":["aat:300008746"],"id":2159621,"name:xx":"Bee Sting Cave"}}
>>>>>>> 03f74aca74312dbeaf24d7e61306dd6a786dc3d0
