{
  "id": 7049353,
  "type": "Feature",
  "properties": {
    "tgn:hierarchy":[
        "tgn:7049353",
        "tgn:1000003",
        "tgn:7003122",
        "tgn:1000080",
        "tgn:7029392"
    ],
    "tgn:id":7049353,
    "tgn:name":"Caruzzone, Secca",
    "tgn:placetype":[
        "aat:300387036"
    ]
},
  "bbox": [],
  "geometry": {"coordinates":[15.216667,37.183333],"type":"Point"}
}