{
  "id": 7295333,
  "type": "Feature",
  "properties": {
    "tgn:hierarchy":[
        "tgn:7295333",
        "tgn:7001165",
        "tgn:1000003",
        "tgn:7002793",
        "tgn:1000095",
        "tgn:7029392"
    ],
    "tgn:id":7295333,
    "tgn:name":"Nazaret, Playa de",
    "tgn:placetype":[
        "aat:300008816"
    ]
},
  "bbox": [],
  "geometry": {"coordinates":[-0.333333,39.445833],"type":"Point"}
}