{
  "id": 2760256,
  "type": "Feature",
  "properties": {
    "tgn:hierarchy":[
        "tgn:2760256",
        "tgn:1000001",
        "tgn:7012149",
        "tgn:2001252",
        "tgn:7007523",
        "tgn:7029392"
    ],
    "tgn:id":2760256,
    "tgn:name":"West Fork Roubidoux Creek",
    "tgn:placetype":[
        "aat:300008706"
    ]
},
  "bbox": [],
  "geometry": {"coordinates":[-92.1667,37.2833],"type":"Point"}
}