{
  "id": 2703007,
  "type": "Feature",
  "properties": {
    "tgn:hierarchy":[
        "tgn:2703007",
        "tgn:1000001",
        "tgn:7012149",
        "tgn:2000181",
        "tgn:7007157",
        "tgn:7029392"
    ],
    "tgn:id":2703007,
    "tgn:name":"Sulphur Valley",
    "tgn:placetype":[
        "aat:300386845"
    ]
},
  "bbox": [],
  "geometry": {"coordinates":[-123.6167,40.45],"type":"Point"}
}