{
  "id": 2277975,
  "type": "Feature",
  "properties": {
    "tgn:hierarchy":[
        "tgn:2277975",
        "tgn:1000001",
        "tgn:7012149",
        "tgn:2001716",
        "tgn:7007708",
        "tgn:7029392"
    ],
    "tgn:id":2277975,
    "tgn:name":"Day Island",
    "tgn:placetype":[
        "aat:300008791"
    ]
},
  "bbox": [],
  "geometry": {"coordinates":[-123.0667,44.05],"type":"Point"}
}