{
  "id": 2274120,
  "type": "Feature",
  "properties": {
    "tgn:hierarchy":[
        "tgn:2274120",
        "tgn:1000001",
        "tgn:2000465",
        "tgn:7012149",
        "tgn:7007250",
        "tgn:7029392"
    ],
    "tgn:id":2274120,
    "tgn:name":"Dailey Lateral",
    "tgn:placetype":[
        "aat:300006075"
    ]
},
  "bbox": [],
  "geometry": {"coordinates":[-116.8667,43.65],"type":"Point"}
}