{
  "id": 7552874,
  "type": "Feature",
  "properties": {
    "tgn:hierarchy":[
        "tgn:7552874",
        "tgn:1000004",
        "tgn:7000198",
        "tgn:7016722",
        "tgn:7029392"
    ],
    "tgn:id":7552874,
    "tgn:name:en":"Manw\u0101r Nad\u012b",
    "tgn:placetype":[
        "aat:300008699"
    ]
},
  "bbox": [],
  "geometry": {"coordinates":[82.817998,26.658529],"type":"Point"}
}