{
  "id": 1114441,
  "type": "Feature",
  "properties": {
    "tgn:hierarchy":[
        "tgn:1114441",
        "tgn:7003505",
        "tgn:7001201",
        "tgn:1000003",
        "tgn:1000078",
        "tgn:7029392"
    ],
    "tgn:id":1114441,
    "tgn:name":"Dungarvan Harbour",
    "tgn:placetype":[
        "aat:300008678"
    ]
},
  "bbox": [],
  "geometry": {"coordinates":[-7.5833,52.0667],"type":"Point"}
}