{
  "id": 2104976,
  "type": "Feature",
  "properties": {
    "tgn:hierarchy":[
        "tgn:2104976",
        "tgn:1000001",
        "tgn:7013727",
        "tgn:7012149",
        "tgn:1002456",
        "tgn:7007826",
        "tgn:7029392"
    ],
    "tgn:id":2104976,
    "tgn:name":"Freeway Manor",
    "tgn:placetype":[
        "aat:300000745"
    ]
},
  "bbox": [],
  "geometry": {"coordinates":[-95.2167,29.6333],"type":"Point"}
}