{
  "id": 1033663,
  "type": "Feature",
  "properties": {
    "tgn:hierarchy":[
        "tgn:1033663",
        "tgn:1000003",
        "tgn:7002883",
        "tgn:1000070",
        "tgn:7029392"
    ],
    "tgn:id":1033663,
    "tgn:name":"La H\u00e4y-les-Rosas",
    "tgn:placetype":[
        "aat:300008347"
    ]
},
  "bbox": [],
  "geometry": {"coordinates":[2.35,48.7833],"type":"Point"}
}