{
  "id": 2710750,
  "type": "Feature",
  "properties": {
    "tgn:hierarchy":[
        "tgn:2710750",
        "tgn:1000001",
        "tgn:7012149",
        "tgn:1002391",
        "tgn:7007826",
        "tgn:7029392"
    ],
    "tgn:id":2710750,
    "tgn:name":"Tanbark Branch",
    "tgn:placetype":[
        "aat:300008699"
    ]
},
  "bbox": [],
  "geometry": {"coordinates":[-96.1333,31.7167],"type":"Point"}
}