{
  "id": 7586227,
  "type": "Feature",
  "properties": {
    "tgn:hierarchy":[
        "tgn:7586227",
        "tgn:1000004",
        "tgn:7000198",
        "tgn:7000799",
        "tgn:7029392"
    ],
    "tgn:id":7586227,
    "tgn:name:en":"Mark\u016bt",
    "tgn:placetype":[
        "aat:300008347"
    ]
},
  "bbox": [],
  "geometry": {"coordinates":[74.192847,34.280357],"type":"Point"}
}