{
  "id": 2304037,
  "type": "Feature",
  "properties": {
    "tgn:hierarchy":[
        "tgn:2304037",
        "tgn:1000001",
        "tgn:7012149",
        "tgn:1002545",
        "tgn:7007157",
        "tgn:7029392"
    ],
    "tgn:id":2304037,
    "tgn:name":"Eagle Spring",
    "tgn:placetype":[
        "aat:300008697"
    ]
},
  "bbox": [],
  "geometry": {"coordinates":[-118.2167,35.1333],"type":"Point"}
}