{
  "id": 2227374,
  "type": "Feature",
  "properties": {
    "tgn:hierarchy":[
        "tgn:2227374",
        "tgn:1000001",
        "tgn:7012149",
        "tgn:2001225",
        "tgn:7007523",
        "tgn:7029392"
    ],
    "tgn:id":2227374,
    "tgn:name":"Cave Spring",
    "tgn:placetype":[
        "aat:300008697"
    ]
},
  "bbox": [],
  "geometry": {"coordinates":[-91.35,36.65],"type":"Point"}
}