{
  "id": 7485937,
  "type": "Feature",
  "properties": {
    "tgn:hierarchy":[
        "tgn:7485937",
        "tgn:7488858",
        "tgn:1000004",
        "tgn:1000141",
        "tgn:7029392"
    ],
    "tgn:id":7485937,
    "tgn:name":"Tongtou Diaoqiao",
    "tgn:placetype":[
        "aat:300007836"
    ]
},
  "bbox": [],
  "geometry": {"coordinates":[120.659167,23.644167],"type":"Point"}
}