{
  "id": 2234209,
  "type": "Feature",
  "properties": {
    "tgn:hierarchy":[
        "tgn:2234209",
        "tgn:1000001",
        "tgn:7012149",
        "tgn:1002994",
        "tgn:7007708",
        "tgn:7029392"
    ],
    "tgn:id":2234209,
    "tgn:name":"Chehalem",
    "tgn:placetype":[
        "aat:300008347"
    ]
},
  "bbox": [],
  "geometry": {"coordinates":[-122.8833,45.3167],"type":"Point"}
}