{
  "id": 7282956,
  "type": "Feature",
  "properties": {
    "tgn:hierarchy":[
        "tgn:7282956",
        "tgn:7016598",
        "tgn:1000049",
        "tgn:1000002",
        "tgn:7029392"
    ],
    "tgn:id":7282956,
    "tgn:name":"Estaci\u00f3n Pedro de Valdivia",
    "tgn:placetype":[
        "aat:300007783"
    ]
},
  "bbox": [],
  "geometry": {"coordinates":[-69.633333,-22.616667],"type":"Point"}
}