{
  "id": 2741710,
  "type": "Feature",
  "properties": {
    "tgn:hierarchy":[
        "tgn:2741710",
        "tgn:1000001",
        "tgn:7012149",
        "tgn:2000210",
        "tgn:7007158",
        "tgn:7029392"
    ],
    "tgn:id":2741710,
    "tgn:name":"Ute Spring Reservoir",
    "tgn:placetype":[
        "aat:300006191"
    ]
},
  "bbox": [],
  "geometry": {"coordinates":[-106.6167,39.7167],"type":"Point"}
}