{
  "id": 7458951,
  "type": "Feature",
  "properties": {
    "tgn:hierarchy":[
        "tgn:7458951",
        "tgn:7002444",
        "tgn:1000003",
        "tgn:7019100",
        "tgn:7008591",
        "tgn:7029392"
    ],
    "tgn:id":7458951,
    "tgn:name:en":"Overtown",
    "tgn:placetype":[
        "aat:300008347"
    ]
},
  "bbox": [],
  "geometry": {"coordinates":[-3.916667,55.75],"type":"Point"}
}