{
  "id": 7581636,
  "type": "Feature",
  "properties": {
    "tgn:hierarchy":[
        "tgn:7581636",
        "tgn:1000004",
        "tgn:7000198",
        "tgn:1001882",
        "tgn:7029392"
    ],
    "tgn:id":7581636,
    "tgn:name:en":"Tadri",
    "tgn:placetype":[
        "aat:300008347"
    ]
},
  "bbox": [],
  "geometry": {"coordinates":[74.35,14.516667],"type":"Point"}
}