{
  "id": 2572022,
  "type": "Feature",
  "properties": {
    "tgn:hierarchy":[
        "tgn:2572022",
        "tgn:1000001",
        "tgn:7012149",
        "tgn:1002924",
        "tgn:7007568",
        "tgn:7029392"
    ],
    "tgn:id":2572022,
    "tgn:name":"Paynes Creek",
    "tgn:placetype":[
        "aat:300132316"
    ]
},
  "bbox": [],
  "geometry": {"coordinates":[-72.3167,40.9833],"type":"Point"}
}