{
  "id": 7173623,
  "type": "Feature",
  "properties": {
    "tgn:hierarchy":[
        "tgn:7173623",
        "tgn:1000003",
        "tgn:7003689",
        "tgn:7000084",
        "tgn:7029392"
    ],
    "tgn:id":7173623,
    "tgn:name":"Gro\u00dfobringen",
    "tgn:placetype":[
        "aat:300008347"
    ]
},
  "bbox": [],
  "geometry": {"coordinates":[11.333333,51.033333],"type":"Point"}
}