{
  "id": 1054361,
  "type": "Feature",
  "properties": {
    "tgn:hierarchy":[
        "tgn:1054361",
        "tgn:1000004",
        "tgn:7012922",
        "tgn:7014786",
        "tgn:7029392"
    ],
    "tgn:id":1054361,
    "tgn:name":"Imeni Timir'azeva",
    "tgn:placetype":[
        "aat:300008347"
    ]
},
  "bbox": [],
  "geometry": {"coordinates":[65.5167,53.65],"type":"Point"}
}