{
  "id": 2564323,
  "type": "Feature",
  "properties": {
    "tgn:hierarchy":[
        "tgn:2564323",
        "tgn:1000001",
        "tgn:7012149",
        "tgn:7007712",
        "tgn:7029392"
    ],
    "tgn:id":2564323,
    "tgn:name":"Paces Branch",
    "tgn:placetype":[
        "aat:300008699"
    ]
},
  "bbox": [],
  "geometry": {"coordinates":[-81.85,33.7333],"type":"Point"}
}