{
  "id": 7399912,
  "type": "Feature",
  "properties": {
    "tgn:hierarchy":[
        "tgn:7399912",
        "tgn:1000001",
        "tgn:7005593",
        "tgn:7005560",
        "tgn:7029392"
    ],
    "tgn:id":7399912,
    "tgn:name":"Puerto Hondo",
    "tgn:placetype":[
        "aat:300008347"
    ]
},
  "bbox": [],
  "geometry": {"coordinates":[-99.772222,21.180556],"type":"Point"}
}