{
  "id": 7341159,
  "type": "Feature",
  "properties": {
    "tgn:hierarchy":[
        "tgn:7341159",
        "tgn:7002820",
        "tgn:7030216",
        "tgn:1000003",
        "tgn:1000095",
        "tgn:7029392"
    ],
    "tgn:id":7341159,
    "tgn:name":"Brugent, R\u00edo",
    "tgn:placetype":[
        "aat:300008699"
    ]
},
  "bbox": [],
  "geometry": {"coordinates":[2.615097,41.988044],"type":"Point"}
}