{
  "id": 1078667,
  "type": "Feature",
  "properties": {
    "tgn:hierarchy":[
        "tgn:1078667",
        "tgn:1000004",
        "tgn:1001554",
        "tgn:1000116",
        "tgn:7029392"
    ],
    "tgn:id":1078667,
    "tgn:name":"Surulangun",
    "tgn:placetype":[
        "aat:300008347"
    ]
},
  "bbox": [],
  "geometry": {"coordinates":[102.7833,-2.5833],"type":"Point"}
}