{
  "id": 7344825,
  "type": "Feature",
  "properties": {
    "tgn:hierarchy":[
        "tgn:7344825",
        "tgn:7002826",
        "tgn:7001158",
        "tgn:1000003",
        "tgn:1000095",
        "tgn:7029392"
    ],
    "tgn:id":7344825,
    "tgn:name":"Ambasaguas",
    "tgn:placetype":[
        "aat:300008347"
    ]
},
  "bbox": [],
  "geometry": {"coordinates":[-6.55,42.266667],"type":"Point"}
}