<<<<<<< HEAD
{
  "id": 2158288,
  "type": "Feature",
  "properties": {
    "tgn:hierarchy":[
        "tgn:2158288",
        "tgn:1000001",
        "tgn:2001429",
        "tgn:7012149",
        "tgn:7007566",
        "tgn:7029392"
    ],
    "tgn:id":2158288,
    "tgn:name":"Beaver Spring",
    "tgn:placetype":[
        "aat:300008697"
    ]
},
  "bbox": [],
  "geometry": {"coordinates":[-108.9,33.45],"type":"Point"}
}
=======
{"geometry":{"type":"Point","coordinates":[-108.900000,33.450000]},"type":"Feature","properties":{"hierarchy":["tgn:2158288","tgn:1000001","tgn:2001429","tgn:7012149","tgn:7007566","tgn:7029392"],"placetype":["aat:300008697"],"id":2158288,"name:xx":"Beaver Spring"}}
>>>>>>> 03f74aca74312dbeaf24d7e61306dd6a786dc3d0
