{
  "id": 2685590,
  "type": "Feature",
  "properties": {
    "tgn:hierarchy":[
        "tgn:2685590",
        "tgn:1000001",
        "tgn:7012149",
        "tgn:2001692",
        "tgn:7007707",
        "tgn:7029392"
    ],
    "tgn:id":2685590,
    "tgn:name":"Spring Aroa Creek",
    "tgn:placetype":[
        "aat:300008706"
    ]
},
  "bbox": [],
  "geometry": {"coordinates":[-101.8333,36.7333],"type":"Point"}
}