{
  "id": 2269589,
  "type": "Feature",
  "properties": {
    "tgn:hierarchy":[
        "tgn:2269589",
        "tgn:1000001",
        "tgn:7012149",
        "tgn:2001277",
        "tgn:7007524",
        "tgn:7029392"
    ],
    "tgn:id":2269589,
    "tgn:name":"Crowfeet Mountain",
    "tgn:placetype":[
        "aat:300008798"
    ]
},
  "bbox": [],
  "geometry": {"coordinates":[-113.6833,48.8333],"type":"Point"}
}