<<<<<<< HEAD
{
  "id": 7021752,
  "type": "Feature",
  "properties": {
    "tgn:hierarchy":[
        "tgn:7021752",
        "tgn:1000001",
        "tgn:7012149",
        "tgn:2001756",
        "tgn:7007712",
        "tgn:7029392"
    ],
    "tgn:id":7021752,
    "tgn:name":"Old Rowe Pond",
    "tgn:placetype":[
        "aat:300006191"
    ]
},
  "bbox": [],
  "geometry": {"coordinates":[-81.4833,33.8],"type":"Point"}
}
=======
{"geometry":{"type":"Point","coordinates":[-81.483300,33.800000]},"type":"Feature","properties":{"hierarchy":["tgn:7021752","tgn:1000001","tgn:7012149","tgn:2001756","tgn:7007712","tgn:7029392"],"placetype":["aat:300006191"],"id":7021752,"name:xx":"Old Rowe Pond"}}
>>>>>>> 03f74aca74312dbeaf24d7e61306dd6a786dc3d0
