{
  "id": 7382823,
  "type": "Feature",
  "properties": {
    "tgn:hierarchy":[
        "tgn:7382823",
        "tgn:1000001",
        "tgn:7005597",
        "tgn:7005560",
        "tgn:7029392"
    ],
    "tgn:id":7382823,
    "tgn:name":"Palos Blancos",
    "tgn:placetype":[
        "aat:300008347"
    ]
},
  "bbox": [],
  "geometry": {"coordinates":[-97.666667,25.583333],"type":"Point"}
}