{
  "id": 2422083,
  "type": "Feature",
  "properties": {
    "tgn:hierarchy":[
        "tgn:2422083",
        "tgn:1000001",
        "tgn:7012149",
        "tgn:2000926",
        "tgn:7007515",
        "tgn:7029392"
    ],
    "tgn:id":2422083,
    "tgn:name":"Jim Hill",
    "tgn:placetype":[
        "aat:300008798"
    ]
},
  "bbox": [],
  "geometry": {"coordinates":[-70.6167,44.2167],"type":"Point"}
}