{
  "id": 2077511,
  "type": "Feature",
  "properties": {
    "tgn:hierarchy":[
        "tgn:2077511",
        "tgn:2001563",
        "tgn:1000001",
        "tgn:7012149",
        "tgn:7007705",
        "tgn:7029392"
    ],
    "tgn:id":2077511,
    "tgn:name":"Coteau",
    "tgn:placetype":[
        "aat:300008347"
    ]
},
  "bbox": [],
  "geometry": {"coordinates":[-102.3167,48.75],"type":"Point"}
}