<<<<<<< HEAD
{
  "id": 2155206,
  "type": "Feature",
  "properties": {
    "tgn:hierarchy":[
        "tgn:2155206",
        "tgn:7006450",
        "tgn:1000001",
        "tgn:7012149",
        "tgn:2124002",
        "tgn:7029392"
    ],
    "tgn:id":2155206,
    "tgn:name":"Bear Mountain",
    "tgn:placetype":[
        "aat:300008798"
    ]
},
  "bbox": [],
  "geometry": {"coordinates":[-135.15,57.05],"type":"Point"}
}
=======
{"geometry":{"type":"Point","coordinates":[-135.150000,57.050000]},"type":"Feature","properties":{"hierarchy":["tgn:2155206","tgn:7006450","tgn:1000001","tgn:7012149","tgn:2124002","tgn:7029392"],"placetype":["aat:300008798"],"id":2155206,"name:xx":"Bear Mountain"}}
>>>>>>> 03f74aca74312dbeaf24d7e61306dd6a786dc3d0
