{
  "id": 7538654,
  "type": "Feature",
  "properties": {
    "tgn:hierarchy":[
        "tgn:7538654",
        "tgn:7001242",
        "tgn:7016833",
        "tgn:7001334",
        "tgn:7029392"
    ],
    "tgn:id":7538654,
    "tgn:name:en":"Mujall\u012b Qibl\u012byah",
    "tgn:placetype":[
        "aat:300008777"
    ]
},
  "bbox": [],
  "geometry": {"coordinates":[30.369796,26.583456],"type":"Point"}
}