{
  "id": 1022786,
  "type": "Feature",
  "properties": {
    "tgn:hierarchy":[
        "tgn:1022786",
        "tgn:7006252",
        "tgn:1000047",
        "tgn:7002455",
        "tgn:1000002",
        "tgn:7029392"
    ],
    "tgn:id":1022786,
    "tgn:name":"S\u00e3o Francisco do Piau\u00ed",
    "tgn:placetype":[
        "aat:300008347"
    ]
},
  "bbox": [],
  "geometry": {"coordinates":[-42.5333,-7.25],"type":"Point"}
}