<<<<<<< HEAD
{
  "id": 2767818,
  "type": "Feature",
  "properties": {
    "tgn:hierarchy":[
        "tgn:2767818",
        "tgn:1000001",
        "tgn:7012149",
        "tgn:2001714",
        "tgn:7007708",
        "tgn:7029392"
    ],
    "tgn:id":2767818,
    "tgn:name":"Whitehorse Creek",
    "tgn:placetype":[
        "aat:300008706"
    ]
},
  "bbox": [],
  "geometry": {"coordinates":[-122.2,42.8667],"type":"Point"}
}
=======
{"geometry":{"type":"Point","coordinates":[-122.200000,42.866700]},"type":"Feature","properties":{"hierarchy":["tgn:2767818","tgn:1000001","tgn:7012149","tgn:2001714","tgn:7007708","tgn:7029392"],"placetype":["aat:300008706"],"id":2767818,"name:xx":"Whitehorse Creek"}}
>>>>>>> 03f74aca74312dbeaf24d7e61306dd6a786dc3d0
