{
  "id": 1075321,
  "type": "Feature",
  "properties": {
    "tgn:hierarchy":[
        "tgn:1075321",
        "tgn:1000004",
        "tgn:7000198",
        "tgn:7016722",
        "tgn:7029392"
    ],
    "tgn:id":1075321,
    "tgn:name:en":"Barhaj",
    "tgn:placetype":[
        "aat:300008347"
    ]
},
  "bbox": [],
  "geometry": {"coordinates":[83.720478,26.27752],"type":"Point"}
}