<<<<<<< HEAD
{
  "id": 7027585,
  "type": "Feature",
  "properties": {
    "tgn:hierarchy":[
        "tgn:7027585",
        "tgn:7002445",
        "tgn:1000003",
        "tgn:7008155",
        "tgn:7008591",
        "tgn:7029392"
    ],
    "tgn:id":7027585,
    "tgn:name":"Harston",
    "tgn:placetype":[
        "aat:300008347",
        "aat:300008372"
    ]
},
  "bbox": [],
  "geometry": {"coordinates":[-0.7667,52.8667],"type":"Point"}
}
=======
{"geometry":{"type":"Point","coordinates":[-0.766700,52.866700]},"type":"Feature","properties":{"hierarchy":["tgn:7027585","tgn:7002445","tgn:1000003","tgn:7008155","tgn:7008591","tgn:7029392"],"placetype":["aat:300008347","aat:300008372"],"id":7027585,"name:xx":"Harston"}}
>>>>>>> 03f74aca74312dbeaf24d7e61306dd6a786dc3d0
