{
  "id": 7331347,
  "type": "Feature",
  "properties": {
    "tgn:hierarchy":[
        "tgn:7331347",
        "tgn:7002827",
        "tgn:1000003",
        "tgn:7002789",
        "tgn:1000095",
        "tgn:7029392"
    ],
    "tgn:id":7331347,
    "tgn:name":"Lacorzana",
    "tgn:placetype":[
        "aat:300008347"
    ]
},
  "bbox": [],
  "geometry": {"coordinates":[-2.883333,42.183333],"type":"Point"}
}