{
  "id": 1128349,
  "type": "Feature",
  "properties": {
    "tgn:hierarchy":[
        "tgn:1128349",
        "tgn:1000001",
        "tgn:7012149",
        "tgn:7007826",
        "tgn:7029392"
    ],
    "tgn:id":1128349,
    "tgn:name":"Paluxy",
    "tgn:placetype":[
        "aat:300008707"
    ]
},
  "bbox": [],
  "geometry": {"coordinates":[-98.0167,32.35],"type":"Point"}
}