{
  "id": 2073738,
  "type": "Feature",
  "properties": {
    "tgn:hierarchy":[
        "tgn:2073738",
        "tgn:1000001",
        "tgn:7013368",
        "tgn:7012149",
        "tgn:7007709",
        "tgn:7029392"
    ],
    "tgn:id":2073738,
    "tgn:name":"Blounts Creek",
    "tgn:placetype":[
        "aat:300008347"
    ]
},
  "bbox": [],
  "geometry": {"coordinates":[-76.95,35.3333],"type":"Point"}
}