{
  "id": 2748203,
  "type": "Feature",
  "properties": {
    "tgn:hierarchy":[
        "tgn:2748203",
        "tgn:1000001",
        "tgn:7012149",
        "tgn:2001869",
        "tgn:7007825",
        "tgn:7029392"
    ],
    "tgn:id":2748203,
    "tgn:name":"Walker Branch",
    "tgn:placetype":[
        "aat:300008699"
    ]
},
  "bbox": [],
  "geometry": {"coordinates":[-85.2167,35.3333],"type":"Point"}
}