{
  "id": 2248544,
  "type": "Feature",
  "properties": {
    "tgn:hierarchy":[
        "tgn:2248544",
        "tgn:1000001",
        "tgn:7006451",
        "tgn:7012149",
        "tgn:2000103",
        "tgn:7029392"
    ],
    "tgn:id":2248544,
    "tgn:name":"Cold Spring Canyon",
    "tgn:placetype":[
        "aat:300008761"
    ]
},
  "bbox": [],
  "geometry": {"coordinates":[-113.15,34.8833],"type":"Point"}
}