{
  "id": 2518846,
  "type": "Feature",
  "properties": {
    "tgn:hierarchy":[
        "tgn:2518846",
        "tgn:1000001",
        "tgn:7012149",
        "tgn:1002368",
        "tgn:7007919",
        "tgn:7029392"
    ],
    "tgn:id":2518846,
    "tgn:name":"Mitchells Branch",
    "tgn:placetype":[
        "aat:300008699"
    ]
},
  "bbox": [],
  "geometry": {"coordinates":[-77.9667,38.8667],"type":"Point"}
}