{
  "id": 7194409,
  "type": "Feature",
  "properties": {
    "tgn:hierarchy":[
        "tgn:7194409",
        "tgn:1000003",
        "tgn:7000094",
        "tgn:7000084",
        "tgn:7029392"
    ],
    "tgn:id":7194409,
    "tgn:name":"Dammwolde",
    "tgn:placetype":[
        "aat:300008347"
    ]
},
  "bbox": [],
  "geometry": {"coordinates":[12.366667,53.333333],"type":"Point"}
}