{
  "id": 7183463,
  "type": "Feature",
  "properties": {
    "tgn:hierarchy":[
        "tgn:7183463",
        "tgn:1000003",
        "tgn:7003682",
        "tgn:7000084",
        "tgn:7029392"
    ],
    "tgn:id":7183463,
    "tgn:name":"Gimmeldingen",
    "tgn:placetype":[
        "aat:300008347"
    ]
},
  "bbox": [],
  "geometry": {"coordinates":[8.153056,49.375278],"type":"Point"}
}