{
  "id": 2572718,
  "type": "Feature",
  "properties": {
    "tgn:hierarchy":[
        "tgn:2572718",
        "tgn:7019618",
        "tgn:1000001",
        "tgn:7012149",
        "tgn:7007564",
        "tgn:7029392"
    ],
    "tgn:id":2572718,
    "tgn:name":"Peaked Mountain",
    "tgn:placetype":[
        "aat:300008798"
    ]
},
  "bbox": [],
  "geometry": {"coordinates":[-72.3333,42.75],"type":"Point"}
}