{
  "id": 7042916,
  "type": "Feature",
  "properties": {
    "tgn:hierarchy":[
        "tgn:7042916",
        "tgn:7003170",
        "tgn:1000003",
        "tgn:7003125",
        "tgn:1000080",
        "tgn:7029392"
    ],
    "tgn:id":7042916,
    "tgn:name":"Rigo, Torrente",
    "tgn:placetype":[
        "aat:300008699"
    ]
},
  "bbox": [],
  "geometry": {"coordinates":[12.266667,42.966667],"type":"Point"}
}