{
  "id": 2190436,
  "type": "Feature",
  "properties": {
    "tgn:hierarchy":[
        "tgn:2190436",
        "tgn:1000001",
        "tgn:2000469",
        "tgn:7012149",
        "tgn:7007250",
        "tgn:7029392"
    ],
    "tgn:id":2190436,
    "tgn:name":"Box Creek",
    "tgn:placetype":[
        "aat:300008706"
    ]
},
  "bbox": [],
  "geometry": {"coordinates":[-114.9833,46.7167],"type":"Point"}
}