<<<<<<< HEAD
{
  "id": 7178037,
  "type": "Feature",
  "properties": {
    "tgn:hierarchy":[
        "tgn:7178037",
        "tgn:7000096",
        "tgn:1000003",
        "tgn:7000084",
        "tgn:7029392"
    ],
    "tgn:id":7178037,
    "tgn:name":"Hainholz",
    "tgn:placetype":[
        "aat:300008863"
    ]
},
  "bbox": [],
  "geometry": {"coordinates":[12.2,53.166667],"type":"Point"}
}
=======
{"geometry":{"type":"Point","coordinates":[12.200000,53.166667]},"type":"Feature","properties":{"hierarchy":["tgn:7178037","tgn:7000096","tgn:1000003","tgn:7000084","tgn:7029392"],"placetype":["aat:300008863"],"id":7178037,"name:xx":"Hainholz"}}
>>>>>>> 03f74aca74312dbeaf24d7e61306dd6a786dc3d0
