{
  "id": 2166824,
  "type": "Feature",
  "properties": {
    "tgn:hierarchy":[
        "tgn:2166824",
        "tgn:1000001",
        "tgn:7012149",
        "tgn:2000981",
        "tgn:7007520",
        "tgn:7029392"
    ],
    "tgn:id":2166824,
    "tgn:name":"Big Brimmer Lake",
    "tgn:placetype":[
        "aat:300008680"
    ]
},
  "bbox": [],
  "geometry": {"coordinates":[-85.2167,43.4167],"type":"Point"}
}