{
  "id": 2480848,
  "type": "Feature",
  "properties": {
    "tgn:hierarchy":[
        "tgn:2480848",
        "tgn:1000001",
        "tgn:7012149",
        "tgn:2001717",
        "tgn:7007708",
        "tgn:7029392"
    ],
    "tgn:id":2480848,
    "tgn:name":"Lakeview Slough",
    "tgn:placetype":[
        "aat:300008699"
    ]
},
  "bbox": [],
  "geometry": {"coordinates":[-122.9333,44.5833],"type":"Point"}
}