{
  "id": 7501210,
  "type": "Feature",
  "properties": {
    "tgn:hierarchy":[
        "tgn:7501210",
        "tgn:1000004",
        "tgn:7467799",
        "tgn:1000141",
        "tgn:7029392"
    ],
    "tgn:id":7501210,
    "tgn:name":"Zhuangwei",
    "tgn:placetype":[
        "aat:300008347"
    ]
},
  "bbox": [],
  "geometry": {"coordinates":[120.491944,24.030556],"type":"Point"}
}