<<<<<<< HEAD
{
  "id": 2254326,
  "type": "Feature",
  "properties": {
    "tgn:hierarchy":[
        "tgn:2254326",
        "tgn:1000001",
        "tgn:7012149",
        "tgn:7007250",
        "tgn:7029392"
    ],
    "tgn:id":2254326,
    "tgn:name":"Coon Creek",
    "tgn:placetype":[
        "aat:300008706"
    ]
},
  "bbox": [],
  "geometry": {"coordinates":[-116.25,43.9667],"type":"Point"}
}
=======
{"geometry":{"type":"Point","coordinates":[-116.250000,43.966700]},"type":"Feature","properties":{"hierarchy":["tgn:2254326","tgn:1000001","tgn:7012149","tgn:7007250","tgn:7029392"],"placetype":["aat:300008706"],"id":2254326,"name:xx":"Coon Creek"}}
>>>>>>> 03f74aca74312dbeaf24d7e61306dd6a786dc3d0
