{
  "id": 2711141,
  "type": "Feature",
  "properties": {
    "tgn:hierarchy":[
        "tgn:2711141",
        "tgn:7006450",
        "tgn:1000001",
        "tgn:2124012",
        "tgn:7012149",
        "tgn:7029392"
    ],
    "tgn:id":2711141,
    "tgn:name":"Tanner Head",
    "tgn:placetype":[
        "aat:300008798"
    ]
},
  "bbox": [],
  "geometry": {"coordinates":[-154.25,56.85],"type":"Point"}
}