{
  "id": 2190313,
  "type": "Feature",
  "properties": {
    "tgn:hierarchy":[
        "tgn:2190313",
        "tgn:1000001",
        "tgn:2000458",
        "tgn:7012149",
        "tgn:7007250",
        "tgn:7029392"
    ],
    "tgn:id":2190313,
    "tgn:name":"Box Canyon",
    "tgn:placetype":[
        "aat:300008761"
    ]
},
  "bbox": [],
  "geometry": {"coordinates":[-114.0667,43.7167],"type":"Point"}
}