<<<<<<< HEAD
{
  "id": 7179251,
  "type": "Feature",
  "properties": {
    "tgn:hierarchy":[
        "tgn:7179251",
        "tgn:7003669",
        "tgn:1000003",
        "tgn:7000084",
        "tgn:7029392"
    ],
    "tgn:id":7179251,
    "tgn:name":"Haberkofen",
    "tgn:placetype":[
        "aat:300008347"
    ]
},
  "bbox": [],
  "geometry": {"coordinates":[12.7,48.816667],"type":"Point"}
}
=======
{"geometry":{"type":"Point","coordinates":[12.700000,48.816667]},"type":"Feature","properties":{"hierarchy":["tgn:7179251","tgn:7003669","tgn:1000003","tgn:7000084","tgn:7029392"],"placetype":["aat:300008347"],"id":7179251,"name:xx":"Haberkofen"}}
>>>>>>> 03f74aca74312dbeaf24d7e61306dd6a786dc3d0
