{
  "id": 2610462,
  "type": "Feature",
  "properties": {
    "tgn:hierarchy":[
        "tgn:2610462",
        "tgn:1000001",
        "tgn:7012149",
        "tgn:2002373",
        "tgn:7007923",
        "tgn:7029392"
    ],
    "tgn:id":2610462,
    "tgn:name":"Red Canyon",
    "tgn:placetype":[
        "aat:300008761"
    ]
},
  "bbox": [],
  "geometry": {"coordinates":[-107.9333,43.5833],"type":"Point"}
}