{
  "id": 2285761,
  "type": "Feature",
  "properties": {
    "tgn:hierarchy":[
        "tgn:2285761",
        "tgn:1000001",
        "tgn:7012149",
        "tgn:2001449",
        "tgn:7007566",
        "tgn:7029392"
    ],
    "tgn:id":2285761,
    "tgn:name":"Devils Mesa",
    "tgn:placetype":[
        "aat:300008798"
    ]
},
  "bbox": [],
  "geometry": {"coordinates":[-107.2333,36.7167],"type":"Point"}
}