{
  "id": 7145229,
  "type": "Feature",
  "properties": {
    "tgn:hierarchy":[
        "tgn:7145229",
        "tgn:7003669",
        "tgn:1000003",
        "tgn:7000084",
        "tgn:7029392"
    ],
    "tgn:id":7145229,
    "tgn:name":"Chostlarn",
    "tgn:placetype":[
        "aat:300008347"
    ]
},
  "bbox": [],
  "geometry": {"coordinates":[13.116667,48.366667],"type":"Point"}
}