{
  "id": 7154311,
  "type": "Feature",
  "properties": {
    "tgn:hierarchy":[
        "tgn:7154311",
        "tgn:7003692",
        "tgn:1000003",
        "tgn:7000084",
        "tgn:7029392"
    ],
    "tgn:id":7154311,
    "tgn:name":"K\u00e4ppele am Hochstr\u00e4ss",
    "tgn:placetype":[
        "aat:300000206"
    ]
},
  "bbox": [],
  "geometry": {"coordinates":[8.666667,48.483333],"type":"Point"}
}