{
  "id": 7545003,
  "type": "Feature",
  "properties": {
    "tgn:hierarchy":[
        "tgn:7545003",
        "tgn:1000004",
        "tgn:7000198",
        "tgn:7016788",
        "tgn:7029392"
    ],
    "tgn:id":7545003,
    "tgn:name:en":"Bhas\u0101war",
    "tgn:placetype":[
        "aat:300008347"
    ]
},
  "bbox": [],
  "geometry": {"coordinates":[77.051836,27.036073],"type":"Point"}
}