{
  "id": 2737582,
  "type": "Feature",
  "properties": {
    "tgn:hierarchy":[
        "tgn:2737582",
        "tgn:1000001",
        "tgn:2000468",
        "tgn:7012149",
        "tgn:7007250",
        "tgn:7029392"
    ],
    "tgn:id":2737582,
    "tgn:name":"Tyler Canyon",
    "tgn:placetype":[
        "aat:300008761"
    ]
},
  "bbox": [],
  "geometry": {"coordinates":[-112.95,43.9833],"type":"Point"}
}