{
  "id": 7014774,
  "type": "Feature",
  "properties": {
    "tgn:hierarchy":[
        "tgn:7014774",
        "tgn:7029392"
    ],
    "tgn:id":7014774,
    "tgn:name":"Mandeb, Bab el",
    "tgn:placetype":[
        "aat:300266559"
    ]
},
  "bbox": [],
  "geometry": {"coordinates":[43.3333,12.6667],"type":"Point"}
}