{
  "id": 7433169,
  "type": "Feature",
  "properties": {
    "tgn:hierarchy":[
        "tgn:7433169",
        "tgn:1000001",
        "tgn:1001960",
        "tgn:7005560",
        "tgn:7029392"
    ],
    "tgn:id":7433169,
    "tgn:name":"Viejito",
    "tgn:placetype":[
        "aat:300387007"
    ]
},
  "bbox": [],
  "geometry": {"coordinates":[-109.866667,28.433333],"type":"Point"}
}