{
  "id": 7421462,
  "type": "Feature",
  "properties": {
    "tgn:hierarchy":[
        "tgn:7421462",
        "tgn:1000001",
        "tgn:7005589",
        "tgn:7005560",
        "tgn:7029392"
    ],
    "tgn:id":7421462,
    "tgn:name:es":"EL Balastre",
    "tgn:placetype":[
        "aat:300008347"
    ]
},
  "bbox": [],
  "geometry": {"coordinates":[-99.224167,25.171667],"type":"Point"}
}