{
  "id": 7089672,
  "type": "Feature",
  "properties": {
    "tgn:hierarchy":[
        "tgn:7089672",
        "tgn:7000096",
        "tgn:1000003",
        "tgn:7000084",
        "tgn:7029392"
    ],
    "tgn:id":7089672,
    "tgn:name":"Wachtel-Berg",
    "tgn:placetype":[
        "aat:300008777"
    ]
},
  "bbox": [],
  "geometry": {"coordinates":[12.733333,52.416667],"type":"Point"}
}