{
  "id": 7064893,
  "type": "Feature",
  "properties": {
    "tgn:hierarchy":[
        "tgn:7064893",
        "tgn:7003669",
        "tgn:1000003",
        "tgn:7000084",
        "tgn:7029392"
    ],
    "tgn:id":7064893,
    "tgn:name":"Stein-Teiche",
    "tgn:placetype":[
        "aat:300008688"
    ]
},
  "bbox": [],
  "geometry": {"coordinates":[12.25,49.933333],"type":"Point"}
}