{
  "id": 2476942,
  "type": "Feature",
  "properties": {
    "tgn:hierarchy":[
        "tgn:2476942",
        "tgn:1000001",
        "tgn:7012149",
        "tgn:1002613",
        "tgn:7007710",
        "tgn:7029392"
    ],
    "tgn:id":2476942,
    "tgn:name":"Lymanwood Hollow",
    "tgn:placetype":[
        "aat:300008761"
    ]
},
  "bbox": [],
  "geometry": {"coordinates":[-77.2833,41.4667],"type":"Point"}
}