{
  "id": 2771236,
  "type": "Feature",
  "properties": {
    "tgn:hierarchy":[
        "tgn:2771236",
        "tgn:1000001",
        "tgn:7006451",
        "tgn:2000093",
        "tgn:7012149",
        "tgn:7029392"
    ],
    "tgn:id":2771236,
    "tgn:name":"Wildcat Spring",
    "tgn:placetype":[
        "aat:300008697"
    ]
},
  "bbox": [],
  "geometry": {"coordinates":[-111.1667,34.2833],"type":"Point"}
}