{
  "id": 7331737,
  "type": "Feature",
  "properties": {
    "tgn:hierarchy":[
        "tgn:7331737",
        "tgn:7002760",
        "tgn:1000003",
        "tgn:1000095",
        "tgn:7029392"
    ],
    "tgn:id":7331737,
    "tgn:name":"La Percebera",
    "tgn:placetype":[
        "aat:300011692"
    ]
},
  "bbox": [],
  "geometry": {"coordinates":[-4.083333,43.433333],"type":"Point"}
}