{
  "id": 2411136,
  "type": "Feature",
  "properties": {
    "tgn:hierarchy":[
        "tgn:2411136",
        "tgn:1000001",
        "tgn:7012149",
        "tgn:2001297",
        "tgn:7007524",
        "tgn:7029392"
    ],
    "tgn:id":2411136,
    "tgn:name":"Indian Creek Reservoir Number One",
    "tgn:placetype":[
        "aat:300006191"
    ]
},
  "bbox": [],
  "geometry": {"coordinates":[-105.9167,45.1833],"type":"Point"}
}