{
  "id": 7568184,
  "type": "Feature",
  "properties": {
    "tgn:hierarchy":[
        "tgn:7568184",
        "tgn:1001828",
        "tgn:1000004",
        "tgn:7000198",
        "tgn:7029392"
    ],
    "tgn:id":7568184,
    "tgn:name:en":"Yapr\u0101l",
    "tgn:placetype":[
        "aat:300008347"
    ]
},
  "bbox": [],
  "geometry": {"coordinates":[78.5425,17.505278],"type":"Point"}
}