{
  "id": 7592174,
  "type": "Feature",
  "properties": {
    "tgn:hierarchy":[
        "tgn:7592174",
        "tgn:1000004",
        "tgn:7000198",
        "tgn:7000799",
        "tgn:7029392"
    ],
    "tgn:id":7592174,
    "tgn:name:en":"Par\u0101ngla",
    "tgn:placetype":[
        "aat:300008347"
    ]
},
  "bbox": [],
  "geometry": {"coordinates":[74.540278,32.8125],"type":"Point"}
}