<<<<<<< HEAD
{
  "id": 7374701,
  "type": "Feature",
  "properties": {
    "tgn:hierarchy":[
        "tgn:7374701",
        "tgn:7005583",
        "tgn:1000001",
        "tgn:7005560",
        "tgn:7029392"
    ],
    "tgn:id":7374701,
    "tgn:name":"La Mesa",
    "tgn:placetype":[
        "aat:300008347"
    ]
},
  "bbox": [],
  "geometry": {"coordinates":[-106.25,25.283333],"type":"Point"}
}
=======
{"geometry":{"type":"Point","coordinates":[-106.250000,25.283333]},"type":"Feature","properties":{"hierarchy":["tgn:7374701","tgn:7005583","tgn:1000001","tgn:7005560","tgn:7029392"],"placetype":["aat:300008347"],"id":7374701,"name:xx":"La Mesa"}}
>>>>>>> 03f74aca74312dbeaf24d7e61306dd6a786dc3d0
