{
  "id": 7539268,
  "type": "Feature",
  "properties": {
    "tgn:hierarchy":[
        "tgn:7539268",
        "tgn:7001242",
        "tgn:7016833",
        "tgn:1001418",
        "tgn:7029392"
    ],
    "tgn:id":7539268,
    "tgn:name:en":"Matruh Reef",
    "tgn:placetype":[
        "aat:300008808"
    ]
},
  "bbox": [],
  "geometry": {"coordinates":[27.233333,31.366667],"type":"Point"}
}