{
  "id": 7069084,
  "type": "Feature",
  "properties": {
    "tgn:hierarchy":[
        "tgn:7069084",
        "tgn:7003669",
        "tgn:1000003",
        "tgn:7000084",
        "tgn:7029392"
    ],
    "tgn:id":7069084,
    "tgn:name":"Steckenhof",
    "tgn:placetype":[
        "aat:300008347"
    ]
},
  "bbox": [],
  "geometry": {"coordinates":[12.666667,49.016667],"type":"Point"}
}