{
  "id": 1091333,
  "type": "Feature",
  "properties": {
    "tgn:hierarchy":[
        "tgn:1091333",
        "tgn:7001242",
        "tgn:1000179",
        "tgn:7593686",
        "tgn:7029392"
    ],
    "tgn:id":1091333,
    "tgn:name":"A\u00eft Melloul",
    "tgn:placetype":[
        "aat:300008347"
    ]
},
  "bbox": [],
  "geometry": {"coordinates":[-9.5167,30.35],"type":"Point"}
}