{
  "id": 7292444,
  "type": "Feature",
  "properties": {
    "tgn:hierarchy":[
        "tgn:7292444",
        "tgn:1001702",
        "tgn:1000049",
        "tgn:1000002",
        "tgn:7029392"
    ],
    "tgn:id":7292444,
    "tgn:name":"Elena, Punta",
    "tgn:placetype":[
        "aat:300386846"
    ]
},
  "bbox": [],
  "geometry": {"coordinates":[-74.516667,-49.033333],"type":"Point"}
}