{
  "id": 7429571,
  "type": "Feature",
  "properties": {
    "tgn:hierarchy":[
        "tgn:7429571",
        "tgn:1001853",
        "tgn:1000001",
        "tgn:7005560",
        "tgn:7029392"
    ],
    "tgn:id":7429571,
    "tgn:name":"Agua Nueva",
    "tgn:placetype":[
        "aat:300008347"
    ]
},
  "bbox": [],
  "geometry": {"coordinates":[-103.183333,25.233333],"type":"Point"}
}