<<<<<<< HEAD
{
  "id": 2336046,
  "type": "Feature",
  "properties": {
    "tgn:hierarchy":[
        "tgn:2336046",
        "tgn:1000001",
        "tgn:7012149",
        "tgn:2001297",
        "tgn:7007524",
        "tgn:7029392"
    ],
    "tgn:id":2336046,
    "tgn:name":"Foster Creek",
    "tgn:placetype":[
        "aat:300008706"
    ]
},
  "bbox": [],
  "geometry": {"coordinates":[-105.2333,45.75],"type":"Point"}
}
=======
{"geometry":{"type":"Point","coordinates":[-105.233300,45.750000]},"type":"Feature","properties":{"hierarchy":["tgn:2336046","tgn:1000001","tgn:7012149","tgn:2001297","tgn:7007524","tgn:7029392"],"placetype":["aat:300008706"],"id":2336046,"name:xx":"Foster Creek"}}
>>>>>>> 03f74aca74312dbeaf24d7e61306dd6a786dc3d0
