{
  "id": 7519170,
  "type": "Feature",
  "properties": {
    "tgn:hierarchy":[
        "tgn:7519170",
        "tgn:1009227",
        "tgn:7001866",
        "tgn:1000226",
        "tgn:1000006",
        "tgn:7029392"
    ],
    "tgn:id":7519170,
    "tgn:name:en":"Anchorage Arm",
    "tgn:placetype":[
        "aat:300132316"
    ]
},
  "bbox": [],
  "geometry": {"coordinates":[166.866667,-45.416667],"type":"Point"}
}