{
  "id": 1050396,
  "type": "Feature",
  "properties": {
    "tgn:hierarchy":[
        "tgn:1050396",
        "tgn:7019094",
        "tgn:7002444",
        "tgn:1000003",
        "tgn:7012161",
        "tgn:7008591",
        "tgn:7029392"
    ],
    "tgn:id":1050396,
    "tgn:name:en":"Arinagour",
    "tgn:placetype":[
        "aat:300008347"
    ]
},
  "bbox": [],
  "geometry": {"coordinates":[-6.516667,56.616667],"type":"Point"}
}