{
  "id": 7412783,
  "type": "Feature",
  "properties": {
    "tgn:hierarchy":[
        "tgn:7412783",
        "tgn:7005580",
        "tgn:1000001",
        "tgn:7005560",
        "tgn:7029392"
    ],
    "tgn:id":7412783,
    "tgn:name":"Nuevo Jatate",
    "tgn:placetype":[
        "aat:300008347"
    ]
},
  "bbox": [],
  "geometry": {"coordinates":[-92.133333,16.783333],"type":"Point"}
}