{
  "id": 7171741,
  "type": "Feature",
  "properties": {
    "tgn:hierarchy":[
        "tgn:7171741",
        "tgn:7003669",
        "tgn:1000003",
        "tgn:7000084",
        "tgn:7029392"
    ],
    "tgn:id":7171741,
    "tgn:name":"Hirsch Bach",
    "tgn:placetype":[
        "aat:300008699"
    ]
},
  "bbox": [],
  "geometry": {"coordinates":[11.566667,47.666667],"type":"Point"}
}