<<<<<<< HEAD
{
  "id": 7171741,
  "type": "Feature",
  "properties": {
    "tgn:hierarchy":[
        "tgn:7171741",
        "tgn:7003669",
        "tgn:1000003",
        "tgn:7000084",
        "tgn:7029392"
    ],
    "tgn:id":7171741,
    "tgn:name":"Hirsch Bach",
    "tgn:placetype":[
        "aat:300008699"
    ]
},
  "bbox": [],
  "geometry": {"coordinates":[11.566667,47.666667],"type":"Point"}
}
=======
{"geometry":{"type":"Point","coordinates":[11.566667,47.666667]},"type":"Feature","properties":{"hierarchy":["tgn:7171741","tgn:7003669","tgn:1000003","tgn:7000084","tgn:7029392"],"placetype":["aat:300008699"],"id":7171741,"name:xx":"Hirsch Bach"}}
>>>>>>> 03f74aca74312dbeaf24d7e61306dd6a786dc3d0
