{
  "id": 7550594,
  "type": "Feature",
  "properties": {
    "tgn:hierarchy":[
        "tgn:7550594",
        "tgn:1000004",
        "tgn:7000198",
        "tgn:1001977",
        "tgn:7029392"
    ],
    "tgn:id":7550594,
    "tgn:name:en":"Dalhousie Point",
    "tgn:placetype":[
        "aat:300386846"
    ]
},
  "bbox": [],
  "geometry": {"coordinates":[88.71698,21.577595],"type":"Point"}
}