{
  "id": 7360552,
  "type": "Feature",
  "properties": {
    "tgn:hierarchy":[
        "tgn:7360552",
        "tgn:1000001",
        "tgn:7005600",
        "tgn:7005560",
        "tgn:7029392"
    ],
    "tgn:id":7360552,
    "tgn:name":"Ebt\u00fan",
    "tgn:placetype":[
        "aat:300008347"
    ]
},
  "bbox": [],
  "geometry": {"coordinates":[-88.25,20.65],"type":"Point"}
}