{
  "id": 2229874,
  "type": "Feature",
  "properties": {
    "tgn:hierarchy":[
        "tgn:2229874",
        "tgn:2002101",
        "tgn:1000001",
        "tgn:7012149",
        "tgn:7007827",
        "tgn:7029392"
    ],
    "tgn:id":2229874,
    "tgn:name":"Cedar Talisman Mine",
    "tgn:placetype":[
        "aat:300000390"
    ]
},
  "bbox": [],
  "geometry": {"coordinates":[-113.1333,38.3667],"type":"Point"}
}