{
  "id": 2139446,
  "type": "Feature",
  "properties": {
    "tgn:hierarchy":[
        "tgn:2139446",
        "tgn:1000001",
        "tgn:7006451",
        "tgn:7012149",
        "tgn:2000099",
        "tgn:7029392"
    ],
    "tgn:id":2139446,
    "tgn:name":"Aspen Wash",
    "tgn:placetype":[
        "aat:300008761"
    ]
},
  "bbox": [],
  "geometry": {"coordinates":[-110.05,36.4333],"type":"Point"}
}