{
  "id": 7552535,
  "type": "Feature",
  "properties": {
    "tgn:hierarchy":[
        "tgn:7552535",
        "tgn:1000004",
        "tgn:7000198",
        "tgn:1001886",
        "tgn:7029392"
    ],
    "tgn:id":7552535,
    "tgn:name:en":"Mann\u0101rakk\u0101t",
    "tgn:placetype":[
        "aat:300008347"
    ]
},
  "bbox": [],
  "geometry": {"coordinates":[76.466667,10.983333],"type":"Point"}
}