{
  "id": 2053210,
  "type": "Feature",
  "properties": {
    "tgn:hierarchy":[
        "tgn:2053210",
        "tgn:1000001",
        "tgn:7012149",
        "tgn:1002406",
        "tgn:7007520",
        "tgn:7029392"
    ],
    "tgn:id":2053210,
    "tgn:name":"Russellville",
    "tgn:placetype":[
        "aat:300008347"
    ]
},
  "bbox": [],
  "geometry": {"coordinates":[-83.55,43.0833],"type":"Point"}
}