{
  "id": 7299626,
  "type": "Feature",
  "properties": {
    "tgn:hierarchy":[
        "tgn:7299626",
        "tgn:1001439",
        "tgn:1000003",
        "tgn:7002797",
        "tgn:1000095",
        "tgn:7029392"
    ],
    "tgn:id":7299626,
    "tgn:name":"Valderas",
    "tgn:placetype":[
        "aat:300008347"
    ]
},
  "bbox": [],
  "geometry": {"coordinates":[-1.033333,37.816667],"type":"Point"}
}