{
  "id": 7175701,
  "type": "Feature",
  "properties": {
    "tgn:hierarchy":[
        "tgn:7175701",
        "tgn:7003669",
        "tgn:1000003",
        "tgn:7000084",
        "tgn:7029392"
    ],
    "tgn:id":7175701,
    "tgn:name":"Gro\u00dfenviecht",
    "tgn:placetype":[
        "aat:300008347"
    ]
},
  "bbox": [],
  "geometry": {"coordinates":[11.816667,48.433333],"type":"Point"}
}