{
  "id": 2386654,
  "type": "Feature",
  "properties": {
    "tgn:hierarchy":[
        "tgn:2386654",
        "tgn:1000001",
        "tgn:7012149",
        "tgn:7016124",
        "tgn:7007240",
        "tgn:7029392"
    ],
    "tgn:id":2386654,
    "tgn:name":"Herman Bay",
    "tgn:placetype":[
        "aat:300132316"
    ]
},
  "bbox": [],
  "geometry": {"coordinates":[-80.2333,27.3333],"type":"Point"}
}