{
  "id": 2541711,
  "type": "Feature",
  "properties": {
    "tgn:hierarchy":[
        "tgn:2541711",
        "tgn:1000001",
        "tgn:2000264",
        "tgn:7012149",
        "tgn:7007240",
        "tgn:7029392"
    ],
    "tgn:id":2541711,
    "tgn:name":"Ninemile Creek",
    "tgn:placetype":[
        "aat:300008706"
    ]
},
  "bbox": [],
  "geometry": {"coordinates":[-81.75,30.3833],"type":"Point"}
}