<<<<<<< HEAD
{
  "id": 7376519,
  "type": "Feature",
  "properties": {
    "tgn:hierarchy":[
        "tgn:7376519",
        "tgn:7005581",
        "tgn:1000001",
        "tgn:7005560",
        "tgn:7029392"
    ],
    "tgn:id":7376519,
    "tgn:name":"Rancho Las Lajas",
    "tgn:placetype":[
        "aat:300000241"
    ]
},
  "bbox": [],
  "geometry": {"coordinates":[-106.6,30.65],"type":"Point"}
}
=======
{"geometry":{"type":"Point","coordinates":[-106.600000,30.650000]},"type":"Feature","properties":{"hierarchy":["tgn:7376519","tgn:7005581","tgn:1000001","tgn:7005560","tgn:7029392"],"placetype":["aat:300000241"],"id":7376519,"name:xx":"Rancho Las Lajas"}}
>>>>>>> 03f74aca74312dbeaf24d7e61306dd6a786dc3d0
