{
  "id": 2340623,
  "type": "Feature",
  "properties": {
    "tgn:hierarchy":[
        "tgn:2340623",
        "tgn:1000001",
        "tgn:7012149",
        "tgn:7018871",
        "tgn:7007920",
        "tgn:7029392"
    ],
    "tgn:id":2340623,
    "tgn:name":"Frenchmans Pond",
    "tgn:placetype":[
        "aat:300008680"
    ]
},
  "bbox": [],
  "geometry": {"coordinates":[-122.4833,47.4333],"type":"Point"}
}