{
  "id": 7168568,
  "type": "Feature",
  "properties": {
    "tgn:hierarchy":[
        "tgn:7168568",
        "tgn:1000003",
        "tgn:7003682",
        "tgn:7000084",
        "tgn:7029392"
    ],
    "tgn:id":7168568,
    "tgn:name":"Hars-Berg",
    "tgn:placetype":[
        "aat:300008777"
    ]
},
  "bbox": [],
  "geometry": {"coordinates":[8.05,49.483333],"type":"Point"}
}