{
  "id": 2683998,
  "type": "Feature",
  "properties": {
    "tgn:hierarchy":[
        "tgn:2683998",
        "tgn:1000001",
        "tgn:7012149",
        "tgn:7007827",
        "tgn:7029392"
    ],
    "tgn:id":2683998,
    "tgn:name":"Spencer Canyon",
    "tgn:placetype":[
        "aat:300008761"
    ]
},
  "bbox": [],
  "geometry": {"coordinates":[-111.5833,39.7833],"type":"Point"}
}