{
  "id": 2630818,
  "type": "Feature",
  "properties": {
    "tgn:hierarchy":[
        "tgn:2630818",
        "tgn:1000001",
        "tgn:7012149",
        "tgn:1002509",
        "tgn:7007520",
        "tgn:7029392"
    ],
    "tgn:id":2630818,
    "tgn:name":"Round Lake",
    "tgn:placetype":[
        "aat:300008680"
    ]
},
  "bbox": [],
  "geometry": {"coordinates":[-84.4667,42.0833],"type":"Point"}
}