{
  "id": 7546369,
  "type": "Feature",
  "properties": {
    "tgn:hierarchy":[
        "tgn:7546369",
        "tgn:1000004",
        "tgn:1001842",
        "tgn:7000198",
        "tgn:7029392"
    ],
    "tgn:id":7546369,
    "tgn:name:en":"Baur\u0101ha",
    "tgn:placetype":[
        "aat:300008347"
    ]
},
  "bbox": [],
  "geometry": {"coordinates":[86.266667,26.566667],"type":"Point"}
}