{
  "id": 1113171,
  "type": "Feature",
  "properties": {
    "tgn:hierarchy":[
        "tgn:1113171",
        "tgn:1000001",
        "tgn:7012149",
        "tgn:1002733",
        "tgn:7007919",
        "tgn:7029392"
    ],
    "tgn:id":1113171,
    "tgn:name":"Ingram Bay",
    "tgn:placetype":[
        "aat:300132316"
    ]
},
  "bbox": [],
  "geometry": {"coordinates":[-76.2833,37.7833],"type":"Point"}
}