{
  "id": 2154032,
  "type": "Feature",
  "properties": {
    "tgn:hierarchy":[
        "tgn:2154032",
        "tgn:1000001",
        "tgn:7012149",
        "tgn:7007157",
        "tgn:1002608",
        "tgn:7029392"
    ],
    "tgn:id":2154032,
    "tgn:name":"Bear Creek",
    "tgn:placetype":[
        "aat:300008706"
    ]
},
  "bbox": [],
  "geometry": {"coordinates":[-117.8667,34.35],"type":"Point"}
}