<<<<<<< HEAD
{
  "id": 2154032,
  "type": "Feature",
  "properties": {
    "tgn:hierarchy":[
        "tgn:2154032",
        "tgn:1000001",
        "tgn:7012149",
        "tgn:7007157",
        "tgn:1002608",
        "tgn:7029392"
    ],
    "tgn:id":2154032,
    "tgn:name":"Bear Creek",
    "tgn:placetype":[
        "aat:300008706"
    ]
},
  "bbox": [],
  "geometry": {"coordinates":[-117.8667,34.35],"type":"Point"}
}
=======
{"geometry":{"type":"Point","coordinates":[-117.866700,34.350000]},"type":"Feature","properties":{"hierarchy":["tgn:2154032","tgn:1000001","tgn:7012149","tgn:7007157","tgn:1002608","tgn:7029392"],"placetype":["aat:300008706"],"id":2154032,"name:xx":"Bear Creek"}}
>>>>>>> 03f74aca74312dbeaf24d7e61306dd6a786dc3d0
