<<<<<<< HEAD
{
  "id": 7377028,
  "type": "Feature",
  "properties": {
    "tgn:hierarchy":[
        "tgn:7377028",
        "tgn:7005581",
        "tgn:1000001",
        "tgn:7005560",
        "tgn:7029392"
    ],
    "tgn:id":7377028,
    "tgn:name":"La Trompa",
    "tgn:placetype":[
        "aat:300008347"
    ]
},
  "bbox": [],
  "geometry": {"coordinates":[-108.7,27.95],"type":"Point"}
}
=======
{"geometry":{"type":"Point","coordinates":[-108.700000,27.950000]},"type":"Feature","properties":{"hierarchy":["tgn:7377028","tgn:7005581","tgn:1000001","tgn:7005560","tgn:7029392"],"placetype":["aat:300008347"],"id":7377028,"name:xx":"La Trompa"}}
>>>>>>> 03f74aca74312dbeaf24d7e61306dd6a786dc3d0
