{
  "id": 2636865,
  "type": "Feature",
  "properties": {
    "tgn:hierarchy":[
        "tgn:2636865",
        "tgn:1000001",
        "tgn:7006451",
        "tgn:7012149",
        "tgn:2000097",
        "tgn:7029392"
    ],
    "tgn:id":2636865,
    "tgn:name":"Sahara Mobile Home Park",
    "tgn:placetype":[
        "aat:300008347"
    ]
},
  "bbox": [],
  "geometry": {"coordinates":[-112.1333,33.5333],"type":"Point"}
}