{
  "id": 2136256,
  "type": "Feature",
  "properties": {
    "tgn:hierarchy":[
        "tgn:2136256",
        "tgn:1000001",
        "tgn:7012149",
        "tgn:2002371",
        "tgn:7007923",
        "tgn:7029392"
    ],
    "tgn:id":2136256,
    "tgn:name":"Arasta Gulch",
    "tgn:placetype":[
        "aat:300008761"
    ]
},
  "bbox": [],
  "geometry": {"coordinates":[-108.7167,42.5167],"type":"Point"}
}