{
  "id": 7269301,
  "type": "Feature",
  "properties": {
    "tgn:concordances":{
        "gn:id":"2747728"
    },
    "tgn:hierarchy":[
        "tgn:7269301",
        "tgn:1000003",
        "tgn:7003624",
        "tgn:7016845",
        "tgn:7029392"
    ],
    "tgn:id":7269301,
    "tgn:name:nl":"Schadron",
    "tgn:placetype":[
        "aat:300008347"
    ]
},
  "bbox": [],
  "geometry": {"coordinates":[5.65,51.633333],"type":"Point"}
}