{
  "id": 7320034,
  "type": "Feature",
  "properties": {
    "tgn:hierarchy":[
        "tgn:7320034",
        "tgn:1001702",
        "tgn:1000049",
        "tgn:1000002",
        "tgn:7029392"
    ],
    "tgn:id":7320034,
    "tgn:name":"Alegr\u00eda, Puerto",
    "tgn:placetype":[
        "aat:300008678"
    ]
},
  "bbox": [],
  "geometry": {"coordinates":[-71.533333,-54.516667],"type":"Point"}
}