<<<<<<< HEAD
{
  "id": 2766300,
  "type": "Feature",
  "properties": {
    "tgn:hierarchy":[
        "tgn:2766300",
        "tgn:1000001",
        "tgn:7012149",
        "tgn:2001512",
        "tgn:7007709",
        "tgn:7029392"
    ],
    "tgn:id":2766300,
    "tgn:name":"White Marsh Run",
    "tgn:placetype":[
        "aat:300008699"
    ]
},
  "bbox": [],
  "geometry": {"coordinates":[-77.6833,35.3333],"type":"Point"}
}
=======
{"geometry":{"type":"Point","coordinates":[-77.683300,35.333300]},"type":"Feature","properties":{"hierarchy":["tgn:2766300","tgn:1000001","tgn:7012149","tgn:2001512","tgn:7007709","tgn:7029392"],"placetype":["aat:300008699"],"id":2766300,"name:xx":"White Marsh Run"}}
>>>>>>> 03f74aca74312dbeaf24d7e61306dd6a786dc3d0
