{
  "id": 2367774,
  "type": "Feature",
  "properties": {
    "tgn:hierarchy":[
        "tgn:2367774",
        "tgn:1000001",
        "tgn:7012149",
        "tgn:7007157",
        "tgn:7014005",
        "tgn:7029392"
    ],
    "tgn:id":2367774,
    "tgn:name":"Grove Hill",
    "tgn:placetype":[
        "aat:300008798"
    ]
},
  "bbox": [],
  "geometry": {"coordinates":[-122.55,37.9667],"type":"Point"}
}