{
  "id": 2208278,
  "type": "Feature",
  "properties": {
    "tgn:hierarchy":[
        "tgn:2208278",
        "tgn:1000001",
        "tgn:7012149",
        "tgn:7007157",
        "tgn:1002894",
        "tgn:7029392"
    ],
    "tgn:id":2208278,
    "tgn:name":"Burma Summit",
    "tgn:placetype":[
        "aat:300008798"
    ]
},
  "bbox": [],
  "geometry": {"coordinates":[-120.1167,39.6333],"type":"Point"}
}