{
  "id": 2328694,
  "type": "Feature",
  "properties": {
    "tgn:hierarchy":[
        "tgn:2328694",
        "tgn:1000001",
        "tgn:7012149",
        "tgn:2000227",
        "tgn:7007158",
        "tgn:7029392"
    ],
    "tgn:id":2328694,
    "tgn:name":"Fishers Peak Mesa",
    "tgn:placetype":[
        "aat:300008798"
    ]
},
  "bbox": [],
  "geometry": {"coordinates":[-104.4333,37.0667],"type":"Point"}
}