{
  "id": 2227630,
  "type": "Feature",
  "properties": {
    "tgn:hierarchy":[
        "tgn:2227630",
        "tgn:1000001",
        "tgn:1002213",
        "tgn:7012149",
        "tgn:7007710",
        "tgn:7029392"
    ],
    "tgn:id":2227630,
    "tgn:name":"Cavey Hollow Cave",
    "tgn:placetype":[
        "aat:300008746"
    ]
},
  "bbox": [],
  "geometry": {"coordinates":[-74.95,40.2667],"type":"Point"}
}