{
  "id": 2643800,
  "type": "Feature",
  "properties": {
    "tgn:hierarchy":[
        "tgn:2643800",
        "tgn:1000001",
        "tgn:1002328",
        "tgn:7012149",
        "tgn:7007568",
        "tgn:7029392"
    ],
    "tgn:id":2643800,
    "tgn:name":"Sanford Hollow",
    "tgn:placetype":[
        "aat:300008761"
    ]
},
  "bbox": [],
  "geometry": {"coordinates":[-74.7167,42.2333],"type":"Point"}
}