{
  "id": 2197756,
  "type": "Feature",
  "properties": {
    "tgn:hierarchy":[
        "tgn:2197756",
        "tgn:1000001",
        "tgn:7012149",
        "tgn:2000346",
        "tgn:7007248",
        "tgn:7029392"
    ],
    "tgn:id":2197756,
    "tgn:name":"Brown Mill",
    "tgn:placetype":[
        "aat:300008347"
    ]
},
  "bbox": [],
  "geometry": {"coordinates":[-84.2333,34.9167],"type":"Point"}
}