{
  "id": 7307367,
  "type": "Feature",
  "properties": {
    "tgn:hierarchy":[
        "tgn:7307367",
        "tgn:7002758",
        "tgn:7002821",
        "tgn:1000003",
        "tgn:1000095",
        "tgn:7029392"
    ],
    "tgn:id":7307367,
    "tgn:name":"Madre, Arroyo de la",
    "tgn:placetype":[
        "aat:300008699"
    ]
},
  "bbox": [],
  "geometry": {"coordinates":[-4.15,36.983333],"type":"Point"}
}