{
  "id": 1095829,
  "type": "Feature",
  "properties": {
    "tgn:hierarchy":[
        "tgn:1095829",
        "tgn:7024147",
        "tgn:7001242",
        "tgn:1000604",
        "tgn:1000208",
        "tgn:7029392"
    ],
    "tgn:id":1095829,
    "tgn:name":"Madjoari",
    "tgn:placetype":[
        "aat:300008347"
    ]
},
  "bbox": [],
  "geometry": {"coordinates":[1.25,11.4333],"type":"Point"}
}