{
  "id": 2098543,
  "type": "Feature",
  "properties": {
    "tgn:hierarchy":[
        "tgn:2098543",
        "tgn:1000001",
        "tgn:7012149",
        "tgn:2001916",
        "tgn:7007825",
        "tgn:7029392"
    ],
    "tgn:id":2098543,
    "tgn:name":"Club Springs",
    "tgn:placetype":[
        "aat:300008347",
        "aat:300387210"
    ]
},
  "bbox": [],
  "geometry": {"coordinates":[-85.85,36.15],"type":"Point"}
}