{
  "id": 7087475,
  "type": "Feature",
  "properties": {
    "tgn:hierarchy":[
        "tgn:7087475",
        "tgn:1000003",
        "tgn:7003682",
        "tgn:7000084",
        "tgn:7029392"
    ],
    "tgn:id":7087475,
    "tgn:name":"W\u00e4ldchen",
    "tgn:placetype":[
        "aat:300000206"
    ]
},
  "bbox": [],
  "geometry": {"coordinates":[7.65,50.816667],"type":"Point"}
}