{
  "id": 7589666,
  "type": "Feature",
  "properties": {
    "tgn:hierarchy":[
        "tgn:7589666",
        "tgn:1000004",
        "tgn:7000198",
        "tgn:7000799",
        "tgn:7029392"
    ],
    "tgn:id":7589666,
    "tgn:name:en":"Sardan N\u0101la",
    "tgn:placetype":[
        "aat:300008699"
    ]
},
  "bbox": [],
  "geometry": {"coordinates":[74.966667,32.776389],"type":"Point"}
}