{
  "id": 2481252,
  "type": "Feature",
  "properties": {
    "tgn:hierarchy":[
        "tgn:2481252",
        "tgn:1000001",
        "tgn:7012149",
        "tgn:2000227",
        "tgn:7007158",
        "tgn:7029392"
    ],
    "tgn:id":2481252,
    "tgn:name":"Lambert Reservoir",
    "tgn:placetype":[
        "aat:300006191"
    ]
},
  "bbox": [],
  "geometry": {"coordinates":[-104.4333,37.75],"type":"Point"}
}