{
  "id": 2546646,
  "type": "Feature",
  "properties": {
    "tgn:hierarchy":[
        "tgn:2546646",
        "tgn:1000001",
        "tgn:2000780",
        "tgn:7012149",
        "tgn:7007255",
        "tgn:7029392"
    ],
    "tgn:id":2546646,
    "tgn:name":"North Fork Little River",
    "tgn:placetype":[
        "aat:300008707"
    ]
},
  "bbox": [],
  "geometry": {"coordinates":[-87.45,36.8833],"type":"Point"}
}