{
  "id": 2040567,
  "type": "Feature",
  "properties": {
    "tgn:hierarchy":[
        "tgn:2040567",
        "tgn:1000001",
        "tgn:7012149",
        "tgn:2000808",
        "tgn:7007255",
        "tgn:7029392"
    ],
    "tgn:id":2040567,
    "tgn:name":"Oakley",
    "tgn:placetype":[
        "aat:300008347",
        "aat:300387210"
    ]
},
  "bbox": [],
  "geometry": {"coordinates":[-84.0833,37.2333],"type":"Point"}
}