{
  "id": 7276611,
  "type": "Feature",
  "properties": {
    "tgn:hierarchy":[
        "tgn:7276611",
        "tgn:1001699",
        "tgn:1000049",
        "tgn:1000002",
        "tgn:7029392"
    ],
    "tgn:id":7276611,
    "tgn:name":"Sorpresa, Caleta",
    "tgn:placetype":[
        "aat:300132317"
    ]
},
  "bbox": [],
  "geometry": {"coordinates":[-73.170833,-44.028333],"type":"Point"}
}