{
  "id": 7495517,
  "type": "Feature",
  "properties": {
    "tgn:hierarchy":[
        "tgn:7495517",
        "tgn:7468018",
        "tgn:1000004",
        "tgn:1000141",
        "tgn:7029392"
    ],
    "tgn:id":7495517,
    "tgn:name":"Jiulong Shan",
    "tgn:placetype":[
        "aat:300008798"
    ]
},
  "bbox": [],
  "geometry": {"coordinates":[120.533314,23.32175],"type":"Point"}
}