{
  "id": 2229764,
  "type": "Feature",
  "properties": {
    "tgn:hierarchy":[
        "tgn:2229764",
        "tgn:1000001",
        "tgn:7012149",
        "tgn:2002190",
        "tgn:7007919",
        "tgn:7029392"
    ],
    "tgn:id":2229764,
    "tgn:name":"Cedar Spring Run",
    "tgn:placetype":[
        "aat:300008699"
    ]
},
  "bbox": [],
  "geometry": {"coordinates":[-78.3667,39.0167],"type":"Point"}
}