{
  "id": 2038251,
  "type": "Feature",
  "properties": {
    "tgn:hierarchy":[
        "tgn:2038251",
        "tgn:1000001",
        "tgn:2000781",
        "tgn:7012149",
        "tgn:7007255",
        "tgn:7029392"
    ],
    "tgn:id":2038251,
    "tgn:name":"Colby Hills",
    "tgn:placetype":[
        "aat:300008347"
    ]
},
  "bbox": [],
  "geometry": {"coordinates":[-84.1833,37.9833],"type":"Point"}
}