{
  "id": 1024426,
  "type": "Feature",
  "properties": {
    "tgn:hierarchy":[
        "tgn:1024426",
        "tgn:1000670",
        "tgn:1000002",
        "tgn:1000056",
        "tgn:7029392"
    ],
    "tgn:id":1024426,
    "tgn:name":"Cerro Azul",
    "tgn:placetype":[
        "aat:300008347"
    ]
},
  "bbox": [],
  "geometry": {"coordinates":[-76.4833,-13.0833],"type":"Point"}
}