{
  "id": 7398344,
  "type": "Feature",
  "properties": {
    "tgn:hierarchy":[
        "tgn:7398344",
        "tgn:1000001",
        "tgn:1001960",
        "tgn:7005560",
        "tgn:7029392"
    ],
    "tgn:id":7398344,
    "tgn:name":"El Tecolote, Ca\u00f1ada",
    "tgn:placetype":[
        "aat:300008773"
    ]
},
  "bbox": [],
  "geometry": {"coordinates":[-111.0225,30.986944],"type":"Point"}
}