<<<<<<< HEAD
{
  "id": 2256904,
  "type": "Feature",
  "properties": {
    "tgn:hierarchy":[
        "tgn:2256904",
        "tgn:1000001",
        "tgn:7013677",
        "tgn:7012149",
        "tgn:7007712",
        "tgn:7029392"
    ],
    "tgn:id":2256904,
    "tgn:name":"Corley Pond",
    "tgn:placetype":[
        "aat:300006191"
    ]
},
  "bbox": [],
  "geometry": {"coordinates":[-82.1,33.9167],"type":"Point"}
}
=======
{"geometry":{"type":"Point","coordinates":[-82.100000,33.916700]},"type":"Feature","properties":{"hierarchy":["tgn:2256904","tgn:1000001","tgn:7013677","tgn:7012149","tgn:7007712","tgn:7029392"],"placetype":["aat:300006191"],"id":2256904,"name:xx":"Corley Pond"}}
>>>>>>> 03f74aca74312dbeaf24d7e61306dd6a786dc3d0
