{
  "id": 7120069,
  "type": "Feature",
  "properties": {
    "tgn:hierarchy":[
        "tgn:7120069",
        "tgn:7003669",
        "tgn:1000003",
        "tgn:7000084",
        "tgn:7029392"
    ],
    "tgn:id":7120069,
    "tgn:name":"Pfeifferh\u00fctte",
    "tgn:placetype":[
        "aat:300008347"
    ]
},
  "bbox": [],
  "geometry": {"coordinates":[11.316667,49.333333],"type":"Point"}
}