{
  "id": 7540612,
  "type": "Feature",
  "properties": {
    "tgn:hierarchy":[
        "tgn:7540612",
        "tgn:7001242",
        "tgn:7016833",
        "tgn:7001335",
        "tgn:7029392"
    ],
    "tgn:id":7540612,
    "tgn:name:en":"Sheikh, Sabkhet el-",
    "tgn:placetype":[
        "aat:300386999"
    ]
},
  "bbox": [],
  "geometry": {"coordinates":[34.082383,31.21818],"type":"Point"}
}