{
  "id": 1096659,
  "type": "Feature",
  "properties": {
    "tgn:hierarchy":[
        "tgn:1096659",
        "tgn:7000490",
        "tgn:1000006",
        "tgn:7001831",
        "tgn:7029392"
    ],
    "tgn:id":1096659,
    "tgn:name":"Coward Springs",
    "tgn:placetype":[
        "aat:300008347"
    ]
},
  "bbox": [],
  "geometry": {"coordinates":[136.8167,-29.4167],"type":"Point"}
}