{
  "id": 2476586,
  "type": "Feature",
  "properties": {
    "tgn:hierarchy":[
        "tgn:2476586",
        "tgn:1000001",
        "tgn:1002270",
        "tgn:7012149",
        "tgn:7007708",
        "tgn:7029392"
    ],
    "tgn:id":2476586,
    "tgn:name":"Luther",
    "tgn:placetype":[
        "aat:300008347"
    ]
},
  "bbox": [],
  "geometry": {"coordinates":[-122.5833,45.45],"type":"Point"}
}