{
  "id": 2382857,
  "type": "Feature",
  "properties": {
    "tgn:hierarchy":[
        "tgn:2382857",
        "tgn:1000001",
        "tgn:2001008",
        "tgn:7012149",
        "tgn:7007521",
        "tgn:7029392"
    ],
    "tgn:id":2382857,
    "tgn:name":"Hazelton",
    "tgn:placetype":[
        "aat:300008347"
    ]
},
  "bbox": [],
  "geometry": {"coordinates":[-93.95,44.95],"type":"Point"}
}