{
  "id": 7581365,
  "type": "Feature",
  "properties": {
    "tgn:hierarchy":[
        "tgn:7581365",
        "tgn:1000004",
        "tgn:7000198",
        "tgn:7000799",
        "tgn:7029392"
    ],
    "tgn:id":7581365,
    "tgn:name:en":"Suru\u012bn",
    "tgn:placetype":[
        "aat:300008347"
    ]
},
  "bbox": [],
  "geometry": {"coordinates":[75.049845,32.767166],"type":"Point"}
}