{
  "id": 2778247,
  "type": "Feature",
  "properties": {
    "tgn:hierarchy":[
        "tgn:2778247",
        "tgn:1000001",
        "tgn:7012149",
        "tgn:2000893",
        "tgn:7007256",
        "tgn:7029392"
    ],
    "tgn:id":2778247,
    "tgn:name":"Wises",
    "tgn:placetype":[
        "aat:300008347"
    ]
},
  "bbox": [],
  "geometry": {"coordinates":[-92.3333,31.2333],"type":"Point"}
}