{
  "id": 2089147,
  "type": "Feature",
  "properties": {
    "tgn:hierarchy":[
        "tgn:2089147",
        "tgn:1000001",
        "tgn:7012149",
        "tgn:1002876",
        "tgn:7007710",
        "tgn:7029392"
    ],
    "tgn:id":2089147,
    "tgn:name":"Haucks",
    "tgn:placetype":[
        "aat:300387016"
    ]
},
  "bbox": [],
  "geometry": {"coordinates":[-76.0333,40.8167],"type":"Point"}
}