{
  "id": 2434901,
  "type": "Feature",
  "properties": {
    "tgn:hierarchy":[
        "tgn:2434901",
        "tgn:1000001",
        "tgn:7012149",
        "tgn:1003017",
        "tgn:7007710",
        "tgn:7029392"
    ],
    "tgn:id":2434901,
    "tgn:name":"Kens Cave",
    "tgn:placetype":[
        "aat:300008746"
    ]
},
  "bbox": [],
  "geometry": {"coordinates":[-79.2333,40.3667],"type":"Point"}
}