{
  "id": 2772127,
  "type": "Feature",
  "properties": {
    "tgn:hierarchy":[
        "tgn:2772127",
        "tgn:1000001",
        "tgn:7006451",
        "tgn:2000092",
        "tgn:7012149",
        "tgn:7029392"
    ],
    "tgn:id":2772127,
    "tgn:name":"Willaha",
    "tgn:placetype":[
        "aat:300008347"
    ]
},
  "bbox": [],
  "geometry": {"coordinates":[-112.25,35.75],"type":"Point"}
}