{
  "id": 2224828,
  "type": "Feature",
  "properties": {
    "tgn:hierarchy":[
        "tgn:2224828",
        "tgn:1000001",
        "tgn:7012149",
        "tgn:7007157",
        "tgn:2000185",
        "tgn:7029392"
    ],
    "tgn:id":2224828,
    "tgn:name":"Caspar Anchorage",
    "tgn:placetype":[
        "aat:300132316"
    ]
},
  "bbox": [],
  "geometry": {"coordinates":[-123.8167,39.35],"type":"Point"}
}