{
  "id": 7329615,
  "type": "Feature",
  "properties": {
    "tgn:hierarchy":[
        "tgn:7329615",
        "tgn:7002824",
        "tgn:1000003",
        "tgn:7002786",
        "tgn:1000095",
        "tgn:7029392"
    ],
    "tgn:id":7329615,
    "tgn:name":"Raso, Playa de",
    "tgn:placetype":[
        "aat:300008816"
    ]
},
  "bbox": [],
  "geometry": {"coordinates":[-8.216667,43.433333],"type":"Point"}
}