{
  "id": 2261499,
  "type": "Feature",
  "properties": {
    "tgn:hierarchy":[
        "tgn:2261499",
        "tgn:2002239",
        "tgn:1000001",
        "tgn:7012149",
        "tgn:7007920",
        "tgn:7029392"
    ],
    "tgn:id":2261499,
    "tgn:name":"Couse Creek",
    "tgn:placetype":[
        "aat:300008706"
    ]
},
  "bbox": [],
  "geometry": {"coordinates":[-117.0667,46.0833],"type":"Point"}
}