{
  "id": 7002769,
  "type": "Feature",
  "properties": {
    "tgn:hierarchy":[
        "tgn:7002769",
        "tgn:1001256",
        "tgn:1000004",
        "tgn:7018454",
        "tgn:1000144",
        "tgn:7029392"
    ],
    "tgn:id":7002769,
    "tgn:name":"Soganli Gecidi",
    "tgn:placetype":[
        "aat:300259572"
    ]
},
  "bbox": [],
  "geometry": {"coordinates":[40.2667,40.55],"type":"Point"}
}