{
  "id": 2380774,
  "type": "Feature",
  "properties": {
    "tgn:hierarchy":[
        "tgn:2380774",
        "tgn:1000001",
        "tgn:2002102",
        "tgn:7012149",
        "tgn:7007827",
        "tgn:7029392"
    ],
    "tgn:id":2380774,
    "tgn:name":"Hawbush Spring",
    "tgn:placetype":[
        "aat:300008697"
    ]
},
  "bbox": [],
  "geometry": {"coordinates":[-112.0833,41.7167],"type":"Point"}
}