{
  "id": 7559797,
  "type": "Feature",
  "properties": {
    "tgn:hierarchy":[
        "tgn:7559797",
        "tgn:1000004",
        "tgn:7000198",
        "tgn:7016722",
        "tgn:7029392"
    ],
    "tgn:id":7559797,
    "tgn:name:en":"Sikandarpur",
    "tgn:placetype":[
        "aat:300008347"
    ]
},
  "bbox": [],
  "geometry": {"coordinates":[79.679518,27.715],"type":"Point"}
}