{
  "id": 2785616,
  "type": "Feature",
  "properties": {
    "tgn:hierarchy":[
        "tgn:2785616",
        "tgn:1000001",
        "tgn:7012149",
        "tgn:1002904",
        "tgn:7007710",
        "tgn:7029392"
    ],
    "tgn:id":2785616,
    "tgn:name":"Yoders Pond",
    "tgn:placetype":[
        "aat:300006191"
    ]
},
  "bbox": [],
  "geometry": {"coordinates":[-79.1333,39.7333],"type":"Point"}
}