{
  "id": 2158672,
  "type": "Feature",
  "properties": {
    "tgn:hierarchy":[
        "tgn:2158672",
        "tgn:1000001",
        "tgn:2001702",
        "tgn:7012149",
        "tgn:7007708",
        "tgn:7029392"
    ],
    "tgn:id":2158672,
    "tgn:name":"Beaverton",
    "tgn:placetype":[
        "aat:300008347"
    ]
},
  "bbox": [],
  "geometry": {"coordinates":[-124.2667,43.2167],"type":"Point"}
}