<<<<<<< HEAD
{
  "id": 2158672,
  "type": "Feature",
  "properties": {
    "tgn:hierarchy":[
        "tgn:2158672",
        "tgn:1000001",
        "tgn:2001702",
        "tgn:7012149",
        "tgn:7007708",
        "tgn:7029392"
    ],
    "tgn:id":2158672,
    "tgn:name":"Beaverton",
    "tgn:placetype":[
        "aat:300008347"
    ]
},
  "bbox": [],
  "geometry": {"coordinates":[-124.2667,43.2167],"type":"Point"}
}
=======
{"geometry":{"type":"Point","coordinates":[-124.266700,43.216700]},"type":"Feature","properties":{"hierarchy":["tgn:2158672","tgn:1000001","tgn:2001702","tgn:7012149","tgn:7007708","tgn:7029392"],"placetype":["aat:300008347"],"id":2158672,"name:xx":"Beaverton"}}
>>>>>>> 03f74aca74312dbeaf24d7e61306dd6a786dc3d0
