<<<<<<< HEAD
{
  "id": 2251609,
  "type": "Feature",
  "properties": {
    "tgn:hierarchy":[
        "tgn:2251609",
        "tgn:1000001",
        "tgn:2002368",
        "tgn:7012149",
        "tgn:7007923",
        "tgn:7029392"
    ],
    "tgn:id":2251609,
    "tgn:name":"Como Lake",
    "tgn:placetype":[
        "aat:300008680"
    ]
},
  "bbox": [],
  "geometry": {"coordinates":[-106.35,41.9],"type":"Point"}
}
=======
{"geometry":{"type":"Point","coordinates":[-106.350000,41.900000]},"type":"Feature","properties":{"hierarchy":["tgn:2251609","tgn:1000001","tgn:2002368","tgn:7012149","tgn:7007923","tgn:7029392"],"placetype":["aat:300008680"],"id":2251609,"name:xx":"Como Lake"}}
>>>>>>> 03f74aca74312dbeaf24d7e61306dd6a786dc3d0
