{
  "id": 2604440,
  "type": "Feature",
  "properties": {
    "tgn:hierarchy":[
        "tgn:2604440",
        "tgn:1000001",
        "tgn:7012149",
        "tgn:7007157",
        "tgn:1002857",
        "tgn:7029392"
    ],
    "tgn:id":2604440,
    "tgn:name":"Rabbit Hole Mine",
    "tgn:placetype":[
        "aat:300000390"
    ]
},
  "bbox": [],
  "geometry": {"coordinates":[-117.5833,34.7167],"type":"Point"}
}