{
  "id": 2676787,
  "type": "Feature",
  "properties": {
    "tgn:hierarchy":[
        "tgn:2676787",
        "tgn:2000919",
        "tgn:1000001",
        "tgn:7012149",
        "tgn:7007515",
        "tgn:7029392"
    ],
    "tgn:id":2676787,
    "tgn:name":"South Branch Caribou Stream",
    "tgn:placetype":[
        "aat:300008699"
    ]
},
  "bbox": [],
  "geometry": {"coordinates":[-68.1167,46.8667],"type":"Point"}
}