{
  "id": 2056787,
  "type": "Feature",
  "properties": {
    "tgn:hierarchy":[
        "tgn:2056787",
        "tgn:1000001",
        "tgn:7012149",
        "tgn:2001115",
        "tgn:7007522",
        "tgn:7029392"
    ],
    "tgn:id":2056787,
    "tgn:name":"Latimer",
    "tgn:placetype":[
        "aat:300008347"
    ]
},
  "bbox": [],
  "geometry": {"coordinates":[-88.8667,30.5333],"type":"Point"}
}