{
  "id": 7485149,
  "type": "Feature",
  "properties": {
    "tgn:hierarchy":[
        "tgn:7485149",
        "tgn:1000004",
        "tgn:7467799",
        "tgn:1000141",
        "tgn:7029392"
    ],
    "tgn:id":7485149,
    "tgn:name":"Tianhou Gong",
    "tgn:placetype":[
        "aat:300007595"
    ]
},
  "bbox": [],
  "geometry": {"coordinates":[120.431667,24.059444],"type":"Point"}
}