{
  "id": 2054584,
  "type": "Feature",
  "properties": {
    "tgn:hierarchy":[
        "tgn:2054584",
        "tgn:1000001",
        "tgn:7012149",
        "tgn:2001067",
        "tgn:7007521",
        "tgn:7029392"
    ],
    "tgn:id":2054584,
    "tgn:name":"Haley",
    "tgn:placetype":[
        "aat:300387016"
    ]
},
  "bbox": [],
  "geometry": {"coordinates":[-92.7167,47.9167],"type":"Point"}
}