<<<<<<< HEAD
{
  "id": 7179116,
  "type": "Feature",
  "properties": {
    "tgn:hierarchy":[
        "tgn:7179116",
        "tgn:1000003",
        "tgn:7003678",
        "tgn:7000084",
        "tgn:7029392"
    ],
    "tgn:id":7179116,
    "tgn:name":"F\u00f6rsterei Hammer",
    "tgn:placetype":[
        "aat:300004792"
    ]
},
  "bbox": [],
  "geometry": {"coordinates":[9.15,51.033333],"type":"Point"}
}
=======
{"geometry":{"type":"Point","coordinates":[9.150000,51.033333]},"type":"Feature","properties":{"hierarchy":["tgn:7179116","tgn:1000003","tgn:7003678","tgn:7000084","tgn:7029392"],"placetype":["aat:300004792"],"id":7179116,"name:xx":"F\u00f6rsterei Hammer"}}
>>>>>>> 03f74aca74312dbeaf24d7e61306dd6a786dc3d0
