{
  "id": 7106635,
  "type": "Feature",
  "properties": {
    "tgn:hierarchy":[
        "tgn:7106635",
        "tgn:1000003",
        "tgn:7003676",
        "tgn:7000084",
        "tgn:7029392"
    ],
    "tgn:id":7106635,
    "tgn:name":"Schlee-Berg",
    "tgn:placetype":[
        "aat:300008777"
    ]
},
  "bbox": [],
  "geometry": {"coordinates":[9.816667,51.966667],"type":"Point"}
}