{
  "id": 1003530,
  "type": "Feature",
  "properties": {
    "tgn:hierarchy":[
        "tgn:1003530",
        "tgn:1000003",
        "tgn:1001780",
        "tgn:7029392"
    ],
    "tgn:id":1003530,
    "tgn:name:cs":"St\u0159edo\u010desk\u00fd",
    "tgn:name:en":"St\u0159edo\u010desk\u00fd",
    "tgn:placetype":[
        "aat:300387064",
        "aat:300236112"
    ]
},
  "bbox": [],
  "geometry": {"coordinates":[14.4167,50.083],"type":"Point"}
}