{
  "id": 7265907,
  "type": "Feature",
  "properties": {
    "tgn:hierarchy":[
        "tgn:7265907",
        "tgn:7003616",
        "tgn:1000003",
        "tgn:7016845",
        "tgn:7029392"
    ],
    "tgn:id":7265907,
    "tgn:name:nl":"Kloosterburen",
    "tgn:placetype":[
        "aat:300008347"
    ]
},
  "bbox": [],
  "geometry": {"coordinates":[5.983333,53.15],"type":"Point"}
}