{
  "id": 7555174,
  "type": "Feature",
  "properties": {
    "tgn:hierarchy":[
        "tgn:7555174",
        "tgn:1000004",
        "tgn:7000198",
        "tgn:7016788",
        "tgn:7029392"
    ],
    "tgn:id":7555174,
    "tgn:name:en":"Osao",
    "tgn:placetype":[
        "aat:300008347"
    ]
},
  "bbox": [],
  "geometry": {"coordinates":[76.058436,24.265501],"type":"Point"}
}