<<<<<<< HEAD
{
  "id": 2406760,
  "type": "Feature",
  "properties": {
    "tgn:hierarchy":[
        "tgn:2406760",
        "tgn:1000001",
        "tgn:2002262",
        "tgn:7012149",
        "tgn:7013961",
        "tgn:7029392"
    ],
    "tgn:id":2406760,
    "tgn:name":"Hunt Road Run",
    "tgn:placetype":[
        "aat:300008699"
    ]
},
  "bbox": [],
  "geometry": {"coordinates":[-80.9167,38.8],"type":"Point"}
}
=======
{"geometry":{"type":"Point","coordinates":[-80.916700,38.800000]},"type":"Feature","properties":{"hierarchy":["tgn:2406760","tgn:1000001","tgn:2002262","tgn:7012149","tgn:7013961","tgn:7029392"],"placetype":["aat:300008699"],"id":2406760,"name:xx":"Hunt Road Run"}}
>>>>>>> 03f74aca74312dbeaf24d7e61306dd6a786dc3d0
