{
  "id": 2781377,
  "type": "Feature",
  "properties": {
    "tgn:hierarchy":[
        "tgn:2781377",
        "tgn:7002659",
        "tgn:1000001",
        "tgn:7012149",
        "tgn:2000051",
        "tgn:7029392"
    ],
    "tgn:id":2781377,
    "tgn:name":"Woodland Mills Creek",
    "tgn:placetype":[
        "aat:300008706"
    ]
},
  "bbox": [],
  "geometry": {"coordinates":[-86.6333,34.4833],"type":"Point"}
}