{
  "id": 1091578,
  "type": "Feature",
  "properties": {
    "tgn:hierarchy":[
        "tgn:1091578",
        "tgn:7001242",
        "tgn:7000400",
        "tgn:1000180",
        "tgn:7029392"
    ],
    "tgn:id":1091578,
    "tgn:name":"Marromeu",
    "tgn:placetype":[
        "aat:300008347"
    ]
},
  "bbox": [],
  "geometry": {"coordinates":[35.9333,-18.3333],"type":"Point"}
}