{
  "id": 7272782,
  "type": "Feature",
  "properties": {
    "tgn:concordances":{
        "gn:id":"2745166"
    },
    "tgn:hierarchy":[
        "tgn:7272782",
        "tgn:1000003",
        "tgn:7006951",
        "tgn:7016845",
        "tgn:7029392"
    ],
    "tgn:id":7272782,
    "tgn:name:nl":"Vrouwenakker",
    "tgn:placetype":[
        "aat:300008347"
    ]
},
  "bbox": [],
  "geometry": {"coordinates":[4.783333,52.233333],"type":"Point"}
}