{
  "id": 7571188,
  "type": "Feature",
  "properties": {
    "tgn:hierarchy":[
        "tgn:7571188",
        "tgn:1000004",
        "tgn:7000198",
        "tgn:7000799",
        "tgn:7029392"
    ],
    "tgn:id":7571188,
    "tgn:name:en":"Harong La",
    "tgn:placetype":[
        "aat:300259572"
    ]
},
  "bbox": [],
  "geometry": {"coordinates":[78.252318,33.931936],"type":"Point"}
}