{
  "id": 7491618,
  "type": "Feature",
  "properties": {
    "tgn:hierarchy":[
        "tgn:7491618",
        "tgn:1000004",
        "tgn:7491221",
        "tgn:1000141",
        "tgn:7029392"
    ],
    "tgn:id":7491618,
    "tgn:name":"Yiwan",
    "tgn:placetype":[
        "aat:300008347"
    ]
},
  "bbox": [],
  "geometry": {"coordinates":[121.398562,23.209246],"type":"Point"}
}