{
  "id": 7067382,
  "type": "Feature",
  "properties": {
    "tgn:hierarchy":[
        "tgn:7067382",
        "tgn:1000003",
        "tgn:7003676",
        "tgn:7000084",
        "tgn:7029392"
    ],
    "tgn:id":7067382,
    "tgn:name":"Stockum",
    "tgn:placetype":[
        "aat:300000206"
    ]
},
  "bbox": [],
  "geometry": {"coordinates":[7.916667,52.533333],"type":"Point"}
}