{
  "id": 2118202,
  "type": "Feature",
  "properties": {
    "tgn:hierarchy":[
        "tgn:2118202",
        "tgn:1000001",
        "tgn:7012149",
        "tgn:2002275",
        "tgn:7013961",
        "tgn:7029392"
    ],
    "tgn:id":2118202,
    "tgn:name":"Fairview",
    "tgn:placetype":[
        "aat:300008347"
    ]
},
  "bbox": [],
  "geometry": {"coordinates":[-80.2333,39.5833],"type":"Point"}
}