<<<<<<< HEAD
{
  "id": 2150727,
  "type": "Feature",
  "properties": {
    "tgn:hierarchy":[
        "tgn:2150727",
        "tgn:1000001",
        "tgn:7012149",
        "tgn:2001056",
        "tgn:7007521",
        "tgn:7029392"
    ],
    "tgn:id":2150727,
    "tgn:name":"Bass Creek",
    "tgn:placetype":[
        "aat:300008706"
    ]
},
  "bbox": [],
  "geometry": {"coordinates":[-92.8,45.85],"type":"Point"}
}
=======
{"geometry":{"type":"Point","coordinates":[-92.800000,45.850000]},"type":"Feature","properties":{"hierarchy":["tgn:2150727","tgn:1000001","tgn:7012149","tgn:2001056","tgn:7007521","tgn:7029392"],"placetype":["aat:300008706"],"id":2150727,"name:xx":"Bass Creek"}}
>>>>>>> 03f74aca74312dbeaf24d7e61306dd6a786dc3d0
