{
  "id": 7589294,
  "type": "Feature",
  "properties": {
    "tgn:hierarchy":[
        "tgn:7589294",
        "tgn:1000004",
        "tgn:7000198",
        "tgn:7000799",
        "tgn:7029392"
    ],
    "tgn:id":7589294,
    "tgn:name:en":"Chak-i-W\u0101talb\u0101gh",
    "tgn:placetype":[
        "aat:300008347"
    ]
},
  "bbox": [],
  "geometry": {"coordinates":[74.766667,34.25],"type":"Point"}
}