{
  "id": 7084910,
  "type": "Feature",
  "properties": {
    "tgn:hierarchy":[
        "tgn:7084910",
        "tgn:1000003",
        "tgn:7003678",
        "tgn:7000084",
        "tgn:7029392"
    ],
    "tgn:id":7084910,
    "tgn:name":"Wei\u00dfer Stein",
    "tgn:placetype":[
        "aat:300008777"
    ]
},
  "bbox": [],
  "geometry": {"coordinates":[8.033333,50.133333],"type":"Point"}
}