{
  "id": 2592259,
  "type": "Feature",
  "properties": {
    "tgn:hierarchy":[
        "tgn:2592259",
        "tgn:1000001",
        "tgn:2001413",
        "tgn:7012149",
        "tgn:7007526",
        "tgn:7029392"
    ],
    "tgn:id":2592259,
    "tgn:name":"Pony Trail Canyon",
    "tgn:placetype":[
        "aat:300008761"
    ]
},
  "bbox": [],
  "geometry": {"coordinates":[-116.25,40.4333],"type":"Point"}
}