{
  "id": 2767012,
  "type": "Feature",
  "properties": {
    "tgn:hierarchy":[
        "tgn:2767012",
        "tgn:1000001",
        "tgn:7006451",
        "tgn:2000093",
        "tgn:7012149",
        "tgn:7029392"
    ],
    "tgn:id":2767012,
    "tgn:name":"White Ridge Tank",
    "tgn:placetype":[
        "aat:300006191"
    ]
},
  "bbox": [],
  "geometry": {"coordinates":[-110.8833,33.7167],"type":"Point"}
}