{
  "id": 2462428,
  "type": "Feature",
  "properties": {
    "tgn:hierarchy":[
        "tgn:2462428",
        "tgn:1000001",
        "tgn:7012149",
        "tgn:1002742",
        "tgn:7007920",
        "tgn:7029392"
    ],
    "tgn:id":2462428,
    "tgn:name":"Little Whisky Mountain",
    "tgn:placetype":[
        "aat:300008798"
    ]
},
  "bbox": [],
  "geometry": {"coordinates":[-119.4333,48.7833],"type":"Point"}
}