{
  "id": 2773718,
  "type": "Feature",
  "properties": {
    "tgn:hierarchy":[
        "tgn:2773718",
        "tgn:1000001",
        "tgn:1002193",
        "tgn:7012149",
        "tgn:7007255",
        "tgn:7029392"
    ],
    "tgn:id":2773718,
    "tgn:name":"Willow Branch",
    "tgn:placetype":[
        "aat:300008699"
    ]
},
  "bbox": [],
  "geometry": {"coordinates":[-84.05,38.6667],"type":"Point"}
}