{
  "id": 7282816,
  "type": "Feature",
  "properties": {
    "tgn:hierarchy":[
        "tgn:7282816",
        "tgn:7016598",
        "tgn:1000049",
        "tgn:1000002",
        "tgn:7029392"
    ],
    "tgn:id":7282816,
    "tgn:name":"Pel\u00f3n, Aguada",
    "tgn:placetype":[
        "aat:300008697"
    ]
},
  "bbox": [],
  "geometry": {"coordinates":[-68.133333,-22.733333],"type":"Point"}
}