{
  "id": 2139536,
  "type": "Feature",
  "properties": {
    "tgn:hierarchy":[
        "tgn:2139536",
        "tgn:1002201",
        "tgn:1000001",
        "tgn:7012149",
        "tgn:7007517",
        "tgn:7029392"
    ],
    "tgn:id":2139536,
    "tgn:name":"Assonet River Reservoir",
    "tgn:placetype":[
        "aat:300006191"
    ]
},
  "bbox": [],
  "geometry": {"coordinates":[-71.05,41.8167],"type":"Point"}
}