{
  "id": 2022865,
  "type": "Feature",
  "properties": {
    "tgn:hierarchy":[
        "tgn:2022865",
        "tgn:1000001",
        "tgn:7012149",
        "tgn:2000370",
        "tgn:7007248",
        "tgn:7029392"
    ],
    "tgn:id":2022865,
    "tgn:name":"Farrar",
    "tgn:placetype":[
        "aat:300008347",
        "aat:300387210"
    ]
},
  "bbox": [],
  "geometry": {"coordinates":[-83.6333,33.45],"type":"Point"}
}