<<<<<<< HEAD
{
  "id": 7487649,
  "type": "Feature",
  "properties": {
    "tgn:hierarchy":[
        "tgn:7487649",
        "tgn:1000004",
        "tgn:7491221",
        "tgn:1000141",
        "tgn:7029392"
    ],
    "tgn:id":7487649,
    "tgn:name":"Kengwei",
    "tgn:placetype":[
        "aat:300387050"
    ]
},
  "bbox": [],
  "geometry": {"coordinates":[121.116667,23.133333],"type":"Point"}
}
=======
{"geometry":{"type":"Point","coordinates":[121.116667,23.133333]},"type":"Feature","properties":{"hierarchy":["tgn:7487649","tgn:1000004","tgn:7491221","tgn:1000141","tgn:7029392"],"placetype":["aat:300387050"],"id":7487649,"name:xx":"Kengwei"}}
>>>>>>> 03f74aca74312dbeaf24d7e61306dd6a786dc3d0
