{
  "id": 7487649,
  "type": "Feature",
  "properties": {
    "tgn:hierarchy":[
        "tgn:7487649",
        "tgn:1000004",
        "tgn:7491221",
        "tgn:1000141",
        "tgn:7029392"
    ],
    "tgn:id":7487649,
    "tgn:name":"Kengwei",
    "tgn:placetype":[
        "aat:300387050"
    ]
},
  "bbox": [],
  "geometry": {"coordinates":[121.116667,23.133333],"type":"Point"}
}