<<<<<<< HEAD
{
  "id": 7373082,
  "type": "Feature",
  "properties": {
    "tgn:hierarchy":[
        "tgn:7373082",
        "tgn:7005581",
        "tgn:1000001",
        "tgn:7005560",
        "tgn:7029392"
    ],
    "tgn:id":7373082,
    "tgn:name":"La Laja",
    "tgn:placetype":[
        "aat:300008347"
    ]
},
  "bbox": [],
  "geometry": {"coordinates":[-107.883333,27.466667],"type":"Point"}
}
=======
{"geometry":{"type":"Point","coordinates":[-107.883333,27.466667]},"type":"Feature","properties":{"hierarchy":["tgn:7373082","tgn:7005581","tgn:1000001","tgn:7005560","tgn:7029392"],"placetype":["aat:300008347"],"id":7373082,"name:xx":"La Laja"}}
>>>>>>> 03f74aca74312dbeaf24d7e61306dd6a786dc3d0
