<<<<<<< HEAD
{
  "id": 7356979,
  "type": "Feature",
  "properties": {
    "tgn:hierarchy":[
        "tgn:7356979",
        "tgn:7005581",
        "tgn:1000001",
        "tgn:7005560",
        "tgn:7029392"
    ],
    "tgn:id":7356979,
    "tgn:name":"Campo 42",
    "tgn:placetype":[
        "aat:300008347"
    ]
},
  "bbox": [],
  "geometry": {"coordinates":[-106.75,28.9],"type":"Point"}
}
=======
{"geometry":{"type":"Point","coordinates":[-106.750000,28.900000]},"type":"Feature","properties":{"hierarchy":["tgn:7356979","tgn:7005581","tgn:1000001","tgn:7005560","tgn:7029392"],"placetype":["aat:300008347"],"id":7356979,"name:xx":"Campo 42"}}
>>>>>>> 03f74aca74312dbeaf24d7e61306dd6a786dc3d0
