{
  "id": 7420922,
  "type": "Feature",
  "properties": {
    "tgn:hierarchy":[
        "tgn:7420922",
        "tgn:7005584",
        "tgn:1000001",
        "tgn:7005560",
        "tgn:7029392"
    ],
    "tgn:id":7420922,
    "tgn:name":"Presa Santo Tom\u00e1s",
    "tgn:placetype":[
        "aat:300006191"
    ]
},
  "bbox": [],
  "geometry": {"coordinates":[-100.898333,21.480278],"type":"Point"}
}