{
  "id": 2416613,
  "type": "Feature",
  "properties": {
    "tgn:hierarchy":[
        "tgn:2416613",
        "tgn:1000001",
        "tgn:7012149",
        "tgn:2000434",
        "tgn:7007248",
        "tgn:7029392"
    ],
    "tgn:id":2416613,
    "tgn:name":"Jack Hole",
    "tgn:placetype":[
        "aat:300008680"
    ]
},
  "bbox": [],
  "geometry": {"coordinates":[-83.5333,32.6333],"type":"Point"}
}