{
  "id": 2559325,
  "type": "Feature",
  "properties": {
    "tgn:hierarchy":[
        "tgn:2559325",
        "tgn:1000001",
        "tgn:7012149",
        "tgn:2000904",
        "tgn:7007256",
        "tgn:7029392"
    ],
    "tgn:id":2559325,
    "tgn:name":"Onion Bayou",
    "tgn:placetype":[
        "aat:300008699"
    ]
},
  "bbox": [],
  "geometry": {"coordinates":[-91.5833,29.7833],"type":"Point"}
}