{
  "id": 7009373,
  "type": "Feature",
  "properties": {
    "tgn:hierarchy":[
        "tgn:7009373",
        "tgn:1000003",
        "tgn:7002889",
        "tgn:1000070",
        "tgn:7029392"
    ],
    "tgn:id":7009373,
    "tgn:name":"Monts\u00e9gur",
    "tgn:placetype":[
        "aat:300000833"
    ]
},
  "bbox": [],
  "geometry": {"coordinates":[1.8167,42.85],"type":"Point"}
}