{
  "id": 7445438,
  "type": "Feature",
  "properties": {
    "tgn:hierarchy":[
        "tgn:7445438",
        "tgn:7002443",
        "tgn:1000003",
        "tgn:7018993",
        "tgn:7008591",
        "tgn:7029392"
    ],
    "tgn:id":7445438,
    "tgn:name:en":"Dandderwen",
    "tgn:placetype":[
        "aat:300008347"
    ]
},
  "bbox": [],
  "geometry": {"coordinates":[-4.725,51.912222],"type":"Point"}
}