<<<<<<< HEAD
{
  "id": 2405000,
  "type": "Feature",
  "properties": {
    "tgn:hierarchy":[
        "tgn:2405000",
        "tgn:1000001",
        "tgn:7012149",
        "tgn:2002246",
        "tgn:7007920",
        "tgn:7029392"
    ],
    "tgn:id":2405000,
    "tgn:name":"Hudson Coulee",
    "tgn:placetype":[
        "aat:300008761"
    ]
},
  "bbox": [],
  "geometry": {"coordinates":[-119.3167,47.5333],"type":"Point"}
}
=======
{"geometry":{"type":"Point","coordinates":[-119.316700,47.533300]},"type":"Feature","properties":{"hierarchy":["tgn:2405000","tgn:1000001","tgn:7012149","tgn:2002246","tgn:7007920","tgn:7029392"],"placetype":["aat:300008761"],"id":2405000,"name:xx":"Hudson Coulee"}}
>>>>>>> 03f74aca74312dbeaf24d7e61306dd6a786dc3d0
