{
  "id": 7196534,
  "type": "Feature",
  "properties": {
    "tgn:hierarchy":[
        "tgn:7196534",
        "tgn:7003692",
        "tgn:1000003",
        "tgn:7000084",
        "tgn:7029392"
    ],
    "tgn:id":7196534,
    "tgn:name":"Deutenberg",
    "tgn:placetype":[
        "aat:300008777"
    ]
},
  "bbox": [],
  "geometry": {"coordinates":[8.55,48.066667],"type":"Point"}
}