{
  "id": 7475657,
  "type": "Feature",
  "properties": {
    "tgn:hierarchy":[
        "tgn:7475657",
        "tgn:7488858",
        "tgn:1000004",
        "tgn:1000141",
        "tgn:7029392"
    ],
    "tgn:id":7475657,
    "tgn:name":"Zhuangzidi",
    "tgn:placetype":[
        "aat:300008347"
    ]
},
  "bbox": [],
  "geometry": {"coordinates":[120.920053,23.976658],"type":"Point"}
}