{
  "id": 2161959,
  "type": "Feature",
  "properties": {
    "tgn:hierarchy":[
        "tgn:2161959",
        "tgn:1000001",
        "tgn:7012149",
        "tgn:7007710",
        "tgn:7029392"
    ],
    "tgn:id":2161959,
    "tgn:name":"Bells Gap Run",
    "tgn:placetype":[
        "aat:300008699"
    ]
},
  "bbox": [],
  "geometry": {"coordinates":[-78.4167,40.6333],"type":"Point"}
}