{
  "id": 2567462,
  "type": "Feature",
  "properties": {
    "tgn:hierarchy":[
        "tgn:2567462",
        "tgn:1000001",
        "tgn:7012149",
        "tgn:1002314",
        "tgn:7007240",
        "tgn:7029392"
    ],
    "tgn:id":2567462,
    "tgn:name":"Papaya Hammock",
    "tgn:placetype":[
        "aat:300008791"
    ]
},
  "bbox": [],
  "geometry": {"coordinates":[-80.7667,25.4833],"type":"Point"}
}