{
  "id": 7564916,
  "type": "Feature",
  "properties": {
    "tgn:hierarchy":[
        "tgn:7564916",
        "tgn:1000004",
        "tgn:7000198",
        "tgn:1001894",
        "tgn:7029392"
    ],
    "tgn:id":7564916,
    "tgn:name:en":"Malwa Bhadra Protected Forest",
    "tgn:placetype":[
        "aat:300008865"
    ]
},
  "bbox": [],
  "geometry": {"coordinates":[79.024046,24.882049],"type":"Point"}
}