{
  "id": 1050206,
  "type": "Feature",
  "properties": {
    "tgn:hierarchy":[
        "tgn:1050206",
        "tgn:1000336",
        "tgn:1000003",
        "tgn:1000091",
        "tgn:7029392"
    ],
    "tgn:id":1050206,
    "tgn:name":"Ocna Mure\u0219",
    "tgn:placetype":[
        "aat:300008347"
    ]
},
  "bbox": [],
  "geometry": {"coordinates":[23.8833,46.4167],"type":"Point"}
}