{
  "id": 2778278,
  "type": "Feature",
  "properties": {
    "tgn:hierarchy":[
        "tgn:2778278",
        "tgn:1000001",
        "tgn:7012149",
        "tgn:7007157",
        "tgn:1002621",
        "tgn:7029392"
    ],
    "tgn:id":2778278,
    "tgn:name":"Wishon Cove",
    "tgn:placetype":[
        "aat:300132316"
    ]
},
  "bbox": [],
  "geometry": {"coordinates":[-119.5333,37.2833],"type":"Point"}
}