{
  "id": 2191824,
  "type": "Feature",
  "properties": {
    "tgn:hierarchy":[
        "tgn:2191824",
        "tgn:1000001",
        "tgn:7012149",
        "tgn:1002545",
        "tgn:7007157",
        "tgn:7029392"
    ],
    "tgn:id":2191824,
    "tgn:name":"Bradshaw Creek",
    "tgn:placetype":[
        "aat:300008706"
    ]
},
  "bbox": [],
  "geometry": {"coordinates":[-118.5667,35.6333],"type":"Point"}
}