{
  "id": 2662017,
  "type": "Feature",
  "properties": {
    "tgn:hierarchy":[
        "tgn:2662017",
        "tgn:1000001",
        "tgn:2001419",
        "tgn:7012149",
        "tgn:7007526",
        "tgn:7029392"
    ],
    "tgn:id":2662017,
    "tgn:name":"Siard Canyon",
    "tgn:placetype":[
        "aat:300008761"
    ]
},
  "bbox": [],
  "geometry": {"coordinates":[-117.5167,40.3833],"type":"Point"}
}