{
  "id": 2630547,
  "type": "Feature",
  "properties": {
    "tgn:hierarchy":[
        "tgn:2630547",
        "tgn:1000001",
        "tgn:7012149",
        "tgn:2000238",
        "tgn:7007158",
        "tgn:7029392"
    ],
    "tgn:id":2630547,
    "tgn:name":"Round Hill",
    "tgn:placetype":[
        "aat:300008798"
    ]
},
  "bbox": [],
  "geometry": {"coordinates":[-106.05,39.1333],"type":"Point"}
}