{
  "id": 7567775,
  "type": "Feature",
  "properties": {
    "tgn:hierarchy":[
        "tgn:7567775",
        "tgn:1000004",
        "tgn:1001869",
        "tgn:7000198",
        "tgn:7029392"
    ],
    "tgn:id":7567775,
    "tgn:name:en":"Shankhodh\u0101r, Bet",
    "tgn:placetype":[
        "aat:300008791"
    ]
},
  "bbox": [],
  "geometry": {"coordinates":[69.130556,22.458333],"type":"Point"}
}