{
  "id": 7116755,
  "type": "Feature",
  "properties": {
    "tgn:hierarchy":[
        "tgn:7116755",
        "tgn:7003669",
        "tgn:1000003",
        "tgn:7000084",
        "tgn:7029392"
    ],
    "tgn:id":7116755,
    "tgn:name":"Oberunsbach",
    "tgn:placetype":[
        "aat:300000206"
    ]
},
  "bbox": [],
  "geometry": {"coordinates":[12.216667,48.65],"type":"Point"}
}