{
  "id": 7472012,
  "type": "Feature",
  "properties": {
    "tgn:hierarchy":[
        "tgn:7472012",
        "tgn:1000004",
        "tgn:7467799",
        "tgn:1000141",
        "tgn:7029392"
    ],
    "tgn:id":7472012,
    "tgn:name":"Daima Qiao",
    "tgn:placetype":[
        "aat:300007836"
    ]
},
  "bbox": [],
  "geometry": {"coordinates":[120.453095,23.94417],"type":"Point"}
}