<<<<<<< HEAD
{
  "id": 7472012,
  "type": "Feature",
  "properties": {
    "tgn:hierarchy":[
        "tgn:7472012",
        "tgn:1000004",
        "tgn:7467799",
        "tgn:1000141",
        "tgn:7029392"
    ],
    "tgn:id":7472012,
    "tgn:name":"Daima Qiao",
    "tgn:placetype":[
        "aat:300007836"
    ]
},
  "bbox": [],
  "geometry": {"coordinates":[120.453095,23.94417],"type":"Point"}
}
=======
{"geometry":{"type":"Point","coordinates":[120.453095,23.944170]},"type":"Feature","properties":{"hierarchy":["tgn:7472012","tgn:1000004","tgn:7467799","tgn:1000141","tgn:7029392"],"placetype":["aat:300007836"],"id":7472012,"name:xx":"Daima Qiao"}}
>>>>>>> 03f74aca74312dbeaf24d7e61306dd6a786dc3d0
