{
  "id": 2360983,
  "type": "Feature",
  "properties": {
    "tgn:hierarchy":[
        "tgn:2360983",
        "tgn:1000001",
        "tgn:7012149",
        "tgn:2001711",
        "tgn:7007708",
        "tgn:7029392"
    ],
    "tgn:id":2360983,
    "tgn:name":"Grassy Range",
    "tgn:placetype":[
        "aat:300386831"
    ]
},
  "bbox": [],
  "geometry": {"coordinates":[-122.6833,42.8833],"type":"Point"}
}