{
  "id": 7330399,
  "type": "Feature",
  "properties": {
    "tgn:hierarchy":[
        "tgn:7330399",
        "tgn:7002758",
        "tgn:7002830",
        "tgn:1000003",
        "tgn:1000095",
        "tgn:7029392"
    ],
    "tgn:id":7330399,
    "tgn:name":"Higuer\u00f3n, R\u00edo",
    "tgn:placetype":[
        "aat:300008699"
    ]
},
  "bbox": [],
  "geometry": {"coordinates":[-3.883333,36.766667],"type":"Point"}
}