{
  "id": 2299755,
  "type": "Feature",
  "properties": {
    "tgn:hierarchy":[
        "tgn:2299755",
        "tgn:1000001",
        "tgn:7012149",
        "tgn:2000983",
        "tgn:7007520",
        "tgn:7029392"
    ],
    "tgn:id":2299755,
    "tgn:name":"Dudgean Swamp",
    "tgn:placetype":[
        "aat:300008905"
    ]
},
  "bbox": [],
  "geometry": {"coordinates":[-85.65,43.5667],"type":"Point"}
}