{
  "id": 2361394,
  "type": "Feature",
  "properties": {
    "tgn:hierarchy":[
        "tgn:2361394",
        "tgn:1000001",
        "tgn:2001413",
        "tgn:7012149",
        "tgn:7007526",
        "tgn:7029392"
    ],
    "tgn:id":2361394,
    "tgn:name":"Gravelly Ford",
    "tgn:placetype":[
        "aat:300008347"
    ]
},
  "bbox": [],
  "geometry": {"coordinates":[-116.3833,40.5667],"type":"Point"}
}