{
  "id": 1028978,
  "type": "Feature",
  "properties": {
    "tgn:hierarchy":[
        "tgn:1028978",
        "tgn:7002445",
        "tgn:7008114",
        "tgn:1000003",
        "tgn:7008591",
        "tgn:7029392"
    ],
    "tgn:id":1028978,
    "tgn:name:en":"Croft",
    "tgn:placetype":[
        "aat:300008347"
    ]
},
  "bbox": [],
  "geometry": {"coordinates":[-2.55,53.433333],"type":"Point"}
}