{
  "id": 1112830,
  "type": "Feature",
  "properties": {
    "tgn:hierarchy":[
        "tgn:1112830",
        "tgn:7005685",
        "tgn:1000001",
        "tgn:7013154",
        "tgn:7029392"
    ],
    "tgn:id":1112830,
    "tgn:name":"Colpoys Bay",
    "tgn:placetype":[
        "aat:300132316"
    ]
},
  "bbox": [],
  "geometry": {"coordinates":[-81.0833,44.7833],"type":"Point"}
}