{
  "id": 2771055,
  "type": "Feature",
  "properties": {
    "tgn:hierarchy":[
        "tgn:2771055",
        "tgn:1000001",
        "tgn:7012149",
        "tgn:2001029",
        "tgn:7007521",
        "tgn:7029392"
    ],
    "tgn:id":2771055,
    "tgn:name":"Wildcat Island",
    "tgn:placetype":[
        "aat:300008791"
    ]
},
  "bbox": [],
  "geometry": {"coordinates":[-93.6667,47.5333],"type":"Point"}
}