{
  "id": 2060738,
  "type": "Feature",
  "properties": {
    "tgn:hierarchy":[
        "tgn:2060738",
        "tgn:1000001",
        "tgn:7012149",
        "tgn:2001188",
        "tgn:7007523",
        "tgn:7029392"
    ],
    "tgn:id":2060738,
    "tgn:name":"Turney",
    "tgn:placetype":[
        "aat:300008347"
    ]
},
  "bbox": [],
  "geometry": {"coordinates":[-94.3167,39.6333],"type":"Point"}
}