{
  "id": 2782723,
  "type": "Feature",
  "properties": {
    "tgn:hierarchy":[
        "tgn:2782723",
        "tgn:7013349",
        "tgn:1000001",
        "tgn:7012149",
        "tgn:7007708",
        "tgn:7029392"
    ],
    "tgn:id":2782723,
    "tgn:name":"Worley Creek",
    "tgn:placetype":[
        "aat:300008706"
    ]
},
  "bbox": [],
  "geometry": {"coordinates":[-118.15,44.6667],"type":"Point"}
}