{
  "id": 2490582,
  "type": "Feature",
  "properties": {
    "tgn:hierarchy":[
        "tgn:2490582",
        "tgn:1000001",
        "tgn:7012149",
        "tgn:7007159",
        "tgn:7029392"
    ],
    "tgn:id":2490582,
    "tgn:name":"Mann Brook",
    "tgn:placetype":[
        "aat:300008699"
    ]
},
  "bbox": [],
  "geometry": {"coordinates":[-73.4333,41.4833],"type":"Point"}
}