{
  "id": 2455665,
  "type": "Feature",
  "properties": {
    "tgn:hierarchy":[
        "tgn:2455665",
        "tgn:1000001",
        "tgn:2001424",
        "tgn:7012149",
        "tgn:7007564",
        "tgn:7029392"
    ],
    "tgn:id":2455665,
    "tgn:name":"Little Gordon Hill",
    "tgn:placetype":[
        "aat:300008798"
    ]
},
  "bbox": [],
  "geometry": {"coordinates":[-71.75,43.5833],"type":"Point"}
}