{
  "id": 7421023,
  "type": "Feature",
  "properties": {
    "tgn:hierarchy":[
        "tgn:7421023",
        "tgn:1001836",
        "tgn:1000001",
        "tgn:7005560",
        "tgn:7029392"
    ],
    "tgn:id":7421023,
    "tgn:name":"San Ram\u00f3n, Isla",
    "tgn:placetype":[
        "aat:300008791"
    ]
},
  "bbox": [],
  "geometry": {"coordinates":[-111.890556,26.749444],"type":"Point"}
}