{
  "id": 7384287,
  "type": "Feature",
  "properties": {
    "tgn:hierarchy":[
        "tgn:7384287",
        "tgn:7005586",
        "tgn:1000001",
        "tgn:7005560",
        "tgn:7029392"
    ],
    "tgn:id":7384287,
    "tgn:name":"Oconahua",
    "tgn:placetype":[
        "aat:300008347"
    ]
},
  "bbox": [],
  "geometry": {"coordinates":[-104.15,20.733333],"type":"Point"}
}