<<<<<<< HEAD
{
  "id": 2339969,
  "type": "Feature",
  "properties": {
    "tgn:hierarchy":[
        "tgn:2339969",
        "tgn:1000001",
        "tgn:7012149",
        "tgn:7014612",
        "tgn:7007568",
        "tgn:7029392"
    ],
    "tgn:id":2339969,
    "tgn:name":"Freemont Pond",
    "tgn:placetype":[
        "aat:300006191"
    ]
},
  "bbox": [],
  "geometry": {"coordinates":[-73.8667,41.1],"type":"Point"}
}
=======
{"geometry":{"type":"Point","coordinates":[-73.866700,41.100000]},"type":"Feature","properties":{"hierarchy":["tgn:2339969","tgn:1000001","tgn:7012149","tgn:7014612","tgn:7007568","tgn:7029392"],"placetype":["aat:300006191"],"id":2339969,"name:xx":"Freemont Pond"}}
>>>>>>> 03f74aca74312dbeaf24d7e61306dd6a786dc3d0
