<<<<<<< HEAD
{
  "id": 7372507,
  "type": "Feature",
  "properties": {
    "tgn:hierarchy":[
        "tgn:7372507",
        "tgn:7005581",
        "tgn:1000001",
        "tgn:7005560",
        "tgn:7029392"
    ],
    "tgn:id":7372507,
    "tgn:name":"La Junta",
    "tgn:placetype":[
        "aat:300008347"
    ]
},
  "bbox": [],
  "geometry": {"coordinates":[-106.8,27.716667],"type":"Point"}
}
=======
{"geometry":{"type":"Point","coordinates":[-106.800000,27.716667]},"type":"Feature","properties":{"hierarchy":["tgn:7372507","tgn:7005581","tgn:1000001","tgn:7005560","tgn:7029392"],"placetype":["aat:300008347"],"id":7372507,"name:xx":"La Junta"}}
>>>>>>> 03f74aca74312dbeaf24d7e61306dd6a786dc3d0
