{
  "id": 7307973,
  "type": "Feature",
  "properties": {
    "tgn:hierarchy":[
        "tgn:7307973",
        "tgn:1001768",
        "tgn:1000049",
        "tgn:1000002",
        "tgn:7029392"
    ],
    "tgn:id":7307973,
    "tgn:name":"Molles, Caleta",
    "tgn:placetype":[
        "aat:300132317"
    ]
},
  "bbox": [],
  "geometry": {"coordinates":[-71.502778,-32.260278],"type":"Point"}
}