{
  "id": 2708849,
  "type": "Feature",
  "properties": {
    "tgn:hierarchy":[
        "tgn:2708849",
        "tgn:1000001",
        "tgn:1002216",
        "tgn:7012149",
        "tgn:7007706",
        "tgn:7029392"
    ],
    "tgn:id":2708849,
    "tgn:name":"Symmes Corner",
    "tgn:placetype":[
        "aat:300008347"
    ]
},
  "bbox": [],
  "geometry": {"coordinates":[-84.5667,39.3333],"type":"Point"}
}