<<<<<<< HEAD
{
  "id": 7112955,
  "type": "Feature",
  "properties": {
    "tgn:hierarchy":[
        "tgn:7112955",
        "tgn:1000003",
        "tgn:7000094",
        "tgn:7000084",
        "tgn:7029392"
    ],
    "tgn:id":7112955,
    "tgn:name":"R\u00f6dlin",
    "tgn:placetype":[
        "aat:300008347"
    ]
},
  "bbox": [],
  "geometry": {"coordinates":[13.233333,53.4],"type":"Point"}
}
=======
{"geometry":{"type":"Point","coordinates":[13.233333,53.400000]},"type":"Feature","properties":{"hierarchy":["tgn:7112955","tgn:1000003","tgn:7000094","tgn:7000084","tgn:7029392"],"placetype":["aat:300008347"],"id":7112955,"name:xx":"R\u00f6dlin"}}
>>>>>>> 03f74aca74312dbeaf24d7e61306dd6a786dc3d0
