{
  "id": 7003167,
  "type": "Feature",
  "properties": {
    "tgn:hierarchy":[
        "tgn:7003167",
        "tgn:1000003",
        "tgn:7009760",
        "tgn:1000080",
        "tgn:7029392"
    ],
    "tgn:id":7003167,
    "tgn:name":"Pistoia",
    "tgn:placetype":[
        "aat:300387145",
        "aat:300000774"
    ]
},
  "bbox": [],
  "geometry": {"coordinates":[10.833333,43.966667],"type":"Point"}
}