{
  "id": 7510600,
  "type": "Feature",
  "properties": {
    "tgn:hierarchy":[
        "tgn:7510600",
        "tgn:1009227",
        "tgn:1000226",
        "tgn:7016729",
        "tgn:1000006",
        "tgn:7029392"
    ],
    "tgn:id":7510600,
    "tgn:name:en":"Two Cottage Creek",
    "tgn:placetype":[
        "aat:300008699"
    ]
},
  "bbox": [],
  "geometry": {"coordinates":[173.35,-41.633333],"type":"Point"}
}