{
  "id": 1006280,
  "type": "Feature",
  "properties": {
    "tgn:hierarchy":[
        "tgn:1006280",
        "tgn:7002681",
        "tgn:7001395",
        "tgn:1000003",
        "tgn:1000074",
        "tgn:7029392"
    ],
    "tgn:id":1006280,
    "tgn:name":"Andik\u00edthira, N\u00edsos",
    "tgn:placetype":[
        "aat:300008791"
    ]
},
  "bbox": [],
  "geometry": {"coordinates":[23.302778,35.868056],"type":"Point"}
}