{
  "id": 7526026,
  "type": "Feature",
  "properties": {
    "tgn:hierarchy":[
        "tgn:7526026",
        "tgn:7001242",
        "tgn:7016833",
        "tgn:1001418",
        "tgn:7029392"
    ],
    "tgn:id":7526026,
    "tgn:name:en":"\u0162arf\u0101', Dayr a\u0163",
    "tgn:placetype":[
        "aat:300386860"
    ]
},
  "bbox": [],
  "geometry": {"coordinates":[29.05,30.566667],"type":"Point"}
}