{
  "id": 7334201,
  "type": "Feature",
  "properties": {
    "tgn:hierarchy":[
        "tgn:7334201",
        "tgn:7002805",
        "tgn:7002758",
        "tgn:1000003",
        "tgn:1000095",
        "tgn:7029392"
    ],
    "tgn:id":7334201,
    "tgn:name":"El Lugarico",
    "tgn:placetype":[
        "aat:300008347"
    ]
},
  "bbox": [],
  "geometry": {"coordinates":[-2.15,37.483333],"type":"Point"}
}