{
  "id": 7497692,
  "type": "Feature",
  "properties": {
    "tgn:hierarchy":[
        "tgn:7497692",
        "tgn:1000004",
        "tgn:1000454",
        "tgn:1000141",
        "tgn:7029392"
    ],
    "tgn:id":7497692,
    "tgn:name":"Leigongqi",
    "tgn:placetype":[
        "aat:300008347"
    ]
},
  "bbox": [],
  "geometry": {"coordinates":[121.343401,25.089063],"type":"Point"}
}