{
  "id": 2168181,
  "type": "Feature",
  "properties": {
    "tgn:hierarchy":[
        "tgn:2168181",
        "tgn:1000001",
        "tgn:1002310",
        "tgn:7012149",
        "tgn:7007710",
        "tgn:7029392"
    ],
    "tgn:id":2168181,
    "tgn:name":"Big Flat Ridge",
    "tgn:placetype":[
        "aat:300266640"
    ]
},
  "bbox": [],
  "geometry": {"coordinates":[-77.4333,39.9667],"type":"Point"}
}