{
  "id": 7309232,
  "type": "Feature",
  "properties": {
    "tgn:hierarchy":[
        "tgn:7309232",
        "tgn:1001768",
        "tgn:1000049",
        "tgn:1000002",
        "tgn:7029392"
    ],
    "tgn:id":7309232,
    "tgn:name":"Maitencillo de Valpara\u00edso, Caleta",
    "tgn:placetype":[
        "aat:300132317"
    ]
},
  "bbox": [],
  "geometry": {"coordinates":[-71.475278,-32.634722],"type":"Point"}
}