{
  "id": 1032428,
  "type": "Feature",
  "properties": {
    "tgn:hierarchy":[
        "tgn:1032428",
        "tgn:1000003",
        "tgn:7002883",
        "tgn:1000070",
        "tgn:7029392"
    ],
    "tgn:id":1032428,
    "tgn:name":"Carri\u00e8res-sous-Poissy",
    "tgn:placetype":[
        "aat:300008347"
    ]
},
  "bbox": [],
  "geometry": {"coordinates":[2.0333,48.95],"type":"Point"}
}