{
  "id": 2183771,
  "type": "Feature",
  "properties": {
    "tgn:hierarchy":[
        "tgn:2183771",
        "tgn:1000001",
        "tgn:7012149",
        "tgn:2001543",
        "tgn:7007709",
        "tgn:7029392"
    ],
    "tgn:id":2183771,
    "tgn:name":"Board Cove Branch",
    "tgn:placetype":[
        "aat:300008699"
    ]
},
  "bbox": [],
  "geometry": {"coordinates":[-83.2167,35.5167],"type":"Point"}
}