{
  "id": 7098614,
  "type": "Feature",
  "properties": {
    "tgn:hierarchy":[
        "tgn:7098614",
        "tgn:7003692",
        "tgn:1000003",
        "tgn:7000084",
        "tgn:7029392"
    ],
    "tgn:id":7098614,
    "tgn:name":"Sonnenberg",
    "tgn:placetype":[
        "aat:300008347"
    ]
},
  "bbox": [],
  "geometry": {"coordinates":[9.05,47.866667],"type":"Point"}
}