{
  "id": 7534844,
  "type": "Feature",
  "properties": {
    "tgn:hierarchy":[
        "tgn:7534844",
        "tgn:7001242",
        "tgn:7016833",
        "tgn:7001335",
        "tgn:7029392"
    ],
    "tgn:id":7534844,
    "tgn:name:en":"B\u00eer el-Kas\u00eeba",
    "tgn:placetype":[
        "aat:300006207"
    ]
},
  "bbox": [],
  "geometry": {"coordinates":[32.55,30.916667],"type":"Point"}
}