{
  "id": 2213553,
  "type": "Feature",
  "properties": {
    "tgn:hierarchy":[
        "tgn:2213553",
        "tgn:1000001",
        "tgn:7012149",
        "tgn:2000729",
        "tgn:7007254",
        "tgn:7029392"
    ],
    "tgn:id":2213553,
    "tgn:name":"Cable Creek",
    "tgn:placetype":[
        "aat:300008706"
    ]
},
  "bbox": [],
  "geometry": {"coordinates":[-95.8333,38.5333],"type":"Point"}
}