{
  "id": 2336462,
  "type": "Feature",
  "properties": {
    "tgn:hierarchy":[
        "tgn:2336462",
        "tgn:1000001",
        "tgn:7012149",
        "tgn:2002379",
        "tgn:7007923",
        "tgn:7029392"
    ],
    "tgn:id":2336462,
    "tgn:name":"Four Bear Creek",
    "tgn:placetype":[
        "aat:300008706"
    ]
},
  "bbox": [],
  "geometry": {"coordinates":[-109.2667,44.0667],"type":"Point"}
}