{
  "id": 7415867,
  "type": "Feature",
  "properties": {
    "tgn:hierarchy":[
        "tgn:7415867",
        "tgn:7005584",
        "tgn:1000001",
        "tgn:7005560",
        "tgn:7029392"
    ],
    "tgn:id":7415867,
    "tgn:name":"La Concepci\u00f3n",
    "tgn:placetype":[
        "aat:300008347"
    ]
},
  "bbox": [],
  "geometry": {"coordinates":[-100.738056,20.178889],"type":"Point"}
}