{
  "id": 7227438,
  "type": "Feature",
  "properties": {
    "tgn:hierarchy":[
        "tgn:7227438",
        "tgn:7002745",
        "tgn:7017076",
        "tgn:1000003",
        "tgn:1000074",
        "tgn:7029392"
    ],
    "tgn:id":7227438,
    "tgn:name":"Gr\u00f3ssos, \u00c1kra",
    "tgn:placetype":[
        "aat:300008850"
    ]
},
  "bbox": [],
  "geometry": {"coordinates":[22.35,36.533333],"type":"Point"}
}