<<<<<<< HEAD
{
  "id": 7378873,
  "type": "Feature",
  "properties": {
    "tgn:hierarchy":[
        "tgn:7378873",
        "tgn:1000001",
        "tgn:7005592",
        "tgn:7005560",
        "tgn:7029392"
    ],
    "tgn:id":7378873,
    "tgn:name":"Mextla",
    "tgn:placetype":[
        "aat:300008347"
    ]
},
  "bbox": [],
  "geometry": {"coordinates":[-98.1,20.266667],"type":"Point"}
}
=======
{"geometry":{"type":"Point","coordinates":[-98.100000,20.266667]},"type":"Feature","properties":{"hierarchy":["tgn:7378873","tgn:1000001","tgn:7005592","tgn:7005560","tgn:7029392"],"placetype":["aat:300008347"],"id":7378873,"name:xx":"Mextla"}}
>>>>>>> 03f74aca74312dbeaf24d7e61306dd6a786dc3d0
