{
  "id": 7315604,
  "type": "Feature",
  "properties": {
    "tgn:hierarchy":[
        "tgn:7315604",
        "tgn:1001637",
        "tgn:1000049",
        "tgn:1000002",
        "tgn:7029392"
    ],
    "tgn:id":7315604,
    "tgn:name":"Chacayal, Cerro",
    "tgn:placetype":[
        "aat:300008777"
    ]
},
  "bbox": [],
  "geometry": {"coordinates":[-72.166667,-37.466667],"type":"Point"}
}