{
  "id": 2644472,
  "type": "Feature",
  "properties": {
    "tgn:hierarchy":[
        "tgn:2644472",
        "tgn:1000001",
        "tgn:7012149",
        "tgn:2000885",
        "tgn:7007256",
        "tgn:7029392"
    ],
    "tgn:id":2644472,
    "tgn:name":"Sarah Ridge",
    "tgn:placetype":[
        "aat:300266640"
    ]
},
  "bbox": [],
  "geometry": {"coordinates":[-90.7167,30.2333],"type":"Point"}
}