{
  "id": 7480387,
  "type": "Feature",
  "properties": {
    "tgn:hierarchy":[
        "tgn:7480387",
        "tgn:7001010",
        "tgn:1000004",
        "tgn:1000141",
        "tgn:7029392"
    ],
    "tgn:id":7480387,
    "tgn:name":"Heping Guoxiao Fenxiao",
    "tgn:placetype":[
        "aat:300006495"
    ]
},
  "bbox": [],
  "geometry": {"coordinates":[121.74085,24.266297],"type":"Point"}
}