<<<<<<< HEAD
{
  "id": 7480387,
  "type": "Feature",
  "properties": {
    "tgn:hierarchy":[
        "tgn:7480387",
        "tgn:7001010",
        "tgn:1000004",
        "tgn:1000141",
        "tgn:7029392"
    ],
    "tgn:id":7480387,
    "tgn:name":"Heping Guoxiao Fenxiao",
    "tgn:placetype":[
        "aat:300006495"
    ]
},
  "bbox": [],
  "geometry": {"coordinates":[121.74085,24.266297],"type":"Point"}
}
=======
{"geometry":{"type":"Point","coordinates":[121.740850,24.266297]},"type":"Feature","properties":{"hierarchy":["tgn:7480387","tgn:7001010","tgn:1000004","tgn:1000141","tgn:7029392"],"placetype":["aat:300006495"],"id":7480387,"name:xx":"Heping Guoxiao Fenxiao"}}
>>>>>>> 03f74aca74312dbeaf24d7e61306dd6a786dc3d0
