<<<<<<< HEAD
{
  "id": 2155248,
  "type": "Feature",
  "properties": {
    "tgn:hierarchy":[
        "tgn:2155248",
        "tgn:1000001",
        "tgn:2000460",
        "tgn:7012149",
        "tgn:7007250",
        "tgn:7029392"
    ],
    "tgn:id":2155248,
    "tgn:name":"Bear Mountain",
    "tgn:placetype":[
        "aat:300008798"
    ]
},
  "bbox": [],
  "geometry": {"coordinates":[-116.0667,48.3],"type":"Point"}
}
=======
{"geometry":{"type":"Point","coordinates":[-116.066700,48.300000]},"type":"Feature","properties":{"hierarchy":["tgn:2155248","tgn:1000001","tgn:2000460","tgn:7012149","tgn:7007250","tgn:7029392"],"placetype":["aat:300008798"],"id":2155248,"name:xx":"Bear Mountain"}}
>>>>>>> 03f74aca74312dbeaf24d7e61306dd6a786dc3d0
