{
  "id": 7402212,
  "type": "Feature",
  "properties": {
    "tgn:hierarchy":[
        "tgn:7402212",
        "tgn:1000001",
        "tgn:7005599",
        "tgn:7005560",
        "tgn:7029392"
    ],
    "tgn:id":7402212,
    "tgn:name":"Jos\u00e9 Guadalupe Rodr\u00edguez",
    "tgn:placetype":[
        "aat:300008347"
    ]
},
  "bbox": [],
  "geometry": {"coordinates":[-96.416667,19.422222],"type":"Point"}
}