{
  "id": 7182978,
  "type": "Feature",
  "properties": {
    "tgn:hierarchy":[
        "tgn:7182978",
        "tgn:1000003",
        "tgn:7003676",
        "tgn:7000084",
        "tgn:7029392"
    ],
    "tgn:id":7182978,
    "tgn:name":"Gehlbergen",
    "tgn:placetype":[
        "aat:300008347"
    ]
},
  "bbox": [],
  "geometry": {"coordinates":[9.05,52.816667],"type":"Point"}
}