{
  "id": 7585548,
  "type": "Feature",
  "properties": {
    "tgn:hierarchy":[
        "tgn:7585548",
        "tgn:1000004",
        "tgn:7000198",
        "tgn:7000799",
        "tgn:7029392"
    ],
    "tgn:id":7585548,
    "tgn:name:en":"Sangoti Forest",
    "tgn:placetype":[
        "aat:300008863"
    ]
},
  "bbox": [],
  "geometry": {"coordinates":[74.230556,33.294444],"type":"Point"}
}