<<<<<<< HEAD
{
  "id": 7379817,
  "type": "Feature",
  "properties": {
    "tgn:hierarchy":[
        "tgn:7379817",
        "tgn:1000001",
        "tgn:1001906",
        "tgn:7005560",
        "tgn:7029392"
    ],
    "tgn:id":7379817,
    "tgn:name":"Los Fortines",
    "tgn:placetype":[
        "aat:300008347"
    ]
},
  "bbox": [],
  "geometry": {"coordinates":[-104.3,21.166667],"type":"Point"}
}
=======
{"geometry":{"type":"Point","coordinates":[-104.300000,21.166667]},"type":"Feature","properties":{"hierarchy":["tgn:7379817","tgn:1000001","tgn:1001906","tgn:7005560","tgn:7029392"],"placetype":["aat:300008347"],"id":7379817,"name:xx":"Los Fortines"}}
>>>>>>> 03f74aca74312dbeaf24d7e61306dd6a786dc3d0
