{
  "id": 7072762,
  "type": "Feature",
  "properties": {
    "tgn:hierarchy":[
        "tgn:7072762",
        "tgn:1000003",
        "tgn:7003677",
        "tgn:7000084",
        "tgn:7029392"
    ],
    "tgn:id":7072762,
    "tgn:name":"F\u00f6rsterei Stritterhof",
    "tgn:placetype":[
        "aat:300004792"
    ]
},
  "bbox": [],
  "geometry": {"coordinates":[6.55,50.466667],"type":"Point"}
}