{
  "id": 2145100,
  "type": "Feature",
  "properties": {
    "tgn:hierarchy":[
        "tgn:2145100",
        "tgn:1002366",
        "tgn:1000001",
        "tgn:7012149",
        "tgn:7007159",
        "tgn:7029392"
    ],
    "tgn:id":2145100,
    "tgn:name":"Bald Mountain",
    "tgn:placetype":[
        "aat:300008798"
    ]
},
  "bbox": [],
  "geometry": {"coordinates":[-73.35,41.1167],"type":"Point"}
}