{
  "id": 7392499,
  "type": "Feature",
  "properties": {
    "tgn:hierarchy":[
        "tgn:7392499",
        "tgn:7005581",
        "tgn:1000001",
        "tgn:7005560",
        "tgn:7029392"
    ],
    "tgn:id":7392499,
    "tgn:name":"Rancho Los Nogales",
    "tgn:placetype":[
        "aat:300008347"
    ]
},
  "bbox": [],
  "geometry": {"coordinates":[-105.616667,26.783333],"type":"Point"}
}