{
  "id": 2598209,
  "type": "Feature",
  "properties": {
    "tgn:hierarchy":[
        "tgn:2598209",
        "tgn:1000001",
        "tgn:7012149",
        "tgn:7007252",
        "tgn:7029392"
    ],
    "tgn:id":2598209,
    "tgn:name":"Preston Miles Ditch",
    "tgn:placetype":[
        "aat:300006075"
    ]
},
  "bbox": [],
  "geometry": {"coordinates":[-85.85,41.4167],"type":"Point"}
}