<<<<<<< HEAD
{
  "id": 7363088,
  "type": "Feature",
  "properties": {
    "tgn:hierarchy":[
        "tgn:7363088",
        "tgn:7005586",
        "tgn:1000001",
        "tgn:7005560",
        "tgn:7029392"
    ],
    "tgn:id":7363088,
    "tgn:name":"El Fais\u00e1n",
    "tgn:placetype":[
        "aat:300008347"
    ]
},
  "bbox": [],
  "geometry": {"coordinates":[-102.9,19.7],"type":"Point"}
}
=======
{"geometry":{"type":"Point","coordinates":[-102.900000,19.700000]},"type":"Feature","properties":{"hierarchy":["tgn:7363088","tgn:7005586","tgn:1000001","tgn:7005560","tgn:7029392"],"placetype":["aat:300008347"],"id":7363088,"name:xx":"El Fais\u00e1n"}}
>>>>>>> 03f74aca74312dbeaf24d7e61306dd6a786dc3d0
