{
  "id": 7260687,
  "type": "Feature",
  "properties": {
    "tgn:hierarchy":[
        "tgn:7260687",
        "tgn:7003614",
        "tgn:1000003",
        "tgn:7016845",
        "tgn:7029392"
    ],
    "tgn:id":7260687,
    "tgn:name:nl":"Exloosche Landen",
    "tgn:placetype":[
        "aat:300055621"
    ]
},
  "bbox": [],
  "geometry": {"coordinates":[6.883333,52.883333],"type":"Point"}
}