{
  "id": 1067085,
  "type": "Feature",
  "properties": {
    "tgn:hierarchy":[
        "tgn:1067085",
        "tgn:1000004",
        "tgn:7002079",
        "tgn:1000111",
        "tgn:7029392"
    ],
    "tgn:id":1067085,
    "tgn:name":"Changlejie",
    "tgn:placetype":[
        "aat:300008347"
    ]
},
  "bbox": [],
  "geometry": {"coordinates":[113.3167,28.8667],"type":"Point"}
}