{
  "id": 1061821,
  "type": "Feature",
  "properties": {
    "tgn:hierarchy":[
        "tgn:1061821",
        "tgn:7002824",
        "tgn:1000003",
        "tgn:7002786",
        "tgn:1000095",
        "tgn:7029392"
    ],
    "tgn:id":1061821,
    "tgn:name":"Baio",
    "tgn:placetype":[
        "aat:300008347"
    ]
},
  "bbox": [],
  "geometry": {"coordinates":[-8.966667,43.15],"type":"Point"}
}