<<<<<<< HEAD
{
  "id": 2159624,
  "type": "Feature",
  "properties": {
    "tgn:hierarchy":[
        "tgn:2159624",
        "tgn:1000001",
        "tgn:7016172",
        "tgn:7012149",
        "tgn:2000179",
        "tgn:7029392"
    ],
    "tgn:id":2159624,
    "tgn:name":"Bee Suck Mountain",
    "tgn:placetype":[
        "aat:300266640"
    ]
},
  "bbox": [],
  "geometry": {"coordinates":[-93.5833,34.8333],"type":"Point"}
}
=======
{"geometry":{"type":"Point","coordinates":[-93.583300,34.833300]},"type":"Feature","properties":{"hierarchy":["tgn:2159624","tgn:1000001","tgn:7016172","tgn:7012149","tgn:2000179","tgn:7029392"],"placetype":["aat:300266640"],"id":2159624,"name:xx":"Bee Suck Mountain"}}
>>>>>>> 03f74aca74312dbeaf24d7e61306dd6a786dc3d0
