<<<<<<< HEAD
{
  "id": 2152788,
  "type": "Feature",
  "properties": {
    "tgn:hierarchy":[
        "tgn:2152788",
        "tgn:1000001",
        "tgn:7012149",
        "tgn:2000905",
        "tgn:7007256",
        "tgn:7029392"
    ],
    "tgn:id":2152788,
    "tgn:name":"Bayou du Chien",
    "tgn:placetype":[
        "aat:300008699"
    ]
},
  "bbox": [],
  "geometry": {"coordinates":[-89.8833,30.25],"type":"Point"}
}
=======
{"geometry":{"type":"Point","coordinates":[-89.883300,30.250000]},"type":"Feature","properties":{"hierarchy":["tgn:2152788","tgn:1000001","tgn:7012149","tgn:2000905","tgn:7007256","tgn:7029392"],"placetype":["aat:300008699"],"id":2152788,"name:xx":"Bayou du Chien"}}
>>>>>>> 03f74aca74312dbeaf24d7e61306dd6a786dc3d0
