{
  "id": 2479664,
  "type": "Feature",
  "properties": {
    "tgn:hierarchy":[
        "tgn:2479664",
        "tgn:1000001",
        "tgn:7012149",
        "tgn:1003008",
        "tgn:7007710",
        "tgn:7029392"
    ],
    "tgn:id":2479664,
    "tgn:name":"Lake Cayuga",
    "tgn:placetype":[
        "aat:300006191"
    ]
},
  "bbox": [],
  "geometry": {"coordinates":[-75.2667,41.65],"type":"Point"}
}