{
  "id": 1075406,
  "type": "Feature",
  "properties": {
    "tgn:hierarchy":[
        "tgn:1075406",
        "tgn:1001828",
        "tgn:1000004",
        "tgn:7000198",
        "tgn:7029392"
    ],
    "tgn:id":1075406,
    "tgn:name:en":"Guntakal",
    "tgn:placetype":[
        "aat:300008347"
    ]
},
  "bbox": [],
  "geometry": {"coordinates":[77.383333,15.166667],"type":"Point"}
}