{
  "id": 2429307,
  "type": "Feature",
  "properties": {
    "tgn:hierarchy":[
        "tgn:2429307",
        "tgn:7002659",
        "tgn:1000001",
        "tgn:7012149",
        "tgn:2000061",
        "tgn:7029392"
    ],
    "tgn:id":2429307,
    "tgn:name":"Junior College Lake",
    "tgn:placetype":[
        "aat:300006191"
    ]
},
  "bbox": [],
  "geometry": {"coordinates":[-85.9333,32.9167],"type":"Point"}
}