{
  "id": 1026019,
  "type": "Feature",
  "properties": {
    "tgn:hierarchy":[
        "tgn:1026019",
        "tgn:7003025",
        "tgn:1000003",
        "tgn:1000062",
        "tgn:7029392"
    ],
    "tgn:id":1026019,
    "tgn:name":"Sankt Andr\u00e4 vor dem Hagenthale",
    "tgn:placetype":[
        "aat:300008347"
    ]
},
  "bbox": [],
  "geometry": {"coordinates":[16.2167,48.3167],"type":"Point"}
}