<<<<<<< HEAD
{
  "id": 7246843,
  "type": "Feature",
  "properties": {
    "tgn:hierarchy":[
        "tgn:7246843",
        "tgn:7003460",
        "tgn:1000003",
        "tgn:1000063",
        "tgn:4012014",
        "tgn:7029392"
    ],
    "tgn:id":7246843,
    "tgn:name":"Crisn\u00e9e",
    "tgn:placetype":[
        "aat:300008347"
    ]
},
  "bbox": [],
  "geometry": {"coordinates":[5.397531,50.716211],"type":"Point"}
}
=======
{"geometry":{"type":"Point","coordinates":[5.397531,50.716211]},"type":"Feature","properties":{"hierarchy":["tgn:7246843","tgn:7003460","tgn:1000003","tgn:1000063","tgn:4012014","tgn:7029392"],"placetype":["aat:300008347"],"id":7246843,"name:xx":"Crisn\u00e9e"}}
>>>>>>> 03f74aca74312dbeaf24d7e61306dd6a786dc3d0
