{
  "id": 2744266,
  "type": "Feature",
  "properties": {
    "tgn:hierarchy":[
        "tgn:2744266",
        "tgn:1000001",
        "tgn:7012149",
        "tgn:2002121",
        "tgn:7007827",
        "tgn:7029392"
    ],
    "tgn:id":2744266,
    "tgn:name":"Vermillion",
    "tgn:placetype":[
        "aat:300008347"
    ]
},
  "bbox": [],
  "geometry": {"coordinates":[-111.95,38.85],"type":"Point"}
}