<<<<<<< HEAD
{
  "id": 2150622,
  "type": "Feature",
  "properties": {
    "tgn:hierarchy":[
        "tgn:2150622",
        "tgn:1000001",
        "tgn:7012149",
        "tgn:7007254",
        "tgn:7029392"
    ],
    "tgn:id":2150622,
    "tgn:name":"Basket Creek",
    "tgn:placetype":[
        "aat:300008706"
    ]
},
  "bbox": [],
  "geometry": {"coordinates":[-97.2833,39.1167],"type":"Point"}
}
=======
{"geometry":{"type":"Point","coordinates":[-97.283300,39.116700]},"type":"Feature","properties":{"hierarchy":["tgn:2150622","tgn:1000001","tgn:7012149","tgn:7007254","tgn:7029392"],"placetype":["aat:300008706"],"id":2150622,"name:xx":"Basket Creek"}}
>>>>>>> 03f74aca74312dbeaf24d7e61306dd6a786dc3d0
