{
  "id": 2481774,
  "type": "Feature",
  "properties": {
    "tgn:hierarchy":[
        "tgn:2481774",
        "tgn:1000001",
        "tgn:7012149",
        "tgn:2001930",
        "tgn:7007825",
        "tgn:7029392"
    ],
    "tgn:id":2481774,
    "tgn:name":"Landings",
    "tgn:placetype":[
        "aat:300008347"
    ]
},
  "bbox": [],
  "geometry": {"coordinates":[-86.8167,35.9667],"type":"Point"}
}