{
  "id": 2210988,
  "type": "Feature",
  "properties": {
    "tgn:hierarchy":[
        "tgn:2210988",
        "tgn:1000001",
        "tgn:7012149",
        "tgn:2000220",
        "tgn:7007158",
        "tgn:7029392"
    ],
    "tgn:id":2210988,
    "tgn:name":"Butler Ditch Number 4",
    "tgn:placetype":[
        "aat:300006075"
    ]
},
  "bbox": [],
  "geometry": {"coordinates":[-106.55,40.6167],"type":"Point"}
}