{
  "id": 7219071,
  "type": "Feature",
  "properties": {
    "tgn:hierarchy":[
        "tgn:7219071",
        "tgn:7011161",
        "tgn:7002674",
        "tgn:1000003",
        "tgn:1000074",
        "tgn:7029392"
    ],
    "tgn:id":7219071,
    "tgn:name":"Vast\u00e1gas",
    "tgn:placetype":[
        "aat:300266640"
    ]
},
  "bbox": [],
  "geometry": {"coordinates":[26.089444,38.216389],"type":"Point"}
}