{
  "id": 7471744,
  "type": "Feature",
  "properties": {
    "tgn:hierarchy":[
        "tgn:7471744",
        "tgn:7468018",
        "tgn:1000004",
        "tgn:1000141",
        "tgn:7029392"
    ],
    "tgn:id":7471744,
    "tgn:name":"Chuanzitou",
    "tgn:placetype":[
        "aat:300008347"
    ]
},
  "bbox": [],
  "geometry": {"coordinates":[120.224527,23.470565],"type":"Point"}
}