{
  "id": 7079629,
  "type": "Feature",
  "properties": {
    "tgn:hierarchy":[
        "tgn:7079629",
        "tgn:1000003",
        "tgn:7003677",
        "tgn:7000084",
        "tgn:7029392"
    ],
    "tgn:id":7079629,
    "tgn:name":"Wolfs Berg",
    "tgn:placetype":[
        "aat:300008777"
    ]
},
  "bbox": [],
  "geometry": {"coordinates":[6.05,51.766667],"type":"Point"}
}