{
  "id": 2293810,
  "type": "Feature",
  "properties": {
    "tgn:hierarchy":[
        "tgn:2293810",
        "tgn:1000001",
        "tgn:7012149",
        "tgn:2002371",
        "tgn:7007923",
        "tgn:7029392"
    ],
    "tgn:id":2293810,
    "tgn:name":"Doughty Draw",
    "tgn:placetype":[
        "aat:300008761"
    ]
},
  "bbox": [],
  "geometry": {"coordinates":[-108.3167,43.1167],"type":"Point"}
}