{
  "id": 7472590,
  "type": "Feature",
  "properties": {
    "tgn:hierarchy":[
        "tgn:7472590",
        "tgn:1000004",
        "tgn:7490934",
        "tgn:1000141",
        "tgn:7029392"
    ],
    "tgn:id":7472590,
    "tgn:name":"Wubiantou",
    "tgn:placetype":[
        "aat:300008347"
    ]
},
  "bbox": [],
  "geometry": {"coordinates":[120.456944,23.369722],"type":"Point"}
}