{
  "id": 7267394,
  "type": "Feature",
  "properties": {
    "tgn:concordances":{
        "gn:id":"2749566"
    },
    "tgn:hierarchy":[
        "tgn:7267394",
        "tgn:1000003",
        "tgn:7003622",
        "tgn:7016845",
        "tgn:7029392"
    ],
    "tgn:id":7267394,
    "tgn:name:nl":"Ooijen",
    "tgn:placetype":[
        "aat:300008347"
    ]
},
  "bbox": [],
  "geometry": {"coordinates":[6.15,51.516667],"type":"Point"}
}