{
  "id": 2207256,
  "type": "Feature",
  "properties": {
    "tgn:hierarchy":[
        "tgn:2207256",
        "tgn:1000001",
        "tgn:7012149",
        "tgn:1002747",
        "tgn:7007568",
        "tgn:7029392"
    ],
    "tgn:id":2207256,
    "tgn:name":"Bunker Hill",
    "tgn:placetype":[
        "aat:300008798"
    ]
},
  "bbox": [],
  "geometry": {"coordinates":[-77.15,42.9833],"type":"Point"}
}