{
  "id": 2725199,
  "type": "Feature",
  "properties": {
    "tgn:hierarchy":[
        "tgn:2725199",
        "tgn:1000001",
        "tgn:7012149",
        "tgn:2000969",
        "tgn:7007520",
        "tgn:7029392"
    ],
    "tgn:id":2725199,
    "tgn:name":"Tonkin Bay",
    "tgn:placetype":[
        "aat:300132316"
    ]
},
  "bbox": [],
  "geometry": {"coordinates":[-88.5667,48.0833],"type":"Point"}
}