{
  "id": 2365128,
  "type": "Feature",
  "properties": {
    "tgn:hierarchy":[
        "tgn:2365128",
        "tgn:1000001",
        "tgn:7012149",
        "tgn:7007239",
        "tgn:7029392"
    ],
    "tgn:id":2365128,
    "tgn:name":"Greens Branch",
    "tgn:placetype":[
        "aat:300008699"
    ]
},
  "bbox": [],
  "geometry": {"coordinates":[-75.6667,39.2667],"type":"Point"}
}