{
  "id": 7200450,
  "type": "Feature",
  "properties": {
    "tgn:hierarchy":[
        "tgn:7200450",
        "tgn:7003669",
        "tgn:1000003",
        "tgn:7000084",
        "tgn:7029392"
    ],
    "tgn:id":7200450,
    "tgn:name":"Ecknach",
    "tgn:placetype":[
        "aat:300008699"
    ]
},
  "bbox": [],
  "geometry": {"coordinates":[11.133333,48.45],"type":"Point"}
}