{
  "id": 2635300,
  "type": "Feature",
  "properties": {
    "tgn:hierarchy":[
        "tgn:2635300",
        "tgn:1000001",
        "tgn:7012149",
        "tgn:2001304",
        "tgn:7007524",
        "tgn:7029392"
    ],
    "tgn:id":2635300,
    "tgn:name":"S and H Mine",
    "tgn:placetype":[
        "aat:300000390"
    ]
},
  "bbox": [],
  "geometry": {"coordinates":[-114.9333,47.3167],"type":"Point"}
}