{
  "id": 1137644,
  "type": "Feature",
  "properties": {
    "tgn:hierarchy":[
        "tgn:1137644",
        "tgn:1000004",
        "tgn:7011459",
        "tgn:7014786",
        "tgn:7029392"
    ],
    "tgn:id":1137644,
    "tgn:name":"Kiyevka",
    "tgn:placetype":[
        "aat:300008347"
    ]
},
  "bbox": [],
  "geometry": {"coordinates":[71.55,50.25],"type":"Point"}
}