{
  "id": 2451910,
  "type": "Feature",
  "properties": {
    "tgn:hierarchy":[
        "tgn:2451910",
        "tgn:1000001",
        "tgn:7012149",
        "tgn:2000361",
        "tgn:7007248",
        "tgn:7029392"
    ],
    "tgn:id":2451910,
    "tgn:name":"Little Beaverdam Creek",
    "tgn:placetype":[
        "aat:300008706"
    ]
},
  "bbox": [],
  "geometry": {"coordinates":[-82.9833,33.2833],"type":"Point"}
}