{
  "id": 7575976,
  "type": "Feature",
  "properties": {
    "tgn:hierarchy":[
        "tgn:7575976",
        "tgn:1000004",
        "tgn:7000198",
        "tgn:7016788",
        "tgn:7029392"
    ],
    "tgn:id":7575976,
    "tgn:name:en":"K\u0101pren",
    "tgn:placetype":[
        "aat:300008347"
    ]
},
  "bbox": [],
  "geometry": {"coordinates":[76.066667,25.416667],"type":"Point"}
}