{
  "id": 2354746,
  "type": "Feature",
  "properties": {
    "tgn:hierarchy":[
        "tgn:2354746",
        "tgn:1000001",
        "tgn:2001417",
        "tgn:7012149",
        "tgn:7007526",
        "tgn:7029392"
    ],
    "tgn:id":2354746,
    "tgn:name":"Good Hope Number 2 Mine",
    "tgn:placetype":[
        "aat:300000390"
    ]
},
  "bbox": [],
  "geometry": {"coordinates":[-118.4167,38.4833],"type":"Point"}
}