{
  "id": 7495579,
  "type": "Feature",
  "properties": {
    "tgn:hierarchy":[
        "tgn:7495579",
        "tgn:7487020",
        "tgn:1000004",
        "tgn:1000141",
        "tgn:7029392"
    ],
    "tgn:id":7495579,
    "tgn:name":"Gui'an Qiao",
    "tgn:placetype":[
        "aat:300007836"
    ]
},
  "bbox": [],
  "geometry": {"coordinates":[120.841743,24.351264],"type":"Point"}
}