{
  "id": 1024511,
  "type": "Feature",
  "properties": {
    "tgn:hierarchy":[
        "tgn:1024511",
        "tgn:1000726",
        "tgn:1000002",
        "tgn:1000056",
        "tgn:7029392"
    ],
    "tgn:id":1024511,
    "tgn:name":"Huach\u00f3n",
    "tgn:placetype":[
        "aat:300008347"
    ]
},
  "bbox": [],
  "geometry": {"coordinates":[-75.95,-10.6667],"type":"Point"}
}