{
  "id": 2757096,
  "type": "Feature",
  "properties": {
    "tgn:hierarchy":[
        "tgn:2757096",
        "tgn:1000001",
        "tgn:7012149",
        "tgn:2001274",
        "tgn:7007524",
        "tgn:7029392"
    ],
    "tgn:id":2757096,
    "tgn:name":"Werner Creek",
    "tgn:placetype":[
        "aat:300008706"
    ]
},
  "bbox": [],
  "geometry": {"coordinates":[-114.4167,48.5833],"type":"Point"}
}