{
  "id": 2451742,
  "type": "Feature",
  "properties": {
    "tgn:hierarchy":[
        "tgn:2451742",
        "tgn:1000001",
        "tgn:2002103",
        "tgn:7012149",
        "tgn:7007827",
        "tgn:7029392"
    ],
    "tgn:id":2451742,
    "tgn:name":"Little Bear Pond",
    "tgn:placetype":[
        "aat:300008680"
    ]
},
  "bbox": [],
  "geometry": {"coordinates":[-111.5167,41.8667],"type":"Point"}
}