{
  "id": 1029360,
  "type": "Feature",
  "properties": {
    "tgn:hierarchy":[
        "tgn:1029360",
        "tgn:7002445",
        "tgn:1000003",
        "tgn:1003654",
        "tgn:7008591",
        "tgn:7029392"
    ],
    "tgn:id":1029360,
    "tgn:name:en":"Grays",
    "tgn:placetype":[
        "aat:300008347",
        "aat:300387220",
        "aat:300008375"
    ]
},
  "bbox": [],
  "geometry": {"coordinates":[0.333333,51.483333],"type":"Point"}
}