{
  "id": 2417431,
  "type": "Feature",
  "properties": {
    "tgn:hierarchy":[
        "tgn:2417431",
        "tgn:7006450",
        "tgn:1000001",
        "tgn:7012149",
        "tgn:2000086",
        "tgn:7029392"
    ],
    "tgn:id":2417431,
    "tgn:name":"Jacksina Creek",
    "tgn:placetype":[
        "aat:300008706"
    ]
},
  "bbox": [],
  "geometry": {"coordinates":[-143.3833,62.1167],"type":"Point"}
}