{
  "id": 1135942,
  "type": "Feature",
  "properties": {
    "tgn:hierarchy":[
        "tgn:1135942",
        "tgn:1000003",
        "tgn:1000063",
        "tgn:7029392"
    ],
    "tgn:id":1135942,
    "tgn:name":"IJzerkanaal",
    "tgn:placetype":[
        "aat:300006075"
    ]
},
  "bbox": [],
  "geometry": {"coordinates":[2.8833,50.85],"type":"Point"}
}