{
  "id": 2404150,
  "type": "Feature",
  "properties": {
    "tgn:hierarchy":[
        "tgn:2404150",
        "tgn:1000001",
        "tgn:7006451",
        "tgn:7012149",
        "tgn:2000098",
        "tgn:7029392"
    ],
    "tgn:id":2404150,
    "tgn:name":"Howland Point",
    "tgn:placetype":[
        "aat:300008850"
    ]
},
  "bbox": [],
  "geometry": {"coordinates":[-114.0667,36.15],"type":"Point"}
}