{
  "id": 2711596,
  "type": "Feature",
  "properties": {
    "tgn:hierarchy":[
        "tgn:2711596",
        "tgn:1000001",
        "tgn:2001632",
        "tgn:7012149",
        "tgn:7007707",
        "tgn:7029392"
    ],
    "tgn:id":2711596,
    "tgn:name":"Tar Branch",
    "tgn:placetype":[
        "aat:300008699"
    ]
},
  "bbox": [],
  "geometry": {"coordinates":[-97.3667,34.4333],"type":"Point"}
}