<<<<<<< HEAD
{
  "id": 7482868,
  "type": "Feature",
  "properties": {
    "tgn:hierarchy":[
        "tgn:7482868",
        "tgn:1000004",
        "tgn:7001009",
        "tgn:1000141",
        "tgn:7029392"
    ],
    "tgn:id":7482868,
    "tgn:name":"Xining Guoxiao",
    "tgn:placetype":[
        "aat:300006495"
    ]
},
  "bbox": [],
  "geometry": {"coordinates":[120.575,24.276389],"type":"Point"}
}
=======
{"geometry":{"type":"Point","coordinates":[120.575000,24.276389]},"type":"Feature","properties":{"hierarchy":["tgn:7482868","tgn:1000004","tgn:7001009","tgn:1000141","tgn:7029392"],"placetype":["aat:300006495"],"id":7482868,"name:xx":"Xining Guoxiao"}}
>>>>>>> 03f74aca74312dbeaf24d7e61306dd6a786dc3d0
