{
  "id": 1132584,
  "type": "Feature",
  "properties": {
    "tgn:hierarchy":[
        "tgn:1132584",
        "tgn:1000001",
        "tgn:7012149",
        "tgn:1002682",
        "tgn:7007710",
        "tgn:7029392"
    ],
    "tgn:id":1132584,
    "tgn:name":"Brodhead Creek",
    "tgn:placetype":[
        "aat:300008706"
    ]
},
  "bbox": [],
  "geometry": {"coordinates":[-75.25,41.1833],"type":"Point"}
}