<<<<<<< HEAD
{
  "id": 7486846,
  "type": "Feature",
  "properties": {
    "tgn:hierarchy":[
        "tgn:7486846",
        "tgn:1000004",
        "tgn:1000454",
        "tgn:1000141",
        "tgn:7029392"
    ],
    "tgn:id":7486846,
    "tgn:name":"Bailiujiading",
    "tgn:placetype":[
        "aat:300387200"
    ]
},
  "bbox": [],
  "geometry": {"coordinates":[121.5,25.2],"type":"Point"}
}
=======
{"geometry":{"type":"Point","coordinates":[121.500000,25.200000]},"type":"Feature","properties":{"hierarchy":["tgn:7486846","tgn:1000004","tgn:1000454","tgn:1000141","tgn:7029392"],"placetype":["aat:300387200"],"id":7486846,"name:xx":"Bailiujiading"}}
>>>>>>> 03f74aca74312dbeaf24d7e61306dd6a786dc3d0
