{
  "id": 1101109,
  "type": "Feature",
  "properties": {
    "tgn:hierarchy":[
        "tgn:1101109",
        "tgn:1000001",
        "tgn:7012149",
        "tgn:1002689",
        "tgn:7007706",
        "tgn:7029392"
    ],
    "tgn:id":1101109,
    "tgn:name":"Englewood Dam",
    "tgn:placetype":[
        "aat:300006084"
    ]
},
  "bbox": [],
  "geometry": {"coordinates":[-84.2833,39.8667],"type":"Point"}
}