{
  "id": 2440541,
  "type": "Feature",
  "properties": {
    "tgn:hierarchy":[
        "tgn:2440541",
        "tgn:1000001",
        "tgn:7012149",
        "tgn:2000991",
        "tgn:7007520",
        "tgn:7029392"
    ],
    "tgn:id":2440541,
    "tgn:name":"Knappen Creek",
    "tgn:placetype":[
        "aat:300008706"
    ]
},
  "bbox": [],
  "geometry": {"coordinates":[-84.6167,44.2667],"type":"Point"}
}