<<<<<<< HEAD
{
  "id": 7482001,
  "type": "Feature",
  "properties": {
    "tgn:hierarchy":[
        "tgn:7482001",
        "tgn:1000004",
        "tgn:7490934",
        "tgn:1000141",
        "tgn:7029392"
    ],
    "tgn:id":7482001,
    "tgn:name":"Yupao Shan",
    "tgn:placetype":[
        "aat:300008777"
    ]
},
  "bbox": [],
  "geometry": {"coordinates":[120.42566,23.074263],"type":"Point"}
}
=======
{"geometry":{"type":"Point","coordinates":[120.425660,23.074263]},"type":"Feature","properties":{"hierarchy":["tgn:7482001","tgn:1000004","tgn:7490934","tgn:1000141","tgn:7029392"],"placetype":["aat:300008777"],"id":7482001,"name:xx":"Yupao Shan"}}
>>>>>>> 03f74aca74312dbeaf24d7e61306dd6a786dc3d0
