{
  "id": 7482001,
  "type": "Feature",
  "properties": {
    "tgn:hierarchy":[
        "tgn:7482001",
        "tgn:1000004",
        "tgn:7490934",
        "tgn:1000141",
        "tgn:7029392"
    ],
    "tgn:id":7482001,
    "tgn:name":"Yupao Shan",
    "tgn:placetype":[
        "aat:300008777"
    ]
},
  "bbox": [],
  "geometry": {"coordinates":[120.42566,23.074263],"type":"Point"}
}