{
  "id": 2531350,
  "type": "Feature",
  "properties": {
    "tgn:hierarchy":[
        "tgn:2531350",
        "tgn:1000001",
        "tgn:2000464",
        "tgn:7012149",
        "tgn:7007250",
        "tgn:7029392"
    ],
    "tgn:id":2531350,
    "tgn:name":"Mule Creek",
    "tgn:placetype":[
        "aat:300008706"
    ]
},
  "bbox": [],
  "geometry": {"coordinates":[-114.75,43.7833],"type":"Point"}
}