{
  "id": 2164721,
  "type": "Feature",
  "properties": {
    "tgn:hierarchy":[
        "tgn:2164721",
        "tgn:1000001",
        "tgn:2001016",
        "tgn:7012149",
        "tgn:7007521",
        "tgn:7029392"
    ],
    "tgn:id":2164721,
    "tgn:name":"Bertha Lake",
    "tgn:placetype":[
        "aat:300008680"
    ]
},
  "bbox": [],
  "geometry": {"coordinates":[-94.25,46.65],"type":"Point"}
}