{
  "id": 2741677,
  "type": "Feature",
  "properties": {
    "tgn:hierarchy":[
        "tgn:2741677",
        "tgn:1000001",
        "tgn:7012149",
        "tgn:2001452",
        "tgn:7007566",
        "tgn:7029392"
    ],
    "tgn:id":2741677,
    "tgn:name":"Ute Dome",
    "tgn:placetype":[
        "aat:300008798"
    ]
},
  "bbox": [],
  "geometry": {"coordinates":[-108.25,36.85],"type":"Point"}
}