{
  "id": 2764790,
  "type": "Feature",
  "properties": {
    "tgn:hierarchy":[
        "tgn:2764790",
        "tgn:1000001",
        "tgn:7012149",
        "tgn:2000488",
        "tgn:7007250",
        "tgn:7029392"
    ],
    "tgn:id":2764790,
    "tgn:name":"Whiskey Draw",
    "tgn:placetype":[
        "aat:300008761"
    ]
},
  "bbox": [],
  "geometry": {"coordinates":[-115.8667,42.0167],"type":"Point"}
}