<<<<<<< HEAD
{
  "id": 2764790,
  "type": "Feature",
  "properties": {
    "tgn:hierarchy":[
        "tgn:2764790",
        "tgn:1000001",
        "tgn:7012149",
        "tgn:2000488",
        "tgn:7007250",
        "tgn:7029392"
    ],
    "tgn:id":2764790,
    "tgn:name":"Whiskey Draw",
    "tgn:placetype":[
        "aat:300008761"
    ]
},
  "bbox": [],
  "geometry": {"coordinates":[-115.8667,42.0167],"type":"Point"}
}
=======
{"geometry":{"type":"Point","coordinates":[-115.866700,42.016700]},"type":"Feature","properties":{"hierarchy":["tgn:2764790","tgn:1000001","tgn:7012149","tgn:2000488","tgn:7007250","tgn:7029392"],"placetype":["aat:300008761"],"id":2764790,"name:xx":"Whiskey Draw"}}
>>>>>>> 03f74aca74312dbeaf24d7e61306dd6a786dc3d0
