{
  "id": 2541598,
  "type": "Feature",
  "properties": {
    "tgn:hierarchy":[
        "tgn:2541598",
        "tgn:1000001",
        "tgn:7012149",
        "tgn:2000784",
        "tgn:7007255",
        "tgn:7029392"
    ],
    "tgn:id":2541598,
    "tgn:name":"Nine Acre Mine",
    "tgn:placetype":[
        "aat:300000390"
    ]
},
  "bbox": [],
  "geometry": {"coordinates":[-88.15,37.35],"type":"Point"}
}