{
  "id": 7294895,
  "type": "Feature",
  "properties": {
    "tgn:hierarchy":[
        "tgn:7294895",
        "tgn:7002824",
        "tgn:1000003",
        "tgn:7002786",
        "tgn:1000095",
        "tgn:7029392"
    ],
    "tgn:id":7294895,
    "tgn:name":"S\u00e1lvora, Isla",
    "tgn:placetype":[
        "aat:300008791"
    ]
},
  "bbox": [],
  "geometry": {"coordinates":[-9.016667,42.483333],"type":"Point"}
}