{
  "id": 7330200,
  "type": "Feature",
  "properties": {
    "tgn:hierarchy":[
        "tgn:7330200",
        "tgn:7002810",
        "tgn:7001158",
        "tgn:1000003",
        "tgn:1000095",
        "tgn:7029392"
    ],
    "tgn:id":7330200,
    "tgn:name":"Hornillayuso",
    "tgn:placetype":[
        "aat:300008347"
    ]
},
  "bbox": [],
  "geometry": {"coordinates":[-3.583333,43.016667],"type":"Point"}
}