{
  "id": 2164276,
  "type": "Feature",
  "properties": {
    "tgn:hierarchy":[
        "tgn:2164276",
        "tgn:1000001",
        "tgn:1002270",
        "tgn:7012149",
        "tgn:7007708",
        "tgn:7029392"
    ],
    "tgn:id":2164276,
    "tgn:name":"Berrenth Quarry",
    "tgn:placetype":[
        "aat:300000390"
    ]
},
  "bbox": [],
  "geometry": {"coordinates":[-122.5833,45.0833],"type":"Point"}
}