{
  "id": 2668875,
  "type": "Feature",
  "properties": {
    "tgn:hierarchy":[
        "tgn:2668875",
        "tgn:1000001",
        "tgn:7012149",
        "tgn:1002464",
        "tgn:7007826",
        "tgn:7029392"
    ],
    "tgn:id":2668875,
    "tgn:name":"Slaughter Lake",
    "tgn:placetype":[
        "aat:300008680"
    ]
},
  "bbox": [],
  "geometry": {"coordinates":[-95.85,32.0833],"type":"Point"}
}