{
  "id": 2655608,
  "type": "Feature",
  "properties": {
    "tgn:hierarchy":[
        "tgn:2655608",
        "tgn:1000001",
        "tgn:7012149",
        "tgn:1002331",
        "tgn:7007826",
        "tgn:7029392"
    ],
    "tgn:id":2655608,
    "tgn:name":"Sharps Branch",
    "tgn:placetype":[
        "aat:300008699"
    ]
},
  "bbox": [],
  "geometry": {"coordinates":[-97.1333,33.0667],"type":"Point"}
}