{
  "id": 7253612,
  "type": "Feature",
  "properties": {
    "tgn:hierarchy":[
        "tgn:7253612",
        "tgn:7003457",
        "tgn:1000003",
        "tgn:1000063",
        "tgn:7018236",
        "tgn:7029392"
    ],
    "tgn:id":7253612,
    "tgn:name":"Snepbeke",
    "tgn:placetype":[
        "aat:300008699"
    ]
},
  "bbox": [],
  "geometry": {"coordinates":[3.533333,50.833333],"type":"Point"}
}