{
  "id": 2311791,
  "type": "Feature",
  "properties": {
    "tgn:hierarchy":[
        "tgn:2311791",
        "tgn:1000001",
        "tgn:7012149",
        "tgn:2001909",
        "tgn:7007825",
        "tgn:7029392"
    ],
    "tgn:id":2311791,
    "tgn:name":"Edwards Spring",
    "tgn:placetype":[
        "aat:300008697"
    ]
},
  "bbox": [],
  "geometry": {"coordinates":[-84.4333,35.9167],"type":"Point"}
}