{
  "id": 7512691,
  "type": "Feature",
  "properties": {
    "tgn:hierarchy":[
        "tgn:7512691",
        "tgn:1009227",
        "tgn:1000226",
        "tgn:7018437",
        "tgn:1000006",
        "tgn:7029392"
    ],
    "tgn:id":7512691,
    "tgn:name:en":"Hillend",
    "tgn:placetype":[
        "aat:300008347"
    ]
},
  "bbox": [],
  "geometry": {"coordinates":[169.75,-46.133333],"type":"Point"}
}