{
  "id": 2378680,
  "type": "Feature",
  "properties": {
    "tgn:hierarchy":[
        "tgn:2378680",
        "tgn:1000001",
        "tgn:7012149",
        "tgn:2002113",
        "tgn:7007827",
        "tgn:7029392"
    ],
    "tgn:id":2378680,
    "tgn:name":"Harry Colwes Draw",
    "tgn:placetype":[
        "aat:300008761"
    ]
},
  "bbox": [],
  "geometry": {"coordinates":[-111.1167,37.25],"type":"Point"}
}