{
  "id": 2354700,
  "type": "Feature",
  "properties": {
    "tgn:hierarchy":[
        "tgn:2354700",
        "tgn:1000001",
        "tgn:7012149",
        "tgn:2000971",
        "tgn:7007520",
        "tgn:7029392"
    ],
    "tgn:id":2354700,
    "tgn:name":"Good Harbor Bay",
    "tgn:placetype":[
        "aat:300132316"
    ]
},
  "bbox": [],
  "geometry": {"coordinates":[-85.8333,44.95],"type":"Point"}
}