{
  "id": 2366088,
  "type": "Feature",
  "properties": {
    "tgn:hierarchy":[
        "tgn:2366088",
        "tgn:1000001",
        "tgn:7012149",
        "tgn:2000491",
        "tgn:7007250",
        "tgn:7029392"
    ],
    "tgn:id":2366088,
    "tgn:name":"Grice Ridge",
    "tgn:placetype":[
        "aat:300266640"
    ]
},
  "bbox": [],
  "geometry": {"coordinates":[-116.0667,46.95],"type":"Point"}
}