<<<<<<< HEAD
{
  "id": 2337807,
  "type": "Feature",
  "properties": {
    "tgn:hierarchy":[
        "tgn:2337807",
        "tgn:1000001",
        "tgn:7012149",
        "tgn:2001251",
        "tgn:7007523",
        "tgn:7029392"
    ],
    "tgn:id":2337807,
    "tgn:name":"Fox Creek Hollow",
    "tgn:placetype":[
        "aat:300008761"
    ]
},
  "bbox": [],
  "geometry": {"coordinates":[-93.15,36.55],"type":"Point"}
}
=======
{"geometry":{"type":"Point","coordinates":[-93.150000,36.550000]},"type":"Feature","properties":{"hierarchy":["tgn:2337807","tgn:1000001","tgn:7012149","tgn:2001251","tgn:7007523","tgn:7029392"],"placetype":["aat:300008761"],"id":2337807,"name:xx":"Fox Creek Hollow"}}
>>>>>>> 03f74aca74312dbeaf24d7e61306dd6a786dc3d0
