{
  "id": 2204709,
  "type": "Feature",
  "properties": {
    "tgn:hierarchy":[
        "tgn:2204709",
        "tgn:1000001",
        "tgn:7012149",
        "tgn:2000220",
        "tgn:7007158",
        "tgn:7029392"
    ],
    "tgn:id":2204709,
    "tgn:name":"Buffalo Peak",
    "tgn:placetype":[
        "aat:300008798"
    ]
},
  "bbox": [],
  "geometry": {"coordinates":[-106.3333,40.4667],"type":"Point"}
}