<<<<<<< HEAD
{
  "id": 2150872,
  "type": "Feature",
  "properties": {
    "tgn:hierarchy":[
        "tgn:2150872",
        "tgn:1000001",
        "tgn:7012149",
        "tgn:2002336",
        "tgn:7007922",
        "tgn:7029392"
    ],
    "tgn:id":2150872,
    "tgn:name":"Bass Lake",
    "tgn:placetype":[
        "aat:300008680"
    ]
},
  "bbox": [],
  "geometry": {"coordinates":[-89.3167,44.85],"type":"Point"}
}
=======
{"geometry":{"type":"Point","coordinates":[-89.316700,44.850000]},"type":"Feature","properties":{"hierarchy":["tgn:2150872","tgn:1000001","tgn:7012149","tgn:2002336","tgn:7007922","tgn:7029392"],"placetype":["aat:300008680"],"id":2150872,"name:xx":"Bass Lake"}}
>>>>>>> 03f74aca74312dbeaf24d7e61306dd6a786dc3d0
