{
  "id": 2519767,
  "type": "Feature",
  "properties": {
    "tgn:hierarchy":[
        "tgn:2519767",
        "tgn:1000001",
        "tgn:7012149",
        "tgn:2001106",
        "tgn:7007522",
        "tgn:7029392"
    ],
    "tgn:id":2519767,
    "tgn:name":"Mohoba",
    "tgn:placetype":[
        "aat:300008347"
    ]
},
  "bbox": [],
  "geometry": {"coordinates":[-88.45,31.0667],"type":"Point"}
}