{
  "id": 7489080,
  "type": "Feature",
  "properties": {
    "tgn:hierarchy":[
        "tgn:7489080",
        "tgn:7488858",
        "tgn:1000004",
        "tgn:1000141",
        "tgn:7029392"
    ],
    "tgn:id":7489080,
    "tgn:name":"Yizhuang",
    "tgn:placetype":[
        "aat:300008347"
    ]
},
  "bbox": [],
  "geometry": {"coordinates":[121.166667,24.05],"type":"Point"}
}