<<<<<<< HEAD
{
  "id": 7489080,
  "type": "Feature",
  "properties": {
    "tgn:hierarchy":[
        "tgn:7489080",
        "tgn:7488858",
        "tgn:1000004",
        "tgn:1000141",
        "tgn:7029392"
    ],
    "tgn:id":7489080,
    "tgn:name":"Yizhuang",
    "tgn:placetype":[
        "aat:300008347"
    ]
},
  "bbox": [],
  "geometry": {"coordinates":[121.166667,24.05],"type":"Point"}
}
=======
{"geometry":{"type":"Point","coordinates":[121.166667,24.050000]},"type":"Feature","properties":{"hierarchy":["tgn:7489080","tgn:7488858","tgn:1000004","tgn:1000141","tgn:7029392"],"placetype":["aat:300008347"],"id":7489080,"name:xx":"Yizhuang"}}
>>>>>>> 03f74aca74312dbeaf24d7e61306dd6a786dc3d0
