{
  "id": 2092940,
  "type": "Feature",
  "properties": {
    "tgn:hierarchy":[
        "tgn:2092940",
        "tgn:1000001",
        "tgn:7012149",
        "tgn:1002690",
        "tgn:7007710",
        "tgn:7029392"
    ],
    "tgn:id":2092940,
    "tgn:name":"Shainline",
    "tgn:placetype":[
        "aat:300387016"
    ]
},
  "bbox": [],
  "geometry": {"coordinates":[-75.35,40.0833],"type":"Point"}
}