{
  "id": 2742966,
  "type": "Feature",
  "properties": {
    "tgn:hierarchy":[
        "tgn:2742966",
        "tgn:1000001",
        "tgn:7012149",
        "tgn:7013855",
        "tgn:7007251",
        "tgn:7029392"
    ],
    "tgn:id":2742966,
    "tgn:name":"Van Patten Woods Forest Preserve",
    "tgn:placetype":[
        "aat:300008863"
    ]
},
  "bbox": [],
  "geometry": {"coordinates":[-87.9333,42.4667],"type":"Point"}
}