{
  "id": 7378478,
  "type": "Feature",
  "properties": {
    "tgn:hierarchy":[
        "tgn:7378478",
        "tgn:1000001",
        "tgn:7005589",
        "tgn:7005560",
        "tgn:7029392"
    ],
    "tgn:id":7378478,
    "tgn:name:es":"La Presa de San Carlos",
    "tgn:placetype":[
        "aat:300008347"
    ]
},
  "bbox": [],
  "geometry": {"coordinates":[-99.981111,23.588889],"type":"Point"}
}