{
  "id": 7565471,
  "type": "Feature",
  "properties": {
    "tgn:hierarchy":[
        "tgn:7565471",
        "tgn:1000004",
        "tgn:7000198",
        "tgn:7016722",
        "tgn:7029392"
    ],
    "tgn:id":7565471,
    "tgn:name:en":"Rond\u0101pur",
    "tgn:placetype":[
        "aat:300008347"
    ]
},
  "bbox": [],
  "geometry": {"coordinates":[79.523761,26.810691],"type":"Point"}
}