{
  "id": 2218520,
  "type": "Feature",
  "properties": {
    "tgn:hierarchy":[
        "tgn:2218520",
        "tgn:1000001",
        "tgn:7012149",
        "tgn:2001750",
        "tgn:7007712",
        "tgn:7029392"
    ],
    "tgn:id":2218520,
    "tgn:name":"Cane Branch",
    "tgn:placetype":[
        "aat:300008699"
    ]
},
  "bbox": [],
  "geometry": {"coordinates":[-78.95,34.0167],"type":"Point"}
}