{
  "id": 2037651,
  "type": "Feature",
  "properties": {
    "tgn:hierarchy":[
        "tgn:2037651",
        "tgn:1000001",
        "tgn:1002189",
        "tgn:7012149",
        "tgn:7007255",
        "tgn:7029392"
    ],
    "tgn:id":2037651,
    "tgn:name":"Beaverlick",
    "tgn:placetype":[
        "aat:300008347"
    ]
},
  "bbox": [],
  "geometry": {"coordinates":[-84.6833,38.8667],"type":"Point"}
}