{
  "id": 7502416,
  "type": "Feature",
  "properties": {
    "tgn:hierarchy":[
        "tgn:7502416",
        "tgn:7001010",
        "tgn:1000004",
        "tgn:1000141",
        "tgn:7029392"
    ],
    "tgn:id":7502416,
    "tgn:name":"Fengbin Xiang Diyi Gongmu",
    "tgn:placetype":[
        "aat:300266755"
    ]
},
  "bbox": [],
  "geometry": {"coordinates":[121.527778,23.596389],"type":"Point"}
}