{
  "id": 2385930,
  "type": "Feature",
  "properties": {
    "tgn:hierarchy":[
        "tgn:2385930",
        "tgn:1000001",
        "tgn:7012149",
        "tgn:1002838",
        "tgn:7007252",
        "tgn:7029392"
    ],
    "tgn:id":2385930,
    "tgn:name":"Henry",
    "tgn:placetype":[
        "aat:300008347"
    ]
},
  "bbox": [],
  "geometry": {"coordinates":[-85.5833,39.7833],"type":"Point"}
}