{
  "id": 7494992,
  "type": "Feature",
  "properties": {
    "tgn:hierarchy":[
        "tgn:7494992",
        "tgn:7468018",
        "tgn:1000004",
        "tgn:1000141",
        "tgn:7029392"
    ],
    "tgn:id":7494992,
    "tgn:name":"Toujiazhuang",
    "tgn:placetype":[
        "aat:300000745"
    ]
},
  "bbox": [],
  "geometry": {"coordinates":[120.460613,23.60229],"type":"Point"}
}