{
  "id": 7551213,
  "type": "Feature",
  "properties": {
    "tgn:hierarchy":[
        "tgn:7551213",
        "tgn:7001819",
        "tgn:1000004",
        "tgn:7000198",
        "tgn:7029392"
    ],
    "tgn:id":7551213,
    "tgn:name:en":"Chemir",
    "tgn:placetype":[
        "aat:300008347"
    ]
},
  "bbox": [],
  "geometry": {"coordinates":[94.01835,27.730069],"type":"Point"}
}