{
  "id": 7476603,
  "type": "Feature",
  "properties": {
    "tgn:hierarchy":[
        "tgn:7476603",
        "tgn:7487020",
        "tgn:1000004",
        "tgn:1000141",
        "tgn:7029392"
    ],
    "tgn:id":7476603,
    "tgn:name":"Beiping",
    "tgn:placetype":[
        "aat:300008347"
    ]
},
  "bbox": [],
  "geometry": {"coordinates":[120.892685,24.590254],"type":"Point"}
}