{
  "id": 7213325,
  "type": "Feature",
  "properties": {
    "tgn:hierarchy":[
        "tgn:7213325",
        "tgn:7000096",
        "tgn:1000003",
        "tgn:7000084",
        "tgn:7029392"
    ],
    "tgn:id":7213325,
    "tgn:name":"Biebersdorf",
    "tgn:placetype":[
        "aat:300008347"
    ]
},
  "bbox": [],
  "geometry": {"coordinates":[13.966667,51.983333],"type":"Point"}
}