{
  "id": 2358517,
  "type": "Feature",
  "properties": {
    "tgn:hierarchy":[
        "tgn:2358517",
        "tgn:1000001",
        "tgn:7014449",
        "tgn:7012149",
        "tgn:7007565",
        "tgn:7029392"
    ],
    "tgn:id":2358517,
    "tgn:name":"Grandad Meadows",
    "tgn:placetype":[
        "aat:300008905"
    ]
},
  "bbox": [],
  "geometry": {"coordinates":[-75.4167,39.3833],"type":"Point"}
}