{
  "id": 1090401,
  "type": "Feature",
  "properties": {
    "tgn:hierarchy":[
        "tgn:1090401",
        "tgn:7001242",
        "tgn:1000539",
        "tgn:1000168",
        "tgn:7029392"
    ],
    "tgn:id":1090401,
    "tgn:name":"Sianhala",
    "tgn:placetype":[
        "aat:300008347"
    ]
},
  "bbox": [],
  "geometry": {"coordinates":[-6.85,10.05],"type":"Point"}
}