{
  "id": 2457486,
  "type": "Feature",
  "properties": {
    "tgn:hierarchy":[
        "tgn:2457486",
        "tgn:7002659",
        "tgn:1000001",
        "tgn:2000014",
        "tgn:7012149",
        "tgn:7029392"
    ],
    "tgn:id":2457486,
    "tgn:name":"Little Lost Creek",
    "tgn:placetype":[
        "aat:300008706"
    ]
},
  "bbox": [],
  "geometry": {"coordinates":[-85.3667,33.5667],"type":"Point"}
}