{
  "id": 7013192,
  "type": "Feature",
  "properties": {
    "tgn:hierarchy":[
        "tgn:7013192",
        "tgn:7005685",
        "tgn:1000001",
        "tgn:7005804",
        "tgn:7029392"
    ],
    "tgn:id":7013192,
    "tgn:name":"Arvida",
    "tgn:placetype":[
        "aat:300008347",
        "aat:300008375"
    ]
},
  "bbox": [],
  "geometry": {"coordinates":[-71.1333,48.4167],"type":"Point"}
}