<<<<<<< HEAD
{
  "id": 2151921,
  "type": "Feature",
  "properties": {
    "tgn:hierarchy":[
        "tgn:2151921",
        "tgn:1000001",
        "tgn:7012149",
        "tgn:7007710",
        "tgn:7029392"
    ],
    "tgn:id":2151921,
    "tgn:name":"Bauer Creek",
    "tgn:placetype":[
        "aat:300008706"
    ]
},
  "bbox": [],
  "geometry": {"coordinates":[-75.5333,40.9],"type":"Point"}
}
=======
{"geometry":{"type":"Point","coordinates":[-75.533300,40.900000]},"type":"Feature","properties":{"hierarchy":["tgn:2151921","tgn:1000001","tgn:7012149","tgn:7007710","tgn:7029392"],"placetype":["aat:300008706"],"id":2151921,"name:xx":"Bauer Creek"}}
>>>>>>> 03f74aca74312dbeaf24d7e61306dd6a786dc3d0
