{
  "id": 7398484,
  "type": "Feature",
  "properties": {
    "tgn:hierarchy":[
        "tgn:7398484",
        "tgn:1000001",
        "tgn:1001893",
        "tgn:7005560",
        "tgn:7029392"
    ],
    "tgn:id":7398484,
    "tgn:name":"San Pedro Xalpa",
    "tgn:placetype":[
        "aat:300008347"
    ]
},
  "bbox": [],
  "geometry": {"coordinates":[-99.188333,19.823889],"type":"Point"}
}