<<<<<<< HEAD
{
  "id": 2767142,
  "type": "Feature",
  "properties": {
    "tgn:hierarchy":[
        "tgn:2767142",
        "tgn:1000001",
        "tgn:7012149",
        "tgn:2001706",
        "tgn:7007708",
        "tgn:7029392"
    ],
    "tgn:id":2767142,
    "tgn:name":"White Rock Creek",
    "tgn:placetype":[
        "aat:300008706"
    ]
},
  "bbox": [],
  "geometry": {"coordinates":[-123.0333,43.1333],"type":"Point"}
}
=======
{"geometry":{"type":"Point","coordinates":[-123.033300,43.133300]},"type":"Feature","properties":{"hierarchy":["tgn:2767142","tgn:1000001","tgn:7012149","tgn:2001706","tgn:7007708","tgn:7029392"],"placetype":["aat:300008706"],"id":2767142,"name:xx":"White Rock Creek"}}
>>>>>>> 03f74aca74312dbeaf24d7e61306dd6a786dc3d0
