{
  "id": 1078203,
  "type": "Feature",
  "properties": {
    "tgn:hierarchy":[
        "tgn:1078203",
        "tgn:1000004",
        "tgn:1001339",
        "tgn:1000116",
        "tgn:7029392"
    ],
    "tgn:id":1078203,
    "tgn:name":"Nameh",
    "tgn:placetype":[
        "aat:300008347"
    ]
},
  "bbox": [],
  "geometry": {"coordinates":[116.35,2.5667],"type":"Point"}
}