{
  "id": 7404903,
  "type": "Feature",
  "properties": {
    "tgn:hierarchy":[
        "tgn:7404903",
        "tgn:7005585",
        "tgn:1000001",
        "tgn:7005560",
        "tgn:7029392"
    ],
    "tgn:id":7404903,
    "tgn:name":"Tucutuato",
    "tgn:placetype":[
        "aat:300008347"
    ]
},
  "bbox": [],
  "geometry": {"coordinates":[-100.616667,18.491667],"type":"Point"}
}