{
  "id": 7255033,
  "type": "Feature",
  "properties": {
    "tgn:hierarchy":[
        "tgn:7255033",
        "tgn:7018238",
        "tgn:1000003",
        "tgn:1000063",
        "tgn:4012014",
        "tgn:7029392"
    ],
    "tgn:id":7255033,
    "tgn:name":"Tilleul du Ch\u00eane",
    "tgn:placetype":[
        "aat:300008347"
    ]
},
  "bbox": [],
  "geometry": {"coordinates":[4.800737,50.77022],"type":"Point"}
}