{
  "id": 7248784,
  "type": "Feature",
  "properties": {
    "tgn:hierarchy":[
        "tgn:7248784",
        "tgn:7003466",
        "tgn:1000003",
        "tgn:1000063",
        "tgn:4012014",
        "tgn:7029392"
    ],
    "tgn:id":7248784,
    "tgn:name":"Bohan, Bois de",
    "tgn:placetype":[
        "aat:300008863"
    ]
},
  "bbox": [],
  "geometry": {"coordinates":[4.866667,49.85],"type":"Point"}
}