{
  "id": 2641252,
  "type": "Feature",
  "properties": {
    "tgn:hierarchy":[
        "tgn:2641252",
        "tgn:1000001",
        "tgn:7012149",
        "tgn:2000223",
        "tgn:7007158",
        "tgn:7029392"
    ],
    "tgn:id":2641252,
    "tgn:name":"Sand Creek",
    "tgn:placetype":[
        "aat:300008706"
    ]
},
  "bbox": [],
  "geometry": {"coordinates":[-102.5333,39.1167],"type":"Point"}
}