{
  "id": 2380622,
  "type": "Feature",
  "properties": {
    "tgn:hierarchy":[
        "tgn:2380622",
        "tgn:1000001",
        "tgn:2001430",
        "tgn:7012149",
        "tgn:7007566",
        "tgn:7029392"
    ],
    "tgn:id":2380622,
    "tgn:name":"Havens Tank",
    "tgn:placetype":[
        "aat:300006191"
    ]
},
  "bbox": [],
  "geometry": {"coordinates":[-104.1333,33.8333],"type":"Point"}
}