{
  "id": 7180567,
  "type": "Feature",
  "properties": {
    "tgn:hierarchy":[
        "tgn:7180567",
        "tgn:7003669",
        "tgn:1000003",
        "tgn:7000084",
        "tgn:7029392"
    ],
    "tgn:id":7180567,
    "tgn:name":"Gatterberg",
    "tgn:placetype":[
        "aat:300387173"
    ]
},
  "bbox": [],
  "geometry": {"coordinates":[12.183333,48.216667],"type":"Point"}
}