{
  "id": 2456079,
  "type": "Feature",
  "properties": {
    "tgn:hierarchy":[
        "tgn:2456079",
        "tgn:1000001",
        "tgn:1002272",
        "tgn:7012149",
        "tgn:7007710",
        "tgn:7029392"
    ],
    "tgn:id":2456079,
    "tgn:name":"Little Hefren Run",
    "tgn:placetype":[
        "aat:300008699"
    ]
},
  "bbox": [],
  "geometry": {"coordinates":[-79.25,41.3667],"type":"Point"}
}