{
  "id": 2115760,
  "type": "Feature",
  "properties": {
    "tgn:hierarchy":[
        "tgn:2115760",
        "tgn:1000001",
        "tgn:7012149",
        "tgn:2002249",
        "tgn:7007920",
        "tgn:7029392"
    ],
    "tgn:id":2115760,
    "tgn:name":"Fairfield",
    "tgn:placetype":[
        "aat:300008347"
    ]
},
  "bbox": [],
  "geometry": {"coordinates":[-117.1667,47.3833],"type":"Point"}
}