{
  "id": 2708817,
  "type": "Feature",
  "properties": {
    "tgn:hierarchy":[
        "tgn:2708817",
        "tgn:1000001",
        "tgn:7012149",
        "tgn:1003038",
        "tgn:7007517",
        "tgn:7029392"
    ],
    "tgn:id":2708817,
    "tgn:name":"Sylvestri Pond",
    "tgn:placetype":[
        "aat:300006191"
    ]
},
  "bbox": [],
  "geometry": {"coordinates":[-71.9833,42.0667],"type":"Point"}
}