{
  "id": 2625410,
  "type": "Feature",
  "properties": {
    "tgn:hierarchy":[
        "tgn:2625410",
        "tgn:1002808",
        "tgn:1000001",
        "tgn:7012149",
        "tgn:7007711",
        "tgn:7029392"
    ],
    "tgn:id":2625410,
    "tgn:name":"Rockland",
    "tgn:placetype":[
        "aat:300008347"
    ]
},
  "bbox": [],
  "geometry": {"coordinates":[-71.6667,41.7833],"type":"Point"}
}