{
  "id": 1131274,
  "type": "Feature",
  "properties": {
    "tgn:hierarchy":[
        "tgn:1131274",
        "tgn:1002001",
        "tgn:1000047",
        "tgn:7002456",
        "tgn:1000002",
        "tgn:7029392"
    ],
    "tgn:id":1131274,
    "tgn:name":"Urarica\u00e1",
    "tgn:placetype":[
        "aat:300008707"
    ]
},
  "bbox": [],
  "geometry": {"coordinates":[-61.9333,3.3333],"type":"Point"}
}