{
  "id": 7059910,
  "type": "Feature",
  "properties": {
    "tgn:hierarchy":[
        "tgn:7059910",
        "tgn:1000003",
        "tgn:7003677",
        "tgn:7000084",
        "tgn:7029392"
    ],
    "tgn:id":7059910,
    "tgn:name":"Ahausen",
    "tgn:placetype":[
        "aat:300000206"
    ]
},
  "bbox": [],
  "geometry": {"coordinates":[7.95,51.15],"type":"Point"}
}