{
  "id": 2299559,
  "type": "Feature",
  "properties": {
    "tgn:hierarchy":[
        "tgn:2299559",
        "tgn:1000001",
        "tgn:7012149",
        "tgn:1002679",
        "tgn:7007520",
        "tgn:7029392"
    ],
    "tgn:id":2299559,
    "tgn:name":"Duck Pond Drain",
    "tgn:placetype":[
        "aat:300006075"
    ]
},
  "bbox": [],
  "geometry": {"coordinates":[-83.5667,41.8333],"type":"Point"}
}