{
  "id": 2461196,
  "type": "Feature",
  "properties": {
    "tgn:hierarchy":[
        "tgn:2461196",
        "tgn:1000001",
        "tgn:7012149",
        "tgn:7014589",
        "tgn:7007515",
        "tgn:7029392"
    ],
    "tgn:id":2461196,
    "tgn:name":"Little Spruce Island",
    "tgn:placetype":[
        "aat:300008791"
    ]
},
  "bbox": [],
  "geometry": {"coordinates":[-67.5167,44.55],"type":"Point"}
}