{
  "id": 2316781,
  "type": "Feature",
  "properties": {
    "tgn:hierarchy":[
        "tgn:2316781",
        "tgn:1000001",
        "tgn:7012149",
        "tgn:7020792",
        "tgn:7007524",
        "tgn:7029392"
    ],
    "tgn:id":2316781,
    "tgn:name":"Emerald Lake",
    "tgn:placetype":[
        "aat:300008680"
    ]
},
  "bbox": [],
  "geometry": {"coordinates":[-113.2667,46.0167],"type":"Point"}
}