{
  "id": 7550648,
  "type": "Feature",
  "properties": {
    "tgn:hierarchy":[
        "tgn:7550648",
        "tgn:1000004",
        "tgn:7031781",
        "tgn:7000198",
        "tgn:7029392"
    ],
    "tgn:id":7550648,
    "tgn:name:en":"Dhurkot",
    "tgn:placetype":[
        "aat:300008347"
    ]
},
  "bbox": [],
  "geometry": {"coordinates":[82.613761,21.938467],"type":"Point"}
}