{
  "id": 7335264,
  "type": "Feature",
  "properties": {
    "tgn:hierarchy":[
        "tgn:7335264",
        "tgn:7007088",
        "tgn:1000003",
        "tgn:7009604",
        "tgn:1000095",
        "tgn:7029392"
    ],
    "tgn:id":7335264,
    "tgn:name":"Gordoa",
    "tgn:placetype":[
        "aat:300008347"
    ]
},
  "bbox": [],
  "geometry": {"coordinates":[-2.382952,42.901998],"type":"Point"}
}