{
  "id": 7141445,
  "type": "Feature",
  "properties": {
    "tgn:hierarchy":[
        "tgn:7141445",
        "tgn:1000003",
        "tgn:7003676",
        "tgn:7000084",
        "tgn:7029392"
    ],
    "tgn:id":7141445,
    "tgn:name":"Lintelner St\u00fch",
    "tgn:placetype":[
        "aat:300008863"
    ]
},
  "bbox": [],
  "geometry": {"coordinates":[9.35,52.95],"type":"Point"}
}