<<<<<<< HEAD
{
  "id": 2332145,
  "type": "Feature",
  "properties": {
    "tgn:hierarchy":[
        "tgn:2332145",
        "tgn:1000001",
        "tgn:7012149",
        "tgn:2002161",
        "tgn:7007919",
        "tgn:7029392"
    ],
    "tgn:id":2332145,
    "tgn:name":"Flint Ridge",
    "tgn:placetype":[
        "aat:300266640"
    ]
},
  "bbox": [],
  "geometry": {"coordinates":[-78.3,39.2167],"type":"Point"}
}
=======
{"geometry":{"type":"Point","coordinates":[-78.300000,39.216700]},"type":"Feature","properties":{"hierarchy":["tgn:2332145","tgn:1000001","tgn:7012149","tgn:2002161","tgn:7007919","tgn:7029392"],"placetype":["aat:300266640"],"id":2332145,"name:xx":"Flint Ridge"}}
>>>>>>> 03f74aca74312dbeaf24d7e61306dd6a786dc3d0
