{
  "id": 2053597,
  "type": "Feature",
  "properties": {
    "tgn:hierarchy":[
        "tgn:2053597",
        "tgn:1000001",
        "tgn:7012149",
        "tgn:2000983",
        "tgn:7007520",
        "tgn:7029392"
    ],
    "tgn:id":2053597,
    "tgn:name":"Volney",
    "tgn:placetype":[
        "aat:300008347",
        "aat:300387210"
    ]
},
  "bbox": [],
  "geometry": {"coordinates":[-86.0167,43.6833],"type":"Point"}
}