{
  "id": 2379520,
  "type": "Feature",
  "properties": {
    "tgn:hierarchy":[
        "tgn:2379520",
        "tgn:1000001",
        "tgn:2000873",
        "tgn:7012149",
        "tgn:7007256",
        "tgn:7029392"
    ],
    "tgn:id":2379520,
    "tgn:name":"Harveys Lake",
    "tgn:placetype":[
        "aat:300006191"
    ]
},
  "bbox": [],
  "geometry": {"coordinates":[-92.3333,30.8333],"type":"Point"}
}