<<<<<<< HEAD
{
  "id": 2334065,
  "type": "Feature",
  "properties": {
    "tgn:hierarchy":[
        "tgn:2334065",
        "tgn:2002305",
        "tgn:1000001",
        "tgn:7012149",
        "tgn:7007922",
        "tgn:7029392"
    ],
    "tgn:id":2334065,
    "tgn:name":"Fordham Creek",
    "tgn:placetype":[
        "aat:300008706"
    ]
},
  "bbox": [],
  "geometry": {"coordinates":[-89.6833,43.9833],"type":"Point"}
}
=======
{"geometry":{"type":"Point","coordinates":[-89.683300,43.983300]},"type":"Feature","properties":{"hierarchy":["tgn:2334065","tgn:2002305","tgn:1000001","tgn:7012149","tgn:7007922","tgn:7029392"],"placetype":["aat:300008706"],"id":2334065,"name:xx":"Fordham Creek"}}
>>>>>>> 03f74aca74312dbeaf24d7e61306dd6a786dc3d0
