{
  "id": 2714131,
  "type": "Feature",
  "properties": {
    "tgn:hierarchy":[
        "tgn:2714131",
        "tgn:1000001",
        "tgn:7012149",
        "tgn:2001709",
        "tgn:7007708",
        "tgn:7029392"
    ],
    "tgn:id":2714131,
    "tgn:name":"Telephone Butte",
    "tgn:placetype":[
        "aat:300008798"
    ]
},
  "bbox": [],
  "geometry": {"coordinates":[-118.8167,43.8167],"type":"Point"}
}