{
  "id": 2162095,
  "type": "Feature",
  "properties": {
    "tgn:hierarchy":[
        "tgn:2162095",
        "tgn:7020393",
        "tgn:1000001",
        "tgn:7012149",
        "tgn:7007705",
        "tgn:7029392"
    ],
    "tgn:id":2162095,
    "tgn:name":"Belmar",
    "tgn:placetype":[
        "aat:300008347"
    ]
},
  "bbox": [],
  "geometry": {"coordinates":[-100.3167,48.65],"type":"Point"}
}