{
  "id": 2380723,
  "type": "Feature",
  "properties": {
    "tgn:hierarchy":[
        "tgn:2380723",
        "tgn:1000001",
        "tgn:7012149",
        "tgn:1002787",
        "tgn:7007523",
        "tgn:7029392"
    ],
    "tgn:id":2380723,
    "tgn:name":"Haw Creek",
    "tgn:placetype":[
        "aat:300008706"
    ]
},
  "bbox": [],
  "geometry": {"coordinates":[-91.2667,39.4833],"type":"Point"}
}