{
  "id": 2037610,
  "type": "Feature",
  "properties": {
    "tgn:hierarchy":[
        "tgn:2037610",
        "tgn:1000001",
        "tgn:7012149",
        "tgn:2000804",
        "tgn:7007255",
        "tgn:7029392"
    ],
    "tgn:id":2037610,
    "tgn:name":"Barnetts Creek",
    "tgn:placetype":[
        "aat:300008347"
    ]
},
  "bbox": [],
  "geometry": {"coordinates":[-82.8667,37.8167],"type":"Point"}
}