{
  "id": 2083977,
  "type": "Feature",
  "properties": {
    "tgn:hierarchy":[
        "tgn:2083977",
        "tgn:1000001",
        "tgn:2001644",
        "tgn:7012149",
        "tgn:7007707",
        "tgn:7029392"
    ],
    "tgn:id":2083977,
    "tgn:name":"Seiling",
    "tgn:placetype":[
        "aat:300008347"
    ]
},
  "bbox": [],
  "geometry": {"coordinates":[-98.9167,36.1333],"type":"Point"}
}