{
  "id": 2575585,
  "type": "Feature",
  "properties": {
    "tgn:hierarchy":[
        "tgn:2575585",
        "tgn:2002305",
        "tgn:1000001",
        "tgn:7012149",
        "tgn:7007922",
        "tgn:7029392"
    ],
    "tgn:id":2575585,
    "tgn:name":"Peppermill Lake",
    "tgn:placetype":[
        "aat:300006191"
    ]
},
  "bbox": [],
  "geometry": {"coordinates":[-89.6333,43.7833],"type":"Point"}
}