{
  "id": 7235819,
  "type": "Feature",
  "properties": {
    "tgn:hierarchy":[
        "tgn:7235819",
        "tgn:7002692",
        "tgn:7012056",
        "tgn:1000003",
        "tgn:1000074",
        "tgn:7029392"
    ],
    "tgn:id":7235819,
    "tgn:name":"Fanerom\u00e9nis, \u00d3rmos",
    "tgn:placetype":[
        "aat:300132316"
    ]
},
  "bbox": [],
  "geometry": {"coordinates":[26.083333,35.233333],"type":"Point"}
}