{
  "id": 2190415,
  "type": "Feature",
  "properties": {
    "tgn:hierarchy":[
        "tgn:2190415",
        "tgn:1000001",
        "tgn:2001419",
        "tgn:7012149",
        "tgn:7007526",
        "tgn:7029392"
    ],
    "tgn:id":2190415,
    "tgn:name":"Box Canyon Spring Number Two",
    "tgn:placetype":[
        "aat:300008697"
    ]
},
  "bbox": [],
  "geometry": {"coordinates":[-118.4667,40.8333],"type":"Point"}
}