<<<<<<< HEAD
{
  "id": 2334406,
  "type": "Feature",
  "properties": {
    "tgn:hierarchy":[
        "tgn:2334406",
        "tgn:1000001",
        "tgn:7012149",
        "tgn:2001289",
        "tgn:7007524",
        "tgn:7029392"
    ],
    "tgn:id":2334406,
    "tgn:name":"Forest Lake",
    "tgn:placetype":[
        "aat:300008680"
    ]
},
  "bbox": [],
  "geometry": {"coordinates":[-110.4333,46.2333],"type":"Point"}
}
=======
{"geometry":{"type":"Point","coordinates":[-110.433300,46.233300]},"type":"Feature","properties":{"hierarchy":["tgn:2334406","tgn:1000001","tgn:7012149","tgn:2001289","tgn:7007524","tgn:7029392"],"placetype":["aat:300008680"],"id":2334406,"name:xx":"Forest Lake"}}
>>>>>>> 03f74aca74312dbeaf24d7e61306dd6a786dc3d0
