{
  "id": 2464989,
  "type": "Feature",
  "properties": {
    "tgn:hierarchy":[
        "tgn:2464989",
        "tgn:1000001",
        "tgn:7012149",
        "tgn:2001551",
        "tgn:7007709",
        "tgn:7029392"
    ],
    "tgn:id":2464989,
    "tgn:name":"Loggy Ridge",
    "tgn:placetype":[
        "aat:300266640"
    ]
},
  "bbox": [],
  "geometry": {"coordinates":[-81.6833,36.2667],"type":"Point"}
}