<<<<<<< HEAD
{
  "id": 2253895,
  "type": "Feature",
  "properties": {
    "tgn:hierarchy":[
        "tgn:2253895",
        "tgn:1000001",
        "tgn:1002840",
        "tgn:7012149",
        "tgn:7007828",
        "tgn:7029392"
    ],
    "tgn:id":2253895,
    "tgn:name":"Cooks Pond",
    "tgn:placetype":[
        "aat:300008680"
    ]
},
  "bbox": [],
  "geometry": {"coordinates":[-72.85,43.5],"type":"Point"}
}
=======
{"geometry":{"type":"Point","coordinates":[-72.850000,43.500000]},"type":"Feature","properties":{"hierarchy":["tgn:2253895","tgn:1000001","tgn:1002840","tgn:7012149","tgn:7007828","tgn:7029392"],"placetype":["aat:300008680"],"id":2253895,"name:xx":"Cooks Pond"}}
>>>>>>> 03f74aca74312dbeaf24d7e61306dd6a786dc3d0
