{
  "id": 1071901,
  "type": "Feature",
  "properties": {
    "tgn:hierarchy":[
        "tgn:1071901",
        "tgn:1000004",
        "tgn:7002087",
        "tgn:1000111",
        "tgn:7029392"
    ],
    "tgn:id":1071901,
    "tgn:name":"Sibochi",
    "tgn:placetype":[
        "aat:300008347"
    ]
},
  "bbox": [],
  "geometry": {"coordinates":[104.5333,28.8333],"type":"Point"}
}