{
  "id": 7338765,
  "type": "Feature",
  "properties": {
    "tgn:hierarchy":[
        "tgn:7338765",
        "tgn:7002825",
        "tgn:7016622",
        "tgn:1000003",
        "tgn:1000095",
        "tgn:7029392"
    ],
    "tgn:id":7338765,
    "tgn:name":"El Charco",
    "tgn:placetype":[
        "aat:300008347"
    ]
},
  "bbox": [],
  "geometry": {"coordinates":[-14.016667,28.233333],"type":"Point"}
}