{
  "id": 7412008,
  "type": "Feature",
  "properties": {
    "tgn:hierarchy":[
        "tgn:7412008",
        "tgn:7005587",
        "tgn:1000001",
        "tgn:7005560",
        "tgn:7029392"
    ],
    "tgn:id":7412008,
    "tgn:name:es":"Los Migueles",
    "tgn:placetype":[
        "aat:300008347"
    ]
},
  "bbox": [],
  "geometry": {"coordinates":[-98.402778,20.165278],"type":"Point"}
}