{
  "id": 7097835,
  "type": "Feature",
  "properties": {
    "tgn:hierarchy":[
        "tgn:7097835",
        "tgn:1000003",
        "tgn:7003682",
        "tgn:7000084",
        "tgn:7029392"
    ],
    "tgn:id":7097835,
    "tgn:name":"Sessenbach",
    "tgn:placetype":[
        "aat:300008347"
    ]
},
  "bbox": [],
  "geometry": {"coordinates":[7.65,50.466667],"type":"Point"}
}