{
  "id": 7324625,
  "type": "Feature",
  "properties": {
    "tgn:hierarchy":[
        "tgn:7324625",
        "tgn:7008911",
        "tgn:1000003",
        "tgn:7002763",
        "tgn:1000095",
        "tgn:7029392"
    ],
    "tgn:id":7324625,
    "tgn:name":"San Esteban de Pravia",
    "tgn:placetype":[
        "aat:300008347"
    ]
},
  "bbox": [],
  "geometry": {"coordinates":[-6.086944,43.5525],"type":"Point"}
}