<<<<<<< HEAD
{
  "id": 2332813,
  "type": "Feature",
  "properties": {
    "tgn:hierarchy":[
        "tgn:2332813",
        "tgn:1000001",
        "tgn:7012149",
        "tgn:7007522",
        "tgn:7029392"
    ],
    "tgn:id":2332813,
    "tgn:name":"Floyd Branch",
    "tgn:placetype":[
        "aat:300008699"
    ]
},
  "bbox": [],
  "geometry": {"coordinates":[-89.35,32.05],"type":"Point"}
}
=======
{"geometry":{"type":"Point","coordinates":[-89.350000,32.050000]},"type":"Feature","properties":{"hierarchy":["tgn:2332813","tgn:1000001","tgn:7012149","tgn:7007522","tgn:7029392"],"placetype":["aat:300008699"],"id":2332813,"name:xx":"Floyd Branch"}}
>>>>>>> 03f74aca74312dbeaf24d7e61306dd6a786dc3d0
