{
  "id": 2491383,
  "type": "Feature",
  "properties": {
    "tgn:hierarchy":[
        "tgn:2491383",
        "tgn:1000001",
        "tgn:7012149",
        "tgn:1002761",
        "tgn:7007706",
        "tgn:7029392"
    ],
    "tgn:id":2491383,
    "tgn:name":"Maple Grove",
    "tgn:placetype":[
        "aat:300008347"
    ]
},
  "bbox": [],
  "geometry": {"coordinates":[-83.1833,41.5833],"type":"Point"}
}