{
  "id": 2415031,
  "type": "Feature",
  "properties": {
    "tgn:hierarchy":[
        "tgn:2415031",
        "tgn:1000001",
        "tgn:7012149",
        "tgn:2001247",
        "tgn:7007523",
        "tgn:7029392"
    ],
    "tgn:id":2415031,
    "tgn:name":"Island Branch",
    "tgn:placetype":[
        "aat:300008699"
    ]
},
  "bbox": [],
  "geometry": {"coordinates":[-91.4667,37.0667],"type":"Point"}
}