{
  "id": 7587798,
  "type": "Feature",
  "properties": {
    "tgn:hierarchy":[
        "tgn:7587798",
        "tgn:1000004",
        "tgn:7000198",
        "tgn:7000799",
        "tgn:7029392"
    ],
    "tgn:id":7587798,
    "tgn:name:en":"Momus",
    "tgn:placetype":[
        "aat:300008347"
    ]
},
  "bbox": [],
  "geometry": {"coordinates":[74.537772,34.115689],"type":"Point"}
}