{
  "id": 7548405,
  "type": "Feature",
  "properties": {
    "tgn:hierarchy":[
        "tgn:7548405",
        "tgn:1000004",
        "tgn:7000198",
        "tgn:7000799",
        "tgn:7029392"
    ],
    "tgn:id":7548405,
    "tgn:name:en":"Chimre",
    "tgn:placetype":[
        "aat:300008347"
    ]
},
  "bbox": [],
  "geometry": {"coordinates":[77.811646,33.97449],"type":"Point"}
}