{
  "id": 2627565,
  "type": "Feature",
  "properties": {
    "tgn:hierarchy":[
        "tgn:2627565",
        "tgn:1000001",
        "tgn:7012149",
        "tgn:2001458",
        "tgn:7007566",
        "tgn:7029392"
    ],
    "tgn:id":2627565,
    "tgn:name":"Rogers Canyon",
    "tgn:placetype":[
        "aat:300008761"
    ]
},
  "bbox": [],
  "geometry": {"coordinates":[-106.0667,34.4667],"type":"Point"}
}