<<<<<<< HEAD
{
  "id": 2408207,
  "type": "Feature",
  "properties": {
    "tgn:hierarchy":[
        "tgn:2408207",
        "tgn:7002659",
        "tgn:1000001",
        "tgn:7012149",
        "tgn:2000057",
        "tgn:7029392"
    ],
    "tgn:id":2408207,
    "tgn:name":"Hurst Hill",
    "tgn:placetype":[
        "aat:300008798"
    ]
},
  "bbox": [],
  "geometry": {"coordinates":[-86.4667,33.5833],"type":"Point"}
}
=======
{"geometry":{"type":"Point","coordinates":[-86.466700,33.583300]},"type":"Feature","properties":{"hierarchy":["tgn:2408207","tgn:7002659","tgn:1000001","tgn:7012149","tgn:2000057","tgn:7029392"],"placetype":["aat:300008798"],"id":2408207,"name:xx":"Hurst Hill"}}
>>>>>>> 03f74aca74312dbeaf24d7e61306dd6a786dc3d0
