{
  "id": 2513486,
  "type": "Feature",
  "properties": {
    "tgn:hierarchy":[
        "tgn:2513486",
        "tgn:1000001",
        "tgn:7012149",
        "tgn:2001440",
        "tgn:7007566",
        "tgn:7029392"
    ],
    "tgn:id":2513486,
    "tgn:name":"Mill Mine",
    "tgn:placetype":[
        "aat:300000390"
    ]
},
  "bbox": [],
  "geometry": {"coordinates":[-108.5333,32.4167],"type":"Point"}
}