{
  "id": 2060779,
  "type": "Feature",
  "properties": {
    "tgn:hierarchy":[
        "tgn:2060779",
        "tgn:1000001",
        "tgn:7012149",
        "tgn:2001256",
        "tgn:7007523",
        "tgn:7029392"
    ],
    "tgn:id":2060779,
    "tgn:name":"Vance",
    "tgn:placetype":[
        "aat:300008347",
        "aat:300387210"
    ]
},
  "bbox": [],
  "geometry": {"coordinates":[-92.7667,37.4333],"type":"Point"}
}