{
  "id": 7516948,
  "type": "Feature",
  "properties": {
    "tgn:hierarchy":[
        "tgn:7516948",
        "tgn:1009227",
        "tgn:1000226",
        "tgn:7016822",
        "tgn:1000006",
        "tgn:7029392"
    ],
    "tgn:id":7516948,
    "tgn:name:en":"North Mavora Lake",
    "tgn:placetype":[
        "aat:300008680"
    ]
},
  "bbox": [],
  "geometry": {"coordinates":[168.166667,-45.233333],"type":"Point"}
}