{
  "id": 2249126,
  "type": "Feature",
  "properties": {
    "tgn:hierarchy":[
        "tgn:2249126",
        "tgn:1000001",
        "tgn:7012149",
        "tgn:2002250",
        "tgn:7007920",
        "tgn:7029392"
    ],
    "tgn:id":2249126,
    "tgn:name":"Cole Creek",
    "tgn:placetype":[
        "aat:300008706"
    ]
},
  "bbox": [],
  "geometry": {"coordinates":[-118.05,48.4667],"type":"Point"}
}