{
  "id": 7274725,
  "type": "Feature",
  "properties": {
    "tgn:concordances":{
        "gn:id":"2744125"
    },
    "tgn:hierarchy":[
        "tgn:7274725",
        "tgn:1000003",
        "tgn:7003613",
        "tgn:7016845",
        "tgn:7029392"
    ],
    "tgn:id":7274725,
    "tgn:name:nl":"Zaadstukken",
    "tgn:placetype":[
        "aat:300008347"
    ]
},
  "bbox": [],
  "geometry": {"coordinates":[7.05,52.966667],"type":"Point"}
}