{
  "id": 2384862,
  "type": "Feature",
  "properties": {
    "tgn:hierarchy":[
        "tgn:2384862",
        "tgn:1000001",
        "tgn:7006451",
        "tgn:7012149",
        "tgn:2000098",
        "tgn:7029392"
    ],
    "tgn:id":2384862,
    "tgn:name":"Hells Hollow",
    "tgn:placetype":[
        "aat:300008761"
    ]
},
  "bbox": [],
  "geometry": {"coordinates":[-113.2167,36.35],"type":"Point"}
}