{
  "id": 2312784,
  "type": "Feature",
  "properties": {
    "tgn:hierarchy":[
        "tgn:2312784",
        "tgn:7006450",
        "tgn:1000001",
        "tgn:7012149",
        "tgn:7019760",
        "tgn:7029392"
    ],
    "tgn:id":2312784,
    "tgn:name":"El Nido Mine",
    "tgn:placetype":[
        "aat:300000390"
    ]
},
  "bbox": [],
  "geometry": {"coordinates":[-136.2833,57.9333],"type":"Point"}
}