{
  "id": 7496059,
  "type": "Feature",
  "properties": {
    "tgn:hierarchy":[
        "tgn:7496059",
        "tgn:1000004",
        "tgn:7001014",
        "tgn:1000141",
        "tgn:7029392"
    ],
    "tgn:id":7496059,
    "tgn:name":"Shengli Qiao",
    "tgn:placetype":[
        "aat:300007836"
    ]
},
  "bbox": [],
  "geometry": {"coordinates":[120.309895,23.702228],"type":"Point"}
}