{
  "id": 2466200,
  "type": "Feature",
  "properties": {
    "tgn:hierarchy":[
        "tgn:2466200",
        "tgn:1000001",
        "tgn:7012149",
        "tgn:7029392"
    ],
    "tgn:id":2466200,
    "tgn:name":"Lonesome Lake",
    "tgn:placetype":[
        "aat:300008680"
    ]
},
  "bbox": [],
  "geometry": {"coordinates":[-109.5833,44.9833],"type":"Point"}
}