{
  "id": 2313008,
  "type": "Feature",
  "properties": {
    "tgn:hierarchy":[
        "tgn:2313008",
        "tgn:1000001",
        "tgn:7016172",
        "tgn:7012149",
        "tgn:2000179",
        "tgn:7029392"
    ],
    "tgn:id":2313008,
    "tgn:name":"Elberta",
    "tgn:placetype":[
        "aat:300008347"
    ]
},
  "bbox": [],
  "geometry": {"coordinates":[-93.15,35.1667],"type":"Point"}
}