<<<<<<< HEAD
{
  "id": 2339410,
  "type": "Feature",
  "properties": {
    "tgn:hierarchy":[
        "tgn:2339410",
        "tgn:2001732",
        "tgn:1000001",
        "tgn:7012149",
        "tgn:7007712",
        "tgn:7029392"
    ],
    "tgn:id":2339410,
    "tgn:name":"Frazier Hill",
    "tgn:placetype":[
        "aat:300008347"
    ]
},
  "bbox": [],
  "geometry": {"coordinates":[-80.0167,33.2],"type":"Point"}
}
=======
{"geometry":{"type":"Point","coordinates":[-80.016700,33.200000]},"type":"Feature","properties":{"hierarchy":["tgn:2339410","tgn:2001732","tgn:1000001","tgn:7012149","tgn:7007712","tgn:7029392"],"placetype":["aat:300008347"],"id":2339410,"name:xx":"Frazier Hill"}}
>>>>>>> 03f74aca74312dbeaf24d7e61306dd6a786dc3d0
