<<<<<<< HEAD
{
  "id": 2404853,
  "type": "Feature",
  "properties": {
    "tgn:hierarchy":[
        "tgn:2404853",
        "tgn:1000001",
        "tgn:7012149",
        "tgn:2001918",
        "tgn:7007825",
        "tgn:7029392"
    ],
    "tgn:id":2404853,
    "tgn:name":"Huckleberry Ridge",
    "tgn:placetype":[
        "aat:300266640"
    ]
},
  "bbox": [],
  "geometry": {"coordinates":[-82.1333,36.4167],"type":"Point"}
}
=======
{"geometry":{"type":"Point","coordinates":[-82.133300,36.416700]},"type":"Feature","properties":{"hierarchy":["tgn:2404853","tgn:1000001","tgn:7012149","tgn:2001918","tgn:7007825","tgn:7029392"],"placetype":["aat:300266640"],"id":2404853,"name:xx":"Huckleberry Ridge"}}
>>>>>>> 03f74aca74312dbeaf24d7e61306dd6a786dc3d0
