{
  "id": 2739805,
  "type": "Feature",
  "properties": {
    "tgn:hierarchy":[
        "tgn:2739805",
        "tgn:1000001",
        "tgn:7012149",
        "tgn:2000219",
        "tgn:7007158",
        "tgn:7029392"
    ],
    "tgn:id":2739805,
    "tgn:name":"Upper Duhme Springs",
    "tgn:placetype":[
        "aat:300008697"
    ]
},
  "bbox": [],
  "geometry": {"coordinates":[-105.8333,37.4167],"type":"Point"}
}