{
  "id": 2775437,
  "type": "Feature",
  "properties": {
    "tgn:hierarchy":[
        "tgn:2775437",
        "tgn:1000001",
        "tgn:7012149",
        "tgn:2000430",
        "tgn:7007248",
        "tgn:7029392"
    ],
    "tgn:id":2775437,
    "tgn:name":"Wilson Cove Creek",
    "tgn:placetype":[
        "aat:300008706"
    ]
},
  "bbox": [],
  "geometry": {"coordinates":[-83.7833,34.9167],"type":"Point"}
}