{
  "id": 2661253,
  "type": "Feature",
  "properties": {
    "tgn:hierarchy":[
        "tgn:2661253",
        "tgn:1000001",
        "tgn:7012149",
        "tgn:2000206",
        "tgn:7007158",
        "tgn:7029392"
    ],
    "tgn:id":2661253,
    "tgn:name":"Shortcut Reservoir",
    "tgn:placetype":[
        "aat:300006191"
    ]
},
  "bbox": [],
  "geometry": {"coordinates":[-108.2333,38.6833],"type":"Point"}
}