{
  "id": 2340196,
  "type": "Feature",
  "properties": {
    "tgn:hierarchy":[
        "tgn:2340196",
        "tgn:1000001",
        "tgn:2002135",
        "tgn:7012149",
        "tgn:7007828",
        "tgn:7029392"
    ],
    "tgn:id":2340196,
    "tgn:name":"French Brook",
    "tgn:placetype":[
        "aat:300008699"
    ]
},
  "bbox": [],
  "geometry": {"coordinates":[-72.8833,44.2333],"type":"Point"}
}