{
  "id": 2383400,
  "type": "Feature",
  "properties": {
    "tgn:hierarchy":[
        "tgn:2383400",
        "tgn:1000001",
        "tgn:1002753",
        "tgn:7012149",
        "tgn:7007828",
        "tgn:7029392"
    ],
    "tgn:id":2383400,
    "tgn:name":"Heart Pond",
    "tgn:placetype":[
        "aat:300008680"
    ]
},
  "bbox": [],
  "geometry": {"coordinates":[-72.35,44.6833],"type":"Point"}
}