{
  "id": 2636647,
  "type": "Feature",
  "properties": {
    "tgn:hierarchy":[
        "tgn:2636647",
        "tgn:2000090",
        "tgn:1000001",
        "tgn:7006451",
        "tgn:7012149",
        "tgn:7029392"
    ],
    "tgn:id":2636647,
    "tgn:name":"Sage House Wash",
    "tgn:placetype":[
        "aat:300008699"
    ]
},
  "bbox": [],
  "geometry": {"coordinates":[-109.2833,35.85],"type":"Point"}
}