{
  "id": 7042407,
  "type": "Feature",
  "properties": {
    "tgn:hierarchy":[
        "tgn:7042407",
        "tgn:7002995",
        "tgn:1000003",
        "tgn:7002997",
        "tgn:1000080",
        "tgn:7029392"
    ],
    "tgn:id":7042407,
    "tgn:name":"Rottanova",
    "tgn:placetype":[
        "aat:300008347"
    ]
},
  "bbox": [],
  "geometry": {"coordinates":[12.015833,45.14],"type":"Point"}
}