<<<<<<< HEAD
{
  "id": 7173546,
  "type": "Feature",
  "properties": {
    "tgn:hierarchy":[
        "tgn:7173546",
        "tgn:1000003",
        "tgn:7003689",
        "tgn:7000084",
        "tgn:7029392"
    ],
    "tgn:id":7173546,
    "tgn:name":"Gro\u00dfbodungen",
    "tgn:placetype":[
        "aat:300008347"
    ]
},
  "bbox": [],
  "geometry": {"coordinates":[10.5,51.466667],"type":"Point"}
}
=======
{"geometry":{"type":"Point","coordinates":[10.500000,51.466667]},"type":"Feature","properties":{"hierarchy":["tgn:7173546","tgn:1000003","tgn:7003689","tgn:7000084","tgn:7029392"],"placetype":["aat:300008347"],"id":7173546,"name:xx":"Gro\u00dfbodungen"}}
>>>>>>> 03f74aca74312dbeaf24d7e61306dd6a786dc3d0
