{
  "id": 2647010,
  "type": "Feature",
  "properties": {
    "tgn:hierarchy":[
        "tgn:2647010",
        "tgn:1000001",
        "tgn:7012149",
        "tgn:7007248",
        "tgn:7029392"
    ],
    "tgn:id":2647010,
    "tgn:name":"Schaffer Creek",
    "tgn:placetype":[
        "aat:300008706"
    ]
},
  "bbox": [],
  "geometry": {"coordinates":[-82.25,33.1167],"type":"Point"}
}