{
  "id": 1094701,
  "type": "Feature",
  "properties": {
    "tgn:hierarchy":[
        "tgn:1094701",
        "tgn:7001242",
        "tgn:1001685",
        "tgn:1000203",
        "tgn:7029392"
    ],
    "tgn:id":1094701,
    "tgn:name":"Mahenge",
    "tgn:placetype":[
        "aat:300008347"
    ]
},
  "bbox": [],
  "geometry": {"coordinates":[36.2667,-7.6333],"type":"Point"}
}