{
  "id": 2274471,
  "type": "Feature",
  "properties": {
    "tgn:hierarchy":[
        "tgn:2274471",
        "tgn:1000001",
        "tgn:7012149",
        "tgn:1002921",
        "tgn:7007526",
        "tgn:7029392"
    ],
    "tgn:id":2274471,
    "tgn:name":"Daley Mine",
    "tgn:placetype":[
        "aat:300000390"
    ]
},
  "bbox": [],
  "geometry": {"coordinates":[-119.6333,39.3167],"type":"Point"}
}