{
  "id": 2391559,
  "type": "Feature",
  "properties": {
    "tgn:hierarchy":[
        "tgn:2391559",
        "tgn:1000001",
        "tgn:7016172",
        "tgn:7012149",
        "tgn:2000164",
        "tgn:7029392"
    ],
    "tgn:id":2391559,
    "tgn:name":"Hills Lake",
    "tgn:placetype":[
        "aat:300008680"
    ]
},
  "bbox": [],
  "geometry": {"coordinates":[-92.1167,34.7667],"type":"Point"}
}