<<<<<<< HEAD
{
  "id": 7110450,
  "type": "Feature",
  "properties": {
    "tgn:hierarchy":[
        "tgn:7110450",
        "tgn:1000003",
        "tgn:7003685",
        "tgn:7000084",
        "tgn:7029392"
    ],
    "tgn:id":7110450,
    "tgn:name":"Reichwalde",
    "tgn:placetype":[
        "aat:300008347"
    ]
},
  "bbox": [],
  "geometry": {"coordinates":[14.666667,51.383333],"type":"Point"}
}
=======
{"geometry":{"type":"Point","coordinates":[14.666667,51.383333]},"type":"Feature","properties":{"hierarchy":["tgn:7110450","tgn:1000003","tgn:7003685","tgn:7000084","tgn:7029392"],"placetype":["aat:300008347"],"id":7110450,"name:xx":"Reichwalde"}}
>>>>>>> 03f74aca74312dbeaf24d7e61306dd6a786dc3d0
