{
  "id": 7502170,
  "type": "Feature",
  "properties": {
    "tgn:hierarchy":[
        "tgn:7502170",
        "tgn:1000004",
        "tgn:7001009",
        "tgn:1000141",
        "tgn:7029392"
    ],
    "tgn:id":7502170,
    "tgn:name":"Hehe",
    "tgn:placetype":[
        "aat:300008347"
    ]
},
  "bbox": [],
  "geometry": {"coordinates":[120.865654,24.169421],"type":"Point"}
}