<<<<<<< HEAD
{
  "id": 2338080,
  "type": "Feature",
  "properties": {
    "tgn:hierarchy":[
        "tgn:2338080",
        "tgn:1000001",
        "tgn:7012149",
        "tgn:1003007",
        "tgn:7007706",
        "tgn:7029392"
    ],
    "tgn:id":2338080,
    "tgn:name":"Fox Lake",
    "tgn:placetype":[
        "aat:300006191"
    ]
},
  "bbox": [],
  "geometry": {"coordinates":[-81.65,40.8833],"type":"Point"}
}
=======
{"geometry":{"type":"Point","coordinates":[-81.650000,40.883300]},"type":"Feature","properties":{"hierarchy":["tgn:2338080","tgn:1000001","tgn:7012149","tgn:1003007","tgn:7007706","tgn:7029392"],"placetype":["aat:300006191"],"id":2338080,"name:xx":"Fox Lake"}}
>>>>>>> 03f74aca74312dbeaf24d7e61306dd6a786dc3d0
