<<<<<<< HEAD
{
  "id": 7350566,
  "type": "Feature",
  "properties": {
    "tgn:hierarchy":[
        "tgn:7350566",
        "tgn:1001835",
        "tgn:1000001",
        "tgn:7005560",
        "tgn:7029392"
    ],
    "tgn:id":7350566,
    "tgn:name":"Blanco, Bah\u00eda",
    "tgn:placetype":[
        "aat:300132316"
    ]
},
  "bbox": [],
  "geometry": {"coordinates":[-114.666667,29.066667],"type":"Point"}
}
=======
{"geometry":{"type":"Point","coordinates":[-114.666667,29.066667]},"type":"Feature","properties":{"hierarchy":["tgn:7350566","tgn:1001835","tgn:1000001","tgn:7005560","tgn:7029392"],"placetype":["aat:300132316"],"id":7350566,"name:xx":"Blanco, Bah\u00eda"}}
>>>>>>> 03f74aca74312dbeaf24d7e61306dd6a786dc3d0
