{
  "id": 7185353,
  "type": "Feature",
  "properties": {
    "tgn:hierarchy":[
        "tgn:7185353",
        "tgn:1000003",
        "tgn:7003689",
        "tgn:7000084",
        "tgn:7029392"
    ],
    "tgn:id":7185353,
    "tgn:name":"G\u00f6ritz-Berg",
    "tgn:placetype":[
        "aat:300008777"
    ]
},
  "bbox": [],
  "geometry": {"coordinates":[11.133333,50.466667],"type":"Point"}
}