{
  "id": 1128925,
  "type": "Feature",
  "properties": {
    "tgn:hierarchy":[
        "tgn:1128925",
        "tgn:7005735",
        "tgn:7005685",
        "tgn:1000001",
        "tgn:7029392"
    ],
    "tgn:id":1128925,
    "tgn:name":"Quesnel",
    "tgn:placetype":[
        "aat:300008707"
    ]
},
  "bbox": [],
  "geometry": {"coordinates":[-122.4833,52.9667],"type":"Point"}
}