{
  "id": 1140609,
  "type": "Feature",
  "properties": {
    "tgn:hierarchy":[
        "tgn:1140609",
        "tgn:7000895",
        "tgn:1000004",
        "tgn:1001010",
        "tgn:1000120",
        "tgn:7029392"
    ],
    "tgn:id":1140609,
    "tgn:name":"Tenry\u016b",
    "tgn:placetype":[
        "aat:300008347"
    ]
},
  "bbox": [],
  "geometry": {"coordinates":[137.85,35.2667],"type":"Point"}
}