{
  "id": 7568586,
  "type": "Feature",
  "properties": {
    "tgn:hierarchy":[
        "tgn:7568586",
        "tgn:1000004",
        "tgn:7000198",
        "tgn:1001996",
        "tgn:7029392"
    ],
    "tgn:id":7568586,
    "tgn:name:en":"Dargot",
    "tgn:placetype":[
        "aat:300008347"
    ]
},
  "bbox": [],
  "geometry": {"coordinates":[77.072219,31.189366],"type":"Point"}
}