{
  "id": 7528090,
  "type": "Feature",
  "properties": {
    "tgn:hierarchy":[
        "tgn:7528090",
        "tgn:7001242",
        "tgn:7001105",
        "tgn:7016833",
        "tgn:7029392"
    ],
    "tgn:id":7528090,
    "tgn:name:en":"Sinn, Khashm as",
    "tgn:placetype":[
        "aat:300386846"
    ]
},
  "bbox": [],
  "geometry": {"coordinates":[30.655264,29.444246],"type":"Point"}
}