{
  "id": 2443454,
  "type": "Feature",
  "properties": {
    "tgn:hierarchy":[
        "tgn:2443454",
        "tgn:1000001",
        "tgn:7012149",
        "tgn:2001281",
        "tgn:7007524",
        "tgn:7029392"
    ],
    "tgn:id":2443454,
    "tgn:name":"La Belle Gulch",
    "tgn:placetype":[
        "aat:300008761"
    ]
},
  "bbox": [],
  "geometry": {"coordinates":[-112.3667,46.1833],"type":"Point"}
}