{
  "id": 1123174,
  "type": "Feature",
  "properties": {
    "tgn:hierarchy":[
        "tgn:1123174",
        "tgn:7001242",
        "tgn:1000149",
        "tgn:1000835",
        "tgn:7029392"
    ],
    "tgn:id":1123174,
    "tgn:name":"Cubal",
    "tgn:placetype":[
        "aat:300008707"
    ]
},
  "bbox": [],
  "geometry": {"coordinates":[14.002,-11.44],"type":"Point"}
}