<<<<<<< HEAD
{
  "id": 2334863,
  "type": "Feature",
  "properties": {
    "tgn:hierarchy":[
        "tgn:2334863",
        "tgn:1000001",
        "tgn:1002934",
        "tgn:7012149",
        "tgn:7007565",
        "tgn:7029392"
    ],
    "tgn:id":2334863,
    "tgn:name":"Forked Brook",
    "tgn:placetype":[
        "aat:300008699"
    ]
},
  "bbox": [],
  "geometry": {"coordinates":[-74.7333,41.2667],"type":"Point"}
}
=======
{"geometry":{"type":"Point","coordinates":[-74.733300,41.266700]},"type":"Feature","properties":{"hierarchy":["tgn:2334863","tgn:1000001","tgn:1002934","tgn:7012149","tgn:7007565","tgn:7029392"],"placetype":["aat:300008699"],"id":2334863,"name:xx":"Forked Brook"}}
>>>>>>> 03f74aca74312dbeaf24d7e61306dd6a786dc3d0
