{
  "id": 2382071,
  "type": "Feature",
  "properties": {
    "tgn:hierarchy":[
        "tgn:2382071",
        "tgn:1000001",
        "tgn:7012149",
        "tgn:7007919",
        "tgn:7029392"
    ],
    "tgn:id":2382071,
    "tgn:name":"Hayfield Bar",
    "tgn:placetype":[
        "aat:300132348"
    ]
},
  "bbox": [],
  "geometry": {"coordinates":[-77.3167,38.2333],"type":"Point"}
}