{
  "id": 2306805,
  "type": "Feature",
  "properties": {
    "tgn:hierarchy":[
        "tgn:2306805",
        "tgn:1000001",
        "tgn:7012149",
        "tgn:2001922",
        "tgn:7007825",
        "tgn:7029392"
    ],
    "tgn:id":2306805,
    "tgn:name":"East Fork Higgins Creek",
    "tgn:placetype":[
        "aat:300008706"
    ]
},
  "bbox": [],
  "geometry": {"coordinates":[-82.4833,35.9833],"type":"Point"}
}