{
  "id": 2100229,
  "type": "Feature",
  "properties": {
    "tgn:hierarchy":[
        "tgn:2100229",
        "tgn:1000001",
        "tgn:7012149",
        "tgn:2001878",
        "tgn:7007825",
        "tgn:7029392"
    ],
    "tgn:id":2100229,
    "tgn:name":"Magnolia",
    "tgn:placetype":[
        "aat:300008347",
        "aat:300387210"
    ]
},
  "bbox": [],
  "geometry": {"coordinates":[-87.8667,36.25],"type":"Point"}
}