{
  "id": 2222835,
  "type": "Feature",
  "properties": {
    "tgn:hierarchy":[
        "tgn:2222835",
        "tgn:1000001",
        "tgn:2000458",
        "tgn:7012149",
        "tgn:7007250",
        "tgn:7029392"
    ],
    "tgn:id":2222835,
    "tgn:name":"Carraway Reservoir",
    "tgn:placetype":[
        "aat:300006191"
    ]
},
  "bbox": [],
  "geometry": {"coordinates":[-113.6833,43.2333],"type":"Point"}
}