{
  "id": 2642140,
  "type": "Feature",
  "properties": {
    "tgn:hierarchy":[
        "tgn:2642140",
        "tgn:1000001",
        "tgn:7012149",
        "tgn:2001461",
        "tgn:7007568",
        "tgn:7029392"
    ],
    "tgn:id":2642140,
    "tgn:name":"Sand Pond Mountain",
    "tgn:placetype":[
        "aat:300008798"
    ]
},
  "bbox": [],
  "geometry": {"coordinates":[-73.8833,43.9333],"type":"Point"}
}