{
  "id": 2546347,
  "type": "Feature",
  "properties": {
    "tgn:hierarchy":[
        "tgn:2546347",
        "tgn:7006450",
        "tgn:1000001",
        "tgn:7012149",
        "tgn:2000089",
        "tgn:7029392"
    ],
    "tgn:id":2546347,
    "tgn:name":"North Fork Harrison Creek",
    "tgn:placetype":[
        "aat:300008706"
    ]
},
  "bbox": [],
  "geometry": {"coordinates":[-145.3167,65.4167],"type":"Point"}
}