<<<<<<< HEAD
{
  "id": 2404301,
  "type": "Feature",
  "properties": {
    "tgn:hierarchy":[
        "tgn:2404301",
        "tgn:1000001",
        "tgn:7012149",
        "tgn:1003020",
        "tgn:7007920",
        "tgn:7029392"
    ],
    "tgn:id":2404301,
    "tgn:name":"Hozomeen Creek",
    "tgn:placetype":[
        "aat:300008706"
    ]
},
  "bbox": [],
  "geometry": {"coordinates":[-121.0167,48.9333],"type":"Point"}
}
=======
{"geometry":{"type":"Point","coordinates":[-121.016700,48.933300]},"type":"Feature","properties":{"hierarchy":["tgn:2404301","tgn:1000001","tgn:7012149","tgn:1003020","tgn:7007920","tgn:7029392"],"placetype":["aat:300008706"],"id":2404301,"name:xx":"Hozomeen Creek"}}
>>>>>>> 03f74aca74312dbeaf24d7e61306dd6a786dc3d0
