{
  "id": 7176070,
  "type": "Feature",
  "properties": {
    "tgn:hierarchy":[
        "tgn:7176070",
        "tgn:1000003",
        "tgn:7003687",
        "tgn:7000084",
        "tgn:7029392"
    ],
    "tgn:id":7176070,
    "tgn:name":"Gr\u00f6\u00dfter H\u00fcgel",
    "tgn:placetype":[
        "aat:300008777"
    ]
},
  "bbox": [],
  "geometry": {"coordinates":[11.833333,51.283333],"type":"Point"}
}