<<<<<<< HEAD
{
  "id": 7176070,
  "type": "Feature",
  "properties": {
    "tgn:hierarchy":[
        "tgn:7176070",
        "tgn:1000003",
        "tgn:7003687",
        "tgn:7000084",
        "tgn:7029392"
    ],
    "tgn:id":7176070,
    "tgn:name":"Gr\u00f6\u00dfter H\u00fcgel",
    "tgn:placetype":[
        "aat:300008777"
    ]
},
  "bbox": [],
  "geometry": {"coordinates":[11.833333,51.283333],"type":"Point"}
}
=======
{"geometry":{"type":"Point","coordinates":[11.833333,51.283333]},"type":"Feature","properties":{"hierarchy":["tgn:7176070","tgn:1000003","tgn:7003687","tgn:7000084","tgn:7029392"],"placetype":["aat:300008777"],"id":7176070,"name:xx":"Gr\u00f6\u00dfter H\u00fcgel"}}
>>>>>>> 03f74aca74312dbeaf24d7e61306dd6a786dc3d0
