{
  "id": 2654487,
  "type": "Feature",
  "properties": {
    "tgn:hierarchy":[
        "tgn:2654487",
        "tgn:1000001",
        "tgn:7012149",
        "tgn:2002288",
        "tgn:7013961",
        "tgn:7029392"
    ],
    "tgn:id":2654487,
    "tgn:name":"Shaffer Mountain",
    "tgn:placetype":[
        "aat:300008798"
    ]
},
  "bbox": [],
  "geometry": {"coordinates":[-79.5167,39.3333],"type":"Point"}
}