{
  "id": 1020630,
  "type": "Feature",
  "properties": {
    "tgn:hierarchy":[
        "tgn:1020630",
        "tgn:1001834",
        "tgn:1000047",
        "tgn:7002455",
        "tgn:1000002",
        "tgn:7029392"
    ],
    "tgn:id":1020630,
    "tgn:name":"Antas",
    "tgn:placetype":[
        "aat:300008347"
    ]
},
  "bbox": [],
  "geometry": {"coordinates":[-38.3333,-10.3333],"type":"Point"}
}