{
  "id": 7501870,
  "type": "Feature",
  "properties": {
    "tgn:hierarchy":[
        "tgn:7501870",
        "tgn:1000004",
        "tgn:7492971",
        "tgn:1000141",
        "tgn:7029392"
    ],
    "tgn:id":7501870,
    "tgn:name":"Houbihu",
    "tgn:placetype":[
        "aat:300008347"
    ]
},
  "bbox": [],
  "geometry": {"coordinates":[120.746111,21.945278],"type":"Point"}
}