{
  "id": 2569023,
  "type": "Feature",
  "properties": {
    "tgn:hierarchy":[
        "tgn:2569023",
        "tgn:1002165",
        "tgn:1000001",
        "tgn:7012149",
        "tgn:7007517",
        "tgn:7029392"
    ],
    "tgn:id":2569023,
    "tgn:name":"Parker Road Pond",
    "tgn:placetype":[
        "aat:300006191"
    ]
},
  "bbox": [],
  "geometry": {"coordinates":[-70.5667,41.5833],"type":"Point"}
}