{
  "id": 2520077,
  "type": "Feature",
  "properties": {
    "tgn:hierarchy":[
        "tgn:2520077",
        "tgn:1000001",
        "tgn:7006451",
        "tgn:2000092",
        "tgn:7012149",
        "tgn:7029392"
    ],
    "tgn:id":2520077,
    "tgn:name":"Molly Ann Draw",
    "tgn:placetype":[
        "aat:300008761"
    ]
},
  "bbox": [],
  "geometry": {"coordinates":[-112.0167,35.65],"type":"Point"}
}