{
  "id": 2449230,
  "type": "Feature",
  "properties": {
    "tgn:hierarchy":[
        "tgn:2449230",
        "tgn:1000001",
        "tgn:7012149",
        "tgn:7029392"
    ],
    "tgn:id":2449230,
    "tgn:name":"Limestone Creek",
    "tgn:placetype":[
        "aat:300008706"
    ]
},
  "bbox": [],
  "geometry": {"coordinates":[-86.15,30.9667],"type":"Point"}
}