{
  "id": 2362560,
  "type": "Feature",
  "properties": {
    "tgn:hierarchy":[
        "tgn:2362560",
        "tgn:1000001",
        "tgn:7012149",
        "tgn:2001715",
        "tgn:7007708",
        "tgn:7029392"
    ],
    "tgn:id":2362560,
    "tgn:name":"Great Basin Waterhole",
    "tgn:placetype":[
        "aat:300006191"
    ]
},
  "bbox": [],
  "geometry": {"coordinates":[-120.2667,43.5333],"type":"Point"}
}