{
  "id": 7077659,
  "type": "Feature",
  "properties": {
    "tgn:hierarchy":[
        "tgn:7077659",
        "tgn:7000096",
        "tgn:1000003",
        "tgn:7000084",
        "tgn:7029392"
    ],
    "tgn:id":7077659,
    "tgn:name":"Koselm\u00fchlen Flie\u00df",
    "tgn:placetype":[
        "aat:300008699"
    ]
},
  "bbox": [],
  "geometry": {"coordinates":[14.15,51.766667],"type":"Point"}
}