{
  "id": 2610571,
  "type": "Feature",
  "properties": {
    "tgn:hierarchy":[
        "tgn:2610571",
        "tgn:1000001",
        "tgn:2001810",
        "tgn:7012149",
        "tgn:7007713",
        "tgn:7029392"
    ],
    "tgn:id":2610571,
    "tgn:name":"Red Cloud Mine",
    "tgn:placetype":[
        "aat:300000390"
    ]
},
  "bbox": [],
  "geometry": {"coordinates":[-103.6333,44.3333],"type":"Point"}
}