{
  "id": 1109106,
  "type": "Feature",
  "properties": {
    "tgn:hierarchy":[
        "tgn:1109106",
        "tgn:1000001",
        "tgn:7006451",
        "tgn:7012149",
        "tgn:7029392"
    ],
    "tgn:id":1109106,
    "tgn:name":"Harcuvar Mountains",
    "tgn:placetype":[
        "aat:300008795"
    ]
},
  "bbox": [],
  "geometry": {"coordinates":[-113.3667,34.05],"type":"Point"}
}