{
  "id": 2349118,
  "type": "Feature",
  "properties": {
    "tgn:hierarchy":[
        "tgn:2349118",
        "tgn:1000001",
        "tgn:7012149",
        "tgn:1002871",
        "tgn:7007568",
        "tgn:7029392"
    ],
    "tgn:id":2349118,
    "tgn:name":"Gilbert Corners",
    "tgn:placetype":[
        "aat:300008347"
    ]
},
  "bbox": [],
  "geometry": {"coordinates":[-73.7333,43.0667],"type":"Point"}
}