{
  "id": 2366213,
  "type": "Feature",
  "properties": {
    "tgn:hierarchy":[
        "tgn:2366213",
        "tgn:1000001",
        "tgn:2000458",
        "tgn:7012149",
        "tgn:7007250",
        "tgn:7029392"
    ],
    "tgn:id":2366213,
    "tgn:name":"Griffin Butte",
    "tgn:placetype":[
        "aat:300008798"
    ]
},
  "bbox": [],
  "geometry": {"coordinates":[-114.4167,43.7167],"type":"Point"}
}