{
  "id": 2507189,
  "type": "Feature",
  "properties": {
    "tgn:hierarchy":[
        "tgn:2507189",
        "tgn:1000001",
        "tgn:7012149",
        "tgn:2001712",
        "tgn:7007708",
        "tgn:7029392"
    ],
    "tgn:id":2507189,
    "tgn:name":"Metolius Water Tank",
    "tgn:placetype":[
        "aat:300006191"
    ]
},
  "bbox": [],
  "geometry": {"coordinates":[-121.15,44.5667],"type":"Point"}
}