{
  "id": 7346490,
  "type": "Feature",
  "properties": {
    "tgn:hierarchy":[
        "tgn:7346490",
        "tgn:7001165",
        "tgn:1000003",
        "tgn:7002793",
        "tgn:1000095",
        "tgn:7029392"
    ],
    "tgn:id":7346490,
    "tgn:name":"Bellreguart",
    "tgn:placetype":[
        "aat:300008347"
    ]
},
  "bbox": [],
  "geometry": {"coordinates":[-0.166667,38.95],"type":"Point"}
}