{
  "id": 2048434,
  "type": "Feature",
  "properties": {
    "tgn:hierarchy":[
        "tgn:2048434",
        "tgn:1000001",
        "tgn:1002902",
        "tgn:7012149",
        "tgn:7007516",
        "tgn:7029392"
    ],
    "tgn:id":2048434,
    "tgn:name":"Rehobeth",
    "tgn:placetype":[
        "aat:300008347"
    ]
},
  "bbox": [],
  "geometry": {"coordinates":[-75.65,38.0333],"type":"Point"}
}