{
  "id": 7087720,
  "type": "Feature",
  "properties": {
    "tgn:hierarchy":[
        "tgn:7087720",
        "tgn:7003692",
        "tgn:1000003",
        "tgn:7000084",
        "tgn:7029392"
    ],
    "tgn:id":7087720,
    "tgn:name":"Weinauer Hof",
    "tgn:placetype":[
        "aat:300000206"
    ]
},
  "bbox": [],
  "geometry": {"coordinates":[8.333333,48.766667],"type":"Point"}
}