{
  "id": 7506117,
  "type": "Feature",
  "properties": {
    "tgn:hierarchy":[
        "tgn:7506117",
        "tgn:1009227",
        "tgn:1000226",
        "tgn:7016729",
        "tgn:1000006",
        "tgn:7029392"
    ],
    "tgn:id":7506117,
    "tgn:name:en":"Scott Point",
    "tgn:placetype":[
        "aat:300386846"
    ]
},
  "bbox": [],
  "geometry": {"coordinates":[174.216667,-41.15],"type":"Point"}
}