{
  "id": 1086097,
  "type": "Feature",
  "properties": {
    "tgn:hierarchy":[
        "tgn:1086097",
        "tgn:1001101",
        "tgn:1000004",
        "tgn:7018453",
        "tgn:1000144",
        "tgn:7029392"
    ],
    "tgn:id":1086097,
    "tgn:name":"Beypazar\u0131",
    "tgn:placetype":[
        "aat:300008347"
    ]
},
  "bbox": [],
  "geometry": {"coordinates":[31.9333,40.1667],"type":"Point"}
}