{
  "id": 7257173,
  "type": "Feature",
  "properties": {
    "tgn:concordances":{
        "gn:id":"2758840"
    },
    "tgn:hierarchy":[
        "tgn:7257173",
        "tgn:1000003",
        "tgn:7003622",
        "tgn:7016845",
        "tgn:7029392"
    ],
    "tgn:id":7257173,
    "tgn:name:nl":"Bleijenbeek",
    "tgn:placetype":[
        "aat:300008347",
        "aat:300387200"
    ]
},
  "bbox": [],
  "geometry": {"coordinates":[6.083333,51.616667],"type":"Point"}
}