{
  "id": 7281018,
  "type": "Feature",
  "properties": {
    "tgn:hierarchy":[
        "tgn:7281018",
        "tgn:7016598",
        "tgn:1000049",
        "tgn:1000002",
        "tgn:7029392"
    ],
    "tgn:id":7281018,
    "tgn:name":"Sichal, Cerro",
    "tgn:placetype":[
        "aat:300008795"
    ]
},
  "bbox": [],
  "geometry": {"coordinates":[-68.983333,-21.65],"type":"Point"}
}