{
  "id": 7011245,
  "type": "Feature",
  "properties": {
    "tgn:hierarchy":[
        "tgn:7011245",
        "tgn:7002445",
        "tgn:1000003",
        "tgn:7012032",
        "tgn:7008591",
        "tgn:7029392"
    ],
    "tgn:id":7011245,
    "tgn:name:en":"Cheddar",
    "tgn:placetype":[
        "aat:300008347"
    ]
},
  "bbox": [],
  "geometry": {"coordinates":[-2.778333,51.280278],"type":"Point"}
}