{
  "id": 2422155,
  "type": "Feature",
  "properties": {
    "tgn:hierarchy":[
        "tgn:2422155",
        "tgn:7002659",
        "tgn:1000001",
        "tgn:7012149",
        "tgn:2000062",
        "tgn:7029392"
    ],
    "tgn:id":2422155,
    "tgn:name":"Jim Mack Branch",
    "tgn:placetype":[
        "aat:300008699"
    ]
},
  "bbox": [],
  "geometry": {"coordinates":[-87.4333,33.2667],"type":"Point"}
}