{
  "id": 2682180,
  "type": "Feature",
  "properties": {
    "tgn:hierarchy":[
        "tgn:2682180",
        "tgn:1000001",
        "tgn:7012149",
        "tgn:7007157",
        "tgn:1002608",
        "tgn:7029392"
    ],
    "tgn:id":2682180,
    "tgn:name":"South Tule Canyon",
    "tgn:placetype":[
        "aat:300008761"
    ]
},
  "bbox": [],
  "geometry": {"coordinates":[-118.4667,34.6167],"type":"Point"}
}