{
  "id": 2445904,
  "type": "Feature",
  "properties": {
    "tgn:hierarchy":[
        "tgn:2445904",
        "tgn:1000001",
        "tgn:2001746",
        "tgn:7012149",
        "tgn:7007712",
        "tgn:7029392"
    ],
    "tgn:id":2445904,
    "tgn:name":"Lester Creek",
    "tgn:placetype":[
        "aat:300008706"
    ]
},
  "bbox": [],
  "geometry": {"coordinates":[-79.5333,33.45],"type":"Point"}
}