{
  "id": 7288535,
  "type": "Feature",
  "properties": {
    "tgn:hierarchy":[
        "tgn:7288535",
        "tgn:1001637",
        "tgn:1000049",
        "tgn:1000002",
        "tgn:7029392"
    ],
    "tgn:id":7288535,
    "tgn:name":"La Capilla",
    "tgn:placetype":[
        "aat:300000206"
    ]
},
  "bbox": [],
  "geometry": {"coordinates":[-72.183333,-37.366667],"type":"Point"}
}