{
  "id": 7512484,
  "type": "Feature",
  "properties": {
    "tgn:hierarchy":[
        "tgn:7512484",
        "tgn:1009227",
        "tgn:1000226",
        "tgn:7018437",
        "tgn:1000006",
        "tgn:7029392"
    ],
    "tgn:id":7512484,
    "tgn:name:en":"Hospital Creek",
    "tgn:placetype":[
        "aat:300008699"
    ]
},
  "bbox": [],
  "geometry": {"coordinates":[169.283333,-44.65],"type":"Point"}
}