{
  "id": 7405821,
  "type": "Feature",
  "properties": {
    "tgn:hierarchy":[
        "tgn:7405821",
        "tgn:1000001",
        "tgn:1001906",
        "tgn:7005560",
        "tgn:7029392"
    ],
    "tgn:id":7405821,
    "tgn:name":"Los Gavilanes",
    "tgn:placetype":[
        "aat:300008347"
    ]
},
  "bbox": [],
  "geometry": {"coordinates":[-104.608333,22.091667],"type":"Point"}
}