{
  "id": 2340195,
  "type": "Feature",
  "properties": {
    "tgn:hierarchy":[
        "tgn:2340195",
        "tgn:1000001",
        "tgn:7012149",
        "tgn:1003040",
        "tgn:7007568",
        "tgn:7029392"
    ],
    "tgn:id":2340195,
    "tgn:name":"French Brook",
    "tgn:placetype":[
        "aat:300008699"
    ]
},
  "bbox": [],
  "geometry": {"coordinates":[-78.35,42.85],"type":"Point"}
}