{
  "id": 7414753,
  "type": "Feature",
  "properties": {
    "tgn:hierarchy":[
        "tgn:7414753",
        "tgn:7005584",
        "tgn:1000001",
        "tgn:7005560",
        "tgn:7029392"
    ],
    "tgn:id":7414753,
    "tgn:name":"Otates",
    "tgn:placetype":[
        "aat:300008347"
    ]
},
  "bbox": [],
  "geometry": {"coordinates":[-101.483056,20.399167],"type":"Point"}
}