{
  "id": 7192408,
  "type": "Feature",
  "properties": {
    "tgn:hierarchy":[
        "tgn:7192408",
        "tgn:1000003",
        "tgn:7003682",
        "tgn:7000084",
        "tgn:7029392"
    ],
    "tgn:id":7192408,
    "tgn:name":"Frechtenhalerhof",
    "tgn:placetype":[
        "aat:300000206"
    ]
},
  "bbox": [],
  "geometry": {"coordinates":[7.916667,49.45],"type":"Point"}
}