{
  "id": 2242153,
  "type": "Feature",
  "properties": {
    "tgn:hierarchy":[
        "tgn:2242153",
        "tgn:1000001",
        "tgn:7012149",
        "tgn:2002288",
        "tgn:7013961",
        "tgn:7029392"
    ],
    "tgn:id":2242153,
    "tgn:name":"Clay Run",
    "tgn:placetype":[
        "aat:300008699"
    ]
},
  "bbox": [],
  "geometry": {"coordinates":[-79.7833,39.6333],"type":"Point"}
}