{
  "id": 2523783,
  "type": "Feature",
  "properties": {
    "tgn:hierarchy":[
        "tgn:2523783",
        "tgn:1000001",
        "tgn:7012149",
        "tgn:2000330",
        "tgn:7007248",
        "tgn:7029392"
    ],
    "tgn:id":2523783,
    "tgn:name":"Moran",
    "tgn:placetype":[
        "aat:300008347"
    ]
},
  "bbox": [],
  "geometry": {"coordinates":[-83.9167,32.8333],"type":"Point"}
}