<<<<<<< HEAD
{
  "id": 2259369,
  "type": "Feature",
  "properties": {
    "tgn:hierarchy":[
        "tgn:2259369",
        "tgn:2000090",
        "tgn:1000001",
        "tgn:7006451",
        "tgn:7012149",
        "tgn:7029392"
    ],
    "tgn:id":2259369,
    "tgn:name":"Cottonwood Spring",
    "tgn:placetype":[
        "aat:300008697"
    ]
},
  "bbox": [],
  "geometry": {"coordinates":[-109.2,36.5667],"type":"Point"}
}
=======
{"geometry":{"type":"Point","coordinates":[-109.200000,36.566700]},"type":"Feature","properties":{"hierarchy":["tgn:2259369","tgn:2000090","tgn:1000001","tgn:7006451","tgn:7012149","tgn:7029392"],"placetype":["aat:300008697"],"id":2259369,"name:xx":"Cottonwood Spring"}}
>>>>>>> 03f74aca74312dbeaf24d7e61306dd6a786dc3d0
