{
  "id": 7521995,
  "type": "Feature",
  "properties": {
    "tgn:hierarchy":[
        "tgn:7521995",
        "tgn:7001242",
        "tgn:7016833",
        "tgn:1001113",
        "tgn:7029392"
    ],
    "tgn:id":7521995,
    "tgn:name:en":"Al Farr\u0101y\u012bn",
    "tgn:placetype":[
        "aat:300008347"
    ]
},
  "bbox": [],
  "geometry": {"coordinates":[31.601172,30.802692],"type":"Point"}
}