{
  "id": 2493583,
  "type": "Feature",
  "properties": {
    "tgn:hierarchy":[
        "tgn:2493583",
        "tgn:1000001",
        "tgn:7012149",
        "tgn:7007522",
        "tgn:7029392"
    ],
    "tgn:id":2493583,
    "tgn:name":"Marsh Hollow",
    "tgn:placetype":[
        "aat:300008761"
    ]
},
  "bbox": [],
  "geometry": {"coordinates":[-88.6667,32.9167],"type":"Point"}
}