{
  "id": 7175337,
  "type": "Feature",
  "properties": {
    "tgn:hierarchy":[
        "tgn:7175337",
        "tgn:1000003",
        "tgn:7003676",
        "tgn:7000084",
        "tgn:7029392"
    ],
    "tgn:id":7175337,
    "tgn:name":"Grie\u00dfem",
    "tgn:placetype":[
        "aat:300008347"
    ]
},
  "bbox": [],
  "geometry": {"coordinates":[9.216667,52.016667],"type":"Point"}
}