{
  "id": 2182736,
  "type": "Feature",
  "properties": {
    "tgn:hierarchy":[
        "tgn:2182736",
        "tgn:1000001",
        "tgn:7016172",
        "tgn:7012149",
        "tgn:2000165",
        "tgn:7029392"
    ],
    "tgn:id":2182736,
    "tgn:name":"Blue Spring Hollow",
    "tgn:placetype":[
        "aat:300008761"
    ]
},
  "bbox": [],
  "geometry": {"coordinates":[-90.9833,36.4667],"type":"Point"}
}