{
  "id": 2414980,
  "type": "Feature",
  "properties": {
    "tgn:hierarchy":[
        "tgn:2414980",
        "tgn:1000001",
        "tgn:7012149",
        "tgn:1002314",
        "tgn:7007240",
        "tgn:7029392"
    ],
    "tgn:id":2414980,
    "tgn:name":"Isla Grande",
    "tgn:placetype":[
        "aat:300008791"
    ]
},
  "bbox": [],
  "geometry": {"coordinates":[-80.25,25.6833],"type":"Point"}
}