{
  "id": 7014913,
  "type": "Feature",
  "properties": {
    "tgn:hierarchy":[
        "tgn:7014913",
        "tgn:1000004",
        "tgn:7011606",
        "tgn:7018214",
        "tgn:7002435",
        "tgn:7029392"
    ],
    "tgn:id":7014913,
    "tgn:name":"Surgut",
    "tgn:placetype":[
        "aat:300008347"
    ]
},
  "bbox": [],
  "geometry": {"coordinates":[73.3333,61.2333],"type":"Point"}
}