{
  "id": 7329831,
  "type": "Feature",
  "properties": {
    "tgn:hierarchy":[
        "tgn:7329831",
        "tgn:7002825",
        "tgn:7016622",
        "tgn:1000003",
        "tgn:1000095",
        "tgn:7029392"
    ],
    "tgn:id":7329831,
    "tgn:name":"Jinojea, Caleta de",
    "tgn:placetype":[
        "aat:300132317"
    ]
},
  "bbox": [],
  "geometry": {"coordinates":[-14.133333,28.45],"type":"Point"}
}