{
  "id": 7357216,
  "type": "Feature",
  "properties": {
    "tgn:hierarchy":[
        "tgn:7357216",
        "tgn:7005581",
        "tgn:1000001",
        "tgn:7005560",
        "tgn:7029392"
    ],
    "tgn:id":7357216,
    "tgn:name":"Rancho Chisco",
    "tgn:placetype":[
        "aat:300000241"
    ]
},
  "bbox": [],
  "geometry": {"coordinates":[-106.716667,28.333333],"type":"Point"}
}