{
  "id": 2567743,
  "type": "Feature",
  "properties": {
    "tgn:hierarchy":[
        "tgn:2567743",
        "tgn:1000001",
        "tgn:7012149",
        "tgn:7007157",
        "tgn:7014475",
        "tgn:7029392"
    ],
    "tgn:id":2567743,
    "tgn:name":"Paradise Creek",
    "tgn:placetype":[
        "aat:300008706"
    ]
},
  "bbox": [],
  "geometry": {"coordinates":[-121.6833,37.1333],"type":"Point"}
}