{
  "id": 2416864,
  "type": "Feature",
  "properties": {
    "tgn:hierarchy":[
        "tgn:2416864",
        "tgn:1000001",
        "tgn:7019560",
        "tgn:7012149",
        "tgn:7007566",
        "tgn:7029392"
    ],
    "tgn:id":2416864,
    "tgn:name":"Jack Tank",
    "tgn:placetype":[
        "aat:300006191"
    ]
},
  "bbox": [],
  "geometry": {"coordinates":[-104.5167,34.0333],"type":"Point"}
}