{
  "id": 2395615,
  "type": "Feature",
  "properties": {
    "tgn:hierarchy":[
        "tgn:2395615",
        "tgn:1000001",
        "tgn:7012149",
        "tgn:2002276",
        "tgn:7013961",
        "tgn:7029392"
    ],
    "tgn:id":2395615,
    "tgn:name":"Hollidays Run",
    "tgn:placetype":[
        "aat:300008699"
    ]
},
  "bbox": [],
  "geometry": {"coordinates":[-80.6667,39.9833],"type":"Point"}
}