<<<<<<< HEAD
{
  "id": 7179901,
  "type": "Feature",
  "properties": {
    "tgn:hierarchy":[
        "tgn:7179901",
        "tgn:1000003",
        "tgn:7003689",
        "tgn:7000084",
        "tgn:7029392"
    ],
    "tgn:id":7179901,
    "tgn:name":"Haar-Berg",
    "tgn:placetype":[
        "aat:300008777"
    ]
},
  "bbox": [],
  "geometry": {"coordinates":[11.116667,50.95],"type":"Point"}
}
=======
{"geometry":{"type":"Point","coordinates":[11.116667,50.950000]},"type":"Feature","properties":{"hierarchy":["tgn:7179901","tgn:1000003","tgn:7003689","tgn:7000084","tgn:7029392"],"placetype":["aat:300008777"],"id":7179901,"name:xx":"Haar-Berg"}}
>>>>>>> 03f74aca74312dbeaf24d7e61306dd6a786dc3d0
