{
  "id": 1029158,
  "type": "Feature",
  "properties": {
    "tgn:hierarchy":[
        "tgn:1029158",
        "tgn:7002445",
        "tgn:1000003",
        "tgn:7008117",
        "tgn:7008591",
        "tgn:7029392"
    ],
    "tgn:id":1029158,
    "tgn:name:en":"Egremont",
    "tgn:placetype":[
        "aat:300008347"
    ]
},
  "bbox": [],
  "geometry": {"coordinates":[-3.516667,54.466667],"type":"Point"}
}