{
  "id": 2458983,
  "type": "Feature",
  "properties": {
    "tgn:hierarchy":[
        "tgn:2458983",
        "tgn:1000001",
        "tgn:7012149",
        "tgn:1002545",
        "tgn:7007157",
        "tgn:7029392"
    ],
    "tgn:id":2458983,
    "tgn:name":"Little Pico Creek",
    "tgn:placetype":[
        "aat:300008706"
    ]
},
  "bbox": [],
  "geometry": {"coordinates":[-121.1167,35.6833],"type":"Point"}
}