{
  "id": 2072746,
  "type": "Feature",
  "properties": {
    "tgn:hierarchy":[
        "tgn:2072746",
        "tgn:1000001",
        "tgn:7012149",
        "tgn:1002875",
        "tgn:7007568",
        "tgn:7029392"
    ],
    "tgn:id":2072746,
    "tgn:name":"Townsend",
    "tgn:placetype":[
        "aat:300008347",
        "aat:300387210"
    ]
},
  "bbox": [],
  "geometry": {"coordinates":[-76.95,42.3333],"type":"Point"}
}