<<<<<<< HEAD
{
  "id": 7482339,
  "type": "Feature",
  "properties": {
    "tgn:hierarchy":[
        "tgn:7482339",
        "tgn:1000004",
        "tgn:7490934",
        "tgn:1000141",
        "tgn:7029392"
    ],
    "tgn:id":7482339,
    "tgn:name":"Guanshan Cun",
    "tgn:placetype":[
        "aat:300387173"
    ]
},
  "bbox": [],
  "geometry": {"coordinates":[120.605556,23.172778],"type":"Point"}
}
=======
{"geometry":{"type":"Point","coordinates":[120.605556,23.172778]},"type":"Feature","properties":{"hierarchy":["tgn:7482339","tgn:1000004","tgn:7490934","tgn:1000141","tgn:7029392"],"placetype":["aat:300387173"],"id":7482339,"name:xx":"Guanshan Cun"}}
>>>>>>> 03f74aca74312dbeaf24d7e61306dd6a786dc3d0
