{
  "id": 2452874,
  "type": "Feature",
  "properties": {
    "tgn:hierarchy":[
        "tgn:2452874",
        "tgn:1000001",
        "tgn:7012149",
        "tgn:7007157",
        "tgn:2000185",
        "tgn:7029392"
    ],
    "tgn:id":2452874,
    "tgn:name":"Little Butte",
    "tgn:placetype":[
        "aat:300008798"
    ]
},
  "bbox": [],
  "geometry": {"coordinates":[-123.65,39.9667],"type":"Point"}
}