{
  "id": 2160508,
  "type": "Feature",
  "properties": {
    "tgn:hierarchy":[
        "tgn:2160508",
        "tgn:1000001",
        "tgn:2001739",
        "tgn:7012149",
        "tgn:7007712",
        "tgn:7029392"
    ],
    "tgn:id":2160508,
    "tgn:name":"Beet Island",
    "tgn:placetype":[
        "aat:300008791"
    ]
},
  "bbox": [],
  "geometry": {"coordinates":[-80.4833,32.5167],"type":"Point"}
}