{
  "id": 2447708,
  "type": "Feature",
  "properties": {
    "tgn:hierarchy":[
        "tgn:2447708",
        "tgn:1000001",
        "tgn:1002286",
        "tgn:7012149",
        "tgn:7007710",
        "tgn:7029392"
    ],
    "tgn:id":2447708,
    "tgn:name":"Lick Run",
    "tgn:placetype":[
        "aat:300008699"
    ]
},
  "bbox": [],
  "geometry": {"coordinates":[-77.9667,41.3333],"type":"Point"}
}