<<<<<<< HEAD
{
  "id": 2151993,
  "type": "Feature",
  "properties": {
    "tgn:hierarchy":[
        "tgn:2151993",
        "tgn:1000001",
        "tgn:7012149",
        "tgn:2001872",
        "tgn:7007825",
        "tgn:7029392"
    ],
    "tgn:id":2151993,
    "tgn:name":"Baugus Branch",
    "tgn:placetype":[
        "aat:300008699"
    ]
},
  "bbox": [],
  "geometry": {"coordinates":[-88.0667,35.2],"type":"Point"}
}
=======
{"geometry":{"type":"Point","coordinates":[-88.066700,35.200000]},"type":"Feature","properties":{"hierarchy":["tgn:2151993","tgn:1000001","tgn:7012149","tgn:2001872","tgn:7007825","tgn:7029392"],"placetype":["aat:300008699"],"id":2151993,"name:xx":"Baugus Branch"}}
>>>>>>> 03f74aca74312dbeaf24d7e61306dd6a786dc3d0
