{
  "id": 2270987,
  "type": "Feature",
  "properties": {
    "tgn:hierarchy":[
        "tgn:2270987",
        "tgn:1000001",
        "tgn:7012149",
        "tgn:7007157",
        "tgn:2000185",
        "tgn:7029392"
    ],
    "tgn:id":2270987,
    "tgn:name":"Cubbler Place",
    "tgn:placetype":[
        "aat:300008347"
    ]
},
  "bbox": [],
  "geometry": {"coordinates":[-123.1333,39.75],"type":"Point"}
}