<<<<<<< HEAD
{
  "id": 2257976,
  "type": "Feature",
  "properties": {
    "tgn:hierarchy":[
        "tgn:2257976",
        "tgn:1000001",
        "tgn:7006451",
        "tgn:7012149",
        "tgn:2000097",
        "tgn:7029392"
    ],
    "tgn:id":2257976,
    "tgn:name":"Cortez Peak",
    "tgn:placetype":[
        "aat:300008798"
    ]
},
  "bbox": [],
  "geometry": {"coordinates":[-113.2167,33.25],"type":"Point"}
}
=======
{"geometry":{"type":"Point","coordinates":[-113.216700,33.250000]},"type":"Feature","properties":{"hierarchy":["tgn:2257976","tgn:1000001","tgn:7006451","tgn:7012149","tgn:2000097","tgn:7029392"],"placetype":["aat:300008798"],"id":2257976,"name:xx":"Cortez Peak"}}
>>>>>>> 03f74aca74312dbeaf24d7e61306dd6a786dc3d0
