{
  "id": 1133688,
  "type": "Feature",
  "properties": {
    "tgn:hierarchy":[
        "tgn:1133688",
        "tgn:1000001",
        "tgn:7012149",
        "tgn:7007826",
        "tgn:7029392"
    ],
    "tgn:id":1133688,
    "tgn:name":"Live Oak Creek",
    "tgn:placetype":[
        "aat:300008706"
    ]
},
  "bbox": [],
  "geometry": {"coordinates":[-100.5333,32.5167],"type":"Point"}
}