<<<<<<< HEAD
{
  "id": 2256519,
  "type": "Feature",
  "properties": {
    "tgn:hierarchy":[
        "tgn:2256519",
        "tgn:1000001",
        "tgn:7012149",
        "tgn:1002520",
        "tgn:7007710",
        "tgn:7029392"
    ],
    "tgn:id":2256519,
    "tgn:name":"Corbettown",
    "tgn:placetype":[
        "aat:300008347"
    ]
},
  "bbox": [],
  "geometry": {"coordinates":[-79.1667,40.9667],"type":"Point"}
}
=======
{"geometry":{"type":"Point","coordinates":[-79.166700,40.966700]},"type":"Feature","properties":{"hierarchy":["tgn:2256519","tgn:1000001","tgn:7012149","tgn:1002520","tgn:7007710","tgn:7029392"],"placetype":["aat:300008347"],"id":2256519,"name:xx":"Corbettown"}}
>>>>>>> 03f74aca74312dbeaf24d7e61306dd6a786dc3d0
