{
  "id": 2210234,
  "type": "Feature",
  "properties": {
    "tgn:hierarchy":[
        "tgn:2210234",
        "tgn:1000001",
        "tgn:7012149",
        "tgn:7007157",
        "tgn:1002675",
        "tgn:7029392"
    ],
    "tgn:id":2210234,
    "tgn:name":"Buscones Peak",
    "tgn:placetype":[
        "aat:300008798"
    ]
},
  "bbox": [],
  "geometry": {"coordinates":[-118.4833,37.7667],"type":"Point"}
}