{
  "id": 7096610,
  "type": "Feature",
  "properties": {
    "tgn:hierarchy":[
        "tgn:7096610",
        "tgn:1000003",
        "tgn:7003688",
        "tgn:7000084",
        "tgn:7029392"
    ],
    "tgn:id":7096610,
    "tgn:name":"Sohrheide",
    "tgn:placetype":[
        "aat:300000206"
    ]
},
  "bbox": [],
  "geometry": {"coordinates":[9.65,54.083333],"type":"Point"}
}