{
  "id": 2091719,
  "type": "Feature",
  "properties": {
    "tgn:hierarchy":[
        "tgn:2091719",
        "tgn:1000001",
        "tgn:7012149",
        "tgn:1002900",
        "tgn:7007710",
        "tgn:7029392"
    ],
    "tgn:id":2091719,
    "tgn:name":"Paxtonville",
    "tgn:placetype":[
        "aat:300008347"
    ]
},
  "bbox": [],
  "geometry": {"coordinates":[-77.0833,40.7667],"type":"Point"}
}