{
  "id": 7432777,
  "type": "Feature",
  "properties": {
    "tgn:hierarchy":[
        "tgn:7432777",
        "tgn:1000001",
        "tgn:7005590",
        "tgn:7005560",
        "tgn:7029392"
    ],
    "tgn:id":7432777,
    "tgn:name":"Tzitzio",
    "tgn:placetype":[
        "aat:300008347"
    ]
},
  "bbox": [],
  "geometry": {"coordinates":[-100.916667,19.566667],"type":"Point"}
}