{
  "id": 7410151,
  "type": "Feature",
  "properties": {
    "tgn:hierarchy":[
        "tgn:7410151",
        "tgn:1000001",
        "tgn:7005590",
        "tgn:7005560",
        "tgn:7029392"
    ],
    "tgn:id":7410151,
    "tgn:name":"Olivos",
    "tgn:placetype":[
        "aat:300008347"
    ]
},
  "bbox": [],
  "geometry": {"coordinates":[-102.15,18.845833],"type":"Point"}
}