{
  "id": 7584647,
  "type": "Feature",
  "properties": {
    "tgn:hierarchy":[
        "tgn:7584647",
        "tgn:1000004",
        "tgn:7000198",
        "tgn:1001894",
        "tgn:7029392"
    ],
    "tgn:id":7584647,
    "tgn:name:en":"Bindr\u0101ban T\u0101l",
    "tgn:placetype":[
        "aat:300008680"
    ]
},
  "bbox": [],
  "geometry": {"coordinates":[78.844464,24.753911],"type":"Point"}
}