{
  "id": 2033994,
  "type": "Feature",
  "properties": {
    "tgn:hierarchy":[
        "tgn:2033994",
        "tgn:1000001",
        "tgn:1002273",
        "tgn:7012149",
        "tgn:7007252",
        "tgn:7029392"
    ],
    "tgn:id":2033994,
    "tgn:name":"Vesta",
    "tgn:placetype":[
        "aat:300008347",
        "aat:300387210"
    ]
},
  "bbox": [],
  "geometry": {"coordinates":[-85.55,38.4833],"type":"Point"}
}