{
  "id": 7143232,
  "type": "Feature",
  "properties": {
    "tgn:hierarchy":[
        "tgn:7143232",
        "tgn:1000003",
        "tgn:7003676",
        "tgn:7000084",
        "tgn:7029392"
    ],
    "tgn:id":7143232,
    "tgn:name":"Loge",
    "tgn:placetype":[
        "aat:300008347"
    ]
},
  "bbox": [],
  "geometry": {"coordinates":[9.083333,51.85],"type":"Point"}
}