{
  "id": 7586755,
  "type": "Feature",
  "properties": {
    "tgn:hierarchy":[
        "tgn:7586755",
        "tgn:1000004",
        "tgn:7000198",
        "tgn:7000799",
        "tgn:7029392"
    ],
    "tgn:id":7586755,
    "tgn:name:en":"Rasikol",
    "tgn:placetype":[
        "aat:300259572"
    ]
},
  "bbox": [],
  "geometry": {"coordinates":[74.483333,34.455556],"type":"Point"}
}