<<<<<<< HEAD
{
  "id": 7112973,
  "type": "Feature",
  "properties": {
    "tgn:hierarchy":[
        "tgn:7112973",
        "tgn:1000003",
        "tgn:7003687",
        "tgn:7000084",
        "tgn:7029392"
    ],
    "tgn:id":7112973,
    "tgn:name":"Rodigkau",
    "tgn:placetype":[
        "aat:300008347"
    ]
},
  "bbox": [],
  "geometry": {"coordinates":[12.15,51.65],"type":"Point"}
}
=======
{"geometry":{"type":"Point","coordinates":[12.150000,51.650000]},"type":"Feature","properties":{"hierarchy":["tgn:7112973","tgn:1000003","tgn:7003687","tgn:7000084","tgn:7029392"],"placetype":["aat:300008347"],"id":7112973,"name:xx":"Rodigkau"}}
>>>>>>> 03f74aca74312dbeaf24d7e61306dd6a786dc3d0
