{
  "id": 2664747,
  "type": "Feature",
  "properties": {
    "tgn:hierarchy":[
        "tgn:2664747",
        "tgn:1000001",
        "tgn:7012149",
        "tgn:2002264",
        "tgn:7013961",
        "tgn:7029392"
    ],
    "tgn:id":2664747,
    "tgn:name":"Simms Cave",
    "tgn:placetype":[
        "aat:300008746"
    ]
},
  "bbox": [],
  "geometry": {"coordinates":[-80.4333,37.8667],"type":"Point"}
}