{
  "id": 7413930,
  "type": "Feature",
  "properties": {
    "tgn:hierarchy":[
        "tgn:7413930",
        "tgn:7005580",
        "tgn:1000001",
        "tgn:7005560",
        "tgn:7029392"
    ],
    "tgn:id":7413930,
    "tgn:name":"Calzada Larga",
    "tgn:placetype":[
        "aat:300008347"
    ]
},
  "bbox": [],
  "geometry": {"coordinates":[-93.45,16.673611],"type":"Point"}
}