{
  "id": 7166385,
  "type": "Feature",
  "properties": {
    "tgn:hierarchy":[
        "tgn:7166385",
        "tgn:1000003",
        "tgn:7003687",
        "tgn:7000084",
        "tgn:7029392"
    ],
    "tgn:id":7166385,
    "tgn:name":"Heidehaus",
    "tgn:placetype":[
        "aat:300000206"
    ]
},
  "bbox": [],
  "geometry": {"coordinates":[11.166667,51.433333],"type":"Point"}
}