<<<<<<< HEAD
{
  "id": 2256090,
  "type": "Feature",
  "properties": {
    "tgn:hierarchy":[
        "tgn:2256090",
        "tgn:1000001",
        "tgn:2002102",
        "tgn:7012149",
        "tgn:7007827",
        "tgn:7029392"
    ],
    "tgn:id":2256090,
    "tgn:name":"Copper Mountain",
    "tgn:placetype":[
        "aat:300008798"
    ]
},
  "bbox": [],
  "geometry": {"coordinates":[-114.0,41.2333],"type":"Point"}
}
=======
{"geometry":{"type":"Point","coordinates":[-114.000000,41.233300]},"type":"Feature","properties":{"hierarchy":["tgn:2256090","tgn:1000001","tgn:2002102","tgn:7012149","tgn:7007827","tgn:7029392"],"placetype":["aat:300008798"],"id":2256090,"name:xx":"Copper Mountain"}}
>>>>>>> 03f74aca74312dbeaf24d7e61306dd6a786dc3d0
