{
  "id": 2482095,
  "type": "Feature",
  "properties": {
    "tgn:hierarchy":[
        "tgn:2482095",
        "tgn:1000001",
        "tgn:7012149",
        "tgn:2001249",
        "tgn:7007523",
        "tgn:7029392"
    ],
    "tgn:id":2482095,
    "tgn:name":"Lanetown Hollow",
    "tgn:placetype":[
        "aat:300008761"
    ]
},
  "bbox": [],
  "geometry": {"coordinates":[-93.4667,36.9333],"type":"Point"}
}