{
  "id": 7429031,
  "type": "Feature",
  "properties": {
    "tgn:hierarchy":[
        "tgn:7429031",
        "tgn:1001835",
        "tgn:1000001",
        "tgn:7005560",
        "tgn:7029392"
    ],
    "tgn:id":7429031,
    "tgn:name":"Playa la Costilla",
    "tgn:placetype":[
        "aat:300008347"
    ]
},
  "bbox": [],
  "geometry": {"coordinates":[-114.666667,30.283333],"type":"Point"}
}