{
  "id": 2631958,
  "type": "Feature",
  "properties": {
    "tgn:hierarchy":[
        "tgn:2631958",
        "tgn:1000001",
        "tgn:7012149",
        "tgn:1002943",
        "tgn:7007708",
        "tgn:7029392"
    ],
    "tgn:id":2631958,
    "tgn:name":"Rover Creek",
    "tgn:placetype":[
        "aat:300008706"
    ]
},
  "bbox": [],
  "geometry": {"coordinates":[-123.9333,45.3167],"type":"Point"}
}