{
  "id": 2775699,
  "type": "Feature",
  "properties": {
    "tgn:hierarchy":[
        "tgn:2775699",
        "tgn:7002659",
        "tgn:1000001",
        "tgn:7012149",
        "tgn:2000038",
        "tgn:7029392"
    ],
    "tgn:id":2775699,
    "tgn:name":"Wilson Heights",
    "tgn:placetype":[
        "aat:300008347"
    ]
},
  "bbox": [],
  "geometry": {"coordinates":[-87.6167,34.8167],"type":"Point"}
}