{
  "id": 7592251,
  "type": "Feature",
  "properties": {
    "tgn:hierarchy":[
        "tgn:7592251",
        "tgn:1000004",
        "tgn:7000198",
        "tgn:7000799",
        "tgn:7029392"
    ],
    "tgn:id":7592251,
    "tgn:name:en":"Trin",
    "tgn:placetype":[
        "aat:300008347"
    ]
},
  "bbox": [],
  "geometry": {"coordinates":[74.937854,32.94226],"type":"Point"}
}