{
  "id": 7391834,
  "type": "Feature",
  "properties": {
    "tgn:hierarchy":[
        "tgn:7391834",
        "tgn:1000001",
        "tgn:7005589",
        "tgn:7005560",
        "tgn:7029392"
    ],
    "tgn:id":7391834,
    "tgn:name":"Rancho Urquizo",
    "tgn:placetype":[
        "aat:300008347"
    ]
},
  "bbox": [],
  "geometry": {"coordinates":[-99.716667,25.883333],"type":"Point"}
}