{
  "id": 2450178,
  "type": "Feature",
  "properties": {
    "tgn:hierarchy":[
        "tgn:2450178",
        "tgn:1000001",
        "tgn:7012149",
        "tgn:2000491",
        "tgn:7007250",
        "tgn:7029392"
    ],
    "tgn:id":2450178,
    "tgn:name":"Line Gulch",
    "tgn:placetype":[
        "aat:300008761"
    ]
},
  "bbox": [],
  "geometry": {"coordinates":[-115.8833,47.4167],"type":"Point"}
}