{
  "id": 2463725,
  "type": "Feature",
  "properties": {
    "tgn:hierarchy":[
        "tgn:2463725",
        "tgn:1000001",
        "tgn:2000586",
        "tgn:7012149",
        "tgn:7007253",
        "tgn:7029392"
    ],
    "tgn:id":2463725,
    "tgn:name":"Locke Branch",
    "tgn:placetype":[
        "aat:300008699"
    ]
},
  "bbox": [],
  "geometry": {"coordinates":[-92.25,40.8167],"type":"Point"}
}