{
  "id": 2297038,
  "type": "Feature",
  "properties": {
    "tgn:hierarchy":[
        "tgn:2297038",
        "tgn:1000001",
        "tgn:7012149",
        "tgn:2001847",
        "tgn:7007825",
        "tgn:7029392"
    ],
    "tgn:id":2297038,
    "tgn:name":"Dry Creek",
    "tgn:placetype":[
        "aat:300008706"
    ]
},
  "bbox": [],
  "geometry": {"coordinates":[-87.0667,36.1667],"type":"Point"}
}