{
  "id": 7531451,
  "type": "Feature",
  "properties": {
    "tgn:hierarchy":[
        "tgn:7531451",
        "tgn:7001242",
        "tgn:7016833",
        "tgn:1001091",
        "tgn:7029392"
    ],
    "tgn:id":7531451,
    "tgn:name":"Madrasat \u0162aha \u1e28usayn",
    "tgn:placetype":[
        "aat:300006495"
    ]
},
  "bbox": [],
  "geometry": {"coordinates":[31.365337,30.126013],"type":"Point"}
}