{
  "id": 2270599,
  "type": "Feature",
  "properties": {
    "tgn:hierarchy":[
        "tgn:2270599",
        "tgn:1000001",
        "tgn:7012149",
        "tgn:2001709",
        "tgn:7007708",
        "tgn:7029392"
    ],
    "tgn:id":2270599,
    "tgn:name":"Crystal Reservoir",
    "tgn:placetype":[
        "aat:300006191"
    ]
},
  "bbox": [],
  "geometry": {"coordinates":[-119.3333,43.9167],"type":"Point"}
}