{
  "id": 2170303,
  "type": "Feature",
  "properties": {
    "tgn:hierarchy":[
        "tgn:2170303",
        "tgn:1000001",
        "tgn:7012149",
        "tgn:2001866",
        "tgn:7007825",
        "tgn:7029392"
    ],
    "tgn:id":2170303,
    "tgn:name":"Big Ridge",
    "tgn:placetype":[
        "aat:300266640"
    ]
},
  "bbox": [],
  "geometry": {"coordinates":[-82.9667,36.1833],"type":"Point"}
}