{
  "id": 2671132,
  "type": "Feature",
  "properties": {
    "tgn:hierarchy":[
        "tgn:2671132",
        "tgn:1000001",
        "tgn:7012149",
        "tgn:2002066",
        "tgn:7007826",
        "tgn:7029392"
    ],
    "tgn:id":2671132,
    "tgn:name":"Smith Creek",
    "tgn:placetype":[
        "aat:300008706"
    ]
},
  "bbox": [],
  "geometry": {"coordinates":[-93.9667,31.3667],"type":"Point"}
}