{
  "id": 2072105,
  "type": "Feature",
  "properties": {
    "tgn:hierarchy":[
        "tgn:2072105",
        "tgn:1000001",
        "tgn:7012149",
        "tgn:7013941",
        "tgn:7007568",
        "tgn:7029392"
    ],
    "tgn:id":2072105,
    "tgn:name":"Saint Regis Falls",
    "tgn:placetype":[
        "aat:300008347"
    ]
},
  "bbox": [],
  "geometry": {"coordinates":[-74.5333,44.6667],"type":"Point"}
}