{
  "id": 2222928,
  "type": "Feature",
  "properties": {
    "tgn:hierarchy":[
        "tgn:2222928",
        "tgn:1000001",
        "tgn:2000267",
        "tgn:7012149",
        "tgn:7007240",
        "tgn:7029392"
    ],
    "tgn:id":2222928,
    "tgn:name":"Carrin Bayou",
    "tgn:placetype":[
        "aat:300132316"
    ]
},
  "bbox": [],
  "geometry": {"coordinates":[-84.85,29.7833],"type":"Point"}
}