{
  "id": 1062079,
  "type": "Feature",
  "properties": {
    "tgn:hierarchy":[
        "tgn:1062079",
        "tgn:7002758",
        "tgn:1001316",
        "tgn:1000003",
        "tgn:1000095",
        "tgn:7029392"
    ],
    "tgn:id":1062079,
    "tgn:name":"Huelma",
    "tgn:placetype":[
        "aat:300008347"
    ]
},
  "bbox": [],
  "geometry": {"coordinates":[-3.45,37.65],"type":"Point"}
}