{
  "id": 7449551,
  "type": "Feature",
  "properties": {
    "tgn:hierarchy":[
        "tgn:7449551",
        "tgn:7002444",
        "tgn:1000003",
        "tgn:7029508",
        "tgn:7008591",
        "tgn:7029392"
    ],
    "tgn:id":7449551,
    "tgn:name:en":"Ham Voe",
    "tgn:placetype":[
        "aat:300132316"
    ]
},
  "bbox": [],
  "geometry": {"coordinates":[-2.05,60.133333],"type":"Point"}
}