{
  "id": 2513319,
  "type": "Feature",
  "properties": {
    "tgn:hierarchy":[
        "tgn:2513319",
        "tgn:1000001",
        "tgn:7012149",
        "tgn:2001288",
        "tgn:7007524",
        "tgn:7029392"
    ],
    "tgn:id":2513319,
    "tgn:name":"Mill Gulch Spring",
    "tgn:placetype":[
        "aat:300008697"
    ]
},
  "bbox": [],
  "geometry": {"coordinates":[-111.95,45.4167],"type":"Point"}
}