{
  "id": 7255179,
  "type": "Feature",
  "properties": {
    "tgn:hierarchy":[
        "tgn:7255179",
        "tgn:7007877",
        "tgn:1000003",
        "tgn:1000063",
        "tgn:4012014",
        "tgn:7029392"
    ],
    "tgn:id":7255179,
    "tgn:name":"Robertsart",
    "tgn:placetype":[
        "aat:300008347"
    ]
},
  "bbox": [],
  "geometry": {"coordinates":[3.703995,50.553687],"type":"Point"}
}