{
  "id": 7439061,
  "type": "Feature",
  "properties": {
    "tgn:hierarchy":[
        "tgn:7439061",
        "tgn:1000001",
        "tgn:1001893",
        "tgn:7005560",
        "tgn:7029392"
    ],
    "tgn:id":7439061,
    "tgn:name":"Texcalyacac",
    "tgn:placetype":[
        "aat:300008347"
    ]
},
  "bbox": [],
  "geometry": {"coordinates":[-99.466667,19.166667],"type":"Point"}
}