{
  "id": 1097082,
  "type": "Feature",
  "properties": {
    "tgn:hierarchy":[
        "tgn:1097082",
        "tgn:7000490",
        "tgn:1000006",
        "tgn:7001830",
        "tgn:7029392"
    ],
    "tgn:id":1097082,
    "tgn:name":"Harrisville",
    "tgn:placetype":[
        "aat:300008347"
    ]
},
  "bbox": [],
  "geometry": {"coordinates":[152.6667,-27.8167],"type":"Point"}
}