{
  "id": 2489161,
  "type": "Feature",
  "properties": {
    "tgn:hierarchy":[
        "tgn:2489161",
        "tgn:1002648",
        "tgn:1000001",
        "tgn:7019158",
        "tgn:7012149",
        "tgn:7007249",
        "tgn:7029392"
    ],
    "tgn:id":2489161,
    "tgn:name":"Makaaikuloa Point",
    "tgn:placetype":[
        "aat:300008850"
    ]
},
  "bbox": [],
  "geometry": {"coordinates":[-156.0333,20.65],"type":"Point"}
}