{
  "id": 7004049,
  "type": "Feature",
  "properties": {
    "tgn:hierarchy":[
        "tgn:7004049",
        "tgn:1000359",
        "tgn:1000003",
        "tgn:1000091",
        "tgn:7029392"
    ],
    "tgn:id":7004049,
    "tgn:name":"Comana",
    "tgn:placetype":[
        "aat:300008347"
    ]
},
  "bbox": [],
  "geometry": {"coordinates":[26.1667,44.1667],"type":"Point"}
}