{
  "id": 7330615,
  "type": "Feature",
  "properties": {
    "tgn:hierarchy":[
        "tgn:7330615",
        "tgn:7002758",
        "tgn:7002821",
        "tgn:1000003",
        "tgn:1000095",
        "tgn:7029392"
    ],
    "tgn:id":7330615,
    "tgn:name":"Guillimona, Sierra de",
    "tgn:placetype":[
        "aat:300266640"
    ]
},
  "bbox": [],
  "geometry": {"coordinates":[-2.516667,38.033333],"type":"Point"}
}