{
  "id": 7105531,
  "type": "Feature",
  "properties": {
    "tgn:hierarchy":[
        "tgn:7105531",
        "tgn:7003669",
        "tgn:1000003",
        "tgn:7000084",
        "tgn:7029392"
    ],
    "tgn:id":7105531,
    "tgn:name":"Schiefer\u00f6d",
    "tgn:placetype":[
        "aat:300000206"
    ]
},
  "bbox": [],
  "geometry": {"coordinates":[13.35,48.366667],"type":"Point"}
}