{
  "id": 7270498,
  "type": "Feature",
  "properties": {
    "tgn:hierarchy":[
        "tgn:7270498",
        "tgn:1000003",
        "tgn:7006951",
        "tgn:7016845",
        "tgn:7029392"
    ],
    "tgn:id":7270498,
    "tgn:name:nl":"Oude Vlie",
    "tgn:placetype":[
        "aat:300387026"
    ]
},
  "bbox": [],
  "geometry": {"coordinates":[5.166667,53.133333],"type":"Point"}
}