<<<<<<< HEAD
{
  "id": 7114390,
  "type": "Feature",
  "properties": {
    "tgn:hierarchy":[
        "tgn:7114390",
        "tgn:7003692",
        "tgn:1000003",
        "tgn:7000084",
        "tgn:7029392"
    ],
    "tgn:id":7114390,
    "tgn:name":"Riedersberg",
    "tgn:placetype":[
        "aat:300008795"
    ]
},
  "bbox": [],
  "geometry": {"coordinates":[9.1,48.283333],"type":"Point"}
}
=======
{"geometry":{"type":"Point","coordinates":[9.100000,48.283333]},"type":"Feature","properties":{"hierarchy":["tgn:7114390","tgn:7003692","tgn:1000003","tgn:7000084","tgn:7029392"],"placetype":["aat:300008795"],"id":7114390,"name:xx":"Riedersberg"}}
>>>>>>> 03f74aca74312dbeaf24d7e61306dd6a786dc3d0
