{
  "id": 1106600,
  "type": "Feature",
  "properties": {
    "tgn:hierarchy":[
        "tgn:1106600",
        "tgn:7001242",
        "tgn:7001311",
        "tgn:7016833",
        "tgn:7029392"
    ],
    "tgn:id":1106600,
    "tgn:name":"Sadd an Na'\u0101m, Jabal",
    "tgn:placetype":[
        "aat:300008795"
    ]
},
  "bbox": [],
  "geometry": {"coordinates":[31.737659,29.799591],"type":"Point"}
}