{
  "id": 7180883,
  "type": "Feature",
  "properties": {
    "tgn:hierarchy":[
        "tgn:7180883",
        "tgn:7003669",
        "tgn:1000003",
        "tgn:7000084",
        "tgn:7029392"
    ],
    "tgn:id":7180883,
    "tgn:name":"Fr\u00fchling",
    "tgn:placetype":[
        "aat:300008347"
    ]
},
  "bbox": [],
  "geometry": {"coordinates":[12.516667,48.016667],"type":"Point"}
}