{
  "id": 7590491,
  "type": "Feature",
  "properties": {
    "tgn:hierarchy":[
        "tgn:7590491",
        "tgn:1000004",
        "tgn:7000198",
        "tgn:7016722",
        "tgn:7029392"
    ],
    "tgn:id":7590491,
    "tgn:name:en":"M\u0101zra Bhanera",
    "tgn:placetype":[
        "aat:300008347"
    ]
},
  "bbox": [],
  "geometry": {"coordinates":[77.37512,29.628527],"type":"Point"}
}