{
  "id": 7385381,
  "type": "Feature",
  "properties": {
    "tgn:hierarchy":[
        "tgn:7385381",
        "tgn:7005581",
        "tgn:1000001",
        "tgn:7005560",
        "tgn:7029392"
    ],
    "tgn:id":7385381,
    "tgn:name":"Rancho Ojo del Alamo",
    "tgn:placetype":[
        "aat:300000241"
    ]
},
  "bbox": [],
  "geometry": {"coordinates":[-106.466667,30.766667],"type":"Point"}
}