{
  "id": 2176507,
  "type": "Feature",
  "properties": {
    "tgn:hierarchy":[
        "tgn:2176507",
        "tgn:1000001",
        "tgn:7012149",
        "tgn:1002557",
        "tgn:7007252",
        "tgn:7029392"
    ],
    "tgn:id":2176507,
    "tgn:name":"Black Lake",
    "tgn:placetype":[
        "aat:300008680"
    ]
},
  "bbox": [],
  "geometry": {"coordinates":[-85.6667,41.3167],"type":"Point"}
}