{
  "id": 2177299,
  "type": "Feature",
  "properties": {
    "tgn:hierarchy":[
        "tgn:2177299",
        "tgn:1000001",
        "tgn:7012149",
        "tgn:2002113",
        "tgn:7007827",
        "tgn:7029392"
    ],
    "tgn:id":2177299,
    "tgn:name":"Black Ridge",
    "tgn:placetype":[
        "aat:300266640"
    ]
},
  "bbox": [],
  "geometry": {"coordinates":[-111.25,37.4667],"type":"Point"}
}