<<<<<<< HEAD
{
  "id": 7026690,
  "type": "Feature",
  "properties": {
    "tgn:hierarchy":[
        "tgn:7026690",
        "tgn:7002445",
        "tgn:1000003",
        "tgn:7008132",
        "tgn:7008591",
        "tgn:7029392"
    ],
    "tgn:id":7026690,
    "tgn:name:en":"Miserden",
    "tgn:placetype":[
        "aat:300008347",
        "aat:300008372"
    ]
},
  "bbox": [],
  "geometry": {"coordinates":[-2.1,51.783333],"type":"Point"}
}
=======
{"geometry":{"type":"Point","coordinates":[-2.100000,51.783333]},"type":"Feature","properties":{"hierarchy":["tgn:7026690","tgn:7002445","tgn:1000003","tgn:7008132","tgn:7008591","tgn:7029392"],"placetype":["aat:300008347","aat:300008372"],"name:en":"Miserden","id":7026690}}
>>>>>>> 03f74aca74312dbeaf24d7e61306dd6a786dc3d0
