<<<<<<< HEAD
{
  "id": 2700066,
  "type": "Feature",
  "properties": {
    "tgn:hierarchy":[
        "tgn:2700066",
        "tgn:1000001",
        "tgn:7012149",
        "tgn:1002701",
        "tgn:7007706",
        "tgn:7029392"
    ],
    "tgn:id":2700066,
    "tgn:name":"Stump Run",
    "tgn:placetype":[
        "aat:300008699"
    ]
},
  "bbox": [],
  "geometry": {"coordinates":[-82.1,40.1],"type":"Point"}
}
=======
{"geometry":{"type":"Point","coordinates":[-82.100000,40.100000]},"type":"Feature","properties":{"hierarchy":["tgn:2700066","tgn:1000001","tgn:7012149","tgn:1002701","tgn:7007706","tgn:7029392"],"placetype":["aat:300008699"],"id":2700066,"name:xx":"Stump Run"}}
>>>>>>> 03f74aca74312dbeaf24d7e61306dd6a786dc3d0
