{
  "id": 7190481,
  "type": "Feature",
  "properties": {
    "tgn:hierarchy":[
        "tgn:7190481",
        "tgn:1000003",
        "tgn:7003677",
        "tgn:7000084",
        "tgn:7029392"
    ],
    "tgn:id":7190481,
    "tgn:name":"Erprath",
    "tgn:placetype":[
        "aat:300000206"
    ]
},
  "bbox": [],
  "geometry": {"coordinates":[6.683333,51.15],"type":"Point"}
}