{
  "id": 7272940,
  "type": "Feature",
  "properties": {
    "tgn:hierarchy":[
        "tgn:7272940",
        "tgn:7003616",
        "tgn:1000003",
        "tgn:7016845",
        "tgn:7029392"
    ],
    "tgn:id":7272940,
    "tgn:name:nl":"Ursulapolder",
    "tgn:placetype":[
        "aat:300006163"
    ]
},
  "bbox": [],
  "geometry": {"coordinates":[5.466667,52.966667],"type":"Point"}
}