{
  "id": 7453629,
  "type": "Feature",
  "properties": {
    "tgn:hierarchy":[
        "tgn:7453629",
        "tgn:7002445",
        "tgn:1000003",
        "tgn:7008165",
        "tgn:7008591",
        "tgn:7029392"
    ],
    "tgn:id":7453629,
    "tgn:name:en":"Dicky Shad",
    "tgn:placetype":[
        "aat:300008808"
    ]
},
  "bbox": [],
  "geometry": {"coordinates":[-1.566667,55.566667],"type":"Point"}
}