{
  "id": 7564377,
  "type": "Feature",
  "properties": {
    "tgn:hierarchy":[
        "tgn:7564377",
        "tgn:1000004",
        "tgn:7000198",
        "tgn:1001894",
        "tgn:7029392"
    ],
    "tgn:id":7564377,
    "tgn:name:en":"Barduw\u0101ha",
    "tgn:placetype":[
        "aat:300008347"
    ]
},
  "bbox": [],
  "geometry": {"coordinates":[79.379606,24.771927],"type":"Point"}
}