{
  "id": 2293631,
  "type": "Feature",
  "properties": {
    "tgn:hierarchy":[
        "tgn:2293631",
        "tgn:1000001",
        "tgn:7012149",
        "tgn:2001711",
        "tgn:7007708",
        "tgn:7029392"
    ],
    "tgn:id":2293631,
    "tgn:name":"Doubleday Creek",
    "tgn:placetype":[
        "aat:300008706"
    ]
},
  "bbox": [],
  "geometry": {"coordinates":[-122.5333,42.4833],"type":"Point"}
}