{
  "id": 7416446,
  "type": "Feature",
  "properties": {
    "tgn:hierarchy":[
        "tgn:7416446",
        "tgn:1000001",
        "tgn:7005591",
        "tgn:7005560",
        "tgn:7029392"
    ],
    "tgn:id":7416446,
    "tgn:name:es":"Valdeflores, R\u00edo",
    "tgn:placetype":[
        "aat:300008699"
    ]
},
  "bbox": [],
  "geometry": {"coordinates":[-96.882222,15.750833],"type":"Point"}
}