{
  "id": 2495767,
  "type": "Feature",
  "properties": {
    "tgn:hierarchy":[
        "tgn:2495767",
        "tgn:1000001",
        "tgn:2000576",
        "tgn:7012149",
        "tgn:7007253",
        "tgn:7029392"
    ],
    "tgn:id":2495767,
    "tgn:name":"Mason Creek",
    "tgn:placetype":[
        "aat:300008706"
    ]
},
  "bbox": [],
  "geometry": {"coordinates":[-91.2667,41.85],"type":"Point"}
}