{
  "id": 7564773,
  "type": "Feature",
  "properties": {
    "tgn:hierarchy":[
        "tgn:7564773",
        "tgn:1000004",
        "tgn:7000198",
        "tgn:7016722",
        "tgn:7029392"
    ],
    "tgn:id":7564773,
    "tgn:name:en":"Gor\u0101bh\u016bpka",
    "tgn:placetype":[
        "aat:300008347"
    ]
},
  "bbox": [],
  "geometry": {"coordinates":[79.316611,26.26865],"type":"Point"}
}