{
  "id": 7005394,
  "type": "Feature",
  "properties": {
    "tgn:hierarchy":[
        "tgn:7005394",
        "tgn:1000001",
        "tgn:7005388",
        "tgn:7029392"
    ],
    "tgn:id":7005394,
    "tgn:name":"Duarte",
    "tgn:placetype":[
        "aat:300387064",
        "aat:300000774"
    ]
},
  "bbox": [],
  "geometry": {"coordinates":[-70.0833,19.25],"type":"Point"}
}