{
  "id": 7300329,
  "type": "Feature",
  "properties": {
    "tgn:hierarchy":[
        "tgn:7300329",
        "tgn:7002818",
        "tgn:1001647",
        "tgn:1000003",
        "tgn:1000095",
        "tgn:7029392"
    ],
    "tgn:id":7300329,
    "tgn:name":"Valdeganga de Cuenca",
    "tgn:placetype":[
        "aat:300008347"
    ]
},
  "bbox": [],
  "geometry": {"coordinates":[-2.183333,39.933333],"type":"Point"}
}