{
  "id": 7367511,
  "type": "Feature",
  "properties": {
    "tgn:hierarchy":[
        "tgn:7367511",
        "tgn:1000001",
        "tgn:7005589",
        "tgn:7005560",
        "tgn:7029392"
    ],
    "tgn:id":7367511,
    "tgn:name:es":"El Porvenir",
    "tgn:placetype":[
        "aat:300008347"
    ]
},
  "bbox": [],
  "geometry": {"coordinates":[-98.747222,25.96],"type":"Point"}
}