{
  "id": 2737393,
  "type": "Feature",
  "properties": {
    "tgn:hierarchy":[
        "tgn:2737393",
        "tgn:1000001",
        "tgn:7012149",
        "tgn:2002055",
        "tgn:7007826",
        "tgn:7029392"
    ],
    "tgn:id":2737393,
    "tgn:name":"Twomile Draw",
    "tgn:placetype":[
        "aat:300008761"
    ]
},
  "bbox": [],
  "geometry": {"coordinates":[-101.85,30.7167],"type":"Point"}
}