{
  "id": 7260426,
  "type": "Feature",
  "properties": {
    "tgn:hierarchy":[
        "tgn:7260426",
        "tgn:1000003",
        "tgn:7003626",
        "tgn:7016845",
        "tgn:7029392"
    ],
    "tgn:id":7260426,
    "tgn:name:nl":"Gravenbos",
    "tgn:placetype":[
        "aat:300008863"
    ]
},
  "bbox": [],
  "geometry": {"coordinates":[6.816667,52.316667],"type":"Point"}
}