{
  "id": 7214471,
  "type": "Feature",
  "properties": {
    "tgn:hierarchy":[
        "tgn:7214471",
        "tgn:7003692",
        "tgn:1000003",
        "tgn:7000084",
        "tgn:7029392"
    ],
    "tgn:id":7214471,
    "tgn:name":"Beurenbach",
    "tgn:placetype":[
        "aat:300008699"
    ]
},
  "bbox": [],
  "geometry": {"coordinates":[8.983333,48.416667],"type":"Point"}
}