{
  "id": 1038858,
  "type": "Feature",
  "properties": {
    "tgn:hierarchy":[
        "tgn:1038858",
        "tgn:1000003",
        "tgn:7003677",
        "tgn:7000084",
        "tgn:7029392"
    ],
    "tgn:id":1038858,
    "tgn:name":"Dr\u00f6schede",
    "tgn:placetype":[
        "aat:300008347"
    ]
},
  "bbox": [],
  "geometry": {"coordinates":[7.65,51.366667],"type":"Point"}
}