<<<<<<< HEAD
{
  "id": 2157407,
  "type": "Feature",
  "properties": {
    "tgn:hierarchy":[
        "tgn:2157407",
        "tgn:1000001",
        "tgn:7012149",
        "tgn:2001686",
        "tgn:7007707",
        "tgn:7029392"
    ],
    "tgn:id":2157407,
    "tgn:name":"Beaver Creek",
    "tgn:placetype":[
        "aat:300008706"
    ]
},
  "bbox": [],
  "geometry": {"coordinates":[-95.7167,34.2],"type":"Point"}
}
=======
{"geometry":{"type":"Point","coordinates":[-95.716700,34.200000]},"type":"Feature","properties":{"hierarchy":["tgn:2157407","tgn:1000001","tgn:7012149","tgn:2001686","tgn:7007707","tgn:7029392"],"placetype":["aat:300008706"],"id":2157407,"name:xx":"Beaver Creek"}}
>>>>>>> 03f74aca74312dbeaf24d7e61306dd6a786dc3d0
