{
  "id": 2493675,
  "type": "Feature",
  "properties": {
    "tgn:hierarchy":[
        "tgn:2493675",
        "tgn:1002996",
        "tgn:1000001",
        "tgn:7012149",
        "tgn:7007711",
        "tgn:7029392"
    ],
    "tgn:id":2493675,
    "tgn:name":"Marsh Point",
    "tgn:placetype":[
        "aat:300008850"
    ]
},
  "bbox": [],
  "geometry": {"coordinates":[-71.6333,41.3667],"type":"Point"}
}