{
  "id": 7282833,
  "type": "Feature",
  "properties": {
    "tgn:hierarchy":[
        "tgn:7282833",
        "tgn:1001702",
        "tgn:1000049",
        "tgn:1000002",
        "tgn:7029392"
    ],
    "tgn:id":7282833,
    "tgn:name":"Peligrosa, Punta",
    "tgn:placetype":[
        "aat:300386846"
    ]
},
  "bbox": [],
  "geometry": {"coordinates":[-75.433333,-49.45],"type":"Point"}
}