{
  "id": 7347947,
  "type": "Feature",
  "properties": {
    "tgn:hierarchy":[
        "tgn:7347947",
        "tgn:7001165",
        "tgn:1000003",
        "tgn:7002793",
        "tgn:1000095",
        "tgn:7029392"
    ],
    "tgn:id":7347947,
    "tgn:name":"Albalat dels Sorells",
    "tgn:placetype":[
        "aat:300008347"
    ]
},
  "bbox": [],
  "geometry": {"coordinates":[-0.35,39.533333],"type":"Point"}
}