{
  "id": 7419449,
  "type": "Feature",
  "properties": {
    "tgn:hierarchy":[
        "tgn:7419449",
        "tgn:1001836",
        "tgn:1000001",
        "tgn:7005560",
        "tgn:7029392"
    ],
    "tgn:id":7419449,
    "tgn:name":"Las Parritas",
    "tgn:placetype":[
        "aat:300008347"
    ]
},
  "bbox": [],
  "geometry": {"coordinates":[-109.796667,23.095],"type":"Point"}
}