{
  "id": 2187094,
  "type": "Feature",
  "properties": {
    "tgn:hierarchy":[
        "tgn:2187094",
        "tgn:1000001",
        "tgn:7012149",
        "tgn:2001257",
        "tgn:7007523",
        "tgn:7029392"
    ],
    "tgn:id":2187094,
    "tgn:name":"Bonnies Lake",
    "tgn:placetype":[
        "aat:300006191"
    ]
},
  "bbox": [],
  "geometry": {"coordinates":[-94.5833,40.5167],"type":"Point"}
}