{
  "id": 2378191,
  "type": "Feature",
  "properties": {
    "tgn:hierarchy":[
        "tgn:2378191",
        "tgn:1000001",
        "tgn:1002182",
        "tgn:7012149",
        "tgn:7007520",
        "tgn:7029392"
    ],
    "tgn:id":2378191,
    "tgn:name":"Harris Lake",
    "tgn:placetype":[
        "aat:300008680"
    ]
},
  "bbox": [],
  "geometry": {"coordinates":[-86.35,42.2167],"type":"Point"}
}