{
  "id": 2206809,
  "type": "Feature",
  "properties": {
    "tgn:hierarchy":[
        "tgn:2206809",
        "tgn:1000001",
        "tgn:2001649",
        "tgn:7012149",
        "tgn:7007707",
        "tgn:7029392"
    ],
    "tgn:id":2206809,
    "tgn:name":"Bullwacker Creek",
    "tgn:placetype":[
        "aat:300008706"
    ]
},
  "bbox": [],
  "geometry": {"coordinates":[-97.6833,36.8833],"type":"Point"}
}