{
  "id": 2153427,
  "type": "Feature",
  "properties": {
    "tgn:hierarchy":[
        "tgn:2153427",
        "tgn:1000001",
        "tgn:7012149",
        "tgn:2000930",
        "tgn:7007515",
        "tgn:7029392"
    ],
    "tgn:id":2153427,
    "tgn:name":"Bean Pond",
    "tgn:placetype":[
        "aat:300008680"
    ]
},
  "bbox": [],
  "geometry": {"coordinates":[-69.9667,45.1167],"type":"Point"}
}