{
  "id": 2706646,
  "type": "Feature",
  "properties": {
    "tgn:hierarchy":[
        "tgn:2706646",
        "tgn:1000001",
        "tgn:7012149",
        "tgn:1002999",
        "tgn:7007526",
        "tgn:7029392"
    ],
    "tgn:id":2706646,
    "tgn:name":"Swan Lake Reservoir",
    "tgn:placetype":[
        "aat:300006191"
    ]
},
  "bbox": [],
  "geometry": {"coordinates":[-119.4833,41.85],"type":"Point"}
}