{
  "id": 1075364,
  "type": "Feature",
  "properties": {
    "tgn:hierarchy":[
        "tgn:1075364",
        "tgn:1000004",
        "tgn:7000198",
        "tgn:1001894",
        "tgn:7029392"
    ],
    "tgn:id":1075364,
    "tgn:name:en":"Gohad",
    "tgn:placetype":[
        "aat:300008347"
    ]
},
  "bbox": [],
  "geometry": {"coordinates":[78.440935,26.424161],"type":"Point"}
}