{
  "id": 7395028,
  "type": "Feature",
  "properties": {
    "tgn:hierarchy":[
        "tgn:7395028",
        "tgn:1000001",
        "tgn:7005601",
        "tgn:7005560",
        "tgn:7029392"
    ],
    "tgn:id":7395028,
    "tgn:name":"Rancho San Jos\u00e9 de la Sierrecilla",
    "tgn:placetype":[
        "aat:300000241"
    ]
},
  "bbox": [],
  "geometry": {"coordinates":[-102.266667,24.216667],"type":"Point"}
}