<<<<<<< HEAD
{
  "id": 7365745,
  "type": "Feature",
  "properties": {
    "tgn:hierarchy":[
        "tgn:7365745",
        "tgn:7005578",
        "tgn:1000001",
        "tgn:7005560",
        "tgn:7029392"
    ],
    "tgn:id":7365745,
    "tgn:name":"El Tasistal",
    "tgn:placetype":[
        "aat:300008347"
    ]
},
  "bbox": [],
  "geometry": {"coordinates":[-91.933333,18.283333],"type":"Point"}
}
=======
{"geometry":{"type":"Point","coordinates":[-91.933333,18.283333]},"type":"Feature","properties":{"hierarchy":["tgn:7365745","tgn:7005578","tgn:1000001","tgn:7005560","tgn:7029392"],"placetype":["aat:300008347"],"id":7365745,"name:xx":"El Tasistal"}}
>>>>>>> 03f74aca74312dbeaf24d7e61306dd6a786dc3d0
