{
  "id": 2419972,
  "type": "Feature",
  "properties": {
    "tgn:hierarchy":[
        "tgn:2419972",
        "tgn:1000001",
        "tgn:7012149",
        "tgn:2000882",
        "tgn:7007256",
        "tgn:7029392"
    ],
    "tgn:id":2419972,
    "tgn:name":"Jean Plaisance Canal",
    "tgn:placetype":[
        "aat:300006075"
    ]
},
  "bbox": [],
  "geometry": {"coordinates":[-90.2667,29.3667],"type":"Point"}
}