{
  "id": 7021296,
  "type": "Feature",
  "properties": {
    "tgn:hierarchy":[
        "tgn:7021296",
        "tgn:1000001",
        "tgn:2002102",
        "tgn:7012149",
        "tgn:7007827",
        "tgn:7029392"
    ],
    "tgn:id":7021296,
    "tgn:name":"Garland Spring",
    "tgn:placetype":[
        "aat:300008697"
    ]
},
  "bbox": [],
  "geometry": {"coordinates":[-112.0667,41.7167],"type":"Point"}
}