{
  "id": 2445131,
  "type": "Feature",
  "properties": {
    "tgn:hierarchy":[
        "tgn:2445131",
        "tgn:1000001",
        "tgn:7012149",
        "tgn:2001866",
        "tgn:7007825",
        "tgn:7029392"
    ],
    "tgn:id":2445131,
    "tgn:name":"Leming Subdivision",
    "tgn:placetype":[
        "aat:300008347"
    ]
},
  "bbox": [],
  "geometry": {"coordinates":[-82.8167,36.1333],"type":"Point"}
}