{
  "id": 7120428,
  "type": "Feature",
  "properties": {
    "tgn:hierarchy":[
        "tgn:7120428",
        "tgn:7003669",
        "tgn:1000003",
        "tgn:7000084",
        "tgn:7029392"
    ],
    "tgn:id":7120428,
    "tgn:name":"Pledl",
    "tgn:placetype":[
        "aat:300008347"
    ]
},
  "bbox": [],
  "geometry": {"coordinates":[13.083333,48.716667],"type":"Point"}
}