<<<<<<< HEAD
{
  "id": 7175680,
  "type": "Feature",
  "properties": {
    "tgn:hierarchy":[
        "tgn:7175680",
        "tgn:1000003",
        "tgn:7003682",
        "tgn:7000084",
        "tgn:7029392"
    ],
    "tgn:id":7175680,
    "tgn:name":"Gro\u00dfes Kessel-Tal",
    "tgn:placetype":[
        "aat:300008761"
    ]
},
  "bbox": [],
  "geometry": {"coordinates":[7.9,49.05],"type":"Point"}
}
=======
{"geometry":{"type":"Point","coordinates":[7.900000,49.050000]},"type":"Feature","properties":{"hierarchy":["tgn:7175680","tgn:1000003","tgn:7003682","tgn:7000084","tgn:7029392"],"placetype":["aat:300008761"],"id":7175680,"name:xx":"Gro\u00dfes Kessel-Tal"}}
>>>>>>> 03f74aca74312dbeaf24d7e61306dd6a786dc3d0
