{
  "id": 7276886,
  "type": "Feature",
  "properties": {
    "tgn:hierarchy":[
        "tgn:7276886",
        "tgn:1001768",
        "tgn:1000049",
        "tgn:1000002",
        "tgn:7029392"
    ],
    "tgn:id":7276886,
    "tgn:name":"Yugo, Quebrada del",
    "tgn:placetype":[
        "aat:300008699"
    ]
},
  "bbox": [],
  "geometry": {"coordinates":[-71.666667,-33.333333],"type":"Point"}
}