{
  "id": 7019661,
  "type": "Feature",
  "properties": {
    "tgn:hierarchy":[
        "tgn:7019661",
        "tgn:7006450",
        "tgn:1000001",
        "tgn:7012149",
        "tgn:2000086",
        "tgn:7029392"
    ],
    "tgn:id":7019661,
    "tgn:name":"Valdez",
    "tgn:placetype":[
        "aat:300008347",
        "aat:300008375"
    ]
},
  "bbox": [],
  "geometry": {"coordinates":[-146.3333,61.1167],"type":"Point"}
}