{
  "id": 7509543,
  "type": "Feature",
  "properties": {
    "tgn:hierarchy":[
        "tgn:7509543",
        "tgn:1009227",
        "tgn:1000226",
        "tgn:7016822",
        "tgn:1000006",
        "tgn:7029392"
    ],
    "tgn:id":7509543,
    "tgn:name:en":"Waikato",
    "tgn:placetype":[
        "aat:300008699"
    ]
},
  "bbox": [],
  "geometry": {"coordinates":[-176.516667,-43.833333],"type":"Point"}
}