{
  "id": 7020957,
  "type": "Feature",
  "properties": {
    "tgn:hierarchy":[
        "tgn:7020957",
        "tgn:1000001",
        "tgn:7012149",
        "tgn:2000485",
        "tgn:7007250",
        "tgn:7029392"
    ],
    "tgn:id":7020957,
    "tgn:name":"Brokie Lake",
    "tgn:placetype":[
        "aat:300008680"
    ]
},
  "bbox": [],
  "geometry": {"coordinates":[-113.6833,43.0833],"type":"Point"}
}