{
  "id": 1116049,
  "type": "Feature",
  "properties": {
    "tgn:hierarchy":[
        "tgn:1116049",
        "tgn:7005685",
        "tgn:1000001",
        "tgn:7024197",
        "tgn:7029392"
    ],
    "tgn:id":1116049,
    "tgn:name":"Curtis Lake",
    "tgn:placetype":[
        "aat:300008680"
    ]
},
  "bbox": [],
  "geometry": {"coordinates":[-89.0333,66.6333],"type":"Point"}
}