{
  "id": 7348201,
  "type": "Feature",
  "properties": {
    "tgn:hierarchy":[
        "tgn:7348201",
        "tgn:7002836",
        "tgn:7016622",
        "tgn:1000003",
        "tgn:1000095",
        "tgn:7029392"
    ],
    "tgn:id":7348201,
    "tgn:name":"Agulo",
    "tgn:placetype":[
        "aat:300008347"
    ]
},
  "bbox": [],
  "geometry": {"coordinates":[-17.183333,28.183333],"type":"Point"}
}