{
  "id": 2716932,
  "type": "Feature",
  "properties": {
    "tgn:hierarchy":[
        "tgn:2716932",
        "tgn:1000001",
        "tgn:7012149",
        "tgn:2001520",
        "tgn:7007709",
        "tgn:7029392"
    ],
    "tgn:id":2716932,
    "tgn:name":"Thickety Creek",
    "tgn:placetype":[
        "aat:300008706"
    ]
},
  "bbox": [],
  "geometry": {"coordinates":[-79.8167,35.25],"type":"Point"}
}