{
  "id": 7219872,
  "type": "Feature",
  "properties": {
    "tgn:hierarchy":[
        "tgn:7219872",
        "tgn:7011330",
        "tgn:7002674",
        "tgn:1000003",
        "tgn:1000074",
        "tgn:7029392"
    ],
    "tgn:id":7219872,
    "tgn:name":"Ko\u00fakkos",
    "tgn:placetype":[
        "aat:300266640"
    ]
},
  "bbox": [],
  "geometry": {"coordinates":[27.124444,36.776389],"type":"Point"}
}