{
  "id": 7233426,
  "type": "Feature",
  "properties": {
    "tgn:hierarchy":[
        "tgn:7233426",
        "tgn:7002690",
        "tgn:7012056",
        "tgn:1000003",
        "tgn:1000074",
        "tgn:7029392"
    ],
    "tgn:id":7233426,
    "tgn:name":"Ay\u00eda Tri\u00e1s",
    "tgn:placetype":[
        "aat:300008347"
    ]
},
  "bbox": [],
  "geometry": {"coordinates":[24.566667,35.35],"type":"Point"}
}