{
  "id": 7558270,
  "type": "Feature",
  "properties": {
    "tgn:hierarchy":[
        "tgn:7558270",
        "tgn:1000004",
        "tgn:7000198",
        "tgn:1001905",
        "tgn:7029392"
    ],
    "tgn:id":7558270,
    "tgn:name:en":"Pasompui",
    "tgn:placetype":[
        "aat:300008347"
    ]
},
  "bbox": [],
  "geometry": {"coordinates":[93.549342,25.513797],"type":"Point"}
}