{
  "id": 2194692,
  "type": "Feature",
  "properties": {
    "tgn:hierarchy":[
        "tgn:2194692",
        "tgn:1000001",
        "tgn:7012149",
        "tgn:2001683",
        "tgn:7007707",
        "tgn:7029392"
    ],
    "tgn:id":2194692,
    "tgn:name":"Brier Creek",
    "tgn:placetype":[
        "aat:300008706"
    ]
},
  "bbox": [],
  "geometry": {"coordinates":[-95.7167,34.8167],"type":"Point"}
}