{
  "id": 2436656,
  "type": "Feature",
  "properties": {
    "tgn:hierarchy":[
        "tgn:2436656",
        "tgn:1000001",
        "tgn:7012149",
        "tgn:2001233",
        "tgn:7007523",
        "tgn:7029392"
    ],
    "tgn:id":2436656,
    "tgn:name":"Kieseweltter Resort",
    "tgn:placetype":[
        "aat:300008347"
    ]
},
  "bbox": [],
  "geometry": {"coordinates":[-92.3333,37.8167],"type":"Point"}
}