{
  "id": 7279352,
  "type": "Feature",
  "properties": {
    "tgn:hierarchy":[
        "tgn:7279352",
        "tgn:1001623",
        "tgn:1000049",
        "tgn:1000002",
        "tgn:7029392"
    ],
    "tgn:id":7279352,
    "tgn:name":"Robinet, Roca",
    "tgn:placetype":[
        "aat:300011692"
    ]
},
  "bbox": [],
  "geometry": {"coordinates":[-72.945278,-44.33],"type":"Point"}
}