{
  "id": 2049789,
  "type": "Feature",
  "properties": {
    "tgn:hierarchy":[
        "tgn:2049789",
        "tgn:1000001",
        "tgn:7013942",
        "tgn:7012149",
        "tgn:7007517",
        "tgn:7029392"
    ],
    "tgn:id":2049789,
    "tgn:name":"Foundry Village",
    "tgn:placetype":[
        "aat:300008347"
    ]
},
  "bbox": [],
  "geometry": {"coordinates":[-72.7167,42.6667],"type":"Point"}
}