{
  "id": 7491090,
  "type": "Feature",
  "properties": {
    "tgn:hierarchy":[
        "tgn:7491090",
        "tgn:7487020",
        "tgn:1000004",
        "tgn:1000141",
        "tgn:7029392"
    ],
    "tgn:id":7491090,
    "tgn:name":"Sanrong Shan",
    "tgn:placetype":[
        "aat:300008798"
    ]
},
  "bbox": [],
  "geometry": {"coordinates":[121.179722,24.457222],"type":"Point"}
}