{
  "id": 2012257,
  "type": "Feature",
  "properties": {
    "tgn:hierarchy":[
        "tgn:2012257",
        "tgn:1000001",
        "tgn:7012149",
        "tgn:1002409",
        "tgn:7007157",
        "tgn:7029392"
    ],
    "tgn:id":2012257,
    "tgn:name":"Logandale",
    "tgn:placetype":[
        "aat:300387016"
    ]
},
  "bbox": [],
  "geometry": {"coordinates":[-122.1833,39.4333],"type":"Point"}
}