{
  "id": 7226313,
  "type": "Feature",
  "properties": {
    "tgn:hierarchy":[
        "tgn:7226313",
        "tgn:7011161",
        "tgn:7002674",
        "tgn:1000003",
        "tgn:1000074",
        "tgn:7029392"
    ],
    "tgn:id":7226313,
    "tgn:name":"Pag\u00eds",
    "tgn:placetype":[
        "aat:300008347"
    ]
},
  "bbox": [],
  "geometry": {"coordinates":[26.0775,38.259167],"type":"Point"}
}