<<<<<<< HEAD
{
  "id": 2409427,
  "type": "Feature",
  "properties": {
    "tgn:hierarchy":[
        "tgn:2409427",
        "tgn:1000001",
        "tgn:7012149",
        "tgn:7007157",
        "tgn:1002710",
        "tgn:7029392"
    ],
    "tgn:id":2409427,
    "tgn:name":"Idaho-Maryland Reservoir",
    "tgn:placetype":[
        "aat:300006191"
    ]
},
  "bbox": [],
  "geometry": {"coordinates":[-121.0,39.2167],"type":"Point"}
}
=======
{"geometry":{"type":"Point","coordinates":[-121.000000,39.216700]},"type":"Feature","properties":{"hierarchy":["tgn:2409427","tgn:1000001","tgn:7012149","tgn:7007157","tgn:1002710","tgn:7029392"],"placetype":["aat:300006191"],"id":2409427,"name:xx":"Idaho-Maryland Reservoir"}}
>>>>>>> 03f74aca74312dbeaf24d7e61306dd6a786dc3d0
