{
  "id": 2110238,
  "type": "Feature",
  "properties": {
    "tgn:hierarchy":[
        "tgn:2110238",
        "tgn:1000001",
        "tgn:2002147",
        "tgn:7012149",
        "tgn:7007919",
        "tgn:7029392"
    ],
    "tgn:id":2110238,
    "tgn:name":"Adsit",
    "tgn:placetype":[
        "aat:300008347",
        "aat:300387210"
    ]
},
  "bbox": [],
  "geometry": {"coordinates":[-77.6833,36.8167],"type":"Point"}
}