{
  "id": 7494026,
  "type": "Feature",
  "properties": {
    "tgn:hierarchy":[
        "tgn:7494026",
        "tgn:1000004",
        "tgn:7491221",
        "tgn:1000141",
        "tgn:7029392"
    ],
    "tgn:id":7494026,
    "tgn:name":"Xingangnanxitou",
    "tgn:placetype":[
        "aat:300387035"
    ]
},
  "bbox": [],
  "geometry": {"coordinates":[121.329936,23.118502],"type":"Point"}
}