{
  "id": 2672654,
  "type": "Feature",
  "properties": {
    "tgn:hierarchy":[
        "tgn:2672654",
        "tgn:1000001",
        "tgn:7012149",
        "tgn:7007158",
        "tgn:7029392"
    ],
    "tgn:id":2672654,
    "tgn:name":"Smuin Gulch",
    "tgn:placetype":[
        "aat:300008761"
    ]
},
  "bbox": [],
  "geometry": {"coordinates":[-107.45,40.4167],"type":"Point"}
}