{
  "id": 2000572,
  "type": "Feature",
  "properties": {
    "tgn:hierarchy":[
        "tgn:2000572",
        "tgn:1000001",
        "tgn:7012149",
        "tgn:7007253",
        "tgn:7029392"
    ],
    "tgn:id":2000572,
    "tgn:name":"Butler",
    "tgn:placetype":[
        "aat:300387145",
        "aat:300000771"
    ]
},
  "bbox": [],
  "geometry": {"coordinates":[-92.7833,42.7333],"type":"Point"}
}