{
  "id": 7324807,
  "type": "Feature",
  "properties": {
    "tgn:hierarchy":[
        "tgn:7324807",
        "tgn:7002820",
        "tgn:7030216",
        "tgn:1000003",
        "tgn:1000095",
        "tgn:7029392"
    ],
    "tgn:id":7324807,
    "tgn:name":"San Miguel de Campmajor",
    "tgn:placetype":[
        "aat:300008347"
    ]
},
  "bbox": [],
  "geometry": {"coordinates":[2.679193,42.135688],"type":"Point"}
}