{
  "id": 7325478,
  "type": "Feature",
  "properties": {
    "tgn:hierarchy":[
        "tgn:7325478",
        "tgn:7002759",
        "tgn:7008909",
        "tgn:1000003",
        "tgn:1000095",
        "tgn:7029392"
    ],
    "tgn:id":7325478,
    "tgn:name":"San Mart\u00edn",
    "tgn:placetype":[
        "aat:300008347"
    ]
},
  "bbox": [],
  "geometry": {"coordinates":[0.672551,42.304174],"type":"Point"}
}