{
  "id": 7579120,
  "type": "Feature",
  "properties": {
    "tgn:hierarchy":[
        "tgn:7579120",
        "tgn:1000004",
        "tgn:1001869",
        "tgn:7000198",
        "tgn:7029392"
    ],
    "tgn:id":7579120,
    "tgn:name:en":"Was\u0101i D\u0101bhla",
    "tgn:placetype":[
        "aat:300007783"
    ]
},
  "bbox": [],
  "geometry": {"coordinates":[72.575455,23.53035],"type":"Point"}
}