{
  "id": 2564716,
  "type": "Feature",
  "properties": {
    "tgn:hierarchy":[
        "tgn:2564716",
        "tgn:7030515",
        "tgn:7006450",
        "tgn:1000001",
        "tgn:7012149",
        "tgn:7029392"
    ],
    "tgn:id":2564716,
    "tgn:name":"Pad Island",
    "tgn:placetype":[
        "aat:300008791"
    ]
},
  "bbox": [],
  "geometry": {"coordinates":[-159.6833,55.7333],"type":"Point"}
}