{
  "id": 7422944,
  "type": "Feature",
  "properties": {
    "tgn:hierarchy":[
        "tgn:7422944",
        "tgn:1000001",
        "tgn:1001960",
        "tgn:7005560",
        "tgn:7029392"
    ],
    "tgn:id":7422944,
    "tgn:name":"Encizo",
    "tgn:placetype":[
        "aat:300008347"
    ]
},
  "bbox": [],
  "geometry": {"coordinates":[-113.05,30.65],"type":"Point"}
}