{
  "id": 7023783,
  "type": "Feature",
  "properties": {
    "tgn:hierarchy":[
        "tgn:7023783",
        "tgn:1000001",
        "tgn:7012149",
        "tgn:7007712",
        "tgn:7029392"
    ],
    "tgn:id":7023783,
    "tgn:name":"Trollingwood Lake",
    "tgn:placetype":[
        "aat:300006191"
    ]
},
  "bbox": [],
  "geometry": {"coordinates":[-82.35,34.6667],"type":"Point"}
}