<<<<<<< HEAD
{
  "id": 7023783,
  "type": "Feature",
  "properties": {
    "tgn:hierarchy":[
        "tgn:7023783",
        "tgn:1000001",
        "tgn:7012149",
        "tgn:7007712",
        "tgn:7029392"
    ],
    "tgn:id":7023783,
    "tgn:name":"Trollingwood Lake",
    "tgn:placetype":[
        "aat:300006191"
    ]
},
  "bbox": [],
  "geometry": {"coordinates":[-82.35,34.6667],"type":"Point"}
}
=======
{"geometry":{"type":"Point","coordinates":[-82.350000,34.666700]},"type":"Feature","properties":{"hierarchy":["tgn:7023783","tgn:1000001","tgn:7012149","tgn:7007712","tgn:7029392"],"placetype":["aat:300006191"],"id":7023783,"name:xx":"Trollingwood Lake"}}
>>>>>>> 03f74aca74312dbeaf24d7e61306dd6a786dc3d0
