{
  "id": 7044262,
  "type": "Feature",
  "properties": {
    "tgn:hierarchy":[
        "tgn:7044262",
        "tgn:1003478",
        "tgn:1000003",
        "tgn:7003120",
        "tgn:1000080",
        "tgn:7029392"
    ],
    "tgn:id":7044262,
    "tgn:name":"Cravegna",
    "tgn:placetype":[
        "aat:300008347"
    ]
},
  "bbox": [],
  "geometry": {"coordinates":[8.316667,46.233333],"type":"Point"}
}