{
  "id": 2226783,
  "type": "Feature",
  "properties": {
    "tgn:hierarchy":[
        "tgn:2226783",
        "tgn:1000001",
        "tgn:7012149",
        "tgn:7007157",
        "tgn:1002675",
        "tgn:7029392"
    ],
    "tgn:id":2226783,
    "tgn:name":"Cattle Creek",
    "tgn:placetype":[
        "aat:300008706"
    ]
},
  "bbox": [],
  "geometry": {"coordinates":[-119.3333,38.0833],"type":"Point"}
}