{
  "id": 2569090,
  "type": "Feature",
  "properties": {
    "tgn:hierarchy":[
        "tgn:2569090",
        "tgn:1000001",
        "tgn:2001739",
        "tgn:7012149",
        "tgn:7007712",
        "tgn:7029392"
    ],
    "tgn:id":2569090,
    "tgn:name":"Parkers Bay",
    "tgn:placetype":[
        "aat:300386845"
    ]
},
  "bbox": [],
  "geometry": {"coordinates":[-80.7667,32.9667],"type":"Point"}
}