{
  "id": 2599102,
  "type": "Feature",
  "properties": {
    "tgn:hierarchy":[
        "tgn:2599102",
        "tgn:1000001",
        "tgn:7012149",
        "tgn:2000985",
        "tgn:7007520",
        "tgn:7029392"
    ],
    "tgn:id":2599102,
    "tgn:name":"Prior Lake",
    "tgn:placetype":[
        "aat:300008680"
    ]
},
  "bbox": [],
  "geometry": {"coordinates":[-84.2833,44.25],"type":"Point"}
}