{
  "id": 2651187,
  "type": "Feature",
  "properties": {
    "tgn:hierarchy":[
        "tgn:2651187",
        "tgn:1000001",
        "tgn:7012149",
        "tgn:7007923",
        "tgn:7029392"
    ],
    "tgn:id":2651187,
    "tgn:name":"Secret Valley Creek",
    "tgn:placetype":[
        "aat:300008706"
    ]
},
  "bbox": [],
  "geometry": {"coordinates":[-110.8333,44.6667],"type":"Point"}
}