{
  "id": 2375729,
  "type": "Feature",
  "properties": {
    "tgn:hierarchy":[
        "tgn:2375729",
        "tgn:1000001",
        "tgn:7016172",
        "tgn:7012149",
        "tgn:2000169",
        "tgn:7029392"
    ],
    "tgn:id":2375729,
    "tgn:name":"Happy Hollow",
    "tgn:placetype":[
        "aat:300008761"
    ]
},
  "bbox": [],
  "geometry": {"coordinates":[-92.5333,35.8833],"type":"Point"}
}