{
  "id": 1094795,
  "type": "Feature",
  "properties": {
    "tgn:hierarchy":[
        "tgn:1094795",
        "tgn:7001242",
        "tgn:7016572",
        "tgn:1000203",
        "tgn:7029392"
    ],
    "tgn:id":1094795,
    "tgn:name":"Ngoywa",
    "tgn:placetype":[
        "aat:300008347"
    ]
},
  "bbox": [],
  "geometry": {"coordinates":[32.8167,-5.9167],"type":"Point"}
}