{
  "id": 1103796,
  "type": "Feature",
  "properties": {
    "tgn:hierarchy":[
        "tgn:1103796",
        "tgn:1000003",
        "tgn:7003685",
        "tgn:7000084",
        "tgn:7029392"
    ],
    "tgn:id":1103796,
    "tgn:name":"Auersberg",
    "tgn:placetype":[
        "aat:300008795"
    ]
},
  "bbox": [],
  "geometry": {"coordinates":[12.65,50.45],"type":"Point"}
}