<<<<<<< HEAD
{
  "id": 7053262,
  "type": "Feature",
  "properties": {
    "tgn:hierarchy":[
        "tgn:7053262",
        "tgn:7003005",
        "tgn:7003014",
        "tgn:1000003",
        "tgn:1000080",
        "tgn:7029392"
    ],
    "tgn:id":7053262,
    "tgn:name":"Magliano Vetere",
    "tgn:placetype":[
        "aat:300008347"
    ]
},
  "bbox": [],
  "geometry": {"coordinates":[15.233333,40.35],"type":"Point"}
}
=======
{"geometry":{"type":"Point","coordinates":[15.233333,40.350000]},"type":"Feature","properties":{"hierarchy":["tgn:7053262","tgn:7003005","tgn:7003014","tgn:1000003","tgn:1000080","tgn:7029392"],"placetype":["aat:300008347"],"id":7053262,"name:xx":"Magliano Vetere"}}
>>>>>>> 03f74aca74312dbeaf24d7e61306dd6a786dc3d0
