{
  "id": 7415342,
  "type": "Feature",
  "properties": {
    "tgn:hierarchy":[
        "tgn:7415342",
        "tgn:7005584",
        "tgn:1000001",
        "tgn:7005560",
        "tgn:7029392"
    ],
    "tgn:id":7415342,
    "tgn:name":"Paredes",
    "tgn:placetype":[
        "aat:300008347"
    ]
},
  "bbox": [],
  "geometry": {"coordinates":[-100.093611,21.231111],"type":"Point"}
}