{
  "id": 7306226,
  "type": "Feature",
  "properties": {
    "tgn:hierarchy":[
        "tgn:7306226",
        "tgn:7002810",
        "tgn:7001158",
        "tgn:1000003",
        "tgn:1000095",
        "tgn:7029392"
    ],
    "tgn:id":7306226,
    "tgn:name":"Manaderos, Manantial de",
    "tgn:placetype":[
        "aat:300008697"
    ]
},
  "bbox": [],
  "geometry": {"coordinates":[-3.716667,42.716667],"type":"Point"}
}