<<<<<<< HEAD
{
  "id": 2402346,
  "type": "Feature",
  "properties": {
    "tgn:hierarchy":[
        "tgn:2402346",
        "tgn:1000001",
        "tgn:7012149",
        "tgn:2002066",
        "tgn:7007826",
        "tgn:7029392"
    ],
    "tgn:id":2402346,
    "tgn:name":"Horton Creek",
    "tgn:placetype":[
        "aat:300008706"
    ]
},
  "bbox": [],
  "geometry": {"coordinates":[-93.9167,31.5167],"type":"Point"}
}
=======
{"geometry":{"type":"Point","coordinates":[-93.916700,31.516700]},"type":"Feature","properties":{"hierarchy":["tgn:2402346","tgn:1000001","tgn:7012149","tgn:2002066","tgn:7007826","tgn:7029392"],"placetype":["aat:300008706"],"id":2402346,"name:xx":"Horton Creek"}}
>>>>>>> 03f74aca74312dbeaf24d7e61306dd6a786dc3d0
