{
  "id": 2161557,
  "type": "Feature",
  "properties": {
    "tgn:hierarchy":[
        "tgn:2161557",
        "tgn:1000001",
        "tgn:7012149",
        "tgn:1002599",
        "tgn:7007708",
        "tgn:7029392"
    ],
    "tgn:id":2161557,
    "tgn:name":"Bellamy",
    "tgn:placetype":[
        "aat:300008347"
    ]
},
  "bbox": [],
  "geometry": {"coordinates":[-123.9333,44.6833],"type":"Point"}
}