{
  "id": 7469607,
  "type": "Feature",
  "properties": {
    "tgn:hierarchy":[
        "tgn:7469607",
        "tgn:1000004",
        "tgn:7490934",
        "tgn:1000141",
        "tgn:7029392"
    ],
    "tgn:id":7469607,
    "tgn:name":"Jingzijiao",
    "tgn:placetype":[
        "aat:300008347"
    ]
},
  "bbox": [],
  "geometry": {"coordinates":[120.1086,23.2602],"type":"Point"}
}