<<<<<<< HEAD
{
  "id": 2333805,
  "type": "Feature",
  "properties": {
    "tgn:hierarchy":[
        "tgn:2333805",
        "tgn:1000001",
        "tgn:7012149",
        "tgn:2000491",
        "tgn:7007250",
        "tgn:7029392"
    ],
    "tgn:id":2333805,
    "tgn:name":"Forage Mountain",
    "tgn:placetype":[
        "aat:300008798"
    ]
},
  "bbox": [],
  "geometry": {"coordinates":[-115.7667,47.1167],"type":"Point"}
}
=======
{"geometry":{"type":"Point","coordinates":[-115.766700,47.116700]},"type":"Feature","properties":{"hierarchy":["tgn:2333805","tgn:1000001","tgn:7012149","tgn:2000491","tgn:7007250","tgn:7029392"],"placetype":["aat:300008798"],"id":2333805,"name:xx":"Forage Mountain"}}
>>>>>>> 03f74aca74312dbeaf24d7e61306dd6a786dc3d0
