{
  "id": 7458319,
  "type": "Feature",
  "properties": {
    "tgn:hierarchy":[
        "tgn:7458319",
        "tgn:7002445",
        "tgn:1000003",
        "tgn:7008165",
        "tgn:7008591",
        "tgn:7029392"
    ],
    "tgn:id":7458319,
    "tgn:name:en":"Newton Skere",
    "tgn:placetype":[
        "aat:300008808"
    ]
},
  "bbox": [],
  "geometry": {"coordinates":[-1.483333,55.566667],"type":"Point"}
}