{
  "id": 7346409,
  "type": "Feature",
  "properties": {
    "tgn:hierarchy":[
        "tgn:7346409",
        "tgn:7002810",
        "tgn:7001158",
        "tgn:1000003",
        "tgn:1000095",
        "tgn:7029392"
    ],
    "tgn:id":7346409,
    "tgn:name":"Arija",
    "tgn:placetype":[
        "aat:300008347"
    ]
},
  "bbox": [],
  "geometry": {"coordinates":[-3.95,42.983333],"type":"Point"}
}