{
  "id": 7473385,
  "type": "Feature",
  "properties": {
    "tgn:hierarchy":[
        "tgn:7473385",
        "tgn:1000004",
        "tgn:1000454",
        "tgn:1000141",
        "tgn:7029392"
    ],
    "tgn:id":7473385,
    "tgn:name":"Tianzibu",
    "tgn:placetype":[
        "aat:300008347"
    ]
},
  "bbox": [],
  "geometry": {"coordinates":[121.431362,25.120128],"type":"Point"}
}