{
  "id": 2096472,
  "type": "Feature",
  "properties": {
    "tgn:hierarchy":[
        "tgn:2096472",
        "tgn:1000001",
        "tgn:2001734",
        "tgn:7012149",
        "tgn:7007712",
        "tgn:7029392"
    ],
    "tgn:id":2096472,
    "tgn:name":"Pierpont",
    "tgn:placetype":[
        "aat:300008347"
    ]
},
  "bbox": [],
  "geometry": {"coordinates":[-80.0333,32.8167],"type":"Point"}
}