{
  "id": 7555599,
  "type": "Feature",
  "properties": {
    "tgn:hierarchy":[
        "tgn:7555599",
        "tgn:1000004",
        "tgn:7000198",
        "tgn:7016788",
        "tgn:7029392"
    ],
    "tgn:id":7555599,
    "tgn:name:en":"Muh\u0101na",
    "tgn:placetype":[
        "aat:300008347"
    ]
},
  "bbox": [],
  "geometry": {"coordinates":[75.727091,26.796906],"type":"Point"}
}