{
  "id": 7345247,
  "type": "Feature",
  "properties": {
    "tgn:hierarchy":[
        "tgn:7345247",
        "tgn:7008911",
        "tgn:1000003",
        "tgn:7002763",
        "tgn:1000095",
        "tgn:7029392"
    ],
    "tgn:id":7345247,
    "tgn:name":"Almenada, Isla",
    "tgn:placetype":[
        "aat:300008791"
    ]
},
  "bbox": [],
  "geometry": {"coordinates":[-4.783333,43.433333],"type":"Point"}
}