{
  "id": 2459594,
  "type": "Feature",
  "properties": {
    "tgn:hierarchy":[
        "tgn:2459594",
        "tgn:1000001",
        "tgn:7013557",
        "tgn:7012149",
        "tgn:7007709",
        "tgn:7029392"
    ],
    "tgn:id":2459594,
    "tgn:name":"Little Rattlesnake Creek",
    "tgn:placetype":[
        "aat:300008706"
    ]
},
  "bbox": [],
  "geometry": {"coordinates":[-79.2333,36.4833],"type":"Point"}
}