{
  "id": 7499473,
  "type": "Feature",
  "properties": {
    "tgn:hierarchy":[
        "tgn:7499473",
        "tgn:1000004",
        "tgn:7492971",
        "tgn:1000141",
        "tgn:7029392"
    ],
    "tgn:id":7499473,
    "tgn:name":"Liufenzhuang",
    "tgn:placetype":[
        "aat:300008347"
    ]
},
  "bbox": [],
  "geometry": {"coordinates":[120.506672,22.568515],"type":"Point"}
}