{
  "id": 2014797,
  "type": "Feature",
  "properties": {
    "tgn:hierarchy":[
        "tgn:2014797",
        "tgn:1000001",
        "tgn:7012149",
        "tgn:7007157",
        "tgn:1002706",
        "tgn:7029392"
    ],
    "tgn:id":2014797,
    "tgn:name":"Veteran Heights",
    "tgn:placetype":[
        "aat:300008347"
    ]
},
  "bbox": [],
  "geometry": {"coordinates":[-122.4333,38.5667],"type":"Point"}
}