{
  "id": 7195564,
  "type": "Feature",
  "properties": {
    "tgn:hierarchy":[
        "tgn:7195564",
        "tgn:1000003",
        "tgn:7003687",
        "tgn:7000084",
        "tgn:7029392"
    ],
    "tgn:id":7195564,
    "tgn:name":"Dorfstelle Politz",
    "tgn:placetype":[
        "aat:300055621"
    ]
},
  "bbox": [],
  "geometry": {"coordinates":[11.816667,51.866667],"type":"Point"}
}