<<<<<<< HEAD
{
  "id": 2760774,
  "type": "Feature",
  "properties": {
    "tgn:hierarchy":[
        "tgn:2760774",
        "tgn:1000001",
        "tgn:7012149",
        "tgn:2000210",
        "tgn:7007158",
        "tgn:7029392"
    ],
    "tgn:id":2760774,
    "tgn:name":"West Grouse Creek",
    "tgn:placetype":[
        "aat:300008706"
    ]
},
  "bbox": [],
  "geometry": {"coordinates":[-106.5,39.5333],"type":"Point"}
}
=======
{"geometry":{"type":"Point","coordinates":[-106.500000,39.533300]},"type":"Feature","properties":{"hierarchy":["tgn:2760774","tgn:1000001","tgn:7012149","tgn:2000210","tgn:7007158","tgn:7029392"],"placetype":["aat:300008706"],"id":2760774,"name:xx":"West Grouse Creek"}}
>>>>>>> 03f74aca74312dbeaf24d7e61306dd6a786dc3d0
