<<<<<<< HEAD
{
  "id": 2158918,
  "type": "Feature",
  "properties": {
    "tgn:hierarchy":[
        "tgn:2158918",
        "tgn:1000001",
        "tgn:7016172",
        "tgn:7012149",
        "tgn:2000173",
        "tgn:7029392"
    ],
    "tgn:id":2158918,
    "tgn:name":"Beckman Hollow",
    "tgn:placetype":[
        "aat:300008761"
    ]
},
  "bbox": [],
  "geometry": {"coordinates":[-92.05,35.9167],"type":"Point"}
}
=======
{"geometry":{"type":"Point","coordinates":[-92.050000,35.916700]},"type":"Feature","properties":{"hierarchy":["tgn:2158918","tgn:1000001","tgn:7016172","tgn:7012149","tgn:2000173","tgn:7029392"],"placetype":["aat:300008761"],"id":2158918,"name:xx":"Beckman Hollow"}}
>>>>>>> 03f74aca74312dbeaf24d7e61306dd6a786dc3d0
