{
  "id": 7210660,
  "type": "Feature",
  "properties": {
    "tgn:hierarchy":[
        "tgn:7210660",
        "tgn:1000003",
        "tgn:7003685",
        "tgn:7000084",
        "tgn:7029392"
    ],
    "tgn:id":7210660,
    "tgn:name":"Belgern, Stadtforst",
    "tgn:placetype":[
        "aat:300008863"
    ]
},
  "bbox": [],
  "geometry": {"coordinates":[13.066667,51.466667],"type":"Point"}
}