{
  "id": 7591952,
  "type": "Feature",
  "properties": {
    "tgn:hierarchy":[
        "tgn:7591952",
        "tgn:1000004",
        "tgn:7000198",
        "tgn:7031786",
        "tgn:7029392"
    ],
    "tgn:id":7591952,
    "tgn:name:en":"Mot\u012bpur",
    "tgn:placetype":[
        "aat:300008347"
    ]
},
  "bbox": [],
  "geometry": {"coordinates":[77.93165,30.32547],"type":"Point"}
}