{
  "id": 7353580,
  "type": "Feature",
  "properties": {
    "tgn:hierarchy":[
        "tgn:7353580",
        "tgn:7005580",
        "tgn:1000001",
        "tgn:7005560",
        "tgn:7029392"
    ],
    "tgn:id":7353580,
    "tgn:name":"Azapac",
    "tgn:placetype":[
        "aat:300008347"
    ]
},
  "bbox": [],
  "geometry": {"coordinates":[-93.433333,17.266667],"type":"Point"}
}