{
  "id": 2471729,
  "type": "Feature",
  "properties": {
    "tgn:hierarchy":[
        "tgn:2471729",
        "tgn:1002176",
        "tgn:1000001",
        "tgn:7012149",
        "tgn:7007828",
        "tgn:7029392"
    ],
    "tgn:id":2471729,
    "tgn:name":"Lost Pond",
    "tgn:placetype":[
        "aat:300008680"
    ]
},
  "bbox": [],
  "geometry": {"coordinates":[-73.05,42.9333],"type":"Point"}
}