{
  "id": 2753214,
  "type": "Feature",
  "properties": {
    "tgn:hierarchy":[
        "tgn:2753214",
        "tgn:1000001",
        "tgn:2002135",
        "tgn:7012149",
        "tgn:7007828",
        "tgn:7029392"
    ],
    "tgn:id":2753214,
    "tgn:name":"Waterbury Reservoir",
    "tgn:placetype":[
        "aat:300006191"
    ]
},
  "bbox": [],
  "geometry": {"coordinates":[-72.7667,44.3667],"type":"Point"}
}