{
  "id": 7561111,
  "type": "Feature",
  "properties": {
    "tgn:hierarchy":[
        "tgn:7561111",
        "tgn:1000004",
        "tgn:7000198",
        "tgn:7016722",
        "tgn:7029392"
    ],
    "tgn:id":7561111,
    "tgn:name:en":"Bachheli",
    "tgn:placetype":[
        "aat:300008347"
    ]
},
  "bbox": [],
  "geometry": {"coordinates":[79.180329,27.816438],"type":"Point"}
}