{
  "id": 2644717,
  "type": "Feature",
  "properties": {
    "tgn:hierarchy":[
        "tgn:2644717",
        "tgn:1000001",
        "tgn:7012149",
        "tgn:2002384",
        "tgn:7007923",
        "tgn:7029392"
    ],
    "tgn:id":2644717,
    "tgn:name":"Sargents Bay",
    "tgn:placetype":[
        "aat:300132316"
    ]
},
  "bbox": [],
  "geometry": {"coordinates":[-110.6333,43.9333],"type":"Point"}
}