{
  "id": 7146116,
  "type": "Feature",
  "properties": {
    "tgn:hierarchy":[
        "tgn:7146116",
        "tgn:1000003",
        "tgn:7000094",
        "tgn:7000084",
        "tgn:7029392"
    ],
    "tgn:id":7146116,
    "tgn:name":"K\u00f6rchow",
    "tgn:placetype":[
        "aat:300008347"
    ]
},
  "bbox": [],
  "geometry": {"coordinates":[11.716667,54.066667],"type":"Point"}
}