{
  "id": 2756248,
  "type": "Feature",
  "properties": {
    "tgn:hierarchy":[
        "tgn:2756248",
        "tgn:1000001",
        "tgn:1002271",
        "tgn:7012149",
        "tgn:7007920",
        "tgn:7029392"
    ],
    "tgn:id":2756248,
    "tgn:name":"Welch Peaks",
    "tgn:placetype":[
        "aat:300008798"
    ]
},
  "bbox": [],
  "geometry": {"coordinates":[-123.05,47.8333],"type":"Point"}
}