<<<<<<< HEAD
{
  "id": 7481341,
  "type": "Feature",
  "properties": {
    "tgn:hierarchy":[
        "tgn:7481341",
        "tgn:1000004",
        "tgn:7492971",
        "tgn:1000141",
        "tgn:7029392"
    ],
    "tgn:id":7481341,
    "tgn:name":"Rixin Gongshang",
    "tgn:placetype":[
        "aat:300006495"
    ]
},
  "bbox": [],
  "geometry": {"coordinates":[120.536283,22.556785],"type":"Point"}
}
=======
{"geometry":{"type":"Point","coordinates":[120.536283,22.556785]},"type":"Feature","properties":{"hierarchy":["tgn:7481341","tgn:1000004","tgn:7492971","tgn:1000141","tgn:7029392"],"placetype":["aat:300006495"],"id":7481341,"name:xx":"Rixin Gongshang"}}
>>>>>>> 03f74aca74312dbeaf24d7e61306dd6a786dc3d0
