{
  "id": 7544895,
  "type": "Feature",
  "properties": {
    "tgn:hierarchy":[
        "tgn:7544895",
        "tgn:1000004",
        "tgn:1001869",
        "tgn:7000198",
        "tgn:7029392"
    ],
    "tgn:id":7544895,
    "tgn:name:en":"Alindra Road",
    "tgn:placetype":[
        "aat:300007783"
    ]
},
  "bbox": [],
  "geometry": {"coordinates":[73.25,22.45],"type":"Point"}
}