{
  "id": 1116056,
  "type": "Feature",
  "properties": {
    "tgn:hierarchy":[
        "tgn:1116056",
        "tgn:7005685",
        "tgn:1000001",
        "tgn:7005804",
        "tgn:7029392"
    ],
    "tgn:id":1116056,
    "tgn:name":"D\u00e9sert, Lac",
    "tgn:placetype":[
        "aat:300008680"
    ]
},
  "bbox": [],
  "geometry": {"coordinates":[-76.3333,46.5833],"type":"Point"}
}