{
  "id": 7184912,
  "type": "Feature",
  "properties": {
    "tgn:hierarchy":[
        "tgn:7184912",
        "tgn:1000003",
        "tgn:7003685",
        "tgn:7000084",
        "tgn:7029392"
    ],
    "tgn:id":7184912,
    "tgn:name":"Gosa",
    "tgn:placetype":[
        "aat:300000745"
    ]
},
  "bbox": [],
  "geometry": {"coordinates":[13.383333,51.266667],"type":"Point"}
}