{
  "id": 2519493,
  "type": "Feature",
  "properties": {
    "tgn:hierarchy":[
        "tgn:2519493",
        "tgn:1000001",
        "tgn:7012149",
        "tgn:2001449",
        "tgn:7007566",
        "tgn:7029392"
    ],
    "tgn:id":2519493,
    "tgn:name":"Moeller Spring",
    "tgn:placetype":[
        "aat:300008697"
    ]
},
  "bbox": [],
  "geometry": {"coordinates":[-106.2333,36.6833],"type":"Point"}
}