{
  "id": 1003939,
  "type": "Feature",
  "properties": {
    "tgn:hierarchy":[
        "tgn:1003939",
        "tgn:7001242",
        "tgn:7016833",
        "tgn:1001079",
        "tgn:7029392"
    ],
    "tgn:id":1003939,
    "tgn:name:en":"Al Muntazah",
    "tgn:placetype":[
        "aat:300000745",
        "aat:300007783"
    ]
},
  "bbox": [],
  "geometry": {"coordinates":[30.0167,31.2833],"type":"Point"}
}