{
  "id": 7420698,
  "type": "Feature",
  "properties": {
    "tgn:hierarchy":[
        "tgn:7420698",
        "tgn:7005584",
        "tgn:1000001",
        "tgn:7005560",
        "tgn:7029392"
    ],
    "tgn:id":7420698,
    "tgn:name":"La Palencia",
    "tgn:placetype":[
        "aat:300008347"
    ]
},
  "bbox": [],
  "geometry": {"coordinates":[-100.710833,21.428056],"type":"Point"}
}