<<<<<<< HEAD
{
  "id": 7117799,
  "type": "Feature",
  "properties": {
    "tgn:hierarchy":[
        "tgn:7117799",
        "tgn:1000003",
        "tgn:7003677",
        "tgn:7000084",
        "tgn:7029392"
    ],
    "tgn:id":7117799,
    "tgn:name":"Ondrup",
    "tgn:placetype":[
        "aat:300387200"
    ]
},
  "bbox": [],
  "geometry": {"coordinates":[7.483333,51.7],"type":"Point"}
}
=======
{"geometry":{"type":"Point","coordinates":[7.483333,51.700000]},"type":"Feature","properties":{"hierarchy":["tgn:7117799","tgn:1000003","tgn:7003677","tgn:7000084","tgn:7029392"],"placetype":["aat:300387200"],"id":7117799,"name:xx":"Ondrup"}}
>>>>>>> 03f74aca74312dbeaf24d7e61306dd6a786dc3d0
