{
  "id": 7329563,
  "type": "Feature",
  "properties": {
    "tgn:hierarchy":[
        "tgn:7329563",
        "tgn:7002824",
        "tgn:1000003",
        "tgn:7002786",
        "tgn:1000095",
        "tgn:7029392"
    ],
    "tgn:id":7329563,
    "tgn:name":"Pi\u00f1eiro",
    "tgn:placetype":[
        "aat:300008347"
    ]
},
  "bbox": [],
  "geometry": {"coordinates":[-8.916667,43.183333],"type":"Point"}
}