{
  "id": 7374535,
  "type": "Feature",
  "properties": {
    "tgn:hierarchy":[
        "tgn:7374535",
        "tgn:7005586",
        "tgn:1000001",
        "tgn:7005560",
        "tgn:7029392"
    ],
    "tgn:id":7374535,
    "tgn:name":"La Cruz",
    "tgn:placetype":[
        "aat:300008347"
    ]
},
  "bbox": [],
  "geometry": {"coordinates":[-103.783333,19.433333],"type":"Point"}
}