{
  "id": 2280483,
  "type": "Feature",
  "properties": {
    "tgn:hierarchy":[
        "tgn:2280483",
        "tgn:1000001",
        "tgn:1002724",
        "tgn:7012149",
        "tgn:7007517",
        "tgn:7029392"
    ],
    "tgn:id":2280483,
    "tgn:name":"Dedham Island",
    "tgn:placetype":[
        "aat:300008347"
    ]
},
  "bbox": [],
  "geometry": {"coordinates":[-71.1667,42.2667],"type":"Point"}
}