{
  "id": 7547110,
  "type": "Feature",
  "properties": {
    "tgn:hierarchy":[
        "tgn:7547110",
        "tgn:1000004",
        "tgn:7000198",
        "tgn:1001895",
        "tgn:7029392"
    ],
    "tgn:id":7547110,
    "tgn:name:en":"B\u0101mni",
    "tgn:placetype":[
        "aat:300008347"
    ]
},
  "bbox": [],
  "geometry": {"coordinates":[76.666667,19.766667],"type":"Point"}
}