{
  "id": 7290303,
  "type": "Feature",
  "properties": {
    "tgn:hierarchy":[
        "tgn:7290303",
        "tgn:1001705",
        "tgn:1000049",
        "tgn:1000002",
        "tgn:7029392"
    ],
    "tgn:id":7290303,
    "tgn:name":"Don Be\u00f1o, Loma de",
    "tgn:placetype":[
        "aat:300008795"
    ]
},
  "bbox": [],
  "geometry": {"coordinates":[-71.666667,-35.316667],"type":"Point"}
}