{
  "id": 7417153,
  "type": "Feature",
  "properties": {
    "tgn:hierarchy":[
        "tgn:7417153",
        "tgn:1000001",
        "tgn:7005591",
        "tgn:7005560",
        "tgn:7029392"
    ],
    "tgn:id":7417153,
    "tgn:name:es":"Yutanicani",
    "tgn:placetype":[
        "aat:300008347"
    ]
},
  "bbox": [],
  "geometry": {"coordinates":[-97.9925,16.281111],"type":"Point"}
}