{
  "id": 1038569,
  "type": "Feature",
  "properties": {
    "tgn:hierarchy":[
        "tgn:1038569",
        "tgn:1000003",
        "tgn:7003676",
        "tgn:7000084",
        "tgn:7029392"
    ],
    "tgn:id":1038569,
    "tgn:name":"Bockenem",
    "tgn:placetype":[
        "aat:300008347"
    ]
},
  "bbox": [],
  "geometry": {"coordinates":[10.133333,52.016667],"type":"Point"}
}