<<<<<<< HEAD
{
  "id": 7054642,
  "type": "Feature",
  "properties": {
    "tgn:hierarchy":[
        "tgn:7054642",
        "tgn:1003488",
        "tgn:1000003",
        "tgn:7002993",
        "tgn:1000080",
        "tgn:7029392"
    ],
    "tgn:id":7054642,
    "tgn:name":"Ponte della Muda",
    "tgn:placetype":[
        "aat:300008347"
    ]
},
  "bbox": [],
  "geometry": {"coordinates":[12.433333,45.95],"type":"Point"}
}
=======
{"geometry":{"type":"Point","coordinates":[12.433333,45.950000]},"type":"Feature","properties":{"hierarchy":["tgn:7054642","tgn:1003488","tgn:1000003","tgn:7002993","tgn:1000080","tgn:7029392"],"placetype":["aat:300008347"],"id":7054642,"name:xx":"Ponte della Muda"}}
>>>>>>> 03f74aca74312dbeaf24d7e61306dd6a786dc3d0
