{
  "id": 7309438,
  "type": "Feature",
  "properties": {
    "tgn:hierarchy":[
        "tgn:7309438",
        "tgn:7002464",
        "tgn:1000049",
        "tgn:1000002",
        "tgn:7029392"
    ],
    "tgn:id":7309438,
    "tgn:name":"Pachani",
    "tgn:placetype":[
        "aat:300008347"
    ]
},
  "bbox": [],
  "geometry": {"coordinates":[-69.633333,-18.483333],"type":"Point"}
}