{
  "id": 7420442,
  "type": "Feature",
  "properties": {
    "tgn:hierarchy":[
        "tgn:7420442",
        "tgn:7005579",
        "tgn:1000001",
        "tgn:7005560",
        "tgn:7029392"
    ],
    "tgn:id":7420442,
    "tgn:name":"El Cortijo",
    "tgn:placetype":[
        "aat:300008347"
    ]
},
  "bbox": [],
  "geometry": {"coordinates":[-102.295833,22.016667],"type":"Point"}
}