{
  "id": 7478583,
  "type": "Feature",
  "properties": {
    "tgn:hierarchy":[
        "tgn:7478583",
        "tgn:7487020",
        "tgn:1000004",
        "tgn:1000141",
        "tgn:7029392"
    ],
    "tgn:id":7478583,
    "tgn:name":"Wuhu Guoxiao",
    "tgn:placetype":[
        "aat:300006495"
    ]
},
  "bbox": [],
  "geometry": {"coordinates":[120.776788,24.520963],"type":"Point"}
}