{
  "id": 2620951,
  "type": "Feature",
  "properties": {
    "tgn:hierarchy":[
        "tgn:2620951",
        "tgn:1000001",
        "tgn:2001414",
        "tgn:7012149",
        "tgn:7007526",
        "tgn:7029392"
    ],
    "tgn:id":2620951,
    "tgn:name":"Road Canyon",
    "tgn:placetype":[
        "aat:300008761"
    ]
},
  "bbox": [],
  "geometry": {"coordinates":[-118.6667,41.7667],"type":"Point"}
}