{
  "id": 2200016,
  "type": "Feature",
  "properties": {
    "tgn:hierarchy":[
        "tgn:2200016",
        "tgn:1000001",
        "tgn:7006451",
        "tgn:2000095",
        "tgn:7012149",
        "tgn:7029392"
    ],
    "tgn:id":2200016,
    "tgn:name":"Brushy Canyon Tank",
    "tgn:placetype":[
        "aat:300006191"
    ]
},
  "bbox": [],
  "geometry": {"coordinates":[-109.1833,33.0667],"type":"Point"}
}