{
  "id": 1089315,
  "type": "Feature",
  "properties": {
    "tgn:hierarchy":[
        "tgn:1089315",
        "tgn:1001144",
        "tgn:7001242",
        "tgn:1000159",
        "tgn:7029392"
    ],
    "tgn:id":1089315,
    "tgn:name":"Marchal",
    "tgn:placetype":[
        "aat:300008347"
    ]
},
  "bbox": [],
  "geometry": {"coordinates":[14.9667,-5.2667],"type":"Point"}
}