{
  "id": 2379806,
  "type": "Feature",
  "properties": {
    "tgn:hierarchy":[
        "tgn:2379806",
        "tgn:1000001",
        "tgn:1002221",
        "tgn:7012149",
        "tgn:7007251",
        "tgn:7029392"
    ],
    "tgn:id":2379806,
    "tgn:name":"Hastings Landing",
    "tgn:placetype":[
        "aat:300008347"
    ]
},
  "bbox": [],
  "geometry": {"coordinates":[-90.6667,38.95],"type":"Point"}
}