{
  "id": 1103490,
  "type": "Feature",
  "properties": {
    "tgn:hierarchy":[
        "tgn:1103490",
        "tgn:7003026",
        "tgn:1000003",
        "tgn:1000062",
        "tgn:7029392"
    ],
    "tgn:id":1103490,
    "tgn:name":"Sauwald",
    "tgn:placetype":[
        "aat:300132451"
    ]
},
  "bbox": [],
  "geometry": {"coordinates":[13.6667,48.4667],"type":"Point"}
}