{
  "id": 2422818,
  "type": "Feature",
  "properties": {
    "tgn:hierarchy":[
        "tgn:2422818",
        "tgn:1000001",
        "tgn:7012149",
        "tgn:2001853",
        "tgn:7007825",
        "tgn:7029392"
    ],
    "tgn:id":2422818,
    "tgn:name":"Joe Cottons Lake",
    "tgn:placetype":[
        "aat:300006191"
    ]
},
  "bbox": [],
  "geometry": {"coordinates":[-89.1333,35.85],"type":"Point"}
}