{
  "id": 2768868,
  "type": "Feature",
  "properties": {
    "tgn:hierarchy":[
        "tgn:2768868",
        "tgn:1000001",
        "tgn:7012149",
        "tgn:2001308",
        "tgn:7007524",
        "tgn:7029392"
    ],
    "tgn:id":2768868,
    "tgn:name":"Whitney Creek",
    "tgn:placetype":[
        "aat:300008706"
    ]
},
  "bbox": [],
  "geometry": {"coordinates":[-109.5167,45.9667],"type":"Point"}
}