<<<<<<< HEAD
{
  "id": 2768868,
  "type": "Feature",
  "properties": {
    "tgn:hierarchy":[
        "tgn:2768868",
        "tgn:1000001",
        "tgn:7012149",
        "tgn:2001308",
        "tgn:7007524",
        "tgn:7029392"
    ],
    "tgn:id":2768868,
    "tgn:name":"Whitney Creek",
    "tgn:placetype":[
        "aat:300008706"
    ]
},
  "bbox": [],
  "geometry": {"coordinates":[-109.5167,45.9667],"type":"Point"}
}
=======
{"geometry":{"type":"Point","coordinates":[-109.516700,45.966700]},"type":"Feature","properties":{"hierarchy":["tgn:2768868","tgn:1000001","tgn:7012149","tgn:2001308","tgn:7007524","tgn:7029392"],"placetype":["aat:300008706"],"id":2768868,"name:xx":"Whitney Creek"}}
>>>>>>> 03f74aca74312dbeaf24d7e61306dd6a786dc3d0
