{
  "id": 7455430,
  "type": "Feature",
  "properties": {
    "tgn:hierarchy":[
        "tgn:7455430",
        "tgn:7002448",
        "tgn:1000003",
        "tgn:7019206",
        "tgn:7008591",
        "tgn:7029392"
    ],
    "tgn:id":7455430,
    "tgn:name:en":"Dullaghan",
    "tgn:placetype":[
        "aat:300008347"
    ]
},
  "bbox": [],
  "geometry": {"coordinates":[-7.516667,54.533333],"type":"Point"}
}