<<<<<<< HEAD
{
  "id": 2405915,
  "type": "Feature",
  "properties": {
    "tgn:hierarchy":[
        "tgn:2405915",
        "tgn:1000001",
        "tgn:2001653",
        "tgn:7012149",
        "tgn:7007707",
        "tgn:7029392"
    ],
    "tgn:id":2405915,
    "tgn:name":"Hulsey Mountain",
    "tgn:placetype":[
        "aat:300008798"
    ]
},
  "bbox": [],
  "geometry": {"coordinates":[-95.1833,35.05],"type":"Point"}
}
=======
{"geometry":{"type":"Point","coordinates":[-95.183300,35.050000]},"type":"Feature","properties":{"hierarchy":["tgn:2405915","tgn:1000001","tgn:2001653","tgn:7012149","tgn:7007707","tgn:7029392"],"placetype":["aat:300008798"],"id":2405915,"name:xx":"Hulsey Mountain"}}
>>>>>>> 03f74aca74312dbeaf24d7e61306dd6a786dc3d0
