{
  "id": 1074262,
  "type": "Feature",
  "properties": {
    "tgn:hierarchy":[
        "tgn:1074262",
        "tgn:7000840",
        "tgn:1000004",
        "tgn:1000112",
        "tgn:7029392"
    ],
    "tgn:id":1074262,
    "tgn:name":"Peyia",
    "tgn:placetype":[
        "aat:300008347"
    ]
},
  "bbox": [],
  "geometry": {"coordinates":[32.3833,34.8833],"type":"Point"}
}