<<<<<<< HEAD
{
  "id": 2768192,
  "type": "Feature",
  "properties": {
    "tgn:hierarchy":[
        "tgn:2768192",
        "tgn:1000001",
        "tgn:7012149",
        "tgn:2001757",
        "tgn:7007712",
        "tgn:7029392"
    ],
    "tgn:id":2768192,
    "tgn:name":"Whites Cross Roads",
    "tgn:placetype":[
        "aat:300008347"
    ]
},
  "bbox": [],
  "geometry": {"coordinates":[-82.15,33.9167],"type":"Point"}
}
=======
{"geometry":{"type":"Point","coordinates":[-82.150000,33.916700]},"type":"Feature","properties":{"hierarchy":["tgn:2768192","tgn:1000001","tgn:7012149","tgn:2001757","tgn:7007712","tgn:7029392"],"placetype":["aat:300008347"],"id":2768192,"name:xx":"Whites Cross Roads"}}
>>>>>>> 03f74aca74312dbeaf24d7e61306dd6a786dc3d0
