{
  "id": 2549733,
  "type": "Feature",
  "properties": {
    "tgn:hierarchy":[
        "tgn:2549733",
        "tgn:1000001",
        "tgn:7012149",
        "tgn:2001460",
        "tgn:7007566",
        "tgn:7029392"
    ],
    "tgn:id":2549733,
    "tgn:name":"North Tank",
    "tgn:placetype":[
        "aat:300006191"
    ]
},
  "bbox": [],
  "geometry": {"coordinates":[-107.1833,34.6833],"type":"Point"}
}