{
  "id": 2583196,
  "type": "Feature",
  "properties": {
    "tgn:hierarchy":[
        "tgn:2583196",
        "tgn:1000001",
        "tgn:7006451",
        "tgn:2000095",
        "tgn:7012149",
        "tgn:7029392"
    ],
    "tgn:id":2583196,
    "tgn:name":"Pine Log Tank",
    "tgn:placetype":[
        "aat:300006191"
    ]
},
  "bbox": [],
  "geometry": {"coordinates":[-109.25,33.35],"type":"Point"}
}