{
  "id": 2706285,
  "type": "Feature",
  "properties": {
    "tgn:hierarchy":[
        "tgn:2706285",
        "tgn:1000001",
        "tgn:7012149",
        "tgn:2001927",
        "tgn:7007825",
        "tgn:7029392"
    ],
    "tgn:id":2706285,
    "tgn:name":"Swamp Hollow",
    "tgn:placetype":[
        "aat:300008761"
    ]
},
  "bbox": [],
  "geometry": {"coordinates":[-87.6833,35.4667],"type":"Point"}
}