{
  "id": 2135378,
  "type": "Feature",
  "properties": {
    "tgn:hierarchy":[
        "tgn:2135378",
        "tgn:1000001",
        "tgn:7012149",
        "tgn:2002280",
        "tgn:7013961",
        "tgn:7029392"
    ],
    "tgn:id":2135378,
    "tgn:name":"Antley Knob",
    "tgn:placetype":[
        "aat:300008798"
    ]
},
  "bbox": [],
  "geometry": {"coordinates":[-82.3167,37.8667],"type":"Point"}
}