{
  "id": 7234101,
  "type": "Feature",
  "properties": {
    "tgn:hierarchy":[
        "tgn:7234101",
        "tgn:7002681",
        "tgn:7001395",
        "tgn:1000003",
        "tgn:1000074",
        "tgn:7029392"
    ],
    "tgn:id":7234101,
    "tgn:name":"Ach\u00e9rdo, \u00c1kra",
    "tgn:placetype":[
        "aat:300008850"
    ]
},
  "bbox": [],
  "geometry": {"coordinates":[23.484784,37.560635],"type":"Point"}
}