{
  "id": 1140437,
  "type": "Feature",
  "properties": {
    "tgn:hierarchy":[
        "tgn:1140437",
        "tgn:7000895",
        "tgn:1000004",
        "tgn:7016854",
        "tgn:1000120",
        "tgn:7029392"
    ],
    "tgn:id":1140437,
    "tgn:name":"Kasugai",
    "tgn:placetype":[
        "aat:300008347"
    ]
},
  "bbox": [],
  "geometry": {"coordinates":[138.65,35.65],"type":"Point"}
}