{
  "id": 2643566,
  "type": "Feature",
  "properties": {
    "tgn:hierarchy":[
        "tgn:2643566",
        "tgn:1000001",
        "tgn:7012149",
        "tgn:7022218",
        "tgn:7007919",
        "tgn:7029392"
    ],
    "tgn:id":2643566,
    "tgn:name":"Sandy Point",
    "tgn:placetype":[
        "aat:300008850"
    ]
},
  "bbox": [],
  "geometry": {"coordinates":[-76.0667,36.8667],"type":"Point"}
}