{
  "id": 2714520,
  "type": "Feature",
  "properties": {
    "tgn:hierarchy":[
        "tgn:2714520",
        "tgn:1000001",
        "tgn:2001432",
        "tgn:7012149",
        "tgn:7007566",
        "tgn:7029392"
    ],
    "tgn:id":2714520,
    "tgn:name":"Templeton Canyon",
    "tgn:placetype":[
        "aat:300008761"
    ]
},
  "bbox": [],
  "geometry": {"coordinates":[-104.9167,36.5667],"type":"Point"}
}