{
  "id": 2044930,
  "type": "Feature",
  "properties": {
    "tgn:hierarchy":[
        "tgn:2044930",
        "tgn:2000919",
        "tgn:1000001",
        "tgn:7012149",
        "tgn:7007515",
        "tgn:7029392"
    ],
    "tgn:id":2044930,
    "tgn:name":"Hamlin",
    "tgn:placetype":[
        "aat:300008347"
    ]
},
  "bbox": [],
  "geometry": {"coordinates":[-67.7833,47.05],"type":"Point"}
}