{
  "id": 7284996,
  "type": "Feature",
  "properties": {
    "tgn:hierarchy":[
        "tgn:7284996",
        "tgn:1001692",
        "tgn:1000049",
        "tgn:1000002",
        "tgn:7029392"
    ],
    "tgn:id":7284996,
    "tgn:name":"Quilaco, Estero",
    "tgn:placetype":[
        "aat:300008699"
    ]
},
  "bbox": [],
  "geometry": {"coordinates":[-72.133333,-38.283333],"type":"Point"}
}