{
  "id": 7540822,
  "type": "Feature",
  "properties": {
    "tgn:hierarchy":[
        "tgn:7540822",
        "tgn:7001242",
        "tgn:7016833",
        "tgn:1001123",
        "tgn:7029392"
    ],
    "tgn:id":7540822,
    "tgn:name":"Jam\u0101\u015fah, Jaz\u012brat al",
    "tgn:placetype":[
        "aat:300008791"
    ]
},
  "bbox": [],
  "geometry": {"coordinates":[32.046944,31.292778],"type":"Point"}
}