{
  "id": 7096426,
  "type": "Feature",
  "properties": {
    "tgn:hierarchy":[
        "tgn:7096426",
        "tgn:1000003",
        "tgn:7003685",
        "tgn:7000084",
        "tgn:7029392"
    ],
    "tgn:id":7096426,
    "tgn:name":"Siedlung Schneckenstein",
    "tgn:placetype":[
        "aat:300008347"
    ]
},
  "bbox": [],
  "geometry": {"coordinates":[12.433333,50.416667],"type":"Point"}
}