{
  "id": 1088275,
  "type": "Feature",
  "properties": {
    "tgn:hierarchy":[
        "tgn:1088275",
        "tgn:1001189",
        "tgn:7001242",
        "tgn:1000153",
        "tgn:7029392"
    ],
    "tgn:id":1088275,
    "tgn:name":"Saa",
    "tgn:placetype":[
        "aat:300008347"
    ]
},
  "bbox": [],
  "geometry": {"coordinates":[11.45,4.3667],"type":"Point"}
}