{
  "id": 2452663,
  "type": "Feature",
  "properties": {
    "tgn:hierarchy":[
        "tgn:2452663",
        "tgn:7002659",
        "tgn:1000001",
        "tgn:2000016",
        "tgn:7012149",
        "tgn:7029392"
    ],
    "tgn:id":2452663,
    "tgn:name":"Little Buck Island",
    "tgn:placetype":[
        "aat:300008791"
    ]
},
  "bbox": [],
  "geometry": {"coordinates":[-87.7833,34.7167],"type":"Point"}
}