{
  "id": 1081265,
  "type": "Feature",
  "properties": {
    "tgn:hierarchy":[
        "tgn:1081265",
        "tgn:7000895",
        "tgn:1000004",
        "tgn:1001037",
        "tgn:1000120",
        "tgn:7029392"
    ],
    "tgn:id":1081265,
    "tgn:name":"Sh\u014dgawa",
    "tgn:placetype":[
        "aat:300008347"
    ]
},
  "bbox": [],
  "geometry": {"coordinates":[136.9833,36.5667],"type":"Point"}
}