{
  "id": 2302726,
  "type": "Feature",
  "properties": {
    "tgn:hierarchy":[
        "tgn:2302726",
        "tgn:1000001",
        "tgn:2001432",
        "tgn:7012149",
        "tgn:7007566",
        "tgn:7029392"
    ],
    "tgn:id":2302726,
    "tgn:name":"Dwyer Mesa",
    "tgn:placetype":[
        "aat:300008798"
    ]
},
  "bbox": [],
  "geometry": {"coordinates":[-104.3167,36.75],"type":"Point"}
}