{
  "id": 1071186,
  "type": "Feature",
  "properties": {
    "tgn:hierarchy":[
        "tgn:1071186",
        "tgn:1000004",
        "tgn:1001678",
        "tgn:1000111",
        "tgn:7029392"
    ],
    "tgn:id":1071186,
    "tgn:name":"Qujiu",
    "tgn:placetype":[
        "aat:300008347"
    ]
},
  "bbox": [],
  "geometry": {"coordinates":[107.5333,22.5333],"type":"Point"}
}