{
  "id": 7437226,
  "type": "Feature",
  "properties": {
    "tgn:hierarchy":[
        "tgn:7437226",
        "tgn:1000001",
        "tgn:7005591",
        "tgn:7005560",
        "tgn:7029392"
    ],
    "tgn:id":7437226,
    "tgn:name":"Santiago Nundichi",
    "tgn:placetype":[
        "aat:300008347"
    ]
},
  "bbox": [],
  "geometry": {"coordinates":[-97.683333,17.35],"type":"Point"}
}