{
  "id": 7409619,
  "type": "Feature",
  "properties": {
    "tgn:hierarchy":[
        "tgn:7409619",
        "tgn:1000001",
        "tgn:7005592",
        "tgn:7005560",
        "tgn:7029392"
    ],
    "tgn:id":7409619,
    "tgn:name":"Chapuco",
    "tgn:placetype":[
        "aat:300008347"
    ]
},
  "bbox": [],
  "geometry": {"coordinates":[-97.416667,18.608333],"type":"Point"}
}