{
  "id": 2401323,
  "type": "Feature",
  "properties": {
    "tgn:hierarchy":[
        "tgn:2401323",
        "tgn:2002139",
        "tgn:1000001",
        "tgn:7012149",
        "tgn:7007919",
        "tgn:7029392"
    ],
    "tgn:id":2401323,
    "tgn:name":"Horsepen Branch",
    "tgn:placetype":[
        "aat:300008699"
    ]
},
  "bbox": [],
  "geometry": {"coordinates":[-77.8167,37.25],"type":"Point"}
}