<<<<<<< HEAD
{
  "id": 2401323,
  "type": "Feature",
  "properties": {
    "tgn:hierarchy":[
        "tgn:2401323",
        "tgn:2002139",
        "tgn:1000001",
        "tgn:7012149",
        "tgn:7007919",
        "tgn:7029392"
    ],
    "tgn:id":2401323,
    "tgn:name":"Horsepen Branch",
    "tgn:placetype":[
        "aat:300008699"
    ]
},
  "bbox": [],
  "geometry": {"coordinates":[-77.8167,37.25],"type":"Point"}
}
=======
{"geometry":{"type":"Point","coordinates":[-77.816700,37.250000]},"type":"Feature","properties":{"hierarchy":["tgn:2401323","tgn:2002139","tgn:1000001","tgn:7012149","tgn:7007919","tgn:7029392"],"placetype":["aat:300008699"],"id":2401323,"name:xx":"Horsepen Branch"}}
>>>>>>> 03f74aca74312dbeaf24d7e61306dd6a786dc3d0
