{
  "id": 7386495,
  "type": "Feature",
  "properties": {
    "tgn:hierarchy":[
        "tgn:7386495",
        "tgn:7005581",
        "tgn:1000001",
        "tgn:7005560",
        "tgn:7029392"
    ],
    "tgn:id":7386495,
    "tgn:name":"Pe\u00f1asco",
    "tgn:placetype":[
        "aat:300008347"
    ]
},
  "bbox": [],
  "geometry": {"coordinates":[-106.05,27.35],"type":"Point"}
}