{
  "id": 7405540,
  "type": "Feature",
  "properties": {
    "tgn:hierarchy":[
        "tgn:7405540",
        "tgn:7005585",
        "tgn:1000001",
        "tgn:7005560",
        "tgn:7029392"
    ],
    "tgn:id":7405540,
    "tgn:name":"Infiernillo, Cerro",
    "tgn:placetype":[
        "aat:300008795"
    ]
},
  "bbox": [],
  "geometry": {"coordinates":[-101.333333,17.966667],"type":"Point"}
}