<<<<<<< HEAD
{
  "id": 7365332,
  "type": "Feature",
  "properties": {
    "tgn:hierarchy":[
        "tgn:7365332",
        "tgn:7005583",
        "tgn:1000001",
        "tgn:7005560",
        "tgn:7029392"
    ],
    "tgn:id":7365332,
    "tgn:name":"El Solinoso, Ojilo",
    "tgn:placetype":[
        "aat:300008697"
    ]
},
  "bbox": [],
  "geometry": {"coordinates":[-103.566667,24.6],"type":"Point"}
}
=======
{"geometry":{"type":"Point","coordinates":[-103.566667,24.600000]},"type":"Feature","properties":{"hierarchy":["tgn:7365332","tgn:7005583","tgn:1000001","tgn:7005560","tgn:7029392"],"placetype":["aat:300008697"],"id":7365332,"name:xx":"El Solinoso, Ojilo"}}
>>>>>>> 03f74aca74312dbeaf24d7e61306dd6a786dc3d0
