{
  "id": 2151431,
  "type": "Feature",
  "properties": {
    "tgn:hierarchy":[
        "tgn:2151431",
        "tgn:1000001",
        "tgn:2000460",
        "tgn:7012149",
        "tgn:7007250",
        "tgn:7029392"
    ],
    "tgn:id":2151431,
    "tgn:name":"Bath Creek Gorge",
    "tgn:placetype":[
        "aat:300008761"
    ]
},
  "bbox": [],
  "geometry": {"coordinates":[-117.0167,48.5667],"type":"Point"}
}