{
  "id": 2765591,
  "type": "Feature",
  "properties": {
    "tgn:hierarchy":[
        "tgn:2765591",
        "tgn:1000001",
        "tgn:7012149",
        "tgn:2002358",
        "tgn:7007922",
        "tgn:7029392"
    ],
    "tgn:id":2765591,
    "tgn:name":"White City",
    "tgn:placetype":[
        "aat:300008347"
    ]
},
  "bbox": [],
  "geometry": {"coordinates":[-90.45,43.6167],"type":"Point"}
}