{
  "id": 2407313,
  "type": "Feature",
  "properties": {
    "tgn:hierarchy":[
        "tgn:2407313",
        "tgn:1000001",
        "tgn:7012149",
        "tgn:2001869",
        "tgn:7007825",
        "tgn:7029392"
    ],
    "tgn:id":2407313,
    "tgn:name":"Huntingdon Forest",
    "tgn:placetype":[
        "aat:300008347"
    ]
},
  "bbox": [],
  "geometry": {"coordinates":[-85.1833,35.1833],"type":"Point"}
}