{
  "id": 7406746,
  "type": "Feature",
  "properties": {
    "tgn:hierarchy":[
        "tgn:7406746",
        "tgn:1000001",
        "tgn:1001906",
        "tgn:7005560",
        "tgn:7029392"
    ],
    "tgn:id":7406746,
    "tgn:name":"La Guitarra",
    "tgn:placetype":[
        "aat:300008347"
    ]
},
  "bbox": [],
  "geometry": {"coordinates":[-105.075,22.483333],"type":"Point"}
}