{
  "id": 2122946,
  "type": "Feature",
  "properties": {
    "tgn:hierarchy":[
        "tgn:2122946",
        "tgn:1000001",
        "tgn:7012149",
        "tgn:2002379",
        "tgn:7007923",
        "tgn:7029392"
    ],
    "tgn:id":2122946,
    "tgn:name":"Garland",
    "tgn:placetype":[
        "aat:300008347"
    ]
},
  "bbox": [],
  "geometry": {"coordinates":[-108.65,44.7667],"type":"Point"}
}