{
  "id": 7202211,
  "type": "Feature",
  "properties": {
    "tgn:hierarchy":[
        "tgn:7202211",
        "tgn:7003692",
        "tgn:1000003",
        "tgn:7000084",
        "tgn:7029392"
    ],
    "tgn:id":7202211,
    "tgn:name":"Bronnacker",
    "tgn:placetype":[
        "aat:300008347"
    ]
},
  "bbox": [],
  "geometry": {"coordinates":[9.483056,49.444167],"type":"Point"}
}