{
  "id": 2510178,
  "type": "Feature",
  "properties": {
    "tgn:hierarchy":[
        "tgn:2510178",
        "tgn:1000001",
        "tgn:7006451",
        "tgn:2000095",
        "tgn:7012149",
        "tgn:7029392"
    ],
    "tgn:id":2510178,
    "tgn:name":"Middle Prong Tank",
    "tgn:placetype":[
        "aat:300006191"
    ]
},
  "bbox": [],
  "geometry": {"coordinates":[-109.3667,33.35],"type":"Point"}
}