{
  "id": 7424857,
  "type": "Feature",
  "properties": {
    "tgn:hierarchy":[
        "tgn:7424857",
        "tgn:1000001",
        "tgn:7005601",
        "tgn:7005560",
        "tgn:7029392"
    ],
    "tgn:id":7424857,
    "tgn:name":"El Hormiguero",
    "tgn:placetype":[
        "aat:300008347"
    ]
},
  "bbox": [],
  "geometry": {"coordinates":[-102.55,22.633333],"type":"Point"}
}