<<<<<<< HEAD
{
  "id": 2258596,
  "type": "Feature",
  "properties": {
    "tgn:hierarchy":[
        "tgn:2258596",
        "tgn:1000001",
        "tgn:2002106",
        "tgn:7012149",
        "tgn:7007827",
        "tgn:7029392"
    ],
    "tgn:id":2258596,
    "tgn:name":"Cottonwood Acres",
    "tgn:placetype":[
        "aat:300008347"
    ]
},
  "bbox": [],
  "geometry": {"coordinates":[-111.85,40.8667],"type":"Point"}
}
=======
{"geometry":{"type":"Point","coordinates":[-111.850000,40.866700]},"type":"Feature","properties":{"hierarchy":["tgn:2258596","tgn:1000001","tgn:2002106","tgn:7012149","tgn:7007827","tgn:7029392"],"placetype":["aat:300008347"],"id":2258596,"name:xx":"Cottonwood Acres"}}
>>>>>>> 03f74aca74312dbeaf24d7e61306dd6a786dc3d0
