{
  "id": 7218815,
  "type": "Feature",
  "properties": {
    "tgn:hierarchy":[
        "tgn:7218815",
        "tgn:7011161",
        "tgn:7002674",
        "tgn:1000003",
        "tgn:1000074",
        "tgn:7029392"
    ],
    "tgn:id":7218815,
    "tgn:name":"Karter\u00e1 R\u00e9ma",
    "tgn:placetype":[
        "aat:300008699"
    ]
},
  "bbox": [],
  "geometry": {"coordinates":[26.051667,38.266111],"type":"Point"}
}