{
  "id": 7181321,
  "type": "Feature",
  "properties": {
    "tgn:hierarchy":[
        "tgn:7181321",
        "tgn:1000003",
        "tgn:7003678",
        "tgn:7000084",
        "tgn:7029392"
    ],
    "tgn:id":7181321,
    "tgn:name":"Frommershausen",
    "tgn:placetype":[
        "aat:300008347"
    ]
},
  "bbox": [],
  "geometry": {"coordinates":[9.483333,51.366667],"type":"Point"}
}