{
  "id": 2727478,
  "type": "Feature",
  "properties": {
    "tgn:hierarchy":[
        "tgn:2727478",
        "tgn:1000001",
        "tgn:2000466",
        "tgn:7012149",
        "tgn:7007250",
        "tgn:7029392"
    ],
    "tgn:id":2727478,
    "tgn:name":"Trail Creek",
    "tgn:placetype":[
        "aat:300008706"
    ]
},
  "bbox": [],
  "geometry": {"coordinates":[-111.45,42.6833],"type":"Point"}
}