<<<<<<< HEAD
{
  "id": 2764171,
  "type": "Feature",
  "properties": {
    "tgn:hierarchy":[
        "tgn:2764171",
        "tgn:1000001",
        "tgn:7006451",
        "tgn:2000091",
        "tgn:7012149",
        "tgn:7029392"
    ],
    "tgn:id":2764171,
    "tgn:name":"Wheeler Place",
    "tgn:placetype":[
        "aat:300008347"
    ]
},
  "bbox": [],
  "geometry": {"coordinates":[-109.0667,32.25],"type":"Point"}
}
=======
{"geometry":{"type":"Point","coordinates":[-109.066700,32.250000]},"type":"Feature","properties":{"hierarchy":["tgn:2764171","tgn:1000001","tgn:7006451","tgn:2000091","tgn:7012149","tgn:7029392"],"placetype":["aat:300008347"],"id":2764171,"name:xx":"Wheeler Place"}}
>>>>>>> 03f74aca74312dbeaf24d7e61306dd6a786dc3d0
