{
  "id": 7381404,
  "type": "Feature",
  "properties": {
    "tgn:hierarchy":[
        "tgn:7381404",
        "tgn:1001835",
        "tgn:1000001",
        "tgn:7005560",
        "tgn:7029392"
    ],
    "tgn:id":7381404,
    "tgn:name":"Los Morros",
    "tgn:placetype":[
        "aat:300008750"
    ]
},
  "bbox": [],
  "geometry": {"coordinates":[-114.816667,32.683333],"type":"Point"}
}