{
  "id": 2217418,
  "type": "Feature",
  "properties": {
    "tgn:hierarchy":[
        "tgn:2217418",
        "tgn:1000001",
        "tgn:7012149",
        "tgn:2002179",
        "tgn:7007919",
        "tgn:7029392"
    ],
    "tgn:id":2217418,
    "tgn:name":"Campbell Branch",
    "tgn:placetype":[
        "aat:300008699"
    ]
},
  "bbox": [],
  "geometry": {"coordinates":[-80.2667,36.65],"type":"Point"}
}