{
  "id": 7141215,
  "type": "Feature",
  "properties": {
    "tgn:hierarchy":[
        "tgn:7141215",
        "tgn:1000003",
        "tgn:7003685",
        "tgn:7000084",
        "tgn:7029392"
    ],
    "tgn:id":7141215,
    "tgn:name":"Lippendorf",
    "tgn:placetype":[
        "aat:300008347"
    ]
},
  "bbox": [],
  "geometry": {"coordinates":[12.383333,51.183333],"type":"Point"}
}