{
  "id": 2455018,
  "type": "Feature",
  "properties": {
    "tgn:hierarchy":[
        "tgn:2455018",
        "tgn:1000001",
        "tgn:7012149",
        "tgn:7007158",
        "tgn:2000240",
        "tgn:7029392"
    ],
    "tgn:id":2455018,
    "tgn:name":"Little Elk Creek",
    "tgn:placetype":[
        "aat:300008706"
    ]
},
  "bbox": [],
  "geometry": {"coordinates":[-107.0667,39.2333],"type":"Point"}
}