{
  "id": 7224978,
  "type": "Feature",
  "properties": {
    "tgn:hierarchy":[
        "tgn:7224978",
        "tgn:7002741",
        "tgn:7017076",
        "tgn:1000003",
        "tgn:1000074",
        "tgn:7029392"
    ],
    "tgn:id":7224978,
    "tgn:name":"Strava\u00ebt\u00f3s",
    "tgn:placetype":[
        "aat:300008795"
    ]
},
  "bbox": [],
  "geometry": {"coordinates":[22.516667,37.866667],"type":"Point"}
}