{
  "id": 7015993,
  "type": "Feature",
  "properties": {
    "tgn:hierarchy":[
        "tgn:7015993",
        "tgn:7013272",
        "tgn:1000001",
        "tgn:7012149",
        "tgn:7013927",
        "tgn:7007710",
        "tgn:7029392"
    ],
    "tgn:id":7015993,
    "tgn:name":"Lawrenceville",
    "tgn:placetype":[
        "aat:300000745"
    ]
},
  "bbox": [],
  "geometry": {"coordinates":[-79.95,40.4667],"type":"Point"}
}