{
  "id": 7102950,
  "type": "Feature",
  "properties": {
    "tgn:hierarchy":[
        "tgn:7102950",
        "tgn:7003669",
        "tgn:1000003",
        "tgn:7000084",
        "tgn:7029392"
    ],
    "tgn:id":7102950,
    "tgn:name":"Sankt Johann",
    "tgn:placetype":[
        "aat:300008347"
    ]
},
  "bbox": [],
  "geometry": {"coordinates":[12.816667,48.166667],"type":"Point"}
}