{
  "id": 1031426,
  "type": "Feature",
  "properties": {
    "tgn:hierarchy":[
        "tgn:1031426",
        "tgn:7024077",
        "tgn:1000003",
        "tgn:1000069",
        "tgn:7029392"
    ],
    "tgn:id":1031426,
    "tgn:name":"Lappaj\u00e4rvi",
    "tgn:placetype":[
        "aat:300008347"
    ]
},
  "bbox": [],
  "geometry": {"coordinates":[23.6667,63.2167],"type":"Point"}
}