<<<<<<< HEAD
{
  "id": 2763003,
  "type": "Feature",
  "properties": {
    "tgn:hierarchy":[
        "tgn:2763003",
        "tgn:1000001",
        "tgn:7012149",
        "tgn:1003008",
        "tgn:7007710",
        "tgn:7029392"
    ],
    "tgn:id":2763003,
    "tgn:name":"Weston Brook",
    "tgn:placetype":[
        "aat:300008699"
    ]
},
  "bbox": [],
  "geometry": {"coordinates":[-75.1833,41.8333],"type":"Point"}
}
=======
{"geometry":{"type":"Point","coordinates":[-75.183300,41.833300]},"type":"Feature","properties":{"hierarchy":["tgn:2763003","tgn:1000001","tgn:7012149","tgn:1003008","tgn:7007710","tgn:7029392"],"placetype":["aat:300008699"],"id":2763003,"name:xx":"Weston Brook"}}
>>>>>>> 03f74aca74312dbeaf24d7e61306dd6a786dc3d0
