{
  "id": 2763003,
  "type": "Feature",
  "properties": {
    "tgn:hierarchy":[
        "tgn:2763003",
        "tgn:1000001",
        "tgn:7012149",
        "tgn:1003008",
        "tgn:7007710",
        "tgn:7029392"
    ],
    "tgn:id":2763003,
    "tgn:name":"Weston Brook",
    "tgn:placetype":[
        "aat:300008699"
    ]
},
  "bbox": [],
  "geometry": {"coordinates":[-75.1833,41.8333],"type":"Point"}
}