<<<<<<< HEAD
{
  "id": 7029879,
  "type": "Feature",
  "properties": {
    "tgn:hierarchy":[
        "tgn:7029879",
        "tgn:7002445",
        "tgn:1000003",
        "tgn:7008166",
        "tgn:7008591",
        "tgn:7029392"
    ],
    "tgn:id":7029879,
    "tgn:name":"Bordley",
    "tgn:name:ang":"Borelaie",
    "tgn:placetype":[
        "aat:300008347",
        "aat:300008372"
    ]
},
  "bbox": [],
  "geometry": {"coordinates":[-2.084,54.068],"type":"Point"}
}
=======
{"geometry":{"type":"Point","coordinates":[-2.084000,54.068000]},"type":"Feature","properties":{"hierarchy":["tgn:7029879","tgn:7002445","tgn:1000003","tgn:7008166","tgn:7008591","tgn:7029392"],"placetype":["aat:300008347","aat:300008372"],"id":7029879,"name:xx":"Bordley","name:ang":"Borelaie"}}
>>>>>>> 03f74aca74312dbeaf24d7e61306dd6a786dc3d0
