{
  "id": 2468864,
  "type": "Feature",
  "properties": {
    "tgn:hierarchy":[
        "tgn:2468864",
        "tgn:7006450",
        "tgn:1000001",
        "tgn:2124089",
        "tgn:7012149",
        "tgn:7029392"
    ],
    "tgn:id":2468864,
    "tgn:name":"Long River",
    "tgn:placetype":[
        "aat:300008707"
    ]
},
  "bbox": [],
  "geometry": {"coordinates":[-133.8833,58.1667],"type":"Point"}
}