{
  "id": 7257392,
  "type": "Feature",
  "properties": {
    "tgn:hierarchy":[
        "tgn:7257392",
        "tgn:7593113",
        "tgn:7016620",
        "tgn:7593112",
        "tgn:1000001",
        "tgn:7029392"
    ],
    "tgn:id":7257392,
    "tgn:name:nl":"Soledad",
    "tgn:placetype":[
        "aat:300055621"
    ]
},
  "bbox": [],
  "geometry": {"coordinates":[-68.35,12.25],"type":"Point"}
}