{
  "id": 2100408,
  "type": "Feature",
  "properties": {
    "tgn:hierarchy":[
        "tgn:2100408",
        "tgn:1000001",
        "tgn:7012149",
        "tgn:7022544",
        "tgn:7007825",
        "tgn:7029392"
    ],
    "tgn:id":2100408,
    "tgn:name":"Milledgeville",
    "tgn:placetype":[
        "aat:300008347"
    ]
},
  "bbox": [],
  "geometry": {"coordinates":[-88.3667,35.3667],"type":"Point"}
}