{
  "id": 2511209,
  "type": "Feature",
  "properties": {
    "tgn:hierarchy":[
        "tgn:2511209",
        "tgn:1000001",
        "tgn:7012149",
        "tgn:2001289",
        "tgn:7007524",
        "tgn:7029392"
    ],
    "tgn:id":2511209,
    "tgn:name":"Mike Day Creek",
    "tgn:placetype":[
        "aat:300008706"
    ]
},
  "bbox": [],
  "geometry": {"coordinates":[-111.0833,46.3167],"type":"Point"}
}