{
  "id": 7109776,
  "type": "Feature",
  "properties": {
    "tgn:hierarchy":[
        "tgn:7109776",
        "tgn:7003692",
        "tgn:1000003",
        "tgn:7000084",
        "tgn:7029392"
    ],
    "tgn:id":7109776,
    "tgn:name":"Reinfelderhof",
    "tgn:placetype":[
        "aat:300000206"
    ]
},
  "bbox": [],
  "geometry": {"coordinates":[8.95,48.033333],"type":"Point"}
}