{
  "id": 7074606,
  "type": "Feature",
  "properties": {
    "tgn:hierarchy":[
        "tgn:7074606",
        "tgn:1000003",
        "tgn:7003688",
        "tgn:7000084",
        "tgn:7029392"
    ],
    "tgn:id":7074606,
    "tgn:name":"L\u00fcttfeld",
    "tgn:placetype":[
        "aat:300008347"
    ]
},
  "bbox": [],
  "geometry": {"coordinates":[9.95,54.65],"type":"Point"}
}