{
  "id": 2035525,
  "type": "Feature",
  "properties": {
    "tgn:hierarchy":[
        "tgn:2035525",
        "tgn:1000001",
        "tgn:2000571",
        "tgn:7012149",
        "tgn:7007253",
        "tgn:7029392"
    ],
    "tgn:id":2035525,
    "tgn:name":"Rembrandt",
    "tgn:placetype":[
        "aat:300008347"
    ]
},
  "bbox": [],
  "geometry": {"coordinates":[-95.15,42.8167],"type":"Point"}
}