{
  "id": 2722549,
  "type": "Feature",
  "properties": {
    "tgn:hierarchy":[
        "tgn:2722549",
        "tgn:1000001",
        "tgn:7012149",
        "tgn:2000183",
        "tgn:7007157",
        "tgn:7029392"
    ],
    "tgn:id":2722549,
    "tgn:name":"Tinemaha Lake",
    "tgn:placetype":[
        "aat:300008680"
    ]
},
  "bbox": [],
  "geometry": {"coordinates":[-118.4167,37.0333],"type":"Point"}
}