{
  "id": 2528707,
  "type": "Feature",
  "properties": {
    "tgn:hierarchy":[
        "tgn:2528707",
        "tgn:1000001",
        "tgn:7012149",
        "tgn:2001307",
        "tgn:7007524",
        "tgn:7029392"
    ],
    "tgn:id":2528707,
    "tgn:name":"Mud Butte",
    "tgn:placetype":[
        "aat:300008798"
    ]
},
  "bbox": [],
  "geometry": {"coordinates":[-109.7333,45.5333],"type":"Point"}
}