{
  "id": 2367009,
  "type": "Feature",
  "properties": {
    "tgn:hierarchy":[
        "tgn:2367009",
        "tgn:1000001",
        "tgn:7012149",
        "tgn:7007157",
        "tgn:7029392"
    ],
    "tgn:id":2367009,
    "tgn:name":"Grizzly Gulch",
    "tgn:placetype":[
        "aat:300008761"
    ]
},
  "bbox": [],
  "geometry": {"coordinates":[-120.9667,39.45],"type":"Point"}
}