<<<<<<< HEAD
{
  "id": 7111155,
  "type": "Feature",
  "properties": {
    "tgn:hierarchy":[
        "tgn:7111155",
        "tgn:1000003",
        "tgn:7003687",
        "tgn:7000084",
        "tgn:7029392"
    ],
    "tgn:id":7111155,
    "tgn:name":"Rittlebener Wald",
    "tgn:placetype":[
        "aat:300008863"
    ]
},
  "bbox": [],
  "geometry": {"coordinates":[11.166667,52.683333],"type":"Point"}
}
=======
{"geometry":{"type":"Point","coordinates":[11.166667,52.683333]},"type":"Feature","properties":{"hierarchy":["tgn:7111155","tgn:1000003","tgn:7003687","tgn:7000084","tgn:7029392"],"placetype":["aat:300008863"],"id":7111155,"name:xx":"Rittlebener Wald"}}
>>>>>>> 03f74aca74312dbeaf24d7e61306dd6a786dc3d0
