{
  "id": 7339146,
  "type": "Feature",
  "properties": {
    "tgn:hierarchy":[
        "tgn:7339146",
        "tgn:7002758",
        "tgn:1001316",
        "tgn:1000003",
        "tgn:1000095",
        "tgn:7029392"
    ],
    "tgn:id":7339146,
    "tgn:name":"Corbunillo",
    "tgn:placetype":[
        "aat:300008347"
    ]
},
  "bbox": [],
  "geometry": {"coordinates":[-3.966667,37.933333],"type":"Point"}
}