<<<<<<< HEAD
{
  "id": 2336981,
  "type": "Feature",
  "properties": {
    "tgn:hierarchy":[
        "tgn:2336981",
        "tgn:1000001",
        "tgn:7012149",
        "tgn:2002057",
        "tgn:7007826",
        "tgn:7029392"
    ],
    "tgn:id":2336981,
    "tgn:name":"Fourmile Draw",
    "tgn:placetype":[
        "aat:300008761"
    ]
},
  "bbox": [],
  "geometry": {"coordinates":[-104.0833,30.3833],"type":"Point"}
}
=======
{"geometry":{"type":"Point","coordinates":[-104.083300,30.383300]},"type":"Feature","properties":{"hierarchy":["tgn:2336981","tgn:1000001","tgn:7012149","tgn:2002057","tgn:7007826","tgn:7029392"],"placetype":["aat:300008761"],"id":2336981,"name:xx":"Fourmile Draw"}}
>>>>>>> 03f74aca74312dbeaf24d7e61306dd6a786dc3d0
