{
  "id": 7543503,
  "type": "Feature",
  "properties": {
    "tgn:hierarchy":[
        "tgn:7543503",
        "tgn:7001242",
        "tgn:7016833",
        "tgn:7001335",
        "tgn:7029392"
    ],
    "tgn:id":7543503,
    "tgn:name":"Akhdar, Wadi al",
    "tgn:placetype":[
        "aat:300379998"
    ]
},
  "bbox": [],
  "geometry": {"coordinates":[33.910202,31.164539],"type":"Point"}
}