{
  "id": 1009734,
  "type": "Feature",
  "properties": {
    "tgn:hierarchy":[
        "tgn:1009734",
        "tgn:1000001",
        "tgn:1002359",
        "tgn:7012149",
        "tgn:7007517",
        "tgn:7029392"
    ],
    "tgn:id":1009734,
    "tgn:name":"Winter Island",
    "tgn:placetype":[
        "aat:300008791"
    ]
},
  "bbox": [],
  "geometry": {"coordinates":[-70.8667,42.5167],"type":"Point"}
}