{
  "id": 2764898,
  "type": "Feature",
  "properties": {
    "tgn:hierarchy":[
        "tgn:2764898",
        "tgn:1000001",
        "tgn:7012149",
        "tgn:7007157",
        "tgn:1002857",
        "tgn:7029392"
    ],
    "tgn:id":2764898,
    "tgn:name":"Whiskey Spring",
    "tgn:placetype":[
        "aat:300008697"
    ]
},
  "bbox": [],
  "geometry": {"coordinates":[-115.4333,34.9833],"type":"Point"}
}