{
  "id": 7230718,
  "type": "Feature",
  "properties": {
    "tgn:hierarchy":[
        "tgn:7230718",
        "tgn:7002735",
        "tgn:7017076",
        "tgn:1000003",
        "tgn:1000074",
        "tgn:7029392"
    ],
    "tgn:id":7230718,
    "tgn:name":"Mastrol\u00e9o",
    "tgn:placetype":[
        "aat:300008777"
    ]
},
  "bbox": [],
  "geometry": {"coordinates":[22.516667,36.716667],"type":"Point"}
}