<<<<<<< HEAD
{
  "id": 7172499,
  "type": "Feature",
  "properties": {
    "tgn:hierarchy":[
        "tgn:7172499",
        "tgn:7000096",
        "tgn:1000003",
        "tgn:7000084",
        "tgn:7029392"
    ],
    "tgn:id":7172499,
    "tgn:name":"Heyen-Graben",
    "tgn:placetype":[
        "aat:300008699"
    ]
},
  "bbox": [],
  "geometry": {"coordinates":[14.433333,52.55],"type":"Point"}
}
=======
{"geometry":{"type":"Point","coordinates":[14.433333,52.550000]},"type":"Feature","properties":{"hierarchy":["tgn:7172499","tgn:7000096","tgn:1000003","tgn:7000084","tgn:7029392"],"placetype":["aat:300008699"],"id":7172499,"name:xx":"Heyen-Graben"}}
>>>>>>> 03f74aca74312dbeaf24d7e61306dd6a786dc3d0
