{
  "id": 7429975,
  "type": "Feature",
  "properties": {
    "tgn:hierarchy":[
        "tgn:7429975",
        "tgn:1000001",
        "tgn:7005595",
        "tgn:7005560",
        "tgn:7029392"
    ],
    "tgn:id":7429975,
    "tgn:name":"El Tecomate, Cerro",
    "tgn:placetype":[
        "aat:300008795"
    ]
},
  "bbox": [],
  "geometry": {"coordinates":[-107.85,25.016667],"type":"Point"}
}