{
  "id": 1067645,
  "type": "Feature",
  "properties": {
    "tgn:hierarchy":[
        "tgn:1067645",
        "tgn:1000004",
        "tgn:1001390",
        "tgn:1000111",
        "tgn:7029392"
    ],
    "tgn:id":1067645,
    "tgn:name":"Daziling",
    "tgn:placetype":[
        "aat:300008347"
    ]
},
  "bbox": [],
  "geometry": {"coordinates":[121.4333,41.35],"type":"Point"}
}