{
  "id": 7040259,
  "type": "Feature",
  "properties": {
    "tgn:hierarchy":[
        "tgn:7040259",
        "tgn:7015163",
        "tgn:1000003",
        "tgn:7003121",
        "tgn:1000080",
        "tgn:7029392"
    ],
    "tgn:id":7040259,
    "tgn:name":"Sarraina, Cala",
    "tgn:placetype":[
        "aat:300132317"
    ]
},
  "bbox": [],
  "geometry": {"coordinates":[8.966667,41.083333],"type":"Point"}
}