{
  "id": 7570171,
  "type": "Feature",
  "properties": {
    "tgn:hierarchy":[
        "tgn:7570171",
        "tgn:1000004",
        "tgn:7000198",
        "tgn:7031786",
        "tgn:7029392"
    ],
    "tgn:id":7570171,
    "tgn:name:en":"Kotal",
    "tgn:placetype":[
        "aat:300008347"
    ]
},
  "bbox": [],
  "geometry": {"coordinates":[78.684419,29.914417],"type":"Point"}
}