{
  "id": 2358931,
  "type": "Feature",
  "properties": {
    "tgn:hierarchy":[
        "tgn:2358931",
        "tgn:1000001",
        "tgn:7012149",
        "tgn:7007708",
        "tgn:7029392"
    ],
    "tgn:id":2358931,
    "tgn:name":"Granite Creek",
    "tgn:placetype":[
        "aat:300008706"
    ]
},
  "bbox": [],
  "geometry": {"coordinates":[-123.8333,42.3167],"type":"Point"}
}