{
  "id": 2439436,
  "type": "Feature",
  "properties": {
    "tgn:hierarchy":[
        "tgn:2439436",
        "tgn:1000001",
        "tgn:2001436",
        "tgn:7012149",
        "tgn:7007566",
        "tgn:7029392"
    ],
    "tgn:id":2439436,
    "tgn:name":"Kirkland Spring",
    "tgn:placetype":[
        "aat:300008697"
    ]
},
  "bbox": [],
  "geometry": {"coordinates":[-104.6333,32.15],"type":"Point"}
}