{
  "id": 7437269,
  "type": "Feature",
  "properties": {
    "tgn:hierarchy":[
        "tgn:7437269",
        "tgn:7005587",
        "tgn:1000001",
        "tgn:7005560",
        "tgn:7029392"
    ],
    "tgn:id":7437269,
    "tgn:name":"Tepenacaxco",
    "tgn:placetype":[
        "aat:300008347"
    ]
},
  "bbox": [],
  "geometry": {"coordinates":[-98.433333,20.133333],"type":"Point"}
}