<<<<<<< HEAD
{
  "id": 2769061,
  "type": "Feature",
  "properties": {
    "tgn:hierarchy":[
        "tgn:2769061",
        "tgn:1000001",
        "tgn:7012149",
        "tgn:2002070",
        "tgn:7007826",
        "tgn:7029392"
    ],
    "tgn:id":2769061,
    "tgn:name":"Whitten Draw",
    "tgn:placetype":[
        "aat:300008761"
    ]
},
  "bbox": [],
  "geometry": {"coordinates":[-100.7,30.9333],"type":"Point"}
}
=======
{"geometry":{"type":"Point","coordinates":[-100.700000,30.933300]},"type":"Feature","properties":{"hierarchy":["tgn:2769061","tgn:1000001","tgn:7012149","tgn:2002070","tgn:7007826","tgn:7029392"],"placetype":["aat:300008761"],"id":2769061,"name:xx":"Whitten Draw"}}
>>>>>>> 03f74aca74312dbeaf24d7e61306dd6a786dc3d0
