{
  "id": 2054147,
  "type": "Feature",
  "properties": {
    "tgn:hierarchy":[
        "tgn:2054147",
        "tgn:1000001",
        "tgn:7012149",
        "tgn:2001038",
        "tgn:7007521",
        "tgn:7029392"
    ],
    "tgn:id":2054147,
    "tgn:name":"Cleveland",
    "tgn:placetype":[
        "aat:300008347"
    ]
},
  "bbox": [],
  "geometry": {"coordinates":[-93.8333,44.3167],"type":"Point"}
}