{
  "id": 1013498,
  "type": "Feature",
  "properties": {
    "tgn:hierarchy":[
        "tgn:1013498",
        "tgn:7005735",
        "tgn:7005685",
        "tgn:1000001",
        "tgn:7029392"
    ],
    "tgn:id":1013498,
    "tgn:name":"Fairmont Hot Springs",
    "tgn:placetype":[
        "aat:300008347"
    ]
},
  "bbox": [],
  "geometry": {"coordinates":[-115.9333,50.3333],"type":"Point"}
}