{
  "id": 7207616,
  "type": "Feature",
  "properties": {
    "tgn:hierarchy":[
        "tgn:7207616",
        "tgn:7003669",
        "tgn:1000003",
        "tgn:7000084",
        "tgn:7029392"
    ],
    "tgn:id":7207616,
    "tgn:name":"Buchet",
    "tgn:placetype":[
        "aat:300000206"
    ]
},
  "bbox": [],
  "geometry": {"coordinates":[12.233333,47.983333],"type":"Point"}
}