<<<<<<< HEAD
{
  "id": 7476649,
  "type": "Feature",
  "properties": {
    "tgn:hierarchy":[
        "tgn:7476649",
        "tgn:1000004",
        "tgn:7004300",
        "tgn:1000141",
        "tgn:7029392"
    ],
    "tgn:id":7476649,
    "tgn:name":"Yong'an Gong",
    "tgn:placetype":[
        "aat:300007595"
    ]
},
  "bbox": [],
  "geometry": {"coordinates":[119.615444,23.593584],"type":"Point"}
}
=======
{"geometry":{"type":"Point","coordinates":[119.615444,23.593584]},"type":"Feature","properties":{"hierarchy":["tgn:7476649","tgn:1000004","tgn:7004300","tgn:1000141","tgn:7029392"],"placetype":["aat:300007595"],"id":7476649,"name:xx":"Yong'an Gong"}}
>>>>>>> 03f74aca74312dbeaf24d7e61306dd6a786dc3d0
