{
  "id": 2390708,
  "type": "Feature",
  "properties": {
    "tgn:hierarchy":[
        "tgn:2390708",
        "tgn:1000001",
        "tgn:7012149",
        "tgn:2000230",
        "tgn:7007158",
        "tgn:7029392"
    ],
    "tgn:id":2390708,
    "tgn:name":"Hightower Creek",
    "tgn:placetype":[
        "aat:300008706"
    ]
},
  "bbox": [],
  "geometry": {"coordinates":[-107.65,39.2833],"type":"Point"}
}