{
  "id": 1125185,
  "type": "Feature",
  "properties": {
    "tgn:hierarchy":[
        "tgn:1125185",
        "tgn:1000003",
        "tgn:1000392",
        "tgn:1000091",
        "tgn:7029392"
    ],
    "tgn:id":1125185,
    "tgn:name":"Jijia",
    "tgn:placetype":[
        "aat:300008707"
    ]
},
  "bbox": [],
  "geometry": {"coordinates":[28.081,46.902],"type":"Point"}
}