{
  "id": 2232776,
  "type": "Feature",
  "properties": {
    "tgn:hierarchy":[
        "tgn:2232776",
        "tgn:1000001",
        "tgn:2001816",
        "tgn:7012149",
        "tgn:7007713",
        "tgn:7029392"
    ],
    "tgn:id":2232776,
    "tgn:name":"Chapman Draw",
    "tgn:placetype":[
        "aat:300008761"
    ]
},
  "bbox": [],
  "geometry": {"coordinates":[-102.1833,44.4833],"type":"Point"}
}