{
  "id": 7263143,
  "type": "Feature",
  "properties": {
    "tgn:concordances":{
        "gn:id":"2757662"
    },
    "tgn:hierarchy":[
        "tgn:7263143",
        "tgn:1000003",
        "tgn:7003624",
        "tgn:7016845",
        "tgn:7029392"
    ],
    "tgn:id":7263143,
    "tgn:name:nl":"Deelse Kampen",
    "tgn:placetype":[
        "aat:300008347"
    ]
},
  "bbox": [],
  "geometry": {"coordinates":[5.683333,51.566667],"type":"Point"}
}