<<<<<<< HEAD
{
  "id": 2760299,
  "type": "Feature",
  "properties": {
    "tgn:hierarchy":[
        "tgn:2760299",
        "tgn:1000001",
        "tgn:7012149",
        "tgn:1002545",
        "tgn:7007157",
        "tgn:7029392"
    ],
    "tgn:id":2760299,
    "tgn:name":"West Fork Sand Canyon",
    "tgn:placetype":[
        "aat:300008761"
    ]
},
  "bbox": [],
  "geometry": {"coordinates":[-118.45,35.3667],"type":"Point"}
}
=======
{"geometry":{"type":"Point","coordinates":[-118.450000,35.366700]},"type":"Feature","properties":{"hierarchy":["tgn:2760299","tgn:1000001","tgn:7012149","tgn:1002545","tgn:7007157","tgn:7029392"],"placetype":["aat:300008761"],"id":2760299,"name:xx":"West Fork Sand Canyon"}}
>>>>>>> 03f74aca74312dbeaf24d7e61306dd6a786dc3d0
