{
  "id": 2352591,
  "type": "Feature",
  "properties": {
    "tgn:hierarchy":[
        "tgn:2352591",
        "tgn:2001422",
        "tgn:1000001",
        "tgn:7012149",
        "tgn:7007564",
        "tgn:7029392"
    ],
    "tgn:id":2352591,
    "tgn:name":"Goat Pasture Hill",
    "tgn:placetype":[
        "aat:300008798"
    ]
},
  "bbox": [],
  "geometry": {"coordinates":[-71.3167,43.4833],"type":"Point"}
}