{
  "id": 7486940,
  "type": "Feature",
  "properties": {
    "tgn:hierarchy":[
        "tgn:7486940",
        "tgn:1000004",
        "tgn:7492971",
        "tgn:1000141",
        "tgn:7029392"
    ],
    "tgn:id":7486940,
    "tgn:name":"Beishi Bi",
    "tgn:placetype":[
        "aat:300386846"
    ]
},
  "bbox": [],
  "geometry": {"coordinates":[120.711944,21.934444],"type":"Point"}
}