{
  "id": 7426655,
  "type": "Feature",
  "properties": {
    "tgn:hierarchy":[
        "tgn:7426655",
        "tgn:7005581",
        "tgn:1000001",
        "tgn:7005560",
        "tgn:7029392"
    ],
    "tgn:id":7426655,
    "tgn:name":"Los Lajeros",
    "tgn:placetype":[
        "aat:300008347"
    ]
},
  "bbox": [],
  "geometry": {"coordinates":[-107.933333,26.683333],"type":"Point"}
}