{
  "id": 7123992,
  "type": "Feature",
  "properties": {
    "tgn:hierarchy":[
        "tgn:7123992",
        "tgn:1000003",
        "tgn:7003687",
        "tgn:7000084",
        "tgn:7029392"
    ],
    "tgn:id":7123992,
    "tgn:name":"Neuhaus",
    "tgn:placetype":[
        "aat:300008347"
    ]
},
  "bbox": [],
  "geometry": {"coordinates":[12.15,52.866667],"type":"Point"}
}