{
  "id": 2079740,
  "type": "Feature",
  "properties": {
    "tgn:hierarchy":[
        "tgn:2079740",
        "tgn:1000001",
        "tgn:7012149",
        "tgn:1002424",
        "tgn:7007706",
        "tgn:7029392"
    ],
    "tgn:id":2079740,
    "tgn:name":"Gladstone",
    "tgn:placetype":[
        "aat:300008347"
    ]
},
  "bbox": [],
  "geometry": {"coordinates":[-83.6833,39.7333],"type":"Point"}
}