{
  "id": 2592059,
  "type": "Feature",
  "properties": {
    "tgn:hierarchy":[
        "tgn:2592059",
        "tgn:1000001",
        "tgn:7012149",
        "tgn:1003038",
        "tgn:7007517",
        "tgn:7029392"
    ],
    "tgn:id":2592059,
    "tgn:name":"Pondville Pond",
    "tgn:placetype":[
        "aat:300006191"
    ]
},
  "bbox": [],
  "geometry": {"coordinates":[-71.8167,42.1833],"type":"Point"}
}