{
  "id": 7007947,
  "type": "Feature",
  "properties": {
    "tgn:hierarchy":[
        "tgn:7007947",
        "tgn:7003458",
        "tgn:1000003",
        "tgn:1000063",
        "tgn:7018236",
        "tgn:7029392"
    ],
    "tgn:id":7007947,
    "tgn:name":"Lissewege",
    "tgn:placetype":[
        "aat:300008347"
    ]
},
  "bbox": [],
  "geometry": {"coordinates":[3.193314,51.294266],"type":"Point"}
}