{
  "id": 7581310,
  "type": "Feature",
  "properties": {
    "tgn:hierarchy":[
        "tgn:7581310",
        "tgn:1000004",
        "tgn:7000198",
        "tgn:7016722",
        "tgn:7029392"
    ],
    "tgn:id":7581310,
    "tgn:name:en":"Sikandra",
    "tgn:placetype":[
        "aat:300008347"
    ]
},
  "bbox": [],
  "geometry": {"coordinates":[77.947311,27.21419],"type":"Point"}
}