{
  "id": 7045092,
  "type": "Feature",
  "properties": {
    "tgn:hierarchy":[
        "tgn:7045092",
        "tgn:7015163",
        "tgn:1000003",
        "tgn:7003121",
        "tgn:1000080",
        "tgn:7029392"
    ],
    "tgn:id":7045092,
    "tgn:name":"Corra, Montela",
    "tgn:placetype":[
        "aat:300008777"
    ]
},
  "bbox": [],
  "geometry": {"coordinates":[8.448889,40.7925],"type":"Point"}
}