{
  "id": 2581219,
  "type": "Feature",
  "properties": {
    "tgn:hierarchy":[
        "tgn:2581219",
        "tgn:1000001",
        "tgn:7012149",
        "tgn:7007826",
        "tgn:7029392"
    ],
    "tgn:id":2581219,
    "tgn:name":"Pilgrim Creek",
    "tgn:placetype":[
        "aat:300008706"
    ]
},
  "bbox": [],
  "geometry": {"coordinates":[-101.1833,34.75],"type":"Point"}
}