{
  "id": 7369136,
  "type": "Feature",
  "properties": {
    "tgn:hierarchy":[
        "tgn:7369136",
        "tgn:7005581",
        "tgn:1000001",
        "tgn:7005560",
        "tgn:7029392"
    ],
    "tgn:id":7369136,
    "tgn:name":"Juicle, Arroyo del",
    "tgn:placetype":[
        "aat:300266554",
        "aat:300008699"
    ]
},
  "bbox": [],
  "geometry": {"coordinates":[-108.533333,30.033333],"type":"Point"}
}