{
  "id": 7384476,
  "type": "Feature",
  "properties": {
    "tgn:hierarchy":[
        "tgn:7384476",
        "tgn:7005580",
        "tgn:1000001",
        "tgn:7005560",
        "tgn:7029392"
    ],
    "tgn:id":7384476,
    "tgn:name":"Nascanano",
    "tgn:placetype":[
        "aat:300008347"
    ]
},
  "bbox": [],
  "geometry": {"coordinates":[-93.366667,17.216667],"type":"Point"}
}