{
  "id": 2195317,
  "type": "Feature",
  "properties": {
    "tgn:hierarchy":[
        "tgn:2195317",
        "tgn:1000001",
        "tgn:2001410",
        "tgn:7012149",
        "tgn:7007526",
        "tgn:7029392"
    ],
    "tgn:id":2195317,
    "tgn:name":"Bristlecone Bridge Cave",
    "tgn:placetype":[
        "aat:300008746"
    ]
},
  "bbox": [],
  "geometry": {"coordinates":[-115.1833,36.6167],"type":"Point"}
}