{
  "id": 1130370,
  "type": "Feature",
  "properties": {
    "tgn:hierarchy":[
        "tgn:1130370",
        "tgn:1000003",
        "tgn:1000078",
        "tgn:7029392"
    ],
    "tgn:id":1130370,
    "tgn:name":"Suck, River",
    "tgn:placetype":[
        "aat:300008707"
    ]
},
  "bbox": [],
  "geometry": {"coordinates":[-8.05,53.2667],"type":"Point"}
}