{
  "id": 1098020,
  "type": "Feature",
  "properties": {
    "tgn:hierarchy":[
        "tgn:1098020",
        "tgn:7000490",
        "tgn:1000006",
        "tgn:7006238",
        "tgn:7029392"
    ],
    "tgn:id":1098020,
    "tgn:name":"Queenscliff",
    "tgn:placetype":[
        "aat:300008347"
    ]
},
  "bbox": [],
  "geometry": {"coordinates":[144.65,-38.2667],"type":"Point"}
}