{
  "id": 1036029,
  "type": "Feature",
  "properties": {
    "tgn:hierarchy":[
        "tgn:1036029",
        "tgn:1000003",
        "tgn:7002883",
        "tgn:1000070",
        "tgn:7029392"
    ],
    "tgn:id":1036029,
    "tgn:name":"Vaur\u00e9al",
    "tgn:placetype":[
        "aat:300008347"
    ]
},
  "bbox": [],
  "geometry": {"coordinates":[2.0333,49.0333],"type":"Point"}
}