{
  "id": 2766522,
  "type": "Feature",
  "properties": {
    "tgn:hierarchy":[
        "tgn:2766522",
        "tgn:1000001",
        "tgn:7016172",
        "tgn:7012149",
        "tgn:2000131",
        "tgn:7029392"
    ],
    "tgn:id":2766522,
    "tgn:name":"White Oak Creek",
    "tgn:placetype":[
        "aat:300008706"
    ]
},
  "bbox": [],
  "geometry": {"coordinates":[-92.3667,34.3667],"type":"Point"}
}