{
  "id": 2737961,
  "type": "Feature",
  "properties": {
    "tgn:hierarchy":[
        "tgn:2737961",
        "tgn:2000090",
        "tgn:1000001",
        "tgn:7006451",
        "tgn:7012149",
        "tgn:7029392"
    ],
    "tgn:id":2737961,
    "tgn:name":"Udall Spring",
    "tgn:placetype":[
        "aat:300008697"
    ]
},
  "bbox": [],
  "geometry": {"coordinates":[-109.3667,33.9333],"type":"Point"}
}