{
  "id": 2715564,
  "type": "Feature",
  "properties": {
    "tgn:hierarchy":[
        "tgn:2715564",
        "tgn:1000001",
        "tgn:2000201",
        "tgn:7012149",
        "tgn:7007158",
        "tgn:7029392"
    ],
    "tgn:id":2715564,
    "tgn:name":"Terrible Mine",
    "tgn:placetype":[
        "aat:300000390"
    ]
},
  "bbox": [],
  "geometry": {"coordinates":[-105.7333,39.6833],"type":"Point"}
}