{
  "id": 2352357,
  "type": "Feature",
  "properties": {
    "tgn:hierarchy":[
        "tgn:2352357",
        "tgn:1000001",
        "tgn:7012149",
        "tgn:7007826",
        "tgn:7029392"
    ],
    "tgn:id":2352357,
    "tgn:name":"Goat Creek",
    "tgn:placetype":[
        "aat:300008706"
    ]
},
  "bbox": [],
  "geometry": {"coordinates":[-99.1667,30.15],"type":"Point"}
}