{
  "id": 2574790,
  "type": "Feature",
  "properties": {
    "tgn:hierarchy":[
        "tgn:2574790",
        "tgn:1000001",
        "tgn:2001430",
        "tgn:7012149",
        "tgn:7007566",
        "tgn:7029392"
    ],
    "tgn:id":2574790,
    "tgn:name":"Pendergrass Canyon",
    "tgn:placetype":[
        "aat:300008761"
    ]
},
  "bbox": [],
  "geometry": {"coordinates":[-105.2667,32.9833],"type":"Point"}
}