<<<<<<< HEAD
{
  "id": 2256696,
  "type": "Feature",
  "properties": {
    "tgn:hierarchy":[
        "tgn:2256696",
        "tgn:1000001",
        "tgn:7012149",
        "tgn:7007157",
        "tgn:7014475",
        "tgn:7029392"
    ],
    "tgn:id":2256696,
    "tgn:name":"Cordoza Ridge",
    "tgn:placetype":[
        "aat:300266640"
    ]
},
  "bbox": [],
  "geometry": {"coordinates":[-121.5167,37.15],"type":"Point"}
}
=======
{"geometry":{"type":"Point","coordinates":[-121.516700,37.150000]},"type":"Feature","properties":{"hierarchy":["tgn:2256696","tgn:1000001","tgn:7012149","tgn:7007157","tgn:7014475","tgn:7029392"],"placetype":["aat:300266640"],"id":2256696,"name:xx":"Cordoza Ridge"}}
>>>>>>> 03f74aca74312dbeaf24d7e61306dd6a786dc3d0
