{
  "id": 2679970,
  "type": "Feature",
  "properties": {
    "tgn:hierarchy":[
        "tgn:2679970",
        "tgn:1000001",
        "tgn:2001418",
        "tgn:7012149",
        "tgn:7007526",
        "tgn:7029392"
    ],
    "tgn:id":2679970,
    "tgn:name":"South Fork Shoshone Creek",
    "tgn:placetype":[
        "aat:300008706"
    ]
},
  "bbox": [],
  "geometry": {"coordinates":[-116.9833,38.65],"type":"Point"}
}