{
  "id": 2073576,
  "type": "Feature",
  "properties": {
    "tgn:hierarchy":[
        "tgn:2073576",
        "tgn:2001467",
        "tgn:1000001",
        "tgn:7012149",
        "tgn:7007709",
        "tgn:7029392"
    ],
    "tgn:id":2073576,
    "tgn:name":"Baldwin",
    "tgn:placetype":[
        "aat:300008347",
        "aat:300387210"
    ]
},
  "bbox": [],
  "geometry": {"coordinates":[-81.5167,36.3333],"type":"Point"}
}