{
  "id": 2736409,
  "type": "Feature",
  "properties": {
    "tgn:hierarchy":[
        "tgn:2736409",
        "tgn:1000001",
        "tgn:7012149",
        "tgn:7007515",
        "tgn:7029392"
    ],
    "tgn:id":2736409,
    "tgn:name":"Twin Pond Brook",
    "tgn:placetype":[
        "aat:300008699"
    ]
},
  "bbox": [],
  "geometry": {"coordinates":[-68.8333,45.95],"type":"Point"}
}