{
  "id": 3000912,
  "type": "Feature",
  "properties": {
    "tgn:hierarchy":[
        "tgn:3000912",
        "tgn:7003013",
        "tgn:7003005",
        "tgn:1000003",
        "tgn:1000080",
        "tgn:7029392"
    ],
    "tgn:id":3000912,
    "tgn:name":"Monte Nuovo",
    "tgn:placetype":[
        "aat:300008795",
        "aat:300132325"
    ]
},
  "bbox": [],
  "geometry": {"coordinates":[14.083333,40.833333],"type":"Point"}
}