{
  "id": 7095422,
  "type": "Feature",
  "properties": {
    "tgn:hierarchy":[
        "tgn:7095422",
        "tgn:7003669",
        "tgn:1000003",
        "tgn:7000084",
        "tgn:7029392"
    ],
    "tgn:id":7095422,
    "tgn:name":"Sch\u00f6nbrunn",
    "tgn:placetype":[
        "aat:300008347"
    ]
},
  "bbox": [],
  "geometry": {"coordinates":[11.583333,50.266667],"type":"Point"}
}