{
  "id": 7538277,
  "type": "Feature",
  "properties": {
    "tgn:hierarchy":[
        "tgn:7538277",
        "tgn:7001242",
        "tgn:7016833",
        "tgn:1001113",
        "tgn:7029392"
    ],
    "tgn:id":7538277,
    "tgn:name":"Nazlat Ayy\u016bb",
    "tgn:placetype":[
        "aat:300008347"
    ]
},
  "bbox": [],
  "geometry": {"coordinates":[31.676497,30.594083],"type":"Point"}
}