{
  "id": 7338507,
  "type": "Feature",
  "properties": {
    "tgn:hierarchy":[
        "tgn:7338507",
        "tgn:7002758",
        "tgn:7002823",
        "tgn:1000003",
        "tgn:1000095",
        "tgn:7029392"
    ],
    "tgn:id":7338507,
    "tgn:name":"Apeadero El Cuervo",
    "tgn:placetype":[
        "aat:300007783"
    ]
},
  "bbox": [],
  "geometry": {"coordinates":[-6.783333,37.516667],"type":"Point"}
}