{
  "id": 7479859,
  "type": "Feature",
  "properties": {
    "tgn:hierarchy":[
        "tgn:7479859",
        "tgn:1000004",
        "tgn:7001013",
        "tgn:1000141",
        "tgn:7029392"
    ],
    "tgn:id":7479859,
    "tgn:name":"Huanxiang Qiao",
    "tgn:placetype":[
        "aat:300007836"
    ]
},
  "bbox": [],
  "geometry": {"coordinates":[121.210556,24.943611],"type":"Point"}
}