{
  "id": 2704279,
  "type": "Feature",
  "properties": {
    "tgn:hierarchy":[
        "tgn:2704279",
        "tgn:1000001",
        "tgn:7016172",
        "tgn:7012149",
        "tgn:2000127",
        "tgn:7029392"
    ],
    "tgn:id":2704279,
    "tgn:name":"Sunny Gap",
    "tgn:placetype":[
        "aat:300008347"
    ]
},
  "bbox": [],
  "geometry": {"coordinates":[-92.3333,35.0833],"type":"Point"}
}