{
  "id": 2785940,
  "type": "Feature",
  "properties": {
    "tgn:hierarchy":[
        "tgn:2785940",
        "tgn:1000001",
        "tgn:1002308",
        "tgn:7012149",
        "tgn:7007710",
        "tgn:7029392"
    ],
    "tgn:id":2785940,
    "tgn:name":"Yosets Lake",
    "tgn:placetype":[
        "aat:300008680"
    ]
},
  "bbox": [],
  "geometry": {"coordinates":[-80.05,41.5833],"type":"Point"}
}