{
  "id": 7527248,
  "type": "Feature",
  "properties": {
    "tgn:hierarchy":[
        "tgn:7527248",
        "tgn:7001242",
        "tgn:7016833",
        "tgn:1001418",
        "tgn:7029392"
    ],
    "tgn:id":7527248,
    "tgn:name":"Z\u0327ala\u0163, 'Alam az\u0327",
    "tgn:placetype":[
        "aat:300008777"
    ]
},
  "bbox": [],
  "geometry": {"coordinates":[24.967202,30.564447],"type":"Point"}
}