{
  "id": 2621627,
  "type": "Feature",
  "properties": {
    "tgn:hierarchy":[
        "tgn:2621627",
        "tgn:7002659",
        "tgn:1000001",
        "tgn:7012149",
        "tgn:2000062",
        "tgn:7029392"
    ],
    "tgn:id":2621627,
    "tgn:name":"Rob Hollow",
    "tgn:placetype":[
        "aat:300008761"
    ]
},
  "bbox": [],
  "geometry": {"coordinates":[-87.4667,33.5667],"type":"Point"}
}