{
  "id": 7249253,
  "type": "Feature",
  "properties": {
    "tgn:hierarchy":[
        "tgn:7249253",
        "tgn:7003457",
        "tgn:1000003",
        "tgn:1000063",
        "tgn:7018236",
        "tgn:7029392"
    ],
    "tgn:id":7249253,
    "tgn:name":"Ottersem",
    "tgn:placetype":[
        "aat:300000206"
    ]
},
  "bbox": [],
  "geometry": {"coordinates":[3.733333,51.016667],"type":"Point"}
}