{
  "id": 7276797,
  "type": "Feature",
  "properties": {
    "tgn:hierarchy":[
        "tgn:7276797",
        "tgn:1001699",
        "tgn:1000049",
        "tgn:1000002",
        "tgn:7029392"
    ],
    "tgn:id":7276797,
    "tgn:name":"Las Maravillas",
    "tgn:placetype":[
        "aat:300008347"
    ]
},
  "bbox": [],
  "geometry": {"coordinates":[-71.889167,-43.766944],"type":"Point"}
}