{
  "id": 7026437,
  "type": "Feature",
  "properties": {
    "tgn:hierarchy":[
        "tgn:7026437",
        "tgn:7002445",
        "tgn:1000003",
        "tgn:7008168",
        "tgn:7008591",
        "tgn:7029392"
    ],
    "tgn:id":7026437,
    "tgn:name:en":"Kingston Bagpuize",
    "tgn:placetype":[
        "aat:300008347",
        "aat:300008372"
    ]
},
  "bbox": [],
  "geometry": {"coordinates":[-1.4167,51.6833],"type":"Point"}
}