{
  "id": 2388955,
  "type": "Feature",
  "properties": {
    "tgn:hierarchy":[
        "tgn:2388955",
        "tgn:1000001",
        "tgn:7012149",
        "tgn:2000473",
        "tgn:7007250",
        "tgn:7029392"
    ],
    "tgn:id":2388955,
    "tgn:name":"Hidden Lake Reservoir",
    "tgn:placetype":[
        "aat:300006191"
    ]
},
  "bbox": [],
  "geometry": {"coordinates":[-111.5833,44.25],"type":"Point"}
}