{
  "id": 1091952,
  "type": "Feature",
  "properties": {
    "tgn:hierarchy":[
        "tgn:1091952",
        "tgn:7001242",
        "tgn:7000542",
        "tgn:1000182",
        "tgn:7029392"
    ],
    "tgn:id":1091952,
    "tgn:name":"Dumboa",
    "tgn:placetype":[
        "aat:300008347"
    ]
},
  "bbox": [],
  "geometry": {"coordinates":[12.9167,11.25],"type":"Point"}
}