{
  "id": 7039862,
  "type": "Feature",
  "properties": {
    "tgn:hierarchy":[
        "tgn:7039862",
        "tgn:7003248",
        "tgn:1000003",
        "tgn:7010380",
        "tgn:1000080",
        "tgn:7029392"
    ],
    "tgn:id":7039862,
    "tgn:name":"Selva di Fasano",
    "tgn:placetype":[
        "aat:300008347"
    ]
},
  "bbox": [],
  "geometry": {"coordinates":[17.316667,40.816667],"type":"Point"}
}