<<<<<<< HEAD
{
  "id": 2766312,
  "type": "Feature",
  "properties": {
    "tgn:hierarchy":[
        "tgn:2766312",
        "tgn:1000001",
        "tgn:7012149",
        "tgn:7019676",
        "tgn:7007566",
        "tgn:7029392"
    ],
    "tgn:id":2766312,
    "tgn:name":"White Mesa",
    "tgn:placetype":[
        "aat:300008798"
    ]
},
  "bbox": [],
  "geometry": {"coordinates":[-107.4833,35.55],"type":"Point"}
}
=======
{"geometry":{"type":"Point","coordinates":[-107.483300,35.550000]},"type":"Feature","properties":{"hierarchy":["tgn:2766312","tgn:1000001","tgn:7012149","tgn:7019676","tgn:7007566","tgn:7029392"],"placetype":["aat:300008798"],"id":2766312,"name:xx":"White Mesa"}}
>>>>>>> 03f74aca74312dbeaf24d7e61306dd6a786dc3d0
