{
  "id": 2078286,
  "type": "Feature",
  "properties": {
    "tgn:hierarchy":[
        "tgn:2078286",
        "tgn:1002175",
        "tgn:1000001",
        "tgn:7012149",
        "tgn:7007706",
        "tgn:7029392"
    ],
    "tgn:id":2078286,
    "tgn:name":"Atlas",
    "tgn:placetype":[
        "aat:300008347"
    ]
},
  "bbox": [],
  "geometry": {"coordinates":[-81.1833,39.8833],"type":"Point"}
}