<<<<<<< HEAD
{
  "id": 2334524,
  "type": "Feature",
  "properties": {
    "tgn:hierarchy":[
        "tgn:2334524",
        "tgn:1000001",
        "tgn:7012149",
        "tgn:1002879",
        "tgn:7007252",
        "tgn:7029392"
    ],
    "tgn:id":2334524,
    "tgn:name":"Forest Run",
    "tgn:placetype":[
        "aat:300008699"
    ]
},
  "bbox": [],
  "geometry": {"coordinates":[-85.85,38.6333],"type":"Point"}
}
=======
{"geometry":{"type":"Point","coordinates":[-85.850000,38.633300]},"type":"Feature","properties":{"hierarchy":["tgn:2334524","tgn:1000001","tgn:7012149","tgn:1002879","tgn:7007252","tgn:7029392"],"placetype":["aat:300008699"],"id":2334524,"name:xx":"Forest Run"}}
>>>>>>> 03f74aca74312dbeaf24d7e61306dd6a786dc3d0
