{
  "id": 2528059,
  "type": "Feature",
  "properties": {
    "tgn:hierarchy":[
        "tgn:2528059",
        "tgn:1000001",
        "tgn:7012149",
        "tgn:2002126",
        "tgn:7007827",
        "tgn:7029392"
    ],
    "tgn:id":2528059,
    "tgn:name":"Mountain Spa",
    "tgn:placetype":[
        "aat:300008347"
    ]
},
  "bbox": [],
  "geometry": {"coordinates":[-111.4667,40.5167],"type":"Point"}
}