<<<<<<< HEAD
{
  "id": 2151475,
  "type": "Feature",
  "properties": {
    "tgn:hierarchy":[
        "tgn:2151475",
        "tgn:2002138",
        "tgn:1000001",
        "tgn:7012149",
        "tgn:7007919",
        "tgn:7029392"
    ],
    "tgn:id":2151475,
    "tgn:name":"Batick Mountain",
    "tgn:placetype":[
        "aat:300008798"
    ]
},
  "bbox": [],
  "geometry": {"coordinates":[-80.2,37.7833],"type":"Point"}
}
=======
{"geometry":{"type":"Point","coordinates":[-80.200000,37.783300]},"type":"Feature","properties":{"hierarchy":["tgn:2151475","tgn:2002138","tgn:1000001","tgn:7012149","tgn:7007919","tgn:7029392"],"placetype":["aat:300008798"],"id":2151475,"name:xx":"Batick Mountain"}}
>>>>>>> 03f74aca74312dbeaf24d7e61306dd6a786dc3d0
