{
  "id": 7529631,
  "type": "Feature",
  "properties": {
    "tgn:hierarchy":[
        "tgn:7529631",
        "tgn:7001242",
        "tgn:7016833",
        "tgn:1001091",
        "tgn:7029392"
    ],
    "tgn:id":7529631,
    "tgn:name":"Masjid al Mu\u015f\u0163af\u00e1",
    "tgn:placetype":[
        "aat:300007544"
    ]
},
  "bbox": [],
  "geometry": {"coordinates":[31.31278,30.076937],"type":"Point"}
}