{
  "id": 2084949,
  "type": "Feature",
  "properties": {
    "tgn:hierarchy":[
        "tgn:2084949",
        "tgn:1000001",
        "tgn:7012149",
        "tgn:2001718",
        "tgn:7007708",
        "tgn:7029392"
    ],
    "tgn:id":2084949,
    "tgn:name":"Juntura",
    "tgn:placetype":[
        "aat:300008347"
    ]
},
  "bbox": [],
  "geometry": {"coordinates":[-118.0667,43.7333],"type":"Point"}
}