<<<<<<< HEAD
{
  "id": 2765965,
  "type": "Feature",
  "properties": {
    "tgn:hierarchy":[
        "tgn:2765965",
        "tgn:1000001",
        "tgn:7012149",
        "tgn:2000205",
        "tgn:7007158",
        "tgn:7029392"
    ],
    "tgn:id":2765965,
    "tgn:name":"White Hills",
    "tgn:placetype":[
        "aat:300008798"
    ]
},
  "bbox": [],
  "geometry": {"coordinates":[-105.4333,38.15],"type":"Point"}
}
=======
{"geometry":{"type":"Point","coordinates":[-105.433300,38.150000]},"type":"Feature","properties":{"hierarchy":["tgn:2765965","tgn:1000001","tgn:7012149","tgn:2000205","tgn:7007158","tgn:7029392"],"placetype":["aat:300008798"],"id":2765965,"name:xx":"White Hills"}}
>>>>>>> 03f74aca74312dbeaf24d7e61306dd6a786dc3d0
