{
  "id": 7438388,
  "type": "Feature",
  "properties": {
    "tgn:hierarchy":[
        "tgn:7438388",
        "tgn:1000001",
        "tgn:7005594",
        "tgn:7005560",
        "tgn:7029392"
    ],
    "tgn:id":7438388,
    "tgn:name":"Tierras Blancas",
    "tgn:placetype":[
        "aat:300008347"
    ]
},
  "bbox": [],
  "geometry": {"coordinates":[-98.583333,21.966667],"type":"Point"}
}