<<<<<<< HEAD
{
  "id": 7057616,
  "type": "Feature",
  "properties": {
    "tgn:hierarchy":[
        "tgn:7057616",
        "tgn:1003432",
        "tgn:1000003",
        "tgn:7003240",
        "tgn:1000080",
        "tgn:7029392"
    ],
    "tgn:id":7057616,
    "tgn:name":"Ascensione, Monte dell'",
    "tgn:placetype":[
        "aat:300008795"
    ]
},
  "bbox": [],
  "geometry": {"coordinates":[13.55,42.916667],"type":"Point"}
}
=======
{"geometry":{"type":"Point","coordinates":[13.550000,42.916667]},"type":"Feature","properties":{"hierarchy":["tgn:7057616","tgn:1003432","tgn:1000003","tgn:7003240","tgn:1000080","tgn:7029392"],"placetype":["aat:300008795"],"id":7057616,"name:xx":"Ascensione, Monte dell'"}}
>>>>>>> 03f74aca74312dbeaf24d7e61306dd6a786dc3d0
