{
  "id": 7396700,
  "type": "Feature",
  "properties": {
    "tgn:hierarchy":[
        "tgn:7396700",
        "tgn:1000001",
        "tgn:7005589",
        "tgn:7005560",
        "tgn:7029392"
    ],
    "tgn:id":7396700,
    "tgn:name":"Santa Domingo",
    "tgn:placetype":[
        "aat:300008347"
    ]
},
  "bbox": [],
  "geometry": {"coordinates":[-99.683333,26.633333],"type":"Point"}
}