{
  "id": 2784155,
  "type": "Feature",
  "properties": {
    "tgn:hierarchy":[
        "tgn:2784155",
        "tgn:1000001",
        "tgn:7012149",
        "tgn:2001714",
        "tgn:7007708",
        "tgn:7029392"
    ],
    "tgn:id":2784155,
    "tgn:name":"Yamsay Spring",
    "tgn:placetype":[
        "aat:300008697"
    ]
},
  "bbox": [],
  "geometry": {"coordinates":[-121.4167,42.7167],"type":"Point"}
}