{
  "id": 2715585,
  "type": "Feature",
  "properties": {
    "tgn:hierarchy":[
        "tgn:2715585",
        "tgn:1000001",
        "tgn:2000315",
        "tgn:7012149",
        "tgn:7007248",
        "tgn:7029392"
    ],
    "tgn:id":2715585,
    "tgn:name":"Territory Prairie",
    "tgn:placetype":[
        "aat:300008905"
    ]
},
  "bbox": [],
  "geometry": {"coordinates":[-82.1833,30.85],"type":"Point"}
}