{
  "id": 2757582,
  "type": "Feature",
  "properties": {
    "tgn:hierarchy":[
        "tgn:2757582",
        "tgn:1000001",
        "tgn:7012149",
        "tgn:7007710",
        "tgn:7029392"
    ],
    "tgn:id":2757582,
    "tgn:name":"West Branch Big Run",
    "tgn:placetype":[
        "aat:300008699"
    ]
},
  "bbox": [],
  "geometry": {"coordinates":[-77.8333,41.1833],"type":"Point"}
}