{
  "id": 7491822,
  "type": "Feature",
  "properties": {
    "tgn:hierarchy":[
        "tgn:7491822",
        "tgn:1000004",
        "tgn:1000959",
        "tgn:1000141",
        "tgn:7029392"
    ],
    "tgn:id":7491822,
    "tgn:name":"Dalunjiao",
    "tgn:placetype":[
        "aat:300008347"
    ]
},
  "bbox": [],
  "geometry": {"coordinates":[121.614474,24.993337],"type":"Point"}
}