{
  "id": 2288061,
  "type": "Feature",
  "properties": {
    "tgn:hierarchy":[
        "tgn:2288061",
        "tgn:1000001",
        "tgn:7006451",
        "tgn:2000093",
        "tgn:7012149",
        "tgn:7029392"
    ],
    "tgn:id":2288061,
    "tgn:name":"Dinner Creek",
    "tgn:placetype":[
        "aat:300008706"
    ]
},
  "bbox": [],
  "geometry": {"coordinates":[-110.95,33.9833],"type":"Point"}
}