{
  "id": 2450843,
  "type": "Feature",
  "properties": {
    "tgn:hierarchy":[
        "tgn:2450843",
        "tgn:1000001",
        "tgn:7012149",
        "tgn:2001440",
        "tgn:7007566",
        "tgn:7029392"
    ],
    "tgn:id":2450843,
    "tgn:name":"Lisbon",
    "tgn:placetype":[
        "aat:300008347"
    ]
},
  "bbox": [],
  "geometry": {"coordinates":[-108.5333,32.2667],"type":"Point"}
}