<<<<<<< HEAD
{
  "id": 2409330,
  "type": "Feature",
  "properties": {
    "tgn:hierarchy":[
        "tgn:2409330",
        "tgn:1000001",
        "tgn:7012149",
        "tgn:2001027",
        "tgn:7007521",
        "tgn:7029392"
    ],
    "tgn:id":2409330,
    "tgn:name":"Ida Lake",
    "tgn:placetype":[
        "aat:300008680"
    ]
},
  "bbox": [],
  "geometry": {"coordinates":[-94.95,46.9667],"type":"Point"}
}
=======
{"geometry":{"type":"Point","coordinates":[-94.950000,46.966700]},"type":"Feature","properties":{"hierarchy":["tgn:2409330","tgn:1000001","tgn:7012149","tgn:2001027","tgn:7007521","tgn:7029392"],"placetype":["aat:300008680"],"id":2409330,"name:xx":"Ida Lake"}}
>>>>>>> 03f74aca74312dbeaf24d7e61306dd6a786dc3d0
