{
  "id": 2000700,
  "type": "Feature",
  "properties": {
    "tgn:hierarchy":[
        "tgn:2000700",
        "tgn:1000001",
        "tgn:7012149",
        "tgn:7007254",
        "tgn:7029392"
    ],
    "tgn:id":2000700,
    "tgn:name":"Haskell",
    "tgn:placetype":[
        "aat:300387145",
        "aat:300000771"
    ]
},
  "bbox": [],
  "geometry": {"coordinates":[-100.8667,37.5667],"type":"Point"}
}