<<<<<<< HEAD
{
  "id": 7351607,
  "type": "Feature",
  "properties": {
    "tgn:hierarchy":[
        "tgn:7351607",
        "tgn:1000001",
        "tgn:7005596",
        "tgn:7005560",
        "tgn:7029392"
    ],
    "tgn:id":7351607,
    "tgn:name":"Arrastradero, Laguna de",
    "tgn:placetype":[
        "aat:300008679"
    ]
},
  "bbox": [],
  "geometry": {"coordinates":[-93.5,18.4],"type":"Point"}
}
=======
{"geometry":{"type":"Point","coordinates":[-93.500000,18.400000]},"type":"Feature","properties":{"hierarchy":["tgn:7351607","tgn:1000001","tgn:7005596","tgn:7005560","tgn:7029392"],"placetype":["aat:300008679"],"id":7351607,"name:xx":"Arrastradero, Laguna de"}}
>>>>>>> 03f74aca74312dbeaf24d7e61306dd6a786dc3d0
