{
  "id": 7549518,
  "type": "Feature",
  "properties": {
    "tgn:hierarchy":[
        "tgn:7549518",
        "tgn:1000004",
        "tgn:7000198",
        "tgn:1001895",
        "tgn:7029392"
    ],
    "tgn:id":7549518,
    "tgn:name:en":"Elephanta Spit",
    "tgn:placetype":[
        "aat:300386848"
    ]
},
  "bbox": [],
  "geometry": {"coordinates":[72.95,18.983333],"type":"Point"}
}