{
  "id": 7325267,
  "type": "Feature",
  "properties": {
    "tgn:hierarchy":[
        "tgn:7325267",
        "tgn:7002810",
        "tgn:7001158",
        "tgn:1000003",
        "tgn:1000095",
        "tgn:7029392"
    ],
    "tgn:id":7325267,
    "tgn:name":"San Mart\u00edn de Don",
    "tgn:placetype":[
        "aat:300008347"
    ]
},
  "bbox": [],
  "geometry": {"coordinates":[-3.166667,42.766667],"type":"Point"}
}