<<<<<<< HEAD
{
  "id": 7244417,
  "type": "Feature",
  "properties": {
    "tgn:hierarchy":[
        "tgn:7244417",
        "tgn:7003456",
        "tgn:1000003",
        "tgn:1000063",
        "tgn:7018236",
        "tgn:7029392"
    ],
    "tgn:id":7244417,
    "tgn:name":"Kruisstraat",
    "tgn:placetype":[
        "aat:300008347"
    ]
},
  "bbox": [],
  "geometry": {"coordinates":[4.666667,51.4],"type":"Point"}
}
=======
{"geometry":{"type":"Point","coordinates":[4.666667,51.400000]},"type":"Feature","properties":{"hierarchy":["tgn:7244417","tgn:7003456","tgn:1000003","tgn:1000063","tgn:7018236","tgn:7029392"],"placetype":["aat:300008347"],"id":7244417,"name:xx":"Kruisstraat"}}
>>>>>>> 03f74aca74312dbeaf24d7e61306dd6a786dc3d0
