{
  "id": 2298712,
  "type": "Feature",
  "properties": {
    "tgn:hierarchy":[
        "tgn:2298712",
        "tgn:1000001",
        "tgn:7006451",
        "tgn:7012149",
        "tgn:7029392"
    ],
    "tgn:id":2298712,
    "tgn:name":"Dry Wash",
    "tgn:placetype":[
        "aat:300008699"
    ]
},
  "bbox": [],
  "geometry": {"coordinates":[-111.65,34.15],"type":"Point"}
}