{
  "id": 7561810,
  "type": "Feature",
  "properties": {
    "tgn:hierarchy":[
        "tgn:7561810",
        "tgn:1000004",
        "tgn:7000198",
        "tgn:7016722",
        "tgn:7029392"
    ],
    "tgn:id":7561810,
    "tgn:name:en":"Husainpur",
    "tgn:placetype":[
        "aat:300008347"
    ]
},
  "bbox": [],
  "geometry": {"coordinates":[79.288821,27.094423],"type":"Point"}
}