{
  "id": 2724931,
  "type": "Feature",
  "properties": {
    "tgn:hierarchy":[
        "tgn:2724931",
        "tgn:1000001",
        "tgn:7012149",
        "tgn:2000789",
        "tgn:7007255",
        "tgn:7029392"
    ],
    "tgn:id":2724931,
    "tgn:name":"Toms Creek",
    "tgn:placetype":[
        "aat:300008706"
    ]
},
  "bbox": [],
  "geometry": {"coordinates":[-82.6167,37.5833],"type":"Point"}
}