{
  "id": 2229918,
  "type": "Feature",
  "properties": {
    "tgn:hierarchy":[
        "tgn:2229918",
        "tgn:1000001",
        "tgn:7012149",
        "tgn:2001394",
        "tgn:7007525",
        "tgn:7029392"
    ],
    "tgn:id":2229918,
    "tgn:name":"Cedar Valley",
    "tgn:placetype":[
        "aat:300008761"
    ]
},
  "bbox": [],
  "geometry": {"coordinates":[-103.75,41.7833],"type":"Point"}
}