{
  "id": 2489719,
  "type": "Feature",
  "properties": {
    "tgn:hierarchy":[
        "tgn:2489719",
        "tgn:1000001",
        "tgn:2002243",
        "tgn:7012149",
        "tgn:7007920",
        "tgn:7029392"
    ],
    "tgn:id":2489719,
    "tgn:name":"Malo Lake",
    "tgn:placetype":[
        "aat:300008680"
    ]
},
  "bbox": [],
  "geometry": {"coordinates":[-118.6167,48.7667],"type":"Point"}
}