{
  "id": 1065367,
  "type": "Feature",
  "properties": {
    "tgn:hierarchy":[
        "tgn:1065367",
        "tgn:7016612",
        "tgn:1000004",
        "tgn:1001515",
        "tgn:7029392"
    ],
    "tgn:id":1065367,
    "tgn:name":"Samang\u0101n",
    "tgn:placetype":[
        "aat:300008347",
        "aat:300387223",
        "aat:300008375"
    ]
},
  "bbox": [],
  "geometry": {"coordinates":[68.0167,36.2667],"type":"Point"}
}