{
  "id": 2154065,
  "type": "Feature",
  "properties": {
    "tgn:hierarchy":[
        "tgn:2154065",
        "tgn:1000001",
        "tgn:7012149",
        "tgn:7007240",
        "tgn:7029392"
    ],
    "tgn:id":2154065,
    "tgn:name":"Bear Creek",
    "tgn:placetype":[
        "aat:300008706"
    ]
},
  "bbox": [],
  "geometry": {"coordinates":[-85.45,30.4667],"type":"Point"}
}