{
  "id": 1082799,
  "type": "Feature",
  "properties": {
    "tgn:hierarchy":[
        "tgn:1082799",
        "tgn:7018970",
        "tgn:7000316",
        "tgn:1000004",
        "tgn:1000128",
        "tgn:7029392"
    ],
    "tgn:id":1082799,
    "tgn:name":"Klagan",
    "tgn:placetype":[
        "aat:300008347"
    ]
},
  "bbox": [],
  "geometry": {"coordinates":[117.4667,5.9667],"type":"Point"}
}