{
  "id": 2693877,
  "type": "Feature",
  "properties": {
    "tgn:hierarchy":[
        "tgn:2693877",
        "tgn:1000001",
        "tgn:2001413",
        "tgn:7012149",
        "tgn:7007526",
        "tgn:7029392"
    ],
    "tgn:id":2693877,
    "tgn:name":"Sterling Tunnel",
    "tgn:placetype":[
        "aat:300000390"
    ]
},
  "bbox": [],
  "geometry": {"coordinates":[-115.9833,39.4667],"type":"Point"}
}