{
  "id": 2582184,
  "type": "Feature",
  "properties": {
    "tgn:hierarchy":[
        "tgn:2582184",
        "tgn:1000001",
        "tgn:7012149",
        "tgn:2001275",
        "tgn:7007524",
        "tgn:7029392"
    ],
    "tgn:id":2582184,
    "tgn:name":"Pine Creek",
    "tgn:placetype":[
        "aat:300008706"
    ]
},
  "bbox": [],
  "geometry": {"coordinates":[-110.9167,45.7667],"type":"Point"}
}