{
  "id": 2726890,
  "type": "Feature",
  "properties": {
    "tgn:hierarchy":[
        "tgn:2726890",
        "tgn:1000001",
        "tgn:7012149",
        "tgn:2001864",
        "tgn:7007825",
        "tgn:7029392"
    ],
    "tgn:id":2726890,
    "tgn:name":"Townsend Branch",
    "tgn:placetype":[
        "aat:300008699"
    ]
},
  "bbox": [],
  "geometry": {"coordinates":[-87.0167,35.0833],"type":"Point"}
}