{
  "id": 1102652,
  "type": "Feature",
  "properties": {
    "tgn:hierarchy":[
        "tgn:1102652",
        "tgn:1000001",
        "tgn:1002359",
        "tgn:7012149",
        "tgn:7007517",
        "tgn:7029392"
    ],
    "tgn:id":1102652,
    "tgn:name":"Georgetown Rowley State Forest",
    "tgn:placetype":[
        "aat:300386976"
    ]
},
  "bbox": [],
  "geometry": {"coordinates":[-70.9667,42.6833],"type":"Point"}
}