{
  "id": 7051599,
  "type": "Feature",
  "properties": {
    "tgn:hierarchy":[
        "tgn:7051599",
        "tgn:7005126",
        "tgn:1000003",
        "tgn:7003120",
        "tgn:1000080",
        "tgn:7029392"
    ],
    "tgn:id":7051599,
    "tgn:name":"Murazzo",
    "tgn:placetype":[
        "aat:300008347"
    ]
},
  "bbox": [],
  "geometry": {"coordinates":[7.65,44.483333],"type":"Point"}
}