{
  "id": 1027909,
  "type": "Feature",
  "properties": {
    "tgn:hierarchy":[
        "tgn:1027909",
        "tgn:7594006",
        "tgn:1000003",
        "tgn:1000066",
        "tgn:7029392"
    ],
    "tgn:id":1027909,
    "tgn:name":"Hoed",
    "tgn:placetype":[
        "aat:300008347"
    ]
},
  "bbox": [],
  "geometry": {"coordinates":[10.8167,56.3167],"type":"Point"}
}