{
  "id": 2409545,
  "type": "Feature",
  "properties": {
    "tgn:hierarchy":[
        "tgn:2409545",
        "tgn:1000001",
        "tgn:7012149",
        "tgn:2001709",
        "tgn:7007708",
        "tgn:7029392"
    ],
    "tgn:id":2409545,
    "tgn:name":"Idol City Mines",
    "tgn:placetype":[
        "aat:300000390"
    ]
},
  "bbox": [],
  "geometry": {"coordinates":[-118.8833,43.7667],"type":"Point"}
}