{
  "id": 4006563,
  "type": "Feature",
  "properties": {
    "tgn:hierarchy":[
        "tgn:4006563",
        "tgn:1000003",
        "tgn:7003677",
        "tgn:7000084",
        "tgn:7029392"
    ],
    "tgn:id":4006563,
    "tgn:name":"Loope",
    "tgn:placetype":[
        "aat:300008347"
    ]
},
  "bbox": [],
  "geometry": {"coordinates":[7.366667,50.966667],"type":"Point"}
}