{
  "id": 7336544,
  "type": "Feature",
  "properties": {
    "tgn:hierarchy":[
        "tgn:7336544",
        "tgn:7002759",
        "tgn:7008909",
        "tgn:1000003",
        "tgn:1000095",
        "tgn:7029392"
    ],
    "tgn:id":7336544,
    "tgn:name":"Fonz",
    "tgn:placetype":[
        "aat:300008347"
    ]
},
  "bbox": [],
  "geometry": {"coordinates":[0.257715,42.010404],"type":"Point"}
}