{
  "id": 2512101,
  "type": "Feature",
  "properties": {
    "tgn:hierarchy":[
        "tgn:2512101",
        "tgn:2001090",
        "tgn:1000001",
        "tgn:7012149",
        "tgn:7007522",
        "tgn:7029392"
    ],
    "tgn:id":2512101,
    "tgn:name":"Mill Branch",
    "tgn:placetype":[
        "aat:300008699"
    ]
},
  "bbox": [],
  "geometry": {"coordinates":[-89.0333,34.95],"type":"Point"}
}