{
  "id": 7562464,
  "type": "Feature",
  "properties": {
    "tgn:hierarchy":[
        "tgn:7562464",
        "tgn:1000004",
        "tgn:7000198",
        "tgn:7016722",
        "tgn:7029392"
    ],
    "tgn:id":7562464,
    "tgn:name:en":"Nawal Purwa",
    "tgn:placetype":[
        "aat:300008347"
    ]
},
  "bbox": [],
  "geometry": {"coordinates":[79.8022,27.1463],"type":"Point"}
}