{
  "id": 1049730,
  "type": "Feature",
  "properties": {
    "tgn:hierarchy":[
        "tgn:1049730",
        "tgn:1000882",
        "tgn:1000003",
        "tgn:1000090",
        "tgn:7029392"
    ],
    "tgn:id":1049730,
    "tgn:name":"Cane\u00e7as",
    "tgn:placetype":[
        "aat:300008347"
    ]
},
  "bbox": [],
  "geometry": {"coordinates":[-9.226,38.813],"type":"Point"}
}