{
  "id": 7579035,
  "type": "Feature",
  "properties": {
    "tgn:hierarchy":[
        "tgn:7579035",
        "tgn:1000004",
        "tgn:7000198",
        "tgn:1001895",
        "tgn:7029392"
    ],
    "tgn:id":7579035,
    "tgn:name:en":"W\u0101n River",
    "tgn:placetype":[
        "aat:300008699"
    ]
},
  "bbox": [],
  "geometry": {"coordinates":[76.45,19.066667],"type":"Point"}
}