{
  "id": 2180366,
  "type": "Feature",
  "properties": {
    "tgn:hierarchy":[
        "tgn:2180366",
        "tgn:1000001",
        "tgn:7006451",
        "tgn:7012149",
        "tgn:2000103",
        "tgn:7029392"
    ],
    "tgn:id":2180366,
    "tgn:name":"Blodgett Basin",
    "tgn:placetype":[
        "aat:300386845"
    ]
},
  "bbox": [],
  "geometry": {"coordinates":[-111.65,34.55],"type":"Point"}
}