{
  "id": 2357759,
  "type": "Feature",
  "properties": {
    "tgn:hierarchy":[
        "tgn:2357759",
        "tgn:1000001",
        "tgn:7012149",
        "tgn:2001056",
        "tgn:7007521",
        "tgn:7029392"
    ],
    "tgn:id":2357759,
    "tgn:name":"Graces Lake",
    "tgn:placetype":[
        "aat:300008680"
    ]
},
  "bbox": [],
  "geometry": {"coordinates":[-92.4333,46.0667],"type":"Point"}
}