{
  "id": 2129857,
  "type": "Feature",
  "properties": {
    "tgn:hierarchy":[
        "tgn:2129857",
        "tgn:1000001",
        "tgn:7012149",
        "tgn:1002592",
        "tgn:7007523",
        "tgn:7029392"
    ],
    "tgn:id":2129857,
    "tgn:name":"Allen Branch",
    "tgn:placetype":[
        "aat:300008699"
    ]
},
  "bbox": [],
  "geometry": {"coordinates":[-91.8833,39.9833],"type":"Point"}
}