{
  "id": 2683397,
  "type": "Feature",
  "properties": {
    "tgn:hierarchy":[
        "tgn:2683397",
        "tgn:1000001",
        "tgn:7012149",
        "tgn:2001202",
        "tgn:7007523",
        "tgn:7029392"
    ],
    "tgn:id":2683397,
    "tgn:name":"Sparrow Creek",
    "tgn:placetype":[
        "aat:300008706"
    ]
},
  "bbox": [],
  "geometry": {"coordinates":[-93.6167,38.3167],"type":"Point"}
}