{
  "id": 7296468,
  "type": "Feature",
  "properties": {
    "tgn:hierarchy":[
        "tgn:7296468",
        "tgn:7002824",
        "tgn:1000003",
        "tgn:7002786",
        "tgn:1000095",
        "tgn:7029392"
    ],
    "tgn:id":7296468,
    "tgn:name":"Ares, Punta de",
    "tgn:placetype":[
        "aat:300386846"
    ]
},
  "bbox": [],
  "geometry": {"coordinates":[-8.241667,43.42],"type":"Point"}
}