{
  "id": 2681145,
  "type": "Feature",
  "properties": {
    "tgn:hierarchy":[
        "tgn:2681145",
        "tgn:1000001",
        "tgn:1002328",
        "tgn:7012149",
        "tgn:7007568",
        "tgn:7029392"
    ],
    "tgn:id":2681145,
    "tgn:name":"South Mountain",
    "tgn:placetype":[
        "aat:300008798"
    ]
},
  "bbox": [],
  "geometry": {"coordinates":[-75.1333,42.1333],"type":"Point"}
}