{
  "id": 2540314,
  "type": "Feature",
  "properties": {
    "tgn:hierarchy":[
        "tgn:2540314",
        "tgn:1000001",
        "tgn:7012149",
        "tgn:2001538",
        "tgn:7007709",
        "tgn:7029392"
    ],
    "tgn:id":2540314,
    "tgn:name":"Newman Millpond",
    "tgn:placetype":[
        "aat:300006191"
    ]
},
  "bbox": [],
  "geometry": {"coordinates":[-78.45,35.15],"type":"Point"}
}