{
  "id": 7316469,
  "type": "Feature",
  "properties": {
    "tgn:hierarchy":[
        "tgn:7316469",
        "tgn:1001637",
        "tgn:1000049",
        "tgn:1000002",
        "tgn:7029392"
    ],
    "tgn:id":7316469,
    "tgn:name":"Carampangue, R\u00edo",
    "tgn:placetype":[
        "aat:300008699"
    ]
},
  "bbox": [],
  "geometry": {"coordinates":[-73.283333,-37.233333],"type":"Point"}
}