{
  "id": 7330328,
  "type": "Feature",
  "properties": {
    "tgn:hierarchy":[
        "tgn:7330328",
        "tgn:7002818",
        "tgn:1001647",
        "tgn:1000003",
        "tgn:1000095",
        "tgn:7029392"
    ],
    "tgn:id":7330328,
    "tgn:name":"Hombr\u00eda, Cerro de la",
    "tgn:placetype":[
        "aat:300008777"
    ]
},
  "bbox": [],
  "geometry": {"coordinates":[-2.466667,39.833333],"type":"Point"}
}