{
  "id": 1057807,
  "type": "Feature",
  "properties": {
    "tgn:hierarchy":[
        "tgn:1057807",
        "tgn:7011551",
        "tgn:1000004",
        "tgn:7018214",
        "tgn:7002435",
        "tgn:7029392"
    ],
    "tgn:id":1057807,
    "tgn:name":"Novozybkov",
    "tgn:placetype":[
        "aat:300008347"
    ]
},
  "bbox": [],
  "geometry": {"coordinates":[31.9667,52.5167],"type":"Point"}
}