{
  "id": 2781999,
  "type": "Feature",
  "properties": {
    "tgn:hierarchy":[
        "tgn:2781999",
        "tgn:1000001",
        "tgn:7012149",
        "tgn:2000879",
        "tgn:7007256",
        "tgn:7029392"
    ],
    "tgn:id":2781999,
    "tgn:name":"Woods Place Canal",
    "tgn:placetype":[
        "aat:300006075"
    ]
},
  "bbox": [],
  "geometry": {"coordinates":[-90.1167,29.8333],"type":"Point"}
}