{
  "id": 7555116,
  "type": "Feature",
  "properties": {
    "tgn:hierarchy":[
        "tgn:7555116",
        "tgn:1000004",
        "tgn:7000198",
        "tgn:1001977",
        "tgn:7029392"
    ],
    "tgn:id":7555116,
    "tgn:name:en":"Nalgora",
    "tgn:placetype":[
        "aat:300008347"
    ]
},
  "bbox": [],
  "geometry": {"coordinates":[88.465153,22.026662],"type":"Point"}
}