{
  "id": 7513781,
  "type": "Feature",
  "properties": {
    "tgn:hierarchy":[
        "tgn:7513781",
        "tgn:1009227",
        "tgn:1000226",
        "tgn:7018437",
        "tgn:1000006",
        "tgn:7029392"
    ],
    "tgn:id":7513781,
    "tgn:name:en":"Fleming River",
    "tgn:placetype":[
        "aat:300008699"
    ]
},
  "bbox": [],
  "geometry": {"coordinates":[169.416667,-46.583333],"type":"Point"}
}