{
  "id": 7014114,
  "type": "Feature",
  "properties": {
    "tgn:hierarchy":[
        "tgn:7014114",
        "tgn:1000001",
        "tgn:2001424",
        "tgn:7012149",
        "tgn:7007564",
        "tgn:7029392"
    ],
    "tgn:id":7014114,
    "tgn:name":"Enfield",
    "tgn:placetype":[
        "aat:300008347"
    ]
},
  "bbox": [],
  "geometry": {"coordinates":[-72.1333,43.6333],"type":"Point"}
}