{
  "id": 7112222,
  "type": "Feature",
  "properties": {
    "tgn:hierarchy":[
        "tgn:7112222",
        "tgn:1000003",
        "tgn:7003682",
        "tgn:7000084",
        "tgn:7029392"
    ],
    "tgn:id":7112222,
    "tgn:name":"Ro\u00dfbacher H\u00e4ubchen",
    "tgn:placetype":[
        "aat:300008777"
    ]
},
  "bbox": [],
  "geometry": {"coordinates":[7.416667,50.583333],"type":"Point"}
}