<<<<<<< HEAD
{
  "id": 7112222,
  "type": "Feature",
  "properties": {
    "tgn:hierarchy":[
        "tgn:7112222",
        "tgn:1000003",
        "tgn:7003682",
        "tgn:7000084",
        "tgn:7029392"
    ],
    "tgn:id":7112222,
    "tgn:name":"Ro\u00dfbacher H\u00e4ubchen",
    "tgn:placetype":[
        "aat:300008777"
    ]
},
  "bbox": [],
  "geometry": {"coordinates":[7.416667,50.583333],"type":"Point"}
}
=======
{"geometry":{"type":"Point","coordinates":[7.416667,50.583333]},"type":"Feature","properties":{"hierarchy":["tgn:7112222","tgn:1000003","tgn:7003682","tgn:7000084","tgn:7029392"],"placetype":["aat:300008777"],"id":7112222,"name:xx":"Ro\u00dfbacher H\u00e4ubchen"}}
>>>>>>> 03f74aca74312dbeaf24d7e61306dd6a786dc3d0
