{
  "id": 7086769,
  "type": "Feature",
  "properties": {
    "tgn:hierarchy":[
        "tgn:7086769",
        "tgn:7003669",
        "tgn:1000003",
        "tgn:7000084",
        "tgn:7029392"
    ],
    "tgn:id":7086769,
    "tgn:name":"Waldhof",
    "tgn:placetype":[
        "aat:300000206"
    ]
},
  "bbox": [],
  "geometry": {"coordinates":[12.616667,48.733333],"type":"Point"}
}