{
  "id": 2240843,
  "type": "Feature",
  "properties": {
    "tgn:hierarchy":[
        "tgn:2240843",
        "tgn:1000001",
        "tgn:7012149",
        "tgn:1002288",
        "tgn:7007523",
        "tgn:7029392"
    ],
    "tgn:id":2240843,
    "tgn:name":"Claradean, Lake",
    "tgn:placetype":[
        "aat:300006191"
    ]
},
  "bbox": [],
  "geometry": {"coordinates":[-92.2833,38.5667],"type":"Point"}
}