{
  "id": 7509287,
  "type": "Feature",
  "properties": {
    "tgn:hierarchy":[
        "tgn:7509287",
        "tgn:1009227",
        "tgn:1000226",
        "tgn:7520095",
        "tgn:1000006",
        "tgn:7029392"
    ],
    "tgn:id":7509287,
    "tgn:name:en":"Thorpe",
    "tgn:placetype":[
        "aat:300008347"
    ]
},
  "bbox": [],
  "geometry": {"coordinates":[172.866667,-41.283333],"type":"Point"}
}