<<<<<<< HEAD
{
  "id": 2339109,
  "type": "Feature",
  "properties": {
    "tgn:hierarchy":[
        "tgn:2339109",
        "tgn:1000001",
        "tgn:2000312",
        "tgn:7012149",
        "tgn:7007248",
        "tgn:7029392"
    ],
    "tgn:id":2339109,
    "tgn:name":"Franklins Pond",
    "tgn:placetype":[
        "aat:300006191"
    ]
},
  "bbox": [],
  "geometry": {"coordinates":[-81.9833,32.3667],"type":"Point"}
}
=======
{"geometry":{"type":"Point","coordinates":[-81.983300,32.366700]},"type":"Feature","properties":{"hierarchy":["tgn:2339109","tgn:1000001","tgn:2000312","tgn:7012149","tgn:7007248","tgn:7029392"],"placetype":["aat:300006191"],"id":2339109,"name:xx":"Franklins Pond"}}
>>>>>>> 03f74aca74312dbeaf24d7e61306dd6a786dc3d0
