{
  "id": 7410978,
  "type": "Feature",
  "properties": {
    "tgn:hierarchy":[
        "tgn:7410978",
        "tgn:1000001",
        "tgn:7005596",
        "tgn:7005560",
        "tgn:7029392"
    ],
    "tgn:id":7410978,
    "tgn:name:es":"Atascadero, Laguna",
    "tgn:placetype":[
        "aat:300008680"
    ]
},
  "bbox": [],
  "geometry": {"coordinates":[-91.916667,17.95],"type":"Point"}
}