{
  "id": 2013308,
  "type": "Feature",
  "properties": {
    "tgn:hierarchy":[
        "tgn:2013308",
        "tgn:1000001",
        "tgn:7012149",
        "tgn:7007157",
        "tgn:1002791",
        "tgn:7029392"
    ],
    "tgn:id":2013308,
    "tgn:name":"Penryn",
    "tgn:placetype":[
        "aat:300008347"
    ]
},
  "bbox": [],
  "geometry": {"coordinates":[-121.1667,38.85],"type":"Point"}
}