{
  "id": 7403665,
  "type": "Feature",
  "properties": {
    "tgn:hierarchy":[
        "tgn:7403665",
        "tgn:1000001",
        "tgn:1001906",
        "tgn:7005560",
        "tgn:7029392"
    ],
    "tgn:id":7403665,
    "tgn:name":"El Desmonte",
    "tgn:placetype":[
        "aat:300008347"
    ]
},
  "bbox": [],
  "geometry": {"coordinates":[-104.1875,21.7125],"type":"Point"}
}