{
  "id": 2198433,
  "type": "Feature",
  "properties": {
    "tgn:hierarchy":[
        "tgn:2198433",
        "tgn:7006450",
        "tgn:1000001",
        "tgn:7019674",
        "tgn:7012149",
        "tgn:7029392"
    ],
    "tgn:id":2198433,
    "tgn:name":"Browns Hill",
    "tgn:placetype":[
        "aat:300008798"
    ]
},
  "bbox": [],
  "geometry": {"coordinates":[-147.4667,64.8167],"type":"Point"}
}