<<<<<<< HEAD
{
  "id": 2335701,
  "type": "Feature",
  "properties": {
    "tgn:hierarchy":[
        "tgn:2335701",
        "tgn:1000001",
        "tgn:7012149",
        "tgn:2002175",
        "tgn:7007919",
        "tgn:7029392"
    ],
    "tgn:id":2335701,
    "tgn:name":"Fortunes Cove",
    "tgn:placetype":[
        "aat:300008761"
    ]
},
  "bbox": [],
  "geometry": {"coordinates":[-78.8833,37.7833],"type":"Point"}
}
=======
{"geometry":{"type":"Point","coordinates":[-78.883300,37.783300]},"type":"Feature","properties":{"hierarchy":["tgn:2335701","tgn:1000001","tgn:7012149","tgn:2002175","tgn:7007919","tgn:7029392"],"placetype":["aat:300008761"],"id":2335701,"name:xx":"Fortunes Cove"}}
>>>>>>> 03f74aca74312dbeaf24d7e61306dd6a786dc3d0
