{
  "id": 2277475,
  "type": "Feature",
  "properties": {
    "tgn:hierarchy":[
        "tgn:2277475",
        "tgn:1000001",
        "tgn:7012149",
        "tgn:1002881",
        "tgn:7007240",
        "tgn:7029392"
    ],
    "tgn:id":2277475,
    "tgn:name":"Davis Point",
    "tgn:placetype":[
        "aat:300008850"
    ]
},
  "bbox": [],
  "geometry": {"coordinates":[-81.1833,28.7333],"type":"Point"}
}