{
  "id": 7444964,
  "type": "Feature",
  "properties": {
    "tgn:hierarchy":[
        "tgn:7444964",
        "tgn:7002443",
        "tgn:7018977",
        "tgn:1000003",
        "tgn:7008591",
        "tgn:7029392"
    ],
    "tgn:id":7444964,
    "tgn:name:en":"Ogmore Forest",
    "tgn:placetype":[
        "aat:300008863"
    ]
},
  "bbox": [],
  "geometry": {"coordinates":[-3.519722,51.595],"type":"Point"}
}