{
  "id": 7277112,
  "type": "Feature",
  "properties": {
    "tgn:hierarchy":[
        "tgn:7277112",
        "tgn:1001708",
        "tgn:1000049",
        "tgn:1000002",
        "tgn:7029392"
    ],
    "tgn:id":7277112,
    "tgn:name":"Yerba Buena",
    "tgn:placetype":[
        "aat:300000206"
    ]
},
  "bbox": [],
  "geometry": {"coordinates":[-71.016667,-34.033333],"type":"Point"}
}