{
  "id": 7009888,
  "type": "Feature",
  "properties": {
    "tgn:hierarchy":[
        "tgn:7009888",
        "tgn:7024077",
        "tgn:1000003",
        "tgn:1000069",
        "tgn:7029392"
    ],
    "tgn:id":7009888,
    "tgn:name":"M\u00e4ntt\u00e4",
    "tgn:placetype":[
        "aat:300008347"
    ]
},
  "bbox": [],
  "geometry": {"coordinates":[24.6333,62.0333],"type":"Point"}
}