{
  "id": 7430072,
  "type": "Feature",
  "properties": {
    "tgn:hierarchy":[
        "tgn:7430072",
        "tgn:1001853",
        "tgn:1000001",
        "tgn:7005560",
        "tgn:7029392"
    ],
    "tgn:id":7430072,
    "tgn:name":"Ca\u00f1\u00f3n de las Vacas",
    "tgn:placetype":[
        "aat:300008347"
    ]
},
  "bbox": [],
  "geometry": {"coordinates":[-101.55,26.683333],"type":"Point"}
}