{
  "id": 2661512,
  "type": "Feature",
  "properties": {
    "tgn:hierarchy":[
        "tgn:2661512",
        "tgn:1000001",
        "tgn:7012149",
        "tgn:7007568",
        "tgn:7029392"
    ],
    "tgn:id":2661512,
    "tgn:name":"Shovel Hollow",
    "tgn:placetype":[
        "aat:300008761"
    ]
},
  "bbox": [],
  "geometry": {"coordinates":[-77.7333,42.1833],"type":"Point"}
}