<<<<<<< HEAD
{
  "id": 7023419,
  "type": "Feature",
  "properties": {
    "tgn:hierarchy":[
        "tgn:7023419",
        "tgn:1000001",
        "tgn:7012149",
        "tgn:7007157",
        "tgn:7029392"
    ],
    "tgn:id":7023419,
    "tgn:name":"Mias Canyon",
    "tgn:placetype":[
        "aat:300008761"
    ]
},
  "bbox": [],
  "geometry": {"coordinates":[-116.9333,34.0],"type":"Point"}
}
=======
{"geometry":{"type":"Point","coordinates":[-116.933300,34.000000]},"type":"Feature","properties":{"hierarchy":["tgn:7023419","tgn:1000001","tgn:7012149","tgn:7007157","tgn:7029392"],"placetype":["aat:300008761"],"id":7023419,"name:xx":"Mias Canyon"}}
>>>>>>> 03f74aca74312dbeaf24d7e61306dd6a786dc3d0
