{
  "id": 7496220,
  "type": "Feature",
  "properties": {
    "tgn:hierarchy":[
        "tgn:7496220",
        "tgn:7487020",
        "tgn:1000004",
        "tgn:1000141",
        "tgn:7029392"
    ],
    "tgn:id":7496220,
    "tgn:name":"Dawokeng",
    "tgn:placetype":[
        "aat:300008699"
    ]
},
  "bbox": [],
  "geometry": {"coordinates":[120.866439,24.408706],"type":"Point"}
}