<<<<<<< HEAD
{
  "id": 2704673,
  "type": "Feature",
  "properties": {
    "tgn:hierarchy":[
        "tgn:2704673",
        "tgn:2002306",
        "tgn:1000001",
        "tgn:7012149",
        "tgn:7007922",
        "tgn:7029392"
    ],
    "tgn:id":2704673,
    "tgn:name":"Sunset Bay",
    "tgn:placetype":[
        "aat:300132316"
    ]
},
  "bbox": [],
  "geometry": {"coordinates":[-90.7167,46.8],"type":"Point"}
}
=======
{"geometry":{"type":"Point","coordinates":[-90.716700,46.800000]},"type":"Feature","properties":{"hierarchy":["tgn:2704673","tgn:2002306","tgn:1000001","tgn:7012149","tgn:7007922","tgn:7029392"],"placetype":["aat:300132316"],"id":2704673,"name:xx":"Sunset Bay"}}
>>>>>>> 03f74aca74312dbeaf24d7e61306dd6a786dc3d0
