{
  "id": 2187212,
  "type": "Feature",
  "properties": {
    "tgn:hierarchy":[
        "tgn:2187212",
        "tgn:1000001",
        "tgn:7012149",
        "tgn:2001714",
        "tgn:7007708",
        "tgn:7029392"
    ],
    "tgn:id":2187212,
    "tgn:name":"Book Spring",
    "tgn:placetype":[
        "aat:300008697"
    ]
},
  "bbox": [],
  "geometry": {"coordinates":[-120.95,42.6167],"type":"Point"}
}