{
  "id": 1031643,
  "type": "Feature",
  "properties": {
    "tgn:hierarchy":[
        "tgn:1031643",
        "tgn:1000003",
        "tgn:7002883",
        "tgn:1000070",
        "tgn:7029392"
    ],
    "tgn:id":1031643,
    "tgn:name":"Egreville",
    "tgn:placetype":[
        "aat:300008347"
    ]
},
  "bbox": [],
  "geometry": {"coordinates":[2.8833,48.1667],"type":"Point"}
}