{
  "id": 2688683,
  "type": "Feature",
  "properties": {
    "tgn:hierarchy":[
        "tgn:2688683",
        "tgn:1000001",
        "tgn:1002601",
        "tgn:7012149",
        "tgn:7007159",
        "tgn:7029392"
    ],
    "tgn:id":2688683,
    "tgn:name":"Spruce Swamp",
    "tgn:placetype":[
        "aat:300008905"
    ]
},
  "bbox": [],
  "geometry": {"coordinates":[-73.3333,41.7833],"type":"Point"}
}