{
  "id": 7342502,
  "type": "Feature",
  "properties": {
    "tgn:hierarchy":[
        "tgn:7342502",
        "tgn:7002824",
        "tgn:1000003",
        "tgn:7002786",
        "tgn:1000095",
        "tgn:7029392"
    ],
    "tgn:id":7342502,
    "tgn:name":"Calo",
    "tgn:placetype":[
        "aat:300008347"
    ]
},
  "bbox": [],
  "geometry": {"coordinates":[-9.133333,43.033333],"type":"Point"}
}