{
  "id": 2246438,
  "type": "Feature",
  "properties": {
    "tgn:hierarchy":[
        "tgn:2246438",
        "tgn:1000001",
        "tgn:7012149",
        "tgn:7014287",
        "tgn:7007568",
        "tgn:7029392"
    ],
    "tgn:id":2246438,
    "tgn:name":"Cobb Brook",
    "tgn:placetype":[
        "aat:300008699"
    ]
},
  "bbox": [],
  "geometry": {"coordinates":[-75.6833,43.4167],"type":"Point"}
}