{
  "id": 7289537,
  "type": "Feature",
  "properties": {
    "tgn:hierarchy":[
        "tgn:7289537",
        "tgn:1001630",
        "tgn:1000049",
        "tgn:1000002",
        "tgn:7029392"
    ],
    "tgn:id":7289537,
    "tgn:name":"In\u00e9s Chica",
    "tgn:placetype":[
        "aat:300008347"
    ]
},
  "bbox": [],
  "geometry": {"coordinates":[-69.366667,-26.15],"type":"Point"}
}