{
  "id": 2242095,
  "type": "Feature",
  "properties": {
    "tgn:hierarchy":[
        "tgn:2242095",
        "tgn:2002308",
        "tgn:1000001",
        "tgn:7012149",
        "tgn:7007922",
        "tgn:7029392"
    ],
    "tgn:id":2242095,
    "tgn:name":"Clay Lake",
    "tgn:placetype":[
        "aat:300008680"
    ]
},
  "bbox": [],
  "geometry": {"coordinates":[-91.2667,46.3833],"type":"Point"}
}