{
  "id": 2756661,
  "type": "Feature",
  "properties": {
    "tgn:hierarchy":[
        "tgn:2756661",
        "tgn:1000001",
        "tgn:7016172",
        "tgn:7012149",
        "tgn:7029392"
    ],
    "tgn:id":2756661,
    "tgn:name":"Wells Creek",
    "tgn:placetype":[
        "aat:300008706"
    ]
},
  "bbox": [],
  "geometry": {"coordinates":[-91.35,36.1833],"type":"Point"}
}