<<<<<<< HEAD
{
  "id": 2335402,
  "type": "Feature",
  "properties": {
    "tgn:hierarchy":[
        "tgn:2335402",
        "tgn:1000001",
        "tgn:7012149",
        "tgn:7022221",
        "tgn:7007919",
        "tgn:7029392"
    ],
    "tgn:id":2335402,
    "tgn:name":"Fort Milroy",
    "tgn:placetype":[
        "aat:300008347"
    ]
},
  "bbox": [],
  "geometry": {"coordinates":[-78.1667,39.1833],"type":"Point"}
}
=======
{"geometry":{"type":"Point","coordinates":[-78.166700,39.183300]},"type":"Feature","properties":{"hierarchy":["tgn:2335402","tgn:1000001","tgn:7012149","tgn:7022221","tgn:7007919","tgn:7029392"],"placetype":["aat:300008347"],"id":2335402,"name:xx":"Fort Milroy"}}
>>>>>>> 03f74aca74312dbeaf24d7e61306dd6a786dc3d0
