{
  "id": 7387604,
  "type": "Feature",
  "properties": {
    "tgn:hierarchy":[
        "tgn:7387604",
        "tgn:1000001",
        "tgn:7005591",
        "tgn:7005560",
        "tgn:7029392"
    ],
    "tgn:id":7387604,
    "tgn:name":"Portillo Yubiago",
    "tgn:placetype":[
        "aat:300008347"
    ]
},
  "bbox": [],
  "geometry": {"coordinates":[-96.216667,15.966667],"type":"Point"}
}