{
  "id": 2024773,
  "type": "Feature",
  "properties": {
    "tgn:hierarchy":[
        "tgn:2024773",
        "tgn:1000001",
        "tgn:7012149",
        "tgn:2000421",
        "tgn:7007248",
        "tgn:7029392"
    ],
    "tgn:id":2024773,
    "tgn:name":"Woodland",
    "tgn:placetype":[
        "aat:300008347"
    ]
},
  "bbox": [],
  "geometry": {"coordinates":[-84.55,32.7833],"type":"Point"}
}