{
  "id": 2476910,
  "type": "Feature",
  "properties": {
    "tgn:hierarchy":[
        "tgn:2476910",
        "tgn:2000090",
        "tgn:1000001",
        "tgn:7006451",
        "tgn:7012149",
        "tgn:7029392"
    ],
    "tgn:id":2476910,
    "tgn:name":"Lyman Lake",
    "tgn:placetype":[
        "aat:300006191"
    ]
},
  "bbox": [],
  "geometry": {"coordinates":[-109.35,34.35],"type":"Point"}
}