{
  "id": 1071235,
  "type": "Feature",
  "properties": {
    "tgn:hierarchy":[
        "tgn:1071235",
        "tgn:1000004",
        "tgn:7002087",
        "tgn:1000111",
        "tgn:7029392"
    ],
    "tgn:id":1071235,
    "tgn:name":"Rongbaca",
    "tgn:placetype":[
        "aat:300008347"
    ]
},
  "bbox": [],
  "geometry": {"coordinates":[99.65,31.6833],"type":"Point"}
}