{
  "id": 1075662,
  "type": "Feature",
  "properties": {
    "tgn:hierarchy":[
        "tgn:1075662",
        "tgn:1000004",
        "tgn:7000198",
        "tgn:1001977",
        "tgn:7029392"
    ],
    "tgn:id":1075662,
    "tgn:name:en":"K\u0101liy\u0101ganj",
    "tgn:placetype":[
        "aat:300008347"
    ]
},
  "bbox": [],
  "geometry": {"coordinates":[88.326646,25.634415],"type":"Point"}
}