{
  "id": 7513310,
  "type": "Feature",
  "properties": {
    "tgn:hierarchy":[
        "tgn:7513310",
        "tgn:1009227",
        "tgn:1000226",
        "tgn:7018437",
        "tgn:1000006",
        "tgn:7029392"
    ],
    "tgn:id":7513310,
    "tgn:name:en":"Gows Burn",
    "tgn:placetype":[
        "aat:300008699"
    ]
},
  "bbox": [],
  "geometry": {"coordinates":[168.95,-45.616667],"type":"Point"}
}