{
  "id": 1103686,
  "type": "Feature",
  "properties": {
    "tgn:hierarchy":[
        "tgn:1103686",
        "tgn:1000003",
        "tgn:1000070",
        "tgn:7002897",
        "tgn:7029392"
    ],
    "tgn:id":1103686,
    "tgn:name":"Albaron",
    "tgn:placetype":[
        "aat:300008795"
    ]
},
  "bbox": [],
  "geometry": {"coordinates":[7.1167,45.3333],"type":"Point"}
}