{
  "id": 1004143,
  "type": "Feature",
  "properties": {
    "tgn:hierarchy":[
        "tgn:1004143",
        "tgn:1001052",
        "tgn:1000004",
        "tgn:7002473",
        "tgn:7018450",
        "tgn:1000144",
        "tgn:7029392"
    ],
    "tgn:id":1004143,
    "tgn:name":"Bostanc\u0131",
    "tgn:placetype":[
        "aat:300000745"
    ]
},
  "bbox": [],
  "geometry": {"coordinates":[29.0833,40.95],"type":"Point"}
}