<<<<<<< HEAD
{
  "id": 2336692,
  "type": "Feature",
  "properties": {
    "tgn:hierarchy":[
        "tgn:2336692",
        "tgn:1000001",
        "tgn:7012149",
        "tgn:1002535",
        "tgn:7007826",
        "tgn:7029392"
    ],
    "tgn:id":2336692,
    "tgn:name":"Four Wire Lake",
    "tgn:placetype":[
        "aat:300008699"
    ]
},
  "bbox": [],
  "geometry": {"coordinates":[-96.4167,32.4167],"type":"Point"}
}
=======
{"geometry":{"type":"Point","coordinates":[-96.416700,32.416700]},"type":"Feature","properties":{"hierarchy":["tgn:2336692","tgn:1000001","tgn:7012149","tgn:1002535","tgn:7007826","tgn:7029392"],"placetype":["aat:300008699"],"id":2336692,"name:xx":"Four Wire Lake"}}
>>>>>>> 03f74aca74312dbeaf24d7e61306dd6a786dc3d0
