{
  "id": 2437977,
  "type": "Feature",
  "properties": {
    "tgn:hierarchy":[
        "tgn:2437977",
        "tgn:2002365",
        "tgn:1000001",
        "tgn:7012149",
        "tgn:7007923",
        "tgn:7029392"
    ],
    "tgn:id":2437977,
    "tgn:name":"King Mountain",
    "tgn:placetype":[
        "aat:300008798"
    ]
},
  "bbox": [],
  "geometry": {"coordinates":[-105.45,41.4667],"type":"Point"}
}