{
  "id": 7329183,
  "type": "Feature",
  "properties": {
    "tgn:hierarchy":[
        "tgn:7329183",
        "tgn:7002835",
        "tgn:7001158",
        "tgn:1000003",
        "tgn:1000095",
        "tgn:7029392"
    ],
    "tgn:id":7329183,
    "tgn:name":"Rebollosa",
    "tgn:placetype":[
        "aat:300008347"
    ]
},
  "bbox": [],
  "geometry": {"coordinates":[-6.083333,40.416667],"type":"Point"}
}