<<<<<<< HEAD
{
  "id": 7376540,
  "type": "Feature",
  "properties": {
    "tgn:hierarchy":[
        "tgn:7376540",
        "tgn:1000001",
        "tgn:1001960",
        "tgn:7005560",
        "tgn:7029392"
    ],
    "tgn:id":7376540,
    "tgn:name":"Rancho Las Lagunitas",
    "tgn:placetype":[
        "aat:300000241"
    ]
},
  "bbox": [],
  "geometry": {"coordinates":[-112.116667,31.3],"type":"Point"}
}
=======
{"geometry":{"type":"Point","coordinates":[-112.116667,31.300000]},"type":"Feature","properties":{"hierarchy":["tgn:7376540","tgn:1000001","tgn:1001960","tgn:7005560","tgn:7029392"],"placetype":["aat:300000241"],"id":7376540,"name:xx":"Rancho Las Lagunitas"}}
>>>>>>> 03f74aca74312dbeaf24d7e61306dd6a786dc3d0
