{
  "id": 2783182,
  "type": "Feature",
  "properties": {
    "tgn:hierarchy":[
        "tgn:2783182",
        "tgn:1000001",
        "tgn:7012149",
        "tgn:1002511",
        "tgn:7007919",
        "tgn:7029392"
    ],
    "tgn:id":2783182,
    "tgn:name":"Wright Island",
    "tgn:placetype":[
        "aat:300008791"
    ]
},
  "bbox": [],
  "geometry": {"coordinates":[-76.85,37.3167],"type":"Point"}
}