{
  "id": 7328252,
  "type": "Feature",
  "properties": {
    "tgn:hierarchy":[
        "tgn:7328252",
        "tgn:7002829",
        "tgn:1000003",
        "tgn:7002786",
        "tgn:1000095",
        "tgn:7029392"
    ],
    "tgn:id":7328252,
    "tgn:name":"Renche",
    "tgn:placetype":[
        "aat:300008347"
    ]
},
  "bbox": [],
  "geometry": {"coordinates":[-7.283333,42.733333],"type":"Point"}
}