{
  "id": 7396205,
  "type": "Feature",
  "properties": {
    "tgn:hierarchy":[
        "tgn:7396205",
        "tgn:7005586",
        "tgn:1000001",
        "tgn:7005560",
        "tgn:7029392"
    ],
    "tgn:id":7396205,
    "tgn:name":"San Antonio, Cerro",
    "tgn:placetype":[
        "aat:300008795"
    ]
},
  "bbox": [],
  "geometry": {"coordinates":[-102.666667,19.366667],"type":"Point"}
}