{
  "id": 1025798,
  "type": "Feature",
  "properties": {
    "tgn:hierarchy":[
        "tgn:1025798",
        "tgn:7003026",
        "tgn:1000003",
        "tgn:1000062",
        "tgn:7029392"
    ],
    "tgn:id":1025798,
    "tgn:name":"Lohnsburg",
    "tgn:placetype":[
        "aat:300008347"
    ]
},
  "bbox": [],
  "geometry": {"coordinates":[13.3833,48.1333],"type":"Point"}
}