<<<<<<< HEAD
{
  "id": 2330980,
  "type": "Feature",
  "properties": {
    "tgn:hierarchy":[
        "tgn:2330980",
        "tgn:1000001",
        "tgn:7012149",
        "tgn:2002084",
        "tgn:7007826",
        "tgn:7029392"
    ],
    "tgn:id":2330980,
    "tgn:name":"Flat Rock Creek",
    "tgn:placetype":[
        "aat:300008706"
    ]
},
  "bbox": [],
  "geometry": {"coordinates":[-99.3167,33.3],"type":"Point"}
}
=======
{"geometry":{"type":"Point","coordinates":[-99.316700,33.300000]},"type":"Feature","properties":{"hierarchy":["tgn:2330980","tgn:1000001","tgn:7012149","tgn:2002084","tgn:7007826","tgn:7029392"],"placetype":["aat:300008706"],"id":2330980,"name:xx":"Flat Rock Creek"}}
>>>>>>> 03f74aca74312dbeaf24d7e61306dd6a786dc3d0
