{
  "id": 7415784,
  "type": "Feature",
  "properties": {
    "tgn:hierarchy":[
        "tgn:7415784",
        "tgn:1000001",
        "tgn:7005591",
        "tgn:7005560",
        "tgn:7029392"
    ],
    "tgn:id":7415784,
    "tgn:name:es":"Zaragoza",
    "tgn:placetype":[
        "aat:300008347"
    ]
},
  "bbox": [],
  "geometry": {"coordinates":[-97.778333,16.671667],"type":"Point"}
}