{
  "id": 2484927,
  "type": "Feature",
  "properties": {
    "tgn:hierarchy":[
        "tgn:2484927",
        "tgn:1000001",
        "tgn:7012149",
        "tgn:7007157",
        "tgn:1002710",
        "tgn:7029392"
    ],
    "tgn:id":2484927,
    "tgn:name":"Lava Cap Mine",
    "tgn:placetype":[
        "aat:300000390"
    ]
},
  "bbox": [],
  "geometry": {"coordinates":[-120.9667,39.2167],"type":"Point"}
}