{
  "id": 2739716,
  "type": "Feature",
  "properties": {
    "tgn:hierarchy":[
        "tgn:2739716",
        "tgn:1000001",
        "tgn:7012149",
        "tgn:1002986",
        "tgn:7007568",
        "tgn:7029392"
    ],
    "tgn:id":2739716,
    "tgn:name":"Upper Dam Pond",
    "tgn:placetype":[
        "aat:300008680"
    ]
},
  "bbox": [],
  "geometry": {"coordinates":[-74.05,43.6667],"type":"Point"}
}