{
  "id": 7310953,
  "type": "Feature",
  "properties": {
    "tgn:hierarchy":[
        "tgn:7310953",
        "tgn:7016598",
        "tgn:1000049",
        "tgn:1000002",
        "tgn:7029392"
    ],
    "tgn:id":7310953,
    "tgn:name":"Monturaque",
    "tgn:placetype":[
        "aat:300008795"
    ]
},
  "bbox": [],
  "geometry": {"coordinates":[-68.533333,-24.216667],"type":"Point"}
}