{
  "id": 2699691,
  "type": "Feature",
  "properties": {
    "tgn:hierarchy":[
        "tgn:2699691",
        "tgn:1000001",
        "tgn:7012149",
        "tgn:1003038",
        "tgn:7007517",
        "tgn:7029392"
    ],
    "tgn:id":2699691,
    "tgn:name":"Stuart Pond",
    "tgn:placetype":[
        "aat:300006191"
    ]
},
  "bbox": [],
  "geometry": {"coordinates":[-71.8167,42.4667],"type":"Point"}
}