{
  "id": 7275138,
  "type": "Feature",
  "properties": {
    "tgn:hierarchy":[
        "tgn:7275138",
        "tgn:1001699",
        "tgn:1000049",
        "tgn:1000002",
        "tgn:7029392"
    ],
    "tgn:id":7275138,
    "tgn:name":"Villatasmo, R\u00edo",
    "tgn:placetype":[
        "aat:300008699"
    ]
},
  "bbox": [],
  "geometry": {"coordinates":[-73.866667,-42.466667],"type":"Point"}
}