{
  "id": 7563671,
  "type": "Feature",
  "properties": {
    "tgn:hierarchy":[
        "tgn:7563671",
        "tgn:1000004",
        "tgn:7000198",
        "tgn:1001894",
        "tgn:7029392"
    ],
    "tgn:id":7563671,
    "tgn:name:en":"Lareti",
    "tgn:placetype":[
        "aat:300008347"
    ]
},
  "bbox": [],
  "geometry": {"coordinates":[79.133069,24.020115],"type":"Point"}
}