{
  "id": 7094970,
  "type": "Feature",
  "properties": {
    "tgn:hierarchy":[
        "tgn:7094970",
        "tgn:7000096",
        "tgn:1000003",
        "tgn:7000084",
        "tgn:7029392"
    ],
    "tgn:id":7094970,
    "tgn:name":"Sch\u00f6nefeld",
    "tgn:placetype":[
        "aat:300008347"
    ]
},
  "bbox": [],
  "geometry": {"coordinates":[12.833333,51.983333],"type":"Point"}
}