{
  "id": 7065088,
  "type": "Feature",
  "properties": {
    "tgn:hierarchy":[
        "tgn:7065088",
        "tgn:7003669",
        "tgn:1000003",
        "tgn:7000084",
        "tgn:7029392"
    ],
    "tgn:id":7065088,
    "tgn:name":"Steinkopf",
    "tgn:placetype":[
        "aat:300008777"
    ]
},
  "bbox": [],
  "geometry": {"coordinates":[10.016667,50.483333],"type":"Point"}
}