{
  "id": 1075302,
  "type": "Feature",
  "properties": {
    "tgn:hierarchy":[
        "tgn:1075302",
        "tgn:1000004",
        "tgn:7000198",
        "tgn:7031786",
        "tgn:7029392"
    ],
    "tgn:id":1075302,
    "tgn:name:en":"Gangotri",
    "tgn:placetype":[
        "aat:300008347"
    ]
},
  "bbox": [],
  "geometry": {"coordinates":[78.943,30.995],"type":"Point"}
}