{
  "id": 2582449,
  "type": "Feature",
  "properties": {
    "tgn:hierarchy":[
        "tgn:2582449",
        "tgn:1000001",
        "tgn:7012149",
        "tgn:2001613",
        "tgn:7007706",
        "tgn:7029392"
    ],
    "tgn:id":2582449,
    "tgn:name":"Pine Grove",
    "tgn:placetype":[
        "aat:300008347"
    ]
},
  "bbox": [],
  "geometry": {"coordinates":[-82.55,39.5833],"type":"Point"}
}