<<<<<<< HEAD
{
  "id": 2766796,
  "type": "Feature",
  "properties": {
    "tgn:hierarchy":[
        "tgn:2766796",
        "tgn:1000001",
        "tgn:2001842",
        "tgn:7012149",
        "tgn:7007825",
        "tgn:7029392"
    ],
    "tgn:id":2766796,
    "tgn:name":"White Oak Valley",
    "tgn:placetype":[
        "aat:300008761"
    ]
},
  "bbox": [],
  "geometry": {"coordinates":[-84.9167,35.25],"type":"Point"}
}
=======
{"geometry":{"type":"Point","coordinates":[-84.916700,35.250000]},"type":"Feature","properties":{"hierarchy":["tgn:2766796","tgn:1000001","tgn:2001842","tgn:7012149","tgn:7007825","tgn:7029392"],"placetype":["aat:300008761"],"id":2766796,"name:xx":"White Oak Valley"}}
>>>>>>> 03f74aca74312dbeaf24d7e61306dd6a786dc3d0
