{
  "id": 2061700,
  "type": "Feature",
  "properties": {
    "tgn:hierarchy":[
        "tgn:2061700",
        "tgn:1000001",
        "tgn:2001261",
        "tgn:7012149",
        "tgn:7007524",
        "tgn:7029392"
    ],
    "tgn:id":2061700,
    "tgn:name":"Saint Xavier",
    "tgn:placetype":[
        "aat:300008347"
    ]
},
  "bbox": [],
  "geometry": {"coordinates":[-107.7167,45.45],"type":"Point"}
}