{
  "id": 7410902,
  "type": "Feature",
  "properties": {
    "tgn:hierarchy":[
        "tgn:7410902",
        "tgn:7005587",
        "tgn:1000001",
        "tgn:7005560",
        "tgn:7029392"
    ],
    "tgn:id":7410902,
    "tgn:name:es":"Puerto del Dexthi",
    "tgn:placetype":[
        "aat:300008347"
    ]
},
  "bbox": [],
  "geometry": {"coordinates":[-99.258333,20.566667],"type":"Point"}
}