{
  "id": 1081266,
  "type": "Feature",
  "properties": {
    "tgn:hierarchy":[
        "tgn:1081266",
        "tgn:7000895",
        "tgn:1000004",
        "tgn:1000977",
        "tgn:1000120",
        "tgn:7029392"
    ],
    "tgn:id":1081266,
    "tgn:name":"Sh\u014dkawa",
    "tgn:placetype":[
        "aat:300008347"
    ]
},
  "bbox": [],
  "geometry": {"coordinates":[136.95,36.0333],"type":"Point"}
}