{
  "id": 7269091,
  "type": "Feature",
  "properties": {
    "tgn:concordances":{
        "gn:id":"2749781"
    },
    "tgn:hierarchy":[
        "tgn:7269091",
        "tgn:7003619",
        "tgn:1000003",
        "tgn:7016845",
        "tgn:7029392"
    ],
    "tgn:id":7269091,
    "tgn:name:nl":"Nude",
    "tgn:placetype":[
        "aat:300008347"
    ]
},
  "bbox": [],
  "geometry": {"coordinates":[5.633333,51.966667],"type":"Point"}
}