<<<<<<< HEAD
{
  "id": 7054973,
  "type": "Feature",
  "properties": {
    "tgn:hierarchy":[
        "tgn:7054973",
        "tgn:1000003",
        "tgn:7003152",
        "tgn:7003237",
        "tgn:1000080",
        "tgn:7029392"
    ],
    "tgn:id":7054973,
    "tgn:name":"Livo",
    "tgn:placetype":[
        "aat:300008347"
    ]
},
  "bbox": [],
  "geometry": {"coordinates":[9.3,46.166667],"type":"Point"}
}
=======
{"geometry":{"type":"Point","coordinates":[9.300000,46.166667]},"type":"Feature","properties":{"hierarchy":["tgn:7054973","tgn:1000003","tgn:7003152","tgn:7003237","tgn:1000080","tgn:7029392"],"placetype":["aat:300008347"],"id":7054973,"name:xx":"Livo"}}
>>>>>>> 03f74aca74312dbeaf24d7e61306dd6a786dc3d0
