{
  "id": 7584502,
  "type": "Feature",
  "properties": {
    "tgn:hierarchy":[
        "tgn:7584502",
        "tgn:1000004",
        "tgn:7000198",
        "tgn:7016883",
        "tgn:7029392"
    ],
    "tgn:id":7584502,
    "tgn:name:en":"Rohar J\u0101g\u012br",
    "tgn:placetype":[
        "aat:300008347"
    ]
},
  "bbox": [],
  "geometry": {"coordinates":[76.528408,30.118598],"type":"Point"}
}