{
  "id": 1084458,
  "type": "Feature",
  "properties": {
    "tgn:hierarchy":[
        "tgn:1084458",
        "tgn:1000004",
        "tgn:1001174",
        "tgn:1000135",
        "tgn:7029392"
    ],
    "tgn:id":1084458,
    "tgn:name":"Mercedes",
    "tgn:placetype":[
        "aat:300008347"
    ]
},
  "bbox": [],
  "geometry": {"coordinates":[123.0167,14.1167],"type":"Point"}
}