{
  "id": 7167038,
  "type": "Feature",
  "properties": {
    "tgn:hierarchy":[
        "tgn:7167038",
        "tgn:7000096",
        "tgn:1000003",
        "tgn:7000084",
        "tgn:7029392"
    ],
    "tgn:id":7167038,
    "tgn:name":"Heinrichsdorf",
    "tgn:placetype":[
        "aat:300008347"
    ]
},
  "bbox": [],
  "geometry": {"coordinates":[14.233333,52.733333],"type":"Point"}
}