{
  "id": 7483741,
  "type": "Feature",
  "properties": {
    "tgn:hierarchy":[
        "tgn:7483741",
        "tgn:1000004",
        "tgn:7490934",
        "tgn:1000141",
        "tgn:7029392"
    ],
    "tgn:id":7483741,
    "tgn:name":"Dongyuan Guozhong",
    "tgn:placetype":[
        "aat:300006495"
    ]
},
  "bbox": [],
  "geometry": {"coordinates":[120.451944,23.272222],"type":"Point"}
}