{
  "id": 7362965,
  "type": "Feature",
  "properties": {
    "tgn:hierarchy":[
        "tgn:7362965",
        "tgn:1000001",
        "tgn:7005595",
        "tgn:7005560",
        "tgn:7029392"
    ],
    "tgn:id":7362965,
    "tgn:name":"El Alvaco",
    "tgn:placetype":[
        "aat:300008347"
    ]
},
  "bbox": [],
  "geometry": {"coordinates":[-107.406389,24.570833],"type":"Point"}
}