{
  "id": 2567797,
  "type": "Feature",
  "properties": {
    "tgn:hierarchy":[
        "tgn:2567797",
        "tgn:1000001",
        "tgn:7012149",
        "tgn:2000926",
        "tgn:7007515",
        "tgn:7029392"
    ],
    "tgn:id":2567797,
    "tgn:name":"Paradise Hill",
    "tgn:placetype":[
        "aat:300008798"
    ]
},
  "bbox": [],
  "geometry": {"coordinates":[-70.7667,44.3833],"type":"Point"}
}