{
  "id": 2623169,
  "type": "Feature",
  "properties": {
    "tgn:hierarchy":[
        "tgn:2623169",
        "tgn:1000001",
        "tgn:2001419",
        "tgn:7012149",
        "tgn:7007526",
        "tgn:7029392"
    ],
    "tgn:id":2623169,
    "tgn:name":"Rochester Weaver Mining Company Mines",
    "tgn:placetype":[
        "aat:300000390"
    ]
},
  "bbox": [],
  "geometry": {"coordinates":[-118.15,40.2667],"type":"Point"}
}