<<<<<<< HEAD
{
  "id": 2709433,
  "type": "Feature",
  "properties": {
    "tgn:hierarchy":[
        "tgn:2709433",
        "tgn:1000001",
        "tgn:2001416",
        "tgn:7012149",
        "tgn:7007526",
        "tgn:7029392"
    ],
    "tgn:id":2709433,
    "tgn:name":"Table Top Mountain",
    "tgn:placetype":[
        "aat:300008798"
    ]
},
  "bbox": [],
  "geometry": {"coordinates":[-115.15,37.4667],"type":"Point"}
}
=======
{"geometry":{"type":"Point","coordinates":[-115.150000,37.466700]},"type":"Feature","properties":{"hierarchy":["tgn:2709433","tgn:1000001","tgn:2001416","tgn:7012149","tgn:7007526","tgn:7029392"],"placetype":["aat:300008798"],"id":2709433,"name:xx":"Table Top Mountain"}}
>>>>>>> 03f74aca74312dbeaf24d7e61306dd6a786dc3d0
