{
  "id": 2594640,
  "type": "Feature",
  "properties": {
    "tgn:hierarchy":[
        "tgn:2594640",
        "tgn:1000001",
        "tgn:7012149",
        "tgn:2000210",
        "tgn:7007158",
        "tgn:7029392"
    ],
    "tgn:id":2594640,
    "tgn:name":"Posey Creek",
    "tgn:placetype":[
        "aat:300008706"
    ]
},
  "bbox": [],
  "geometry": {"coordinates":[-106.8833,39.7667],"type":"Point"}
}