{
  "id": 7318335,
  "type": "Feature",
  "properties": {
    "tgn:hierarchy":[
        "tgn:7318335",
        "tgn:1001705",
        "tgn:1000049",
        "tgn:1000002",
        "tgn:7029392"
    ],
    "tgn:id":7318335,
    "tgn:name":"Cordillerilla, Cerro",
    "tgn:placetype":[
        "aat:300008777"
    ]
},
  "bbox": [],
  "geometry": {"coordinates":[-71.333333,-35.083333],"type":"Point"}
}