{
  "id": 2615612,
  "type": "Feature",
  "properties": {
    "tgn:hierarchy":[
        "tgn:2615612",
        "tgn:1000001",
        "tgn:7012149",
        "tgn:2000376",
        "tgn:7007248",
        "tgn:7029392"
    ],
    "tgn:id":2615612,
    "tgn:name":"Revere",
    "tgn:placetype":[
        "aat:300008347"
    ]
},
  "bbox": [],
  "geometry": {"coordinates":[-84.1667,33.0167],"type":"Point"}
}