{
  "id": 7076968,
  "type": "Feature",
  "properties": {
    "tgn:hierarchy":[
        "tgn:7076968",
        "tgn:1000003",
        "tgn:7003682",
        "tgn:7000084",
        "tgn:7029392"
    ],
    "tgn:id":7076968,
    "tgn:name":"Kreisfreie Stadt Neustadt an der Weinstra\u00dfe",
    "tgn:placetype":[
        "aat:300387198"
    ]
},
  "bbox": [],
  "geometry": {"coordinates":[8.185278,49.344722],"type":"Point"}
}