{
  "id": 7159698,
  "type": "Feature",
  "properties": {
    "tgn:hierarchy":[
        "tgn:7159698",
        "tgn:1000003",
        "tgn:7003688",
        "tgn:7000084",
        "tgn:7029392"
    ],
    "tgn:id":7159698,
    "tgn:name":"Hoffnung",
    "tgn:placetype":[
        "aat:300000206"
    ]
},
  "bbox": [],
  "geometry": {"coordinates":[10.266667,54.033333],"type":"Point"}
}