{
  "id": 7083329,
  "type": "Feature",
  "properties": {
    "tgn:hierarchy":[
        "tgn:7083329",
        "tgn:7003669",
        "tgn:1000003",
        "tgn:7000084",
        "tgn:7029392"
    ],
    "tgn:id":7083329,
    "tgn:name":"Willerskirchen",
    "tgn:placetype":[
        "aat:300000206"
    ]
},
  "bbox": [],
  "geometry": {"coordinates":[12.333333,48.516667],"type":"Point"}
}