{
  "id": 2637709,
  "type": "Feature",
  "properties": {
    "tgn:hierarchy":[
        "tgn:2637709",
        "tgn:2000090",
        "tgn:1000001",
        "tgn:7006451",
        "tgn:7012149",
        "tgn:7029392"
    ],
    "tgn:id":2637709,
    "tgn:name":"Saint Peters Dome",
    "tgn:placetype":[
        "aat:300008798"
    ]
},
  "bbox": [],
  "geometry": {"coordinates":[-109.55,34.1333],"type":"Point"}
}