{
  "id": 7290293,
  "type": "Feature",
  "properties": {
    "tgn:hierarchy":[
        "tgn:7290293",
        "tgn:1001657",
        "tgn:1000049",
        "tgn:1000002",
        "tgn:7029392"
    ],
    "tgn:id":7290293,
    "tgn:name":"Echegoyen, Puntilla",
    "tgn:placetype":[
        "aat:300387002"
    ]
},
  "bbox": [],
  "geometry": {"coordinates":[-71.133333,-29.35],"type":"Point"}
}