{
  "id": 7092581,
  "type": "Feature",
  "properties": {
    "tgn:hierarchy":[
        "tgn:7092581",
        "tgn:1000003",
        "tgn:7003676",
        "tgn:7000084",
        "tgn:7029392"
    ],
    "tgn:id":7092581,
    "tgn:name":"Upstedt",
    "tgn:placetype":[
        "aat:300008347"
    ]
},
  "bbox": [],
  "geometry": {"coordinates":[10.066667,52.05],"type":"Point"}
}