{
  "id": 7308347,
  "type": "Feature",
  "properties": {
    "tgn:hierarchy":[
        "tgn:7308347",
        "tgn:1001702",
        "tgn:1000049",
        "tgn:1000002",
        "tgn:7029392"
    ],
    "tgn:id":7308347,
    "tgn:name":"Marta, Isla",
    "tgn:placetype":[
        "aat:300008791"
    ]
},
  "bbox": [],
  "geometry": {"coordinates":[-72.283333,-52.566667],"type":"Point"}
}