{
  "id": 7539895,
  "type": "Feature",
  "properties": {
    "tgn:hierarchy":[
        "tgn:7539895",
        "tgn:7001242",
        "tgn:7001311",
        "tgn:7016833",
        "tgn:7029392"
    ],
    "tgn:id":7539895,
    "tgn:name:en":"Samnah, Jabal",
    "tgn:placetype":[
        "aat:300008795"
    ]
},
  "bbox": [],
  "geometry": {"coordinates":[33.573911,26.459195],"type":"Point"}
}