<<<<<<< HEAD
{
  "id": 7353221,
  "type": "Feature",
  "properties": {
    "tgn:hierarchy":[
        "tgn:7353221",
        "tgn:1000001",
        "tgn:7005600",
        "tgn:7005560",
        "tgn:7029392"
    ],
    "tgn:id":7353221,
    "tgn:name":"Bece",
    "tgn:placetype":[
        "aat:300008347"
    ]
},
  "bbox": [],
  "geometry": {"coordinates":[-88.816667,21.25],"type":"Point"}
}
=======
{"geometry":{"type":"Point","coordinates":[-88.816667,21.250000]},"type":"Feature","properties":{"hierarchy":["tgn:7353221","tgn:1000001","tgn:7005600","tgn:7005560","tgn:7029392"],"placetype":["aat:300008347"],"id":7353221,"name:xx":"Bece"}}
>>>>>>> 03f74aca74312dbeaf24d7e61306dd6a786dc3d0
