{
  "id": 7512600,
  "type": "Feature",
  "properties": {
    "tgn:hierarchy":[
        "tgn:7512600",
        "tgn:1009227",
        "tgn:1000226",
        "tgn:7016822",
        "tgn:1000006",
        "tgn:7029392"
    ],
    "tgn:id":7512600,
    "tgn:name:en":"Hokuri Creek",
    "tgn:placetype":[
        "aat:300008699"
    ]
},
  "bbox": [],
  "geometry": {"coordinates":[168.05,-44.416667],"type":"Point"}
}