{
  "id": 2527016,
  "type": "Feature",
  "properties": {
    "tgn:hierarchy":[
        "tgn:2527016",
        "tgn:1000001",
        "tgn:7012149",
        "tgn:2001525",
        "tgn:7007709",
        "tgn:7029392"
    ],
    "tgn:id":2527016,
    "tgn:name":"Mount Bolus",
    "tgn:placetype":[
        "aat:300008347"
    ]
},
  "bbox": [],
  "geometry": {"coordinates":[-79.05,35.9167],"type":"Point"}
}