{
  "id": 1114099,
  "type": "Feature",
  "properties": {
    "tgn:hierarchy":[
        "tgn:1114099",
        "tgn:7005685",
        "tgn:1000001",
        "tgn:1000296",
        "tgn:7029392"
    ],
    "tgn:id":1114099,
    "tgn:name":"Byam Channel",
    "tgn:placetype":[
        "aat:300008713"
    ]
},
  "bbox": [],
  "geometry": {"coordinates":[-105.25,75.25],"type":"Point"}
}