{
  "id": 7237286,
  "type": "Feature",
  "properties": {
    "tgn:hierarchy":[
        "tgn:7237286",
        "tgn:7002724",
        "tgn:7002715",
        "tgn:1000003",
        "tgn:1000074",
        "tgn:7029392"
    ],
    "tgn:id":7237286,
    "tgn:name":"\u00c1yios And\u00f3nios",
    "tgn:placetype":[
        "aat:300008347"
    ]
},
  "bbox": [],
  "geometry": {"coordinates":[21.283333,40.633333],"type":"Point"}
}