{
  "id": 2174468,
  "type": "Feature",
  "properties": {
    "tgn:hierarchy":[
        "tgn:2174468",
        "tgn:1000001",
        "tgn:7012149",
        "tgn:2000290",
        "tgn:7007240",
        "tgn:7029392"
    ],
    "tgn:id":2174468,
    "tgn:name":"Bishop Lake",
    "tgn:placetype":[
        "aat:300008905"
    ]
},
  "bbox": [],
  "geometry": {"coordinates":[-86.05,30.4167],"type":"Point"}
}