{
  "id": 7565819,
  "type": "Feature",
  "properties": {
    "tgn:hierarchy":[
        "tgn:7565819",
        "tgn:1000004",
        "tgn:7000198",
        "tgn:1001894",
        "tgn:7029392"
    ],
    "tgn:id":7565819,
    "tgn:name:en":"Nanhi Tehri",
    "tgn:placetype":[
        "aat:300008347"
    ]
},
  "bbox": [],
  "geometry": {"coordinates":[79.069552,24.682498],"type":"Point"}
}