{
  "id": 2310361,
  "type": "Feature",
  "properties": {
    "tgn:hierarchy":[
        "tgn:2310361",
        "tgn:1000001",
        "tgn:7012149",
        "tgn:2000210",
        "tgn:7007158",
        "tgn:7029392"
    ],
    "tgn:id":2310361,
    "tgn:name":"Eby Creek",
    "tgn:placetype":[
        "aat:300008706"
    ]
},
  "bbox": [],
  "geometry": {"coordinates":[-106.8667,39.7667],"type":"Point"}
}