{
  "id": 7260405,
  "type": "Feature",
  "properties": {
    "tgn:hierarchy":[
        "tgn:7260405",
        "tgn:7003616",
        "tgn:1000003",
        "tgn:7016845",
        "tgn:7029392"
    ],
    "tgn:id":7260405,
    "tgn:name:nl":"De Kolken",
    "tgn:placetype":[
        "aat:300387200"
    ]
},
  "bbox": [],
  "geometry": {"coordinates":[6.116667,53.35],"type":"Point"}
}