{
  "id": 2781176,
  "type": "Feature",
  "properties": {
    "tgn:hierarchy":[
        "tgn:2781176",
        "tgn:1000001",
        "tgn:7012149",
        "tgn:2001487",
        "tgn:7007709",
        "tgn:7029392"
    ],
    "tgn:id":2781176,
    "tgn:name":"Woodfield",
    "tgn:placetype":[
        "aat:300008347"
    ]
},
  "bbox": [],
  "geometry": {"coordinates":[-78.9333,35.0833],"type":"Point"}
}