{
  "id": 7587713,
  "type": "Feature",
  "properties": {
    "tgn:hierarchy":[
        "tgn:7587713",
        "tgn:1000004",
        "tgn:7000198",
        "tgn:7000799",
        "tgn:7029392"
    ],
    "tgn:id":7587713,
    "tgn:name:en":"Miragund Jh\u012bl",
    "tgn:placetype":[
        "aat:300008903"
    ]
},
  "bbox": [],
  "geometry": {"coordinates":[74.636498,34.123929],"type":"Point"}
}