<<<<<<< HEAD
{
  "id": 7171953,
  "type": "Feature",
  "properties": {
    "tgn:hierarchy":[
        "tgn:7171953",
        "tgn:7003669",
        "tgn:1000003",
        "tgn:7000084",
        "tgn:7029392"
    ],
    "tgn:id":7171953,
    "tgn:name":"Hirn",
    "tgn:placetype":[
        "aat:300000206"
    ]
},
  "bbox": [],
  "geometry": {"coordinates":[10.4,47.816667],"type":"Point"}
}
=======
{"geometry":{"type":"Point","coordinates":[10.400000,47.816667]},"type":"Feature","properties":{"hierarchy":["tgn:7171953","tgn:7003669","tgn:1000003","tgn:7000084","tgn:7029392"],"placetype":["aat:300000206"],"id":7171953,"name:xx":"Hirn"}}
>>>>>>> 03f74aca74312dbeaf24d7e61306dd6a786dc3d0
