{
  "id": 7352853,
  "type": "Feature",
  "properties": {
    "tgn:hierarchy":[
        "tgn:7352853",
        "tgn:7005586",
        "tgn:1000001",
        "tgn:7005560",
        "tgn:7029392"
    ],
    "tgn:id":7352853,
    "tgn:name":"Buenavista",
    "tgn:placetype":[
        "aat:300008347"
    ]
},
  "bbox": [],
  "geometry": {"coordinates":[-103.216667,20.383333],"type":"Point"}
}