{
  "id": 7286099,
  "type": "Feature",
  "properties": {
    "tgn:hierarchy":[
        "tgn:7286099",
        "tgn:1001702",
        "tgn:1000049",
        "tgn:1000002",
        "tgn:7029392"
    ],
    "tgn:id":7286099,
    "tgn:name":"India, Bah\u00eda",
    "tgn:placetype":[
        "aat:300132316"
    ]
},
  "bbox": [],
  "geometry": {"coordinates":[-69.15,-55.466667],"type":"Point"}
}