{
  "id": 2411442,
  "type": "Feature",
  "properties": {
    "tgn:hierarchy":[
        "tgn:2411442",
        "tgn:1000001",
        "tgn:7012149",
        "tgn:2002375",
        "tgn:7007923",
        "tgn:7029392"
    ],
    "tgn:id":2411442,
    "tgn:name":"Indian Hill",
    "tgn:placetype":[
        "aat:300008798"
    ]
},
  "bbox": [],
  "geometry": {"coordinates":[-104.6333,41.5333],"type":"Point"}
}