{
  "id": 2596733,
  "type": "Feature",
  "properties": {
    "tgn:hierarchy":[
        "tgn:2596733",
        "tgn:1000001",
        "tgn:1002318",
        "tgn:7012149",
        "tgn:7007710",
        "tgn:7029392"
    ],
    "tgn:id":2596733,
    "tgn:name":"Powell Creek",
    "tgn:placetype":[
        "aat:300008706"
    ]
},
  "bbox": [],
  "geometry": {"coordinates":[-76.7833,40.4667],"type":"Point"}
}