{
  "id": 2094568,
  "type": "Feature",
  "properties": {
    "tgn:hierarchy":[
        "tgn:2094568",
        "tgn:1000001",
        "tgn:1002272",
        "tgn:7012149",
        "tgn:7007710",
        "tgn:7029392"
    ],
    "tgn:id":2094568,
    "tgn:name":"Wildcat",
    "tgn:placetype":[
        "aat:300008347"
    ]
},
  "bbox": [],
  "geometry": {"coordinates":[-79.4667,41.0167],"type":"Point"}
}