{
  "id": 2329924,
  "type": "Feature",
  "properties": {
    "tgn:hierarchy":[
        "tgn:2329924",
        "tgn:1000001",
        "tgn:7012149",
        "tgn:2002342",
        "tgn:7007922",
        "tgn:7029392"
    ],
    "tgn:id":2329924,
    "tgn:name":"Flag Lake",
    "tgn:placetype":[
        "aat:300008680"
    ]
},
  "bbox": [],
  "geometry": {"coordinates":[-89.5167,45.6167],"type":"Point"}
}