{
  "id": 7591227,
  "type": "Feature",
  "properties": {
    "tgn:hierarchy":[
        "tgn:7591227",
        "tgn:1000004",
        "tgn:7000198",
        "tgn:7000799",
        "tgn:7029392"
    ],
    "tgn:id":7591227,
    "tgn:name:en":"Patha ni Gai",
    "tgn:placetype":[
        "aat:300008347"
    ]
},
  "bbox": [],
  "geometry": {"coordinates":[74.105556,33.208333],"type":"Point"}
}