{
  "id": 7443492,
  "type": "Feature",
  "properties": {
    "tgn:hierarchy":[
        "tgn:7443492",
        "tgn:7002444",
        "tgn:1000003",
        "tgn:7008082",
        "tgn:7008591",
        "tgn:7029392"
    ],
    "tgn:id":7443492,
    "tgn:name:en":"Urigill, Loch",
    "tgn:placetype":[
        "aat:300008680"
    ]
},
  "bbox": [],
  "geometry": {"coordinates":[-4.966667,58.033333],"type":"Point"}
}