{
  "id": 2126405,
  "type": "Feature",
  "properties": {
    "tgn:hierarchy":[
        "tgn:2126405",
        "tgn:1000001",
        "tgn:7012149",
        "tgn:2001442",
        "tgn:7007566",
        "tgn:7029392"
    ],
    "tgn:id":2126405,
    "tgn:name":"Adobe Tank",
    "tgn:placetype":[
        "aat:300006191"
    ]
},
  "bbox": [],
  "geometry": {"coordinates":[-104.95,34.05],"type":"Point"}
}