<<<<<<< HEAD
{
  "id": 7059728,
  "type": "Feature",
  "properties": {
    "tgn:hierarchy":[
        "tgn:7059728",
        "tgn:1000003",
        "tgn:7003676",
        "tgn:7000084",
        "tgn:7029392"
    ],
    "tgn:id":7059728,
    "tgn:name":"Ahler Bach",
    "tgn:placetype":[
        "aat:300008699"
    ]
},
  "bbox": [],
  "geometry": {"coordinates":[7.783333,52.6],"type":"Point"}
}
=======
{"geometry":{"type":"Point","coordinates":[7.783333,52.600000]},"type":"Feature","properties":{"hierarchy":["tgn:7059728","tgn:1000003","tgn:7003676","tgn:7000084","tgn:7029392"],"placetype":["aat:300008699"],"id":7059728,"name:xx":"Ahler Bach"}}
>>>>>>> 03f74aca74312dbeaf24d7e61306dd6a786dc3d0
