{
  "id": 2510599,
  "type": "Feature",
  "properties": {
    "tgn:hierarchy":[
        "tgn:2510599",
        "tgn:1000001",
        "tgn:7006451",
        "tgn:2000094",
        "tgn:7012149",
        "tgn:7029392"
    ],
    "tgn:id":2510599,
    "tgn:name":"Middle Wash",
    "tgn:placetype":[
        "aat:300008699"
    ]
},
  "bbox": [],
  "geometry": {"coordinates":[-109.9667,32.7833],"type":"Point"}
}