{
  "id": 1054212,
  "type": "Feature",
  "properties": {
    "tgn:hierarchy":[
        "tgn:1054212",
        "tgn:1000004",
        "tgn:1003405",
        "tgn:7018214",
        "tgn:7002435",
        "tgn:7029392"
    ],
    "tgn:id":1054212,
    "tgn:name":"Gukovo",
    "tgn:placetype":[
        "aat:300008347"
    ]
},
  "bbox": [],
  "geometry": {"coordinates":[39.9833,48.0833],"type":"Point"}
}