{
  "id": 7309368,
  "type": "Feature",
  "properties": {
    "tgn:hierarchy":[
        "tgn:7309368",
        "tgn:1001695",
        "tgn:1000049",
        "tgn:1000002",
        "tgn:7029392"
    ],
    "tgn:id":7309368,
    "tgn:name":"Los Puquios, Quebrada",
    "tgn:placetype":[
        "aat:300008699"
    ]
},
  "bbox": [],
  "geometry": {"coordinates":[-70.283333,-34.15],"type":"Point"}
}