{
  "id": 2778955,
  "type": "Feature",
  "properties": {
    "tgn:hierarchy":[
        "tgn:2778955",
        "tgn:1000001",
        "tgn:7012149",
        "tgn:2000751",
        "tgn:7007254",
        "tgn:7029392"
    ],
    "tgn:id":2778955,
    "tgn:name":"Wolf Creek",
    "tgn:placetype":[
        "aat:300008706"
    ]
},
  "bbox": [],
  "geometry": {"coordinates":[-98.6667,39.95],"type":"Point"}
}