{
  "id": 2367124,
  "type": "Feature",
  "properties": {
    "tgn:hierarchy":[
        "tgn:2367124",
        "tgn:1000001",
        "tgn:1002184",
        "tgn:7012149",
        "tgn:7007252",
        "tgn:7029392"
    ],
    "tgn:id":2367124,
    "tgn:name":"Groff Ditch",
    "tgn:placetype":[
        "aat:300006075"
    ]
},
  "bbox": [],
  "geometry": {"coordinates":[-85.3667,40.5167],"type":"Point"}
}