{
  "id": 7419931,
  "type": "Feature",
  "properties": {
    "tgn:hierarchy":[
        "tgn:7419931",
        "tgn:1001836",
        "tgn:1000001",
        "tgn:7005560",
        "tgn:7029392"
    ],
    "tgn:id":7419931,
    "tgn:name":"Chimetl\u00e1n",
    "tgn:placetype":[
        "aat:300008347"
    ]
},
  "bbox": [],
  "geometry": {"coordinates":[-110.377778,24.096389],"type":"Point"}
}