{
  "id": 7147872,
  "type": "Feature",
  "properties": {
    "tgn:hierarchy":[
        "tgn:7147872",
        "tgn:1000003",
        "tgn:7003676",
        "tgn:7000084",
        "tgn:7029392"
    ],
    "tgn:id":7147872,
    "tgn:name":"Langel",
    "tgn:placetype":[
        "aat:300008347"
    ]
},
  "bbox": [],
  "geometry": {"coordinates":[9.083333,53.566667],"type":"Point"}
}