<<<<<<< HEAD
{
  "id": 7364200,
  "type": "Feature",
  "properties": {
    "tgn:hierarchy":[
        "tgn:7364200",
        "tgn:1000001",
        "tgn:7005599",
        "tgn:7005560",
        "tgn:7029392"
    ],
    "tgn:id":7364200,
    "tgn:name":"El Ciruelar",
    "tgn:placetype":[
        "aat:300008347"
    ]
},
  "bbox": [],
  "geometry": {"coordinates":[-98.133333,21.3],"type":"Point"}
}
=======
{"geometry":{"type":"Point","coordinates":[-98.133333,21.300000]},"type":"Feature","properties":{"hierarchy":["tgn:7364200","tgn:1000001","tgn:7005599","tgn:7005560","tgn:7029392"],"placetype":["aat:300008347"],"id":7364200,"name:xx":"El Ciruelar"}}
>>>>>>> 03f74aca74312dbeaf24d7e61306dd6a786dc3d0
