{
  "id": 2277938,
  "type": "Feature",
  "properties": {
    "tgn:hierarchy":[
        "tgn:2277938",
        "tgn:1000001",
        "tgn:7012149",
        "tgn:7007157",
        "tgn:7014475",
        "tgn:7029392"
    ],
    "tgn:id":2277938,
    "tgn:name":"Day Creek",
    "tgn:placetype":[
        "aat:300008706"
    ]
},
  "bbox": [],
  "geometry": {"coordinates":[-121.6167,37.05],"type":"Point"}
}