{
  "id": 2299790,
  "type": "Feature",
  "properties": {
    "tgn:hierarchy":[
        "tgn:2299790",
        "tgn:1000001",
        "tgn:1002712",
        "tgn:7012149",
        "tgn:7007159",
        "tgn:7029392"
    ],
    "tgn:id":2299790,
    "tgn:name":"Dudley Creek",
    "tgn:placetype":[
        "aat:300008706"
    ]
},
  "bbox": [],
  "geometry": {"coordinates":[-72.5333,41.25],"type":"Point"}
}