{
  "id": 7165398,
  "type": "Feature",
  "properties": {
    "tgn:hierarchy":[
        "tgn:7165398",
        "tgn:1000003",
        "tgn:7003678",
        "tgn:7000084",
        "tgn:7029392"
    ],
    "tgn:id":7165398,
    "tgn:name":"Igelsbett",
    "tgn:placetype":[
        "aat:300008863"
    ]
},
  "bbox": [],
  "geometry": {"coordinates":[9.266667,51.433333],"type":"Point"}
}