{
  "id": 2626885,
  "type": "Feature",
  "properties": {
    "tgn:hierarchy":[
        "tgn:2626885",
        "tgn:1000001",
        "tgn:1002480",
        "tgn:7012149",
        "tgn:7007564",
        "tgn:7029392"
    ],
    "tgn:id":2626885,
    "tgn:name":"Rocky Pond Brook",
    "tgn:placetype":[
        "aat:300008699"
    ]
},
  "bbox": [],
  "geometry": {"coordinates":[-71.6167,42.75],"type":"Point"}
}