<<<<<<< HEAD
{
  "id": 2335600,
  "type": "Feature",
  "properties": {
    "tgn:hierarchy":[
        "tgn:2335600",
        "tgn:1002309",
        "tgn:1000001",
        "tgn:7012149",
        "tgn:7007565",
        "tgn:7029392"
    ],
    "tgn:id":2335600,
    "tgn:name":"Fortescue Neck",
    "tgn:placetype":[
        "aat:300008850"
    ]
},
  "bbox": [],
  "geometry": {"coordinates":[-75.15,39.25],"type":"Point"}
}
=======
{"geometry":{"type":"Point","coordinates":[-75.150000,39.250000]},"type":"Feature","properties":{"hierarchy":["tgn:2335600","tgn:1002309","tgn:1000001","tgn:7012149","tgn:7007565","tgn:7029392"],"placetype":["aat:300008850"],"id":2335600,"name:xx":"Fortescue Neck"}}
>>>>>>> 03f74aca74312dbeaf24d7e61306dd6a786dc3d0
