{
  "id": 2134717,
  "type": "Feature",
  "properties": {
    "tgn:hierarchy":[
        "tgn:2134717",
        "tgn:1000001",
        "tgn:2001415",
        "tgn:7012149",
        "tgn:7007526",
        "tgn:7029392"
    ],
    "tgn:id":2134717,
    "tgn:name":"Antelope Creek",
    "tgn:placetype":[
        "aat:300008706"
    ]
},
  "bbox": [],
  "geometry": {"coordinates":[-117.35,39.5167],"type":"Point"}
}