{
  "id": 2579448,
  "type": "Feature",
  "properties": {
    "tgn:hierarchy":[
        "tgn:2579448",
        "tgn:1000001",
        "tgn:7012149",
        "tgn:1002871",
        "tgn:7007568",
        "tgn:7029392"
    ],
    "tgn:id":2579448,
    "tgn:name":"Pickerel Pond",
    "tgn:placetype":[
        "aat:300008680"
    ]
},
  "bbox": [],
  "geometry": {"coordinates":[-73.8333,43.2167],"type":"Point"}
}