<<<<<<< HEAD
{
  "id": 2760833,
  "type": "Feature",
  "properties": {
    "tgn:hierarchy":[
        "tgn:2760833",
        "tgn:7030515",
        "tgn:7006450",
        "tgn:1000001",
        "tgn:7012149",
        "tgn:7029392"
    ],
    "tgn:id":2760833,
    "tgn:name":"West Head",
    "tgn:placetype":[
        "aat:300008850"
    ]
},
  "bbox": [],
  "geometry": {"coordinates":[-160.5167,55.3667],"type":"Point"}
}
=======
{"geometry":{"type":"Point","coordinates":[-160.516700,55.366700]},"type":"Feature","properties":{"hierarchy":["tgn:2760833","tgn:7030515","tgn:7006450","tgn:1000001","tgn:7012149","tgn:7029392"],"placetype":["aat:300008850"],"id":2760833,"name:xx":"West Head"}}
>>>>>>> 03f74aca74312dbeaf24d7e61306dd6a786dc3d0
