<<<<<<< HEAD
{
  "id": 2256961,
  "type": "Feature",
  "properties": {
    "tgn:hierarchy":[
        "tgn:2256961",
        "tgn:7002659",
        "tgn:1000001",
        "tgn:7012149",
        "tgn:2000022",
        "tgn:7029392"
    ],
    "tgn:id":2256961,
    "tgn:name":"Corn Creek",
    "tgn:placetype":[
        "aat:300008706"
    ]
},
  "bbox": [],
  "geometry": {"coordinates":[-85.5167,31.5333],"type":"Point"}
}
=======
{"geometry":{"type":"Point","coordinates":[-85.516700,31.533300]},"type":"Feature","properties":{"hierarchy":["tgn:2256961","tgn:7002659","tgn:1000001","tgn:7012149","tgn:2000022","tgn:7029392"],"placetype":["aat:300008706"],"id":2256961,"name:xx":"Corn Creek"}}
>>>>>>> 03f74aca74312dbeaf24d7e61306dd6a786dc3d0
