{
  "id": 2215925,
  "type": "Feature",
  "properties": {
    "tgn:hierarchy":[
        "tgn:2215925",
        "tgn:1000001",
        "tgn:2001355",
        "tgn:7012149",
        "tgn:7007525",
        "tgn:7029392"
    ],
    "tgn:id":2215925,
    "tgn:name":"Cameron",
    "tgn:placetype":[
        "aat:300008347"
    ]
},
  "bbox": [],
  "geometry": {"coordinates":[-98.6333,40.9167],"type":"Point"}
}