{
  "id": 2664137,
  "type": "Feature",
  "properties": {
    "tgn:hierarchy":[
        "tgn:2664137",
        "tgn:1000001",
        "tgn:7012149",
        "tgn:2001274",
        "tgn:7007524",
        "tgn:7029392"
    ],
    "tgn:id":2664137,
    "tgn:name":"Silver Run Creek",
    "tgn:placetype":[
        "aat:300008706"
    ]
},
  "bbox": [],
  "geometry": {"coordinates":[-114.0333,48.25],"type":"Point"}
}