{
  "id": 2227643,
  "type": "Feature",
  "properties": {
    "tgn:hierarchy":[
        "tgn:2227643",
        "tgn:7013349",
        "tgn:1000001",
        "tgn:7012149",
        "tgn:7007708",
        "tgn:7029392"
    ],
    "tgn:id":2227643,
    "tgn:name":"Cavin Swamp",
    "tgn:placetype":[
        "aat:300008905"
    ]
},
  "bbox": [],
  "geometry": {"coordinates":[-118.25,44.4167],"type":"Point"}
}