{
  "id": 2299943,
  "type": "Feature",
  "properties": {
    "tgn:hierarchy":[
        "tgn:2299943",
        "tgn:1000001",
        "tgn:7012149",
        "tgn:2001764",
        "tgn:7007712",
        "tgn:7029392"
    ],
    "tgn:id":2299943,
    "tgn:name":"Duffies Pond",
    "tgn:placetype":[
        "aat:300006191"
    ]
},
  "bbox": [],
  "geometry": {"coordinates":[-80.85,33.8333],"type":"Point"}
}