{
  "id": 7133572,
  "type": "Feature",
  "properties": {
    "tgn:hierarchy":[
        "tgn:7133572",
        "tgn:1000003",
        "tgn:7003677",
        "tgn:7000084",
        "tgn:7029392"
    ],
    "tgn:id":7133572,
    "tgn:name":"Munscheid",
    "tgn:placetype":[
        "aat:300008347"
    ]
},
  "bbox": [],
  "geometry": {"coordinates":[7.166667,51.45],"type":"Point"}
}