<<<<<<< HEAD
{
  "id": 2330769,
  "type": "Feature",
  "properties": {
    "tgn:hierarchy":[
        "tgn:2330769",
        "tgn:1000001",
        "tgn:2001780",
        "tgn:7012149",
        "tgn:7007713",
        "tgn:7029392"
    ],
    "tgn:id":2330769,
    "tgn:name":"Flat Lake",
    "tgn:placetype":[
        "aat:300008680"
    ]
},
  "bbox": [],
  "geometry": {"coordinates":[-99.7833,45.6667],"type":"Point"}
}
=======
{"geometry":{"type":"Point","coordinates":[-99.783300,45.666700]},"type":"Feature","properties":{"hierarchy":["tgn:2330769","tgn:1000001","tgn:2001780","tgn:7012149","tgn:7007713","tgn:7029392"],"placetype":["aat:300008680"],"id":2330769,"name:xx":"Flat Lake"}}
>>>>>>> 03f74aca74312dbeaf24d7e61306dd6a786dc3d0
