{
  "id": 2450061,
  "type": "Feature",
  "properties": {
    "tgn:hierarchy":[
        "tgn:2450061",
        "tgn:1000001",
        "tgn:7012149",
        "tgn:1002397",
        "tgn:7007568",
        "tgn:7029392"
    ],
    "tgn:id":2450061,
    "tgn:name":"Lindsley Corners",
    "tgn:placetype":[
        "aat:300008347"
    ]
},
  "bbox": [],
  "geometry": {"coordinates":[-74.3667,43.1667],"type":"Point"}
}