{
  "id": 7309440,
  "type": "Feature",
  "properties": {
    "tgn:hierarchy":[
        "tgn:7309440",
        "tgn:1001637",
        "tgn:1000049",
        "tgn:1000002",
        "tgn:7029392"
    ],
    "tgn:id":7309440,
    "tgn:name":"Pachagua, Estero",
    "tgn:placetype":[
        "aat:300008699"
    ]
},
  "bbox": [],
  "geometry": {"coordinates":[-72.533333,-37.033333],"type":"Point"}
}