{
  "id": 7164102,
  "type": "Feature",
  "properties": {
    "tgn:hierarchy":[
        "tgn:7164102",
        "tgn:1000003",
        "tgn:7003677",
        "tgn:7000084",
        "tgn:7029392"
    ],
    "tgn:id":7164102,
    "tgn:name":"H\u00fcns-Berg",
    "tgn:placetype":[
        "aat:300008777"
    ]
},
  "bbox": [],
  "geometry": {"coordinates":[7.866667,50.95],"type":"Point"}
}