<<<<<<< HEAD
{
  "id": 2338031,
  "type": "Feature",
  "properties": {
    "tgn:hierarchy":[
        "tgn:2338031",
        "tgn:1000001",
        "tgn:7012149",
        "tgn:2002164",
        "tgn:7007919",
        "tgn:7029392"
    ],
    "tgn:id":2338031,
    "tgn:name":"Fox Knob",
    "tgn:placetype":[
        "aat:300008798"
    ]
},
  "bbox": [],
  "geometry": {"coordinates":[-81.3,36.5833],"type":"Point"}
}
=======
{"geometry":{"type":"Point","coordinates":[-81.300000,36.583300]},"type":"Feature","properties":{"hierarchy":["tgn:2338031","tgn:1000001","tgn:7012149","tgn:2002164","tgn:7007919","tgn:7029392"],"placetype":["aat:300008798"],"id":2338031,"name:xx":"Fox Knob"}}
>>>>>>> 03f74aca74312dbeaf24d7e61306dd6a786dc3d0
