{
  "id": 2648663,
  "type": "Feature",
  "properties": {
    "tgn:hierarchy":[
        "tgn:2648663",
        "tgn:7002659",
        "tgn:1000001",
        "tgn:7012149",
        "tgn:2000022",
        "tgn:7029392"
    ],
    "tgn:id":2648663,
    "tgn:name":"Sconyers Branch",
    "tgn:placetype":[
        "aat:300008699"
    ]
},
  "bbox": [],
  "geometry": {"coordinates":[-85.7167,31.25],"type":"Point"}
}