{
  "id": 2663139,
  "type": "Feature",
  "properties": {
    "tgn:hierarchy":[
        "tgn:2663139",
        "tgn:7006450",
        "tgn:1000001",
        "tgn:7012149",
        "tgn:7029392"
    ],
    "tgn:id":2663139,
    "tgn:name":"Silver Creek",
    "tgn:placetype":[
        "aat:300008706"
    ]
},
  "bbox": [],
  "geometry": {"coordinates":[-153.8667,59.65],"type":"Point"}
}