{
  "id": 1095087,
  "type": "Feature",
  "properties": {
    "tgn:hierarchy":[
        "tgn:1095087",
        "tgn:7001242",
        "tgn:1000909",
        "tgn:1000206",
        "tgn:7029392"
    ],
    "tgn:id":1095087,
    "tgn:name":"Nabiswera",
    "tgn:placetype":[
        "aat:300008347"
    ]
},
  "bbox": [],
  "geometry": {"coordinates":[32.2833,1.4667],"type":"Point"}
}