{
  "id": 7521550,
  "type": "Feature",
  "properties": {
    "tgn:hierarchy":[
        "tgn:7521550",
        "tgn:7001242",
        "tgn:7016833",
        "tgn:1001079",
        "tgn:7029392"
    ],
    "tgn:id":7521550,
    "tgn:name:en":"Al Ar\u0101mil",
    "tgn:placetype":[
        "aat:300011692"
    ]
},
  "bbox": [],
  "geometry": {"coordinates":[29.85,31.183333],"type":"Point"}
}