{
  "id": 7326633,
  "type": "Feature",
  "properties": {
    "tgn:hierarchy":[
        "tgn:7326633",
        "tgn:7002825",
        "tgn:7016622",
        "tgn:1000003",
        "tgn:1000095",
        "tgn:7029392"
    ],
    "tgn:id":7326633,
    "tgn:name":"Pe\u00f1\u00f3n Bermejo, Punta del",
    "tgn:placetype":[
        "aat:300386846"
    ]
},
  "bbox": [],
  "geometry": {"coordinates":[-15.816667,27.95],"type":"Point"}
}