{
  "id": 6000188,
  "type": "Feature",
  "properties": {
    "tgn:hierarchy":[
        "tgn:6000188",
        "tgn:7001242",
        "tgn:1000179",
        "tgn:7593698",
        "tgn:7029392"
    ],
    "tgn:id":6000188,
    "tgn:name":"Alhucemas",
    "tgn:placetype":[
        "aat:300132316"
    ]
},
  "bbox": [],
  "geometry": {"coordinates":[-3.829,35.25],"type":"Point"}
}