{
  "id": 7474951,
  "type": "Feature",
  "properties": {
    "tgn:hierarchy":[
        "tgn:7474951",
        "tgn:7001010",
        "tgn:1000004",
        "tgn:1000141",
        "tgn:7029392"
    ],
    "tgn:id":7474951,
    "tgn:name":"Wanshan Tang",
    "tgn:placetype":[
        "aat:300007595"
    ]
},
  "bbox": [],
  "geometry": {"coordinates":[121.347778,24.038333],"type":"Point"}
}