{
  "id": 7081620,
  "type": "Feature",
  "properties": {
    "tgn:hierarchy":[
        "tgn:7081620",
        "tgn:7003692",
        "tgn:1000003",
        "tgn:7000084",
        "tgn:7029392"
    ],
    "tgn:id":7081620,
    "tgn:name":"W\u00fcstmatte",
    "tgn:placetype":[
        "aat:300000206"
    ]
},
  "bbox": [],
  "geometry": {"coordinates":[7.933333,48.383333],"type":"Point"}
}