{
  "id": 7294539,
  "type": "Feature",
  "properties": {
    "tgn:hierarchy":[
        "tgn:7294539",
        "tgn:7002825",
        "tgn:7016622",
        "tgn:1000003",
        "tgn:1000095",
        "tgn:7029392"
    ],
    "tgn:id":7294539,
    "tgn:name":"Vega de R\u00edo de Palmas",
    "tgn:placetype":[
        "aat:300008347"
    ]
},
  "bbox": [],
  "geometry": {"coordinates":[-14.083333,28.383333],"type":"Point"}
}