<<<<<<< HEAD
{
  "id": 7116292,
  "type": "Feature",
  "properties": {
    "tgn:hierarchy":[
        "tgn:7116292",
        "tgn:7003669",
        "tgn:1000003",
        "tgn:7000084",
        "tgn:7029392"
    ],
    "tgn:id":7116292,
    "tgn:name":"Oberweihbach",
    "tgn:placetype":[
        "aat:300000206"
    ]
},
  "bbox": [],
  "geometry": {"coordinates":[10.15,47.683333],"type":"Point"}
}
=======
{"geometry":{"type":"Point","coordinates":[10.150000,47.683333]},"type":"Feature","properties":{"hierarchy":["tgn:7116292","tgn:7003669","tgn:1000003","tgn:7000084","tgn:7029392"],"placetype":["aat:300000206"],"id":7116292,"name:xx":"Oberweihbach"}}
>>>>>>> 03f74aca74312dbeaf24d7e61306dd6a786dc3d0
