{
  "id": 7508384,
  "type": "Feature",
  "properties": {
    "tgn:hierarchy":[
        "tgn:7508384",
        "tgn:7016670",
        "tgn:1008380",
        "tgn:1000226",
        "tgn:1000006",
        "tgn:7029392"
    ],
    "tgn:id":7508384,
    "tgn:name:en":"Opoutama Stream",
    "tgn:placetype":[
        "aat:300008699"
    ]
},
  "bbox": [],
  "geometry": {"coordinates":[177.833333,-39.066667],"type":"Point"}
}