{
  "id": 7591552,
  "type": "Feature",
  "properties": {
    "tgn:hierarchy":[
        "tgn:7591552",
        "tgn:1000004",
        "tgn:7000198",
        "tgn:7000799",
        "tgn:7029392"
    ],
    "tgn:id":7591552,
    "tgn:name:en":"Sult\u0101na",
    "tgn:placetype":[
        "aat:300008347"
    ]
},
  "bbox": [],
  "geometry": {"coordinates":[75.019444,34.561111],"type":"Point"}
}