{
  "id": 7577973,
  "type": "Feature",
  "properties": {
    "tgn:hierarchy":[
        "tgn:7577973",
        "tgn:1000004",
        "tgn:1001842",
        "tgn:7000198",
        "tgn:7029392"
    ],
    "tgn:id":7577973,
    "tgn:name:en":"Khutauna",
    "tgn:placetype":[
        "aat:300008347"
    ]
},
  "bbox": [],
  "geometry": {"coordinates":[86.395897,26.496939],"type":"Point"}
}