<<<<<<< HEAD
{
  "id": 2157560,
  "type": "Feature",
  "properties": {
    "tgn:hierarchy":[
        "tgn:2157560",
        "tgn:1000001",
        "tgn:7012149",
        "tgn:2002381",
        "tgn:7007923",
        "tgn:7029392"
    ],
    "tgn:id":2157560,
    "tgn:name":"Beaver Creek Hills",
    "tgn:placetype":[
        "aat:300386831"
    ]
},
  "bbox": [],
  "geometry": {"coordinates":[-107.05,44.7167],"type":"Point"}
}
=======
{"geometry":{"type":"Point","coordinates":[-107.050000,44.716700]},"type":"Feature","properties":{"hierarchy":["tgn:2157560","tgn:1000001","tgn:7012149","tgn:2002381","tgn:7007923","tgn:7029392"],"placetype":["aat:300386831"],"id":2157560,"name:xx":"Beaver Creek Hills"}}
>>>>>>> 03f74aca74312dbeaf24d7e61306dd6a786dc3d0
