{
  "id": 2555124,
  "type": "Feature",
  "properties": {
    "tgn:hierarchy":[
        "tgn:2555124",
        "tgn:1000001",
        "tgn:1003037",
        "tgn:7012149",
        "tgn:7007516",
        "tgn:7029392"
    ],
    "tgn:id":2555124,
    "tgn:name":"Ocean City Inlet",
    "tgn:placetype":[
        "aat:300132316"
    ]
},
  "bbox": [],
  "geometry": {"coordinates":[-75.0833,38.3167],"type":"Point"}
}