{
  "id": 2783661,
  "type": "Feature",
  "properties": {
    "tgn:hierarchy":[
        "tgn:2783661",
        "tgn:1000001",
        "tgn:7012149",
        "tgn:7029392"
    ],
    "tgn:id":2783661,
    "tgn:name":"Wylie, Lake",
    "tgn:placetype":[
        "aat:300006191"
    ]
},
  "bbox": [],
  "geometry": {"coordinates":[-81.0333,35.0333],"type":"Point"}
}