{
  "id": 2035990,
  "type": "Feature",
  "properties": {
    "tgn:hierarchy":[
        "tgn:2035990",
        "tgn:1000001",
        "tgn:7012149",
        "tgn:2000717",
        "tgn:7007254",
        "tgn:7029392"
    ],
    "tgn:id":2035990,
    "tgn:name":"Antelope",
    "tgn:placetype":[
        "aat:300008347",
        "aat:300387210"
    ]
},
  "bbox": [],
  "geometry": {"coordinates":[-96.9667,38.4333],"type":"Point"}
}