{
  "id": 2437837,
  "type": "Feature",
  "properties": {
    "tgn:hierarchy":[
        "tgn:2437837",
        "tgn:1000001",
        "tgn:2001175",
        "tgn:7012149",
        "tgn:7007523",
        "tgn:7029392"
    ],
    "tgn:id":2437837,
    "tgn:name":"King Hill",
    "tgn:placetype":[
        "aat:300008798"
    ]
},
  "bbox": [],
  "geometry": {"coordinates":[-94.85,39.7167],"type":"Point"}
}