{
  "id": 1074237,
  "type": "Feature",
  "properties": {
    "tgn:hierarchy":[
        "tgn:1074237",
        "tgn:7593931",
        "tgn:1000004",
        "tgn:7029392"
    ],
    "tgn:id":1074237,
    "tgn:name":"Akrotiri",
    "tgn:placetype":[
        "aat:300008347"
    ]
},
  "bbox": [],
  "geometry": {"coordinates":[32.95,34.5833],"type":"Point"}
}