{
  "id": 7314885,
  "type": "Feature",
  "properties": {
    "tgn:hierarchy":[
        "tgn:7314885",
        "tgn:1001692",
        "tgn:1000049",
        "tgn:1000002",
        "tgn:7029392"
    ],
    "tgn:id":7314885,
    "tgn:name":"Lol\u00e9n, R\u00edo",
    "tgn:placetype":[
        "aat:300008699"
    ]
},
  "bbox": [],
  "geometry": {"coordinates":[-71.233333,-38.483333],"type":"Point"}
}