{
  "id": 7062337,
  "type": "Feature",
  "properties": {
    "tgn:hierarchy":[
        "tgn:7062337",
        "tgn:1000003",
        "tgn:7003682",
        "tgn:7000084",
        "tgn:7029392"
    ],
    "tgn:id":7062337,
    "tgn:name":"Ammel Bach",
    "tgn:placetype":[
        "aat:300008699"
    ]
},
  "bbox": [],
  "geometry": {"coordinates":[8.133333,49.65],"type":"Point"}
}