{
  "id": 2541590,
  "type": "Feature",
  "properties": {
    "tgn:hierarchy":[
        "tgn:2541590",
        "tgn:1000001",
        "tgn:7012149",
        "tgn:2002379",
        "tgn:7007923",
        "tgn:7029392"
    ],
    "tgn:id":2541590,
    "tgn:name":"Nina Reservoir",
    "tgn:placetype":[
        "aat:300006191"
    ]
},
  "bbox": [],
  "geometry": {"coordinates":[-109.1667,44.2833],"type":"Point"}
}