{
  "id": 7532223,
  "type": "Feature",
  "properties": {
    "tgn:hierarchy":[
        "tgn:7532223",
        "tgn:7001242",
        "tgn:7016833",
        "tgn:7001335",
        "tgn:7029392"
    ],
    "tgn:id":7532223,
    "tgn:name:en":"El-Mineitir",
    "tgn:placetype":[
        "aat:300008217"
    ]
},
  "bbox": [],
  "geometry": {"coordinates":[34.021944,31.091667],"type":"Point"}
}