{
  "id": 7139030,
  "type": "Feature",
  "properties": {
    "tgn:hierarchy":[
        "tgn:7139030",
        "tgn:7003669",
        "tgn:1000003",
        "tgn:7000084",
        "tgn:7029392"
    ],
    "tgn:id":7139030,
    "tgn:name":"Langenwalder Weiher",
    "tgn:placetype":[
        "aat:300008680"
    ]
},
  "bbox": [],
  "geometry": {"coordinates":[10.733333,47.683333],"type":"Point"}
}