{
  "id": 2424020,
  "type": "Feature",
  "properties": {
    "tgn:hierarchy":[
        "tgn:2424020",
        "tgn:1000001",
        "tgn:7012149",
        "tgn:2000222",
        "tgn:7007158",
        "tgn:7029392"
    ],
    "tgn:id":2424020,
    "tgn:name":"Johns Creek",
    "tgn:placetype":[
        "aat:300008706"
    ]
},
  "bbox": [],
  "geometry": {"coordinates":[-103.3667,38.45],"type":"Point"}
}