{
  "id": 2433022,
  "type": "Feature",
  "properties": {
    "tgn:hierarchy":[
        "tgn:2433022",
        "tgn:1000001",
        "tgn:7012149",
        "tgn:2000550",
        "tgn:7007252",
        "tgn:7029392"
    ],
    "tgn:id":2433022,
    "tgn:name":"Keiser Hill",
    "tgn:placetype":[
        "aat:300008798"
    ]
},
  "bbox": [],
  "geometry": {"coordinates":[-86.7333,37.9667],"type":"Point"}
}