{
  "id": 1007786,
  "type": "Feature",
  "properties": {
    "tgn:hierarchy":[
        "tgn:1007786",
        "tgn:7001242",
        "tgn:1001889",
        "tgn:7000497",
        "tgn:1000182",
        "tgn:7029392"
    ],
    "tgn:id":1007786,
    "tgn:name":"Lagos Island",
    "tgn:placetype":[
        "aat:300008791"
    ]
},
  "bbox": [],
  "geometry": {"coordinates":[3.3833,6.45],"type":"Point"}
}