{
  "id": 2620063,
  "type": "Feature",
  "properties": {
    "tgn:hierarchy":[
        "tgn:2620063",
        "tgn:1000001",
        "tgn:2000457",
        "tgn:7012149",
        "tgn:7007250",
        "tgn:7029392"
    ],
    "tgn:id":2620063,
    "tgn:name":"Rising River",
    "tgn:placetype":[
        "aat:300008347"
    ]
},
  "bbox": [],
  "geometry": {"coordinates":[-112.3167,43.3167],"type":"Point"}
}