<<<<<<< HEAD
{
  "id": 2257930,
  "type": "Feature",
  "properties": {
    "tgn:hierarchy":[
        "tgn:2257930",
        "tgn:1000001",
        "tgn:2124025",
        "tgn:7012149",
        "tgn:7007516",
        "tgn:7029392"
    ],
    "tgn:id":2257930,
    "tgn:name":"Corsica River",
    "tgn:placetype":[
        "aat:300008707"
    ]
},
  "bbox": [],
  "geometry": {"coordinates":[-76.0667,39.05],"type":"Point"}
}
=======
{"geometry":{"type":"Point","coordinates":[-76.066700,39.050000]},"type":"Feature","properties":{"hierarchy":["tgn:2257930","tgn:1000001","tgn:2124025","tgn:7012149","tgn:7007516","tgn:7029392"],"placetype":["aat:300008707"],"id":2257930,"name:xx":"Corsica River"}}
>>>>>>> 03f74aca74312dbeaf24d7e61306dd6a786dc3d0
