{
  "id": 7403050,
  "type": "Feature",
  "properties": {
    "tgn:hierarchy":[
        "tgn:7403050",
        "tgn:1000001",
        "tgn:7005600",
        "tgn:7005560",
        "tgn:7029392"
    ],
    "tgn:id":7403050,
    "tgn:name":"Cavich",
    "tgn:placetype":[
        "aat:300008347"
    ]
},
  "bbox": [],
  "geometry": {"coordinates":[-87.8125,20.691667],"type":"Point"}
}