<<<<<<< HEAD
{
  "id": 7024078,
  "type": "Feature",
  "properties": {
    "tgn:hierarchy":[
        "tgn:7024078",
        "tgn:1000001",
        "tgn:7029392"
    ],
    "tgn:id":7024078,
    "tgn:name":"Champlain, Lake",
    "tgn:placetype":[
        "aat:300008680"
    ]
},
  "bbox": [],
  "geometry": {"coordinates":[-73.3333,44.5333],"type":"Point"}
}
=======
{"geometry":{"type":"Point","coordinates":[-73.333300,44.533300]},"type":"Feature","properties":{"hierarchy":["tgn:7024078","tgn:1000001","tgn:7029392"],"placetype":["aat:300008680"],"id":7024078,"name:xx":"Champlain, Lake"}}
>>>>>>> 03f74aca74312dbeaf24d7e61306dd6a786dc3d0
