{
  "id": 7024078,
  "type": "Feature",
  "properties": {
    "tgn:hierarchy":[
        "tgn:7024078",
        "tgn:1000001",
        "tgn:7029392"
    ],
    "tgn:id":7024078,
    "tgn:name":"Champlain, Lake",
    "tgn:placetype":[
        "aat:300008680"
    ]
},
  "bbox": [],
  "geometry": {"coordinates":[-73.3333,44.5333],"type":"Point"}
}