{
  "id": 7280234,
  "type": "Feature",
  "properties": {
    "tgn:hierarchy":[
        "tgn:7280234",
        "tgn:7002464",
        "tgn:1000049",
        "tgn:1000002",
        "tgn:7029392"
    ],
    "tgn:id":7280234,
    "tgn:name":"Quisama",
    "tgn:placetype":[
        "aat:300008347"
    ]
},
  "bbox": [],
  "geometry": {"coordinates":[-69.466667,-19.316667],"type":"Point"}
}