{
  "id": 2179841,
  "type": "Feature",
  "properties": {
    "tgn:hierarchy":[
        "tgn:2179841",
        "tgn:1000001",
        "tgn:7012149",
        "tgn:1002994",
        "tgn:7007708",
        "tgn:7029392"
    ],
    "tgn:id":2179841,
    "tgn:name":"Bledsoe Creek",
    "tgn:placetype":[
        "aat:300008706"
    ]
},
  "bbox": [],
  "geometry": {"coordinates":[-123.0833,45.6667],"type":"Point"}
}