{
  "id": 2362425,
  "type": "Feature",
  "properties": {
    "tgn:hierarchy":[
        "tgn:2362425",
        "tgn:1000001",
        "tgn:2002108",
        "tgn:7012149",
        "tgn:7007827",
        "tgn:7029392"
    ],
    "tgn:id":2362425,
    "tgn:name":"Greasewood Tank",
    "tgn:placetype":[
        "aat:300006191"
    ]
},
  "bbox": [],
  "geometry": {"coordinates":[-110.4667,38.8167],"type":"Point"}
}