{
  "id": 2362239,
  "type": "Feature",
  "properties": {
    "tgn:hierarchy":[
        "tgn:2362239",
        "tgn:1000001",
        "tgn:1002539",
        "tgn:7012149",
        "tgn:7007516",
        "tgn:7029392"
    ],
    "tgn:id":2362239,
    "tgn:name":"Grays Inn Creek",
    "tgn:placetype":[
        "aat:300008706"
    ]
},
  "bbox": [],
  "geometry": {"coordinates":[-76.2167,39.1333],"type":"Point"}
}