{
  "id": 7592229,
  "type": "Feature",
  "properties": {
    "tgn:hierarchy":[
        "tgn:7592229",
        "tgn:1000004",
        "tgn:7000198",
        "tgn:7000799",
        "tgn:7029392"
    ],
    "tgn:id":7592229,
    "tgn:name:en":"Bikhon",
    "tgn:placetype":[
        "aat:300008347"
    ]
},
  "bbox": [],
  "geometry": {"coordinates":[74.997559,32.910303],"type":"Point"}
}