{
  "id": 2129970,
  "type": "Feature",
  "properties": {
    "tgn:hierarchy":[
        "tgn:2129970",
        "tgn:1000001",
        "tgn:2001472",
        "tgn:7012149",
        "tgn:7007709",
        "tgn:7029392"
    ],
    "tgn:id":2129970,
    "tgn:name":"Allen Creek",
    "tgn:placetype":[
        "aat:300008706"
    ]
},
  "bbox": [],
  "geometry": {"coordinates":[-78.0833,34.0167],"type":"Point"}
}