{
  "id": 7554160,
  "type": "Feature",
  "properties": {
    "tgn:hierarchy":[
        "tgn:7554160",
        "tgn:1001828",
        "tgn:1000004",
        "tgn:7000198",
        "tgn:7029392"
    ],
    "tgn:id":7554160,
    "tgn:name:en":"N\u0101chugunta",
    "tgn:placetype":[
        "aat:300008347"
    ]
},
  "bbox": [],
  "geometry": {"coordinates":[80.883333,15.783333],"type":"Point"}
}