<<<<<<< HEAD
{
  "id": 7377619,
  "type": "Feature",
  "properties": {
    "tgn:hierarchy":[
        "tgn:7377619",
        "tgn:7005581",
        "tgn:1000001",
        "tgn:7005560",
        "tgn:7029392"
    ],
    "tgn:id":7377619,
    "tgn:name":"Las Calaveras",
    "tgn:placetype":[
        "aat:300008347"
    ]
},
  "bbox": [],
  "geometry": {"coordinates":[-108.2,28.0],"type":"Point"}
}
=======
{"geometry":{"type":"Point","coordinates":[-108.200000,28.000000]},"type":"Feature","properties":{"hierarchy":["tgn:7377619","tgn:7005581","tgn:1000001","tgn:7005560","tgn:7029392"],"placetype":["aat:300008347"],"id":7377619,"name:xx":"Las Calaveras"}}
>>>>>>> 03f74aca74312dbeaf24d7e61306dd6a786dc3d0
