{
  "id": 7532651,
  "type": "Feature",
  "properties": {
    "tgn:hierarchy":[
        "tgn:7532651",
        "tgn:7001242",
        "tgn:7016833",
        "tgn:1001091",
        "tgn:7029392"
    ],
    "tgn:id":7532651,
    "tgn:name":"Masjid F\u0101\u0163imah an Nabaw\u012byah",
    "tgn:placetype":[
        "aat:300007544"
    ]
},
  "bbox": [],
  "geometry": {"coordinates":[31.260849,30.039153],"type":"Point"}
}