<<<<<<< HEAD
{
  "id": 7178673,
  "type": "Feature",
  "properties": {
    "tgn:hierarchy":[
        "tgn:7178673",
        "tgn:7000096",
        "tgn:1000003",
        "tgn:7000084",
        "tgn:7029392"
    ],
    "tgn:id":7178673,
    "tgn:name":"Hammerteich",
    "tgn:placetype":[
        "aat:300008680"
    ]
},
  "bbox": [],
  "geometry": {"coordinates":[13.55,51.6],"type":"Point"}
}
=======
{"geometry":{"type":"Point","coordinates":[13.550000,51.600000]},"type":"Feature","properties":{"hierarchy":["tgn:7178673","tgn:7000096","tgn:1000003","tgn:7000084","tgn:7029392"],"placetype":["aat:300008680"],"id":7178673,"name:xx":"Hammerteich"}}
>>>>>>> 03f74aca74312dbeaf24d7e61306dd6a786dc3d0
