{
  "id": 2342727,
  "type": "Feature",
  "properties": {
    "tgn:hierarchy":[
        "tgn:2342727",
        "tgn:7002659",
        "tgn:1000001",
        "tgn:2000019",
        "tgn:7012149",
        "tgn:7029392"
    ],
    "tgn:id":2342727,
    "tgn:name":"Fuqua Pond",
    "tgn:placetype":[
        "aat:300006191"
    ]
},
  "bbox": [],
  "geometry": {"coordinates":[-86.5667,31.2667],"type":"Point"}
}