{
  "id": 7467782,
  "type": "Feature",
  "properties": {
    "tgn:hierarchy":[
        "tgn:7467782",
        "tgn:7469009",
        "tgn:1000004",
        "tgn:1000141",
        "tgn:7029392"
    ],
    "tgn:id":7467782,
    "tgn:name":"Changle",
    "tgn:placetype":[
        "aat:300008347"
    ]
},
  "bbox": [],
  "geometry": {"coordinates":[118.416667,24.45],"type":"Point"}
}