{
  "id": 7428988,
  "type": "Feature",
  "properties": {
    "tgn:hierarchy":[
        "tgn:7428988",
        "tgn:7005583",
        "tgn:1000001",
        "tgn:7005560",
        "tgn:7029392"
    ],
    "tgn:id":7428988,
    "tgn:name":"Charco de Dimas, R\u00edo",
    "tgn:placetype":[
        "aat:300008699"
    ]
},
  "bbox": [],
  "geometry": {"coordinates":[-104.283333,23.683333],"type":"Point"}
}