{
  "id": 2173147,
  "type": "Feature",
  "properties": {
    "tgn:hierarchy":[
        "tgn:2173147",
        "tgn:7019618",
        "tgn:1000001",
        "tgn:7012149",
        "tgn:7007564",
        "tgn:7029392"
    ],
    "tgn:id":2173147,
    "tgn:name":"Bingham Hill",
    "tgn:placetype":[
        "aat:300008798"
    ]
},
  "bbox": [],
  "geometry": {"coordinates":[-72.2667,43.0167],"type":"Point"}
}