{
  "id": 7135992,
  "type": "Feature",
  "properties": {
    "tgn:hierarchy":[
        "tgn:7135992",
        "tgn:7003692",
        "tgn:1000003",
        "tgn:7000084",
        "tgn:7029392"
    ],
    "tgn:id":7135992,
    "tgn:name":"Schlo\u00df Morstein",
    "tgn:placetype":[
        "aat:300006891"
    ]
},
  "bbox": [],
  "geometry": {"coordinates":[9.881944,49.221389],"type":"Point"}
}