<<<<<<< HEAD
{
  "id": 2156918,
  "type": "Feature",
  "properties": {
    "tgn:hierarchy":[
        "tgn:2156918",
        "tgn:1000001",
        "tgn:7012149",
        "tgn:1002815",
        "tgn:7007922",
        "tgn:7029392"
    ],
    "tgn:id":2156918,
    "tgn:name":"Beaumont",
    "tgn:placetype":[
        "aat:300008347"
    ]
},
  "bbox": [],
  "geometry": {"coordinates":[-88.1,42.7333],"type":"Point"}
}
=======
{"geometry":{"type":"Point","coordinates":[-88.100000,42.733300]},"type":"Feature","properties":{"hierarchy":["tgn:2156918","tgn:1000001","tgn:7012149","tgn:1002815","tgn:7007922","tgn:7029392"],"placetype":["aat:300008347"],"id":2156918,"name:xx":"Beaumont"}}
>>>>>>> 03f74aca74312dbeaf24d7e61306dd6a786dc3d0
