{
  "id": 7210512,
  "type": "Feature",
  "properties": {
    "tgn:hierarchy":[
        "tgn:7210512",
        "tgn:1000003",
        "tgn:7003688",
        "tgn:7000084",
        "tgn:7029392"
    ],
    "tgn:id":7210512,
    "tgn:name":"Bauhof",
    "tgn:placetype":[
        "aat:300000206"
    ]
},
  "bbox": [],
  "geometry": {"coordinates":[10.616667,54.133333],"type":"Point"}
}