{
  "id": 7365078,
  "type": "Feature",
  "properties": {
    "tgn:hierarchy":[
        "tgn:7365078",
        "tgn:1000001",
        "tgn:7005601",
        "tgn:7005560",
        "tgn:7029392"
    ],
    "tgn:id":7365078,
    "tgn:name":"El Ranchito",
    "tgn:placetype":[
        "aat:300008347"
    ]
},
  "bbox": [],
  "geometry": {"coordinates":[-101.416667,22.516667],"type":"Point"}
}