{
  "id": 2614922,
  "type": "Feature",
  "properties": {
    "tgn:hierarchy":[
        "tgn:2614922",
        "tgn:1000001",
        "tgn:7012149",
        "tgn:1002611",
        "tgn:7007706",
        "tgn:7029392"
    ],
    "tgn:id":2614922,
    "tgn:name":"Reno Side Cut",
    "tgn:placetype":[
        "aat:300006075"
    ]
},
  "bbox": [],
  "geometry": {"coordinates":[-83.2833,41.65],"type":"Point"}
}