{
  "id": 2368618,
  "type": "Feature",
  "properties": {
    "tgn:hierarchy":[
        "tgn:2368618",
        "tgn:1000001",
        "tgn:7016172",
        "tgn:7012149",
        "tgn:2000175",
        "tgn:7029392"
    ],
    "tgn:id":2368618,
    "tgn:name":"Gulf Mountain",
    "tgn:placetype":[
        "aat:300008798"
    ]
},
  "bbox": [],
  "geometry": {"coordinates":[-92.6167,35.5333],"type":"Point"}
}