{
  "id": 7221068,
  "type": "Feature",
  "properties": {
    "tgn:hierarchy":[
        "tgn:7221068",
        "tgn:7002748",
        "tgn:7001399",
        "tgn:1000003",
        "tgn:1000074",
        "tgn:7029392"
    ],
    "tgn:id":7221068,
    "tgn:name":"Marath\u00e9a",
    "tgn:placetype":[
        "aat:300008347"
    ]
},
  "bbox": [],
  "geometry": {"coordinates":[21.995833,39.53],"type":"Point"}
}