<<<<<<< HEAD
{
  "id": 7051577,
  "type": "Feature",
  "properties": {
    "tgn:hierarchy":[
        "tgn:7051577",
        "tgn:7002996",
        "tgn:1000003",
        "tgn:7002997",
        "tgn:1000080",
        "tgn:7029392"
    ],
    "tgn:id":7051577,
    "tgn:name":"Musano",
    "tgn:placetype":[
        "aat:300008347"
    ]
},
  "bbox": [],
  "geometry": {"coordinates":[12.114444,45.726111],"type":"Point"}
}
=======
{"geometry":{"type":"Point","coordinates":[12.114444,45.726111]},"type":"Feature","properties":{"hierarchy":["tgn:7051577","tgn:7002996","tgn:1000003","tgn:7002997","tgn:1000080","tgn:7029392"],"placetype":["aat:300008347"],"id":7051577,"name:xx":"Musano"}}
>>>>>>> 03f74aca74312dbeaf24d7e61306dd6a786dc3d0
