<<<<<<< HEAD
{
  "id": 2155976,
  "type": "Feature",
  "properties": {
    "tgn:hierarchy":[
        "tgn:2155976",
        "tgn:1000001",
        "tgn:7006451",
        "tgn:2000092",
        "tgn:7012149",
        "tgn:7029392"
    ],
    "tgn:id":2155976,
    "tgn:name":"Bear Wallow Canyon",
    "tgn:placetype":[
        "aat:300008761"
    ]
},
  "bbox": [],
  "geometry": {"coordinates":[-111.7,34.8667],"type":"Point"}
}
=======
{"geometry":{"type":"Point","coordinates":[-111.700000,34.866700]},"type":"Feature","properties":{"hierarchy":["tgn:2155976","tgn:1000001","tgn:7006451","tgn:2000092","tgn:7012149","tgn:7029392"],"placetype":["aat:300008761"],"id":2155976,"name:xx":"Bear Wallow Canyon"}}
>>>>>>> 03f74aca74312dbeaf24d7e61306dd6a786dc3d0
