{
  "id": 1054740,
  "type": "Feature",
  "properties": {
    "tgn:hierarchy":[
        "tgn:1054740",
        "tgn:1000004",
        "tgn:1003555",
        "tgn:7018214",
        "tgn:7002435",
        "tgn:7029392"
    ],
    "tgn:id":1054740,
    "tgn:name":"Yessentuki",
    "tgn:placetype":[
        "aat:300008347"
    ]
},
  "bbox": [],
  "geometry": {"coordinates":[42.8833,44.05],"type":"Point"}
}