{
  "id": 7542413,
  "type": "Feature",
  "properties": {
    "tgn:hierarchy":[
        "tgn:7542413",
        "tgn:7001242",
        "tgn:1001059",
        "tgn:7016833",
        "tgn:7029392"
    ],
    "tgn:id":7542413,
    "tgn:name":"Tur'at ash Shuwan al 'Uly\u0101",
    "tgn:placetype":[
        "aat:300006075"
    ]
},
  "bbox": [],
  "geometry": {"coordinates":[31.455636,30.881706],"type":"Point"}
}