{
  "id": 2481785,
  "type": "Feature",
  "properties": {
    "tgn:hierarchy":[
        "tgn:2481785",
        "tgn:1000001",
        "tgn:7012149",
        "tgn:1002789",
        "tgn:7007710",
        "tgn:7029392"
    ],
    "tgn:id":2481785,
    "tgn:name":"Landis Lake",
    "tgn:placetype":[
        "aat:300006191"
    ]
},
  "bbox": [],
  "geometry": {"coordinates":[-74.95,41.1333],"type":"Point"}
}