{
  "id": 1008239,
  "type": "Feature",
  "properties": {
    "tgn:hierarchy":[
        "tgn:1008239",
        "tgn:1001069",
        "tgn:7001242",
        "tgn:1000201",
        "tgn:7029392"
    ],
    "tgn:id":1008239,
    "tgn:name":"Mukawwar",
    "tgn:placetype":[
        "aat:300008791"
    ]
},
  "bbox": [],
  "geometry": {"coordinates":[37.2833,20.8333],"type":"Point"}
}