{
  "id": 2334614,
  "type": "Feature",
  "properties": {
    "tgn:hierarchy":[
        "tgn:2334614",
        "tgn:1000001",
        "tgn:7012149",
        "tgn:2001764",
        "tgn:7007712",
        "tgn:7029392"
    ],
    "tgn:id":2334614,
    "tgn:name":"Forestwood Estates",
    "tgn:placetype":[
        "aat:300008347"
    ]
},
  "bbox": [],
  "geometry": {"coordinates":[-80.9333,34.0833],"type":"Point"}
}