{
  "id": 2524958,
  "type": "Feature",
  "properties": {
    "tgn:hierarchy":[
        "tgn:2524958",
        "tgn:1000001",
        "tgn:7012149",
        "tgn:7007826",
        "tgn:7029392"
    ],
    "tgn:id":2524958,
    "tgn:name":"Morris Branch",
    "tgn:placetype":[
        "aat:300008699"
    ]
},
  "bbox": [],
  "geometry": {"coordinates":[-97.4667,33.2167],"type":"Point"}
}