<<<<<<< HEAD
{
  "id": 2766945,
  "type": "Feature",
  "properties": {
    "tgn:hierarchy":[
        "tgn:2766945",
        "tgn:1000001",
        "tgn:2001734",
        "tgn:7012149",
        "tgn:7007712",
        "tgn:7029392"
    ],
    "tgn:id":2766945,
    "tgn:name":"White Point Landing",
    "tgn:placetype":[
        "aat:300008347"
    ]
},
  "bbox": [],
  "geometry": {"coordinates":[-80.2667,32.6333],"type":"Point"}
}
=======
{"geometry":{"type":"Point","coordinates":[-80.266700,32.633300]},"type":"Feature","properties":{"hierarchy":["tgn:2766945","tgn:1000001","tgn:2001734","tgn:7012149","tgn:7007712","tgn:7029392"],"placetype":["aat:300008347"],"id":2766945,"name:xx":"White Point Landing"}}
>>>>>>> 03f74aca74312dbeaf24d7e61306dd6a786dc3d0
