{
  "id": 2444816,
  "type": "Feature",
  "properties": {
    "tgn:hierarchy":[
        "tgn:2444816",
        "tgn:1000001",
        "tgn:1002283",
        "tgn:7012149",
        "tgn:7007520",
        "tgn:7029392"
    ],
    "tgn:id":2444816,
    "tgn:name":"Lehman Drain",
    "tgn:placetype":[
        "aat:300006075"
    ]
},
  "bbox": [],
  "geometry": {"coordinates":[-84.7667,42.8833],"type":"Point"}
}