{
  "id": 1035326,
  "type": "Feature",
  "properties": {
    "tgn:hierarchy":[
        "tgn:1035326",
        "tgn:1000003",
        "tgn:7002889",
        "tgn:1000070",
        "tgn:7029392"
    ],
    "tgn:id":1035326,
    "tgn:name":"Saint-G\u00e9ry",
    "tgn:placetype":[
        "aat:300008347"
    ]
},
  "bbox": [],
  "geometry": {"coordinates":[1.5667,44.4667],"type":"Point"}
}