{
  "id": 7061370,
  "type": "Feature",
  "properties": {
    "tgn:hierarchy":[
        "tgn:7061370",
        "tgn:7003669",
        "tgn:1000003",
        "tgn:7000084",
        "tgn:7029392"
    ],
    "tgn:id":7061370,
    "tgn:name":"Aschau",
    "tgn:placetype":[
        "aat:300000206"
    ]
},
  "bbox": [],
  "geometry": {"coordinates":[12.783333,47.866667],"type":"Point"}
}