<<<<<<< HEAD
{
  "id": 2150090,
  "type": "Feature",
  "properties": {
    "tgn:hierarchy":[
        "tgn:2150090",
        "tgn:2000664",
        "tgn:1000001",
        "tgn:7012149",
        "tgn:7007254",
        "tgn:7029392"
    ],
    "tgn:id":2150090,
    "tgn:name":"Barton Lake",
    "tgn:placetype":[
        "aat:300006191"
    ]
},
  "bbox": [],
  "geometry": {"coordinates":[-98.7667,38.45],"type":"Point"}
}
=======
{"geometry":{"type":"Point","coordinates":[-98.766700,38.450000]},"type":"Feature","properties":{"hierarchy":["tgn:2150090","tgn:2000664","tgn:1000001","tgn:7012149","tgn:7007254","tgn:7029392"],"placetype":["aat:300006191"],"id":2150090,"name:xx":"Barton Lake"}}
>>>>>>> 03f74aca74312dbeaf24d7e61306dd6a786dc3d0
