<<<<<<< HEAD
{
  "id": 2408891,
  "type": "Feature",
  "properties": {
    "tgn:hierarchy":[
        "tgn:2408891",
        "tgn:7006450",
        "tgn:1000001",
        "tgn:2124053",
        "tgn:7012149",
        "tgn:7029392"
    ],
    "tgn:id":2408891,
    "tgn:name":"Hyphen Gulch",
    "tgn:placetype":[
        "aat:300008761"
    ]
},
  "bbox": [],
  "geometry": {"coordinates":[-149.05,62.3167],"type":"Point"}
}
=======
{"geometry":{"type":"Point","coordinates":[-149.050000,62.316700]},"type":"Feature","properties":{"hierarchy":["tgn:2408891","tgn:7006450","tgn:1000001","tgn:2124053","tgn:7012149","tgn:7029392"],"placetype":["aat:300008761"],"id":2408891,"name:xx":"Hyphen Gulch"}}
>>>>>>> 03f74aca74312dbeaf24d7e61306dd6a786dc3d0
