{
  "id": 2018770,
  "type": "Feature",
  "properties": {
    "tgn:hierarchy":[
        "tgn:2018770",
        "tgn:1000001",
        "tgn:7012149",
        "tgn:1002749",
        "tgn:7007240",
        "tgn:7029392"
    ],
    "tgn:id":2018770,
    "tgn:name":"Buena Vista",
    "tgn:placetype":[
        "aat:300008347"
    ]
},
  "bbox": [],
  "geometry": {"coordinates":[-81.5167,28.3667],"type":"Point"}
}