<<<<<<< HEAD
{
  "id": 7118323,
  "type": "Feature",
  "properties": {
    "tgn:hierarchy":[
        "tgn:7118323",
        "tgn:1000003",
        "tgn:7000094",
        "tgn:7000084",
        "tgn:7029392"
    ],
    "tgn:id":7118323,
    "tgn:name":"Pantelitz",
    "tgn:placetype":[
        "aat:300008347"
    ]
},
  "bbox": [],
  "geometry": {"coordinates":[12.966667,54.3],"type":"Point"}
}
=======
{"geometry":{"type":"Point","coordinates":[12.966667,54.300000]},"type":"Feature","properties":{"hierarchy":["tgn:7118323","tgn:1000003","tgn:7000094","tgn:7000084","tgn:7029392"],"placetype":["aat:300008347"],"id":7118323,"name:xx":"Pantelitz"}}
>>>>>>> 03f74aca74312dbeaf24d7e61306dd6a786dc3d0
