{
  "id": 7182478,
  "type": "Feature",
  "properties": {
    "tgn:hierarchy":[
        "tgn:7182478",
        "tgn:1000003",
        "tgn:7000094",
        "tgn:7000084",
        "tgn:7029392"
    ],
    "tgn:id":7182478,
    "tgn:name":"Friedrichshof",
    "tgn:placetype":[
        "aat:300008347"
    ]
},
  "bbox": [],
  "geometry": {"coordinates":[12.516667,53.966667],"type":"Point"}
}