{
  "id": 1005988,
  "type": "Feature",
  "properties": {
    "tgn:hierarchy":[
        "tgn:1005988",
        "tgn:7003669",
        "tgn:1000003",
        "tgn:7000084",
        "tgn:7004333",
        "tgn:7029392"
    ],
    "tgn:id":1005988,
    "tgn:name":"Schwabing",
    "tgn:placetype":[
        "aat:300000745",
        "aat:300387332"
    ]
},
  "bbox": [],
  "geometry": {"coordinates":[11.583333,48.166667],"type":"Point"}
}