<<<<<<< HEAD
{
  "id": 2760155,
  "type": "Feature",
  "properties": {
    "tgn:hierarchy":[
        "tgn:2760155",
        "tgn:1000001",
        "tgn:7012149",
        "tgn:2001847",
        "tgn:7007825",
        "tgn:7029392"
    ],
    "tgn:id":2760155,
    "tgn:name":"West Fork Pond Creek",
    "tgn:placetype":[
        "aat:300008706"
    ]
},
  "bbox": [],
  "geometry": {"coordinates":[-87.0167,36.1333],"type":"Point"}
}
=======
{"geometry":{"type":"Point","coordinates":[-87.016700,36.133300]},"type":"Feature","properties":{"hierarchy":["tgn:2760155","tgn:1000001","tgn:7012149","tgn:2001847","tgn:7007825","tgn:7029392"],"placetype":["aat:300008706"],"id":2760155,"name:xx":"West Fork Pond Creek"}}
>>>>>>> 03f74aca74312dbeaf24d7e61306dd6a786dc3d0
