{
  "id": 2760155,
  "type": "Feature",
  "properties": {
    "tgn:hierarchy":[
        "tgn:2760155",
        "tgn:1000001",
        "tgn:7012149",
        "tgn:2001847",
        "tgn:7007825",
        "tgn:7029392"
    ],
    "tgn:id":2760155,
    "tgn:name":"West Fork Pond Creek",
    "tgn:placetype":[
        "aat:300008706"
    ]
},
  "bbox": [],
  "geometry": {"coordinates":[-87.0167,36.1333],"type":"Point"}
}