{
  "id": 2717425,
  "type": "Feature",
  "properties": {
    "tgn:hierarchy":[
        "tgn:2717425",
        "tgn:1000001",
        "tgn:7006451",
        "tgn:7012149",
        "tgn:2000098",
        "tgn:7029392"
    ],
    "tgn:id":2717425,
    "tgn:name":"Thistle Flat Pond",
    "tgn:placetype":[
        "aat:300006191"
    ]
},
  "bbox": [],
  "geometry": {"coordinates":[-113.5167,36.6333],"type":"Point"}
}