{
  "id": 7501132,
  "type": "Feature",
  "properties": {
    "tgn:hierarchy":[
        "tgn:7501132",
        "tgn:7488858",
        "tgn:1000004",
        "tgn:1000141",
        "tgn:7029392"
    ],
    "tgn:id":7501132,
    "tgn:name":"Fenghuang Sihao Qiao",
    "tgn:placetype":[
        "aat:300007836"
    ]
},
  "bbox": [],
  "geometry": {"coordinates":[120.813889,23.728333],"type":"Point"}
}