{
  "id": 2438405,
  "type": "Feature",
  "properties": {
    "tgn:hierarchy":[
        "tgn:2438405",
        "tgn:1000001",
        "tgn:2001702",
        "tgn:7012149",
        "tgn:7007708",
        "tgn:7029392"
    ],
    "tgn:id":2438405,
    "tgn:name":"Kings Landing",
    "tgn:placetype":[
        "aat:300008347"
    ]
},
  "bbox": [],
  "geometry": {"coordinates":[-124.2167,43.25],"type":"Point"}
}