{
  "id": 2660593,
  "type": "Feature",
  "properties": {
    "tgn:hierarchy":[
        "tgn:2660593",
        "tgn:1000001",
        "tgn:7012149",
        "tgn:2001255",
        "tgn:7007523",
        "tgn:7029392"
    ],
    "tgn:id":2660593,
    "tgn:name":"Shook Creek",
    "tgn:placetype":[
        "aat:300008706"
    ]
},
  "bbox": [],
  "geometry": {"coordinates":[-90.2833,37.0333],"type":"Point"}
}