{
  "id": 2701700,
  "type": "Feature",
  "properties": {
    "tgn:hierarchy":[
        "tgn:2701700",
        "tgn:1000001",
        "tgn:7012149",
        "tgn:2000205",
        "tgn:7007158",
        "tgn:7029392"
    ],
    "tgn:id":2701700,
    "tgn:name":"Sugarloaf",
    "tgn:placetype":[
        "aat:300008798"
    ]
},
  "bbox": [],
  "geometry": {"coordinates":[-105.35,38.1167],"type":"Point"}
}