{
  "id": 2249851,
  "type": "Feature",
  "properties": {
    "tgn:hierarchy":[
        "tgn:2249851",
        "tgn:1000001",
        "tgn:7014423",
        "tgn:7012149",
        "tgn:7007517",
        "tgn:7029392"
    ],
    "tgn:id":2249851,
    "tgn:name":"College Pond",
    "tgn:placetype":[
        "aat:300008680"
    ]
},
  "bbox": [],
  "geometry": {"coordinates":[-70.65,41.8667],"type":"Point"}
}