{
  "id": 1105603,
  "type": "Feature",
  "properties": {
    "tgn:hierarchy":[
        "tgn:1105603",
        "tgn:1000003",
        "tgn:7003678",
        "tgn:7000084",
        "tgn:7029392"
    ],
    "tgn:id":1105603,
    "tgn:name":"Malibocus",
    "tgn:placetype":[
        "aat:300008795"
    ]
},
  "bbox": [],
  "geometry": {"coordinates":[8.6833,49.7333],"type":"Point"}
}