{
  "id": 2529141,
  "type": "Feature",
  "properties": {
    "tgn:hierarchy":[
        "tgn:2529141",
        "tgn:1000001",
        "tgn:7012149",
        "tgn:2002293",
        "tgn:7013961",
        "tgn:7029392"
    ],
    "tgn:id":2529141,
    "tgn:name":"Mud Fork",
    "tgn:placetype":[
        "aat:300008699"
    ]
},
  "bbox": [],
  "geometry": {"coordinates":[-81.25,38.6833],"type":"Point"}
}