{
  "id": 2074769,
  "type": "Feature",
  "properties": {
    "tgn:hierarchy":[
        "tgn:2074769",
        "tgn:1000001",
        "tgn:7012149",
        "tgn:2001508",
        "tgn:7007709",
        "tgn:7029392"
    ],
    "tgn:id":2074769,
    "tgn:name":"Gateway",
    "tgn:placetype":[
        "aat:300008347",
        "aat:300387210"
    ]
},
  "bbox": [],
  "geometry": {"coordinates":[-83.3167,35.4167],"type":"Point"}
}