{
  "id": 7500405,
  "type": "Feature",
  "properties": {
    "tgn:hierarchy":[
        "tgn:7500405",
        "tgn:1000004",
        "tgn:7004300",
        "tgn:1000141",
        "tgn:7029392"
    ],
    "tgn:id":7500405,
    "tgn:name":"Hou Wan",
    "tgn:placetype":[
        "aat:300266557"
    ]
},
  "bbox": [],
  "geometry": {"coordinates":[119.491111,23.572778],"type":"Point"}
}