{
  "id": 2400831,
  "type": "Feature",
  "properties": {
    "tgn:hierarchy":[
        "tgn:2400831",
        "tgn:1000001",
        "tgn:7012149",
        "tgn:2001713",
        "tgn:7007708",
        "tgn:7029392"
    ],
    "tgn:id":2400831,
    "tgn:name":"Horse Range",
    "tgn:placetype":[
        "aat:300386831"
    ]
},
  "bbox": [],
  "geometry": {"coordinates":[-123.6833,42.65],"type":"Point"}
}