{
  "id": 7499755,
  "type": "Feature",
  "properties": {
    "tgn:hierarchy":[
        "tgn:7499755",
        "tgn:7488858",
        "tgn:1000004",
        "tgn:1000141",
        "tgn:7029392"
    ],
    "tgn:id":7499755,
    "tgn:name":"Junda Nanxi",
    "tgn:placetype":[
        "aat:300008699"
    ]
},
  "bbox": [],
  "geometry": {"coordinates":[121.012128,23.575673],"type":"Point"}
}