{
  "id": 2285452,
  "type": "Feature",
  "properties": {
    "tgn:hierarchy":[
        "tgn:2285452",
        "tgn:1000001",
        "tgn:7012149",
        "tgn:2000737",
        "tgn:7007254",
        "tgn:7029392"
    ],
    "tgn:id":2285452,
    "tgn:name":"Devils Ditch",
    "tgn:placetype":[
        "aat:300008699"
    ]
},
  "bbox": [],
  "geometry": {"coordinates":[-97.8333,37.8667],"type":"Point"}
}