{
  "id": 4003518,
  "type": "Feature",
  "properties": {
    "tgn:hierarchy":[
        "tgn:4003518",
        "tgn:7002445",
        "tgn:1000003",
        "tgn:7008153",
        "tgn:7008591",
        "tgn:7029392"
    ],
    "tgn:id":4003518,
    "tgn:name:en":"Edenhall",
    "tgn:placetype":[
        "aat:300008347"
    ]
},
  "bbox": [],
  "geometry": {"coordinates":[-2.666667,54.666667],"type":"Point"}
}