{
  "id": 2535959,
  "type": "Feature",
  "properties": {
    "tgn:hierarchy":[
        "tgn:2535959",
        "tgn:1000001",
        "tgn:7012149",
        "tgn:2001440",
        "tgn:7007566",
        "tgn:7029392"
    ],
    "tgn:id":2535959,
    "tgn:name":"National Mine",
    "tgn:placetype":[
        "aat:300000390"
    ]
},
  "bbox": [],
  "geometry": {"coordinates":[-109.0333,32.25],"type":"Point"}
}