{
  "id": 7015115,
  "type": "Feature",
  "properties": {
    "tgn:hierarchy":[
        "tgn:7015115",
        "tgn:1000003",
        "tgn:7006670",
        "tgn:7029392"
    ],
    "tgn:id":7015115,
    "tgn:name":"Ljutomer, Ob\u010dina",
    "tgn:placetype":[
        "aat:300387064",
        "aat:300387081"
    ]
},
  "bbox": [],
  "geometry": {"coordinates":[16.1333,46.5333],"type":"Point"}
}