{
  "id": 2044432,
  "type": "Feature",
  "properties": {
    "tgn:hierarchy":[
        "tgn:2044432",
        "tgn:1000001",
        "tgn:2000922",
        "tgn:7012149",
        "tgn:7007515",
        "tgn:7029392"
    ],
    "tgn:id":2044432,
    "tgn:name":"Bayside",
    "tgn:placetype":[
        "aat:300008347",
        "aat:300387210"
    ]
},
  "bbox": [],
  "geometry": {"coordinates":[-68.4167,44.45],"type":"Point"}
}