<<<<<<< HEAD
{
  "id": 2764384,
  "type": "Feature",
  "properties": {
    "tgn:hierarchy":[
        "tgn:2764384",
        "tgn:1000001",
        "tgn:2002108",
        "tgn:7012149",
        "tgn:7007827",
        "tgn:7029392"
    ],
    "tgn:id":2764384,
    "tgn:name":"Whetstone Creek",
    "tgn:placetype":[
        "aat:300008706"
    ]
},
  "bbox": [],
  "geometry": {"coordinates":[-111.1667,39.3667],"type":"Point"}
}
=======
{"geometry":{"type":"Point","coordinates":[-111.166700,39.366700]},"type":"Feature","properties":{"hierarchy":["tgn:2764384","tgn:1000001","tgn:2002108","tgn:7012149","tgn:7007827","tgn:7029392"],"placetype":["aat:300008706"],"id":2764384,"name:xx":"Whetstone Creek"}}
>>>>>>> 03f74aca74312dbeaf24d7e61306dd6a786dc3d0
