{
  "id": 2645530,
  "type": "Feature",
  "properties": {
    "tgn:hierarchy":[
        "tgn:2645530",
        "tgn:1000001",
        "tgn:7012149",
        "tgn:2000342",
        "tgn:7007248",
        "tgn:7029392"
    ],
    "tgn:id":2645530,
    "tgn:name":"Sawdust Bay",
    "tgn:placetype":[
        "aat:300008905"
    ]
},
  "bbox": [],
  "geometry": {"coordinates":[-81.2333,32.4833],"type":"Point"}
}