{
  "id": 2671794,
  "type": "Feature",
  "properties": {
    "tgn:hierarchy":[
        "tgn:2671794",
        "tgn:7002659",
        "tgn:1000001",
        "tgn:7012149",
        "tgn:2000048",
        "tgn:7029392"
    ],
    "tgn:id":2671794,
    "tgn:name":"Smith Pond",
    "tgn:placetype":[
        "aat:300006191"
    ]
},
  "bbox": [],
  "geometry": {"coordinates":[-88.2333,30.5667],"type":"Point"}
}