{
  "id": 2024499,
  "type": "Feature",
  "properties": {
    "tgn:hierarchy":[
        "tgn:2024499",
        "tgn:1000001",
        "tgn:7012149",
        "tgn:2000436",
        "tgn:7007248",
        "tgn:7029392"
    ],
    "tgn:id":2024499,
    "tgn:name":"The Rock",
    "tgn:placetype":[
        "aat:300008347"
    ]
},
  "bbox": [],
  "geometry": {"coordinates":[-84.2333,32.95],"type":"Point"}
}