{
  "id": 2201802,
  "type": "Feature",
  "properties": {
    "tgn:hierarchy":[
        "tgn:2201802",
        "tgn:1000001",
        "tgn:7012149",
        "tgn:2001751",
        "tgn:7007712",
        "tgn:7029392"
    ],
    "tgn:id":2201802,
    "tgn:name":"Buck Drive",
    "tgn:placetype":[
        "aat:300008905"
    ]
},
  "bbox": [],
  "geometry": {"coordinates":[-81.0833,32.5167],"type":"Point"}
}