{
  "id": 7502126,
  "type": "Feature",
  "properties": {
    "tgn:hierarchy":[
        "tgn:7502126",
        "tgn:1000004",
        "tgn:7471332",
        "tgn:1000141",
        "tgn:7029392"
    ],
    "tgn:id":7502126,
    "tgn:name":"Xiaruliao",
    "tgn:placetype":[
        "aat:300008347"
    ]
},
  "bbox": [],
  "geometry": {"coordinates":[120.97,24.911944],"type":"Point"}
}