{
  "id": 2787309,
  "type": "Feature",
  "properties": {
    "tgn:hierarchy":[
        "tgn:2787309",
        "tgn:1000001",
        "tgn:7012149",
        "tgn:7019676",
        "tgn:7007566",
        "tgn:7029392"
    ],
    "tgn:id":2787309,
    "tgn:name":"Zuni Canal",
    "tgn:placetype":[
        "aat:300006075"
    ]
},
  "bbox": [],
  "geometry": {"coordinates":[-108.8333,35.0833],"type":"Point"}
}