{
  "id": 1102025,
  "type": "Feature",
  "properties": {
    "tgn:hierarchy":[
        "tgn:1102025",
        "tgn:1000001",
        "tgn:7012149",
        "tgn:7007919",
        "tgn:7029392"
    ],
    "tgn:id":1102025,
    "tgn:name":"Richmond National Battlefield Park",
    "tgn:placetype":[
        "aat:300000835",
        "aat:300000833"
    ]
},
  "bbox": [],
  "geometry": {"coordinates":[-77.3667,37.4167],"type":"Point"}
}