{
  "id": 2777560,
  "type": "Feature",
  "properties": {
    "tgn:hierarchy":[
        "tgn:2777560",
        "tgn:1000001",
        "tgn:7012149",
        "tgn:7007157",
        "tgn:2000188",
        "tgn:7029392"
    ],
    "tgn:id":2777560,
    "tgn:name":"Winnibulli Mountain",
    "tgn:placetype":[
        "aat:300008798"
    ]
},
  "bbox": [],
  "geometry": {"coordinates":[-122.1333,40.8333],"type":"Point"}
}