{
  "id": 2716433,
  "type": "Feature",
  "properties": {
    "tgn:hierarchy":[
        "tgn:2716433",
        "tgn:1000001",
        "tgn:7012149",
        "tgn:2002129",
        "tgn:7007827",
        "tgn:7029392"
    ],
    "tgn:id":2716433,
    "tgn:name":"The Hermitage",
    "tgn:placetype":[
        "aat:300008347"
    ]
},
  "bbox": [],
  "geometry": {"coordinates":[-111.8667,41.25],"type":"Point"}
}