{
  "id": 7260389,
  "type": "Feature",
  "properties": {
    "tgn:hierarchy":[
        "tgn:7260389",
        "tgn:1000003",
        "tgn:7006951",
        "tgn:7016845",
        "tgn:7029392"
    ],
    "tgn:id":7260389,
    "tgn:name:nl":"De Krim",
    "tgn:placetype":[
        "aat:300387502"
    ]
},
  "bbox": [],
  "geometry": {"coordinates":[4.833333,53.166667],"type":"Point"}
}