<<<<<<< HEAD
{
  "id": 2769063,
  "type": "Feature",
  "properties": {
    "tgn:hierarchy":[
        "tgn:2769063",
        "tgn:1000001",
        "tgn:7012149",
        "tgn:2000931",
        "tgn:7007515",
        "tgn:7029392"
    ],
    "tgn:id":2769063,
    "tgn:name":"Whitten Hill",
    "tgn:placetype":[
        "aat:300008798"
    ]
},
  "bbox": [],
  "geometry": {"coordinates":[-69.3,44.4667],"type":"Point"}
}
=======
{"geometry":{"type":"Point","coordinates":[-69.300000,44.466700]},"type":"Feature","properties":{"hierarchy":["tgn:2769063","tgn:1000001","tgn:7012149","tgn:2000931","tgn:7007515","tgn:7029392"],"placetype":["aat:300008798"],"id":2769063,"name:xx":"Whitten Hill"}}
>>>>>>> 03f74aca74312dbeaf24d7e61306dd6a786dc3d0
