{
  "id": 2307177,
  "type": "Feature",
  "properties": {
    "tgn:hierarchy":[
        "tgn:2307177",
        "tgn:1000001",
        "tgn:7012149",
        "tgn:2001309",
        "tgn:7007524",
        "tgn:7029392"
    ],
    "tgn:id":2307177,
    "tgn:name":"East Fork North Fork Teton River",
    "tgn:placetype":[
        "aat:300008707"
    ]
},
  "bbox": [],
  "geometry": {"coordinates":[-112.75,47.9833],"type":"Point"}
}