{
  "id": 7258686,
  "type": "Feature",
  "properties": {
    "tgn:concordances":{
        "gn:id":"2758506"
    },
    "tgn:hierarchy":[
        "tgn:7258686",
        "tgn:1000003",
        "tgn:7003632",
        "tgn:7016845",
        "tgn:7029392"
    ],
    "tgn:id":7258686,
    "tgn:name:nl":"Bovenberg",
    "tgn:placetype":[
        "aat:300008347"
    ]
},
  "bbox": [],
  "geometry": {"coordinates":[4.833333,51.95],"type":"Point"}
}