{
  "id": 1120015,
  "type": "Feature",
  "properties": {
    "tgn:hierarchy":[
        "tgn:1120015",
        "tgn:1000001",
        "tgn:7012149",
        "tgn:1002556",
        "tgn:7007706",
        "tgn:7029392"
    ],
    "tgn:id":1120015,
    "tgn:name":"Knox Lake",
    "tgn:placetype":[
        "aat:300006191"
    ]
},
  "bbox": [],
  "geometry": {"coordinates":[-82.5167,40.4833],"type":"Point"}
}