{
  "id": 2227301,
  "type": "Feature",
  "properties": {
    "tgn:hierarchy":[
        "tgn:2227301",
        "tgn:1000001",
        "tgn:7012149",
        "tgn:2002113",
        "tgn:7007827",
        "tgn:7029392"
    ],
    "tgn:id":2227301,
    "tgn:name":"Cave Point",
    "tgn:placetype":[
        "aat:300008850"
    ]
},
  "bbox": [],
  "geometry": {"coordinates":[-111.0167,37.2833],"type":"Point"}
}