<<<<<<< HEAD
{
  "id": 2403813,
  "type": "Feature",
  "properties": {
    "tgn:hierarchy":[
        "tgn:2403813",
        "tgn:1000001",
        "tgn:2000783",
        "tgn:7012149",
        "tgn:7007255",
        "tgn:7029392"
    ],
    "tgn:id":2403813,
    "tgn:name":"Howards Creek",
    "tgn:placetype":[
        "aat:300008706"
    ]
},
  "bbox": [],
  "geometry": {"coordinates":[-85.1833,36.7167],"type":"Point"}
}
=======
{"geometry":{"type":"Point","coordinates":[-85.183300,36.716700]},"type":"Feature","properties":{"hierarchy":["tgn:2403813","tgn:1000001","tgn:2000783","tgn:7012149","tgn:7007255","tgn:7029392"],"placetype":["aat:300008706"],"id":2403813,"name:xx":"Howards Creek"}}
>>>>>>> 03f74aca74312dbeaf24d7e61306dd6a786dc3d0
