{
  "id": 2403813,
  "type": "Feature",
  "properties": {
    "tgn:hierarchy":[
        "tgn:2403813",
        "tgn:1000001",
        "tgn:2000783",
        "tgn:7012149",
        "tgn:7007255",
        "tgn:7029392"
    ],
    "tgn:id":2403813,
    "tgn:name":"Howards Creek",
    "tgn:placetype":[
        "aat:300008706"
    ]
},
  "bbox": [],
  "geometry": {"coordinates":[-85.1833,36.7167],"type":"Point"}
}