{
  "id": 1087712,
  "type": "Feature",
  "properties": {
    "tgn:hierarchy":[
        "tgn:1087712",
        "tgn:7001242",
        "tgn:1000149",
        "tgn:1000899",
        "tgn:7029392"
    ],
    "tgn:id":1087712,
    "tgn:name":"Cassamba",
    "tgn:placetype":[
        "aat:300008347"
    ]
},
  "bbox": [],
  "geometry": {"coordinates":[20.3333,-13.1167],"type":"Point"}
}