{
  "id": 2004600,
  "type": "Feature",
  "properties": {
    "tgn:hierarchy":[
        "tgn:2004600",
        "tgn:7002659",
        "tgn:1000001",
        "tgn:7012149",
        "tgn:2000035",
        "tgn:7029392"
    ],
    "tgn:id":2004600,
    "tgn:name":"Mount Carmel",
    "tgn:placetype":[
        "aat:300008347",
        "aat:300387210"
    ]
},
  "bbox": [],
  "geometry": {"coordinates":[-85.7667,34.9333],"type":"Point"}
}