{
  "id": 7515891,
  "type": "Feature",
  "properties": {
    "tgn:hierarchy":[
        "tgn:7515891",
        "tgn:1009227",
        "tgn:7001866",
        "tgn:1000226",
        "tgn:1000006",
        "tgn:7029392"
    ],
    "tgn:id":7515891,
    "tgn:name:en":"Lillburn Stream",
    "tgn:placetype":[
        "aat:300008699"
    ]
},
  "bbox": [],
  "geometry": {"coordinates":[172.166667,-43.083333],"type":"Point"}
}