{
  "id": 7574324,
  "type": "Feature",
  "properties": {
    "tgn:hierarchy":[
        "tgn:7574324",
        "tgn:1000004",
        "tgn:7000198",
        "tgn:7016788",
        "tgn:7029392"
    ],
    "tgn:id":7574324,
    "tgn:name:en":"Jaitpur",
    "tgn:placetype":[
        "aat:300008347"
    ]
},
  "bbox": [],
  "geometry": {"coordinates":[74.06428,28.876959],"type":"Point"}
}