{
  "id": 2273426,
  "type": "Feature",
  "properties": {
    "tgn:hierarchy":[
        "tgn:2273426",
        "tgn:1000001",
        "tgn:7020676",
        "tgn:7012149",
        "tgn:7007256",
        "tgn:7029392"
    ],
    "tgn:id":2273426,
    "tgn:name":"Cypress Island",
    "tgn:placetype":[
        "aat:300008791"
    ]
},
  "bbox": [],
  "geometry": {"coordinates":[-92.8167,29.9167],"type":"Point"}
}