{
  "id": 2763835,
  "type": "Feature",
  "properties": {
    "tgn:hierarchy":[
        "tgn:2763835",
        "tgn:1000001",
        "tgn:7012149",
        "tgn:1002613",
        "tgn:7007710",
        "tgn:7029392"
    ],
    "tgn:id":2763835,
    "tgn:name":"Wheatfield Hollow",
    "tgn:placetype":[
        "aat:300008761"
    ]
},
  "bbox": [],
  "geometry": {"coordinates":[-77.3833,41.5167],"type":"Point"}
}