<<<<<<< HEAD
{
  "id": 2763835,
  "type": "Feature",
  "properties": {
    "tgn:hierarchy":[
        "tgn:2763835",
        "tgn:1000001",
        "tgn:7012149",
        "tgn:1002613",
        "tgn:7007710",
        "tgn:7029392"
    ],
    "tgn:id":2763835,
    "tgn:name":"Wheatfield Hollow",
    "tgn:placetype":[
        "aat:300008761"
    ]
},
  "bbox": [],
  "geometry": {"coordinates":[-77.3833,41.5167],"type":"Point"}
}
=======
{"geometry":{"type":"Point","coordinates":[-77.383300,41.516700]},"type":"Feature","properties":{"hierarchy":["tgn:2763835","tgn:1000001","tgn:7012149","tgn:1002613","tgn:7007710","tgn:7029392"],"placetype":["aat:300008761"],"id":2763835,"name:xx":"Wheatfield Hollow"}}
>>>>>>> 03f74aca74312dbeaf24d7e61306dd6a786dc3d0
