{
  "id": 7440302,
  "type": "Feature",
  "properties": {
    "tgn:hierarchy":[
        "tgn:7440302",
        "tgn:7005583",
        "tgn:1000001",
        "tgn:7005560",
        "tgn:7029392"
    ],
    "tgn:id":7440302,
    "tgn:name":"Santa Catarina",
    "tgn:placetype":[
        "aat:300008347"
    ]
},
  "bbox": [],
  "geometry": {"coordinates":[-106.383333,24.533333],"type":"Point"}
}