{
  "id": 1101651,
  "type": "Feature",
  "properties": {
    "tgn:hierarchy":[
        "tgn:1101651",
        "tgn:1001190",
        "tgn:1000004",
        "tgn:7000299",
        "tgn:7029392"
    ],
    "tgn:id":1101651,
    "tgn:name":"Kyeryong-san Kukrip Kongw\u014fn",
    "tgn:placetype":[
        "aat:300008189"
    ]
},
  "bbox": [],
  "geometry": {"coordinates":[127.2167,36.35],"type":"Point"}
}