<<<<<<< HEAD
{
  "id": 2250371,
  "type": "Feature",
  "properties": {
    "tgn:hierarchy":[
        "tgn:2250371",
        "tgn:1000001",
        "tgn:7012149",
        "tgn:2001291",
        "tgn:7007524",
        "tgn:7029392"
    ],
    "tgn:id":2250371,
    "tgn:name":"Coloma",
    "tgn:placetype":[
        "aat:300008347"
    ]
},
  "bbox": [],
  "geometry": {"coordinates":[-113.3667,46.8333],"type":"Point"}
}
=======
{"geometry":{"type":"Point","coordinates":[-113.366700,46.833300]},"type":"Feature","properties":{"hierarchy":["tgn:2250371","tgn:1000001","tgn:7012149","tgn:2001291","tgn:7007524","tgn:7029392"],"placetype":["aat:300008347"],"id":2250371,"name:xx":"Coloma"}}
>>>>>>> 03f74aca74312dbeaf24d7e61306dd6a786dc3d0
