{
  "id": 7558011,
  "type": "Feature",
  "properties": {
    "tgn:hierarchy":[
        "tgn:7558011",
        "tgn:1000004",
        "tgn:7000198",
        "tgn:7031783",
        "tgn:7029392"
    ],
    "tgn:id":7558011,
    "tgn:name:en":"P\u0101njw\u0101ra",
    "tgn:placetype":[
        "aat:300008347"
    ]
},
  "bbox": [],
  "geometry": {"coordinates":[87.096611,24.854054],"type":"Point"}
}