{
  "id": 1017276,
  "type": "Feature",
  "properties": {
    "tgn:hierarchy":[
        "tgn:1017276",
        "tgn:7005584",
        "tgn:1000001",
        "tgn:7005560",
        "tgn:7029392"
    ],
    "tgn:id":1017276,
    "tgn:name":"Comonfort",
    "tgn:placetype":[
        "aat:300008347"
    ]
},
  "bbox": [],
  "geometry": {"coordinates":[-100.766667,20.716667],"type":"Point"}
}