{
  "id": 7436486,
  "type": "Feature",
  "properties": {
    "tgn:hierarchy":[
        "tgn:7436486",
        "tgn:1000001",
        "tgn:7005589",
        "tgn:7005560",
        "tgn:7029392"
    ],
    "tgn:id":7436486,
    "tgn:name":"Soledad",
    "tgn:placetype":[
        "aat:300008347"
    ]
},
  "bbox": [],
  "geometry": {"coordinates":[-99.766667,25.483333],"type":"Point"}
}