{
  "id": 7276726,
  "type": "Feature",
  "properties": {
    "tgn:hierarchy":[
        "tgn:7276726",
        "tgn:1001657",
        "tgn:1000049",
        "tgn:1000002",
        "tgn:7029392"
    ],
    "tgn:id":7276726,
    "tgn:name":"Villa Se\u00f1or, Punta",
    "tgn:placetype":[
        "aat:300386846"
    ]
},
  "bbox": [],
  "geometry": {"coordinates":[-71.699444,-30.479167],"type":"Point"}
}