{
  "id": 2260219,
  "type": "Feature",
  "properties": {
    "tgn:hierarchy":[
        "tgn:2260219",
        "tgn:1000001",
        "tgn:2002106",
        "tgn:7012149",
        "tgn:7007827",
        "tgn:7029392"
    ],
    "tgn:id":2260219,
    "tgn:name":"Country Oaks",
    "tgn:placetype":[
        "aat:300008347"
    ]
},
  "bbox": [],
  "geometry": {"coordinates":[-111.9167,41.0833],"type":"Point"}
}