{
  "id": 2333974,
  "type": "Feature",
  "properties": {
    "tgn:hierarchy":[
        "tgn:2333974",
        "tgn:1000001",
        "tgn:7012149",
        "tgn:2001849",
        "tgn:7007825",
        "tgn:7029392"
    ],
    "tgn:id":2333974,
    "tgn:name":"Ford Hollow",
    "tgn:placetype":[
        "aat:300008761"
    ]
},
  "bbox": [],
  "geometry": {"coordinates":[-83.6167,36.45],"type":"Point"}
}