<<<<<<< HEAD
{
  "id": 2333974,
  "type": "Feature",
  "properties": {
    "tgn:hierarchy":[
        "tgn:2333974",
        "tgn:1000001",
        "tgn:7012149",
        "tgn:2001849",
        "tgn:7007825",
        "tgn:7029392"
    ],
    "tgn:id":2333974,
    "tgn:name":"Ford Hollow",
    "tgn:placetype":[
        "aat:300008761"
    ]
},
  "bbox": [],
  "geometry": {"coordinates":[-83.6167,36.45],"type":"Point"}
}
=======
{"geometry":{"type":"Point","coordinates":[-83.616700,36.450000]},"type":"Feature","properties":{"hierarchy":["tgn:2333974","tgn:1000001","tgn:7012149","tgn:2001849","tgn:7007825","tgn:7029392"],"placetype":["aat:300008761"],"id":2333974,"name:xx":"Ford Hollow"}}
>>>>>>> 03f74aca74312dbeaf24d7e61306dd6a786dc3d0
