{
  "id": 1053171,
  "type": "Feature",
  "properties": {
    "tgn:hierarchy":[
        "tgn:1053171",
        "tgn:1003354",
        "tgn:1000004",
        "tgn:7018214",
        "tgn:7002435",
        "tgn:7029392"
    ],
    "tgn:id":1053171,
    "tgn:name":"Bureya",
    "tgn:placetype":[
        "aat:300008347"
    ]
},
  "bbox": [],
  "geometry": {"coordinates":[129.8333,49.8167],"type":"Point"}
}