{
  "id": 1102745,
  "type": "Feature",
  "properties": {
    "tgn:hierarchy":[
        "tgn:1102745",
        "tgn:1000001",
        "tgn:7012149",
        "tgn:7007157",
        "tgn:7029392"
    ],
    "tgn:id":1102745,
    "tgn:name":"Charles Lee Tilden Regional Park",
    "tgn:placetype":[
        "aat:300008187"
    ]
},
  "bbox": [],
  "geometry": {"coordinates":[-122.2333,37.8833],"type":"Point"}
}