{
  "id": 2179626,
  "type": "Feature",
  "properties": {
    "tgn:hierarchy":[
        "tgn:2179626",
        "tgn:1000001",
        "tgn:2002107",
        "tgn:7012149",
        "tgn:7007827",
        "tgn:7029392"
    ],
    "tgn:id":2179626,
    "tgn:name":"Blank Spring",
    "tgn:placetype":[
        "aat:300008697"
    ]
},
  "bbox": [],
  "geometry": {"coordinates":[-110.0333,40.5667],"type":"Point"}
}