{
  "id": 2753878,
  "type": "Feature",
  "properties": {
    "tgn:hierarchy":[
        "tgn:2753878",
        "tgn:1000001",
        "tgn:7012149",
        "tgn:2000890",
        "tgn:7007256",
        "tgn:7029392"
    ],
    "tgn:id":2753878,
    "tgn:name":"Watson Branch",
    "tgn:placetype":[
        "aat:300008699"
    ]
},
  "bbox": [],
  "geometry": {"coordinates":[-92.1833,32.35],"type":"Point"}
}