{
  "id": 2383423,
  "type": "Feature",
  "properties": {
    "tgn:hierarchy":[
        "tgn:2383423",
        "tgn:1000001",
        "tgn:1002714",
        "tgn:7012149",
        "tgn:7007159",
        "tgn:7029392"
    ],
    "tgn:id":2383423,
    "tgn:name":"Hearthstone Hill",
    "tgn:placetype":[
        "aat:300008798"
    ]
},
  "bbox": [],
  "geometry": {"coordinates":[-72.1167,41.5833],"type":"Point"}
}