{
  "id": 7288055,
  "type": "Feature",
  "properties": {
    "tgn:hierarchy":[
        "tgn:7288055",
        "tgn:7016598",
        "tgn:1000049",
        "tgn:1000002",
        "tgn:7029392"
    ],
    "tgn:id":7288055,
    "tgn:name":"La Cortadera, Cerro",
    "tgn:placetype":[
        "aat:300008795"
    ]
},
  "bbox": [],
  "geometry": {"coordinates":[-70.383333,-25.466667],"type":"Point"}
}