<<<<<<< HEAD
{
  "id": 7357987,
  "type": "Feature",
  "properties": {
    "tgn:hierarchy":[
        "tgn:7357987",
        "tgn:1000001",
        "tgn:7005595",
        "tgn:7005560",
        "tgn:7029392"
    ],
    "tgn:id":7357987,
    "tgn:name":"Ejido M\u00e9xico",
    "tgn:placetype":[
        "aat:300008347"
    ]
},
  "bbox": [],
  "geometry": {"coordinates":[-109.016667,25.8],"type":"Point"}
}
=======
{"geometry":{"type":"Point","coordinates":[-109.016667,25.800000]},"type":"Feature","properties":{"hierarchy":["tgn:7357987","tgn:1000001","tgn:7005595","tgn:7005560","tgn:7029392"],"placetype":["aat:300008347"],"id":7357987,"name:xx":"Ejido M\u00e9xico"}}
>>>>>>> 03f74aca74312dbeaf24d7e61306dd6a786dc3d0
