{
  "id": 7516226,
  "type": "Feature",
  "properties": {
    "tgn:hierarchy":[
        "tgn:7516226",
        "tgn:7016670",
        "tgn:1008380",
        "tgn:1000226",
        "tgn:1000006",
        "tgn:7029392"
    ],
    "tgn:id":7516226,
    "tgn:name:en":"Mangaroa",
    "tgn:placetype":[
        "aat:300008699"
    ]
},
  "bbox": [],
  "geometry": {"coordinates":[176.816667,-39.166667],"type":"Point"}
}