{
  "id": 2747935,
  "type": "Feature",
  "properties": {
    "tgn:hierarchy":[
        "tgn:2747935",
        "tgn:1000001",
        "tgn:7012149",
        "tgn:2001756",
        "tgn:7007712",
        "tgn:7029392"
    ],
    "tgn:id":2747935,
    "tgn:name":"Walden",
    "tgn:placetype":[
        "aat:300008347"
    ]
},
  "bbox": [],
  "geometry": {"coordinates":[-81.1833,34.05],"type":"Point"}
}