{
  "id": 7589979,
  "type": "Feature",
  "properties": {
    "tgn:hierarchy":[
        "tgn:7589979",
        "tgn:1000004",
        "tgn:7000198",
        "tgn:7000799",
        "tgn:7029392"
    ],
    "tgn:id":7589979,
    "tgn:name:en":"Doba Sar J\u0101r\u0101n",
    "tgn:placetype":[
        "aat:300008347"
    ]
},
  "bbox": [],
  "geometry": {"coordinates":[73.926389,34.038889],"type":"Point"}
}