{
  "id": 7045889,
  "type": "Feature",
  "properties": {
    "tgn:hierarchy":[
        "tgn:7045889",
        "tgn:7015163",
        "tgn:1000003",
        "tgn:7003121",
        "tgn:1000080",
        "tgn:7029392"
    ],
    "tgn:id":7045889,
    "tgn:name":"Conte, Porto",
    "tgn:placetype":[
        "aat:300132316"
    ]
},
  "bbox": [],
  "geometry": {"coordinates":[8.183889,40.578056],"type":"Point"}
}