{
  "id": 7401046,
  "type": "Feature",
  "properties": {
    "tgn:hierarchy":[
        "tgn:7401046",
        "tgn:1000001",
        "tgn:7005599",
        "tgn:7005560",
        "tgn:7029392"
    ],
    "tgn:id":7401046,
    "tgn:name":"La Guadalupe",
    "tgn:placetype":[
        "aat:300008347"
    ]
},
  "bbox": [],
  "geometry": {"coordinates":[-97.625,20.708333],"type":"Point"}
}