{
  "id": 7527149,
  "type": "Feature",
  "properties": {
    "tgn:hierarchy":[
        "tgn:7527149",
        "tgn:7001242",
        "tgn:7016833",
        "tgn:1001091",
        "tgn:7029392"
    ],
    "tgn:id":7527149,
    "tgn:name":"Mut\u1e29af Jawharat al L\u0101l\u0101",
    "tgn:placetype":[
        "aat:300005768"
    ]
},
  "bbox": [],
  "geometry": {"coordinates":[31.257107,30.033451],"type":"Point"}
}