{
  "id": 2291421,
  "type": "Feature",
  "properties": {
    "tgn:hierarchy":[
        "tgn:2291421",
        "tgn:1000001",
        "tgn:7006451",
        "tgn:7012149",
        "tgn:2000098",
        "tgn:7029392"
    ],
    "tgn:id":2291421,
    "tgn:name":"Dolan Springs",
    "tgn:placetype":[
        "aat:300008347"
    ]
},
  "bbox": [],
  "geometry": {"coordinates":[-114.2667,35.5833],"type":"Point"}
}