{
  "id": 7214702,
  "type": "Feature",
  "properties": {
    "tgn:hierarchy":[
        "tgn:7214702",
        "tgn:7003669",
        "tgn:1000003",
        "tgn:7000084",
        "tgn:7029392"
    ],
    "tgn:id":7214702,
    "tgn:name":"Beuerbach",
    "tgn:placetype":[
        "aat:300008347"
    ]
},
  "bbox": [],
  "geometry": {"coordinates":[10.916667,48.15],"type":"Point"}
}