{
  "id": 7495944,
  "type": "Feature",
  "properties": {
    "tgn:hierarchy":[
        "tgn:7495944",
        "tgn:7487020",
        "tgn:1000004",
        "tgn:1000141",
        "tgn:7029392"
    ],
    "tgn:id":7495944,
    "tgn:name":"Buwei Sanhao Qiao",
    "tgn:placetype":[
        "aat:300007836"
    ]
},
  "bbox": [],
  "geometry": {"coordinates":[120.823954,24.3229],"type":"Point"}
}