{
  "id": 2208809,
  "type": "Feature",
  "properties": {
    "tgn:hierarchy":[
        "tgn:2208809",
        "tgn:2000453",
        "tgn:1000001",
        "tgn:7012149",
        "tgn:7007250",
        "tgn:7029392"
    ],
    "tgn:id":2208809,
    "tgn:name":"Burnt Basin",
    "tgn:placetype":[
        "aat:300386845"
    ]
},
  "bbox": [],
  "geometry": {"coordinates":[-116.25,44.5833],"type":"Point"}
}