<<<<<<< HEAD
{
  "id": 2256794,
  "type": "Feature",
  "properties": {
    "tgn:hierarchy":[
        "tgn:2256794",
        "tgn:1000001",
        "tgn:1002330",
        "tgn:7012149",
        "tgn:7007710",
        "tgn:7029392"
    ],
    "tgn:id":2256794,
    "tgn:name":"Coreze",
    "tgn:placetype":[
        "aat:300008347"
    ]
},
  "bbox": [],
  "geometry": {"coordinates":[-75.3,39.9833],"type":"Point"}
}
=======
{"geometry":{"type":"Point","coordinates":[-75.300000,39.983300]},"type":"Feature","properties":{"hierarchy":["tgn:2256794","tgn:1000001","tgn:1002330","tgn:7012149","tgn:7007710","tgn:7029392"],"placetype":["aat:300008347"],"id":2256794,"name:xx":"Coreze"}}
>>>>>>> 03f74aca74312dbeaf24d7e61306dd6a786dc3d0
