<<<<<<< HEAD
{
  "id": 7367614,
  "type": "Feature",
  "properties": {
    "tgn:hierarchy":[
        "tgn:7367614",
        "tgn:7005586",
        "tgn:1000001",
        "tgn:7005560",
        "tgn:7029392"
    ],
    "tgn:id":7367614,
    "tgn:name":"Estrecho, Punta el",
    "tgn:placetype":[
        "aat:300386846"
    ]
},
  "bbox": [],
  "geometry": {"coordinates":[-104.8,19.233333],"type":"Point"}
}
=======
{"geometry":{"type":"Point","coordinates":[-104.800000,19.233333]},"type":"Feature","properties":{"hierarchy":["tgn:7367614","tgn:7005586","tgn:1000001","tgn:7005560","tgn:7029392"],"placetype":["aat:300386846"],"id":7367614,"name:xx":"Estrecho, Punta el"}}
>>>>>>> 03f74aca74312dbeaf24d7e61306dd6a786dc3d0
