{
  "id": 1006315,
  "type": "Feature",
  "properties": {
    "tgn:hierarchy":[
        "tgn:1006315",
        "tgn:7006247",
        "tgn:1000047",
        "tgn:7002456",
        "tgn:1000002",
        "tgn:7029392"
    ],
    "tgn:id":1006315,
    "tgn:name":"Arapiri, Ilha",
    "tgn:placetype":[
        "aat:300008791"
    ]
},
  "bbox": [],
  "geometry": {"coordinates":[-54.9333,-2.0667],"type":"Point"}
}