{
  "id": 2093753,
  "type": "Feature",
  "properties": {
    "tgn:hierarchy":[
        "tgn:2093753",
        "tgn:1000001",
        "tgn:7012149",
        "tgn:1002564",
        "tgn:7007710",
        "tgn:7029392"
    ],
    "tgn:id":2093753,
    "tgn:name":"Tooley Corners",
    "tgn:placetype":[
        "aat:300008347",
        "aat:300387210"
    ]
},
  "bbox": [],
  "geometry": {"coordinates":[-75.5667,41.3333],"type":"Point"}
}