{
  "id": 7222823,
  "type": "Feature",
  "properties": {
    "tgn:hierarchy":[
        "tgn:7222823",
        "tgn:4003773",
        "tgn:7001395",
        "tgn:1000003",
        "tgn:1000074",
        "tgn:7029392"
    ],
    "tgn:id":7222823,
    "tgn:name":"Mesopotami\u00e1",
    "tgn:placetype":[
        "aat:300008347"
    ]
},
  "bbox": [],
  "geometry": {"coordinates":[22.166667,38.916667],"type":"Point"}
}