{
  "id": 2260077,
  "type": "Feature",
  "properties": {
    "tgn:hierarchy":[
        "tgn:2260077",
        "tgn:1000001",
        "tgn:2000870",
        "tgn:7012149",
        "tgn:7007256",
        "tgn:7029392"
    ],
    "tgn:id":2260077,
    "tgn:name":"Country Club Estates",
    "tgn:placetype":[
        "aat:300008347"
    ]
},
  "bbox": [],
  "geometry": {"coordinates":[-91.0833,30.4167],"type":"Point"}
}