{
  "id": 2455984,
  "type": "Feature",
  "properties": {
    "tgn:hierarchy":[
        "tgn:2455984",
        "tgn:1000001",
        "tgn:7012149",
        "tgn:7007255",
        "tgn:7029392"
    ],
    "tgn:id":2455984,
    "tgn:name":"Little Hardwick Creek",
    "tgn:placetype":[
        "aat:300008706"
    ]
},
  "bbox": [],
  "geometry": {"coordinates":[-83.9333,37.7667],"type":"Point"}
}