{
  "id": 2044086,
  "type": "Feature",
  "properties": {
    "tgn:hierarchy":[
        "tgn:2044086",
        "tgn:1000001",
        "tgn:2000863",
        "tgn:7012149",
        "tgn:7007256",
        "tgn:7029392"
    ],
    "tgn:id":2044086,
    "tgn:name":"Stegall",
    "tgn:placetype":[
        "aat:300387016"
    ]
},
  "bbox": [],
  "geometry": {"coordinates":[-93.4167,30.2333],"type":"Point"}
}