{
  "id": 2600934,
  "type": "Feature",
  "properties": {
    "tgn:hierarchy":[
        "tgn:2600934",
        "tgn:1000001",
        "tgn:7012149",
        "tgn:2000910",
        "tgn:7007256",
        "tgn:7029392"
    ],
    "tgn:id":2600934,
    "tgn:name":"Pumpkin Islands",
    "tgn:placetype":[
        "aat:300386853"
    ]
},
  "bbox": [],
  "geometry": {"coordinates":[-92.3167,29.65],"type":"Point"}
}