{
  "id": 2033143,
  "type": "Feature",
  "properties": {
    "tgn:hierarchy":[
        "tgn:2033143",
        "tgn:1000001",
        "tgn:7012149",
        "tgn:1002370",
        "tgn:7007252",
        "tgn:7029392"
    ],
    "tgn:id":2033143,
    "tgn:name":"Nulltown",
    "tgn:placetype":[
        "aat:300008347"
    ]
},
  "bbox": [],
  "geometry": {"coordinates":[-85.15,39.5667],"type":"Point"}
}