{
  "id": 2182515,
  "type": "Feature",
  "properties": {
    "tgn:hierarchy":[
        "tgn:2182515",
        "tgn:1000001",
        "tgn:7012149",
        "tgn:7007157",
        "tgn:1002972",
        "tgn:7029392"
    ],
    "tgn:id":2182515,
    "tgn:name":"Blue Rock Spring",
    "tgn:placetype":[
        "aat:300008697"
    ]
},
  "bbox": [],
  "geometry": {"coordinates":[-119.3333,34.8333],"type":"Point"}
}