{
  "id": 2232012,
  "type": "Feature",
  "properties": {
    "tgn:hierarchy":[
        "tgn:2232012",
        "tgn:1000001",
        "tgn:7016172",
        "tgn:7012149",
        "tgn:2000144",
        "tgn:7029392"
    ],
    "tgn:id":2232012,
    "tgn:name":"Champion",
    "tgn:placetype":[
        "aat:300008347"
    ]
},
  "bbox": [],
  "geometry": {"coordinates":[-91.65,33.9333],"type":"Point"}
}