{
  "id": 7526457,
  "type": "Feature",
  "properties": {
    "tgn:hierarchy":[
        "tgn:7526457",
        "tgn:7001242",
        "tgn:7016833",
        "tgn:7001334",
        "tgn:7029392"
    ],
    "tgn:id":7526457,
    "tgn:name:en":"Tham\u0101niyat Ajr\u0101s",
    "tgn:placetype":[
        "aat:300008777"
    ]
},
  "bbox": [],
  "geometry": {"coordinates":[26.23696,22.805891],"type":"Point"}
}