{
  "id": 2008144,
  "type": "Feature",
  "properties": {
    "tgn:hierarchy":[
        "tgn:2008144",
        "tgn:1000001",
        "tgn:7016172",
        "tgn:7012149",
        "tgn:2000134",
        "tgn:7029392"
    ],
    "tgn:id":2008144,
    "tgn:name":"Durian",
    "tgn:placetype":[
        "aat:300008347",
        "aat:300387210"
    ]
},
  "bbox": [],
  "geometry": {"coordinates":[-92.75,34.2833],"type":"Point"}
}