{
  "id": 7285005,
  "type": "Feature",
  "properties": {
    "tgn:hierarchy":[
        "tgn:7285005",
        "tgn:1001699",
        "tgn:1000049",
        "tgn:1000002",
        "tgn:7029392"
    ],
    "tgn:id":7285005,
    "tgn:name":"Quihue, Estero",
    "tgn:placetype":[
        "aat:300008699"
    ]
},
  "bbox": [],
  "geometry": {"coordinates":[-73.766667,-40.366667],"type":"Point"}
}