<<<<<<< HEAD
{
  "id": 7056169,
  "type": "Feature",
  "properties": {
    "tgn:hierarchy":[
        "tgn:7056169",
        "tgn:7003158",
        "tgn:1000003",
        "tgn:7003124",
        "tgn:1000080",
        "tgn:7029392"
    ],
    "tgn:id":7056169,
    "tgn:name":"Ledro, Val di",
    "tgn:placetype":[
        "aat:300008761"
    ]
},
  "bbox": [],
  "geometry": {"coordinates":[10.75,45.883333],"type":"Point"}
}
=======
{"geometry":{"type":"Point","coordinates":[10.750000,45.883333]},"type":"Feature","properties":{"hierarchy":["tgn:7056169","tgn:7003158","tgn:1000003","tgn:7003124","tgn:1000080","tgn:7029392"],"placetype":["aat:300008761"],"id":7056169,"name:xx":"Ledro, Val di"}}
>>>>>>> 03f74aca74312dbeaf24d7e61306dd6a786dc3d0
