<<<<<<< HEAD
{
  "id": 2400590,
  "type": "Feature",
  "properties": {
    "tgn:hierarchy":[
        "tgn:2400590",
        "tgn:7006450",
        "tgn:1000001",
        "tgn:2124012",
        "tgn:7012149",
        "tgn:7029392"
    ],
    "tgn:id":2400590,
    "tgn:name":"Horse Marine Lake",
    "tgn:placetype":[
        "aat:300008680"
    ]
},
  "bbox": [],
  "geometry": {"coordinates":[-153.9,57.1167],"type":"Point"}
}
=======
{"geometry":{"type":"Point","coordinates":[-153.900000,57.116700]},"type":"Feature","properties":{"hierarchy":["tgn:2400590","tgn:7006450","tgn:1000001","tgn:2124012","tgn:7012149","tgn:7029392"],"placetype":["aat:300008680"],"id":2400590,"name:xx":"Horse Marine Lake"}}
>>>>>>> 03f74aca74312dbeaf24d7e61306dd6a786dc3d0
