<<<<<<< HEAD
{
  "id": 2763916,
  "type": "Feature",
  "properties": {
    "tgn:hierarchy":[
        "tgn:2763916",
        "tgn:1000001",
        "tgn:7012149",
        "tgn:2001924",
        "tgn:7007825",
        "tgn:7029392"
    ],
    "tgn:id":2763916,
    "tgn:name":"Wheatstone Creek",
    "tgn:placetype":[
        "aat:300008706"
    ]
},
  "bbox": [],
  "geometry": {"coordinates":[-85.4333,35.6833],"type":"Point"}
}
=======
{"geometry":{"type":"Point","coordinates":[-85.433300,35.683300]},"type":"Feature","properties":{"hierarchy":["tgn:2763916","tgn:1000001","tgn:7012149","tgn:2001924","tgn:7007825","tgn:7029392"],"placetype":["aat:300008706"],"id":2763916,"name:xx":"Wheatstone Creek"}}
>>>>>>> 03f74aca74312dbeaf24d7e61306dd6a786dc3d0
