{
  "id": 2392154,
  "type": "Feature",
  "properties": {
    "tgn:hierarchy":[
        "tgn:2392154",
        "tgn:2000566",
        "tgn:1000001",
        "tgn:7012149",
        "tgn:7007253",
        "tgn:7029392"
    ],
    "tgn:id":2392154,
    "tgn:name":"Hinkle Creek",
    "tgn:placetype":[
        "aat:300008706"
    ]
},
  "bbox": [],
  "geometry": {"coordinates":[-92.15,42.1667],"type":"Point"}
}