<<<<<<< HEAD
{
  "id": 7371123,
  "type": "Feature",
  "properties": {
    "tgn:hierarchy":[
        "tgn:7371123",
        "tgn:1000001",
        "tgn:7005600",
        "tgn:7005560",
        "tgn:7029392"
    ],
    "tgn:id":7371123,
    "tgn:name":"Granada",
    "tgn:placetype":[
        "aat:300008347"
    ]
},
  "bbox": [],
  "geometry": {"coordinates":[-90.033333,20.583333],"type":"Point"}
}
=======
{"geometry":{"type":"Point","coordinates":[-90.033333,20.583333]},"type":"Feature","properties":{"hierarchy":["tgn:7371123","tgn:1000001","tgn:7005600","tgn:7005560","tgn:7029392"],"placetype":["aat:300008347"],"id":7371123,"name:xx":"Granada"}}
>>>>>>> 03f74aca74312dbeaf24d7e61306dd6a786dc3d0
