{
  "id": 2637865,
  "type": "Feature",
  "properties": {
    "tgn:hierarchy":[
        "tgn:2637865",
        "tgn:1000001",
        "tgn:7012149",
        "tgn:7007566",
        "tgn:7029392"
    ],
    "tgn:id":2637865,
    "tgn:name":"Salada, Ca\u00f1ada",
    "tgn:placetype":[
        "aat:300008699"
    ]
},
  "bbox": [],
  "geometry": {"coordinates":[-107.3167,35.5833],"type":"Point"}
}