{
  "id": 7317826,
  "type": "Feature",
  "properties": {
    "tgn:hierarchy":[
        "tgn:7317826",
        "tgn:1001702",
        "tgn:1000049",
        "tgn:1000002",
        "tgn:7029392"
    ],
    "tgn:id":7317826,
    "tgn:name":"Chica, Isla",
    "tgn:placetype":[
        "aat:300008791"
    ]
},
  "bbox": [],
  "geometry": {"coordinates":[-72.916667,-51.883333],"type":"Point"}
}