{
  "id": 1107705,
  "type": "Feature",
  "properties": {
    "tgn:hierarchy":[
        "tgn:1107705",
        "tgn:1000002",
        "tgn:7029392"
    ],
    "tgn:id":1107705,
    "tgn:name":"Lan\u00edn, Volc\u00e1n",
    "tgn:placetype":[
        "aat:300132325"
    ]
},
  "bbox": [],
  "geometry": {"coordinates":[-71.55,-39.5833],"type":"Point"}
}