{
  "id": 1024722,
  "type": "Feature",
  "properties": {
    "tgn:hierarchy":[
        "tgn:1024722",
        "tgn:1000637",
        "tgn:1000002",
        "tgn:1000056",
        "tgn:7029392"
    ],
    "tgn:id":1024722,
    "tgn:name":"Quivilla",
    "tgn:placetype":[
        "aat:300008347"
    ]
},
  "bbox": [],
  "geometry": {"coordinates":[-76.6333,-9.5333],"type":"Point"}
}