{
  "id": 2600319,
  "type": "Feature",
  "properties": {
    "tgn:hierarchy":[
        "tgn:2600319",
        "tgn:1000001",
        "tgn:2001582",
        "tgn:7012149",
        "tgn:7007705",
        "tgn:7029392"
    ],
    "tgn:id":2600319,
    "tgn:name":"Pudwill Lake",
    "tgn:placetype":[
        "aat:300008680"
    ]
},
  "bbox": [],
  "geometry": {"coordinates":[-99.45,46.15],"type":"Point"}
}