{
  "id": 2765518,
  "type": "Feature",
  "properties": {
    "tgn:hierarchy":[
        "tgn:2765518",
        "tgn:1000001",
        "tgn:7012149",
        "tgn:2001821",
        "tgn:7007713",
        "tgn:7029392"
    ],
    "tgn:id":2765518,
    "tgn:name":"White Butte",
    "tgn:placetype":[
        "aat:300008798"
    ]
},
  "bbox": [],
  "geometry": {"coordinates":[-102.3667,43.8833],"type":"Point"}
}