{
  "id": 2060096,
  "type": "Feature",
  "properties": {
    "tgn:hierarchy":[
        "tgn:2060096",
        "tgn:1000001",
        "tgn:7012149",
        "tgn:1002984",
        "tgn:7007523",
        "tgn:7029392"
    ],
    "tgn:id":2060096,
    "tgn:name":"Pinckney",
    "tgn:placetype":[
        "aat:300008347",
        "aat:300387210"
    ]
},
  "bbox": [],
  "geometry": {"coordinates":[-91.2167,38.6667],"type":"Point"}
}