<<<<<<< HEAD
{
  "id": 7482584,
  "type": "Feature",
  "properties": {
    "tgn:hierarchy":[
        "tgn:7482584",
        "tgn:1000004",
        "tgn:7001014",
        "tgn:1000141",
        "tgn:7029392"
    ],
    "tgn:id":7482584,
    "tgn:name":"Yunjia Daqiao",
    "tgn:placetype":[
        "aat:300007836"
    ]
},
  "bbox": [],
  "geometry": {"coordinates":[120.177222,23.513333],"type":"Point"}
}
=======
{"geometry":{"type":"Point","coordinates":[120.177222,23.513333]},"type":"Feature","properties":{"hierarchy":["tgn:7482584","tgn:1000004","tgn:7001014","tgn:1000141","tgn:7029392"],"placetype":["aat:300007836"],"id":7482584,"name:xx":"Yunjia Daqiao"}}
>>>>>>> 03f74aca74312dbeaf24d7e61306dd6a786dc3d0
