{
  "id": 7512678,
  "type": "Feature",
  "properties": {
    "tgn:hierarchy":[
        "tgn:7512678",
        "tgn:1009227",
        "tgn:1000226",
        "tgn:7018437",
        "tgn:1000006",
        "tgn:7029392"
    ],
    "tgn:id":7512678,
    "tgn:name:en":"Hinahina Hill",
    "tgn:placetype":[
        "aat:300008795"
    ]
},
  "bbox": [],
  "geometry": {"coordinates":[169.616667,-46.516667],"type":"Point"}
}