{
  "id": 1100418,
  "type": "Feature",
  "properties": {
    "tgn:hierarchy":[
        "tgn:1100418",
        "tgn:7003013",
        "tgn:7003005",
        "tgn:1000003",
        "tgn:7004474",
        "tgn:1000080",
        "tgn:7029392"
    ],
    "tgn:id":1100418,
    "tgn:name":"Palazzo Reale",
    "tgn:placetype":[
        "aat:300004792",
        "aat:300005734"
    ]
},
  "bbox": [],
  "geometry": {"coordinates":[14.25,40.835833],"type":"Point"}
}