<<<<<<< HEAD
{
  "id": 7240417,
  "type": "Feature",
  "properties": {
    "tgn:hierarchy":[
        "tgn:7240417",
        "tgn:7003457",
        "tgn:1000003",
        "tgn:1000063",
        "tgn:7018236",
        "tgn:7029392"
    ],
    "tgn:id":7240417,
    "tgn:name":"Hof ter Erpen",
    "tgn:placetype":[
        "aat:300000206"
    ]
},
  "bbox": [],
  "geometry": {"coordinates":[3.883333,50.866667],"type":"Point"}
}
=======
{"geometry":{"type":"Point","coordinates":[3.883333,50.866667]},"type":"Feature","properties":{"hierarchy":["tgn:7240417","tgn:7003457","tgn:1000003","tgn:1000063","tgn:7018236","tgn:7029392"],"placetype":["aat:300000206"],"id":7240417,"name:xx":"Hof ter Erpen"}}
>>>>>>> 03f74aca74312dbeaf24d7e61306dd6a786dc3d0
