{
  "id": 7145101,
  "type": "Feature",
  "properties": {
    "tgn:hierarchy":[
        "tgn:7145101",
        "tgn:1000003",
        "tgn:7003677",
        "tgn:7000084",
        "tgn:7029392"
    ],
    "tgn:id":7145101,
    "tgn:name":"Kn\u00f6ttinghausen",
    "tgn:placetype":[
        "aat:300000206"
    ]
},
  "bbox": [],
  "geometry": {"coordinates":[8.55,52.316667],"type":"Point"}
}