<<<<<<< HEAD
{
  "id": 7357642,
  "type": "Feature",
  "properties": {
    "tgn:hierarchy":[
        "tgn:7357642",
        "tgn:7005587",
        "tgn:1000001",
        "tgn:7005560",
        "tgn:7029392"
    ],
    "tgn:id":7357642,
    "tgn:name":"Cumbre",
    "tgn:placetype":[
        "aat:300008347"
    ]
},
  "bbox": [],
  "geometry": {"coordinates":[-98.866667,20.2],"type":"Point"}
}
=======
{"geometry":{"type":"Point","coordinates":[-98.866667,20.200000]},"type":"Feature","properties":{"hierarchy":["tgn:7357642","tgn:7005587","tgn:1000001","tgn:7005560","tgn:7029392"],"placetype":["aat:300008347"],"id":7357642,"name:xx":"Cumbre"}}
>>>>>>> 03f74aca74312dbeaf24d7e61306dd6a786dc3d0
