{
  "id": 2009585,
  "type": "Feature",
  "properties": {
    "tgn:hierarchy":[
        "tgn:2009585",
        "tgn:1000001",
        "tgn:7016172",
        "tgn:2000115",
        "tgn:7012149",
        "tgn:7029392"
    ],
    "tgn:id":2009585,
    "tgn:name":"Success",
    "tgn:placetype":[
        "aat:300008347"
    ]
},
  "bbox": [],
  "geometry": {"coordinates":[-90.7167,36.45],"type":"Point"}
}