{
  "id": 2775958,
  "type": "Feature",
  "properties": {
    "tgn:hierarchy":[
        "tgn:2775958",
        "tgn:1000001",
        "tgn:2000871",
        "tgn:7012149",
        "tgn:7007256",
        "tgn:7029392"
    ],
    "tgn:id":2775958,
    "tgn:name":"Wilson Point",
    "tgn:placetype":[
        "aat:300008347"
    ]
},
  "bbox": [],
  "geometry": {"coordinates":[-91.0833,32.9167],"type":"Point"}
}