{
  "id": 7044049,
  "type": "Feature",
  "properties": {
    "tgn:hierarchy":[
        "tgn:7044049",
        "tgn:7003013",
        "tgn:7003005",
        "tgn:1000003",
        "tgn:1000080",
        "tgn:7029392"
    ],
    "tgn:id":7044049,
    "tgn:name":"Capodichino",
    "tgn:placetype":[
        "aat:300008347"
    ]
},
  "bbox": [],
  "geometry": {"coordinates":[14.266667,40.883333],"type":"Point"}
}