{
  "id": 2395860,
  "type": "Feature",
  "properties": {
    "tgn:hierarchy":[
        "tgn:2395860",
        "tgn:1000001",
        "tgn:7012149",
        "tgn:2001303",
        "tgn:7007524",
        "tgn:7029392"
    ],
    "tgn:id":2395860,
    "tgn:name":"Hollowwood Creek",
    "tgn:placetype":[
        "aat:300008706"
    ]
},
  "bbox": [],
  "geometry": {"coordinates":[-106.4333,45.5333],"type":"Point"}
}