{
  "id": 7235443,
  "type": "Feature",
  "properties": {
    "tgn:hierarchy":[
        "tgn:7235443",
        "tgn:7002728",
        "tgn:7002715",
        "tgn:1000003",
        "tgn:1000074",
        "tgn:7029392"
    ],
    "tgn:id":7235443,
    "tgn:name":"Arch\u00e1ngelos",
    "tgn:placetype":[
        "aat:300008347"
    ]
},
  "bbox": [],
  "geometry": {"coordinates":[22.274444,41.080278],"type":"Point"}
}