{
  "id": 7339283,
  "type": "Feature",
  "properties": {
    "tgn:hierarchy":[
        "tgn:7339283",
        "tgn:7008911",
        "tgn:1000003",
        "tgn:7002763",
        "tgn:1000095",
        "tgn:7029392"
    ],
    "tgn:id":7339283,
    "tgn:name":"Demu\u00e9s",
    "tgn:placetype":[
        "aat:300008347"
    ]
},
  "bbox": [],
  "geometry": {"coordinates":[-4.983333,43.316667],"type":"Point"}
}