<<<<<<< HEAD
{
  "id": 7176945,
  "type": "Feature",
  "properties": {
    "tgn:hierarchy":[
        "tgn:7176945",
        "tgn:1000003",
        "tgn:7003677",
        "tgn:7000084",
        "tgn:7029392"
    ],
    "tgn:id":7176945,
    "tgn:name":"Haggeney",
    "tgn:placetype":[
        "aat:300000206"
    ]
},
  "bbox": [],
  "geometry": {"coordinates":[8.2,51.666667],"type":"Point"}
}
=======
{"geometry":{"type":"Point","coordinates":[8.200000,51.666667]},"type":"Feature","properties":{"hierarchy":["tgn:7176945","tgn:1000003","tgn:7003677","tgn:7000084","tgn:7029392"],"placetype":["aat:300000206"],"id":7176945,"name:xx":"Haggeney"}}
>>>>>>> 03f74aca74312dbeaf24d7e61306dd6a786dc3d0
