{
  "id": 7144771,
  "type": "Feature",
  "properties": {
    "tgn:hierarchy":[
        "tgn:7144771",
        "tgn:7000096",
        "tgn:1000003",
        "tgn:7000084",
        "tgn:7029392"
    ],
    "tgn:id":7144771,
    "tgn:name":"Kolzenburger Heide",
    "tgn:placetype":[
        "aat:300386887"
    ]
},
  "bbox": [],
  "geometry": {"coordinates":[13.183333,52.033333],"type":"Point"}
}