{
  "id": 2088855,
  "type": "Feature",
  "properties": {
    "tgn:hierarchy":[
        "tgn:2088855",
        "tgn:1000001",
        "tgn:1002330",
        "tgn:7012149",
        "tgn:7007710",
        "tgn:7029392"
    ],
    "tgn:id":2088855,
    "tgn:name":"Gradyville",
    "tgn:placetype":[
        "aat:300008347"
    ]
},
  "bbox": [],
  "geometry": {"coordinates":[-75.4667,39.9333],"type":"Point"}
}