{
  "id": 1080374,
  "type": "Feature",
  "properties": {
    "tgn:hierarchy":[
        "tgn:1080374",
        "tgn:7016696",
        "tgn:1000004",
        "tgn:7000894",
        "tgn:1000120",
        "tgn:7029392"
    ],
    "tgn:id":1080374,
    "tgn:name":"Kamakura",
    "tgn:placetype":[
        "aat:300008347",
        "aat:300000547",
        "aat:300008375",
        "aat:300387270"
    ]
},
  "bbox": [],
  "geometry": {"coordinates":[139.55,35.3167],"type":"Point"}
}