{
  "id": 7065278,
  "type": "Feature",
  "properties": {
    "tgn:hierarchy":[
        "tgn:7065278",
        "tgn:7003692",
        "tgn:1000003",
        "tgn:7000084",
        "tgn:7029392"
    ],
    "tgn:id":7065278,
    "tgn:name":"Steingasse",
    "tgn:placetype":[
        "aat:300008347"
    ]
},
  "bbox": [],
  "geometry": {"coordinates":[9.433056,49.735556],"type":"Point"}
}