{
  "id": 1130737,
  "type": "Feature",
  "properties": {
    "tgn:hierarchy":[
        "tgn:1130737",
        "tgn:1000047",
        "tgn:1000002",
        "tgn:7029392"
    ],
    "tgn:id":1130737,
    "tgn:name":"Tenente Marques, Rio",
    "tgn:placetype":[
        "aat:300008707"
    ]
},
  "bbox": [],
  "geometry": {"coordinates":[-59.982,-11.114],"type":"Point"}
}