<<<<<<< HEAD
{
  "id": 2763362,
  "type": "Feature",
  "properties": {
    "tgn:hierarchy":[
        "tgn:2763362",
        "tgn:1000001",
        "tgn:1002277",
        "tgn:7012149",
        "tgn:7007251",
        "tgn:7029392"
    ],
    "tgn:id":2763362,
    "tgn:name":"Wet Weather Creek",
    "tgn:placetype":[
        "aat:300008706"
    ]
},
  "bbox": [],
  "geometry": {"coordinates":[-88.2667,38.8333],"type":"Point"}
}
=======
{"geometry":{"type":"Point","coordinates":[-88.266700,38.833300]},"type":"Feature","properties":{"hierarchy":["tgn:2763362","tgn:1000001","tgn:1002277","tgn:7012149","tgn:7007251","tgn:7029392"],"placetype":["aat:300008706"],"id":2763362,"name:xx":"Wet Weather Creek"}}
>>>>>>> 03f74aca74312dbeaf24d7e61306dd6a786dc3d0
