<<<<<<< HEAD
{
  "id": 2766203,
  "type": "Feature",
  "properties": {
    "tgn:hierarchy":[
        "tgn:2766203",
        "tgn:1000001",
        "tgn:7012149",
        "tgn:2001532",
        "tgn:7007709",
        "tgn:7029392"
    ],
    "tgn:id":2766203,
    "tgn:name":"White Lake",
    "tgn:placetype":[
        "aat:300006191"
    ]
},
  "bbox": [],
  "geometry": {"coordinates":[-79.7167,35.8833],"type":"Point"}
}
=======
{"geometry":{"type":"Point","coordinates":[-79.716700,35.883300]},"type":"Feature","properties":{"hierarchy":["tgn:2766203","tgn:1000001","tgn:7012149","tgn:2001532","tgn:7007709","tgn:7029392"],"placetype":["aat:300006191"],"id":2766203,"name:xx":"White Lake"}}
>>>>>>> 03f74aca74312dbeaf24d7e61306dd6a786dc3d0
