{
  "id": 2766203,
  "type": "Feature",
  "properties": {
    "tgn:hierarchy":[
        "tgn:2766203",
        "tgn:1000001",
        "tgn:7012149",
        "tgn:2001532",
        "tgn:7007709",
        "tgn:7029392"
    ],
    "tgn:id":2766203,
    "tgn:name":"White Lake",
    "tgn:placetype":[
        "aat:300006191"
    ]
},
  "bbox": [],
  "geometry": {"coordinates":[-79.7167,35.8833],"type":"Point"}
}