<<<<<<< HEAD
{
  "id": 2252320,
  "type": "Feature",
  "properties": {
    "tgn:hierarchy":[
        "tgn:2252320",
        "tgn:1000001",
        "tgn:7012149",
        "tgn:2002248",
        "tgn:7007920",
        "tgn:7029392"
    ],
    "tgn:id":2252320,
    "tgn:name":"Confusion Ridge",
    "tgn:placetype":[
        "aat:300266640"
    ]
},
  "bbox": [],
  "geometry": {"coordinates":[-117.2667,48.9833],"type":"Point"}
}
=======
{"geometry":{"type":"Point","coordinates":[-117.266700,48.983300]},"type":"Feature","properties":{"hierarchy":["tgn:2252320","tgn:1000001","tgn:7012149","tgn:2002248","tgn:7007920","tgn:7029392"],"placetype":["aat:300266640"],"id":2252320,"name:xx":"Confusion Ridge"}}
>>>>>>> 03f74aca74312dbeaf24d7e61306dd6a786dc3d0
