{
  "id": 2268863,
  "type": "Feature",
  "properties": {
    "tgn:hierarchy":[
        "tgn:2268863",
        "tgn:1000001",
        "tgn:7012149",
        "tgn:1002986",
        "tgn:7007568",
        "tgn:7029392"
    ],
    "tgn:id":2268863,
    "tgn:name":"Cross Pond",
    "tgn:placetype":[
        "aat:300008680"
    ]
},
  "bbox": [],
  "geometry": {"coordinates":[-73.95,43.6667],"type":"Point"}
}