{
  "id": 7196969,
  "type": "Feature",
  "properties": {
    "tgn:hierarchy":[
        "tgn:7196969",
        "tgn:7003692",
        "tgn:1000003",
        "tgn:7000084",
        "tgn:7029392"
    ],
    "tgn:id":7196969,
    "tgn:name":"Dietenwengen",
    "tgn:placetype":[
        "aat:300008347"
    ]
},
  "bbox": [],
  "geometry": {"coordinates":[9.866667,48.016667],"type":"Point"}
}