{
  "id": 7045050,
  "type": "Feature",
  "properties": {
    "tgn:hierarchy":[
        "tgn:7045050",
        "tgn:7005126",
        "tgn:1000003",
        "tgn:7003120",
        "tgn:1000080",
        "tgn:7029392"
    ],
    "tgn:id":7045050,
    "tgn:name":"Foresto",
    "tgn:placetype":[
        "aat:300008347"
    ]
},
  "bbox": [],
  "geometry": {"coordinates":[7.733333,44.733333],"type":"Point"}
}