{
  "id": 2442414,
  "type": "Feature",
  "properties": {
    "tgn:hierarchy":[
        "tgn:2442414",
        "tgn:1000001",
        "tgn:7012149",
        "tgn:2001286",
        "tgn:7007524",
        "tgn:7029392"
    ],
    "tgn:id":2442414,
    "tgn:name":"Krinklehorn Peak",
    "tgn:placetype":[
        "aat:300008798"
    ]
},
  "bbox": [],
  "geometry": {"coordinates":[-114.7833,48.8167],"type":"Point"}
}