<<<<<<< HEAD
{
  "id": 7470756,
  "type": "Feature",
  "properties": {
    "tgn:hierarchy":[
        "tgn:7470756",
        "tgn:7468018",
        "tgn:1000004",
        "tgn:1000141",
        "tgn:7029392"
    ],
    "tgn:id":7470756,
    "tgn:name":"Zhuweizi",
    "tgn:placetype":[
        "aat:300008347"
    ]
},
  "bbox": [],
  "geometry": {"coordinates":[120.310818,23.507756],"type":"Point"}
}
=======
{"geometry":{"type":"Point","coordinates":[120.310818,23.507756]},"type":"Feature","properties":{"hierarchy":["tgn:7470756","tgn:7468018","tgn:1000004","tgn:1000141","tgn:7029392"],"placetype":["aat:300008347"],"id":7470756,"name:xx":"Zhuweizi"}}
>>>>>>> 03f74aca74312dbeaf24d7e61306dd6a786dc3d0
