{
  "id": 2415854,
  "type": "Feature",
  "properties": {
    "tgn:hierarchy":[
        "tgn:2415854",
        "tgn:1000001",
        "tgn:7012149",
        "tgn:7007708",
        "tgn:7029392"
    ],
    "tgn:id":2415854,
    "tgn:name":"Ives Creek",
    "tgn:placetype":[
        "aat:300008706"
    ]
},
  "bbox": [],
  "geometry": {"coordinates":[-119.6333,44.8667],"type":"Point"}
}