{
  "id": 2777462,
  "type": "Feature",
  "properties": {
    "tgn:hierarchy":[
        "tgn:2777462",
        "tgn:2000768",
        "tgn:1000001",
        "tgn:7012149",
        "tgn:7007255",
        "tgn:7029392"
    ],
    "tgn:id":2777462,
    "tgn:name":"Winlock Knob",
    "tgn:placetype":[
        "aat:300008798"
    ]
},
  "bbox": [],
  "geometry": {"coordinates":[-85.7833,37.0833],"type":"Point"}
}