{
  "id": 2592801,
  "type": "Feature",
  "properties": {
    "tgn:hierarchy":[
        "tgn:2592801",
        "tgn:1000001",
        "tgn:7012149",
        "tgn:1002418",
        "tgn:7007920",
        "tgn:7029392"
    ],
    "tgn:id":2592801,
    "tgn:name":"Pope Lake",
    "tgn:placetype":[
        "aat:300008680"
    ]
},
  "bbox": [],
  "geometry": {"coordinates":[-123.9333,47.4167],"type":"Point"}
}