{
  "id": 7277271,
  "type": "Feature",
  "properties": {
    "tgn:hierarchy":[
        "tgn:7277271",
        "tgn:1001699",
        "tgn:1000049",
        "tgn:1000002",
        "tgn:7029392"
    ],
    "tgn:id":7277271,
    "tgn:name":"Canal Cholgo",
    "tgn:placetype":[
        "aat:300008676"
    ]
},
  "bbox": [],
  "geometry": {"coordinates":[-72.465,-42.108056],"type":"Point"}
}