{
  "id": 7490799,
  "type": "Feature",
  "properties": {
    "tgn:hierarchy":[
        "tgn:7490799",
        "tgn:7001010",
        "tgn:1000004",
        "tgn:1000141",
        "tgn:7029392"
    ],
    "tgn:id":7490799,
    "tgn:name":"Sangziliao",
    "tgn:placetype":[
        "aat:300008347"
    ]
},
  "bbox": [],
  "geometry": {"coordinates":[121.255,23.185556],"type":"Point"}
}