{
  "id": 2241109,
  "type": "Feature",
  "properties": {
    "tgn:hierarchy":[
        "tgn:2241109",
        "tgn:1000001",
        "tgn:2001701",
        "tgn:7012149",
        "tgn:7007708",
        "tgn:7029392"
    ],
    "tgn:id":2241109,
    "tgn:name":"Clark Creek",
    "tgn:placetype":[
        "aat:300008706"
    ]
},
  "bbox": [],
  "geometry": {"coordinates":[-123.5167,44.6167],"type":"Point"}
}