{
  "id": 2522491,
  "type": "Feature",
  "properties": {
    "tgn:hierarchy":[
        "tgn:2522491",
        "tgn:1000001",
        "tgn:7012149",
        "tgn:2002247",
        "tgn:7007920",
        "tgn:7029392"
    ],
    "tgn:id":2522491,
    "tgn:name":"Moonshine Bay",
    "tgn:placetype":[
        "aat:300132316"
    ]
},
  "bbox": [],
  "geometry": {"coordinates":[-118.5333,47.8667],"type":"Point"}
}