{
  "id": 7575116,
  "type": "Feature",
  "properties": {
    "tgn:hierarchy":[
        "tgn:7575116",
        "tgn:7016678",
        "tgn:7000204",
        "tgn:1006722",
        "tgn:1000004",
        "tgn:7000198",
        "tgn:7029392"
    ],
    "tgn:id":7575116,
    "tgn:name:en":"Keating Point",
    "tgn:placetype":[
        "aat:300386846"
    ]
},
  "bbox": [],
  "geometry": {"coordinates":[92.766667,9.25],"type":"Point"}
}