<<<<<<< HEAD
{
  "id": 7483340,
  "type": "Feature",
  "properties": {
    "tgn:hierarchy":[
        "tgn:7483340",
        "tgn:7001004",
        "tgn:1000004",
        "tgn:1000141",
        "tgn:7029392"
    ],
    "tgn:id":7483340,
    "tgn:name":"Xibuting Shan",
    "tgn:placetype":[
        "aat:300008798"
    ]
},
  "bbox": [],
  "geometry": {"coordinates":[120.614167,23.062222],"type":"Point"}
}
=======
{"geometry":{"type":"Point","coordinates":[120.614167,23.062222]},"type":"Feature","properties":{"hierarchy":["tgn:7483340","tgn:7001004","tgn:1000004","tgn:1000141","tgn:7029392"],"placetype":["aat:300008798"],"id":7483340,"name:xx":"Xibuting Shan"}}
>>>>>>> 03f74aca74312dbeaf24d7e61306dd6a786dc3d0
