{
  "id": 2516246,
  "type": "Feature",
  "properties": {
    "tgn:hierarchy":[
        "tgn:2516246",
        "tgn:1000001",
        "tgn:7012149",
        "tgn:2000969",
        "tgn:7007520",
        "tgn:7029392"
    ],
    "tgn:id":2516246,
    "tgn:name":"Mine Point",
    "tgn:placetype":[
        "aat:300008850"
    ]
},
  "bbox": [],
  "geometry": {"coordinates":[-88.5667,48.0667],"type":"Point"}
}