<<<<<<< HEAD
{
  "id": 2334564,
  "type": "Feature",
  "properties": {
    "tgn:hierarchy":[
        "tgn:2334564",
        "tgn:1000001",
        "tgn:7012149",
        "tgn:1002987",
        "tgn:7007706",
        "tgn:7029392"
    ],
    "tgn:id":2334564,
    "tgn:name":"Forest, Lake",
    "tgn:placetype":[
        "aat:300006191"
    ]
},
  "bbox": [],
  "geometry": {"coordinates":[-84.1833,39.5333],"type":"Point"}
}
=======
{"geometry":{"type":"Point","coordinates":[-84.183300,39.533300]},"type":"Feature","properties":{"hierarchy":["tgn:2334564","tgn:1000001","tgn:7012149","tgn:1002987","tgn:7007706","tgn:7029392"],"placetype":["aat:300006191"],"id":2334564,"name:xx":"Forest, Lake"}}
>>>>>>> 03f74aca74312dbeaf24d7e61306dd6a786dc3d0
