{
  "id": 2334564,
  "type": "Feature",
  "properties": {
    "tgn:hierarchy":[
        "tgn:2334564",
        "tgn:1000001",
        "tgn:7012149",
        "tgn:1002987",
        "tgn:7007706",
        "tgn:7029392"
    ],
    "tgn:id":2334564,
    "tgn:name":"Forest, Lake",
    "tgn:placetype":[
        "aat:300006191"
    ]
},
  "bbox": [],
  "geometry": {"coordinates":[-84.1833,39.5333],"type":"Point"}
}