{
  "id": 2328338,
  "type": "Feature",
  "properties": {
    "tgn:hierarchy":[
        "tgn:2328338",
        "tgn:1000001",
        "tgn:7012149",
        "tgn:2000479",
        "tgn:7007250",
        "tgn:7029392"
    ],
    "tgn:id":2328338,
    "tgn:name":"Fisher Creek",
    "tgn:placetype":[
        "aat:300008706"
    ]
},
  "bbox": [],
  "geometry": {"coordinates":[-116.45,47.6833],"type":"Point"}
}