{
  "id": 7014444,
  "type": "Feature",
  "properties": {
    "tgn:hierarchy":[
        "tgn:7014444",
        "tgn:1000001",
        "tgn:7012149",
        "tgn:7022240",
        "tgn:7007523",
        "tgn:7029392"
    ],
    "tgn:id":7014444,
    "tgn:name":"Saint Louis",
    "tgn:placetype":[
        "aat:300387256",
        "aat:300387277",
        "aat:300008347",
        "aat:300387218",
        "aat:300008389",
        "aat:300387308",
        "aat:300005135",
        "aat:300264742",
        "aat:300387270",
        "aat:300387302",
        "aat:300387293",
        "aat:300387291"
    ]
},
  "bbox": [],
  "geometry": {"coordinates":[-90.1833,38.6167],"type":"Point"}
}