{
  "id": 2488825,
  "type": "Feature",
  "properties": {
    "tgn:hierarchy":[
        "tgn:2488825",
        "tgn:1000001",
        "tgn:7012149",
        "tgn:7007157",
        "tgn:1002915",
        "tgn:7029392"
    ],
    "tgn:id":2488825,
    "tgn:name":"Main Canal",
    "tgn:placetype":[
        "aat:300006075"
    ]
},
  "bbox": [],
  "geometry": {"coordinates":[-121.0833,37.4667],"type":"Point"}
}