{
  "id": 7034808,
  "type": "Feature",
  "properties": {
    "tgn:hierarchy":[
        "tgn:7034808",
        "tgn:1000003",
        "tgn:7003236",
        "tgn:1000080",
        "tgn:7029392"
    ],
    "tgn:id":7034808,
    "tgn:name":"Cannette, Punta",
    "tgn:placetype":[
        "aat:300386846"
    ]
},
  "bbox": [],
  "geometry": {"coordinates":[9.152778,44.344167],"type":"Point"}
}