{
  "id": 2054768,
  "type": "Feature",
  "properties": {
    "tgn:hierarchy":[
        "tgn:2054768",
        "tgn:1000001",
        "tgn:7012149",
        "tgn:2001065",
        "tgn:7007521",
        "tgn:7029392"
    ],
    "tgn:id":2054768,
    "tgn:name":"Kenneth",
    "tgn:placetype":[
        "aat:300008347"
    ]
},
  "bbox": [],
  "geometry": {"coordinates":[-96.0667,43.75],"type":"Point"}
}