{
  "id": 2394820,
  "type": "Feature",
  "properties": {
    "tgn:hierarchy":[
        "tgn:2394820",
        "tgn:1000001",
        "tgn:1002270",
        "tgn:7012149",
        "tgn:7007708",
        "tgn:7029392"
    ],
    "tgn:id":2394820,
    "tgn:name":"Holcomb",
    "tgn:placetype":[
        "aat:300008347"
    ]
},
  "bbox": [],
  "geometry": {"coordinates":[-122.5167,45.3667],"type":"Point"}
}