{
  "id": 7180433,
  "type": "Feature",
  "properties": {
    "tgn:hierarchy":[
        "tgn:7180433",
        "tgn:1000003",
        "tgn:7003676",
        "tgn:7000084",
        "tgn:7029392"
    ],
    "tgn:id":7180433,
    "tgn:name":"Fuchs-Berg",
    "tgn:placetype":[
        "aat:300008777"
    ]
},
  "bbox": [],
  "geometry": {"coordinates":[9.35,53.466667],"type":"Point"}
}