<<<<<<< HEAD
{
  "id": 7053868,
  "type": "Feature",
  "properties": {
    "tgn:hierarchy":[
        "tgn:7053868",
        "tgn:7009084",
        "tgn:7004154",
        "tgn:1000003",
        "tgn:1000080",
        "tgn:7029392"
    ],
    "tgn:id":7053868,
    "tgn:name":"Porrara, Monte",
    "tgn:placetype":[
        "aat:300008795"
    ]
},
  "bbox": [],
  "geometry": {"coordinates":[14.1,41.966667],"type":"Point"}
}
=======
{"geometry":{"type":"Point","coordinates":[14.100000,41.966667]},"type":"Feature","properties":{"hierarchy":["tgn:7053868","tgn:7009084","tgn:7004154","tgn:1000003","tgn:1000080","tgn:7029392"],"placetype":["aat:300008795"],"id":7053868,"name:xx":"Porrara, Monte"}}
>>>>>>> 03f74aca74312dbeaf24d7e61306dd6a786dc3d0
