{
  "id": 2364214,
  "type": "Feature",
  "properties": {
    "tgn:hierarchy":[
        "tgn:2364214",
        "tgn:1000001",
        "tgn:7012149",
        "tgn:2002011",
        "tgn:7007826",
        "tgn:7029392"
    ],
    "tgn:id":2364214,
    "tgn:name":"Green Pond Gully",
    "tgn:placetype":[
        "aat:300008761"
    ]
},
  "bbox": [],
  "geometry": {"coordinates":[-94.2667,30.0833],"type":"Point"}
}