{
  "id": 2115835,
  "type": "Feature",
  "properties": {
    "tgn:hierarchy":[
        "tgn:2115835",
        "tgn:1000001",
        "tgn:7012149",
        "tgn:1003042",
        "tgn:7007920",
        "tgn:7029392"
    ],
    "tgn:id":2115835,
    "tgn:name":"Fruitvale",
    "tgn:placetype":[
        "aat:300008347"
    ]
},
  "bbox": [],
  "geometry": {"coordinates":[-120.55,46.6167],"type":"Point"}
}