{
  "id": 2388725,
  "type": "Feature",
  "properties": {
    "tgn:hierarchy":[
        "tgn:2388725",
        "tgn:1000001",
        "tgn:7006451",
        "tgn:7012149",
        "tgn:2000098",
        "tgn:7029392"
    ],
    "tgn:id":2388725,
    "tgn:name":"Hidden Canyon",
    "tgn:placetype":[
        "aat:300008761"
    ]
},
  "bbox": [],
  "geometry": {"coordinates":[-113.6167,36.3833],"type":"Point"}
}