<<<<<<< HEAD
{
  "id": 7374990,
  "type": "Feature",
  "properties": {
    "tgn:hierarchy":[
        "tgn:7374990",
        "tgn:1000001",
        "tgn:7005595",
        "tgn:7005560",
        "tgn:7029392"
    ],
    "tgn:id":7374990,
    "tgn:name":"La Cuesta",
    "tgn:placetype":[
        "aat:300008347"
    ]
},
  "bbox": [],
  "geometry": {"coordinates":[-108.766667,26.166667],"type":"Point"}
}
=======
{"geometry":{"type":"Point","coordinates":[-108.766667,26.166667]},"type":"Feature","properties":{"hierarchy":["tgn:7374990","tgn:1000001","tgn:7005595","tgn:7005560","tgn:7029392"],"placetype":["aat:300008347"],"id":7374990,"name:xx":"La Cuesta"}}
>>>>>>> 03f74aca74312dbeaf24d7e61306dd6a786dc3d0
