{
  "id": 2668062,
  "type": "Feature",
  "properties": {
    "tgn:hierarchy":[
        "tgn:2668062",
        "tgn:1000001",
        "tgn:2001747",
        "tgn:7012149",
        "tgn:7007712",
        "tgn:7029392"
    ],
    "tgn:id":2668062,
    "tgn:name":"Skyland",
    "tgn:placetype":[
        "aat:300008347"
    ]
},
  "bbox": [],
  "geometry": {"coordinates":[-82.2667,35.0333],"type":"Point"}
}