{
  "id": 2194163,
  "type": "Feature",
  "properties": {
    "tgn:hierarchy":[
        "tgn:2194163",
        "tgn:1000001",
        "tgn:7012149",
        "tgn:2001912",
        "tgn:7007825",
        "tgn:7029392"
    ],
    "tgn:id":2194163,
    "tgn:name":"Brickyard Hollow",
    "tgn:placetype":[
        "aat:300008761"
    ]
},
  "bbox": [],
  "geometry": {"coordinates":[-84.5667,36.3333],"type":"Point"}
}