{
  "id": 2684585,
  "type": "Feature",
  "properties": {
    "tgn:hierarchy":[
        "tgn:2684585",
        "tgn:1000001",
        "tgn:7012149",
        "tgn:2000712",
        "tgn:7007254",
        "tgn:7029392"
    ],
    "tgn:id":2684585,
    "tgn:name":"Spillman Creek",
    "tgn:placetype":[
        "aat:300008706"
    ]
},
  "bbox": [],
  "geometry": {"coordinates":[-98.3667,39.1167],"type":"Point"}
}