{
  "id": 7291548,
  "type": "Feature",
  "properties": {
    "tgn:hierarchy":[
        "tgn:7291548",
        "tgn:1001630",
        "tgn:1000049",
        "tgn:1000002",
        "tgn:7029392"
    ],
    "tgn:id":7291548,
    "tgn:name":"El Jote, Cerro",
    "tgn:placetype":[
        "aat:300008795"
    ]
},
  "bbox": [],
  "geometry": {"coordinates":[-70.516667,-28.75],"type":"Point"}
}