{
  "id": 2490218,
  "type": "Feature",
  "properties": {
    "tgn:hierarchy":[
        "tgn:2490218",
        "tgn:1000001",
        "tgn:7012149",
        "tgn:2000215",
        "tgn:7007158",
        "tgn:7029392"
    ],
    "tgn:id":2490218,
    "tgn:name":"Manchester Mine",
    "tgn:placetype":[
        "aat:300000390"
    ]
},
  "bbox": [],
  "geometry": {"coordinates":[-105.4667,39.9167],"type":"Point"}
}