{
  "id": 2383741,
  "type": "Feature",
  "properties": {
    "tgn:hierarchy":[
        "tgn:2383741",
        "tgn:1000001",
        "tgn:7012149",
        "tgn:2001716",
        "tgn:7007708",
        "tgn:7029392"
    ],
    "tgn:id":2383741,
    "tgn:name":"Heceta Bank",
    "tgn:placetype":[
        "aat:300132348"
    ]
},
  "bbox": [],
  "geometry": {"coordinates":[-124.8333,44.0833],"type":"Point"}
}