{
  "id": 2725902,
  "type": "Feature",
  "properties": {
    "tgn:hierarchy":[
        "tgn:2725902",
        "tgn:1000001",
        "tgn:2002366",
        "tgn:7012149",
        "tgn:7007923",
        "tgn:7029392"
    ],
    "tgn:id":2725902,
    "tgn:name":"Torry Gulch",
    "tgn:placetype":[
        "aat:300008761"
    ]
},
  "bbox": [],
  "geometry": {"coordinates":[-107.6667,44.6667],"type":"Point"}
}