{
  "id": 7494195,
  "type": "Feature",
  "properties": {
    "tgn:hierarchy":[
        "tgn:7494195",
        "tgn:7001010",
        "tgn:1000004",
        "tgn:1000141",
        "tgn:7029392"
    ],
    "tgn:id":7494195,
    "tgn:name":"Changhua Xincun",
    "tgn:placetype":[
        "aat:300000498"
    ]
},
  "bbox": [],
  "geometry": {"coordinates":[121.502307,23.58369],"type":"Point"}
}