{
  "id": 2050042,
  "type": "Feature",
  "properties": {
    "tgn:hierarchy":[
        "tgn:2050042",
        "tgn:1000001",
        "tgn:1002359",
        "tgn:7012149",
        "tgn:7007517",
        "tgn:7029392"
    ],
    "tgn:id":2050042,
    "tgn:name":"Lynn",
    "tgn:placetype":[
        "aat:300008347",
        "aat:300008389",
        "aat:300387308",
        "aat:300387302",
        "aat:300387292"
    ]
},
  "bbox": [],
  "geometry": {"coordinates":[-70.95,42.4667],"type":"Point"}
}