{
  "id": 7186024,
  "type": "Feature",
  "properties": {
    "tgn:hierarchy":[
        "tgn:7186024",
        "tgn:1000003",
        "tgn:7003687",
        "tgn:7000084",
        "tgn:7029392"
    ],
    "tgn:id":7186024,
    "tgn:name":"G\u00f6lzau",
    "tgn:placetype":[
        "aat:300000745"
    ]
},
  "bbox": [],
  "geometry": {"coordinates":[12.083333,51.65],"type":"Point"}
}