{
  "id": 2681307,
  "type": "Feature",
  "properties": {
    "tgn:hierarchy":[
        "tgn:2681307",
        "tgn:1000001",
        "tgn:7012149",
        "tgn:2002003",
        "tgn:7007826",
        "tgn:7029392"
    ],
    "tgn:id":2681307,
    "tgn:name":"South Pasture Tank",
    "tgn:placetype":[
        "aat:300006191"
    ]
},
  "bbox": [],
  "geometry": {"coordinates":[-102.45,33.7833],"type":"Point"}
}