{
  "id": 2678498,
  "type": "Feature",
  "properties": {
    "tgn:hierarchy":[
        "tgn:2678498",
        "tgn:1000001",
        "tgn:7012149",
        "tgn:7007526",
        "tgn:7029392"
    ],
    "tgn:id":2678498,
    "tgn:name":"South Fork Cottonwood Creek",
    "tgn:placetype":[
        "aat:300008706"
    ]
},
  "bbox": [],
  "geometry": {"coordinates":[-115.75,38.05],"type":"Point"}
}