{
  "id": 7499354,
  "type": "Feature",
  "properties": {
    "tgn:hierarchy":[
        "tgn:7499354",
        "tgn:7001010",
        "tgn:1000004",
        "tgn:1000141",
        "tgn:7029392"
    ],
    "tgn:id":7499354,
    "tgn:name":"Qiyan Qiao",
    "tgn:placetype":[
        "aat:300007836"
    ]
},
  "bbox": [],
  "geometry": {"coordinates":[121.456786,23.497871],"type":"Point"}
}