{
  "id": 2199379,
  "type": "Feature",
  "properties": {
    "tgn:hierarchy":[
        "tgn:2199379",
        "tgn:2000454",
        "tgn:1000001",
        "tgn:7012149",
        "tgn:7007250",
        "tgn:7029392"
    ],
    "tgn:id":2199379,
    "tgn:name":"Brush Creek",
    "tgn:placetype":[
        "aat:300008706"
    ]
},
  "bbox": [],
  "geometry": {"coordinates":[-112.0333,42.4833],"type":"Point"}
}