{
  "id": 2003371,
  "type": "Feature",
  "properties": {
    "tgn:hierarchy":[
        "tgn:2003371",
        "tgn:7002659",
        "tgn:1000001",
        "tgn:7012149",
        "tgn:2000050",
        "tgn:7029392"
    ],
    "tgn:id":2003371,
    "tgn:name":"Eastmont",
    "tgn:placetype":[
        "aat:300387016"
    ]
},
  "bbox": [],
  "geometry": {"coordinates":[-86.2167,32.3833],"type":"Point"}
}