{
  "id": 2482298,
  "type": "Feature",
  "properties": {
    "tgn:hierarchy":[
        "tgn:2482298",
        "tgn:1000001",
        "tgn:7016098",
        "tgn:7012149",
        "tgn:7007516",
        "tgn:7029392"
    ],
    "tgn:id":2482298,
    "tgn:name":"Langley Hollow",
    "tgn:placetype":[
        "aat:300008680"
    ]
},
  "bbox": [],
  "geometry": {"coordinates":[-76.4333,38.1333],"type":"Point"}
}