<<<<<<< HEAD
{
  "id": 2154164,
  "type": "Feature",
  "properties": {
    "tgn:hierarchy":[
        "tgn:2154164",
        "tgn:1000001",
        "tgn:1002222",
        "tgn:7012149",
        "tgn:7007520",
        "tgn:7029392"
    ],
    "tgn:id":2154164,
    "tgn:name":"Bear Creek",
    "tgn:placetype":[
        "aat:300008706"
    ]
},
  "bbox": [],
  "geometry": {"coordinates":[-84.9333,42.3167],"type":"Point"}
}
=======
{"geometry":{"type":"Point","coordinates":[-84.933300,42.316700]},"type":"Feature","properties":{"hierarchy":["tgn:2154164","tgn:1000001","tgn:1002222","tgn:7012149","tgn:7007520","tgn:7029392"],"placetype":["aat:300008706"],"id":2154164,"name:xx":"Bear Creek"}}
>>>>>>> 03f74aca74312dbeaf24d7e61306dd6a786dc3d0
