{
  "id": 2271644,
  "type": "Feature",
  "properties": {
    "tgn:hierarchy":[
        "tgn:2271644",
        "tgn:1000001",
        "tgn:7012149",
        "tgn:1002501",
        "tgn:7007710",
        "tgn:7029392"
    ],
    "tgn:id":2271644,
    "tgn:name":"Cummings Reservoir",
    "tgn:placetype":[
        "aat:300006191"
    ]
},
  "bbox": [],
  "geometry": {"coordinates":[-79.1667,40.6833],"type":"Point"}
}