{
  "id": 2325087,
  "type": "Feature",
  "properties": {
    "tgn:hierarchy":[
        "tgn:2325087",
        "tgn:1000001",
        "tgn:7012149",
        "tgn:7007157",
        "tgn:1002791",
        "tgn:7029392"
    ],
    "tgn:id":2325087,
    "tgn:name":"Fern Lake",
    "tgn:placetype":[
        "aat:300008680"
    ]
},
  "bbox": [],
  "geometry": {"coordinates":[-120.25,39.0333],"type":"Point"}
}