{
  "id": 2705412,
  "type": "Feature",
  "properties": {
    "tgn:hierarchy":[
        "tgn:2705412",
        "tgn:1000001",
        "tgn:2001009",
        "tgn:7012149",
        "tgn:7007521",
        "tgn:7029392"
    ],
    "tgn:id":2705412,
    "tgn:name":"Surprise Lake",
    "tgn:placetype":[
        "aat:300008680"
    ]
},
  "bbox": [],
  "geometry": {"coordinates":[-94.4333,46.95],"type":"Point"}
}