{
  "id": 7326843,
  "type": "Feature",
  "properties": {
    "tgn:hierarchy":[
        "tgn:7326843",
        "tgn:7002759",
        "tgn:7002843",
        "tgn:1000003",
        "tgn:1000095",
        "tgn:7029392"
    ],
    "tgn:id":7326843,
    "tgn:name":"Pellejeros, Arroyo de los",
    "tgn:placetype":[
        "aat:300266554",
        "aat:300008699"
    ]
},
  "bbox": [],
  "geometry": {"coordinates":[-0.416667,40.433333],"type":"Point"}
}