{
  "id": 7408518,
  "type": "Feature",
  "properties": {
    "tgn:hierarchy":[
        "tgn:7408518",
        "tgn:1000001",
        "tgn:1001893",
        "tgn:7005560",
        "tgn:7029392"
    ],
    "tgn:id":7408518,
    "tgn:name":"Presa El Molino",
    "tgn:placetype":[
        "aat:300006191"
    ]
},
  "bbox": [],
  "geometry": {"coordinates":[-99.75,20.125],"type":"Point"}
}