{
  "id": 2006106,
  "type": "Feature",
  "properties": {
    "tgn:hierarchy":[
        "tgn:2006106",
        "tgn:7019654",
        "tgn:7006450",
        "tgn:1000001",
        "tgn:7012149",
        "tgn:7019760",
        "tgn:7029392"
    ],
    "tgn:id":2006106,
    "tgn:name":"Hawk Inlet",
    "tgn:placetype":[
        "aat:300008347"
    ]
},
  "bbox": [],
  "geometry": {"coordinates":[-134.75,58.1167],"type":"Point"}
}