{
  "id": 1105288,
  "type": "Feature",
  "properties": {
    "tgn:hierarchy":[
        "tgn:1105288",
        "tgn:1000004",
        "tgn:7491221",
        "tgn:1000141",
        "tgn:7029392"
    ],
    "tgn:id":1105288,
    "tgn:name":"Kuan Shan",
    "tgn:placetype":[
        "aat:300008795"
    ]
},
  "bbox": [],
  "geometry": {"coordinates":[120.911667,23.228333],"type":"Point"}
}