{
  "id": 2696867,
  "type": "Feature",
  "properties": {
    "tgn:hierarchy":[
        "tgn:2696867",
        "tgn:1000001",
        "tgn:7012149",
        "tgn:1002986",
        "tgn:7007568",
        "tgn:7029392"
    ],
    "tgn:id":2696867,
    "tgn:name":"Stones Pond",
    "tgn:placetype":[
        "aat:300006191"
    ]
},
  "bbox": [],
  "geometry": {"coordinates":[-73.8333,43.3167],"type":"Point"}
}