{
  "id": 2750981,
  "type": "Feature",
  "properties": {
    "tgn:hierarchy":[
        "tgn:2750981",
        "tgn:1000001",
        "tgn:7012149",
        "tgn:2002382",
        "tgn:7007923",
        "tgn:7029392"
    ],
    "tgn:id":2750981,
    "tgn:name":"Wardell Reservoir",
    "tgn:placetype":[
        "aat:300006191"
    ]
},
  "bbox": [],
  "geometry": {"coordinates":[-109.85,42.4833],"type":"Point"}
}