{
  "id": 2366208,
  "type": "Feature",
  "properties": {
    "tgn:hierarchy":[
        "tgn:2366208",
        "tgn:1000001",
        "tgn:7019982",
        "tgn:7012149",
        "tgn:7007517",
        "tgn:7029392"
    ],
    "tgn:id":2366208,
    "tgn:name":"Griffin Brook",
    "tgn:placetype":[
        "aat:300008699"
    ]
},
  "bbox": [],
  "geometry": {"coordinates":[-72.9833,42.25],"type":"Point"}
}