{
  "id": 7437072,
  "type": "Feature",
  "properties": {
    "tgn:hierarchy":[
        "tgn:7437072",
        "tgn:1000001",
        "tgn:1001893",
        "tgn:7005560",
        "tgn:7029392"
    ],
    "tgn:id":7437072,
    "tgn:name":"Tepetitl\u00e1n",
    "tgn:placetype":[
        "aat:300008347"
    ]
},
  "bbox": [],
  "geometry": {"coordinates":[-99.916667,19.633333],"type":"Point"}
}