{
  "id": 2034564,
  "type": "Feature",
  "properties": {
    "tgn:hierarchy":[
        "tgn:2034564",
        "tgn:1000001",
        "tgn:7012149",
        "tgn:2000659",
        "tgn:7007253",
        "tgn:7029392"
    ],
    "tgn:id":2034564,
    "tgn:name":"Cornelia",
    "tgn:placetype":[
        "aat:300008347"
    ]
},
  "bbox": [],
  "geometry": {"coordinates":[-93.6667,42.7833],"type":"Point"}
}