{
  "id": 2606722,
  "type": "Feature",
  "properties": {
    "tgn:hierarchy":[
        "tgn:2606722",
        "tgn:7006450",
        "tgn:1000001",
        "tgn:2124053",
        "tgn:7012149",
        "tgn:7029392"
    ],
    "tgn:id":2606722,
    "tgn:name":"Ramsdyke Creek",
    "tgn:placetype":[
        "aat:300008706"
    ]
},
  "bbox": [],
  "geometry": {"coordinates":[-150.8667,62.5833],"type":"Point"}
}