{
  "id": 7340481,
  "type": "Feature",
  "properties": {
    "tgn:hierarchy":[
        "tgn:7340481",
        "tgn:7002834",
        "tgn:1000003",
        "tgn:7002786",
        "tgn:1000095",
        "tgn:7029392"
    ],
    "tgn:id":7340481,
    "tgn:name":"Cort\u00e9s, Punta",
    "tgn:placetype":[
        "aat:300386846"
    ]
},
  "bbox": [],
  "geometry": {"coordinates":[-8.733333,42.266667],"type":"Point"}
}