{
  "id": 2023904,
  "type": "Feature",
  "properties": {
    "tgn:hierarchy":[
        "tgn:2023904",
        "tgn:1000001",
        "tgn:7012149",
        "tgn:2000400",
        "tgn:7007248",
        "tgn:7029392"
    ],
    "tgn:id":2023904,
    "tgn:name":"Philomath",
    "tgn:placetype":[
        "aat:300008347"
    ]
},
  "bbox": [],
  "geometry": {"coordinates":[-82.9833,33.7167],"type":"Point"}
}