{
  "id": 7356378,
  "type": "Feature",
  "properties": {
    "tgn:hierarchy":[
        "tgn:7356378",
        "tgn:7005581",
        "tgn:1000001",
        "tgn:7005560",
        "tgn:7029392"
    ],
    "tgn:id":7356378,
    "tgn:name":"Rancho California",
    "tgn:placetype":[
        "aat:300000241"
    ]
},
  "bbox": [],
  "geometry": {"coordinates":[-106.566667,25.966667],"type":"Point"}
}