{
  "id": 7123726,
  "type": "Feature",
  "properties": {
    "tgn:hierarchy":[
        "tgn:7123726",
        "tgn:1000003",
        "tgn:7003682",
        "tgn:7000084",
        "tgn:7029392"
    ],
    "tgn:id":7123726,
    "tgn:name":"Neuhaus Sang",
    "tgn:placetype":[
        "aat:300000206"
    ]
},
  "bbox": [],
  "geometry": {"coordinates":[6.733333,49.783333],"type":"Point"}
}