{
  "id": 7540242,
  "type": "Feature",
  "properties": {
    "tgn:hierarchy":[
        "tgn:7540242",
        "tgn:7001242",
        "tgn:7016833",
        "tgn:7001336",
        "tgn:7029392"
    ],
    "tgn:id":7540242,
    "tgn:name:en":"Millan, Ras el-",
    "tgn:placetype":[
        "aat:300008808"
    ]
},
  "bbox": [],
  "geometry": {"coordinates":[33.85,27.866667],"type":"Point"}
}