{
  "id": 7401161,
  "type": "Feature",
  "properties": {
    "tgn:hierarchy":[
        "tgn:7401161",
        "tgn:1000001",
        "tgn:7005599",
        "tgn:7005560",
        "tgn:7029392"
    ],
    "tgn:id":7401161,
    "tgn:name":"El Triunfo",
    "tgn:placetype":[
        "aat:300008347"
    ]
},
  "bbox": [],
  "geometry": {"coordinates":[-96.866667,19.066667],"type":"Point"}
}