<<<<<<< HEAD
{
  "id": 2768269,
  "type": "Feature",
  "properties": {
    "tgn:hierarchy":[
        "tgn:2768269",
        "tgn:7002659",
        "tgn:1000001",
        "tgn:7012149",
        "tgn:2000021",
        "tgn:7029392"
    ],
    "tgn:id":2768269,
    "tgn:name":"Whites Pond",
    "tgn:placetype":[
        "aat:300008680"
    ]
},
  "bbox": [],
  "geometry": {"coordinates":[-86.9667,34.2],"type":"Point"}
}
=======
{"geometry":{"type":"Point","coordinates":[-86.966700,34.200000]},"type":"Feature","properties":{"hierarchy":["tgn:2768269","tgn:7002659","tgn:1000001","tgn:7012149","tgn:2000021","tgn:7029392"],"placetype":["aat:300008680"],"id":2768269,"name:xx":"Whites Pond"}}
>>>>>>> 03f74aca74312dbeaf24d7e61306dd6a786dc3d0
