{
  "id": 2709390,
  "type": "Feature",
  "properties": {
    "tgn:hierarchy":[
        "tgn:2709390",
        "tgn:1000001",
        "tgn:2001747",
        "tgn:7012149",
        "tgn:7007712",
        "tgn:7029392"
    ],
    "tgn:id":2709390,
    "tgn:name":"Table Rock Cove",
    "tgn:placetype":[
        "aat:300006191"
    ]
},
  "bbox": [],
  "geometry": {"coordinates":[-82.6667,35.05],"type":"Point"}
}