{
  "id": 7148618,
  "type": "Feature",
  "properties": {
    "tgn:hierarchy":[
        "tgn:7148618",
        "tgn:1000003",
        "tgn:7003676",
        "tgn:7000084",
        "tgn:7029392"
    ],
    "tgn:id":7148618,
    "tgn:name":"Kuperstede",
    "tgn:placetype":[
        "aat:300000206"
    ]
},
  "bbox": [],
  "geometry": {"coordinates":[7.933333,53.633333],"type":"Point"}
}