{
  "id": 7145474,
  "type": "Feature",
  "properties": {
    "tgn:hierarchy":[
        "tgn:7145474",
        "tgn:7003669",
        "tgn:1000003",
        "tgn:7000084",
        "tgn:7029392"
    ],
    "tgn:id":7145474,
    "tgn:name":"Kolm\u00f6d",
    "tgn:placetype":[
        "aat:300000206"
    ]
},
  "bbox": [],
  "geometry": {"coordinates":[11.966667,48.616667],"type":"Point"}
}