{
  "id": 2220458,
  "type": "Feature",
  "properties": {
    "tgn:hierarchy":[
        "tgn:2220458",
        "tgn:7006450",
        "tgn:1000001",
        "tgn:2124012",
        "tgn:7012149",
        "tgn:7029392"
    ],
    "tgn:id":2220458,
    "tgn:name":"Cape Kasiak",
    "tgn:placetype":[
        "aat:300008850"
    ]
},
  "bbox": [],
  "geometry": {"coordinates":[-153.4833,57.0667],"type":"Point"}
}