{
  "id": 7040153,
  "type": "Feature",
  "properties": {
    "tgn:hierarchy":[
        "tgn:7040153",
        "tgn:1003447",
        "tgn:7007850",
        "tgn:1000003",
        "tgn:1000080",
        "tgn:7029392"
    ],
    "tgn:id":7040153,
    "tgn:name":"Savuto",
    "tgn:placetype":[
        "aat:300008347"
    ]
},
  "bbox": [],
  "geometry": {"coordinates":[16.166667,39.066667],"type":"Point"}
}