{
  "id": 7484245,
  "type": "Feature",
  "properties": {
    "tgn:hierarchy":[
        "tgn:7484245",
        "tgn:7001004",
        "tgn:1000004",
        "tgn:1000141",
        "tgn:7029392"
    ],
    "tgn:id":7484245,
    "tgn:name":"Pingziding",
    "tgn:placetype":[
        "aat:300008347"
    ]
},
  "bbox": [],
  "geometry": {"coordinates":[120.514167,23.002222],"type":"Point"}
}