{
  "id": 2782529,
  "type": "Feature",
  "properties": {
    "tgn:hierarchy":[
        "tgn:2782529",
        "tgn:1000001",
        "tgn:2001702",
        "tgn:7012149",
        "tgn:7007708",
        "tgn:7029392"
    ],
    "tgn:id":2782529,
    "tgn:name":"Woolsey Creek",
    "tgn:placetype":[
        "aat:300008706"
    ]
},
  "bbox": [],
  "geometry": {"coordinates":[-124.2667,43.1333],"type":"Point"}
}