{
  "id": 1061088,
  "type": "Feature",
  "properties": {
    "tgn:hierarchy":[
        "tgn:1061088",
        "tgn:1000004",
        "tgn:7011600",
        "tgn:7018214",
        "tgn:7002435",
        "tgn:7029392"
    ],
    "tgn:id":1061088,
    "tgn:name":"Verkhynaya Tura",
    "tgn:placetype":[
        "aat:300008347"
    ]
},
  "bbox": [],
  "geometry": {"coordinates":[59.8333,58.3667],"type":"Point"}
}