<<<<<<< HEAD
{
  "id": 7355896,
  "type": "Feature",
  "properties": {
    "tgn:hierarchy":[
        "tgn:7355896",
        "tgn:7005586",
        "tgn:1000001",
        "tgn:7005560",
        "tgn:7029392"
    ],
    "tgn:id":7355896,
    "tgn:name":"Carburo",
    "tgn:placetype":[
        "aat:300007783"
    ]
},
  "bbox": [],
  "geometry": {"coordinates":[-103.416667,20.683333],"type":"Point"}
}
=======
{"geometry":{"type":"Point","coordinates":[-103.416667,20.683333]},"type":"Feature","properties":{"hierarchy":["tgn:7355896","tgn:7005586","tgn:1000001","tgn:7005560","tgn:7029392"],"placetype":["aat:300007783"],"id":7355896,"name:xx":"Carburo"}}
>>>>>>> 03f74aca74312dbeaf24d7e61306dd6a786dc3d0
