{
  "id": 7355896,
  "type": "Feature",
  "properties": {
    "tgn:hierarchy":[
        "tgn:7355896",
        "tgn:7005586",
        "tgn:1000001",
        "tgn:7005560",
        "tgn:7029392"
    ],
    "tgn:id":7355896,
    "tgn:name":"Carburo",
    "tgn:placetype":[
        "aat:300007783"
    ]
},
  "bbox": [],
  "geometry": {"coordinates":[-103.416667,20.683333],"type":"Point"}
}