{
  "id": 2672912,
  "type": "Feature",
  "properties": {
    "tgn:hierarchy":[
        "tgn:2672912",
        "tgn:1000001",
        "tgn:7012149",
        "tgn:2000969",
        "tgn:7007520",
        "tgn:7029392"
    ],
    "tgn:id":2672912,
    "tgn:name":"Snake Creek",
    "tgn:placetype":[
        "aat:300008706"
    ]
},
  "bbox": [],
  "geometry": {"coordinates":[-88.1833,47.35],"type":"Point"}
}