{
  "id": 7562446,
  "type": "Feature",
  "properties": {
    "tgn:hierarchy":[
        "tgn:7562446",
        "tgn:1000004",
        "tgn:7000198",
        "tgn:7016722",
        "tgn:7029392"
    ],
    "tgn:id":7562446,
    "tgn:name:en":"Dalelnagar",
    "tgn:placetype":[
        "aat:300008347"
    ]
},
  "bbox": [],
  "geometry": {"coordinates":[79.268931,27.856781],"type":"Point"}
}