{
  "id": 2128327,
  "type": "Feature",
  "properties": {
    "tgn:hierarchy":[
        "tgn:2128327",
        "tgn:1000001",
        "tgn:1002259",
        "tgn:7012149",
        "tgn:7007568",
        "tgn:7029392"
    ],
    "tgn:id":2128327,
    "tgn:name":"Alder Bottom Creek",
    "tgn:placetype":[
        "aat:300008706"
    ]
},
  "bbox": [],
  "geometry": {"coordinates":[-79.55,42.0833],"type":"Point"}
}