{
  "id": 7529667,
  "type": "Feature",
  "properties": {
    "tgn:hierarchy":[
        "tgn:7529667",
        "tgn:7001242",
        "tgn:7016833",
        "tgn:7001336",
        "tgn:7029392"
    ],
    "tgn:id":7529667,
    "tgn:name:en":"Umm Rayjah, W\u0101d\u012b",
    "tgn:placetype":[
        "aat:300379998"
    ]
},
  "bbox": [],
  "geometry": {"coordinates":[33.576082,28.960686],"type":"Point"}
}