{
  "id": 1116952,
  "type": "Feature",
  "properties": {
    "tgn:hierarchy":[
        "tgn:1116952",
        "tgn:7006477",
        "tgn:1001203",
        "tgn:1000002",
        "tgn:7029392"
    ],
    "tgn:id":1116952,
    "tgn:name":"La Plata, Lago",
    "tgn:placetype":[
        "aat:300008680"
    ]
},
  "bbox": [],
  "geometry": {"coordinates":[-71.8333,-44.8833],"type":"Point"}
}