{
  "id": 2301004,
  "type": "Feature",
  "properties": {
    "tgn:hierarchy":[
        "tgn:2301004",
        "tgn:1002716",
        "tgn:1000001",
        "tgn:7012149",
        "tgn:7007711",
        "tgn:7029392"
    ],
    "tgn:id":2301004,
    "tgn:name":"Dundery Brook",
    "tgn:placetype":[
        "aat:300008699"
    ]
},
  "bbox": [],
  "geometry": {"coordinates":[-71.1833,41.5167],"type":"Point"}
}