{
  "id": 1107999,
  "type": "Feature",
  "properties": {
    "tgn:hierarchy":[
        "tgn:1107999",
        "tgn:1001172",
        "tgn:1008967",
        "tgn:1000002",
        "tgn:1000056",
        "tgn:7029392"
    ],
    "tgn:id":1107999,
    "tgn:name":"Guanay, Cerro",
    "tgn:placetype":[
        "aat:300008777"
    ]
},
  "bbox": [],
  "geometry": {"coordinates":[-77.2167,-12.1167],"type":"Point"}
}