<<<<<<< HEAD
{
  "id": 2406666,
  "type": "Feature",
  "properties": {
    "tgn:hierarchy":[
        "tgn:2406666",
        "tgn:1000001",
        "tgn:7012149",
        "tgn:1002553",
        "tgn:7007920",
        "tgn:7029392"
    ],
    "tgn:id":2406666,
    "tgn:name":"Hunt Creek",
    "tgn:placetype":[
        "aat:300008706"
    ]
},
  "bbox": [],
  "geometry": {"coordinates":[-120.1667,47.0667],"type":"Point"}
}
=======
{"geometry":{"type":"Point","coordinates":[-120.166700,47.066700]},"type":"Feature","properties":{"hierarchy":["tgn:2406666","tgn:1000001","tgn:7012149","tgn:1002553","tgn:7007920","tgn:7029392"],"placetype":["aat:300008706"],"id":2406666,"name:xx":"Hunt Creek"}}
>>>>>>> 03f74aca74312dbeaf24d7e61306dd6a786dc3d0
