{
  "id": 7546294,
  "type": "Feature",
  "properties": {
    "tgn:hierarchy":[
        "tgn:7546294",
        "tgn:1000004",
        "tgn:1001871",
        "tgn:7000198",
        "tgn:7029392"
    ],
    "tgn:id":7546294,
    "tgn:name:en":"B\u0101khli",
    "tgn:placetype":[
        "aat:300008347"
    ]
},
  "bbox": [],
  "geometry": {"coordinates":[76.51762,30.022605],"type":"Point"}
}