{
  "id": 1009282,
  "type": "Feature",
  "properties": {
    "tgn:hierarchy":[
        "tgn:1009282",
        "tgn:7006450",
        "tgn:1000001",
        "tgn:7012149",
        "tgn:2000082",
        "tgn:7029392"
    ],
    "tgn:id":1009282,
    "tgn:name":"Suemez Island",
    "tgn:placetype":[
        "aat:300008791"
    ]
},
  "bbox": [],
  "geometry": {"coordinates":[-133.35,55.25],"type":"Point"}
}