{
  "id": 7077064,
  "type": "Feature",
  "properties": {
    "tgn:hierarchy":[
        "tgn:7077064",
        "tgn:1000003",
        "tgn:7003678",
        "tgn:7000084",
        "tgn:7029392"
    ],
    "tgn:id":7077064,
    "tgn:name":"Odenwaldkreis",
    "tgn:placetype":[
        "aat:300387198"
    ]
},
  "bbox": [],
  "geometry": {"coordinates":[8.992778,49.688056],"type":"Point"}
}