{
  "id": 2224279,
  "type": "Feature",
  "properties": {
    "tgn:hierarchy":[
        "tgn:2224279",
        "tgn:1000001",
        "tgn:7012149",
        "tgn:2000214",
        "tgn:7007158",
        "tgn:7029392"
    ],
    "tgn:id":2224279,
    "tgn:name":"Cascade Canyon",
    "tgn:placetype":[
        "aat:300008761"
    ]
},
  "bbox": [],
  "geometry": {"coordinates":[-108.2167,39.55],"type":"Point"}
}