{
  "id": 7075992,
  "type": "Feature",
  "properties": {
    "tgn:hierarchy":[
        "tgn:7075992",
        "tgn:1000003",
        "tgn:7003677",
        "tgn:7000084",
        "tgn:7029392"
    ],
    "tgn:id":7075992,
    "tgn:name":"Niederrheinisches Tiefland",
    "tgn:placetype":[
        "aat:300055621"
    ]
},
  "bbox": [],
  "geometry": {"coordinates":[6.366667,51.45],"type":"Point"}
}