<<<<<<< HEAD
{
  "id": 2762129,
  "type": "Feature",
  "properties": {
    "tgn:hierarchy":[
        "tgn:2762129",
        "tgn:1000001",
        "tgn:7006451",
        "tgn:7012149",
        "tgn:2000102",
        "tgn:7029392"
    ],
    "tgn:id":2762129,
    "tgn:name":"West Six Tank",
    "tgn:placetype":[
        "aat:300006191"
    ]
},
  "bbox": [],
  "geometry": {"coordinates":[-110.6333,31.4167],"type":"Point"}
}
=======
{"geometry":{"type":"Point","coordinates":[-110.633300,31.416700]},"type":"Feature","properties":{"hierarchy":["tgn:2762129","tgn:1000001","tgn:7006451","tgn:7012149","tgn:2000102","tgn:7029392"],"placetype":["aat:300006191"],"id":2762129,"name:xx":"West Six Tank"}}
>>>>>>> 03f74aca74312dbeaf24d7e61306dd6a786dc3d0
