{
  "id": 7509394,
  "type": "Feature",
  "properties": {
    "tgn:hierarchy":[
        "tgn:7509394",
        "tgn:1008380",
        "tgn:1000226",
        "tgn:7018426",
        "tgn:1000006",
        "tgn:7029392"
    ],
    "tgn:id":7509394,
    "tgn:name:en":"Table Mountain",
    "tgn:placetype":[
        "aat:300008795"
    ]
},
  "bbox": [],
  "geometry": {"coordinates":[175.666667,-37.05],"type":"Point"}
}