{
  "id": 2587721,
  "type": "Feature",
  "properties": {
    "tgn:hierarchy":[
        "tgn:2587721",
        "tgn:1000001",
        "tgn:7012149",
        "tgn:7007157",
        "tgn:1002710",
        "tgn:7029392"
    ],
    "tgn:id":2587721,
    "tgn:name":"Pleasant Valley",
    "tgn:placetype":[
        "aat:300386845"
    ]
},
  "bbox": [],
  "geometry": {"coordinates":[-121.1833,39.25],"type":"Point"}
}