<<<<<<< HEAD
{
  "id": 7482765,
  "type": "Feature",
  "properties": {
    "tgn:hierarchy":[
        "tgn:7482765",
        "tgn:1000004",
        "tgn:7489179",
        "tgn:1000141",
        "tgn:7029392"
    ],
    "tgn:id":7482765,
    "tgn:name":"Guoling Guoxiao",
    "tgn:placetype":[
        "aat:300006495"
    ]
},
  "bbox": [],
  "geometry": {"coordinates":[121.814444,24.759444],"type":"Point"}
}
=======
{"geometry":{"type":"Point","coordinates":[121.814444,24.759444]},"type":"Feature","properties":{"hierarchy":["tgn:7482765","tgn:1000004","tgn:7489179","tgn:1000141","tgn:7029392"],"placetype":["aat:300006495"],"id":7482765,"name:xx":"Guoling Guoxiao"}}
>>>>>>> 03f74aca74312dbeaf24d7e61306dd6a786dc3d0
