{
  "id": 2557755,
  "type": "Feature",
  "properties": {
    "tgn:hierarchy":[
        "tgn:2557755",
        "tgn:1000001",
        "tgn:2001092",
        "tgn:7012149",
        "tgn:7007522",
        "tgn:7029392"
    ],
    "tgn:id":2557755,
    "tgn:name":"Old River Run",
    "tgn:placetype":[
        "aat:300008707"
    ]
},
  "bbox": [],
  "geometry": {"coordinates":[-89.1833,34.0167],"type":"Point"}
}