{
  "id": 2328175,
  "type": "Feature",
  "properties": {
    "tgn:hierarchy":[
        "tgn:2328175",
        "tgn:1000001",
        "tgn:2001412",
        "tgn:7012149",
        "tgn:7007526",
        "tgn:7029392"
    ],
    "tgn:id":2328175,
    "tgn:name":"Fish Spring",
    "tgn:placetype":[
        "aat:300008697"
    ]
},
  "bbox": [],
  "geometry": {"coordinates":[-118.0333,37.9833],"type":"Point"}
}