{
  "id": 7590270,
  "type": "Feature",
  "properties": {
    "tgn:hierarchy":[
        "tgn:7590270",
        "tgn:1000004",
        "tgn:7000198",
        "tgn:7000799",
        "tgn:7029392"
    ],
    "tgn:id":7590270,
    "tgn:name:en":"Barwan",
    "tgn:placetype":[
        "aat:300008347"
    ]
},
  "bbox": [],
  "geometry": {"coordinates":[73.889658,34.3863],"type":"Point"}
}