{
  "id": 1077915,
  "type": "Feature",
  "properties": {
    "tgn:hierarchy":[
        "tgn:1077915",
        "tgn:1000004",
        "tgn:1001336",
        "tgn:1000116",
        "tgn:7029392"
    ],
    "tgn:id":1077915,
    "tgn:name":"Kualapesaguan",
    "tgn:placetype":[
        "aat:300008347"
    ]
},
  "bbox": [],
  "geometry": {"coordinates":[110.1333,-2.0167],"type":"Point"}
}