{
  "id": 7542154,
  "type": "Feature",
  "properties": {
    "tgn:hierarchy":[
        "tgn:7542154",
        "tgn:7001242",
        "tgn:1001059",
        "tgn:7016833",
        "tgn:7029392"
    ],
    "tgn:id":7542154,
    "tgn:name:en":"Mu\u1e29ammad ash Sha\u1e29\u1e29\u0101t",
    "tgn:placetype":[
        "aat:300000206"
    ]
},
  "bbox": [],
  "geometry": {"coordinates":[31.436752,30.769432],"type":"Point"}
}