{
  "id": 7491926,
  "type": "Feature",
  "properties": {
    "tgn:hierarchy":[
        "tgn:7491926",
        "tgn:1000004",
        "tgn:7491221",
        "tgn:1000141",
        "tgn:7029392"
    ],
    "tgn:id":7491926,
    "tgn:name":"Damawuku Shan",
    "tgn:placetype":[
        "aat:300008798"
    ]
},
  "bbox": [],
  "geometry": {"coordinates":[121.287222,22.977778],"type":"Point"}
}