{
  "id": 2413981,
  "type": "Feature",
  "properties": {
    "tgn:hierarchy":[
        "tgn:2413981",
        "tgn:1000001",
        "tgn:7012149",
        "tgn:2002379",
        "tgn:7007923",
        "tgn:7029392"
    ],
    "tgn:id":2413981,
    "tgn:name":"Iron Creek",
    "tgn:placetype":[
        "aat:300008706"
    ]
},
  "bbox": [],
  "geometry": {"coordinates":[-108.9167,44.0167],"type":"Point"}
}