<<<<<<< HEAD
{
  "id": 7022831,
  "type": "Feature",
  "properties": {
    "tgn:hierarchy":[
        "tgn:7022831",
        "tgn:1000001",
        "tgn:7012149",
        "tgn:7007248",
        "tgn:7029392"
    ],
    "tgn:id":7022831,
    "tgn:name":"Reservoir Four",
    "tgn:placetype":[
        "aat:300006191"
    ]
},
  "bbox": [],
  "geometry": {"coordinates":[-84.0833,34.3],"type":"Point"}
}
=======
{"geometry":{"type":"Point","coordinates":[-84.083300,34.300000]},"type":"Feature","properties":{"hierarchy":["tgn:7022831","tgn:1000001","tgn:7012149","tgn:7007248","tgn:7029392"],"placetype":["aat:300006191"],"id":7022831,"name:xx":"Reservoir Four"}}
>>>>>>> 03f74aca74312dbeaf24d7e61306dd6a786dc3d0
