{
  "id": 7582190,
  "type": "Feature",
  "properties": {
    "tgn:hierarchy":[
        "tgn:7582190",
        "tgn:1000004",
        "tgn:7000198",
        "tgn:7016788",
        "tgn:7029392"
    ],
    "tgn:id":7582190,
    "tgn:name:en":"Gadoli",
    "tgn:placetype":[
        "aat:300008347"
    ]
},
  "bbox": [],
  "geometry": {"coordinates":[75.654745,28.427591],"type":"Point"}
}