{
  "id": 7522141,
  "type": "Feature",
  "properties": {
    "tgn:hierarchy":[
        "tgn:7522141",
        "tgn:7001242",
        "tgn:7016833",
        "tgn:1001080",
        "tgn:7029392"
    ],
    "tgn:id":7522141,
    "tgn:name:en":"Ab\u016b Rimth, \u1e28\u0101mad",
    "tgn:placetype":[
        "aat:300008805"
    ]
},
  "bbox": [],
  "geometry": {"coordinates":[31.85,30.333333],"type":"Point"}
}