{
  "id": 1053704,
  "type": "Feature",
  "properties": {
    "tgn:hierarchy":[
        "tgn:1053704",
        "tgn:1000004",
        "tgn:7011573",
        "tgn:7018214",
        "tgn:7002435",
        "tgn:7029392"
    ],
    "tgn:id":1053704,
    "tgn:name":"Dorokhovo",
    "tgn:placetype":[
        "aat:300008347"
    ]
},
  "bbox": [],
  "geometry": {"coordinates":[36.5333,55.5333],"type":"Point"}
}