{
  "id": 2389152,
  "type": "Feature",
  "properties": {
    "tgn:hierarchy":[
        "tgn:2389152",
        "tgn:1000001",
        "tgn:2001432",
        "tgn:7012149",
        "tgn:7007566",
        "tgn:7029392"
    ],
    "tgn:id":2389152,
    "tgn:name":"Hidden Valley",
    "tgn:placetype":[
        "aat:300008761"
    ]
},
  "bbox": [],
  "geometry": {"coordinates":[-105.05,36.4833],"type":"Point"}
}