{
  "id": 2190229,
  "type": "Feature",
  "properties": {
    "tgn:hierarchy":[
        "tgn:2190229",
        "tgn:1000001",
        "tgn:7012149",
        "tgn:2001926",
        "tgn:7007825",
        "tgn:7029392"
    ],
    "tgn:id":2190229,
    "tgn:name":"Bowser Ridge",
    "tgn:placetype":[
        "aat:300266640"
    ]
},
  "bbox": [],
  "geometry": {"coordinates":[-82.5333,36.4167],"type":"Point"}
}