{
  "id": 2431471,
  "type": "Feature",
  "properties": {
    "tgn:hierarchy":[
        "tgn:2431471",
        "tgn:1000001",
        "tgn:7012149",
        "tgn:1002742",
        "tgn:7007920",
        "tgn:7029392"
    ],
    "tgn:id":2431471,
    "tgn:name":"Kartar Creek",
    "tgn:placetype":[
        "aat:300008706"
    ]
},
  "bbox": [],
  "geometry": {"coordinates":[-119.15,48.2667],"type":"Point"}
}