{
  "id": 7294664,
  "type": "Feature",
  "properties": {
    "tgn:hierarchy":[
        "tgn:7294664",
        "tgn:7002758",
        "tgn:7002821",
        "tgn:1000003",
        "tgn:1000095",
        "tgn:7029392"
    ],
    "tgn:id":7294664,
    "tgn:name":"Venta, Arroyo de la",
    "tgn:placetype":[
        "aat:300008699"
    ]
},
  "bbox": [],
  "geometry": {"coordinates":[-3.85,36.933333],"type":"Point"}
}