{
  "id": 7339273,
  "type": "Feature",
  "properties": {
    "tgn:hierarchy":[
        "tgn:7339273",
        "tgn:7002803",
        "tgn:1001647",
        "tgn:1000003",
        "tgn:1000095",
        "tgn:7029392"
    ],
    "tgn:id":7339273,
    "tgn:name":"Derramadero",
    "tgn:placetype":[
        "aat:300008347"
    ]
},
  "bbox": [],
  "geometry": {"coordinates":[-2.05,38.483333],"type":"Point"}
}