{
  "id": 2196169,
  "type": "Feature",
  "properties": {
    "tgn:hierarchy":[
        "tgn:2196169",
        "tgn:1000001",
        "tgn:1002210",
        "tgn:7012149",
        "tgn:7007706",
        "tgn:7029392"
    ],
    "tgn:id":2196169,
    "tgn:name":"Brodie Lake",
    "tgn:placetype":[
        "aat:300006191"
    ]
},
  "bbox": [],
  "geometry": {"coordinates":[-84.0167,38.8667],"type":"Point"}
}