{
  "id": 2138876,
  "type": "Feature",
  "properties": {
    "tgn:hierarchy":[
        "tgn:2138876",
        "tgn:1000001",
        "tgn:7012149",
        "tgn:2002279",
        "tgn:7013961",
        "tgn:7029392"
    ],
    "tgn:id":2138876,
    "tgn:name":"Ashcabin Run",
    "tgn:placetype":[
        "aat:300008699"
    ]
},
  "bbox": [],
  "geometry": {"coordinates":[-78.9167,39.4667],"type":"Point"}
}