{
  "id": 2703805,
  "type": "Feature",
  "properties": {
    "tgn:hierarchy":[
        "tgn:2703805",
        "tgn:1000001",
        "tgn:2001429",
        "tgn:7012149",
        "tgn:7007566",
        "tgn:7029392"
    ],
    "tgn:id":2703805,
    "tgn:name":"Sun Tank",
    "tgn:placetype":[
        "aat:300006191"
    ]
},
  "bbox": [],
  "geometry": {"coordinates":[-108.9833,33.3667],"type":"Point"}
}