{
  "id": 7150750,
  "type": "Feature",
  "properties": {
    "tgn:hierarchy":[
        "tgn:7150750",
        "tgn:7003669",
        "tgn:1000003",
        "tgn:7000084",
        "tgn:7029392"
    ],
    "tgn:id":7150750,
    "tgn:name":"Krinning",
    "tgn:placetype":[
        "aat:300000206"
    ]
},
  "bbox": [],
  "geometry": {"coordinates":[12.316667,47.866667],"type":"Point"}
}