{
  "id": 7304852,
  "type": "Feature",
  "properties": {
    "tgn:hierarchy":[
        "tgn:7304852",
        "tgn:7008911",
        "tgn:1000003",
        "tgn:7002763",
        "tgn:1000095",
        "tgn:7029392"
    ],
    "tgn:id":7304852,
    "tgn:name":"Lavares",
    "tgn:placetype":[
        "aat:300008347"
    ]
},
  "bbox": [],
  "geometry": {"coordinates":[-5.95,43.283333],"type":"Point"}
}