{
  "id": 7385890,
  "type": "Feature",
  "properties": {
    "tgn:hierarchy":[
        "tgn:7385890",
        "tgn:7005581",
        "tgn:1000001",
        "tgn:7005560",
        "tgn:7029392"
    ],
    "tgn:id":7385890,
    "tgn:name":"Pres\u00f3n, Arroyo",
    "tgn:placetype":[
        "aat:300266554",
        "aat:300008699"
    ]
},
  "bbox": [],
  "geometry": {"coordinates":[-104.833333,29.333333],"type":"Point"}
}