{
  "id": 7155597,
  "type": "Feature",
  "properties": {
    "tgn:hierarchy":[
        "tgn:7155597",
        "tgn:1000003",
        "tgn:7003676",
        "tgn:7000084",
        "tgn:7029392"
    ],
    "tgn:id":7155597,
    "tgn:name":"Klein Hesepe",
    "tgn:placetype":[
        "aat:300008347"
    ]
},
  "bbox": [],
  "geometry": {"coordinates":[7.233333,52.633333],"type":"Point"}
}