{
  "id": 7523599,
  "type": "Feature",
  "properties": {
    "tgn:hierarchy":[
        "tgn:7523599",
        "tgn:7001242",
        "tgn:7016833",
        "tgn:1001113",
        "tgn:7029392"
    ],
    "tgn:id":7523599,
    "tgn:name:en":"A\u015f \u015e\u0101l\u1e29\u012byah",
    "tgn:placetype":[
        "aat:300008347"
    ]
},
  "bbox": [],
  "geometry": {"coordinates":[31.989369,30.780112],"type":"Point"}
}