{
  "id": 2768687,
  "type": "Feature",
  "properties": {
    "tgn:hierarchy":[
        "tgn:2768687",
        "tgn:1000001",
        "tgn:7016172",
        "tgn:7012149",
        "tgn:2000172",
        "tgn:7029392"
    ],
    "tgn:id":2768687,
    "tgn:name":"Whitlock Branch",
    "tgn:placetype":[
        "aat:300008699"
    ]
},
  "bbox": [],
  "geometry": {"coordinates":[-91.5333,36.0333],"type":"Point"}
}