{
  "id": 1132856,
  "type": "Feature",
  "properties": {
    "tgn:hierarchy":[
        "tgn:1132856",
        "tgn:1000001",
        "tgn:7012149",
        "tgn:1002873",
        "tgn:7007568",
        "tgn:7029392"
    ],
    "tgn:id":1132856,
    "tgn:name":"Cobleskill Creek",
    "tgn:placetype":[
        "aat:300008706"
    ]
},
  "bbox": [],
  "geometry": {"coordinates":[-74.55,42.6333],"type":"Point"}
}