{
  "id": 2722605,
  "type": "Feature",
  "properties": {
    "tgn:hierarchy":[
        "tgn:2722605",
        "tgn:1000001",
        "tgn:7012149",
        "tgn:1002932",
        "tgn:7007710",
        "tgn:7029392"
    ],
    "tgn:id":2722605,
    "tgn:name":"Tinker Hill",
    "tgn:placetype":[
        "aat:300008798"
    ]
},
  "bbox": [],
  "geometry": {"coordinates":[-75.5167,41.6833],"type":"Point"}
}