{
  "id": 2293939,
  "type": "Feature",
  "properties": {
    "tgn:hierarchy":[
        "tgn:2293939",
        "tgn:1000001",
        "tgn:2001098",
        "tgn:7012149",
        "tgn:7007522",
        "tgn:7029392"
    ],
    "tgn:id":2293939,
    "tgn:name":"Douglas Lake",
    "tgn:placetype":[
        "aat:300006191"
    ]
},
  "bbox": [],
  "geometry": {"coordinates":[-88.55,33.6333],"type":"Point"}
}