{
  "id": 2136416,
  "type": "Feature",
  "properties": {
    "tgn:hierarchy":[
        "tgn:2136416",
        "tgn:1000001",
        "tgn:2000939",
        "tgn:7012149",
        "tgn:7007516",
        "tgn:7029392"
    ],
    "tgn:id":2136416,
    "tgn:name":"Arcadia Shores",
    "tgn:placetype":[
        "aat:300008347"
    ]
},
  "bbox": [],
  "geometry": {"coordinates":[-76.15,38.75],"type":"Point"}
}