{
  "id": 7563391,
  "type": "Feature",
  "properties": {
    "tgn:hierarchy":[
        "tgn:7563391",
        "tgn:1000004",
        "tgn:7000198",
        "tgn:1001894",
        "tgn:7029392"
    ],
    "tgn:id":7563391,
    "tgn:name:en":"Ladora",
    "tgn:placetype":[
        "aat:300008347"
    ]
},
  "bbox": [],
  "geometry": {"coordinates":[79.048663,24.149293],"type":"Point"}
}