<<<<<<< HEAD
{
  "id": 2258049,
  "type": "Feature",
  "properties": {
    "tgn:hierarchy":[
        "tgn:2258049",
        "tgn:1002366",
        "tgn:1000001",
        "tgn:7012149",
        "tgn:7007159",
        "tgn:7029392"
    ],
    "tgn:id":2258049,
    "tgn:name":"Cos Cob Pond",
    "tgn:placetype":[
        "aat:300008680"
    ]
},
  "bbox": [],
  "geometry": {"coordinates":[-73.6,41.0333],"type":"Point"}
}
=======
{"geometry":{"type":"Point","coordinates":[-73.600000,41.033300]},"type":"Feature","properties":{"hierarchy":["tgn:2258049","tgn:1002366","tgn:1000001","tgn:7012149","tgn:7007159","tgn:7029392"],"placetype":["aat:300008680"],"id":2258049,"name:xx":"Cos Cob Pond"}}
>>>>>>> 03f74aca74312dbeaf24d7e61306dd6a786dc3d0
