{
  "id": 1074148,
  "type": "Feature",
  "properties": {
    "tgn:hierarchy":[
        "tgn:1074148",
        "tgn:1000004",
        "tgn:7002078",
        "tgn:1000111",
        "tgn:7029392"
    ],
    "tgn:id":1074148,
    "tgn:name":"Zhujiawan",
    "tgn:placetype":[
        "aat:300008347"
    ]
},
  "bbox": [],
  "geometry": {"coordinates":[114.1667,30.9333],"type":"Point"}
}