{
  "id": 2329493,
  "type": "Feature",
  "properties": {
    "tgn:hierarchy":[
        "tgn:2329493",
        "tgn:1000001",
        "tgn:7012149",
        "tgn:1002892",
        "tgn:7007520",
        "tgn:7029392"
    ],
    "tgn:id":2329493,
    "tgn:name":"Five Points North",
    "tgn:placetype":[
        "aat:300008347"
    ]
},
  "bbox": [],
  "geometry": {"coordinates":[-84.1667,43.0667],"type":"Point"}
}