{
  "id": 7242256,
  "type": "Feature",
  "properties": {
    "tgn:hierarchy":[
        "tgn:7242256",
        "tgn:7007877",
        "tgn:1000003",
        "tgn:1000063",
        "tgn:4012014",
        "tgn:7029392"
    ],
    "tgn:id":7242256,
    "tgn:name":"La Houlette",
    "tgn:placetype":[
        "aat:300008347"
    ]
},
  "bbox": [],
  "geometry": {"coordinates":[3.68235,50.31774],"type":"Point"}
}