{
  "id": 7552882,
  "type": "Feature",
  "properties": {
    "tgn:hierarchy":[
        "tgn:7552882",
        "tgn:1001828",
        "tgn:1000004",
        "tgn:7000198",
        "tgn:7029392"
    ],
    "tgn:id":7552882,
    "tgn:name:en":"P\u0101mudurti",
    "tgn:placetype":[
        "aat:300008347"
    ]
},
  "bbox": [],
  "geometry": {"coordinates":[77.983333,14.266667],"type":"Point"}
}