<<<<<<< HEAD
{
  "id": 2334512,
  "type": "Feature",
  "properties": {
    "tgn:hierarchy":[
        "tgn:2334512",
        "tgn:1000001",
        "tgn:7012149",
        "tgn:7007158",
        "tgn:2000251",
        "tgn:7029392"
    ],
    "tgn:id":2334512,
    "tgn:name":"Forest Queen Mine",
    "tgn:placetype":[
        "aat:300000390"
    ]
},
  "bbox": [],
  "geometry": {"coordinates":[-105.1333,38.7333],"type":"Point"}
}
=======
{"geometry":{"type":"Point","coordinates":[-105.133300,38.733300]},"type":"Feature","properties":{"hierarchy":["tgn:2334512","tgn:1000001","tgn:7012149","tgn:7007158","tgn:2000251","tgn:7029392"],"placetype":["aat:300000390"],"id":2334512,"name:xx":"Forest Queen Mine"}}
>>>>>>> 03f74aca74312dbeaf24d7e61306dd6a786dc3d0
