{
  "id": 7157697,
  "type": "Feature",
  "properties": {
    "tgn:hierarchy":[
        "tgn:7157697",
        "tgn:7000096",
        "tgn:1000003",
        "tgn:7000084",
        "tgn:7029392"
    ],
    "tgn:id":7157697,
    "tgn:name":"Kleiner Hauptkanal",
    "tgn:placetype":[
        "aat:300006075"
    ]
},
  "bbox": [],
  "geometry": {"coordinates":[12.833333,52.716667],"type":"Point"}
}