{
  "id": 2615922,
  "type": "Feature",
  "properties": {
    "tgn:hierarchy":[
        "tgn:2615922",
        "tgn:1000001",
        "tgn:7016172",
        "tgn:7012149",
        "tgn:2000132",
        "tgn:7029392"
    ],
    "tgn:id":2615922,
    "tgn:name":"Reynolds Park Lake",
    "tgn:placetype":[
        "aat:300006191"
    ]
},
  "bbox": [],
  "geometry": {"coordinates":[-90.5167,36.0667],"type":"Point"}
}