<<<<<<< HEAD
{
  "id": 7052605,
  "type": "Feature",
  "properties": {
    "tgn:hierarchy":[
        "tgn:7052605",
        "tgn:7007850",
        "tgn:7024842",
        "tgn:1000003",
        "tgn:1000080",
        "tgn:7029392"
    ],
    "tgn:id":7052605,
    "tgn:name":"Ionadi",
    "tgn:placetype":[
        "aat:300008347"
    ]
},
  "bbox": [],
  "geometry": {"coordinates":[16.05,38.616667],"type":"Point"}
}
=======
{"geometry":{"type":"Point","coordinates":[16.050000,38.616667]},"type":"Feature","properties":{"hierarchy":["tgn:7052605","tgn:7007850","tgn:7024842","tgn:1000003","tgn:1000080","tgn:7029392"],"placetype":["aat:300008347"],"id":7052605,"name:xx":"Ionadi"}}
>>>>>>> 03f74aca74312dbeaf24d7e61306dd6a786dc3d0
