{
  "id": 2011829,
  "type": "Feature",
  "properties": {
    "tgn:hierarchy":[
        "tgn:2011829",
        "tgn:1000001",
        "tgn:7012149",
        "tgn:1002392",
        "tgn:7007157",
        "tgn:7029392"
    ],
    "tgn:id":2011829,
    "tgn:name":"Humphreys Station",
    "tgn:placetype":[
        "aat:300008347",
        "aat:300387210"
    ]
},
  "bbox": [],
  "geometry": {"coordinates":[-119.4333,36.95],"type":"Point"}
}