<<<<<<< HEAD
{
  "id": 2258564,
  "type": "Feature",
  "properties": {
    "tgn:hierarchy":[
        "tgn:2258564",
        "tgn:1000001",
        "tgn:7012149",
        "tgn:2000488",
        "tgn:7007250",
        "tgn:7029392"
    ],
    "tgn:id":2258564,
    "tgn:name":"Cottontail Island",
    "tgn:placetype":[
        "aat:300008791"
    ]
},
  "bbox": [],
  "geometry": {"coordinates":[-116.75,43.45],"type":"Point"}
}
=======
{"geometry":{"type":"Point","coordinates":[-116.750000,43.450000]},"type":"Feature","properties":{"hierarchy":["tgn:2258564","tgn:1000001","tgn:7012149","tgn:2000488","tgn:7007250","tgn:7029392"],"placetype":["aat:300008791"],"id":2258564,"name:xx":"Cottontail Island"}}
>>>>>>> 03f74aca74312dbeaf24d7e61306dd6a786dc3d0
