<<<<<<< HEAD
{
  "id": 2332961,
  "type": "Feature",
  "properties": {
    "tgn:hierarchy":[
        "tgn:2332961",
        "tgn:1000001",
        "tgn:2001263",
        "tgn:7012149",
        "tgn:7007524",
        "tgn:7029392"
    ],
    "tgn:id":2332961,
    "tgn:name":"Flume Hollow",
    "tgn:placetype":[
        "aat:300008761"
    ]
},
  "bbox": [],
  "geometry": {"coordinates":[-111.3,46.3167],"type":"Point"}
}
=======
{"geometry":{"type":"Point","coordinates":[-111.300000,46.316700]},"type":"Feature","properties":{"hierarchy":["tgn:2332961","tgn:1000001","tgn:2001263","tgn:7012149","tgn:7007524","tgn:7029392"],"placetype":["aat:300008761"],"id":2332961,"name:xx":"Flume Hollow"}}
>>>>>>> 03f74aca74312dbeaf24d7e61306dd6a786dc3d0
