{
  "id": 7351793,
  "type": "Feature",
  "properties": {
    "tgn:hierarchy":[
        "tgn:7351793",
        "tgn:1000001",
        "tgn:1001960",
        "tgn:7005560",
        "tgn:7029392"
    ],
    "tgn:id":7351793,
    "tgn:name":"Caj\u00f3n de Cuitaca, Cerro",
    "tgn:placetype":[
        "aat:300008795"
    ]
},
  "bbox": [],
  "geometry": {"coordinates":[-110.483333,31.016667],"type":"Point"}
}