<<<<<<< HEAD
{
  "id": 7351793,
  "type": "Feature",
  "properties": {
    "tgn:hierarchy":[
        "tgn:7351793",
        "tgn:1000001",
        "tgn:1001960",
        "tgn:7005560",
        "tgn:7029392"
    ],
    "tgn:id":7351793,
    "tgn:name":"Caj\u00f3n de Cuitaca, Cerro",
    "tgn:placetype":[
        "aat:300008795"
    ]
},
  "bbox": [],
  "geometry": {"coordinates":[-110.483333,31.016667],"type":"Point"}
}
=======
{"geometry":{"type":"Point","coordinates":[-110.483333,31.016667]},"type":"Feature","properties":{"hierarchy":["tgn:7351793","tgn:1000001","tgn:1001960","tgn:7005560","tgn:7029392"],"placetype":["aat:300008795"],"id":7351793,"name:xx":"Caj\u00f3n de Cuitaca, Cerro"}}
>>>>>>> 03f74aca74312dbeaf24d7e61306dd6a786dc3d0
