{
  "id": 2290806,
  "type": "Feature",
  "properties": {
    "tgn:hierarchy":[
        "tgn:2290806",
        "tgn:1000001",
        "tgn:7012149",
        "tgn:2001831",
        "tgn:7007713",
        "tgn:7029392"
    ],
    "tgn:id":2290806,
    "tgn:name":"Dog Ear Buttes",
    "tgn:placetype":[
        "aat:300008798"
    ]
},
  "bbox": [],
  "geometry": {"coordinates":[-99.9167,43.25],"type":"Point"}
}