{
  "id": 7563244,
  "type": "Feature",
  "properties": {
    "tgn:hierarchy":[
        "tgn:7563244",
        "tgn:1000004",
        "tgn:7000198",
        "tgn:7016722",
        "tgn:7029392"
    ],
    "tgn:id":7563244,
    "tgn:name:en":"Chh\u0101chhari",
    "tgn:placetype":[
        "aat:300008347"
    ]
},
  "bbox": [],
  "geometry": {"coordinates":[79.414497,25.427541],"type":"Point"}
}