{
  "id": 7590867,
  "type": "Feature",
  "properties": {
    "tgn:hierarchy":[
        "tgn:7590867",
        "tgn:1000004",
        "tgn:7000198",
        "tgn:7000799",
        "tgn:7029392"
    ],
    "tgn:id":7590867,
    "tgn:name:en":"Kh\u0101g Forest",
    "tgn:placetype":[
        "aat:300008863"
    ]
},
  "bbox": [],
  "geometry": {"coordinates":[74.490677,33.996148],"type":"Point"}
}