{
  "id": 2277303,
  "type": "Feature",
  "properties": {
    "tgn:hierarchy":[
        "tgn:2277303",
        "tgn:7002659",
        "tgn:1000001",
        "tgn:7012149",
        "tgn:2000053",
        "tgn:7029392"
    ],
    "tgn:id":2277303,
    "tgn:name":"Davis Lake",
    "tgn:placetype":[
        "aat:300006191"
    ]
},
  "bbox": [],
  "geometry": {"coordinates":[-88.05,33.4833],"type":"Point"}
}