{
  "id": 2633525,
  "type": "Feature",
  "properties": {
    "tgn:hierarchy":[
        "tgn:2633525",
        "tgn:1000001",
        "tgn:7012149",
        "tgn:2001286",
        "tgn:7007524",
        "tgn:7029392"
    ],
    "tgn:id":2633525,
    "tgn:name":"Runt Creek",
    "tgn:placetype":[
        "aat:300008706"
    ]
},
  "bbox": [],
  "geometry": {"coordinates":[-115.85,48.8833],"type":"Point"}
}