{
  "id": 7515751,
  "type": "Feature",
  "properties": {
    "tgn:hierarchy":[
        "tgn:7515751",
        "tgn:1008380",
        "tgn:7000507",
        "tgn:1000226",
        "tgn:1000006",
        "tgn:7029392"
    ],
    "tgn:id":7515751,
    "tgn:name:en":"Mangonui, Port",
    "tgn:placetype":[
        "aat:300008678"
    ]
},
  "bbox": [],
  "geometry": {"coordinates":[173.55,-34.983333],"type":"Point"}
}