{
  "id": 7588458,
  "type": "Feature",
  "properties": {
    "tgn:hierarchy":[
        "tgn:7588458",
        "tgn:1000004",
        "tgn:7000198",
        "tgn:7000799",
        "tgn:7029392"
    ],
    "tgn:id":7588458,
    "tgn:name:en":"Far\u0101shgund",
    "tgn:placetype":[
        "aat:300008347"
    ]
},
  "bbox": [],
  "geometry": {"coordinates":[74.683333,34.066667],"type":"Point"}
}