<<<<<<< HEAD
{
  "id": 7361700,
  "type": "Feature",
  "properties": {
    "tgn:hierarchy":[
        "tgn:7361700",
        "tgn:1000001",
        "tgn:1001906",
        "tgn:7005560",
        "tgn:7029392"
    ],
    "tgn:id":7361700,
    "tgn:name":"El Canelito",
    "tgn:placetype":[
        "aat:300008347"
    ]
},
  "bbox": [],
  "geometry": {"coordinates":[-100.716667,24.633333],"type":"Point"}
}
=======
{"geometry":{"type":"Point","coordinates":[-100.716667,24.633333]},"type":"Feature","properties":{"hierarchy":["tgn:7361700","tgn:1000001","tgn:1001906","tgn:7005560","tgn:7029392"],"placetype":["aat:300008347"],"id":7361700,"name:xx":"El Canelito"}}
>>>>>>> 03f74aca74312dbeaf24d7e61306dd6a786dc3d0
