{
  "id": 2100811,
  "type": "Feature",
  "properties": {
    "tgn:hierarchy":[
        "tgn:2100811",
        "tgn:1000001",
        "tgn:7012149",
        "tgn:2001855",
        "tgn:7007825",
        "tgn:7029392"
    ],
    "tgn:id":2100811,
    "tgn:name":"Oak Hill",
    "tgn:placetype":[
        "aat:300008347"
    ]
},
  "bbox": [],
  "geometry": {"coordinates":[-86.7667,36.0833],"type":"Point"}
}