{
  "id": 2258496,
  "type": "Feature",
  "properties": {
    "tgn:hierarchy":[
        "tgn:2258496",
        "tgn:1000001",
        "tgn:7012149",
        "tgn:2001897",
        "tgn:7007825",
        "tgn:7029392"
    ],
    "tgn:id":2258496,
    "tgn:name":"Cotton Port Ridge",
    "tgn:placetype":[
        "aat:300266640"
    ]
},
  "bbox": [],
  "geometry": {"coordinates":[-84.85,35.45],"type":"Point"}
}