<<<<<<< HEAD
{
  "id": 2403565,
  "type": "Feature",
  "properties": {
    "tgn:hierarchy":[
        "tgn:2403565",
        "tgn:1000001",
        "tgn:7012149",
        "tgn:7007157",
        "tgn:2000190",
        "tgn:7029392"
    ],
    "tgn:id":2403565,
    "tgn:name":"Howard Creek",
    "tgn:placetype":[
        "aat:300008706"
    ]
},
  "bbox": [],
  "geometry": {"coordinates":[-121.6333,40.2833],"type":"Point"}
}
=======
{"geometry":{"type":"Point","coordinates":[-121.633300,40.283300]},"type":"Feature","properties":{"hierarchy":["tgn:2403565","tgn:1000001","tgn:7012149","tgn:7007157","tgn:2000190","tgn:7029392"],"placetype":["aat:300008706"],"id":2403565,"name:xx":"Howard Creek"}}
>>>>>>> 03f74aca74312dbeaf24d7e61306dd6a786dc3d0
