{
  "id": 2301035,
  "type": "Feature",
  "properties": {
    "tgn:hierarchy":[
        "tgn:2301035",
        "tgn:1000001",
        "tgn:7012149",
        "tgn:2002191",
        "tgn:7007919",
        "tgn:7029392"
    ],
    "tgn:id":2301035,
    "tgn:name":"Dunford Ridge",
    "tgn:placetype":[
        "aat:300266640"
    ]
},
  "bbox": [],
  "geometry": {"coordinates":[-81.5167,36.75],"type":"Point"}
}