{
  "id": 2774451,
  "type": "Feature",
  "properties": {
    "tgn:hierarchy":[
        "tgn:2774451",
        "tgn:1000001",
        "tgn:7012149",
        "tgn:2002011",
        "tgn:7007826",
        "tgn:7029392"
    ],
    "tgn:id":2774451,
    "tgn:name":"Willow Lake",
    "tgn:placetype":[
        "aat:300008680"
    ]
},
  "bbox": [],
  "geometry": {"coordinates":[-94.0333,29.75],"type":"Point"}
}