{
  "id": 7514607,
  "type": "Feature",
  "properties": {
    "tgn:hierarchy":[
        "tgn:7514607",
        "tgn:1009227",
        "tgn:1000226",
        "tgn:7016822",
        "tgn:1000006",
        "tgn:7029392"
    ],
    "tgn:id":7514607,
    "tgn:name:en":"Deep Bight",
    "tgn:placetype":[
        "aat:300132316"
    ]
},
  "bbox": [],
  "geometry": {"coordinates":[166.033333,-50.683333],"type":"Point"}
}