<<<<<<< HEAD
{
  "id": 2158965,
  "type": "Feature",
  "properties": {
    "tgn:hierarchy":[
        "tgn:2158965",
        "tgn:1000001",
        "tgn:7012149",
        "tgn:1002460",
        "tgn:7007826",
        "tgn:7029392"
    ],
    "tgn:id":2158965,
    "tgn:name":"Beckum Creek",
    "tgn:placetype":[
        "aat:300008706"
    ]
},
  "bbox": [],
  "geometry": {"coordinates":[-94.2833,32.6667],"type":"Point"}
}
=======
{"geometry":{"type":"Point","coordinates":[-94.283300,32.666700]},"type":"Feature","properties":{"hierarchy":["tgn:2158965","tgn:1000001","tgn:7012149","tgn:1002460","tgn:7007826","tgn:7029392"],"placetype":["aat:300008706"],"id":2158965,"name:xx":"Beckum Creek"}}
>>>>>>> 03f74aca74312dbeaf24d7e61306dd6a786dc3d0
