{
  "id": 2161345,
  "type": "Feature",
  "properties": {
    "tgn:hierarchy":[
        "tgn:2161345",
        "tgn:1000001",
        "tgn:2000670",
        "tgn:7012149",
        "tgn:7007254",
        "tgn:7029392"
    ],
    "tgn:id":2161345,
    "tgn:name":"Bell Mound",
    "tgn:placetype":[
        "aat:300008798"
    ]
},
  "bbox": [],
  "geometry": {"coordinates":[-94.9333,37.2833],"type":"Point"}
}