{
  "id": 7559560,
  "type": "Feature",
  "properties": {
    "tgn:hierarchy":[
        "tgn:7559560",
        "tgn:1000004",
        "tgn:7031781",
        "tgn:7000198",
        "tgn:7029392"
    ],
    "tgn:id":7559560,
    "tgn:name:en":"R\u0101j\u0101dera",
    "tgn:placetype":[
        "aat:300008347"
    ]
},
  "bbox": [],
  "geometry": {"coordinates":[84.231129,23.286374],"type":"Point"}
}