{
  "id": 1104937,
  "type": "Feature",
  "properties": {
    "tgn:hierarchy":[
        "tgn:1104937",
        "tgn:7003028",
        "tgn:1000003",
        "tgn:1000062",
        "tgn:7029392"
    ],
    "tgn:id":1104937,
    "tgn:name":"Hochwildstelle",
    "tgn:placetype":[
        "aat:300008795"
    ]
},
  "bbox": [],
  "geometry": {"coordinates":[13.8333,47.3333],"type":"Point"}
}