{
  "id": 7525334,
  "type": "Feature",
  "properties": {
    "tgn:hierarchy":[
        "tgn:7525334",
        "tgn:7001242",
        "tgn:7016833",
        "tgn:7000123",
        "tgn:7029392"
    ],
    "tgn:id":7525334,
    "tgn:name:en":"Dahsahash Sharq\u012b, \u1e28aw\u1e11 ad",
    "tgn:placetype":[
        "aat:300343519"
    ]
},
  "bbox": [],
  "geometry": {"coordinates":[32.183333,26.033333],"type":"Point"}
}