<<<<<<< HEAD
{
  "id": 2764338,
  "type": "Feature",
  "properties": {
    "tgn:hierarchy":[
        "tgn:2764338",
        "tgn:1000001",
        "tgn:7012149",
        "tgn:2001856",
        "tgn:7007825",
        "tgn:7029392"
    ],
    "tgn:id":2764338,
    "tgn:name":"Whetstone Branch",
    "tgn:placetype":[
        "aat:300008699"
    ]
},
  "bbox": [],
  "geometry": {"coordinates":[-88.15,35.45],"type":"Point"}
}
=======
{"geometry":{"type":"Point","coordinates":[-88.150000,35.450000]},"type":"Feature","properties":{"hierarchy":["tgn:2764338","tgn:1000001","tgn:7012149","tgn:2001856","tgn:7007825","tgn:7029392"],"placetype":["aat:300008699"],"id":2764338,"name:xx":"Whetstone Branch"}}
>>>>>>> 03f74aca74312dbeaf24d7e61306dd6a786dc3d0
