<<<<<<< HEAD
{
  "id": 7377320,
  "type": "Feature",
  "properties": {
    "tgn:hierarchy":[
        "tgn:7377320",
        "tgn:7005581",
        "tgn:1000001",
        "tgn:7005560",
        "tgn:7029392"
    ],
    "tgn:id":7377320,
    "tgn:name":"La Union",
    "tgn:placetype":[
        "aat:300008347"
    ]
},
  "bbox": [],
  "geometry": {"coordinates":[-106.866667,28.783333],"type":"Point"}
}
=======
{"geometry":{"type":"Point","coordinates":[-106.866667,28.783333]},"type":"Feature","properties":{"hierarchy":["tgn:7377320","tgn:7005581","tgn:1000001","tgn:7005560","tgn:7029392"],"placetype":["aat:300008347"],"id":7377320,"name:xx":"La Union"}}
>>>>>>> 03f74aca74312dbeaf24d7e61306dd6a786dc3d0
