{
  "id": 7487770,
  "type": "Feature",
  "properties": {
    "tgn:hierarchy":[
        "tgn:7487770",
        "tgn:1000004",
        "tgn:1000959",
        "tgn:1000141",
        "tgn:7029392"
    ],
    "tgn:id":7487770,
    "tgn:name":"Nanjiao",
    "tgn:placetype":[
        "aat:300008347"
    ]
},
  "bbox": [],
  "geometry": {"coordinates":[121.516667,24.983333],"type":"Point"}
}