{
  "id": 7571472,
  "type": "Feature",
  "properties": {
    "tgn:hierarchy":[
        "tgn:7571472",
        "tgn:1000004",
        "tgn:7000198",
        "tgn:1001977",
        "tgn:7029392"
    ],
    "tgn:id":7571472,
    "tgn:name:en":"H\u0101sim\u0101ra",
    "tgn:placetype":[
        "aat:300007783"
    ]
},
  "bbox": [],
  "geometry": {"coordinates":[89.36612,26.734554],"type":"Point"}
}