{
  "id": 7438442,
  "type": "Feature",
  "properties": {
    "tgn:hierarchy":[
        "tgn:7438442",
        "tgn:1000001",
        "tgn:7005600",
        "tgn:7005560",
        "tgn:7029392"
    ],
    "tgn:id":7438442,
    "tgn:name":"Telchaquillo",
    "tgn:placetype":[
        "aat:300008347"
    ]
},
  "bbox": [],
  "geometry": {"coordinates":[-89.466667,20.633333],"type":"Point"}
}