{
  "id": 7388057,
  "type": "Feature",
  "properties": {
    "tgn:hierarchy":[
        "tgn:7388057",
        "tgn:1000001",
        "tgn:1001960",
        "tgn:7005560",
        "tgn:7029392"
    ],
    "tgn:id":7388057,
    "tgn:name":"Piedra, Isla de",
    "tgn:placetype":[
        "aat:300008791"
    ]
},
  "bbox": [],
  "geometry": {"coordinates":[-106.333333,23.166667],"type":"Point"}
}