{
  "id": 7117270,
  "type": "Feature",
  "properties": {
    "tgn:hierarchy":[
        "tgn:7117270",
        "tgn:1000003",
        "tgn:7003676",
        "tgn:7000084",
        "tgn:7029392"
    ],
    "tgn:id":7117270,
    "tgn:name":"Ostsiedlung Alhorn",
    "tgn:placetype":[
        "aat:300008347"
    ]
},
  "bbox": [],
  "geometry": {"coordinates":[8.233333,52.866667],"type":"Point"}
}