{
  "id": 2779812,
  "type": "Feature",
  "properties": {
    "tgn:hierarchy":[
        "tgn:2779812",
        "tgn:1000001",
        "tgn:7012149",
        "tgn:1002352",
        "tgn:7007710",
        "tgn:7029392"
    ],
    "tgn:id":2779812,
    "tgn:name":"Wolf Run Spring",
    "tgn:placetype":[
        "aat:300008697"
    ]
},
  "bbox": [],
  "geometry": {"coordinates":[-78.8667,41.5833],"type":"Point"}
}