{
  "id": 7501768,
  "type": "Feature",
  "properties": {
    "tgn:hierarchy":[
        "tgn:7501768",
        "tgn:7001004",
        "tgn:1000004",
        "tgn:1000141",
        "tgn:7029392"
    ],
    "tgn:id":7501768,
    "tgn:name":"Longhu Gong",
    "tgn:placetype":[
        "aat:300007595"
    ]
},
  "bbox": [],
  "geometry": {"coordinates":[120.417778,22.945556],"type":"Point"}
}