{
  "id": 7047166,
  "type": "Feature",
  "properties": {
    "tgn:hierarchy":[
        "tgn:7047166",
        "tgn:7015163",
        "tgn:1000003",
        "tgn:7003121",
        "tgn:1000080",
        "tgn:7029392"
    ],
    "tgn:id":7047166,
    "tgn:name":"Coghinas, Foce del",
    "tgn:placetype":[
        "aat:300387057"
    ]
},
  "bbox": [],
  "geometry": {"coordinates":[8.816667,40.933333],"type":"Point"}
}