{
  "id": 2710450,
  "type": "Feature",
  "properties": {
    "tgn:hierarchy":[
        "tgn:2710450",
        "tgn:1000001",
        "tgn:7012149",
        "tgn:7007708",
        "tgn:7029392"
    ],
    "tgn:id":2710450,
    "tgn:name":"Tamarack Creek",
    "tgn:placetype":[
        "aat:300008706"
    ]
},
  "bbox": [],
  "geometry": {"coordinates":[-119.6333,44.8833],"type":"Point"}
}