{
  "id": 7294968,
  "type": "Feature",
  "properties": {
    "tgn:hierarchy":[
        "tgn:7294968",
        "tgn:7001158",
        "tgn:7002848",
        "tgn:1000003",
        "tgn:1000095",
        "tgn:7029392"
    ],
    "tgn:id":7294968,
    "tgn:name":"Viloria",
    "tgn:placetype":[
        "aat:300008347"
    ]
},
  "bbox": [],
  "geometry": {"coordinates":[-4.383333,41.45],"type":"Point"}
}