{
  "id": 7145407,
  "type": "Feature",
  "properties": {
    "tgn:hierarchy":[
        "tgn:7145407",
        "tgn:1000003",
        "tgn:7003685",
        "tgn:7000084",
        "tgn:7029392"
    ],
    "tgn:id":7145407,
    "tgn:name":"Kossen",
    "tgn:placetype":[
        "aat:300008347"
    ]
},
  "bbox": [],
  "geometry": {"coordinates":[12.633333,51.416667],"type":"Point"}
}