{
  "id": 7437162,
  "type": "Feature",
  "properties": {
    "tgn:hierarchy":[
        "tgn:7437162",
        "tgn:7005581",
        "tgn:1000001",
        "tgn:7005560",
        "tgn:7029392"
    ],
    "tgn:id":7437162,
    "tgn:name":"Rancho Silva",
    "tgn:placetype":[
        "aat:300000241"
    ]
},
  "bbox": [],
  "geometry": {"coordinates":[-106.233333,28.516667],"type":"Point"}
}