{
  "id": 7265013,
  "type": "Feature",
  "properties": {
    "tgn:hierarchy":[
        "tgn:7265013",
        "tgn:7003614",
        "tgn:1000003",
        "tgn:7016845",
        "tgn:7029392"
    ],
    "tgn:id":7265013,
    "tgn:name:nl":"Kievitslanden",
    "tgn:placetype":[
        "aat:300387200"
    ]
},
  "bbox": [],
  "geometry": {"coordinates":[6.783333,53.05],"type":"Point"}
}