{
  "id": 2630632,
  "type": "Feature",
  "properties": {
    "tgn:hierarchy":[
        "tgn:2630632",
        "tgn:1000001",
        "tgn:7012149",
        "tgn:1003034",
        "tgn:7007826",
        "tgn:7029392"
    ],
    "tgn:id":2630632,
    "tgn:name":"Round Holes, The",
    "tgn:placetype":[
        "aat:300008680"
    ]
},
  "bbox": [],
  "geometry": {"coordinates":[-95.3833,32.6667],"type":"Point"}
}