{
  "id": 7524162,
  "type": "Feature",
  "properties": {
    "tgn:hierarchy":[
        "tgn:7524162",
        "tgn:7001242",
        "tgn:7016833",
        "tgn:7001335",
        "tgn:7029392"
    ],
    "tgn:id":7524162,
    "tgn:name:en":"El-Qushl\u00e2q\u00e2t",
    "tgn:placetype":[
        "aat:300008347"
    ]
},
  "bbox": [],
  "geometry": {"coordinates":[33.816667,31.133333],"type":"Point"}
}