{
  "id": 2633265,
  "type": "Feature",
  "properties": {
    "tgn:hierarchy":[
        "tgn:2633265",
        "tgn:1000001",
        "tgn:7012149",
        "tgn:2001753",
        "tgn:7007712",
        "tgn:7029392"
    ],
    "tgn:id":2633265,
    "tgn:name":"Rum Creek",
    "tgn:placetype":[
        "aat:300008706"
    ]
},
  "bbox": [],
  "geometry": {"coordinates":[-80.75,34.65],"type":"Point"}
}