{
  "id": 2315182,
  "type": "Feature",
  "properties": {
    "tgn:hierarchy":[
        "tgn:2315182",
        "tgn:7002659",
        "tgn:1000001",
        "tgn:7012149",
        "tgn:2000047",
        "tgn:7029392"
    ],
    "tgn:id":2315182,
    "tgn:name":"Ellenburg Mountain",
    "tgn:placetype":[
        "aat:300008798"
    ]
},
  "bbox": [],
  "geometry": {"coordinates":[-86.2167,34.3667],"type":"Point"}
}