{
  "id": 2490924,
  "type": "Feature",
  "properties": {
    "tgn:hierarchy":[
        "tgn:2490924",
        "tgn:1000001",
        "tgn:2000304",
        "tgn:7012149",
        "tgn:7007248",
        "tgn:7029392"
    ],
    "tgn:id":2490924,
    "tgn:name":"Manson",
    "tgn:placetype":[
        "aat:300008347"
    ]
},
  "bbox": [],
  "geometry": {"coordinates":[-81.9667,31.3333],"type":"Point"}
}