<<<<<<< HEAD
{
  "id": 7059215,
  "type": "Feature",
  "properties": {
    "tgn:hierarchy":[
        "tgn:7059215",
        "tgn:7016648",
        "tgn:1000001",
        "tgn:7593111",
        "tgn:7029392"
    ],
    "tgn:id":7059215,
    "tgn:name":"Lag\u00fan",
    "tgn:placetype":[
        "aat:300008347"
    ]
},
  "bbox": [],
  "geometry": {"coordinates":[-69.15,12.316],"type":"Point"}
}
=======
{"geometry":{"type":"Point","coordinates":[-69.150000,12.316000]},"type":"Feature","properties":{"hierarchy":["tgn:7059215","tgn:7016648","tgn:1000001","tgn:7593111","tgn:7029392"],"placetype":["aat:300008347"],"id":7059215,"name:xx":"Lag\u00fan"}}
>>>>>>> 03f74aca74312dbeaf24d7e61306dd6a786dc3d0
