{
  "id": 7059215,
  "type": "Feature",
  "properties": {
    "tgn:hierarchy":[
        "tgn:7059215",
        "tgn:7016648",
        "tgn:1000001",
        "tgn:7593111",
        "tgn:7029392"
    ],
    "tgn:id":7059215,
    "tgn:name":"Lag\u00fan",
    "tgn:placetype":[
        "aat:300008347"
    ]
},
  "bbox": [],
  "geometry": {"coordinates":[-69.15,12.316],"type":"Point"}
}