{
  "id": 7557858,
  "type": "Feature",
  "properties": {
    "tgn:hierarchy":[
        "tgn:7557858",
        "tgn:1000004",
        "tgn:7000198",
        "tgn:1001894",
        "tgn:7029392"
    ],
    "tgn:id":7557858,
    "tgn:name:en":"Rao",
    "tgn:placetype":[
        "aat:300007783"
    ]
},
  "bbox": [],
  "geometry": {"coordinates":[75.805091,22.632338],"type":"Point"}
}