{
  "id": 7545132,
  "type": "Feature",
  "properties": {
    "tgn:hierarchy":[
        "tgn:7545132",
        "tgn:1000004",
        "tgn:7000201",
        "tgn:7000198",
        "tgn:7029392"
    ],
    "tgn:id":7545132,
    "tgn:name:en":"Badarpur",
    "tgn:placetype":[
        "aat:300008347"
    ]
},
  "bbox": [],
  "geometry": {"coordinates":[77.302213,28.502279],"type":"Point"}
}