<<<<<<< HEAD
{
  "id": 2332524,
  "type": "Feature",
  "properties": {
    "tgn:hierarchy":[
        "tgn:2332524",
        "tgn:2001726",
        "tgn:1000001",
        "tgn:7012149",
        "tgn:7007712",
        "tgn:7029392"
    ],
    "tgn:id":2332524,
    "tgn:name":"Florence, Lake",
    "tgn:placetype":[
        "aat:300008680",
        "aat:300006191"
    ]
},
  "bbox": [],
  "geometry": {"coordinates":[-81.8,33.3833],"type":"Point"}
}
=======
{"geometry":{"type":"Point","coordinates":[-81.800000,33.383300]},"type":"Feature","properties":{"hierarchy":["tgn:2332524","tgn:2001726","tgn:1000001","tgn:7012149","tgn:7007712","tgn:7029392"],"placetype":["aat:300008680","aat:300006191"],"id":2332524,"name:xx":"Florence, Lake"}}
>>>>>>> 03f74aca74312dbeaf24d7e61306dd6a786dc3d0
