{
  "id": 1043771,
  "type": "Feature",
  "properties": {
    "tgn:hierarchy":[
        "tgn:1043771",
        "tgn:7003134",
        "tgn:1000003",
        "tgn:7008516",
        "tgn:1000080",
        "tgn:7029392"
    ],
    "tgn:id":1043771,
    "tgn:name":"Campegine",
    "tgn:placetype":[
        "aat:300008347"
    ]
},
  "bbox": [],
  "geometry": {"coordinates":[10.533333,44.783333],"type":"Point"}
}