{
  "id": 2051198,
  "type": "Feature",
  "properties": {
    "tgn:hierarchy":[
        "tgn:2051198",
        "tgn:1002166",
        "tgn:1000001",
        "tgn:7012149",
        "tgn:7007520",
        "tgn:7029392"
    ],
    "tgn:id":2051198,
    "tgn:name":"Banfield",
    "tgn:placetype":[
        "aat:300008347"
    ]
},
  "bbox": [],
  "geometry": {"coordinates":[-85.2833,42.45],"type":"Point"}
}