<<<<<<< HEAD
{
  "id": 7244367,
  "type": "Feature",
  "properties": {
    "tgn:hierarchy":[
        "tgn:7244367",
        "tgn:7003461",
        "tgn:1000003",
        "tgn:1000063",
        "tgn:7018236",
        "tgn:7029392"
    ],
    "tgn:id":7244367,
    "tgn:name":"Kerkom-bij-Sint-Truiden",
    "tgn:placetype":[
        "aat:300008347"
    ]
},
  "bbox": [],
  "geometry": {"coordinates":[5.184513,50.77352],"type":"Point"}
}
=======
{"geometry":{"type":"Point","coordinates":[5.184513,50.773520]},"type":"Feature","properties":{"hierarchy":["tgn:7244367","tgn:7003461","tgn:1000003","tgn:1000063","tgn:7018236","tgn:7029392"],"placetype":["aat:300008347"],"id":7244367,"name:xx":"Kerkom-bij-Sint-Truiden"}}
>>>>>>> 03f74aca74312dbeaf24d7e61306dd6a786dc3d0
