{
  "id": 2479298,
  "type": "Feature",
  "properties": {
    "tgn:hierarchy":[
        "tgn:2479298",
        "tgn:1000001",
        "tgn:7012149",
        "tgn:2001291",
        "tgn:7007524",
        "tgn:7029392"
    ],
    "tgn:id":2479298,
    "tgn:name":"Lagoon Lake",
    "tgn:placetype":[
        "aat:300008680"
    ]
},
  "bbox": [],
  "geometry": {"coordinates":[-113.8333,47.35],"type":"Point"}
}