{
  "id": 7186497,
  "type": "Feature",
  "properties": {
    "tgn:hierarchy":[
        "tgn:7186497",
        "tgn:1000003",
        "tgn:7003678",
        "tgn:7000084",
        "tgn:7029392"
    ],
    "tgn:id":7186497,
    "tgn:name":"F\u00f6rsterei Goldgrube",
    "tgn:placetype":[
        "aat:300004792"
    ]
},
  "bbox": [],
  "geometry": {"coordinates":[8.566667,50.233333],"type":"Point"}
}