{
  "id": 2526793,
  "type": "Feature",
  "properties": {
    "tgn:hierarchy":[
        "tgn:2526793",
        "tgn:1000001",
        "tgn:7012149",
        "tgn:2001924",
        "tgn:7007825",
        "tgn:7029392"
    ],
    "tgn:id":2526793,
    "tgn:name":"Moulder Mountain",
    "tgn:placetype":[
        "aat:300008798"
    ]
},
  "bbox": [],
  "geometry": {"coordinates":[-85.55,35.7167],"type":"Point"}
}