{
  "id": 2341345,
  "type": "Feature",
  "properties": {
    "tgn:hierarchy":[
        "tgn:2341345",
        "tgn:1000001",
        "tgn:7012149",
        "tgn:1002545",
        "tgn:7007157",
        "tgn:7029392"
    ],
    "tgn:id":2341345,
    "tgn:name":"Frog Creek",
    "tgn:placetype":[
        "aat:300008706"
    ]
},
  "bbox": [],
  "geometry": {"coordinates":[-118.1333,35.4833],"type":"Point"}
}