<<<<<<< HEAD
{
  "id": 7172735,
  "type": "Feature",
  "properties": {
    "tgn:hierarchy":[
        "tgn:7172735",
        "tgn:1000003",
        "tgn:7003685",
        "tgn:7000084",
        "tgn:7029392"
    ],
    "tgn:id":7172735,
    "tgn:name":"Heu-Teich",
    "tgn:placetype":[
        "aat:300008688"
    ]
},
  "bbox": [],
  "geometry": {"coordinates":[14.6,51.333333],"type":"Point"}
}
=======
{"geometry":{"type":"Point","coordinates":[14.600000,51.333333]},"type":"Feature","properties":{"hierarchy":["tgn:7172735","tgn:1000003","tgn:7003685","tgn:7000084","tgn:7029392"],"placetype":["aat:300008688"],"id":7172735,"name:xx":"Heu-Teich"}}
>>>>>>> 03f74aca74312dbeaf24d7e61306dd6a786dc3d0
