{
  "id": 7389590,
  "type": "Feature",
  "properties": {
    "tgn:hierarchy":[
        "tgn:7389590",
        "tgn:1001853",
        "tgn:1000001",
        "tgn:7005560",
        "tgn:7029392"
    ],
    "tgn:id":7389590,
    "tgn:name":"Reith",
    "tgn:placetype":[
        "aat:300008347"
    ]
},
  "bbox": [],
  "geometry": {"coordinates":[-101.233333,29.483333],"type":"Point"}
}