{
  "id": 7566393,
  "type": "Feature",
  "properties": {
    "tgn:hierarchy":[
        "tgn:7566393",
        "tgn:1000004",
        "tgn:7000198",
        "tgn:7016722",
        "tgn:7029392"
    ],
    "tgn:id":7566393,
    "tgn:name:en":"Barampura",
    "tgn:placetype":[
        "aat:300008347"
    ]
},
  "bbox": [],
  "geometry": {"coordinates":[79.115873,25.65739],"type":"Point"}
}