{
  "id": 7588247,
  "type": "Feature",
  "properties": {
    "tgn:hierarchy":[
        "tgn:7588247",
        "tgn:1000004",
        "tgn:7000198",
        "tgn:7000799",
        "tgn:7029392"
    ],
    "tgn:id":7588247,
    "tgn:name:en":"N\u0101dgul",
    "tgn:placetype":[
        "aat:300008699"
    ]
},
  "bbox": [],
  "geometry": {"coordinates":[74.923611,34.244444],"type":"Point"}
}