{
  "id": 7023324,
  "type": "Feature",
  "properties": {
    "tgn:hierarchy":[
        "tgn:7023324",
        "tgn:1000001",
        "tgn:7012149",
        "tgn:7007710",
        "tgn:7029392"
    ],
    "tgn:id":7023324,
    "tgn:name":"Smoke Draft",
    "tgn:placetype":[
        "aat:300008761"
    ]
},
  "bbox": [],
  "geometry": {"coordinates":[-78.0333,41.2667],"type":"Point"}
}