{
  "id": 2238761,
  "type": "Feature",
  "properties": {
    "tgn:hierarchy":[
        "tgn:2238761",
        "tgn:1000001",
        "tgn:7012149",
        "tgn:1002986",
        "tgn:7007568",
        "tgn:7029392"
    ],
    "tgn:id":2238761,
    "tgn:name":"Christian Hill",
    "tgn:placetype":[
        "aat:300008347"
    ]
},
  "bbox": [],
  "geometry": {"coordinates":[-74.0667,43.7333],"type":"Point"}
}