<<<<<<< HEAD
{
  "id": 2154551,
  "type": "Feature",
  "properties": {
    "tgn:hierarchy":[
        "tgn:2154551",
        "tgn:1000001",
        "tgn:7006451",
        "tgn:2000095",
        "tgn:7012149",
        "tgn:7029392"
    ],
    "tgn:id":2154551,
    "tgn:name":"Bear Cub Spring",
    "tgn:placetype":[
        "aat:300008697"
    ]
},
  "bbox": [],
  "geometry": {"coordinates":[-109.3833,33.4167],"type":"Point"}
}
=======
{"geometry":{"type":"Point","coordinates":[-109.383300,33.416700]},"type":"Feature","properties":{"hierarchy":["tgn:2154551","tgn:1000001","tgn:7006451","tgn:2000095","tgn:7012149","tgn:7029392"],"placetype":["aat:300008697"],"id":2154551,"name:xx":"Bear Cub Spring"}}
>>>>>>> 03f74aca74312dbeaf24d7e61306dd6a786dc3d0
