{
  "id": 1092083,
  "type": "Feature",
  "properties": {
    "tgn:hierarchy":[
        "tgn:1092083",
        "tgn:7001242",
        "tgn:7015049",
        "tgn:1000182",
        "tgn:7029392"
    ],
    "tgn:id":1092083,
    "tgn:name":"Jalingo",
    "tgn:placetype":[
        "aat:300008347",
        "aat:300387221",
        "aat:300008375"
    ]
},
  "bbox": [],
  "geometry": {"coordinates":[11.4167,8.9167],"type":"Point"}
}