{
  "id": 7225933,
  "type": "Feature",
  "properties": {
    "tgn:hierarchy":[
        "tgn:7225933",
        "tgn:7002709",
        "tgn:7002705",
        "tgn:1000003",
        "tgn:1000074",
        "tgn:7029392"
    ],
    "tgn:id":7225933,
    "tgn:name":"P\u00e9ramos, Vrachonis\u00edda",
    "tgn:placetype":[
        "aat:300008791"
    ]
},
  "bbox": [],
  "geometry": {"coordinates":[20.269722,39.383056],"type":"Point"}
}