{
  "id": 7498591,
  "type": "Feature",
  "properties": {
    "tgn:hierarchy":[
        "tgn:7498591",
        "tgn:1000004",
        "tgn:7491221",
        "tgn:1000141",
        "tgn:7029392"
    ],
    "tgn:id":7498591,
    "tgn:name":"Gaotai Qiao",
    "tgn:placetype":[
        "aat:300007836"
    ]
},
  "bbox": [],
  "geometry": {"coordinates":[121.0923,22.8203],"type":"Point"}
}