{
  "id": 2327769,
  "type": "Feature",
  "properties": {
    "tgn:hierarchy":[
        "tgn:2327769",
        "tgn:7006450",
        "tgn:1000001",
        "tgn:7012149",
        "tgn:2000089",
        "tgn:7029392"
    ],
    "tgn:id":2327769,
    "tgn:name":"Fish Creek Lake",
    "tgn:placetype":[
        "aat:300008680"
    ]
},
  "bbox": [],
  "geometry": {"coordinates":[-152.7167,63.6833],"type":"Point"}
}