<<<<<<< HEAD
{
  "id": 7367443,
  "type": "Feature",
  "properties": {
    "tgn:hierarchy":[
        "tgn:7367443",
        "tgn:1000001",
        "tgn:7005589",
        "tgn:7005560",
        "tgn:7029392"
    ],
    "tgn:id":7367443,
    "tgn:name":"Estanque Nuevo",
    "tgn:placetype":[
        "aat:300008347"
    ]
},
  "bbox": [],
  "geometry": {"coordinates":[-100.25,24.1],"type":"Point"}
}
=======
{"geometry":{"type":"Point","coordinates":[-100.250000,24.100000]},"type":"Feature","properties":{"hierarchy":["tgn:7367443","tgn:1000001","tgn:7005589","tgn:7005560","tgn:7029392"],"placetype":["aat:300008347"],"id":7367443,"name:xx":"Estanque Nuevo"}}
>>>>>>> 03f74aca74312dbeaf24d7e61306dd6a786dc3d0
