<<<<<<< HEAD
{
  "id": 7021264,
  "type": "Feature",
  "properties": {
    "tgn:hierarchy":[
        "tgn:7021264",
        "tgn:1000001",
        "tgn:7012149",
        "tgn:2002284",
        "tgn:7013961",
        "tgn:7029392"
    ],
    "tgn:id":7021264,
    "tgn:name":"Spring Branch",
    "tgn:placetype":[
        "aat:300008699"
    ]
},
  "bbox": [],
  "geometry": {"coordinates":[-81.1667,38.2667],"type":"Point"}
}
=======
{"geometry":{"type":"Point","coordinates":[-81.166700,38.266700]},"type":"Feature","properties":{"hierarchy":["tgn:7021264","tgn:1000001","tgn:7012149","tgn:2002284","tgn:7013961","tgn:7029392"],"placetype":["aat:300008699"],"id":7021264,"name:xx":"Spring Branch"}}
>>>>>>> 03f74aca74312dbeaf24d7e61306dd6a786dc3d0
