{
  "id": 7258724,
  "type": "Feature",
  "properties": {
    "tgn:hierarchy":[
        "tgn:7258724",
        "tgn:1000003",
        "tgn:7003624",
        "tgn:7016845",
        "tgn:7029392"
    ],
    "tgn:id":7258724,
    "tgn:name:nl":"Alm",
    "tgn:placetype":[
        "aat:300008699"
    ]
},
  "bbox": [],
  "geometry": {"coordinates":[4.933333,51.766667],"type":"Point"}
}