{
  "id": 2678139,
  "type": "Feature",
  "properties": {
    "tgn:hierarchy":[
        "tgn:2678139",
        "tgn:7002659",
        "tgn:1000001",
        "tgn:7012149",
        "tgn:7021514",
        "tgn:7029392"
    ],
    "tgn:id":2678139,
    "tgn:name":"South Fork Blackoak Creek",
    "tgn:placetype":[
        "aat:300008706"
    ]
},
  "bbox": [],
  "geometry": {"coordinates":[-85.9167,34.45],"type":"Point"}
}