{
  "id": 1054726,
  "type": "Feature",
  "properties": {
    "tgn:hierarchy":[
        "tgn:1054726",
        "tgn:1000004",
        "tgn:6004412",
        "tgn:7018214",
        "tgn:7002435",
        "tgn:7029392"
    ],
    "tgn:id":1054726,
    "tgn:name":"Yermilovka",
    "tgn:placetype":[
        "aat:300008347"
    ]
},
  "bbox": [],
  "geometry": {"coordinates":[72.9167,57.6667],"type":"Point"}
}