{
  "id": 7108656,
  "type": "Feature",
  "properties": {
    "tgn:hierarchy":[
        "tgn:7108656",
        "tgn:1000003",
        "tgn:7003678",
        "tgn:7000084",
        "tgn:7029392"
    ],
    "tgn:id":7108656,
    "tgn:name":"Reh Berg",
    "tgn:placetype":[
        "aat:300008777"
    ]
},
  "bbox": [],
  "geometry": {"coordinates":[8.783333,50.366667],"type":"Point"}
}