{
  "id": 2543500,
  "type": "Feature",
  "properties": {
    "tgn:hierarchy":[
        "tgn:2543500",
        "tgn:1000001",
        "tgn:7012149",
        "tgn:2124023",
        "tgn:7007248",
        "tgn:7029392"
    ],
    "tgn:id":2543500,
    "tgn:name":"Norris Lake",
    "tgn:placetype":[
        "aat:300006191"
    ]
},
  "bbox": [],
  "geometry": {"coordinates":[-84.0333,33.75],"type":"Point"}
}