{
  "id": 2145047,
  "type": "Feature",
  "properties": {
    "tgn:hierarchy":[
        "tgn:2145047",
        "tgn:7006450",
        "tgn:1000001",
        "tgn:7012149",
        "tgn:2000086",
        "tgn:7029392"
    ],
    "tgn:id":2145047,
    "tgn:name":"Bald Mountain",
    "tgn:placetype":[
        "aat:300008798"
    ]
},
  "bbox": [],
  "geometry": {"coordinates":[-142.25,60.95],"type":"Point"}
}