{
  "id": 7385406,
  "type": "Feature",
  "properties": {
    "tgn:hierarchy":[
        "tgn:7385406",
        "tgn:7005586",
        "tgn:1000001",
        "tgn:7005560",
        "tgn:7029392"
    ],
    "tgn:id":7385406,
    "tgn:name":"Ojo de Agua del Mezcal",
    "tgn:placetype":[
        "aat:300008347"
    ]
},
  "bbox": [],
  "geometry": {"coordinates":[-102.95,19.883333],"type":"Point"}
}