<<<<<<< HEAD
{
  "id": 2402879,
  "type": "Feature",
  "properties": {
    "tgn:hierarchy":[
        "tgn:2402879",
        "tgn:1000001",
        "tgn:2000922",
        "tgn:7012149",
        "tgn:7007515",
        "tgn:7029392"
    ],
    "tgn:id":2402879,
    "tgn:name":"Hothole Mountain",
    "tgn:placetype":[
        "aat:300008798"
    ]
},
  "bbox": [],
  "geometry": {"coordinates":[-68.65,44.6167],"type":"Point"}
}
=======
{"geometry":{"type":"Point","coordinates":[-68.650000,44.616700]},"type":"Feature","properties":{"hierarchy":["tgn:2402879","tgn:1000001","tgn:2000922","tgn:7012149","tgn:7007515","tgn:7029392"],"placetype":["aat:300008798"],"id":2402879,"name:xx":"Hothole Mountain"}}
>>>>>>> 03f74aca74312dbeaf24d7e61306dd6a786dc3d0
