{
  "id": 7514605,
  "type": "Feature",
  "properties": {
    "tgn:hierarchy":[
        "tgn:7514605",
        "tgn:1009227",
        "tgn:1000226",
        "tgn:7016729",
        "tgn:1000006",
        "tgn:7029392"
    ],
    "tgn:id":7514605,
    "tgn:name:en":"Deep Creek",
    "tgn:placetype":[
        "aat:300008347"
    ]
},
  "bbox": [],
  "geometry": {"coordinates":[173.633333,-41.35],"type":"Point"}
}