{
  "id": 2139806,
  "type": "Feature",
  "properties": {
    "tgn:hierarchy":[
        "tgn:2139806",
        "tgn:1000001",
        "tgn:7012149",
        "tgn:2001509",
        "tgn:7007709",
        "tgn:7029392"
    ],
    "tgn:id":2139806,
    "tgn:name":"Atkinson Mill Pond",
    "tgn:placetype":[
        "aat:300006191"
    ]
},
  "bbox": [],
  "geometry": {"coordinates":[-78.25,35.6667],"type":"Point"}
}