{
  "id": 7358416,
  "type": "Feature",
  "properties": {
    "tgn:hierarchy":[
        "tgn:7358416",
        "tgn:1000001",
        "tgn:1001960",
        "tgn:7005560",
        "tgn:7029392"
    ],
    "tgn:id":7358416,
    "tgn:name":"Colonia Progreso",
    "tgn:placetype":[
        "aat:300008347"
    ]
},
  "bbox": [],
  "geometry": {"coordinates":[-109.55,31.25],"type":"Point"}
}