{
  "id": 2096311,
  "type": "Feature",
  "properties": {
    "tgn:hierarchy":[
        "tgn:2096311",
        "tgn:2001726",
        "tgn:1000001",
        "tgn:7012149",
        "tgn:7007712",
        "tgn:7029392"
    ],
    "tgn:id":2096311,
    "tgn:name":"Nicholson Village",
    "tgn:placetype":[
        "aat:300008347"
    ]
},
  "bbox": [],
  "geometry": {"coordinates":[-81.65,33.55],"type":"Point"}
}