{
  "id": 7404732,
  "type": "Feature",
  "properties": {
    "tgn:hierarchy":[
        "tgn:7404732",
        "tgn:1000001",
        "tgn:7005592",
        "tgn:7005560",
        "tgn:7029392"
    ],
    "tgn:id":7404732,
    "tgn:name":"Tepetzitzintla",
    "tgn:placetype":[
        "aat:300008347"
    ]
},
  "bbox": [],
  "geometry": {"coordinates":[-97.116667,18.475],"type":"Point"}
}