{
  "id": 2778598,
  "type": "Feature",
  "properties": {
    "tgn:hierarchy":[
        "tgn:2778598",
        "tgn:1000001",
        "tgn:7012149",
        "tgn:2002129",
        "tgn:7007827",
        "tgn:7029392"
    ],
    "tgn:id":2778598,
    "tgn:name":"Wm Lunds Lynne Addition",
    "tgn:placetype":[
        "aat:300008347"
    ]
},
  "bbox": [],
  "geometry": {"coordinates":[-111.95,41.25],"type":"Point"}
}