{
  "id": 7200551,
  "type": "Feature",
  "properties": {
    "tgn:hierarchy":[
        "tgn:7200551",
        "tgn:1000003",
        "tgn:7003676",
        "tgn:7000084",
        "tgn:7029392"
    ],
    "tgn:id":7200551,
    "tgn:name":"Drachen-Berg",
    "tgn:placetype":[
        "aat:300008777"
    ]
},
  "bbox": [],
  "geometry": {"coordinates":[10.783333,52.233333],"type":"Point"}
}