{
  "id": 2319005,
  "type": "Feature",
  "properties": {
    "tgn:hierarchy":[
        "tgn:2319005",
        "tgn:7006450",
        "tgn:1000001",
        "tgn:7012149",
        "tgn:2000089",
        "tgn:7029392"
    ],
    "tgn:id":2319005,
    "tgn:name":"Esperanto Placer Mine",
    "tgn:placetype":[
        "aat:300000390"
    ]
},
  "bbox": [],
  "geometry": {"coordinates":[-156.75,63.4167],"type":"Point"}
}