{
  "id": 2104667,
  "type": "Feature",
  "properties": {
    "tgn:hierarchy":[
        "tgn:2104667",
        "tgn:1000001",
        "tgn:7012149",
        "tgn:2002081",
        "tgn:7007826",
        "tgn:7029392"
    ],
    "tgn:id":2104667,
    "tgn:name":"Hamby",
    "tgn:placetype":[
        "aat:300008347",
        "aat:300387210"
    ]
},
  "bbox": [],
  "geometry": {"coordinates":[-99.6167,32.5167],"type":"Point"}
}