{
  "id": 2147127,
  "type": "Feature",
  "properties": {
    "tgn:hierarchy":[
        "tgn:2147127",
        "tgn:1000001",
        "tgn:2001427",
        "tgn:7012149",
        "tgn:7007564",
        "tgn:7029392"
    ],
    "tgn:id":2147127,
    "tgn:name":"Baptist Pond",
    "tgn:placetype":[
        "aat:300008680"
    ]
},
  "bbox": [],
  "geometry": {"coordinates":[-72.0667,43.45],"type":"Point"}
}