{
  "id": 2008671,
  "type": "Feature",
  "properties": {
    "tgn:hierarchy":[
        "tgn:2008671",
        "tgn:1000001",
        "tgn:7016172",
        "tgn:7012149",
        "tgn:2000139",
        "tgn:7029392"
    ],
    "tgn:id":2008671,
    "tgn:name":"Lake Dick",
    "tgn:placetype":[
        "aat:300008347",
        "aat:300387210"
    ]
},
  "bbox": [],
  "geometry": {"coordinates":[-91.8333,34.25],"type":"Point"}
}