{
  "id": 7150586,
  "type": "Feature",
  "properties": {
    "tgn:hierarchy":[
        "tgn:7150586",
        "tgn:7000096",
        "tgn:1000003",
        "tgn:7000084",
        "tgn:7029392"
    ],
    "tgn:id":7150586,
    "tgn:name":"Kr\u00e4merpfuhl",
    "tgn:placetype":[
        "aat:300008347"
    ]
},
  "bbox": [],
  "geometry": {"coordinates":[13.033333,52.683333],"type":"Point"}
}