{
  "id": 1119479,
  "type": "Feature",
  "properties": {
    "tgn:hierarchy":[
        "tgn:1119479",
        "tgn:7002444",
        "tgn:1000003",
        "tgn:7008082",
        "tgn:7008591",
        "tgn:7029392"
    ],
    "tgn:id":1119479,
    "tgn:name:en":"Blackwater Reservoir",
    "tgn:placetype":[
        "aat:300006191"
    ]
},
  "bbox": [],
  "geometry": {"coordinates":[-4.766667,56.683333],"type":"Point"}
}