{
  "id": 2167101,
  "type": "Feature",
  "properties": {
    "tgn:hierarchy":[
        "tgn:2167101",
        "tgn:1000001",
        "tgn:7012149",
        "tgn:1002742",
        "tgn:7007920",
        "tgn:7029392"
    ],
    "tgn:id":2167101,
    "tgn:name":"Big Canyon Creek",
    "tgn:placetype":[
        "aat:300008706"
    ]
},
  "bbox": [],
  "geometry": {"coordinates":[-119.7667,48.65],"type":"Point"}
}