{
  "id": 7334770,
  "type": "Feature",
  "properties": {
    "tgn:hierarchy":[
        "tgn:7334770",
        "tgn:7002825",
        "tgn:7016622",
        "tgn:1000003",
        "tgn:1000095",
        "tgn:7029392"
    ],
    "tgn:id":7334770,
    "tgn:name":"El Poris de las Playas",
    "tgn:placetype":[
        "aat:300386846"
    ]
},
  "bbox": [],
  "geometry": {"coordinates":[-13.983333,28.216667],"type":"Point"}
}