{
  "id": 7143170,
  "type": "Feature",
  "properties": {
    "tgn:hierarchy":[
        "tgn:7143170",
        "tgn:1000003",
        "tgn:7003677",
        "tgn:7000084",
        "tgn:7029392"
    ],
    "tgn:id":7143170,
    "tgn:name":"Bahnhof L\u00fcchtringen",
    "tgn:placetype":[
        "aat:300007783"
    ]
},
  "bbox": [],
  "geometry": {"coordinates":[9.426389,51.790278],"type":"Point"}
}