<<<<<<< HEAD
{
  "id": 7117497,
  "type": "Feature",
  "properties": {
    "tgn:hierarchy":[
        "tgn:7117497",
        "tgn:1000003",
        "tgn:7003688",
        "tgn:7000084",
        "tgn:7029392"
    ],
    "tgn:id":7117497,
    "tgn:name":"Ostlicher Strom",
    "tgn:placetype":[
        "aat:300008699"
    ]
},
  "bbox": [],
  "geometry": {"coordinates":[8.95,53.966667],"type":"Point"}
}
=======
{"geometry":{"type":"Point","coordinates":[8.950000,53.966667]},"type":"Feature","properties":{"hierarchy":["tgn:7117497","tgn:1000003","tgn:7003688","tgn:7000084","tgn:7029392"],"placetype":["aat:300008699"],"id":7117497,"name:xx":"Ostlicher Strom"}}
>>>>>>> 03f74aca74312dbeaf24d7e61306dd6a786dc3d0
