{
  "id": 2175972,
  "type": "Feature",
  "properties": {
    "tgn:hierarchy":[
        "tgn:2175972",
        "tgn:1000001",
        "tgn:7012149",
        "tgn:2001303",
        "tgn:7007524",
        "tgn:7029392"
    ],
    "tgn:id":2175972,
    "tgn:name":"Black Eagle Creek",
    "tgn:placetype":[
        "aat:300008706"
    ]
},
  "bbox": [],
  "geometry": {"coordinates":[-106.4167,45.3333],"type":"Point"}
}