{
  "id": 2560861,
  "type": "Feature",
  "properties": {
    "tgn:hierarchy":[
        "tgn:2560861",
        "tgn:1000001",
        "tgn:7012149",
        "tgn:2000960",
        "tgn:7007520",
        "tgn:7029392"
    ],
    "tgn:id":2560861,
    "tgn:name":"Ormes Lake",
    "tgn:placetype":[
        "aat:300008680"
    ]
},
  "bbox": [],
  "geometry": {"coordinates":[-89.65,46.2667],"type":"Point"}
}