{
  "id": 2392497,
  "type": "Feature",
  "properties": {
    "tgn:hierarchy":[
        "tgn:2392497",
        "tgn:1000001",
        "tgn:7012149",
        "tgn:2000495",
        "tgn:7007250",
        "tgn:7029392"
    ],
    "tgn:id":2392497,
    "tgn:name":"Hitt Peak",
    "tgn:placetype":[
        "aat:300008798"
    ]
},
  "bbox": [],
  "geometry": {"coordinates":[-116.9167,44.5833],"type":"Point"}
}