{
  "id": 2690600,
  "type": "Feature",
  "properties": {
    "tgn:hierarchy":[
        "tgn:2690600",
        "tgn:1000001",
        "tgn:2001805",
        "tgn:7012149",
        "tgn:7007713",
        "tgn:7029392"
    ],
    "tgn:id":2690600,
    "tgn:name":"Stamford",
    "tgn:placetype":[
        "aat:300008347"
    ]
},
  "bbox": [],
  "geometry": {"coordinates":[-101.0833,43.8833],"type":"Point"}
}