{
  "id": 2226439,
  "type": "Feature",
  "properties": {
    "tgn:hierarchy":[
        "tgn:2226439",
        "tgn:1000001",
        "tgn:7012149",
        "tgn:2002128",
        "tgn:7007827",
        "tgn:7029392"
    ],
    "tgn:id":2226439,
    "tgn:name":"Cathedral Valley",
    "tgn:placetype":[
        "aat:300055621"
    ]
},
  "bbox": [],
  "geometry": {"coordinates":[-111.35,38.4833],"type":"Point"}
}