{
  "id": 7520379,
  "type": "Feature",
  "properties": {
    "tgn:hierarchy":[
        "tgn:7520379",
        "tgn:7001242",
        "tgn:7016833",
        "tgn:7029392"
    ],
    "tgn:id":7520379,
    "tgn:name:en":"Guegab, Oases of",
    "tgn:placetype":[
        "aat:300008686"
    ]
},
  "bbox": [],
  "geometry": {"coordinates":[24.716667,29.683333],"type":"Point"}
}