{
  "id": 7318736,
  "type": "Feature",
  "properties": {
    "tgn:hierarchy":[
        "tgn:7318736",
        "tgn:1001630",
        "tgn:1000049",
        "tgn:1000002",
        "tgn:7029392"
    ],
    "tgn:id":7318736,
    "tgn:name":"Cachitos",
    "tgn:placetype":[
        "aat:300008347"
    ]
},
  "bbox": [],
  "geometry": {"coordinates":[-69.45,-27.883333],"type":"Point"}
}