{
  "id": 2174624,
  "type": "Feature",
  "properties": {
    "tgn:hierarchy":[
        "tgn:2174624",
        "tgn:1000001",
        "tgn:7012149",
        "tgn:2002379",
        "tgn:7007923",
        "tgn:7029392"
    ],
    "tgn:id":2174624,
    "tgn:name":"Bison Peak",
    "tgn:placetype":[
        "aat:300008798"
    ]
},
  "bbox": [],
  "geometry": {"coordinates":[-110.2167,44.9333],"type":"Point"}
}