{
  "id": 2219652,
  "type": "Feature",
  "properties": {
    "tgn:hierarchy":[
        "tgn:2219652",
        "tgn:1000001",
        "tgn:7012149",
        "tgn:2001449",
        "tgn:7007566",
        "tgn:7029392"
    ],
    "tgn:id":2219652,
    "tgn:name":"Canon Largo Tank",
    "tgn:placetype":[
        "aat:300006191"
    ]
},
  "bbox": [],
  "geometry": {"coordinates":[-106.25,36.4333],"type":"Point"}
}