{
  "id": 7560256,
  "type": "Feature",
  "properties": {
    "tgn:hierarchy":[
        "tgn:7560256",
        "tgn:1000004",
        "tgn:7000198",
        "tgn:7016722",
        "tgn:7029392"
    ],
    "tgn:id":7560256,
    "tgn:name:en":"Koila Gy\u0101npur",
    "tgn:placetype":[
        "aat:300008347"
    ]
},
  "bbox": [],
  "geometry": {"coordinates":[79.677514,27.601245],"type":"Point"}
}