<<<<<<< HEAD
{
  "id": 7056859,
  "type": "Feature",
  "properties": {
    "tgn:hierarchy":[
        "tgn:7056859",
        "tgn:7015163",
        "tgn:1000003",
        "tgn:7003121",
        "tgn:1000080",
        "tgn:7029392"
    ],
    "tgn:id":7056859,
    "tgn:name":"Abes, Montigiu",
    "tgn:placetype":[
        "aat:300008777"
    ]
},
  "bbox": [],
  "geometry": {"coordinates":[8.95,40.65],"type":"Point"}
}
=======
{"geometry":{"type":"Point","coordinates":[8.950000,40.650000]},"type":"Feature","properties":{"hierarchy":["tgn:7056859","tgn:7015163","tgn:1000003","tgn:7003121","tgn:1000080","tgn:7029392"],"placetype":["aat:300008777"],"id":7056859,"name:xx":"Abes, Montigiu"}}
>>>>>>> 03f74aca74312dbeaf24d7e61306dd6a786dc3d0
