{
  "id": 2025569,
  "type": "Feature",
  "properties": {
    "tgn:hierarchy":[
        "tgn:2025569",
        "tgn:1000001",
        "tgn:7012149",
        "tgn:2000473",
        "tgn:7007250",
        "tgn:7029392"
    ],
    "tgn:id":2025569,
    "tgn:name":"Drummond",
    "tgn:placetype":[
        "aat:300008347"
    ]
},
  "bbox": [],
  "geometry": {"coordinates":[-111.3333,43.9833],"type":"Point"}
}