{
  "id": 7534767,
  "type": "Feature",
  "properties": {
    "tgn:hierarchy":[
        "tgn:7534767",
        "tgn:7001242",
        "tgn:7016833",
        "tgn:1001092",
        "tgn:7029392"
    ],
    "tgn:id":7534767,
    "tgn:name":"Kafr 'Abd as Sayyid Naww\u0101r",
    "tgn:placetype":[
        "aat:300008347"
    ]
},
  "bbox": [],
  "geometry": {"coordinates":[31.299044,30.576238],"type":"Point"}
}