{
  "id": 7449984,
  "type": "Feature",
  "properties": {
    "tgn:hierarchy":[
        "tgn:7449984",
        "tgn:7002445",
        "tgn:1000003",
        "tgn:7012077",
        "tgn:7008591",
        "tgn:7029392"
    ],
    "tgn:id":7449984,
    "tgn:name:en":"East Rutts",
    "tgn:placetype":[
        "aat:300008808"
    ]
},
  "bbox": [],
  "geometry": {"coordinates":[-3.983333,50.233333],"type":"Point"}
}