{
  "id": 7558880,
  "type": "Feature",
  "properties": {
    "tgn:hierarchy":[
        "tgn:7558880",
        "tgn:1000004",
        "tgn:7000198",
        "tgn:7016788",
        "tgn:7029392"
    ],
    "tgn:id":7558880,
    "tgn:name:en":"Sard\u0101rgarh",
    "tgn:placetype":[
        "aat:300008347"
    ]
},
  "bbox": [],
  "geometry": {"coordinates":[73.744661,29.375432],"type":"Point"}
}