{
  "id": 7336312,
  "type": "Feature",
  "properties": {
    "tgn:hierarchy":[
        "tgn:7336312",
        "tgn:7002820",
        "tgn:7030216",
        "tgn:1000003",
        "tgn:1000095",
        "tgn:7029392"
    ],
    "tgn:id":7336312,
    "tgn:name":"Fornells de la Selva",
    "tgn:placetype":[
        "aat:300008347"
    ]
},
  "bbox": [],
  "geometry": {"coordinates":[2.811885,41.929978],"type":"Point"}
}