{
  "id": 2370332,
  "type": "Feature",
  "properties": {
    "tgn:hierarchy":[
        "tgn:2370332",
        "tgn:1000001",
        "tgn:7012149",
        "tgn:1002352",
        "tgn:7007710",
        "tgn:7029392"
    ],
    "tgn:id":2370332,
    "tgn:name":"H C Hollow",
    "tgn:placetype":[
        "aat:300008761"
    ]
},
  "bbox": [],
  "geometry": {"coordinates":[-78.45,41.5167],"type":"Point"}
}