{
  "id": 1012082,
  "type": "Feature",
  "properties": {
    "tgn:hierarchy":[
        "tgn:1012082",
        "tgn:1000001",
        "tgn:1001960",
        "tgn:7005560",
        "tgn:1009445",
        "tgn:7029392"
    ],
    "tgn:id":1012082,
    "tgn:name":"Las \u00c1nimas, Punta",
    "tgn:placetype":[
        "aat:300386846"
    ]
},
  "bbox": [],
  "geometry": {"coordinates":[-113.25,28.833333],"type":"Point"}
}