{
  "id": 7560608,
  "type": "Feature",
  "properties": {
    "tgn:hierarchy":[
        "tgn:7560608",
        "tgn:1000004",
        "tgn:7000198",
        "tgn:7016722",
        "tgn:7029392"
    ],
    "tgn:id":7560608,
    "tgn:name:en":"Arrua",
    "tgn:placetype":[
        "aat:300008347"
    ]
},
  "bbox": [],
  "geometry": {"coordinates":[79.434238,27.201144],"type":"Point"}
}