{
  "id": 7226045,
  "type": "Feature",
  "properties": {
    "tgn:hierarchy":[
        "tgn:7226045",
        "tgn:7002681",
        "tgn:7001395",
        "tgn:1000003",
        "tgn:1000074",
        "tgn:7029392"
    ],
    "tgn:id":7226045,
    "tgn:name":"Mour\u00edkion",
    "tgn:placetype":[
        "aat:300008347"
    ]
},
  "bbox": [],
  "geometry": {"coordinates":[23.35,38.416667],"type":"Point"}
}