<<<<<<< HEAD
{
  "id": 2330426,
  "type": "Feature",
  "properties": {
    "tgn:hierarchy":[
        "tgn:2330426",
        "tgn:1000001",
        "tgn:7012149",
        "tgn:2000473",
        "tgn:7007250",
        "tgn:7029392"
    ],
    "tgn:id":2330426,
    "tgn:name":"Flat Canyon",
    "tgn:placetype":[
        "aat:300008761"
    ]
},
  "bbox": [],
  "geometry": {"coordinates":[-111.1833,44.2667],"type":"Point"}
}
=======
{"geometry":{"type":"Point","coordinates":[-111.183300,44.266700]},"type":"Feature","properties":{"hierarchy":["tgn:2330426","tgn:1000001","tgn:7012149","tgn:2000473","tgn:7007250","tgn:7029392"],"placetype":["aat:300008761"],"id":2330426,"name:xx":"Flat Canyon"}}
>>>>>>> 03f74aca74312dbeaf24d7e61306dd6a786dc3d0
