{
  "id": 2734764,
  "type": "Feature",
  "properties": {
    "tgn:hierarchy":[
        "tgn:2734764",
        "tgn:1000001",
        "tgn:7012149",
        "tgn:2001056",
        "tgn:7007521",
        "tgn:7029392"
    ],
    "tgn:id":2734764,
    "tgn:name":"Tuxedo Bar",
    "tgn:placetype":[
        "aat:300132348"
    ]
},
  "bbox": [],
  "geometry": {"coordinates":[-93.0333,45.8333],"type":"Point"}
}