{
  "id": 1112637,
  "type": "Feature",
  "properties": {
    "tgn:hierarchy":[
        "tgn:1112637",
        "tgn:7005685",
        "tgn:1000001",
        "tgn:7013154",
        "tgn:7029392"
    ],
    "tgn:id":1112637,
    "tgn:name":"Baltic Bay",
    "tgn:placetype":[
        "aat:300132316"
    ]
},
  "bbox": [],
  "geometry": {"coordinates":[-83.7167,48.3667],"type":"Point"}
}