{
  "id": 1137383,
  "type": "Feature",
  "properties": {
    "tgn:hierarchy":[
        "tgn:1137383",
        "tgn:1000003",
        "tgn:1003410",
        "tgn:7006660",
        "tgn:7029392"
    ],
    "tgn:id":1137383,
    "tgn:name":"Druzhba",
    "tgn:placetype":[
        "aat:300008347"
    ]
},
  "bbox": [],
  "geometry": {"coordinates":[33.95,52.05],"type":"Point"}
}