{
  "id": 2732759,
  "type": "Feature",
  "properties": {
    "tgn:hierarchy":[
        "tgn:2732759",
        "tgn:1000001",
        "tgn:2001839",
        "tgn:7012149",
        "tgn:7007825",
        "tgn:7029392"
    ],
    "tgn:id":2732759,
    "tgn:name":"Turkey Creek",
    "tgn:placetype":[
        "aat:300008706"
    ]
},
  "bbox": [],
  "geometry": {"coordinates":[-88.1333,35.95],"type":"Point"}
}