{
  "id": 7333670,
  "type": "Feature",
  "properties": {
    "tgn:hierarchy":[
        "tgn:7333670",
        "tgn:7002760",
        "tgn:1000003",
        "tgn:1000095",
        "tgn:7029392"
    ],
    "tgn:id":7333670,
    "tgn:name":"Escudo, Sierra del",
    "tgn:placetype":[
        "aat:300266640"
    ]
},
  "bbox": [],
  "geometry": {"coordinates":[-4.333333,43.283333],"type":"Point"}
}