{
  "id": 1027108,
  "type": "Feature",
  "properties": {
    "tgn:hierarchy":[
        "tgn:1027108",
        "tgn:7593919",
        "tgn:1000003",
        "tgn:1001780",
        "tgn:7029392"
    ],
    "tgn:id":1027108,
    "tgn:name":"Brod",
    "tgn:placetype":[
        "aat:300008347"
    ]
},
  "bbox": [],
  "geometry": {"coordinates":[12.75,49.8333],"type":"Point"}
}