{
  "id": 2098346,
  "type": "Feature",
  "properties": {
    "tgn:hierarchy":[
        "tgn:2098346",
        "tgn:1000001",
        "tgn:7012149",
        "tgn:2001929",
        "tgn:7007825",
        "tgn:7029392"
    ],
    "tgn:id":2098346,
    "tgn:name":"Yateston",
    "tgn:placetype":[
        "aat:300008347",
        "aat:300387210"
    ]
},
  "bbox": [],
  "geometry": {"coordinates":[-85.5833,35.8833],"type":"Point"}
}