<<<<<<< HEAD
{
  "id": 7178652,
  "type": "Feature",
  "properties": {
    "tgn:hierarchy":[
        "tgn:7178652",
        "tgn:1000003",
        "tgn:7003677",
        "tgn:7000084",
        "tgn:7029392"
    ],
    "tgn:id":7178652,
    "tgn:name":"Hammoor",
    "tgn:placetype":[
        "aat:300387200"
    ]
},
  "bbox": [],
  "geometry": {"coordinates":[8.366667,51.766667],"type":"Point"}
}
=======
{"geometry":{"type":"Point","coordinates":[8.366667,51.766667]},"type":"Feature","properties":{"hierarchy":["tgn:7178652","tgn:1000003","tgn:7003677","tgn:7000084","tgn:7029392"],"placetype":["aat:300387200"],"id":7178652,"name:xx":"Hammoor"}}
>>>>>>> 03f74aca74312dbeaf24d7e61306dd6a786dc3d0
