{
  "id": 1024882,
  "type": "Feature",
  "properties": {
    "tgn:hierarchy":[
        "tgn:1024882",
        "tgn:7002640",
        "tgn:1000002",
        "tgn:1000058",
        "tgn:7029392"
    ],
    "tgn:id":1024882,
    "tgn:name":"Constituci\u00f3n",
    "tgn:placetype":[
        "aat:300008347"
    ]
},
  "bbox": [],
  "geometry": {"coordinates":[-57.85,-31.0833],"type":"Point"}
}