<<<<<<< HEAD
{
  "id": 2765051,
  "type": "Feature",
  "properties": {
    "tgn:hierarchy":[
        "tgn:2765051",
        "tgn:1000001",
        "tgn:7012149",
        "tgn:2001043",
        "tgn:7007521",
        "tgn:7029392"
    ],
    "tgn:id":2765051,
    "tgn:name":"Whisky Lake",
    "tgn:placetype":[
        "aat:300008680"
    ]
},
  "bbox": [],
  "geometry": {"coordinates":[-95.95,48.3667],"type":"Point"}
}
=======
{"geometry":{"type":"Point","coordinates":[-95.950000,48.366700]},"type":"Feature","properties":{"hierarchy":["tgn:2765051","tgn:1000001","tgn:7012149","tgn:2001043","tgn:7007521","tgn:7029392"],"placetype":["aat:300008680"],"id":2765051,"name:xx":"Whisky Lake"}}
>>>>>>> 03f74aca74312dbeaf24d7e61306dd6a786dc3d0
