{
  "id": 7524206,
  "type": "Feature",
  "properties": {
    "tgn:hierarchy":[
        "tgn:7524206",
        "tgn:7001242",
        "tgn:7016833",
        "tgn:1001123",
        "tgn:7029392"
    ],
    "tgn:id":7524206,
    "tgn:name":"Birak Gazar, Gaz\u00e2yir",
    "tgn:placetype":[
        "aat:300008791"
    ]
},
  "bbox": [],
  "geometry": {"coordinates":[32.016667,31.133333],"type":"Point"}
}