{
  "id": 7243392,
  "type": "Feature",
  "properties": {
    "tgn:hierarchy":[
        "tgn:7243392",
        "tgn:7003460",
        "tgn:1000003",
        "tgn:1000063",
        "tgn:4012014",
        "tgn:7029392"
    ],
    "tgn:id":7243392,
    "tgn:name":"Latour",
    "tgn:placetype":[
        "aat:300008347"
    ]
},
  "bbox": [],
  "geometry": {"coordinates":[5.883333,50.366667],"type":"Point"}
}