{
  "id": 2399693,
  "type": "Feature",
  "properties": {
    "tgn:hierarchy":[
        "tgn:2399693",
        "tgn:1000001",
        "tgn:7012149",
        "tgn:2000210",
        "tgn:7007158",
        "tgn:7029392"
    ],
    "tgn:id":2399693,
    "tgn:name":"Hornsilver Mountain",
    "tgn:placetype":[
        "aat:300008798"
    ]
},
  "bbox": [],
  "geometry": {"coordinates":[-106.3167,39.4833],"type":"Point"}
}