<<<<<<< HEAD
{
  "id": 2769071,
  "type": "Feature",
  "properties": {
    "tgn:hierarchy":[
        "tgn:2769071",
        "tgn:1000001",
        "tgn:1002601",
        "tgn:7012149",
        "tgn:7007159",
        "tgn:7029392"
    ],
    "tgn:id":2769071,
    "tgn:name":"Whitten Swamp",
    "tgn:placetype":[
        "aat:300008905"
    ]
},
  "bbox": [],
  "geometry": {"coordinates":[-73.4833,41.7833],"type":"Point"}
}
=======
{"geometry":{"type":"Point","coordinates":[-73.483300,41.783300]},"type":"Feature","properties":{"hierarchy":["tgn:2769071","tgn:1000001","tgn:1002601","tgn:7012149","tgn:7007159","tgn:7029392"],"placetype":["aat:300008905"],"id":2769071,"name:xx":"Whitten Swamp"}}
>>>>>>> 03f74aca74312dbeaf24d7e61306dd6a786dc3d0
