{
  "id": 7508428,
  "type": "Feature",
  "properties": {
    "tgn:hierarchy":[
        "tgn:7508428",
        "tgn:1008380",
        "tgn:7000507",
        "tgn:1000226",
        "tgn:1000006",
        "tgn:7029392"
    ],
    "tgn:id":7508428,
    "tgn:name:en":"Paihikokuri Stream",
    "tgn:placetype":[
        "aat:300008699"
    ]
},
  "bbox": [],
  "geometry": {"coordinates":[173.433333,-35.266667],"type":"Point"}
}