{
  "id": 2458392,
  "type": "Feature",
  "properties": {
    "tgn:hierarchy":[
        "tgn:2458392",
        "tgn:1000001",
        "tgn:2001009",
        "tgn:7012149",
        "tgn:7007521",
        "tgn:7029392"
    ],
    "tgn:id":2458392,
    "tgn:name":"Little Mule Lake",
    "tgn:placetype":[
        "aat:300008680"
    ]
},
  "bbox": [],
  "geometry": {"coordinates":[-94.2667,46.8833],"type":"Point"}
}