{
  "id": 2441512,
  "type": "Feature",
  "properties": {
    "tgn:hierarchy":[
        "tgn:2441512",
        "tgn:1000001",
        "tgn:7012149",
        "tgn:2000205",
        "tgn:7007158",
        "tgn:7029392"
    ],
    "tgn:id":2441512,
    "tgn:name":"Koch Springs",
    "tgn:placetype":[
        "aat:300008697"
    ]
},
  "bbox": [],
  "geometry": {"coordinates":[-105.5833,38.2333],"type":"Point"}
}