{
  "id": 2468045,
  "type": "Feature",
  "properties": {
    "tgn:hierarchy":[
        "tgn:2468045",
        "tgn:1000001",
        "tgn:7012149",
        "tgn:2001696",
        "tgn:7007707",
        "tgn:7029392"
    ],
    "tgn:id":2468045,
    "tgn:name":"Long Lake",
    "tgn:placetype":[
        "aat:300008680"
    ]
},
  "bbox": [],
  "geometry": {"coordinates":[-95.9667,36.85],"type":"Point"}
}