{
  "id": 1016567,
  "type": "Feature",
  "properties": {
    "tgn:hierarchy":[
        "tgn:1016567",
        "tgn:7593552",
        "tgn:1000001",
        "tgn:7024573",
        "tgn:7029392"
    ],
    "tgn:id":1016567,
    "tgn:name":"Etah",
    "tgn:placetype":[
        "aat:300008347",
        "aat:300167671"
    ]
},
  "bbox": [],
  "geometry": {"coordinates":[-72.6333,78.3167],"type":"Point"}
}