{
  "id": 1125571,
  "type": "Feature",
  "properties": {
    "tgn:hierarchy":[
        "tgn:1125571",
        "tgn:1000004",
        "tgn:7012941",
        "tgn:7018214",
        "tgn:7002435",
        "tgn:7029392"
    ],
    "tgn:id":1125571,
    "tgn:name":"Kimerka",
    "tgn:placetype":[
        "aat:300008707"
    ]
},
  "bbox": [],
  "geometry": {"coordinates":[37.3667,56.8667],"type":"Point"}
}