{
  "id": 2223668,
  "type": "Feature",
  "properties": {
    "tgn:hierarchy":[
        "tgn:2223668",
        "tgn:1000001",
        "tgn:2002105",
        "tgn:7012149",
        "tgn:7007827",
        "tgn:7029392"
    ],
    "tgn:id":2223668,
    "tgn:name":"Carter Dugway",
    "tgn:placetype":[
        "aat:300008761"
    ]
},
  "bbox": [],
  "geometry": {"coordinates":[-109.9333,40.9167],"type":"Point"}
}