{
  "id": 7394856,
  "type": "Feature",
  "properties": {
    "tgn:hierarchy":[
        "tgn:7394856",
        "tgn:1000001",
        "tgn:7005589",
        "tgn:7005560",
        "tgn:7029392"
    ],
    "tgn:id":7394856,
    "tgn:name":"Rancho San Jos\u00e9 de la Esperanza",
    "tgn:placetype":[
        "aat:300000241"
    ]
},
  "bbox": [],
  "geometry": {"coordinates":[-99.733333,26.583333],"type":"Point"}
}