{
  "id": 2126185,
  "type": "Feature",
  "properties": {
    "tgn:hierarchy":[
        "tgn:2126185",
        "tgn:1000001",
        "tgn:7012149",
        "tgn:2001029",
        "tgn:7007521",
        "tgn:7029392"
    ],
    "tgn:id":2126185,
    "tgn:name":"Adele Lake",
    "tgn:placetype":[
        "aat:300008680"
    ]
},
  "bbox": [],
  "geometry": {"coordinates":[-93.65,47.4667],"type":"Point"}
}