{
  "id": 2464747,
  "type": "Feature",
  "properties": {
    "tgn:hierarchy":[
        "tgn:2464747",
        "tgn:1000001",
        "tgn:7012149",
        "tgn:2000813",
        "tgn:7007255",
        "tgn:7029392"
    ],
    "tgn:id":2464747,
    "tgn:name":"Logan Creek",
    "tgn:placetype":[
        "aat:300008706"
    ]
},
  "bbox": [],
  "geometry": {"coordinates":[-84.6667,37.4833],"type":"Point"}
}