{
  "id": 2087215,
  "type": "Feature",
  "properties": {
    "tgn:hierarchy":[
        "tgn:2087215",
        "tgn:1000001",
        "tgn:7012149",
        "tgn:1002580",
        "tgn:7007710",
        "tgn:7029392"
    ],
    "tgn:id":2087215,
    "tgn:name":"Chewton",
    "tgn:placetype":[
        "aat:300008347"
    ]
},
  "bbox": [],
  "geometry": {"coordinates":[-80.3167,40.8833],"type":"Point"}
}