{
  "id": 2168226,
  "type": "Feature",
  "properties": {
    "tgn:hierarchy":[
        "tgn:2168226",
        "tgn:1000001",
        "tgn:7012149",
        "tgn:2000811",
        "tgn:7007255",
        "tgn:7029392"
    ],
    "tgn:id":2168226,
    "tgn:name":"Big Fork",
    "tgn:placetype":[
        "aat:300008699"
    ]
},
  "bbox": [],
  "geometry": {"coordinates":[-83.25,37.0333],"type":"Point"}
}