{
  "id": 7496727,
  "type": "Feature",
  "properties": {
    "tgn:hierarchy":[
        "tgn:7496727",
        "tgn:1000004",
        "tgn:1000454",
        "tgn:1000141",
        "tgn:7029392"
    ],
    "tgn:id":7496727,
    "tgn:name":"Zengjia",
    "tgn:placetype":[
        "aat:300008347"
    ]
},
  "bbox": [],
  "geometry": {"coordinates":[121.36109,24.905708],"type":"Point"}
}