{
  "id": 1116341,
  "type": "Feature",
  "properties": {
    "tgn:hierarchy":[
        "tgn:1116341",
        "tgn:7005694",
        "tgn:7005685",
        "tgn:1000001",
        "tgn:7029392"
    ],
    "tgn:id":1116341,
    "tgn:name":"Frog Lake",
    "tgn:placetype":[
        "aat:300008680"
    ]
},
  "bbox": [],
  "geometry": {"coordinates":[-110.3333,53.9167],"type":"Point"}
}