<<<<<<< HEAD
{
  "id": 2335190,
  "type": "Feature",
  "properties": {
    "tgn:hierarchy":[
        "tgn:2335190",
        "tgn:1000001",
        "tgn:7016172",
        "tgn:7012149",
        "tgn:2000170",
        "tgn:7029392"
    ],
    "tgn:id":2335190,
    "tgn:name":"Fort Chaffee",
    "tgn:placetype":[
        "aat:300008347"
    ]
},
  "bbox": [],
  "geometry": {"coordinates":[-94.3,35.3],"type":"Point"}
}
=======
{"geometry":{"type":"Point","coordinates":[-94.300000,35.300000]},"type":"Feature","properties":{"hierarchy":["tgn:2335190","tgn:1000001","tgn:7016172","tgn:7012149","tgn:2000170","tgn:7029392"],"placetype":["aat:300008347"],"id":2335190,"name:xx":"Fort Chaffee"}}
>>>>>>> 03f74aca74312dbeaf24d7e61306dd6a786dc3d0
