{
  "id": 2148151,
  "type": "Feature",
  "properties": {
    "tgn:hierarchy":[
        "tgn:2148151",
        "tgn:1000001",
        "tgn:7012149",
        "tgn:2000816",
        "tgn:7007255",
        "tgn:7029392"
    ],
    "tgn:id":2148151,
    "tgn:name":"Barkley Canal",
    "tgn:placetype":[
        "aat:300006075"
    ]
},
  "bbox": [],
  "geometry": {"coordinates":[-88.2167,36.9833],"type":"Point"}
}