<<<<<<< HEAD
{
  "id": 7057119,
  "type": "Feature",
  "properties": {
    "tgn:hierarchy":[
        "tgn:7057119",
        "tgn:7015163",
        "tgn:1000003",
        "tgn:7003121",
        "tgn:1000080",
        "tgn:7029392"
    ],
    "tgn:id":7057119,
    "tgn:name":"Baracche Napoletane, Cala",
    "tgn:placetype":[
        "aat:300132317"
    ]
},
  "bbox": [],
  "geometry": {"coordinates":[8.316667,41.05],"type":"Point"}
}
=======
{"geometry":{"type":"Point","coordinates":[8.316667,41.050000]},"type":"Feature","properties":{"hierarchy":["tgn:7057119","tgn:7015163","tgn:1000003","tgn:7003121","tgn:1000080","tgn:7029392"],"placetype":["aat:300132317"],"id":7057119,"name:xx":"Baracche Napoletane, Cala"}}
>>>>>>> 03f74aca74312dbeaf24d7e61306dd6a786dc3d0
