{
  "id": 7285092,
  "type": "Feature",
  "properties": {
    "tgn:hierarchy":[
        "tgn:7285092",
        "tgn:1001623",
        "tgn:1000049",
        "tgn:1000002",
        "tgn:7029392"
    ],
    "tgn:id":7285092,
    "tgn:name":"Puerto Guadal",
    "tgn:placetype":[
        "aat:300008347"
    ]
},
  "bbox": [],
  "geometry": {"coordinates":[-72.683333,-46.85],"type":"Point"}
}