{
  "id": 7560607,
  "type": "Feature",
  "properties": {
    "tgn:hierarchy":[
        "tgn:7560607",
        "tgn:1000004",
        "tgn:7000198",
        "tgn:7016722",
        "tgn:7029392"
    ],
    "tgn:id":7560607,
    "tgn:name:en":"Ranb\u012brpur",
    "tgn:placetype":[
        "aat:300008347"
    ]
},
  "bbox": [],
  "geometry": {"coordinates":[79.424366,27.199457],"type":"Point"}
}