{
  "id": 2438567,
  "type": "Feature",
  "properties": {
    "tgn:hierarchy":[
        "tgn:2438567",
        "tgn:1000001",
        "tgn:7012149",
        "tgn:7007157",
        "tgn:2000187",
        "tgn:7029392"
    ],
    "tgn:id":2438567,
    "tgn:name":"Kingsbury Ravine",
    "tgn:placetype":[
        "aat:300008761"
    ]
},
  "bbox": [],
  "geometry": {"coordinates":[-121.05,40.0333],"type":"Point"}
}