{
  "id": 7336869,
  "type": "Feature",
  "properties": {
    "tgn:hierarchy":[
        "tgn:7336869",
        "tgn:7002758",
        "tgn:7002817",
        "tgn:1000003",
        "tgn:1000095",
        "tgn:7029392"
    ],
    "tgn:id":7336869,
    "tgn:name":"Gata, Sierra de",
    "tgn:placetype":[
        "aat:300008777"
    ]
},
  "bbox": [],
  "geometry": {"coordinates":[-5.283333,38.233333],"type":"Point"}
}