{
  "id": 7005368,
  "type": "Feature",
  "properties": {
    "tgn:hierarchy":[
        "tgn:7005368",
        "tgn:1000003",
        "tgn:7003143",
        "tgn:7003236",
        "tgn:1000080",
        "tgn:7029392"
    ],
    "tgn:id":7005368,
    "tgn:name":"L\u00e9rici",
    "tgn:placetype":[
        "aat:300008347"
    ]
},
  "bbox": [],
  "geometry": {"coordinates":[9.916667,44.066667],"type":"Point"}
}