{
  "id": 7476707,
  "type": "Feature",
  "properties": {
    "tgn:hierarchy":[
        "tgn:7476707",
        "tgn:7487020",
        "tgn:1000004",
        "tgn:1000141",
        "tgn:7029392"
    ],
    "tgn:id":7476707,
    "tgn:name":"Duchuantou",
    "tgn:placetype":[
        "aat:300008347"
    ]
},
  "bbox": [],
  "geometry": {"coordinates":[120.832715,24.657353],"type":"Point"}
}