{
  "id": 2628041,
  "type": "Feature",
  "properties": {
    "tgn:hierarchy":[
        "tgn:2628041",
        "tgn:1000001",
        "tgn:7012149",
        "tgn:2001548",
        "tgn:7007709",
        "tgn:7029392"
    ],
    "tgn:id":2628041,
    "tgn:name":"Rolling Hills",
    "tgn:placetype":[
        "aat:300008347"
    ]
},
  "bbox": [],
  "geometry": {"coordinates":[-78.6333,35.65],"type":"Point"}
}