{
  "id": 1109169,
  "type": "Feature",
  "properties": {
    "tgn:hierarchy":[
        "tgn:1109169",
        "tgn:1000003",
        "tgn:7006670",
        "tgn:7029392"
    ],
    "tgn:id":1109169,
    "tgn:name:en":"Julian Alps",
    "tgn:placetype":[
        "aat:300386831"
    ]
},
  "bbox": [],
  "geometry": {"coordinates":[13.75,46.3333],"type":"Point"}
}