{
  "id": 2175458,
  "type": "Feature",
  "properties": {
    "tgn:hierarchy":[
        "tgn:2175458",
        "tgn:1000001",
        "tgn:7012149",
        "tgn:2001437",
        "tgn:7007566",
        "tgn:7029392"
    ],
    "tgn:id":2175458,
    "tgn:name":"Black Canyon",
    "tgn:placetype":[
        "aat:300008761"
    ]
},
  "bbox": [],
  "geometry": {"coordinates":[-107.8333,33.1833],"type":"Point"}
}