{
  "id": 7369345,
  "type": "Feature",
  "properties": {
    "tgn:hierarchy":[
        "tgn:7369345",
        "tgn:1000001",
        "tgn:7005595",
        "tgn:7005560",
        "tgn:7029392"
    ],
    "tgn:id":7369345,
    "tgn:name":"Ixtit\u00e1n",
    "tgn:placetype":[
        "aat:300008347"
    ]
},
  "bbox": [],
  "geometry": {"coordinates":[-106.333333,23.966667],"type":"Point"}
}