{
  "id": 7387094,
  "type": "Feature",
  "properties": {
    "tgn:hierarchy":[
        "tgn:7387094",
        "tgn:7016644",
        "tgn:1000001",
        "tgn:7005560",
        "tgn:7029392"
    ],
    "tgn:id":7387094,
    "tgn:name":"Periquillo",
    "tgn:placetype":[
        "aat:300007783"
    ]
},
  "bbox": [],
  "geometry": {"coordinates":[-103.95,18.933333],"type":"Point"}
}