{
  "id": 7494282,
  "type": "Feature",
  "properties": {
    "tgn:hierarchy":[
        "tgn:7494282",
        "tgn:1000004",
        "tgn:7001014",
        "tgn:1000141",
        "tgn:7029392"
    ],
    "tgn:id":7494282,
    "tgn:name":"Dapi Guozhong",
    "tgn:placetype":[
        "aat:300006495"
    ]
},
  "bbox": [],
  "geometry": {"coordinates":[120.429047,23.641418],"type":"Point"}
}