{
  "id": 7337721,
  "type": "Feature",
  "properties": {
    "tgn:hierarchy":[
        "tgn:7337721",
        "tgn:7002835",
        "tgn:7001158",
        "tgn:1000003",
        "tgn:1000095",
        "tgn:7029392"
    ],
    "tgn:id":7337721,
    "tgn:name":"Chagarcia Medianero",
    "tgn:placetype":[
        "aat:300008347"
    ]
},
  "bbox": [],
  "geometry": {"coordinates":[-5.366667,40.65],"type":"Point"}
}