{
  "id": 7044700,
  "type": "Feature",
  "properties": {
    "tgn:hierarchy":[
        "tgn:7044700",
        "tgn:7005880",
        "tgn:1000003",
        "tgn:7003237",
        "tgn:1000080",
        "tgn:7029392"
    ],
    "tgn:id":7044700,
    "tgn:name":"Corte Torriana",
    "tgn:placetype":[
        "aat:300008347"
    ]
},
  "bbox": [],
  "geometry": {"coordinates":[11.066667,45.066667],"type":"Point"}
}