{
  "id": 2470376,
  "type": "Feature",
  "properties": {
    "tgn:hierarchy":[
        "tgn:2470376",
        "tgn:2002365",
        "tgn:1000001",
        "tgn:7012149",
        "tgn:7007923",
        "tgn:7029392"
    ],
    "tgn:id":2470376,
    "tgn:name":"Lori Lake",
    "tgn:placetype":[
        "aat:300008680"
    ]
},
  "bbox": [],
  "geometry": {"coordinates":[-105.7667,41.3833],"type":"Point"}
}