{
  "id": 2031340,
  "type": "Feature",
  "properties": {
    "tgn:hierarchy":[
        "tgn:2031340",
        "tgn:1000001",
        "tgn:7012149",
        "tgn:2000555",
        "tgn:7007252",
        "tgn:7029392"
    ],
    "tgn:id":2031340,
    "tgn:name":"Centerville",
    "tgn:placetype":[
        "aat:300008347",
        "aat:300387210"
    ]
},
  "bbox": [],
  "geometry": {"coordinates":[-87.05,37.9833],"type":"Point"}
}