{
  "id": 2633567,
  "type": "Feature",
  "properties": {
    "tgn:hierarchy":[
        "tgn:2633567",
        "tgn:1000001",
        "tgn:7012149",
        "tgn:7029392"
    ],
    "tgn:id":2633567,
    "tgn:name":"Rupert Valley",
    "tgn:placetype":[
        "aat:300008761"
    ]
},
  "bbox": [],
  "geometry": {"coordinates":[-73.2333,43.2333],"type":"Point"}
}