{
  "id": 7178861,
  "type": "Feature",
  "properties": {
    "tgn:hierarchy":[
        "tgn:7178861",
        "tgn:1000003",
        "tgn:7003688",
        "tgn:7000084",
        "tgn:7029392"
    ],
    "tgn:id":7178861,
    "tgn:name":"G\u00fcderottfeld",
    "tgn:placetype":[
        "aat:300000206"
    ]
},
  "bbox": [],
  "geometry": {"coordinates":[9.816667,54.616667],"type":"Point"}
}