{
  "id": 7309495,
  "type": "Feature",
  "properties": {
    "tgn:hierarchy":[
        "tgn:7309495",
        "tgn:1001623",
        "tgn:1000049",
        "tgn:1000002",
        "tgn:7029392"
    ],
    "tgn:id":7309495,
    "tgn:name":"Nuevo Reino, Playa",
    "tgn:placetype":[
        "aat:300008816"
    ]
},
  "bbox": [],
  "geometry": {"coordinates":[-72.683333,-44.733333],"type":"Point"}
}