<<<<<<< HEAD
{
  "id": 2402430,
  "type": "Feature",
  "properties": {
    "tgn:hierarchy":[
        "tgn:2402430",
        "tgn:1000001",
        "tgn:7012149",
        "tgn:1002994",
        "tgn:7007708",
        "tgn:7029392"
    ],
    "tgn:id":2402430,
    "tgn:name":"Hortons Reservoir",
    "tgn:placetype":[
        "aat:300006191"
    ]
},
  "bbox": [],
  "geometry": {"coordinates":[-123.0167,45.4],"type":"Point"}
}
=======
{"geometry":{"type":"Point","coordinates":[-123.016700,45.400000]},"type":"Feature","properties":{"hierarchy":["tgn:2402430","tgn:1000001","tgn:7012149","tgn:1002994","tgn:7007708","tgn:7029392"],"placetype":["aat:300006191"],"id":2402430,"name:xx":"Hortons Reservoir"}}
>>>>>>> 03f74aca74312dbeaf24d7e61306dd6a786dc3d0
