{
  "id": 2737527,
  "type": "Feature",
  "properties": {
    "tgn:hierarchy":[
        "tgn:2737527",
        "tgn:1000001",
        "tgn:7012149",
        "tgn:1002486",
        "tgn:7007826",
        "tgn:7029392"
    ],
    "tgn:id":2737527,
    "tgn:name":"Tyer Branch",
    "tgn:placetype":[
        "aat:300008699"
    ]
},
  "bbox": [],
  "geometry": {"coordinates":[-95.4167,31.45],"type":"Point"}
}