{
  "id": 2549801,
  "type": "Feature",
  "properties": {
    "tgn:hierarchy":[
        "tgn:2549801",
        "tgn:1000001",
        "tgn:7012149",
        "tgn:7007158",
        "tgn:2000246",
        "tgn:7029392"
    ],
    "tgn:id":2549801,
    "tgn:name":"North Tracy Canyon",
    "tgn:placetype":[
        "aat:300008761"
    ]
},
  "bbox": [],
  "geometry": {"coordinates":[-106.2833,38.0333],"type":"Point"}
}