{
  "id": 2490554,
  "type": "Feature",
  "properties": {
    "tgn:hierarchy":[
        "tgn:2490554",
        "tgn:7006450",
        "tgn:1000001",
        "tgn:7012149",
        "tgn:2000089",
        "tgn:7029392"
    ],
    "tgn:id":2490554,
    "tgn:name":"Manley Hot Springs Dome",
    "tgn:placetype":[
        "aat:300008798"
    ]
},
  "bbox": [],
  "geometry": {"coordinates":[-150.7333,65.0167],"type":"Point"}
}