{
  "id": 2200239,
  "type": "Feature",
  "properties": {
    "tgn:hierarchy":[
        "tgn:2200239",
        "tgn:1000001",
        "tgn:2000772",
        "tgn:7012149",
        "tgn:7007255",
        "tgn:7029392"
    ],
    "tgn:id":2200239,
    "tgn:name":"Brushy Fork",
    "tgn:placetype":[
        "aat:300008699"
    ]
},
  "bbox": [],
  "geometry": {"coordinates":[-83.05,37.5667],"type":"Point"}
}