{
  "id": 7311798,
  "type": "Feature",
  "properties": {
    "tgn:hierarchy":[
        "tgn:7311798",
        "tgn:1001657",
        "tgn:1000049",
        "tgn:1000002",
        "tgn:7029392"
    ],
    "tgn:id":7311798,
    "tgn:name":"Las Mollacas",
    "tgn:placetype":[
        "aat:300008347"
    ]
},
  "bbox": [],
  "geometry": {"coordinates":[-70.916667,-30.35],"type":"Point"}
}