{
  "id": 2224881,
  "type": "Feature",
  "properties": {
    "tgn:hierarchy":[
        "tgn:2224881",
        "tgn:2001171",
        "tgn:1000001",
        "tgn:7012149",
        "tgn:7007523",
        "tgn:7029392"
    ],
    "tgn:id":2224881,
    "tgn:name":"Cass Lake",
    "tgn:placetype":[
        "aat:300006191"
    ]
},
  "bbox": [],
  "geometry": {"coordinates":[-94.2167,37.5667],"type":"Point"}
}