{
  "id": 2227967,
  "type": "Feature",
  "properties": {
    "tgn:hierarchy":[
        "tgn:2227967",
        "tgn:7002659",
        "tgn:1000001",
        "tgn:7012149",
        "tgn:2000064",
        "tgn:7029392"
    ],
    "tgn:id":2227967,
    "tgn:name":"Cedar Branch",
    "tgn:placetype":[
        "aat:300008699"
    ]
},
  "bbox": [],
  "geometry": {"coordinates":[-88.2333,31.6667],"type":"Point"}
}