{
  "id": 2528802,
  "type": "Feature",
  "properties": {
    "tgn:hierarchy":[
        "tgn:2528802",
        "tgn:1000001",
        "tgn:7012149",
        "tgn:2000421",
        "tgn:7007248",
        "tgn:7029392"
    ],
    "tgn:id":2528802,
    "tgn:name":"Mud Creek",
    "tgn:placetype":[
        "aat:300008706"
    ]
},
  "bbox": [],
  "geometry": {"coordinates":[-84.5667,32.8167],"type":"Point"}
}