{
  "id": 2318625,
  "type": "Feature",
  "properties": {
    "tgn:hierarchy":[
        "tgn:2318625",
        "tgn:1000001",
        "tgn:2000323",
        "tgn:7012149",
        "tgn:7007248",
        "tgn:7029392"
    ],
    "tgn:id":2318625,
    "tgn:name":"Ernest",
    "tgn:placetype":[
        "aat:300008347"
    ]
},
  "bbox": [],
  "geometry": {"coordinates":[-82.65,30.7667],"type":"Point"}
}