{
  "id": 7423985,
  "type": "Feature",
  "properties": {
    "tgn:hierarchy":[
        "tgn:7423985",
        "tgn:1000001",
        "tgn:1001906",
        "tgn:7005560",
        "tgn:7029392"
    ],
    "tgn:id":7423985,
    "tgn:name":"Las Pilas",
    "tgn:placetype":[
        "aat:300008347"
    ]
},
  "bbox": [],
  "geometry": {"coordinates":[-105.066667,22.520833],"type":"Point"}
}