{
  "id": 1018071,
  "type": "Feature",
  "properties": {
    "tgn:hierarchy":[
        "tgn:1018071",
        "tgn:1000001",
        "tgn:1001960",
        "tgn:7005560",
        "tgn:7029392"
    ],
    "tgn:id":1018071,
    "tgn:name":"Puerto Libertad",
    "tgn:placetype":[
        "aat:300008347"
    ]
},
  "bbox": [],
  "geometry": {"coordinates":[-112.716667,29.916667],"type":"Point"}
}