{
  "id": 2393423,
  "type": "Feature",
  "properties": {
    "tgn:hierarchy":[
        "tgn:2393423",
        "tgn:1000001",
        "tgn:2000861",
        "tgn:7012149",
        "tgn:7007256",
        "tgn:7029392"
    ],
    "tgn:id":2393423,
    "tgn:name":"Hog Branch",
    "tgn:placetype":[
        "aat:300008699"
    ]
},
  "bbox": [],
  "geometry": {"coordinates":[-93.5667,32.9167],"type":"Point"}
}