<<<<<<< HEAD
{
  "id": 7471593,
  "type": "Feature",
  "properties": {
    "tgn:hierarchy":[
        "tgn:7471593",
        "tgn:7468018",
        "tgn:1000004",
        "tgn:1000141",
        "tgn:7029392"
    ],
    "tgn:id":7471593,
    "tgn:name":"Zhouzi",
    "tgn:placetype":[
        "aat:300008347"
    ]
},
  "bbox": [],
  "geometry": {"coordinates":[120.19403,23.451596],"type":"Point"}
}
=======
{"geometry":{"type":"Point","coordinates":[120.194030,23.451596]},"type":"Feature","properties":{"hierarchy":["tgn:7471593","tgn:7468018","tgn:1000004","tgn:1000141","tgn:7029392"],"placetype":["aat:300008347"],"id":7471593,"name:xx":"Zhouzi"}}
>>>>>>> 03f74aca74312dbeaf24d7e61306dd6a786dc3d0
