{
  "id": 7505825,
  "type": "Feature",
  "properties": {
    "tgn:hierarchy":[
        "tgn:7505825",
        "tgn:1009227",
        "tgn:1000226",
        "tgn:7018437",
        "tgn:1000006",
        "tgn:7029392"
    ],
    "tgn:id":7505825,
    "tgn:name:en":"Tokarahi",
    "tgn:placetype":[
        "aat:300008347"
    ]
},
  "bbox": [],
  "geometry": {"coordinates":[170.65,-44.95],"type":"Point"}
}