{
  "id": 7330339,
  "type": "Feature",
  "properties": {
    "tgn:hierarchy":[
        "tgn:7330339",
        "tgn:7002835",
        "tgn:7001158",
        "tgn:1000003",
        "tgn:1000095",
        "tgn:7029392"
    ],
    "tgn:id":7330339,
    "tgn:name":"Hoja, Arroyo de la",
    "tgn:placetype":[
        "aat:300266554",
        "aat:300008699"
    ]
},
  "bbox": [],
  "geometry": {"coordinates":[-5.833333,40.616667],"type":"Point"}
}