{
  "id": 2239616,
  "type": "Feature",
  "properties": {
    "tgn:hierarchy":[
        "tgn:2239616",
        "tgn:1000001",
        "tgn:7012149",
        "tgn:2000928",
        "tgn:7007515",
        "tgn:7029392"
    ],
    "tgn:id":2239616,
    "tgn:name":"Churchill Ridge",
    "tgn:placetype":[
        "aat:300266640"
    ]
},
  "bbox": [],
  "geometry": {"coordinates":[-69.2667,46.4667],"type":"Point"}
}