{
  "id": 2523402,
  "type": "Feature",
  "properties": {
    "tgn:hierarchy":[
        "tgn:2523402",
        "tgn:1000001",
        "tgn:7012149",
        "tgn:2001056",
        "tgn:7007521",
        "tgn:7029392"
    ],
    "tgn:id":2523402,
    "tgn:name":"Moose Creek",
    "tgn:placetype":[
        "aat:300008706"
    ]
},
  "bbox": [],
  "geometry": {"coordinates":[-92.5167,46.05],"type":"Point"}
}