<<<<<<< HEAD
{
  "id": 2151491,
  "type": "Feature",
  "properties": {
    "tgn:hierarchy":[
        "tgn:2151491",
        "tgn:1000001",
        "tgn:7012149",
        "tgn:2000891",
        "tgn:7007256",
        "tgn:7029392"
    ],
    "tgn:id":2151491,
    "tgn:name":"Batola, Lake",
    "tgn:placetype":[
        "aat:300008680"
    ]
},
  "bbox": [],
  "geometry": {"coordinates":[-89.8,29.6667],"type":"Point"}
}
=======
{"geometry":{"type":"Point","coordinates":[-89.800000,29.666700]},"type":"Feature","properties":{"hierarchy":["tgn:2151491","tgn:1000001","tgn:7012149","tgn:2000891","tgn:7007256","tgn:7029392"],"placetype":["aat:300008680"],"id":2151491,"name:xx":"Batola, Lake"}}
>>>>>>> 03f74aca74312dbeaf24d7e61306dd6a786dc3d0
