{
  "id": 2413606,
  "type": "Feature",
  "properties": {
    "tgn:hierarchy":[
        "tgn:2413606",
        "tgn:1000001",
        "tgn:2001431",
        "tgn:7012149",
        "tgn:7007566",
        "tgn:7029392"
    ],
    "tgn:id":2413606,
    "tgn:name":"Irene Number Two",
    "tgn:placetype":[
        "aat:300000390"
    ]
},
  "bbox": [],
  "geometry": {"coordinates":[-107.9833,35.0167],"type":"Point"}
}