{
  "id": 2594513,
  "type": "Feature",
  "properties": {
    "tgn:hierarchy":[
        "tgn:2594513",
        "tgn:7006450",
        "tgn:1000001",
        "tgn:7012149",
        "tgn:2000079",
        "tgn:7029392"
    ],
    "tgn:id":2594513,
    "tgn:name":"Portland Creek",
    "tgn:placetype":[
        "aat:300008706"
    ]
},
  "bbox": [],
  "geometry": {"coordinates":[-163.8167,65.05],"type":"Point"}
}