{
  "id": 7490746,
  "type": "Feature",
  "properties": {
    "tgn:hierarchy":[
        "tgn:7490746",
        "tgn:1000004",
        "tgn:7467799",
        "tgn:1000141",
        "tgn:7029392"
    ],
    "tgn:id":7490746,
    "tgn:name":"Taixi Cun",
    "tgn:placetype":[
        "aat:300387173"
    ]
},
  "bbox": [],
  "geometry": {"coordinates":[120.280615,23.843647],"type":"Point"}
}