<<<<<<< HEAD
{
  "id": 2251524,
  "type": "Feature",
  "properties": {
    "tgn:hierarchy":[
        "tgn:2251524",
        "tgn:1000001",
        "tgn:7012149",
        "tgn:7007248",
        "tgn:7029392"
    ],
    "tgn:id":2251524,
    "tgn:name":"Commissioner Creek",
    "tgn:placetype":[
        "aat:300008706"
    ]
},
  "bbox": [],
  "geometry": {"coordinates":[-83.4667,33.0333],"type":"Point"}
}
=======
{"geometry":{"type":"Point","coordinates":[-83.466700,33.033300]},"type":"Feature","properties":{"hierarchy":["tgn:2251524","tgn:1000001","tgn:7012149","tgn:7007248","tgn:7029392"],"placetype":["aat:300008706"],"id":2251524,"name:xx":"Commissioner Creek"}}
>>>>>>> 03f74aca74312dbeaf24d7e61306dd6a786dc3d0
