{
  "id": 2228375,
  "type": "Feature",
  "properties": {
    "tgn:hierarchy":[
        "tgn:2228375",
        "tgn:1000001",
        "tgn:7012149",
        "tgn:2001129",
        "tgn:7007522",
        "tgn:7029392"
    ],
    "tgn:id":2228375,
    "tgn:name":"Cedar Creek",
    "tgn:placetype":[
        "aat:300008347"
    ]
},
  "bbox": [],
  "geometry": {"coordinates":[-88.4333,33.3167],"type":"Point"}
}