{
  "id": 7231285,
  "type": "Feature",
  "properties": {
    "tgn:hierarchy":[
        "tgn:7231285",
        "tgn:7002741",
        "tgn:7017076",
        "tgn:1000003",
        "tgn:1000074",
        "tgn:7029392"
    ],
    "tgn:id":7231285,
    "tgn:name":"Khalki\u00e1nika",
    "tgn:placetype":[
        "aat:300008347"
    ]
},
  "bbox": [],
  "geometry": {"coordinates":[22.266667,38.033333],"type":"Point"}
}