{
  "id": 2505905,
  "type": "Feature",
  "properties": {
    "tgn:hierarchy":[
        "tgn:2505905",
        "tgn:1000001",
        "tgn:7012149",
        "tgn:1002387",
        "tgn:7007710",
        "tgn:7029392"
    ],
    "tgn:id":2505905,
    "tgn:name":"Mercersburg Reservoir",
    "tgn:placetype":[
        "aat:300006191"
    ]
},
  "bbox": [],
  "geometry": {"coordinates":[-77.95,39.8667],"type":"Point"}
}