{
  "id": 7420251,
  "type": "Feature",
  "properties": {
    "tgn:hierarchy":[
        "tgn:7420251",
        "tgn:7005584",
        "tgn:1000001",
        "tgn:7005560",
        "tgn:7029392"
    ],
    "tgn:id":7420251,
    "tgn:name":"El Guam\u00fcchil",
    "tgn:placetype":[
        "aat:300008347"
    ]
},
  "bbox": [],
  "geometry": {"coordinates":[-99.945278,21.321389],"type":"Point"}
}