{
  "id": 2375183,
  "type": "Feature",
  "properties": {
    "tgn:hierarchy":[
        "tgn:2375183",
        "tgn:1000001",
        "tgn:7012149",
        "tgn:2001256",
        "tgn:7007523",
        "tgn:7029392"
    ],
    "tgn:id":2375183,
    "tgn:name":"Hannah Branch",
    "tgn:placetype":[
        "aat:300008699"
    ]
},
  "bbox": [],
  "geometry": {"coordinates":[-92.85,37.2833],"type":"Point"}
}