{
  "id": 7239133,
  "type": "Feature",
  "properties": {
    "tgn:hierarchy":[
        "tgn:7239133",
        "tgn:7007877",
        "tgn:1000003",
        "tgn:1000063",
        "tgn:4012014",
        "tgn:7029392"
    ],
    "tgn:id":7239133,
    "tgn:name":"Hayettes, Bois des",
    "tgn:placetype":[
        "aat:300008863"
    ]
},
  "bbox": [],
  "geometry": {"coordinates":[4.183333,50.033333],"type":"Point"}
}