{
  "id": 2209101,
  "type": "Feature",
  "properties": {
    "tgn:hierarchy":[
        "tgn:2209101",
        "tgn:1000001",
        "tgn:7006451",
        "tgn:7012149",
        "tgn:2000103",
        "tgn:7029392"
    ],
    "tgn:id":2209101,
    "tgn:name":"Burnt Hole Spring Number Two",
    "tgn:placetype":[
        "aat:300006191"
    ]
},
  "bbox": [],
  "geometry": {"coordinates":[-111.9667,34.05],"type":"Point"}
}