{
  "id": 2113576,
  "type": "Feature",
  "properties": {
    "tgn:hierarchy":[
        "tgn:2113576",
        "tgn:1000001",
        "tgn:7012149",
        "tgn:2002179",
        "tgn:7007919",
        "tgn:7029392"
    ],
    "tgn:id":2113576,
    "tgn:name":"Patrick Springs",
    "tgn:placetype":[
        "aat:300008347"
    ]
},
  "bbox": [],
  "geometry": {"coordinates":[-80.1833,36.6333],"type":"Point"}
}