{
  "id": 2746373,
  "type": "Feature",
  "properties": {
    "tgn:hierarchy":[
        "tgn:2746373",
        "tgn:1000001",
        "tgn:7012149",
        "tgn:1002392",
        "tgn:7007157",
        "tgn:7029392"
    ],
    "tgn:id":2746373,
    "tgn:name":"W K Hill",
    "tgn:placetype":[
        "aat:300008798"
    ]
},
  "bbox": [],
  "geometry": {"coordinates":[-120.3167,36.2167],"type":"Point"}
}