{
  "id": 2693626,
  "type": "Feature",
  "properties": {
    "tgn:hierarchy":[
        "tgn:2693626",
        "tgn:1000001",
        "tgn:7012149",
        "tgn:1002624",
        "tgn:7007568",
        "tgn:7029392"
    ],
    "tgn:id":2693626,
    "tgn:name":"Stephens Creek",
    "tgn:placetype":[
        "aat:300008706"
    ]
},
  "bbox": [],
  "geometry": {"coordinates":[-75.75,43.1333],"type":"Point"}
}