{
  "id": 2563676,
  "type": "Feature",
  "properties": {
    "tgn:hierarchy":[
        "tgn:2563676",
        "tgn:1000001",
        "tgn:2001432",
        "tgn:7012149",
        "tgn:7007566",
        "tgn:7029392"
    ],
    "tgn:id":2563676,
    "tgn:name":"Ox Canyon",
    "tgn:placetype":[
        "aat:300008761"
    ]
},
  "bbox": [],
  "geometry": {"coordinates":[-104.6667,36.7667],"type":"Point"}
}