{
  "id": 7483753,
  "type": "Feature",
  "properties": {
    "tgn:hierarchy":[
        "tgn:7483753",
        "tgn:1000004",
        "tgn:7490934",
        "tgn:1000141",
        "tgn:7029392"
    ],
    "tgn:id":7483753,
    "tgn:name":"Shanzijiao",
    "tgn:placetype":[
        "aat:300387033"
    ]
},
  "bbox": [],
  "geometry": {"coordinates":[120.42,23.385556],"type":"Point"}
}