{
  "id": 7582556,
  "type": "Feature",
  "properties": {
    "tgn:hierarchy":[
        "tgn:7582556",
        "tgn:1000004",
        "tgn:7000198",
        "tgn:1001894",
        "tgn:7029392"
    ],
    "tgn:id":7582556,
    "tgn:name:en":"Bhartiya",
    "tgn:placetype":[
        "aat:300008347"
    ]
},
  "bbox": [],
  "geometry": {"coordinates":[78.875926,24.10327],"type":"Point"}
}