{
  "id": 7522942,
  "type": "Feature",
  "properties": {
    "tgn:hierarchy":[
        "tgn:7522942",
        "tgn:7001242",
        "tgn:7016833",
        "tgn:7001335",
        "tgn:7029392"
    ],
    "tgn:id":7522942,
    "tgn:name:en":"Bardawil Peninsula",
    "tgn:placetype":[
        "aat:300008804"
    ]
},
  "bbox": [],
  "geometry": {"coordinates":[32.893333,31.079722],"type":"Point"}
}