{
  "id": 2195005,
  "type": "Feature",
  "properties": {
    "tgn:hierarchy":[
        "tgn:2195005",
        "tgn:1000001",
        "tgn:7012149",
        "tgn:7007158",
        "tgn:7029392"
    ],
    "tgn:id":2195005,
    "tgn:name":"Brighton Lateral Ditch",
    "tgn:placetype":[
        "aat:300006075"
    ]
},
  "bbox": [],
  "geometry": {"coordinates":[-104.7833,40.0167],"type":"Point"}
}