<<<<<<< HEAD
{
  "id": 2768906,
  "type": "Feature",
  "properties": {
    "tgn:hierarchy":[
        "tgn:2768906",
        "tgn:1000001",
        "tgn:7012149",
        "tgn:2001145",
        "tgn:7007522",
        "tgn:7029392"
    ],
    "tgn:id":2768906,
    "tgn:name":"Whitney Lake",
    "tgn:placetype":[
        "aat:300008680"
    ]
},
  "bbox": [],
  "geometry": {"coordinates":[-90.35,34.4],"type":"Point"}
}
=======
{"geometry":{"type":"Point","coordinates":[-90.350000,34.400000]},"type":"Feature","properties":{"hierarchy":["tgn:2768906","tgn:1000001","tgn:7012149","tgn:2001145","tgn:7007522","tgn:7029392"],"placetype":["aat:300008680"],"id":2768906,"name:xx":"Whitney Lake"}}
>>>>>>> 03f74aca74312dbeaf24d7e61306dd6a786dc3d0
