{
  "id": 2132397,
  "type": "Feature",
  "properties": {
    "tgn:hierarchy":[
        "tgn:2132397",
        "tgn:7006450",
        "tgn:1000001",
        "tgn:2124012",
        "tgn:7012149",
        "tgn:7029392"
    ],
    "tgn:id":2132397,
    "tgn:name":"Amook Island",
    "tgn:placetype":[
        "aat:300008791"
    ]
},
  "bbox": [],
  "geometry": {"coordinates":[-153.8333,57.4833],"type":"Point"}
}