{
  "id": 2455008,
  "type": "Feature",
  "properties": {
    "tgn:hierarchy":[
        "tgn:2455008",
        "tgn:7006450",
        "tgn:1000001",
        "tgn:7012149",
        "tgn:2000086",
        "tgn:7029392"
    ],
    "tgn:id":2455008,
    "tgn:name":"Little Eldorado Creek",
    "tgn:placetype":[
        "aat:300008706"
    ]
},
  "bbox": [],
  "geometry": {"coordinates":[-141.8167,62.1167],"type":"Point"}
}