{
  "id": 7490988,
  "type": "Feature",
  "properties": {
    "tgn:hierarchy":[
        "tgn:7490988",
        "tgn:1000004",
        "tgn:7467799",
        "tgn:1000141",
        "tgn:7029392"
    ],
    "tgn:id":7490988,
    "tgn:name":"Paizilutou",
    "tgn:placetype":[
        "aat:300008347"
    ]
},
  "bbox": [],
  "geometry": {"coordinates":[120.5659,23.8811],"type":"Point"}
}