{
  "id": 7167429,
  "type": "Feature",
  "properties": {
    "tgn:hierarchy":[
        "tgn:7167429",
        "tgn:7003692",
        "tgn:1000003",
        "tgn:7000084",
        "tgn:7029392"
    ],
    "tgn:id":7167429,
    "tgn:name":"Hartobel",
    "tgn:placetype":[
        "aat:300000206"
    ]
},
  "bbox": [],
  "geometry": {"coordinates":[9.533333,47.833333],"type":"Point"}
}