{
  "id": 7484409,
  "type": "Feature",
  "properties": {
    "tgn:hierarchy":[
        "tgn:7484409",
        "tgn:7001004",
        "tgn:1000004",
        "tgn:1000141",
        "tgn:7029392"
    ],
    "tgn:id":7484409,
    "tgn:name":"Kuoting Shan",
    "tgn:placetype":[
        "aat:300008798"
    ]
},
  "bbox": [],
  "geometry": {"coordinates":[120.6225,23.055833],"type":"Point"}
}