{
  "id": 2518569,
  "type": "Feature",
  "properties": {
    "tgn:hierarchy":[
        "tgn:2518569",
        "tgn:1000001",
        "tgn:7012149",
        "tgn:7007525",
        "tgn:7029392"
    ],
    "tgn:id":2518569,
    "tgn:name":"Mitchell Creek Canyon",
    "tgn:placetype":[
        "aat:300008761"
    ]
},
  "bbox": [],
  "geometry": {"coordinates":[-100.35,40.7167],"type":"Point"}
}