{
  "id": 2165968,
  "type": "Feature",
  "properties": {
    "tgn:hierarchy":[
        "tgn:2165968",
        "tgn:1000001",
        "tgn:7012149",
        "tgn:2001718",
        "tgn:7007708",
        "tgn:7029392"
    ],
    "tgn:id":2165968,
    "tgn:name":"Big Arrow Reservoir",
    "tgn:placetype":[
        "aat:300006191"
    ]
},
  "bbox": [],
  "geometry": {"coordinates":[-117.65,42.3333],"type":"Point"}
}