{
  "id": 7236136,
  "type": "Feature",
  "properties": {
    "tgn:hierarchy":[
        "tgn:7236136",
        "tgn:7002739",
        "tgn:7017076",
        "tgn:1000003",
        "tgn:1000074",
        "tgn:7029392"
    ],
    "tgn:id":7236136,
    "tgn:name":"\u00c9vandron",
    "tgn:placetype":[
        "aat:300008347"
    ]
},
  "bbox": [],
  "geometry": {"coordinates":[22.366667,37.45],"type":"Point"}
}