{
  "id": 2480428,
  "type": "Feature",
  "properties": {
    "tgn:hierarchy":[
        "tgn:2480428",
        "tgn:1000001",
        "tgn:7012149",
        "tgn:2000882",
        "tgn:7007256",
        "tgn:7029392"
    ],
    "tgn:id":2480428,
    "tgn:name":"Lake Trois Jeans",
    "tgn:placetype":[
        "aat:300132316"
    ]
},
  "bbox": [],
  "geometry": {"coordinates":[-90.3667,29.2833],"type":"Point"}
}