{
  "id": 1116185,
  "type": "Feature",
  "properties": {
    "tgn:hierarchy":[
        "tgn:1116185",
        "tgn:7005685",
        "tgn:1000001",
        "tgn:7005804",
        "tgn:7029392"
    ],
    "tgn:id":1116185,
    "tgn:name":"Eau Claire, Lac \u00e0 l'",
    "tgn:placetype":[
        "aat:300008680"
    ]
},
  "bbox": [],
  "geometry": {"coordinates":[-73.0667,46.55],"type":"Point"}
}