{
  "id": 7299921,
  "type": "Feature",
  "properties": {
    "tgn:hierarchy":[
        "tgn:7299921",
        "tgn:7007780",
        "tgn:1000003",
        "tgn:7009604",
        "tgn:1000095",
        "tgn:7029392"
    ],
    "tgn:id":7299921,
    "tgn:name":"Turulla, Punta de la",
    "tgn:placetype":[
        "aat:300386846"
    ]
},
  "bbox": [],
  "geometry": {"coordinates":[-1.85,43.366667],"type":"Point"}
}