{
  "id": 2465085,
  "type": "Feature",
  "properties": {
    "tgn:hierarchy":[
        "tgn:2465085",
        "tgn:7023902",
        "tgn:1000001",
        "tgn:7012149",
        "tgn:7007249",
        "tgn:7029392"
    ],
    "tgn:id":2465085,
    "tgn:name":"Lokoaka Pond",
    "tgn:placetype":[
        "aat:300008680"
    ]
},
  "bbox": [],
  "geometry": {"coordinates":[-155.0167,19.7333],"type":"Point"}
}