{
  "id": 7376919,
  "type": "Feature",
  "properties": {
    "tgn:hierarchy":[
        "tgn:7376919",
        "tgn:1000001",
        "tgn:7005589",
        "tgn:7005560",
        "tgn:7029392"
    ],
    "tgn:id":7376919,
    "tgn:name":"Las Amarillas",
    "tgn:placetype":[
        "aat:300008347"
    ]
},
  "bbox": [],
  "geometry": {"coordinates":[-98.916667,25.316667],"type":"Point"}
}