{
  "id": 2183069,
  "type": "Feature",
  "properties": {
    "tgn:hierarchy":[
        "tgn:2183069",
        "tgn:1000001",
        "tgn:7012149",
        "tgn:2001281",
        "tgn:7007524",
        "tgn:7029392"
    ],
    "tgn:id":2183069,
    "tgn:name":"Bluebird Mine",
    "tgn:placetype":[
        "aat:300000390"
    ]
},
  "bbox": [],
  "geometry": {"coordinates":[-112.15,46.35],"type":"Point"}
}