{
  "id": 2115698,
  "type": "Feature",
  "properties": {
    "tgn:hierarchy":[
        "tgn:2115698",
        "tgn:1000001",
        "tgn:7012149",
        "tgn:2002252",
        "tgn:7007920",
        "tgn:7029392"
    ],
    "tgn:id":2115698,
    "tgn:name":"Elberton",
    "tgn:placetype":[
        "aat:300008347",
        "aat:300387210"
    ]
},
  "bbox": [],
  "geometry": {"coordinates":[-117.2167,46.9667],"type":"Point"}
}