{
  "id": 1133181,
  "type": "Feature",
  "properties": {
    "tgn:hierarchy":[
        "tgn:1133181",
        "tgn:7005685",
        "tgn:1000001",
        "tgn:7013154",
        "tgn:7029392"
    ],
    "tgn:id":1133181,
    "tgn:name":"Fansher Creek",
    "tgn:placetype":[
        "aat:300008706"
    ]
},
  "bbox": [],
  "geometry": {"coordinates":[-82.0167,42.6167],"type":"Point"}
}