{
  "id": 2784613,
  "type": "Feature",
  "properties": {
    "tgn:hierarchy":[
        "tgn:2784613",
        "tgn:1000001",
        "tgn:7012149",
        "tgn:2000885",
        "tgn:7007256",
        "tgn:7029392"
    ],
    "tgn:id":2784613,
    "tgn:name":"Yawn",
    "tgn:placetype":[
        "aat:300008347"
    ]
},
  "bbox": [],
  "geometry": {"coordinates":[-90.5833,30.6167],"type":"Point"}
}