{
  "id": 2060331,
  "type": "Feature",
  "properties": {
    "tgn:hierarchy":[
        "tgn:2060331",
        "tgn:1000001",
        "tgn:7012149",
        "tgn:1002671",
        "tgn:7007523",
        "tgn:7029392"
    ],
    "tgn:id":2060331,
    "tgn:name":"Saint Anthony",
    "tgn:placetype":[
        "aat:300008347"
    ]
},
  "bbox": [],
  "geometry": {"coordinates":[-92.2667,38.15],"type":"Point"}
}