{
  "id": 1048263,
  "type": "Feature",
  "properties": {
    "tgn:concordances":{
        "gn:id":"2744114"
    },
    "tgn:hierarchy":[
        "tgn:1048263",
        "tgn:1000003",
        "tgn:7006951",
        "tgn:7016845",
        "tgn:7029392"
    ],
    "tgn:id":1048263,
    "tgn:name:nl":"Zaanstad",
    "tgn:placetype":[
        "aat:300008347",
        "aat:300008389"
    ]
},
  "bbox": [],
  "geometry": {"coordinates":[4.833333,52.45],"type":"Point"}
}