{
  "id": 2334218,
  "type": "Feature",
  "properties": {
    "tgn:hierarchy":[
        "tgn:2334218",
        "tgn:1000001",
        "tgn:2000465",
        "tgn:7012149",
        "tgn:7007250",
        "tgn:7029392"
    ],
    "tgn:id":2334218,
    "tgn:name":"Forest Canal",
    "tgn:placetype":[
        "aat:300006075"
    ]
},
  "bbox": [],
  "geometry": {"coordinates":[-116.6667,43.5833],"type":"Point"}
}