{
  "id": 2627050,
  "type": "Feature",
  "properties": {
    "tgn:hierarchy":[
        "tgn:2627050",
        "tgn:2002306",
        "tgn:1000001",
        "tgn:7012149",
        "tgn:7007922",
        "tgn:7029392"
    ],
    "tgn:id":2627050,
    "tgn:name":"Rocky Run",
    "tgn:placetype":[
        "aat:300008699"
    ]
},
  "bbox": [],
  "geometry": {"coordinates":[-90.6667,46.0167],"type":"Point"}
}