{
  "id": 1046526,
  "type": "Feature",
  "properties": {
    "tgn:hierarchy":[
        "tgn:1046526",
        "tgn:7003127",
        "tgn:1000003",
        "tgn:7008516",
        "tgn:1000080",
        "tgn:7029392"
    ],
    "tgn:id":1046526,
    "tgn:name":"San Giorgio di Piano",
    "tgn:placetype":[
        "aat:300008347"
    ]
},
  "bbox": [],
  "geometry": {"coordinates":[11.366667,44.65],"type":"Point"}
}