{
  "id": 2618256,
  "type": "Feature",
  "properties": {
    "tgn:hierarchy":[
        "tgn:2618256",
        "tgn:1000001",
        "tgn:7012149",
        "tgn:2002304",
        "tgn:7013961",
        "tgn:7029392"
    ],
    "tgn:id":2618256,
    "tgn:name":"Riggins Branch",
    "tgn:placetype":[
        "aat:300008699"
    ]
},
  "bbox": [],
  "geometry": {"coordinates":[-81.6667,37.7167],"type":"Point"}
}