{
  "id": 1120760,
  "type": "Feature",
  "properties": {
    "tgn:hierarchy":[
        "tgn:1120760",
        "tgn:1002132",
        "tgn:1000001",
        "tgn:7012149",
        "tgn:7007919",
        "tgn:7029392"
    ],
    "tgn:id":1120760,
    "tgn:name":"Toms Cove",
    "tgn:placetype":[
        "aat:300132317"
    ]
},
  "bbox": [],
  "geometry": {"coordinates":[-75.3667,37.8667],"type":"Point"}
}