{
  "id": 2640326,
  "type": "Feature",
  "properties": {
    "tgn:hierarchy":[
        "tgn:2640326",
        "tgn:1000001",
        "tgn:7012149",
        "tgn:2001451",
        "tgn:7007566",
        "tgn:7029392"
    ],
    "tgn:id":2640326,
    "tgn:name":"San Diego, Ca\u00f1on de",
    "tgn:placetype":[
        "aat:300008761"
    ]
},
  "bbox": [],
  "geometry": {"coordinates":[-106.6333,35.85],"type":"Point"}
}