{
  "id": 2073717,
  "type": "Feature",
  "properties": {
    "tgn:hierarchy":[
        "tgn:2073717",
        "tgn:1000001",
        "tgn:7012149",
        "tgn:2001490",
        "tgn:7007709",
        "tgn:7029392"
    ],
    "tgn:id":2073717,
    "tgn:name":"Bixby",
    "tgn:placetype":[
        "aat:300008347"
    ]
},
  "bbox": [],
  "geometry": {"coordinates":[-80.45,35.9333],"type":"Point"}
}