{
  "id": 2199139,
  "type": "Feature",
  "properties": {
    "tgn:hierarchy":[
        "tgn:2199139",
        "tgn:1000001",
        "tgn:7012149",
        "tgn:1002291",
        "tgn:7007826",
        "tgn:7029392"
    ],
    "tgn:id":2199139,
    "tgn:name":"Brune Creek",
    "tgn:placetype":[
        "aat:300008706"
    ]
},
  "bbox": [],
  "geometry": {"coordinates":[-96.4833,29.7833],"type":"Point"}
}