{
  "id": 2242957,
  "type": "Feature",
  "properties": {
    "tgn:hierarchy":[
        "tgn:2242957",
        "tgn:1000001",
        "tgn:7006451",
        "tgn:7012149",
        "tgn:2000104",
        "tgn:7029392"
    ],
    "tgn:id":2242957,
    "tgn:name":"Clear Lake",
    "tgn:placetype":[
        "aat:300008680"
    ]
},
  "bbox": [],
  "geometry": {"coordinates":[-114.5167,33.0167],"type":"Point"}
}