{
  "id": 2504203,
  "type": "Feature",
  "properties": {
    "tgn:hierarchy":[
        "tgn:2504203",
        "tgn:1000001",
        "tgn:7012149",
        "tgn:7014185",
        "tgn:7007710",
        "tgn:7029392"
    ],
    "tgn:id":2504203,
    "tgn:name":"Meadow Run",
    "tgn:placetype":[
        "aat:300008699"
    ]
},
  "bbox": [],
  "geometry": {"coordinates":[-79.9833,39.9667],"type":"Point"}
}