{
  "id": 7428219,
  "type": "Feature",
  "properties": {
    "tgn:hierarchy":[
        "tgn:7428219",
        "tgn:7005581",
        "tgn:1000001",
        "tgn:7005560",
        "tgn:7029392"
    ],
    "tgn:id":7428219,
    "tgn:name":"Huirnima",
    "tgn:placetype":[
        "aat:300008347"
    ]
},
  "bbox": [],
  "geometry": {"coordinates":[-107.516667,27.983333],"type":"Point"}
}