{
  "id": 2738471,
  "type": "Feature",
  "properties": {
    "tgn:hierarchy":[
        "tgn:2738471",
        "tgn:1000001",
        "tgn:7013638",
        "tgn:7012149",
        "tgn:7007568",
        "tgn:7029392"
    ],
    "tgn:id":2738471,
    "tgn:name":"Underhill Pond",
    "tgn:placetype":[
        "aat:300006191"
    ]
},
  "bbox": [],
  "geometry": {"coordinates":[-73.7833,42.25],"type":"Point"}
}