{
  "id": 2291133,
  "type": "Feature",
  "properties": {
    "tgn:hierarchy":[
        "tgn:2291133",
        "tgn:1000001",
        "tgn:7012149",
        "tgn:7007157",
        "tgn:1002957",
        "tgn:7029392"
    ],
    "tgn:id":2291133,
    "tgn:name":"Doghead Peak",
    "tgn:placetype":[
        "aat:300008798"
    ]
},
  "bbox": [],
  "geometry": {"coordinates":[-119.4167,38.05],"type":"Point"}
}