{
  "id": 7594005,
  "type": "Feature",
  "properties": {
    "tgn:hierarchy":[
        "tgn:7594005",
        "tgn:1000003",
        "tgn:1000066",
        "tgn:7029392"
    ],
    "tgn:id":7594005,
    "tgn:name":"Hovedstaden",
    "tgn:placetype":[
        "aat:300387064",
        "aat:300236112"
    ]
},
  "bbox": [],
  "geometry": {"coordinates":[12.333,55.833],"type":"Point"}
}