<<<<<<< HEAD
{
  "id": 2257023,
  "type": "Feature",
  "properties": {
    "tgn:hierarchy":[
        "tgn:2257023",
        "tgn:1000001",
        "tgn:2000267",
        "tgn:7012149",
        "tgn:7007240",
        "tgn:7029392"
    ],
    "tgn:id":2257023,
    "tgn:name":"Corn Landing Lake",
    "tgn:placetype":[
        "aat:300008680"
    ]
},
  "bbox": [],
  "geometry": {"coordinates":[-84.4333,29.95],"type":"Point"}
}
=======
{"geometry":{"type":"Point","coordinates":[-84.433300,29.950000]},"type":"Feature","properties":{"hierarchy":["tgn:2257023","tgn:1000001","tgn:2000267","tgn:7012149","tgn:7007240","tgn:7029392"],"placetype":["aat:300008680"],"id":2257023,"name:xx":"Corn Landing Lake"}}
>>>>>>> 03f74aca74312dbeaf24d7e61306dd6a786dc3d0
