{
  "id": 2464901,
  "type": "Feature",
  "properties": {
    "tgn:hierarchy":[
        "tgn:2464901",
        "tgn:1000001",
        "tgn:7012149",
        "tgn:2001709",
        "tgn:7007708",
        "tgn:7029392"
    ],
    "tgn:id":2464901,
    "tgn:name":"Loggan Springs",
    "tgn:placetype":[
        "aat:300008697"
    ]
},
  "bbox": [],
  "geometry": {"coordinates":[-118.6167,43.65],"type":"Point"}
}