{
  "id": 2238013,
  "type": "Feature",
  "properties": {
    "tgn:hierarchy":[
        "tgn:2238013",
        "tgn:1000001",
        "tgn:7012149",
        "tgn:7007157",
        "tgn:1002621",
        "tgn:7029392"
    ],
    "tgn:id":2238013,
    "tgn:name":"Chiquito Ridge",
    "tgn:placetype":[
        "aat:300266640"
    ]
},
  "bbox": [],
  "geometry": {"coordinates":[-119.4167,37.35],"type":"Point"}
}