{
  "id": 7065497,
  "type": "Feature",
  "properties": {
    "tgn:hierarchy":[
        "tgn:7065497",
        "tgn:1000003",
        "tgn:7003677",
        "tgn:7000084",
        "tgn:7029392"
    ],
    "tgn:id":7065497,
    "tgn:name":"Sterbecke",
    "tgn:placetype":[
        "aat:300008699"
    ]
},
  "bbox": [],
  "geometry": {"coordinates":[7.533333,51.283333],"type":"Point"}
}