{
  "id": 2635377,
  "type": "Feature",
  "properties": {
    "tgn:hierarchy":[
        "tgn:2635377",
        "tgn:1000001",
        "tgn:7012149",
        "tgn:2001288",
        "tgn:7007524",
        "tgn:7029392"
    ],
    "tgn:id":2635377,
    "tgn:name":"SE NW Section 36 Mine",
    "tgn:placetype":[
        "aat:300000390"
    ]
},
  "bbox": [],
  "geometry": {"coordinates":[-112.0333,45.4333],"type":"Point"}
}