{
  "id": 2061176,
  "type": "Feature",
  "properties": {
    "tgn:hierarchy":[
        "tgn:2061176",
        "tgn:1000001",
        "tgn:7012149",
        "tgn:2001275",
        "tgn:7007524",
        "tgn:7029392"
    ],
    "tgn:id":2061176,
    "tgn:name":"Central Park",
    "tgn:placetype":[
        "aat:300008347",
        "aat:300387210"
    ]
},
  "bbox": [],
  "geometry": {"coordinates":[-111.2667,45.8167],"type":"Point"}
}