{
  "id": 7224581,
  "type": "Feature",
  "properties": {
    "tgn:hierarchy":[
        "tgn:7224581",
        "tgn:7002745",
        "tgn:7017076",
        "tgn:1000003",
        "tgn:1000074",
        "tgn:7029392"
    ],
    "tgn:id":7224581,
    "tgn:name":"Ner\u00e1ki, \u00d3rmos",
    "tgn:placetype":[
        "aat:300132316"
    ]
},
  "bbox": [],
  "geometry": {"coordinates":[23.15,36.516667],"type":"Point"}
}