{
  "id": 2521151,
  "type": "Feature",
  "properties": {
    "tgn:hierarchy":[
        "tgn:2521151",
        "tgn:1000001",
        "tgn:1002190",
        "tgn:7012149",
        "tgn:7007523",
        "tgn:7029392"
    ],
    "tgn:id":2521151,
    "tgn:name":"Monte Gurwit Lake",
    "tgn:placetype":[
        "aat:300006191"
    ]
},
  "bbox": [],
  "geometry": {"coordinates":[-92.3833,39.15],"type":"Point"}
}