{
  "id": 7071060,
  "type": "Feature",
  "properties": {
    "tgn:hierarchy":[
        "tgn:7071060",
        "tgn:1000003",
        "tgn:7003677",
        "tgn:7000084",
        "tgn:7029392"
    ],
    "tgn:id":7071060,
    "tgn:name":"Teindeln",
    "tgn:placetype":[
        "aat:300008347"
    ]
},
  "bbox": [],
  "geometry": {"coordinates":[7.816667,51.25],"type":"Point"}
}