<<<<<<< HEAD
{
  "id": 2259471,
  "type": "Feature",
  "properties": {
    "tgn:hierarchy":[
        "tgn:2259471",
        "tgn:1000001",
        "tgn:7012149",
        "tgn:7007157",
        "tgn:2000186",
        "tgn:7029392"
    ],
    "tgn:id":2259471,
    "tgn:name":"Cottonwood Springs",
    "tgn:placetype":[
        "aat:300008697"
    ]
},
  "bbox": [],
  "geometry": {"coordinates":[-120.5667,41.1833],"type":"Point"}
}
=======
{"geometry":{"type":"Point","coordinates":[-120.566700,41.183300]},"type":"Feature","properties":{"hierarchy":["tgn:2259471","tgn:1000001","tgn:7012149","tgn:7007157","tgn:2000186","tgn:7029392"],"placetype":["aat:300008697"],"id":2259471,"name:xx":"Cottonwood Springs"}}
>>>>>>> 03f74aca74312dbeaf24d7e61306dd6a786dc3d0
