{
  "id": 2259471,
  "type": "Feature",
  "properties": {
    "tgn:hierarchy":[
        "tgn:2259471",
        "tgn:1000001",
        "tgn:7012149",
        "tgn:7007157",
        "tgn:2000186",
        "tgn:7029392"
    ],
    "tgn:id":2259471,
    "tgn:name":"Cottonwood Springs",
    "tgn:placetype":[
        "aat:300008697"
    ]
},
  "bbox": [],
  "geometry": {"coordinates":[-120.5667,41.1833],"type":"Point"}
}