{
  "id": 2327259,
  "type": "Feature",
  "properties": {
    "tgn:hierarchy":[
        "tgn:2327259",
        "tgn:1000001",
        "tgn:1002229",
        "tgn:7012149",
        "tgn:7007710",
        "tgn:7029392"
    ],
    "tgn:id":2327259,
    "tgn:name":"First Fork",
    "tgn:placetype":[
        "aat:300008347"
    ]
},
  "bbox": [],
  "geometry": {"coordinates":[-78.0333,41.45],"type":"Point"}
}