{
  "id": 2170688,
  "type": "Feature",
  "properties": {
    "tgn:hierarchy":[
        "tgn:2170688",
        "tgn:1000001",
        "tgn:7016172",
        "tgn:7012149",
        "tgn:2000158",
        "tgn:7029392"
    ],
    "tgn:id":2170688,
    "tgn:name":"Big Sandy Bayou",
    "tgn:placetype":[
        "aat:300008699"
    ]
},
  "bbox": [],
  "geometry": {"coordinates":[-90.9333,34.2333],"type":"Point"}
}