{
  "id": 7505118,
  "type": "Feature",
  "properties": {
    "tgn:hierarchy":[
        "tgn:7505118",
        "tgn:1009892",
        "tgn:1000226",
        "tgn:1000006",
        "tgn:7029392"
    ],
    "tgn:id":7505118,
    "tgn:name:en":"Depot Island",
    "tgn:placetype":[
        "aat:300008791"
    ]
},
  "bbox": [],
  "geometry": {"coordinates":[179.022778,-47.750833],"type":"Point"}
}