{
  "id": 7482055,
  "type": "Feature",
  "properties": {
    "tgn:hierarchy":[
        "tgn:7482055",
        "tgn:1000004",
        "tgn:7492971",
        "tgn:1000141",
        "tgn:7029392"
    ],
    "tgn:id":7482055,
    "tgn:name":"Santai Qiao",
    "tgn:placetype":[
        "aat:300007836"
    ]
},
  "bbox": [],
  "geometry": {"coordinates":[120.6443,22.717637],"type":"Point"}
}