{
  "id": 2320495,
  "type": "Feature",
  "properties": {
    "tgn:hierarchy":[
        "tgn:2320495",
        "tgn:1000001",
        "tgn:7012149",
        "tgn:2002111",
        "tgn:7007827",
        "tgn:7029392"
    ],
    "tgn:id":2320495,
    "tgn:name":"Everstein Hollow",
    "tgn:placetype":[
        "aat:300008761"
    ]
},
  "bbox": [],
  "geometry": {"coordinates":[-112.9667,37.5167],"type":"Point"}
}