{
  "id": 2530534,
  "type": "Feature",
  "properties": {
    "tgn:hierarchy":[
        "tgn:2530534",
        "tgn:1000001",
        "tgn:7012149",
        "tgn:2001193",
        "tgn:7007523",
        "tgn:7029392"
    ],
    "tgn:id":2530534,
    "tgn:name":"Muddy Creek",
    "tgn:placetype":[
        "aat:300008706"
    ]
},
  "bbox": [],
  "geometry": {"coordinates":[-93.7667,39.9667],"type":"Point"}
}