{
  "id": 2035935,
  "type": "Feature",
  "properties": {
    "tgn:hierarchy":[
        "tgn:2035935",
        "tgn:1000001",
        "tgn:2000582",
        "tgn:7012149",
        "tgn:7007253",
        "tgn:7029392"
    ],
    "tgn:id":2035935,
    "tgn:name":"Wood",
    "tgn:placetype":[
        "aat:300008347",
        "aat:300387210"
    ]
},
  "bbox": [],
  "geometry": {"coordinates":[-91.3167,42.65],"type":"Point"}
}