{
  "id": 2091959,
  "type": "Feature",
  "properties": {
    "tgn:hierarchy":[
        "tgn:2091959",
        "tgn:1000001",
        "tgn:7012149",
        "tgn:1002387",
        "tgn:7007710",
        "tgn:7029392"
    ],
    "tgn:id":2091959,
    "tgn:name":"Pinola",
    "tgn:placetype":[
        "aat:300008347"
    ]
},
  "bbox": [],
  "geometry": {"coordinates":[-77.5833,40.0333],"type":"Point"}
}