{
  "id": 2639876,
  "type": "Feature",
  "properties": {
    "tgn:hierarchy":[
        "tgn:2639876",
        "tgn:1000001",
        "tgn:7012149",
        "tgn:2000181",
        "tgn:7007157",
        "tgn:7029392"
    ],
    "tgn:id":2639876,
    "tgn:name":"Samoa Peninsula",
    "tgn:placetype":[
        "aat:300008850"
    ]
},
  "bbox": [],
  "geometry": {"coordinates":[-124.1833,40.8167],"type":"Point"}
}