{
  "id": 2411467,
  "type": "Feature",
  "properties": {
    "tgn:hierarchy":[
        "tgn:2411467",
        "tgn:1000001",
        "tgn:2001476",
        "tgn:7012149",
        "tgn:7007709",
        "tgn:7029392"
    ],
    "tgn:id":2411467,
    "tgn:name":"Indian Hills",
    "tgn:placetype":[
        "aat:300008347"
    ]
},
  "bbox": [],
  "geometry": {"coordinates":[-81.5333,35.9667],"type":"Point"}
}