{
  "id": 7547812,
  "type": "Feature",
  "properties": {
    "tgn:hierarchy":[
        "tgn:7547812",
        "tgn:1000004",
        "tgn:7000198",
        "tgn:1001894",
        "tgn:7029392"
    ],
    "tgn:id":7547812,
    "tgn:name:en":"Bhains\u0101na",
    "tgn:placetype":[
        "aat:300008347"
    ]
},
  "bbox": [],
  "geometry": {"coordinates":[76.890367,23.763065],"type":"Point"}
}