{
  "id": 7068189,
  "type": "Feature",
  "properties": {
    "tgn:hierarchy":[
        "tgn:7068189",
        "tgn:1000003",
        "tgn:7003677",
        "tgn:7000084",
        "tgn:7029392"
    ],
    "tgn:id":7068189,
    "tgn:name":"Treuen-Bach",
    "tgn:placetype":[
        "aat:300008699"
    ]
},
  "bbox": [],
  "geometry": {"coordinates":[6.833333,50.583333],"type":"Point"}
}