{
  "id": 2142001,
  "type": "Feature",
  "properties": {
    "tgn:hierarchy":[
        "tgn:2142001",
        "tgn:1000001",
        "tgn:2001629",
        "tgn:7012149",
        "tgn:7007707",
        "tgn:7029392"
    ],
    "tgn:id":2142001,
    "tgn:name":"Bachelor Springs",
    "tgn:placetype":[
        "aat:300008697"
    ]
},
  "bbox": [],
  "geometry": {"coordinates":[-96.1667,34.15],"type":"Point"}
}