<<<<<<< HEAD
{
  "id": 7475693,
  "type": "Feature",
  "properties": {
    "tgn:hierarchy":[
        "tgn:7475693",
        "tgn:7487020",
        "tgn:1000004",
        "tgn:1000141",
        "tgn:7029392"
    ],
    "tgn:id":7475693,
    "tgn:name":"Tiancuo",
    "tgn:placetype":[
        "aat:300008347"
    ]
},
  "bbox": [],
  "geometry": {"coordinates":[120.774478,24.60606],"type":"Point"}
}
=======
{"geometry":{"type":"Point","coordinates":[120.774478,24.606060]},"type":"Feature","properties":{"hierarchy":["tgn:7475693","tgn:7487020","tgn:1000004","tgn:1000141","tgn:7029392"],"placetype":["aat:300008347"],"id":7475693,"name:xx":"Tiancuo"}}
>>>>>>> 03f74aca74312dbeaf24d7e61306dd6a786dc3d0
