{
  "id": 7475693,
  "type": "Feature",
  "properties": {
    "tgn:hierarchy":[
        "tgn:7475693",
        "tgn:7487020",
        "tgn:1000004",
        "tgn:1000141",
        "tgn:7029392"
    ],
    "tgn:id":7475693,
    "tgn:name":"Tiancuo",
    "tgn:placetype":[
        "aat:300008347"
    ]
},
  "bbox": [],
  "geometry": {"coordinates":[120.774478,24.60606],"type":"Point"}
}