{
  "id": 2154903,
  "type": "Feature",
  "properties": {
    "tgn:hierarchy":[
        "tgn:2154903",
        "tgn:1000001",
        "tgn:7012149",
        "tgn:2002126",
        "tgn:7007827",
        "tgn:7029392"
    ],
    "tgn:id":2154903,
    "tgn:name":"Bear Hollow",
    "tgn:placetype":[
        "aat:300008761"
    ]
},
  "bbox": [],
  "geometry": {"coordinates":[-110.95,40.15],"type":"Point"}
}