<<<<<<< HEAD
{
  "id": 2154903,
  "type": "Feature",
  "properties": {
    "tgn:hierarchy":[
        "tgn:2154903",
        "tgn:1000001",
        "tgn:7012149",
        "tgn:2002126",
        "tgn:7007827",
        "tgn:7029392"
    ],
    "tgn:id":2154903,
    "tgn:name":"Bear Hollow",
    "tgn:placetype":[
        "aat:300008761"
    ]
},
  "bbox": [],
  "geometry": {"coordinates":[-110.95,40.15],"type":"Point"}
}
=======
{"geometry":{"type":"Point","coordinates":[-110.950000,40.150000]},"type":"Feature","properties":{"hierarchy":["tgn:2154903","tgn:1000001","tgn:7012149","tgn:2002126","tgn:7007827","tgn:7029392"],"placetype":["aat:300008761"],"id":2154903,"name:xx":"Bear Hollow"}}
>>>>>>> 03f74aca74312dbeaf24d7e61306dd6a786dc3d0
