{
  "id": 2641827,
  "type": "Feature",
  "properties": {
    "tgn:hierarchy":[
        "tgn:2641827",
        "tgn:2002240",
        "tgn:1000001",
        "tgn:7012149",
        "tgn:7007920",
        "tgn:7029392"
    ],
    "tgn:id":2641827,
    "tgn:name":"Sand Island",
    "tgn:placetype":[
        "aat:300008791"
    ]
},
  "bbox": [],
  "geometry": {"coordinates":[-119.6333,45.8833],"type":"Point"}
}