{
  "id": 7442827,
  "type": "Feature",
  "properties": {
    "tgn:hierarchy":[
        "tgn:7442827",
        "tgn:7002445",
        "tgn:1000003",
        "tgn:7012077",
        "tgn:7008591",
        "tgn:7029392"
    ],
    "tgn:id":7442827,
    "tgn:name:en":"Hilsea Point Rock",
    "tgn:placetype":[
        "aat:300008808"
    ]
},
  "bbox": [],
  "geometry": {"coordinates":[-4.041667,50.291667],"type":"Point"}
}