{
  "id": 2087078,
  "type": "Feature",
  "properties": {
    "tgn:hierarchy":[
        "tgn:2087078",
        "tgn:1000001",
        "tgn:1002294",
        "tgn:7012149",
        "tgn:7007710",
        "tgn:7029392"
    ],
    "tgn:id":2087078,
    "tgn:name":"Central",
    "tgn:placetype":[
        "aat:300008347"
    ]
},
  "bbox": [],
  "geometry": {"coordinates":[-76.3667,41.2833],"type":"Point"}
}