{
  "id": 2540693,
  "type": "Feature",
  "properties": {
    "tgn:hierarchy":[
        "tgn:2540693",
        "tgn:1000001",
        "tgn:7012149",
        "tgn:2001255",
        "tgn:7007523",
        "tgn:7029392"
    ],
    "tgn:id":2540693,
    "tgn:name":"Newtown Hollow",
    "tgn:placetype":[
        "aat:300008761"
    ]
},
  "bbox": [],
  "geometry": {"coordinates":[-90.6833,37.0667],"type":"Point"}
}