{
  "id": 7589083,
  "type": "Feature",
  "properties": {
    "tgn:hierarchy":[
        "tgn:7589083",
        "tgn:1000004",
        "tgn:7000198",
        "tgn:7000799",
        "tgn:7029392"
    ],
    "tgn:id":7589083,
    "tgn:name:en":"Parhuti",
    "tgn:placetype":[
        "aat:300008347"
    ]
},
  "bbox": [],
  "geometry": {"coordinates":[74.199254,33.484085],"type":"Point"}
}