{
  "id": 2221444,
  "type": "Feature",
  "properties": {
    "tgn:hierarchy":[
        "tgn:2221444",
        "tgn:1000001",
        "tgn:7012149",
        "tgn:2000182",
        "tgn:7007157",
        "tgn:7029392"
    ],
    "tgn:id":2221444,
    "tgn:name":"Cargo Mine",
    "tgn:placetype":[
        "aat:300000390"
    ]
},
  "bbox": [],
  "geometry": {"coordinates":[-114.7667,32.8333],"type":"Point"}
}