{
  "id": 7279118,
  "type": "Feature",
  "properties": {
    "tgn:hierarchy":[
        "tgn:7279118",
        "tgn:1001702",
        "tgn:1000049",
        "tgn:1000002",
        "tgn:7029392"
    ],
    "tgn:id":7279118,
    "tgn:name":"Rous, Pen\u00ednsula",
    "tgn:placetype":[
        "aat:300008804"
    ]
},
  "bbox": [],
  "geometry": {"coordinates":[-69.416667,-55.333333],"type":"Point"}
}