{
  "id": 2700450,
  "type": "Feature",
  "properties": {
    "tgn:hierarchy":[
        "tgn:2700450",
        "tgn:1000001",
        "tgn:7012149",
        "tgn:2002118",
        "tgn:7007827",
        "tgn:7029392"
    ],
    "tgn:id":2700450,
    "tgn:name":"Success Estates",
    "tgn:placetype":[
        "aat:300008347"
    ]
},
  "bbox": [],
  "geometry": {"coordinates":[-111.8333,40.5333],"type":"Point"}
}