{
  "id": 2485503,
  "type": "Feature",
  "properties": {
    "tgn:hierarchy":[
        "tgn:2485503",
        "tgn:2001731",
        "tgn:1000001",
        "tgn:7012149",
        "tgn:7007712",
        "tgn:7029392"
    ],
    "tgn:id":2485503,
    "tgn:name":"Lawton",
    "tgn:placetype":[
        "aat:300008347"
    ]
},
  "bbox": [],
  "geometry": {"coordinates":[-80.7833,32.1333],"type":"Point"}
}