{
  "id": 7107583,
  "type": "Feature",
  "properties": {
    "tgn:hierarchy":[
        "tgn:7107583",
        "tgn:1000003",
        "tgn:7003678",
        "tgn:7000084",
        "tgn:7029392"
    ],
    "tgn:id":7107583,
    "tgn:name":"Raues Heil",
    "tgn:placetype":[
        "aat:300008777"
    ]
},
  "bbox": [],
  "geometry": {"coordinates":[9.233333,50.166667],"type":"Point"}
}