{
  "id": 2397698,
  "type": "Feature",
  "properties": {
    "tgn:hierarchy":[
        "tgn:2397698",
        "tgn:1000001",
        "tgn:7012149",
        "tgn:1002518",
        "tgn:7007568",
        "tgn:7029392"
    ],
    "tgn:id":2397698,
    "tgn:name":"Honeyville",
    "tgn:placetype":[
        "aat:300008347"
    ]
},
  "bbox": [],
  "geometry": {"coordinates":[-75.9667,43.85],"type":"Point"}
}