{
  "id": 7420053,
  "type": "Feature",
  "properties": {
    "tgn:hierarchy":[
        "tgn:7420053",
        "tgn:7005584",
        "tgn:1000001",
        "tgn:7005560",
        "tgn:7029392"
    ],
    "tgn:id":7420053,
    "tgn:name":"Puerto de Palmas",
    "tgn:placetype":[
        "aat:300008347"
    ]
},
  "bbox": [],
  "geometry": {"coordinates":[-100.109167,21.419444],"type":"Point"}
}