{
  "id": 2305385,
  "type": "Feature",
  "properties": {
    "tgn:hierarchy":[
        "tgn:2305385",
        "tgn:1000001",
        "tgn:7012149",
        "tgn:2002383",
        "tgn:7007923",
        "tgn:7029392"
    ],
    "tgn:id":2305385,
    "tgn:name":"East Branch Willow Creek",
    "tgn:placetype":[
        "aat:300008706"
    ]
},
  "bbox": [],
  "geometry": {"coordinates":[-107.9833,41.25],"type":"Point"}
}