{
  "id": 2309130,
  "type": "Feature",
  "properties": {
    "tgn:hierarchy":[
        "tgn:2309130",
        "tgn:1000001",
        "tgn:7012149",
        "tgn:2001930",
        "tgn:7007825",
        "tgn:7029392"
    ],
    "tgn:id":2309130,
    "tgn:name":"East Seward Hills Branch",
    "tgn:placetype":[
        "aat:300008699"
    ]
},
  "bbox": [],
  "geometry": {"coordinates":[-86.7833,35.9333],"type":"Point"}
}