<<<<<<< HEAD
{
  "id": 2334239,
  "type": "Feature",
  "properties": {
    "tgn:hierarchy":[
        "tgn:2334239",
        "tgn:1000001",
        "tgn:7012149",
        "tgn:2001289",
        "tgn:7007524",
        "tgn:7029392"
    ],
    "tgn:id":2334239,
    "tgn:name":"Forest Creek",
    "tgn:placetype":[
        "aat:300008706"
    ]
},
  "bbox": [],
  "geometry": {"coordinates":[-110.45,46.2333],"type":"Point"}
}
=======
{"geometry":{"type":"Point","coordinates":[-110.450000,46.233300]},"type":"Feature","properties":{"hierarchy":["tgn:2334239","tgn:1000001","tgn:7012149","tgn:2001289","tgn:7007524","tgn:7029392"],"placetype":["aat:300008706"],"id":2334239,"name:xx":"Forest Creek"}}
>>>>>>> 03f74aca74312dbeaf24d7e61306dd6a786dc3d0
