{
  "id": 2268943,
  "type": "Feature",
  "properties": {
    "tgn:hierarchy":[
        "tgn:2268943",
        "tgn:1000001",
        "tgn:7012149",
        "tgn:2001527",
        "tgn:7007709",
        "tgn:7029392"
    ],
    "tgn:id":2268943,
    "tgn:name":"Cross Way Island",
    "tgn:placetype":[
        "aat:300008791"
    ]
},
  "bbox": [],
  "geometry": {"coordinates":[-78.0667,34.3667],"type":"Point"}
}