{
  "id": 2514124,
  "type": "Feature",
  "properties": {
    "tgn:hierarchy":[
        "tgn:2514124",
        "tgn:1000001",
        "tgn:7012149",
        "tgn:2000917",
        "tgn:7007256",
        "tgn:7029392"
    ],
    "tgn:id":2514124,
    "tgn:name":"Miller Branch",
    "tgn:placetype":[
        "aat:300008699"
    ]
},
  "bbox": [],
  "geometry": {"coordinates":[-92.5667,31.9833],"type":"Point"}
}