{
  "id": 7354358,
  "type": "Feature",
  "properties": {
    "tgn:hierarchy":[
        "tgn:7354358",
        "tgn:1000001",
        "tgn:7005599",
        "tgn:7005560",
        "tgn:7029392"
    ],
    "tgn:id":7354358,
    "tgn:name":"Chuilapan",
    "tgn:placetype":[
        "aat:300008347"
    ]
},
  "bbox": [],
  "geometry": {"coordinates":[-95.283333,18.366667],"type":"Point"}
}