{
  "id": 7489334,
  "type": "Feature",
  "properties": {
    "tgn:hierarchy":[
        "tgn:7489334",
        "tgn:1000004",
        "tgn:7467799",
        "tgn:1000141",
        "tgn:7029392"
    ],
    "tgn:id":7489334,
    "tgn:name":"Renli Cun",
    "tgn:placetype":[
        "aat:300387173"
    ]
},
  "bbox": [],
  "geometry": {"coordinates":[120.536839,23.931866],"type":"Point"}
}