{
  "id": 7553110,
  "type": "Feature",
  "properties": {
    "tgn:hierarchy":[
        "tgn:7553110",
        "tgn:1000004",
        "tgn:1001869",
        "tgn:7000198",
        "tgn:7029392"
    ],
    "tgn:id":7553110,
    "tgn:name:en":"Nazarbagh",
    "tgn:placetype":[
        "aat:300007783"
    ]
},
  "bbox": [],
  "geometry": {"coordinates":[70.833333,22.816667],"type":"Point"}
}