{
  "id": 2640006,
  "type": "Feature",
  "properties": {
    "tgn:hierarchy":[
        "tgn:2640006",
        "tgn:1000001",
        "tgn:7012149",
        "tgn:7016021",
        "tgn:7007568",
        "tgn:7029392"
    ],
    "tgn:id":2640006,
    "tgn:name":"Sampson Pond Outlet",
    "tgn:placetype":[
        "aat:300008699"
    ]
},
  "bbox": [],
  "geometry": {"coordinates":[-74.75,44.2667],"type":"Point"}
}