{
  "id": 7366604,
  "type": "Feature",
  "properties": {
    "tgn:hierarchy":[
        "tgn:7366604",
        "tgn:1001853",
        "tgn:1000001",
        "tgn:7005560",
        "tgn:7029392"
    ],
    "tgn:id":7366604,
    "tgn:name":"El Reventado",
    "tgn:placetype":[
        "aat:300006191"
    ]
},
  "bbox": [],
  "geometry": {"coordinates":[-100.133333,27.983333],"type":"Point"}
}