{
  "id": 1016393,
  "type": "Feature",
  "properties": {
    "tgn:hierarchy":[
        "tgn:1016393",
        "tgn:1001374",
        "tgn:1000001",
        "tgn:7004624",
        "tgn:7029392"
    ],
    "tgn:id":1016393,
    "tgn:name":"Melena del Sur",
    "tgn:placetype":[
        "aat:300008347"
    ]
},
  "bbox": [],
  "geometry": {"coordinates":[-82.15,22.7833],"type":"Point"}
}