{
  "id": 7227851,
  "type": "Feature",
  "properties": {
    "tgn:hierarchy":[
        "tgn:7227851",
        "tgn:7002692",
        "tgn:7012056",
        "tgn:1000003",
        "tgn:1000074",
        "tgn:7029392"
    ],
    "tgn:id":7227851,
    "tgn:name":"Lith\u00ednai",
    "tgn:placetype":[
        "aat:300008347"
    ]
},
  "bbox": [],
  "geometry": {"coordinates":[26.05,35.083333],"type":"Point"}
}