{
  "id": 7430342,
  "type": "Feature",
  "properties": {
    "tgn:hierarchy":[
        "tgn:7430342",
        "tgn:7005583",
        "tgn:1000001",
        "tgn:7005560",
        "tgn:7029392"
    ],
    "tgn:id":7430342,
    "tgn:name":"Presa Francisco Zarco",
    "tgn:placetype":[
        "aat:300006191"
    ]
},
  "bbox": [],
  "geometry": {"coordinates":[-103.833333,25.283333],"type":"Point"}
}