{
  "id": 2384800,
  "type": "Feature",
  "properties": {
    "tgn:hierarchy":[
        "tgn:2384800",
        "tgn:1000001",
        "tgn:7012149",
        "tgn:2000491",
        "tgn:7007250",
        "tgn:7029392"
    ],
    "tgn:id":2384800,
    "tgn:name":"Hells Gulch",
    "tgn:placetype":[
        "aat:300008761"
    ]
},
  "bbox": [],
  "geometry": {"coordinates":[-116.0167,47.8333],"type":"Point"}
}