{
  "id": 1072581,
  "type": "Feature",
  "properties": {
    "tgn:hierarchy":[
        "tgn:1072581",
        "tgn:1000004",
        "tgn:7002079",
        "tgn:1000111",
        "tgn:7029392"
    ],
    "tgn:id":1072581,
    "tgn:name":"Wenmingsi",
    "tgn:placetype":[
        "aat:300008347"
    ]
},
  "bbox": [],
  "geometry": {"coordinates":[113.3333,25.55],"type":"Point"}
}