{
  "id": 2373216,
  "type": "Feature",
  "properties": {
    "tgn:hierarchy":[
        "tgn:2373216",
        "tgn:2002130",
        "tgn:1000001",
        "tgn:7012149",
        "tgn:7007828",
        "tgn:7029392"
    ],
    "tgn:id":2373216,
    "tgn:name":"Halnon Brook",
    "tgn:placetype":[
        "aat:300008699"
    ]
},
  "bbox": [],
  "geometry": {"coordinates":[-73.05,43.95],"type":"Point"}
}