{
  "id": 2574232,
  "type": "Feature",
  "properties": {
    "tgn:hierarchy":[
        "tgn:2574232",
        "tgn:1000001",
        "tgn:7012149",
        "tgn:1002582",
        "tgn:7007240",
        "tgn:7029392"
    ],
    "tgn:id":2574232,
    "tgn:name":"Pejuan Point",
    "tgn:placetype":[
        "aat:300008850"
    ]
},
  "bbox": [],
  "geometry": {"coordinates":[-82.2167,26.6167],"type":"Point"}
}