{
  "id": 7150668,
  "type": "Feature",
  "properties": {
    "tgn:hierarchy":[
        "tgn:7150668",
        "tgn:1000003",
        "tgn:7003687",
        "tgn:7000084",
        "tgn:7029392"
    ],
    "tgn:id":7150668,
    "tgn:name":"Kuh-Berg",
    "tgn:placetype":[
        "aat:300008777"
    ]
},
  "bbox": [],
  "geometry": {"coordinates":[11.233333,51.616667],"type":"Point"}
}