{
  "id": 7411067,
  "type": "Feature",
  "properties": {
    "tgn:hierarchy":[
        "tgn:7411067",
        "tgn:1000001",
        "tgn:7005598",
        "tgn:7005560",
        "tgn:7029392"
    ],
    "tgn:id":7411067,
    "tgn:name":"La Rosa",
    "tgn:placetype":[
        "aat:300008347"
    ]
},
  "bbox": [],
  "geometry": {"coordinates":[-98.009722,19.591667],"type":"Point"}
}