{
  "id": 1015504,
  "type": "Feature",
  "properties": {
    "tgn:hierarchy":[
        "tgn:1015504",
        "tgn:7005685",
        "tgn:1000001",
        "tgn:7005804",
        "tgn:7029392"
    ],
    "tgn:id":1015504,
    "tgn:name":"Matap\u00e9dia",
    "tgn:placetype":[
        "aat:300008347"
    ]
},
  "bbox": [],
  "geometry": {"coordinates":[-66.9667,47.9833],"type":"Point"}
}