{
  "id": 2039104,
  "type": "Feature",
  "properties": {
    "tgn:hierarchy":[
        "tgn:2039104",
        "tgn:1000001",
        "tgn:7012149",
        "tgn:2000839",
        "tgn:7007255",
        "tgn:7029392"
    ],
    "tgn:id":2039104,
    "tgn:name":"Goochtown",
    "tgn:placetype":[
        "aat:300008347",
        "aat:300387210"
    ]
},
  "bbox": [],
  "geometry": {"coordinates":[-84.5833,37.3167],"type":"Point"}
}