<<<<<<< HEAD
{
  "id": 2338220,
  "type": "Feature",
  "properties": {
    "tgn:hierarchy":[
        "tgn:2338220",
        "tgn:1000001",
        "tgn:1002318",
        "tgn:7012149",
        "tgn:7007710",
        "tgn:7029392"
    ],
    "tgn:id":2338220,
    "tgn:name":"Fox Ridge Court",
    "tgn:placetype":[
        "aat:300008347"
    ]
},
  "bbox": [],
  "geometry": {"coordinates":[-76.8833,40.2667],"type":"Point"}
}
=======
{"geometry":{"type":"Point","coordinates":[-76.883300,40.266700]},"type":"Feature","properties":{"hierarchy":["tgn:2338220","tgn:1000001","tgn:1002318","tgn:7012149","tgn:7007710","tgn:7029392"],"placetype":["aat:300008347"],"id":2338220,"name:xx":"Fox Ridge Court"}}
>>>>>>> 03f74aca74312dbeaf24d7e61306dd6a786dc3d0
