{
  "id": 2746517,
  "type": "Feature",
  "properties": {
    "tgn:hierarchy":[
        "tgn:2746517",
        "tgn:1000001",
        "tgn:7012149",
        "tgn:7014589",
        "tgn:7007515",
        "tgn:7029392"
    ],
    "tgn:id":2746517,
    "tgn:name":"Wabassus Lake",
    "tgn:placetype":[
        "aat:300008680"
    ]
},
  "bbox": [],
  "geometry": {"coordinates":[-67.8833,45.15],"type":"Point"}
}