{
  "id": 2314675,
  "type": "Feature",
  "properties": {
    "tgn:hierarchy":[
        "tgn:2314675",
        "tgn:1000001",
        "tgn:7012149",
        "tgn:2002291",
        "tgn:7013961",
        "tgn:7029392"
    ],
    "tgn:id":2314675,
    "tgn:name":"Elk Run",
    "tgn:placetype":[
        "aat:300008699"
    ]
},
  "bbox": [],
  "geometry": {"coordinates":[-79.65,38.6833],"type":"Point"}
}