{
  "id": 7395783,
  "type": "Feature",
  "properties": {
    "tgn:hierarchy":[
        "tgn:7395783",
        "tgn:1000001",
        "tgn:7005595",
        "tgn:7005560",
        "tgn:7029392"
    ],
    "tgn:id":7395783,
    "tgn:name":"San Antonio",
    "tgn:placetype":[
        "aat:300008347"
    ]
},
  "bbox": [],
  "geometry": {"coordinates":[-107.266667,25.016667],"type":"Point"}
}