<<<<<<< HEAD
{
  "id": 7485195,
  "type": "Feature",
  "properties": {
    "tgn:hierarchy":[
        "tgn:7485195",
        "tgn:1000004",
        "tgn:7491221",
        "tgn:1000141",
        "tgn:7029392"
    ],
    "tgn:id":7485195,
    "tgn:name":"Fushan Chezhan",
    "tgn:placetype":[
        "aat:300007783"
    ]
},
  "bbox": [],
  "geometry": {"coordinates":[120.933056,22.428333],"type":"Point"}
}
=======
{"geometry":{"type":"Point","coordinates":[120.933056,22.428333]},"type":"Feature","properties":{"hierarchy":["tgn:7485195","tgn:1000004","tgn:7491221","tgn:1000141","tgn:7029392"],"placetype":["aat:300007783"],"id":7485195,"name:xx":"Fushan Chezhan"}}
>>>>>>> 03f74aca74312dbeaf24d7e61306dd6a786dc3d0
