{
  "id": 7485195,
  "type": "Feature",
  "properties": {
    "tgn:hierarchy":[
        "tgn:7485195",
        "tgn:1000004",
        "tgn:7491221",
        "tgn:1000141",
        "tgn:7029392"
    ],
    "tgn:id":7485195,
    "tgn:name":"Fushan Chezhan",
    "tgn:placetype":[
        "aat:300007783"
    ]
},
  "bbox": [],
  "geometry": {"coordinates":[120.933056,22.428333],"type":"Point"}
}