{
  "id": 2735008,
  "type": "Feature",
  "properties": {
    "tgn:hierarchy":[
        "tgn:2735008",
        "tgn:1000001",
        "tgn:2001413",
        "tgn:7012149",
        "tgn:7007526",
        "tgn:7029392"
    ],
    "tgn:id":2735008,
    "tgn:name":"Twenty Seven Spring",
    "tgn:placetype":[
        "aat:300008697"
    ]
},
  "bbox": [],
  "geometry": {"coordinates":[-116.4167,40.25],"type":"Point"}
}