{
  "id": 7505141,
  "type": "Feature",
  "properties": {
    "tgn:hierarchy":[
        "tgn:7505141",
        "tgn:1009227",
        "tgn:1000226",
        "tgn:7016822",
        "tgn:1000006",
        "tgn:7029392"
    ],
    "tgn:id":7505141,
    "tgn:name:en":"Lookout Bay",
    "tgn:placetype":[
        "aat:300132317"
    ]
},
  "bbox": [],
  "geometry": {"coordinates":[169.158056,-52.545],"type":"Point"}
}