{
  "id": 7543420,
  "type": "Feature",
  "properties": {
    "tgn:hierarchy":[
        "tgn:7543420",
        "tgn:7001242",
        "tgn:7016833",
        "tgn:7001335",
        "tgn:7029392"
    ],
    "tgn:id":7543420,
    "tgn:name:en":"Kissufim Crossing",
    "tgn:placetype":[
        "aat:300008217"
    ]
},
  "bbox": [],
  "geometry": {"coordinates":[34.382778,31.371111],"type":"Point"}
}