{
  "id": 2628587,
  "type": "Feature",
  "properties": {
    "tgn:hierarchy":[
        "tgn:2628587",
        "tgn:1000001",
        "tgn:7012149",
        "tgn:7018871",
        "tgn:7007920",
        "tgn:7029392"
    ],
    "tgn:id":2628587,
    "tgn:name":"Rooster Comb Mountain",
    "tgn:placetype":[
        "aat:300008798"
    ]
},
  "bbox": [],
  "geometry": {"coordinates":[-121.5667,47.2333],"type":"Point"}
}