{
  "id": 7375027,
  "type": "Feature",
  "properties": {
    "tgn:hierarchy":[
        "tgn:7375027",
        "tgn:1001853",
        "tgn:1000001",
        "tgn:7005560",
        "tgn:7029392"
    ],
    "tgn:id":7375027,
    "tgn:name":"La Botica",
    "tgn:placetype":[
        "aat:300008347"
    ]
},
  "bbox": [],
  "geometry": {"coordinates":[-102.933333,26.466667],"type":"Point"}
}