{
  "id": 7523717,
  "type": "Feature",
  "properties": {
    "tgn:hierarchy":[
        "tgn:7523717",
        "tgn:7001242",
        "tgn:7016833",
        "tgn:7001336",
        "tgn:7029392"
    ],
    "tgn:id":7523717,
    "tgn:name:en":"El-Hamm\u00e1",
    "tgn:placetype":[
        "aat:300006207"
    ]
},
  "bbox": [],
  "geometry": {"coordinates":[33.316667,29.283333],"type":"Point"}
}