<<<<<<< HEAD
{
  "id": 2254323,
  "type": "Feature",
  "properties": {
    "tgn:hierarchy":[
        "tgn:2254323",
        "tgn:1000001",
        "tgn:7012149",
        "tgn:2000494",
        "tgn:7007250",
        "tgn:7029392"
    ],
    "tgn:id":2254323,
    "tgn:name":"Coon Creek",
    "tgn:placetype":[
        "aat:300008706"
    ]
},
  "bbox": [],
  "geometry": {"coordinates":[-115.15,44.9333],"type":"Point"}
}
=======
{"geometry":{"type":"Point","coordinates":[-115.150000,44.933300]},"type":"Feature","properties":{"hierarchy":["tgn:2254323","tgn:1000001","tgn:7012149","tgn:2000494","tgn:7007250","tgn:7029392"],"placetype":["aat:300008706"],"id":2254323,"name:xx":"Coon Creek"}}
>>>>>>> 03f74aca74312dbeaf24d7e61306dd6a786dc3d0
