{
  "id": 7013463,
  "type": "Feature",
  "properties": {
    "tgn:hierarchy":[
        "tgn:7013463",
        "tgn:1000001",
        "tgn:7012149",
        "tgn:1002356",
        "tgn:7007568",
        "tgn:7029392"
    ],
    "tgn:id":7013463,
    "tgn:name":"Buffalo",
    "tgn:placetype":[
        "aat:300008347",
        "aat:300008416",
        "aat:300008389",
        "aat:300387270",
        "aat:300387302",
        "aat:300120599",
        "aat:300387288",
        "aat:300387296"
    ]
},
  "bbox": [],
  "geometry": {"coordinates":[-78.8667,42.8833],"type":"Point"}
}