{
  "id": 2015634,
  "type": "Feature",
  "properties": {
    "tgn:hierarchy":[
        "tgn:2015634",
        "tgn:1000001",
        "tgn:7012149",
        "tgn:2000230",
        "tgn:7007158",
        "tgn:7029392"
    ],
    "tgn:id":2015634,
    "tgn:name":"Fruitvale",
    "tgn:placetype":[
        "aat:300008347"
    ]
},
  "bbox": [],
  "geometry": {"coordinates":[-108.4833,39.0667],"type":"Point"}
}