{
  "id": 7195244,
  "type": "Feature",
  "properties": {
    "tgn:hierarchy":[
        "tgn:7195244",
        "tgn:7003669",
        "tgn:1000003",
        "tgn:7000084",
        "tgn:7029392"
    ],
    "tgn:id":7195244,
    "tgn:name":"Deisenhofen",
    "tgn:placetype":[
        "aat:300008347"
    ]
},
  "bbox": [],
  "geometry": {"coordinates":[10.533333,48.616667],"type":"Point"}
}