{
  "id": 7300153,
  "type": "Feature",
  "properties": {
    "tgn:hierarchy":[
        "tgn:7300153",
        "tgn:7001122",
        "tgn:1000003",
        "tgn:7002765",
        "tgn:1000095",
        "tgn:7029392"
    ],
    "tgn:id":7300153,
    "tgn:name":"Tuent, Cala",
    "tgn:placetype":[
        "aat:300132317"
    ]
},
  "bbox": [],
  "geometry": {"coordinates":[2.766667,39.85],"type":"Point"}
}