{
  "id": 7571942,
  "type": "Feature",
  "properties": {
    "tgn:hierarchy":[
        "tgn:7571942",
        "tgn:1000004",
        "tgn:1001832",
        "tgn:7000198",
        "tgn:7029392"
    ],
    "tgn:id":7571942,
    "tgn:name:en":"Jelkarjh\u0101r",
    "tgn:placetype":[
        "aat:300008347"
    ]
},
  "bbox": [],
  "geometry": {"coordinates":[90.524888,26.458358],"type":"Point"}
}