{
  "id": 2678721,
  "type": "Feature",
  "properties": {
    "tgn:hierarchy":[
        "tgn:2678721",
        "tgn:1000001",
        "tgn:7012149",
        "tgn:2002381",
        "tgn:7007923",
        "tgn:7029392"
    ],
    "tgn:id":2678721,
    "tgn:name":"South Fork Earley Creek",
    "tgn:placetype":[
        "aat:300008706"
    ]
},
  "bbox": [],
  "geometry": {"coordinates":[-107.1667,44.95],"type":"Point"}
}