{
  "id": 7161680,
  "type": "Feature",
  "properties": {
    "tgn:hierarchy":[
        "tgn:7161680",
        "tgn:7003669",
        "tgn:1000003",
        "tgn:7000084",
        "tgn:7029392"
    ],
    "tgn:id":7161680,
    "tgn:name":"Hohenzeller Forst",
    "tgn:placetype":[
        "aat:300008863"
    ]
},
  "bbox": [],
  "geometry": {"coordinates":[11.216667,48.35],"type":"Point"}
}