{
  "id": 2500410,
  "type": "Feature",
  "properties": {
    "tgn:hierarchy":[
        "tgn:2500410",
        "tgn:1000001",
        "tgn:1002216",
        "tgn:7012149",
        "tgn:7007706",
        "tgn:7029392"
    ],
    "tgn:id":2500410,
    "tgn:name":"McDonald",
    "tgn:placetype":[
        "aat:300008347"
    ]
},
  "bbox": [],
  "geometry": {"coordinates":[-84.7667,39.5167],"type":"Point"}
}