{
  "id": 2432919,
  "type": "Feature",
  "properties": {
    "tgn:hierarchy":[
        "tgn:2432919",
        "tgn:1000001",
        "tgn:7012149",
        "tgn:2001543",
        "tgn:7007709",
        "tgn:7029392"
    ],
    "tgn:id":2432919,
    "tgn:name":"Keg Drive Branch",
    "tgn:placetype":[
        "aat:300008699"
    ]
},
  "bbox": [],
  "geometry": {"coordinates":[-83.45,35.5667],"type":"Point"}
}