{
  "id": 7235963,
  "type": "Feature",
  "properties": {
    "tgn:hierarchy":[
        "tgn:7235963",
        "tgn:7002752",
        "tgn:7001399",
        "tgn:1000003",
        "tgn:1000074",
        "tgn:7029392"
    ],
    "tgn:id":7235963,
    "tgn:name":"\u00c1gios Vissar\u00edon",
    "tgn:placetype":[
        "aat:300008347"
    ]
},
  "bbox": [],
  "geometry": {"coordinates":[21.618056,39.470278],"type":"Point"}
}