{
  "id": 7311668,
  "type": "Feature",
  "properties": {
    "tgn:hierarchy":[
        "tgn:7311668",
        "tgn:1001695",
        "tgn:1000049",
        "tgn:1000002",
        "tgn:7029392"
    ],
    "tgn:id":7311668,
    "tgn:name":"Las Pircas",
    "tgn:placetype":[
        "aat:300387200"
    ]
},
  "bbox": [],
  "geometry": {"coordinates":[-70.833333,-34.766667],"type":"Point"}
}