{
  "id": 2709978,
  "type": "Feature",
  "properties": {
    "tgn:hierarchy":[
        "tgn:2709978",
        "tgn:7006450",
        "tgn:1000001",
        "tgn:2124053",
        "tgn:7012149",
        "tgn:7029392"
    ],
    "tgn:id":2709978,
    "tgn:name":"Talachulitna Creek",
    "tgn:placetype":[
        "aat:300008706"
    ]
},
  "bbox": [],
  "geometry": {"coordinates":[-151.7333,61.6333],"type":"Point"}
}