{
  "id": 1086243,
  "type": "Feature",
  "properties": {
    "tgn:hierarchy":[
        "tgn:1086243",
        "tgn:1001511",
        "tgn:1000004",
        "tgn:7018453",
        "tgn:1000144",
        "tgn:7029392"
    ],
    "tgn:id":1086243,
    "tgn:name":"Bolucan",
    "tgn:placetype":[
        "aat:300008347"
    ]
},
  "bbox": [],
  "geometry": {"coordinates":[37.7333,39.7167],"type":"Point"}
}