{
  "id": 7487459,
  "type": "Feature",
  "properties": {
    "tgn:hierarchy":[
        "tgn:7487459",
        "tgn:1000004",
        "tgn:7492971",
        "tgn:1000141",
        "tgn:7029392"
    ],
    "tgn:id":7487459,
    "tgn:name":"Kengzinei",
    "tgn:placetype":[
        "aat:300008347"
    ]
},
  "bbox": [],
  "geometry": {"coordinates":[120.854444,21.916389],"type":"Point"}
}