{
  "id": 7309500,
  "type": "Feature",
  "properties": {
    "tgn:hierarchy":[
        "tgn:7309500",
        "tgn:1001702",
        "tgn:1000049",
        "tgn:1000002",
        "tgn:7029392"
    ],
    "tgn:id":7309500,
    "tgn:name":"Nuevo, R\u00edo",
    "tgn:placetype":[
        "aat:300008699"
    ]
},
  "bbox": [],
  "geometry": {"coordinates":[-69.433333,-53.35],"type":"Point"}
}