{
  "id": 2664726,
  "type": "Feature",
  "properties": {
    "tgn:hierarchy":[
        "tgn:2664726",
        "tgn:1000001",
        "tgn:7006451",
        "tgn:2000095",
        "tgn:7012149",
        "tgn:7029392"
    ],
    "tgn:id":2664726,
    "tgn:name":"Simmons Spring",
    "tgn:placetype":[
        "aat:300008697"
    ]
},
  "bbox": [],
  "geometry": {"coordinates":[-109.4667,33.3167],"type":"Point"}
}