{
  "id": 7564824,
  "type": "Feature",
  "properties": {
    "tgn:hierarchy":[
        "tgn:7564824",
        "tgn:1000004",
        "tgn:1001871",
        "tgn:7000198",
        "tgn:7029392"
    ],
    "tgn:id":7564824,
    "tgn:name:en":"Faradw\u0101li Johri",
    "tgn:placetype":[
        "aat:300008688"
    ]
},
  "bbox": [],
  "geometry": {"coordinates":[75.675666,28.536579],"type":"Point"}
}