{
  "id": 2149931,
  "type": "Feature",
  "properties": {
    "tgn:hierarchy":[
        "tgn:2149931",
        "tgn:1000001",
        "tgn:7012149",
        "tgn:2000224",
        "tgn:7007158",
        "tgn:7029392"
    ],
    "tgn:id":2149931,
    "tgn:name":"Bartlett Mountain",
    "tgn:placetype":[
        "aat:300008798"
    ]
},
  "bbox": [],
  "geometry": {"coordinates":[-106.15,39.3667],"type":"Point"}
}