{
  "id": 2197332,
  "type": "Feature",
  "properties": {
    "tgn:hierarchy":[
        "tgn:2197332",
        "tgn:1000001",
        "tgn:1003029",
        "tgn:7012149",
        "tgn:7007828",
        "tgn:7029392"
    ],
    "tgn:id":2197332,
    "tgn:name":"Brown Brook",
    "tgn:placetype":[
        "aat:300008699"
    ]
},
  "bbox": [],
  "geometry": {"coordinates":[-72.85,42.75],"type":"Point"}
}