{
  "id": 7588562,
  "type": "Feature",
  "properties": {
    "tgn:hierarchy":[
        "tgn:7588562",
        "tgn:1000004",
        "tgn:7000198",
        "tgn:7000799",
        "tgn:7029392"
    ],
    "tgn:id":7588562,
    "tgn:name:en":"W\u0101rasangham",
    "tgn:placetype":[
        "aat:300008347"
    ]
},
  "bbox": [],
  "geometry": {"coordinates":[74.698725,34.058491],"type":"Point"}
}