{
  "id": 7033410,
  "type": "Feature",
  "properties": {
    "tgn:hierarchy":[
        "tgn:7033410",
        "tgn:7003006",
        "tgn:1000003",
        "tgn:7002997",
        "tgn:1000080",
        "tgn:7029392"
    ],
    "tgn:id":7033410,
    "tgn:name":"Bagnara",
    "tgn:placetype":[
        "aat:300008347"
    ]
},
  "bbox": [],
  "geometry": {"coordinates":[12.851111,45.841667],"type":"Point"}
}