{
  "id": 2768182,
  "type": "Feature",
  "properties": {
    "tgn:hierarchy":[
        "tgn:2768182",
        "tgn:1000001",
        "tgn:7012149",
        "tgn:1002980",
        "tgn:7007826",
        "tgn:7029392"
    ],
    "tgn:id":2768182,
    "tgn:name":"Whites Creek",
    "tgn:placetype":[
        "aat:300008706"
    ]
},
  "bbox": [],
  "geometry": {"coordinates":[-95.5333,30.95],"type":"Point"}
}