{
  "id": 1063328,
  "type": "Feature",
  "properties": {
    "tgn:hierarchy":[
        "tgn:1063328",
        "tgn:1000003",
        "tgn:7024620",
        "tgn:1000097",
        "tgn:7029392"
    ],
    "tgn:id":1063328,
    "tgn:name":"Ljungskile",
    "tgn:placetype":[
        "aat:300008347"
    ]
},
  "bbox": [],
  "geometry": {"coordinates":[11.9167,58.2333],"type":"Point"}
}