{
  "id": 7274730,
  "type": "Feature",
  "properties": {
    "tgn:concordances":{
        "gn:id":"2744130"
    },
    "tgn:hierarchy":[
        "tgn:7274730",
        "tgn:7003614",
        "tgn:1000003",
        "tgn:7016845",
        "tgn:7029392"
    ],
    "tgn:id":7274730,
    "tgn:name:nl":"Yde",
    "tgn:placetype":[
        "aat:300008347"
    ]
},
  "bbox": [],
  "geometry": {"coordinates":[6.583333,53.116667],"type":"Point"}
}