{
  "id": 1095216,
  "type": "Feature",
  "properties": {
    "tgn:hierarchy":[
        "tgn:1095216",
        "tgn:7001242",
        "tgn:7016833",
        "tgn:1001335",
        "tgn:7029392"
    ],
    "tgn:id":1095216,
    "tgn:name":"Al \u1e24add\u0101d\u012b",
    "tgn:placetype":[
        "aat:300008347"
    ]
},
  "bbox": [],
  "geometry": {"coordinates":[30.789826,31.330311],"type":"Point"}
}