{
  "id": 7108932,
  "type": "Feature",
  "properties": {
    "tgn:hierarchy":[
        "tgn:7108932",
        "tgn:1000003",
        "tgn:7003676",
        "tgn:7000084",
        "tgn:7029392"
    ],
    "tgn:id":7108932,
    "tgn:name":"Reesseln",
    "tgn:placetype":[
        "aat:300008347"
    ]
},
  "bbox": [],
  "geometry": {"coordinates":[10.85,53.233333],"type":"Point"}
}