{
  "id": 1083862,
  "type": "Feature",
  "properties": {
    "tgn:hierarchy":[
        "tgn:1083862",
        "tgn:7000360",
        "tgn:1000004",
        "tgn:1000133",
        "tgn:7029392"
    ],
    "tgn:id":1083862,
    "tgn:name":"Yakmach",
    "tgn:placetype":[
        "aat:300008347"
    ]
},
  "bbox": [],
  "geometry": {"coordinates":[63.8333,28.7333],"type":"Point"}
}