{
  "id": 7258372,
  "type": "Feature",
  "properties": {
    "tgn:hierarchy":[
        "tgn:7258372",
        "tgn:1000003",
        "tgn:7003632",
        "tgn:7016845",
        "tgn:7029392"
    ],
    "tgn:id":7258372,
    "tgn:name:nl":"Adegeest",
    "tgn:placetype":[
        "aat:300000745"
    ]
},
  "bbox": [],
  "geometry": {"coordinates":[4.45,52.133333],"type":"Point"}
}