{
  "id": 1002276,
  "type": "Feature",
  "properties": {
    "tgn:hierarchy":[
        "tgn:1002276",
        "tgn:1000001",
        "tgn:7012149",
        "tgn:7007708",
        "tgn:7029392"
    ],
    "tgn:id":1002276,
    "tgn:name":"Clatsop",
    "tgn:placetype":[
        "aat:300387145",
        "aat:300000771"
    ]
},
  "bbox": [],
  "geometry": {"coordinates":[-123.6667,45.9667],"type":"Point"}
}