{
  "id": 2592873,
  "type": "Feature",
  "properties": {
    "tgn:hierarchy":[
        "tgn:2592873",
        "tgn:1000001",
        "tgn:7012149",
        "tgn:2000643",
        "tgn:7007253",
        "tgn:7029392"
    ],
    "tgn:id":2592873,
    "tgn:name":"Poplar",
    "tgn:placetype":[
        "aat:300008347"
    ]
},
  "bbox": [],
  "geometry": {"coordinates":[-95.0833,41.6833],"type":"Point"}
}