{
  "id": 7586083,
  "type": "Feature",
  "properties": {
    "tgn:hierarchy":[
        "tgn:7586083",
        "tgn:1000004",
        "tgn:7000198",
        "tgn:1001977",
        "tgn:7029392"
    ],
    "tgn:id":7586083,
    "tgn:name:en":"Sadd\u0101r\u0101t",
    "tgn:placetype":[
        "aat:300008347"
    ]
},
  "bbox": [],
  "geometry": {"coordinates":[88.419722,22.718056],"type":"Point"}
}