{
  "id": 2744029,
  "type": "Feature",
  "properties": {
    "tgn:hierarchy":[
        "tgn:2744029",
        "tgn:1000001",
        "tgn:7012149",
        "tgn:7007157",
        "tgn:1002684",
        "tgn:7029392"
    ],
    "tgn:id":2744029,
    "tgn:name":"Ventana Cone",
    "tgn:placetype":[
        "aat:300008798"
    ]
},
  "bbox": [],
  "geometry": {"coordinates":[-121.6667,36.2833],"type":"Point"}
}