{
  "id": 2602299,
  "type": "Feature",
  "properties": {
    "tgn:hierarchy":[
        "tgn:2602299",
        "tgn:7006450",
        "tgn:1000001",
        "tgn:7019698",
        "tgn:7012149",
        "tgn:7029392"
    ],
    "tgn:id":2602299,
    "tgn:name":"Pye Reef",
    "tgn:placetype":[
        "aat:300132348"
    ]
},
  "bbox": [],
  "geometry": {"coordinates":[-150.4167,59.3167],"type":"Point"}
}