<<<<<<< HEAD
{
  "id": 2405817,
  "type": "Feature",
  "properties": {
    "tgn:hierarchy":[
        "tgn:2405817",
        "tgn:1000001",
        "tgn:2000266",
        "tgn:7012149",
        "tgn:7007240",
        "tgn:7029392"
    ],
    "tgn:id":2405817,
    "tgn:name":"Hull Cypress Swamp",
    "tgn:placetype":[
        "aat:300008905"
    ]
},
  "bbox": [],
  "geometry": {"coordinates":[-81.2,29.2833],"type":"Point"}
}
=======
{"geometry":{"type":"Point","coordinates":[-81.200000,29.283300]},"type":"Feature","properties":{"hierarchy":["tgn:2405817","tgn:1000001","tgn:2000266","tgn:7012149","tgn:7007240","tgn:7029392"],"placetype":["aat:300008905"],"id":2405817,"name:xx":"Hull Cypress Swamp"}}
>>>>>>> 03f74aca74312dbeaf24d7e61306dd6a786dc3d0
