{
  "id": 2268411,
  "type": "Feature",
  "properties": {
    "tgn:hierarchy":[
        "tgn:2268411",
        "tgn:1000001",
        "tgn:7012149",
        "tgn:2002192",
        "tgn:7007919",
        "tgn:7029392"
    ],
    "tgn:id":2268411,
    "tgn:name":"Crooked Run",
    "tgn:placetype":[
        "aat:300008699"
    ]
},
  "bbox": [],
  "geometry": {"coordinates":[-81.3667,37.1167],"type":"Point"}
}