{
  "id": 2751505,
  "type": "Feature",
  "properties": {
    "tgn:hierarchy":[
        "tgn:2751505",
        "tgn:7002659",
        "tgn:1000001",
        "tgn:7012149",
        "tgn:2000038",
        "tgn:7029392"
    ],
    "tgn:id":2751505,
    "tgn:name":"Warmack Spring",
    "tgn:placetype":[
        "aat:300008697"
    ]
},
  "bbox": [],
  "geometry": {"coordinates":[-87.25,34.7833],"type":"Point"}
}