<<<<<<< HEAD
{
  "id": 7026846,
  "type": "Feature",
  "properties": {
    "tgn:hierarchy":[
        "tgn:7026846",
        "tgn:7002445",
        "tgn:1000003",
        "tgn:7008139",
        "tgn:7008591",
        "tgn:7029392"
    ],
    "tgn:id":7026846,
    "tgn:name:en":"Faccombe",
    "tgn:placetype":[
        "aat:300008347",
        "aat:300008372"
    ]
},
  "bbox": [],
  "geometry": {"coordinates":[-1.433333,51.316667],"type":"Point"}
}
=======
{"geometry":{"type":"Point","coordinates":[-1.433333,51.316667]},"type":"Feature","properties":{"hierarchy":["tgn:7026846","tgn:7002445","tgn:1000003","tgn:7008139","tgn:7008591","tgn:7029392"],"placetype":["aat:300008347","aat:300008372"],"name:en":"Faccombe","id":7026846}}
>>>>>>> 03f74aca74312dbeaf24d7e61306dd6a786dc3d0
