{
  "id": 7217621,
  "type": "Feature",
  "properties": {
    "tgn:hierarchy":[
        "tgn:7217621",
        "tgn:7011164",
        "tgn:7002674",
        "tgn:1000003",
        "tgn:1000074",
        "tgn:7029392"
    ],
    "tgn:id":7217621,
    "tgn:name":"Patni\u00f3ti, \u00d3rmos",
    "tgn:placetype":[
        "aat:300185707"
    ]
},
  "bbox": [],
  "geometry": {"coordinates":[26.614167,37.679167],"type":"Point"}
}