{
  "id": 7393422,
  "type": "Feature",
  "properties": {
    "tgn:hierarchy":[
        "tgn:7393422",
        "tgn:1001853",
        "tgn:1000001",
        "tgn:7005560",
        "tgn:7029392"
    ],
    "tgn:id":7393422,
    "tgn:name":"San Francisco",
    "tgn:placetype":[
        "aat:300008347"
    ]
},
  "bbox": [],
  "geometry": {"coordinates":[-102.566667,27.633333],"type":"Point"}
}