{
  "id": 7300514,
  "type": "Feature",
  "properties": {
    "tgn:hierarchy":[
        "tgn:7300514",
        "tgn:7002842",
        "tgn:7001158",
        "tgn:1000003",
        "tgn:1000095",
        "tgn:7029392"
    ],
    "tgn:id":7300514,
    "tgn:name":"Tejado",
    "tgn:placetype":[
        "aat:300008347"
    ]
},
  "bbox": [],
  "geometry": {"coordinates":[-2.266667,41.583333],"type":"Point"}
}