{
  "id": 2186746,
  "type": "Feature",
  "properties": {
    "tgn:hierarchy":[
        "tgn:2186746",
        "tgn:1000001",
        "tgn:7012149",
        "tgn:2001287",
        "tgn:7007524",
        "tgn:7029392"
    ],
    "tgn:id":2186746,
    "tgn:name":"Bonin Springs",
    "tgn:placetype":[
        "aat:300008697"
    ]
},
  "bbox": [],
  "geometry": {"coordinates":[-106.1167,47.7333],"type":"Point"}
}