<<<<<<< HEAD
{
  "id": 2334759,
  "type": "Feature",
  "properties": {
    "tgn:hierarchy":[
        "tgn:2334759",
        "tgn:1000001",
        "tgn:7012149",
        "tgn:7007919",
        "tgn:7029392"
    ],
    "tgn:id":2334759,
    "tgn:name":"Fork Mountain",
    "tgn:placetype":[
        "aat:300008798"
    ]
},
  "bbox": [],
  "geometry": {"coordinates":[-80.0167,37.6333],"type":"Point"}
}
=======
{"geometry":{"type":"Point","coordinates":[-80.016700,37.633300]},"type":"Feature","properties":{"hierarchy":["tgn:2334759","tgn:1000001","tgn:7012149","tgn:7007919","tgn:7029392"],"placetype":["aat:300008798"],"id":2334759,"name:xx":"Fork Mountain"}}
>>>>>>> 03f74aca74312dbeaf24d7e61306dd6a786dc3d0
