{
  "id": 2145982,
  "type": "Feature",
  "properties": {
    "tgn:hierarchy":[
        "tgn:2145982",
        "tgn:1000001",
        "tgn:7016172",
        "tgn:7012149",
        "tgn:2000177",
        "tgn:7029392"
    ],
    "tgn:id":2145982,
    "tgn:name":"Ball Hollow",
    "tgn:placetype":[
        "aat:300008761"
    ]
},
  "bbox": [],
  "geometry": {"coordinates":[-91.9167,35.35],"type":"Point"}
}