{
  "id": 1081286,
  "type": "Feature",
  "properties": {
    "tgn:hierarchy":[
        "tgn:1081286",
        "tgn:1000975",
        "tgn:1000004",
        "tgn:7000901",
        "tgn:1000120",
        "tgn:7029392"
    ],
    "tgn:id":1081286,
    "tgn:name":"Shiida",
    "tgn:placetype":[
        "aat:300008347"
    ]
},
  "bbox": [],
  "geometry": {"coordinates":[131.0667,33.65],"type":"Point"}
}