{
  "id": 2313906,
  "type": "Feature",
  "properties": {
    "tgn:hierarchy":[
        "tgn:2313906",
        "tgn:1000001",
        "tgn:1002189",
        "tgn:7012149",
        "tgn:7007255",
        "tgn:7029392"
    ],
    "tgn:id":2313906,
    "tgn:name":"Elijahs Creek",
    "tgn:placetype":[
        "aat:300008706"
    ]
},
  "bbox": [],
  "geometry": {"coordinates":[-84.6333,39.05],"type":"Point"}
}