{
  "id": 7426507,
  "type": "Feature",
  "properties": {
    "tgn:hierarchy":[
        "tgn:7426507",
        "tgn:1000001",
        "tgn:7005594",
        "tgn:7005560",
        "tgn:7029392"
    ],
    "tgn:id":7426507,
    "tgn:name":"Ojo Caliente",
    "tgn:placetype":[
        "aat:300008347"
    ]
},
  "bbox": [],
  "geometry": {"coordinates":[-99.233333,21.65],"type":"Point"}
}