{
  "id": 2439139,
  "type": "Feature",
  "properties": {
    "tgn:hierarchy":[
        "tgn:2439139",
        "tgn:7023902",
        "tgn:1000001",
        "tgn:7012149",
        "tgn:7007249",
        "tgn:7029392"
    ],
    "tgn:id":2439139,
    "tgn:name":"Kipaepae",
    "tgn:placetype":[
        "aat:300055621"
    ]
},
  "bbox": [],
  "geometry": {"coordinates":[-155.5667,19.0333],"type":"Point"}
}