{
  "id": 2776466,
  "type": "Feature",
  "properties": {
    "tgn:hierarchy":[
        "tgn:2776466",
        "tgn:1000001",
        "tgn:7012149",
        "tgn:2002119",
        "tgn:7007827",
        "tgn:7029392"
    ],
    "tgn:id":2776466,
    "tgn:name":"Wind Whistle Draw",
    "tgn:placetype":[
        "aat:300008761"
    ]
},
  "bbox": [],
  "geometry": {"coordinates":[-109.45,38.1667],"type":"Point"}
}