{
  "id": 1025122,
  "type": "Feature",
  "properties": {
    "tgn:hierarchy":[
        "tgn:1025122",
        "tgn:1001866",
        "tgn:1000002",
        "tgn:1000059",
        "tgn:7029392"
    ],
    "tgn:id":1025122,
    "tgn:name":"El Rastro",
    "tgn:placetype":[
        "aat:300008347"
    ]
},
  "bbox": [],
  "geometry": {"coordinates":[-67.45,9.05],"type":"Point"}
}