{
  "id": 1093065,
  "type": "Feature",
  "properties": {
    "tgn:hierarchy":[
        "tgn:1093065",
        "tgn:7001242",
        "tgn:7017576",
        "tgn:1000193",
        "tgn:7029392"
    ],
    "tgn:id":1093065,
    "tgn:name":"Florentia",
    "tgn:placetype":[
        "aat:300008347"
    ]
},
  "bbox": [],
  "geometry": {"coordinates":[28.1333,-26.2667],"type":"Point"}
}