{
  "id": 2290264,
  "type": "Feature",
  "properties": {
    "tgn:hierarchy":[
        "tgn:2290264",
        "tgn:1000001",
        "tgn:2000925",
        "tgn:7012149",
        "tgn:7007515",
        "tgn:7029392"
    ],
    "tgn:id":2290264,
    "tgn:name":"Dodge Lower Cove",
    "tgn:placetype":[
        "aat:300132316"
    ]
},
  "bbox": [],
  "geometry": {"coordinates":[-69.5667,43.9667],"type":"Point"}
}