{
  "id": 7561450,
  "type": "Feature",
  "properties": {
    "tgn:hierarchy":[
        "tgn:7561450",
        "tgn:1000004",
        "tgn:7000198",
        "tgn:7016722",
        "tgn:7029392"
    ],
    "tgn:id":7561450,
    "tgn:name:en":"Simra",
    "tgn:placetype":[
        "aat:300008347"
    ]
},
  "bbox": [],
  "geometry": {"coordinates":[79.107628,27.859014],"type":"Point"}
}