{
  "id": 2005241,
  "type": "Feature",
  "properties": {
    "tgn:hierarchy":[
        "tgn:2005241",
        "tgn:7002659",
        "tgn:1000001",
        "tgn:7012149",
        "tgn:2000062",
        "tgn:7029392"
    ],
    "tgn:id":2005241,
    "tgn:name":"Searles",
    "tgn:placetype":[
        "aat:300008347"
    ]
},
  "bbox": [],
  "geometry": {"coordinates":[-87.3167,33.3167],"type":"Point"}
}