{
  "id": 7362561,
  "type": "Feature",
  "properties": {
    "tgn:hierarchy":[
        "tgn:7362561",
        "tgn:1000001",
        "tgn:7005597",
        "tgn:7005560",
        "tgn:7029392"
    ],
    "tgn:id":7362561,
    "tgn:name":"El Carrizo",
    "tgn:placetype":[
        "aat:300008347"
    ]
},
  "bbox": [],
  "geometry": {"coordinates":[-99.416667,22.95],"type":"Point"}
}