{
  "id": 2339735,
  "type": "Feature",
  "properties": {
    "tgn:hierarchy":[
        "tgn:2339735",
        "tgn:1000001",
        "tgn:7012149",
        "tgn:2002249",
        "tgn:7007920",
        "tgn:7029392"
    ],
    "tgn:id":2339735,
    "tgn:name":"Freedom",
    "tgn:placetype":[
        "aat:300008347"
    ]
},
  "bbox": [],
  "geometry": {"coordinates":[-117.3667,47.3667],"type":"Point"}
}