{
  "id": 7526232,
  "type": "Feature",
  "properties": {
    "tgn:hierarchy":[
        "tgn:7526232",
        "tgn:7001242",
        "tgn:7016833",
        "tgn:1001418",
        "tgn:7029392"
    ],
    "tgn:id":7526232,
    "tgn:name:en":"Sidi Kashshak",
    "tgn:placetype":[
        "aat:300007558"
    ]
},
  "bbox": [],
  "geometry": {"coordinates":[25.38981,31.333853],"type":"Point"}
}