{
  "id": 7491647,
  "type": "Feature",
  "properties": {
    "tgn:hierarchy":[
        "tgn:7491647",
        "tgn:1000004",
        "tgn:7492971",
        "tgn:1000141",
        "tgn:7029392"
    ],
    "tgn:id":7491647,
    "tgn:name":"Dalin",
    "tgn:placetype":[
        "aat:300008347"
    ]
},
  "bbox": [],
  "geometry": {"coordinates":[120.6014,22.586256],"type":"Point"}
}