{
  "id": 2702865,
  "type": "Feature",
  "properties": {
    "tgn:hierarchy":[
        "tgn:2702865",
        "tgn:1000001",
        "tgn:7012149",
        "tgn:2001926",
        "tgn:7007825",
        "tgn:7029392"
    ],
    "tgn:id":2702865,
    "tgn:name":"Sulphur Spring Branch",
    "tgn:placetype":[
        "aat:300008699"
    ]
},
  "bbox": [],
  "geometry": {"coordinates":[-82.5333,36.1333],"type":"Point"}
}