{
  "id": 2045897,
  "type": "Feature",
  "properties": {
    "tgn:hierarchy":[
        "tgn:2045897",
        "tgn:1000001",
        "tgn:2000921",
        "tgn:7012149",
        "tgn:7007515",
        "tgn:7029392"
    ],
    "tgn:id":2045897,
    "tgn:name":"Wilton",
    "tgn:placetype":[
        "aat:300008347"
    ]
},
  "bbox": [],
  "geometry": {"coordinates":[-70.2167,44.5833],"type":"Point"}
}