{
  "id": 7315785,
  "type": "Feature",
  "properties": {
    "tgn:hierarchy":[
        "tgn:7315785",
        "tgn:1001623",
        "tgn:1000049",
        "tgn:1000002",
        "tgn:7029392"
    ],
    "tgn:id":7315785,
    "tgn:name":"Centro, Islote",
    "tgn:placetype":[
        "aat:300008791"
    ]
},
  "bbox": [],
  "geometry": {"coordinates":[-73.75,-45.783333],"type":"Point"}
}