{
  "id": 2082897,
  "type": "Feature",
  "properties": {
    "tgn:hierarchy":[
        "tgn:2082897",
        "tgn:1000001",
        "tgn:7012149",
        "tgn:2001673",
        "tgn:7007707",
        "tgn:7029392"
    ],
    "tgn:id":2082897,
    "tgn:name":"Braggs",
    "tgn:placetype":[
        "aat:300008347"
    ]
},
  "bbox": [],
  "geometry": {"coordinates":[-95.1833,35.65],"type":"Point"}
}