{
  "id": 7522035,
  "type": "Feature",
  "properties": {
    "tgn:hierarchy":[
        "tgn:7522035",
        "tgn:7001242",
        "tgn:7016833",
        "tgn:1001418",
        "tgn:7029392"
    ],
    "tgn:id":7522035,
    "tgn:name:en":"Abu Raqaba, Deir",
    "tgn:placetype":[
        "aat:300386860"
    ]
},
  "bbox": [],
  "geometry": {"coordinates":[28.07652,30.768202],"type":"Point"}
}