{
  "id": 7453989,
  "type": "Feature",
  "properties": {
    "tgn:hierarchy":[
        "tgn:7453989",
        "tgn:7002445",
        "tgn:7019021",
        "tgn:1000003",
        "tgn:7008591",
        "tgn:7029392"
    ],
    "tgn:id":7453989,
    "tgn:name:en":"Chew Stoke",
    "tgn:placetype":[
        "aat:300008347"
    ]
},
  "bbox": [],
  "geometry": {"coordinates":[-2.630833,51.356111],"type":"Point"}
}