{
  "id": 7524568,
  "type": "Feature",
  "properties": {
    "tgn:hierarchy":[
        "tgn:7524568",
        "tgn:7001242",
        "tgn:7016833",
        "tgn:1001225",
        "tgn:7029392"
    ],
    "tgn:id":7524568,
    "tgn:name":"Awl\u0101d Khalaf",
    "tgn:placetype":[
        "aat:300008347"
    ]
},
  "bbox": [],
  "geometry": {"coordinates":[31.741826,31.331937],"type":"Point"}
}