{
  "id": 2759927,
  "type": "Feature",
  "properties": {
    "tgn:hierarchy":[
        "tgn:2759927",
        "tgn:1000001",
        "tgn:7012149",
        "tgn:2000482",
        "tgn:7007250",
        "tgn:7029392"
    ],
    "tgn:id":2759927,
    "tgn:name":"West Fork Maloney Creek",
    "tgn:placetype":[
        "aat:300008706"
    ]
},
  "bbox": [],
  "geometry": {"coordinates":[-116.65,46.0833],"type":"Point"}
}