{
  "id": 7403326,
  "type": "Feature",
  "properties": {
    "tgn:hierarchy":[
        "tgn:7403326",
        "tgn:1000001",
        "tgn:1001906",
        "tgn:7005560",
        "tgn:7029392"
    ],
    "tgn:id":7403326,
    "tgn:name":"Don Boni, Isla",
    "tgn:placetype":[
        "aat:300008791"
    ]
},
  "bbox": [],
  "geometry": {"coordinates":[-106.533333,21.541667],"type":"Point"}
}