{
  "id": 2056261,
  "type": "Feature",
  "properties": {
    "tgn:hierarchy":[
        "tgn:2056261",
        "tgn:1000001",
        "tgn:7012149",
        "tgn:2001123",
        "tgn:7007522",
        "tgn:7029392"
    ],
    "tgn:id":2056261,
    "tgn:name":"Daleville",
    "tgn:placetype":[
        "aat:300008347"
    ]
},
  "bbox": [],
  "geometry": {"coordinates":[-88.6667,32.5667],"type":"Point"}
}