{
  "id": 2226477,
  "type": "Feature",
  "properties": {
    "tgn:hierarchy":[
        "tgn:2226477",
        "tgn:7006450",
        "tgn:1000001",
        "tgn:2124012",
        "tgn:7012149",
        "tgn:7029392"
    ],
    "tgn:id":2226477,
    "tgn:name":"Catherine, Lake",
    "tgn:placetype":[
        "aat:300008680"
    ]
},
  "bbox": [],
  "geometry": {"coordinates":[-152.4833,57.7667],"type":"Point"}
}