{
  "id": 7511429,
  "type": "Feature",
  "properties": {
    "tgn:hierarchy":[
        "tgn:7511429",
        "tgn:1009227",
        "tgn:7001866",
        "tgn:1000226",
        "tgn:1000006",
        "tgn:7029392"
    ],
    "tgn:id":7511429,
    "tgn:name:en":"Mowbray River",
    "tgn:placetype":[
        "aat:300008699"
    ]
},
  "bbox": [],
  "geometry": {"coordinates":[170.983333,-43.883333],"type":"Point"}
}