{
  "id": 1052435,
  "type": "Feature",
  "properties": {
    "tgn:hierarchy":[
        "tgn:1052435",
        "tgn:7011450",
        "tgn:1000004",
        "tgn:7014786",
        "tgn:7029392"
    ],
    "tgn:id":1052435,
    "tgn:name":"Bayganin",
    "tgn:placetype":[
        "aat:300008347"
    ]
},
  "bbox": [],
  "geometry": {"coordinates":[55.8833,48.7167],"type":"Point"}
}