{
  "id": 7574545,
  "type": "Feature",
  "properties": {
    "tgn:hierarchy":[
        "tgn:7574545",
        "tgn:1000004",
        "tgn:7000198",
        "tgn:7001797",
        "tgn:7029392"
    ],
    "tgn:id":7574545,
    "tgn:name:en":"Kunnatt\u016br",
    "tgn:placetype":[
        "aat:300008347"
    ]
},
  "bbox": [],
  "geometry": {"coordinates":[77.416667,11.266667],"type":"Point"}
}