<<<<<<< HEAD
{
  "id": 2707110,
  "type": "Feature",
  "properties": {
    "tgn:hierarchy":[
        "tgn:2707110",
        "tgn:1000001",
        "tgn:7012149",
        "tgn:7007158",
        "tgn:2000243",
        "tgn:7029392"
    ],
    "tgn:id":2707110,
    "tgn:name":"Swede Creek",
    "tgn:placetype":[
        "aat:300008706"
    ]
},
  "bbox": [],
  "geometry": {"coordinates":[-107.5167,39.9667],"type":"Point"}
}
=======
{"geometry":{"type":"Point","coordinates":[-107.516700,39.966700]},"type":"Feature","properties":{"hierarchy":["tgn:2707110","tgn:1000001","tgn:7012149","tgn:7007158","tgn:2000243","tgn:7029392"],"placetype":["aat:300008706"],"id":2707110,"name:xx":"Swede Creek"}}
>>>>>>> 03f74aca74312dbeaf24d7e61306dd6a786dc3d0
