{
  "id": 7346807,
  "type": "Feature",
  "properties": {
    "tgn:hierarchy":[
        "tgn:7346807",
        "tgn:1001439",
        "tgn:1000003",
        "tgn:7002797",
        "tgn:1000095",
        "tgn:7029392"
    ],
    "tgn:id":7346807,
    "tgn:name":"Atalay\u00f3n, Cabezo del",
    "tgn:placetype":[
        "aat:300008777"
    ]
},
  "bbox": [],
  "geometry": {"coordinates":[-1.116667,37.55],"type":"Point"}
}