{
  "id": 7262137,
  "type": "Feature",
  "properties": {
    "tgn:hierarchy":[
        "tgn:7262137",
        "tgn:1000003",
        "tgn:7003622",
        "tgn:7016845",
        "tgn:7029392"
    ],
    "tgn:id":7262137,
    "tgn:name:nl":"Kasteel Genhoes",
    "tgn:placetype":[
        "aat:300006891"
    ]
},
  "bbox": [],
  "geometry": {"coordinates":[5.85,50.866667],"type":"Point"}
}