{
  "id": 2063650,
  "type": "Feature",
  "properties": {
    "tgn:hierarchy":[
        "tgn:2063650",
        "tgn:1000001",
        "tgn:2001427",
        "tgn:7012149",
        "tgn:7007564",
        "tgn:7029392"
    ],
    "tgn:id":2063650,
    "tgn:name":"Newport",
    "tgn:placetype":[
        "aat:300008347"
    ]
},
  "bbox": [],
  "geometry": {"coordinates":[-72.1667,43.35],"type":"Point"}
}