{
  "id": 7419127,
  "type": "Feature",
  "properties": {
    "tgn:hierarchy":[
        "tgn:7419127",
        "tgn:1000001",
        "tgn:7005589",
        "tgn:7005560",
        "tgn:7029392"
    ],
    "tgn:id":7419127,
    "tgn:name:es":"U\u00f1a de Gato, R\u00edo",
    "tgn:placetype":[
        "aat:300008699"
    ]
},
  "bbox": [],
  "geometry": {"coordinates":[-99.859167,27.658889],"type":"Point"}
}