{
  "id": 7233619,
  "type": "Feature",
  "properties": {
    "tgn:hierarchy":[
        "tgn:7233619",
        "tgn:7002680",
        "tgn:7001395",
        "tgn:1000003",
        "tgn:1000074",
        "tgn:7029392"
    ],
    "tgn:id":7233619,
    "tgn:name":"Dhimo\u00fali",
    "tgn:placetype":[
        "aat:300008777"
    ]
},
  "bbox": [],
  "geometry": {"coordinates":[22.15,38.35],"type":"Point"}
}