{
  "id": 2727641,
  "type": "Feature",
  "properties": {
    "tgn:hierarchy":[
        "tgn:2727641",
        "tgn:1000001",
        "tgn:2002108",
        "tgn:7012149",
        "tgn:7007827",
        "tgn:7029392"
    ],
    "tgn:id":2727641,
    "tgn:name":"Trail Mountain",
    "tgn:placetype":[
        "aat:300008798"
    ]
},
  "bbox": [],
  "geometry": {"coordinates":[-111.2333,39.3833],"type":"Point"}
}