{
  "id": 2708465,
  "type": "Feature",
  "properties": {
    "tgn:hierarchy":[
        "tgn:2708465",
        "tgn:1000001",
        "tgn:7012149",
        "tgn:2002267",
        "tgn:7013961",
        "tgn:7029392"
    ],
    "tgn:id":2708465,
    "tgn:name":"Sycamore Creek",
    "tgn:placetype":[
        "aat:300008706"
    ]
},
  "bbox": [],
  "geometry": {"coordinates":[-80.45,39.25],"type":"Point"}
}