{
  "id": 2255291,
  "type": "Feature",
  "properties": {
    "tgn:hierarchy":[
        "tgn:2255291",
        "tgn:2001934",
        "tgn:1000001",
        "tgn:7012149",
        "tgn:7007826",
        "tgn:7029392"
    ],
    "tgn:id":2255291,
    "tgn:name":"Cooper, Lake",
    "tgn:placetype":[
        "aat:300006191"
    ]
},
  "bbox": [],
  "geometry": {"coordinates":[-98.7833,33.4333],"type":"Point"}
}