<<<<<<< HEAD
{
  "id": 2255291,
  "type": "Feature",
  "properties": {
    "tgn:hierarchy":[
        "tgn:2255291",
        "tgn:2001934",
        "tgn:1000001",
        "tgn:7012149",
        "tgn:7007826",
        "tgn:7029392"
    ],
    "tgn:id":2255291,
    "tgn:name":"Cooper, Lake",
    "tgn:placetype":[
        "aat:300006191"
    ]
},
  "bbox": [],
  "geometry": {"coordinates":[-98.7833,33.4333],"type":"Point"}
}
=======
{"geometry":{"type":"Point","coordinates":[-98.783300,33.433300]},"type":"Feature","properties":{"hierarchy":["tgn:2255291","tgn:2001934","tgn:1000001","tgn:7012149","tgn:7007826","tgn:7029392"],"placetype":["aat:300006191"],"id":2255291,"name:xx":"Cooper, Lake"}}
>>>>>>> 03f74aca74312dbeaf24d7e61306dd6a786dc3d0
