{
  "id": 7500632,
  "type": "Feature",
  "properties": {
    "tgn:hierarchy":[
        "tgn:7500632",
        "tgn:7001004",
        "tgn:1000004",
        "tgn:1000141",
        "tgn:7029392"
    ],
    "tgn:id":7500632,
    "tgn:name":"Zhongbu Qiao",
    "tgn:placetype":[
        "aat:300007836"
    ]
},
  "bbox": [],
  "geometry": {"coordinates":[120.4375,22.920556],"type":"Point"}
}