{
  "id": 2203921,
  "type": "Feature",
  "properties": {
    "tgn:hierarchy":[
        "tgn:2203921",
        "tgn:1000001",
        "tgn:2001021",
        "tgn:7012149",
        "tgn:7007521",
        "tgn:7029392"
    ],
    "tgn:id":2203921,
    "tgn:name":"Bucksnort",
    "tgn:placetype":[
        "aat:300008347"
    ]
},
  "bbox": [],
  "geometry": {"coordinates":[-92.05,43.8167],"type":"Point"}
}