{
  "id": 2482338,
  "type": "Feature",
  "properties": {
    "tgn:hierarchy":[
        "tgn:2482338",
        "tgn:7002659",
        "tgn:1000001",
        "tgn:7012149",
        "tgn:2000051",
        "tgn:7029392"
    ],
    "tgn:id":2482338,
    "tgn:name":"Langs Cave",
    "tgn:placetype":[
        "aat:300008746"
    ]
},
  "bbox": [],
  "geometry": {"coordinates":[-86.6333,34.5167],"type":"Point"}
}