{
  "id": 1074921,
  "type": "Feature",
  "properties": {
    "tgn:hierarchy":[
        "tgn:1074921",
        "tgn:1000004",
        "tgn:7000198",
        "tgn:1001895",
        "tgn:7029392"
    ],
    "tgn:id":1074921,
    "tgn:name:en":"Ch\u0101ndvad",
    "tgn:placetype":[
        "aat:300008347"
    ]
},
  "bbox": [],
  "geometry": {"coordinates":[74.25,20.333333],"type":"Point"}
}