{
  "id": 2782222,
  "type": "Feature",
  "properties": {
    "tgn:hierarchy":[
        "tgn:2782222",
        "tgn:1000001",
        "tgn:7012149",
        "tgn:2000536",
        "tgn:7007251",
        "tgn:7029392"
    ],
    "tgn:id":2782222,
    "tgn:name":"Woodvale",
    "tgn:placetype":[
        "aat:300008347"
    ]
},
  "bbox": [],
  "geometry": {"coordinates":[-90.6333,41.0167],"type":"Point"}
}