{
  "id": 2173077,
  "type": "Feature",
  "properties": {
    "tgn:hierarchy":[
        "tgn:2173077",
        "tgn:7013349",
        "tgn:1000001",
        "tgn:7012149",
        "tgn:7007708",
        "tgn:7029392"
    ],
    "tgn:id":2173077,
    "tgn:name":"Binder Gulch",
    "tgn:placetype":[
        "aat:300008761"
    ]
},
  "bbox": [],
  "geometry": {"coordinates":[-117.2667,44.3833],"type":"Point"}
}