{
  "id": 7137958,
  "type": "Feature",
  "properties": {
    "tgn:hierarchy":[
        "tgn:7137958",
        "tgn:1000003",
        "tgn:7003678",
        "tgn:7000084",
        "tgn:7029392"
    ],
    "tgn:id":7137958,
    "tgn:name":"Gut Liebenz",
    "tgn:placetype":[
        "aat:300000206"
    ]
},
  "bbox": [],
  "geometry": {"coordinates":[9.966667,50.95],"type":"Point"}
}