{
  "id": 7361737,
  "type": "Feature",
  "properties": {
    "tgn:hierarchy":[
        "tgn:7361737",
        "tgn:1000001",
        "tgn:7005589",
        "tgn:7005560",
        "tgn:7029392"
    ],
    "tgn:id":7361737,
    "tgn:name":"Rancho El Jonuco",
    "tgn:placetype":[
        "aat:300000241"
    ]
},
  "bbox": [],
  "geometry": {"coordinates":[-99.85,27.016667],"type":"Point"}
}