<<<<<<< HEAD
{
  "id": 7361737,
  "type": "Feature",
  "properties": {
    "tgn:hierarchy":[
        "tgn:7361737",
        "tgn:1000001",
        "tgn:7005589",
        "tgn:7005560",
        "tgn:7029392"
    ],
    "tgn:id":7361737,
    "tgn:name":"Rancho El Jonuco",
    "tgn:placetype":[
        "aat:300000241"
    ]
},
  "bbox": [],
  "geometry": {"coordinates":[-99.85,27.016667],"type":"Point"}
}
=======
{"geometry":{"type":"Point","coordinates":[-99.850000,27.016667]},"type":"Feature","properties":{"hierarchy":["tgn:7361737","tgn:1000001","tgn:7005589","tgn:7005560","tgn:7029392"],"placetype":["aat:300000241"],"id":7361737,"name:xx":"Rancho El Jonuco"}}
>>>>>>> 03f74aca74312dbeaf24d7e61306dd6a786dc3d0
