<<<<<<< HEAD
{
  "id": 2254678,
  "type": "Feature",
  "properties": {
    "tgn:hierarchy":[
        "tgn:2254678",
        "tgn:1000001",
        "tgn:7012149",
        "tgn:1002645",
        "tgn:7007920",
        "tgn:7029392"
    ],
    "tgn:id":2254678,
    "tgn:name":"Coon Lake",
    "tgn:placetype":[
        "aat:300008680"
    ]
},
  "bbox": [],
  "geometry": {"coordinates":[-122.85,47.3833],"type":"Point"}
}
=======
{"geometry":{"type":"Point","coordinates":[-122.850000,47.383300]},"type":"Feature","properties":{"hierarchy":["tgn:2254678","tgn:1000001","tgn:7012149","tgn:1002645","tgn:7007920","tgn:7029392"],"placetype":["aat:300008680"],"id":2254678,"name:xx":"Coon Lake"}}
>>>>>>> 03f74aca74312dbeaf24d7e61306dd6a786dc3d0
