<<<<<<< HEAD
{
  "id": 2407578,
  "type": "Feature",
  "properties": {
    "tgn:hierarchy":[
        "tgn:2407578",
        "tgn:1000001",
        "tgn:2000924",
        "tgn:7012149",
        "tgn:7007515",
        "tgn:7029392"
    ],
    "tgn:id":2407578,
    "tgn:name":"Hupper Shoal",
    "tgn:placetype":[
        "aat:300132348"
    ]
},
  "bbox": [],
  "geometry": {"coordinates":[-69.1667,43.8833],"type":"Point"}
}
=======
{"geometry":{"type":"Point","coordinates":[-69.166700,43.883300]},"type":"Feature","properties":{"hierarchy":["tgn:2407578","tgn:1000001","tgn:2000924","tgn:7012149","tgn:7007515","tgn:7029392"],"placetype":["aat:300132348"],"id":2407578,"name:xx":"Hupper Shoal"}}
>>>>>>> 03f74aca74312dbeaf24d7e61306dd6a786dc3d0
