<<<<<<< HEAD
{
  "id": 2766643,
  "type": "Feature",
  "properties": {
    "tgn:hierarchy":[
        "tgn:2766643",
        "tgn:7002659",
        "tgn:1000001",
        "tgn:7012149",
        "tgn:2000039",
        "tgn:7029392"
    ],
    "tgn:id":2766643,
    "tgn:name":"White Oak Hollow",
    "tgn:placetype":[
        "aat:300008761"
    ]
},
  "bbox": [],
  "geometry": {"coordinates":[-87.3333,34.6],"type":"Point"}
}
=======
{"geometry":{"type":"Point","coordinates":[-87.333300,34.600000]},"type":"Feature","properties":{"hierarchy":["tgn:2766643","tgn:7002659","tgn:1000001","tgn:7012149","tgn:2000039","tgn:7029392"],"placetype":["aat:300008761"],"id":2766643,"name:xx":"White Oak Hollow"}}
>>>>>>> 03f74aca74312dbeaf24d7e61306dd6a786dc3d0
