<<<<<<< HEAD
{
  "id": 7179250,
  "type": "Feature",
  "properties": {
    "tgn:hierarchy":[
        "tgn:7179250",
        "tgn:1000003",
        "tgn:7003677",
        "tgn:7000084",
        "tgn:7029392"
    ],
    "tgn:id":7179250,
    "tgn:name":"Haberland",
    "tgn:placetype":[
        "aat:300000206"
    ]
},
  "bbox": [],
  "geometry": {"coordinates":[8.65,51.9],"type":"Point"}
}
=======
{"geometry":{"type":"Point","coordinates":[8.650000,51.900000]},"type":"Feature","properties":{"hierarchy":["tgn:7179250","tgn:1000003","tgn:7003677","tgn:7000084","tgn:7029392"],"placetype":["aat:300000206"],"id":7179250,"name:xx":"Haberland"}}
>>>>>>> 03f74aca74312dbeaf24d7e61306dd6a786dc3d0
