{
  "id": 6004568,
  "type": "Feature",
  "properties": {
    "tgn:hierarchy":[
        "tgn:6004568",
        "tgn:7003458",
        "tgn:1000003",
        "tgn:1000063",
        "tgn:7018236",
        "tgn:7029392"
    ],
    "tgn:id":6004568,
    "tgn:name":"Passendale",
    "tgn:placetype":[
        "aat:300008347"
    ]
},
  "bbox": [],
  "geometry": {"coordinates":[3.020879,50.900428],"type":"Point"}
}