{
  "id": 7284182,
  "type": "Feature",
  "properties": {
    "tgn:hierarchy":[
        "tgn:7284182",
        "tgn:1001657",
        "tgn:1000049",
        "tgn:1000002",
        "tgn:7029392"
    ],
    "tgn:id":7284182,
    "tgn:name":"Potrero El Pingo",
    "tgn:placetype":[
        "aat:300008347"
    ]
},
  "bbox": [],
  "geometry": {"coordinates":[-70.65,-30.566667],"type":"Point"}
}