<<<<<<< HEAD
{
  "id": 7473253,
  "type": "Feature",
  "properties": {
    "tgn:hierarchy":[
        "tgn:7473253",
        "tgn:7487020",
        "tgn:1000004",
        "tgn:1000141",
        "tgn:7029392"
    ],
    "tgn:id":7473253,
    "tgn:name":"Tongluo Xiang",
    "tgn:placetype":[
        "aat:300387173"
    ]
},
  "bbox": [],
  "geometry": {"coordinates":[120.8,24.466667],"type":"Point"}
}
=======
{"geometry":{"type":"Point","coordinates":[120.800000,24.466667]},"type":"Feature","properties":{"hierarchy":["tgn:7473253","tgn:7487020","tgn:1000004","tgn:1000141","tgn:7029392"],"placetype":["aat:300387173"],"id":7473253,"name:xx":"Tongluo Xiang"}}
>>>>>>> 03f74aca74312dbeaf24d7e61306dd6a786dc3d0
