{
  "id": 2494915,
  "type": "Feature",
  "properties": {
    "tgn:hierarchy":[
        "tgn:2494915",
        "tgn:1000001",
        "tgn:7012149",
        "tgn:1002469",
        "tgn:7007255",
        "tgn:7029392"
    ],
    "tgn:id":2494915,
    "tgn:name":"Martini Run",
    "tgn:placetype":[
        "aat:300008699"
    ]
},
  "bbox": [],
  "geometry": {"coordinates":[-85.1167,38.5333],"type":"Point"}
}