{
  "id": 2178586,
  "type": "Feature",
  "properties": {
    "tgn:hierarchy":[
        "tgn:2178586",
        "tgn:1000001",
        "tgn:7012149",
        "tgn:2000974",
        "tgn:7007520",
        "tgn:7029392"
    ],
    "tgn:id":2178586,
    "tgn:name":"Blacksmith Bayou",
    "tgn:placetype":[
        "aat:300008680"
    ]
},
  "bbox": [],
  "geometry": {"coordinates":[-86.0167,44.25],"type":"Point"}
}