{
  "id": 7560131,
  "type": "Feature",
  "properties": {
    "tgn:hierarchy":[
        "tgn:7560131",
        "tgn:1000004",
        "tgn:7000198",
        "tgn:7016788",
        "tgn:7029392"
    ],
    "tgn:id":7560131,
    "tgn:name:en":"Bisanh\u0101la",
    "tgn:placetype":[
        "aat:300008347"
    ]
},
  "bbox": [],
  "geometry": {"coordinates":[75.727,26.9255],"type":"Point"}
}