{
  "id": 7317082,
  "type": "Feature",
  "properties": {
    "tgn:hierarchy":[
        "tgn:7317082",
        "tgn:1001695",
        "tgn:1000049",
        "tgn:1000002",
        "tgn:7029392"
    ],
    "tgn:id":7317082,
    "tgn:name":"Chipana, Cerro",
    "tgn:placetype":[
        "aat:300008795"
    ]
},
  "bbox": [],
  "geometry": {"coordinates":[-70.95,-34.85],"type":"Point"}
}