{
  "id": 2435392,
  "type": "Feature",
  "properties": {
    "tgn:hierarchy":[
        "tgn:2435392",
        "tgn:1000001",
        "tgn:7012149",
        "tgn:2001894",
        "tgn:7007825",
        "tgn:7029392"
    ],
    "tgn:id":2435392,
    "tgn:name":"Kern Branch",
    "tgn:placetype":[
        "aat:300008699"
    ]
},
  "bbox": [],
  "geometry": {"coordinates":[-85.5167,35.2333],"type":"Point"}
}