{
  "id": 2202458,
  "type": "Feature",
  "properties": {
    "tgn:hierarchy":[
        "tgn:2202458",
        "tgn:1000001",
        "tgn:2001473",
        "tgn:7012149",
        "tgn:7007709",
        "tgn:7029392"
    ],
    "tgn:id":2202458,
    "tgn:name":"Buck Ridge",
    "tgn:placetype":[
        "aat:300266640"
    ]
},
  "bbox": [],
  "geometry": {"coordinates":[-82.35,35.55],"type":"Point"}
}