{
  "id": 2307007,
  "type": "Feature",
  "properties": {
    "tgn:hierarchy":[
        "tgn:2307007",
        "tgn:1000001",
        "tgn:7012149",
        "tgn:2000360",
        "tgn:7007248",
        "tgn:7029392"
    ],
    "tgn:id":2307007,
    "tgn:name":"East Fork Little River",
    "tgn:placetype":[
        "aat:300008707"
    ]
},
  "bbox": [],
  "geometry": {"coordinates":[-83.7667,34.4833],"type":"Point"}
}