{
  "id": 2356870,
  "type": "Feature",
  "properties": {
    "tgn:hierarchy":[
        "tgn:2356870",
        "tgn:7002659",
        "tgn:1000001",
        "tgn:7012149",
        "tgn:2000035",
        "tgn:7029392"
    ],
    "tgn:id":2356870,
    "tgn:name":"Goshen Hollow",
    "tgn:placetype":[
        "aat:300008761"
    ]
},
  "bbox": [],
  "geometry": {"coordinates":[-86.0333,34.8333],"type":"Point"}
}