{
  "id": 7394387,
  "type": "Feature",
  "properties": {
    "tgn:hierarchy":[
        "tgn:7394387",
        "tgn:1000001",
        "tgn:7005595",
        "tgn:7005560",
        "tgn:7029392"
    ],
    "tgn:id":7394387,
    "tgn:name":"San Lorenzo",
    "tgn:placetype":[
        "aat:300008347"
    ]
},
  "bbox": [],
  "geometry": {"coordinates":[-107.118889,24.435556],"type":"Point"}
}