{
  "id": 7554370,
  "type": "Feature",
  "properties": {
    "tgn:hierarchy":[
        "tgn:7554370",
        "tgn:1001828",
        "tgn:1000004",
        "tgn:7000198",
        "tgn:7029392"
    ],
    "tgn:id":7554370,
    "tgn:name:en":"Medap\u0101du",
    "tgn:placetype":[
        "aat:300008347"
    ]
},
  "bbox": [],
  "geometry": {"coordinates":[82.166667,17.016667],"type":"Point"}
}