{
  "id": 7186928,
  "type": "Feature",
  "properties": {
    "tgn:hierarchy":[
        "tgn:7186928",
        "tgn:1000003",
        "tgn:7003678",
        "tgn:7000084",
        "tgn:7029392"
    ],
    "tgn:id":7186928,
    "tgn:name":"Goldberg",
    "tgn:placetype":[
        "aat:300008777"
    ]
},
  "bbox": [],
  "geometry": {"coordinates":[9.15,50.65],"type":"Point"}
}