{
  "id": 7429931,
  "type": "Feature",
  "properties": {
    "tgn:hierarchy":[
        "tgn:7429931",
        "tgn:1001835",
        "tgn:1000001",
        "tgn:7005560",
        "tgn:7029392"
    ],
    "tgn:id":7429931,
    "tgn:name":"Coronel Esteban Cant\u00fa",
    "tgn:placetype":[
        "aat:300008347"
    ]
},
  "bbox": [],
  "geometry": {"coordinates":[-116.666667,31.583333],"type":"Point"}
}