{
  "id": 2320166,
  "type": "Feature",
  "properties": {
    "tgn:hierarchy":[
        "tgn:2320166",
        "tgn:1000001",
        "tgn:1002210",
        "tgn:7012149",
        "tgn:7007706",
        "tgn:7029392"
    ],
    "tgn:id":2320166,
    "tgn:name":"Evans Run",
    "tgn:placetype":[
        "aat:300008699"
    ]
},
  "bbox": [],
  "geometry": {"coordinates":[-83.8833,38.8667],"type":"Point"}
}