<<<<<<< HEAD
{
  "id": 7477515,
  "type": "Feature",
  "properties": {
    "tgn:hierarchy":[
        "tgn:7477515",
        "tgn:7001010",
        "tgn:1000004",
        "tgn:1000141",
        "tgn:7029392"
    ],
    "tgn:id":7477515,
    "tgn:name":"Fengming Erhao Qiao",
    "tgn:placetype":[
        "aat:300007836"
    ]
},
  "bbox": [],
  "geometry": {"coordinates":[121.444349,23.754896],"type":"Point"}
}
=======
{"geometry":{"type":"Point","coordinates":[121.444349,23.754896]},"type":"Feature","properties":{"hierarchy":["tgn:7477515","tgn:7001010","tgn:1000004","tgn:1000141","tgn:7029392"],"placetype":["aat:300007836"],"id":7477515,"name:xx":"Fengming Erhao Qiao"}}
>>>>>>> 03f74aca74312dbeaf24d7e61306dd6a786dc3d0
