{
  "id": 2759347,
  "type": "Feature",
  "properties": {
    "tgn:hierarchy":[
        "tgn:2759347",
        "tgn:1000001",
        "tgn:7012149",
        "tgn:1002742",
        "tgn:7007920",
        "tgn:7029392"
    ],
    "tgn:id":2759347,
    "tgn:name":"West Fork Cougar Creek",
    "tgn:placetype":[
        "aat:300008706"
    ]
},
  "bbox": [],
  "geometry": {"coordinates":[-118.95,48.7333],"type":"Point"}
}