{
  "id": 7283873,
  "type": "Feature",
  "properties": {
    "tgn:hierarchy":[
        "tgn:7283873",
        "tgn:1001692",
        "tgn:1000049",
        "tgn:1000002",
        "tgn:7029392"
    ],
    "tgn:id":7283873,
    "tgn:name":"Quinquich\u00e1n, Estero",
    "tgn:placetype":[
        "aat:300008699"
    ]
},
  "bbox": [],
  "geometry": {"coordinates":[-72.55,-39.25],"type":"Point"}
}