{
  "id": 2284526,
  "type": "Feature",
  "properties": {
    "tgn:hierarchy":[
        "tgn:2284526",
        "tgn:1000001",
        "tgn:7012149",
        "tgn:7007157",
        "tgn:2000189",
        "tgn:7029392"
    ],
    "tgn:id":2284526,
    "tgn:name":"Des Moines Creek",
    "tgn:placetype":[
        "aat:300008706"
    ]
},
  "bbox": [],
  "geometry": {"coordinates":[-123.5167,41.95],"type":"Point"}
}