{
  "id": 7547113,
  "type": "Feature",
  "properties": {
    "tgn:hierarchy":[
        "tgn:7547113",
        "tgn:1000004",
        "tgn:7000198",
        "tgn:1001894",
        "tgn:7029392"
    ],
    "tgn:id":7547113,
    "tgn:name:en":"Bamn\u0101la",
    "tgn:placetype":[
        "aat:300008347"
    ]
},
  "bbox": [],
  "geometry": {"coordinates":[75.86631,21.815912],"type":"Point"}
}