{
  "id": 7184437,
  "type": "Feature",
  "properties": {
    "tgn:hierarchy":[
        "tgn:7184437",
        "tgn:1000003",
        "tgn:7003688",
        "tgn:7000084",
        "tgn:7029392"
    ],
    "tgn:id":7184437,
    "tgn:name":"Grauh\u00f6ft",
    "tgn:placetype":[
        "aat:300000206"
    ]
},
  "bbox": [],
  "geometry": {"coordinates":[9.933333,54.666667],"type":"Point"}
}