{
  "id": 2306345,
  "type": "Feature",
  "properties": {
    "tgn:hierarchy":[
        "tgn:2306345",
        "tgn:1000001",
        "tgn:7012149",
        "tgn:2001713",
        "tgn:7007708",
        "tgn:7029392"
    ],
    "tgn:id":2306345,
    "tgn:name":"East Fork Chapman Creek",
    "tgn:placetype":[
        "aat:300008706"
    ]
},
  "bbox": [],
  "geometry": {"coordinates":[-123.5833,42.1833],"type":"Point"}
}