{
  "id": 2331715,
  "type": "Feature",
  "properties": {
    "tgn:hierarchy":[
        "tgn:2331715",
        "tgn:1000001",
        "tgn:7012149",
        "tgn:1002681",
        "tgn:7007568",
        "tgn:7029392"
    ],
    "tgn:id":2331715,
    "tgn:name":"Fleming Creek",
    "tgn:placetype":[
        "aat:300008706"
    ]
},
  "bbox": [],
  "geometry": {"coordinates":[-77.6333,43.2167],"type":"Point"}
}