<<<<<<< HEAD
{
  "id": 2331715,
  "type": "Feature",
  "properties": {
    "tgn:hierarchy":[
        "tgn:2331715",
        "tgn:1000001",
        "tgn:7012149",
        "tgn:1002681",
        "tgn:7007568",
        "tgn:7029392"
    ],
    "tgn:id":2331715,
    "tgn:name":"Fleming Creek",
    "tgn:placetype":[
        "aat:300008706"
    ]
},
  "bbox": [],
  "geometry": {"coordinates":[-77.6333,43.2167],"type":"Point"}
}
=======
{"geometry":{"type":"Point","coordinates":[-77.633300,43.216700]},"type":"Feature","properties":{"hierarchy":["tgn:2331715","tgn:1000001","tgn:7012149","tgn:1002681","tgn:7007568","tgn:7029392"],"placetype":["aat:300008706"],"id":2331715,"name:xx":"Fleming Creek"}}
>>>>>>> 03f74aca74312dbeaf24d7e61306dd6a786dc3d0
