{
  "id": 7574431,
  "type": "Feature",
  "properties": {
    "tgn:hierarchy":[
        "tgn:7574431",
        "tgn:1000004",
        "tgn:7031781",
        "tgn:7000198",
        "tgn:7029392"
    ],
    "tgn:id":7574431,
    "tgn:name:en":"Kuni",
    "tgn:placetype":[
        "aat:300008347"
    ]
},
  "bbox": [],
  "geometry": {"coordinates":[83.063679,22.869046],"type":"Point"}
}