{
  "id": 7369714,
  "type": "Feature",
  "properties": {
    "tgn:hierarchy":[
        "tgn:7369714",
        "tgn:1000001",
        "tgn:7005590",
        "tgn:7005560",
        "tgn:7029392"
    ],
    "tgn:id":7369714,
    "tgn:name":"Huancito",
    "tgn:placetype":[
        "aat:300008347"
    ]
},
  "bbox": [],
  "geometry": {"coordinates":[-102.083333,19.833333],"type":"Point"}
}