{
  "id": 2135023,
  "type": "Feature",
  "properties": {
    "tgn:hierarchy":[
        "tgn:2135023",
        "tgn:1000001",
        "tgn:2002368",
        "tgn:7012149",
        "tgn:7007923",
        "tgn:7029392"
    ],
    "tgn:id":2135023,
    "tgn:name":"Antelope Springs",
    "tgn:placetype":[
        "aat:300008697"
    ]
},
  "bbox": [],
  "geometry": {"coordinates":[-106.25,42.4167],"type":"Point"}
}