{
  "id": 2750133,
  "type": "Feature",
  "properties": {
    "tgn:hierarchy":[
        "tgn:2750133",
        "tgn:1000001",
        "tgn:7012149",
        "tgn:2000406",
        "tgn:7007248",
        "tgn:7029392"
    ],
    "tgn:id":2750133,
    "tgn:name":"Walthrall",
    "tgn:placetype":[
        "aat:300008347"
    ]
},
  "bbox": [],
  "geometry": {"coordinates":[-85.2667,33.9333],"type":"Point"}
}