{
  "id": 2180943,
  "type": "Feature",
  "properties": {
    "tgn:hierarchy":[
        "tgn:2180943",
        "tgn:1000001",
        "tgn:7012149",
        "tgn:1002943",
        "tgn:7007708",
        "tgn:7029392"
    ],
    "tgn:id":2180943,
    "tgn:name":"Blowout Creek",
    "tgn:placetype":[
        "aat:300008706"
    ]
},
  "bbox": [],
  "geometry": {"coordinates":[-123.6833,45.5333],"type":"Point"}
}