<<<<<<< HEAD
{
  "id": 7115794,
  "type": "Feature",
  "properties": {
    "tgn:hierarchy":[
        "tgn:7115794",
        "tgn:1000003",
        "tgn:7003689",
        "tgn:7000084",
        "tgn:7029392"
    ],
    "tgn:id":7115794,
    "tgn:name":"Ohratalsperre",
    "tgn:placetype":[
        "aat:300006191"
    ]
},
  "bbox": [],
  "geometry": {"coordinates":[10.716667,50.766667],"type":"Point"}
}
=======
{"geometry":{"type":"Point","coordinates":[10.716667,50.766667]},"type":"Feature","properties":{"hierarchy":["tgn:7115794","tgn:1000003","tgn:7003689","tgn:7000084","tgn:7029392"],"placetype":["aat:300006191"],"id":7115794,"name:xx":"Ohratalsperre"}}
>>>>>>> 03f74aca74312dbeaf24d7e61306dd6a786dc3d0
