<<<<<<< HEAD
{
  "id": 2336015,
  "type": "Feature",
  "properties": {
    "tgn:hierarchy":[
        "tgn:2336015",
        "tgn:1000001",
        "tgn:2001435",
        "tgn:7012149",
        "tgn:7007566",
        "tgn:7029392"
    ],
    "tgn:id":2336015,
    "tgn:name":"Foster Canyon",
    "tgn:placetype":[
        "aat:300008761"
    ]
},
  "bbox": [],
  "geometry": {"coordinates":[-107.0167,32.4667],"type":"Point"}
}
=======
{"geometry":{"type":"Point","coordinates":[-107.016700,32.466700]},"type":"Feature","properties":{"hierarchy":["tgn:2336015","tgn:1000001","tgn:2001435","tgn:7012149","tgn:7007566","tgn:7029392"],"placetype":["aat:300008761"],"id":2336015,"name:xx":"Foster Canyon"}}
>>>>>>> 03f74aca74312dbeaf24d7e61306dd6a786dc3d0
