{
  "id": 7271740,
  "type": "Feature",
  "properties": {
    "tgn:concordances":{
        "gn:id":"2746306"
    },
    "tgn:hierarchy":[
        "tgn:7271740",
        "tgn:1000003",
        "tgn:7003624",
        "tgn:7016845",
        "tgn:7029392"
    ],
    "tgn:id":7271740,
    "tgn:name:nl":"Tiggeltscheberg",
    "tgn:placetype":[
        "aat:300008347"
    ]
},
  "bbox": [],
  "geometry": {"coordinates":[4.666667,51.533333],"type":"Point"}
}