{
  "id": 7447321,
  "type": "Feature",
  "properties": {
    "tgn:hierarchy":[
        "tgn:7447321",
        "tgn:7002445",
        "tgn:1000003",
        "tgn:7008117",
        "tgn:7008591",
        "tgn:7029392"
    ],
    "tgn:id":7447321,
    "tgn:name:en":"Silloth Bank",
    "tgn:placetype":[
        "aat:300386970"
    ]
},
  "bbox": [],
  "geometry": {"coordinates":[-3.416667,54.883333],"type":"Point"}
}