{
  "id": 1072989,
  "type": "Feature",
  "properties": {
    "tgn:hierarchy":[
        "tgn:1072989",
        "tgn:1000004",
        "tgn:7002082",
        "tgn:1000111",
        "tgn:7029392"
    ],
    "tgn:id":1072989,
    "tgn:name":"Xihuashan",
    "tgn:placetype":[
        "aat:300008347"
    ]
},
  "bbox": [],
  "geometry": {"coordinates":[114.3333,25.4333],"type":"Point"}
}