{
  "id": 2323377,
  "type": "Feature",
  "properties": {
    "tgn:hierarchy":[
        "tgn:2323377",
        "tgn:1000001",
        "tgn:7012149",
        "tgn:1002482",
        "tgn:7007706",
        "tgn:7029392"
    ],
    "tgn:id":2323377,
    "tgn:name":"Farmerstown Lake",
    "tgn:placetype":[
        "aat:300008680"
    ]
},
  "bbox": [],
  "geometry": {"coordinates":[-81.7167,40.4667],"type":"Point"}
}