{
  "id": 2402427,
  "type": "Feature",
  "properties": {
    "tgn:hierarchy":[
        "tgn:2402427",
        "tgn:1000001",
        "tgn:1002934",
        "tgn:7012149",
        "tgn:7007565",
        "tgn:7029392"
    ],
    "tgn:id":2402427,
    "tgn:name":"Hortons Pond",
    "tgn:placetype":[
        "aat:300008680"
    ]
},
  "bbox": [],
  "geometry": {"coordinates":[-74.75,41.0667],"type":"Point"}
}