{
  "id": 7166538,
  "type": "Feature",
  "properties": {
    "tgn:hierarchy":[
        "tgn:7166538",
        "tgn:1000003",
        "tgn:7003688",
        "tgn:7000084",
        "tgn:7029392"
    ],
    "tgn:id":7166538,
    "tgn:name":"Heisterende",
    "tgn:placetype":[
        "aat:300008347"
    ]
},
  "bbox": [],
  "geometry": {"coordinates":[9.633333,53.833333],"type":"Point"}
}