{
  "id": 7056203,
  "type": "Feature",
  "properties": {
    "tgn:hierarchy":[
        "tgn:7056203",
        "tgn:1003429",
        "tgn:1000003",
        "tgn:7003240",
        "tgn:1000080",
        "tgn:7029392"
    ],
    "tgn:id":7056203,
    "tgn:name":"Le Casaccie",
    "tgn:placetype":[
        "aat:300008347"
    ]
},
  "bbox": [],
  "geometry": {"coordinates":[12.75,43.416667],"type":"Point"}
}