{
  "id": 7243140,
  "type": "Feature",
  "properties": {
    "tgn:hierarchy":[
        "tgn:7243140",
        "tgn:7003458",
        "tgn:1000003",
        "tgn:1000063",
        "tgn:7018236",
        "tgn:7029392"
    ],
    "tgn:id":7243140,
    "tgn:name":"La Plus Douve",
    "tgn:placetype":[
        "aat:300000206"
    ]
},
  "bbox": [],
  "geometry": {"coordinates":[2.85,50.75],"type":"Point"}
}