{
  "id": 7370646,
  "type": "Feature",
  "properties": {
    "tgn:hierarchy":[
        "tgn:7370646",
        "tgn:7005583",
        "tgn:1000001",
        "tgn:7005560",
        "tgn:7029392"
    ],
    "tgn:id":7370646,
    "tgn:name":"Javalina",
    "tgn:placetype":[
        "aat:300008347"
    ]
},
  "bbox": [],
  "geometry": {"coordinates":[-106.45,25.366667],"type":"Point"}
}