{
  "id": 7028343,
  "type": "Feature",
  "properties": {
    "tgn:hierarchy":[
        "tgn:7028343",
        "tgn:7002445",
        "tgn:1000003",
        "tgn:7008160",
        "tgn:7008591",
        "tgn:7029392"
    ],
    "tgn:id":7028343,
    "tgn:name":"Corpusty",
    "tgn:placetype":[
        "aat:300008347",
        "aat:300008372"
    ]
},
  "bbox": [],
  "geometry": {"coordinates":[1.133333,52.816667],"type":"Point"}
}