{
  "id": 1069549,
  "type": "Feature",
  "properties": {
    "tgn:hierarchy":[
        "tgn:1069549",
        "tgn:1000004",
        "tgn:7001745",
        "tgn:1000111",
        "tgn:7029392"
    ],
    "tgn:id":1069549,
    "tgn:name":"Keshitage",
    "tgn:placetype":[
        "aat:300008347"
    ]
},
  "bbox": [],
  "geometry": {"coordinates":[78.0833,37.3833],"type":"Point"}
}