{
  "id": 7230874,
  "type": "Feature",
  "properties": {
    "tgn:hierarchy":[
        "tgn:7230874",
        "tgn:7002745",
        "tgn:7017076",
        "tgn:1000003",
        "tgn:1000074",
        "tgn:7029392"
    ],
    "tgn:id":7230874,
    "tgn:name":"Khel\u00e1dhi, \u00c1kra",
    "tgn:placetype":[
        "aat:300008850"
    ]
},
  "bbox": [],
  "geometry": {"coordinates":[23.05,36.283333],"type":"Point"}
}