{
  "id": 2311809,
  "type": "Feature",
  "properties": {
    "tgn:hierarchy":[
        "tgn:2311809",
        "tgn:1000001",
        "tgn:7012149",
        "tgn:2001042",
        "tgn:7007521",
        "tgn:7029392"
    ],
    "tgn:id":2311809,
    "tgn:name":"Edwin Lake",
    "tgn:placetype":[
        "aat:300008680"
    ]
},
  "bbox": [],
  "geometry": {"coordinates":[-95.7667,47.3333],"type":"Point"}
}