<<<<<<< HEAD
{
  "id": 2254958,
  "type": "Feature",
  "properties": {
    "tgn:hierarchy":[
        "tgn:2254958",
        "tgn:1000001",
        "tgn:7012149",
        "tgn:2001844",
        "tgn:7007825",
        "tgn:7029392"
    ],
    "tgn:id":2254958,
    "tgn:name":"Cooper Branch",
    "tgn:placetype":[
        "aat:300008699"
    ]
},
  "bbox": [],
  "geometry": {"coordinates":[-86.05,35.6833],"type":"Point"}
}
=======
{"geometry":{"type":"Point","coordinates":[-86.050000,35.683300]},"type":"Feature","properties":{"hierarchy":["tgn:2254958","tgn:1000001","tgn:7012149","tgn:2001844","tgn:7007825","tgn:7029392"],"placetype":["aat:300008699"],"id":2254958,"name:xx":"Cooper Branch"}}
>>>>>>> 03f74aca74312dbeaf24d7e61306dd6a786dc3d0
