{
  "id": 1067610,
  "type": "Feature",
  "properties": {
    "tgn:hierarchy":[
        "tgn:1067610",
        "tgn:1000004",
        "tgn:7002081",
        "tgn:1000111",
        "tgn:7029392"
    ],
    "tgn:id":1067610,
    "tgn:name":"Daxujia",
    "tgn:placetype":[
        "aat:300008347"
    ]
},
  "bbox": [],
  "geometry": {"coordinates":[117.55,34.2833],"type":"Point"}
}