{
  "id": 2565643,
  "type": "Feature",
  "properties": {
    "tgn:hierarchy":[
        "tgn:2565643",
        "tgn:1000001",
        "tgn:2001428",
        "tgn:7012149",
        "tgn:7007566",
        "tgn:7029392"
    ],
    "tgn:id":2565643,
    "tgn:name":"Pajarito Lateral",
    "tgn:placetype":[
        "aat:300006075"
    ]
},
  "bbox": [],
  "geometry": {"coordinates":[-106.6833,35.0333],"type":"Point"}
}