{
  "id": 1116620,
  "type": "Feature",
  "properties": {
    "tgn:hierarchy":[
        "tgn:1116620",
        "tgn:1000001",
        "tgn:7012149",
        "tgn:7007565",
        "tgn:7029392"
    ],
    "tgn:id":1116620,
    "tgn:name":"Hopatcong, Lake",
    "tgn:placetype":[
        "aat:300008680"
    ]
},
  "bbox": [],
  "geometry": {"coordinates":[-74.6167,40.9667],"type":"Point"}
}