{
  "id": 2242349,
  "type": "Feature",
  "properties": {
    "tgn:hierarchy":[
        "tgn:2242349",
        "tgn:1000001",
        "tgn:2000469",
        "tgn:7012149",
        "tgn:7007250",
        "tgn:7029392"
    ],
    "tgn:id":2242349,
    "tgn:name":"Clayton Creek",
    "tgn:placetype":[
        "aat:300008706"
    ]
},
  "bbox": [],
  "geometry": {"coordinates":[-115.0833,46.6667],"type":"Point"}
}