{
  "id": 7130884,
  "type": "Feature",
  "properties": {
    "tgn:hierarchy":[
        "tgn:7130884",
        "tgn:1000003",
        "tgn:7003688",
        "tgn:7000084",
        "tgn:7029392"
    ],
    "tgn:id":7130884,
    "tgn:name":"Mittelkoog",
    "tgn:placetype":[
        "aat:300006163"
    ]
},
  "bbox": [],
  "geometry": {"coordinates":[8.733333,54.333333],"type":"Point"}
}