<<<<<<< HEAD
{
  "id": 7379334,
  "type": "Feature",
  "properties": {
    "tgn:hierarchy":[
        "tgn:7379334",
        "tgn:1000001",
        "tgn:1001960",
        "tgn:7005560",
        "tgn:7029392"
    ],
    "tgn:id":7379334,
    "tgn:name":"Rancho Maricopa",
    "tgn:placetype":[
        "aat:300000241"
    ]
},
  "bbox": [],
  "geometry": {"coordinates":[-111.75,30.133333],"type":"Point"}
}
=======
{"geometry":{"type":"Point","coordinates":[-111.750000,30.133333]},"type":"Feature","properties":{"hierarchy":["tgn:7379334","tgn:1000001","tgn:1001960","tgn:7005560","tgn:7029392"],"placetype":["aat:300000241"],"id":7379334,"name:xx":"Rancho Maricopa"}}
>>>>>>> 03f74aca74312dbeaf24d7e61306dd6a786dc3d0
