{
  "id": 7091921,
  "type": "Feature",
  "properties": {
    "tgn:hierarchy":[
        "tgn:7091921",
        "tgn:7003669",
        "tgn:1000003",
        "tgn:7000084",
        "tgn:7029392"
    ],
    "tgn:id":7091921,
    "tgn:name":"Unterm\u00fchlhausen",
    "tgn:placetype":[
        "aat:300008347"
    ]
},
  "bbox": [],
  "geometry": {"coordinates":[10.916667,48.083333],"type":"Point"}
}