{
  "id": 2660966,
  "type": "Feature",
  "properties": {
    "tgn:hierarchy":[
        "tgn:2660966",
        "tgn:1000001",
        "tgn:7012149",
        "tgn:2001515",
        "tgn:7007709",
        "tgn:7029392"
    ],
    "tgn:id":2660966,
    "tgn:name":"Short Creek",
    "tgn:placetype":[
        "aat:300008706"
    ]
},
  "bbox": [],
  "geometry": {"coordinates":[-83.25,35.0833],"type":"Point"}
}