{
  "id": 1140757,
  "type": "Feature",
  "properties": {
    "tgn:hierarchy":[
        "tgn:1140757",
        "tgn:1000004",
        "tgn:1001430",
        "tgn:1000135",
        "tgn:7029392"
    ],
    "tgn:id":1140757,
    "tgn:name":"San Jose",
    "tgn:placetype":[
        "aat:300008347"
    ]
},
  "bbox": [],
  "geometry": {"coordinates":[121.05,12.4167],"type":"Point"}
}