<<<<<<< HEAD
{
  "id": 7489646,
  "type": "Feature",
  "properties": {
    "tgn:hierarchy":[
        "tgn:7489646",
        "tgn:1000004",
        "tgn:7004300",
        "tgn:1000141",
        "tgn:7029392"
    ],
    "tgn:id":7489646,
    "tgn:name":"Daqitou",
    "tgn:placetype":[
        "aat:300387033"
    ]
},
  "bbox": [],
  "geometry": {"coordinates":[119.556225,23.667809],"type":"Point"}
}
=======
{"geometry":{"type":"Point","coordinates":[119.556225,23.667809]},"type":"Feature","properties":{"hierarchy":["tgn:7489646","tgn:1000004","tgn:7004300","tgn:1000141","tgn:7029392"],"placetype":["aat:300387033"],"id":7489646,"name:xx":"Daqitou"}}
>>>>>>> 03f74aca74312dbeaf24d7e61306dd6a786dc3d0
