{
  "id": 2646425,
  "type": "Feature",
  "properties": {
    "tgn:hierarchy":[
        "tgn:2646425",
        "tgn:1000001",
        "tgn:7012149",
        "tgn:7018871",
        "tgn:7007920",
        "tgn:7029392"
    ],
    "tgn:id":2646425,
    "tgn:name":"Sawyer, Lake",
    "tgn:placetype":[
        "aat:300006191"
    ]
},
  "bbox": [],
  "geometry": {"coordinates":[-122.0333,47.3333],"type":"Point"}
}