{
  "id": 2361158,
  "type": "Feature",
  "properties": {
    "tgn:hierarchy":[
        "tgn:2361158",
        "tgn:1000001",
        "tgn:7012149",
        "tgn:2000909",
        "tgn:7007256",
        "tgn:7029392"
    ],
    "tgn:id":2361158,
    "tgn:name":"Gravel",
    "tgn:placetype":[
        "aat:300008347"
    ]
},
  "bbox": [],
  "geometry": {"coordinates":[-92.15,32.9167],"type":"Point"}
}