{
  "id": 7062148,
  "type": "Feature",
  "properties": {
    "tgn:hierarchy":[
        "tgn:7062148",
        "tgn:7003692",
        "tgn:1000003",
        "tgn:7000084",
        "tgn:7029392"
    ],
    "tgn:id":7062148,
    "tgn:name":"Bachere",
    "tgn:placetype":[
        "aat:300008347"
    ]
},
  "bbox": [],
  "geometry": {"coordinates":[8.066667,48.216667],"type":"Point"}
}