{
  "id": 2085174,
  "type": "Feature",
  "properties": {
    "tgn:hierarchy":[
        "tgn:2085174",
        "tgn:1000001",
        "tgn:1002293",
        "tgn:7012149",
        "tgn:7007708",
        "tgn:7029392"
    ],
    "tgn:id":2085174,
    "tgn:name":"Natal",
    "tgn:placetype":[
        "aat:300008347",
        "aat:300387210"
    ]
},
  "bbox": [],
  "geometry": {"coordinates":[-123.1833,45.9667],"type":"Point"}
}