{
  "id": 7592862,
  "type": "Feature",
  "properties": {
    "tgn:hierarchy":[
        "tgn:7592862",
        "tgn:1000004",
        "tgn:7000198",
        "tgn:7000799",
        "tgn:7029392"
    ],
    "tgn:id":7592862,
    "tgn:name:en":"Khui diDheri",
    "tgn:placetype":[
        "aat:300008347"
    ]
},
  "bbox": [],
  "geometry": {"coordinates":[74.391667,33.088889],"type":"Point"}
}