{
  "id": 7381379,
  "type": "Feature",
  "properties": {
    "tgn:hierarchy":[
        "tgn:7381379",
        "tgn:1000001",
        "tgn:7005597",
        "tgn:7005560",
        "tgn:7029392"
    ],
    "tgn:id":7381379,
    "tgn:name":"Rancho Los Algodones",
    "tgn:placetype":[
        "aat:300000241"
    ]
},
  "bbox": [],
  "geometry": {"coordinates":[-98.116667,24.75],"type":"Point"}
}