{
  "id": 7217067,
  "type": "Feature",
  "properties": {
    "tgn:hierarchy":[
        "tgn:7217067",
        "tgn:7002706",
        "tgn:7002705",
        "tgn:1000003",
        "tgn:1000074",
        "tgn:7029392"
    ],
    "tgn:id":7217067,
    "tgn:name":"Z\u00edfkos",
    "tgn:placetype":[
        "aat:300008347"
    ]
},
  "bbox": [],
  "geometry": {"coordinates":[21.060833,39.486944],"type":"Point"}
}