{
  "id": 7249180,
  "type": "Feature",
  "properties": {
    "tgn:hierarchy":[
        "tgn:7249180",
        "tgn:7007877",
        "tgn:1000003",
        "tgn:1000063",
        "tgn:4012014",
        "tgn:7029392"
    ],
    "tgn:id":7249180,
    "tgn:name":"Neuve Cour",
    "tgn:placetype":[
        "aat:300000206"
    ]
},
  "bbox": [],
  "geometry": {"coordinates":[4.183333,50.683333],"type":"Point"}
}