{
  "id": 7032330,
  "type": "Feature",
  "properties": {
    "tgn:hierarchy":[
        "tgn:7032330",
        "tgn:1000003",
        "tgn:7003682",
        "tgn:7000084",
        "tgn:7029392"
    ],
    "tgn:id":7032330,
    "tgn:name:de":"Riedelberg",
    "tgn:placetype":[
        "aat:300008347",
        "aat:300008375"
    ]
},
  "bbox": [],
  "geometry": {"coordinates":[7.45,49.183333],"type":"Point"}
}