<<<<<<< HEAD
{
  "id": 7480100,
  "type": "Feature",
  "properties": {
    "tgn:hierarchy":[
        "tgn:7480100",
        "tgn:1000004",
        "tgn:7490934",
        "tgn:1000141",
        "tgn:7029392"
    ],
    "tgn:id":7480100,
    "tgn:name":"Dingdian",
    "tgn:placetype":[
        "aat:300008347"
    ]
},
  "bbox": [],
  "geometry": {"coordinates":[120.375874,23.077112],"type":"Point"}
}
=======
{"geometry":{"type":"Point","coordinates":[120.375874,23.077112]},"type":"Feature","properties":{"hierarchy":["tgn:7480100","tgn:1000004","tgn:7490934","tgn:1000141","tgn:7029392"],"placetype":["aat:300008347"],"id":7480100,"name:xx":"Dingdian"}}
>>>>>>> 03f74aca74312dbeaf24d7e61306dd6a786dc3d0
