{
  "id": 1035146,
  "type": "Feature",
  "properties": {
    "tgn:hierarchy":[
        "tgn:1035146",
        "tgn:1000003",
        "tgn:7001097",
        "tgn:1000070",
        "tgn:7029392"
    ],
    "tgn:id":1035146,
    "tgn:name":"Rosenda\u00ebl",
    "tgn:placetype":[
        "aat:300008347"
    ]
},
  "bbox": [],
  "geometry": {"coordinates":[2.404,51.041],"type":"Point"}
}