{
  "id": 7556451,
  "type": "Feature",
  "properties": {
    "tgn:hierarchy":[
        "tgn:7556451",
        "tgn:1000004",
        "tgn:7000198",
        "tgn:7016694",
        "tgn:7029392"
    ],
    "tgn:id":7556451,
    "tgn:name:en":"R\u0101machandi",
    "tgn:placetype":[
        "aat:300008347"
    ]
},
  "bbox": [],
  "geometry": {"coordinates":[85.589824,20.061833],"type":"Point"}
}