{
  "id": 2194777,
  "type": "Feature",
  "properties": {
    "tgn:hierarchy":[
        "tgn:2194777",
        "tgn:1000001",
        "tgn:7012149",
        "tgn:2002264",
        "tgn:7013961",
        "tgn:7029392"
    ],
    "tgn:id":2194777,
    "tgn:name":"Briery Knob",
    "tgn:placetype":[
        "aat:300008798"
    ]
},
  "bbox": [],
  "geometry": {"coordinates":[-80.5833,38.0167],"type":"Point"}
}