{
  "id": 2345165,
  "type": "Feature",
  "properties": {
    "tgn:hierarchy":[
        "tgn:2345165",
        "tgn:1000001",
        "tgn:7012149",
        "tgn:7014334",
        "tgn:7007919",
        "tgn:7029392"
    ],
    "tgn:id":2345165,
    "tgn:name":"Gardys Millpond",
    "tgn:placetype":[
        "aat:300006191"
    ]
},
  "bbox": [],
  "geometry": {"coordinates":[-76.6833,37.9667],"type":"Point"}
}