{
  "id": 7582477,
  "type": "Feature",
  "properties": {
    "tgn:hierarchy":[
        "tgn:7582477",
        "tgn:1000004",
        "tgn:7000198",
        "tgn:7016788",
        "tgn:7029392"
    ],
    "tgn:id":7582477,
    "tgn:name:en":"Dhattarw\u0101la",
    "tgn:placetype":[
        "aat:300008347"
    ]
},
  "bbox": [],
  "geometry": {"coordinates":[75.510728,28.279384],"type":"Point"}
}