{
  "id": 7336730,
  "type": "Feature",
  "properties": {
    "tgn:hierarchy":[
        "tgn:7336730",
        "tgn:7002758",
        "tgn:1001316",
        "tgn:1000003",
        "tgn:1000095",
        "tgn:7029392"
    ],
    "tgn:id":7336730,
    "tgn:name":"Fuente la Bella, Arroyo de",
    "tgn:placetype":[
        "aat:300266554",
        "aat:300008699"
    ]
},
  "bbox": [],
  "geometry": {"coordinates":[-3.35,37.566667],"type":"Point"}
}