{
  "id": 7197234,
  "type": "Feature",
  "properties": {
    "tgn:hierarchy":[
        "tgn:7197234",
        "tgn:7000096",
        "tgn:1000003",
        "tgn:7000084",
        "tgn:7029392"
    ],
    "tgn:id":7197234,
    "tgn:name":"Der Quillow",
    "tgn:placetype":[
        "aat:300008699"
    ]
},
  "bbox": [],
  "geometry": {"coordinates":[13.866667,53.35],"type":"Point"}
}