{
  "id": 7060258,
  "type": "Feature",
  "properties": {
    "tgn:hierarchy":[
        "tgn:7060258",
        "tgn:1000003",
        "tgn:7003688",
        "tgn:7000084",
        "tgn:7029392"
    ],
    "tgn:id":7060258,
    "tgn:name":"Adolfshof",
    "tgn:placetype":[
        "aat:300000206"
    ]
},
  "bbox": [],
  "geometry": {"coordinates":[10.316667,54.333333],"type":"Point"}
}