{
  "id": 2290401,
  "type": "Feature",
  "properties": {
    "tgn:hierarchy":[
        "tgn:2290401",
        "tgn:1000001",
        "tgn:7012149",
        "tgn:2000853",
        "tgn:7007255",
        "tgn:7029392"
    ],
    "tgn:id":2290401,
    "tgn:name":"Doe Branch",
    "tgn:placetype":[
        "aat:300008699"
    ]
},
  "bbox": [],
  "geometry": {"coordinates":[-83.6333,37.7667],"type":"Point"}
}