<<<<<<< HEAD
{
  "id": 2403245,
  "type": "Feature",
  "properties": {
    "tgn:hierarchy":[
        "tgn:2403245",
        "tgn:1000001",
        "tgn:7006451",
        "tgn:7012149",
        "tgn:2000101",
        "tgn:7029392"
    ],
    "tgn:id":2403245,
    "tgn:name":"House Rock Spring",
    "tgn:placetype":[
        "aat:300008697"
    ]
},
  "bbox": [],
  "geometry": {"coordinates":[-111.0333,33.4333],"type":"Point"}
}
=======
{"geometry":{"type":"Point","coordinates":[-111.033300,33.433300]},"type":"Feature","properties":{"hierarchy":["tgn:2403245","tgn:1000001","tgn:7006451","tgn:7012149","tgn:2000101","tgn:7029392"],"placetype":["aat:300008697"],"id":2403245,"name:xx":"House Rock Spring"}}
>>>>>>> 03f74aca74312dbeaf24d7e61306dd6a786dc3d0
