{
  "id": 2225704,
  "type": "Feature",
  "properties": {
    "tgn:hierarchy":[
        "tgn:2225704",
        "tgn:1000001",
        "tgn:2000672",
        "tgn:7012149",
        "tgn:7007254",
        "tgn:7029392"
    ],
    "tgn:id":2225704,
    "tgn:name":"Cat Creek",
    "tgn:placetype":[
        "aat:300008706"
    ]
},
  "bbox": [],
  "geometry": {"coordinates":[-99.7167,37.4333],"type":"Point"}
}