{
  "id": 2416169,
  "type": "Feature",
  "properties": {
    "tgn:hierarchy":[
        "tgn:2416169",
        "tgn:1000001",
        "tgn:7012149",
        "tgn:2000227",
        "tgn:7007158",
        "tgn:7029392"
    ],
    "tgn:id":2416169,
    "tgn:name":"J J Water Spring",
    "tgn:placetype":[
        "aat:300008697"
    ]
},
  "bbox": [],
  "geometry": {"coordinates":[-103.55,37.3833],"type":"Point"}
}