{
  "id": 2566948,
  "type": "Feature",
  "properties": {
    "tgn:hierarchy":[
        "tgn:2566948",
        "tgn:1000001",
        "tgn:7012149",
        "tgn:2000281",
        "tgn:7007240",
        "tgn:7029392"
    ],
    "tgn:id":2566948,
    "tgn:name":"Panther Creek",
    "tgn:placetype":[
        "aat:300008706"
    ]
},
  "bbox": [],
  "geometry": {"coordinates":[-86.65,30.9833],"type":"Point"}
}