{
  "id": 7421055,
  "type": "Feature",
  "properties": {
    "tgn:hierarchy":[
        "tgn:7421055",
        "tgn:1001836",
        "tgn:1000001",
        "tgn:7005560",
        "tgn:7029392"
    ],
    "tgn:id":7421055,
    "tgn:name":"El Mezquital",
    "tgn:placetype":[
        "aat:300008347"
    ]
},
  "bbox": [],
  "geometry": {"coordinates":[-112.340278,26.234167],"type":"Point"}
}