{
  "id": 7273703,
  "type": "Feature",
  "properties": {
    "tgn:hierarchy":[
        "tgn:7273703",
        "tgn:7003619",
        "tgn:1000003",
        "tgn:7016845",
        "tgn:7029392"
    ],
    "tgn:id":7273703,
    "tgn:name:nl":"Wittenberg",
    "tgn:placetype":[
        "aat:300008863"
    ]
},
  "bbox": [],
  "geometry": {"coordinates":[5.733333,52.216667],"type":"Point"}
}