{
  "id": 7384249,
  "type": "Feature",
  "properties": {
    "tgn:hierarchy":[
        "tgn:7384249",
        "tgn:1000001",
        "tgn:1001960",
        "tgn:7005560",
        "tgn:7029392"
    ],
    "tgn:id":7384249,
    "tgn:name":"Mochicahui, Cerro",
    "tgn:placetype":[
        "aat:300008795"
    ]
},
  "bbox": [],
  "geometry": {"coordinates":[-109.666667,27.35],"type":"Point"}
}