{
  "id": 7330941,
  "type": "Feature",
  "properties": {
    "tgn:hierarchy":[
        "tgn:7330941",
        "tgn:7002825",
        "tgn:7016622",
        "tgn:1000003",
        "tgn:1000095",
        "tgn:7029392"
    ],
    "tgn:id":7330941,
    "tgn:name":"Guatisea, Monte",
    "tgn:placetype":[
        "aat:300008795"
    ]
},
  "bbox": [],
  "geometry": {"coordinates":[-13.616667,28.983333],"type":"Point"}
}