{
  "id": 7565279,
  "type": "Feature",
  "properties": {
    "tgn:hierarchy":[
        "tgn:7565279",
        "tgn:1000004",
        "tgn:7000198",
        "tgn:7016722",
        "tgn:7029392"
    ],
    "tgn:id":7565279,
    "tgn:name:en":"Ronaha",
    "tgn:placetype":[
        "aat:300008347"
    ]
},
  "bbox": [],
  "geometry": {"coordinates":[79.509304,26.821179],"type":"Point"}
}