{
  "id": 2094303,
  "type": "Feature",
  "properties": {
    "tgn:hierarchy":[
        "tgn:2094303",
        "tgn:1000001",
        "tgn:1002194",
        "tgn:7012149",
        "tgn:7007710",
        "tgn:7029392"
    ],
    "tgn:id":2094303,
    "tgn:name":"West Burlington",
    "tgn:placetype":[
        "aat:300008347"
    ]
},
  "bbox": [],
  "geometry": {"coordinates":[-76.6667,41.75],"type":"Point"}
}