{
  "id": 7457106,
  "type": "Feature",
  "properties": {
    "tgn:hierarchy":[
        "tgn:7457106",
        "tgn:7002445",
        "tgn:1000003",
        "tgn:7008166",
        "tgn:7008591",
        "tgn:7029392"
    ],
    "tgn:id":7457106,
    "tgn:name:en":"Pickering Moor",
    "tgn:placetype":[
        "aat:300386886"
    ]
},
  "bbox": [],
  "geometry": {"coordinates":[-0.75,54.333333],"type":"Point"}
}