{
  "id": 7316256,
  "type": "Feature",
  "properties": {
    "tgn:hierarchy":[
        "tgn:7316256",
        "tgn:7016598",
        "tgn:1000049",
        "tgn:1000002",
        "tgn:7029392"
    ],
    "tgn:id":7316256,
    "tgn:name":"Cas, Llano de",
    "tgn:placetype":[
        "aat:300008805"
    ]
},
  "bbox": [],
  "geometry": {"coordinates":[-68.033333,-23.45],"type":"Point"}
}