{
  "id": 2615337,
  "type": "Feature",
  "properties": {
    "tgn:hierarchy":[
        "tgn:2615337",
        "tgn:1000001",
        "tgn:7012149",
        "tgn:2001683",
        "tgn:7007707",
        "tgn:7029392"
    ],
    "tgn:id":2615337,
    "tgn:name":"Reservoir Number 4",
    "tgn:placetype":[
        "aat:300006191"
    ]
},
  "bbox": [],
  "geometry": {"coordinates":[-95.9667,34.85],"type":"Point"}
}