{
  "id": 2278933,
  "type": "Feature",
  "properties": {
    "tgn:hierarchy":[
        "tgn:2278933",
        "tgn:1002996",
        "tgn:1000001",
        "tgn:7012149",
        "tgn:7007711",
        "tgn:7029392"
    ],
    "tgn:id":2278933,
    "tgn:name":"Dead Man Spring",
    "tgn:placetype":[
        "aat:300008697"
    ]
},
  "bbox": [],
  "geometry": {"coordinates":[-71.55,41.3833],"type":"Point"}
}