{
  "id": 7324984,
  "type": "Feature",
  "properties": {
    "tgn:hierarchy":[
        "tgn:7324984",
        "tgn:7002759",
        "tgn:7008909",
        "tgn:1000003",
        "tgn:1000095",
        "tgn:7029392"
    ],
    "tgn:id":7324984,
    "tgn:name":"Santa Eulalia de la Pe\u00f1a",
    "tgn:placetype":[
        "aat:300008347"
    ]
},
  "bbox": [],
  "geometry": {"coordinates":[-0.40662,42.262084],"type":"Point"}
}