{
  "id": 7399238,
  "type": "Feature",
  "properties": {
    "tgn:hierarchy":[
        "tgn:7399238",
        "tgn:1000001",
        "tgn:7005593",
        "tgn:7005560",
        "tgn:7029392"
    ],
    "tgn:id":7399238,
    "tgn:name":"Santa Mar\u00eda, R\u00edo",
    "tgn:placetype":[
        "aat:300008699"
    ]
},
  "bbox": [],
  "geometry": {"coordinates":[-99.683333,21.491667],"type":"Point"}
}