{
  "id": 2711640,
  "type": "Feature",
  "properties": {
    "tgn:hierarchy":[
        "tgn:2711640",
        "tgn:1000001",
        "tgn:7012149",
        "tgn:2000811",
        "tgn:7007255",
        "tgn:7029392"
    ],
    "tgn:id":2711640,
    "tgn:name":"Tar Kiln Branch",
    "tgn:placetype":[
        "aat:300008699"
    ]
},
  "bbox": [],
  "geometry": {"coordinates":[-83.35,37.1333],"type":"Point"}
}