{
  "id": 2223693,
  "type": "Feature",
  "properties": {
    "tgn:hierarchy":[
        "tgn:2223693",
        "tgn:1002136",
        "tgn:1000001",
        "tgn:7012149",
        "tgn:7007706",
        "tgn:7029392"
    ],
    "tgn:id":2223693,
    "tgn:name":"Carter Hollow",
    "tgn:placetype":[
        "aat:300008761"
    ]
},
  "bbox": [],
  "geometry": {"coordinates":[-83.65,38.65],"type":"Point"}
}