{
  "id": 7175722,
  "type": "Feature",
  "properties": {
    "tgn:hierarchy":[
        "tgn:7175722",
        "tgn:1000003",
        "tgn:7003688",
        "tgn:7000084",
        "tgn:7029392"
    ],
    "tgn:id":7175722,
    "tgn:name":"Gro\u00dfenrader Holz",
    "tgn:placetype":[
        "aat:300008863"
    ]
},
  "bbox": [],
  "geometry": {"coordinates":[9.233333,54.033333],"type":"Point"}
}