<<<<<<< HEAD
{
  "id": 7371224,
  "type": "Feature",
  "properties": {
    "tgn:hierarchy":[
        "tgn:7371224",
        "tgn:7005581",
        "tgn:1000001",
        "tgn:7005560",
        "tgn:7029392"
    ],
    "tgn:id":7371224,
    "tgn:name":"Rancho Hacebuches",
    "tgn:placetype":[
        "aat:300000241"
    ]
},
  "bbox": [],
  "geometry": {"coordinates":[-105.0,28.883333],"type":"Point"}
}
=======
{"geometry":{"type":"Point","coordinates":[-105.000000,28.883333]},"type":"Feature","properties":{"hierarchy":["tgn:7371224","tgn:7005581","tgn:1000001","tgn:7005560","tgn:7029392"],"placetype":["aat:300000241"],"id":7371224,"name:xx":"Rancho Hacebuches"}}
>>>>>>> 03f74aca74312dbeaf24d7e61306dd6a786dc3d0
