{
  "id": 2731484,
  "type": "Feature",
  "properties": {
    "tgn:hierarchy":[
        "tgn:2731484",
        "tgn:1000001",
        "tgn:2001099",
        "tgn:7012149",
        "tgn:7007522",
        "tgn:7029392"
    ],
    "tgn:id":2731484,
    "tgn:name":"Tula Lake",
    "tgn:placetype":[
        "aat:300008680"
    ]
},
  "bbox": [],
  "geometry": {"coordinates":[-90.4667,34.3167],"type":"Point"}
}