{
  "id": 7265276,
  "type": "Feature",
  "properties": {
    "tgn:hierarchy":[
        "tgn:7265276",
        "tgn:1000003",
        "tgn:7003626",
        "tgn:7016845",
        "tgn:7029392"
    ],
    "tgn:id":7265276,
    "tgn:name:nl":"Kurkswijk",
    "tgn:placetype":[
        "aat:300006075"
    ]
},
  "bbox": [],
  "geometry": {"coordinates":[6.45,52.583333],"type":"Point"}
}