{
  "id": 7120719,
  "type": "Feature",
  "properties": {
    "tgn:hierarchy":[
        "tgn:7120719",
        "tgn:7003669",
        "tgn:1000003",
        "tgn:7000084",
        "tgn:7029392"
    ],
    "tgn:id":7120719,
    "tgn:name":"Pf\u00e4lzerhof",
    "tgn:placetype":[
        "aat:300008347"
    ]
},
  "bbox": [],
  "geometry": {"coordinates":[12.516667,49.65],"type":"Point"}
}