{
  "id": 7403696,
  "type": "Feature",
  "properties": {
    "tgn:hierarchy":[
        "tgn:7403696",
        "tgn:1000001",
        "tgn:1001906",
        "tgn:7005560",
        "tgn:7029392"
    ],
    "tgn:id":7403696,
    "tgn:name":"El Pozo",
    "tgn:placetype":[
        "aat:300008347"
    ]
},
  "bbox": [],
  "geometry": {"coordinates":[-104.466667,21.641667],"type":"Point"}
}