{
  "id": 2695922,
  "type": "Feature",
  "properties": {
    "tgn:hierarchy":[
        "tgn:2695922",
        "tgn:1000001",
        "tgn:7012149",
        "tgn:2002342",
        "tgn:7007922",
        "tgn:7029392"
    ],
    "tgn:id":2695922,
    "tgn:name":"Stockley Creek",
    "tgn:placetype":[
        "aat:300008706"
    ]
},
  "bbox": [],
  "geometry": {"coordinates":[-89.1167,45.5333],"type":"Point"}
}