{
  "id": 2044701,
  "type": "Feature",
  "properties": {
    "tgn:hierarchy":[
        "tgn:2044701",
        "tgn:1000001",
        "tgn:7012149",
        "tgn:2000930",
        "tgn:7007515",
        "tgn:7029392"
    ],
    "tgn:id":2044701,
    "tgn:name":"Dogtown",
    "tgn:placetype":[
        "aat:300008347",
        "aat:300387210"
    ]
},
  "bbox": [],
  "geometry": {"coordinates":[-69.35,44.7833],"type":"Point"}
}