{
  "id": 2036553,
  "type": "Feature",
  "properties": {
    "tgn:hierarchy":[
        "tgn:2036553",
        "tgn:1000001",
        "tgn:2000694",
        "tgn:7012149",
        "tgn:7007254",
        "tgn:7029392"
    ],
    "tgn:id":2036553,
    "tgn:name":"Ingalls",
    "tgn:placetype":[
        "aat:300008347"
    ]
},
  "bbox": [],
  "geometry": {"coordinates":[-100.45,37.8167],"type":"Point"}
}