{
  "id": 2781535,
  "type": "Feature",
  "properties": {
    "tgn:hierarchy":[
        "tgn:2781535",
        "tgn:1002156",
        "tgn:1000001",
        "tgn:7012149",
        "tgn:7007706",
        "tgn:7029392"
    ],
    "tgn:id":2781535,
    "tgn:name":"Woodmere",
    "tgn:placetype":[
        "aat:300008347"
    ]
},
  "bbox": [],
  "geometry": {"coordinates":[-80.9333,41.85],"type":"Point"}
}