{
  "id": 2511361,
  "type": "Feature",
  "properties": {
    "tgn:hierarchy":[
        "tgn:2511361",
        "tgn:7002659",
        "tgn:1000001",
        "tgn:7012149",
        "tgn:2000025",
        "tgn:7029392"
    ],
    "tgn:id":2511361,
    "tgn:name":"Milam Lake",
    "tgn:placetype":[
        "aat:300006191"
    ]
},
  "bbox": [],
  "geometry": {"coordinates":[-86.1833,32.6333],"type":"Point"}
}