{
  "id": 2685138,
  "type": "Feature",
  "properties": {
    "tgn:hierarchy":[
        "tgn:2685138",
        "tgn:1000001",
        "tgn:1002840",
        "tgn:7012149",
        "tgn:7007828",
        "tgn:7029392"
    ],
    "tgn:id":2685138,
    "tgn:name":"Spoon Mountain",
    "tgn:placetype":[
        "aat:300008798"
    ]
},
  "bbox": [],
  "geometry": {"coordinates":[-73.0667,43.4667],"type":"Point"}
}