{
  "id": 7470659,
  "type": "Feature",
  "properties": {
    "tgn:hierarchy":[
        "tgn:7470659",
        "tgn:1000004",
        "tgn:7001009",
        "tgn:1000141",
        "tgn:7029392"
    ],
    "tgn:id":7470659,
    "tgn:name":"Qingshui",
    "tgn:placetype":[
        "aat:300008347"
    ]
},
  "bbox": [],
  "geometry": {"coordinates":[120.568056,24.270278],"type":"Point"}
}