{
  "id": 7050056,
  "type": "Feature",
  "properties": {
    "tgn:hierarchy":[
        "tgn:7050056",
        "tgn:7003008",
        "tgn:1000003",
        "tgn:7002997",
        "tgn:1000080",
        "tgn:7029392"
    ],
    "tgn:id":7050056,
    "tgn:name":"Meda",
    "tgn:placetype":[
        "aat:300008347"
    ]
},
  "bbox": [],
  "geometry": {"coordinates":[11.383333,45.766667],"type":"Point"}
}