<<<<<<< HEAD
{
  "id": 7050056,
  "type": "Feature",
  "properties": {
    "tgn:hierarchy":[
        "tgn:7050056",
        "tgn:7003008",
        "tgn:1000003",
        "tgn:7002997",
        "tgn:1000080",
        "tgn:7029392"
    ],
    "tgn:id":7050056,
    "tgn:name":"Meda",
    "tgn:placetype":[
        "aat:300008347"
    ]
},
  "bbox": [],
  "geometry": {"coordinates":[11.383333,45.766667],"type":"Point"}
}
=======
{"geometry":{"type":"Point","coordinates":[11.383333,45.766667]},"type":"Feature","properties":{"hierarchy":["tgn:7050056","tgn:7003008","tgn:1000003","tgn:7002997","tgn:1000080","tgn:7029392"],"placetype":["aat:300008347"],"id":7050056,"name:xx":"Meda"}}
>>>>>>> 03f74aca74312dbeaf24d7e61306dd6a786dc3d0
