{
  "id": 2663718,
  "type": "Feature",
  "properties": {
    "tgn:hierarchy":[
        "tgn:2663718",
        "tgn:1000001",
        "tgn:7012149",
        "tgn:1003038",
        "tgn:7007517",
        "tgn:7029392"
    ],
    "tgn:id":2663718,
    "tgn:name":"Silver Lake",
    "tgn:placetype":[
        "aat:300006191"
    ]
},
  "bbox": [],
  "geometry": {"coordinates":[-71.65,42.1833],"type":"Point"}
}