{
  "id": 7159812,
  "type": "Feature",
  "properties": {
    "tgn:hierarchy":[
        "tgn:7159812",
        "tgn:1000003",
        "tgn:7003676",
        "tgn:7000084",
        "tgn:7029392"
    ],
    "tgn:id":7159812,
    "tgn:name":"Hohnstorf",
    "tgn:placetype":[
        "aat:300008347"
    ]
},
  "bbox": [],
  "geometry": {"coordinates":[10.55,53.366667],"type":"Point"}
}