{
  "id": 2601350,
  "type": "Feature",
  "properties": {
    "tgn:hierarchy":[
        "tgn:2601350",
        "tgn:1000001",
        "tgn:7012149",
        "tgn:2002169",
        "tgn:7007919",
        "tgn:7029392"
    ],
    "tgn:id":2601350,
    "tgn:name":"Purchase Ridge",
    "tgn:placetype":[
        "aat:300266640"
    ]
},
  "bbox": [],
  "geometry": {"coordinates":[-82.7833,36.6833],"type":"Point"}
}