{
  "id": 7099395,
  "type": "Feature",
  "properties": {
    "tgn:hierarchy":[
        "tgn:7099395",
        "tgn:1000003",
        "tgn:7003688",
        "tgn:7000084",
        "tgn:7029392"
    ],
    "tgn:id":7099395,
    "tgn:name":"Sierhagen",
    "tgn:placetype":[
        "aat:300008347"
    ]
},
  "bbox": [],
  "geometry": {"coordinates":[10.783333,54.133333],"type":"Point"}
}