{
  "id": 7277861,
  "type": "Feature",
  "properties": {
    "tgn:hierarchy":[
        "tgn:7277861",
        "tgn:1001702",
        "tgn:1000049",
        "tgn:1000002",
        "tgn:7029392"
    ],
    "tgn:id":7277861,
    "tgn:name":"Ventisquero, Bah\u00eda",
    "tgn:placetype":[
        "aat:300132316"
    ]
},
  "bbox": [],
  "geometry": {"coordinates":[-72.916667,-53.366667],"type":"Point"}
}