{
  "id": 7305874,
  "type": "Feature",
  "properties": {
    "tgn:hierarchy":[
        "tgn:7305874",
        "tgn:1001439",
        "tgn:1000003",
        "tgn:7002797",
        "tgn:1000095",
        "tgn:7029392"
    ],
    "tgn:id":7305874,
    "tgn:name":"Los Cantareros",
    "tgn:placetype":[
        "aat:300008347"
    ]
},
  "bbox": [],
  "geometry": {"coordinates":[-1.383333,37.716667],"type":"Point"}
}