{
  "id": 1117876,
  "type": "Feature",
  "properties": {
    "tgn:hierarchy":[
        "tgn:1117876",
        "tgn:7005685",
        "tgn:1000001",
        "tgn:7013154",
        "tgn:7029392"
    ],
    "tgn:id":1117876,
    "tgn:name":"Red Lake",
    "tgn:placetype":[
        "aat:300008680"
    ]
},
  "bbox": [],
  "geometry": {"coordinates":[-93.9167,51.0833],"type":"Point"}
}