{
  "id": 2203282,
  "type": "Feature",
  "properties": {
    "tgn:hierarchy":[
        "tgn:2203282",
        "tgn:1000001",
        "tgn:7012149",
        "tgn:7029392"
    ],
    "tgn:id":2203282,
    "tgn:name":"Buckhorn Knob",
    "tgn:placetype":[
        "aat:300008798"
    ]
},
  "bbox": [],
  "geometry": {"coordinates":[-80.9667,37.2833],"type":"Point"}
}