{
  "id": 7010208,
  "type": "Feature",
  "properties": {
    "tgn:hierarchy":[
        "tgn:7010208",
        "tgn:1000003",
        "tgn:7002890",
        "tgn:1000070",
        "tgn:7029392"
    ],
    "tgn:id":7010208,
    "tgn:name":"Beugneux",
    "tgn:placetype":[
        "aat:300008347"
    ]
},
  "bbox": [],
  "geometry": {"coordinates":[3.4167,49.2333],"type":"Point"}
}