{
  "id": 7585450,
  "type": "Feature",
  "properties": {
    "tgn:hierarchy":[
        "tgn:7585450",
        "tgn:1000004",
        "tgn:7000198",
        "tgn:7016722",
        "tgn:7029392"
    ],
    "tgn:id":7585450,
    "tgn:name:en":"Asaupura",
    "tgn:placetype":[
        "aat:300008347"
    ]
},
  "bbox": [],
  "geometry": {"coordinates":[78.481441,24.890844],"type":"Point"}
}