{
  "id": 2149720,
  "type": "Feature",
  "properties": {
    "tgn:hierarchy":[
        "tgn:2149720",
        "tgn:2001004",
        "tgn:1000001",
        "tgn:7012149",
        "tgn:7007521",
        "tgn:7029392"
    ],
    "tgn:id":2149720,
    "tgn:name":"Barry Lake",
    "tgn:placetype":[
        "aat:300008680"
    ]
},
  "bbox": [],
  "geometry": {"coordinates":[-96.5667,45.5667],"type":"Point"}
}