{
  "id": 2529653,
  "type": "Feature",
  "properties": {
    "tgn:hierarchy":[
        "tgn:2529653",
        "tgn:1000001",
        "tgn:7012149",
        "tgn:7007157",
        "tgn:1002621",
        "tgn:7029392"
    ],
    "tgn:id":2529653,
    "tgn:name":"Mud Lakes",
    "tgn:placetype":[
        "aat:300008680"
    ]
},
  "bbox": [],
  "geometry": {"coordinates":[-119.4167,37.5333],"type":"Point"}
}