{
  "id": 7178013,
  "type": "Feature",
  "properties": {
    "tgn:hierarchy":[
        "tgn:7178013",
        "tgn:1000003",
        "tgn:7003678",
        "tgn:7000084",
        "tgn:7029392"
    ],
    "tgn:id":7178013,
    "tgn:name":"Hain Kopf",
    "tgn:placetype":[
        "aat:300008777"
    ]
},
  "bbox": [],
  "geometry": {"coordinates":[8.933333,50.966667],"type":"Point"}
}