{
  "id": 7330947,
  "type": "Feature",
  "properties": {
    "tgn:hierarchy":[
        "tgn:7330947",
        "tgn:7002759",
        "tgn:7008909",
        "tgn:1000003",
        "tgn:1000095",
        "tgn:7029392"
    ],
    "tgn:id":7330947,
    "tgn:name":"Guasa",
    "tgn:placetype":[
        "aat:300008347"
    ]
},
  "bbox": [],
  "geometry": {"coordinates":[-0.512795,42.56792],"type":"Point"}
}