{
  "id": 1065372,
  "type": "Feature",
  "properties": {
    "tgn:hierarchy":[
        "tgn:1065372",
        "tgn:7016612",
        "tgn:1000004",
        "tgn:1001293",
        "tgn:7029392"
    ],
    "tgn:id":1065372,
    "tgn:name":"Adraskan",
    "tgn:placetype":[
        "aat:300008347"
    ]
},
  "bbox": [],
  "geometry": {"coordinates":[62.2667,33.6333],"type":"Point"}
}