{
  "id": 7593618,
  "type": "Feature",
  "properties": {
    "tgn:hierarchy":[
        "tgn:7593618",
        "tgn:1000001",
        "tgn:7005605",
        "tgn:7029392"
    ],
    "tgn:id":7593618,
    "tgn:name":"Trinity Palmetto Point",
    "tgn:placetype":[
        "aat:300387064",
        "aat:300387092"
    ]
},
  "bbox": [],
  "geometry": {"coordinates":[-62.766,17.316],"type":"Point"}
}