{
  "id": 7485784,
  "type": "Feature",
  "properties": {
    "tgn:hierarchy":[
        "tgn:7485784",
        "tgn:1000004",
        "tgn:7001014",
        "tgn:1000141",
        "tgn:7029392"
    ],
    "tgn:id":7485784,
    "tgn:name":"Bade Qiao",
    "tgn:placetype":[
        "aat:300007836"
    ]
},
  "bbox": [],
  "geometry": {"coordinates":[120.6225,23.693333],"type":"Point"}
}