{
  "id": 7568784,
  "type": "Feature",
  "properties": {
    "tgn:hierarchy":[
        "tgn:7568784",
        "tgn:1000004",
        "tgn:7000198",
        "tgn:7016722",
        "tgn:7029392"
    ],
    "tgn:id":7568784,
    "tgn:name:en":"Jos",
    "tgn:placetype":[
        "aat:300008347"
    ]
},
  "bbox": [],
  "geometry": {"coordinates":[77.402222,29.579722],"type":"Point"}
}