{
  "id": 7288922,
  "type": "Feature",
  "properties": {
    "tgn:hierarchy":[
        "tgn:7288922",
        "tgn:1001657",
        "tgn:1000049",
        "tgn:1000002",
        "tgn:7029392"
    ],
    "tgn:id":7288922,
    "tgn:name":"Laguna de la Overa Primero, Paso de la",
    "tgn:placetype":[
        "aat:300259572"
    ]
},
  "bbox": [],
  "geometry": {"coordinates":[-70.433333,-31.116667],"type":"Point"}
}