{
  "id": 2571352,
  "type": "Feature",
  "properties": {
    "tgn:hierarchy":[
        "tgn:2571352",
        "tgn:1000001",
        "tgn:2000272",
        "tgn:7012149",
        "tgn:7007240",
        "tgn:7029392"
    ],
    "tgn:id":2571352,
    "tgn:name":"Paul Island",
    "tgn:placetype":[
        "aat:300008791"
    ]
},
  "bbox": [],
  "geometry": {"coordinates":[-85.8333,30.8167],"type":"Point"}
}