{
  "id": 7197434,
  "type": "Feature",
  "properties": {
    "tgn:hierarchy":[
        "tgn:7197434",
        "tgn:1000003",
        "tgn:7003682",
        "tgn:7000084",
        "tgn:7029392"
    ],
    "tgn:id":7197434,
    "tgn:name":"Dermbach",
    "tgn:placetype":[
        "aat:300008347"
    ]
},
  "bbox": [],
  "geometry": {"coordinates":[7.95,50.783333],"type":"Point"}
}