{
  "id": 1071096,
  "type": "Feature",
  "properties": {
    "tgn:hierarchy":[
        "tgn:1071096",
        "tgn:1000004",
        "tgn:7002087",
        "tgn:1000111",
        "tgn:7029392"
    ],
    "tgn:id":1071096,
    "tgn:name":"Qingshuixi",
    "tgn:placetype":[
        "aat:300008347"
    ]
},
  "bbox": [],
  "geometry": {"coordinates":[103.9167,29.1667],"type":"Point"}
}