{
  "id": 1036729,
  "type": "Feature",
  "properties": {
    "tgn:hierarchy":[
        "tgn:1036729",
        "tgn:1000003",
        "tgn:7000094",
        "tgn:7000084",
        "tgn:7029392"
    ],
    "tgn:id":1036729,
    "tgn:name":"Friedrichsruhe",
    "tgn:placetype":[
        "aat:300008347"
    ]
},
  "bbox": [],
  "geometry": {"coordinates":[11.733333,53.516667],"type":"Point"}
}