{
  "id": 2772370,
  "type": "Feature",
  "properties": {
    "tgn:hierarchy":[
        "tgn:2772370",
        "tgn:1000001",
        "tgn:2001704",
        "tgn:7012149",
        "tgn:7007708",
        "tgn:7029392"
    ],
    "tgn:id":2772370,
    "tgn:name":"William Miller Creek",
    "tgn:placetype":[
        "aat:300008706"
    ]
},
  "bbox": [],
  "geometry": {"coordinates":[-124.2667,42.4667],"type":"Point"}
}