{
  "id": 2126344,
  "type": "Feature",
  "properties": {
    "tgn:hierarchy":[
        "tgn:2126344",
        "tgn:1000001",
        "tgn:7012149",
        "tgn:2001990",
        "tgn:7007826",
        "tgn:7029392"
    ],
    "tgn:id":2126344,
    "tgn:name":"Adobe Creek",
    "tgn:placetype":[
        "aat:300008706"
    ]
},
  "bbox": [],
  "geometry": {"coordinates":[-99.05,30.3667],"type":"Point"}
}