{
  "id": 2550186,
  "type": "Feature",
  "properties": {
    "tgn:hierarchy":[
        "tgn:2550186",
        "tgn:1000001",
        "tgn:7012149",
        "tgn:1002439",
        "tgn:7007252",
        "tgn:7029392"
    ],
    "tgn:id":2550186,
    "tgn:name":"Northern Beach",
    "tgn:placetype":[
        "aat:300008347"
    ]
},
  "bbox": [],
  "geometry": {"coordinates":[-86.0667,39.95],"type":"Point"}
}