{
  "id": 2608833,
  "type": "Feature",
  "properties": {
    "tgn:hierarchy":[
        "tgn:2608833",
        "tgn:1000001",
        "tgn:7012149",
        "tgn:1002990",
        "tgn:7007708",
        "tgn:7029392"
    ],
    "tgn:id":2608833,
    "tgn:name":"Rattlesnake Spring",
    "tgn:placetype":[
        "aat:300008697"
    ]
},
  "bbox": [],
  "geometry": {"coordinates":[-120.5167,45.0167],"type":"Point"}
}