{
  "id": 7291831,
  "type": "Feature",
  "properties": {
    "tgn:hierarchy":[
        "tgn:7291831",
        "tgn:1001637",
        "tgn:1000049",
        "tgn:1000002",
        "tgn:7029392"
    ],
    "tgn:id":7291831,
    "tgn:name":"Flores, Laguna",
    "tgn:placetype":[
        "aat:300008680"
    ]
},
  "bbox": [],
  "geometry": {"coordinates":[-72.533333,-37.15],"type":"Point"}
}