{
  "id": 2710060,
  "type": "Feature",
  "properties": {
    "tgn:hierarchy":[
        "tgn:2710060",
        "tgn:1000001",
        "tgn:7012149",
        "tgn:2000494",
        "tgn:7007250",
        "tgn:7029392"
    ],
    "tgn:id":2710060,
    "tgn:name":"Talc Creek",
    "tgn:placetype":[
        "aat:300008706"
    ]
},
  "bbox": [],
  "geometry": {"coordinates":[-115.1333,45.0667],"type":"Point"}
}