{
  "id": 2633613,
  "type": "Feature",
  "properties": {
    "tgn:hierarchy":[
        "tgn:2633613",
        "tgn:1000001",
        "tgn:7012149",
        "tgn:7007157",
        "tgn:2000189",
        "tgn:7029392"
    ],
    "tgn:id":2633613,
    "tgn:name":"Rusby Gulch",
    "tgn:placetype":[
        "aat:300008761"
    ]
},
  "bbox": [],
  "geometry": {"coordinates":[-122.8167,41.7333],"type":"Point"}
}