<<<<<<< HEAD
{
  "id": 2334100,
  "type": "Feature",
  "properties": {
    "tgn:hierarchy":[
        "tgn:2334100",
        "tgn:1000001",
        "tgn:1002328",
        "tgn:7012149",
        "tgn:7007568",
        "tgn:7029392"
    ],
    "tgn:id":2334100,
    "tgn:name":"Fords Hill",
    "tgn:placetype":[
        "aat:300008798"
    ]
},
  "bbox": [],
  "geometry": {"coordinates":[-74.7333,42.1667],"type":"Point"}
}
=======
{"geometry":{"type":"Point","coordinates":[-74.733300,42.166700]},"type":"Feature","properties":{"hierarchy":["tgn:2334100","tgn:1000001","tgn:1002328","tgn:7012149","tgn:7007568","tgn:7029392"],"placetype":["aat:300008798"],"id":2334100,"name:xx":"Fords Hill"}}
>>>>>>> 03f74aca74312dbeaf24d7e61306dd6a786dc3d0
