{
  "id": 2237430,
  "type": "Feature",
  "properties": {
    "tgn:hierarchy":[
        "tgn:2237430",
        "tgn:1000001",
        "tgn:7012149",
        "tgn:7007709",
        "tgn:7029392"
    ],
    "tgn:id":2237430,
    "tgn:name":"China Creek",
    "tgn:placetype":[
        "aat:300008706"
    ]
},
  "bbox": [],
  "geometry": {"coordinates":[-81.6833,36.1333],"type":"Point"}
}