{
  "id": 7583399,
  "type": "Feature",
  "properties": {
    "tgn:hierarchy":[
        "tgn:7583399",
        "tgn:1000004",
        "tgn:7000198",
        "tgn:7016722",
        "tgn:7029392"
    ],
    "tgn:id":7583399,
    "tgn:name:en":"P\u0101h North Reserved Forest",
    "tgn:placetype":[
        "aat:300008865"
    ]
},
  "bbox": [],
  "geometry": {"coordinates":[78.666158,24.70331],"type":"Point"}
}