{
  "id": 7321444,
  "type": "Feature",
  "properties": {
    "tgn:hierarchy":[
        "tgn:7321444",
        "tgn:1001623",
        "tgn:1000049",
        "tgn:1000002",
        "tgn:7029392"
    ],
    "tgn:id":7321444,
    "tgn:name":"Camargo, Punta",
    "tgn:placetype":[
        "aat:300386846"
    ]
},
  "bbox": [],
  "geometry": {"coordinates":[-72.75,-44.45],"type":"Point"}
}