{
  "id": 7495883,
  "type": "Feature",
  "properties": {
    "tgn:hierarchy":[
        "tgn:7495883",
        "tgn:7001001",
        "tgn:1000004",
        "tgn:1000141",
        "tgn:7029392"
    ],
    "tgn:id":7495883,
    "tgn:name":"Shuiniucuo",
    "tgn:placetype":[
        "aat:300387033"
    ]
},
  "bbox": [],
  "geometry": {"coordinates":[120.383124,23.503448],"type":"Point"}
}