<<<<<<< HEAD
{
  "id": 2408968,
  "type": "Feature",
  "properties": {
    "tgn:hierarchy":[
        "tgn:2408968",
        "tgn:1000001",
        "tgn:2001638",
        "tgn:7012149",
        "tgn:7007707",
        "tgn:7029392"
    ],
    "tgn:id":2408968,
    "tgn:name":"I-See-O Tank",
    "tgn:placetype":[
        "aat:300006191"
    ]
},
  "bbox": [],
  "geometry": {"coordinates":[-98.3,34.7],"type":"Point"}
}
=======
{"geometry":{"type":"Point","coordinates":[-98.300000,34.700000]},"type":"Feature","properties":{"hierarchy":["tgn:2408968","tgn:1000001","tgn:2001638","tgn:7012149","tgn:7007707","tgn:7029392"],"placetype":["aat:300006191"],"id":2408968,"name:xx":"I-See-O Tank"}}
>>>>>>> 03f74aca74312dbeaf24d7e61306dd6a786dc3d0
