{
  "id": 7344888,
  "type": "Feature",
  "properties": {
    "tgn:hierarchy":[
        "tgn:7344888",
        "tgn:7008912",
        "tgn:7030216",
        "tgn:1000003",
        "tgn:1000095",
        "tgn:7029392"
    ],
    "tgn:id":7344888,
    "tgn:name":"Altr\u00f3n",
    "tgn:placetype":[
        "aat:300008347"
    ]
},
  "bbox": [],
  "geometry": {"coordinates":[1.1035,42.45045],"type":"Point"}
}