{
  "id": 2234379,
  "type": "Feature",
  "properties": {
    "tgn:hierarchy":[
        "tgn:2234379",
        "tgn:1000001",
        "tgn:7012149",
        "tgn:2000930",
        "tgn:7007515",
        "tgn:7029392"
    ],
    "tgn:id":2234379,
    "tgn:name":"Cheney Pond",
    "tgn:placetype":[
        "aat:300006191"
    ]
},
  "bbox": [],
  "geometry": {"coordinates":[-70.1833,45.8833],"type":"Point"}
}