{
  "id": 2356246,
  "type": "Feature",
  "properties": {
    "tgn:hierarchy":[
        "tgn:2356246",
        "tgn:1000001",
        "tgn:2002108",
        "tgn:7012149",
        "tgn:7007827",
        "tgn:7029392"
    ],
    "tgn:id":2356246,
    "tgn:name":"Gooseberry Spring",
    "tgn:placetype":[
        "aat:300008697"
    ]
},
  "bbox": [],
  "geometry": {"coordinates":[-110.5833,39.1833],"type":"Point"}
}