<<<<<<< HEAD
{
  "id": 7024013,
  "type": "Feature",
  "properties": {
    "tgn:hierarchy":[
        "tgn:7024013",
        "tgn:7003820",
        "tgn:1000003",
        "tgn:1000090",
        "tgn:7029392"
    ],
    "tgn:id":7024013,
    "tgn:name":"Condeixa-a-Velha",
    "tgn:placetype":[
        "aat:300008347",
        "aat:300008372"
    ]
},
  "bbox": [],
  "geometry": {"coordinates":[-8.494,40.101],"type":"Point"}
}
=======
{"geometry":{"type":"Point","coordinates":[-8.494000,40.101000]},"type":"Feature","properties":{"hierarchy":["tgn:7024013","tgn:7003820","tgn:1000003","tgn:1000090","tgn:7029392"],"placetype":["aat:300008347","aat:300008372"],"id":7024013,"name:xx":"Condeixa-a-Velha"}}
>>>>>>> 03f74aca74312dbeaf24d7e61306dd6a786dc3d0
