{
  "id": 7503833,
  "type": "Feature",
  "properties": {
    "tgn:hierarchy":[
        "tgn:7503833",
        "tgn:1000004",
        "tgn:7491221",
        "tgn:1000141",
        "tgn:7029392"
    ],
    "tgn:id":7503833,
    "tgn:name":"Zhiben Shanzhuang",
    "tgn:placetype":[
        "aat:300005567"
    ]
},
  "bbox": [],
  "geometry": {"coordinates":[120.991111,22.687778],"type":"Point"}
}