{
  "id": 7429898,
  "type": "Feature",
  "properties": {
    "tgn:hierarchy":[
        "tgn:7429898",
        "tgn:7005583",
        "tgn:1000001",
        "tgn:7005560",
        "tgn:7029392"
    ],
    "tgn:id":7429898,
    "tgn:name":"Cuesta Colorada",
    "tgn:placetype":[
        "aat:300008347"
    ]
},
  "bbox": [],
  "geometry": {"coordinates":[-104.966667,24.666667],"type":"Point"}
}