{
  "id": 7361914,
  "type": "Feature",
  "properties": {
    "tgn:hierarchy":[
        "tgn:7361914",
        "tgn:7005586",
        "tgn:1000001",
        "tgn:7005560",
        "tgn:7029392"
    ],
    "tgn:id":7361914,
    "tgn:name":"El Cuis",
    "tgn:placetype":[
        "aat:300008347"
    ]
},
  "bbox": [],
  "geometry": {"coordinates":[-104.116667,20.533333],"type":"Point"}
}