{
  "id": 7142528,
  "type": "Feature",
  "properties": {
    "tgn:hierarchy":[
        "tgn:7142528",
        "tgn:1000003",
        "tgn:7003677",
        "tgn:7000084",
        "tgn:7029392"
    ],
    "tgn:id":7142528,
    "tgn:name":"Lohhof",
    "tgn:placetype":[
        "aat:300000206"
    ]
},
  "bbox": [],
  "geometry": {"coordinates":[6.683333,51.133333],"type":"Point"}
}