{
  "id": 2199680,
  "type": "Feature",
  "properties": {
    "tgn:hierarchy":[
        "tgn:2199680",
        "tgn:1000001",
        "tgn:1002724",
        "tgn:7012149",
        "tgn:7007517",
        "tgn:7029392"
    ],
    "tgn:id":2199680,
    "tgn:name":"Brush Island",
    "tgn:placetype":[
        "aat:300008791"
    ]
},
  "bbox": [],
  "geometry": {"coordinates":[-70.7833,42.25],"type":"Point"}
}