{
  "id": 7540580,
  "type": "Feature",
  "properties": {
    "tgn:hierarchy":[
        "tgn:7540580",
        "tgn:7001242",
        "tgn:7016833",
        "tgn:7000123",
        "tgn:7029392"
    ],
    "tgn:id":7540580,
    "tgn:name:en":"Naj' Haww\u0101rah",
    "tgn:placetype":[
        "aat:300008347"
    ]
},
  "bbox": [],
  "geometry": {"coordinates":[32.35,26.066667],"type":"Point"}
}