{
  "id": 2773575,
  "type": "Feature",
  "properties": {
    "tgn:hierarchy":[
        "tgn:2773575",
        "tgn:1000001",
        "tgn:7012149",
        "tgn:2002173",
        "tgn:7007919",
        "tgn:7029392"
    ],
    "tgn:id":2773575,
    "tgn:name":"Williston Branch",
    "tgn:placetype":[
        "aat:300008699"
    ]
},
  "bbox": [],
  "geometry": {"coordinates":[-78.6333,36.5833],"type":"Point"}
}