{
  "id": 7226021,
  "type": "Feature",
  "properties": {
    "tgn:hierarchy":[
        "tgn:7226021",
        "tgn:7002690",
        "tgn:7012056",
        "tgn:1000003",
        "tgn:1000074",
        "tgn:7029392"
    ],
    "tgn:id":7226021,
    "tgn:name":"Mourtzan\u00e1",
    "tgn:placetype":[
        "aat:300008347"
    ]
},
  "bbox": [],
  "geometry": {"coordinates":[24.783333,35.35],"type":"Point"}
}