{
  "id": 7218349,
  "type": "Feature",
  "properties": {
    "tgn:hierarchy":[
        "tgn:7218349",
        "tgn:4003773",
        "tgn:7001395",
        "tgn:1000003",
        "tgn:1000074",
        "tgn:7029392"
    ],
    "tgn:id":7218349,
    "tgn:name":"Xerovo\u00fani",
    "tgn:placetype":[
        "aat:300008777"
    ]
},
  "bbox": [],
  "geometry": {"coordinates":[22.45,39.016667],"type":"Point"}
}