{
  "id": 7213768,
  "type": "Feature",
  "properties": {
    "tgn:hierarchy":[
        "tgn:7213768",
        "tgn:7003692",
        "tgn:1000003",
        "tgn:7000084",
        "tgn:7029392"
    ],
    "tgn:id":7213768,
    "tgn:name":"Birkholz",
    "tgn:placetype":[
        "aat:300000206"
    ]
},
  "bbox": [],
  "geometry": {"coordinates":[10.016667,48.916667],"type":"Point"}
}