{
  "id": 7388402,
  "type": "Feature",
  "properties": {
    "tgn:hierarchy":[
        "tgn:7388402",
        "tgn:1001853",
        "tgn:1000001",
        "tgn:7005560",
        "tgn:7029392"
    ],
    "tgn:id":7388402,
    "tgn:name":"Puerto Rico",
    "tgn:placetype":[
        "aat:300000241"
    ]
},
  "bbox": [],
  "geometry": {"coordinates":[-102.816667,29.166667],"type":"Point"}
}