{
  "id": 7415541,
  "type": "Feature",
  "properties": {
    "tgn:hierarchy":[
        "tgn:7415541",
        "tgn:1000001",
        "tgn:7005591",
        "tgn:7005560",
        "tgn:7029392"
    ],
    "tgn:id":7415541,
    "tgn:name:es":"Loma Bonita",
    "tgn:placetype":[
        "aat:300008347"
    ]
},
  "bbox": [],
  "geometry": {"coordinates":[-97.945833,17.054167],"type":"Point"}
}