{
  "id": 1130768,
  "type": "Feature",
  "properties": {
    "tgn:hierarchy":[
        "tgn:1130768",
        "tgn:1000003",
        "tgn:7001097",
        "tgn:1000070",
        "tgn:7029392"
    ],
    "tgn:id":1130768,
    "tgn:name":"Ternoise",
    "tgn:placetype":[
        "aat:300008707"
    ]
},
  "bbox": [],
  "geometry": {"coordinates":[2.0167,50.3833],"type":"Point"}
}