{
  "id": 7186435,
  "type": "Feature",
  "properties": {
    "tgn:hierarchy":[
        "tgn:7186435",
        "tgn:1000003",
        "tgn:7003676",
        "tgn:7000084",
        "tgn:7029392"
    ],
    "tgn:id":7186435,
    "tgn:name":"Grabstederfeld",
    "tgn:placetype":[
        "aat:300387200"
    ]
},
  "bbox": [],
  "geometry": {"coordinates":[7.983333,53.35],"type":"Point"}
}