<<<<<<< HEAD
{
  "id": 7486794,
  "type": "Feature",
  "properties": {
    "tgn:hierarchy":[
        "tgn:7486794",
        "tgn:1000004",
        "tgn:7492971",
        "tgn:1000141",
        "tgn:7029392"
    ],
    "tgn:id":7486794,
    "tgn:name":"Ligang Xiang",
    "tgn:placetype":[
        "aat:300387173"
    ]
},
  "bbox": [],
  "geometry": {"coordinates":[120.5,22.8],"type":"Point"}
}
=======
{"geometry":{"type":"Point","coordinates":[120.500000,22.800000]},"type":"Feature","properties":{"hierarchy":["tgn:7486794","tgn:1000004","tgn:7492971","tgn:1000141","tgn:7029392"],"placetype":["aat:300387173"],"id":7486794,"name:xx":"Ligang Xiang"}}
>>>>>>> 03f74aca74312dbeaf24d7e61306dd6a786dc3d0
