<<<<<<< HEAD
{
  "id": 7021451,
  "type": "Feature",
  "properties": {
    "tgn:hierarchy":[
        "tgn:7021451",
        "tgn:1000001",
        "tgn:2000263",
        "tgn:7012149",
        "tgn:7007240",
        "tgn:7029392"
    ],
    "tgn:id":7021451,
    "tgn:name":"Cow Ponds",
    "tgn:placetype":[
        "aat:300008680"
    ]
},
  "bbox": [],
  "geometry": {"coordinates":[-83.0167,29.7],"type":"Point"}
}
=======
{"geometry":{"type":"Point","coordinates":[-83.016700,29.700000]},"type":"Feature","properties":{"hierarchy":["tgn:7021451","tgn:1000001","tgn:2000263","tgn:7012149","tgn:7007240","tgn:7029392"],"placetype":["aat:300008680"],"id":7021451,"name:xx":"Cow Ponds"}}
>>>>>>> 03f74aca74312dbeaf24d7e61306dd6a786dc3d0
