{
  "id": 2648231,
  "type": "Feature",
  "properties": {
    "tgn:hierarchy":[
        "tgn:2648231",
        "tgn:1000001",
        "tgn:7012149",
        "tgn:2001927",
        "tgn:7007825",
        "tgn:7029392"
    ],
    "tgn:id":2648231,
    "tgn:name":"Schote Hollow",
    "tgn:placetype":[
        "aat:300008761"
    ]
},
  "bbox": [],
  "geometry": {"coordinates":[-87.9833,35.35],"type":"Point"}
}