{
  "id": 7230470,
  "type": "Feature",
  "properties": {
    "tgn:hierarchy":[
        "tgn:7230470",
        "tgn:7011270",
        "tgn:7002674",
        "tgn:1000003",
        "tgn:1000074",
        "tgn:7029392"
    ],
    "tgn:id":7230470,
    "tgn:name":"Khondrop\u00f3, \u00c1kra",
    "tgn:placetype":[
        "aat:300008850"
    ]
},
  "bbox": [],
  "geometry": {"coordinates":[24.666667,36.966667],"type":"Point"}
}