{
  "id": 1056760,
  "type": "Feature",
  "properties": {
    "tgn:hierarchy":[
        "tgn:1056760",
        "tgn:1000004",
        "tgn:7012922",
        "tgn:7014786",
        "tgn:7029392"
    ],
    "tgn:id":1056760,
    "tgn:name":"Malorossiyskiy",
    "tgn:placetype":[
        "aat:300008347"
    ]
},
  "bbox": [],
  "geometry": {"coordinates":[62.45,53.1833],"type":"Point"}
}