{
  "id": 7590086,
  "type": "Feature",
  "properties": {
    "tgn:hierarchy":[
        "tgn:7590086",
        "tgn:1000004",
        "tgn:1001871",
        "tgn:7000198",
        "tgn:7029392"
    ],
    "tgn:id":7590086,
    "tgn:name:en":"Charpura",
    "tgn:placetype":[
        "aat:300008347"
    ]
},
  "bbox": [],
  "geometry": {"coordinates":[77.117545,29.806752],"type":"Point"}
}