{
  "id": 7166690,
  "type": "Feature",
  "properties": {
    "tgn:hierarchy":[
        "tgn:7166690",
        "tgn:7003669",
        "tgn:1000003",
        "tgn:7000084",
        "tgn:7029392"
    ],
    "tgn:id":7166690,
    "tgn:name":"H\u00e4usellohe",
    "tgn:placetype":[
        "aat:300008347"
    ]
},
  "bbox": [],
  "geometry": {"coordinates":[12.183333,50.15],"type":"Point"}
}