{
  "id": 7080495,
  "type": "Feature",
  "properties": {
    "tgn:hierarchy":[
        "tgn:7080495",
        "tgn:7000096",
        "tgn:1000003",
        "tgn:7000084",
        "tgn:7029392"
    ],
    "tgn:id":7080495,
    "tgn:name":"Woschkower Berge",
    "tgn:placetype":[
        "aat:300008777"
    ]
},
  "bbox": [],
  "geometry": {"coordinates":[14.033333,51.616667],"type":"Point"}
}