{
  "id": 2260642,
  "type": "Feature",
  "properties": {
    "tgn:hierarchy":[
        "tgn:2260642",
        "tgn:1000001",
        "tgn:7012149",
        "tgn:2001050",
        "tgn:7007521",
        "tgn:7029392"
    ],
    "tgn:id":2260642,
    "tgn:name":"County Ditch Number Nine",
    "tgn:placetype":[
        "aat:300006075"
    ]
},
  "bbox": [],
  "geometry": {"coordinates":[-94.25,44.4333],"type":"Point"}
}