{
  "id": 7429717,
  "type": "Feature",
  "properties": {
    "tgn:hierarchy":[
        "tgn:7429717",
        "tgn:1001835",
        "tgn:1000001",
        "tgn:7005560",
        "tgn:7029392"
    ],
    "tgn:id":7429717,
    "tgn:name":"La Calera",
    "tgn:placetype":[
        "aat:300008347"
    ]
},
  "bbox": [],
  "geometry": {"coordinates":[-116.05,32.45],"type":"Point"}
}