{
  "id": 2689757,
  "type": "Feature",
  "properties": {
    "tgn:hierarchy":[
        "tgn:2689757",
        "tgn:1000001",
        "tgn:7012149",
        "tgn:2000928",
        "tgn:7007515",
        "tgn:7029392"
    ],
    "tgn:id":2689757,
    "tgn:name":"Squaws Bosom",
    "tgn:placetype":[
        "aat:300008798"
    ]
},
  "bbox": [],
  "geometry": {"coordinates":[-69.0667,45.9167],"type":"Point"}
}