{
  "id": 1012267,
  "type": "Feature",
  "properties": {
    "tgn:hierarchy":[
        "tgn:1012267",
        "tgn:7001242",
        "tgn:1000149",
        "tgn:1000954",
        "tgn:7029392"
    ],
    "tgn:id":1012267,
    "tgn:name":"Padr\u00e3o, Ponta do",
    "tgn:placetype":[
        "aat:300386846"
    ]
},
  "bbox": [],
  "geometry": {"coordinates":[12.3333,-6.0833],"type":"Point"}
}