{
  "id": 2653496,
  "type": "Feature",
  "properties": {
    "tgn:hierarchy":[
        "tgn:2653496",
        "tgn:1000001",
        "tgn:7012149",
        "tgn:2001855",
        "tgn:7007825",
        "tgn:7029392"
    ],
    "tgn:id":2653496,
    "tgn:name":"Seventeen Seventysix Estates",
    "tgn:placetype":[
        "aat:300008347"
    ]
},
  "bbox": [],
  "geometry": {"coordinates":[-86.95,36.0833],"type":"Point"}
}