<<<<<<< HEAD
{
  "id": 2151769,
  "type": "Feature",
  "properties": {
    "tgn:hierarchy":[
        "tgn:2151769",
        "tgn:1000001",
        "tgn:1002305",
        "tgn:7012149",
        "tgn:7007920",
        "tgn:7029392"
    ],
    "tgn:id":2151769,
    "tgn:name":"Battle Mountain",
    "tgn:placetype":[
        "aat:300008798"
    ]
},
  "bbox": [],
  "geometry": {"coordinates":[-122.75,46.05],"type":"Point"}
}
=======
{"geometry":{"type":"Point","coordinates":[-122.750000,46.050000]},"type":"Feature","properties":{"hierarchy":["tgn:2151769","tgn:1000001","tgn:1002305","tgn:7012149","tgn:7007920","tgn:7029392"],"placetype":["aat:300008798"],"id":2151769,"name:xx":"Battle Mountain"}}
>>>>>>> 03f74aca74312dbeaf24d7e61306dd6a786dc3d0
