<<<<<<< HEAD
{
  "id": 7050475,
  "type": "Feature",
  "properties": {
    "tgn:hierarchy":[
        "tgn:7050475",
        "tgn:1003450",
        "tgn:7007850",
        "tgn:1000003",
        "tgn:1000080",
        "tgn:7029392"
    ],
    "tgn:id":7050475,
    "tgn:name":"Masseria Caruso",
    "tgn:placetype":[
        "aat:300008347"
    ]
},
  "bbox": [],
  "geometry": {"coordinates":[16.766667,39.533333],"type":"Point"}
}
=======
{"geometry":{"type":"Point","coordinates":[16.766667,39.533333]},"type":"Feature","properties":{"hierarchy":["tgn:7050475","tgn:1003450","tgn:7007850","tgn:1000003","tgn:1000080","tgn:7029392"],"placetype":["aat:300008347"],"id":7050475,"name:xx":"Masseria Caruso"}}
>>>>>>> 03f74aca74312dbeaf24d7e61306dd6a786dc3d0
