{
  "id": 7523800,
  "type": "Feature",
  "properties": {
    "tgn:hierarchy":[
        "tgn:7523800",
        "tgn:7001242",
        "tgn:7016833",
        "tgn:1001418",
        "tgn:7029392"
    ],
    "tgn:id":7523800,
    "tgn:name:en":"Al Qu\u015fayr",
    "tgn:placetype":[
        "aat:300008057"
    ]
},
  "bbox": [],
  "geometry": {"coordinates":[28.475499,30.716857],"type":"Point"}
}