{
  "id": 2450596,
  "type": "Feature",
  "properties": {
    "tgn:hierarchy":[
        "tgn:2450596",
        "tgn:1000001",
        "tgn:7012149",
        "tgn:2000366",
        "tgn:7007248",
        "tgn:7029392"
    ],
    "tgn:id":2450596,
    "tgn:name":"Lion Country Lake",
    "tgn:placetype":[
        "aat:300006191"
    ]
},
  "bbox": [],
  "geometry": {"coordinates":[-84.2667,33.5167],"type":"Point"}
}