{
  "id": 2277911,
  "type": "Feature",
  "properties": {
    "tgn:hierarchy":[
        "tgn:2277911",
        "tgn:1000001",
        "tgn:2002324",
        "tgn:7012149",
        "tgn:7007922",
        "tgn:7029392"
    ],
    "tgn:id":2277911,
    "tgn:name":"Day Branch",
    "tgn:placetype":[
        "aat:300008699"
    ]
},
  "bbox": [],
  "geometry": {"coordinates":[-90.7333,42.8333],"type":"Point"}
}