{
  "id": 7288358,
  "type": "Feature",
  "properties": {
    "tgn:hierarchy":[
        "tgn:7288358",
        "tgn:1001702",
        "tgn:1000049",
        "tgn:1000002",
        "tgn:7029392"
    ],
    "tgn:id":7288358,
    "tgn:name":"Jerd\u00e1n, Isla",
    "tgn:placetype":[
        "aat:300008791"
    ]
},
  "bbox": [],
  "geometry": {"coordinates":[-67.466667,-55.816667],"type":"Point"}
}