{
  "id": 7441134,
  "type": "Feature",
  "properties": {
    "tgn:hierarchy":[
        "tgn:7441134",
        "tgn:1000001",
        "tgn:7005597",
        "tgn:7005560",
        "tgn:7029392"
    ],
    "tgn:id":7441134,
    "tgn:name":"Rancho Santa Juana",
    "tgn:placetype":[
        "aat:300000241"
    ]
},
  "bbox": [],
  "geometry": {"coordinates":[-99.333333,24.266667],"type":"Point"}
}