{
  "id": 2764335,
  "type": "Feature",
  "properties": {
    "tgn:hierarchy":[
        "tgn:2764335",
        "tgn:1000001",
        "tgn:7012149",
        "tgn:2001162",
        "tgn:7007522",
        "tgn:7029392"
    ],
    "tgn:id":2764335,
    "tgn:name":"Whetstone Branch",
    "tgn:placetype":[
        "aat:300008699"
    ]
},
  "bbox": [],
  "geometry": {"coordinates":[-88.7833,31.5833],"type":"Point"}
}