<<<<<<< HEAD
{
  "id": 7373383,
  "type": "Feature",
  "properties": {
    "tgn:hierarchy":[
        "tgn:7373383",
        "tgn:1000001",
        "tgn:7005597",
        "tgn:7005560",
        "tgn:7029392"
    ],
    "tgn:id":7373383,
    "tgn:name":"La Leona",
    "tgn:placetype":[
        "aat:300008347"
    ]
},
  "bbox": [],
  "geometry": {"coordinates":[-99.1,23.066667],"type":"Point"}
}
=======
{"geometry":{"type":"Point","coordinates":[-99.100000,23.066667]},"type":"Feature","properties":{"hierarchy":["tgn:7373383","tgn:1000001","tgn:7005597","tgn:7005560","tgn:7029392"],"placetype":["aat:300008347"],"id":7373383,"name:xx":"La Leona"}}
>>>>>>> 03f74aca74312dbeaf24d7e61306dd6a786dc3d0
