{
  "id": 1036059,
  "type": "Feature",
  "properties": {
    "tgn:hierarchy":[
        "tgn:1036059",
        "tgn:1000003",
        "tgn:1000070",
        "tgn:7002895",
        "tgn:7029392"
    ],
    "tgn:id":1036059,
    "tgn:name":"Vergons",
    "tgn:placetype":[
        "aat:300008347"
    ]
},
  "bbox": [],
  "geometry": {"coordinates":[6.5833,43.9167],"type":"Point"}
}