<<<<<<< HEAD
{
  "id": 2761065,
  "type": "Feature",
  "properties": {
    "tgn:hierarchy":[
        "tgn:2761065",
        "tgn:7006450",
        "tgn:1000001",
        "tgn:2124053",
        "tgn:7012149",
        "tgn:7029392"
    ],
    "tgn:id":2761065,
    "tgn:name":"West Lake",
    "tgn:placetype":[
        "aat:300008680"
    ]
},
  "bbox": [],
  "geometry": {"coordinates":[-149.9333,61.5667],"type":"Point"}
}
=======
{"geometry":{"type":"Point","coordinates":[-149.933300,61.566700]},"type":"Feature","properties":{"hierarchy":["tgn:2761065","tgn:7006450","tgn:1000001","tgn:2124053","tgn:7012149","tgn:7029392"],"placetype":["aat:300008680"],"id":2761065,"name:xx":"West Lake"}}
>>>>>>> 03f74aca74312dbeaf24d7e61306dd6a786dc3d0
