{
  "id": 1003948,
  "type": "Feature",
  "properties": {
    "tgn:hierarchy":[
        "tgn:1003948",
        "tgn:1000004",
        "tgn:7000198",
        "tgn:1001977",
        "tgn:7029392"
    ],
    "tgn:id":1003948,
    "tgn:name:en":"\u0100l\u012bpur",
    "tgn:placetype":[
        "aat:300008347",
        "aat:300000745"
    ]
},
  "bbox": [],
  "geometry": {"coordinates":[88.323,22.531],"type":"Point"}
}