{
  "id": 2227554,
  "type": "Feature",
  "properties": {
    "tgn:hierarchy":[
        "tgn:2227554",
        "tgn:1000001",
        "tgn:7012149",
        "tgn:2000229",
        "tgn:7007158",
        "tgn:7029392"
    ],
    "tgn:id":2227554,
    "tgn:name":"Cave, The",
    "tgn:placetype":[
        "aat:300008746"
    ]
},
  "bbox": [],
  "geometry": {"coordinates":[-103.0333,40.5667],"type":"Point"}
}