{
  "id": 7391012,
  "type": "Feature",
  "properties": {
    "tgn:hierarchy":[
        "tgn:7391012",
        "tgn:1000001",
        "tgn:1001960",
        "tgn:7005560",
        "tgn:7029392"
    ],
    "tgn:id":7391012,
    "tgn:name":"R\u00edo Muerto, Estero del",
    "tgn:placetype":[
        "aat:300185707"
    ]
},
  "bbox": [],
  "geometry": {"coordinates":[-110.65,27.783333],"type":"Point"}
}