{
  "id": 2080818,
  "type": "Feature",
  "properties": {
    "tgn:hierarchy":[
        "tgn:2080818",
        "tgn:1000001",
        "tgn:7012149",
        "tgn:1002611",
        "tgn:7007706",
        "tgn:7029392"
    ],
    "tgn:id":2080818,
    "tgn:name":"Monclova",
    "tgn:placetype":[
        "aat:300008347"
    ]
},
  "bbox": [],
  "geometry": {"coordinates":[-83.7167,41.55],"type":"Point"}
}