{
  "id": 7448205,
  "type": "Feature",
  "properties": {
    "tgn:hierarchy":[
        "tgn:7448205",
        "tgn:7002443",
        "tgn:1000003",
        "tgn:7018993",
        "tgn:7008591",
        "tgn:7029392"
    ],
    "tgn:id":7448205,
    "tgn:name:en":"Stack Rocks",
    "tgn:placetype":[
        "aat:300011692"
    ]
},
  "bbox": [],
  "geometry": {"coordinates":[-5.174167,51.775278],"type":"Point"}
}