{
  "id": 1000739,
  "type": "Feature",
  "properties": {
    "tgn:hierarchy":[
        "tgn:1000739",
        "tgn:1000001",
        "tgn:7005493",
        "tgn:7029392"
    ],
    "tgn:id":1000739,
    "tgn:name":"Retalhuleu",
    "tgn:placetype":[
        "aat:300008631",
        "aat:300387064",
        "aat:300000772"
    ]
},
  "bbox": [],
  "geometry": {"coordinates":[-91.8333,14.3333],"type":"Point"}
}