{
  "id": 7303364,
  "type": "Feature",
  "properties": {
    "tgn:hierarchy":[
        "tgn:7303364",
        "tgn:7001155",
        "tgn:1000003",
        "tgn:7002790",
        "tgn:1000095",
        "tgn:7029392"
    ],
    "tgn:id":7303364,
    "tgn:name":"Olaz-Subiza",
    "tgn:placetype":[
        "aat:300008347"
    ]
},
  "bbox": [],
  "geometry": {"coordinates":[-1.65,42.716667],"type":"Point"}
}