{
  "id": 2230185,
  "type": "Feature",
  "properties": {
    "tgn:hierarchy":[
        "tgn:2230185",
        "tgn:1000001",
        "tgn:7006451",
        "tgn:2000093",
        "tgn:7012149",
        "tgn:7029392"
    ],
    "tgn:id":2230185,
    "tgn:name":"Cement Tank",
    "tgn:placetype":[
        "aat:300006191"
    ]
},
  "bbox": [],
  "geometry": {"coordinates":[-110.8167,33.5167],"type":"Point"}
}