<<<<<<< HEAD
{
  "id": 2333385,
  "type": "Feature",
  "properties": {
    "tgn:hierarchy":[
        "tgn:2333385",
        "tgn:1000001",
        "tgn:7006451",
        "tgn:7012149",
        "tgn:2000099",
        "tgn:7029392"
    ],
    "tgn:id":2333385,
    "tgn:name":"Folette Spring",
    "tgn:placetype":[
        "aat:300008697"
    ]
},
  "bbox": [],
  "geometry": {"coordinates":[-109.95,34.0833],"type":"Point"}
}
=======
{"geometry":{"type":"Point","coordinates":[-109.950000,34.083300]},"type":"Feature","properties":{"hierarchy":["tgn:2333385","tgn:1000001","tgn:7006451","tgn:7012149","tgn:2000099","tgn:7029392"],"placetype":["aat:300008697"],"id":2333385,"name:xx":"Folette Spring"}}
>>>>>>> 03f74aca74312dbeaf24d7e61306dd6a786dc3d0
