<<<<<<< HEAD
{
  "id": 7176266,
  "type": "Feature",
  "properties": {
    "tgn:hierarchy":[
        "tgn:7176266",
        "tgn:1000003",
        "tgn:7003676",
        "tgn:7000084",
        "tgn:7029392"
    ],
    "tgn:id":7176266,
    "tgn:name":"Gro\u00df Str\u00fcckhausen",
    "tgn:placetype":[
        "aat:300000206"
    ]
},
  "bbox": [],
  "geometry": {"coordinates":[7.966667,53.6],"type":"Point"}
}
=======
{"geometry":{"type":"Point","coordinates":[7.966667,53.600000]},"type":"Feature","properties":{"hierarchy":["tgn:7176266","tgn:1000003","tgn:7003676","tgn:7000084","tgn:7029392"],"placetype":["aat:300000206"],"id":7176266,"name:xx":"Gro\u00df Str\u00fcckhausen"}}
>>>>>>> 03f74aca74312dbeaf24d7e61306dd6a786dc3d0
