<<<<<<< HEAD
{
  "id": 2408005,
  "type": "Feature",
  "properties": {
    "tgn:hierarchy":[
        "tgn:2408005",
        "tgn:1000001",
        "tgn:7012149",
        "tgn:2002061",
        "tgn:7007826",
        "tgn:7029392"
    ],
    "tgn:id":2408005,
    "tgn:name":"Hurricane Creek",
    "tgn:placetype":[
        "aat:300008706"
    ]
},
  "bbox": [],
  "geometry": {"coordinates":[-94.9,33.6333],"type":"Point"}
}
=======
{"geometry":{"type":"Point","coordinates":[-94.900000,33.633300]},"type":"Feature","properties":{"hierarchy":["tgn:2408005","tgn:1000001","tgn:7012149","tgn:2002061","tgn:7007826","tgn:7029392"],"placetype":["aat:300008706"],"id":2408005,"name:xx":"Hurricane Creek"}}
>>>>>>> 03f74aca74312dbeaf24d7e61306dd6a786dc3d0
