{
  "id": 7239597,
  "type": "Feature",
  "properties": {
    "tgn:hierarchy":[
        "tgn:7239597",
        "tgn:7003461",
        "tgn:1000003",
        "tgn:1000063",
        "tgn:7018236",
        "tgn:7029392"
    ],
    "tgn:id":7239597,
    "tgn:name":"Heide",
    "tgn:placetype":[
        "aat:300008347"
    ]
},
  "bbox": [],
  "geometry": {"coordinates":[5.316667,51.25],"type":"Point"}
}