{
  "id": 2156139,
  "type": "Feature",
  "properties": {
    "tgn:hierarchy":[
        "tgn:2156139",
        "tgn:1000001",
        "tgn:7012149",
        "tgn:2002264",
        "tgn:7013961",
        "tgn:7029392"
    ],
    "tgn:id":2156139,
    "tgn:name":"Beard Spring",
    "tgn:placetype":[
        "aat:300008697"
    ]
},
  "bbox": [],
  "geometry": {"coordinates":[-80.3333,38.0333],"type":"Point"}
}