<<<<<<< HEAD
{
  "id": 2156139,
  "type": "Feature",
  "properties": {
    "tgn:hierarchy":[
        "tgn:2156139",
        "tgn:1000001",
        "tgn:7012149",
        "tgn:2002264",
        "tgn:7013961",
        "tgn:7029392"
    ],
    "tgn:id":2156139,
    "tgn:name":"Beard Spring",
    "tgn:placetype":[
        "aat:300008697"
    ]
},
  "bbox": [],
  "geometry": {"coordinates":[-80.3333,38.0333],"type":"Point"}
}
=======
{"geometry":{"type":"Point","coordinates":[-80.333300,38.033300]},"type":"Feature","properties":{"hierarchy":["tgn:2156139","tgn:1000001","tgn:7012149","tgn:2002264","tgn:7013961","tgn:7029392"],"placetype":["aat:300008697"],"id":2156139,"name:xx":"Beard Spring"}}
>>>>>>> 03f74aca74312dbeaf24d7e61306dd6a786dc3d0
