{
  "id": 7362285,
  "type": "Feature",
  "properties": {
    "tgn:hierarchy":[
        "tgn:7362285",
        "tgn:7005586",
        "tgn:1000001",
        "tgn:7005560",
        "tgn:7029392"
    ],
    "tgn:id":7362285,
    "tgn:name":"El Llanito",
    "tgn:placetype":[
        "aat:300008347"
    ]
},
  "bbox": [],
  "geometry": {"coordinates":[-104.666667,20.166667],"type":"Point"}
}