<<<<<<< HEAD
{
  "id": 7488342,
  "type": "Feature",
  "properties": {
    "tgn:hierarchy":[
        "tgn:7488342",
        "tgn:1000004",
        "tgn:7471332",
        "tgn:1000141",
        "tgn:7029392"
    ],
    "tgn:id":7488342,
    "tgn:name":"Guanwu Gongzuozhan",
    "tgn:placetype":[
        "aat:300000517"
    ]
},
  "bbox": [],
  "geometry": {"coordinates":[121.113889,24.505833],"type":"Point"}
}
=======
{"geometry":{"type":"Point","coordinates":[121.113889,24.505833]},"type":"Feature","properties":{"hierarchy":["tgn:7488342","tgn:1000004","tgn:7471332","tgn:1000141","tgn:7029392"],"placetype":["aat:300000517"],"id":7488342,"name:xx":"Guanwu Gongzuozhan"}}
>>>>>>> 03f74aca74312dbeaf24d7e61306dd6a786dc3d0
