{
  "id": 7488342,
  "type": "Feature",
  "properties": {
    "tgn:hierarchy":[
        "tgn:7488342",
        "tgn:1000004",
        "tgn:7471332",
        "tgn:1000141",
        "tgn:7029392"
    ],
    "tgn:id":7488342,
    "tgn:name":"Guanwu Gongzuozhan",
    "tgn:placetype":[
        "aat:300000517"
    ]
},
  "bbox": [],
  "geometry": {"coordinates":[121.113889,24.505833],"type":"Point"}
}