{
  "id": 7314202,
  "type": "Feature",
  "properties": {
    "tgn:hierarchy":[
        "tgn:7314202",
        "tgn:7016598",
        "tgn:1000049",
        "tgn:1000002",
        "tgn:7029392"
    ],
    "tgn:id":7314202,
    "tgn:name":"Lorca, Pampa",
    "tgn:placetype":[
        "aat:300008805"
    ]
},
  "bbox": [],
  "geometry": {"coordinates":[-69.566667,-25.566667],"type":"Point"}
}