{
  "id": 7469775,
  "type": "Feature",
  "properties": {
    "tgn:hierarchy":[
        "tgn:7469775",
        "tgn:7001010",
        "tgn:1000004",
        "tgn:1000141",
        "tgn:7029392"
    ],
    "tgn:id":7469775,
    "tgn:name":"Jinyan Shan",
    "tgn:placetype":[
        "aat:300008798"
    ]
},
  "bbox": [],
  "geometry": {"coordinates":[121.724414,24.248317],"type":"Point"}
}