{
  "id": 7415149,
  "type": "Feature",
  "properties": {
    "tgn:hierarchy":[
        "tgn:7415149",
        "tgn:7005584",
        "tgn:1000001",
        "tgn:7005560",
        "tgn:7029392"
    ],
    "tgn:id":7415149,
    "tgn:name":"El Campamento, Cerro",
    "tgn:placetype":[
        "aat:300008795"
    ]
},
  "bbox": [],
  "geometry": {"coordinates":[-100.906389,19.976389],"type":"Point"}
}