{
  "id": 1057210,
  "type": "Feature",
  "properties": {
    "tgn:hierarchy":[
        "tgn:1057210",
        "tgn:7012908",
        "tgn:1000004",
        "tgn:7014786",
        "tgn:7029392"
    ],
    "tgn:id":1057210,
    "tgn:name":"Munayly",
    "tgn:placetype":[
        "aat:300008347"
    ]
},
  "bbox": [],
  "geometry": {"coordinates":[54.55,46.7667],"type":"Point"}
}