{
  "id": 2746738,
  "type": "Feature",
  "properties": {
    "tgn:hierarchy":[
        "tgn:2746738",
        "tgn:1000001",
        "tgn:7012149",
        "tgn:2001907",
        "tgn:7007825",
        "tgn:7029392"
    ],
    "tgn:id":2746738,
    "tgn:name":"Wade Pit",
    "tgn:placetype":[
        "aat:300008746"
    ]
},
  "bbox": [],
  "geometry": {"coordinates":[-85.45,36.1333],"type":"Point"}
}