{
  "id": 2715771,
  "type": "Feature",
  "properties": {
    "tgn:hierarchy":[
        "tgn:2715771",
        "tgn:1000001",
        "tgn:2001424",
        "tgn:7012149",
        "tgn:7007564",
        "tgn:7029392"
    ],
    "tgn:id":2715771,
    "tgn:name":"Teter Meadow Brook",
    "tgn:placetype":[
        "aat:300008699"
    ]
},
  "bbox": [],
  "geometry": {"coordinates":[-71.9667,44.2667],"type":"Point"}
}