<<<<<<< HEAD
{
  "id": 2334598,
  "type": "Feature",
  "properties": {
    "tgn:hierarchy":[
        "tgn:2334598",
        "tgn:1000001",
        "tgn:7012149",
        "tgn:2000797",
        "tgn:7007255",
        "tgn:7029392"
    ],
    "tgn:id":2334598,
    "tgn:name":"Foresters Creek",
    "tgn:placetype":[
        "aat:300008706"
    ]
},
  "bbox": [],
  "geometry": {"coordinates":[-83.4167,36.7667],"type":"Point"}
}
=======
{"geometry":{"type":"Point","coordinates":[-83.416700,36.766700]},"type":"Feature","properties":{"hierarchy":["tgn:2334598","tgn:1000001","tgn:7012149","tgn:2000797","tgn:7007255","tgn:7029392"],"placetype":["aat:300008706"],"id":2334598,"name:xx":"Foresters Creek"}}
>>>>>>> 03f74aca74312dbeaf24d7e61306dd6a786dc3d0
