{
  "id": 7264593,
  "type": "Feature",
  "properties": {
    "tgn:concordances":{
        "gn:id":"2751550"
    },
    "tgn:hierarchy":[
        "tgn:7264593",
        "tgn:7003616",
        "tgn:1000003",
        "tgn:7016845",
        "tgn:7029392"
    ],
    "tgn:id":7264593,
    "tgn:name:nl":"Lippenwoude",
    "tgn:placetype":[
        "aat:300008347"
    ]
},
  "bbox": [],
  "geometry": {"coordinates":[5.65,52.966667],"type":"Point"}
}