{
  "id": 7329921,
  "type": "Feature",
  "properties": {
    "tgn:hierarchy":[
        "tgn:7329921",
        "tgn:7002810",
        "tgn:7001158",
        "tgn:1000003",
        "tgn:1000095",
        "tgn:7029392"
    ],
    "tgn:id":7329921,
    "tgn:name":"Huidobro",
    "tgn:placetype":[
        "aat:300008347"
    ]
},
  "bbox": [],
  "geometry": {"coordinates":[-3.683333,42.766667],"type":"Point"}
}