{
  "id": 7537366,
  "type": "Feature",
  "properties": {
    "tgn:hierarchy":[
        "tgn:7537366",
        "tgn:7001242",
        "tgn:7001311",
        "tgn:7016833",
        "tgn:7029392"
    ],
    "tgn:id":7537366,
    "tgn:name:en":"Qu\u015f\u016br al Ban\u0101t",
    "tgn:placetype":[
        "aat:300055621"
    ]
},
  "bbox": [],
  "geometry": {"coordinates":[33.261748,25.923034],"type":"Point"}
}