{
  "id": 7498951,
  "type": "Feature",
  "properties": {
    "tgn:hierarchy":[
        "tgn:7498951",
        "tgn:1000004",
        "tgn:7001009",
        "tgn:1000141",
        "tgn:7029392"
    ],
    "tgn:id":7498951,
    "tgn:name":"Niucheng",
    "tgn:placetype":[
        "aat:300008347"
    ]
},
  "bbox": [],
  "geometry": {"coordinates":[120.728103,24.035604],"type":"Point"}
}