{
  "id": 7174876,
  "type": "Feature",
  "properties": {
    "tgn:hierarchy":[
        "tgn:7174876",
        "tgn:1000003",
        "tgn:7003677",
        "tgn:7000084",
        "tgn:7029392"
    ],
    "tgn:id":7174876,
    "tgn:name":"Gripsh\u00f6ver",
    "tgn:placetype":[
        "aat:300000206"
    ]
},
  "bbox": [],
  "geometry": {"coordinates":[7.55,51.783333],"type":"Point"}
}