{
  "id": 2763438,
  "type": "Feature",
  "properties": {
    "tgn:hierarchy":[
        "tgn:2763438",
        "tgn:1000001",
        "tgn:7012149",
        "tgn:7007158",
        "tgn:7029392"
    ],
    "tgn:id":2763438,
    "tgn:name":"Wetzel Creek",
    "tgn:placetype":[
        "aat:300008706"
    ]
},
  "bbox": [],
  "geometry": {"coordinates":[-103.7833,39.7167],"type":"Point"}
}