{
  "id": 7020449,
  "type": "Feature",
  "properties": {
    "tgn:hierarchy":[
        "tgn:7020449",
        "tgn:1000001",
        "tgn:7012149",
        "tgn:2001535",
        "tgn:7007709",
        "tgn:7029392"
    ],
    "tgn:id":7020449,
    "tgn:name":"Reidsville Quarry Lake",
    "tgn:placetype":[
        "aat:300006191"
    ]
},
  "bbox": [],
  "geometry": {"coordinates":[-79.7167,36.3667],"type":"Point"}
}