<<<<<<< HEAD
{
  "id": 7020449,
  "type": "Feature",
  "properties": {
    "tgn:hierarchy":[
        "tgn:7020449",
        "tgn:1000001",
        "tgn:7012149",
        "tgn:2001535",
        "tgn:7007709",
        "tgn:7029392"
    ],
    "tgn:id":7020449,
    "tgn:name":"Reidsville Quarry Lake",
    "tgn:placetype":[
        "aat:300006191"
    ]
},
  "bbox": [],
  "geometry": {"coordinates":[-79.7167,36.3667],"type":"Point"}
}
=======
{"geometry":{"type":"Point","coordinates":[-79.716700,36.366700]},"type":"Feature","properties":{"hierarchy":["tgn:7020449","tgn:1000001","tgn:7012149","tgn:2001535","tgn:7007709","tgn:7029392"],"placetype":["aat:300006191"],"id":7020449,"name:xx":"Reidsville Quarry Lake"}}
>>>>>>> 03f74aca74312dbeaf24d7e61306dd6a786dc3d0
