<<<<<<< HEAD
{
  "id": 7357974,
  "type": "Feature",
  "properties": {
    "tgn:hierarchy":[
        "tgn:7357974",
        "tgn:7005581",
        "tgn:1000001",
        "tgn:7005560",
        "tgn:7029392"
    ],
    "tgn:id":7357974,
    "tgn:name":"Colonia D\u00edaz",
    "tgn:placetype":[
        "aat:300008347"
    ]
},
  "bbox": [],
  "geometry": {"coordinates":[-108.0,31.166667],"type":"Point"}
}
=======
{"geometry":{"type":"Point","coordinates":[-108.000000,31.166667]},"type":"Feature","properties":{"hierarchy":["tgn:7357974","tgn:7005581","tgn:1000001","tgn:7005560","tgn:7029392"],"placetype":["aat:300008347"],"id":7357974,"name:xx":"Colonia D\u00edaz"}}
>>>>>>> 03f74aca74312dbeaf24d7e61306dd6a786dc3d0
