<<<<<<< HEAD
{
  "id": 7475077,
  "type": "Feature",
  "properties": {
    "tgn:hierarchy":[
        "tgn:7475077",
        "tgn:1000004",
        "tgn:7001014",
        "tgn:1000141",
        "tgn:7029392"
    ],
    "tgn:id":7475077,
    "tgn:name":"Daxin Guoxiao",
    "tgn:placetype":[
        "aat:300006495"
    ]
},
  "bbox": [],
  "geometry": {"coordinates":[120.557941,23.855321],"type":"Point"}
}
=======
{"geometry":{"type":"Point","coordinates":[120.557941,23.855321]},"type":"Feature","properties":{"hierarchy":["tgn:7475077","tgn:1000004","tgn:7001014","tgn:1000141","tgn:7029392"],"placetype":["aat:300006495"],"id":7475077,"name:xx":"Daxin Guoxiao"}}
>>>>>>> 03f74aca74312dbeaf24d7e61306dd6a786dc3d0
