{
  "id": 7185182,
  "type": "Feature",
  "properties": {
    "tgn:hierarchy":[
        "tgn:7185182",
        "tgn:1000003",
        "tgn:7000094",
        "tgn:7000084",
        "tgn:7029392"
    ],
    "tgn:id":7185182,
    "tgn:name":"Glocken-Berg",
    "tgn:placetype":[
        "aat:300008777"
    ]
},
  "bbox": [],
  "geometry": {"coordinates":[12.35,53.666667],"type":"Point"}
}