{
  "id": 7519873,
  "type": "Feature",
  "properties": {
    "tgn:hierarchy":[
        "tgn:7519873",
        "tgn:1009227",
        "tgn:1000226",
        "tgn:1000006",
        "tgn:7016850",
        "tgn:7029392"
    ],
    "tgn:id":7519873,
    "tgn:name:en":"Berlins Creek",
    "tgn:placetype":[
        "aat:300008699"
    ]
},
  "bbox": [],
  "geometry": {"coordinates":[171.833333,-41.866667],"type":"Point"}
}