{
  "id": 2526247,
  "type": "Feature",
  "properties": {
    "tgn:hierarchy":[
        "tgn:2526247",
        "tgn:2000765",
        "tgn:1000001",
        "tgn:7012149",
        "tgn:7007255",
        "tgn:7029392"
    ],
    "tgn:id":2526247,
    "tgn:name":"Moss Branch",
    "tgn:placetype":[
        "aat:300008699"
    ]
},
  "bbox": [],
  "geometry": {"coordinates":[-85.4667,37.05],"type":"Point"}
}