{
  "id": 7437938,
  "type": "Feature",
  "properties": {
    "tgn:hierarchy":[
        "tgn:7437938",
        "tgn:1001836",
        "tgn:1000001",
        "tgn:7005560",
        "tgn:7029392"
    ],
    "tgn:id":7437938,
    "tgn:name":"Tinaja",
    "tgn:placetype":[
        "aat:300008347"
    ]
},
  "bbox": [],
  "geometry": {"coordinates":[-101.816667,27.283333],"type":"Point"}
}