{
  "id": 1045604,
  "type": "Feature",
  "properties": {
    "tgn:hierarchy":[
        "tgn:1045604",
        "tgn:1003506",
        "tgn:1000003",
        "tgn:7002993",
        "tgn:1000080",
        "tgn:7029392"
    ],
    "tgn:id":1045604,
    "tgn:name":"Mortegliano",
    "tgn:placetype":[
        "aat:300008347"
    ]
},
  "bbox": [],
  "geometry": {"coordinates":[13.173333,45.944167],"type":"Point"}
}