{
  "id": 2579473,
  "type": "Feature",
  "properties": {
    "tgn:hierarchy":[
        "tgn:2579473",
        "tgn:1000001",
        "tgn:2000922",
        "tgn:7012149",
        "tgn:7007515",
        "tgn:7029392"
    ],
    "tgn:id":2579473,
    "tgn:name":"Pickering Island",
    "tgn:placetype":[
        "aat:300008791"
    ]
},
  "bbox": [],
  "geometry": {"coordinates":[-68.7333,44.25],"type":"Point"}
}