{
  "id": 2620997,
  "type": "Feature",
  "properties": {
    "tgn:hierarchy":[
        "tgn:2620997",
        "tgn:1000001",
        "tgn:2001414",
        "tgn:7012149",
        "tgn:7007526",
        "tgn:7029392"
    ],
    "tgn:id":2620997,
    "tgn:name":"Road Creek",
    "tgn:placetype":[
        "aat:300008706"
    ]
},
  "bbox": [],
  "geometry": {"coordinates":[-117.5333,41.6667],"type":"Point"}
}