{
  "id": 2291569,
  "type": "Feature",
  "properties": {
    "tgn:hierarchy":[
        "tgn:2291569",
        "tgn:1000001",
        "tgn:7012149",
        "tgn:2000959",
        "tgn:7007520",
        "tgn:7029392"
    ],
    "tgn:id":2291569,
    "tgn:name":"Dollar Lake",
    "tgn:placetype":[
        "aat:300008680"
    ]
},
  "bbox": [],
  "geometry": {"coordinates":[-84.35,44.1333],"type":"Point"}
}