{
  "id": 2687525,
  "type": "Feature",
  "properties": {
    "tgn:hierarchy":[
        "tgn:2687525",
        "tgn:1000001",
        "tgn:7012149",
        "tgn:1002603",
        "tgn:7007520",
        "tgn:7029392"
    ],
    "tgn:id":2687525,
    "tgn:name":"Spring Mill Pond",
    "tgn:placetype":[
        "aat:300008680"
    ]
},
  "bbox": [],
  "geometry": {"coordinates":[-83.7167,42.4833],"type":"Point"}
}