{
  "id": 2496790,
  "type": "Feature",
  "properties": {
    "tgn:hierarchy":[
        "tgn:2496790",
        "tgn:1000001",
        "tgn:7012149",
        "tgn:2000928",
        "tgn:7007515",
        "tgn:7029392"
    ],
    "tgn:id":2496790,
    "tgn:name":"Matthews Pond",
    "tgn:placetype":[
        "aat:300008680"
    ]
},
  "bbox": [],
  "geometry": {"coordinates":[-69.05,46.3167],"type":"Point"}
}