{
  "id": 7569793,
  "type": "Feature",
  "properties": {
    "tgn:hierarchy":[
        "tgn:7569793",
        "tgn:1001828",
        "tgn:1000004",
        "tgn:7000198",
        "tgn:7029392"
    ],
    "tgn:id":7569793,
    "tgn:name:en":"Upparguda",
    "tgn:placetype":[
        "aat:300008347"
    ]
},
  "bbox": [],
  "geometry": {"coordinates":[78.615,17.189722],"type":"Point"}
}