{
  "id": 2390282,
  "type": "Feature",
  "properties": {
    "tgn:hierarchy":[
        "tgn:2390282",
        "tgn:1000001",
        "tgn:7016172",
        "tgn:7012149",
        "tgn:2000161",
        "tgn:7029392"
    ],
    "tgn:id":2390282,
    "tgn:name":"Highland",
    "tgn:placetype":[
        "aat:300008347"
    ]
},
  "bbox": [],
  "geometry": {"coordinates":[-93.95,34.6167],"type":"Point"}
}