{
  "id": 2296034,
  "type": "Feature",
  "properties": {
    "tgn:hierarchy":[
        "tgn:2296034",
        "tgn:1000001",
        "tgn:7012149",
        "tgn:1002645",
        "tgn:7007920",
        "tgn:7029392"
    ],
    "tgn:id":2296034,
    "tgn:name":"Dry Bed Lakes",
    "tgn:placetype":[
        "aat:300008680"
    ]
},
  "bbox": [],
  "geometry": {"coordinates":[-123.3833,47.3167],"type":"Point"}
}