{
  "id": 1045553,
  "type": "Feature",
  "properties": {
    "tgn:hierarchy":[
        "tgn:1045553",
        "tgn:1000003",
        "tgn:7003122",
        "tgn:1001737",
        "tgn:1000080",
        "tgn:7029392"
    ],
    "tgn:id":1045553,
    "tgn:name":"Monterosso Almo",
    "tgn:placetype":[
        "aat:300008347"
    ]
},
  "bbox": [],
  "geometry": {"coordinates":[14.766667,37.083333],"type":"Point"}
}