{
  "id": 2571989,
  "type": "Feature",
  "properties": {
    "tgn:hierarchy":[
        "tgn:2571989",
        "tgn:1000001",
        "tgn:7012149",
        "tgn:2002175",
        "tgn:7007919",
        "tgn:7029392"
    ],
    "tgn:id":2571989,
    "tgn:name":"Payne Pond",
    "tgn:placetype":[
        "aat:300006191"
    ]
},
  "bbox": [],
  "geometry": {"coordinates":[-78.8667,37.7333],"type":"Point"}
}