{
  "id": 2496493,
  "type": "Feature",
  "properties": {
    "tgn:hierarchy":[
        "tgn:2496493",
        "tgn:1000001",
        "tgn:7012149",
        "tgn:2000390",
        "tgn:7007248",
        "tgn:7029392"
    ],
    "tgn:id":2496493,
    "tgn:name":"Mathis Lake",
    "tgn:placetype":[
        "aat:300008680"
    ]
},
  "bbox": [],
  "geometry": {"coordinates":[-84.7167,33.0667],"type":"Point"}
}