{
  "id": 7524390,
  "type": "Feature",
  "properties": {
    "tgn:hierarchy":[
        "tgn:7524390",
        "tgn:7001242",
        "tgn:7016833",
        "tgn:7001335",
        "tgn:7029392"
    ],
    "tgn:id":7524390,
    "tgn:name":"Awgh\u0101dat al M\u0101shiyah",
    "tgn:placetype":[
        "aat:300008750"
    ]
},
  "bbox": [],
  "geometry": {"coordinates":[32.84691,30.72682],"type":"Point"}
}