{
  "id": 2456332,
  "type": "Feature",
  "properties": {
    "tgn:hierarchy":[
        "tgn:2456332",
        "tgn:1000001",
        "tgn:7012149",
        "tgn:2001275",
        "tgn:7007524",
        "tgn:7029392"
    ],
    "tgn:id":2456332,
    "tgn:name":"Little Horseshoe Creek",
    "tgn:placetype":[
        "aat:300008706"
    ]
},
  "bbox": [],
  "geometry": {"coordinates":[-111.2333,45.95],"type":"Point"}
}