{
  "id": 2513575,
  "type": "Feature",
  "properties": {
    "tgn:hierarchy":[
        "tgn:2513575",
        "tgn:1000001",
        "tgn:1002539",
        "tgn:7012149",
        "tgn:7007516",
        "tgn:7029392"
    ],
    "tgn:id":2513575,
    "tgn:name":"Mill Pond",
    "tgn:placetype":[
        "aat:300008680"
    ]
},
  "bbox": [],
  "geometry": {"coordinates":[-75.8167,39.2667],"type":"Point"}
}