{
  "id": 1080891,
  "type": "Feature",
  "properties": {
    "tgn:hierarchy":[
        "tgn:1080891",
        "tgn:7000897",
        "tgn:1001040",
        "tgn:1000004",
        "tgn:1000120",
        "tgn:7029392"
    ],
    "tgn:id":1080891,
    "tgn:name":"Mutsumi",
    "tgn:placetype":[
        "aat:300008347"
    ]
},
  "bbox": [],
  "geometry": {"coordinates":[131.5667,34.4333],"type":"Point"}
}