{
  "id": 7551626,
  "type": "Feature",
  "properties": {
    "tgn:hierarchy":[
        "tgn:7551626",
        "tgn:1000004",
        "tgn:7000198",
        "tgn:1001895",
        "tgn:7029392"
    ],
    "tgn:id":7551626,
    "tgn:name:en":"Dolphin Rock",
    "tgn:placetype":[
        "aat:300011692"
    ]
},
  "bbox": [],
  "geometry": {"coordinates":[72.8375,18.913056],"type":"Point"}
}