<<<<<<< HEAD
{
  "id": 2407415,
  "type": "Feature",
  "properties": {
    "tgn:hierarchy":[
        "tgn:2407415",
        "tgn:1000001",
        "tgn:7012149",
        "tgn:7014589",
        "tgn:7007515",
        "tgn:7029392"
    ],
    "tgn:id":2407415,
    "tgn:name":"Huntley Creek",
    "tgn:placetype":[
        "aat:300008706"
    ]
},
  "bbox": [],
  "geometry": {"coordinates":[-67.25,44.7167],"type":"Point"}
}
=======
{"geometry":{"type":"Point","coordinates":[-67.250000,44.716700]},"type":"Feature","properties":{"hierarchy":["tgn:2407415","tgn:1000001","tgn:7012149","tgn:7014589","tgn:7007515","tgn:7029392"],"placetype":["aat:300008706"],"id":2407415,"name:xx":"Huntley Creek"}}
>>>>>>> 03f74aca74312dbeaf24d7e61306dd6a786dc3d0
