{
  "id": 7097739,
  "type": "Feature",
  "properties": {
    "tgn:hierarchy":[
        "tgn:7097739",
        "tgn:1000003",
        "tgn:7003676",
        "tgn:7000084",
        "tgn:7029392"
    ],
    "tgn:id":7097739,
    "tgn:name":"Sophiental, Staatsforst",
    "tgn:placetype":[
        "aat:300008863"
    ]
},
  "bbox": [],
  "geometry": {"coordinates":[10.566667,52.316667],"type":"Point"}
}