{
  "id": 7300157,
  "type": "Feature",
  "properties": {
    "tgn:hierarchy":[
        "tgn:7300157",
        "tgn:7002807",
        "tgn:1000003",
        "tgn:7003837",
        "tgn:1000095",
        "tgn:7029392"
    ],
    "tgn:id":7300157,
    "tgn:name":"Tudia, Sierra de",
    "tgn:placetype":[
        "aat:300008795"
    ]
},
  "bbox": [],
  "geometry": {"coordinates":[-6.333333,38.033333],"type":"Point"}
}