{
  "id": 2586008,
  "type": "Feature",
  "properties": {
    "tgn:hierarchy":[
        "tgn:2586008",
        "tgn:1000001",
        "tgn:7012149",
        "tgn:7007157",
        "tgn:7014005",
        "tgn:7029392"
    ],
    "tgn:id":2586008,
    "tgn:name":"Pirates Cove",
    "tgn:placetype":[
        "aat:300132316"
    ]
},
  "bbox": [],
  "geometry": {"coordinates":[-122.55,37.85],"type":"Point"}
}