{
  "id": 1042545,
  "type": "Feature",
  "properties": {
    "tgn:hierarchy":[
        "tgn:1042545",
        "tgn:7594017",
        "tgn:1000003",
        "tgn:1000077",
        "tgn:7029392"
    ],
    "tgn:id":1042545,
    "tgn:name":"Raufarh\u00f6fn",
    "tgn:placetype":[
        "aat:300008347"
    ]
},
  "bbox": [],
  "geometry": {"coordinates":[-15.9167,66.4667],"type":"Point"}
}