<<<<<<< HEAD
{
  "id": 7246292,
  "type": "Feature",
  "properties": {
    "tgn:hierarchy":[
        "tgn:7246292",
        "tgn:7003461",
        "tgn:1000003",
        "tgn:1000063",
        "tgn:7018236",
        "tgn:7029392"
    ],
    "tgn:id":7246292,
    "tgn:name":"Burg",
    "tgn:placetype":[
        "aat:300005567"
    ]
},
  "bbox": [],
  "geometry": {"coordinates":[5.2,50.966667],"type":"Point"}
}
=======
{"geometry":{"type":"Point","coordinates":[5.200000,50.966667]},"type":"Feature","properties":{"hierarchy":["tgn:7246292","tgn:7003461","tgn:1000003","tgn:1000063","tgn:7018236","tgn:7029392"],"placetype":["aat:300005567"],"id":7246292,"name:xx":"Burg"}}
>>>>>>> 03f74aca74312dbeaf24d7e61306dd6a786dc3d0
