{
  "id": 2202059,
  "type": "Feature",
  "properties": {
    "tgn:hierarchy":[
        "tgn:2202059",
        "tgn:1000001",
        "tgn:7012149",
        "tgn:2000546",
        "tgn:7007252",
        "tgn:7029392"
    ],
    "tgn:id":2202059,
    "tgn:name":"Buck Knob",
    "tgn:placetype":[
        "aat:300008798"
    ]
},
  "bbox": [],
  "geometry": {"coordinates":[-86.8167,38.7333],"type":"Point"}
}