{
  "id": 7589792,
  "type": "Feature",
  "properties": {
    "tgn:hierarchy":[
        "tgn:7589792",
        "tgn:1000004",
        "tgn:1001871",
        "tgn:7000198",
        "tgn:7029392"
    ],
    "tgn:id":7589792,
    "tgn:name:en":"Sikandarpur",
    "tgn:placetype":[
        "aat:300008347"
    ]
},
  "bbox": [],
  "geometry": {"coordinates":[77.152537,29.839245],"type":"Point"}
}