{
  "id": 2261576,
  "type": "Feature",
  "properties": {
    "tgn:hierarchy":[
        "tgn:2261576",
        "tgn:1000001",
        "tgn:2002102",
        "tgn:7012149",
        "tgn:7007827",
        "tgn:7029392"
    ],
    "tgn:id":2261576,
    "tgn:name":"Cove Canyon",
    "tgn:placetype":[
        "aat:300008761"
    ]
},
  "bbox": [],
  "geometry": {"coordinates":[-113.2667,41.8667],"type":"Point"}
}