{
  "id": 7405724,
  "type": "Feature",
  "properties": {
    "tgn:hierarchy":[
        "tgn:7405724",
        "tgn:7005585",
        "tgn:1000001",
        "tgn:7005560",
        "tgn:7029392"
    ],
    "tgn:id":7405724,
    "tgn:name":"Papalutla, R\u00edo",
    "tgn:placetype":[
        "aat:300008699"
    ]
},
  "bbox": [],
  "geometry": {"coordinates":[-98.916667,18.033333],"type":"Point"}
}