{
  "id": 7381000,
  "type": "Feature",
  "properties": {
    "tgn:hierarchy":[
        "tgn:7381000",
        "tgn:1001853",
        "tgn:1000001",
        "tgn:7005560",
        "tgn:7029392"
    ],
    "tgn:id":7381000,
    "tgn:name":"Los Lirios",
    "tgn:placetype":[
        "aat:300008347"
    ]
},
  "bbox": [],
  "geometry": {"coordinates":[-100.633333,25.366667],"type":"Point"}
}