{
  "id": 7035256,
  "type": "Feature",
  "properties": {
    "tgn:hierarchy":[
        "tgn:7035256",
        "tgn:7003006",
        "tgn:1000003",
        "tgn:7002997",
        "tgn:1000080",
        "tgn:7029392"
    ],
    "tgn:id":7035256,
    "tgn:name":"Grande, Valle",
    "tgn:placetype":[
        "aat:300008679"
    ]
},
  "bbox": [],
  "geometry": {"coordinates":[13.050278,45.655278],"type":"Point"}
}