<<<<<<< HEAD
{
  "id": 2402188,
  "type": "Feature",
  "properties": {
    "tgn:hierarchy":[
        "tgn:2402188",
        "tgn:1000001",
        "tgn:7012149",
        "tgn:2002387",
        "tgn:7007923",
        "tgn:7029392"
    ],
    "tgn:id":2402188,
    "tgn:name":"Horsethief Canyon",
    "tgn:placetype":[
        "aat:300008761"
    ]
},
  "bbox": [],
  "geometry": {"coordinates":[-104.2,44.0667],"type":"Point"}
}
=======
{"geometry":{"type":"Point","coordinates":[-104.200000,44.066700]},"type":"Feature","properties":{"hierarchy":["tgn:2402188","tgn:1000001","tgn:7012149","tgn:2002387","tgn:7007923","tgn:7029392"],"placetype":["aat:300008761"],"id":2402188,"name:xx":"Horsethief Canyon"}}
>>>>>>> 03f74aca74312dbeaf24d7e61306dd6a786dc3d0
