{
  "id": 2094739,
  "type": "Feature",
  "properties": {
    "tgn:hierarchy":[
        "tgn:2094739",
        "tgn:1000001",
        "tgn:7013387",
        "tgn:7012149",
        "tgn:7007710",
        "tgn:7029392"
    ],
    "tgn:id":2094739,
    "tgn:name":"Wyomissing",
    "tgn:placetype":[
        "aat:300008347"
    ]
},
  "bbox": [],
  "geometry": {"coordinates":[-75.95,40.3167],"type":"Point"}
}