{
  "id": 1060797,
  "type": "Feature",
  "properties": {
    "tgn:hierarchy":[
        "tgn:1060797",
        "tgn:1000004",
        "tgn:7011606",
        "tgn:7018214",
        "tgn:7002435",
        "tgn:7029392"
    ],
    "tgn:id":1060797,
    "tgn:name":"Ust Manya",
    "tgn:placetype":[
        "aat:300008347"
    ]
},
  "bbox": [],
  "geometry": {"coordinates":[60.25,62.25],"type":"Point"}
}