{
  "id": 2586857,
  "type": "Feature",
  "properties": {
    "tgn:hierarchy":[
        "tgn:2586857",
        "tgn:7002659",
        "tgn:1000001",
        "tgn:7012149",
        "tgn:2000036",
        "tgn:7029392"
    ],
    "tgn:id":2586857,
    "tgn:name":"Plain View",
    "tgn:placetype":[
        "aat:300008347"
    ]
},
  "bbox": [],
  "geometry": {"coordinates":[-86.7667,33.5667],"type":"Point"}
}