{
  "id": 7517937,
  "type": "Feature",
  "properties": {
    "tgn:hierarchy":[
        "tgn:7517937",
        "tgn:7520092",
        "tgn:1008380",
        "tgn:1000226",
        "tgn:1000006",
        "tgn:7029392"
    ],
    "tgn:id":7517937,
    "tgn:name:en":"Maungawaru",
    "tgn:placetype":[
        "aat:300008795"
    ]
},
  "bbox": [],
  "geometry": {"coordinates":[177.75,-38.05],"type":"Point"}
}