{
  "id": 2498233,
  "type": "Feature",
  "properties": {
    "tgn:hierarchy":[
        "tgn:2498233",
        "tgn:1000001",
        "tgn:2001419",
        "tgn:7012149",
        "tgn:7007526",
        "tgn:7029392"
    ],
    "tgn:id":2498233,
    "tgn:name":"Mazuma Mine",
    "tgn:placetype":[
        "aat:300000390"
    ]
},
  "bbox": [],
  "geometry": {"coordinates":[-118.4833,40.3167],"type":"Point"}
}