{
  "id": 2087714,
  "type": "Feature",
  "properties": {
    "tgn:hierarchy":[
        "tgn:2087714",
        "tgn:1002153",
        "tgn:1000001",
        "tgn:7012149",
        "tgn:7007710",
        "tgn:7029392"
    ],
    "tgn:id":2087714,
    "tgn:name":"Dayton",
    "tgn:placetype":[
        "aat:300008347"
    ]
},
  "bbox": [],
  "geometry": {"coordinates":[-79.2333,40.8667],"type":"Point"}
}