{
  "id": 7426230,
  "type": "Feature",
  "properties": {
    "tgn:hierarchy":[
        "tgn:7426230",
        "tgn:7005581",
        "tgn:1000001",
        "tgn:7005560",
        "tgn:7029392"
    ],
    "tgn:id":7426230,
    "tgn:name":"El Bilito",
    "tgn:placetype":[
        "aat:300008347"
    ]
},
  "bbox": [],
  "geometry": {"coordinates":[-107.716667,30.716667],"type":"Point"}
}