<<<<<<< HEAD
{
  "id": 7245588,
  "type": "Feature",
  "properties": {
    "tgn:hierarchy":[
        "tgn:7245588",
        "tgn:7003465",
        "tgn:1000003",
        "tgn:1000063",
        "tgn:4012014",
        "tgn:7029392"
    ],
    "tgn:id":7245588,
    "tgn:name":"Bronze",
    "tgn:placetype":[
        "aat:300008699"
    ]
},
  "bbox": [],
  "geometry": {"coordinates":[5.566667,50.183333],"type":"Point"}
}
=======
{"geometry":{"type":"Point","coordinates":[5.566667,50.183333]},"type":"Feature","properties":{"hierarchy":["tgn:7245588","tgn:7003465","tgn:1000003","tgn:1000063","tgn:4012014","tgn:7029392"],"placetype":["aat:300008699"],"id":7245588,"name:xx":"Bronze"}}
>>>>>>> 03f74aca74312dbeaf24d7e61306dd6a786dc3d0
