{
  "id": 7245588,
  "type": "Feature",
  "properties": {
    "tgn:hierarchy":[
        "tgn:7245588",
        "tgn:7003465",
        "tgn:1000003",
        "tgn:1000063",
        "tgn:4012014",
        "tgn:7029392"
    ],
    "tgn:id":7245588,
    "tgn:name":"Bronze",
    "tgn:placetype":[
        "aat:300008699"
    ]
},
  "bbox": [],
  "geometry": {"coordinates":[5.566667,50.183333],"type":"Point"}
}