<<<<<<< HEAD
{
  "id": 7244055,
  "type": "Feature",
  "properties": {
    "tgn:hierarchy":[
        "tgn:7244055",
        "tgn:7003466",
        "tgn:1000003",
        "tgn:1000063",
        "tgn:4012014",
        "tgn:7029392"
    ],
    "tgn:id":7244055,
    "tgn:name":"Ferme de la Jonqui\u00e8re",
    "tgn:placetype":[
        "aat:300000206"
    ]
},
  "bbox": [],
  "geometry": {"coordinates":[4.516667,50.166667],"type":"Point"}
}
=======
{"geometry":{"type":"Point","coordinates":[4.516667,50.166667]},"type":"Feature","properties":{"hierarchy":["tgn:7244055","tgn:7003466","tgn:1000003","tgn:1000063","tgn:4012014","tgn:7029392"],"placetype":["aat:300000206"],"id":7244055,"name:xx":"Ferme de la Jonqui\u00e8re"}}
>>>>>>> 03f74aca74312dbeaf24d7e61306dd6a786dc3d0
