{
  "id": 2195292,
  "type": "Feature",
  "properties": {
    "tgn:hierarchy":[
        "tgn:2195292",
        "tgn:1000001",
        "tgn:1002260",
        "tgn:7012149",
        "tgn:7007920",
        "tgn:7029392"
    ],
    "tgn:id":2195292,
    "tgn:name":"Brisky Canyon",
    "tgn:placetype":[
        "aat:300008761"
    ]
},
  "bbox": [],
  "geometry": {"coordinates":[-120.55,47.4667],"type":"Point"}
}