{
  "id": 7263255,
  "type": "Feature",
  "properties": {
    "tgn:concordances":{
        "gn:id":"2757499"
    },
    "tgn:hierarchy":[
        "tgn:7263255",
        "tgn:1000003",
        "tgn:7003622",
        "tgn:7016845",
        "tgn:7029392"
    ],
    "tgn:id":7263255,
    "tgn:name:nl":"De Horck",
    "tgn:placetype":[
        "aat:300008347"
    ]
},
  "bbox": [],
  "geometry": {"coordinates":[5.883333,51.233333],"type":"Point"}
}