{
  "id": 7411705,
  "type": "Feature",
  "properties": {
    "tgn:hierarchy":[
        "tgn:7411705",
        "tgn:7005580",
        "tgn:1000001",
        "tgn:7005560",
        "tgn:7029392"
    ],
    "tgn:id":7411705,
    "tgn:name":"Las Delicias",
    "tgn:placetype":[
        "aat:300008347"
    ]
},
  "bbox": [],
  "geometry": {"coordinates":[-91.480556,17.363889],"type":"Point"}
}