{
  "id": 7311505,
  "type": "Feature",
  "properties": {
    "tgn:hierarchy":[
        "tgn:7311505",
        "tgn:1001695",
        "tgn:1000049",
        "tgn:1000002",
        "tgn:7029392"
    ],
    "tgn:id":7311505,
    "tgn:name":"Lo Camus",
    "tgn:placetype":[
        "aat:300008777"
    ]
},
  "bbox": [],
  "geometry": {"coordinates":[-71.65,-34.216667],"type":"Point"}
}