{
  "id": 2650164,
  "type": "Feature",
  "properties": {
    "tgn:hierarchy":[
        "tgn:2650164",
        "tgn:7030515",
        "tgn:7006450",
        "tgn:1000001",
        "tgn:7012149",
        "tgn:7029392"
    ],
    "tgn:id":2650164,
    "tgn:name":"Seal Cape",
    "tgn:placetype":[
        "aat:300008850"
    ]
},
  "bbox": [],
  "geometry": {"coordinates":[-164.6333,54.3833],"type":"Point"}
}