{
  "id": 7496944,
  "type": "Feature",
  "properties": {
    "tgn:hierarchy":[
        "tgn:7496944",
        "tgn:1000004",
        "tgn:1000454",
        "tgn:1000141",
        "tgn:7029392"
    ],
    "tgn:id":7496944,
    "tgn:name":"Wugukeng Xi",
    "tgn:placetype":[
        "aat:300008699"
    ]
},
  "bbox": [],
  "geometry": {"coordinates":[121.440432,25.083009],"type":"Point"}
}