{
  "id": 2533760,
  "type": "Feature",
  "properties": {
    "tgn:hierarchy":[
        "tgn:2533760",
        "tgn:1000001",
        "tgn:2000469",
        "tgn:7012149",
        "tgn:7007250",
        "tgn:7029392"
    ],
    "tgn:id":2533760,
    "tgn:name":"Mutton Gulch",
    "tgn:placetype":[
        "aat:300008761"
    ]
},
  "bbox": [],
  "geometry": {"coordinates":[-115.8167,46.45],"type":"Point"}
}