{
  "id": 2570161,
  "type": "Feature",
  "properties": {
    "tgn:hierarchy":[
        "tgn:2570161",
        "tgn:1002541",
        "tgn:1000001",
        "tgn:7012149",
        "tgn:7007711",
        "tgn:7029392"
    ],
    "tgn:id":2570161,
    "tgn:name":"Passeonkquis Cove",
    "tgn:placetype":[
        "aat:300132316"
    ]
},
  "bbox": [],
  "geometry": {"coordinates":[-71.3833,41.7333],"type":"Point"}
}