<<<<<<< HEAD
{
  "id": 7178771,
  "type": "Feature",
  "properties": {
    "tgn:hierarchy":[
        "tgn:7178771",
        "tgn:1000003",
        "tgn:7003676",
        "tgn:7000084",
        "tgn:7029392"
    ],
    "tgn:id":7178771,
    "tgn:name":"Hackel-Berg",
    "tgn:placetype":[
        "aat:300008777"
    ]
},
  "bbox": [],
  "geometry": {"coordinates":[10.183333,51.7],"type":"Point"}
}
=======
{"geometry":{"type":"Point","coordinates":[10.183333,51.700000]},"type":"Feature","properties":{"hierarchy":["tgn:7178771","tgn:1000003","tgn:7003676","tgn:7000084","tgn:7029392"],"placetype":["aat:300008777"],"id":7178771,"name:xx":"Hackel-Berg"}}
>>>>>>> 03f74aca74312dbeaf24d7e61306dd6a786dc3d0
