{
  "id": 7006438,
  "type": "Feature",
  "properties": {
    "tgn:hierarchy":[
        "tgn:7006438",
        "tgn:7006425",
        "tgn:1000003",
        "tgn:7006417",
        "tgn:7029392"
    ],
    "tgn:id":7006438,
    "tgn:name":"Matit, Rrethi i",
    "tgn:placetype":[
        "aat:300387145",
        "aat:300387081"
    ]
},
  "bbox": [],
  "geometry": {"coordinates":[20.083333,41.583333],"type":"Point"}
}