{
  "id": 7566186,
  "type": "Feature",
  "properties": {
    "tgn:hierarchy":[
        "tgn:7566186",
        "tgn:1000004",
        "tgn:7000198",
        "tgn:7016722",
        "tgn:7029392"
    ],
    "tgn:id":7566186,
    "tgn:name:en":"B\u0101mhangaon",
    "tgn:placetype":[
        "aat:300008347"
    ]
},
  "bbox": [],
  "geometry": {"coordinates":[79.75708,26.750114],"type":"Point"}
}