{
  "id": 2432657,
  "type": "Feature",
  "properties": {
    "tgn:hierarchy":[
        "tgn:2432657",
        "tgn:1000001",
        "tgn:7012149",
        "tgn:2000845",
        "tgn:7007255",
        "tgn:7029392"
    ],
    "tgn:id":2432657,
    "tgn:name":"Keeling Hill",
    "tgn:placetype":[
        "aat:300008798"
    ]
},
  "bbox": [],
  "geometry": {"coordinates":[-87.25,36.85],"type":"Point"}
}