{
  "id": 7484086,
  "type": "Feature",
  "properties": {
    "tgn:hierarchy":[
        "tgn:7484086",
        "tgn:1000004",
        "tgn:7492971",
        "tgn:1000141",
        "tgn:7029392"
    ],
    "tgn:id":7484086,
    "tgn:name":"Jialu Chezhan",
    "tgn:placetype":[
        "aat:300007783"
    ]
},
  "bbox": [],
  "geometry": {"coordinates":[120.624444,22.330556],"type":"Point"}
}