{
  "id": 2694850,
  "type": "Feature",
  "properties": {
    "tgn:hierarchy":[
        "tgn:2694850",
        "tgn:1002933",
        "tgn:1000001",
        "tgn:7012149",
        "tgn:7007239",
        "tgn:7029392"
    ],
    "tgn:id":2694850,
    "tgn:name":"Stickweed Pond",
    "tgn:placetype":[
        "aat:300008680"
    ]
},
  "bbox": [],
  "geometry": {"coordinates":[-75.25,38.8333],"type":"Point"}
}