{
  "id": 7030404,
  "type": "Feature",
  "properties": {
    "tgn:hierarchy":[
        "tgn:7030404",
        "tgn:1000004",
        "tgn:1001261",
        "tgn:1000111",
        "tgn:7029392"
    ],
    "tgn:id":7030404,
    "tgn:name":"Maiji Shan",
    "tgn:placetype":[
        "aat:300387007",
        "aat:300008795"
    ]
},
  "bbox": [],
  "geometry": {"coordinates":[106.05,34.299],"type":"Point"}
}