{
  "id": 2509462,
  "type": "Feature",
  "properties": {
    "tgn:hierarchy":[
        "tgn:2509462",
        "tgn:7013349",
        "tgn:1000001",
        "tgn:7012149",
        "tgn:7007708",
        "tgn:7029392"
    ],
    "tgn:id":2509462,
    "tgn:name":"Middle Fork Swayze Creek",
    "tgn:placetype":[
        "aat:300008706"
    ]
},
  "bbox": [],
  "geometry": {"coordinates":[-117.3333,44.5667],"type":"Point"}
}