{
  "id": 7554057,
  "type": "Feature",
  "properties": {
    "tgn:hierarchy":[
        "tgn:7554057",
        "tgn:1000004",
        "tgn:7000198",
        "tgn:7016788",
        "tgn:7029392"
    ],
    "tgn:id":7554057,
    "tgn:name:en":"Nip\u0101nia",
    "tgn:placetype":[
        "aat:300008347"
    ]
},
  "bbox": [],
  "geometry": {"coordinates":[76.865717,24.619392],"type":"Point"}
}