{
  "id": 2675790,
  "type": "Feature",
  "properties": {
    "tgn:hierarchy":[
        "tgn:2675790",
        "tgn:1000001",
        "tgn:7013649",
        "tgn:7012149",
        "tgn:7007251",
        "tgn:7029392"
    ],
    "tgn:id":2675790,
    "tgn:name":"Somme Woods",
    "tgn:placetype":[
        "aat:300132451"
    ]
},
  "bbox": [],
  "geometry": {"coordinates":[-87.8167,42.1333],"type":"Point"}
}