{
  "id": 7419139,
  "type": "Feature",
  "properties": {
    "tgn:hierarchy":[
        "tgn:7419139",
        "tgn:1000001",
        "tgn:7005589",
        "tgn:7005560",
        "tgn:7029392"
    ],
    "tgn:id":7419139,
    "tgn:name:es":"Larga de las Tripas, Laguna",
    "tgn:placetype":[
        "aat:300008680"
    ]
},
  "bbox": [],
  "geometry": {"coordinates":[-100.156111,27.593611],"type":"Point"}
}