<<<<<<< HEAD
{
  "id": 7377797,
  "type": "Feature",
  "properties": {
    "tgn:hierarchy":[
        "tgn:7377797",
        "tgn:1001853",
        "tgn:1000001",
        "tgn:7005560",
        "tgn:7029392"
    ],
    "tgn:id":7377797,
    "tgn:name":"Las Canteras, Sierra",
    "tgn:placetype":[
        "aat:300266640"
    ]
},
  "bbox": [],
  "geometry": {"coordinates":[-100.9,25.2],"type":"Point"}
}
=======
{"geometry":{"type":"Point","coordinates":[-100.900000,25.200000]},"type":"Feature","properties":{"hierarchy":["tgn:7377797","tgn:1001853","tgn:1000001","tgn:7005560","tgn:7029392"],"placetype":["aat:300266640"],"id":7377797,"name:xx":"Las Canteras, Sierra"}}
>>>>>>> 03f74aca74312dbeaf24d7e61306dd6a786dc3d0
