{
  "id": 1055558,
  "type": "Feature",
  "properties": {
    "tgn:hierarchy":[
        "tgn:1055558",
        "tgn:7012220",
        "tgn:1000004",
        "tgn:7006659",
        "tgn:7029392"
    ],
    "tgn:id":1055558,
    "tgn:name":"Komsomolsk",
    "tgn:placetype":[
        "aat:300008347"
    ]
},
  "bbox": [],
  "geometry": {"coordinates":[63.5667,39.0167],"type":"Point"}
}