<<<<<<< HEAD
{
  "id": 7372891,
  "type": "Feature",
  "properties": {
    "tgn:hierarchy":[
        "tgn:7372891",
        "tgn:1000001",
        "tgn:1001960",
        "tgn:7005560",
        "tgn:7029392"
    ],
    "tgn:id":7372891,
    "tgn:name":"Rancho La Fele\u00f1a",
    "tgn:placetype":[
        "aat:300000241"
    ]
},
  "bbox": [],
  "geometry": {"coordinates":[-110.65,30.216667],"type":"Point"}
}
=======
{"geometry":{"type":"Point","coordinates":[-110.650000,30.216667]},"type":"Feature","properties":{"hierarchy":["tgn:7372891","tgn:1000001","tgn:1001960","tgn:7005560","tgn:7029392"],"placetype":["aat:300000241"],"id":7372891,"name:xx":"Rancho La Fele\u00f1a"}}
>>>>>>> 03f74aca74312dbeaf24d7e61306dd6a786dc3d0
