{
  "id": 2516630,
  "type": "Feature",
  "properties": {
    "tgn:hierarchy":[
        "tgn:2516630",
        "tgn:1000001",
        "tgn:7012149",
        "tgn:2000346",
        "tgn:7007248",
        "tgn:7029392"
    ],
    "tgn:id":2516630,
    "tgn:name":"Mineral Springs",
    "tgn:placetype":[
        "aat:300008697"
    ]
},
  "bbox": [],
  "geometry": {"coordinates":[-84.3167,34.85],"type":"Point"}
}