{
  "id": 7477616,
  "type": "Feature",
  "properties": {
    "tgn:hierarchy":[
        "tgn:7477616",
        "tgn:7488858",
        "tgn:1000004",
        "tgn:1000141",
        "tgn:7029392"
    ],
    "tgn:id":7477616,
    "tgn:name":"Dayan Suidao",
    "tgn:placetype":[
        "aat:300007899"
    ]
},
  "bbox": [],
  "geometry": {"coordinates":[120.9223,23.9261],"type":"Point"}
}