<<<<<<< HEAD
{
  "id": 7477616,
  "type": "Feature",
  "properties": {
    "tgn:hierarchy":[
        "tgn:7477616",
        "tgn:7488858",
        "tgn:1000004",
        "tgn:1000141",
        "tgn:7029392"
    ],
    "tgn:id":7477616,
    "tgn:name":"Dayan Suidao",
    "tgn:placetype":[
        "aat:300007899"
    ]
},
  "bbox": [],
  "geometry": {"coordinates":[120.9223,23.9261],"type":"Point"}
}
=======
{"geometry":{"type":"Point","coordinates":[120.922300,23.926100]},"type":"Feature","properties":{"hierarchy":["tgn:7477616","tgn:7488858","tgn:1000004","tgn:1000141","tgn:7029392"],"placetype":["aat:300007899"],"id":7477616,"name:xx":"Dayan Suidao"}}
>>>>>>> 03f74aca74312dbeaf24d7e61306dd6a786dc3d0
