{
  "id": 2775396,
  "type": "Feature",
  "properties": {
    "tgn:hierarchy":[
        "tgn:2775396",
        "tgn:1000001",
        "tgn:2001429",
        "tgn:7012149",
        "tgn:7007566",
        "tgn:7029392"
    ],
    "tgn:id":2775396,
    "tgn:name":"Wilson Canyon",
    "tgn:placetype":[
        "aat:300008761"
    ]
},
  "bbox": [],
  "geometry": {"coordinates":[-108.5667,33.6833],"type":"Point"}
}