<<<<<<< HEAD
{
  "id": 2405888,
  "type": "Feature",
  "properties": {
    "tgn:hierarchy":[
        "tgn:2405888",
        "tgn:1000001",
        "tgn:7012149",
        "tgn:2000559",
        "tgn:7007252",
        "tgn:7029392"
    ],
    "tgn:id":2405888,
    "tgn:name":"Hulman Lodge Lake",
    "tgn:placetype":[
        "aat:300006191"
    ]
},
  "bbox": [],
  "geometry": {"coordinates":[-87.3167,39.4667],"type":"Point"}
}
=======
{"geometry":{"type":"Point","coordinates":[-87.316700,39.466700]},"type":"Feature","properties":{"hierarchy":["tgn:2405888","tgn:1000001","tgn:7012149","tgn:2000559","tgn:7007252","tgn:7029392"],"placetype":["aat:300006191"],"id":2405888,"name:xx":"Hulman Lodge Lake"}}
>>>>>>> 03f74aca74312dbeaf24d7e61306dd6a786dc3d0
