<<<<<<< HEAD
{
  "id": 7241240,
  "type": "Feature",
  "properties": {
    "tgn:hierarchy":[
        "tgn:7241240",
        "tgn:7003466",
        "tgn:1000003",
        "tgn:1000063",
        "tgn:4012014",
        "tgn:7029392"
    ],
    "tgn:id":7241240,
    "tgn:name":"Le Cahoti",
    "tgn:placetype":[
        "aat:300008347"
    ]
},
  "bbox": [],
  "geometry": {"coordinates":[5.004977,50.353308],"type":"Point"}
}
=======
{"geometry":{"type":"Point","coordinates":[5.004977,50.353308]},"type":"Feature","properties":{"hierarchy":["tgn:7241240","tgn:7003466","tgn:1000003","tgn:1000063","tgn:4012014","tgn:7029392"],"placetype":["aat:300008347"],"id":7241240,"name:xx":"Le Cahoti"}}
>>>>>>> 03f74aca74312dbeaf24d7e61306dd6a786dc3d0
