{
  "id": 7234295,
  "type": "Feature",
  "properties": {
    "tgn:hierarchy":[
        "tgn:7234295",
        "tgn:7002690",
        "tgn:7012056",
        "tgn:1000003",
        "tgn:1000074",
        "tgn:7029392"
    ],
    "tgn:id":7234295,
    "tgn:name":"Ath\u00e1natoi",
    "tgn:placetype":[
        "aat:300008347"
    ]
},
  "bbox": [],
  "geometry": {"coordinates":[25.083333,35.283333],"type":"Point"}
}