{
  "id": 7591078,
  "type": "Feature",
  "properties": {
    "tgn:hierarchy":[
        "tgn:7591078",
        "tgn:1000004",
        "tgn:7000198",
        "tgn:7000799",
        "tgn:7029392"
    ],
    "tgn:id":7591078,
    "tgn:name:en":"Salmen de Kothe",
    "tgn:placetype":[
        "aat:300008347"
    ]
},
  "bbox": [],
  "geometry": {"coordinates":[74.882996,32.577195],"type":"Point"}
}