{
  "id": 2564494,
  "type": "Feature",
  "properties": {
    "tgn:hierarchy":[
        "tgn:2564494",
        "tgn:2000919",
        "tgn:1000001",
        "tgn:7012149",
        "tgn:7007515",
        "tgn:7029392"
    ],
    "tgn:id":2564494,
    "tgn:name":"Packard Hill",
    "tgn:placetype":[
        "aat:300008798"
    ]
},
  "bbox": [],
  "geometry": {"coordinates":[-67.8667,46.4333],"type":"Point"}
}