{
  "id": 7301275,
  "type": "Feature",
  "properties": {
    "tgn:hierarchy":[
        "tgn:7301275",
        "tgn:7002759",
        "tgn:7008909",
        "tgn:1000003",
        "tgn:1000095",
        "tgn:7029392"
    ],
    "tgn:id":7301275,
    "tgn:name":"Monesma",
    "tgn:placetype":[
        "aat:300008347"
    ]
},
  "bbox": [],
  "geometry": {"coordinates":[0.062214,41.924375],"type":"Point"}
}