{
  "id": 7581580,
  "type": "Feature",
  "properties": {
    "tgn:hierarchy":[
        "tgn:7581580",
        "tgn:1000004",
        "tgn:7000198",
        "tgn:7016788",
        "tgn:7029392"
    ],
    "tgn:id":7581580,
    "tgn:name:en":"S\u012blor",
    "tgn:placetype":[
        "aat:300008347"
    ]
},
  "bbox": [],
  "geometry": {"coordinates":[75.608661,25.376552],"type":"Point"}
}