<<<<<<< HEAD
{
  "id": 2259751,
  "type": "Feature",
  "properties": {
    "tgn:hierarchy":[
        "tgn:2259751",
        "tgn:1000001",
        "tgn:7012149",
        "tgn:2002113",
        "tgn:7007827",
        "tgn:7029392"
    ],
    "tgn:id":2259751,
    "tgn:name":"Cougar Knoll",
    "tgn:placetype":[
        "aat:300008798"
    ]
},
  "bbox": [],
  "geometry": {"coordinates":[-111.1333,37.3],"type":"Point"}
}
=======
{"geometry":{"type":"Point","coordinates":[-111.133300,37.300000]},"type":"Feature","properties":{"hierarchy":["tgn:2259751","tgn:1000001","tgn:7012149","tgn:2002113","tgn:7007827","tgn:7029392"],"placetype":["aat:300008798"],"id":2259751,"name:xx":"Cougar Knoll"}}
>>>>>>> 03f74aca74312dbeaf24d7e61306dd6a786dc3d0
