{
  "id": 7482126,
  "type": "Feature",
  "properties": {
    "tgn:hierarchy":[
        "tgn:7482126",
        "tgn:1000004",
        "tgn:7489179",
        "tgn:1000141",
        "tgn:7029392"
    ],
    "tgn:id":7482126,
    "tgn:name":"Wuming Xi",
    "tgn:placetype":[
        "aat:300008699"
    ]
},
  "bbox": [],
  "geometry": {"coordinates":[121.758611,24.438056],"type":"Point"}
}