<<<<<<< HEAD
{
  "id": 7482126,
  "type": "Feature",
  "properties": {
    "tgn:hierarchy":[
        "tgn:7482126",
        "tgn:1000004",
        "tgn:7489179",
        "tgn:1000141",
        "tgn:7029392"
    ],
    "tgn:id":7482126,
    "tgn:name":"Wuming Xi",
    "tgn:placetype":[
        "aat:300008699"
    ]
},
  "bbox": [],
  "geometry": {"coordinates":[121.758611,24.438056],"type":"Point"}
}
=======
{"geometry":{"type":"Point","coordinates":[121.758611,24.438056]},"type":"Feature","properties":{"hierarchy":["tgn:7482126","tgn:1000004","tgn:7489179","tgn:1000141","tgn:7029392"],"placetype":["aat:300008699"],"id":7482126,"name:xx":"Wuming Xi"}}
>>>>>>> 03f74aca74312dbeaf24d7e61306dd6a786dc3d0
