<<<<<<< HEAD
{
  "id": 2766095,
  "type": "Feature",
  "properties": {
    "tgn:hierarchy":[
        "tgn:2766095",
        "tgn:1000001",
        "tgn:7012149",
        "tgn:2000960",
        "tgn:7007520",
        "tgn:7029392"
    ],
    "tgn:id":2766095,
    "tgn:name":"White House Creek",
    "tgn:placetype":[
        "aat:300008706"
    ]
},
  "bbox": [],
  "geometry": {"coordinates":[-89.5167,46.3833],"type":"Point"}
}
=======
{"geometry":{"type":"Point","coordinates":[-89.516700,46.383300]},"type":"Feature","properties":{"hierarchy":["tgn:2766095","tgn:1000001","tgn:7012149","tgn:2000960","tgn:7007520","tgn:7029392"],"placetype":["aat:300008706"],"id":2766095,"name:xx":"White House Creek"}}
>>>>>>> 03f74aca74312dbeaf24d7e61306dd6a786dc3d0
