{
  "id": 2024459,
  "type": "Feature",
  "properties": {
    "tgn:hierarchy":[
        "tgn:2024459",
        "tgn:1000001",
        "tgn:7012149",
        "tgn:2000433",
        "tgn:7007248",
        "tgn:7029392"
    ],
    "tgn:id":2024459,
    "tgn:name":"Sycamore",
    "tgn:placetype":[
        "aat:300008347"
    ]
},
  "bbox": [],
  "geometry": {"coordinates":[-83.6333,31.6667],"type":"Point"}
}