{
  "id": 2414892,
  "type": "Feature",
  "properties": {
    "tgn:hierarchy":[
        "tgn:2414892",
        "tgn:1000001",
        "tgn:7012149",
        "tgn:7007157",
        "tgn:1002621",
        "tgn:7029392"
    ],
    "tgn:id":2414892,
    "tgn:name":"Isberg Peak",
    "tgn:placetype":[
        "aat:300008798"
    ]
},
  "bbox": [],
  "geometry": {"coordinates":[-119.3167,37.65],"type":"Point"}
}