{
  "id": 7499074,
  "type": "Feature",
  "properties": {
    "tgn:hierarchy":[
        "tgn:7499074",
        "tgn:1000004",
        "tgn:1000959",
        "tgn:1000141",
        "tgn:7029392"
    ],
    "tgn:id":7499074,
    "tgn:name":"Fuyou Gong",
    "tgn:placetype":[
        "aat:300007595"
    ]
},
  "bbox": [],
  "geometry": {"coordinates":[121.538464,25.068627],"type":"Point"}
}