{
  "id": 7373897,
  "type": "Feature",
  "properties": {
    "tgn:hierarchy":[
        "tgn:7373897",
        "tgn:1000001",
        "tgn:7005589",
        "tgn:7005560",
        "tgn:7029392"
    ],
    "tgn:id":7373897,
    "tgn:name":"La Bandera",
    "tgn:placetype":[
        "aat:300008347"
    ]
},
  "bbox": [],
  "geometry": {"coordinates":[-100.05,26.35],"type":"Point"}
}