<<<<<<< HEAD
{
  "id": 7373897,
  "type": "Feature",
  "properties": {
    "tgn:hierarchy":[
        "tgn:7373897",
        "tgn:1000001",
        "tgn:7005589",
        "tgn:7005560",
        "tgn:7029392"
    ],
    "tgn:id":7373897,
    "tgn:name":"La Bandera",
    "tgn:placetype":[
        "aat:300008347"
    ]
},
  "bbox": [],
  "geometry": {"coordinates":[-100.05,26.35],"type":"Point"}
}
=======
{"geometry":{"type":"Point","coordinates":[-100.050000,26.350000]},"type":"Feature","properties":{"hierarchy":["tgn:7373897","tgn:1000001","tgn:7005589","tgn:7005560","tgn:7029392"],"placetype":["aat:300008347"],"id":7373897,"name:xx":"La Bandera"}}
>>>>>>> 03f74aca74312dbeaf24d7e61306dd6a786dc3d0
