{
  "id": 7316367,
  "type": "Feature",
  "properties": {
    "tgn:hierarchy":[
        "tgn:7316367",
        "tgn:1001657",
        "tgn:1000049",
        "tgn:1000002",
        "tgn:7029392"
    ],
    "tgn:id":7316367,
    "tgn:name":"Castillo, Portillo del",
    "tgn:placetype":[
        "aat:300259572"
    ]
},
  "bbox": [],
  "geometry": {"coordinates":[-70.233333,-30.616667],"type":"Point"}
}