{
  "id": 2077735,
  "type": "Feature",
  "properties": {
    "tgn:hierarchy":[
        "tgn:2077735",
        "tgn:1000001",
        "tgn:2001590",
        "tgn:7012149",
        "tgn:7007705",
        "tgn:7029392"
    ],
    "tgn:id":2077735,
    "tgn:name":"Joliette",
    "tgn:placetype":[
        "aat:300008347"
    ]
},
  "bbox": [],
  "geometry": {"coordinates":[-97.2167,48.8167],"type":"Point"}
}