{
  "id": 1095451,
  "type": "Feature",
  "properties": {
    "tgn:hierarchy":[
        "tgn:1095451",
        "tgn:7001242",
        "tgn:7016833",
        "tgn:7001312",
        "tgn:7029392"
    ],
    "tgn:id":1095451,
    "tgn:name":"Dam\u0101\u1e6d",
    "tgn:placetype":[
        "aat:300008347"
    ]
},
  "bbox": [],
  "geometry": {"coordinates":[30.959909,30.944378],"type":"Point"}
}