{
  "id": 7343023,
  "type": "Feature",
  "properties": {
    "tgn:hierarchy":[
        "tgn:7343023",
        "tgn:7001165",
        "tgn:1000003",
        "tgn:7002793",
        "tgn:1000095",
        "tgn:7029392"
    ],
    "tgn:id":7343023,
    "tgn:name":"Caser\u00edo Casas de Capuchinos",
    "tgn:placetype":[
        "aat:300008347"
    ]
},
  "bbox": [],
  "geometry": {"coordinates":[-0.583333,38.816667],"type":"Point"}
}