{
  "id": 7111642,
  "type": "Feature",
  "properties": {
    "tgn:hierarchy":[
        "tgn:7111642",
        "tgn:7003692",
        "tgn:1000003",
        "tgn:7000084",
        "tgn:7029392"
    ],
    "tgn:id":7111642,
    "tgn:name":"Rippberg",
    "tgn:placetype":[
        "aat:300008347"
    ]
},
  "bbox": [],
  "geometry": {"coordinates":[9.293333,49.622222],"type":"Point"}
}