<<<<<<< HEAD
{
  "id": 2250558,
  "type": "Feature",
  "properties": {
    "tgn:hierarchy":[
        "tgn:2250558",
        "tgn:1000001",
        "tgn:2001415",
        "tgn:7012149",
        "tgn:7007526",
        "tgn:7029392"
    ],
    "tgn:id":2250558,
    "tgn:name":"Color Back Mine",
    "tgn:placetype":[
        "aat:300000390"
    ]
},
  "bbox": [],
  "geometry": {"coordinates":[-116.6833,40.35],"type":"Point"}
}
=======
{"geometry":{"type":"Point","coordinates":[-116.683300,40.350000]},"type":"Feature","properties":{"hierarchy":["tgn:2250558","tgn:1000001","tgn:2001415","tgn:7012149","tgn:7007526","tgn:7029392"],"placetype":["aat:300000390"],"id":2250558,"name:xx":"Color Back Mine"}}
>>>>>>> 03f74aca74312dbeaf24d7e61306dd6a786dc3d0
