{
  "id": 2268331,
  "type": "Feature",
  "properties": {
    "tgn:hierarchy":[
        "tgn:2268331",
        "tgn:1000001",
        "tgn:7012149",
        "tgn:7007826",
        "tgn:7029392"
    ],
    "tgn:id":2268331,
    "tgn:name":"Crooked Marsh",
    "tgn:placetype":[
        "aat:300008905"
    ]
},
  "bbox": [],
  "geometry": {"coordinates":[-94.5667,29.8833],"type":"Point"}
}