{
  "id": 2136565,
  "type": "Feature",
  "properties": {
    "tgn:hierarchy":[
        "tgn:2136565",
        "tgn:1000001",
        "tgn:7012149",
        "tgn:2000441",
        "tgn:7007248",
        "tgn:7029392"
    ],
    "tgn:id":2136565,
    "tgn:name":"Archers Lakes",
    "tgn:placetype":[
        "aat:300006191"
    ]
},
  "bbox": [],
  "geometry": {"coordinates":[-82.6833,33.1167],"type":"Point"}
}