{
  "id": 2482700,
  "type": "Feature",
  "properties": {
    "tgn:hierarchy":[
        "tgn:2482700",
        "tgn:1000001",
        "tgn:7012149",
        "tgn:1002945",
        "tgn:7007710",
        "tgn:7029392"
    ],
    "tgn:id":2482700,
    "tgn:name":"Lard, Lake",
    "tgn:placetype":[
        "aat:300008680"
    ]
},
  "bbox": [],
  "geometry": {"coordinates":[-77.4167,41.7833],"type":"Point"}
}