<<<<<<< HEAD
{
  "id": 7477575,
  "type": "Feature",
  "properties": {
    "tgn:hierarchy":[
        "tgn:7477575",
        "tgn:1000004",
        "tgn:1000454",
        "tgn:1000141",
        "tgn:7029392"
    ],
    "tgn:id":7477575,
    "tgn:name":"Sirui Diyi Suidao",
    "tgn:placetype":[
        "aat:300007899"
    ]
},
  "bbox": [],
  "geometry": {"coordinates":[121.7714,25.103059],"type":"Point"}
}
=======
{"geometry":{"type":"Point","coordinates":[121.771400,25.103059]},"type":"Feature","properties":{"hierarchy":["tgn:7477575","tgn:1000004","tgn:1000454","tgn:1000141","tgn:7029392"],"placetype":["aat:300007899"],"id":7477575,"name:xx":"Sirui Diyi Suidao"}}
>>>>>>> 03f74aca74312dbeaf24d7e61306dd6a786dc3d0
