{
  "id": 7477575,
  "type": "Feature",
  "properties": {
    "tgn:hierarchy":[
        "tgn:7477575",
        "tgn:1000004",
        "tgn:1000454",
        "tgn:1000141",
        "tgn:7029392"
    ],
    "tgn:id":7477575,
    "tgn:name":"Sirui Diyi Suidao",
    "tgn:placetype":[
        "aat:300007899"
    ]
},
  "bbox": [],
  "geometry": {"coordinates":[121.7714,25.103059],"type":"Point"}
}