{
  "id": 7418273,
  "type": "Feature",
  "properties": {
    "tgn:hierarchy":[
        "tgn:7418273",
        "tgn:1000001",
        "tgn:7005589",
        "tgn:7005560",
        "tgn:7029392"
    ],
    "tgn:id":7418273,
    "tgn:name:es":"Cuauht\u00e9moc",
    "tgn:placetype":[
        "aat:300008347"
    ]
},
  "bbox": [],
  "geometry": {"coordinates":[-99.278333,25.033889],"type":"Point"}
}