{
  "id": 2606719,
  "type": "Feature",
  "properties": {
    "tgn:hierarchy":[
        "tgn:2606719",
        "tgn:1000001",
        "tgn:7012149",
        "tgn:7014589",
        "tgn:7007515",
        "tgn:7029392"
    ],
    "tgn:id":2606719,
    "tgn:name":"Ramsdell Cove",
    "tgn:placetype":[
        "aat:300132316"
    ]
},
  "bbox": [],
  "geometry": {"coordinates":[-67.7667,44.55],"type":"Point"}
}