{
  "id": 2433367,
  "type": "Feature",
  "properties": {
    "tgn:hierarchy":[
        "tgn:2433367",
        "tgn:1000001",
        "tgn:7012149",
        "tgn:2000450",
        "tgn:7007248",
        "tgn:7029392"
    ],
    "tgn:id":2433367,
    "tgn:name":"Kelley Lake",
    "tgn:placetype":[
        "aat:300006191"
    ]
},
  "bbox": [],
  "geometry": {"coordinates":[-83.65,31.4833],"type":"Point"}
}