{
  "id": 2309810,
  "type": "Feature",
  "properties": {
    "tgn:hierarchy":[
        "tgn:2309810",
        "tgn:1000001",
        "tgn:7012149",
        "tgn:7007515",
        "tgn:7029392"
    ],
    "tgn:id":2309810,
    "tgn:name":"Eastern River",
    "tgn:placetype":[
        "aat:300008707"
    ]
},
  "bbox": [],
  "geometry": {"coordinates":[-69.6667,44.1667],"type":"Point"}
}