{
  "id": 2347456,
  "type": "Feature",
  "properties": {
    "tgn:hierarchy":[
        "tgn:2347456",
        "tgn:7006450",
        "tgn:1000001",
        "tgn:7012149",
        "tgn:2000089",
        "tgn:7029392"
    ],
    "tgn:id":2347456,
    "tgn:name":"George Meadow",
    "tgn:placetype":[
        "aat:300055621"
    ]
},
  "bbox": [],
  "geometry": {"coordinates":[-147.4667,66.4167],"type":"Point"}
}