{
  "id": 7403491,
  "type": "Feature",
  "properties": {
    "tgn:hierarchy":[
        "tgn:7403491",
        "tgn:1000001",
        "tgn:1001906",
        "tgn:7005560",
        "tgn:7029392"
    ],
    "tgn:id":7403491,
    "tgn:name":"El Pujido",
    "tgn:placetype":[
        "aat:300008347"
    ]
},
  "bbox": [],
  "geometry": {"coordinates":[-104.954167,21.204167],"type":"Point"}
}