{
  "id": 1118557,
  "type": "Feature",
  "properties": {
    "tgn:hierarchy":[
        "tgn:1118557",
        "tgn:1000003",
        "tgn:1003508",
        "tgn:7003237",
        "tgn:1000080",
        "tgn:7029392"
    ],
    "tgn:id":1118557,
    "tgn:name":"Varese, Lago di",
    "tgn:placetype":[
        "aat:300008680"
    ]
},
  "bbox": [],
  "geometry": {"coordinates":[8.75,45.816667],"type":"Point"}
}