{
  "id": 2681253,
  "type": "Feature",
  "properties": {
    "tgn:hierarchy":[
        "tgn:2681253",
        "tgn:1000001",
        "tgn:7012149",
        "tgn:2001291",
        "tgn:7007524",
        "tgn:7029392"
    ],
    "tgn:id":2681253,
    "tgn:name":"South One Horse Lake",
    "tgn:placetype":[
        "aat:300008680"
    ]
},
  "bbox": [],
  "geometry": {"coordinates":[-114.2333,46.65],"type":"Point"}
}