{
  "id": 2653878,
  "type": "Feature",
  "properties": {
    "tgn:hierarchy":[
        "tgn:2653878",
        "tgn:1000001",
        "tgn:7012149",
        "tgn:2000220",
        "tgn:7007158",
        "tgn:7029392"
    ],
    "tgn:id":2653878,
    "tgn:name":"Seymour Lake",
    "tgn:placetype":[
        "aat:300006191"
    ]
},
  "bbox": [],
  "geometry": {"coordinates":[-106.3833,40.4667],"type":"Point"}
}