{
  "id": 1135950,
  "type": "Feature",
  "properties": {
    "tgn:hierarchy":[
        "tgn:1135950",
        "tgn:7001242",
        "tgn:7016833",
        "tgn:7029392"
    ],
    "tgn:id":1135950,
    "tgn:name":"Tur'at al Ism\u0101'\u012bl\u012byah",
    "tgn:placetype":[
        "aat:300006075"
    ]
},
  "bbox": [],
  "geometry": {"coordinates":[31.241,30.105],"type":"Point"}
}