{
  "id": 7359053,
  "type": "Feature",
  "properties": {
    "tgn:hierarchy":[
        "tgn:7359053",
        "tgn:1000001",
        "tgn:7005595",
        "tgn:7005560",
        "tgn:7029392"
    ],
    "tgn:id":7359053,
    "tgn:name":"Rancho El Aguajito",
    "tgn:placetype":[
        "aat:300000241"
    ]
},
  "bbox": [],
  "geometry": {"coordinates":[-108.38,26.519167],"type":"Point"}
}