<<<<<<< HEAD
{
  "id": 7359053,
  "type": "Feature",
  "properties": {
    "tgn:hierarchy":[
        "tgn:7359053",
        "tgn:1000001",
        "tgn:7005595",
        "tgn:7005560",
        "tgn:7029392"
    ],
    "tgn:id":7359053,
    "tgn:name":"Rancho El Aguajito",
    "tgn:placetype":[
        "aat:300000241"
    ]
},
  "bbox": [],
  "geometry": {"coordinates":[-108.38,26.519167],"type":"Point"}
}
=======
{"geometry":{"type":"Point","coordinates":[-108.380000,26.519167]},"type":"Feature","properties":{"hierarchy":["tgn:7359053","tgn:1000001","tgn:7005595","tgn:7005560","tgn:7029392"],"placetype":["aat:300000241"],"id":7359053,"name:xx":"Rancho El Aguajito"}}
>>>>>>> 03f74aca74312dbeaf24d7e61306dd6a786dc3d0
