<<<<<<< HEAD
{
  "id": 2769642,
  "type": "Feature",
  "properties": {
    "tgn:hierarchy":[
        "tgn:2769642",
        "tgn:1000001",
        "tgn:7006451",
        "tgn:2000092",
        "tgn:7012149",
        "tgn:7029392"
    ],
    "tgn:id":2769642,
    "tgn:name":"Wier Number Eight Tank",
    "tgn:placetype":[
        "aat:300006191"
    ]
},
  "bbox": [],
  "geometry": {"coordinates":[-111.5167,34.7833],"type":"Point"}
}
=======
{"geometry":{"type":"Point","coordinates":[-111.516700,34.783300]},"type":"Feature","properties":{"hierarchy":["tgn:2769642","tgn:1000001","tgn:7006451","tgn:2000092","tgn:7012149","tgn:7029392"],"placetype":["aat:300006191"],"id":2769642,"name:xx":"Wier Number Eight Tank"}}
>>>>>>> 03f74aca74312dbeaf24d7e61306dd6a786dc3d0
