{
  "id": 7324053,
  "type": "Feature",
  "properties": {
    "tgn:hierarchy":[
        "tgn:7324053",
        "tgn:7002835",
        "tgn:7001158",
        "tgn:1000003",
        "tgn:1000095",
        "tgn:7029392"
    ],
    "tgn:id":7324053,
    "tgn:name":"Santa Olalla de Yeltes",
    "tgn:placetype":[
        "aat:300008347"
    ]
},
  "bbox": [],
  "geometry": {"coordinates":[-6.216667,40.783333],"type":"Point"}
}