{
  "id": 7004348,
  "type": "Feature",
  "properties": {
    "tgn:hierarchy":[
        "tgn:7004348",
        "tgn:1000146",
        "tgn:1000004",
        "tgn:7000261",
        "tgn:7029392"
    ],
    "tgn:id":7004348,
    "tgn:name":"Ibb",
    "tgn:placetype":[
        "aat:300387145",
        "aat:300235093"
    ]
},
  "bbox": [],
  "geometry": {"coordinates":[44.1667,14.05],"type":"Point"}
}