{
  "id": 7035502,
  "type": "Feature",
  "properties": {
    "tgn:hierarchy":[
        "tgn:7035502",
        "tgn:1003506",
        "tgn:1000003",
        "tgn:7002993",
        "tgn:1000080",
        "tgn:7029392"
    ],
    "tgn:id":7035502,
    "tgn:name":"Casere",
    "tgn:placetype":[
        "aat:300008347"
    ]
},
  "bbox": [],
  "geometry": {"coordinates":[13.515,46.405556],"type":"Point"}
}