{
  "id": 2377779,
  "type": "Feature",
  "properties": {
    "tgn:hierarchy":[
        "tgn:2377779",
        "tgn:2002101",
        "tgn:1000001",
        "tgn:7012149",
        "tgn:7007827",
        "tgn:7029392"
    ],
    "tgn:id":2377779,
    "tgn:name":"Harriet Mine",
    "tgn:placetype":[
        "aat:300000390"
    ]
},
  "bbox": [],
  "geometry": {"coordinates":[-112.8667,38.25],"type":"Point"}
}