{
  "id": 7329776,
  "type": "Feature",
  "properties": {
    "tgn:hierarchy":[
        "tgn:7329776",
        "tgn:7002803",
        "tgn:1001647",
        "tgn:1000003",
        "tgn:1000095",
        "tgn:7029392"
    ],
    "tgn:id":7329776,
    "tgn:name":"Juanete",
    "tgn:placetype":[
        "aat:300387200"
    ]
},
  "bbox": [],
  "geometry": {"coordinates":[-1.233333,39.233333],"type":"Point"}
}