{
  "id": 2582657,
  "type": "Feature",
  "properties": {
    "tgn:hierarchy":[
        "tgn:2582657",
        "tgn:1000001",
        "tgn:2000862",
        "tgn:7012149",
        "tgn:7007256",
        "tgn:7029392"
    ],
    "tgn:id":2582657,
    "tgn:name":"Pine Hill Estates",
    "tgn:placetype":[
        "aat:300008347"
    ]
},
  "bbox": [],
  "geometry": {"coordinates":[-93.8333,32.5333],"type":"Point"}
}