{
  "id": 2454868,
  "type": "Feature",
  "properties": {
    "tgn:hierarchy":[
        "tgn:2454868",
        "tgn:7002659",
        "tgn:1000001",
        "tgn:2000012",
        "tgn:7012149",
        "tgn:7029392"
    ],
    "tgn:id":2454868,
    "tgn:name":"Little Duck Roost",
    "tgn:placetype":[
        "aat:300008905"
    ]
},
  "bbox": [],
  "geometry": {"coordinates":[-87.9333,31.2833],"type":"Point"}
}