{
  "id": 2137901,
  "type": "Feature",
  "properties": {
    "tgn:hierarchy":[
        "tgn:2137901",
        "tgn:1002996",
        "tgn:1000001",
        "tgn:7012149",
        "tgn:7007711",
        "tgn:7029392"
    ],
    "tgn:id":2137901,
    "tgn:name":"Arrow Swamp",
    "tgn:placetype":[
        "aat:300008905"
    ]
},
  "bbox": [],
  "geometry": {"coordinates":[-71.55,41.5167],"type":"Point"}
}