{
  "id": 1118079,
  "type": "Feature",
  "properties": {
    "tgn:hierarchy":[
        "tgn:1118079",
        "tgn:7003712",
        "tgn:7003670",
        "tgn:1000003",
        "tgn:7000084",
        "tgn:7029392"
    ],
    "tgn:id":1118079,
    "tgn:name":"Seddinsee",
    "tgn:placetype":[
        "aat:300008680"
    ]
},
  "bbox": [],
  "geometry": {"coordinates":[13.683333,52.383333],"type":"Point"}
}