{
  "id": 2116424,
  "type": "Feature",
  "properties": {
    "tgn:hierarchy":[
        "tgn:2116424",
        "tgn:1000001",
        "tgn:7012149",
        "tgn:1002594",
        "tgn:7007920",
        "tgn:7029392"
    ],
    "tgn:id":2116424,
    "tgn:name":"Onalaska",
    "tgn:placetype":[
        "aat:300008347"
    ]
},
  "bbox": [],
  "geometry": {"coordinates":[-122.7167,46.5667],"type":"Point"}
}