{
  "id": 7486272,
  "type": "Feature",
  "properties": {
    "tgn:hierarchy":[
        "tgn:7486272",
        "tgn:1000004",
        "tgn:1000454",
        "tgn:1000141",
        "tgn:7029392"
    ],
    "tgn:id":7486272,
    "tgn:name":"Ganjiaofang",
    "tgn:placetype":[
        "aat:300008347"
    ]
},
  "bbox": [],
  "geometry": {"coordinates":[121.65895,24.938655],"type":"Point"}
}