{
  "id": 2555451,
  "type": "Feature",
  "properties": {
    "tgn:hierarchy":[
        "tgn:2555451",
        "tgn:1000001",
        "tgn:7012149",
        "tgn:2001764",
        "tgn:7007712",
        "tgn:7029392"
    ],
    "tgn:id":2555451,
    "tgn:name":"Odom Pond",
    "tgn:placetype":[
        "aat:300006191"
    ]
},
  "bbox": [],
  "geometry": {"coordinates":[-80.75,34.0333],"type":"Point"}
}