{
  "id": 2450832,
  "type": "Feature",
  "properties": {
    "tgn:hierarchy":[
        "tgn:2450832",
        "tgn:1000001",
        "tgn:7012149",
        "tgn:7007157",
        "tgn:1002937",
        "tgn:7029392"
    ],
    "tgn:id":2450832,
    "tgn:name":"Lira",
    "tgn:placetype":[
        "aat:300008347"
    ]
},
  "bbox": [],
  "geometry": {"coordinates":[-121.8667,39.1333],"type":"Point"}
}