{
  "id": 2468844,
  "type": "Feature",
  "properties": {
    "tgn:hierarchy":[
        "tgn:2468844",
        "tgn:1000001",
        "tgn:7012149",
        "tgn:1002767",
        "tgn:7007920",
        "tgn:7029392"
    ],
    "tgn:id":2468844,
    "tgn:name":"Long Ridge",
    "tgn:placetype":[
        "aat:300266640"
    ]
},
  "bbox": [],
  "geometry": {"coordinates":[-123.4167,46.45],"type":"Point"}
}