{
  "id": 7410958,
  "type": "Feature",
  "properties": {
    "tgn:hierarchy":[
        "tgn:7410958",
        "tgn:1000001",
        "tgn:7005596",
        "tgn:7005560",
        "tgn:7029392"
    ],
    "tgn:id":7410958,
    "tgn:name:es":"San Ignacio, Laguna",
    "tgn:placetype":[
        "aat:300008680"
    ]
},
  "bbox": [],
  "geometry": {"coordinates":[-91.745833,17.8125],"type":"Point"}
}