{
  "id": 2351776,
  "type": "Feature",
  "properties": {
    "tgn:hierarchy":[
        "tgn:2351776",
        "tgn:1002155",
        "tgn:1000001",
        "tgn:7012149",
        "tgn:7007706",
        "tgn:7029392"
    ],
    "tgn:id":2351776,
    "tgn:name":"Glenn Run",
    "tgn:placetype":[
        "aat:300008699"
    ]
},
  "bbox": [],
  "geometry": {"coordinates":[-82.1667,40.8333],"type":"Point"}
}