{
  "id": 2304092,
  "type": "Feature",
  "properties": {
    "tgn:hierarchy":[
        "tgn:2304092",
        "tgn:1000001",
        "tgn:7012149",
        "tgn:1002751",
        "tgn:7007568",
        "tgn:7029392"
    ],
    "tgn:id":2304092,
    "tgn:name":"Eagle Valley",
    "tgn:placetype":[
        "aat:300008347"
    ]
},
  "bbox": [],
  "geometry": {"coordinates":[-74.2167,41.15],"type":"Point"}
}