{
  "id": 2685650,
  "type": "Feature",
  "properties": {
    "tgn:hierarchy":[
        "tgn:2685650",
        "tgn:1000001",
        "tgn:7016172",
        "tgn:7012149",
        "tgn:2000167",
        "tgn:7029392"
    ],
    "tgn:id":2685650,
    "tgn:name":"Spring Branch",
    "tgn:placetype":[
        "aat:300008699"
    ]
},
  "bbox": [],
  "geometry": {"coordinates":[-92.75,34.5667],"type":"Point"}
}