{
  "id": 2517121,
  "type": "Feature",
  "properties": {
    "tgn:hierarchy":[
        "tgn:2517121",
        "tgn:1000001",
        "tgn:1002213",
        "tgn:7012149",
        "tgn:7007710",
        "tgn:7029392"
    ],
    "tgn:id":2517121,
    "tgn:name":"Mink Run",
    "tgn:placetype":[
        "aat:300008699"
    ]
},
  "bbox": [],
  "geometry": {"coordinates":[-75.1833,40.45],"type":"Point"}
}