{
  "id": 7312011,
  "type": "Feature",
  "properties": {
    "tgn:hierarchy":[
        "tgn:7312011",
        "tgn:1001768",
        "tgn:1000049",
        "tgn:1000002",
        "tgn:7029392"
    ],
    "tgn:id":7312011,
    "tgn:name":"Las Eras, Cerro",
    "tgn:placetype":[
        "aat:300008795"
    ]
},
  "bbox": [],
  "geometry": {"coordinates":[-71.45,-32.533333],"type":"Point"}
}