{
  "id": 7504797,
  "type": "Feature",
  "properties": {
    "tgn:hierarchy":[
        "tgn:7504797",
        "tgn:7000508",
        "tgn:1008380",
        "tgn:1000226",
        "tgn:1000006",
        "tgn:7029392"
    ],
    "tgn:id":7504797,
    "tgn:name:en":"Milford Beach",
    "tgn:placetype":[
        "aat:300008816"
    ]
},
  "bbox": [],
  "geometry": {"coordinates":[174.771667,-36.768889],"type":"Point"}
}