{
  "id": 2620376,
  "type": "Feature",
  "properties": {
    "tgn:hierarchy":[
        "tgn:2620376",
        "tgn:1000001",
        "tgn:7012149",
        "tgn:2002360",
        "tgn:7007922",
        "tgn:7029392"
    ],
    "tgn:id":2620376,
    "tgn:name":"River Lake",
    "tgn:placetype":[
        "aat:300008680"
    ]
},
  "bbox": [],
  "geometry": {"coordinates":[-91.5333,45.7333],"type":"Point"}
}