{
  "id": 2231044,
  "type": "Feature",
  "properties": {
    "tgn:hierarchy":[
        "tgn:2231044",
        "tgn:1000001",
        "tgn:7012149",
        "tgn:2001457",
        "tgn:7007566",
        "tgn:7029392"
    ],
    "tgn:id":2231044,
    "tgn:name":"Cerro de la Olla",
    "tgn:placetype":[
        "aat:300008798"
    ]
},
  "bbox": [],
  "geometry": {"coordinates":[-105.7833,36.75],"type":"Point"}
}