{
  "id": 7564953,
  "type": "Feature",
  "properties": {
    "tgn:hierarchy":[
        "tgn:7564953",
        "tgn:1000004",
        "tgn:7000198",
        "tgn:7016722",
        "tgn:7029392"
    ],
    "tgn:id":7564953,
    "tgn:name:en":"Ganeshpur",
    "tgn:placetype":[
        "aat:300008347"
    ]
},
  "bbox": [],
  "geometry": {"coordinates":[79.55414,26.866294],"type":"Point"}
}