{
  "id": 2467875,
  "type": "Feature",
  "properties": {
    "tgn:hierarchy":[
        "tgn:2467875",
        "tgn:1000001",
        "tgn:7012149",
        "tgn:2000488",
        "tgn:7007250",
        "tgn:7029392"
    ],
    "tgn:id":2467875,
    "tgn:name":"Long Lake",
    "tgn:placetype":[
        "aat:300008680"
    ]
},
  "bbox": [],
  "geometry": {"coordinates":[-115.7167,42.2833],"type":"Point"}
}