{
  "id": 2626029,
  "type": "Feature",
  "properties": {
    "tgn:hierarchy":[
        "tgn:2626029",
        "tgn:1000001",
        "tgn:7012149",
        "tgn:7007708",
        "tgn:7029392"
    ],
    "tgn:id":2626029,
    "tgn:name":"Rocky Canyon",
    "tgn:placetype":[
        "aat:300008761"
    ]
},
  "bbox": [],
  "geometry": {"coordinates":[-119.3667,42.1333],"type":"Point"}
}