{
  "id": 2612834,
  "type": "Feature",
  "properties": {
    "tgn:hierarchy":[
        "tgn:2612834",
        "tgn:1000001",
        "tgn:7012149",
        "tgn:2000183",
        "tgn:7007157",
        "tgn:7029392"
    ],
    "tgn:id":2612834,
    "tgn:name":"Redlands Spring",
    "tgn:placetype":[
        "aat:300008697"
    ]
},
  "bbox": [],
  "geometry": {"coordinates":[-117.1667,35.9333],"type":"Point"}
}