{
  "id": 7495049,
  "type": "Feature",
  "properties": {
    "tgn:hierarchy":[
        "tgn:7495049",
        "tgn:7488858",
        "tgn:1000004",
        "tgn:1000141",
        "tgn:7029392"
    ],
    "tgn:id":7495049,
    "tgn:name":"Xitou Qiao",
    "tgn:placetype":[
        "aat:300007836"
    ]
},
  "bbox": [],
  "geometry": {"coordinates":[120.6466,23.9701],"type":"Point"}
}