{
  "id": 7380062,
  "type": "Feature",
  "properties": {
    "tgn:hierarchy":[
        "tgn:7380062",
        "tgn:1001853",
        "tgn:1000001",
        "tgn:7005560",
        "tgn:7029392"
    ],
    "tgn:id":7380062,
    "tgn:name":"Mimbre, Sierra del",
    "tgn:placetype":[
        "aat:300008795"
    ]
},
  "bbox": [],
  "geometry": {"coordinates":[-103.15,24.95],"type":"Point"}
}