<<<<<<< HEAD
{
  "id": 2156802,
  "type": "Feature",
  "properties": {
    "tgn:hierarchy":[
        "tgn:2156802",
        "tgn:1000001",
        "tgn:7012149",
        "tgn:2001458",
        "tgn:7007566",
        "tgn:7029392"
    ],
    "tgn:id":2156802,
    "tgn:name":"Beatty Hill",
    "tgn:placetype":[
        "aat:300008798"
    ]
},
  "bbox": [],
  "geometry": {"coordinates":[-106.0667,34.25],"type":"Point"}
}
=======
{"geometry":{"type":"Point","coordinates":[-106.066700,34.250000]},"type":"Feature","properties":{"hierarchy":["tgn:2156802","tgn:1000001","tgn:7012149","tgn:2001458","tgn:7007566","tgn:7029392"],"placetype":["aat:300008798"],"id":2156802,"name:xx":"Beatty Hill"}}
>>>>>>> 03f74aca74312dbeaf24d7e61306dd6a786dc3d0
