{
  "id": 7307531,
  "type": "Feature",
  "properties": {
    "tgn:hierarchy":[
        "tgn:7307531",
        "tgn:7002844",
        "tgn:7030216",
        "tgn:1000003",
        "tgn:1000095",
        "tgn:7029392"
    ],
    "tgn:id":7307531,
    "tgn:name":"Llaver\u00eda",
    "tgn:placetype":[
        "aat:300008347"
    ]
},
  "bbox": [],
  "geometry": {"coordinates":[0.85,41.083333],"type":"Point"}
}