{
  "id": 2319343,
  "type": "Feature",
  "properties": {
    "tgn:hierarchy":[
        "tgn:2319343",
        "tgn:1000001",
        "tgn:7006451",
        "tgn:7012149",
        "tgn:2000097",
        "tgn:7029392"
    ],
    "tgn:id":2319343,
    "tgn:name":"Estrella Estates Family Park",
    "tgn:placetype":[
        "aat:300008347"
    ]
},
  "bbox": [],
  "geometry": {"coordinates":[-112.0833,33.4667],"type":"Point"}
}