{
  "id": 7431407,
  "type": "Feature",
  "properties": {
    "tgn:hierarchy":[
        "tgn:7431407",
        "tgn:1001853",
        "tgn:1000001",
        "tgn:7005560",
        "tgn:7029392"
    ],
    "tgn:id":7431407,
    "tgn:name":"El Treinta",
    "tgn:placetype":[
        "aat:300008347"
    ]
},
  "bbox": [],
  "geometry": {"coordinates":[-101.383333,28.316667],"type":"Point"}
}