{
  "id": 7187479,
  "type": "Feature",
  "properties": {
    "tgn:hierarchy":[
        "tgn:7187479",
        "tgn:1000003",
        "tgn:7003677",
        "tgn:7000084",
        "tgn:7029392"
    ],
    "tgn:id":7187479,
    "tgn:name":"Engels",
    "tgn:placetype":[
        "aat:300000206"
    ]
},
  "bbox": [],
  "geometry": {"coordinates":[7.266667,52.183333],"type":"Point"}
}