{
  "id": 7548386,
  "type": "Feature",
  "properties": {
    "tgn:hierarchy":[
        "tgn:7548386",
        "tgn:1000004",
        "tgn:1001869",
        "tgn:7000198",
        "tgn:7029392"
    ],
    "tgn:id":7548386,
    "tgn:name:en":"Deohati",
    "tgn:placetype":[
        "aat:300008347"
    ]
},
  "bbox": [],
  "geometry": {"coordinates":[74.096948,22.395992],"type":"Point"}
}