{
  "id": 7587993,
  "type": "Feature",
  "properties": {
    "tgn:hierarchy":[
        "tgn:7587993",
        "tgn:1000004",
        "tgn:7000198",
        "tgn:7000799",
        "tgn:7029392"
    ],
    "tgn:id":7587993,
    "tgn:name:en":"Sutu Kuturb\u0101gh",
    "tgn:placetype":[
        "aat:300008347"
    ]
},
  "bbox": [],
  "geometry": {"coordinates":[74.836197,34.024512],"type":"Point"}
}