{
  "id": 2432065,
  "type": "Feature",
  "properties": {
    "tgn:hierarchy":[
        "tgn:2432065",
        "tgn:1002483",
        "tgn:7019080",
        "tgn:1000001",
        "tgn:7012149",
        "tgn:7007249",
        "tgn:7029392"
    ],
    "tgn:id":2432065,
    "tgn:name":"Kawaipapa Gulch",
    "tgn:placetype":[
        "aat:300008761"
    ]
},
  "bbox": [],
  "geometry": {"coordinates":[-157.9167,21.5833],"type":"Point"}
}