{
  "id": 1020928,
  "type": "Feature",
  "properties": {
    "tgn:hierarchy":[
        "tgn:1020928",
        "tgn:1001945",
        "tgn:1000047",
        "tgn:7002457",
        "tgn:1000002",
        "tgn:7029392"
    ],
    "tgn:id":1020928,
    "tgn:name":"C\u00e1ssia dos Coqueiros",
    "tgn:placetype":[
        "aat:300008347"
    ]
},
  "bbox": [],
  "geometry": {"coordinates":[-47.1667,-21.2833],"type":"Point"}
}