{
  "id": 2166260,
  "type": "Feature",
  "properties": {
    "tgn:hierarchy":[
        "tgn:2166260",
        "tgn:1000001",
        "tgn:1002191",
        "tgn:7012149",
        "tgn:7007826",
        "tgn:7029392"
    ],
    "tgn:id":2166260,
    "tgn:name":"Big Bee Mountain",
    "tgn:placetype":[
        "aat:300008798"
    ]
},
  "bbox": [],
  "geometry": {"coordinates":[-97.65,31.7833],"type":"Point"}
}