{
  "id": 7568975,
  "type": "Feature",
  "properties": {
    "tgn:hierarchy":[
        "tgn:7568975",
        "tgn:1000004",
        "tgn:7000198",
        "tgn:7016788",
        "tgn:7029392"
    ],
    "tgn:id":7568975,
    "tgn:name:en":"R\u0101puriyo",
    "tgn:placetype":[
        "aat:300008347"
    ]
},
  "bbox": [],
  "geometry": {"coordinates":[74.778883,28.245261],"type":"Point"}
}