{
  "id": 2228482,
  "type": "Feature",
  "properties": {
    "tgn:hierarchy":[
        "tgn:2228482",
        "tgn:1000001",
        "tgn:7012149",
        "tgn:1003044",
        "tgn:7007708",
        "tgn:7029392"
    ],
    "tgn:id":2228482,
    "tgn:name":"Cedar Creek",
    "tgn:placetype":[
        "aat:300008706"
    ]
},
  "bbox": [],
  "geometry": {"coordinates":[-123.7167,45.0833],"type":"Point"}
}