{
  "id": 7225279,
  "type": "Feature",
  "properties": {
    "tgn:hierarchy":[
        "tgn:7225279",
        "tgn:7002711",
        "tgn:7001338",
        "tgn:1000003",
        "tgn:1000074",
        "tgn:7029392"
    ],
    "tgn:id":7225279,
    "tgn:name":"Neno\u00fadha, \u00c1kra",
    "tgn:placetype":[
        "aat:300008850"
    ]
},
  "bbox": [],
  "geometry": {"coordinates":[20.066667,39.666667],"type":"Point"}
}