{
  "id": 2462868,
  "type": "Feature",
  "properties": {
    "tgn:hierarchy":[
        "tgn:2462868",
        "tgn:1002139",
        "tgn:1000001",
        "tgn:7012149",
        "tgn:7007568",
        "tgn:7029392"
    ],
    "tgn:id":2462868,
    "tgn:name":"Littles Lake",
    "tgn:placetype":[
        "aat:300008680"
    ]
},
  "bbox": [],
  "geometry": {"coordinates":[-73.7333,42.6833],"type":"Point"}
}