{
  "id": 2266843,
  "type": "Feature",
  "properties": {
    "tgn:hierarchy":[
        "tgn:2266843",
        "tgn:1000001",
        "tgn:7012149",
        "tgn:7014510",
        "tgn:7007920",
        "tgn:7029392"
    ],
    "tgn:id":2266843,
    "tgn:name":"Crescent Mine",
    "tgn:placetype":[
        "aat:300000390"
    ]
},
  "bbox": [],
  "geometry": {"coordinates":[-121.2167,48.5333],"type":"Point"}
}