{
  "id": 2385310,
  "type": "Feature",
  "properties": {
    "tgn:hierarchy":[
        "tgn:2385310",
        "tgn:1000001",
        "tgn:7012149",
        "tgn:2001515",
        "tgn:7007709",
        "tgn:7029392"
    ],
    "tgn:id":2385310,
    "tgn:name":"Hemp Patch Branch",
    "tgn:placetype":[
        "aat:300008699"
    ]
},
  "bbox": [],
  "geometry": {"coordinates":[-83.4667,35.0333],"type":"Point"}
}