{
  "id": 1117365,
  "type": "Feature",
  "properties": {
    "tgn:hierarchy":[
        "tgn:1117365",
        "tgn:7005685",
        "tgn:1000001",
        "tgn:7005734",
        "tgn:7029392"
    ],
    "tgn:id":1117365,
    "tgn:name":"Moose Lake",
    "tgn:placetype":[
        "aat:300008680"
    ]
},
  "bbox": [],
  "geometry": {"coordinates":[-99.75,53.9167],"type":"Point"}
}