{
  "id": 2151478,
  "type": "Feature",
  "properties": {
    "tgn:hierarchy":[
        "tgn:2151478",
        "tgn:1000001",
        "tgn:7012149",
        "tgn:1003038",
        "tgn:7007517",
        "tgn:7029392"
    ],
    "tgn:id":2151478,
    "tgn:name":"Bating Brook",
    "tgn:placetype":[
        "aat:300008699"
    ]
},
  "bbox": [],
  "geometry": {"coordinates":[-71.7333,42.0333],"type":"Point"}
}