{
  "id": 2384811,
  "type": "Feature",
  "properties": {
    "tgn:hierarchy":[
        "tgn:2384811",
        "tgn:1000001",
        "tgn:2000922",
        "tgn:7012149",
        "tgn:7007515",
        "tgn:7029392"
    ],
    "tgn:id":2384811,
    "tgn:name":"Hells Half Acre",
    "tgn:placetype":[
        "aat:300008791"
    ]
},
  "bbox": [],
  "geometry": {"coordinates":[-68.6167,44.15],"type":"Point"}
}