<<<<<<< HEAD
{
  "id": 7376997,
  "type": "Feature",
  "properties": {
    "tgn:hierarchy":[
        "tgn:7376997",
        "tgn:1000001",
        "tgn:7005601",
        "tgn:7005560",
        "tgn:7029392"
    ],
    "tgn:id":7376997,
    "tgn:name":"Las Mar\u00edas",
    "tgn:placetype":[
        "aat:300008347"
    ]
},
  "bbox": [],
  "geometry": {"coordinates":[-104.05,22.666667],"type":"Point"}
}
=======
{"geometry":{"type":"Point","coordinates":[-104.050000,22.666667]},"type":"Feature","properties":{"hierarchy":["tgn:7376997","tgn:1000001","tgn:7005601","tgn:7005560","tgn:7029392"],"placetype":["aat:300008347"],"id":7376997,"name:xx":"Las Mar\u00edas"}}
>>>>>>> 03f74aca74312dbeaf24d7e61306dd6a786dc3d0
