{
  "id": 2395729,
  "type": "Feature",
  "properties": {
    "tgn:hierarchy":[
        "tgn:2395729",
        "tgn:1000001",
        "tgn:7012149",
        "tgn:2000909",
        "tgn:7007256",
        "tgn:7029392"
    ],
    "tgn:id":2395729,
    "tgn:name":"Hollman Creek",
    "tgn:placetype":[
        "aat:300008706"
    ]
},
  "bbox": [],
  "geometry": {"coordinates":[-92.15,32.7667],"type":"Point"}
}