<<<<<<< HEAD
{
  "id": 2334348,
  "type": "Feature",
  "properties": {
    "tgn:hierarchy":[
        "tgn:2334348",
        "tgn:1000001",
        "tgn:2001748",
        "tgn:7012149",
        "tgn:7007712",
        "tgn:7029392"
    ],
    "tgn:id":2334348,
    "tgn:name":"Forest Hills",
    "tgn:placetype":[
        "aat:300008347"
    ]
},
  "bbox": [],
  "geometry": {"coordinates":[-82.1833,34.2333],"type":"Point"}
}
=======
{"geometry":{"type":"Point","coordinates":[-82.183300,34.233300]},"type":"Feature","properties":{"hierarchy":["tgn:2334348","tgn:1000001","tgn:2001748","tgn:7012149","tgn:7007712","tgn:7029392"],"placetype":["aat:300008347"],"id":2334348,"name:xx":"Forest Hills"}}
>>>>>>> 03f74aca74312dbeaf24d7e61306dd6a786dc3d0
