{
  "id": 1101088,
  "type": "Feature",
  "properties": {
    "tgn:hierarchy":[
        "tgn:1101088",
        "tgn:1000004",
        "tgn:7000198",
        "tgn:7031783",
        "tgn:7029392"
    ],
    "tgn:id":1101088,
    "tgn:name":"Canada Dam",
    "tgn:placetype":[
        "aat:300006084"
    ]
},
  "bbox": [],
  "geometry": {"coordinates":[87.1667,24.1667],"type":"Point"}
}