{
  "id": 2035095,
  "type": "Feature",
  "properties": {
    "tgn:hierarchy":[
        "tgn:2035095",
        "tgn:1000001",
        "tgn:7012149",
        "tgn:2000615",
        "tgn:7007253",
        "tgn:7029392"
    ],
    "tgn:id":2035095,
    "tgn:name":"Ledyard",
    "tgn:placetype":[
        "aat:300008347"
    ]
},
  "bbox": [],
  "geometry": {"coordinates":[-94.15,43.4167],"type":"Point"}
}