{
  "id": 7315691,
  "type": "Feature",
  "properties": {
    "tgn:hierarchy":[
        "tgn:7315691",
        "tgn:7016598",
        "tgn:1000049",
        "tgn:1000002",
        "tgn:7029392"
    ],
    "tgn:id":7315691,
    "tgn:name":"Cerroqui, Cerro",
    "tgn:placetype":[
        "aat:300008795"
    ]
},
  "bbox": [],
  "geometry": {"coordinates":[-68.416667,-22.133333],"type":"Point"}
}