{
  "id": 7167933,
  "type": "Feature",
  "properties": {
    "tgn:hierarchy":[
        "tgn:7167933",
        "tgn:1000003",
        "tgn:7003682",
        "tgn:7000084",
        "tgn:7029392"
    ],
    "tgn:id":7167933,
    "tgn:name":"Heimbacher Wald",
    "tgn:placetype":[
        "aat:300008863"
    ]
},
  "bbox": [],
  "geometry": {"coordinates":[7.55,50.466667],"type":"Point"}
}