<<<<<<< HEAD
{
  "id": 2330002,
  "type": "Feature",
  "properties": {
    "tgn:hierarchy":[
        "tgn:2330002",
        "tgn:1000001",
        "tgn:7012149",
        "tgn:1002911",
        "tgn:7007919",
        "tgn:7029392"
    ],
    "tgn:id":2330002,
    "tgn:name":"Flag Run",
    "tgn:placetype":[
        "aat:300008699"
    ]
},
  "bbox": [],
  "geometry": {"coordinates":[-77.0667,36.7333],"type":"Point"}
}
=======
{"geometry":{"type":"Point","coordinates":[-77.066700,36.733300]},"type":"Feature","properties":{"hierarchy":["tgn:2330002","tgn:1000001","tgn:7012149","tgn:1002911","tgn:7007919","tgn:7029392"],"placetype":["aat:300008699"],"id":2330002,"name:xx":"Flag Run"}}
>>>>>>> 03f74aca74312dbeaf24d7e61306dd6a786dc3d0
