{
  "id": 2380049,
  "type": "Feature",
  "properties": {
    "tgn:hierarchy":[
        "tgn:2380049",
        "tgn:1000001",
        "tgn:7012149",
        "tgn:2001846",
        "tgn:7007825",
        "tgn:7029392"
    ],
    "tgn:id":2380049,
    "tgn:name":"Hatcher Pyrite Mine",
    "tgn:placetype":[
        "aat:300000390"
    ]
},
  "bbox": [],
  "geometry": {"coordinates":[-82.0333,36.4167],"type":"Point"}
}