{
  "id": 2489949,
  "type": "Feature",
  "properties": {
    "tgn:hierarchy":[
        "tgn:2489949",
        "tgn:1000001",
        "tgn:7006451",
        "tgn:7012149",
        "tgn:2000104",
        "tgn:7029392"
    ],
    "tgn:id":2489949,
    "tgn:name":"Mammon Mine",
    "tgn:placetype":[
        "aat:300000390"
    ]
},
  "bbox": [],
  "geometry": {"coordinates":[-114.1167,34.15],"type":"Point"}
}