{
  "id": 2473697,
  "type": "Feature",
  "properties": {
    "tgn:hierarchy":[
        "tgn:2473697",
        "tgn:1000001",
        "tgn:2001024",
        "tgn:7012149",
        "tgn:7007521",
        "tgn:7029392"
    ],
    "tgn:id":2473697,
    "tgn:name":"Lower Elk Lake",
    "tgn:placetype":[
        "aat:300008680"
    ]
},
  "bbox": [],
  "geometry": {"coordinates":[-95.7833,45.85],"type":"Point"}
}