<<<<<<< HEAD
{
  "id": 2330207,
  "type": "Feature",
  "properties": {
    "tgn:hierarchy":[
        "tgn:2330207",
        "tgn:1000001",
        "tgn:7012149",
        "tgn:2002169",
        "tgn:7007919",
        "tgn:7029392"
    ],
    "tgn:id":2330207,
    "tgn:name":"Flanary Branch",
    "tgn:placetype":[
        "aat:300008699"
    ]
},
  "bbox": [],
  "geometry": {"coordinates":[-82.9,36.8167],"type":"Point"}
}
=======
{"geometry":{"type":"Point","coordinates":[-82.900000,36.816700]},"type":"Feature","properties":{"hierarchy":["tgn:2330207","tgn:1000001","tgn:7012149","tgn:2002169","tgn:7007919","tgn:7029392"],"placetype":["aat:300008699"],"id":2330207,"name:xx":"Flanary Branch"}}
>>>>>>> 03f74aca74312dbeaf24d7e61306dd6a786dc3d0
