{
  "id": 2653221,
  "type": "Feature",
  "properties": {
    "tgn:hierarchy":[
        "tgn:2653221",
        "tgn:1000001",
        "tgn:7014449",
        "tgn:7012149",
        "tgn:7007565",
        "tgn:7029392"
    ],
    "tgn:id":2653221,
    "tgn:name":"Seven Stars",
    "tgn:placetype":[
        "aat:300008347"
    ]
},
  "bbox": [],
  "geometry": {"coordinates":[-75.3333,39.6833],"type":"Point"}
}