{
  "id": 2454321,
  "type": "Feature",
  "properties": {
    "tgn:hierarchy":[
        "tgn:2454321",
        "tgn:1000001",
        "tgn:7012149",
        "tgn:2001862",
        "tgn:7007825",
        "tgn:7029392"
    ],
    "tgn:id":2454321,
    "tgn:name":"Little Crow Creek Cave",
    "tgn:placetype":[
        "aat:300008746"
    ]
},
  "bbox": [],
  "geometry": {"coordinates":[-85.9667,35.0167],"type":"Point"}
}