{
  "id": 2703969,
  "type": "Feature",
  "properties": {
    "tgn:hierarchy":[
        "tgn:2703969",
        "tgn:1000001",
        "tgn:7012149",
        "tgn:2001306",
        "tgn:7007524",
        "tgn:7029392"
    ],
    "tgn:id":2703969,
    "tgn:name":"Sunday Ridge",
    "tgn:placetype":[
        "aat:300266640"
    ]
},
  "bbox": [],
  "geometry": {"coordinates":[-112.7167,45.9333],"type":"Point"}
}