{
  "id": 2396717,
  "type": "Feature",
  "properties": {
    "tgn:hierarchy":[
        "tgn:2396717",
        "tgn:1000001",
        "tgn:7006451",
        "tgn:2000094",
        "tgn:7012149",
        "tgn:7029392"
    ],
    "tgn:id":2396717,
    "tgn:name":"Holyoke Wash",
    "tgn:placetype":[
        "aat:300008699"
    ]
},
  "bbox": [],
  "geometry": {"coordinates":[-109.7833,32.9333],"type":"Point"}
}