{
  "id": 7121487,
  "type": "Feature",
  "properties": {
    "tgn:hierarchy":[
        "tgn:7121487",
        "tgn:1000003",
        "tgn:7003676",
        "tgn:7000084",
        "tgn:7029392"
    ],
    "tgn:id":7121487,
    "tgn:name":"Parensen",
    "tgn:placetype":[
        "aat:300008347"
    ]
},
  "bbox": [],
  "geometry": {"coordinates":[9.916667,51.616667],"type":"Point"}
}