{
  "id": 7571570,
  "type": "Feature",
  "properties": {
    "tgn:hierarchy":[
        "tgn:7571570",
        "tgn:1000004",
        "tgn:7000198",
        "tgn:1001895",
        "tgn:7029392"
    ],
    "tgn:id":7571570,
    "tgn:name:en":"Girn\u0101 River",
    "tgn:placetype":[
        "aat:300008699"
    ]
},
  "bbox": [],
  "geometry": {"coordinates":[75.31609,21.142062],"type":"Point"}
}