{
  "id": 7088156,
  "type": "Feature",
  "properties": {
    "tgn:hierarchy":[
        "tgn:7088156",
        "tgn:7003669",
        "tgn:1000003",
        "tgn:7000084",
        "tgn:7029392"
    ],
    "tgn:id":7088156,
    "tgn:name":"Waitzau",
    "tgn:placetype":[
        "aat:300000206"
    ]
},
  "bbox": [],
  "geometry": {"coordinates":[13.316667,48.416667],"type":"Point"}
}