{
  "id": 2418034,
  "type": "Feature",
  "properties": {
    "tgn:hierarchy":[
        "tgn:2418034",
        "tgn:1000001",
        "tgn:7016172",
        "tgn:7012149",
        "tgn:2000164",
        "tgn:7029392"
    ],
    "tgn:id":2418034,
    "tgn:name":"Jackson Reservoir",
    "tgn:placetype":[
        "aat:300006191"
    ]
},
  "bbox": [],
  "geometry": {"coordinates":[-92.3667,34.7667],"type":"Point"}
}