{
  "id": 2629964,
  "type": "Feature",
  "properties": {
    "tgn:hierarchy":[
        "tgn:2629964",
        "tgn:7016099",
        "tgn:1000001",
        "tgn:7012149",
        "tgn:7007516",
        "tgn:7029392"
    ],
    "tgn:id":2629964,
    "tgn:name":"Ross Valley Farms",
    "tgn:placetype":[
        "aat:300008347"
    ]
},
  "bbox": [],
  "geometry": {"coordinates":[-76.65,39.5667],"type":"Point"}
}