{
  "id": 7571481,
  "type": "Feature",
  "properties": {
    "tgn:hierarchy":[
        "tgn:7571481",
        "tgn:1000004",
        "tgn:1001869",
        "tgn:7000198",
        "tgn:7029392"
    ],
    "tgn:id":7571481,
    "tgn:name:en":"Hasanpur",
    "tgn:placetype":[
        "aat:300008347"
    ]
},
  "bbox": [],
  "geometry": {"coordinates":[72.545425,24.24762],"type":"Point"}
}