{
  "id": 2772538,
  "type": "Feature",
  "properties": {
    "tgn:hierarchy":[
        "tgn:2772538",
        "tgn:1000001",
        "tgn:7012149",
        "tgn:2000888",
        "tgn:7007256",
        "tgn:7029392"
    ],
    "tgn:id":2772538,
    "tgn:name":"Williams Corner",
    "tgn:placetype":[
        "aat:300008347"
    ]
},
  "bbox": [],
  "geometry": {"coordinates":[-92.9167,31.6667],"type":"Point"}
}