{
  "id": 2317207,
  "type": "Feature",
  "properties": {
    "tgn:hierarchy":[
        "tgn:2317207",
        "tgn:1000001",
        "tgn:7012149",
        "tgn:1002625",
        "tgn:7007706",
        "tgn:7029392"
    ],
    "tgn:id":2317207,
    "tgn:name":"Emma Welch Ditch",
    "tgn:placetype":[
        "aat:300006075"
    ]
},
  "bbox": [],
  "geometry": {"coordinates":[-83.45,39.8167],"type":"Point"}
}