{
  "id": 7240134,
  "type": "Feature",
  "properties": {
    "tgn:hierarchy":[
        "tgn:7240134",
        "tgn:7003461",
        "tgn:1000003",
        "tgn:1000063",
        "tgn:7018236",
        "tgn:7029392"
    ],
    "tgn:id":7240134,
    "tgn:name":"Eetzevelderbeek",
    "tgn:placetype":[
        "aat:300008699"
    ]
},
  "bbox": [],
  "geometry": {"coordinates":[5.633333,51.116667],"type":"Point"}
}