<<<<<<< HEAD
{
  "id": 2766117,
  "type": "Feature",
  "properties": {
    "tgn:hierarchy":[
        "tgn:2766117",
        "tgn:1000001",
        "tgn:7012149",
        "tgn:2001036",
        "tgn:7007521",
        "tgn:7029392"
    ],
    "tgn:id":2766117,
    "tgn:name":"White Iron",
    "tgn:placetype":[
        "aat:300008347"
    ]
},
  "bbox": [],
  "geometry": {"coordinates":[-91.7667,47.9],"type":"Point"}
}
=======
{"geometry":{"type":"Point","coordinates":[-91.766700,47.900000]},"type":"Feature","properties":{"hierarchy":["tgn:2766117","tgn:1000001","tgn:7012149","tgn:2001036","tgn:7007521","tgn:7029392"],"placetype":["aat:300008347"],"id":2766117,"name:xx":"White Iron"}}
>>>>>>> 03f74aca74312dbeaf24d7e61306dd6a786dc3d0
