{
  "id": 2374903,
  "type": "Feature",
  "properties": {
    "tgn:hierarchy":[
        "tgn:2374903",
        "tgn:1000001",
        "tgn:7012149",
        "tgn:7007159",
        "tgn:7029392"
    ],
    "tgn:id":2374903,
    "tgn:name":"Hanging Hills",
    "tgn:placetype":[
        "aat:300386831"
    ]
},
  "bbox": [],
  "geometry": {"coordinates":[-72.8167,41.55],"type":"Point"}
}