<<<<<<< HEAD
{
  "id": 2402214,
  "type": "Feature",
  "properties": {
    "tgn:hierarchy":[
        "tgn:2402214",
        "tgn:1000001",
        "tgn:7012149",
        "tgn:2002371",
        "tgn:7007923",
        "tgn:7029392"
    ],
    "tgn:id":2402214,
    "tgn:name":"Horsethief Gulch",
    "tgn:placetype":[
        "aat:300008761"
    ]
},
  "bbox": [],
  "geometry": {"coordinates":[-108.15,43.0667],"type":"Point"}
}
=======
{"geometry":{"type":"Point","coordinates":[-108.150000,43.066700]},"type":"Feature","properties":{"hierarchy":["tgn:2402214","tgn:1000001","tgn:7012149","tgn:2002371","tgn:7007923","tgn:7029392"],"placetype":["aat:300008761"],"id":2402214,"name:xx":"Horsethief Gulch"}}
>>>>>>> 03f74aca74312dbeaf24d7e61306dd6a786dc3d0
