{
  "id": 7498387,
  "type": "Feature",
  "properties": {
    "tgn:hierarchy":[
        "tgn:7498387",
        "tgn:7001004",
        "tgn:1000004",
        "tgn:1000141",
        "tgn:7029392"
    ],
    "tgn:id":7498387,
    "tgn:name":"Lu Shan",
    "tgn:placetype":[
        "aat:300008798"
    ]
},
  "bbox": [],
  "geometry": {"coordinates":[120.988483,23.45075],"type":"Point"}
}