{
  "id": 7134085,
  "type": "Feature",
  "properties": {
    "tgn:hierarchy":[
        "tgn:7134085",
        "tgn:7003669",
        "tgn:1000003",
        "tgn:7000084",
        "tgn:7029392"
    ],
    "tgn:id":7134085,
    "tgn:name":"M\u00fchlberg",
    "tgn:placetype":[
        "aat:300008777"
    ]
},
  "bbox": [],
  "geometry": {"coordinates":[12.233333,49.616667],"type":"Point"}
}