{
  "id": 2586909,
  "type": "Feature",
  "properties": {
    "tgn:hierarchy":[
        "tgn:2586909",
        "tgn:1000001",
        "tgn:7012149",
        "tgn:1002703",
        "tgn:7007826",
        "tgn:7029392"
    ],
    "tgn:id":2586909,
    "tgn:name":"Plainview",
    "tgn:placetype":[
        "aat:300008347"
    ]
},
  "bbox": [],
  "geometry": {"coordinates":[-94.5667,31.5333],"type":"Point"}
}