{
  "id": 7467700,
  "type": "Feature",
  "properties": {
    "tgn:hierarchy":[
        "tgn:7467700",
        "tgn:7488858",
        "tgn:1000004",
        "tgn:1000141",
        "tgn:7029392"
    ],
    "tgn:id":7467700,
    "tgn:name":"Dongbu",
    "tgn:placetype":[
        "aat:300008347"
    ]
},
  "bbox": [],
  "geometry": {"coordinates":[121.003946,23.923915],"type":"Point"}
}