{
  "id": 2509879,
  "type": "Feature",
  "properties": {
    "tgn:hierarchy":[
        "tgn:2509879",
        "tgn:7006450",
        "tgn:1000001",
        "tgn:7012149",
        "tgn:7019760",
        "tgn:7029392"
    ],
    "tgn:id":2509879,
    "tgn:name":"Middle Mountain",
    "tgn:placetype":[
        "aat:300008798"
    ]
},
  "bbox": [],
  "geometry": {"coordinates":[-134.2667,57.45],"type":"Point"}
}