{
  "id": 1120717,
  "type": "Feature",
  "properties": {
    "tgn:hierarchy":[
        "tgn:1120717",
        "tgn:1000001",
        "tgn:7012149",
        "tgn:7007157",
        "tgn:1002915",
        "tgn:7029392"
    ],
    "tgn:id":1120717,
    "tgn:name":"Woodward Reservoir",
    "tgn:placetype":[
        "aat:300006191"
    ]
},
  "bbox": [],
  "geometry": {"coordinates":[-120.8667,37.85],"type":"Point"}
}