{
  "id": 2359955,
  "type": "Feature",
  "properties": {
    "tgn:hierarchy":[
        "tgn:2359955",
        "tgn:1000001",
        "tgn:2000951",
        "tgn:7012149",
        "tgn:7007520",
        "tgn:7029392"
    ],
    "tgn:id":2359955,
    "tgn:name":"Grass Bay",
    "tgn:placetype":[
        "aat:300132316"
    ]
},
  "bbox": [],
  "geometry": {"coordinates":[-84.3667,45.65],"type":"Point"}
}