{
  "id": 2006302,
  "type": "Feature",
  "properties": {
    "tgn:hierarchy":[
        "tgn:2006302",
        "tgn:7006450",
        "tgn:1000001",
        "tgn:7012149",
        "tgn:7019760",
        "tgn:7029392"
    ],
    "tgn:id":2006302,
    "tgn:name":"Pelican",
    "tgn:placetype":[
        "aat:300008347"
    ]
},
  "bbox": [],
  "geometry": {"coordinates":[-136.2167,57.95],"type":"Point"}
}