{
  "id": 7484921,
  "type": "Feature",
  "properties": {
    "tgn:hierarchy":[
        "tgn:7484921",
        "tgn:1000004",
        "tgn:7491221",
        "tgn:1000141",
        "tgn:7029392"
    ],
    "tgn:id":7484921,
    "tgn:name":"Dawu Yihao Suidao",
    "tgn:placetype":[
        "aat:300007899"
    ]
},
  "bbox": [],
  "geometry": {"coordinates":[120.893056,22.357778],"type":"Point"}
}