{
  "id": 2473998,
  "type": "Feature",
  "properties": {
    "tgn:hierarchy":[
        "tgn:2473998",
        "tgn:1000001",
        "tgn:7012149",
        "tgn:2000811",
        "tgn:7007255",
        "tgn:7029392"
    ],
    "tgn:id":2473998,
    "tgn:name":"Lower Joe Fork",
    "tgn:placetype":[
        "aat:300008699"
    ]
},
  "bbox": [],
  "geometry": {"coordinates":[-83.2833,36.9667],"type":"Point"}
}