<<<<<<< HEAD
{
  "id": 7055077,
  "type": "Feature",
  "properties": {
    "tgn:hierarchy":[
        "tgn:7055077",
        "tgn:1000003",
        "tgn:7003142",
        "tgn:7003236",
        "tgn:1000080",
        "tgn:7029392"
    ],
    "tgn:id":7055077,
    "tgn:name":"Polcevera, Valle",
    "tgn:placetype":[
        "aat:300008761"
    ]
},
  "bbox": [],
  "geometry": {"coordinates":[8.95,44.416667],"type":"Point"}
}
=======
{"geometry":{"type":"Point","coordinates":[8.950000,44.416667]},"type":"Feature","properties":{"hierarchy":["tgn:7055077","tgn:1000003","tgn:7003142","tgn:7003236","tgn:1000080","tgn:7029392"],"placetype":["aat:300008761"],"id":7055077,"name:xx":"Polcevera, Valle"}}
>>>>>>> 03f74aca74312dbeaf24d7e61306dd6a786dc3d0
