{
  "id": 1053006,
  "type": "Feature",
  "properties": {
    "tgn:hierarchy":[
        "tgn:1053006",
        "tgn:1000004",
        "tgn:7011600",
        "tgn:7018214",
        "tgn:7002435",
        "tgn:7029392"
    ],
    "tgn:id":1053006,
    "tgn:name":"Bolotovskoye",
    "tgn:placetype":[
        "aat:300008347"
    ]
},
  "bbox": [],
  "geometry": {"coordinates":[62.4667,58.5167],"type":"Point"}
}