{
  "id": 7338300,
  "type": "Feature",
  "properties": {
    "tgn:hierarchy":[
        "tgn:7338300",
        "tgn:7002816",
        "tgn:1001647",
        "tgn:1000003",
        "tgn:1000095",
        "tgn:7029392"
    ],
    "tgn:id":7338300,
    "tgn:name":"Castillo, Sierra del",
    "tgn:placetype":[
        "aat:300266640"
    ]
},
  "bbox": [],
  "geometry": {"coordinates":[-4.583333,39.05],"type":"Point"}
}