{
  "id": 2185439,
  "type": "Feature",
  "properties": {
    "tgn:hierarchy":[
        "tgn:2185439",
        "tgn:1000001",
        "tgn:7012149",
        "tgn:2000329",
        "tgn:7007248",
        "tgn:7029392"
    ],
    "tgn:id":2185439,
    "tgn:name":"Bohanon Crossroad",
    "tgn:placetype":[
        "aat:300008347"
    ]
},
  "bbox": [],
  "geometry": {"coordinates":[-84.8667,33.2667],"type":"Point"}
}