<<<<<<< HEAD
{
  "id": 7374019,
  "type": "Feature",
  "properties": {
    "tgn:hierarchy":[
        "tgn:7374019",
        "tgn:1000001",
        "tgn:7005597",
        "tgn:7005560",
        "tgn:7029392"
    ],
    "tgn:id":7374019,
    "tgn:name":"La Guitarra",
    "tgn:placetype":[
        "aat:300008699"
    ]
},
  "bbox": [],
  "geometry": {"coordinates":[-99.583333,23.733333],"type":"Point"}
}
=======
{"geometry":{"type":"Point","coordinates":[-99.583333,23.733333]},"type":"Feature","properties":{"hierarchy":["tgn:7374019","tgn:1000001","tgn:7005597","tgn:7005560","tgn:7029392"],"placetype":["aat:300008699"],"id":7374019,"name:xx":"La Guitarra"}}
>>>>>>> 03f74aca74312dbeaf24d7e61306dd6a786dc3d0
