{
  "id": 2324407,
  "type": "Feature",
  "properties": {
    "tgn:hierarchy":[
        "tgn:2324407",
        "tgn:1000001",
        "tgn:7012149",
        "tgn:7007157",
        "tgn:7014516",
        "tgn:7029392"
    ],
    "tgn:id":2324407,
    "tgn:name":"Felder Creek",
    "tgn:placetype":[
        "aat:300008706"
    ]
},
  "bbox": [],
  "geometry": {"coordinates":[-122.5333,38.2667],"type":"Point"}
}