{
  "id": 2131459,
  "type": "Feature",
  "properties": {
    "tgn:hierarchy":[
        "tgn:2131459",
        "tgn:1000001",
        "tgn:2000198",
        "tgn:7012149",
        "tgn:7007158",
        "tgn:7029392"
    ],
    "tgn:id":2131459,
    "tgn:name":"Altona",
    "tgn:placetype":[
        "aat:300008347"
    ]
},
  "bbox": [],
  "geometry": {"coordinates":[-105.2667,40.1333],"type":"Point"}
}