{
  "id": 7384276,
  "type": "Feature",
  "properties": {
    "tgn:hierarchy":[
        "tgn:7384276",
        "tgn:1000001",
        "tgn:7005591",
        "tgn:7005560",
        "tgn:7029392"
    ],
    "tgn:id":7384276,
    "tgn:name":"Ocotal",
    "tgn:placetype":[
        "aat:300008347"
    ]
},
  "bbox": [],
  "geometry": {"coordinates":[-95.166667,16.783333],"type":"Point"}
}