{
  "id": 7276612,
  "type": "Feature",
  "properties": {
    "tgn:hierarchy":[
        "tgn:7276612",
        "tgn:1001699",
        "tgn:1000049",
        "tgn:1000002",
        "tgn:7029392"
    ],
    "tgn:id":7276612,
    "tgn:name":"Mena, Estero",
    "tgn:placetype":[
        "aat:300008676"
    ]
},
  "bbox": [],
  "geometry": {"coordinates":[-73.215556,-44.1275],"type":"Point"}
}