{
  "id": 2204658,
  "type": "Feature",
  "properties": {
    "tgn:hierarchy":[
        "tgn:2204658",
        "tgn:2002308",
        "tgn:1000001",
        "tgn:7012149",
        "tgn:7007922",
        "tgn:7029392"
    ],
    "tgn:id":2204658,
    "tgn:name":"Buffalo Lake",
    "tgn:placetype":[
        "aat:300008680"
    ]
},
  "bbox": [],
  "geometry": {"coordinates":[-90.95,46.15],"type":"Point"}
}