{
  "id": 2190716,
  "type": "Feature",
  "properties": {
    "tgn:hierarchy":[
        "tgn:2190716",
        "tgn:7006450",
        "tgn:1000001",
        "tgn:7012149",
        "tgn:2000079",
        "tgn:7029392"
    ],
    "tgn:id":2190716,
    "tgn:name":"Boxer River",
    "tgn:placetype":[
        "aat:300008707"
    ]
},
  "bbox": [],
  "geometry": {"coordinates":[-171.5333,63.4167],"type":"Point"}
}