{
  "id": 7521057,
  "type": "Feature",
  "properties": {
    "tgn:hierarchy":[
        "tgn:7521057",
        "tgn:7001242",
        "tgn:7016833",
        "tgn:7001334",
        "tgn:7029392"
    ],
    "tgn:id":7521057,
    "tgn:name:en":"Ad Duqm",
    "tgn:placetype":[
        "aat:300008795"
    ]
},
  "bbox": [],
  "geometry": {"coordinates":[32.404659,25.202748],"type":"Point"}
}