<<<<<<< HEAD
{
  "id": 2150835,
  "type": "Feature",
  "properties": {
    "tgn:hierarchy":[
        "tgn:2150835",
        "tgn:1000001",
        "tgn:7012149",
        "tgn:2001054",
        "tgn:7007521",
        "tgn:7029392"
    ],
    "tgn:id":2150835,
    "tgn:name":"Bass Lake",
    "tgn:placetype":[
        "aat:300008680"
    ]
},
  "bbox": [],
  "geometry": {"coordinates":[-95.9333,46.5167],"type":"Point"}
}
=======
{"geometry":{"type":"Point","coordinates":[-95.933300,46.516700]},"type":"Feature","properties":{"hierarchy":["tgn:2150835","tgn:1000001","tgn:7012149","tgn:2001054","tgn:7007521","tgn:7029392"],"placetype":["aat:300008680"],"id":2150835,"name:xx":"Bass Lake"}}
>>>>>>> 03f74aca74312dbeaf24d7e61306dd6a786dc3d0
