{
  "id": 2625586,
  "type": "Feature",
  "properties": {
    "tgn:hierarchy":[
        "tgn:2625586",
        "tgn:1000001",
        "tgn:7012149",
        "tgn:7007158",
        "tgn:7029392"
    ],
    "tgn:id":2625586,
    "tgn:name":"Rockwell Ditch",
    "tgn:placetype":[
        "aat:300006075"
    ]
},
  "bbox": [],
  "geometry": {"coordinates":[-105.0333,40.2833],"type":"Point"}
}