{
  "id": 2498267,
  "type": "Feature",
  "properties": {
    "tgn:hierarchy":[
        "tgn:2498267",
        "tgn:1000001",
        "tgn:2000197",
        "tgn:7012149",
        "tgn:7007158",
        "tgn:7029392"
    ],
    "tgn:id":2498267,
    "tgn:name":"Mc Clave Drainage Ditch",
    "tgn:placetype":[
        "aat:300006075"
    ]
},
  "bbox": [],
  "geometry": {"coordinates":[-102.8167,38.1167],"type":"Point"}
}