{
  "id": 7193952,
  "type": "Feature",
  "properties": {
    "tgn:hierarchy":[
        "tgn:7193952",
        "tgn:1000003",
        "tgn:7003682",
        "tgn:7000084",
        "tgn:7029392"
    ],
    "tgn:id":7193952,
    "tgn:name":"Frankeneck",
    "tgn:placetype":[
        "aat:300008347"
    ]
},
  "bbox": [],
  "geometry": {"coordinates":[8.048611,49.376389],"type":"Point"}
}