{
  "id": 2086268,
  "type": "Feature",
  "properties": {
    "tgn:hierarchy":[
        "tgn:2086268",
        "tgn:1000001",
        "tgn:1002213",
        "tgn:7012149",
        "tgn:7007710",
        "tgn:7029392"
    ],
    "tgn:id":2086268,
    "tgn:name":"Bedminster",
    "tgn:placetype":[
        "aat:300008347"
    ]
},
  "bbox": [],
  "geometry": {"coordinates":[-75.1667,40.4167],"type":"Point"}
}