{
  "id": 2344041,
  "type": "Feature",
  "properties": {
    "tgn:hierarchy":[
        "tgn:2344041",
        "tgn:1000001",
        "tgn:7012149",
        "tgn:2002333",
        "tgn:7007922",
        "tgn:7029392"
    ],
    "tgn:id":2344041,
    "tgn:name":"Galyan Springs",
    "tgn:placetype":[
        "aat:300008680"
    ]
},
  "bbox": [],
  "geometry": {"coordinates":[-88.8167,45.1333],"type":"Point"}
}