{
  "id": 7324402,
  "type": "Feature",
  "properties": {
    "tgn:hierarchy":[
        "tgn:7324402",
        "tgn:7002831",
        "tgn:1000003",
        "tgn:7002786",
        "tgn:1000095",
        "tgn:7029392"
    ],
    "tgn:id":7324402,
    "tgn:name":"San Fiz",
    "tgn:placetype":[
        "aat:300008347"
    ]
},
  "bbox": [],
  "geometry": {"coordinates":[-7.05,42.35],"type":"Point"}
}