{
  "id": 2027733,
  "type": "Feature",
  "properties": {
    "tgn:hierarchy":[
        "tgn:2027733",
        "tgn:1000001",
        "tgn:7019012",
        "tgn:7012149",
        "tgn:7007251",
        "tgn:7029392"
    ],
    "tgn:id":2027733,
    "tgn:name":"Elva",
    "tgn:placetype":[
        "aat:300008347",
        "aat:300387210"
    ]
},
  "bbox": [],
  "geometry": {"coordinates":[-88.7667,41.85],"type":"Point"}
}