{
  "id": 7591821,
  "type": "Feature",
  "properties": {
    "tgn:hierarchy":[
        "tgn:7591821",
        "tgn:1000004",
        "tgn:7000198",
        "tgn:7000799",
        "tgn:7029392"
    ],
    "tgn:id":7591821,
    "tgn:name:en":"Duwal Khalka",
    "tgn:placetype":[
        "aat:300008347"
    ]
},
  "bbox": [],
  "geometry": {"coordinates":[74.800997,32.951333],"type":"Point"}
}