{
  "id": 2286831,
  "type": "Feature",
  "properties": {
    "tgn:hierarchy":[
        "tgn:2286831",
        "tgn:1000001",
        "tgn:7012149",
        "tgn:2001763",
        "tgn:7007712",
        "tgn:7029392"
    ],
    "tgn:id":2286831,
    "tgn:name":"Diana, Lake",
    "tgn:placetype":[
        "aat:300006191"
    ]
},
  "bbox": [],
  "geometry": {"coordinates":[-82.8667,34.9167],"type":"Point"}
}