<<<<<<< HEAD
{
  "id": 7364317,
  "type": "Feature",
  "properties": {
    "tgn:hierarchy":[
        "tgn:7364317",
        "tgn:7005581",
        "tgn:1000001",
        "tgn:7005560",
        "tgn:7029392"
    ],
    "tgn:id":7364317,
    "tgn:name":"Rancho El Bejuco",
    "tgn:placetype":[
        "aat:300000241"
    ]
},
  "bbox": [],
  "geometry": {"coordinates":[-105.233333,27.8],"type":"Point"}
}
=======
{"geometry":{"type":"Point","coordinates":[-105.233333,27.800000]},"type":"Feature","properties":{"hierarchy":["tgn:7364317","tgn:7005581","tgn:1000001","tgn:7005560","tgn:7029392"],"placetype":["aat:300000241"],"id":7364317,"name:xx":"Rancho El Bejuco"}}
>>>>>>> 03f74aca74312dbeaf24d7e61306dd6a786dc3d0
