{
  "id": 2679627,
  "type": "Feature",
  "properties": {
    "tgn:hierarchy":[
        "tgn:2679627",
        "tgn:1000001",
        "tgn:7012149",
        "tgn:7007157",
        "tgn:1002675",
        "tgn:7029392"
    ],
    "tgn:id":2679627,
    "tgn:name":"South Fork Perry Aiken Creek",
    "tgn:placetype":[
        "aat:300008706"
    ]
},
  "bbox": [],
  "geometry": {"coordinates":[-118.2167,37.6167],"type":"Point"}
}