{
  "id": 7265529,
  "type": "Feature",
  "properties": {
    "tgn:hierarchy":[
        "tgn:7265529",
        "tgn:1000003",
        "tgn:7003632",
        "tgn:7016845",
        "tgn:7029392"
    ],
    "tgn:id":7265529,
    "tgn:name:nl":"Lage Bergse Bos",
    "tgn:placetype":[
        "aat:300008187"
    ]
},
  "bbox": [],
  "geometry": {"coordinates":[4.516667,51.966667],"type":"Point"}
}