{
  "id": 2026347,
  "type": "Feature",
  "properties": {
    "tgn:hierarchy":[
        "tgn:2026347",
        "tgn:1000001",
        "tgn:7012149",
        "tgn:1002532",
        "tgn:7007251",
        "tgn:7029392"
    ],
    "tgn:id":2026347,
    "tgn:name":"Appel Siding",
    "tgn:placetype":[
        "aat:300387016"
    ]
},
  "bbox": [],
  "geometry": {"coordinates":[-88.1333,41.0333],"type":"Point"}
}