<<<<<<< HEAD
{
  "id": 2335241,
  "type": "Feature",
  "properties": {
    "tgn:hierarchy":[
        "tgn:2335241",
        "tgn:1000001",
        "tgn:7012149",
        "tgn:2000757",
        "tgn:7007254",
        "tgn:7029392"
    ],
    "tgn:id":2335241,
    "tgn:name":"Fort Downer",
    "tgn:placetype":[
        "aat:300008347"
    ]
},
  "bbox": [],
  "geometry": {"coordinates":[-99.9667,38.8333],"type":"Point"}
}
=======
{"geometry":{"type":"Point","coordinates":[-99.966700,38.833300]},"type":"Feature","properties":{"hierarchy":["tgn:2335241","tgn:1000001","tgn:7012149","tgn:2000757","tgn:7007254","tgn:7029392"],"placetype":["aat:300008347"],"id":2335241,"name:xx":"Fort Downer"}}
>>>>>>> 03f74aca74312dbeaf24d7e61306dd6a786dc3d0
