{
  "id": 2335241,
  "type": "Feature",
  "properties": {
    "tgn:hierarchy":[
        "tgn:2335241",
        "tgn:1000001",
        "tgn:7012149",
        "tgn:2000757",
        "tgn:7007254",
        "tgn:7029392"
    ],
    "tgn:id":2335241,
    "tgn:name":"Fort Downer",
    "tgn:placetype":[
        "aat:300008347"
    ]
},
  "bbox": [],
  "geometry": {"coordinates":[-99.9667,38.8333],"type":"Point"}
}