{
  "id": 2051250,
  "type": "Feature",
  "properties": {
    "tgn:hierarchy":[
        "tgn:2051250",
        "tgn:1000001",
        "tgn:2000952",
        "tgn:7012149",
        "tgn:7007520",
        "tgn:7029392"
    ],
    "tgn:id":2051250,
    "tgn:name":"Bay Mills",
    "tgn:placetype":[
        "aat:300008347"
    ]
},
  "bbox": [],
  "geometry": {"coordinates":[-84.5833,46.4333],"type":"Point"}
}