{
  "id": 2198335,
  "type": "Feature",
  "properties": {
    "tgn:hierarchy":[
        "tgn:2198335",
        "tgn:1000001",
        "tgn:7012149",
        "tgn:7007568",
        "tgn:7029392"
    ],
    "tgn:id":2198335,
    "tgn:name":"Browns Creek",
    "tgn:placetype":[
        "aat:300008706"
    ]
},
  "bbox": [],
  "geometry": {"coordinates":[-77.9333,42.9167],"type":"Point"}
}