{
  "id": 7036138,
  "type": "Feature",
  "properties": {
    "tgn:hierarchy":[
        "tgn:7036138",
        "tgn:7002996",
        "tgn:1000003",
        "tgn:7002997",
        "tgn:1000080",
        "tgn:7029392"
    ],
    "tgn:id":7036138,
    "tgn:name":"Miane Premaor",
    "tgn:placetype":[
        "aat:300008347"
    ]
},
  "bbox": [],
  "geometry": {"coordinates":[12.124722,45.936944],"type":"Point"}
}