{
  "id": 2586301,
  "type": "Feature",
  "properties": {
    "tgn:hierarchy":[
        "tgn:2586301",
        "tgn:1000001",
        "tgn:7012149",
        "tgn:2001714",
        "tgn:7007708",
        "tgn:7029392"
    ],
    "tgn:id":2586301,
    "tgn:name":"Pitch Log Creek",
    "tgn:placetype":[
        "aat:300008706"
    ]
},
  "bbox": [],
  "geometry": {"coordinates":[-120.9333,42.1167],"type":"Point"}
}