{
  "id": 1065963,
  "type": "Feature",
  "properties": {
    "tgn:hierarchy":[
        "tgn:1065963",
        "tgn:1000004",
        "tgn:7000191",
        "tgn:1000105",
        "tgn:7029392"
    ],
    "tgn:id":1065963,
    "tgn:name":"Th\u0101kurgaon",
    "tgn:placetype":[
        "aat:300008347"
    ]
},
  "bbox": [],
  "geometry": {"coordinates":[88.4667,26.0333],"type":"Point"}
}