{
  "id": 7305800,
  "type": "Feature",
  "properties": {
    "tgn:hierarchy":[
        "tgn:7305800",
        "tgn:7002824",
        "tgn:1000003",
        "tgn:7002786",
        "tgn:1000095",
        "tgn:7029392"
    ],
    "tgn:id":7305800,
    "tgn:name":"Manto\u00f1o",
    "tgn:placetype":[
        "aat:300008347"
    ]
},
  "bbox": [],
  "geometry": {"coordinates":[-8.966667,42.75],"type":"Point"}
}