{
  "id": 2053559,
  "type": "Feature",
  "properties": {
    "tgn:hierarchy":[
        "tgn:2053559",
        "tgn:1000001",
        "tgn:7012149",
        "tgn:1002603",
        "tgn:7007520",
        "tgn:7029392"
    ],
    "tgn:id":2053559,
    "tgn:name":"Unadilla",
    "tgn:placetype":[
        "aat:300008347"
    ]
},
  "bbox": [],
  "geometry": {"coordinates":[-84.05,42.4167],"type":"Point"}
}