<<<<<<< HEAD
{
  "id": 2259746,
  "type": "Feature",
  "properties": {
    "tgn:hierarchy":[
        "tgn:2259746",
        "tgn:1000001",
        "tgn:7012149",
        "tgn:2002019",
        "tgn:7007826",
        "tgn:7029392"
    ],
    "tgn:id":2259746,
    "tgn:name":"Cougar Hollow",
    "tgn:placetype":[
        "aat:300008761"
    ]
},
  "bbox": [],
  "geometry": {"coordinates":[-99.95,30.45],"type":"Point"}
}
=======
{"geometry":{"type":"Point","coordinates":[-99.950000,30.450000]},"type":"Feature","properties":{"hierarchy":["tgn:2259746","tgn:1000001","tgn:7012149","tgn:2002019","tgn:7007826","tgn:7029392"],"placetype":["aat:300008761"],"id":2259746,"name:xx":"Cougar Hollow"}}
>>>>>>> 03f74aca74312dbeaf24d7e61306dd6a786dc3d0
