{
  "id": 2642927,
  "type": "Feature",
  "properties": {
    "tgn:hierarchy":[
        "tgn:2642927",
        "tgn:1000001",
        "tgn:7012149",
        "tgn:2001505",
        "tgn:7007709",
        "tgn:7029392"
    ],
    "tgn:id":2642927,
    "tgn:name":"Sandstone Hill",
    "tgn:placetype":[
        "aat:300008798"
    ]
},
  "bbox": [],
  "geometry": {"coordinates":[-79.3333,35.0333],"type":"Point"}
}