{
  "id": 2510983,
  "type": "Feature",
  "properties": {
    "tgn:hierarchy":[
        "tgn:2510983",
        "tgn:1000001",
        "tgn:7012149",
        "tgn:2001719",
        "tgn:7007708",
        "tgn:7029392"
    ],
    "tgn:id":2510983,
    "tgn:name":"Midway",
    "tgn:placetype":[
        "aat:300008347"
    ]
},
  "bbox": [],
  "geometry": {"coordinates":[-119.65,45.25],"type":"Point"}
}