{
  "id": 2452689,
  "type": "Feature",
  "properties": {
    "tgn:hierarchy":[
        "tgn:2452689",
        "tgn:1000001",
        "tgn:7012149",
        "tgn:2000972",
        "tgn:7007520",
        "tgn:7029392"
    ],
    "tgn:id":2452689,
    "tgn:name":"Little Buckeye Lake",
    "tgn:placetype":[
        "aat:300008680"
    ]
},
  "bbox": [],
  "geometry": {"coordinates":[-85.7167,46.45],"type":"Point"}
}