{
  "id": 7462476,
  "type": "Feature",
  "properties": {
    "tgn:hierarchy":[
        "tgn:7462476",
        "tgn:7002445",
        "tgn:1000003",
        "tgn:7008153",
        "tgn:7008591",
        "tgn:7029392"
    ],
    "tgn:id":7462476,
    "tgn:name:en":"Highgate",
    "tgn:placetype":[
        "aat:300008347"
    ]
},
  "bbox": [],
  "geometry": {"coordinates":[0.516667,51.033333],"type":"Point"}
}