{
  "id": 2299422,
  "type": "Feature",
  "properties": {
    "tgn:hierarchy":[
        "tgn:2299422",
        "tgn:1000001",
        "tgn:1002278",
        "tgn:7012149",
        "tgn:7007710",
        "tgn:7029392"
    ],
    "tgn:id":2299422,
    "tgn:name":"Duck Marshes",
    "tgn:placetype":[
        "aat:300006191"
    ]
},
  "bbox": [],
  "geometry": {"coordinates":[-78.3167,41.2333],"type":"Point"}
}