{
  "id": 7567812,
  "type": "Feature",
  "properties": {
    "tgn:hierarchy":[
        "tgn:7567812",
        "tgn:1000004",
        "tgn:7000198",
        "tgn:7001797",
        "tgn:7029392"
    ],
    "tgn:id":7567812,
    "tgn:name:en":"Kilanu",
    "tgn:placetype":[
        "aat:300008347"
    ]
},
  "bbox": [],
  "geometry": {"coordinates":[79.959722,13.194167],"type":"Point"}
}