{
  "id": 7223871,
  "type": "Feature",
  "properties": {
    "tgn:hierarchy":[
        "tgn:7223871",
        "tgn:7011163",
        "tgn:7002674",
        "tgn:1000003",
        "tgn:1000074",
        "tgn:7029392"
    ],
    "tgn:id":7223871,
    "tgn:name":"Thir\u00e9a",
    "tgn:placetype":[
        "aat:300008347"
    ]
},
  "bbox": [],
  "geometry": {"coordinates":[26.516667,41.416667],"type":"Point"}
}