{
  "id": 7176757,
  "type": "Feature",
  "properties": {
    "tgn:hierarchy":[
        "tgn:7176757",
        "tgn:7003692",
        "tgn:1000003",
        "tgn:7000084",
        "tgn:7029392"
    ],
    "tgn:id":7176757,
    "tgn:name":"Hag-M\u00fchle",
    "tgn:placetype":[
        "aat:300008347"
    ]
},
  "bbox": [],
  "geometry": {"coordinates":[9.733333,47.666667],"type":"Point"}
}