{
  "id": 2348759,
  "type": "Feature",
  "properties": {
    "tgn:hierarchy":[
        "tgn:2348759",
        "tgn:1000001",
        "tgn:7012149",
        "tgn:2000828",
        "tgn:7007255",
        "tgn:7029392"
    ],
    "tgn:id":2348759,
    "tgn:name":"Gibson Hollow",
    "tgn:placetype":[
        "aat:300008761"
    ]
},
  "bbox": [],
  "geometry": {"coordinates":[-85.5167,36.9167],"type":"Point"}
}