{
  "id": 1111895,
  "type": "Feature",
  "properties": {
    "tgn:hierarchy":[
        "tgn:1111895",
        "tgn:1000003",
        "tgn:7006951",
        "tgn:7016845",
        "tgn:7029392"
    ],
    "tgn:id":1111895,
    "tgn:name":"Beemster",
    "tgn:placetype":[
        "aat:300387346"
    ]
},
  "bbox": [],
  "geometry": {"coordinates":[4.9167,52.5833],"type":"Point"}
}