{
  "id": 1010941,
  "type": "Feature",
  "properties": {
    "tgn:hierarchy":[
        "tgn:1010941",
        "tgn:7013003",
        "tgn:7005685",
        "tgn:1000001",
        "tgn:7024197",
        "tgn:7029392"
    ],
    "tgn:id":1010941,
    "tgn:name":"Mercy, Cape",
    "tgn:placetype":[
        "aat:300008850"
    ]
},
  "bbox": [],
  "geometry": {"coordinates":[-63.6667,64.9333],"type":"Point"}
}