{
  "id": 1019122,
  "type": "Feature",
  "properties": {
    "tgn:hierarchy":[
        "tgn:1019122",
        "tgn:7006477",
        "tgn:7006348",
        "tgn:1000002",
        "tgn:7029392"
    ],
    "tgn:id":1019122,
    "tgn:name":"Aguada de Guerra",
    "tgn:placetype":[
        "aat:300008347"
    ]
},
  "bbox": [],
  "geometry": {"coordinates":[-68.3833,-41.05],"type":"Point"}
}