{
  "id": 7563143,
  "type": "Feature",
  "properties": {
    "tgn:hierarchy":[
        "tgn:7563143",
        "tgn:1000004",
        "tgn:7000198",
        "tgn:7016722",
        "tgn:7029392"
    ],
    "tgn:id":7563143,
    "tgn:name:en":"Khajuri",
    "tgn:placetype":[
        "aat:300008347"
    ]
},
  "bbox": [],
  "geometry": {"coordinates":[79.411109,27.797342],"type":"Point"}
}