{
  "id": 7585707,
  "type": "Feature",
  "properties": {
    "tgn:hierarchy":[
        "tgn:7585707",
        "tgn:1000004",
        "tgn:7000198",
        "tgn:7000799",
        "tgn:7029392"
    ],
    "tgn:id":7585707,
    "tgn:name:en":"Gulu Hail",
    "tgn:placetype":[
        "aat:300008347"
    ]
},
  "bbox": [],
  "geometry": {"coordinates":[74.180556,33.252778],"type":"Point"}
}