{
  "id": 2679347,
  "type": "Feature",
  "properties": {
    "tgn:hierarchy":[
        "tgn:2679347",
        "tgn:1000001",
        "tgn:1002198",
        "tgn:7012149",
        "tgn:7007826",
        "tgn:7029392"
    ],
    "tgn:id":2679347,
    "tgn:name":"South Fork Marys Creek",
    "tgn:placetype":[
        "aat:300008706"
    ]
},
  "bbox": [],
  "geometry": {"coordinates":[-95.3667,29.5167],"type":"Point"}
}