{
  "id": 7069658,
  "type": "Feature",
  "properties": {
    "tgn:hierarchy":[
        "tgn:7069658",
        "tgn:7003669",
        "tgn:1000003",
        "tgn:7000084",
        "tgn:7029392"
    ],
    "tgn:id":7069658,
    "tgn:name":"Thon-Berg",
    "tgn:placetype":[
        "aat:300008777"
    ]
},
  "bbox": [],
  "geometry": {"coordinates":[10.733333,50.05],"type":"Point"}
}