{
  "id": 2443651,
  "type": "Feature",
  "properties": {
    "tgn:hierarchy":[
        "tgn:2443651",
        "tgn:1002134",
        "tgn:1000001",
        "tgn:7012149",
        "tgn:7007251",
        "tgn:7029392"
    ],
    "tgn:id":2443651,
    "tgn:name":"La Grange Island",
    "tgn:placetype":[
        "aat:300008791"
    ]
},
  "bbox": [],
  "geometry": {"coordinates":[-91.4833,40.0333],"type":"Point"}
}