{
  "id": 2192110,
  "type": "Feature",
  "properties": {
    "tgn:hierarchy":[
        "tgn:2192110",
        "tgn:1000001",
        "tgn:7012149",
        "tgn:2001493",
        "tgn:7007709",
        "tgn:7029392"
    ],
    "tgn:id":2192110,
    "tgn:name":"Brake",
    "tgn:placetype":[
        "aat:300008347"
    ]
},
  "bbox": [],
  "geometry": {"coordinates":[-77.7333,35.9167],"type":"Point"}
}