{
  "id": 7514028,
  "type": "Feature",
  "properties": {
    "tgn:hierarchy":[
        "tgn:7514028",
        "tgn:1009227",
        "tgn:1000226",
        "tgn:7016729",
        "tgn:1000006",
        "tgn:7029392"
    ],
    "tgn:id":7514028,
    "tgn:name:en":"Flaxbourne River",
    "tgn:placetype":[
        "aat:300008699"
    ]
},
  "bbox": [],
  "geometry": {"coordinates":[174.183333,-41.85],"type":"Point"}
}