{
  "id": 7509420,
  "type": "Feature",
  "properties": {
    "tgn:hierarchy":[
        "tgn:7509420",
        "tgn:1009227",
        "tgn:7001866",
        "tgn:1000226",
        "tgn:1000006",
        "tgn:7029392"
    ],
    "tgn:id":7509420,
    "tgn:name:en":"Swin River",
    "tgn:placetype":[
        "aat:300008699"
    ]
},
  "bbox": [],
  "geometry": {"coordinates":[171.183333,-43.483333],"type":"Point"}
}