{
  "id": 7283287,
  "type": "Feature",
  "properties": {
    "tgn:hierarchy":[
        "tgn:7283287",
        "tgn:1001699",
        "tgn:1000049",
        "tgn:1000002",
        "tgn:7029392"
    ],
    "tgn:id":7283287,
    "tgn:name":"Pargua, Bah\u00eda",
    "tgn:placetype":[
        "aat:300132316"
    ]
},
  "bbox": [],
  "geometry": {"coordinates":[-73.430833,-41.797222],"type":"Point"}
}