{
  "id": 2667444,
  "type": "Feature",
  "properties": {
    "tgn:hierarchy":[
        "tgn:2667444",
        "tgn:7002659",
        "tgn:1000001",
        "tgn:2000006",
        "tgn:7012149",
        "tgn:7029392"
    ],
    "tgn:id":2667444,
    "tgn:name":"Skippers Pond",
    "tgn:placetype":[
        "aat:300006191"
    ]
},
  "bbox": [],
  "geometry": {"coordinates":[-86.6833,31.6333],"type":"Point"}
}