<<<<<<< HEAD
{
  "id": 7485533,
  "type": "Feature",
  "properties": {
    "tgn:hierarchy":[
        "tgn:7485533",
        "tgn:1000004",
        "tgn:7492971",
        "tgn:1000141",
        "tgn:7029392"
    ],
    "tgn:id":7485533,
    "tgn:name":"Wuzhao Shan",
    "tgn:placetype":[
        "aat:300008777"
    ]
},
  "bbox": [],
  "geometry": {"coordinates":[120.713889,22.004167],"type":"Point"}
}
=======
{"geometry":{"type":"Point","coordinates":[120.713889,22.004167]},"type":"Feature","properties":{"hierarchy":["tgn:7485533","tgn:1000004","tgn:7492971","tgn:1000141","tgn:7029392"],"placetype":["aat:300008777"],"id":7485533,"name:xx":"Wuzhao Shan"}}
>>>>>>> 03f74aca74312dbeaf24d7e61306dd6a786dc3d0
