{
  "id": 2121968,
  "type": "Feature",
  "properties": {
    "tgn:hierarchy":[
        "tgn:2121968",
        "tgn:1000001",
        "tgn:7012149",
        "tgn:2002329",
        "tgn:7007922",
        "tgn:7029392"
    ],
    "tgn:id":2121968,
    "tgn:name":"New Miner",
    "tgn:placetype":[
        "aat:300008347"
    ]
},
  "bbox": [],
  "geometry": {"coordinates":[-90.0333,44.1667],"type":"Point"}
}