{
  "id": 1037065,
  "type": "Feature",
  "properties": {
    "tgn:hierarchy":[
        "tgn:1037065",
        "tgn:1000003",
        "tgn:7003689",
        "tgn:7000084",
        "tgn:7029392"
    ],
    "tgn:id":1037065,
    "tgn:name":"Kindelbr\u00fcck",
    "tgn:placetype":[
        "aat:300008347"
    ]
},
  "bbox": [],
  "geometry": {"coordinates":[11.083333,51.266667],"type":"Point"}
}