{
  "id": 2360841,
  "type": "Feature",
  "properties": {
    "tgn:hierarchy":[
        "tgn:2360841",
        "tgn:1000001",
        "tgn:7012149",
        "tgn:2002371",
        "tgn:7007923",
        "tgn:7029392"
    ],
    "tgn:id":2360841,
    "tgn:name":"Grassy Lake",
    "tgn:placetype":[
        "aat:300008680"
    ]
},
  "bbox": [],
  "geometry": {"coordinates":[-108.3333,42.2667],"type":"Point"}
}