{
  "id": 7550194,
  "type": "Feature",
  "properties": {
    "tgn:hierarchy":[
        "tgn:7550194",
        "tgn:1000004",
        "tgn:7000198",
        "tgn:7031783",
        "tgn:7029392"
    ],
    "tgn:id":7550194,
    "tgn:name:en":"Biru",
    "tgn:placetype":[
        "aat:300008347"
    ]
},
  "bbox": [],
  "geometry": {"coordinates":[84.550154,22.686207],"type":"Point"}
}