{
  "id": 7012595,
  "type": "Feature",
  "properties": {
    "tgn:hierarchy":[
        "tgn:7012595",
        "tgn:7003026",
        "tgn:1000003",
        "tgn:1000062",
        "tgn:7029392"
    ],
    "tgn:id":7012595,
    "tgn:name":"Mauthausen",
    "tgn:placetype":[
        "aat:300008347",
        "aat:300387268",
        "aat:300008375"
    ]
},
  "bbox": [],
  "geometry": {"coordinates":[14.5167,48.25],"type":"Point"}
}