{
  "id": 7433239,
  "type": "Feature",
  "properties": {
    "tgn:hierarchy":[
        "tgn:7433239",
        "tgn:7005581",
        "tgn:1000001",
        "tgn:7005560",
        "tgn:7029392"
    ],
    "tgn:id":7433239,
    "tgn:name":"Tunas, Puerto de las",
    "tgn:placetype":[
        "aat:300259572"
    ]
},
  "bbox": [],
  "geometry": {"coordinates":[-107.05,29.95],"type":"Point"}
}