{
  "id": 7399827,
  "type": "Feature",
  "properties": {
    "tgn:hierarchy":[
        "tgn:7399827",
        "tgn:1000001",
        "tgn:7005593",
        "tgn:7005560",
        "tgn:7029392"
    ],
    "tgn:id":7399827,
    "tgn:name":"Palo Boludo, Cerro",
    "tgn:placetype":[
        "aat:300008795"
    ]
},
  "bbox": [],
  "geometry": {"coordinates":[-99.475,21.091667],"type":"Point"}
}