{
  "id": 7239724,
  "type": "Feature",
  "properties": {
    "tgn:hierarchy":[
        "tgn:7239724",
        "tgn:7003460",
        "tgn:1000003",
        "tgn:1000063",
        "tgn:4012014",
        "tgn:7029392"
    ],
    "tgn:id":7239724,
    "tgn:name":"Gillenbusch",
    "tgn:placetype":[
        "aat:300008863"
    ]
},
  "bbox": [],
  "geometry": {"coordinates":[6.083333,50.183333],"type":"Point"}
}