{
  "id": 2666067,
  "type": "Feature",
  "properties": {
    "tgn:hierarchy":[
        "tgn:2666067",
        "tgn:1000001",
        "tgn:7012149",
        "tgn:1003026",
        "tgn:7007826",
        "tgn:7029392"
    ],
    "tgn:id":2666067,
    "tgn:name":"Site Number Two",
    "tgn:placetype":[
        "aat:300006191"
    ]
},
  "bbox": [],
  "geometry": {"coordinates":[-97.3333,30.6167],"type":"Point"}
}