{
  "id": 2303366,
  "type": "Feature",
  "properties": {
    "tgn:hierarchy":[
        "tgn:2303366",
        "tgn:1000001",
        "tgn:2001025",
        "tgn:7012149",
        "tgn:7007521",
        "tgn:7029392"
    ],
    "tgn:id":2303366,
    "tgn:name":"Eagle Creek",
    "tgn:placetype":[
        "aat:300008706"
    ]
},
  "bbox": [],
  "geometry": {"coordinates":[-93.4333,45.0667],"type":"Point"}
}