{
  "id": 7273802,
  "type": "Feature",
  "properties": {
    "tgn:hierarchy":[
        "tgn:7273802",
        "tgn:1000003",
        "tgn:7003624",
        "tgn:7016845",
        "tgn:7029392"
    ],
    "tgn:id":7273802,
    "tgn:name:nl":"Waardhuizensebrug",
    "tgn:placetype":[
        "aat:300007836"
    ]
},
  "bbox": [],
  "geometry": {"coordinates":[4.983333,51.783333],"type":"Point"}
}