{
  "id": 7362324,
  "type": "Feature",
  "properties": {
    "tgn:hierarchy":[
        "tgn:7362324",
        "tgn:7005584",
        "tgn:1000001",
        "tgn:7005560",
        "tgn:7029392"
    ],
    "tgn:id":7362324,
    "tgn:name":"El Carmen",
    "tgn:placetype":[
        "aat:300008347"
    ]
},
  "bbox": [],
  "geometry": {"coordinates":[-101.416667,20.883333],"type":"Point"}
}