{
  "id": 7389021,
  "type": "Feature",
  "properties": {
    "tgn:hierarchy":[
        "tgn:7389021",
        "tgn:1000001",
        "tgn:1001960",
        "tgn:7005560",
        "tgn:7029392"
    ],
    "tgn:id":7389021,
    "tgn:name":"Pozo Seco",
    "tgn:placetype":[
        "aat:300008347"
    ]
},
  "bbox": [],
  "geometry": {"coordinates":[-109.933333,31.316667],"type":"Point"}
}