<<<<<<< HEAD
{
  "id": 2333265,
  "type": "Feature",
  "properties": {
    "tgn:hierarchy":[
        "tgn:2333265",
        "tgn:1000001",
        "tgn:7012149",
        "tgn:2001544",
        "tgn:7007709",
        "tgn:7029392"
    ],
    "tgn:id":2333265,
    "tgn:name":"Fodderstack Mountain",
    "tgn:placetype":[
        "aat:300008798"
    ]
},
  "bbox": [],
  "geometry": {"coordinates":[-82.6333,35.2833],"type":"Point"}
}
=======
{"geometry":{"type":"Point","coordinates":[-82.633300,35.283300]},"type":"Feature","properties":{"hierarchy":["tgn:2333265","tgn:1000001","tgn:7012149","tgn:2001544","tgn:7007709","tgn:7029392"],"placetype":["aat:300008798"],"id":2333265,"name:xx":"Fodderstack Mountain"}}
>>>>>>> 03f74aca74312dbeaf24d7e61306dd6a786dc3d0
