{
  "id": 2333265,
  "type": "Feature",
  "properties": {
    "tgn:hierarchy":[
        "tgn:2333265",
        "tgn:1000001",
        "tgn:7012149",
        "tgn:2001544",
        "tgn:7007709",
        "tgn:7029392"
    ],
    "tgn:id":2333265,
    "tgn:name":"Fodderstack Mountain",
    "tgn:placetype":[
        "aat:300008798"
    ]
},
  "bbox": [],
  "geometry": {"coordinates":[-82.6333,35.2833],"type":"Point"}
}