{
  "id": 2647032,
  "type": "Feature",
  "properties": {
    "tgn:hierarchy":[
        "tgn:2647032",
        "tgn:1000001",
        "tgn:7012149",
        "tgn:1002742",
        "tgn:7007920",
        "tgn:7029392"
    ],
    "tgn:id":2647032,
    "tgn:name":"Schalow Mountain",
    "tgn:placetype":[
        "aat:300008798"
    ]
},
  "bbox": [],
  "geometry": {"coordinates":[-119.6833,48.5833],"type":"Point"}
}