{
  "id": 2107514,
  "type": "Feature",
  "properties": {
    "tgn:hierarchy":[
        "tgn:2107514",
        "tgn:1000001",
        "tgn:7012149",
        "tgn:2001961",
        "tgn:7007826",
        "tgn:7029392"
    ],
    "tgn:id":2107514,
    "tgn:name":"Sattler",
    "tgn:placetype":[
        "aat:300008347"
    ]
},
  "bbox": [],
  "geometry": {"coordinates":[-98.1667,29.8333],"type":"Point"}
}