{
  "id": 7565160,
  "type": "Feature",
  "properties": {
    "tgn:hierarchy":[
        "tgn:7565160",
        "tgn:1000004",
        "tgn:7000198",
        "tgn:7016788",
        "tgn:7029392"
    ],
    "tgn:id":7565160,
    "tgn:name:en":"Sut\u0101rw\u0101la Tibba",
    "tgn:placetype":[
        "aat:300008347"
    ]
},
  "bbox": [],
  "geometry": {"coordinates":[71.116524,27.57993],"type":"Point"}
}