{
  "id": 7025776,
  "type": "Feature",
  "properties": {
    "tgn:hierarchy":[
        "tgn:7025776",
        "tgn:7002445",
        "tgn:1000003",
        "tgn:7012077",
        "tgn:7008591",
        "tgn:7029392"
    ],
    "tgn:id":7025776,
    "tgn:name:en":"Walkhampton",
    "tgn:placetype":[
        "aat:300008347"
    ]
},
  "bbox": [],
  "geometry": {"coordinates":[-4.066667,50.516667],"type":"Point"}
}