{
  "id": 2061292,
  "type": "Feature",
  "properties": {
    "tgn:hierarchy":[
        "tgn:2061292",
        "tgn:1000001",
        "tgn:7012149",
        "tgn:2001291",
        "tgn:7007524",
        "tgn:7029392"
    ],
    "tgn:id":2061292,
    "tgn:name":"Evaro",
    "tgn:placetype":[
        "aat:300008347"
    ]
},
  "bbox": [],
  "geometry": {"coordinates":[-114.0833,47.0167],"type":"Point"}
}