{
  "id": 2752248,
  "type": "Feature",
  "properties": {
    "tgn:hierarchy":[
        "tgn:2752248",
        "tgn:1000001",
        "tgn:7012149",
        "tgn:1003021",
        "tgn:7007252",
        "tgn:7029392"
    ],
    "tgn:id":2752248,
    "tgn:name":"Washburn Ditch",
    "tgn:placetype":[
        "aat:300006075"
    ]
},
  "bbox": [],
  "geometry": {"coordinates":[-86.5833,40.8833],"type":"Point"}
}