<<<<<<< HEAD
{
  "id": 7353443,
  "type": "Feature",
  "properties": {
    "tgn:hierarchy":[
        "tgn:7353443",
        "tgn:7005581",
        "tgn:1000001",
        "tgn:7005560",
        "tgn:7029392"
    ],
    "tgn:id":7353443,
    "tgn:name":"Buenavista Tecorichic",
    "tgn:placetype":[
        "aat:300008347"
    ]
},
  "bbox": [],
  "geometry": {"coordinates":[-106.733333,26.75],"type":"Point"}
}
=======
{"geometry":{"type":"Point","coordinates":[-106.733333,26.750000]},"type":"Feature","properties":{"hierarchy":["tgn:7353443","tgn:7005581","tgn:1000001","tgn:7005560","tgn:7029392"],"placetype":["aat:300008347"],"id":7353443,"name:xx":"Buenavista Tecorichic"}}
>>>>>>> 03f74aca74312dbeaf24d7e61306dd6a786dc3d0
