{
  "id": 2420458,
  "type": "Feature",
  "properties": {
    "tgn:hierarchy":[
        "tgn:2420458",
        "tgn:1000001",
        "tgn:2001095",
        "tgn:7012149",
        "tgn:7007522",
        "tgn:7029392"
    ],
    "tgn:id":2420458,
    "tgn:name":"Jenkins Creek",
    "tgn:placetype":[
        "aat:300008706"
    ]
},
  "bbox": [],
  "geometry": {"coordinates":[-89.2833,33.3833],"type":"Point"}
}