{
  "id": 2360476,
  "type": "Feature",
  "properties": {
    "tgn:hierarchy":[
        "tgn:2360476",
        "tgn:1000001",
        "tgn:1003029",
        "tgn:7012149",
        "tgn:7007828",
        "tgn:7029392"
    ],
    "tgn:id":2360476,
    "tgn:name":"Grassy Brook",
    "tgn:placetype":[
        "aat:300008699"
    ]
},
  "bbox": [],
  "geometry": {"coordinates":[-72.5667,43.0667],"type":"Point"}
}