{
  "id": 7438666,
  "type": "Feature",
  "properties": {
    "tgn:hierarchy":[
        "tgn:7438666",
        "tgn:1000001",
        "tgn:7005588",
        "tgn:7005560",
        "tgn:7029392"
    ],
    "tgn:id":7438666,
    "tgn:name":"Tehuixtla",
    "tgn:placetype":[
        "aat:300008347"
    ]
},
  "bbox": [],
  "geometry": {"coordinates":[-99.266667,18.55],"type":"Point"}
}