{
  "id": 2216300,
  "type": "Feature",
  "properties": {
    "tgn:hierarchy":[
        "tgn:2216300",
        "tgn:1000001",
        "tgn:7012149",
        "tgn:2000930",
        "tgn:7007515",
        "tgn:7029392"
    ],
    "tgn:id":2216300,
    "tgn:name":"Camp Brook",
    "tgn:placetype":[
        "aat:300008699"
    ]
},
  "bbox": [],
  "geometry": {"coordinates":[-69.95,46.05],"type":"Point"}
}