{
  "id": 2278793,
  "type": "Feature",
  "properties": {
    "tgn:hierarchy":[
        "tgn:2278793",
        "tgn:1000001",
        "tgn:7012149",
        "tgn:2001722",
        "tgn:7007708",
        "tgn:7029392"
    ],
    "tgn:id":2278793,
    "tgn:name":"Dead Horse Ridge",
    "tgn:placetype":[
        "aat:300266640"
    ]
},
  "bbox": [],
  "geometry": {"coordinates":[-116.85,45.45],"type":"Point"}
}