{
  "id": 2282205,
  "type": "Feature",
  "properties": {
    "tgn:hierarchy":[
        "tgn:2282205",
        "tgn:1000001",
        "tgn:2002311",
        "tgn:7012149",
        "tgn:7007922",
        "tgn:7029392"
    ],
    "tgn:id":2282205,
    "tgn:name":"Deer Lake",
    "tgn:placetype":[
        "aat:300008680"
    ]
},
  "bbox": [],
  "geometry": {"coordinates":[-92.1667,46.0333],"type":"Point"}
}