{
  "id": 2606423,
  "type": "Feature",
  "properties": {
    "tgn:hierarchy":[
        "tgn:2606423",
        "tgn:1000001",
        "tgn:7012149",
        "tgn:1002570",
        "tgn:7007706",
        "tgn:7029392"
    ],
    "tgn:id":2606423,
    "tgn:name":"Ram Island",
    "tgn:placetype":[
        "aat:300008791"
    ]
},
  "bbox": [],
  "geometry": {"coordinates":[-81.2667,41.7333],"type":"Point"}
}