{
  "id": 2173987,
  "type": "Feature",
  "properties": {
    "tgn:hierarchy":[
        "tgn:2173987",
        "tgn:7006450",
        "tgn:1000001",
        "tgn:2124012",
        "tgn:7012149",
        "tgn:7029392"
    ],
    "tgn:id":2173987,
    "tgn:name":"Bird Point",
    "tgn:placetype":[
        "aat:300008850"
    ]
},
  "bbox": [],
  "geometry": {"coordinates":[-152.7833,57.9167],"type":"Point"}
}