{
  "id": 7538705,
  "type": "Feature",
  "properties": {
    "tgn:hierarchy":[
        "tgn:7538705",
        "tgn:7001242",
        "tgn:7001311",
        "tgn:7016833",
        "tgn:7029392"
    ],
    "tgn:id":7538705,
    "tgn:name:en":"Niqr\u016bb at Ta\u1e29t\u0101n\u012b, Jabal",
    "tgn:placetype":[
        "aat:300008795"
    ]
},
  "bbox": [],
  "geometry": {"coordinates":[35.0161,23.010933],"type":"Point"}
}