{
  "id": 7530605,
  "type": "Feature",
  "properties": {
    "tgn:hierarchy":[
        "tgn:7530605",
        "tgn:7001242",
        "tgn:7016833",
        "tgn:1001083",
        "tgn:7029392"
    ],
    "tgn:id":7530605,
    "tgn:name":"Mu\u1e29\u0101faz\u0327at al J\u012bzah",
    "tgn:placetype":[
        "aat:300386996"
    ]
},
  "bbox": [],
  "geometry": {"coordinates":[31.199566,30.009207],"type":"Point"}
}