{
  "id": 7569026,
  "type": "Feature",
  "properties": {
    "tgn:hierarchy":[
        "tgn:7569026",
        "tgn:1000004",
        "tgn:7000198",
        "tgn:1001996",
        "tgn:7029392"
    ],
    "tgn:id":7569026,
    "tgn:name:en":"Panhech Protected Forest",
    "tgn:placetype":[
        "aat:300008863"
    ]
},
  "bbox": [],
  "geometry": {"coordinates":[77.077778,31.143056],"type":"Point"}
}