{
  "id": 7468036,
  "type": "Feature",
  "properties": {
    "tgn:hierarchy":[
        "tgn:7468036",
        "tgn:1000004",
        "tgn:1000454",
        "tgn:1000141",
        "tgn:7029392"
    ],
    "tgn:id":7468036,
    "tgn:name":"Jiaxizikeng",
    "tgn:placetype":[
        "aat:300008347"
    ]
},
  "bbox": [],
  "geometry": {"coordinates":[121.31669,25.116114],"type":"Point"}
}