{
  "id": 2086915,
  "type": "Feature",
  "properties": {
    "tgn:hierarchy":[
        "tgn:2086915",
        "tgn:1000001",
        "tgn:7012149",
        "tgn:1002995",
        "tgn:7007710",
        "tgn:7029392"
    ],
    "tgn:id":2086915,
    "tgn:name":"California",
    "tgn:placetype":[
        "aat:300008347"
    ]
},
  "bbox": [],
  "geometry": {"coordinates":[-79.8833,40.05],"type":"Point"}
}