{
  "id": 7367459,
  "type": "Feature",
  "properties": {
    "tgn:hierarchy":[
        "tgn:7367459",
        "tgn:1000001",
        "tgn:7005595",
        "tgn:7005560",
        "tgn:7029392"
    ],
    "tgn:id":7367459,
    "tgn:name":"El Sabino",
    "tgn:placetype":[
        "aat:300008347"
    ]
},
  "bbox": [],
  "geometry": {"coordinates":[-106.822222,24.384444],"type":"Point"}
}