<<<<<<< HEAD
{
  "id": 2409725,
  "type": "Feature",
  "properties": {
    "tgn:hierarchy":[
        "tgn:2409725",
        "tgn:7006450",
        "tgn:1000001",
        "tgn:7012149",
        "tgn:2124005",
        "tgn:7029392"
    ],
    "tgn:id":2409725,
    "tgn:name":"Ikroavik Lake",
    "tgn:placetype":[
        "aat:300008680"
    ]
},
  "bbox": [],
  "geometry": {"coordinates":[-156.6333,71.2167],"type":"Point"}
}
=======
{"geometry":{"type":"Point","coordinates":[-156.633300,71.216700]},"type":"Feature","properties":{"hierarchy":["tgn:2409725","tgn:7006450","tgn:1000001","tgn:7012149","tgn:2124005","tgn:7029392"],"placetype":["aat:300008680"],"id":2409725,"name:xx":"Ikroavik Lake"}}
>>>>>>> 03f74aca74312dbeaf24d7e61306dd6a786dc3d0
