{
  "id": 7517013,
  "type": "Feature",
  "properties": {
    "tgn:hierarchy":[
        "tgn:7517013",
        "tgn:1009227",
        "tgn:1000226",
        "tgn:7016729",
        "tgn:1000006",
        "tgn:7029392"
    ],
    "tgn:id":7517013,
    "tgn:name:en":"Mill Creek",
    "tgn:placetype":[
        "aat:300008699"
    ]
},
  "bbox": [],
  "geometry": {"coordinates":[174.75,-41.216667],"type":"Point"}
}