{
  "id": 7309892,
  "type": "Feature",
  "properties": {
    "tgn:hierarchy":[
        "tgn:7309892",
        "tgn:7002464",
        "tgn:1000049",
        "tgn:1000002",
        "tgn:7029392"
    ],
    "tgn:id":7309892,
    "tgn:name":"Ossa",
    "tgn:placetype":[
        "aat:300008347"
    ]
},
  "bbox": [],
  "geometry": {"coordinates":[-69.85,-18.283333],"type":"Point"}
}