{
  "id": 2709340,
  "type": "Feature",
  "properties": {
    "tgn:hierarchy":[
        "tgn:2709340",
        "tgn:1000001",
        "tgn:7012149",
        "tgn:2001275",
        "tgn:7007524",
        "tgn:7029392"
    ],
    "tgn:id":2709340,
    "tgn:name":"Table Mountain Mine",
    "tgn:placetype":[
        "aat:300000390"
    ]
},
  "bbox": [],
  "geometry": {"coordinates":[-111.25,45.3167],"type":"Point"}
}