{
  "id": 2409862,
  "type": "Feature",
  "properties": {
    "tgn:hierarchy":[
        "tgn:2409862",
        "tgn:1000001",
        "tgn:7012149",
        "tgn:2002373",
        "tgn:7007923",
        "tgn:7029392"
    ],
    "tgn:id":2409862,
    "tgn:name":"Ilo Ridge",
    "tgn:placetype":[
        "aat:300266640"
    ]
},
  "bbox": [],
  "geometry": {"coordinates":[-108.5667,43.8833],"type":"Point"}
}