{
  "id": 2207245,
  "type": "Feature",
  "properties": {
    "tgn:hierarchy":[
        "tgn:2207245",
        "tgn:1000001",
        "tgn:7012149",
        "tgn:2001191",
        "tgn:7007523",
        "tgn:7029392"
    ],
    "tgn:id":2207245,
    "tgn:name":"Bunker Hill",
    "tgn:placetype":[
        "aat:300008798"
    ]
},
  "bbox": [],
  "geometry": {"coordinates":[-93.6333,37.4333],"type":"Point"}
}