{
  "id": 7558130,
  "type": "Feature",
  "properties": {
    "tgn:hierarchy":[
        "tgn:7558130",
        "tgn:1000004",
        "tgn:1001871",
        "tgn:7000198",
        "tgn:7029392"
    ],
    "tgn:id":7558130,
    "tgn:name:en":"R\u0101thdhana Railroad Station",
    "tgn:placetype":[
        "aat:300007783"
    ]
},
  "bbox": [],
  "geometry": {"coordinates":[77.059435,28.903369],"type":"Point"}
}