{
  "id": 2138789,
  "type": "Feature",
  "properties": {
    "tgn:hierarchy":[
        "tgn:2138789",
        "tgn:1002808",
        "tgn:1000001",
        "tgn:7012149",
        "tgn:7007711",
        "tgn:7029392"
    ],
    "tgn:id":2138789,
    "tgn:name":"Ash Swamp",
    "tgn:placetype":[
        "aat:300008905"
    ]
},
  "bbox": [],
  "geometry": {"coordinates":[-71.4167,41.9833],"type":"Point"}
}