{
  "id": 1055038,
  "type": "Feature",
  "properties": {
    "tgn:hierarchy":[
        "tgn:1055038",
        "tgn:1000004",
        "tgn:7011457",
        "tgn:7014786",
        "tgn:7029392"
    ],
    "tgn:id":1055038,
    "tgn:name":"Karagay",
    "tgn:placetype":[
        "aat:300008347"
    ]
},
  "bbox": [],
  "geometry": {"coordinates":[47.6167,48.65],"type":"Point"}
}