<<<<<<< HEAD
{
  "id": 2766256,
  "type": "Feature",
  "properties": {
    "tgn:hierarchy":[
        "tgn:2766256",
        "tgn:1000001",
        "tgn:7012149",
        "tgn:7007157",
        "tgn:1002867",
        "tgn:7029392"
    ],
    "tgn:id":2766256,
    "tgn:name":"White Ledge Canyon",
    "tgn:placetype":[
        "aat:300008761"
    ]
},
  "bbox": [],
  "geometry": {"coordinates":[-119.8167,34.7167],"type":"Point"}
}
=======
{"geometry":{"type":"Point","coordinates":[-119.816700,34.716700]},"type":"Feature","properties":{"hierarchy":["tgn:2766256","tgn:1000001","tgn:7012149","tgn:7007157","tgn:1002867","tgn:7029392"],"placetype":["aat:300008761"],"id":2766256,"name:xx":"White Ledge Canyon"}}
>>>>>>> 03f74aca74312dbeaf24d7e61306dd6a786dc3d0
