{
  "id": 7276516,
  "type": "Feature",
  "properties": {
    "tgn:hierarchy":[
        "tgn:7276516",
        "tgn:7002464",
        "tgn:1000049",
        "tgn:1000002",
        "tgn:7029392"
    ],
    "tgn:id":7276516,
    "tgn:name":"Toctosaya",
    "tgn:placetype":[
        "aat:300008347"
    ]
},
  "bbox": [],
  "geometry": {"coordinates":[-68.683333,-19.316667],"type":"Point"}
}