{
  "id": 2148435,
  "type": "Feature",
  "properties": {
    "tgn:hierarchy":[
        "tgn:2148435",
        "tgn:1000001",
        "tgn:7012149",
        "tgn:7007158",
        "tgn:2000251",
        "tgn:7029392"
    ],
    "tgn:id":2148435,
    "tgn:name":"Barnard Creek",
    "tgn:placetype":[
        "aat:300008706"
    ]
},
  "bbox": [],
  "geometry": {"coordinates":[-105.1333,38.7833],"type":"Point"}
}