{
  "id": 2502841,
  "type": "Feature",
  "properties": {
    "tgn:hierarchy":[
        "tgn:2502841",
        "tgn:1000001",
        "tgn:1002174",
        "tgn:7012149",
        "tgn:7007826",
        "tgn:7029392"
    ],
    "tgn:id":2502841,
    "tgn:name":"McMillan Mountains",
    "tgn:placetype":[
        "aat:300008798"
    ]
},
  "bbox": [],
  "geometry": {"coordinates":[-97.7833,31.0667],"type":"Point"}
}