{
  "id": 7019178,
  "type": "Feature",
  "properties": {
    "tgn:hierarchy":[
        "tgn:7019178",
        "tgn:1000001",
        "tgn:7012149",
        "tgn:7007253",
        "tgn:7029392"
    ],
    "tgn:id":7019178,
    "tgn:name":"Clarke",
    "tgn:placetype":[
        "aat:300387145",
        "aat:300000771"
    ]
},
  "bbox": [],
  "geometry": {"coordinates":[-93.7833,41.0333],"type":"Point"}
}