{
  "id": 2618494,
  "type": "Feature",
  "properties": {
    "tgn:hierarchy":[
        "tgn:2618494",
        "tgn:1000001",
        "tgn:7012149",
        "tgn:2000837",
        "tgn:7007255",
        "tgn:7029392"
    ],
    "tgn:id":2618494,
    "tgn:name":"Right Fork Dixfork",
    "tgn:placetype":[
        "aat:300008699"
    ]
},
  "bbox": [],
  "geometry": {"coordinates":[-82.35,37.55],"type":"Point"}
}