{
  "id": 2672666,
  "type": "Feature",
  "properties": {
    "tgn:hierarchy":[
        "tgn:2672666",
        "tgn:1000001",
        "tgn:7012149",
        "tgn:7007564",
        "tgn:7029392"
    ],
    "tgn:id":2672666,
    "tgn:name":"Smutty Hollow",
    "tgn:placetype":[
        "aat:300008761"
    ]
},
  "bbox": [],
  "geometry": {"coordinates":[-71.9833,44.2667],"type":"Point"}
}