{
  "id": 2376873,
  "type": "Feature",
  "properties": {
    "tgn:hierarchy":[
        "tgn:2376873",
        "tgn:1000001",
        "tgn:7006451",
        "tgn:7012149",
        "tgn:2000097",
        "tgn:7029392"
    ],
    "tgn:id":2376873,
    "tgn:name":"Hargan Mine",
    "tgn:placetype":[
        "aat:300000390"
    ]
},
  "bbox": [],
  "geometry": {"coordinates":[-112.8667,33.2167],"type":"Point"}
}