{
  "id": 2640084,
  "type": "Feature",
  "properties": {
    "tgn:hierarchy":[
        "tgn:2640084",
        "tgn:1000001",
        "tgn:7012149",
        "tgn:2002289",
        "tgn:7013961",
        "tgn:7029392"
    ],
    "tgn:id":2640084,
    "tgn:name":"Sams Fork",
    "tgn:placetype":[
        "aat:300008699"
    ]
},
  "bbox": [],
  "geometry": {"coordinates":[-81.9333,38.3667],"type":"Point"}
}