{
  "id": 7586021,
  "type": "Feature",
  "properties": {
    "tgn:hierarchy":[
        "tgn:7586021",
        "tgn:1000004",
        "tgn:7000198",
        "tgn:7000799",
        "tgn:7029392"
    ],
    "tgn:id":7586021,
    "tgn:name:en":"Br\u0101ripur",
    "tgn:placetype":[
        "aat:300008347"
    ]
},
  "bbox": [],
  "geometry": {"coordinates":[74.296597,34.406778],"type":"Point"}
}