{
  "id": 1102692,
  "type": "Feature",
  "properties": {
    "tgn:hierarchy":[
        "tgn:1102692",
        "tgn:7000490",
        "tgn:1000006",
        "tgn:7001831",
        "tgn:7029392"
    ],
    "tgn:id":1102692,
    "tgn:name":"Belair Recreation Park",
    "tgn:placetype":[
        "aat:300008187"
    ]
},
  "bbox": [],
  "geometry": {"coordinates":[138.65,-35.0167],"type":"Point"}
}