{
  "id": 7559351,
  "type": "Feature",
  "properties": {
    "tgn:hierarchy":[
        "tgn:7559351",
        "tgn:1000004",
        "tgn:7000198",
        "tgn:1001895",
        "tgn:7029392"
    ],
    "tgn:id":7559351,
    "tgn:name:en":"S\u0101rola",
    "tgn:placetype":[
        "aat:300008347"
    ]
},
  "bbox": [],
  "geometry": {"coordinates":[74.666667,18.95],"type":"Point"}
}