{
  "id": 7494286,
  "type": "Feature",
  "properties": {
    "tgn:hierarchy":[
        "tgn:7494286",
        "tgn:7468018",
        "tgn:1000004",
        "tgn:1000141",
        "tgn:7029392"
    ],
    "tgn:id":7494286,
    "tgn:name":"Minxiong Guozhong",
    "tgn:placetype":[
        "aat:300006495"
    ]
},
  "bbox": [],
  "geometry": {"coordinates":[120.421339,23.55668],"type":"Point"}
}