<<<<<<< HEAD
{
  "id": 2250367,
  "type": "Feature",
  "properties": {
    "tgn:hierarchy":[
        "tgn:2250367",
        "tgn:1000001",
        "tgn:7012149",
        "tgn:2001708",
        "tgn:7007708",
        "tgn:7029392"
    ],
    "tgn:id":2250367,
    "tgn:name":"Colo Spring",
    "tgn:placetype":[
        "aat:300008697"
    ]
},
  "bbox": [],
  "geometry": {"coordinates":[-118.7333,44.0667],"type":"Point"}
}
=======
{"geometry":{"type":"Point","coordinates":[-118.733300,44.066700]},"type":"Feature","properties":{"hierarchy":["tgn:2250367","tgn:1000001","tgn:7012149","tgn:2001708","tgn:7007708","tgn:7029392"],"placetype":["aat:300008697"],"id":2250367,"name:xx":"Colo Spring"}}
>>>>>>> 03f74aca74312dbeaf24d7e61306dd6a786dc3d0
