{
  "id": 2250367,
  "type": "Feature",
  "properties": {
    "tgn:hierarchy":[
        "tgn:2250367",
        "tgn:1000001",
        "tgn:7012149",
        "tgn:2001708",
        "tgn:7007708",
        "tgn:7029392"
    ],
    "tgn:id":2250367,
    "tgn:name":"Colo Spring",
    "tgn:placetype":[
        "aat:300008697"
    ]
},
  "bbox": [],
  "geometry": {"coordinates":[-118.7333,44.0667],"type":"Point"}
}