{
  "id": 7108552,
  "type": "Feature",
  "properties": {
    "tgn:hierarchy":[
        "tgn:7108552",
        "tgn:7003669",
        "tgn:1000003",
        "tgn:7000084",
        "tgn:7029392"
    ],
    "tgn:id":7108552,
    "tgn:name":"Rabenstein",
    "tgn:placetype":[
        "aat:300008777"
    ]
},
  "bbox": [],
  "geometry": {"coordinates":[12.616667,47.783333],"type":"Point"}
}