{
  "id": 7534194,
  "type": "Feature",
  "properties": {
    "tgn:hierarchy":[
        "tgn:7534194",
        "tgn:7001242",
        "tgn:7001311",
        "tgn:7016833",
        "tgn:7029392"
    ],
    "tgn:id":7534194,
    "tgn:name:en":"Ma\u1e29daf, W\u0101d\u012b al",
    "tgn:placetype":[
        "aat:300379998"
    ]
},
  "bbox": [],
  "geometry": {"coordinates":[33.607148,25.733488],"type":"Point"}
}