{
  "id": 2498120,
  "type": "Feature",
  "properties": {
    "tgn:hierarchy":[
        "tgn:2498120",
        "tgn:1000001",
        "tgn:2001737",
        "tgn:7012149",
        "tgn:7007712",
        "tgn:7029392"
    ],
    "tgn:id":2498120,
    "tgn:name":"Mays Lake",
    "tgn:placetype":[
        "aat:300006191"
    ]
},
  "bbox": [],
  "geometry": {"coordinates":[-80.1667,34.5667],"type":"Point"}
}