{
  "id": 7593877,
  "type": "Feature",
  "properties": {
    "tgn:hierarchy":[
        "tgn:7593877",
        "tgn:1000003",
        "tgn:7006413",
        "tgn:7029392"
    ],
    "tgn:id":7593877,
    "tgn:name":"Vratsa",
    "tgn:placetype":[
        "aat:300387064",
        "aat:300000774"
    ]
},
  "bbox": [],
  "geometry": {"coordinates":[23.816,43.416],"type":"Point"}
}