{
  "id": 1125600,
  "type": "Feature",
  "properties": {
    "tgn:hierarchy":[
        "tgn:1125600",
        "tgn:7016675",
        "tgn:1000004",
        "tgn:7000896",
        "tgn:1000120",
        "tgn:7029392"
    ],
    "tgn:id":1125600,
    "tgn:name":"Kishida",
    "tgn:placetype":[
        "aat:300008707"
    ]
},
  "bbox": [],
  "geometry": {"coordinates":[134.45,35.6333],"type":"Point"}
}