{
  "id": 7233652,
  "type": "Feature",
  "properties": {
    "tgn:hierarchy":[
        "tgn:7233652",
        "tgn:4003773",
        "tgn:7001395",
        "tgn:1000003",
        "tgn:1000074",
        "tgn:7029392"
    ],
    "tgn:id":7233652,
    "tgn:name":"Dh\u00edlofon",
    "tgn:placetype":[
        "aat:300008347"
    ]
},
  "bbox": [],
  "geometry": {"coordinates":[22.133333,38.866667],"type":"Point"}
}