{
  "id": 7519177,
  "type": "Feature",
  "properties": {
    "tgn:hierarchy":[
        "tgn:7519177",
        "tgn:1009227",
        "tgn:1000226",
        "tgn:1000006",
        "tgn:7016850",
        "tgn:7029392"
    ],
    "tgn:id":7519177,
    "tgn:name:en":"Brownings Pass",
    "tgn:placetype":[
        "aat:300259572"
    ]
},
  "bbox": [],
  "geometry": {"coordinates":[171.35,-42.95],"type":"Point"}
}