<<<<<<< HEAD
{
  "id": 2258243,
  "type": "Feature",
  "properties": {
    "tgn:hierarchy":[
        "tgn:2258243",
        "tgn:7002659",
        "tgn:1000001",
        "tgn:7012149",
        "tgn:2000059",
        "tgn:7029392"
    ],
    "tgn:id":2258243,
    "tgn:name":"Cotohaga Creek",
    "tgn:placetype":[
        "aat:300008706"
    ]
},
  "bbox": [],
  "geometry": {"coordinates":[-88.2167,32.4167],"type":"Point"}
}
=======
{"geometry":{"type":"Point","coordinates":[-88.216700,32.416700]},"type":"Feature","properties":{"hierarchy":["tgn:2258243","tgn:7002659","tgn:1000001","tgn:7012149","tgn:2000059","tgn:7029392"],"placetype":["aat:300008706"],"id":2258243,"name:xx":"Cotohaga Creek"}}
>>>>>>> 03f74aca74312dbeaf24d7e61306dd6a786dc3d0
