{
  "id": 2140477,
  "type": "Feature",
  "properties": {
    "tgn:hierarchy":[
        "tgn:2140477",
        "tgn:1000001",
        "tgn:1002284",
        "tgn:7012149",
        "tgn:7007568",
        "tgn:7029392"
    ],
    "tgn:id":2140477,
    "tgn:name":"Ausable Point",
    "tgn:placetype":[
        "aat:300008850"
    ]
},
  "bbox": [],
  "geometry": {"coordinates":[-73.4167,44.5667],"type":"Point"}
}