{
  "id": 2624595,
  "type": "Feature",
  "properties": {
    "tgn:hierarchy":[
        "tgn:2624595",
        "tgn:1000001",
        "tgn:1002712",
        "tgn:7012149",
        "tgn:7007159",
        "tgn:7029392"
    ],
    "tgn:id":2624595,
    "tgn:name":"Rock Rimmon",
    "tgn:placetype":[
        "aat:300008798"
    ]
},
  "bbox": [],
  "geometry": {"coordinates":[-73.05,41.4167],"type":"Point"}
}