{
  "id": 2313722,
  "type": "Feature",
  "properties": {
    "tgn:hierarchy":[
        "tgn:2313722",
        "tgn:1002145",
        "tgn:1000001",
        "tgn:7012149",
        "tgn:7007157",
        "tgn:7029392"
    ],
    "tgn:id":2313722,
    "tgn:name":"Elephants Back",
    "tgn:placetype":[
        "aat:300008798"
    ]
},
  "bbox": [],
  "geometry": {"coordinates":[-119.9667,38.6667],"type":"Point"}
}