{
  "id": 7582150,
  "type": "Feature",
  "properties": {
    "tgn:hierarchy":[
        "tgn:7582150",
        "tgn:1000004",
        "tgn:7000198",
        "tgn:7016722",
        "tgn:7029392"
    ],
    "tgn:id":7582150,
    "tgn:name:en":"B\u016brhi",
    "tgn:placetype":[
        "aat:300008347"
    ]
},
  "bbox": [],
  "geometry": {"coordinates":[78.850856,24.534403],"type":"Point"}
}