{
  "id": 2112336,
  "type": "Feature",
  "properties": {
    "tgn:hierarchy":[
        "tgn:2112336",
        "tgn:1000001",
        "tgn:7012149",
        "tgn:2002169",
        "tgn:7007919",
        "tgn:7029392"
    ],
    "tgn:id":2112336,
    "tgn:name":"Hubbard Springs",
    "tgn:placetype":[
        "aat:300008347"
    ]
},
  "bbox": [],
  "geometry": {"coordinates":[-83.2167,36.7167],"type":"Point"}
}