{
  "id": 2557958,
  "type": "Feature",
  "properties": {
    "tgn:hierarchy":[
        "tgn:2557958",
        "tgn:1000001",
        "tgn:2001416",
        "tgn:7012149",
        "tgn:7007526",
        "tgn:7029392"
    ],
    "tgn:id":2557958,
    "tgn:name":"Old Tikaboo Spring",
    "tgn:placetype":[
        "aat:300008697"
    ]
},
  "bbox": [],
  "geometry": {"coordinates":[-115.7333,37.5333],"type":"Point"}
}