{
  "id": 2352899,
  "type": "Feature",
  "properties": {
    "tgn:hierarchy":[
        "tgn:2352899",
        "tgn:1000001",
        "tgn:7012149",
        "tgn:7007157",
        "tgn:1002857",
        "tgn:7029392"
    ],
    "tgn:id":2352899,
    "tgn:name":"Gocke Valley",
    "tgn:placetype":[
        "aat:300386845"
    ]
},
  "bbox": [],
  "geometry": {"coordinates":[-116.75,34.2167],"type":"Point"}
}