{
  "id": 7594257,
  "type": "Feature",
  "properties": {
    "tgn:hierarchy":[
        "tgn:7594257",
        "tgn:7002445",
        "tgn:1000003",
        "tgn:7011961",
        "tgn:7008591",
        "tgn:7029392"
    ],
    "tgn:id":7594257,
    "tgn:name":"Old Warren",
    "tgn:placetype":[
        "aat:300008347",
        "aat:300387007",
        "aat:300167671",
        "aat:300006911",
        "aat:300019279"
    ]
},
  "bbox": [],
  "geometry": {"coordinates":[-2.59,50.68],"type":"Point"}
}