{
  "id": 2724380,
  "type": "Feature",
  "properties": {
    "tgn:hierarchy":[
        "tgn:2724380",
        "tgn:2002137",
        "tgn:1000001",
        "tgn:7012149",
        "tgn:7007919",
        "tgn:7029392"
    ],
    "tgn:id":2724380,
    "tgn:name":"Tom Mountain",
    "tgn:placetype":[
        "aat:300008798"
    ]
},
  "bbox": [],
  "geometry": {"coordinates":[-78.6667,37.9667],"type":"Point"}
}