{
  "id": 7577949,
  "type": "Feature",
  "properties": {
    "tgn:hierarchy":[
        "tgn:7577949",
        "tgn:1000004",
        "tgn:7000198",
        "tgn:7000799",
        "tgn:7029392"
    ],
    "tgn:id":7577949,
    "tgn:name:en":"Kumdok",
    "tgn:placetype":[
        "aat:300008347"
    ]
},
  "bbox": [],
  "geometry": {"coordinates":[78.190137,33.5213],"type":"Point"}
}