{
  "id": 7230246,
  "type": "Feature",
  "properties": {
    "tgn:hierarchy":[
        "tgn:7230246",
        "tgn:7002745",
        "tgn:7017076",
        "tgn:1000003",
        "tgn:1000074",
        "tgn:7029392"
    ],
    "tgn:id":7230246,
    "tgn:name":"Kam\u00edla",
    "tgn:placetype":[
        "aat:300008777"
    ]
},
  "bbox": [],
  "geometry": {"coordinates":[23.133333,36.533333],"type":"Point"}
}