{
  "id": 2622895,
  "type": "Feature",
  "properties": {
    "tgn:hierarchy":[
        "tgn:2622895",
        "tgn:1000001",
        "tgn:7012149",
        "tgn:7007157",
        "tgn:7029392"
    ],
    "tgn:id":2622895,
    "tgn:name":"Robinson Ravine",
    "tgn:placetype":[
        "aat:300008761"
    ]
},
  "bbox": [],
  "geometry": {"coordinates":[-121.35,39.4333],"type":"Point"}
}