{
  "id": 1063502,
  "type": "Feature",
  "properties": {
    "tgn:hierarchy":[
        "tgn:1063502",
        "tgn:1000003",
        "tgn:7003781",
        "tgn:1000097",
        "tgn:7029392"
    ],
    "tgn:id":1063502,
    "tgn:name":"Rekarne",
    "tgn:placetype":[
        "aat:300008347"
    ]
},
  "bbox": [],
  "geometry": {"coordinates":[16.3333,59.4333],"type":"Point"}
}