{
  "id": 7154349,
  "type": "Feature",
  "properties": {
    "tgn:hierarchy":[
        "tgn:7154349",
        "tgn:7003669",
        "tgn:1000003",
        "tgn:7000084",
        "tgn:7029392"
    ],
    "tgn:id":7154349,
    "tgn:name":"Kapflhof",
    "tgn:placetype":[
        "aat:300000206"
    ]
},
  "bbox": [],
  "geometry": {"coordinates":[12.683333,48.983333],"type":"Point"}
}