{
  "id": 7185589,
  "type": "Feature",
  "properties": {
    "tgn:hierarchy":[
        "tgn:7185589",
        "tgn:7003669",
        "tgn:1000003",
        "tgn:7000084",
        "tgn:7029392"
    ],
    "tgn:id":7185589,
    "tgn:name":"G\u00f6pperl",
    "tgn:placetype":[
        "aat:300000206"
    ]
},
  "bbox": [],
  "geometry": {"coordinates":[12.733333,48.133333],"type":"Point"}
}