{
  "id": 2263036,
  "type": "Feature",
  "properties": {
    "tgn:hierarchy":[
        "tgn:2263036",
        "tgn:1000001",
        "tgn:7012149",
        "tgn:1002425",
        "tgn:7007919",
        "tgn:7029392"
    ],
    "tgn:id":2263036,
    "tgn:name":"Cowie Corner",
    "tgn:placetype":[
        "aat:300008347"
    ]
},
  "bbox": [],
  "geometry": {"coordinates":[-77.5667,36.7667],"type":"Point"}
}