{
  "id": 2464063,
  "type": "Feature",
  "properties": {
    "tgn:hierarchy":[
        "tgn:2464063",
        "tgn:1000001",
        "tgn:7012149",
        "tgn:1003004",
        "tgn:7007252",
        "tgn:7029392"
    ],
    "tgn:id":2464063,
    "tgn:name":"Locust Creek",
    "tgn:placetype":[
        "aat:300008706"
    ]
},
  "bbox": [],
  "geometry": {"coordinates":[-84.9833,39.75],"type":"Point"}
}