<<<<<<< HEAD
{
  "id": 2255137,
  "type": "Feature",
  "properties": {
    "tgn:hierarchy":[
        "tgn:2255137",
        "tgn:1000001",
        "tgn:7012149",
        "tgn:2001898",
        "tgn:7007825",
        "tgn:7029392"
    ],
    "tgn:id":2255137,
    "tgn:name":"Cooper Hollow",
    "tgn:placetype":[
        "aat:300008761"
    ]
},
  "bbox": [],
  "geometry": {"coordinates":[-84.1,35.5],"type":"Point"}
}
=======
{"geometry":{"type":"Point","coordinates":[-84.100000,35.500000]},"type":"Feature","properties":{"hierarchy":["tgn:2255137","tgn:1000001","tgn:7012149","tgn:2001898","tgn:7007825","tgn:7029392"],"placetype":["aat:300008761"],"id":2255137,"name:xx":"Cooper Hollow"}}
>>>>>>> 03f74aca74312dbeaf24d7e61306dd6a786dc3d0
