{
  "id": 7317946,
  "type": "Feature",
  "properties": {
    "tgn:hierarchy":[
        "tgn:7317946",
        "tgn:1001692",
        "tgn:1000049",
        "tgn:1000002",
        "tgn:7029392"
    ],
    "tgn:id":7317946,
    "tgn:name":"Cipreses, Cerro",
    "tgn:placetype":[
        "aat:300008777"
    ]
},
  "bbox": [],
  "geometry": {"coordinates":[-72.416667,-38.35],"type":"Point"}
}