{
  "id": 2662100,
  "type": "Feature",
  "properties": {
    "tgn:hierarchy":[
        "tgn:2662100",
        "tgn:1000001",
        "tgn:7012149",
        "tgn:1002926",
        "tgn:7007568",
        "tgn:7029392"
    ],
    "tgn:id":2662100,
    "tgn:name":"Sicans Pond",
    "tgn:placetype":[
        "aat:300008680"
    ]
},
  "bbox": [],
  "geometry": {"coordinates":[-74.8333,41.65],"type":"Point"}
}