{
  "id": 2581863,
  "type": "Feature",
  "properties": {
    "tgn:hierarchy":[
        "tgn:2581863",
        "tgn:1000001",
        "tgn:1002340",
        "tgn:7012149",
        "tgn:7007526",
        "tgn:7029392"
    ],
    "tgn:id":2581863,
    "tgn:name":"Pine Basin",
    "tgn:placetype":[
        "aat:300386845"
    ]
},
  "bbox": [],
  "geometry": {"coordinates":[-119.85,38.9667],"type":"Point"}
}