{
  "id": 7317439,
  "type": "Feature",
  "properties": {
    "tgn:hierarchy":[
        "tgn:7317439",
        "tgn:1001768",
        "tgn:1000049",
        "tgn:1000002",
        "tgn:7029392"
    ],
    "tgn:id":7317439,
    "tgn:name":"Comunidad Quebrada de Herrera",
    "tgn:placetype":[
        "aat:300387200"
    ]
},
  "bbox": [],
  "geometry": {"coordinates":[-70.766667,-32.666667],"type":"Point"}
}