{
  "id": 2654893,
  "type": "Feature",
  "properties": {
    "tgn:hierarchy":[
        "tgn:2654893",
        "tgn:1000001",
        "tgn:1002753",
        "tgn:7012149",
        "tgn:7007828",
        "tgn:7029392"
    ],
    "tgn:id":2654893,
    "tgn:name":"Shalney Branch",
    "tgn:placetype":[
        "aat:300008699"
    ]
},
  "bbox": [],
  "geometry": {"coordinates":[-72.4167,44.7333],"type":"Point"}
}