{
  "id": 2040981,
  "type": "Feature",
  "properties": {
    "tgn:hierarchy":[
        "tgn:2040981",
        "tgn:1000001",
        "tgn:7012149",
        "tgn:2000820",
        "tgn:7007255",
        "tgn:7029392"
    ],
    "tgn:id":2040981,
    "tgn:name":"Redhouse",
    "tgn:placetype":[
        "aat:300008347"
    ]
},
  "bbox": [],
  "geometry": {"coordinates":[-84.2667,37.8167],"type":"Point"}
}