{
  "id": 2457528,
  "type": "Feature",
  "properties": {
    "tgn:hierarchy":[
        "tgn:2457528",
        "tgn:1000001",
        "tgn:7012149",
        "tgn:1002794",
        "tgn:7007708",
        "tgn:7029392"
    ],
    "tgn:id":2457528,
    "tgn:name":"Little Luckiamute River",
    "tgn:placetype":[
        "aat:300008707"
    ]
},
  "bbox": [],
  "geometry": {"coordinates":[-123.6167,44.8667],"type":"Point"}
}