{
  "id": 7308120,
  "type": "Feature",
  "properties": {
    "tgn:hierarchy":[
        "tgn:7308120",
        "tgn:1001702",
        "tgn:1000049",
        "tgn:1000002",
        "tgn:7029392"
    ],
    "tgn:id":7308120,
    "tgn:name":"Medio, Isla del",
    "tgn:placetype":[
        "aat:300008791"
    ]
},
  "bbox": [],
  "geometry": {"coordinates":[-75.083333,-51.516667],"type":"Point"}
}