{
  "id": 2612562,
  "type": "Feature",
  "properties": {
    "tgn:hierarchy":[
        "tgn:2612562",
        "tgn:1000001",
        "tgn:7012149",
        "tgn:7007713",
        "tgn:7029392"
    ],
    "tgn:id":2612562,
    "tgn:name":"Redbird Canyon",
    "tgn:placetype":[
        "aat:300008761"
    ]
},
  "bbox": [],
  "geometry": {"coordinates":[-103.9167,43.9833],"type":"Point"}
}