{
  "id": 7383864,
  "type": "Feature",
  "properties": {
    "tgn:hierarchy":[
        "tgn:7383864",
        "tgn:7005581",
        "tgn:1000001",
        "tgn:7005560",
        "tgn:7029392"
    ],
    "tgn:id":7383864,
    "tgn:name":"Nahu\u00e9rachic",
    "tgn:placetype":[
        "aat:300008347"
    ]
},
  "bbox": [],
  "geometry": {"coordinates":[-108.083333,29.166667],"type":"Point"}
}