{
  "id": 1048516,
  "type": "Feature",
  "properties": {
    "tgn:hierarchy":[
        "tgn:1048516",
        "tgn:7003659",
        "tgn:1000003",
        "tgn:1000088",
        "tgn:7029392"
    ],
    "tgn:id":1048516,
    "tgn:name":"Eidsvoll",
    "tgn:placetype":[
        "aat:300008347",
        "aat:300387320",
        "aat:300008375"
    ]
},
  "bbox": [],
  "geometry": {"coordinates":[11.2333,60.3167],"type":"Point"}
}