{
  "id": 1125225,
  "type": "Feature",
  "properties": {
    "tgn:hierarchy":[
        "tgn:1125225",
        "tgn:1000004",
        "tgn:7029392"
    ],
    "tgn:id":1125225,
    "tgn:name":"Jordan",
    "tgn:placetype":[
        "aat:300008707"
    ]
},
  "bbox": [],
  "geometry": {"coordinates":[35.5833,31.75],"type":"Point"}
}