{
  "id": 7350902,
  "type": "Feature",
  "properties": {
    "tgn:hierarchy":[
        "tgn:7350902",
        "tgn:7005584",
        "tgn:1000001",
        "tgn:7005560",
        "tgn:7029392"
    ],
    "tgn:id":7350902,
    "tgn:name":"Arag\u00f3n",
    "tgn:placetype":[
        "aat:300008347"
    ]
},
  "bbox": [],
  "geometry": {"coordinates":[-101.35,20.116667],"type":"Point"}
}