{
  "id": 2074380,
  "type": "Feature",
  "properties": {
    "tgn:hierarchy":[
        "tgn:2074380",
        "tgn:1000001",
        "tgn:7012149",
        "tgn:1002403",
        "tgn:7007709",
        "tgn:7029392"
    ],
    "tgn:id":2074380,
    "tgn:name":"Drum Hill",
    "tgn:placetype":[
        "aat:300008347",
        "aat:300387210"
    ]
},
  "bbox": [],
  "geometry": {"coordinates":[-76.7167,36.5333],"type":"Point"}
}