{
  "id": 7589124,
  "type": "Feature",
  "properties": {
    "tgn:hierarchy":[
        "tgn:7589124",
        "tgn:1000004",
        "tgn:7000198",
        "tgn:7000799",
        "tgn:7029392"
    ],
    "tgn:id":7589124,
    "tgn:name:en":"Khappi",
    "tgn:placetype":[
        "aat:300008347"
    ]
},
  "bbox": [],
  "geometry": {"coordinates":[73.9125,34.334722],"type":"Point"}
}