{
  "id": 2413714,
  "type": "Feature",
  "properties": {
    "tgn:hierarchy":[
        "tgn:2413714",
        "tgn:1000001",
        "tgn:7012149",
        "tgn:1002751",
        "tgn:7007568",
        "tgn:7029392"
    ],
    "tgn:id":2413714,
    "tgn:name":"Irish Ditch",
    "tgn:placetype":[
        "aat:300006075"
    ]
},
  "bbox": [],
  "geometry": {"coordinates":[-74.3667,41.3333],"type":"Point"}
}