{
  "id": 2122231,
  "type": "Feature",
  "properties": {
    "tgn:hierarchy":[
        "tgn:2122231",
        "tgn:1000001",
        "tgn:7012149",
        "tgn:2002355",
        "tgn:7007922",
        "tgn:7029392"
    ],
    "tgn:id":2122231,
    "tgn:name":"Rhine",
    "tgn:placetype":[
        "aat:300008347"
    ]
},
  "bbox": [],
  "geometry": {"coordinates":[-87.95,43.85],"type":"Point"}
}