{
  "id": 2710407,
  "type": "Feature",
  "properties": {
    "tgn:hierarchy":[
        "tgn:2710407",
        "tgn:1000001",
        "tgn:7012149",
        "tgn:2001067",
        "tgn:7007521",
        "tgn:7029392"
    ],
    "tgn:id":2710407,
    "tgn:name":"Tamarack Bay",
    "tgn:placetype":[
        "aat:300132316"
    ]
},
  "bbox": [],
  "geometry": {"coordinates":[-92.05,47.8833],"type":"Point"}
}