{
  "id": 7540517,
  "type": "Feature",
  "properties": {
    "tgn:hierarchy":[
        "tgn:7540517",
        "tgn:7001242",
        "tgn:1001075",
        "tgn:7016833",
        "tgn:7029392"
    ],
    "tgn:id":7540517,
    "tgn:name:en":"Minsh\u0101t Bish\u0101rah",
    "tgn:placetype":[
        "aat:300008347"
    ]
},
  "bbox": [],
  "geometry": {"coordinates":[30.598825,30.816382],"type":"Point"}
}