{
  "id": 1011461,
  "type": "Feature",
  "properties": {
    "tgn:hierarchy":[
        "tgn:1011461",
        "tgn:7003502",
        "tgn:7003478",
        "tgn:1000003",
        "tgn:1000078",
        "tgn:7029392"
    ],
    "tgn:id":1011461,
    "tgn:name":"Inishowen Head",
    "tgn:placetype":[
        "aat:300387499"
    ]
},
  "bbox": [],
  "geometry": {"coordinates":[-6.9333,55.15],"type":"Point"}
}