{
  "id": 7223477,
  "type": "Feature",
  "properties": {
    "tgn:hierarchy":[
        "tgn:7223477",
        "tgn:7002690",
        "tgn:7012056",
        "tgn:1000003",
        "tgn:1000074",
        "tgn:7029392"
    ],
    "tgn:id":7223477,
    "tgn:name":"Orth\u00ed P\u00e9tra",
    "tgn:placetype":[
        "aat:300008777"
    ]
},
  "bbox": [],
  "geometry": {"coordinates":[24.95,35.083333],"type":"Point"}
}