{
  "id": 2540611,
  "type": "Feature",
  "properties": {
    "tgn:hierarchy":[
        "tgn:2540611",
        "tgn:2000943",
        "tgn:1000001",
        "tgn:7012149",
        "tgn:7007520",
        "tgn:7029392"
    ],
    "tgn:id":2540611,
    "tgn:name":"Newton Lake",
    "tgn:placetype":[
        "aat:300008680"
    ]
},
  "bbox": [],
  "geometry": {"coordinates":[-85.9333,46.55],"type":"Point"}
}