{
  "id": 2137992,
  "type": "Feature",
  "properties": {
    "tgn:hierarchy":[
        "tgn:2137992",
        "tgn:1000001",
        "tgn:7012149",
        "tgn:7007157",
        "tgn:7029392"
    ],
    "tgn:id":2137992,
    "tgn:name":"Arrowhead Mountain",
    "tgn:placetype":[
        "aat:300008798"
    ]
},
  "bbox": [],
  "geometry": {"coordinates":[-122.3833,38.2667],"type":"Point"}
}