{
  "id": 2622886,
  "type": "Feature",
  "properties": {
    "tgn:hierarchy":[
        "tgn:2622886",
        "tgn:1000001",
        "tgn:7012149",
        "tgn:2001236",
        "tgn:7007523",
        "tgn:7029392"
    ],
    "tgn:id":2622886,
    "tgn:name":"Robinson Pond",
    "tgn:placetype":[
        "aat:300008680"
    ]
},
  "bbox": [],
  "geometry": {"coordinates":[-90.8833,37.35],"type":"Point"}
}