{
  "id": 1100925,
  "type": "Feature",
  "properties": {
    "tgn:hierarchy":[
        "tgn:1100925",
        "tgn:7001242",
        "tgn:7000607",
        "tgn:1000172",
        "tgn:7029392"
    ],
    "tgn:id":1100925,
    "tgn:name":"Marble Arch",
    "tgn:placetype":[
        "aat:300006958"
    ]
},
  "bbox": [],
  "geometry": {"coordinates":[18.4833,30.45],"type":"Point"}
}