{
  "id": 7261732,
  "type": "Feature",
  "properties": {
    "tgn:hierarchy":[
        "tgn:7261732",
        "tgn:1000003",
        "tgn:7003624",
        "tgn:7016845",
        "tgn:7029392"
    ],
    "tgn:id":7261732,
    "tgn:name:nl":"De Sneider",
    "tgn:placetype":[
        "aat:300387200"
    ]
},
  "bbox": [],
  "geometry": {"coordinates":[4.516667,51.483333],"type":"Point"}
}