{
  "id": 7037068,
  "type": "Feature",
  "properties": {
    "tgn:hierarchy":[
        "tgn:7037068",
        "tgn:1003450",
        "tgn:7007850",
        "tgn:1000003",
        "tgn:1000080",
        "tgn:7029392"
    ],
    "tgn:id":7037068,
    "tgn:name":"Vigne di Pietra Pertosa",
    "tgn:placetype":[
        "aat:300008347"
    ]
},
  "bbox": [],
  "geometry": {"coordinates":[16.833333,39.383333],"type":"Point"}
}