{
  "id": 2400133,
  "type": "Feature",
  "properties": {
    "tgn:hierarchy":[
        "tgn:2400133",
        "tgn:2001468",
        "tgn:1000001",
        "tgn:7012149",
        "tgn:7007709",
        "tgn:7029392"
    ],
    "tgn:id":2400133,
    "tgn:name":"Horse Creek",
    "tgn:placetype":[
        "aat:300008706"
    ]
},
  "bbox": [],
  "geometry": {"coordinates":[-82.0167,36.1167],"type":"Point"}
}