<<<<<<< HEAD
{
  "id": 2158295,
  "type": "Feature",
  "properties": {
    "tgn:hierarchy":[
        "tgn:2158295",
        "tgn:1000001",
        "tgn:1002260",
        "tgn:7012149",
        "tgn:7007920",
        "tgn:7029392"
    ],
    "tgn:id":2158295,
    "tgn:name":"Beaver Spring",
    "tgn:placetype":[
        "aat:300008697"
    ]
},
  "bbox": [],
  "geometry": {"coordinates":[-120.25,47.95],"type":"Point"}
}
=======
{"geometry":{"type":"Point","coordinates":[-120.250000,47.950000]},"type":"Feature","properties":{"hierarchy":["tgn:2158295","tgn:1000001","tgn:1002260","tgn:7012149","tgn:7007920","tgn:7029392"],"placetype":["aat:300008697"],"id":2158295,"name:xx":"Beaver Spring"}}
>>>>>>> 03f74aca74312dbeaf24d7e61306dd6a786dc3d0
