{
  "id": 2230401,
  "type": "Feature",
  "properties": {
    "tgn:hierarchy":[
        "tgn:2230401",
        "tgn:1000001",
        "tgn:2002134",
        "tgn:7012149",
        "tgn:7007828",
        "tgn:7029392"
    ],
    "tgn:id":2230401,
    "tgn:name":"Center Brook",
    "tgn:placetype":[
        "aat:300008699"
    ]
},
  "bbox": [],
  "geometry": {"coordinates":[-72.2833,44.0333],"type":"Point"}
}