{
  "id": 2193753,
  "type": "Feature",
  "properties": {
    "tgn:hierarchy":[
        "tgn:2193753",
        "tgn:1000001",
        "tgn:7012149",
        "tgn:2000961",
        "tgn:7007520",
        "tgn:7029392"
    ],
    "tgn:id":2193753,
    "tgn:name":"Brewster Lake",
    "tgn:placetype":[
        "aat:300008680"
    ]
},
  "bbox": [],
  "geometry": {"coordinates":[-85.5833,44.5667],"type":"Point"}
}