{
  "id": 7399643,
  "type": "Feature",
  "properties": {
    "tgn:hierarchy":[
        "tgn:7399643",
        "tgn:1000001",
        "tgn:7005593",
        "tgn:7005560",
        "tgn:7029392"
    ],
    "tgn:id":7399643,
    "tgn:name":"El Garabatillo, Arroyo",
    "tgn:placetype":[
        "aat:300008699"
    ]
},
  "bbox": [],
  "geometry": {"coordinates":[-100.268056,20.883333],"type":"Point"}
}