{
  "id": 2323496,
  "type": "Feature",
  "properties": {
    "tgn:hierarchy":[
        "tgn:2323496",
        "tgn:1000001",
        "tgn:7012149",
        "tgn:2000975",
        "tgn:7007520",
        "tgn:7029392"
    ],
    "tgn:id":2323496,
    "tgn:name":"Farquar Lake",
    "tgn:placetype":[
        "aat:300008680"
    ]
},
  "bbox": [],
  "geometry": {"coordinates":[-87.4833,46.2333],"type":"Point"}
}