{
  "id": 7144275,
  "type": "Feature",
  "properties": {
    "tgn:hierarchy":[
        "tgn:7144275",
        "tgn:7000096",
        "tgn:1000003",
        "tgn:7000084",
        "tgn:7029392"
    ],
    "tgn:id":7144275,
    "tgn:name":"Krachtsheide",
    "tgn:placetype":[
        "aat:300000206"
    ]
},
  "bbox": [],
  "geometry": {"coordinates":[14.15,52.233333],"type":"Point"}
}