{
  "id": 2100123,
  "type": "Feature",
  "properties": {
    "tgn:hierarchy":[
        "tgn:2100123",
        "tgn:1000001",
        "tgn:7012149",
        "tgn:2001859",
        "tgn:7007825",
        "tgn:7029392"
    ],
    "tgn:id":2100123,
    "tgn:name":"Locust Grove",
    "tgn:placetype":[
        "aat:300008347",
        "aat:300387210"
    ]
},
  "bbox": [],
  "geometry": {"coordinates":[-89.25,36.1667],"type":"Point"}
}