{
  "id": 7037809,
  "type": "Feature",
  "properties": {
    "tgn:hierarchy":[
        "tgn:7037809",
        "tgn:7003248",
        "tgn:1000003",
        "tgn:7010380",
        "tgn:1000080",
        "tgn:7029392"
    ],
    "tgn:id":7037809,
    "tgn:name":"Vecchio, Porto",
    "tgn:placetype":[
        "aat:300008678"
    ]
},
  "bbox": [],
  "geometry": {"coordinates":[16.866667,41.116667],"type":"Point"}
}