{
  "id": 2472582,
  "type": "Feature",
  "properties": {
    "tgn:hierarchy":[
        "tgn:2472582",
        "tgn:1000001",
        "tgn:7012149",
        "tgn:1002787",
        "tgn:7007523",
        "tgn:7029392"
    ],
    "tgn:id":2472582,
    "tgn:name":"Love Lake",
    "tgn:placetype":[
        "aat:300006191"
    ]
},
  "bbox": [],
  "geometry": {"coordinates":[-91.2167,39.45],"type":"Point"}
}