{
  "id": 2490438,
  "type": "Feature",
  "properties": {
    "tgn:hierarchy":[
        "tgn:2490438",
        "tgn:7023902",
        "tgn:1000001",
        "tgn:7012149",
        "tgn:7007249",
        "tgn:7029392"
    ],
    "tgn:id":2490438,
    "tgn:name":"Manienie Gulch",
    "tgn:placetype":[
        "aat:300008761"
    ]
},
  "bbox": [],
  "geometry": {"coordinates":[-155.4167,19.95],"type":"Point"}
}