{
  "id": 7011466,
  "type": "Feature",
  "properties": {
    "tgn:hierarchy":[
        "tgn:7011466",
        "tgn:7011506",
        "tgn:1000003",
        "tgn:1001780",
        "tgn:7029392"
    ],
    "tgn:id":7011466,
    "tgn:name":"Hlubok\u00e1 nad Vltava",
    "tgn:placetype":[
        "aat:300008347"
    ]
},
  "bbox": [],
  "geometry": {"coordinates":[14.45,49.0667],"type":"Point"}
}