{
  "id": 2137248,
  "type": "Feature",
  "properties": {
    "tgn:hierarchy":[
        "tgn:2137248",
        "tgn:1000001",
        "tgn:7012149",
        "tgn:2001454",
        "tgn:7007566",
        "tgn:7029392"
    ],
    "tgn:id":2137248,
    "tgn:name":"Armington Mine",
    "tgn:placetype":[
        "aat:300000390"
    ]
},
  "bbox": [],
  "geometry": {"coordinates":[-106.1167,35.4833],"type":"Point"}
}