{
  "id": 7584573,
  "type": "Feature",
  "properties": {
    "tgn:hierarchy":[
        "tgn:7584573",
        "tgn:1000004",
        "tgn:7000198",
        "tgn:1001894",
        "tgn:7029392"
    ],
    "tgn:id":7584573,
    "tgn:name:en":"Harbanspur",
    "tgn:placetype":[
        "aat:300008347"
    ]
},
  "bbox": [],
  "geometry": {"coordinates":[78.241539,24.103138],"type":"Point"}
}