{
  "id": 7107095,
  "type": "Feature",
  "properties": {
    "tgn:hierarchy":[
        "tgn:7107095",
        "tgn:1000003",
        "tgn:7003676",
        "tgn:7000084",
        "tgn:7029392"
    ],
    "tgn:id":7107095,
    "tgn:name":"Schlamins-Berge",
    "tgn:placetype":[
        "aat:300008777"
    ]
},
  "bbox": [],
  "geometry": {"coordinates":[10.683333,52.866667],"type":"Point"}
}