{
  "id": 2714536,
  "type": "Feature",
  "properties": {
    "tgn:hierarchy":[
        "tgn:2714536",
        "tgn:1000001",
        "tgn:7012149",
        "tgn:2001849",
        "tgn:7007825",
        "tgn:7029392"
    ],
    "tgn:id":2714536,
    "tgn:name":"Templin Pond",
    "tgn:placetype":[
        "aat:300008680"
    ]
},
  "bbox": [],
  "geometry": {"coordinates":[-83.7333,36.5333],"type":"Point"}
}