{
  "id": 1092829,
  "type": "Feature",
  "properties": {
    "tgn:hierarchy":[
        "tgn:1092829",
        "tgn:7001242",
        "tgn:7017576",
        "tgn:1000193",
        "tgn:7029392"
    ],
    "tgn:id":1092829,
    "tgn:name":"Armadale",
    "tgn:placetype":[
        "aat:300008347"
    ]
},
  "bbox": [],
  "geometry": {"coordinates":[27.95,-26.2833],"type":"Point"}
}