{
  "id": 1124147,
  "type": "Feature",
  "properties": {
    "tgn:hierarchy":[
        "tgn:1124147",
        "tgn:1000003",
        "tgn:7003122",
        "tgn:1000080",
        "tgn:7029392"
    ],
    "tgn:id":1124147,
    "tgn:name":"Gela",
    "tgn:placetype":[
        "aat:300008707",
        "aat:300008699"
    ]
},
  "bbox": [],
  "geometry": {"coordinates":[14.25,37.05],"type":"Point"}
}