{
  "id": 2702766,
  "type": "Feature",
  "properties": {
    "tgn:hierarchy":[
        "tgn:2702766",
        "tgn:1000001",
        "tgn:7012149",
        "tgn:7007157",
        "tgn:1002856",
        "tgn:7029392"
    ],
    "tgn:id":2702766,
    "tgn:name":"Sulphur Spring",
    "tgn:placetype":[
        "aat:300008697"
    ]
},
  "bbox": [],
  "geometry": {"coordinates":[-120.7667,36.2833],"type":"Point"}
}