{
  "id": 2729212,
  "type": "Feature",
  "properties": {
    "tgn:hierarchy":[
        "tgn:2729212",
        "tgn:1000001",
        "tgn:7012149",
        "tgn:2000877",
        "tgn:7007256",
        "tgn:7029392"
    ],
    "tgn:id":2729212,
    "tgn:name":"Trinity Canal",
    "tgn:placetype":[
        "aat:300006075"
    ]
},
  "bbox": [],
  "geometry": {"coordinates":[-91.4333,30.35],"type":"Point"}
}