{
  "id": 7515592,
  "type": "Feature",
  "properties": {
    "tgn:hierarchy":[
        "tgn:7515592",
        "tgn:1009227",
        "tgn:1000226",
        "tgn:7016822",
        "tgn:1000006",
        "tgn:7029392"
    ],
    "tgn:id":7515592,
    "tgn:name:en":"Mouat, Lake",
    "tgn:placetype":[
        "aat:300008680"
    ]
},
  "bbox": [],
  "geometry": {"coordinates":[167.016667,-46.016667],"type":"Point"}
}