{
  "id": 7501416,
  "type": "Feature",
  "properties": {
    "tgn:hierarchy":[
        "tgn:7501416",
        "tgn:7488858",
        "tgn:1000004",
        "tgn:1000141",
        "tgn:7029392"
    ],
    "tgn:id":7501416,
    "tgn:name":"Xinxiang Guoxiao",
    "tgn:placetype":[
        "aat:300006495"
    ]
},
  "bbox": [],
  "geometry": {"coordinates":[120.869722,23.64],"type":"Point"}
}