{
  "id": 2561694,
  "type": "Feature",
  "properties": {
    "tgn:hierarchy":[
        "tgn:2561694",
        "tgn:1002140",
        "tgn:1000001",
        "tgn:7012149",
        "tgn:7007520",
        "tgn:7029392"
    ],
    "tgn:id":2561694,
    "tgn:name":"Osterhout Lake",
    "tgn:placetype":[
        "aat:300008680"
    ]
},
  "bbox": [],
  "geometry": {"coordinates":[-86.0333,42.4333],"type":"Point"}
}