{
  "id": 2105114,
  "type": "Feature",
  "properties": {
    "tgn:hierarchy":[
        "tgn:2105114",
        "tgn:1000001",
        "tgn:7012149",
        "tgn:1002980",
        "tgn:7007826",
        "tgn:7029392"
    ],
    "tgn:id":2105114,
    "tgn:name":"Huntsville",
    "tgn:placetype":[
        "aat:300008347"
    ]
},
  "bbox": [],
  "geometry": {"coordinates":[-95.55,30.7167],"type":"Point"}
}