{
  "id": 7189294,
  "type": "Feature",
  "properties": {
    "tgn:hierarchy":[
        "tgn:7189294",
        "tgn:1000003",
        "tgn:7003678",
        "tgn:7000084",
        "tgn:7029392"
    ],
    "tgn:id":7189294,
    "tgn:name":"Eisel-Berg",
    "tgn:placetype":[
        "aat:300008777"
    ]
},
  "bbox": [],
  "geometry": {"coordinates":[8.866667,50.683333],"type":"Point"}
}