{
  "id": 2200946,
  "type": "Feature",
  "properties": {
    "tgn:hierarchy":[
        "tgn:2200946",
        "tgn:1000001",
        "tgn:7012149",
        "tgn:2002167",
        "tgn:7007919",
        "tgn:7029392"
    ],
    "tgn:id":2200946,
    "tgn:name":"Bryant Lakes",
    "tgn:placetype":[
        "aat:300006191"
    ]
},
  "bbox": [],
  "geometry": {"coordinates":[-80.05,36.75],"type":"Point"}
}