{
  "id": 7194458,
  "type": "Feature",
  "properties": {
    "tgn:hierarchy":[
        "tgn:7194458",
        "tgn:7003669",
        "tgn:1000003",
        "tgn:7000084",
        "tgn:7029392"
    ],
    "tgn:id":7194458,
    "tgn:name":"D\u00f6hlau",
    "tgn:placetype":[
        "aat:300008347"
    ]
},
  "bbox": [],
  "geometry": {"coordinates":[11.95,50.283333],"type":"Point"}
}