{
  "id": 2412198,
  "type": "Feature",
  "properties": {
    "tgn:hierarchy":[
        "tgn:2412198",
        "tgn:1000001",
        "tgn:7012149",
        "tgn:2001199",
        "tgn:7007523",
        "tgn:7029392"
    ],
    "tgn:id":2412198,
    "tgn:name":"Indian Spring",
    "tgn:placetype":[
        "aat:300008697"
    ]
},
  "bbox": [],
  "geometry": {"coordinates":[-93.35,37.0833],"type":"Point"}
}