{
  "id": 2625462,
  "type": "Feature",
  "properties": {
    "tgn:hierarchy":[
        "tgn:2625462",
        "tgn:7013349",
        "tgn:1000001",
        "tgn:7012149",
        "tgn:7007708",
        "tgn:7029392"
    ],
    "tgn:id":2625462,
    "tgn:name":"Rockne Gulch",
    "tgn:placetype":[
        "aat:300008761"
    ]
},
  "bbox": [],
  "geometry": {"coordinates":[-118.1167,44.75],"type":"Point"}
}