{
  "id": 2750195,
  "type": "Feature",
  "properties": {
    "tgn:hierarchy":[
        "tgn:2750195",
        "tgn:1000001",
        "tgn:7012149",
        "tgn:2000392",
        "tgn:7007248",
        "tgn:7029392"
    ],
    "tgn:id":2750195,
    "tgn:name":"Walton Lake",
    "tgn:placetype":[
        "aat:300006191"
    ]
},
  "bbox": [],
  "geometry": {"coordinates":[-84.1667,31.0833],"type":"Point"}
}