{
  "id": 7227736,
  "type": "Feature",
  "properties": {
    "tgn:hierarchy":[
        "tgn:7227736",
        "tgn:7002706",
        "tgn:7002705",
        "tgn:1000003",
        "tgn:1000074",
        "tgn:7029392"
    ],
    "tgn:id":7227736,
    "tgn:name":"Kary\u00e1",
    "tgn:placetype":[
        "aat:300008347"
    ]
},
  "bbox": [],
  "geometry": {"coordinates":[21.290556,39.360278],"type":"Point"}
}