<<<<<<< HEAD
{
  "id": 7488795,
  "type": "Feature",
  "properties": {
    "tgn:hierarchy":[
        "tgn:7488795",
        "tgn:1000004",
        "tgn:7467799",
        "tgn:1000141",
        "tgn:7029392"
    ],
    "tgn:id":7488795,
    "tgn:name":"Kulingjiao",
    "tgn:placetype":[
        "aat:300000745"
    ]
},
  "bbox": [],
  "geometry": {"coordinates":[120.565961,24.09261],"type":"Point"}
}
=======
{"geometry":{"type":"Point","coordinates":[120.565961,24.092610]},"type":"Feature","properties":{"hierarchy":["tgn:7488795","tgn:1000004","tgn:7467799","tgn:1000141","tgn:7029392"],"placetype":["aat:300000745"],"id":7488795,"name:xx":"Kulingjiao"}}
>>>>>>> 03f74aca74312dbeaf24d7e61306dd6a786dc3d0
