{
  "id": 1099846,
  "type": "Feature",
  "properties": {
    "tgn:hierarchy":[
        "tgn:1099846",
        "tgn:1000976",
        "tgn:1000004",
        "tgn:7000893",
        "tgn:1000120",
        "tgn:7029392"
    ],
    "tgn:id":1099846,
    "tgn:name":"Nakoso-no-seki-ato",
    "tgn:placetype":[
        "aat:300008347",
        "aat:300167671"
    ]
},
  "bbox": [],
  "geometry": {"coordinates":[140.7667,36.8833],"type":"Point"}
}