<<<<<<< HEAD
{
  "id": 2152687,
  "type": "Feature",
  "properties": {
    "tgn:hierarchy":[
        "tgn:2152687",
        "tgn:1000001",
        "tgn:7012149",
        "tgn:2000519",
        "tgn:7007251",
        "tgn:7029392"
    ],
    "tgn:id":2152687,
    "tgn:name":"Bayou Creek",
    "tgn:placetype":[
        "aat:300008706"
    ]
},
  "bbox": [],
  "geometry": {"coordinates":[-88.8333,37.2167],"type":"Point"}
}
=======
{"geometry":{"type":"Point","coordinates":[-88.833300,37.216700]},"type":"Feature","properties":{"hierarchy":["tgn:2152687","tgn:1000001","tgn:7012149","tgn:2000519","tgn:7007251","tgn:7029392"],"placetype":["aat:300008706"],"id":2152687,"name:xx":"Bayou Creek"}}
>>>>>>> 03f74aca74312dbeaf24d7e61306dd6a786dc3d0
