{
  "id": 2720491,
  "type": "Feature",
  "properties": {
    "tgn:hierarchy":[
        "tgn:2720491",
        "tgn:1000001",
        "tgn:2000469",
        "tgn:7012149",
        "tgn:7007250",
        "tgn:7029392"
    ],
    "tgn:id":2720491,
    "tgn:name":"Thunder Spring",
    "tgn:placetype":[
        "aat:300008697"
    ]
},
  "bbox": [],
  "geometry": {"coordinates":[-115.7833,46.7667],"type":"Point"}
}