{
  "id": 2737993,
  "type": "Feature",
  "properties": {
    "tgn:hierarchy":[
        "tgn:2737993",
        "tgn:2000919",
        "tgn:1000001",
        "tgn:7012149",
        "tgn:7007515",
        "tgn:7029392"
    ],
    "tgn:id":2737993,
    "tgn:name":"Ugh Lake",
    "tgn:placetype":[
        "aat:300008680"
    ]
},
  "bbox": [],
  "geometry": {"coordinates":[-69.55,46.7333],"type":"Point"}
}