{
  "id": 7268834,
  "type": "Feature",
  "properties": {
    "tgn:hierarchy":[
        "tgn:7268834",
        "tgn:7003619",
        "tgn:1000003",
        "tgn:7016845",
        "tgn:7029392"
    ],
    "tgn:id":7268834,
    "tgn:name:nl":"Noordijkerkanaal",
    "tgn:placetype":[
        "aat:300006075"
    ]
},
  "bbox": [],
  "geometry": {"coordinates":[6.55,52.15],"type":"Point"}
}