{
  "id": 2630566,
  "type": "Feature",
  "properties": {
    "tgn:hierarchy":[
        "tgn:2630566",
        "tgn:1000001",
        "tgn:7014352",
        "tgn:7012149",
        "tgn:7007564",
        "tgn:7029392"
    ],
    "tgn:id":2630566,
    "tgn:name":"Round Hill",
    "tgn:placetype":[
        "aat:300008798"
    ]
},
  "bbox": [],
  "geometry": {"coordinates":[-70.9333,42.9333],"type":"Point"}
}