{
  "id": 7553589,
  "type": "Feature",
  "properties": {
    "tgn:hierarchy":[
        "tgn:7553589",
        "tgn:1000004",
        "tgn:7000198",
        "tgn:7016788",
        "tgn:7029392"
    ],
    "tgn:id":7553589,
    "tgn:name:en":"Ratanshahr",
    "tgn:placetype":[
        "aat:300008347"
    ]
},
  "bbox": [],
  "geometry": {"coordinates":[75.538747,28.155833],"type":"Point"}
}