{
  "id": 7121603,
  "type": "Feature",
  "properties": {
    "tgn:hierarchy":[
        "tgn:7121603",
        "tgn:7003669",
        "tgn:1000003",
        "tgn:7000084",
        "tgn:7029392"
    ],
    "tgn:id":7121603,
    "tgn:name":"Pirkenhof",
    "tgn:placetype":[
        "aat:300000206"
    ]
},
  "bbox": [],
  "geometry": {"coordinates":[11.916667,49.283333],"type":"Point"}
}