{
  "id": 7117918,
  "type": "Feature",
  "properties": {
    "tgn:hierarchy":[
        "tgn:7117918",
        "tgn:1000003",
        "tgn:7003678",
        "tgn:7000084",
        "tgn:7029392"
    ],
    "tgn:id":7117918,
    "tgn:name":"Ober Seibertenrod",
    "tgn:placetype":[
        "aat:300008347"
    ]
},
  "bbox": [],
  "geometry": {"coordinates":[9.15,50.583333],"type":"Point"}
}