{
  "id": 7093460,
  "type": "Feature",
  "properties": {
    "tgn:hierarchy":[
        "tgn:7093460",
        "tgn:1000003",
        "tgn:7003682",
        "tgn:7000084",
        "tgn:7029392"
    ],
    "tgn:id":7093460,
    "tgn:name":"Schweifeld",
    "tgn:placetype":[
        "aat:300008347"
    ]
},
  "bbox": [],
  "geometry": {"coordinates":[7.316667,50.633333],"type":"Point"}
}