{
  "id": 7213801,
  "type": "Feature",
  "properties": {
    "tgn:hierarchy":[
        "tgn:7213801",
        "tgn:7003669",
        "tgn:1000003",
        "tgn:7000084",
        "tgn:7029392"
    ],
    "tgn:id":7213801,
    "tgn:name":"Biberhof",
    "tgn:placetype":[
        "aat:300000206"
    ]
},
  "bbox": [],
  "geometry": {"coordinates":[10.75,48.816667],"type":"Point"}
}