{
  "id": 7071449,
  "type": "Feature",
  "properties": {
    "tgn:hierarchy":[
        "tgn:7071449",
        "tgn:7003669",
        "tgn:1000003",
        "tgn:7000084",
        "tgn:7029392"
    ],
    "tgn:id":7071449,
    "tgn:name":"Thiemitz",
    "tgn:placetype":[
        "aat:300008699"
    ]
},
  "bbox": [],
  "geometry": {"coordinates":[11.533333,50.283333],"type":"Point"}
}