{
  "id": 7329153,
  "type": "Feature",
  "properties": {
    "tgn:hierarchy":[
        "tgn:7329153",
        "tgn:7002847",
        "tgn:1001647",
        "tgn:1000003",
        "tgn:1000095",
        "tgn:7029392"
    ],
    "tgn:id":7329153,
    "tgn:name":"Recas",
    "tgn:placetype":[
        "aat:300008347"
    ]
},
  "bbox": [],
  "geometry": {"coordinates":[-3.983333,40.05],"type":"Point"}
}