{
  "id": 7378013,
  "type": "Feature",
  "properties": {
    "tgn:hierarchy":[
        "tgn:7378013",
        "tgn:1000001",
        "tgn:1001960",
        "tgn:7005560",
        "tgn:7029392"
    ],
    "tgn:id":7378013,
    "tgn:name":"Rancho La Polvareda",
    "tgn:placetype":[
        "aat:300000241"
    ]
},
  "bbox": [],
  "geometry": {"coordinates":[-111.216667,30.083333],"type":"Point"}
}