{
  "id": 2470804,
  "type": "Feature",
  "properties": {
    "tgn:hierarchy":[
        "tgn:2470804",
        "tgn:1000001",
        "tgn:7012149",
        "tgn:2001449",
        "tgn:7007566",
        "tgn:7029392"
    ],
    "tgn:id":2470804,
    "tgn:name":"Lost Canyon",
    "tgn:placetype":[
        "aat:300008761"
    ]
},
  "bbox": [],
  "geometry": {"coordinates":[-107.2167,36.6167],"type":"Point"}
}