<<<<<<< HEAD
{
  "id": 2763316,
  "type": "Feature",
  "properties": {
    "tgn:hierarchy":[
        "tgn:2763316",
        "tgn:1000001",
        "tgn:7012149",
        "tgn:2001717",
        "tgn:7007708",
        "tgn:7029392"
    ],
    "tgn:id":2763316,
    "tgn:name":"Wet Horse Creek",
    "tgn:placetype":[
        "aat:300008706"
    ]
},
  "bbox": [],
  "geometry": {"coordinates":[-122.3167,44.3333],"type":"Point"}
}
=======
{"geometry":{"type":"Point","coordinates":[-122.316700,44.333300]},"type":"Feature","properties":{"hierarchy":["tgn:2763316","tgn:1000001","tgn:7012149","tgn:2001717","tgn:7007708","tgn:7029392"],"placetype":["aat:300008706"],"id":2763316,"name:xx":"Wet Horse Creek"}}
>>>>>>> 03f74aca74312dbeaf24d7e61306dd6a786dc3d0
