{
  "id": 2698917,
  "type": "Feature",
  "properties": {
    "tgn:hierarchy":[
        "tgn:2698917",
        "tgn:1000001",
        "tgn:7012149",
        "tgn:2001449",
        "tgn:7007566",
        "tgn:7029392"
    ],
    "tgn:id":2698917,
    "tgn:name":"Strawberry Mine",
    "tgn:placetype":[
        "aat:300000390"
    ]
},
  "bbox": [],
  "geometry": {"coordinates":[-106.1333,36.6333],"type":"Point"}
}