{
  "id": 7575128,
  "type": "Feature",
  "properties": {
    "tgn:hierarchy":[
        "tgn:7575128",
        "tgn:7001819",
        "tgn:1000004",
        "tgn:7000198",
        "tgn:7029392"
    ],
    "tgn:id":7575128,
    "tgn:name:en":"Chia-ya Shan-k'ou",
    "tgn:placetype":[
        "aat:300259572"
    ]
},
  "bbox": [],
  "geometry": {"coordinates":[96.566667,28.816667],"type":"Point"}
}