{
  "id": 1096432,
  "type": "Feature",
  "properties": {
    "tgn:hierarchy":[
        "tgn:1096432",
        "tgn:7000490",
        "tgn:1000006",
        "tgn:7001992",
        "tgn:7029392"
    ],
    "tgn:id":1096432,
    "tgn:name":"Burnie",
    "tgn:placetype":[
        "aat:300008347"
    ]
},
  "bbox": [],
  "geometry": {"coordinates":[145.9167,-41.05],"type":"Point"}
}