{
  "id": 7552922,
  "type": "Feature",
  "properties": {
    "tgn:hierarchy":[
        "tgn:7552922",
        "tgn:1000004",
        "tgn:7000198",
        "tgn:1001895",
        "tgn:7029392"
    ],
    "tgn:id":7552922,
    "tgn:name:en":"Mukabeli",
    "tgn:placetype":[
        "aat:300008347"
    ]
},
  "bbox": [],
  "geometry": {"coordinates":[80.533333,19.116667],"type":"Point"}
}