{
  "id": 2208804,
  "type": "Feature",
  "properties": {
    "tgn:hierarchy":[
        "tgn:2208804",
        "tgn:1000001",
        "tgn:7012149",
        "tgn:2000911",
        "tgn:7007256",
        "tgn:7029392"
    ],
    "tgn:id":2208804,
    "tgn:name":"Burnstown",
    "tgn:placetype":[
        "aat:300008347"
    ]
},
  "bbox": [],
  "geometry": {"coordinates":[-92.9333,31.2667],"type":"Point"}
}