{
  "id": 2408595,
  "type": "Feature",
  "properties": {
    "tgn:hierarchy":[
        "tgn:2408595",
        "tgn:2001726",
        "tgn:1000001",
        "tgn:7012149",
        "tgn:7007712",
        "tgn:7029392"
    ],
    "tgn:id":2408595,
    "tgn:name":"Huttos Pond",
    "tgn:placetype":[
        "aat:300006191"
    ]
},
  "bbox": [],
  "geometry": {"coordinates":[-81.5333,33.7167],"type":"Point"}
}