<<<<<<< HEAD
{
  "id": 2152437,
  "type": "Feature",
  "properties": {
    "tgn:hierarchy":[
        "tgn:2152437",
        "tgn:1000001",
        "tgn:7012149",
        "tgn:2000442",
        "tgn:7007248",
        "tgn:7029392"
    ],
    "tgn:id":2152437,
    "tgn:name":"Bay Pond",
    "tgn:placetype":[
        "aat:300008905"
    ]
},
  "bbox": [],
  "geometry": {"coordinates":[-81.85,31.4667],"type":"Point"}
}
=======
{"geometry":{"type":"Point","coordinates":[-81.850000,31.466700]},"type":"Feature","properties":{"hierarchy":["tgn:2152437","tgn:1000001","tgn:7012149","tgn:2000442","tgn:7007248","tgn:7029392"],"placetype":["aat:300008905"],"id":2152437,"name:xx":"Bay Pond"}}
>>>>>>> 03f74aca74312dbeaf24d7e61306dd6a786dc3d0
