<<<<<<< HEAD
{
  "id": 2403976,
  "type": "Feature",
  "properties": {
    "tgn:hierarchy":[
        "tgn:2403976",
        "tgn:1000001",
        "tgn:7012149",
        "tgn:2001279",
        "tgn:7007524",
        "tgn:7029392"
    ],
    "tgn:id":2403976,
    "tgn:name":"Howell Creek",
    "tgn:placetype":[
        "aat:300008706"
    ]
},
  "bbox": [],
  "geometry": {"coordinates":[-113.7167,46.4833],"type":"Point"}
}
=======
{"geometry":{"type":"Point","coordinates":[-113.716700,46.483300]},"type":"Feature","properties":{"hierarchy":["tgn:2403976","tgn:1000001","tgn:7012149","tgn:2001279","tgn:7007524","tgn:7029392"],"placetype":["aat:300008706"],"id":2403976,"name:xx":"Howell Creek"}}
>>>>>>> 03f74aca74312dbeaf24d7e61306dd6a786dc3d0
