{
  "id": 2520028,
  "type": "Feature",
  "properties": {
    "tgn:hierarchy":[
        "tgn:2520028",
        "tgn:7002659",
        "tgn:1000001",
        "tgn:2000010",
        "tgn:7012149",
        "tgn:7029392"
    ],
    "tgn:id":2520028,
    "tgn:name":"Mollie Branch",
    "tgn:placetype":[
        "aat:300008699"
    ]
},
  "bbox": [],
  "geometry": {"coordinates":[-86.8333,32.8833],"type":"Point"}
}