{
  "id": 2161940,
  "type": "Feature",
  "properties": {
    "tgn:hierarchy":[
        "tgn:2161940",
        "tgn:1000001",
        "tgn:7012149",
        "tgn:7029392"
    ],
    "tgn:id":2161940,
    "tgn:name":"Bells Brook",
    "tgn:placetype":[
        "aat:300008699"
    ]
},
  "bbox": [],
  "geometry": {"coordinates":[-78.25,42.0167],"type":"Point"}
}