{
  "id": 7154013,
  "type": "Feature",
  "properties": {
    "tgn:hierarchy":[
        "tgn:7154013",
        "tgn:1000003",
        "tgn:7003676",
        "tgn:7000084",
        "tgn:7029392"
    ],
    "tgn:id":7154013,
    "tgn:name":"Isingerode",
    "tgn:placetype":[
        "aat:300008347"
    ]
},
  "bbox": [],
  "geometry": {"coordinates":[10.583333,52.033333],"type":"Point"}
}