{
  "id": 7378459,
  "type": "Feature",
  "properties": {
    "tgn:hierarchy":[
        "tgn:7378459",
        "tgn:1000001",
        "tgn:7005589",
        "tgn:7005560",
        "tgn:7029392"
    ],
    "tgn:id":7378459,
    "tgn:name:es":"La Primavera",
    "tgn:placetype":[
        "aat:300008347"
    ]
},
  "bbox": [],
  "geometry": {"coordinates":[-100.1675,24.691667],"type":"Point"}
}