{
  "id": 7214101,
  "type": "Feature",
  "properties": {
    "tgn:hierarchy":[
        "tgn:7214101",
        "tgn:1000003",
        "tgn:7003688",
        "tgn:7000084",
        "tgn:7029392"
    ],
    "tgn:id":7214101,
    "tgn:name":"B\u00f6kingharde",
    "tgn:placetype":[
        "aat:300055621"
    ]
},
  "bbox": [],
  "geometry": {"coordinates":[8.816667,54.766667],"type":"Point"}
}