{
  "id": 2659201,
  "type": "Feature",
  "properties": {
    "tgn:hierarchy":[
        "tgn:2659201",
        "tgn:1000001",
        "tgn:7012149",
        "tgn:2001459",
        "tgn:7007566",
        "tgn:7029392"
    ],
    "tgn:id":2659201,
    "tgn:name":"Shields Lake",
    "tgn:placetype":[
        "aat:300008680"
    ]
},
  "bbox": [],
  "geometry": {"coordinates":[-103.3333,35.9667],"type":"Point"}
}