{
  "id": 2660845,
  "type": "Feature",
  "properties": {
    "tgn:hierarchy":[
        "tgn:2660845",
        "tgn:1000001",
        "tgn:7012149",
        "tgn:2001543",
        "tgn:7007709",
        "tgn:7029392"
    ],
    "tgn:id":2660845,
    "tgn:name":"Short Branch",
    "tgn:placetype":[
        "aat:300008699"
    ]
},
  "bbox": [],
  "geometry": {"coordinates":[-83.5167,35.35],"type":"Point"}
}