{
  "id": 1002158,
  "type": "Feature",
  "properties": {
    "tgn:hierarchy":[
        "tgn:1002158",
        "tgn:1000001",
        "tgn:7012149",
        "tgn:7007523",
        "tgn:7029392"
    ],
    "tgn:id":1002158,
    "tgn:name":"Audrain",
    "tgn:placetype":[
        "aat:300387145",
        "aat:300000771"
    ]
},
  "bbox": [],
  "geometry": {"coordinates":[-91.8667,39.2167],"type":"Point"}
}