{
  "id": 7322367,
  "type": "Feature",
  "properties": {
    "tgn:hierarchy":[
        "tgn:7322367",
        "tgn:1001692",
        "tgn:1000049",
        "tgn:1000002",
        "tgn:7029392"
    ],
    "tgn:id":7322367,
    "tgn:name":"Cailaco, Estero",
    "tgn:placetype":[
        "aat:300008699"
    ]
},
  "bbox": [],
  "geometry": {"coordinates":[-72.616667,-38.716667],"type":"Point"}
}