{
  "id": 7019639,
  "type": "Feature",
  "properties": {
    "tgn:hierarchy":[
        "tgn:7019639",
        "tgn:1000001",
        "tgn:2001425",
        "tgn:7012149",
        "tgn:7007564",
        "tgn:7029392"
    ],
    "tgn:id":7019639,
    "tgn:name":"Kimball Pond",
    "tgn:placetype":[
        "aat:300006191"
    ]
},
  "bbox": [],
  "geometry": {"coordinates":[-71.5667,43.0833],"type":"Point"}
}