{
  "id": 7449413,
  "type": "Feature",
  "properties": {
    "tgn:hierarchy":[
        "tgn:7449413",
        "tgn:7002444",
        "tgn:1000003",
        "tgn:7008082",
        "tgn:7008591",
        "tgn:7029392"
    ],
    "tgn:id":7449413,
    "tgn:name:en":"Glenquoich Forest",
    "tgn:placetype":[
        "aat:300008863"
    ]
},
  "bbox": [],
  "geometry": {"coordinates":[-5.133333,57.066667],"type":"Point"}
}