{
  "id": 7001718,
  "type": "Feature",
  "properties": {
    "tgn:hierarchy":[
        "tgn:7001718",
        "tgn:1000004",
        "tgn:7001800",
        "tgn:1000111",
        "tgn:7029392"
    ],
    "tgn:id":7001718,
    "tgn:name":"Wuzhishan",
    "tgn:placetype":[
        "aat:300008795"
    ]
},
  "bbox": [],
  "geometry": {"coordinates":[109.75,18.9833],"type":"Point"}
}