{
  "id": 2764123,
  "type": "Feature",
  "properties": {
    "tgn:hierarchy":[
        "tgn:2764123",
        "tgn:1002145",
        "tgn:1000001",
        "tgn:7012149",
        "tgn:7007157",
        "tgn:7029392"
    ],
    "tgn:id":2764123,
    "tgn:name":"Wheeler Lake",
    "tgn:placetype":[
        "aat:300008680"
    ]
},
  "bbox": [],
  "geometry": {"coordinates":[-119.9667,38.5167],"type":"Point"}
}