<<<<<<< HEAD
{
  "id": 2764123,
  "type": "Feature",
  "properties": {
    "tgn:hierarchy":[
        "tgn:2764123",
        "tgn:1002145",
        "tgn:1000001",
        "tgn:7012149",
        "tgn:7007157",
        "tgn:7029392"
    ],
    "tgn:id":2764123,
    "tgn:name":"Wheeler Lake",
    "tgn:placetype":[
        "aat:300008680"
    ]
},
  "bbox": [],
  "geometry": {"coordinates":[-119.9667,38.5167],"type":"Point"}
}
=======
{"geometry":{"type":"Point","coordinates":[-119.966700,38.516700]},"type":"Feature","properties":{"hierarchy":["tgn:2764123","tgn:1002145","tgn:1000001","tgn:7012149","tgn:7007157","tgn:7029392"],"placetype":["aat:300008680"],"id":2764123,"name:xx":"Wheeler Lake"}}
>>>>>>> 03f74aca74312dbeaf24d7e61306dd6a786dc3d0
