{
  "id": 2326229,
  "type": "Feature",
  "properties": {
    "tgn:hierarchy":[
        "tgn:2326229",
        "tgn:1000001",
        "tgn:7012149",
        "tgn:7007157",
        "tgn:1002894",
        "tgn:7029392"
    ],
    "tgn:id":2326229,
    "tgn:name":"Fillmore Hill",
    "tgn:placetype":[
        "aat:300008798"
    ]
},
  "bbox": [],
  "geometry": {"coordinates":[-120.75,39.4667],"type":"Point"}
}