{
  "id": 7386094,
  "type": "Feature",
  "properties": {
    "tgn:hierarchy":[
        "tgn:7386094",
        "tgn:7005587",
        "tgn:1000001",
        "tgn:7005560",
        "tgn:7029392"
    ],
    "tgn:id":7386094,
    "tgn:name":"Pitol",
    "tgn:placetype":[
        "aat:300008347"
    ]
},
  "bbox": [],
  "geometry": {"coordinates":[-99.183333,20.166667],"type":"Point"}
}