{
  "id": 2648882,
  "type": "Feature",
  "properties": {
    "tgn:hierarchy":[
        "tgn:2648882",
        "tgn:1000001",
        "tgn:7012149",
        "tgn:2000355",
        "tgn:7007248",
        "tgn:7029392"
    ],
    "tgn:id":2648882,
    "tgn:name":"Scott Branch",
    "tgn:placetype":[
        "aat:300008699"
    ]
},
  "bbox": [],
  "geometry": {"coordinates":[-84.65,34.4333],"type":"Point"}
}