{
  "id": 2172455,
  "type": "Feature",
  "properties": {
    "tgn:hierarchy":[
        "tgn:2172455",
        "tgn:7013313",
        "tgn:1000001",
        "tgn:7012149",
        "tgn:7007826",
        "tgn:7029392"
    ],
    "tgn:id":2172455,
    "tgn:name":"Bill Mott Bayou",
    "tgn:placetype":[
        "aat:300008680"
    ]
},
  "bbox": [],
  "geometry": {"coordinates":[-96.9167,28.1667],"type":"Point"}
}