{
  "id": 7439126,
  "type": "Feature",
  "properties": {
    "tgn:hierarchy":[
        "tgn:7439126",
        "tgn:1001836",
        "tgn:1000001",
        "tgn:7005560",
        "tgn:7029392"
    ],
    "tgn:id":7439126,
    "tgn:name":"Tecomaja",
    "tgn:placetype":[
        "aat:300008347"
    ]
},
  "bbox": [],
  "geometry": {"coordinates":[-111.283333,25.733333],"type":"Point"}
}