{
  "id": 7304310,
  "type": "Feature",
  "properties": {
    "tgn:hierarchy":[
        "tgn:7304310",
        "tgn:7008911",
        "tgn:1000003",
        "tgn:7002763",
        "tgn:1000095",
        "tgn:7029392"
    ],
    "tgn:id":7304310,
    "tgn:name":"Los Carriles",
    "tgn:placetype":[
        "aat:300008347"
    ]
},
  "bbox": [],
  "geometry": {"coordinates":[-4.916667,43.416667],"type":"Point"}
}