<<<<<<< HEAD
{
  "id": 7368679,
  "type": "Feature",
  "properties": {
    "tgn:hierarchy":[
        "tgn:7368679",
        "tgn:1000001",
        "tgn:7005597",
        "tgn:7005560",
        "tgn:7029392"
    ],
    "tgn:id":7368679,
    "tgn:name":"Juanillo",
    "tgn:placetype":[
        "aat:300266554",
        "aat:300008699"
    ]
},
  "bbox": [],
  "geometry": {"coordinates":[-98.6,23.2],"type":"Point"}
}
=======
{"geometry":{"type":"Point","coordinates":[-98.600000,23.200000]},"type":"Feature","properties":{"hierarchy":["tgn:7368679","tgn:1000001","tgn:7005597","tgn:7005560","tgn:7029392"],"placetype":["aat:300266554","aat:300008699"],"id":7368679,"name:xx":"Juanillo"}}
>>>>>>> 03f74aca74312dbeaf24d7e61306dd6a786dc3d0
