<<<<<<< HEAD
{
  "id": 7470645,
  "type": "Feature",
  "properties": {
    "tgn:hierarchy":[
        "tgn:7470645",
        "tgn:7001001",
        "tgn:1000004",
        "tgn:1000141",
        "tgn:7029392"
    ],
    "tgn:id":7470645,
    "tgn:name":"Zhuweizi",
    "tgn:placetype":[
        "aat:300000745"
    ]
},
  "bbox": [],
  "geometry": {"coordinates":[120.436667,23.483333],"type":"Point"}
}
=======
{"geometry":{"type":"Point","coordinates":[120.436667,23.483333]},"type":"Feature","properties":{"hierarchy":["tgn:7470645","tgn:7001001","tgn:1000004","tgn:1000141","tgn:7029392"],"placetype":["aat:300000745"],"id":7470645,"name:xx":"Zhuweizi"}}
>>>>>>> 03f74aca74312dbeaf24d7e61306dd6a786dc3d0
