{
  "id": 7215702,
  "type": "Feature",
  "properties": {
    "tgn:hierarchy":[
        "tgn:7215702",
        "tgn:1000003",
        "tgn:7003676",
        "tgn:7000084",
        "tgn:7029392"
    ],
    "tgn:id":7215702,
    "tgn:name":"Achtum-Uppen",
    "tgn:placetype":[
        "aat:300387173"
    ]
},
  "bbox": [],
  "geometry": {"coordinates":[10.016667,52.15],"type":"Point"}
}