{
  "id": 7569053,
  "type": "Feature",
  "properties": {
    "tgn:hierarchy":[
        "tgn:7569053",
        "tgn:1001828",
        "tgn:1000004",
        "tgn:7000198",
        "tgn:7029392"
    ],
    "tgn:id":7569053,
    "tgn:name:en":"J\u0101mai Osm\u0101nia Railroad Station",
    "tgn:placetype":[
        "aat:300007783"
    ]
},
  "bbox": [],
  "geometry": {"coordinates":[78.518056,17.408889],"type":"Point"}
}