{
  "id": 2636893,
  "type": "Feature",
  "properties": {
    "tgn:hierarchy":[
        "tgn:2636893",
        "tgn:1000001",
        "tgn:7012149",
        "tgn:1002742",
        "tgn:7007920",
        "tgn:7029392"
    ],
    "tgn:id":2636893,
    "tgn:name":"Sailor Boy Mine",
    "tgn:placetype":[
        "aat:300000390"
    ]
},
  "bbox": [],
  "geometry": {"coordinates":[-119.0333,48.15],"type":"Point"}
}