{
  "id": 2685519,
  "type": "Feature",
  "properties": {
    "tgn:hierarchy":[
        "tgn:2685519",
        "tgn:7006450",
        "tgn:1000001",
        "tgn:7012149",
        "tgn:2000088",
        "tgn:7029392"
    ],
    "tgn:id":2685519,
    "tgn:name":"Spray Island",
    "tgn:placetype":[
        "aat:300008791"
    ]
},
  "bbox": [],
  "geometry": {"coordinates":[-132.7833,56.9833],"type":"Point"}
}