{
  "id": 2535433,
  "type": "Feature",
  "properties": {
    "tgn:hierarchy":[
        "tgn:2535433",
        "tgn:1000001",
        "tgn:7012149",
        "tgn:1002690",
        "tgn:7007710",
        "tgn:7029392"
    ],
    "tgn:id":2535433,
    "tgn:name":"Narcissa",
    "tgn:placetype":[
        "aat:300008347"
    ]
},
  "bbox": [],
  "geometry": {"coordinates":[-75.25,40.1167],"type":"Point"}
}