{
  "id": 2288127,
  "type": "Feature",
  "properties": {
    "tgn:hierarchy":[
        "tgn:2288127",
        "tgn:1000001",
        "tgn:7012149",
        "tgn:2001218",
        "tgn:7007523",
        "tgn:7029392"
    ],
    "tgn:id":2288127,
    "tgn:name":"Dinsmore",
    "tgn:placetype":[
        "aat:300008347"
    ]
},
  "bbox": [],
  "geometry": {"coordinates":[-93.7333,40.3333],"type":"Point"}
}