<<<<<<< HEAD
{
  "id": 7479573,
  "type": "Feature",
  "properties": {
    "tgn:hierarchy":[
        "tgn:7479573",
        "tgn:1000004",
        "tgn:7490934",
        "tgn:1000141",
        "tgn:7029392"
    ],
    "tgn:id":7479573,
    "tgn:name":"Yujing Gongshang",
    "tgn:placetype":[
        "aat:300006495"
    ]
},
  "bbox": [],
  "geometry": {"coordinates":[120.461,23.121361],"type":"Point"}
}
=======
{"geometry":{"type":"Point","coordinates":[120.461000,23.121361]},"type":"Feature","properties":{"hierarchy":["tgn:7479573","tgn:1000004","tgn:7490934","tgn:1000141","tgn:7029392"],"placetype":["aat:300006495"],"id":7479573,"name:xx":"Yujing Gongshang"}}
>>>>>>> 03f74aca74312dbeaf24d7e61306dd6a786dc3d0
