<<<<<<< HEAD
{
  "id": 7114509,
  "type": "Feature",
  "properties": {
    "tgn:hierarchy":[
        "tgn:7114509",
        "tgn:1000003",
        "tgn:7000094",
        "tgn:7000084",
        "tgn:7029392"
    ],
    "tgn:id":7114509,
    "tgn:name":"Rolofshagen",
    "tgn:placetype":[
        "aat:300008347"
    ]
},
  "bbox": [],
  "geometry": {"coordinates":[11.166667,53.9],"type":"Point"}
}
=======
{"geometry":{"type":"Point","coordinates":[11.166667,53.900000]},"type":"Feature","properties":{"hierarchy":["tgn:7114509","tgn:1000003","tgn:7000094","tgn:7000084","tgn:7029392"],"placetype":["aat:300008347"],"id":7114509,"name:xx":"Rolofshagen"}}
>>>>>>> 03f74aca74312dbeaf24d7e61306dd6a786dc3d0
