{
  "id": 1097508,
  "type": "Feature",
  "properties": {
    "tgn:hierarchy":[
        "tgn:1097508",
        "tgn:7000490",
        "tgn:1000006",
        "tgn:7001829",
        "tgn:7029392"
    ],
    "tgn:id":1097508,
    "tgn:name":"McArthur River",
    "tgn:placetype":[
        "aat:300008347"
    ]
},
  "bbox": [],
  "geometry": {"coordinates":[136.1167,-16.45],"type":"Point"}
}