{
  "id": 1122002,
  "type": "Feature",
  "properties": {
    "tgn:hierarchy":[
        "tgn:1122002",
        "tgn:1000001",
        "tgn:7012149",
        "tgn:7007826",
        "tgn:7029392"
    ],
    "tgn:id":1122002,
    "tgn:name":"Blanco",
    "tgn:placetype":[
        "aat:300008707"
    ]
},
  "bbox": [],
  "geometry": {"coordinates":[-98.6833,30.0833],"type":"Point"}
}