{
  "id": 7223510,
  "type": "Feature",
  "properties": {
    "tgn:hierarchy":[
        "tgn:7223510",
        "tgn:7002706",
        "tgn:7002705",
        "tgn:1000003",
        "tgn:1000074",
        "tgn:7029392"
    ],
    "tgn:id":7223510,
    "tgn:name":"Melissourgo\u00ed",
    "tgn:placetype":[
        "aat:300008347"
    ]
},
  "bbox": [],
  "geometry": {"coordinates":[21.146667,39.509444],"type":"Point"}
}