{
  "id": 1027399,
  "type": "Feature",
  "properties": {
    "tgn:hierarchy":[
        "tgn:1027399",
        "tgn:7027131",
        "tgn:1000003",
        "tgn:7011765",
        "tgn:7029392"
    ],
    "tgn:id":1027399,
    "tgn:name":"Mur\u00e1\u0148",
    "tgn:placetype":[
        "aat:300008347"
    ]
},
  "bbox": [],
  "geometry": {"coordinates":[20.05,48.7333],"type":"Point"}
}