{
  "id": 2569855,
  "type": "Feature",
  "properties": {
    "tgn:hierarchy":[
        "tgn:2569855",
        "tgn:1000001",
        "tgn:7012149",
        "tgn:2000927",
        "tgn:7007515",
        "tgn:7029392"
    ],
    "tgn:id":2569855,
    "tgn:name":"Partridge Cove",
    "tgn:placetype":[
        "aat:300132316"
    ]
},
  "bbox": [],
  "geometry": {"coordinates":[-68.8167,45.5833],"type":"Point"}
}