{
  "id": 7479745,
  "type": "Feature",
  "properties": {
    "tgn:hierarchy":[
        "tgn:7479745",
        "tgn:1000004",
        "tgn:7490934",
        "tgn:1000141",
        "tgn:7029392"
    ],
    "tgn:id":7479745,
    "tgn:name":"Taizi Guozhong",
    "tgn:placetype":[
        "aat:300006495"
    ]
},
  "bbox": [],
  "geometry": {"coordinates":[120.27,23.291389],"type":"Point"}
}