{
  "id": 2000729,
  "type": "Feature",
  "properties": {
    "tgn:hierarchy":[
        "tgn:2000729",
        "tgn:1000001",
        "tgn:7012149",
        "tgn:7007254",
        "tgn:7029392"
    ],
    "tgn:id":2000729,
    "tgn:name":"Osage",
    "tgn:placetype":[
        "aat:300387145",
        "aat:300000771"
    ]
},
  "bbox": [],
  "geometry": {"coordinates":[-95.7333,38.65],"type":"Point"}
}