<<<<<<< HEAD
{
  "id": 7057402,
  "type": "Feature",
  "properties": {
    "tgn:hierarchy":[
        "tgn:7057402",
        "tgn:1003478",
        "tgn:1000003",
        "tgn:7003120",
        "tgn:1000080",
        "tgn:7029392"
    ],
    "tgn:id":7057402,
    "tgn:name":"Auzate",
    "tgn:placetype":[
        "aat:300008347"
    ]
},
  "bbox": [],
  "geometry": {"coordinates":[8.416667,45.733333],"type":"Point"}
}
=======
{"geometry":{"type":"Point","coordinates":[8.416667,45.733333]},"type":"Feature","properties":{"hierarchy":["tgn:7057402","tgn:1003478","tgn:1000003","tgn:7003120","tgn:1000080","tgn:7029392"],"placetype":["aat:300008347"],"id":7057402,"name:xx":"Auzate"}}
>>>>>>> 03f74aca74312dbeaf24d7e61306dd6a786dc3d0
