<<<<<<< HEAD
{
  "id": 2337053,
  "type": "Feature",
  "properties": {
    "tgn:hierarchy":[
        "tgn:2337053",
        "tgn:1000001",
        "tgn:7012149",
        "tgn:2000289",
        "tgn:7007240",
        "tgn:7029392"
    ],
    "tgn:id":2337053,
    "tgn:name":"Fourmile Point",
    "tgn:placetype":[
        "aat:300008850"
    ]
},
  "bbox": [],
  "geometry": {"coordinates":[-84.2,30.1],"type":"Point"}
}
=======
{"geometry":{"type":"Point","coordinates":[-84.200000,30.100000]},"type":"Feature","properties":{"hierarchy":["tgn:2337053","tgn:1000001","tgn:7012149","tgn:2000289","tgn:7007240","tgn:7029392"],"placetype":["aat:300008850"],"id":2337053,"name:xx":"Fourmile Point"}}
>>>>>>> 03f74aca74312dbeaf24d7e61306dd6a786dc3d0
