{
  "id": 7468590,
  "type": "Feature",
  "properties": {
    "tgn:hierarchy":[
        "tgn:7468590",
        "tgn:1000004",
        "tgn:7471332",
        "tgn:1000141",
        "tgn:7029392"
    ],
    "tgn:id":7468590,
    "tgn:name":"Xinbu Zhen",
    "tgn:placetype":[
        "aat:300387173"
    ]
},
  "bbox": [],
  "geometry": {"coordinates":[121.083333,24.85],"type":"Point"}
}