<<<<<<< HEAD
{
  "id": 2330865,
  "type": "Feature",
  "properties": {
    "tgn:hierarchy":[
        "tgn:2330865",
        "tgn:1000001",
        "tgn:7012149",
        "tgn:2000490",
        "tgn:7007250",
        "tgn:7029392"
    ],
    "tgn:id":2330865,
    "tgn:name":"Flat Ridge",
    "tgn:placetype":[
        "aat:300266640"
    ]
},
  "bbox": [],
  "geometry": {"coordinates":[-112.7667,42.3333],"type":"Point"}
}
=======
{"geometry":{"type":"Point","coordinates":[-112.766700,42.333300]},"type":"Feature","properties":{"hierarchy":["tgn:2330865","tgn:1000001","tgn:7012149","tgn:2000490","tgn:7007250","tgn:7029392"],"placetype":["aat:300266640"],"id":2330865,"name:xx":"Flat Ridge"}}
>>>>>>> 03f74aca74312dbeaf24d7e61306dd6a786dc3d0
