{
  "id": 2330865,
  "type": "Feature",
  "properties": {
    "tgn:hierarchy":[
        "tgn:2330865",
        "tgn:1000001",
        "tgn:7012149",
        "tgn:2000490",
        "tgn:7007250",
        "tgn:7029392"
    ],
    "tgn:id":2330865,
    "tgn:name":"Flat Ridge",
    "tgn:placetype":[
        "aat:300266640"
    ]
},
  "bbox": [],
  "geometry": {"coordinates":[-112.7667,42.3333],"type":"Point"}
}