<<<<<<< HEAD
{
  "id": 2766598,
  "type": "Feature",
  "properties": {
    "tgn:hierarchy":[
        "tgn:2766598",
        "tgn:1000001",
        "tgn:7012149",
        "tgn:1002795",
        "tgn:7007826",
        "tgn:7029392"
    ],
    "tgn:id":2766598,
    "tgn:name":"White Oak Creek",
    "tgn:placetype":[
        "aat:300008706"
    ]
},
  "bbox": [],
  "geometry": {"coordinates":[-94.9167,30.9333],"type":"Point"}
}
=======
{"geometry":{"type":"Point","coordinates":[-94.916700,30.933300]},"type":"Feature","properties":{"hierarchy":["tgn:2766598","tgn:1000001","tgn:7012149","tgn:1002795","tgn:7007826","tgn:7029392"],"placetype":["aat:300008706"],"id":2766598,"name:xx":"White Oak Creek"}}
>>>>>>> 03f74aca74312dbeaf24d7e61306dd6a786dc3d0
