{
  "id": 7395403,
  "type": "Feature",
  "properties": {
    "tgn:hierarchy":[
        "tgn:7395403",
        "tgn:1000001",
        "tgn:7005601",
        "tgn:7005560",
        "tgn:7029392"
    ],
    "tgn:id":7395403,
    "tgn:name":"San Isidro",
    "tgn:placetype":[
        "aat:300008347"
    ]
},
  "bbox": [],
  "geometry": {"coordinates":[-102.216667,24.55],"type":"Point"}
}