{
  "id": 2348496,
  "type": "Feature",
  "properties": {
    "tgn:hierarchy":[
        "tgn:2348496",
        "tgn:1000001",
        "tgn:2000669",
        "tgn:7012149",
        "tgn:7007254",
        "tgn:7029392"
    ],
    "tgn:id":2348496,
    "tgn:name":"Gibbs",
    "tgn:placetype":[
        "aat:300008347"
    ]
},
  "bbox": [],
  "geometry": {"coordinates":[-96.3167,37.1333],"type":"Point"}
}