{
  "id": 7520217,
  "type": "Feature",
  "properties": {
    "tgn:hierarchy":[
        "tgn:7520217",
        "tgn:7001242",
        "tgn:7016833",
        "tgn:7000124",
        "tgn:7029392"
    ],
    "tgn:id":7520217,
    "tgn:name:en":"Al \u1e28ijz",
    "tgn:placetype":[
        "aat:300008347"
    ]
},
  "bbox": [],
  "geometry": {"coordinates":[31.973611,26.228333],"type":"Point"}
}