{
  "id": 2354730,
  "type": "Feature",
  "properties": {
    "tgn:hierarchy":[
        "tgn:2354730",
        "tgn:1000001",
        "tgn:7012149",
        "tgn:2001851",
        "tgn:7007825",
        "tgn:7029392"
    ],
    "tgn:id":2354730,
    "tgn:name":"Good Hope Branch",
    "tgn:placetype":[
        "aat:300008699"
    ]
},
  "bbox": [],
  "geometry": {"coordinates":[-83.0833,35.9667],"type":"Point"}
}