{
  "id": 2487132,
  "type": "Feature",
  "properties": {
    "tgn:hierarchy":[
        "tgn:2487132",
        "tgn:1000001",
        "tgn:7012149",
        "tgn:7007157",
        "tgn:2000185",
        "tgn:7029392"
    ],
    "tgn:id":2487132,
    "tgn:name":"Leech Lake Mountain",
    "tgn:placetype":[
        "aat:300008798"
    ]
},
  "bbox": [],
  "geometry": {"coordinates":[-123.0667,39.9167],"type":"Point"}
}