{
  "id": 2495582,
  "type": "Feature",
  "properties": {
    "tgn:hierarchy":[
        "tgn:2495582",
        "tgn:1000001",
        "tgn:2001099",
        "tgn:7012149",
        "tgn:7007522",
        "tgn:7029392"
    ],
    "tgn:id":2495582,
    "tgn:name":"Mascot",
    "tgn:placetype":[
        "aat:300008347"
    ]
},
  "bbox": [],
  "geometry": {"coordinates":[-90.4833,34.45],"type":"Point"}
}