<<<<<<< HEAD
{
  "id": 2252452,
  "type": "Feature",
  "properties": {
    "tgn:hierarchy":[
        "tgn:2252452",
        "tgn:1000001",
        "tgn:1002253",
        "tgn:7012149",
        "tgn:7007251",
        "tgn:7029392"
    ],
    "tgn:id":2252452,
    "tgn:name":"Conkey Branch",
    "tgn:placetype":[
        "aat:300008699"
    ]
},
  "bbox": [],
  "geometry": {"coordinates":[-87.9667,40.1],"type":"Point"}
}
=======
{"geometry":{"type":"Point","coordinates":[-87.966700,40.100000]},"type":"Feature","properties":{"hierarchy":["tgn:2252452","tgn:1000001","tgn:1002253","tgn:7012149","tgn:7007251","tgn:7029392"],"placetype":["aat:300008699"],"id":2252452,"name:xx":"Conkey Branch"}}
>>>>>>> 03f74aca74312dbeaf24d7e61306dd6a786dc3d0
