{
  "id": 2585646,
  "type": "Feature",
  "properties": {
    "tgn:hierarchy":[
        "tgn:2585646",
        "tgn:1000001",
        "tgn:7012149",
        "tgn:7007157",
        "tgn:1002791",
        "tgn:7029392"
    ],
    "tgn:id":2585646,
    "tgn:name":"Pioneer Mine",
    "tgn:placetype":[
        "aat:300000390"
    ]
},
  "bbox": [],
  "geometry": {"coordinates":[-120.7167,39.1667],"type":"Point"}
}