{
  "id": 1003938,
  "type": "Feature",
  "properties": {
    "tgn:hierarchy":[
        "tgn:1003938",
        "tgn:7001242",
        "tgn:7016833",
        "tgn:1001091",
        "tgn:7029392"
    ],
    "tgn:id":1003938,
    "tgn:name:en":"Al Marj",
    "tgn:placetype":[
        "aat:300000745",
        "aat:300007783"
    ]
},
  "bbox": [],
  "geometry": {"coordinates":[31.3333,30.15],"type":"Point"}
}