{
  "id": 7228414,
  "type": "Feature",
  "properties": {
    "tgn:hierarchy":[
        "tgn:7228414",
        "tgn:7002735",
        "tgn:7017076",
        "tgn:1000003",
        "tgn:1000074",
        "tgn:7029392"
    ],
    "tgn:id":7228414,
    "tgn:name":"Kast\u00e1nia",
    "tgn:placetype":[
        "aat:300008347"
    ]
},
  "bbox": [],
  "geometry": {"coordinates":[22.316667,36.866667],"type":"Point"}
}