<<<<<<< HEAD
{
  "id": 2255735,
  "type": "Feature",
  "properties": {
    "tgn:hierarchy":[
        "tgn:2255735",
        "tgn:1000001",
        "tgn:2001411",
        "tgn:7012149",
        "tgn:7007526",
        "tgn:7029392"
    ],
    "tgn:id":2255735,
    "tgn:name":"Copper Bell Mine",
    "tgn:placetype":[
        "aat:300000390"
    ]
},
  "bbox": [],
  "geometry": {"coordinates":[-116.0,40.5167],"type":"Point"}
}
=======
{"geometry":{"type":"Point","coordinates":[-116.000000,40.516700]},"type":"Feature","properties":{"hierarchy":["tgn:2255735","tgn:1000001","tgn:2001411","tgn:7012149","tgn:7007526","tgn:7029392"],"placetype":["aat:300000390"],"id":2255735,"name:xx":"Copper Bell Mine"}}
>>>>>>> 03f74aca74312dbeaf24d7e61306dd6a786dc3d0
