<<<<<<< HEAD
{
  "id": 2405080,
  "type": "Feature",
  "properties": {
    "tgn:hierarchy":[
        "tgn:2405080",
        "tgn:2001623",
        "tgn:1000001",
        "tgn:7012149",
        "tgn:7007707",
        "tgn:7029392"
    ],
    "tgn:id":2405080,
    "tgn:name":"Hudson Mountain",
    "tgn:placetype":[
        "aat:300008798"
    ]
},
  "bbox": [],
  "geometry": {"coordinates":[-94.7,35.6833],"type":"Point"}
}
=======
{"geometry":{"type":"Point","coordinates":[-94.700000,35.683300]},"type":"Feature","properties":{"hierarchy":["tgn:2405080","tgn:2001623","tgn:1000001","tgn:7012149","tgn:7007707","tgn:7029392"],"placetype":["aat:300008798"],"id":2405080,"name:xx":"Hudson Mountain"}}
>>>>>>> 03f74aca74312dbeaf24d7e61306dd6a786dc3d0
