{
  "id": 2454337,
  "type": "Feature",
  "properties": {
    "tgn:hierarchy":[
        "tgn:2454337",
        "tgn:1000001",
        "tgn:7012149",
        "tgn:2000982",
        "tgn:7007520",
        "tgn:7029392"
    ],
    "tgn:id":2454337,
    "tgn:name":"Little Crystal Lake",
    "tgn:placetype":[
        "aat:300008680"
    ]
},
  "bbox": [],
  "geometry": {"coordinates":[-84.3333,44.9167],"type":"Point"}
}