{
  "id": 2588414,
  "type": "Feature",
  "properties": {
    "tgn:hierarchy":[
        "tgn:2588414",
        "tgn:1000001",
        "tgn:7012149",
        "tgn:1002924",
        "tgn:7007568",
        "tgn:7029392"
    ],
    "tgn:id":2588414,
    "tgn:name":"Plum Island Rock",
    "tgn:placetype":[
        "aat:300132348"
    ]
},
  "bbox": [],
  "geometry": {"coordinates":[-72.1667,41.1667],"type":"Point"}
}