{
  "id": 7401738,
  "type": "Feature",
  "properties": {
    "tgn:hierarchy":[
        "tgn:7401738",
        "tgn:1000001",
        "tgn:7005599",
        "tgn:7005560",
        "tgn:7029392"
    ],
    "tgn:id":7401738,
    "tgn:name":"Miguel Alem\u00e1n",
    "tgn:placetype":[
        "aat:300008347"
    ]
},
  "bbox": [],
  "geometry": {"coordinates":[-96.791667,18.883333],"type":"Point"}
}