{
  "id": 7102925,
  "type": "Feature",
  "properties": {
    "tgn:hierarchy":[
        "tgn:7102925",
        "tgn:1000003",
        "tgn:7003685",
        "tgn:7000084",
        "tgn:7029392"
    ],
    "tgn:id":7102925,
    "tgn:name":"Rotes Vorwerk",
    "tgn:placetype":[
        "aat:300000206"
    ]
},
  "bbox": [],
  "geometry": {"coordinates":[13.316667,50.883333],"type":"Point"}
}