{
  "id": 2720537,
  "type": "Feature",
  "properties": {
    "tgn:hierarchy":[
        "tgn:2720537",
        "tgn:1000001",
        "tgn:7012149",
        "tgn:2000494",
        "tgn:7007250",
        "tgn:7029392"
    ],
    "tgn:id":2720537,
    "tgn:name":"Thunderbolt Mountain",
    "tgn:placetype":[
        "aat:300008798"
    ]
},
  "bbox": [],
  "geometry": {"coordinates":[-115.6333,44.7167],"type":"Point"}
}