{
  "id": 2574308,
  "type": "Feature",
  "properties": {
    "tgn:hierarchy":[
        "tgn:2574308",
        "tgn:1000001",
        "tgn:7012149",
        "tgn:2002155",
        "tgn:7007919",
        "tgn:7029392"
    ],
    "tgn:id":2574308,
    "tgn:name":"Pelham, Lake",
    "tgn:placetype":[
        "aat:300006191"
    ]
},
  "bbox": [],
  "geometry": {"coordinates":[-78.0167,38.4667],"type":"Point"}
}