{
  "id": 2289643,
  "type": "Feature",
  "properties": {
    "tgn:hierarchy":[
        "tgn:2289643",
        "tgn:1000001",
        "tgn:7012149",
        "tgn:2001908",
        "tgn:7007825",
        "tgn:7029392"
    ],
    "tgn:id":2289643,
    "tgn:name":"Dixon Slope Mine",
    "tgn:placetype":[
        "aat:300000390"
    ]
},
  "bbox": [],
  "geometry": {"coordinates":[-85.0167,35.5167],"type":"Point"}
}