{
  "id": 2216525,
  "type": "Feature",
  "properties": {
    "tgn:hierarchy":[
        "tgn:2216525",
        "tgn:1000001",
        "tgn:7012149",
        "tgn:2001300",
        "tgn:7007524",
        "tgn:7029392"
    ],
    "tgn:id":2216525,
    "tgn:name":"Camp Creek",
    "tgn:placetype":[
        "aat:300008706"
    ]
},
  "bbox": [],
  "geometry": {"coordinates":[-113.9333,45.75],"type":"Point"}
}