{
  "id": 7104470,
  "type": "Feature",
  "properties": {
    "tgn:hierarchy":[
        "tgn:7104470",
        "tgn:7003669",
        "tgn:1000003",
        "tgn:7000084",
        "tgn:7029392"
    ],
    "tgn:id":7104470,
    "tgn:name":"Schnepfenried",
    "tgn:placetype":[
        "aat:300000206"
    ]
},
  "bbox": [],
  "geometry": {"coordinates":[12.483333,49.266667],"type":"Point"}
}