{
  "id": 2487156,
  "type": "Feature",
  "properties": {
    "tgn:hierarchy":[
        "tgn:2487156",
        "tgn:1000001",
        "tgn:7012149",
        "tgn:2002371",
        "tgn:7007923",
        "tgn:7029392"
    ],
    "tgn:id":2487156,
    "tgn:name":"Leeds Creek",
    "tgn:placetype":[
        "aat:300008706"
    ]
},
  "bbox": [],
  "geometry": {"coordinates":[-110.0167,43.55],"type":"Point"}
}