{
  "id": 2376086,
  "type": "Feature",
  "properties": {
    "tgn:hierarchy":[
        "tgn:2376086",
        "tgn:1000001",
        "tgn:7012149",
        "tgn:1002790",
        "tgn:7007240",
        "tgn:7029392"
    ],
    "tgn:id":2376086,
    "tgn:name":"Harbor Lake",
    "tgn:placetype":[
        "aat:300008680"
    ]
},
  "bbox": [],
  "geometry": {"coordinates":[-82.7333,27.9833],"type":"Point"}
}