{
  "id": 2711787,
  "type": "Feature",
  "properties": {
    "tgn:hierarchy":[
        "tgn:2711787",
        "tgn:1000001",
        "tgn:2001702",
        "tgn:7012149",
        "tgn:7007708",
        "tgn:7029392"
    ],
    "tgn:id":2711787,
    "tgn:name":"Tarheel Arm",
    "tgn:placetype":[
        "aat:300132316"
    ]
},
  "bbox": [],
  "geometry": {"coordinates":[-124.25,43.35],"type":"Point"}
}