{
  "id": 7304307,
  "type": "Feature",
  "properties": {
    "tgn:hierarchy":[
        "tgn:7304307",
        "tgn:7002758",
        "tgn:7002821",
        "tgn:1000003",
        "tgn:1000095",
        "tgn:7029392"
    ],
    "tgn:id":7304307,
    "tgn:name":"Los Carriones",
    "tgn:placetype":[
        "aat:300008347"
    ]
},
  "bbox": [],
  "geometry": {"coordinates":[-2.666667,37.683333],"type":"Point"}
}