{
  "id": 7270525,
  "type": "Feature",
  "properties": {
    "tgn:hierarchy":[
        "tgn:7270525",
        "tgn:7003614",
        "tgn:1000003",
        "tgn:7016845",
        "tgn:7029392"
    ],
    "tgn:id":7270525,
    "tgn:name:nl":"Oude Runde",
    "tgn:placetype":[
        "aat:300008699"
    ]
},
  "bbox": [],
  "geometry": {"coordinates":[7.066667,52.833333],"type":"Point"}
}