{
  "id": 7510608,
  "type": "Feature",
  "properties": {
    "tgn:hierarchy":[
        "tgn:7510608",
        "tgn:1009227",
        "tgn:1000226",
        "tgn:7018437",
        "tgn:1000006",
        "tgn:7029392"
    ],
    "tgn:id":7510608,
    "tgn:name:en":"Twin Peaks",
    "tgn:placetype":[
        "aat:300008798"
    ]
},
  "bbox": [],
  "geometry": {"coordinates":[169.083333,-44.483333],"type":"Point"}
}