{
  "id": 2275172,
  "type": "Feature",
  "properties": {
    "tgn:hierarchy":[
        "tgn:2275172",
        "tgn:1000001",
        "tgn:7012149",
        "tgn:2000825",
        "tgn:7007255",
        "tgn:7029392"
    ],
    "tgn:id":2275172,
    "tgn:name":"Daniel Boone Cave",
    "tgn:placetype":[
        "aat:300008746"
    ]
},
  "bbox": [],
  "geometry": {"coordinates":[-86.05,37.95],"type":"Point"}
}