{
  "id": 7094541,
  "type": "Feature",
  "properties": {
    "tgn:hierarchy":[
        "tgn:7094541",
        "tgn:1000003",
        "tgn:7003688",
        "tgn:7000084",
        "tgn:7029392"
    ],
    "tgn:id":7094541,
    "tgn:name":"Seebruch",
    "tgn:placetype":[
        "aat:300008863"
    ]
},
  "bbox": [],
  "geometry": {"coordinates":[10.766667,53.733333],"type":"Point"}
}