{
  "id": 1038584,
  "type": "Feature",
  "properties": {
    "tgn:hierarchy":[
        "tgn:1038584",
        "tgn:1000003",
        "tgn:7003676",
        "tgn:7000084",
        "tgn:7029392"
    ],
    "tgn:id":1038584,
    "tgn:name":"Bohmte",
    "tgn:placetype":[
        "aat:300008347"
    ]
},
  "bbox": [],
  "geometry": {"coordinates":[8.316667,52.366667],"type":"Point"}
}