{
  "id": 7562926,
  "type": "Feature",
  "properties": {
    "tgn:hierarchy":[
        "tgn:7562926",
        "tgn:1000004",
        "tgn:7000198",
        "tgn:7016722",
        "tgn:7029392"
    ],
    "tgn:id":7562926,
    "tgn:name:en":"Habibull\u0101hpur Amritpur",
    "tgn:placetype":[
        "aat:300008347"
    ]
},
  "bbox": [],
  "geometry": {"coordinates":[79.525642,27.744636],"type":"Point"}
}