{
  "id": 2053836,
  "type": "Feature",
  "properties": {
    "tgn:hierarchy":[
        "tgn:2053836",
        "tgn:1000001",
        "tgn:2001005",
        "tgn:7012149",
        "tgn:7007521",
        "tgn:7029392"
    ],
    "tgn:id":2053836,
    "tgn:name":"Amboy",
    "tgn:placetype":[
        "aat:300008347"
    ]
},
  "bbox": [],
  "geometry": {"coordinates":[-94.15,43.8833],"type":"Point"}
}