{
  "id": 7555573,
  "type": "Feature",
  "properties": {
    "tgn:hierarchy":[
        "tgn:7555573",
        "tgn:1000004",
        "tgn:7000198",
        "tgn:1001894",
        "tgn:7029392"
    ],
    "tgn:id":7555573,
    "tgn:name:en":"Moh\u0101sa",
    "tgn:placetype":[
        "aat:300008347"
    ]
},
  "bbox": [],
  "geometry": {"coordinates":[77.635608,24.384463],"type":"Point"}
}