{
  "id": 2121339,
  "type": "Feature",
  "properties": {
    "tgn:hierarchy":[
        "tgn:2121339",
        "tgn:1000001",
        "tgn:7012149",
        "tgn:1002672",
        "tgn:7007922",
        "tgn:7029392"
    ],
    "tgn:id":2121339,
    "tgn:name":"Hales Corners",
    "tgn:placetype":[
        "aat:300008347"
    ]
},
  "bbox": [],
  "geometry": {"coordinates":[-88.0333,42.9333],"type":"Point"}
}