{
  "id": 1085234,
  "type": "Feature",
  "properties": {
    "tgn:hierarchy":[
        "tgn:1085234",
        "tgn:1000004",
        "tgn:1002084",
        "tgn:1000140",
        "tgn:7029392"
    ],
    "tgn:id":1085234,
    "tgn:name":"Salq\u012bn",
    "tgn:placetype":[
        "aat:300008347"
    ]
},
  "bbox": [],
  "geometry": {"coordinates":[36.4333,36.1667],"type":"Point"}
}