{
  "id": 7218803,
  "type": "Feature",
  "properties": {
    "tgn:hierarchy":[
        "tgn:7218803",
        "tgn:7011161",
        "tgn:7002674",
        "tgn:1000003",
        "tgn:1000074",
        "tgn:7029392"
    ],
    "tgn:id":7218803,
    "tgn:name":"Spal\u00e1dia",
    "tgn:placetype":[
        "aat:300387200"
    ]
},
  "bbox": [],
  "geometry": {"coordinates":[26.126389,38.339444],"type":"Point"}
}