{
  "id": 2136893,
  "type": "Feature",
  "properties": {
    "tgn:hierarchy":[
        "tgn:2136893",
        "tgn:1000001",
        "tgn:7012149",
        "tgn:2000927",
        "tgn:7007515",
        "tgn:7029392"
    ],
    "tgn:id":2136893,
    "tgn:name":"Argyle",
    "tgn:placetype":[
        "aat:300008347"
    ]
},
  "bbox": [],
  "geometry": {"coordinates":[-68.6667,45.05],"type":"Point"}
}