{
  "id": 7177012,
  "type": "Feature",
  "properties": {
    "tgn:hierarchy":[
        "tgn:7177012",
        "tgn:1000003",
        "tgn:7003687",
        "tgn:7000084",
        "tgn:7029392"
    ],
    "tgn:id":7177012,
    "tgn:name":"Gutenberg",
    "tgn:placetype":[
        "aat:300008347"
    ]
},
  "bbox": [],
  "geometry": {"coordinates":[11.966667,51.55],"type":"Point"}
}