{
  "id": 1022256,
  "type": "Feature",
  "properties": {
    "tgn:hierarchy":[
        "tgn:1022256",
        "tgn:7006064",
        "tgn:1000047",
        "tgn:7002455",
        "tgn:1000002",
        "tgn:7029392"
    ],
    "tgn:id":1022256,
    "tgn:name":"Oiticica",
    "tgn:placetype":[
        "aat:300008347"
    ]
},
  "bbox": [],
  "geometry": {"coordinates":[-41.0667,-5.0333],"type":"Point"}
}