{
  "id": 7378129,
  "type": "Feature",
  "properties": {
    "tgn:hierarchy":[
        "tgn:7378129",
        "tgn:7005581",
        "tgn:1000001",
        "tgn:7005560",
        "tgn:7029392"
    ],
    "tgn:id":7378129,
    "tgn:name":"Rancho Las Pe\u00f1as",
    "tgn:placetype":[
        "aat:300000241"
    ]
},
  "bbox": [],
  "geometry": {"coordinates":[-104.916667,27.466667],"type":"Point"}
}