{
  "id": 1075926,
  "type": "Feature",
  "properties": {
    "tgn:hierarchy":[
        "tgn:1075926",
        "tgn:1000004",
        "tgn:7000198",
        "tgn:1001894",
        "tgn:7029392"
    ],
    "tgn:id":1075926,
    "tgn:name:en":"Korwai",
    "tgn:placetype":[
        "aat:300008347"
    ]
},
  "bbox": [],
  "geometry": {"coordinates":[78.040068,24.117744],"type":"Point"}
}