{
  "id": 2172250,
  "type": "Feature",
  "properties": {
    "tgn:hierarchy":[
        "tgn:2172250",
        "tgn:1000001",
        "tgn:2002245",
        "tgn:7012149",
        "tgn:7007920",
        "tgn:7029392"
    ],
    "tgn:id":2172250,
    "tgn:name":"Bihmaier Springs",
    "tgn:placetype":[
        "aat:300008697"
    ]
},
  "bbox": [],
  "geometry": {"coordinates":[-117.5333,46.45],"type":"Point"}
}