<<<<<<< HEAD
{
  "id": 2259425,
  "type": "Feature",
  "properties": {
    "tgn:hierarchy":[
        "tgn:2259425",
        "tgn:1000001",
        "tgn:7012149",
        "tgn:2001715",
        "tgn:7007708",
        "tgn:7029392"
    ],
    "tgn:id":2259425,
    "tgn:name":"Cottonwood Spring",
    "tgn:placetype":[
        "aat:300008697"
    ]
},
  "bbox": [],
  "geometry": {"coordinates":[-120.8,42.3833],"type":"Point"}
}
=======
{"geometry":{"type":"Point","coordinates":[-120.800000,42.383300]},"type":"Feature","properties":{"hierarchy":["tgn:2259425","tgn:1000001","tgn:7012149","tgn:2001715","tgn:7007708","tgn:7029392"],"placetype":["aat:300008697"],"id":2259425,"name:xx":"Cottonwood Spring"}}
>>>>>>> 03f74aca74312dbeaf24d7e61306dd6a786dc3d0
