{
  "id": 7325326,
  "type": "Feature",
  "properties": {
    "tgn:hierarchy":[
        "tgn:7325326",
        "tgn:7002813",
        "tgn:7002758",
        "tgn:1000003",
        "tgn:1000095",
        "tgn:7029392"
    ],
    "tgn:id":7325326,
    "tgn:name":"San Carlos, Salinas de",
    "tgn:placetype":[
        "aat:300386883"
    ]
},
  "bbox": [],
  "geometry": {"coordinates":[-6.183333,36.566667],"type":"Point"}
}