{
  "id": 2362621,
  "type": "Feature",
  "properties": {
    "tgn:hierarchy":[
        "tgn:2362621",
        "tgn:1000001",
        "tgn:2002136",
        "tgn:7012149",
        "tgn:7007828",
        "tgn:7029392"
    ],
    "tgn:id":2362621,
    "tgn:name":"Great Brook",
    "tgn:placetype":[
        "aat:300008699"
    ]
},
  "bbox": [],
  "geometry": {"coordinates":[-72.6167,43.3667],"type":"Point"}
}