{
  "id": 7082290,
  "type": "Feature",
  "properties": {
    "tgn:hierarchy":[
        "tgn:7082290",
        "tgn:7000096",
        "tgn:1000003",
        "tgn:7000084",
        "tgn:7029392"
    ],
    "tgn:id":7082290,
    "tgn:name":"Westgraben",
    "tgn:placetype":[
        "aat:300008699"
    ]
},
  "bbox": [],
  "geometry": {"coordinates":[13.966667,51.883333],"type":"Point"}
}