{
  "id": 7412331,
  "type": "Feature",
  "properties": {
    "tgn:hierarchy":[
        "tgn:7412331",
        "tgn:1000001",
        "tgn:7005596",
        "tgn:7005560",
        "tgn:7029392"
    ],
    "tgn:id":7412331,
    "tgn:name:es":"Paso del Rosario",
    "tgn:placetype":[
        "aat:300008347"
    ]
},
  "bbox": [],
  "geometry": {"coordinates":[-93.608333,17.85],"type":"Point"}
}