{
  "id": 2316770,
  "type": "Feature",
  "properties": {
    "tgn:hierarchy":[
        "tgn:2316770",
        "tgn:1000001",
        "tgn:7012149",
        "tgn:1002540",
        "tgn:7007520",
        "tgn:7029392"
    ],
    "tgn:id":2316770,
    "tgn:name":"Emerald Lake",
    "tgn:placetype":[
        "aat:300008680"
    ]
},
  "bbox": [],
  "geometry": {"coordinates":[-85.6167,43.0167],"type":"Point"}
}