{
  "id": 7067417,
  "type": "Feature",
  "properties": {
    "tgn:hierarchy":[
        "tgn:7067417",
        "tgn:7003692",
        "tgn:1000003",
        "tgn:7000084",
        "tgn:7029392"
    ],
    "tgn:id":7067417,
    "tgn:name":"Stockland",
    "tgn:placetype":[
        "aat:300000206"
    ]
},
  "bbox": [],
  "geometry": {"coordinates":[9.883333,48.083333],"type":"Point"}
}