{
  "id": 7543800,
  "type": "Feature",
  "properties": {
    "tgn:hierarchy":[
        "tgn:7543800",
        "tgn:7001242",
        "tgn:1001059",
        "tgn:7016833",
        "tgn:7029392"
    ],
    "tgn:id":7543800,
    "tgn:name:en":"Tir'at ash Sharq\u0101w\u012byah",
    "tgn:placetype":[
        "aat:300006075"
    ]
},
  "bbox": [],
  "geometry": {"coordinates":[31.421638,31.079566],"type":"Point"}
}