{
  "id": 7015308,
  "type": "Feature",
  "properties": {
    "tgn:hierarchy":[
        "tgn:7015308",
        "tgn:1000001",
        "tgn:7012149",
        "tgn:7007157",
        "tgn:7023900",
        "tgn:1002608",
        "tgn:7029392"
    ],
    "tgn:id":7015308,
    "tgn:name":"Century City",
    "tgn:placetype":[
        "aat:300000745"
    ]
},
  "bbox": [],
  "geometry": {"coordinates":[-118.4167,34.05],"type":"Point"}
}