{
  "id": 7497338,
  "type": "Feature",
  "properties": {
    "tgn:hierarchy":[
        "tgn:7497338",
        "tgn:1000004",
        "tgn:7001009",
        "tgn:1000141",
        "tgn:7029392"
    ],
    "tgn:id":7497338,
    "tgn:name":"Shengang Erhao Qiao",
    "tgn:placetype":[
        "aat:300007836"
    ]
},
  "bbox": [],
  "geometry": {"coordinates":[120.657556,24.245892],"type":"Point"}
}