{
  "id": 7218796,
  "type": "Feature",
  "properties": {
    "tgn:hierarchy":[
        "tgn:7218796",
        "tgn:7011161",
        "tgn:7002674",
        "tgn:1000003",
        "tgn:1000074",
        "tgn:7029392"
    ],
    "tgn:id":7218796,
    "tgn:name":"Remat\u00e1ki",
    "tgn:placetype":[
        "aat:300008699"
    ]
},
  "bbox": [],
  "geometry": {"coordinates":[26.015833,38.3325],"type":"Point"}
}