<<<<<<< HEAD
{
  "id": 2769211,
  "type": "Feature",
  "properties": {
    "tgn:hierarchy":[
        "tgn:2769211",
        "tgn:1000001",
        "tgn:1002724",
        "tgn:7012149",
        "tgn:7007517",
        "tgn:7029392"
    ],
    "tgn:id":2769211,
    "tgn:name":"Whortleberry Pond",
    "tgn:placetype":[
        "aat:300008680"
    ]
},
  "bbox": [],
  "geometry": {"coordinates":[-70.9333,42.1833],"type":"Point"}
}
=======
{"geometry":{"type":"Point","coordinates":[-70.933300,42.183300]},"type":"Feature","properties":{"hierarchy":["tgn:2769211","tgn:1000001","tgn:1002724","tgn:7012149","tgn:7007517","tgn:7029392"],"placetype":["aat:300008680"],"id":2769211,"name:xx":"Whortleberry Pond"}}
>>>>>>> 03f74aca74312dbeaf24d7e61306dd6a786dc3d0
