{
  "id": 1101373,
  "type": "Feature",
  "properties": {
    "tgn:hierarchy":[
        "tgn:1101373",
        "tgn:1003353",
        "tgn:1000004",
        "tgn:7014786",
        "tgn:7029392"
    ],
    "tgn:id":1101373,
    "tgn:name":"Alma-Atinskij zapovednik",
    "tgn:placetype":[
        "aat:300008189"
    ]
},
  "bbox": [],
  "geometry": {"coordinates":[77.4167,43.1667],"type":"Point"}
}