{
  "id": 7230629,
  "type": "Feature",
  "properties": {
    "tgn:hierarchy":[
        "tgn:7230629",
        "tgn:7002681",
        "tgn:7001395",
        "tgn:1000003",
        "tgn:1000074",
        "tgn:7029392"
    ],
    "tgn:id":7230629,
    "tgn:name":"Kal\u00f3yiros, \u00c1kra",
    "tgn:placetype":[
        "aat:300008850"
    ]
},
  "bbox": [],
  "geometry": {"coordinates":[24.266667,37.616667],"type":"Point"}
}