{
  "id": 2644020,
  "type": "Feature",
  "properties": {
    "tgn:hierarchy":[
        "tgn:2644020",
        "tgn:1000001",
        "tgn:7006451",
        "tgn:7012149",
        "tgn:2000101",
        "tgn:7029392"
    ],
    "tgn:id":2644020,
    "tgn:name":"Santa Cruz Wash",
    "tgn:placetype":[
        "aat:300008701"
    ]
},
  "bbox": [],
  "geometry": {"coordinates":[-111.7667,32.7667],"type":"Point"}
}