{
  "id": 7525354,
  "type": "Feature",
  "properties": {
    "tgn:hierarchy":[
        "tgn:7525354",
        "tgn:7001242",
        "tgn:7001311",
        "tgn:7016833",
        "tgn:7029392"
    ],
    "tgn:id":7525354,
    "tgn:name:en":"Daghbag el-'Atshan, W\u00e2di el",
    "tgn:placetype":[
        "aat:300379998"
    ]
},
  "bbox": [],
  "geometry": {"coordinates":[33.834652,25.380353],"type":"Point"}
}