{
  "id": 7570946,
  "type": "Feature",
  "properties": {
    "tgn:hierarchy":[
        "tgn:7570946",
        "tgn:1000004",
        "tgn:7000198",
        "tgn:7000799",
        "tgn:7029392"
    ],
    "tgn:id":7570946,
    "tgn:name:en":"Haraz",
    "tgn:placetype":[
        "aat:300008347"
    ]
},
  "bbox": [],
  "geometry": {"coordinates":[75.783333,33.566667],"type":"Point"}
}