{
  "id": 2745329,
  "type": "Feature",
  "properties": {
    "tgn:hierarchy":[
        "tgn:2745329",
        "tgn:1000001",
        "tgn:7012149",
        "tgn:2000549",
        "tgn:7007252",
        "tgn:7029392"
    ],
    "tgn:id":2745329,
    "tgn:name":"Vinegar Hill",
    "tgn:placetype":[
        "aat:300008798"
    ]
},
  "bbox": [],
  "geometry": {"coordinates":[-87.0167,39.4333],"type":"Point"}
}