{
  "id": 7363882,
  "type": "Feature",
  "properties": {
    "tgn:hierarchy":[
        "tgn:7363882",
        "tgn:1000001",
        "tgn:7005599",
        "tgn:7005560",
        "tgn:7029392"
    ],
    "tgn:id":7363882,
    "tgn:name":"El Morro",
    "tgn:placetype":[
        "aat:300008347"
    ]
},
  "bbox": [],
  "geometry": {"coordinates":[-96.433333,19.85],"type":"Point"}
}