{
  "id": 2043111,
  "type": "Feature",
  "properties": {
    "tgn:hierarchy":[
        "tgn:2043111",
        "tgn:1000001",
        "tgn:7012149",
        "tgn:2000917",
        "tgn:7007256",
        "tgn:7029392"
    ],
    "tgn:id":2043111,
    "tgn:name":"Jordan Hill",
    "tgn:placetype":[
        "aat:300008347"
    ]
},
  "bbox": [],
  "geometry": {"coordinates":[-92.5167,31.85],"type":"Point"}
}