{
  "id": 2488877,
  "type": "Feature",
  "properties": {
    "tgn:hierarchy":[
        "tgn:2488877",
        "tgn:1000001",
        "tgn:7016172",
        "tgn:7012149",
        "tgn:2000165",
        "tgn:7029392"
    ],
    "tgn:id":2488877,
    "tgn:name":"Main Ditch",
    "tgn:placetype":[
        "aat:300006075"
    ]
},
  "bbox": [],
  "geometry": {"coordinates":[-90.85,36.35],"type":"Point"}
}