{
  "id": 2302207,
  "type": "Feature",
  "properties": {
    "tgn:hierarchy":[
        "tgn:2302207",
        "tgn:1000001",
        "tgn:7012149",
        "tgn:7016022",
        "tgn:7007251",
        "tgn:7029392"
    ],
    "tgn:id":2302207,
    "tgn:name":"Dutch Hill",
    "tgn:placetype":[
        "aat:300008798"
    ]
},
  "bbox": [],
  "geometry": {"coordinates":[-89.85,38.2833],"type":"Point"}
}