{
  "id": 2494319,
  "type": "Feature",
  "properties": {
    "tgn:hierarchy":[
        "tgn:2494319",
        "tgn:1000001",
        "tgn:7012149",
        "tgn:2001449",
        "tgn:7007566",
        "tgn:7029392"
    ],
    "tgn:id":2494319,
    "tgn:name":"Martin Canyon",
    "tgn:placetype":[
        "aat:300008761"
    ]
},
  "bbox": [],
  "geometry": {"coordinates":[-107.5667,36.5833],"type":"Point"}
}