{
  "id": 2509719,
  "type": "Feature",
  "properties": {
    "tgn:hierarchy":[
        "tgn:2509719",
        "tgn:1000001",
        "tgn:7012149",
        "tgn:2001963",
        "tgn:7007826",
        "tgn:7029392"
    ],
    "tgn:id":2509719,
    "tgn:name":"Middle Kickapoo Creek",
    "tgn:placetype":[
        "aat:300008706"
    ]
},
  "bbox": [],
  "geometry": {"coordinates":[-99.9333,31.2167],"type":"Point"}
}