{
  "id": 7529310,
  "type": "Feature",
  "properties": {
    "tgn:hierarchy":[
        "tgn:7529310",
        "tgn:7001242",
        "tgn:7001311",
        "tgn:7016833",
        "tgn:7029392"
    ],
    "tgn:id":7529310,
    "tgn:name:en":"Umm Saw\u0101s\u012b, Jabal",
    "tgn:placetype":[
        "aat:300008795"
    ]
},
  "bbox": [],
  "geometry": {"coordinates":[32.888294,27.995461],"type":"Point"}
}