{
  "id": 2599723,
  "type": "Feature",
  "properties": {
    "tgn:hierarchy":[
        "tgn:2599723",
        "tgn:1000001",
        "tgn:7012149",
        "tgn:2002384",
        "tgn:7007923",
        "tgn:7029392"
    ],
    "tgn:id":2599723,
    "tgn:name":"Prospectors Mountain",
    "tgn:placetype":[
        "aat:300008798"
    ]
},
  "bbox": [],
  "geometry": {"coordinates":[-110.8333,43.6333],"type":"Point"}
}