{
  "id": 7395890,
  "type": "Feature",
  "properties": {
    "tgn:hierarchy":[
        "tgn:7395890",
        "tgn:7005584",
        "tgn:1000001",
        "tgn:7005560",
        "tgn:7029392"
    ],
    "tgn:id":7395890,
    "tgn:name":"San Juan",
    "tgn:placetype":[
        "aat:300008347"
    ]
},
  "bbox": [],
  "geometry": {"coordinates":[-100.766667,20.716667],"type":"Point"}
}