{
  "id": 2262895,
  "type": "Feature",
  "properties": {
    "tgn:hierarchy":[
        "tgn:2262895",
        "tgn:1000001",
        "tgn:7006451",
        "tgn:7012149",
        "tgn:2000103",
        "tgn:7029392"
    ],
    "tgn:id":2262895,
    "tgn:name":"Cowboy Tank",
    "tgn:placetype":[
        "aat:300006191"
    ]
},
  "bbox": [],
  "geometry": {"coordinates":[-112.6333,34.6667],"type":"Point"}
}