<<<<<<< HEAD
{
  "id": 7471123,
  "type": "Feature",
  "properties": {
    "tgn:hierarchy":[
        "tgn:7471123",
        "tgn:7468018",
        "tgn:1000004",
        "tgn:1000141",
        "tgn:7029392"
    ],
    "tgn:id":7471123,
    "tgn:name":"Jiushe",
    "tgn:placetype":[
        "aat:300008347"
    ]
},
  "bbox": [],
  "geometry": {"coordinates":[120.549663,23.47894],"type":"Point"}
}
=======
{"geometry":{"type":"Point","coordinates":[120.549663,23.478940]},"type":"Feature","properties":{"hierarchy":["tgn:7471123","tgn:7468018","tgn:1000004","tgn:1000141","tgn:7029392"],"placetype":["aat:300008347"],"id":7471123,"name:xx":"Jiushe"}}
>>>>>>> 03f74aca74312dbeaf24d7e61306dd6a786dc3d0
