{
  "id": 2552753,
  "type": "Feature",
  "properties": {
    "tgn:hierarchy":[
        "tgn:2552753",
        "tgn:1000001",
        "tgn:7012149",
        "tgn:2002289",
        "tgn:7013961",
        "tgn:7029392"
    ],
    "tgn:id":2552753,
    "tgn:name":"Nye",
    "tgn:placetype":[
        "aat:300008347"
    ]
},
  "bbox": [],
  "geometry": {"coordinates":[-82.0333,38.3333],"type":"Point"}
}