{
  "id": 7223644,
  "type": "Feature",
  "properties": {
    "tgn:hierarchy":[
        "tgn:7223644",
        "tgn:7011164",
        "tgn:7002674",
        "tgn:1000003",
        "tgn:1000074",
        "tgn:7029392"
    ],
    "tgn:id":7223644,
    "tgn:name":"Sardh\u00e9lla, \u00c1kra",
    "tgn:placetype":[
        "aat:300008850"
    ]
},
  "bbox": [],
  "geometry": {"coordinates":[26.566667,37.383333],"type":"Point"}
}