{
  "id": 7236622,
  "type": "Feature",
  "properties": {
    "tgn:hierarchy":[
        "tgn:7236622",
        "tgn:7002741",
        "tgn:7017076",
        "tgn:1000003",
        "tgn:1000074",
        "tgn:7029392"
    ],
    "tgn:id":7236622,
    "tgn:name":"\u00c1no Aiyial\u00f3s",
    "tgn:placetype":[
        "aat:300008347"
    ]
},
  "bbox": [],
  "geometry": {"coordinates":[22.383333,38.116667],"type":"Point"}
}