{
  "id": 7017390,
  "type": "Feature",
  "properties": {
    "tgn:hierarchy":[
        "tgn:7017390",
        "tgn:1000003",
        "tgn:7006667",
        "tgn:7029392"
    ],
    "tgn:id":7017390,
    "tgn:name":"Veles",
    "tgn:placetype":[
        "aat:300387064",
        "aat:300265612",
        "aat:300387081"
    ]
},
  "bbox": [],
  "geometry": {"coordinates":[21.76278,41.77583],"type":"Point"}
}