{
  "id": 2228190,
  "type": "Feature",
  "properties": {
    "tgn:hierarchy":[
        "tgn:2228190",
        "tgn:1000001",
        "tgn:7012149",
        "tgn:7007157",
        "tgn:2000189",
        "tgn:7029392"
    ],
    "tgn:id":2228190,
    "tgn:name":"Cedar Cove",
    "tgn:placetype":[
        "aat:300008761"
    ]
},
  "bbox": [],
  "geometry": {"coordinates":[-122.8667,41.85],"type":"Point"}
}