{
  "id": 1012319,
  "type": "Feature",
  "properties": {
    "tgn:hierarchy":[
        "tgn:1012319",
        "tgn:1008058",
        "tgn:1001914",
        "tgn:1000002",
        "tgn:1000059",
        "tgn:7029392"
    ],
    "tgn:id":1012319,
    "tgn:name":"Piedras, Punta",
    "tgn:placetype":[
        "aat:300386846"
    ]
},
  "bbox": [],
  "geometry": {"coordinates":[-61.6667,10.6667],"type":"Point"}
}