{
  "id": 7099500,
  "type": "Feature",
  "properties": {
    "tgn:hierarchy":[
        "tgn:7099500",
        "tgn:1000003",
        "tgn:7003677",
        "tgn:7000084",
        "tgn:7029392"
    ],
    "tgn:id":7099500,
    "tgn:name":"Spielberg",
    "tgn:placetype":[
        "aat:300000206"
    ]
},
  "bbox": [],
  "geometry": {"coordinates":[9.033333,51.916667],"type":"Point"}
}