{
  "id": 7063710,
  "type": "Feature",
  "properties": {
    "tgn:hierarchy":[
        "tgn:7063710",
        "tgn:7003692",
        "tgn:1000003",
        "tgn:7000084",
        "tgn:7029392"
    ],
    "tgn:id":7063710,
    "tgn:name":"Aulfingen",
    "tgn:placetype":[
        "aat:300008347"
    ]
},
  "bbox": [],
  "geometry": {"coordinates":[8.666667,47.883333],"type":"Point"}
}