{
  "id": 7133741,
  "type": "Feature",
  "properties": {
    "tgn:hierarchy":[
        "tgn:7133741",
        "tgn:1000003",
        "tgn:7003677",
        "tgn:7000084",
        "tgn:7029392"
    ],
    "tgn:id":7133741,
    "tgn:name":"Bahnhof Neersen",
    "tgn:placetype":[
        "aat:300007783"
    ]
},
  "bbox": [],
  "geometry": {"coordinates":[6.483333,51.233333],"type":"Point"}
}