{
  "id": 7446659,
  "type": "Feature",
  "properties": {
    "tgn:hierarchy":[
        "tgn:7446659",
        "tgn:7002445",
        "tgn:1000003",
        "tgn:7012077",
        "tgn:7008591",
        "tgn:7029392"
    ],
    "tgn:id":7446659,
    "tgn:name:en":"Sandquay",
    "tgn:placetype":[
        "aat:300008347"
    ]
},
  "bbox": [],
  "geometry": {"coordinates":[-3.583333,50.366667],"type":"Point"}
}