{
  "id": 7526996,
  "type": "Feature",
  "properties": {
    "tgn:hierarchy":[
        "tgn:7526996",
        "tgn:7001242",
        "tgn:7016833",
        "tgn:7001335",
        "tgn:7029392"
    ],
    "tgn:id":7526996,
    "tgn:name:en":"Wukhami, R\u00e2s el-",
    "tgn:placetype":[
        "aat:300008795"
    ]
},
  "bbox": [],
  "geometry": {"coordinates":[33.533333,30.366667],"type":"Point"}
}