{
  "id": 2428375,
  "type": "Feature",
  "properties": {
    "tgn:hierarchy":[
        "tgn:2428375",
        "tgn:1000001",
        "tgn:7012149",
        "tgn:2001043",
        "tgn:7007521",
        "tgn:7029392"
    ],
    "tgn:id":2428375,
    "tgn:name":"Judicial Ditch Number Twenty",
    "tgn:placetype":[
        "aat:300006075"
    ]
},
  "bbox": [],
  "geometry": {"coordinates":[-97.0167,48.25],"type":"Point"}
}