{
  "id": 2113627,
  "type": "Feature",
  "properties": {
    "tgn:hierarchy":[
        "tgn:2113627",
        "tgn:1000001",
        "tgn:7012149",
        "tgn:2002194",
        "tgn:7007919",
        "tgn:7029392"
    ],
    "tgn:id":2113627,
    "tgn:name":"Phillip",
    "tgn:placetype":[
        "aat:300008347",
        "aat:300387210"
    ]
},
  "bbox": [],
  "geometry": {"coordinates":[-82.2667,36.6667],"type":"Point"}
}