{
  "id": 7211819,
  "type": "Feature",
  "properties": {
    "tgn:hierarchy":[
        "tgn:7211819",
        "tgn:1000003",
        "tgn:7003676",
        "tgn:7000084",
        "tgn:7029392"
    ],
    "tgn:id":7211819,
    "tgn:name":"Betenbach",
    "tgn:placetype":[
        "aat:300008699"
    ]
},
  "bbox": [],
  "geometry": {"coordinates":[9.716667,53.333333],"type":"Point"}
}