{
  "id": 2174832,
  "type": "Feature",
  "properties": {
    "tgn:hierarchy":[
        "tgn:2174832",
        "tgn:1000001",
        "tgn:7012149",
        "tgn:7007157",
        "tgn:7029392"
    ],
    "tgn:id":2174832,
    "tgn:name":"Bitterwater Valley",
    "tgn:placetype":[
        "aat:300008761"
    ]
},
  "bbox": [],
  "geometry": {"coordinates":[-120.1333,35.5833],"type":"Point"}
}