{
  "id": 7226778,
  "type": "Feature",
  "properties": {
    "tgn:hierarchy":[
        "tgn:7226778",
        "tgn:7011270",
        "tgn:7002674",
        "tgn:1000003",
        "tgn:1000074",
        "tgn:7029392"
    ],
    "tgn:id":7226778,
    "tgn:name":"Mn\u00edmata, \u00c1kra",
    "tgn:placetype":[
        "aat:300386846"
    ]
},
  "bbox": [],
  "geometry": {"coordinates":[24.95,37.483333],"type":"Point"}
}