{
  "id": 2097310,
  "type": "Feature",
  "properties": {
    "tgn:hierarchy":[
        "tgn:2097310",
        "tgn:1000001",
        "tgn:2001806",
        "tgn:7012149",
        "tgn:7007713",
        "tgn:7029392"
    ],
    "tgn:id":2097310,
    "tgn:name":"Lane",
    "tgn:placetype":[
        "aat:300008347"
    ]
},
  "bbox": [],
  "geometry": {"coordinates":[-98.4167,44.0667],"type":"Point"}
}