{
  "id": 7378761,
  "type": "Feature",
  "properties": {
    "tgn:hierarchy":[
        "tgn:7378761",
        "tgn:7005581",
        "tgn:1000001",
        "tgn:7005560",
        "tgn:7029392"
    ],
    "tgn:id":7378761,
    "tgn:name":"Los Pozos",
    "tgn:placetype":[
        "aat:300008347"
    ]
},
  "bbox": [],
  "geometry": {"coordinates":[-105.966667,29.083333],"type":"Point"}
}