{
  "id": 2405886,
  "type": "Feature",
  "properties": {
    "tgn:hierarchy":[
        "tgn:2405886",
        "tgn:1000001",
        "tgn:7012149",
        "tgn:1002636",
        "tgn:7007708",
        "tgn:7029392"
    ],
    "tgn:id":2405886,
    "tgn:name":"Hullt",
    "tgn:placetype":[
        "aat:300008347"
    ]
},
  "bbox": [],
  "geometry": {"coordinates":[-122.6333,44.8833],"type":"Point"}
}