{
  "id": 7584562,
  "type": "Feature",
  "properties": {
    "tgn:hierarchy":[
        "tgn:7584562",
        "tgn:1000004",
        "tgn:7000198",
        "tgn:1001894",
        "tgn:7029392"
    ],
    "tgn:id":7584562,
    "tgn:name:en":"Durg\u0101pur",
    "tgn:placetype":[
        "aat:300008347"
    ]
},
  "bbox": [],
  "geometry": {"coordinates":[78.919074,24.784372],"type":"Point"}
}