{
  "id": 7381141,
  "type": "Feature",
  "properties": {
    "tgn:hierarchy":[
        "tgn:7381141",
        "tgn:7005585",
        "tgn:1000001",
        "tgn:7005560",
        "tgn:7029392"
    ],
    "tgn:id":7381141,
    "tgn:name":"Media Luna, Cerro",
    "tgn:placetype":[
        "aat:300008795"
    ]
},
  "bbox": [],
  "geometry": {"coordinates":[-99.633333,17.85],"type":"Point"}
}