{
  "id": 7275235,
  "type": "Feature",
  "properties": {
    "tgn:hierarchy":[
        "tgn:7275235",
        "tgn:1001702",
        "tgn:1000049",
        "tgn:1000002",
        "tgn:7029392"
    ],
    "tgn:id":7275235,
    "tgn:name":"Unicornio, Islas",
    "tgn:placetype":[
        "aat:300008791"
    ]
},
  "bbox": [],
  "geometry": {"coordinates":[-72.383333,-52.633333],"type":"Point"}
}