{
  "id": 7270109,
  "type": "Feature",
  "properties": {
    "tgn:hierarchy":[
        "tgn:7270109",
        "tgn:1000003",
        "tgn:7006951",
        "tgn:7016845",
        "tgn:7029392"
    ],
    "tgn:id":7270109,
    "tgn:name:nl":"Muidertrekvaart",
    "tgn:placetype":[
        "aat:300006075"
    ]
},
  "bbox": [],
  "geometry": {"coordinates":[5.066667,52.333333],"type":"Point"}
}