{
  "id": 2756488,
  "type": "Feature",
  "properties": {
    "tgn:hierarchy":[
        "tgn:2756488",
        "tgn:1000001",
        "tgn:7012149",
        "tgn:2000238",
        "tgn:7007158",
        "tgn:7029392"
    ],
    "tgn:id":2756488,
    "tgn:name":"Weller",
    "tgn:placetype":[
        "aat:300008347"
    ]
},
  "bbox": [],
  "geometry": {"coordinates":[-105.6167,39.4333],"type":"Point"}
}