{
  "id": 1063821,
  "type": "Feature",
  "properties": {
    "tgn:hierarchy":[
        "tgn:1063821",
        "tgn:1000003",
        "tgn:7003780",
        "tgn:1000097",
        "tgn:7029392"
    ],
    "tgn:id":1063821,
    "tgn:name":"Valskog",
    "tgn:placetype":[
        "aat:300008347"
    ]
},
  "bbox": [],
  "geometry": {"coordinates":[15.9667,59.45],"type":"Point"}
}