<<<<<<< HEAD
{
  "id": 7377181,
  "type": "Feature",
  "properties": {
    "tgn:hierarchy":[
        "tgn:7377181",
        "tgn:7005581",
        "tgn:1000001",
        "tgn:7005560",
        "tgn:7029392"
    ],
    "tgn:id":7377181,
    "tgn:name":"Rancho Las Anitas",
    "tgn:placetype":[
        "aat:300000241"
    ]
},
  "bbox": [],
  "geometry": {"coordinates":[-105.983333,28.75],"type":"Point"}
}
=======
{"geometry":{"type":"Point","coordinates":[-105.983333,28.750000]},"type":"Feature","properties":{"hierarchy":["tgn:7377181","tgn:7005581","tgn:1000001","tgn:7005560","tgn:7029392"],"placetype":["aat:300000241"],"id":7377181,"name:xx":"Rancho Las Anitas"}}
>>>>>>> 03f74aca74312dbeaf24d7e61306dd6a786dc3d0
