{
  "id": 7377181,
  "type": "Feature",
  "properties": {
    "tgn:hierarchy":[
        "tgn:7377181",
        "tgn:7005581",
        "tgn:1000001",
        "tgn:7005560",
        "tgn:7029392"
    ],
    "tgn:id":7377181,
    "tgn:name":"Rancho Las Anitas",
    "tgn:placetype":[
        "aat:300000241"
    ]
},
  "bbox": [],
  "geometry": {"coordinates":[-105.983333,28.75],"type":"Point"}
}