{
  "id": 1024083,
  "type": "Feature",
  "properties": {
    "tgn:hierarchy":[
        "tgn:1024083",
        "tgn:1001396",
        "tgn:7002560",
        "tgn:1000051",
        "tgn:1000002",
        "tgn:7029392"
    ],
    "tgn:id":1024083,
    "tgn:name":"Babahoyo",
    "tgn:placetype":[
        "aat:300008347",
        "aat:300008389",
        "aat:300387223",
        "aat:300387286"
    ]
},
  "bbox": [],
  "geometry": {"coordinates":[-79.534,-1.802],"type":"Point"}
}