{
  "id": 2480195,
  "type": "Feature",
  "properties": {
    "tgn:hierarchy":[
        "tgn:2480195",
        "tgn:1000001",
        "tgn:1002213",
        "tgn:7012149",
        "tgn:7007710",
        "tgn:7029392"
    ],
    "tgn:id":2480195,
    "tgn:name":"Lake Neshaminy",
    "tgn:placetype":[
        "aat:300006191"
    ]
},
  "bbox": [],
  "geometry": {"coordinates":[-74.95,40.2167],"type":"Point"}
}