{
  "id": 7453406,
  "type": "Feature",
  "properties": {
    "tgn:hierarchy":[
        "tgn:7453406",
        "tgn:7002445",
        "tgn:1000003",
        "tgn:7008127",
        "tgn:7008591",
        "tgn:7029392"
    ],
    "tgn:id":7453406,
    "tgn:name:en":"Dipton",
    "tgn:placetype":[
        "aat:300008347"
    ]
},
  "bbox": [],
  "geometry": {"coordinates":[-1.75,54.883333],"type":"Point"}
}