{
  "id": 1093706,
  "type": "Feature",
  "properties": {
    "tgn:hierarchy":[
        "tgn:1093706",
        "tgn:7001242",
        "tgn:7016749",
        "tgn:1000193",
        "tgn:7029392"
    ],
    "tgn:id":1093706,
    "tgn:name":"Tugela",
    "tgn:placetype":[
        "aat:300008347"
    ]
},
  "bbox": [],
  "geometry": {"coordinates":[31.4167,-29.1833],"type":"Point"}
}