{
  "id": 2497835,
  "type": "Feature",
  "properties": {
    "tgn:hierarchy":[
        "tgn:2497835",
        "tgn:1000001",
        "tgn:7012149",
        "tgn:2002376",
        "tgn:7007923",
        "tgn:7029392"
    ],
    "tgn:id":2497835,
    "tgn:name":"Mayfield Creek",
    "tgn:placetype":[
        "aat:300008706"
    ]
},
  "bbox": [],
  "geometry": {"coordinates":[-110.7833,42.1333],"type":"Point"}
}