{
  "id": 7276561,
  "type": "Feature",
  "properties": {
    "tgn:hierarchy":[
        "tgn:7276561",
        "tgn:1001699",
        "tgn:1000049",
        "tgn:1000002",
        "tgn:7029392"
    ],
    "tgn:id":7276561,
    "tgn:name":"Lago Tres Mar\u00edas",
    "tgn:placetype":[
        "aat:300008680"
    ]
},
  "bbox": [],
  "geometry": {"coordinates":[-73.8325,-42.966667],"type":"Point"}
}