{
  "id": 7261764,
  "type": "Feature",
  "properties": {
    "tgn:hierarchy":[
        "tgn:7261764",
        "tgn:1000003",
        "tgn:7003613",
        "tgn:7016845",
        "tgn:7029392"
    ],
    "tgn:id":7261764,
    "tgn:name:nl":"Haansvaart",
    "tgn:placetype":[
        "aat:300006075"
    ]
},
  "bbox": [],
  "geometry": {"coordinates":[6.85,53.233333],"type":"Point"}
}