{
  "id": 2364970,
  "type": "Feature",
  "properties": {
    "tgn:hierarchy":[
        "tgn:2364970",
        "tgn:1000001",
        "tgn:7006451",
        "tgn:2000093",
        "tgn:7012149",
        "tgn:7029392"
    ],
    "tgn:id":2364970,
    "tgn:name":"Greenhorn Tank",
    "tgn:placetype":[
        "aat:300006191"
    ]
},
  "bbox": [],
  "geometry": {"coordinates":[-111.5667,34.2833],"type":"Point"}
}