{
  "id": 2159380,
  "type": "Feature",
  "properties": {
    "tgn:hierarchy":[
        "tgn:2159380",
        "tgn:1000001",
        "tgn:7012149",
        "tgn:2002042",
        "tgn:7007826",
        "tgn:7029392"
    ],
    "tgn:id":2159380,
    "tgn:name":"Bee Cove Creek",
    "tgn:placetype":[
        "aat:300008706"
    ]
},
  "bbox": [],
  "geometry": {"coordinates":[-98.45,31.3333],"type":"Point"}
}