<<<<<<< HEAD
{
  "id": 7171558,
  "type": "Feature",
  "properties": {
    "tgn:hierarchy":[
        "tgn:7171558",
        "tgn:7003669",
        "tgn:1000003",
        "tgn:7000084",
        "tgn:7029392"
    ],
    "tgn:id":7171558,
    "tgn:name":"Hillstett",
    "tgn:placetype":[
        "aat:300008347"
    ]
},
  "bbox": [],
  "geometry": {"coordinates":[12.483333,49.333333],"type":"Point"}
}
=======
{"geometry":{"type":"Point","coordinates":[12.483333,49.333333]},"type":"Feature","properties":{"hierarchy":["tgn:7171558","tgn:7003669","tgn:1000003","tgn:7000084","tgn:7029392"],"placetype":["aat:300008347"],"id":7171558,"name:xx":"Hillstett"}}
>>>>>>> 03f74aca74312dbeaf24d7e61306dd6a786dc3d0
