{
  "id": 7225342,
  "type": "Feature",
  "properties": {
    "tgn:hierarchy":[
        "tgn:7225342",
        "tgn:7002752",
        "tgn:7001399",
        "tgn:1000003",
        "tgn:1000074",
        "tgn:7029392"
    ],
    "tgn:id":7225342,
    "tgn:name":"Stef\u00e1nion",
    "tgn:placetype":[
        "aat:300008347"
    ]
},
  "bbox": [],
  "geometry": {"coordinates":[21.301667,39.678056],"type":"Point"}
}