{
  "id": 7547239,
  "type": "Feature",
  "properties": {
    "tgn:hierarchy":[
        "tgn:7547239",
        "tgn:1000004",
        "tgn:7000198",
        "tgn:7001797",
        "tgn:7029392"
    ],
    "tgn:id":7547239,
    "tgn:name:en":"Arumb\u0101v\u016br",
    "tgn:placetype":[
        "aat:300008347"
    ]
},
  "bbox": [],
  "geometry": {"coordinates":[78.733333,11.383333],"type":"Point"}
}