{
  "id": 7155567,
  "type": "Feature",
  "properties": {
    "tgn:hierarchy":[
        "tgn:7155567",
        "tgn:7003669",
        "tgn:1000003",
        "tgn:7000084",
        "tgn:7029392"
    ],
    "tgn:id":7155567,
    "tgn:name":"Kleinholzen",
    "tgn:placetype":[
        "aat:300008347"
    ]
},
  "bbox": [],
  "geometry": {"coordinates":[12.166667,47.866667],"type":"Point"}
}