{
  "id": 2497183,
  "type": "Feature",
  "properties": {
    "tgn:hierarchy":[
        "tgn:2497183",
        "tgn:1000001",
        "tgn:7012149",
        "tgn:2001969",
        "tgn:7007826",
        "tgn:7029392"
    ],
    "tgn:id":2497183,
    "tgn:name":"Maverick Draw",
    "tgn:placetype":[
        "aat:300008761"
    ]
},
  "bbox": [],
  "geometry": {"coordinates":[-104.1833,31.5833],"type":"Point"}
}