<<<<<<< HEAD
{
  "id": 2152465,
  "type": "Feature",
  "properties": {
    "tgn:hierarchy":[
        "tgn:2152465",
        "tgn:7016099",
        "tgn:1000001",
        "tgn:7012149",
        "tgn:7007516",
        "tgn:7029392"
    ],
    "tgn:id":2152465,
    "tgn:name":"Bay Shore Park",
    "tgn:placetype":[
        "aat:300008347"
    ]
},
  "bbox": [],
  "geometry": {"coordinates":[-76.4167,39.2],"type":"Point"}
}
=======
{"geometry":{"type":"Point","coordinates":[-76.416700,39.200000]},"type":"Feature","properties":{"hierarchy":["tgn:2152465","tgn:7016099","tgn:1000001","tgn:7012149","tgn:7007516","tgn:7029392"],"placetype":["aat:300008347"],"id":2152465,"name:xx":"Bay Shore Park"}}
>>>>>>> 03f74aca74312dbeaf24d7e61306dd6a786dc3d0
