{
  "id": 7485038,
  "type": "Feature",
  "properties": {
    "tgn:hierarchy":[
        "tgn:7485038",
        "tgn:7468018",
        "tgn:1000004",
        "tgn:1000141",
        "tgn:7029392"
    ],
    "tgn:id":7485038,
    "tgn:name":"Dingshiguping",
    "tgn:placetype":[
        "aat:300008347"
    ]
},
  "bbox": [],
  "geometry": {"coordinates":[120.637222,23.534167],"type":"Point"}
}