{
  "id": 7230869,
  "type": "Feature",
  "properties": {
    "tgn:hierarchy":[
        "tgn:7230869",
        "tgn:7002690",
        "tgn:7012056",
        "tgn:1000003",
        "tgn:1000074",
        "tgn:7029392"
    ],
    "tgn:id":7230869,
    "tgn:name":"Khelian\u00e1",
    "tgn:placetype":[
        "aat:300008347"
    ]
},
  "bbox": [],
  "geometry": {"coordinates":[24.833333,35.35],"type":"Point"}
}