{
  "id": 1092710,
  "type": "Feature",
  "properties": {
    "tgn:hierarchy":[
        "tgn:1092710",
        "tgn:7001242",
        "tgn:1001747",
        "tgn:1000192",
        "tgn:7029392"
    ],
    "tgn:id":1092710,
    "tgn:name":"Golweyn",
    "tgn:placetype":[
        "aat:300008347"
    ]
},
  "bbox": [],
  "geometry": {"coordinates":[44.55,1.6333],"type":"Point"}
}