{
  "id": 1082783,
  "type": "Feature",
  "properties": {
    "tgn:hierarchy":[
        "tgn:1082783",
        "tgn:7000316",
        "tgn:1001952",
        "tgn:1000004",
        "tgn:1000128",
        "tgn:7029392"
    ],
    "tgn:id":1082783,
    "tgn:name":"Kanowit",
    "tgn:placetype":[
        "aat:300008347"
    ]
},
  "bbox": [],
  "geometry": {"coordinates":[112.25,2.05],"type":"Point"}
}