{
  "id": 7400330,
  "type": "Feature",
  "properties": {
    "tgn:hierarchy":[
        "tgn:7400330",
        "tgn:1000001",
        "tgn:7005599",
        "tgn:7005560",
        "tgn:7029392"
    ],
    "tgn:id":7400330,
    "tgn:name":"El Higo",
    "tgn:placetype":[
        "aat:300008347"
    ]
},
  "bbox": [],
  "geometry": {"coordinates":[-97.766667,21.45],"type":"Point"}
}