{
  "id": 1114332,
  "type": "Feature",
  "properties": {
    "tgn:hierarchy":[
        "tgn:1114332",
        "tgn:1000004",
        "tgn:1001390",
        "tgn:1000111",
        "tgn:7029392"
    ],
    "tgn:id":1114332,
    "tgn:name":"Liaohe Kou",
    "tgn:placetype":[
        "aat:300266571"
    ]
},
  "bbox": [],
  "geometry": {"coordinates":[122.15,40.65],"type":"Point"}
}