{
  "id": 7233788,
  "type": "Feature",
  "properties": {
    "tgn:hierarchy":[
        "tgn:7233788",
        "tgn:7002741",
        "tgn:7017076",
        "tgn:1000003",
        "tgn:1000074",
        "tgn:7029392"
    ],
    "tgn:id":7233788,
    "tgn:name":"Alaton\u00edsi",
    "tgn:placetype":[
        "aat:300008791"
    ]
},
  "bbox": [],
  "geometry": {"coordinates":[22.866667,38.233333],"type":"Point"}
}