{
  "id": 2636600,
  "type": "Feature",
  "properties": {
    "tgn:hierarchy":[
        "tgn:2636600",
        "tgn:1000001",
        "tgn:7012149",
        "tgn:2001709",
        "tgn:7007708",
        "tgn:7029392"
    ],
    "tgn:id":2636600,
    "tgn:name":"Sage Hen Hill Reservoir",
    "tgn:placetype":[
        "aat:300006191"
    ]
},
  "bbox": [],
  "geometry": {"coordinates":[-119.2833,43.5167],"type":"Point"}
}