{
  "id": 2390760,
  "type": "Feature",
  "properties": {
    "tgn:hierarchy":[
        "tgn:2390760",
        "tgn:1000001",
        "tgn:2001430",
        "tgn:7012149",
        "tgn:7007566",
        "tgn:7029392"
    ],
    "tgn:id":2390760,
    "tgn:name":"Highway Mill",
    "tgn:placetype":[
        "aat:300008347"
    ]
},
  "bbox": [],
  "geometry": {"coordinates":[-104.8333,33.35],"type":"Point"}
}