{
  "id": 1056661,
  "type": "Feature",
  "properties": {
    "tgn:hierarchy":[
        "tgn:1056661",
        "tgn:1000003",
        "tgn:7006618",
        "tgn:7006542",
        "tgn:7029392"
    ],
    "tgn:id":1056661,
    "tgn:name":"Mai\u0161iagala",
    "tgn:placetype":[
        "aat:300008347"
    ]
},
  "bbox": [],
  "geometry": {"coordinates":[25.0667,54.8667],"type":"Point"}
}