{
  "id": 7095438,
  "type": "Feature",
  "properties": {
    "tgn:hierarchy":[
        "tgn:7095438",
        "tgn:7003692",
        "tgn:1000003",
        "tgn:7000084",
        "tgn:7029392"
    ],
    "tgn:id":7095438,
    "tgn:name":"Schw\u00f6rershof",
    "tgn:placetype":[
        "aat:300000206"
    ]
},
  "bbox": [],
  "geometry": {"coordinates":[8.15,47.983333],"type":"Point"}
}