{
  "id": 2209727,
  "type": "Feature",
  "properties": {
    "tgn:hierarchy":[
        "tgn:2209727",
        "tgn:1000001",
        "tgn:7012149",
        "tgn:2001969",
        "tgn:7007826",
        "tgn:7029392"
    ],
    "tgn:id":2209727,
    "tgn:name":"Burro Canyon",
    "tgn:placetype":[
        "aat:300008761"
    ]
},
  "bbox": [],
  "geometry": {"coordinates":[-104.6833,31.5833],"type":"Point"}
}