{
  "id": 2561582,
  "type": "Feature",
  "properties": {
    "tgn:hierarchy":[
        "tgn:2561582",
        "tgn:7002659",
        "tgn:1000001",
        "tgn:7012149",
        "tgn:2000040",
        "tgn:7029392"
    ],
    "tgn:id":2561582,
    "tgn:name":"Osment Pond",
    "tgn:placetype":[
        "aat:300006191"
    ]
},
  "bbox": [],
  "geometry": {"coordinates":[-85.2667,32.6833],"type":"Point"}
}