{
  "id": 2179546,
  "type": "Feature",
  "properties": {
    "tgn:hierarchy":[
        "tgn:2179546",
        "tgn:1000001",
        "tgn:7012149",
        "tgn:2001706",
        "tgn:7007708",
        "tgn:7029392"
    ],
    "tgn:id":2179546,
    "tgn:name":"Bland Branch",
    "tgn:placetype":[
        "aat:300008699"
    ]
},
  "bbox": [],
  "geometry": {"coordinates":[-123.1167,42.95],"type":"Point"}
}