{
  "id": 7302269,
  "type": "Feature",
  "properties": {
    "tgn:hierarchy":[
        "tgn:7302269",
        "tgn:7002759",
        "tgn:7008909",
        "tgn:1000003",
        "tgn:1000095",
        "tgn:7029392"
    ],
    "tgn:id":7302269,
    "tgn:name":"Nocito",
    "tgn:placetype":[
        "aat:300008347"
    ]
},
  "bbox": [],
  "geometry": {"coordinates":[-0.253514,42.321174],"type":"Point"}
}