<<<<<<< HEAD
{
  "id": 2157728,
  "type": "Feature",
  "properties": {
    "tgn:hierarchy":[
        "tgn:2157728",
        "tgn:1000001",
        "tgn:7016172",
        "tgn:7012149",
        "tgn:2000127",
        "tgn:7029392"
    ],
    "tgn:id":2157728,
    "tgn:name":"Beaver Fork Lake",
    "tgn:placetype":[
        "aat:300006191"
    ]
},
  "bbox": [],
  "geometry": {"coordinates":[-92.4333,35.1333],"type":"Point"}
}
=======
{"geometry":{"type":"Point","coordinates":[-92.433300,35.133300]},"type":"Feature","properties":{"hierarchy":["tgn:2157728","tgn:1000001","tgn:7016172","tgn:7012149","tgn:2000127","tgn:7029392"],"placetype":["aat:300006191"],"id":2157728,"name:xx":"Beaver Fork Lake"}}
>>>>>>> 03f74aca74312dbeaf24d7e61306dd6a786dc3d0
