{
  "id": 2725371,
  "type": "Feature",
  "properties": {
    "tgn:hierarchy":[
        "tgn:2725371",
        "tgn:1000001",
        "tgn:7012149",
        "tgn:2002118",
        "tgn:7007827",
        "tgn:7029392"
    ],
    "tgn:id":2725371,
    "tgn:name":"Tooele Fork",
    "tgn:placetype":[
        "aat:300008761"
    ]
},
  "bbox": [],
  "geometry": {"coordinates":[-112.1667,40.4833],"type":"Point"}
}