{
  "id": 1035483,
  "type": "Feature",
  "properties": {
    "tgn:hierarchy":[
        "tgn:1035483",
        "tgn:1000003",
        "tgn:1000070",
        "tgn:7002897",
        "tgn:7029392"
    ],
    "tgn:id":1035483,
    "tgn:name":"Saint Paul-Trois-Ch\u00e2teaux",
    "tgn:placetype":[
        "aat:300008347"
    ]
},
  "bbox": [],
  "geometry": {"coordinates":[4.7667,44.35],"type":"Point"}
}