{
  "id": 2134594,
  "type": "Feature",
  "properties": {
    "tgn:hierarchy":[
        "tgn:2134594",
        "tgn:1000001",
        "tgn:2000458",
        "tgn:7012149",
        "tgn:7007250",
        "tgn:7029392"
    ],
    "tgn:id":2134594,
    "tgn:name":"Antelope Butte",
    "tgn:placetype":[
        "aat:300008798"
    ]
},
  "bbox": [],
  "geometry": {"coordinates":[-113.1167,43.25],"type":"Point"}
}