{
  "id": 7200996,
  "type": "Feature",
  "properties": {
    "tgn:hierarchy":[
        "tgn:7200996",
        "tgn:1000003",
        "tgn:7003677",
        "tgn:7000084",
        "tgn:7029392"
    ],
    "tgn:id":7200996,
    "tgn:name":"Bahnhof Dortmund-Kirchh\u00f6rde",
    "tgn:placetype":[
        "aat:300007783"
    ]
},
  "bbox": [],
  "geometry": {"coordinates":[7.446667,51.451389],"type":"Point"}
}