{
  "id": 1054488,
  "type": "Feature",
  "properties": {
    "tgn:hierarchy":[
        "tgn:1054488",
        "tgn:1000003",
        "tgn:7012067",
        "tgn:7006660",
        "tgn:7029392"
    ],
    "tgn:id":1054488,
    "tgn:name":"Izvaryne",
    "tgn:placetype":[
        "aat:300008347"
    ]
},
  "bbox": [],
  "geometry": {"coordinates":[39.8667,48.2833],"type":"Point"}
}