{
  "id": 2083724,
  "type": "Feature",
  "properties": {
    "tgn:hierarchy":[
        "tgn:2083724",
        "tgn:1000001",
        "tgn:7012149",
        "tgn:2001676",
        "tgn:7007707",
        "tgn:7029392"
    ],
    "tgn:id":2083724,
    "tgn:name":"Okfuskee",
    "tgn:placetype":[
        "aat:300008347",
        "aat:300387210"
    ]
},
  "bbox": [],
  "geometry": {"coordinates":[-96.2167,35.5833],"type":"Point"}
}