{
  "id": 7449139,
  "type": "Feature",
  "properties": {
    "tgn:hierarchy":[
        "tgn:7449139",
        "tgn:7002445",
        "tgn:1000003",
        "tgn:7008117",
        "tgn:7008591",
        "tgn:7029392"
    ],
    "tgn:id":7449139,
    "tgn:name:en":"Sebergham",
    "tgn:placetype":[
        "aat:300008347"
    ]
},
  "bbox": [],
  "geometry": {"coordinates":[-2.983333,54.75],"type":"Point"}
}