{
  "id": 7516678,
  "type": "Feature",
  "properties": {
    "tgn:hierarchy":[
        "tgn:7516678",
        "tgn:1008380",
        "tgn:1000226",
        "tgn:7016827",
        "tgn:1000006",
        "tgn:7029392"
    ],
    "tgn:id":7516678,
    "tgn:name:en":"Mangaone Stream",
    "tgn:placetype":[
        "aat:300008699"
    ]
},
  "bbox": [],
  "geometry": {"coordinates":[174.733333,-38.766667],"type":"Point"}
}