{
  "id": 2675546,
  "type": "Feature",
  "properties": {
    "tgn:hierarchy":[
        "tgn:2675546",
        "tgn:1000001",
        "tgn:1002271",
        "tgn:7012149",
        "tgn:7007920",
        "tgn:7029392"
    ],
    "tgn:id":2675546,
    "tgn:name":"Solmar Lake",
    "tgn:placetype":[
        "aat:300006191"
    ]
},
  "bbox": [],
  "geometry": {"coordinates":[-123.2167,48.0833],"type":"Point"}
}