{
  "id": 7489522,
  "type": "Feature",
  "properties": {
    "tgn:hierarchy":[
        "tgn:7489522",
        "tgn:7488858",
        "tgn:1000004",
        "tgn:1000141",
        "tgn:7029392"
    ],
    "tgn:id":7489522,
    "tgn:name:en":"Jitsugetsu, Lake",
    "tgn:placetype":[
        "aat:300008680"
    ]
},
  "bbox": [],
  "geometry": {"coordinates":[120.918296,23.860983],"type":"Point"}
}