{
  "id": 7399772,
  "type": "Feature",
  "properties": {
    "tgn:hierarchy":[
        "tgn:7399772",
        "tgn:1000001",
        "tgn:7005593",
        "tgn:7005560",
        "tgn:7029392"
    ],
    "tgn:id":7399772,
    "tgn:name":"La Venta",
    "tgn:placetype":[
        "aat:300008347"
    ]
},
  "bbox": [],
  "geometry": {"coordinates":[-99.584722,20.875],"type":"Point"}
}