{
  "id": 7036008,
  "type": "Feature",
  "properties": {
    "tgn:hierarchy":[
        "tgn:7036008",
        "tgn:7002991",
        "tgn:1000003",
        "tgn:7002997",
        "tgn:1000080",
        "tgn:7029392"
    ],
    "tgn:id":7036008,
    "tgn:name":"Chiave",
    "tgn:placetype":[
        "aat:300008347"
    ]
},
  "bbox": [],
  "geometry": {"coordinates":[12.136389,46.555278],"type":"Point"}
}