{
  "id": 2495298,
  "type": "Feature",
  "properties": {
    "tgn:hierarchy":[
        "tgn:2495298",
        "tgn:1000001",
        "tgn:2000956",
        "tgn:7012149",
        "tgn:7007520",
        "tgn:7029392"
    ],
    "tgn:id":2495298,
    "tgn:name":"Mary Lake",
    "tgn:placetype":[
        "aat:300008680"
    ]
},
  "bbox": [],
  "geometry": {"coordinates":[-87.8167,45.75],"type":"Point"}
}