{
  "id": 7568864,
  "type": "Feature",
  "properties": {
    "tgn:hierarchy":[
        "tgn:7568864",
        "tgn:1000004",
        "tgn:7000198",
        "tgn:7016788",
        "tgn:7029392"
    ],
    "tgn:id":7568864,
    "tgn:name:en":"J\u0101ndwa",
    "tgn:placetype":[
        "aat:300008347"
    ]
},
  "bbox": [],
  "geometry": {"coordinates":[74.815367,28.128834],"type":"Point"}
}