<<<<<<< HEAD
{
  "id": 7023064,
  "type": "Feature",
  "properties": {
    "tgn:hierarchy":[
        "tgn:7023064",
        "tgn:1000001",
        "tgn:7012149",
        "tgn:7029392"
    ],
    "tgn:id":7023064,
    "tgn:name":"Haigler Canal",
    "tgn:placetype":[
        "aat:300006075"
    ]
},
  "bbox": [],
  "geometry": {"coordinates":[-102.05,40.05],"type":"Point"}
}
=======
{"geometry":{"type":"Point","coordinates":[-102.050000,40.050000]},"type":"Feature","properties":{"hierarchy":["tgn:7023064","tgn:1000001","tgn:7012149","tgn:7029392"],"placetype":["aat:300006075"],"id":7023064,"name:xx":"Haigler Canal"}}
>>>>>>> 03f74aca74312dbeaf24d7e61306dd6a786dc3d0
