{
  "id": 7023064,
  "type": "Feature",
  "properties": {
    "tgn:hierarchy":[
        "tgn:7023064",
        "tgn:1000001",
        "tgn:7012149",
        "tgn:7029392"
    ],
    "tgn:id":7023064,
    "tgn:name":"Haigler Canal",
    "tgn:placetype":[
        "aat:300006075"
    ]
},
  "bbox": [],
  "geometry": {"coordinates":[-102.05,40.05],"type":"Point"}
}