{
  "id": 2328620,
  "type": "Feature",
  "properties": {
    "tgn:hierarchy":[
        "tgn:2328620",
        "tgn:1000001",
        "tgn:7012149",
        "tgn:1002768",
        "tgn:7007240",
        "tgn:7029392"
    ],
    "tgn:id":2328620,
    "tgn:name":"Fisherman Island",
    "tgn:placetype":[
        "aat:300008791"
    ]
},
  "bbox": [],
  "geometry": {"coordinates":[-80.0333,26.6667],"type":"Point"}
}