{
  "id": 1134972,
  "type": "Feature",
  "properties": {
    "tgn:hierarchy":[
        "tgn:1134972",
        "tgn:1000001",
        "tgn:7014090",
        "tgn:7012149",
        "tgn:7007565",
        "tgn:7029392"
    ],
    "tgn:id":1134972,
    "tgn:name":"Waackaack Creek",
    "tgn:placetype":[
        "aat:300008706"
    ]
},
  "bbox": [],
  "geometry": {"coordinates":[-74.1167,40.3833],"type":"Point"}
}