{
  "id": 7565712,
  "type": "Feature",
  "properties": {
    "tgn:hierarchy":[
        "tgn:7565712",
        "tgn:1000004",
        "tgn:7000198",
        "tgn:7016788",
        "tgn:7029392"
    ],
    "tgn:id":7565712,
    "tgn:name:en":"J\u0101jgi ki Dh\u0101ni",
    "tgn:placetype":[
        "aat:300008347"
    ]
},
  "bbox": [],
  "geometry": {"coordinates":[71.872876,27.14775],"type":"Point"}
}