{
  "id": 2133559,
  "type": "Feature",
  "properties": {
    "tgn:hierarchy":[
        "tgn:2133559",
        "tgn:1000001",
        "tgn:1002665",
        "tgn:7012149",
        "tgn:7007517",
        "tgn:7029392"
    ],
    "tgn:id":2133559,
    "tgn:name":"Andrew, Mount",
    "tgn:placetype":[
        "aat:300008798"
    ]
},
  "bbox": [],
  "geometry": {"coordinates":[-71.0833,42.4167],"type":"Point"}
}