{
  "id": 7078816,
  "type": "Feature",
  "properties": {
    "tgn:hierarchy":[
        "tgn:7078816",
        "tgn:1000003",
        "tgn:7003682",
        "tgn:7000084",
        "tgn:7029392"
    ],
    "tgn:id":7078816,
    "tgn:name":"Hof Wi\u00dfberg",
    "tgn:placetype":[
        "aat:300000206"
    ]
},
  "bbox": [],
  "geometry": {"coordinates":[8.033333,49.85],"type":"Point"}
}