{
  "id": 2742127,
  "type": "Feature",
  "properties": {
    "tgn:hierarchy":[
        "tgn:2742127",
        "tgn:1002178",
        "tgn:1000001",
        "tgn:7012149",
        "tgn:7007565",
        "tgn:7029392"
    ],
    "tgn:id":2742127,
    "tgn:name":"Valentine Brook",
    "tgn:placetype":[
        "aat:300008699"
    ]
},
  "bbox": [],
  "geometry": {"coordinates":[-74.15,41.05],"type":"Point"}
}