{
  "id": 2616445,
  "type": "Feature",
  "properties": {
    "tgn:hierarchy":[
        "tgn:2616445",
        "tgn:1000001",
        "tgn:7012149",
        "tgn:2002342",
        "tgn:7007922",
        "tgn:7029392"
    ],
    "tgn:id":2616445,
    "tgn:name":"Rice Creek",
    "tgn:placetype":[
        "aat:300008706"
    ]
},
  "bbox": [],
  "geometry": {"coordinates":[-89.2333,45.8167],"type":"Point"}
}