<<<<<<< HEAD
{
  "id": 7364473,
  "type": "Feature",
  "properties": {
    "tgn:hierarchy":[
        "tgn:7364473",
        "tgn:1001853",
        "tgn:1000001",
        "tgn:7005560",
        "tgn:7029392"
    ],
    "tgn:id":7364473,
    "tgn:name":"Fern\u00e1ndez",
    "tgn:placetype":[
        "aat:300008347"
    ]
},
  "bbox": [],
  "geometry": {"coordinates":[-100.466667,28.4],"type":"Point"}
}
=======
{"geometry":{"type":"Point","coordinates":[-100.466667,28.400000]},"type":"Feature","properties":{"hierarchy":["tgn:7364473","tgn:1001853","tgn:1000001","tgn:7005560","tgn:7029392"],"placetype":["aat:300008347"],"id":7364473,"name:xx":"Fern\u00e1ndez"}}
>>>>>>> 03f74aca74312dbeaf24d7e61306dd6a786dc3d0
