{
  "id": 7588219,
  "type": "Feature",
  "properties": {
    "tgn:hierarchy":[
        "tgn:7588219",
        "tgn:1000004",
        "tgn:7000198",
        "tgn:7000799",
        "tgn:7029392"
    ],
    "tgn:id":7588219,
    "tgn:name:en":"Kalipur",
    "tgn:placetype":[
        "aat:300008347"
    ]
},
  "bbox": [],
  "geometry": {"coordinates":[74.560128,34.007725],"type":"Point"}
}