<<<<<<< HEAD
{
  "id": 7483158,
  "type": "Feature",
  "properties": {
    "tgn:hierarchy":[
        "tgn:7483158",
        "tgn:7487020",
        "tgn:1000004",
        "tgn:1000141",
        "tgn:7029392"
    ],
    "tgn:id":7483158,
    "tgn:name":"Yindou Shan",
    "tgn:placetype":[
        "aat:300008777"
    ]
},
  "bbox": [],
  "geometry": {"coordinates":[120.674444,24.435278],"type":"Point"}
}
=======
{"geometry":{"type":"Point","coordinates":[120.674444,24.435278]},"type":"Feature","properties":{"hierarchy":["tgn:7483158","tgn:7487020","tgn:1000004","tgn:1000141","tgn:7029392"],"placetype":["aat:300008777"],"id":7483158,"name:xx":"Yindou Shan"}}
>>>>>>> 03f74aca74312dbeaf24d7e61306dd6a786dc3d0
