{
  "id": 7169237,
  "type": "Feature",
  "properties": {
    "tgn:hierarchy":[
        "tgn:7169237",
        "tgn:7000096",
        "tgn:1000003",
        "tgn:7000084",
        "tgn:7029392"
    ],
    "tgn:id":7169237,
    "tgn:name":"Hell-Berge",
    "tgn:placetype":[
        "aat:300008777"
    ]
},
  "bbox": [],
  "geometry": {"coordinates":[13.566667,51.883333],"type":"Point"}
}