{
  "id": 7194511,
  "type": "Feature",
  "properties": {
    "tgn:hierarchy":[
        "tgn:7194511",
        "tgn:7003669",
        "tgn:1000003",
        "tgn:7000084",
        "tgn:7029392"
    ],
    "tgn:id":7194511,
    "tgn:name":"Diensth\u00fctte",
    "tgn:placetype":[
        "aat:300000206"
    ]
},
  "bbox": [],
  "geometry": {"coordinates":[12.933333,48.233333],"type":"Point"}
}