{
  "id": 2189132,
  "type": "Feature",
  "properties": {
    "tgn:hierarchy":[
        "tgn:2189132",
        "tgn:1002165",
        "tgn:1000001",
        "tgn:7012149",
        "tgn:7007517",
        "tgn:7029392"
    ],
    "tgn:id":2189132,
    "tgn:name":"Bound Brook Island",
    "tgn:placetype":[
        "aat:300008798"
    ]
},
  "bbox": [],
  "geometry": {"coordinates":[-70.0667,41.95],"type":"Point"}
}