<<<<<<< HEAD
{
  "id": 7480605,
  "type": "Feature",
  "properties": {
    "tgn:hierarchy":[
        "tgn:7480605",
        "tgn:1000004",
        "tgn:7471332",
        "tgn:1000141",
        "tgn:7029392"
    ],
    "tgn:id":7480605,
    "tgn:name":"Zhonghe Qiao",
    "tgn:placetype":[
        "aat:300007836"
    ]
},
  "bbox": [],
  "geometry": {"coordinates":[121.066389,24.891389],"type":"Point"}
}
=======
{"geometry":{"type":"Point","coordinates":[121.066389,24.891389]},"type":"Feature","properties":{"hierarchy":["tgn:7480605","tgn:1000004","tgn:7471332","tgn:1000141","tgn:7029392"],"placetype":["aat:300007836"],"id":7480605,"name:xx":"Zhonghe Qiao"}}
>>>>>>> 03f74aca74312dbeaf24d7e61306dd6a786dc3d0
