{
  "id": 7304494,
  "type": "Feature",
  "properties": {
    "tgn:hierarchy":[
        "tgn:7304494",
        "tgn:7002842",
        "tgn:7001158",
        "tgn:1000003",
        "tgn:1000095",
        "tgn:7029392"
    ],
    "tgn:id":7304494,
    "tgn:name":"Liceras",
    "tgn:placetype":[
        "aat:300008347"
    ]
},
  "bbox": [],
  "geometry": {"coordinates":[-3.233333,41.383333],"type":"Point"}
}