<<<<<<< HEAD
{
  "id": 7351358,
  "type": "Feature",
  "properties": {
    "tgn:hierarchy":[
        "tgn:7351358",
        "tgn:7005586",
        "tgn:1000001",
        "tgn:7005560",
        "tgn:7029392"
    ],
    "tgn:id":7351358,
    "tgn:name":"Bola Gorda, Cerro",
    "tgn:placetype":[
        "aat:300008795"
    ]
},
  "bbox": [],
  "geometry": {"coordinates":[-105.066667,19.7],"type":"Point"}
}
=======
{"geometry":{"type":"Point","coordinates":[-105.066667,19.700000]},"type":"Feature","properties":{"hierarchy":["tgn:7351358","tgn:7005586","tgn:1000001","tgn:7005560","tgn:7029392"],"placetype":["aat:300008795"],"id":7351358,"name:xx":"Bola Gorda, Cerro"}}
>>>>>>> 03f74aca74312dbeaf24d7e61306dd6a786dc3d0
