{
  "id": 2596040,
  "type": "Feature",
  "properties": {
    "tgn:hierarchy":[
        "tgn:2596040",
        "tgn:1000001",
        "tgn:7012149",
        "tgn:2000291",
        "tgn:7007240",
        "tgn:7029392"
    ],
    "tgn:id":2596040,
    "tgn:name":"Potter Pond",
    "tgn:placetype":[
        "aat:300008680"
    ]
},
  "bbox": [],
  "geometry": {"coordinates":[-85.65,30.5667],"type":"Point"}
}