{
  "id": 2332499,
  "type": "Feature",
  "properties": {
    "tgn:hierarchy":[
        "tgn:2332499",
        "tgn:1000001",
        "tgn:7012149",
        "tgn:2000283",
        "tgn:7007240",
        "tgn:7029392"
    ],
    "tgn:id":2332499,
    "tgn:name":"Florence Point",
    "tgn:placetype":[
        "aat:300008850"
    ]
},
  "bbox": [],
  "geometry": {"coordinates":[-81.5833,29.9833],"type":"Point"}
}