<<<<<<< HEAD
{
  "id": 7486945,
  "type": "Feature",
  "properties": {
    "tgn:hierarchy":[
        "tgn:7486945",
        "tgn:1000004",
        "tgn:7004300",
        "tgn:1000141",
        "tgn:7029392"
    ],
    "tgn:id":7486945,
    "tgn:name":"Baishazhuang",
    "tgn:placetype":[
        "aat:300387200"
    ]
},
  "bbox": [],
  "geometry": {"coordinates":[119.6,23.75],"type":"Point"}
}
=======
{"geometry":{"type":"Point","coordinates":[119.600000,23.750000]},"type":"Feature","properties":{"hierarchy":["tgn:7486945","tgn:1000004","tgn:7004300","tgn:1000141","tgn:7029392"],"placetype":["aat:300387200"],"id":7486945,"name:xx":"Baishazhuang"}}
>>>>>>> 03f74aca74312dbeaf24d7e61306dd6a786dc3d0
