{
  "id": 1010541,
  "type": "Feature",
  "properties": {
    "tgn:hierarchy":[
        "tgn:1010541",
        "tgn:7001122",
        "tgn:1000003",
        "tgn:7002765",
        "tgn:1000095",
        "tgn:7008042",
        "tgn:7029392"
    ],
    "tgn:id":1010541,
    "tgn:name":"Caballer\u00eda, Cabo de",
    "tgn:placetype":[
        "aat:300008850"
    ]
},
  "bbox": [],
  "geometry": {"coordinates":[4.083333,40.083333],"type":"Point"}
}