{
  "id": 2152633,
  "type": "Feature",
  "properties": {
    "tgn:hierarchy":[
        "tgn:2152633",
        "tgn:7002659",
        "tgn:1000001",
        "tgn:7012149",
        "tgn:2000036",
        "tgn:7029392"
    ],
    "tgn:id":2152633,
    "tgn:name":"Baylor Lake",
    "tgn:placetype":[
        "aat:300006191"
    ]
},
  "bbox": [],
  "geometry": {"coordinates":[-87.0333,33.2833],"type":"Point"}
}