{
  "id": 7450590,
  "type": "Feature",
  "properties": {
    "tgn:hierarchy":[
        "tgn:7450590",
        "tgn:7002445",
        "tgn:1000003",
        "tgn:7008165",
        "tgn:7008591",
        "tgn:7029392"
    ],
    "tgn:id":7450590,
    "tgn:name:en":"Fenham Flats",
    "tgn:placetype":[
        "aat:300386970"
    ]
},
  "bbox": [],
  "geometry": {"coordinates":[-1.816667,55.65],"type":"Point"}
}