{
  "id": 7205705,
  "type": "Feature",
  "properties": {
    "tgn:hierarchy":[
        "tgn:7205705",
        "tgn:7000096",
        "tgn:1000003",
        "tgn:7000084",
        "tgn:7029392"
    ],
    "tgn:id":7205705,
    "tgn:name":"Charlottenhof",
    "tgn:placetype":[
        "aat:300000206"
    ]
},
  "bbox": [],
  "geometry": {"coordinates":[14.15,52.416667],"type":"Point"}
}