{
  "id": 2221257,
  "type": "Feature",
  "properties": {
    "tgn:hierarchy":[
        "tgn:2221257",
        "tgn:1000001",
        "tgn:7012149",
        "tgn:2001252",
        "tgn:7007523",
        "tgn:7029392"
    ],
    "tgn:id":2221257,
    "tgn:name":"Cardinal Acres",
    "tgn:placetype":[
        "aat:300008347"
    ]
},
  "bbox": [],
  "geometry": {"coordinates":[-91.6667,37.05],"type":"Point"}
}