{
  "id": 2231890,
  "type": "Feature",
  "properties": {
    "tgn:hierarchy":[
        "tgn:2231890",
        "tgn:1000001",
        "tgn:7012149",
        "tgn:2001282",
        "tgn:7007524",
        "tgn:7029392"
    ],
    "tgn:id":2231890,
    "tgn:name":"Chambers Mine",
    "tgn:placetype":[
        "aat:300000390"
    ]
},
  "bbox": [],
  "geometry": {"coordinates":[-110.5833,47.1833],"type":"Point"}
}