{
  "id": 2493265,
  "type": "Feature",
  "properties": {
    "tgn:hierarchy":[
        "tgn:2493265",
        "tgn:1000001",
        "tgn:7012149",
        "tgn:2000904",
        "tgn:7007256",
        "tgn:7029392"
    ],
    "tgn:id":2493265,
    "tgn:name":"Marone Point",
    "tgn:placetype":[
        "aat:300008850"
    ]
},
  "bbox": [],
  "geometry": {"coordinates":[-91.6333,29.6333],"type":"Point"}
}