{
  "id": 7410199,
  "type": "Feature",
  "properties": {
    "tgn:hierarchy":[
        "tgn:7410199",
        "tgn:1000001",
        "tgn:7005590",
        "tgn:7005560",
        "tgn:7029392"
    ],
    "tgn:id":7410199,
    "tgn:name":"El Ahuijote",
    "tgn:placetype":[
        "aat:300008347"
    ]
},
  "bbox": [],
  "geometry": {"coordinates":[-101.883333,18.891667],"type":"Point"}
}