{
  "id": 7516110,
  "type": "Feature",
  "properties": {
    "tgn:hierarchy":[
        "tgn:7516110",
        "tgn:1009227",
        "tgn:1000226",
        "tgn:1000006",
        "tgn:7016850",
        "tgn:7029392"
    ],
    "tgn:id":7516110,
    "tgn:name:en":"Monros Creek",
    "tgn:placetype":[
        "aat:300008699"
    ]
},
  "bbox": [],
  "geometry": {"coordinates":[169.266667,-43.716667],"type":"Point"}
}