{
  "id": 1103316,
  "type": "Feature",
  "properties": {
    "tgn:hierarchy":[
        "tgn:1103316",
        "tgn:7003669",
        "tgn:1000003",
        "tgn:7000084",
        "tgn:7029392"
    ],
    "tgn:id":1103316,
    "tgn:name":"Teufelsh\u00f6hle",
    "tgn:placetype":[
        "aat:300008746"
    ]
},
  "bbox": [],
  "geometry": {"coordinates":[11.4167,49.75],"type":"Point"}
}