{
  "id": 2359520,
  "type": "Feature",
  "properties": {
    "tgn:hierarchy":[
        "tgn:2359520",
        "tgn:1000001",
        "tgn:1002328",
        "tgn:7012149",
        "tgn:7007568",
        "tgn:7029392"
    ],
    "tgn:id":2359520,
    "tgn:name":"Grant Mills",
    "tgn:placetype":[
        "aat:300008347"
    ]
},
  "bbox": [],
  "geometry": {"coordinates":[-74.6667,42.0833],"type":"Point"}
}