<<<<<<< HEAD
{
  "id": 2155063,
  "type": "Feature",
  "properties": {
    "tgn:hierarchy":[
        "tgn:2155063",
        "tgn:1000001",
        "tgn:7012149",
        "tgn:1002576",
        "tgn:7007520",
        "tgn:7029392"
    ],
    "tgn:id":2155063,
    "tgn:name":"Bear Lake",
    "tgn:placetype":[
        "aat:300008680"
    ]
},
  "bbox": [],
  "geometry": {"coordinates":[-83.2333,43.1167],"type":"Point"}
}
=======
{"geometry":{"type":"Point","coordinates":[-83.233300,43.116700]},"type":"Feature","properties":{"hierarchy":["tgn:2155063","tgn:1000001","tgn:7012149","tgn:1002576","tgn:7007520","tgn:7029392"],"placetype":["aat:300008680"],"id":2155063,"name:xx":"Bear Lake"}}
>>>>>>> 03f74aca74312dbeaf24d7e61306dd6a786dc3d0
