<<<<<<< HEAD
{
  "id": 7112429,
  "type": "Feature",
  "properties": {
    "tgn:hierarchy":[
        "tgn:7112429",
        "tgn:7003692",
        "tgn:1000003",
        "tgn:7000084",
        "tgn:7029392"
    ],
    "tgn:id":7112429,
    "tgn:name":"Rossacker",
    "tgn:placetype":[
        "aat:300000206"
    ]
},
  "bbox": [],
  "geometry": {"coordinates":[8.366667,48.066667],"type":"Point"}
}
=======
{"geometry":{"type":"Point","coordinates":[8.366667,48.066667]},"type":"Feature","properties":{"hierarchy":["tgn:7112429","tgn:7003692","tgn:1000003","tgn:7000084","tgn:7029392"],"placetype":["aat:300000206"],"id":7112429,"name:xx":"Rossacker"}}
>>>>>>> 03f74aca74312dbeaf24d7e61306dd6a786dc3d0
