{
  "id": 1044675,
  "type": "Feature",
  "properties": {
    "tgn:hierarchy":[
        "tgn:1044675",
        "tgn:7003158",
        "tgn:1000003",
        "tgn:7003124",
        "tgn:1000080",
        "tgn:7029392"
    ],
    "tgn:id":1044675,
    "tgn:name":"Forno",
    "tgn:placetype":[
        "aat:300008347"
    ]
},
  "bbox": [],
  "geometry": {"coordinates":[11.6167,46.35],"type":"Point"}
}