<<<<<<< HEAD
{
  "id": 7350817,
  "type": "Feature",
  "properties": {
    "tgn:hierarchy":[
        "tgn:7350817",
        "tgn:7005585",
        "tgn:1000001",
        "tgn:7005560",
        "tgn:7029392"
    ],
    "tgn:id":7350817,
    "tgn:name":"Cabeza de Perro, Cerro",
    "tgn:placetype":[
        "aat:300008777"
    ]
},
  "bbox": [],
  "geometry": {"coordinates":[-100.483333,17.3],"type":"Point"}
}
=======
{"geometry":{"type":"Point","coordinates":[-100.483333,17.300000]},"type":"Feature","properties":{"hierarchy":["tgn:7350817","tgn:7005585","tgn:1000001","tgn:7005560","tgn:7029392"],"placetype":["aat:300008777"],"id":7350817,"name:xx":"Cabeza de Perro, Cerro"}}
>>>>>>> 03f74aca74312dbeaf24d7e61306dd6a786dc3d0
