{
  "id": 7088006,
  "type": "Feature",
  "properties": {
    "tgn:hierarchy":[
        "tgn:7088006",
        "tgn:1000003",
        "tgn:7000094",
        "tgn:7000084",
        "tgn:7029392"
    ],
    "tgn:id":7088006,
    "tgn:name":"Wedendorf",
    "tgn:placetype":[
        "aat:300008347"
    ]
},
  "bbox": [],
  "geometry": {"coordinates":[11.116667,53.766667],"type":"Point"}
}