{
  "id": 2220784,
  "type": "Feature",
  "properties": {
    "tgn:hierarchy":[
        "tgn:2220784",
        "tgn:1000001",
        "tgn:7012149",
        "tgn:7007520",
        "tgn:7029392"
    ],
    "tgn:id":2220784,
    "tgn:name":"Capone Creek",
    "tgn:placetype":[
        "aat:300008706"
    ]
},
  "bbox": [],
  "geometry": {"coordinates":[-88.9167,46.8833],"type":"Point"}
}