<<<<<<< HEAD
{
  "id": 2761968,
  "type": "Feature",
  "properties": {
    "tgn:hierarchy":[
        "tgn:2761968",
        "tgn:1000001",
        "tgn:7012149",
        "tgn:1002290",
        "tgn:7007826",
        "tgn:7029392"
    ],
    "tgn:id":2761968,
    "tgn:name":"West Rowlett Creek",
    "tgn:placetype":[
        "aat:300008706"
    ]
},
  "bbox": [],
  "geometry": {"coordinates":[-96.7667,33.15],"type":"Point"}
}
=======
{"geometry":{"type":"Point","coordinates":[-96.766700,33.150000]},"type":"Feature","properties":{"hierarchy":["tgn:2761968","tgn:1000001","tgn:7012149","tgn:1002290","tgn:7007826","tgn:7029392"],"placetype":["aat:300008706"],"id":2761968,"name:xx":"West Rowlett Creek"}}
>>>>>>> 03f74aca74312dbeaf24d7e61306dd6a786dc3d0
