{
  "id": 7092846,
  "type": "Feature",
  "properties": {
    "tgn:hierarchy":[
        "tgn:7092846",
        "tgn:7003669",
        "tgn:1000003",
        "tgn:7000084",
        "tgn:7029392"
    ],
    "tgn:id":7092846,
    "tgn:name":"Schrammlhof",
    "tgn:placetype":[
        "aat:300008347"
    ]
},
  "bbox": [],
  "geometry": {"coordinates":[11.916667,49.05],"type":"Point"}
}