<<<<<<< HEAD
{
  "id": 7485551,
  "type": "Feature",
  "properties": {
    "tgn:hierarchy":[
        "tgn:7485551",
        "tgn:1000004",
        "tgn:7467799",
        "tgn:1000141",
        "tgn:7029392"
    ],
    "tgn:id":7485551,
    "tgn:name":"Wenzi Shan",
    "tgn:placetype":[
        "aat:300387033"
    ]
},
  "bbox": [],
  "geometry": {"coordinates":[120.455833,24.127222],"type":"Point"}
}
=======
{"geometry":{"type":"Point","coordinates":[120.455833,24.127222]},"type":"Feature","properties":{"hierarchy":["tgn:7485551","tgn:1000004","tgn:7467799","tgn:1000141","tgn:7029392"],"placetype":["aat:300387033"],"id":7485551,"name:xx":"Wenzi Shan"}}
>>>>>>> 03f74aca74312dbeaf24d7e61306dd6a786dc3d0
