{
  "id": 2584171,
  "type": "Feature",
  "properties": {
    "tgn:hierarchy":[
        "tgn:2584171",
        "tgn:1000001",
        "tgn:7012149",
        "tgn:2002353",
        "tgn:7007922",
        "tgn:7029392"
    ],
    "tgn:id":2584171,
    "tgn:name":"Pines, Lake Of the",
    "tgn:placetype":[
        "aat:300008680"
    ]
},
  "bbox": [],
  "geometry": {"coordinates":[-90.7167,45.7667],"type":"Point"}
}