{
  "id": 7154557,
  "type": "Feature",
  "properties": {
    "tgn:hierarchy":[
        "tgn:7154557",
        "tgn:1000003",
        "tgn:7003687",
        "tgn:7000084",
        "tgn:7029392"
    ],
    "tgn:id":7154557,
    "tgn:name":"Bahnhof Kapen",
    "tgn:placetype":[
        "aat:300007783"
    ]
},
  "bbox": [],
  "geometry": {"coordinates":[12.333333,51.816667],"type":"Point"}
}