<<<<<<< HEAD
{
  "id": 2335834,
  "type": "Feature",
  "properties": {
    "tgn:hierarchy":[
        "tgn:2335834",
        "tgn:7006450",
        "tgn:1000001",
        "tgn:7012149",
        "tgn:2000089",
        "tgn:7029392"
    ],
    "tgn:id":2335834,
    "tgn:name":"Fortythree Pup",
    "tgn:placetype":[
        "aat:300008699"
    ]
},
  "bbox": [],
  "geometry": {"coordinates":[-145.0167,65.4],"type":"Point"}
}
=======
{"geometry":{"type":"Point","coordinates":[-145.016700,65.400000]},"type":"Feature","properties":{"hierarchy":["tgn:2335834","tgn:7006450","tgn:1000001","tgn:7012149","tgn:2000089","tgn:7029392"],"placetype":["aat:300008699"],"id":2335834,"name:xx":"Fortythree Pup"}}
>>>>>>> 03f74aca74312dbeaf24d7e61306dd6a786dc3d0
