{
  "id": 1027993,
  "type": "Feature",
  "properties": {
    "tgn:hierarchy":[
        "tgn:1027993",
        "tgn:1000003",
        "tgn:7594009",
        "tgn:1000066",
        "tgn:7029392"
    ],
    "tgn:id":1027993,
    "tgn:name":"Landby",
    "tgn:placetype":[
        "aat:300008347"
    ]
},
  "bbox": [],
  "geometry": {"coordinates":[10.6333,55.4333],"type":"Point"}
}