{
  "id": 1077036,
  "type": "Feature",
  "properties": {
    "tgn:hierarchy":[
        "tgn:1077036",
        "tgn:1000004",
        "tgn:7000198",
        "tgn:7016694",
        "tgn:7029392"
    ],
    "tgn:id":1077036,
    "tgn:name:en":"Sonepur",
    "tgn:placetype":[
        "aat:300008347"
    ]
},
  "bbox": [],
  "geometry": {"coordinates":[83.916667,20.833333],"type":"Point"}
}