{
  "id": 7566082,
  "type": "Feature",
  "properties": {
    "tgn:hierarchy":[
        "tgn:7566082",
        "tgn:1000004",
        "tgn:7000198",
        "tgn:1001894",
        "tgn:7029392"
    ],
    "tgn:id":7566082,
    "tgn:name:en":"Mir\u0101wali",
    "tgn:placetype":[
        "aat:300008347"
    ]
},
  "bbox": [],
  "geometry": {"coordinates":[79.189084,24.622311],"type":"Point"}
}