<<<<<<< HEAD
{
  "id": 7111956,
  "type": "Feature",
  "properties": {
    "tgn:hierarchy":[
        "tgn:7111956",
        "tgn:7003669",
        "tgn:1000003",
        "tgn:7000084",
        "tgn:7029392"
    ],
    "tgn:id":7111956,
    "tgn:name":"Ro\u00dfendorf",
    "tgn:placetype":[
        "aat:300008347"
    ]
},
  "bbox": [],
  "geometry": {"coordinates":[10.833333,49.466667],"type":"Point"}
}
=======
{"geometry":{"type":"Point","coordinates":[10.833333,49.466667]},"type":"Feature","properties":{"hierarchy":["tgn:7111956","tgn:7003669","tgn:1000003","tgn:7000084","tgn:7029392"],"placetype":["aat:300008347"],"id":7111956,"name:xx":"Ro\u00dfendorf"}}
>>>>>>> 03f74aca74312dbeaf24d7e61306dd6a786dc3d0
