{
  "id": 7031950,
  "type": "Feature",
  "properties": {
    "tgn:hierarchy":[
        "tgn:7031950",
        "tgn:7001242",
        "tgn:7030585",
        "tgn:1000198",
        "tgn:7029392"
    ],
    "tgn:id":7031950,
    "tgn:name:en":"Ai-Ais",
    "tgn:placetype":[
        "aat:300008347"
    ]
},
  "bbox": [],
  "geometry": {"coordinates":[17.491,-27.916],"type":"Point"}
}