{
  "id": 7014316,
  "type": "Feature",
  "properties": {
    "tgn:hierarchy":[
        "tgn:7014316",
        "tgn:1000001",
        "tgn:7012149",
        "tgn:2002363",
        "tgn:7007922",
        "tgn:7029392"
    ],
    "tgn:id":7014316,
    "tgn:name":"Oshkosh",
    "tgn:placetype":[
        "aat:300008347",
        "aat:300008416",
        "aat:300008389",
        "aat:300387302"
    ]
},
  "bbox": [],
  "geometry": {"coordinates":[-88.5333,44.0167],"type":"Point"}
}