{
  "id": 7153943,
  "type": "Feature",
  "properties": {
    "tgn:hierarchy":[
        "tgn:7153943",
        "tgn:1000003",
        "tgn:7003685",
        "tgn:7000084",
        "tgn:7029392"
    ],
    "tgn:id":7153943,
    "tgn:name":"Kalbitz",
    "tgn:placetype":[
        "aat:300008347"
    ]
},
  "bbox": [],
  "geometry": {"coordinates":[13.266667,51.266667],"type":"Point"}
}