{
  "id": 2397202,
  "type": "Feature",
  "properties": {
    "tgn:hierarchy":[
        "tgn:2397202",
        "tgn:1000001",
        "tgn:2001431",
        "tgn:7012149",
        "tgn:7007566",
        "tgn:7029392"
    ],
    "tgn:id":2397202,
    "tgn:name":"Honda, Laguna",
    "tgn:placetype":[
        "aat:300008680"
    ]
},
  "bbox": [],
  "geometry": {"coordinates":[-107.7667,34.8333],"type":"Point"}
}