{
  "id": 7590768,
  "type": "Feature",
  "properties": {
    "tgn:hierarchy":[
        "tgn:7590768",
        "tgn:1000004",
        "tgn:7000198",
        "tgn:7000799",
        "tgn:7029392"
    ],
    "tgn:id":7590768,
    "tgn:name:en":"B\u0101tla",
    "tgn:placetype":[
        "aat:300008347"
    ]
},
  "bbox": [],
  "geometry": {"coordinates":[74.643122,32.859921],"type":"Point"}
}