{
  "id": 2683007,
  "type": "Feature",
  "properties": {
    "tgn:hierarchy":[
        "tgn:2683007",
        "tgn:1000001",
        "tgn:7012149",
        "tgn:2001915",
        "tgn:7007825",
        "tgn:7029392"
    ],
    "tgn:id":2683007,
    "tgn:name":"Spain Bottom",
    "tgn:placetype":[
        "aat:300008761"
    ]
},
  "bbox": [],
  "geometry": {"coordinates":[-89.65,35.15],"type":"Point"}
}