{
  "id": 7225658,
  "type": "Feature",
  "properties": {
    "tgn:hierarchy":[
        "tgn:7225658",
        "tgn:7002680",
        "tgn:7001395",
        "tgn:1000003",
        "tgn:1000074",
        "tgn:7029392"
    ],
    "tgn:id":7225658,
    "tgn:name":"N\u00e9a Kalidh\u00f3n",
    "tgn:placetype":[
        "aat:300008347"
    ]
},
  "bbox": [],
  "geometry": {"coordinates":[21.533333,38.35],"type":"Point"}
}