{
  "id": 7463754,
  "type": "Feature",
  "properties": {
    "tgn:hierarchy":[
        "tgn:7463754",
        "tgn:7002444",
        "tgn:1000003",
        "tgn:7008082",
        "tgn:7008591",
        "tgn:7029392"
    ],
    "tgn:id":7463754,
    "tgn:name:en":"Kilmuir",
    "tgn:placetype":[
        "aat:300008347"
    ]
},
  "bbox": [],
  "geometry": {"coordinates":[-4.083333,57.716667],"type":"Point"}
}