{
  "id": 2025891,
  "type": "Feature",
  "properties": {
    "tgn:hierarchy":[
        "tgn:2025891",
        "tgn:1000001",
        "tgn:7012149",
        "tgn:2000495",
        "tgn:7007250",
        "tgn:7029392"
    ],
    "tgn:id":2025891,
    "tgn:name":"Midvale",
    "tgn:placetype":[
        "aat:300008347"
    ]
},
  "bbox": [],
  "geometry": {"coordinates":[-116.7333,44.4667],"type":"Point"}
}