{
  "id": 2303455,
  "type": "Feature",
  "properties": {
    "tgn:hierarchy":[
        "tgn:2303455",
        "tgn:1000001",
        "tgn:7006451",
        "tgn:7012149",
        "tgn:2000104",
        "tgn:7029392"
    ],
    "tgn:id":2303455,
    "tgn:name":"Eagle Eye Mine",
    "tgn:placetype":[
        "aat:300000390"
    ]
},
  "bbox": [],
  "geometry": {"coordinates":[-113.8833,33.5833],"type":"Point"}
}