{
  "id": 7531968,
  "type": "Feature",
  "properties": {
    "tgn:hierarchy":[
        "tgn:7531968",
        "tgn:7001242",
        "tgn:7016833",
        "tgn:7001335",
        "tgn:7029392"
    ],
    "tgn:id":7531968,
    "tgn:name:en":"El-Deheisha",
    "tgn:placetype":[
        "aat:300008884"
    ]
},
  "bbox": [],
  "geometry": {"coordinates":[33.718611,31.114444],"type":"Point"}
}