{
  "id": 2684304,
  "type": "Feature",
  "properties": {
    "tgn:hierarchy":[
        "tgn:2684304",
        "tgn:1000001",
        "tgn:7012149",
        "tgn:2002341",
        "tgn:7007922",
        "tgn:7029392"
    ],
    "tgn:id":2684304,
    "tgn:name":"Spice Lake",
    "tgn:placetype":[
        "aat:300008680"
    ]
},
  "bbox": [],
  "geometry": {"coordinates":[-88.3333,44.9167],"type":"Point"}
}