<<<<<<< HEAD
{
  "id": 7050539,
  "type": "Feature",
  "properties": {
    "tgn:hierarchy":[
        "tgn:7050539",
        "tgn:7003150",
        "tgn:1000003",
        "tgn:7003237",
        "tgn:1000080",
        "tgn:7029392"
    ],
    "tgn:id":7050539,
    "tgn:name":"Lardara",
    "tgn:placetype":[
        "aat:300008347"
    ]
},
  "bbox": [],
  "geometry": {"coordinates":[9.783333,45.15],"type":"Point"}
}
=======
{"geometry":{"type":"Point","coordinates":[9.783333,45.150000]},"type":"Feature","properties":{"hierarchy":["tgn:7050539","tgn:7003150","tgn:1000003","tgn:7003237","tgn:1000080","tgn:7029392"],"placetype":["aat:300008347"],"id":7050539,"name:xx":"Lardara"}}
>>>>>>> 03f74aca74312dbeaf24d7e61306dd6a786dc3d0
