{
  "id": 2511053,
  "type": "Feature",
  "properties": {
    "tgn:hierarchy":[
        "tgn:2511053",
        "tgn:1000001",
        "tgn:7012149",
        "tgn:1002582",
        "tgn:7007240",
        "tgn:7029392"
    ],
    "tgn:id":2511053,
    "tgn:name":"Midway Island",
    "tgn:placetype":[
        "aat:300008791"
    ]
},
  "bbox": [],
  "geometry": {"coordinates":[-81.8167,26.6833],"type":"Point"}
}