{
  "id": 1057035,
  "type": "Feature",
  "properties": {
    "tgn:hierarchy":[
        "tgn:1057035",
        "tgn:7011476",
        "tgn:1000004",
        "tgn:7006655",
        "tgn:7029392"
    ],
    "tgn:id":1057035,
    "tgn:name":"Mirza-Aki",
    "tgn:placetype":[
        "aat:300008347"
    ]
},
  "bbox": [],
  "geometry": {"coordinates":[73.4167,40.75],"type":"Point"}
}