{
  "id": 7261900,
  "type": "Feature",
  "properties": {
    "tgn:hierarchy":[
        "tgn:7261900",
        "tgn:1000003",
        "tgn:7003624",
        "tgn:7016845",
        "tgn:7029392"
    ],
    "tgn:id":7261900,
    "tgn:name:nl":"Deurnse Peel",
    "tgn:placetype":[
        "aat:300386887"
    ]
},
  "bbox": [],
  "geometry": {"coordinates":[5.866667,51.416667],"type":"Point"}
}