{
  "id": 7395842,
  "type": "Feature",
  "properties": {
    "tgn:hierarchy":[
        "tgn:7395842",
        "tgn:7005585",
        "tgn:1000001",
        "tgn:7005560",
        "tgn:7029392"
    ],
    "tgn:id":7395842,
    "tgn:name":"San Felipe",
    "tgn:placetype":[
        "aat:300008347"
    ]
},
  "bbox": [],
  "geometry": {"coordinates":[-101.316667,17.666667],"type":"Point"}
}