{
  "id": 2379782,
  "type": "Feature",
  "properties": {
    "tgn:hierarchy":[
        "tgn:2379782",
        "tgn:1000001",
        "tgn:7012149",
        "tgn:1002823",
        "tgn:7007706",
        "tgn:7029392"
    ],
    "tgn:id":2379782,
    "tgn:name":"Hastings",
    "tgn:placetype":[
        "aat:300008347"
    ]
},
  "bbox": [],
  "geometry": {"coordinates":[-82.4333,40.65],"type":"Point"}
}