{
  "id": 2086556,
  "type": "Feature",
  "properties": {
    "tgn:hierarchy":[
        "tgn:2086556",
        "tgn:1000001",
        "tgn:1002217",
        "tgn:7012149",
        "tgn:7007710",
        "tgn:7029392"
    ],
    "tgn:id":2086556,
    "tgn:name":"Bonus",
    "tgn:placetype":[
        "aat:300008347",
        "aat:300387210"
    ]
},
  "bbox": [],
  "geometry": {"coordinates":[-79.7167,41.1167],"type":"Point"}
}