{
  "id": 1020302,
  "type": "Feature",
  "properties": {
    "tgn:hierarchy":[
        "tgn:1020302",
        "tgn:1000752",
        "tgn:1000046",
        "tgn:1000002",
        "tgn:7029392"
    ],
    "tgn:id":1020302,
    "tgn:name":"El Carmen",
    "tgn:placetype":[
        "aat:300008347"
    ]
},
  "bbox": [],
  "geometry": {"coordinates":[-58.5833,-18.85],"type":"Point"}
}