<<<<<<< HEAD
{
  "id": 2154130,
  "type": "Feature",
  "properties": {
    "tgn:hierarchy":[
        "tgn:2154130",
        "tgn:1000001",
        "tgn:7012149",
        "tgn:7007253",
        "tgn:7029392"
    ],
    "tgn:id":2154130,
    "tgn:name":"Bear Creek",
    "tgn:placetype":[
        "aat:300008706"
    ]
},
  "bbox": [],
  "geometry": {"coordinates":[-91.6,43.4333],"type":"Point"}
}
=======
{"geometry":{"type":"Point","coordinates":[-91.600000,43.433300]},"type":"Feature","properties":{"hierarchy":["tgn:2154130","tgn:1000001","tgn:7012149","tgn:7007253","tgn:7029392"],"placetype":["aat:300008706"],"id":2154130,"name:xx":"Bear Creek"}}
>>>>>>> 03f74aca74312dbeaf24d7e61306dd6a786dc3d0
