<<<<<<< HEAD
{
  "id": 2257026,
  "type": "Feature",
  "properties": {
    "tgn:hierarchy":[
        "tgn:2257026",
        "tgn:1002996",
        "tgn:1000001",
        "tgn:7012149",
        "tgn:7007711",
        "tgn:7029392"
    ],
    "tgn:id":2257026,
    "tgn:name":"Corn Neck",
    "tgn:placetype":[
        "aat:300008850"
    ]
},
  "bbox": [],
  "geometry": {"coordinates":[-71.55,41.2],"type":"Point"}
}
=======
{"geometry":{"type":"Point","coordinates":[-71.550000,41.200000]},"type":"Feature","properties":{"hierarchy":["tgn:2257026","tgn:1002996","tgn:1000001","tgn:7012149","tgn:7007711","tgn:7029392"],"placetype":["aat:300008850"],"id":2257026,"name:xx":"Corn Neck"}}
>>>>>>> 03f74aca74312dbeaf24d7e61306dd6a786dc3d0
