{
  "id": 7493041,
  "type": "Feature",
  "properties": {
    "tgn:hierarchy":[
        "tgn:7493041",
        "tgn:1000004",
        "tgn:1000454",
        "tgn:1000141",
        "tgn:7029392"
    ],
    "tgn:id":7493041,
    "tgn:name":"Shen'ao Shan",
    "tgn:placetype":[
        "aat:300008777"
    ]
},
  "bbox": [],
  "geometry": {"coordinates":[121.805583,25.1303],"type":"Point"}
}