{
  "id": 2664233,
  "type": "Feature",
  "properties": {
    "tgn:hierarchy":[
        "tgn:2664233",
        "tgn:1000001",
        "tgn:7012149",
        "tgn:2001155",
        "tgn:7007522",
        "tgn:7029392"
    ],
    "tgn:id":2664233,
    "tgn:name":"Silver Springs Hill",
    "tgn:placetype":[
        "aat:300008798"
    ]
},
  "bbox": [],
  "geometry": {"coordinates":[-88.7667,34.7667],"type":"Point"}
}