{
  "id": 7590766,
  "type": "Feature",
  "properties": {
    "tgn:hierarchy":[
        "tgn:7590766",
        "tgn:1000004",
        "tgn:7000198",
        "tgn:7000799",
        "tgn:7029392"
    ],
    "tgn:id":7590766,
    "tgn:name:en":"Najle Chak",
    "tgn:placetype":[
        "aat:300008347"
    ]
},
  "bbox": [],
  "geometry": {"coordinates":[74.626313,32.868858],"type":"Point"}
}