{
  "id": 1059406,
  "type": "Feature",
  "properties": {
    "tgn:hierarchy":[
        "tgn:1059406",
        "tgn:7012152",
        "tgn:1000003",
        "tgn:7006541",
        "tgn:7029392"
    ],
    "tgn:id":1059406,
    "tgn:name":"Sigulda",
    "tgn:placetype":[
        "aat:300008347"
    ]
},
  "bbox": [],
  "geometry": {"coordinates":[24.85,57.15],"type":"Point"}
}