{
  "id": 7535724,
  "type": "Feature",
  "properties": {
    "tgn:hierarchy":[
        "tgn:7535724",
        "tgn:7001242",
        "tgn:7016833",
        "tgn:1001418",
        "tgn:7029392"
    ],
    "tgn:id":7535724,
    "tgn:name:en":"Gh\u00f4t el Kaliala",
    "tgn:placetype":[
        "aat:300055621"
    ]
},
  "bbox": [],
  "geometry": {"coordinates":[24.962189,31.10565],"type":"Point"}
}