{
  "id": 2377711,
  "type": "Feature",
  "properties": {
    "tgn:hierarchy":[
        "tgn:2377711",
        "tgn:1000001",
        "tgn:7012149",
        "tgn:2000443",
        "tgn:7007248",
        "tgn:7029392"
    ],
    "tgn:id":2377711,
    "tgn:name":"Harrel Mill Creek",
    "tgn:placetype":[
        "aat:300008706"
    ]
},
  "bbox": [],
  "geometry": {"coordinates":[-84.5667,32.0167],"type":"Point"}
}