{
  "id": 1014038,
  "type": "Feature",
  "properties": {
    "tgn:hierarchy":[
        "tgn:1014038",
        "tgn:7005685",
        "tgn:1000001",
        "tgn:7005734",
        "tgn:7029392"
    ],
    "tgn:id":1014038,
    "tgn:name":"Weir River",
    "tgn:placetype":[
        "aat:300008347"
    ]
},
  "bbox": [],
  "geometry": {"coordinates":[-94.0833,56.8167],"type":"Point"}
}