{
  "id": 7191106,
  "type": "Feature",
  "properties": {
    "tgn:hierarchy":[
        "tgn:7191106",
        "tgn:7003669",
        "tgn:1000003",
        "tgn:7000084",
        "tgn:7029392"
    ],
    "tgn:id":7191106,
    "tgn:name":"Forstberg",
    "tgn:placetype":[
        "aat:300008347"
    ]
},
  "bbox": [],
  "geometry": {"coordinates":[12.05,49.116667],"type":"Point"}
}