<<<<<<< HEAD
{
  "id": 7473706,
  "type": "Feature",
  "properties": {
    "tgn:hierarchy":[
        "tgn:7473706",
        "tgn:7469009",
        "tgn:1000004",
        "tgn:1000141",
        "tgn:7029392"
    ],
    "tgn:id":7473706,
    "tgn:name":"Dongdian",
    "tgn:placetype":[
        "aat:300008347"
    ]
},
  "bbox": [],
  "geometry": {"coordinates":[118.439739,24.479984],"type":"Point"}
}
=======
{"geometry":{"type":"Point","coordinates":[118.439739,24.479984]},"type":"Feature","properties":{"hierarchy":["tgn:7473706","tgn:7469009","tgn:1000004","tgn:1000141","tgn:7029392"],"placetype":["aat:300008347"],"id":7473706,"name:xx":"Dongdian"}}
>>>>>>> 03f74aca74312dbeaf24d7e61306dd6a786dc3d0
