{
  "id": 2147909,
  "type": "Feature",
  "properties": {
    "tgn:hierarchy":[
        "tgn:2147909",
        "tgn:1000001",
        "tgn:7012149",
        "tgn:1002613",
        "tgn:7007710",
        "tgn:7029392"
    ],
    "tgn:id":2147909,
    "tgn:name":"Bark Cabin Natural Area",
    "tgn:placetype":[
        "aat:300055621"
    ]
},
  "bbox": [],
  "geometry": {"coordinates":[-77.3833,41.4167],"type":"Point"}
}