{
  "id": 7237854,
  "type": "Feature",
  "properties": {
    "tgn:hierarchy":[
        "tgn:7237854",
        "tgn:7003460",
        "tgn:1000003",
        "tgn:1000063",
        "tgn:4012014",
        "tgn:7029392"
    ],
    "tgn:id":7237854,
    "tgn:name":"Fraineux",
    "tgn:placetype":[
        "aat:300008347"
    ]
},
  "bbox": [],
  "geometry": {"coordinates":[5.396892,50.512443],"type":"Point"}
}