{
  "id": 1063986,
  "type": "Feature",
  "properties": {
    "tgn:hierarchy":[
        "tgn:1063986",
        "tgn:7003746",
        "tgn:1000003",
        "tgn:7011731",
        "tgn:7029392"
    ],
    "tgn:id":1063986,
    "tgn:name":"Chancy",
    "tgn:placetype":[
        "aat:300008347"
    ]
},
  "bbox": [],
  "geometry": {"coordinates":[5.9667,46.15],"type":"Point"}
}