<<<<<<< HEAD
{
  "id": 2761244,
  "type": "Feature",
  "properties": {
    "tgn:hierarchy":[
        "tgn:2761244",
        "tgn:1000001",
        "tgn:2002370",
        "tgn:7012149",
        "tgn:7007923",
        "tgn:7029392"
    ],
    "tgn:id":2761244,
    "tgn:name":"West Lytle Creek",
    "tgn:placetype":[
        "aat:300008706"
    ]
},
  "bbox": [],
  "geometry": {"coordinates":[-104.55,44.5],"type":"Point"}
}
=======
{"geometry":{"type":"Point","coordinates":[-104.550000,44.500000]},"type":"Feature","properties":{"hierarchy":["tgn:2761244","tgn:1000001","tgn:2002370","tgn:7012149","tgn:7007923","tgn:7029392"],"placetype":["aat:300008706"],"id":2761244,"name:xx":"West Lytle Creek"}}
>>>>>>> 03f74aca74312dbeaf24d7e61306dd6a786dc3d0
