{
  "id": 2734442,
  "type": "Feature",
  "properties": {
    "tgn:hierarchy":[
        "tgn:2734442",
        "tgn:1000001",
        "tgn:7012149",
        "tgn:7007705",
        "tgn:7029392"
    ],
    "tgn:id":2734442,
    "tgn:name":"Turtle Mountains",
    "tgn:placetype":[
        "aat:300386831"
    ]
},
  "bbox": [],
  "geometry": {"coordinates":[-100.05,48.9333],"type":"Point"}
}