{
  "id": 2511490,
  "type": "Feature",
  "properties": {
    "tgn:hierarchy":[
        "tgn:2511490",
        "tgn:1000001",
        "tgn:7012149",
        "tgn:2002270",
        "tgn:7013961",
        "tgn:7029392"
    ],
    "tgn:id":2511490,
    "tgn:name":"Mile Branch",
    "tgn:placetype":[
        "aat:300008699"
    ]
},
  "bbox": [],
  "geometry": {"coordinates":[-81.45,38.2333],"type":"Point"}
}