{
  "id": 2057736,
  "type": "Feature",
  "properties": {
    "tgn:hierarchy":[
        "tgn:2057736",
        "tgn:2001086",
        "tgn:1000001",
        "tgn:7012149",
        "tgn:7007522",
        "tgn:7029392"
    ],
    "tgn:id":2057736,
    "tgn:name":"Washington",
    "tgn:placetype":[
        "aat:300008347"
    ]
},
  "bbox": [],
  "geometry": {"coordinates":[-91.2833,31.5667],"type":"Point"}
}