<<<<<<< HEAD
{
  "id": 7487762,
  "type": "Feature",
  "properties": {
    "tgn:hierarchy":[
        "tgn:7487762",
        "tgn:1000004",
        "tgn:7001014",
        "tgn:1000141",
        "tgn:7029392"
    ],
    "tgn:id":7487762,
    "tgn:name":"Nanjingcuo",
    "tgn:placetype":[
        "aat:300008347"
    ]
},
  "bbox": [],
  "geometry": {"coordinates":[120.413254,23.576151],"type":"Point"}
}
=======
{"geometry":{"type":"Point","coordinates":[120.413254,23.576151]},"type":"Feature","properties":{"hierarchy":["tgn:7487762","tgn:1000004","tgn:7001014","tgn:1000141","tgn:7029392"],"placetype":["aat:300008347"],"id":7487762,"name:xx":"Nanjingcuo"}}
>>>>>>> 03f74aca74312dbeaf24d7e61306dd6a786dc3d0
