{
  "id": 2238216,
  "type": "Feature",
  "properties": {
    "tgn:hierarchy":[
        "tgn:2238216",
        "tgn:1000001",
        "tgn:2001643",
        "tgn:7012149",
        "tgn:7007707",
        "tgn:7029392"
    ],
    "tgn:id":2238216,
    "tgn:name":"Chloeta",
    "tgn:placetype":[
        "aat:300008347"
    ]
},
  "bbox": [],
  "geometry": {"coordinates":[-94.9667,36.4167],"type":"Point"}
}