{
  "id": 2149956,
  "type": "Feature",
  "properties": {
    "tgn:hierarchy":[
        "tgn:2149956",
        "tgn:1000001",
        "tgn:7012149",
        "tgn:2001461",
        "tgn:7007568",
        "tgn:7029392"
    ],
    "tgn:id":2149956,
    "tgn:name":"Bartlett Pond",
    "tgn:placetype":[
        "aat:300008680"
    ]
},
  "bbox": [],
  "geometry": {"coordinates":[-74.0167,44.3333],"type":"Point"}
}