{
  "id": 7307120,
  "type": "Feature",
  "properties": {
    "tgn:hierarchy":[
        "tgn:7307120",
        "tgn:7008912",
        "tgn:7030216",
        "tgn:1000003",
        "tgn:1000095",
        "tgn:7029392"
    ],
    "tgn:id":7307120,
    "tgn:name":"Martinet",
    "tgn:placetype":[
        "aat:300008347"
    ]
},
  "bbox": [],
  "geometry": {"coordinates":[1.695574,42.3596],"type":"Point"}
}