{
  "id": 2749924,
  "type": "Feature",
  "properties": {
    "tgn:hierarchy":[
        "tgn:2749924",
        "tgn:1000001",
        "tgn:7012149",
        "tgn:2001617",
        "tgn:7007706",
        "tgn:7029392"
    ],
    "tgn:id":2749924,
    "tgn:name":"Walnutcamp Run",
    "tgn:placetype":[
        "aat:300008699"
    ]
},
  "bbox": [],
  "geometry": {"coordinates":[-80.9667,39.65],"type":"Point"}
}