{
  "id": 7351589,
  "type": "Feature",
  "properties": {
    "tgn:hierarchy":[
        "tgn:7351589",
        "tgn:1001853",
        "tgn:1000001",
        "tgn:7005560",
        "tgn:7029392"
    ],
    "tgn:id":7351589,
    "tgn:name":"Arroyitos",
    "tgn:placetype":[
        "aat:300008347"
    ]
},
  "bbox": [],
  "geometry": {"coordinates":[-99.933333,27.916667],"type":"Point"}
}