{
  "id": 2349222,
  "type": "Feature",
  "properties": {
    "tgn:hierarchy":[
        "tgn:2349222",
        "tgn:7030516",
        "tgn:7006450",
        "tgn:1000001",
        "tgn:7012149",
        "tgn:7029392"
    ],
    "tgn:id":2349222,
    "tgn:name":"Gilbert Ridge",
    "tgn:placetype":[
        "aat:300266640"
    ]
},
  "bbox": [],
  "geometry": {"coordinates":[173.2333,52.85],"type":"Point"}
}