{
  "id": 2568507,
  "type": "Feature",
  "properties": {
    "tgn:hierarchy":[
        "tgn:2568507",
        "tgn:1000001",
        "tgn:7012149",
        "tgn:2001546",
        "tgn:7007709",
        "tgn:7029392"
    ],
    "tgn:id":2568507,
    "tgn:name":"Park Place",
    "tgn:placetype":[
        "aat:300008347"
    ]
},
  "bbox": [],
  "geometry": {"coordinates":[-80.5167,34.9667],"type":"Point"}
}