{
  "id": 7414567,
  "type": "Feature",
  "properties": {
    "tgn:hierarchy":[
        "tgn:7414567",
        "tgn:1000001",
        "tgn:7005591",
        "tgn:7005560",
        "tgn:7029392"
    ],
    "tgn:id":7414567,
    "tgn:name:es":"La L\u00e1mina",
    "tgn:placetype":[
        "aat:300008347"
    ]
},
  "bbox": [],
  "geometry": {"coordinates":[-95.363056,16.265556],"type":"Point"}
}