{
  "id": 2161531,
  "type": "Feature",
  "properties": {
    "tgn:hierarchy":[
        "tgn:2161531",
        "tgn:1000001",
        "tgn:7012149",
        "tgn:7007157",
        "tgn:1002894",
        "tgn:7029392"
    ],
    "tgn:id":2161531,
    "tgn:name":"Bella Union Ravine",
    "tgn:placetype":[
        "aat:300008761"
    ]
},
  "bbox": [],
  "geometry": {"coordinates":[-120.95,39.6333],"type":"Point"}
}