{
  "id": 7480862,
  "type": "Feature",
  "properties": {
    "tgn:hierarchy":[
        "tgn:7480862",
        "tgn:1000004",
        "tgn:7471332",
        "tgn:1000141",
        "tgn:7029392"
    ],
    "tgn:id":7480862,
    "tgn:name":"Baozhong Erhao Qiao",
    "tgn:placetype":[
        "aat:300007836"
    ]
},
  "bbox": [],
  "geometry": {"coordinates":[121.036111,24.831389],"type":"Point"}
}