<<<<<<< HEAD
{
  "id": 7474305,
  "type": "Feature",
  "properties": {
    "tgn:hierarchy":[
        "tgn:7474305",
        "tgn:7468018",
        "tgn:1000004",
        "tgn:1000141",
        "tgn:7029392"
    ],
    "tgn:id":7474305,
    "tgn:name":"Yuemeitan",
    "tgn:placetype":[
        "aat:300008347"
    ]
},
  "bbox": [],
  "geometry": {"coordinates":[120.351463,23.522333],"type":"Point"}
}
=======
{"geometry":{"type":"Point","coordinates":[120.351463,23.522333]},"type":"Feature","properties":{"hierarchy":["tgn:7474305","tgn:7468018","tgn:1000004","tgn:1000141","tgn:7029392"],"placetype":["aat:300008347"],"id":7474305,"name:xx":"Yuemeitan"}}
>>>>>>> 03f74aca74312dbeaf24d7e61306dd6a786dc3d0
