{
  "id": 2272812,
  "type": "Feature",
  "properties": {
    "tgn:hierarchy":[
        "tgn:2272812",
        "tgn:1000001",
        "tgn:7012149",
        "tgn:7007709",
        "tgn:7029392"
    ],
    "tgn:id":2272812,
    "tgn:name":"Cutawhiskie Creek",
    "tgn:placetype":[
        "aat:300008706"
    ]
},
  "bbox": [],
  "geometry": {"coordinates":[-77.2667,36.2667],"type":"Point"}
}