{
  "id": 7016872,
  "type": "Feature",
  "properties": {
    "tgn:hierarchy":[
        "tgn:7016872",
        "tgn:1000003",
        "tgn:7015085",
        "tgn:7006670",
        "tgn:7029392"
    ],
    "tgn:id":7016872,
    "tgn:name":"Kras",
    "tgn:placetype":[
        "aat:300000835",
        "aat:300132339"
    ]
},
  "bbox": [],
  "geometry": {"coordinates":[13.95,45.75],"type":"Point"}
}