{
  "id": 7558208,
  "type": "Feature",
  "properties": {
    "tgn:hierarchy":[
        "tgn:7558208",
        "tgn:1000004",
        "tgn:7000198",
        "tgn:1003539",
        "tgn:7029392"
    ],
    "tgn:id":7558208,
    "tgn:name:en":"Sangsik",
    "tgn:placetype":[
        "aat:300008347"
    ]
},
  "bbox": [],
  "geometry": {"coordinates":[90.864855,25.525646],"type":"Point"}
}