<<<<<<< HEAD
{
  "id": 2254911,
  "type": "Feature",
  "properties": {
    "tgn:hierarchy":[
        "tgn:2254911",
        "tgn:1000001",
        "tgn:7012149",
        "tgn:2001442",
        "tgn:7007566",
        "tgn:7029392"
    ],
    "tgn:id":2254911,
    "tgn:name":"Cooper",
    "tgn:placetype":[
        "aat:300008347"
    ]
},
  "bbox": [],
  "geometry": {"coordinates":[-105.7833,33.9167],"type":"Point"}
}
=======
{"geometry":{"type":"Point","coordinates":[-105.783300,33.916700]},"type":"Feature","properties":{"hierarchy":["tgn:2254911","tgn:1000001","tgn:7012149","tgn:2001442","tgn:7007566","tgn:7029392"],"placetype":["aat:300008347"],"id":2254911,"name:xx":"Cooper"}}
>>>>>>> 03f74aca74312dbeaf24d7e61306dd6a786dc3d0
