{
  "id": 2254911,
  "type": "Feature",
  "properties": {
    "tgn:hierarchy":[
        "tgn:2254911",
        "tgn:1000001",
        "tgn:7012149",
        "tgn:2001442",
        "tgn:7007566",
        "tgn:7029392"
    ],
    "tgn:id":2254911,
    "tgn:name":"Cooper",
    "tgn:placetype":[
        "aat:300008347"
    ]
},
  "bbox": [],
  "geometry": {"coordinates":[-105.7833,33.9167],"type":"Point"}
}