{
  "id": 7225763,
  "type": "Feature",
  "properties": {
    "tgn:hierarchy":[
        "tgn:7225763",
        "tgn:7002745",
        "tgn:7017076",
        "tgn:1000003",
        "tgn:1000074",
        "tgn:7029392"
    ],
    "tgn:id":7225763,
    "tgn:name":"Spili\u00e1roi, \u00c1kra",
    "tgn:placetype":[
        "aat:300386846"
    ]
},
  "bbox": [],
  "geometry": {"coordinates":[22.366667,36.616667],"type":"Point"}
}