{
  "id": 7088762,
  "type": "Feature",
  "properties": {
    "tgn:hierarchy":[
        "tgn:7088762",
        "tgn:1000003",
        "tgn:7003682",
        "tgn:7000084",
        "tgn:7029392"
    ],
    "tgn:id":7088762,
    "tgn:name":"Walmerbach",
    "tgn:placetype":[
        "aat:300008699"
    ]
},
  "bbox": [],
  "geometry": {"coordinates":[6.766667,50.133333],"type":"Point"}
}