<<<<<<< HEAD
{
  "id": 7353177,
  "type": "Feature",
  "properties": {
    "tgn:hierarchy":[
        "tgn:7353177",
        "tgn:1000001",
        "tgn:1001960",
        "tgn:7005560",
        "tgn:7029392"
    ],
    "tgn:id":7353177,
    "tgn:name":"Buenavista",
    "tgn:placetype":[
        "aat:300008347"
    ]
},
  "bbox": [],
  "geometry": {"coordinates":[-109.4,27.1],"type":"Point"}
}
=======
{"geometry":{"type":"Point","coordinates":[-109.400000,27.100000]},"type":"Feature","properties":{"hierarchy":["tgn:7353177","tgn:1000001","tgn:1001960","tgn:7005560","tgn:7029392"],"placetype":["aat:300008347"],"id":7353177,"name:xx":"Buenavista"}}
>>>>>>> 03f74aca74312dbeaf24d7e61306dd6a786dc3d0
