{
  "id": 2339947,
  "type": "Feature",
  "properties": {
    "tgn:hierarchy":[
        "tgn:2339947",
        "tgn:1000001",
        "tgn:7012149",
        "tgn:2002271",
        "tgn:7013961",
        "tgn:7029392"
    ],
    "tgn:id":2339947,
    "tgn:name":"Freemans Creek",
    "tgn:placetype":[
        "aat:300008706"
    ]
},
  "bbox": [],
  "geometry": {"coordinates":[-80.5167,39.0833],"type":"Point"}
}