{
  "id": 7258674,
  "type": "Feature",
  "properties": {
    "tgn:hierarchy":[
        "tgn:7258674",
        "tgn:1000003",
        "tgn:7003632",
        "tgn:7016845",
        "tgn:7029392"
    ],
    "tgn:id":7258674,
    "tgn:name:nl":"Bovenkerk, Polder",
    "tgn:placetype":[
        "aat:300006163"
    ]
},
  "bbox": [],
  "geometry": {"coordinates":[4.783333,51.966667],"type":"Point"}
}