<<<<<<< HEAD
{
  "id": 7113315,
  "type": "Feature",
  "properties": {
    "tgn:hierarchy":[
        "tgn:7113315",
        "tgn:7003669",
        "tgn:1000003",
        "tgn:7000084",
        "tgn:7029392"
    ],
    "tgn:id":7113315,
    "tgn:name":"Reusch",
    "tgn:placetype":[
        "aat:300008347"
    ]
},
  "bbox": [],
  "geometry": {"coordinates":[10.1,49.35],"type":"Point"}
}
=======
{"geometry":{"type":"Point","coordinates":[10.100000,49.350000]},"type":"Feature","properties":{"hierarchy":["tgn:7113315","tgn:7003669","tgn:1000003","tgn:7000084","tgn:7029392"],"placetype":["aat:300008347"],"id":7113315,"name:xx":"Reusch"}}
>>>>>>> 03f74aca74312dbeaf24d7e61306dd6a786dc3d0
