{
  "id": 2446534,
  "type": "Feature",
  "properties": {
    "tgn:hierarchy":[
        "tgn:2446534",
        "tgn:1000001",
        "tgn:7012149",
        "tgn:2002165",
        "tgn:7007919",
        "tgn:7029392"
    ],
    "tgn:id":2446534,
    "tgn:name":"Lewis Mountain",
    "tgn:placetype":[
        "aat:300008798"
    ]
},
  "bbox": [],
  "geometry": {"coordinates":[-78.4667,38.4167],"type":"Point"}
}