{
  "id": 1105131,
  "type": "Feature",
  "properties": {
    "tgn:hierarchy":[
        "tgn:1105131",
        "tgn:1000004",
        "tgn:1001161",
        "tgn:1000135",
        "tgn:7029392"
    ],
    "tgn:id":1105131,
    "tgn:name":"Kaatoan",
    "tgn:placetype":[
        "aat:300008795"
    ]
},
  "bbox": [],
  "geometry": {"coordinates":[124.9833,8.1167],"type":"Point"}
}