{
  "id": 2774537,
  "type": "Feature",
  "properties": {
    "tgn:hierarchy":[
        "tgn:2774537",
        "tgn:1000001",
        "tgn:7012149",
        "tgn:1002746",
        "tgn:7007568",
        "tgn:7029392"
    ],
    "tgn:id":2774537,
    "tgn:name":"Willow Point",
    "tgn:placetype":[
        "aat:300008850"
    ]
},
  "bbox": [],
  "geometry": {"coordinates":[-76.2667,42.7833],"type":"Point"}
}