{
  "id": 7277923,
  "type": "Feature",
  "properties": {
    "tgn:hierarchy":[
        "tgn:7277923",
        "tgn:1001699",
        "tgn:1000049",
        "tgn:1000002",
        "tgn:7029392"
    ],
    "tgn:id":7277923,
    "tgn:name":"R\u00edo Collil",
    "tgn:placetype":[
        "aat:300008699"
    ]
},
  "bbox": [],
  "geometry": {"coordinates":[-73.954444,-42.553889],"type":"Point"}
}