{
  "id": 7252745,
  "type": "Feature",
  "properties": {
    "tgn:hierarchy":[
        "tgn:7252745",
        "tgn:7007877",
        "tgn:1000003",
        "tgn:1000063",
        "tgn:4012014",
        "tgn:7029392"
    ],
    "tgn:id":7252745,
    "tgn:name":"Tout lui Faut",
    "tgn:placetype":[
        "aat:300000206"
    ]
},
  "bbox": [],
  "geometry": {"coordinates":[4.433333,50.633333],"type":"Point"}
}