{
  "id": 7333317,
  "type": "Feature",
  "properties": {
    "tgn:hierarchy":[
        "tgn:7333317",
        "tgn:7010420",
        "tgn:1000003",
        "tgn:7002795",
        "tgn:1000095",
        "tgn:7029392"
    ],
    "tgn:id":7333317,
    "tgn:name":"Fuente del Berrato, Arroyo de la",
    "tgn:placetype":[
        "aat:300008699"
    ]
},
  "bbox": [],
  "geometry": {"coordinates":[-3.466667,40.05],"type":"Point"}
}