{
  "id": 7404010,
  "type": "Feature",
  "properties": {
    "tgn:hierarchy":[
        "tgn:7404010",
        "tgn:7005578",
        "tgn:1000001",
        "tgn:7005560",
        "tgn:7029392"
    ],
    "tgn:id":7404010,
    "tgn:name":"Sitymue, Laguna",
    "tgn:placetype":[
        "aat:300008680"
    ]
},
  "bbox": [],
  "geometry": {"coordinates":[-90.316667,18.583333],"type":"Point"}
}