{
  "id": 1063866,
  "type": "Feature",
  "properties": {
    "tgn:hierarchy":[
        "tgn:1063866",
        "tgn:1000003",
        "tgn:1000462",
        "tgn:1000097",
        "tgn:7029392"
    ],
    "tgn:id":1063866,
    "tgn:name":"Ytterharn\u00e4s",
    "tgn:placetype":[
        "aat:300008347"
    ]
},
  "bbox": [],
  "geometry": {"coordinates":[17.35,60.65],"type":"Point"}
}