{
  "id": 2245879,
  "type": "Feature",
  "properties": {
    "tgn:hierarchy":[
        "tgn:2245879",
        "tgn:1000001",
        "tgn:2002369",
        "tgn:7012149",
        "tgn:7007923",
        "tgn:7029392"
    ],
    "tgn:id":2245879,
    "tgn:name":"Coal Hill",
    "tgn:placetype":[
        "aat:300008798"
    ]
},
  "bbox": [],
  "geometry": {"coordinates":[-105.8333,43.0167],"type":"Point"}
}