<<<<<<< HEAD
{
  "id": 7378430,
  "type": "Feature",
  "properties": {
    "tgn:hierarchy":[
        "tgn:7378430",
        "tgn:1000001",
        "tgn:7005589",
        "tgn:7005560",
        "tgn:7029392"
    ],
    "tgn:id":7378430,
    "tgn:name":"La Providencia",
    "tgn:placetype":[
        "aat:300008347"
    ]
},
  "bbox": [],
  "geometry": {"coordinates":[-98.783333,25.95],"type":"Point"}
}
=======
{"geometry":{"type":"Point","coordinates":[-98.783333,25.950000]},"type":"Feature","properties":{"hierarchy":["tgn:7378430","tgn:1000001","tgn:7005589","tgn:7005560","tgn:7029392"],"placetype":["aat:300008347"],"id":7378430,"name:xx":"La Providencia"}}
>>>>>>> 03f74aca74312dbeaf24d7e61306dd6a786dc3d0
