<<<<<<< HEAD
{
  "id": 7052830,
  "type": "Feature",
  "properties": {
    "tgn:hierarchy":[
        "tgn:7052830",
        "tgn:1000003",
        "tgn:7003152",
        "tgn:7003237",
        "tgn:1000080",
        "tgn:7029392"
    ],
    "tgn:id":7052830,
    "tgn:name":"Malinone",
    "tgn:placetype":[
        "aat:300008347"
    ]
},
  "bbox": [],
  "geometry": {"coordinates":[9.483333,46.35],"type":"Point"}
}
=======
{"geometry":{"type":"Point","coordinates":[9.483333,46.350000]},"type":"Feature","properties":{"hierarchy":["tgn:7052830","tgn:1000003","tgn:7003152","tgn:7003237","tgn:1000080","tgn:7029392"],"placetype":["aat:300008347"],"id":7052830,"name:xx":"Malinone"}}
>>>>>>> 03f74aca74312dbeaf24d7e61306dd6a786dc3d0
