{
  "id": 2539499,
  "type": "Feature",
  "properties": {
    "tgn:hierarchy":[
        "tgn:2539499",
        "tgn:1000001",
        "tgn:1002712",
        "tgn:7012149",
        "tgn:7007159",
        "tgn:7029392"
    ],
    "tgn:id":2539499,
    "tgn:name":"New Naugatuck Reservoir",
    "tgn:placetype":[
        "aat:300006191"
    ]
},
  "bbox": [],
  "geometry": {"coordinates":[-72.9833,41.45],"type":"Point"}
}