{
  "id": 2630666,
  "type": "Feature",
  "properties": {
    "tgn:hierarchy":[
        "tgn:2630666",
        "tgn:1000001",
        "tgn:2000955",
        "tgn:7012149",
        "tgn:7007520",
        "tgn:7029392"
    ],
    "tgn:id":2630666,
    "tgn:name":"Round Island",
    "tgn:placetype":[
        "aat:300008791"
    ]
},
  "bbox": [],
  "geometry": {"coordinates":[-87.1667,45.6333],"type":"Point"}
}