{
  "id": 1117497,
  "type": "Feature",
  "properties": {
    "tgn:hierarchy":[
        "tgn:1117497",
        "tgn:7594394",
        "tgn:1000003",
        "tgn:1000069",
        "tgn:7029392"
    ],
    "tgn:id":1117497,
    "tgn:name":"Nilakka",
    "tgn:placetype":[
        "aat:300008680"
    ]
},
  "bbox": [],
  "geometry": {"coordinates":[26.55,63.116667],"type":"Point"}
}