{
  "id": 2077879,
  "type": "Feature",
  "properties": {
    "tgn:hierarchy":[
        "tgn:2077879",
        "tgn:1000001",
        "tgn:2001575",
        "tgn:7012149",
        "tgn:7007705",
        "tgn:7029392"
    ],
    "tgn:id":2077879,
    "tgn:name":"New Leipzig",
    "tgn:placetype":[
        "aat:300008347"
    ]
},
  "bbox": [],
  "geometry": {"coordinates":[-101.9333,46.3667],"type":"Point"}
}