{
  "id": 2209725,
  "type": "Feature",
  "properties": {
    "tgn:hierarchy":[
        "tgn:2209725",
        "tgn:1000001",
        "tgn:7012149",
        "tgn:7007566",
        "tgn:7029392"
    ],
    "tgn:id":2209725,
    "tgn:name":"Burro Canyon",
    "tgn:placetype":[
        "aat:300008761"
    ]
},
  "bbox": [],
  "geometry": {"coordinates":[-104.1667,35.8833],"type":"Point"}
}