{
  "id": 2276725,
  "type": "Feature",
  "properties": {
    "tgn:hierarchy":[
        "tgn:2276725",
        "tgn:1000001",
        "tgn:7012149",
        "tgn:2000963",
        "tgn:7007520",
        "tgn:7029392"
    ],
    "tgn:id":2276725,
    "tgn:name":"Davidson Lakes",
    "tgn:placetype":[
        "aat:300008680"
    ]
},
  "bbox": [],
  "geometry": {"coordinates":[-88.9667,46.5167],"type":"Point"}
}