{
  "id": 1055748,
  "type": "Feature",
  "properties": {
    "tgn:hierarchy":[
        "tgn:1055748",
        "tgn:1000003",
        "tgn:7011668",
        "tgn:7006660",
        "tgn:7029392"
    ],
    "tgn:id":1055748,
    "tgn:name":"Kozova",
    "tgn:placetype":[
        "aat:300008347"
    ]
},
  "bbox": [],
  "geometry": {"coordinates":[25.15,49.4167],"type":"Point"}
}