{
  "id": 7246073,
  "type": "Feature",
  "properties": {
    "tgn:hierarchy":[
        "tgn:7246073",
        "tgn:7003457",
        "tgn:1000003",
        "tgn:1000063",
        "tgn:7018236",
        "tgn:7029392"
    ],
    "tgn:id":7246073,
    "tgn:name":"Booigem",
    "tgn:placetype":[
        "aat:300008347"
    ]
},
  "bbox": [],
  "geometry": {"coordinates":[3.962025,50.996441],"type":"Point"}
}