<<<<<<< HEAD
{
  "id": 2159910,
  "type": "Feature",
  "properties": {
    "tgn:hierarchy":[
        "tgn:2159910",
        "tgn:1000001",
        "tgn:7012149",
        "tgn:2000839",
        "tgn:7007255",
        "tgn:7029392"
    ],
    "tgn:id":2159910,
    "tgn:name":"Beech Grove Ridge",
    "tgn:placetype":[
        "aat:300266640"
    ]
},
  "bbox": [],
  "geometry": {"coordinates":[-84.6833,37.15],"type":"Point"}
}
=======
{"geometry":{"type":"Point","coordinates":[-84.683300,37.150000]},"type":"Feature","properties":{"hierarchy":["tgn:2159910","tgn:1000001","tgn:7012149","tgn:2000839","tgn:7007255","tgn:7029392"],"placetype":["aat:300266640"],"id":2159910,"name:xx":"Beech Grove Ridge"}}
>>>>>>> 03f74aca74312dbeaf24d7e61306dd6a786dc3d0
