{
  "id": 2143096,
  "type": "Feature",
  "properties": {
    "tgn:hierarchy":[
        "tgn:2143096",
        "tgn:1000001",
        "tgn:7006451",
        "tgn:7012149",
        "tgn:2000099",
        "tgn:7029392"
    ],
    "tgn:id":2143096,
    "tgn:name":"Baha Tank",
    "tgn:placetype":[
        "aat:300006191"
    ]
},
  "bbox": [],
  "geometry": {"coordinates":[-109.9333,33.9167],"type":"Point"}
}