{
  "id": 2234728,
  "type": "Feature",
  "properties": {
    "tgn:hierarchy":[
        "tgn:2234728",
        "tgn:1000001",
        "tgn:7012149",
        "tgn:2000217",
        "tgn:7007158",
        "tgn:7029392"
    ],
    "tgn:id":2234728,
    "tgn:name":"Cherry Creek",
    "tgn:placetype":[
        "aat:300008706"
    ]
},
  "bbox": [],
  "geometry": {"coordinates":[-107.2667,38.25],"type":"Point"}
}