{
  "id": 1139295,
  "type": "Feature",
  "properties": {
    "tgn:hierarchy":[
        "tgn:1139295",
        "tgn:1000004",
        "tgn:7002078",
        "tgn:1000111",
        "tgn:7029392"
    ],
    "tgn:id":1139295,
    "tgn:name":"Longgang",
    "tgn:placetype":[
        "aat:300008347"
    ]
},
  "bbox": [],
  "geometry": {"coordinates":[114.9167,29.6333],"type":"Point"}
}