{
  "id": 2199236,
  "type": "Feature",
  "properties": {
    "tgn:hierarchy":[
        "tgn:2199236",
        "tgn:1000001",
        "tgn:2001738",
        "tgn:7012149",
        "tgn:7007712",
        "tgn:7029392"
    ],
    "tgn:id":2199236,
    "tgn:name":"Brunson Branch",
    "tgn:placetype":[
        "aat:300008699"
    ]
},
  "bbox": [],
  "geometry": {"coordinates":[-80.0833,33.6833],"type":"Point"}
}