{
  "id": 1123932,
  "type": "Feature",
  "properties": {
    "tgn:hierarchy":[
        "tgn:1123932",
        "tgn:1000001",
        "tgn:7012149",
        "tgn:2001296",
        "tgn:7007524",
        "tgn:7029392"
    ],
    "tgn:id":1123932,
    "tgn:name":"Fisher",
    "tgn:placetype":[
        "aat:300008707"
    ]
},
  "bbox": [],
  "geometry": {"coordinates":[-112.5333,48.3667],"type":"Point"}
}