{
  "id": 7089566,
  "type": "Feature",
  "properties": {
    "tgn:hierarchy":[
        "tgn:7089566",
        "tgn:1000003",
        "tgn:7003689",
        "tgn:7000084",
        "tgn:7029392"
    ],
    "tgn:id":7089566,
    "tgn:name":"Vieh-Berg",
    "tgn:placetype":[
        "aat:300008777"
    ]
},
  "bbox": [],
  "geometry": {"coordinates":[11.983333,50.733333],"type":"Point"}
}