{
  "id": 7284277,
  "type": "Feature",
  "properties": {
    "tgn:hierarchy":[
        "tgn:7284277",
        "tgn:7016598",
        "tgn:1000049",
        "tgn:1000002",
        "tgn:7029392"
    ],
    "tgn:id":7284277,
    "tgn:name":"Pingo, Cerro del",
    "tgn:placetype":[
        "aat:300008795"
    ]
},
  "bbox": [],
  "geometry": {"coordinates":[-70.25,-25.633333],"type":"Point"}
}