{
  "id": 1010197,
  "type": "Feature",
  "properties": {
    "tgn:hierarchy":[
        "tgn:1010197",
        "tgn:1000003",
        "tgn:7003676",
        "tgn:7000084",
        "tgn:7029392"
    ],
    "tgn:id":1010197,
    "tgn:name":"Ostfriesische Inseln",
    "tgn:placetype":[
        "aat:300386854",
        "aat:300008791"
    ]
},
  "bbox": [],
  "geometry": {"coordinates":[7.416667,53.733333],"type":"Point"}
}