{
  "id": 2609212,
  "type": "Feature",
  "properties": {
    "tgn:hierarchy":[
        "tgn:2609212",
        "tgn:1000001",
        "tgn:7012149",
        "tgn:1002315",
        "tgn:7007826",
        "tgn:7029392"
    ],
    "tgn:id":2609212,
    "tgn:name":"Rawlins",
    "tgn:placetype":[
        "aat:300008347"
    ]
},
  "bbox": [],
  "geometry": {"coordinates":[-96.7333,32.8333],"type":"Point"}
}