{
  "id": 2688589,
  "type": "Feature",
  "properties": {
    "tgn:hierarchy":[
        "tgn:2688589",
        "tgn:1000001",
        "tgn:2000925",
        "tgn:7012149",
        "tgn:7007515",
        "tgn:7029392"
    ],
    "tgn:id":2688589,
    "tgn:name":"Spruce Point",
    "tgn:placetype":[
        "aat:300008850"
    ]
},
  "bbox": [],
  "geometry": {"coordinates":[-69.6167,43.8167],"type":"Point"}
}