{
  "id": 7440683,
  "type": "Feature",
  "properties": {
    "tgn:hierarchy":[
        "tgn:7440683",
        "tgn:7005580",
        "tgn:1000001",
        "tgn:7005560",
        "tgn:7029392"
    ],
    "tgn:id":7440683,
    "tgn:name":"Santa Mar\u00eda",
    "tgn:placetype":[
        "aat:300008347"
    ]
},
  "bbox": [],
  "geometry": {"coordinates":[-93.283333,17.666667],"type":"Point"}
}