<<<<<<< HEAD
{
  "id": 7240722,
  "type": "Feature",
  "properties": {
    "tgn:hierarchy":[
        "tgn:7240722",
        "tgn:7003466",
        "tgn:1000003",
        "tgn:1000063",
        "tgn:4012014",
        "tgn:7029392"
    ],
    "tgn:id":7240722,
    "tgn:name":"Fin Fourneau",
    "tgn:placetype":[
        "aat:300008347"
    ]
},
  "bbox": [],
  "geometry": {"coordinates":[4.95,50.233333],"type":"Point"}
}
=======
{"geometry":{"type":"Point","coordinates":[4.950000,50.233333]},"type":"Feature","properties":{"hierarchy":["tgn:7240722","tgn:7003466","tgn:1000003","tgn:1000063","tgn:4012014","tgn:7029392"],"placetype":["aat:300008347"],"id":7240722,"name:xx":"Fin Fourneau"}}
>>>>>>> 03f74aca74312dbeaf24d7e61306dd6a786dc3d0
