{
  "id": 2042288,
  "type": "Feature",
  "properties": {
    "tgn:hierarchy":[
        "tgn:2042288",
        "tgn:1000001",
        "tgn:7012149",
        "tgn:2000902",
        "tgn:7007256",
        "tgn:7029392"
    ],
    "tgn:id":2042288,
    "tgn:name":"Beggs",
    "tgn:placetype":[
        "aat:300008347",
        "aat:300387210"
    ]
},
  "bbox": [],
  "geometry": {"coordinates":[-92.05,30.6667],"type":"Point"}
}