{
  "id": 2775555,
  "type": "Feature",
  "properties": {
    "tgn:hierarchy":[
        "tgn:2775555",
        "tgn:1000001",
        "tgn:7012149",
        "tgn:2001719",
        "tgn:7007708",
        "tgn:7029392"
    ],
    "tgn:id":2775555,
    "tgn:name":"Wilson Creek",
    "tgn:placetype":[
        "aat:300008706"
    ]
},
  "bbox": [],
  "geometry": {"coordinates":[-119.2833,45.15],"type":"Point"}
}