{
  "id": 2459426,
  "type": "Feature",
  "properties": {
    "tgn:hierarchy":[
        "tgn:2459426",
        "tgn:1000001",
        "tgn:2000604",
        "tgn:7012149",
        "tgn:7007253",
        "tgn:7029392"
    ],
    "tgn:id":2459426,
    "tgn:name":"Little Potomac Creek",
    "tgn:placetype":[
        "aat:300008706"
    ]
},
  "bbox": [],
  "geometry": {"coordinates":[-91.4667,41.05],"type":"Point"}
}