{
  "id": 7047666,
  "type": "Feature",
  "properties": {
    "tgn:hierarchy":[
        "tgn:7047666",
        "tgn:1003489",
        "tgn:7004610",
        "tgn:1000003",
        "tgn:1000080",
        "tgn:7029392"
    ],
    "tgn:id":7047666,
    "tgn:name":"Cirigliano, Fiume",
    "tgn:placetype":[
        "aat:300008699"
    ]
},
  "bbox": [],
  "geometry": {"coordinates":[16.216667,40.333333],"type":"Point"}
}