{
  "id": 7527618,
  "type": "Feature",
  "properties": {
    "tgn:hierarchy":[
        "tgn:7527618",
        "tgn:7001242",
        "tgn:7016833",
        "tgn:7029392"
    ],
    "tgn:id":7527618,
    "tgn:name":"Umm 'Al\u0101qah, W\u0101d\u012b",
    "tgn:placetype":[
        "aat:300379998"
    ]
},
  "bbox": [],
  "geometry": {"coordinates":[31.509708,29.888811],"type":"Point"}
}