{
  "id": 2222262,
  "type": "Feature",
  "properties": {
    "tgn:hierarchy":[
        "tgn:2222262",
        "tgn:1000001",
        "tgn:7014423",
        "tgn:7012149",
        "tgn:7007517",
        "tgn:7029392"
    ],
    "tgn:id":2222262,
    "tgn:name":"Carolina Hill",
    "tgn:placetype":[
        "aat:300008798"
    ]
},
  "bbox": [],
  "geometry": {"coordinates":[-70.7167,42.1167],"type":"Point"}
}