{
  "id": 1043114,
  "type": "Feature",
  "properties": {
    "tgn:hierarchy":[
        "tgn:1043114",
        "tgn:7003132",
        "tgn:1000003",
        "tgn:7008516",
        "tgn:1000080",
        "tgn:7029392"
    ],
    "tgn:id":1043114,
    "tgn:name":"Agazzano",
    "tgn:placetype":[
        "aat:300008347"
    ]
},
  "bbox": [],
  "geometry": {"coordinates":[9.516667,44.95],"type":"Point"}
}