<<<<<<< HEAD
{
  "id": 7483245,
  "type": "Feature",
  "properties": {
    "tgn:hierarchy":[
        "tgn:7483245",
        "tgn:1000004",
        "tgn:7490934",
        "tgn:1000141",
        "tgn:7029392"
    ],
    "tgn:id":7483245,
    "tgn:name":"Zhuzi Jianshan Dongfeng",
    "tgn:placetype":[
        "aat:300008798"
    ]
},
  "bbox": [],
  "geometry": {"coordinates":[120.573889,23.177222],"type":"Point"}
}
=======
{"geometry":{"type":"Point","coordinates":[120.573889,23.177222]},"type":"Feature","properties":{"hierarchy":["tgn:7483245","tgn:1000004","tgn:7490934","tgn:1000141","tgn:7029392"],"placetype":["aat:300008798"],"id":7483245,"name:xx":"Zhuzi Jianshan Dongfeng"}}
>>>>>>> 03f74aca74312dbeaf24d7e61306dd6a786dc3d0
