<<<<<<< HEAD
{
  "id": 2256409,
  "type": "Feature",
  "properties": {
    "tgn:hierarchy":[
        "tgn:2256409",
        "tgn:1000001",
        "tgn:7012149",
        "tgn:2000237",
        "tgn:7007158",
        "tgn:7029392"
    ],
    "tgn:id":2256409,
    "tgn:name":"Cora Belle Mine",
    "tgn:placetype":[
        "aat:300000390"
    ]
},
  "bbox": [],
  "geometry": {"coordinates":[-107.6833,37.9167],"type":"Point"}
}
=======
{"geometry":{"type":"Point","coordinates":[-107.683300,37.916700]},"type":"Feature","properties":{"hierarchy":["tgn:2256409","tgn:1000001","tgn:7012149","tgn:2000237","tgn:7007158","tgn:7029392"],"placetype":["aat:300000390"],"id":2256409,"name:xx":"Cora Belle Mine"}}
>>>>>>> 03f74aca74312dbeaf24d7e61306dd6a786dc3d0
