{
  "id": 7217533,
  "type": "Feature",
  "properties": {
    "tgn:hierarchy":[
        "tgn:7217533",
        "tgn:7002680",
        "tgn:7001395",
        "tgn:1000003",
        "tgn:1000074",
        "tgn:7029392"
    ],
    "tgn:id":7217533,
    "tgn:name":"Trizon\u00eda",
    "tgn:placetype":[
        "aat:300008347"
    ]
},
  "bbox": [],
  "geometry": {"coordinates":[22.083333,38.366667],"type":"Point"}
}