{
  "id": 7301971,
  "type": "Feature",
  "properties": {
    "tgn:hierarchy":[
        "tgn:7301971",
        "tgn:7002844",
        "tgn:7030216",
        "tgn:1000003",
        "tgn:1000095",
        "tgn:7029392"
    ],
    "tgn:id":7301971,
    "tgn:name":"Mitj Jorn, R\u00edo",
    "tgn:placetype":[
        "aat:300008699"
    ]
},
  "bbox": [],
  "geometry": {"coordinates":[0.85,40.683333],"type":"Point"}
}