{
  "id": 7072435,
  "type": "Feature",
  "properties": {
    "tgn:hierarchy":[
        "tgn:7072435",
        "tgn:7003669",
        "tgn:1000003",
        "tgn:7000084",
        "tgn:7029392"
    ],
    "tgn:id":7072435,
    "tgn:name":"T\u00e4schle-Graben",
    "tgn:placetype":[
        "aat:300008699"
    ]
},
  "bbox": [],
  "geometry": {"coordinates":[10.416667,47.416667],"type":"Point"}
}