{
  "id": 7476487,
  "type": "Feature",
  "properties": {
    "tgn:hierarchy":[
        "tgn:7476487",
        "tgn:1000004",
        "tgn:7489179",
        "tgn:1000141",
        "tgn:7029392"
    ],
    "tgn:id":7476487,
    "tgn:name":"Annong Xi",
    "tgn:placetype":[
        "aat:300008699"
    ]
},
  "bbox": [],
  "geometry": {"coordinates":[121.752549,24.695934],"type":"Point"}
}