{
  "id": 7110522,
  "type": "Feature",
  "properties": {
    "tgn:hierarchy":[
        "tgn:7110522",
        "tgn:1000003",
        "tgn:7003687",
        "tgn:7000084",
        "tgn:7029392"
    ],
    "tgn:id":7110522,
    "tgn:name":"Raunitz",
    "tgn:placetype":[
        "aat:300000745"
    ]
},
  "bbox": [],
  "geometry": {"coordinates":[11.866667,51.566667],"type":"Point"}
}