<<<<<<< HEAD
{
  "id": 7110522,
  "type": "Feature",
  "properties": {
    "tgn:hierarchy":[
        "tgn:7110522",
        "tgn:1000003",
        "tgn:7003687",
        "tgn:7000084",
        "tgn:7029392"
    ],
    "tgn:id":7110522,
    "tgn:name":"Raunitz",
    "tgn:placetype":[
        "aat:300000745"
    ]
},
  "bbox": [],
  "geometry": {"coordinates":[11.866667,51.566667],"type":"Point"}
}
=======
{"geometry":{"type":"Point","coordinates":[11.866667,51.566667]},"type":"Feature","properties":{"hierarchy":["tgn:7110522","tgn:1000003","tgn:7003687","tgn:7000084","tgn:7029392"],"placetype":["aat:300000745"],"id":7110522,"name:xx":"Raunitz"}}
>>>>>>> 03f74aca74312dbeaf24d7e61306dd6a786dc3d0
