{
  "id": 7457917,
  "type": "Feature",
  "properties": {
    "tgn:hierarchy":[
        "tgn:7457917",
        "tgn:7019140",
        "tgn:7002444",
        "tgn:1000003",
        "tgn:7008591",
        "tgn:7029392"
    ],
    "tgn:id":7457917,
    "tgn:name:en":"Mooran, Burn of",
    "tgn:placetype":[
        "aat:300008699"
    ]
},
  "bbox": [],
  "geometry": {"coordinates":[-2.716667,56.85],"type":"Point"}
}