<<<<<<< HEAD
{
  "id": 7379795,
  "type": "Feature",
  "properties": {
    "tgn:hierarchy":[
        "tgn:7379795",
        "tgn:1000001",
        "tgn:1001960",
        "tgn:7005560",
        "tgn:7029392"
    ],
    "tgn:id":7379795,
    "tgn:name":"Rancho Mart\u00ednez",
    "tgn:placetype":[
        "aat:300000241"
    ]
},
  "bbox": [],
  "geometry": {"coordinates":[-109.8,30.233333],"type":"Point"}
}
=======
{"geometry":{"type":"Point","coordinates":[-109.800000,30.233333]},"type":"Feature","properties":{"hierarchy":["tgn:7379795","tgn:1000001","tgn:1001960","tgn:7005560","tgn:7029392"],"placetype":["aat:300000241"],"id":7379795,"name:xx":"Rancho Mart\u00ednez"}}
>>>>>>> 03f74aca74312dbeaf24d7e61306dd6a786dc3d0
