{
  "id": 7294396,
  "type": "Feature",
  "properties": {
    "tgn:hierarchy":[
        "tgn:7294396",
        "tgn:7002826",
        "tgn:7001158",
        "tgn:1000003",
        "tgn:1000095",
        "tgn:7029392"
    ],
    "tgn:id":7294396,
    "tgn:name":"Vegarienza",
    "tgn:placetype":[
        "aat:300008347"
    ]
},
  "bbox": [],
  "geometry": {"coordinates":[-6.05,42.783333],"type":"Point"}
}