{
  "id": 7218386,
  "type": "Feature",
  "properties": {
    "tgn:hierarchy":[
        "tgn:7218386",
        "tgn:7011170",
        "tgn:7002715",
        "tgn:1000003",
        "tgn:1000074",
        "tgn:7029392"
    ],
    "tgn:id":7218386,
    "tgn:name":"Tragasi\u00e1",
    "tgn:placetype":[
        "aat:300008347"
    ]
},
  "bbox": [],
  "geometry": {"coordinates":[24.933333,40.966667],"type":"Point"}
}