{
  "id": 2255456,
  "type": "Feature",
  "properties": {
    "tgn:hierarchy":[
        "tgn:2255456",
        "tgn:1000001",
        "tgn:7012149",
        "tgn:7013867",
        "tgn:7007710",
        "tgn:7029392"
    ],
    "tgn:id":2255456,
    "tgn:name":"Coover Run",
    "tgn:placetype":[
        "aat:300008699"
    ]
},
  "bbox": [],
  "geometry": {"coordinates":[-76.1167,40.1833],"type":"Point"}
}