<<<<<<< HEAD
{
  "id": 2255456,
  "type": "Feature",
  "properties": {
    "tgn:hierarchy":[
        "tgn:2255456",
        "tgn:1000001",
        "tgn:7012149",
        "tgn:7013867",
        "tgn:7007710",
        "tgn:7029392"
    ],
    "tgn:id":2255456,
    "tgn:name":"Coover Run",
    "tgn:placetype":[
        "aat:300008699"
    ]
},
  "bbox": [],
  "geometry": {"coordinates":[-76.1167,40.1833],"type":"Point"}
}
=======
{"geometry":{"type":"Point","coordinates":[-76.116700,40.183300]},"type":"Feature","properties":{"hierarchy":["tgn:2255456","tgn:1000001","tgn:7012149","tgn:7013867","tgn:7007710","tgn:7029392"],"placetype":["aat:300008699"],"id":2255456,"name:xx":"Coover Run"}}
>>>>>>> 03f74aca74312dbeaf24d7e61306dd6a786dc3d0
