{
  "id": 7585864,
  "type": "Feature",
  "properties": {
    "tgn:hierarchy":[
        "tgn:7585864",
        "tgn:1000004",
        "tgn:7000198",
        "tgn:7000799",
        "tgn:7029392"
    ],
    "tgn:id":7585864,
    "tgn:name:en":"Nathipur",
    "tgn:placetype":[
        "aat:300008347"
    ]
},
  "bbox": [],
  "geometry": {"coordinates":[74.389756,34.36437],"type":"Point"}
}