{
  "id": 7079274,
  "type": "Feature",
  "properties": {
    "tgn:hierarchy":[
        "tgn:7079274",
        "tgn:1000003",
        "tgn:7003678",
        "tgn:7000084",
        "tgn:7029392"
    ],
    "tgn:id":7079274,
    "tgn:name":"Wirbelau",
    "tgn:placetype":[
        "aat:300008347"
    ]
},
  "bbox": [],
  "geometry": {"coordinates":[8.233333,50.45],"type":"Point"}
}