{
  "id": 7377003,
  "type": "Feature",
  "properties": {
    "tgn:hierarchy":[
        "tgn:7377003",
        "tgn:7005583",
        "tgn:1000001",
        "tgn:7005560",
        "tgn:7029392"
    ],
    "tgn:id":7377003,
    "tgn:name":"Las \u00c1nimas",
    "tgn:placetype":[
        "aat:300008347"
    ]
},
  "bbox": [],
  "geometry": {"coordinates":[-105.433333,23.433333],"type":"Point"}
}