{
  "id": 2214741,
  "type": "Feature",
  "properties": {
    "tgn:hierarchy":[
        "tgn:2214741",
        "tgn:1000001",
        "tgn:7012149",
        "tgn:2002019",
        "tgn:7007826",
        "tgn:7029392"
    ],
    "tgn:id":2214741,
    "tgn:name":"Calf Creek",
    "tgn:placetype":[
        "aat:300008706"
    ]
},
  "bbox": [],
  "geometry": {"coordinates":[-99.8833,30.4833],"type":"Point"}
}