{
  "id": 2270101,
  "type": "Feature",
  "properties": {
    "tgn:hierarchy":[
        "tgn:2270101",
        "tgn:1000001",
        "tgn:7012149",
        "tgn:2002057",
        "tgn:7007826",
        "tgn:7029392"
    ],
    "tgn:id":2270101,
    "tgn:name":"Cruz, Cerro de la",
    "tgn:placetype":[
        "aat:300008798"
    ]
},
  "bbox": [],
  "geometry": {"coordinates":[-104.5333,29.9833],"type":"Point"}
}