{
  "id": 2469087,
  "type": "Feature",
  "properties": {
    "tgn:hierarchy":[
        "tgn:2469087",
        "tgn:1000001",
        "tgn:7006451",
        "tgn:7012149",
        "tgn:2000099",
        "tgn:7029392"
    ],
    "tgn:id":2469087,
    "tgn:name":"Long Tom Spring",
    "tgn:placetype":[
        "aat:300008697"
    ]
},
  "bbox": [],
  "geometry": {"coordinates":[-110.2167,34.0167],"type":"Point"}
}