{
  "id": 7011834,
  "type": "Feature",
  "properties": {
    "tgn:hierarchy":[
        "tgn:7011834",
        "tgn:7002445",
        "tgn:7018921",
        "tgn:1000003",
        "tgn:7008136",
        "tgn:7008591",
        "tgn:7029392"
    ],
    "tgn:id":7011834,
    "tgn:name:en":"Hanworth",
    "tgn:placetype":[
        "aat:300008347",
        "aat:300000745",
        "aat:300000874"
    ]
},
  "bbox": [],
  "geometry": {"coordinates":[-0.3833,51.4333],"type":"Point"}
}