{
  "id": 7183273,
  "type": "Feature",
  "properties": {
    "tgn:hierarchy":[
        "tgn:7183273",
        "tgn:1000003",
        "tgn:7003678",
        "tgn:7000084",
        "tgn:7029392"
    ],
    "tgn:id":7183273,
    "tgn:name":"Fulder-Berg",
    "tgn:placetype":[
        "aat:300008777"
    ]
},
  "bbox": [],
  "geometry": {"coordinates":[9.783333,50.516667],"type":"Point"}
}