{
  "id": 2350180,
  "type": "Feature",
  "properties": {
    "tgn:hierarchy":[
        "tgn:2350180",
        "tgn:1000001",
        "tgn:7012149",
        "tgn:2001896",
        "tgn:7007825",
        "tgn:7029392"
    ],
    "tgn:id":2350180,
    "tgn:name":"Gin Branch",
    "tgn:placetype":[
        "aat:300008699"
    ]
},
  "bbox": [],
  "geometry": {"coordinates":[-87.15,35.6333],"type":"Point"}
}