{
  "id": 7427922,
  "type": "Feature",
  "properties": {
    "tgn:hierarchy":[
        "tgn:7427922",
        "tgn:1000001",
        "tgn:7005594",
        "tgn:7005560",
        "tgn:7029392"
    ],
    "tgn:id":7427922,
    "tgn:name":"Zaragoza",
    "tgn:placetype":[
        "aat:300008347"
    ]
},
  "bbox": [],
  "geometry": {"coordinates":[-100.716667,23.65],"type":"Point"}
}