{
  "id": 1131076,
  "type": "Feature",
  "properties": {
    "tgn:hierarchy":[
        "tgn:1131076",
        "tgn:7003818",
        "tgn:1000003",
        "tgn:1000090",
        "tgn:7029392"
    ],
    "tgn:id":1131076,
    "tgn:name":"Tuela, Rio",
    "tgn:placetype":[
        "aat:300008707"
    ]
},
  "bbox": [],
  "geometry": {"coordinates":[-7.198,41.51],"type":"Point"}
}