<<<<<<< HEAD
{
  "id": 2155245,
  "type": "Feature",
  "properties": {
    "tgn:hierarchy":[
        "tgn:2155245",
        "tgn:1000001",
        "tgn:2000319",
        "tgn:7012149",
        "tgn:7007248",
        "tgn:7029392"
    ],
    "tgn:id":2155245,
    "tgn:name":"Bear Mountain",
    "tgn:placetype":[
        "aat:300008798"
    ]
},
  "bbox": [],
  "geometry": {"coordinates":[-84.6333,34.3],"type":"Point"}
}
=======
{"geometry":{"type":"Point","coordinates":[-84.633300,34.300000]},"type":"Feature","properties":{"hierarchy":["tgn:2155245","tgn:1000001","tgn:2000319","tgn:7012149","tgn:7007248","tgn:7029392"],"placetype":["aat:300008798"],"id":2155245,"name:xx":"Bear Mountain"}}
>>>>>>> 03f74aca74312dbeaf24d7e61306dd6a786dc3d0
