<<<<<<< HEAD
{
  "id": 2333754,
  "type": "Feature",
  "properties": {
    "tgn:hierarchy":[
        "tgn:2333754",
        "tgn:1000001",
        "tgn:7012149",
        "tgn:2000543",
        "tgn:7007252",
        "tgn:7029392"
    ],
    "tgn:id":2333754,
    "tgn:name":"Foote Pond",
    "tgn:placetype":[
        "aat:300008680"
    ]
},
  "bbox": [],
  "geometry": {"coordinates":[-87.85,38.25],"type":"Point"}
}
=======
{"geometry":{"type":"Point","coordinates":[-87.850000,38.250000]},"type":"Feature","properties":{"hierarchy":["tgn:2333754","tgn:1000001","tgn:7012149","tgn:2000543","tgn:7007252","tgn:7029392"],"placetype":["aat:300008680"],"id":2333754,"name:xx":"Foote Pond"}}
>>>>>>> 03f74aca74312dbeaf24d7e61306dd6a786dc3d0
