{
  "id": 1050980,
  "type": "Feature",
  "properties": {
    "tgn:hierarchy":[
        "tgn:1050980",
        "tgn:7002444",
        "tgn:1000003",
        "tgn:7008076",
        "tgn:7008591",
        "tgn:7029392"
    ],
    "tgn:id":1050980,
    "tgn:name":"Peat Inn",
    "tgn:placetype":[
        "aat:300008347"
    ]
},
  "bbox": [],
  "geometry": {"coordinates":[-2.8833,56.2833],"type":"Point"}
}