{
  "id": 7564965,
  "type": "Feature",
  "properties": {
    "tgn:hierarchy":[
        "tgn:7564965",
        "tgn:1000004",
        "tgn:7000198",
        "tgn:7000799",
        "tgn:7029392"
    ],
    "tgn:id":7564965,
    "tgn:name:en":"Nar\u0101yanpur",
    "tgn:placetype":[
        "aat:300008347"
    ]
},
  "bbox": [],
  "geometry": {"coordinates":[74.880748,32.479823],"type":"Point"}
}