{
  "id": 7226317,
  "type": "Feature",
  "properties": {
    "tgn:hierarchy":[
        "tgn:7226317",
        "tgn:7002711",
        "tgn:7001338",
        "tgn:1000003",
        "tgn:1000074",
        "tgn:7029392"
    ],
    "tgn:id":7226317,
    "tgn:name":"G\u00e1\u00efos",
    "tgn:placetype":[
        "aat:300008347"
    ]
},
  "bbox": [],
  "geometry": {"coordinates":[20.185556,39.197222],"type":"Point"}
}