{
  "id": 2125378,
  "type": "Feature",
  "properties": {
    "tgn:hierarchy":[
        "tgn:2125378",
        "tgn:1000001",
        "tgn:7012149",
        "tgn:7007248",
        "tgn:7029392"
    ],
    "tgn:id":2125378,
    "tgn:name":"Acocks Creek",
    "tgn:placetype":[
        "aat:300008706"
    ]
},
  "bbox": [],
  "geometry": {"coordinates":[-84.9333,31.2333],"type":"Point"}
}