{
  "id": 7369270,
  "type": "Feature",
  "properties": {
    "tgn:hierarchy":[
        "tgn:7369270",
        "tgn:1000001",
        "tgn:7005599",
        "tgn:7005560",
        "tgn:7029392"
    ],
    "tgn:id":7369270,
    "tgn:name":"Hornitos",
    "tgn:placetype":[
        "aat:300008347"
    ]
},
  "bbox": [],
  "geometry": {"coordinates":[-96.416667,19.433333],"type":"Point"}
}