{
  "id": 1076745,
  "type": "Feature",
  "properties": {
    "tgn:hierarchy":[
        "tgn:1076745",
        "tgn:1000004",
        "tgn:7000198",
        "tgn:1001977",
        "tgn:7029392"
    ],
    "tgn:id":1076745,
    "tgn:name":"Ram\u0101n\u0101thpur",
    "tgn:placetype":[
        "aat:300008347"
    ]
},
  "bbox": [],
  "geometry": {"coordinates":[88.2333,22.6833],"type":"Point"}
}