{
  "id": 7099678,
  "type": "Feature",
  "properties": {
    "tgn:hierarchy":[
        "tgn:7099678",
        "tgn:1000003",
        "tgn:7003685",
        "tgn:7000084",
        "tgn:7029392"
    ],
    "tgn:id":7099678,
    "tgn:name":"Seifen",
    "tgn:placetype":[
        "aat:300008347"
    ]
},
  "bbox": [],
  "geometry": {"coordinates":[13.633333,50.916667],"type":"Point"}
}