<<<<<<< HEAD
{
  "id": 2407575,
  "type": "Feature",
  "properties": {
    "tgn:hierarchy":[
        "tgn:2407575",
        "tgn:1000001",
        "tgn:7012149",
        "tgn:2002301",
        "tgn:7013961",
        "tgn:7029392"
    ],
    "tgn:id":2407575,
    "tgn:name":"Hupp Run",
    "tgn:placetype":[
        "aat:300008699"
    ]
},
  "bbox": [],
  "geometry": {"coordinates":[-80.7833,39.5333],"type":"Point"}
}
=======
{"geometry":{"type":"Point","coordinates":[-80.783300,39.533300]},"type":"Feature","properties":{"hierarchy":["tgn:2407575","tgn:1000001","tgn:7012149","tgn:2002301","tgn:7013961","tgn:7029392"],"placetype":["aat:300008699"],"id":2407575,"name:xx":"Hupp Run"}}
>>>>>>> 03f74aca74312dbeaf24d7e61306dd6a786dc3d0
