{
  "id": 7509329,
  "type": "Feature",
  "properties": {
    "tgn:hierarchy":[
        "tgn:7509329",
        "tgn:1009227",
        "tgn:1000226",
        "tgn:7018437",
        "tgn:1000006",
        "tgn:7029392"
    ],
    "tgn:id":7509329,
    "tgn:name:en":"The Reefs",
    "tgn:placetype":[
        "aat:300008347"
    ]
},
  "bbox": [],
  "geometry": {"coordinates":[170.25,-45.633333],"type":"Point"}
}