{
  "id": 2129653,
  "type": "Feature",
  "properties": {
    "tgn:hierarchy":[
        "tgn:2129653",
        "tgn:1000001",
        "tgn:7012149",
        "tgn:7007157",
        "tgn:1002828",
        "tgn:7029392"
    ],
    "tgn:id":2129653,
    "tgn:name":"Alkali Wash",
    "tgn:placetype":[
        "aat:300008699"
    ]
},
  "bbox": [],
  "geometry": {"coordinates":[-116.5833,33.5333],"type":"Point"}
}