<<<<<<< HEAD
{
  "id": 7176367,
  "type": "Feature",
  "properties": {
    "tgn:hierarchy":[
        "tgn:7176367",
        "tgn:7003692",
        "tgn:1000003",
        "tgn:7000084",
        "tgn:7029392"
    ],
    "tgn:id":7176367,
    "tgn:name":"Gr\u00fcnmettstetten",
    "tgn:placetype":[
        "aat:300008347"
    ]
},
  "bbox": [],
  "geometry": {"coordinates":[8.616667,48.45],"type":"Point"}
}
=======
{"geometry":{"type":"Point","coordinates":[8.616667,48.450000]},"type":"Feature","properties":{"hierarchy":["tgn:7176367","tgn:7003692","tgn:1000003","tgn:7000084","tgn:7029392"],"placetype":["aat:300008347"],"id":7176367,"name:xx":"Gr\u00fcnmettstetten"}}
>>>>>>> 03f74aca74312dbeaf24d7e61306dd6a786dc3d0
