{
  "id": 7310720,
  "type": "Feature",
  "properties": {
    "tgn:hierarchy":[
        "tgn:7310720",
        "tgn:1001702",
        "tgn:1000049",
        "tgn:1000002",
        "tgn:7029392"
    ],
    "tgn:id":7310720,
    "tgn:name":"Morgan, Isla",
    "tgn:placetype":[
        "aat:300008791"
    ]
},
  "bbox": [],
  "geometry": {"coordinates":[-75.023056,-50.066111],"type":"Point"}
}