{
  "id": 1068555,
  "type": "Feature",
  "properties": {
    "tgn:hierarchy":[
        "tgn:1068555",
        "tgn:1000004",
        "tgn:7018053",
        "tgn:1000111",
        "tgn:7029392"
    ],
    "tgn:id":1068555,
    "tgn:name":"Haiyuan",
    "tgn:placetype":[
        "aat:300008347"
    ]
},
  "bbox": [],
  "geometry": {"coordinates":[105.5333,36.5667],"type":"Point"}
}