{
  "id": 1006120,
  "type": "Feature",
  "properties": {
    "tgn:hierarchy":[
        "tgn:1006120",
        "tgn:1010237",
        "tgn:7016730",
        "tgn:1000006",
        "tgn:7029392"
    ],
    "tgn:id":1006120,
    "tgn:name":"Utirik",
    "tgn:placetype":[
        "aat:300008793"
    ]
},
  "bbox": [],
  "geometry": {"coordinates":[169.8167,11.3167],"type":"Point"}
}