{
  "id": 7416034,
  "type": "Feature",
  "properties": {
    "tgn:hierarchy":[
        "tgn:7416034",
        "tgn:7005584",
        "tgn:1000001",
        "tgn:7005560",
        "tgn:7029392"
    ],
    "tgn:id":7416034,
    "tgn:name":"Las Trojes",
    "tgn:placetype":[
        "aat:300008347"
    ]
},
  "bbox": [],
  "geometry": {"coordinates":[-101.445278,20.838611],"type":"Point"}
}