{
  "id": 2423553,
  "type": "Feature",
  "properties": {
    "tgn:hierarchy":[
        "tgn:2423553",
        "tgn:1000001",
        "tgn:7012149",
        "tgn:2002084",
        "tgn:7007826",
        "tgn:7029392"
    ],
    "tgn:id":2423553,
    "tgn:name":"John House Canyon",
    "tgn:placetype":[
        "aat:300008761"
    ]
},
  "bbox": [],
  "geometry": {"coordinates":[-99.3167,33.0167],"type":"Point"}
}