{
  "id": 2162834,
  "type": "Feature",
  "properties": {
    "tgn:hierarchy":[
        "tgn:2162834",
        "tgn:1000001",
        "tgn:2000782",
        "tgn:7012149",
        "tgn:7007255",
        "tgn:7029392"
    ],
    "tgn:id":2162834,
    "tgn:name":"Benge",
    "tgn:placetype":[
        "aat:300008347"
    ]
},
  "bbox": [],
  "geometry": {"coordinates":[-83.9167,37.2167],"type":"Point"}
}