{
  "id": 7583609,
  "type": "Feature",
  "properties": {
    "tgn:hierarchy":[
        "tgn:7583609",
        "tgn:1000004",
        "tgn:7000198",
        "tgn:1001894",
        "tgn:7029392"
    ],
    "tgn:id":7583609,
    "tgn:name:en":"Gora Protected Forest",
    "tgn:placetype":[
        "aat:300008865"
    ]
},
  "bbox": [],
  "geometry": {"coordinates":[78.842867,25.204623],"type":"Point"}
}