{
  "id": 7504851,
  "type": "Feature",
  "properties": {
    "tgn:hierarchy":[
        "tgn:7504851",
        "tgn:7016670",
        "tgn:1008380",
        "tgn:1000226",
        "tgn:1000006",
        "tgn:7029392"
    ],
    "tgn:id":7504851,
    "tgn:name:en":"Breakwater Harbour",
    "tgn:placetype":[
        "aat:300008678"
    ]
},
  "bbox": [],
  "geometry": {"coordinates":[176.916667,-39.465278],"type":"Point"}
}