{
  "id": 2027892,
  "type": "Feature",
  "properties": {
    "tgn:hierarchy":[
        "tgn:2027892",
        "tgn:1000001",
        "tgn:7012149",
        "tgn:1002739",
        "tgn:7007251",
        "tgn:7029392"
    ],
    "tgn:id":2027892,
    "tgn:name":"Forreston",
    "tgn:placetype":[
        "aat:300008347"
    ]
},
  "bbox": [],
  "geometry": {"coordinates":[-89.5667,42.1167],"type":"Point"}
}