{
  "id": 7329170,
  "type": "Feature",
  "properties": {
    "tgn:hierarchy":[
        "tgn:7329170",
        "tgn:7002824",
        "tgn:1000003",
        "tgn:7002786",
        "tgn:1000095",
        "tgn:7029392"
    ],
    "tgn:id":7329170,
    "tgn:name":"Rebordi\u00f1o, Punta de",
    "tgn:placetype":[
        "aat:300386846"
    ]
},
  "bbox": [],
  "geometry": {"coordinates":[-9.05,42.766667],"type":"Point"}
}