{
  "id": 2695203,
  "type": "Feature",
  "properties": {
    "tgn:hierarchy":[
        "tgn:2695203",
        "tgn:1000001",
        "tgn:7012149",
        "tgn:2001191",
        "tgn:7007523",
        "tgn:7029392"
    ],
    "tgn:id":2695203,
    "tgn:name":"Stillhouse Hollow",
    "tgn:placetype":[
        "aat:300008761"
    ]
},
  "bbox": [],
  "geometry": {"coordinates":[-93.7333,37.2833],"type":"Point"}
}