<<<<<<< HEAD
{
  "id": 2151550,
  "type": "Feature",
  "properties": {
    "tgn:hierarchy":[
        "tgn:2151550",
        "tgn:1000001",
        "tgn:2000301",
        "tgn:7012149",
        "tgn:7007248",
        "tgn:7029392"
    ],
    "tgn:id":2151550,
    "tgn:name":"Batterbee Branch",
    "tgn:placetype":[
        "aat:300008699"
    ]
},
  "bbox": [],
  "geometry": {"coordinates":[-83.1833,31.1],"type":"Point"}
}
=======
{"geometry":{"type":"Point","coordinates":[-83.183300,31.100000]},"type":"Feature","properties":{"hierarchy":["tgn:2151550","tgn:1000001","tgn:2000301","tgn:7012149","tgn:7007248","tgn:7029392"],"placetype":["aat:300008699"],"id":2151550,"name:xx":"Batterbee Branch"}}
>>>>>>> 03f74aca74312dbeaf24d7e61306dd6a786dc3d0
