{
  "id": 2178131,
  "type": "Feature",
  "properties": {
    "tgn:hierarchy":[
        "tgn:2178131",
        "tgn:1000001",
        "tgn:7012149",
        "tgn:2001298",
        "tgn:7007524",
        "tgn:7029392"
    ],
    "tgn:id":2178131,
    "tgn:name":"Blackfoot City",
    "tgn:placetype":[
        "aat:300008347",
        "aat:300167671",
        "aat:300008547"
    ]
},
  "bbox": [],
  "geometry": {"coordinates":[-112.5333,46.6667],"type":"Point"}
}