{
  "id": 7167518,
  "type": "Feature",
  "properties": {
    "tgn:hierarchy":[
        "tgn:7167518",
        "tgn:7003669",
        "tgn:1000003",
        "tgn:7000084",
        "tgn:7029392"
    ],
    "tgn:id":7167518,
    "tgn:name":"Hege",
    "tgn:placetype":[
        "aat:300008347"
    ]
},
  "bbox": [],
  "geometry": {"coordinates":[9.616667,47.583333],"type":"Point"}
}