{
  "id": 2434596,
  "type": "Feature",
  "properties": {
    "tgn:hierarchy":[
        "tgn:2434596",
        "tgn:1000001",
        "tgn:7012149",
        "tgn:1002392",
        "tgn:7007157",
        "tgn:7029392"
    ],
    "tgn:id":2434596,
    "tgn:name":"Kennedy Grove",
    "tgn:placetype":[
        "aat:300132451"
    ]
},
  "bbox": [],
  "geometry": {"coordinates":[-118.8167,36.75],"type":"Point"}
}