<<<<<<< HEAD
{
  "id": 2152149,
  "type": "Feature",
  "properties": {
    "tgn:hierarchy":[
        "tgn:2152149",
        "tgn:1000001",
        "tgn:7016172",
        "tgn:7012149",
        "tgn:2000140",
        "tgn:7029392"
    ],
    "tgn:id":2152149,
    "tgn:name":"Baxter Point",
    "tgn:placetype":[
        "aat:300008850"
    ]
},
  "bbox": [],
  "geometry": {"coordinates":[-93.4833,35.5833],"type":"Point"}
}
=======
{"geometry":{"type":"Point","coordinates":[-93.483300,35.583300]},"type":"Feature","properties":{"hierarchy":["tgn:2152149","tgn:1000001","tgn:7016172","tgn:7012149","tgn:2000140","tgn:7029392"],"placetype":["aat:300008850"],"id":2152149,"name:xx":"Baxter Point"}}
>>>>>>> 03f74aca74312dbeaf24d7e61306dd6a786dc3d0
