{
  "id": 2187821,
  "type": "Feature",
  "properties": {
    "tgn:hierarchy":[
        "tgn:2187821",
        "tgn:1002300",
        "tgn:1000001",
        "tgn:7012149",
        "tgn:7007564",
        "tgn:7029392"
    ],
    "tgn:id":2187821,
    "tgn:name":"Boott Spur",
    "tgn:placetype":[
        "aat:300008798"
    ]
},
  "bbox": [],
  "geometry": {"coordinates":[-71.2833,44.25],"type":"Point"}
}