{
  "id": 2431907,
  "type": "Feature",
  "properties": {
    "tgn:hierarchy":[
        "tgn:2431907",
        "tgn:1002483",
        "tgn:7019080",
        "tgn:1000001",
        "tgn:7012149",
        "tgn:7007249",
        "tgn:7029392"
    ],
    "tgn:id":2431907,
    "tgn:name":"Kaula Bay",
    "tgn:placetype":[
        "aat:300132316"
    ]
},
  "bbox": [],
  "geometry": {"coordinates":[-158.1167,21.3333],"type":"Point"}
}