{
  "id": 7377708,
  "type": "Feature",
  "properties": {
    "tgn:hierarchy":[
        "tgn:7377708",
        "tgn:1000001",
        "tgn:7005589",
        "tgn:7005560",
        "tgn:7029392"
    ],
    "tgn:id":7377708,
    "tgn:name":"La Soledad",
    "tgn:placetype":[
        "aat:300008347"
    ]
},
  "bbox": [],
  "geometry": {"coordinates":[-99.966667,26.683333],"type":"Point"}
}