{
  "id": 2203153,
  "type": "Feature",
  "properties": {
    "tgn:hierarchy":[
        "tgn:2203153",
        "tgn:1000001",
        "tgn:2000467",
        "tgn:7012149",
        "tgn:7007250",
        "tgn:7029392"
    ],
    "tgn:id":2203153,
    "tgn:name":"Buckhorn Canyon",
    "tgn:placetype":[
        "aat:300008761"
    ]
},
  "bbox": [],
  "geometry": {"coordinates":[-114.1167,42.3167],"type":"Point"}
}