<<<<<<< HEAD
{
  "id": 2764581,
  "type": "Feature",
  "properties": {
    "tgn:hierarchy":[
        "tgn:2764581",
        "tgn:7002659",
        "tgn:1000001",
        "tgn:7012149",
        "tgn:7029392"
    ],
    "tgn:id":2764581,
    "tgn:name":"Whippoorwill Creek",
    "tgn:placetype":[
        "aat:300008706"
    ]
},
  "bbox": [],
  "geometry": {"coordinates":[-86.0167,34.35],"type":"Point"}
}
=======
{"geometry":{"type":"Point","coordinates":[-86.016700,34.350000]},"type":"Feature","properties":{"hierarchy":["tgn:2764581","tgn:7002659","tgn:1000001","tgn:7012149","tgn:7029392"],"placetype":["aat:300008706"],"id":2764581,"name:xx":"Whippoorwill Creek"}}
>>>>>>> 03f74aca74312dbeaf24d7e61306dd6a786dc3d0
