{
  "id": 7276184,
  "type": "Feature",
  "properties": {
    "tgn:hierarchy":[
        "tgn:7276184",
        "tgn:1001705",
        "tgn:1000049",
        "tgn:1000002",
        "tgn:7029392"
    ],
    "tgn:id":7276184,
    "tgn:name":"Torilla, Punta de la",
    "tgn:placetype":[
        "aat:300386846"
    ]
},
  "bbox": [],
  "geometry": {"coordinates":[-72.066667,-34.833333],"type":"Point"}
}