{
  "id": 2531722,
  "type": "Feature",
  "properties": {
    "tgn:hierarchy":[
        "tgn:2531722",
        "tgn:1000001",
        "tgn:7012149",
        "tgn:2002060",
        "tgn:7007826",
        "tgn:7029392"
    ],
    "tgn:id":2531722,
    "tgn:name":"Mullen Hollow",
    "tgn:placetype":[
        "aat:300008761"
    ]
},
  "bbox": [],
  "geometry": {"coordinates":[-99.9667,29.95],"type":"Point"}
}