{
  "id": 1087394,
  "type": "Feature",
  "properties": {
    "tgn:hierarchy":[
        "tgn:1087394",
        "tgn:1000486",
        "tgn:7001242",
        "tgn:7016752",
        "tgn:7029392"
    ],
    "tgn:id":1087394,
    "tgn:name":"Bous Bernous",
    "tgn:placetype":[
        "aat:300008347"
    ]
},
  "bbox": [],
  "geometry": {"coordinates":[-2.8833,27.3667],"type":"Point"}
}