{
  "id": 1129891,
  "type": "Feature",
  "properties": {
    "tgn:hierarchy":[
        "tgn:1129891",
        "tgn:7003127",
        "tgn:1000003",
        "tgn:7008516",
        "tgn:1000080",
        "tgn:7029392"
    ],
    "tgn:id":1129891,
    "tgn:name":"Setta",
    "tgn:placetype":[
        "aat:300008707",
        "aat:300008699"
    ]
},
  "bbox": [],
  "geometry": {"coordinates":[11.233333,44.366667],"type":"Point"}
}