{
  "id": 7478584,
  "type": "Feature",
  "properties": {
    "tgn:hierarchy":[
        "tgn:7478584",
        "tgn:7487020",
        "tgn:1000004",
        "tgn:1000141",
        "tgn:7029392"
    ],
    "tgn:id":7478584,
    "tgn:name":"Xianhua Gong",
    "tgn:placetype":[
        "aat:300007595"
    ]
},
  "bbox": [],
  "geometry": {"coordinates":[120.780833,24.524337],"type":"Point"}
}