{
  "id": 1121637,
  "type": "Feature",
  "properties": {
    "tgn:hierarchy":[
        "tgn:1121637",
        "tgn:7005572",
        "tgn:1000001",
        "tgn:7005565",
        "tgn:7029392"
    ],
    "tgn:id":1121637,
    "tgn:name":"Balsas, R\u00edo",
    "tgn:placetype":[
        "aat:300008707"
    ]
},
  "bbox": [],
  "geometry": {"coordinates":[-77.9833,8.25],"type":"Point"}
}