{
  "id": 2458606,
  "type": "Feature",
  "properties": {
    "tgn:hierarchy":[
        "tgn:2458606",
        "tgn:1000001",
        "tgn:7012149",
        "tgn:2002176",
        "tgn:7007919",
        "tgn:7029392"
    ],
    "tgn:id":2458606,
    "tgn:name":"Little Nottoway River",
    "tgn:placetype":[
        "aat:300008707"
    ]
},
  "bbox": [],
  "geometry": {"coordinates":[-78.1333,37.1333],"type":"Point"}
}