{
  "id": 7418769,
  "type": "Feature",
  "properties": {
    "tgn:hierarchy":[
        "tgn:7418769",
        "tgn:7005579",
        "tgn:1000001",
        "tgn:7005560",
        "tgn:7029392"
    ],
    "tgn:id":7418769,
    "tgn:name":"El Montero, Arroyo",
    "tgn:placetype":[
        "aat:300266554",
        "aat:300008699"
    ]
},
  "bbox": [],
  "geometry": {"coordinates":[-102.175,22.241667],"type":"Point"}
}