{
  "id": 7554915,
  "type": "Feature",
  "properties": {
    "tgn:hierarchy":[
        "tgn:7554915",
        "tgn:1000004",
        "tgn:7000198",
        "tgn:7031783",
        "tgn:7029392"
    ],
    "tgn:id":7554915,
    "tgn:name:en":"Obra",
    "tgn:placetype":[
        "aat:300008347"
    ]
},
  "bbox": [],
  "geometry": {"coordinates":[83.819103,24.086599],"type":"Point"}
}