{
  "id": 7437853,
  "type": "Feature",
  "properties": {
    "tgn:hierarchy":[
        "tgn:7437853",
        "tgn:7005581",
        "tgn:1000001",
        "tgn:7005560",
        "tgn:7029392"
    ],
    "tgn:id":7437853,
    "tgn:name":"Rancho Seco",
    "tgn:placetype":[
        "aat:300000241"
    ]
},
  "bbox": [],
  "geometry": {"coordinates":[-105.333333,27.866667],"type":"Point"}
}