{
  "id": 7094166,
  "type": "Feature",
  "properties": {
    "tgn:hierarchy":[
        "tgn:7094166",
        "tgn:1000003",
        "tgn:7003676",
        "tgn:7000084",
        "tgn:7029392"
    ],
    "tgn:id":7094166,
    "tgn:name":"Sch\u00fcttel-Berg",
    "tgn:placetype":[
        "aat:300008777"
    ]
},
  "bbox": [],
  "geometry": {"coordinates":[9.983333,52.75],"type":"Point"}
}