{
  "id": 7375018,
  "type": "Feature",
  "properties": {
    "tgn:hierarchy":[
        "tgn:7375018",
        "tgn:7005586",
        "tgn:1000001",
        "tgn:7005560",
        "tgn:7029392"
    ],
    "tgn:id":7375018,
    "tgn:name":"La Cuadrilla",
    "tgn:placetype":[
        "aat:300008699"
    ]
},
  "bbox": [],
  "geometry": {"coordinates":[-105.066667,20.816667],"type":"Point"}
}