{
  "id": 7177839,
  "type": "Feature",
  "properties": {
    "tgn:hierarchy":[
        "tgn:7177839",
        "tgn:1000003",
        "tgn:7003678",
        "tgn:7000084",
        "tgn:7029392"
    ],
    "tgn:id":7177839,
    "tgn:name":"Hainrode",
    "tgn:placetype":[
        "aat:300008347"
    ]
},
  "bbox": [],
  "geometry": {"coordinates":[9.566667,50.966667],"type":"Point"}
}