{
  "id": 7284832,
  "type": "Feature",
  "properties": {
    "tgn:hierarchy":[
        "tgn:7284832",
        "tgn:1001699",
        "tgn:1000049",
        "tgn:1000002",
        "tgn:7029392"
    ],
    "tgn:id":7284832,
    "tgn:name":"Pullafqu\u00e9n, Estero",
    "tgn:placetype":[
        "aat:300008699"
    ]
},
  "bbox": [],
  "geometry": {"coordinates":[-73.133333,-39.55],"type":"Point"}
}