{
  "id": 2738598,
  "type": "Feature",
  "properties": {
    "tgn:hierarchy":[
        "tgn:2738598",
        "tgn:7006450",
        "tgn:1000001",
        "tgn:7012149",
        "tgn:2000087",
        "tgn:7029392"
    ],
    "tgn:id":2738598,
    "tgn:name":"Ungulungwak Hill",
    "tgn:placetype":[
        "aat:300008798"
    ]
},
  "bbox": [],
  "geometry": {"coordinates":[-164.2333,62.25],"type":"Point"}
}