{
  "id": 7262918,
  "type": "Feature",
  "properties": {
    "tgn:hierarchy":[
        "tgn:7262918",
        "tgn:1000003",
        "tgn:7003635",
        "tgn:7016845",
        "tgn:7029392"
    ],
    "tgn:id":7262918,
    "tgn:name:nl":"Clapshoek",
    "tgn:placetype":[
        "aat:300387200"
    ]
},
  "bbox": [],
  "geometry": {"coordinates":[4.133333,51.533333],"type":"Point"}
}