{
  "id": 2374661,
  "type": "Feature",
  "properties": {
    "tgn:hierarchy":[
        "tgn:2374661",
        "tgn:1000001",
        "tgn:7012149",
        "tgn:2000181",
        "tgn:7007157",
        "tgn:7029392"
    ],
    "tgn:id":2374661,
    "tgn:name":"Hancorne Prairie",
    "tgn:placetype":[
        "aat:300055621"
    ]
},
  "bbox": [],
  "geometry": {"coordinates":[-123.8667,41.25],"type":"Point"}
}