{
  "id": 7456686,
  "type": "Feature",
  "properties": {
    "tgn:hierarchy":[
        "tgn:7456686",
        "tgn:7002445",
        "tgn:1000003",
        "tgn:7012077",
        "tgn:7008591",
        "tgn:7029392"
    ],
    "tgn:id":7456686,
    "tgn:name:en":"Ore Stone",
    "tgn:placetype":[
        "aat:300011692"
    ]
},
  "bbox": [],
  "geometry": {"coordinates":[-3.483333,50.45],"type":"Point"}
}