{
  "id": 7008979,
  "type": "Feature",
  "properties": {
    "tgn:hierarchy":[
        "tgn:7008979",
        "tgn:1000003",
        "tgn:7002883",
        "tgn:1000070",
        "tgn:7029392"
    ],
    "tgn:id":7008979,
    "tgn:name":"Beauvais",
    "tgn:placetype":[
        "aat:300008347"
    ]
},
  "bbox": [],
  "geometry": {"coordinates":[2.05,48.5333],"type":"Point"}
}