{
  "id": 7021665,
  "type": "Feature",
  "properties": {
    "tgn:hierarchy":[
        "tgn:7021665",
        "tgn:1000001",
        "tgn:2001737",
        "tgn:7012149",
        "tgn:7007712",
        "tgn:7029392"
    ],
    "tgn:id":7021665,
    "tgn:name":"Joplin Mill Branch",
    "tgn:placetype":[
        "aat:300008699"
    ]
},
  "bbox": [],
  "geometry": {"coordinates":[-80.2667,34.65],"type":"Point"}
}