{
  "id": 7519173,
  "type": "Feature",
  "properties": {
    "tgn:hierarchy":[
        "tgn:7519173",
        "tgn:1009227",
        "tgn:7001866",
        "tgn:1000226",
        "tgn:1000006",
        "tgn:7029392"
    ],
    "tgn:id":7519173,
    "tgn:name:en":"Anaweka River",
    "tgn:placetype":[
        "aat:300008699"
    ]
},
  "bbox": [],
  "geometry": {"coordinates":[172.283333,-40.75],"type":"Point"}
}