{
  "id": 2564136,
  "type": "Feature",
  "properties": {
    "tgn:hierarchy":[
        "tgn:2564136",
        "tgn:1000001",
        "tgn:2001701",
        "tgn:7012149",
        "tgn:7007708",
        "tgn:7029392"
    ],
    "tgn:id":2564136,
    "tgn:name":"P M Delaubenfelds Reservoir",
    "tgn:placetype":[
        "aat:300006191"
    ]
},
  "bbox": [],
  "geometry": {"coordinates":[-123.35,44.4333],"type":"Point"}
}