{
  "id": 7314460,
  "type": "Feature",
  "properties": {
    "tgn:hierarchy":[
        "tgn:7314460",
        "tgn:1001705",
        "tgn:1000049",
        "tgn:1000002",
        "tgn:7029392"
    ],
    "tgn:id":7314460,
    "tgn:name":"Loncomila",
    "tgn:placetype":[
        "aat:300000206"
    ]
},
  "bbox": [],
  "geometry": {"coordinates":[-71.75,-35.666667],"type":"Point"}
}