{
  "id": 1059993,
  "type": "Feature",
  "properties": {
    "tgn:hierarchy":[
        "tgn:1059993",
        "tgn:1003391",
        "tgn:1000003",
        "tgn:7006657",
        "tgn:7029392"
    ],
    "tgn:id":1059993,
    "tgn:name":"Svir",
    "tgn:placetype":[
        "aat:300008347"
    ]
},
  "bbox": [],
  "geometry": {"coordinates":[26.395,54.851],"type":"Point"}
}