<<<<<<< HEAD
{
  "id": 7359202,
  "type": "Feature",
  "properties": {
    "tgn:hierarchy":[
        "tgn:7359202",
        "tgn:1000001",
        "tgn:7005599",
        "tgn:7005560",
        "tgn:7029392"
    ],
    "tgn:id":7359202,
    "tgn:name":"Cieneguitas",
    "tgn:placetype":[
        "aat:300008347"
    ]
},
  "bbox": [],
  "geometry": {"coordinates":[-96.516667,19.533333],"type":"Point"}
}
=======
{"geometry":{"type":"Point","coordinates":[-96.516667,19.533333]},"type":"Feature","properties":{"hierarchy":["tgn:7359202","tgn:1000001","tgn:7005599","tgn:7005560","tgn:7029392"],"placetype":["aat:300008347"],"id":7359202,"name:xx":"Cieneguitas"}}
>>>>>>> 03f74aca74312dbeaf24d7e61306dd6a786dc3d0
