{
  "id": 7207458,
  "type": "Feature",
  "properties": {
    "tgn:hierarchy":[
        "tgn:7207458",
        "tgn:1000003",
        "tgn:7003687",
        "tgn:7000084",
        "tgn:7029392"
    ],
    "tgn:id":7207458,
    "tgn:name":"Cr\u00f6chern",
    "tgn:placetype":[
        "aat:300008347"
    ]
},
  "bbox": [],
  "geometry": {"coordinates":[11.65,52.383333],"type":"Point"}
}