{
  "id": 7072629,
  "type": "Feature",
  "properties": {
    "tgn:hierarchy":[
        "tgn:7072629",
        "tgn:7000096",
        "tgn:1000003",
        "tgn:7000084",
        "tgn:7029392"
    ],
    "tgn:id":7072629,
    "tgn:name":"Tarnower Wiesen",
    "tgn:placetype":[
        "aat:300386990"
    ]
},
  "bbox": [],
  "geometry": {"coordinates":[12.783333,52.733333],"type":"Point"}
}