{
  "id": 2556324,
  "type": "Feature",
  "properties": {
    "tgn:hierarchy":[
        "tgn:2556324",
        "tgn:1000001",
        "tgn:7012149",
        "tgn:2001976",
        "tgn:7007826",
        "tgn:7029392"
    ],
    "tgn:id":2556324,
    "tgn:name":"Oklahoma Draw",
    "tgn:placetype":[
        "aat:300008761"
    ]
},
  "bbox": [],
  "geometry": {"coordinates":[-100.6667,34.85],"type":"Point"}
}