{
  "id": 7030199,
  "type": "Feature",
  "properties": {
    "tgn:hierarchy":[
        "tgn:7030199",
        "tgn:1000003",
        "tgn:7012216",
        "tgn:1000070",
        "tgn:7029392"
    ],
    "tgn:id":7030199,
    "tgn:name":"Guern",
    "tgn:placetype":[
        "aat:300008347"
    ]
},
  "bbox": [],
  "geometry": {"coordinates":[-3.084,48.033],"type":"Point"}
}