{
  "id": 1032273,
  "type": "Feature",
  "properties": {
    "tgn:hierarchy":[
        "tgn:1032273",
        "tgn:1000003",
        "tgn:7002882",
        "tgn:1000070",
        "tgn:7029392"
    ],
    "tgn:id":1032273,
    "tgn:name":"Bourneville",
    "tgn:placetype":[
        "aat:300008347"
    ]
},
  "bbox": [],
  "geometry": {"coordinates":[0.6167,49.3833],"type":"Point"}
}