<<<<<<< HEAD
{
  "id": 2253933,
  "type": "Feature",
  "properties": {
    "tgn:hierarchy":[
        "tgn:2253933",
        "tgn:1000001",
        "tgn:7012149",
        "tgn:2001906",
        "tgn:7007825",
        "tgn:7029392"
    ],
    "tgn:id":2253933,
    "tgn:name":"Cookson Branch",
    "tgn:placetype":[
        "aat:300008699"
    ]
},
  "bbox": [],
  "geometry": {"coordinates":[-84.6333,35.05],"type":"Point"}
}
=======
{"geometry":{"type":"Point","coordinates":[-84.633300,35.050000]},"type":"Feature","properties":{"hierarchy":["tgn:2253933","tgn:1000001","tgn:7012149","tgn:2001906","tgn:7007825","tgn:7029392"],"placetype":["aat:300008699"],"id":2253933,"name:xx":"Cookson Branch"}}
>>>>>>> 03f74aca74312dbeaf24d7e61306dd6a786dc3d0
