{
  "id": 2165352,
  "type": "Feature",
  "properties": {
    "tgn:hierarchy":[
        "tgn:2165352",
        "tgn:1000001",
        "tgn:2001419",
        "tgn:7012149",
        "tgn:7007526",
        "tgn:7029392"
    ],
    "tgn:id":2165352,
    "tgn:name":"Betty Creek",
    "tgn:placetype":[
        "aat:300008706"
    ]
},
  "bbox": [],
  "geometry": {"coordinates":[-119.25,40.4167],"type":"Point"}
}