{
  "id": 2069191,
  "type": "Feature",
  "properties": {
    "tgn:hierarchy":[
        "tgn:2069191",
        "tgn:1000001",
        "tgn:7012149",
        "tgn:1002593",
        "tgn:7007568",
        "tgn:7029392"
    ],
    "tgn:id":2069191,
    "tgn:name":"Fish Creek",
    "tgn:placetype":[
        "aat:300008347",
        "aat:300387210"
    ]
},
  "bbox": [],
  "geometry": {"coordinates":[-75.5333,43.5167],"type":"Point"}
}