{
  "id": 2479691,
  "type": "Feature",
  "properties": {
    "tgn:hierarchy":[
        "tgn:2479691",
        "tgn:1000001",
        "tgn:1002246",
        "tgn:7012149",
        "tgn:7007568",
        "tgn:7029392"
    ],
    "tgn:id":2479691,
    "tgn:name":"Lake Como Outlet",
    "tgn:placetype":[
        "aat:300008699"
    ]
},
  "bbox": [],
  "geometry": {"coordinates":[-76.2833,42.6667],"type":"Point"}
}