<<<<<<< HEAD
{
  "id": 2765481,
  "type": "Feature",
  "properties": {
    "tgn:hierarchy":[
        "tgn:2765481",
        "tgn:1000001",
        "tgn:7012149",
        "tgn:2002154",
        "tgn:7007919",
        "tgn:7029392"
    ],
    "tgn:id":2765481,
    "tgn:name":"White Branch",
    "tgn:placetype":[
        "aat:300008699"
    ]
},
  "bbox": [],
  "geometry": {"coordinates":[-80.3833,37.4333],"type":"Point"}
}
=======
{"geometry":{"type":"Point","coordinates":[-80.383300,37.433300]},"type":"Feature","properties":{"hierarchy":["tgn:2765481","tgn:1000001","tgn:7012149","tgn:2002154","tgn:7007919","tgn:7029392"],"placetype":["aat:300008699"],"id":2765481,"name:xx":"White Branch"}}
>>>>>>> 03f74aca74312dbeaf24d7e61306dd6a786dc3d0
