{
  "id": 2765481,
  "type": "Feature",
  "properties": {
    "tgn:hierarchy":[
        "tgn:2765481",
        "tgn:1000001",
        "tgn:7012149",
        "tgn:2002154",
        "tgn:7007919",
        "tgn:7029392"
    ],
    "tgn:id":2765481,
    "tgn:name":"White Branch",
    "tgn:placetype":[
        "aat:300008699"
    ]
},
  "bbox": [],
  "geometry": {"coordinates":[-80.3833,37.4333],"type":"Point"}
}