<<<<<<< HEAD
{
  "id": 7025007,
  "type": "Feature",
  "properties": {
    "tgn:hierarchy":[
        "tgn:7025007",
        "tgn:7002445",
        "tgn:7008104",
        "tgn:1000003",
        "tgn:7008591",
        "tgn:7029392"
    ],
    "tgn:id":7025007,
    "tgn:name:ang":"Bertone",
    "tgn:placetype":[
        "aat:300008347"
    ]
},
  "bbox": [],
  "geometry": {"coordinates":[-1.05,51.9667],"type":"Point"}
}
=======
{"geometry":{"type":"Point","coordinates":[-1.050000,51.966700]},"type":"Feature","properties":{"hierarchy":["tgn:7025007","tgn:7002445","tgn:7008104","tgn:1000003","tgn:7008591","tgn:7029392"],"placetype":["aat:300008347"],"id":7025007,"name:ang":"Bertone"}}
>>>>>>> 03f74aca74312dbeaf24d7e61306dd6a786dc3d0
