{
  "id": 2188893,
  "type": "Feature",
  "properties": {
    "tgn:hierarchy":[
        "tgn:2188893",
        "tgn:1000001",
        "tgn:7012149",
        "tgn:2001274",
        "tgn:7007524",
        "tgn:7029392"
    ],
    "tgn:id":2188893,
    "tgn:name":"Boulder Glacier",
    "tgn:placetype":[
        "aat:300008835"
    ]
},
  "bbox": [],
  "geometry": {"coordinates":[-114.0833,48.95],"type":"Point"}
}