<<<<<<< HEAD
{
  "id": 2706776,
  "type": "Feature",
  "properties": {
    "tgn:hierarchy":[
        "tgn:2706776",
        "tgn:1000001",
        "tgn:7012149",
        "tgn:2000208",
        "tgn:7007158",
        "tgn:7029392"
    ],
    "tgn:id":2706776,
    "tgn:name":"Swank Reservoir",
    "tgn:placetype":[
        "aat:300006191"
    ]
},
  "bbox": [],
  "geometry": {"coordinates":[-108.1833,37.6667],"type":"Point"}
}
=======
{"geometry":{"type":"Point","coordinates":[-108.183300,37.666700]},"type":"Feature","properties":{"hierarchy":["tgn:2706776","tgn:1000001","tgn:7012149","tgn:2000208","tgn:7007158","tgn:7029392"],"placetype":["aat:300006191"],"id":2706776,"name:xx":"Swank Reservoir"}}
>>>>>>> 03f74aca74312dbeaf24d7e61306dd6a786dc3d0
