{
  "id": 2260476,
  "type": "Feature",
  "properties": {
    "tgn:hierarchy":[
        "tgn:2260476",
        "tgn:1000001",
        "tgn:7012149",
        "tgn:2001062",
        "tgn:7007521",
        "tgn:7029392"
    ],
    "tgn:id":2260476,
    "tgn:name":"County Ditch Number Fiftyfour",
    "tgn:placetype":[
        "aat:300006075"
    ]
},
  "bbox": [],
  "geometry": {"coordinates":[-95.25,44.3667],"type":"Point"}
}