{
  "id": 1112759,
  "type": "Feature",
  "properties": {
    "tgn:hierarchy":[
        "tgn:1112759",
        "tgn:7006450",
        "tgn:1000001",
        "tgn:7012149",
        "tgn:2124005",
        "tgn:7029392"
    ],
    "tgn:id":1112759,
    "tgn:name":"Camden Bay",
    "tgn:placetype":[
        "aat:300132316"
    ]
},
  "bbox": [],
  "geometry": {"coordinates":[-145.2667,70.0667],"type":"Point"}
}