{
  "id": 2108654,
  "type": "Feature",
  "properties": {
    "tgn:hierarchy":[
        "tgn:2108654",
        "tgn:1000001",
        "tgn:7012149",
        "tgn:2001973",
        "tgn:7007826",
        "tgn:7029392"
    ],
    "tgn:id":2108654,
    "tgn:name":"Yowell",
    "tgn:placetype":[
        "aat:300008347",
        "aat:300387210"
    ]
},
  "bbox": [],
  "geometry": {"coordinates":[-95.85,33.3333],"type":"Point"}
}