<<<<<<< HEAD
{
  "id": 2251477,
  "type": "Feature",
  "properties": {
    "tgn:hierarchy":[
        "tgn:2251477",
        "tgn:1000001",
        "tgn:7012149",
        "tgn:7007520",
        "tgn:7029392"
    ],
    "tgn:id":2251477,
    "tgn:name":"Commencement Creek",
    "tgn:placetype":[
        "aat:300008706"
    ]
},
  "bbox": [],
  "geometry": {"coordinates":[-86.3667,46.3833],"type":"Point"}
}
=======
{"geometry":{"type":"Point","coordinates":[-86.366700,46.383300]},"type":"Feature","properties":{"hierarchy":["tgn:2251477","tgn:1000001","tgn:7012149","tgn:7007520","tgn:7029392"],"placetype":["aat:300008706"],"id":2251477,"name:xx":"Commencement Creek"}}
>>>>>>> 03f74aca74312dbeaf24d7e61306dd6a786dc3d0
