{
  "id": 2054063,
  "type": "Feature",
  "properties": {
    "tgn:hierarchy":[
        "tgn:2054063",
        "tgn:1000001",
        "tgn:7012149",
        "tgn:2001040",
        "tgn:7007521",
        "tgn:7029392"
    ],
    "tgn:id":2054063,
    "tgn:name":"Burchard",
    "tgn:placetype":[
        "aat:300008347",
        "aat:300387210"
    ]
},
  "bbox": [],
  "geometry": {"coordinates":[-95.9833,44.25],"type":"Point"}
}