{
  "id": 7590235,
  "type": "Feature",
  "properties": {
    "tgn:hierarchy":[
        "tgn:7590235",
        "tgn:1000004",
        "tgn:7000198",
        "tgn:7016722",
        "tgn:7029392"
    ],
    "tgn:id":7590235,
    "tgn:name:en":"Jog\u012bpura",
    "tgn:placetype":[
        "aat:300008347"
    ]
},
  "bbox": [],
  "geometry": {"coordinates":[77.413626,29.74927],"type":"Point"}
}