{
  "id": 7581363,
  "type": "Feature",
  "properties": {
    "tgn:hierarchy":[
        "tgn:7581363",
        "tgn:1000004",
        "tgn:7000198",
        "tgn:1001895",
        "tgn:7029392"
    ],
    "tgn:id":7581363,
    "tgn:name:en":"Surul",
    "tgn:placetype":[
        "aat:300008347"
    ]
},
  "bbox": [],
  "geometry": {"coordinates":[73.983333,17.95],"type":"Point"}
}