{
  "id": 2334931,
  "type": "Feature",
  "properties": {
    "tgn:hierarchy":[
        "tgn:2334931",
        "tgn:1000001",
        "tgn:7012149",
        "tgn:7007157",
        "tgn:1002566",
        "tgn:7029392"
    ],
    "tgn:id":2334931,
    "tgn:name":"Forks Creek",
    "tgn:placetype":[
        "aat:300008706"
    ]
},
  "bbox": [],
  "geometry": {"coordinates":[-123.0667,39.5667],"type":"Point"}
}