{
  "id": 1064200,
  "type": "Feature",
  "properties": {
    "tgn:hierarchy":[
        "tgn:1064200",
        "tgn:1000003",
        "tgn:7003750",
        "tgn:7011731",
        "tgn:7029392"
    ],
    "tgn:id":1064200,
    "tgn:name":"Littau",
    "tgn:placetype":[
        "aat:300008347"
    ]
},
  "bbox": [],
  "geometry": {"coordinates":[8.2667,47.05],"type":"Point"}
}