{
  "id": 1056656,
  "type": "Feature",
  "properties": {
    "tgn:hierarchy":[
        "tgn:1056656",
        "tgn:1000003",
        "tgn:7011664",
        "tgn:7006660",
        "tgn:7029392"
    ],
    "tgn:id":1056656,
    "tgn:name":"Maheriv",
    "tgn:placetype":[
        "aat:300008347"
    ]
},
  "bbox": [],
  "geometry": {"coordinates":[23.7167,50.1333],"type":"Point"}
}