{
  "id": 7421537,
  "type": "Feature",
  "properties": {
    "tgn:hierarchy":[
        "tgn:7421537",
        "tgn:7005579",
        "tgn:1000001",
        "tgn:7005560",
        "tgn:7029392"
    ],
    "tgn:id":7421537,
    "tgn:name":"Pe\u00f1a Blanca",
    "tgn:placetype":[
        "aat:300008347"
    ]
},
  "bbox": [],
  "geometry": {"coordinates":[-102.747222,21.8875],"type":"Point"}
}