{
  "id": 7302111,
  "type": "Feature",
  "properties": {
    "tgn:hierarchy":[
        "tgn:7302111",
        "tgn:7002758",
        "tgn:7002821",
        "tgn:1000003",
        "tgn:1000095",
        "tgn:7029392"
    ],
    "tgn:id":7302111,
    "tgn:name":"Mecina, R\u00edo",
    "tgn:placetype":[
        "aat:300008699"
    ]
},
  "bbox": [],
  "geometry": {"coordinates":[-3.133333,36.983333],"type":"Point"}
}