{
  "id": 2279233,
  "type": "Feature",
  "properties": {
    "tgn:hierarchy":[
        "tgn:2279233",
        "tgn:1000001",
        "tgn:2001704",
        "tgn:7012149",
        "tgn:7007708",
        "tgn:7029392"
    ],
    "tgn:id":2279233,
    "tgn:name":"Deadline Creek",
    "tgn:placetype":[
        "aat:300008706"
    ]
},
  "bbox": [],
  "geometry": {"coordinates":[-124.2167,42.5333],"type":"Point"}
}