{
  "id": 7325986,
  "type": "Feature",
  "properties": {
    "tgn:hierarchy":[
        "tgn:7325986",
        "tgn:7002824",
        "tgn:1000003",
        "tgn:7002786",
        "tgn:1000095",
        "tgn:7029392"
    ],
    "tgn:id":7325986,
    "tgn:name":"Ramil",
    "tgn:placetype":[
        "aat:300008347"
    ]
},
  "bbox": [],
  "geometry": {"coordinates":[-8.666667,43.166667],"type":"Point"}
}