<<<<<<< HEAD
{
  "id": 7473419,
  "type": "Feature",
  "properties": {
    "tgn:hierarchy":[
        "tgn:7473419",
        "tgn:1000004",
        "tgn:7001009",
        "tgn:1000141",
        "tgn:7029392"
    ],
    "tgn:id":7473419,
    "tgn:name":"Dongshan Li",
    "tgn:placetype":[
        "aat:300387173"
    ]
},
  "bbox": [],
  "geometry": {"coordinates":[120.767987,24.188303],"type":"Point"}
}
=======
{"geometry":{"type":"Point","coordinates":[120.767987,24.188303]},"type":"Feature","properties":{"hierarchy":["tgn:7473419","tgn:1000004","tgn:7001009","tgn:1000141","tgn:7029392"],"placetype":["aat:300387173"],"id":7473419,"name:xx":"Dongshan Li"}}
>>>>>>> 03f74aca74312dbeaf24d7e61306dd6a786dc3d0
