{
  "id": 7307731,
  "type": "Feature",
  "properties": {
    "tgn:hierarchy":[
        "tgn:7307731",
        "tgn:7001158",
        "tgn:7002848",
        "tgn:1000003",
        "tgn:1000095",
        "tgn:7029392"
    ],
    "tgn:id":7307731,
    "tgn:name":"Llano de Olmedo",
    "tgn:placetype":[
        "aat:300008347"
    ]
},
  "bbox": [],
  "geometry": {"coordinates":[-4.616667,41.266667],"type":"Point"}
}