{
  "id": 7158815,
  "type": "Feature",
  "properties": {
    "tgn:hierarchy":[
        "tgn:7158815",
        "tgn:7003669",
        "tgn:1000003",
        "tgn:7000084",
        "tgn:7029392"
    ],
    "tgn:id":7158815,
    "tgn:name":"H\u00f6lzlashof",
    "tgn:placetype":[
        "aat:300008347"
    ]
},
  "bbox": [],
  "geometry": {"coordinates":[11.95,49.95],"type":"Point"}
}