{
  "id": 7505117,
  "type": "Feature",
  "properties": {
    "tgn:hierarchy":[
        "tgn:7505117",
        "tgn:1009892",
        "tgn:1000226",
        "tgn:1000006",
        "tgn:7029392"
    ],
    "tgn:id":7505117,
    "tgn:name:en":"Ranfurly Island",
    "tgn:placetype":[
        "aat:300008791"
    ]
},
  "bbox": [],
  "geometry": {"coordinates":[179.031111,-47.751111],"type":"Point"}
}