{
  "id": 7043456,
  "type": "Feature",
  "properties": {
    "tgn:hierarchy":[
        "tgn:7043456",
        "tgn:7002991",
        "tgn:1000003",
        "tgn:7002997",
        "tgn:1000080",
        "tgn:7029392"
    ],
    "tgn:id":7043456,
    "tgn:name":"Pren",
    "tgn:placetype":[
        "aat:300008347"
    ]
},
  "bbox": [],
  "geometry": {"coordinates":[11.883333,46.05],"type":"Point"}
}