<<<<<<< HEAD
{
  "id": 2331030,
  "type": "Feature",
  "properties": {
    "tgn:hierarchy":[
        "tgn:2331030",
        "tgn:1000001",
        "tgn:7012149",
        "tgn:1002432",
        "tgn:7007706",
        "tgn:7029392"
    ],
    "tgn:id":2331030,
    "tgn:name":"Flat Run",
    "tgn:placetype":[
        "aat:300008699"
    ]
},
  "bbox": [],
  "geometry": {"coordinates":[-81.6667,39.9333],"type":"Point"}
}
=======
{"geometry":{"type":"Point","coordinates":[-81.666700,39.933300]},"type":"Feature","properties":{"hierarchy":["tgn:2331030","tgn:1000001","tgn:7012149","tgn:1002432","tgn:7007706","tgn:7029392"],"placetype":["aat:300008699"],"id":2331030,"name:xx":"Flat Run"}}
>>>>>>> 03f74aca74312dbeaf24d7e61306dd6a786dc3d0
