<<<<<<< HEAD
{
  "id": 2407139,
  "type": "Feature",
  "properties": {
    "tgn:hierarchy":[
        "tgn:2407139",
        "tgn:1000001",
        "tgn:2000275",
        "tgn:7012149",
        "tgn:7007240",
        "tgn:7029392"
    ],
    "tgn:id":2407139,
    "tgn:name":"Hunters Hammock",
    "tgn:placetype":[
        "aat:300008791"
    ]
},
  "bbox": [],
  "geometry": {"coordinates":[-80.8833,25.8],"type":"Point"}
}
=======
{"geometry":{"type":"Point","coordinates":[-80.883300,25.800000]},"type":"Feature","properties":{"hierarchy":["tgn:2407139","tgn:1000001","tgn:2000275","tgn:7012149","tgn:7007240","tgn:7029392"],"placetype":["aat:300008791"],"id":2407139,"name:xx":"Hunters Hammock"}}
>>>>>>> 03f74aca74312dbeaf24d7e61306dd6a786dc3d0
