{
  "id": 7316387,
  "type": "Feature",
  "properties": {
    "tgn:hierarchy":[
        "tgn:7316387",
        "tgn:1001695",
        "tgn:1000049",
        "tgn:1000002",
        "tgn:7029392"
    ],
    "tgn:id":7316387,
    "tgn:name":"Cartagena, Estero",
    "tgn:placetype":[
        "aat:300008699"
    ]
},
  "bbox": [],
  "geometry": {"coordinates":[-71.816667,-34.183333],"type":"Point"}
}