<<<<<<< HEAD
{
  "id": 7370511,
  "type": "Feature",
  "properties": {
    "tgn:hierarchy":[
        "tgn:7370511",
        "tgn:1000001",
        "tgn:1001906",
        "tgn:7005560",
        "tgn:7029392"
    ],
    "tgn:id":7370511,
    "tgn:name":"Guayabitos",
    "tgn:placetype":[
        "aat:300008347"
    ]
},
  "bbox": [],
  "geometry": {"coordinates":[-105.433333,21.916667],"type":"Point"}
}
=======
{"geometry":{"type":"Point","coordinates":[-105.433333,21.916667]},"type":"Feature","properties":{"hierarchy":["tgn:7370511","tgn:1000001","tgn:1001906","tgn:7005560","tgn:7029392"],"placetype":["aat:300008347"],"id":7370511,"name:xx":"Guayabitos"}}
>>>>>>> 03f74aca74312dbeaf24d7e61306dd6a786dc3d0
