{
  "id": 1102272,
  "type": "Feature",
  "properties": {
    "tgn:hierarchy":[
        "tgn:1102272",
        "tgn:1000001",
        "tgn:7012149",
        "tgn:1002718",
        "tgn:7007568",
        "tgn:7029392"
    ],
    "tgn:id":1102272,
    "tgn:name":"Fort Niagara State Park",
    "tgn:placetype":[
        "aat:300008192"
    ]
},
  "bbox": [],
  "geometry": {"coordinates":[-79.05,43.25],"type":"Point"}
}