<<<<<<< HEAD
{
  "id": 7113483,
  "type": "Feature",
  "properties": {
    "tgn:hierarchy":[
        "tgn:7113483",
        "tgn:1000003",
        "tgn:7003677",
        "tgn:7000084",
        "tgn:7029392"
    ],
    "tgn:id":7113483,
    "tgn:name":"Riepen",
    "tgn:placetype":[
        "aat:300000206"
    ]
},
  "bbox": [],
  "geometry": {"coordinates":[9.166667,51.533333],"type":"Point"}
}
=======
{"geometry":{"type":"Point","coordinates":[9.166667,51.533333]},"type":"Feature","properties":{"hierarchy":["tgn:7113483","tgn:1000003","tgn:7003677","tgn:7000084","tgn:7029392"],"placetype":["aat:300000206"],"id":7113483,"name:xx":"Riepen"}}
>>>>>>> 03f74aca74312dbeaf24d7e61306dd6a786dc3d0
