{
  "id": 2392231,
  "type": "Feature",
  "properties": {
    "tgn:hierarchy":[
        "tgn:2392231",
        "tgn:1000001",
        "tgn:7012149",
        "tgn:2000439",
        "tgn:7007248",
        "tgn:7029392"
    ],
    "tgn:id":2392231,
    "tgn:name":"Hinson Crossing",
    "tgn:placetype":[
        "aat:300008347"
    ]
},
  "bbox": [],
  "geometry": {"coordinates":[-82.65,31.1667],"type":"Point"}
}