{
  "id": 2470611,
  "type": "Feature",
  "properties": {
    "tgn:hierarchy":[
        "tgn:2470611",
        "tgn:1000001",
        "tgn:7012149",
        "tgn:7007157",
        "tgn:1002748",
        "tgn:7029392"
    ],
    "tgn:id":2470611,
    "tgn:name":"Los Pinos Peak",
    "tgn:placetype":[
        "aat:300008798"
    ]
},
  "bbox": [],
  "geometry": {"coordinates":[-117.4667,33.65],"type":"Point"}
}