{
  "id": 7321793,
  "type": "Feature",
  "properties": {
    "tgn:hierarchy":[
        "tgn:7321793",
        "tgn:1001705",
        "tgn:1000049",
        "tgn:1000002",
        "tgn:7029392"
    ],
    "tgn:id":7321793,
    "tgn:name":"Belco",
    "tgn:placetype":[
        "aat:300000206"
    ]
},
  "bbox": [],
  "geometry": {"coordinates":[-72.083333,-35.866667],"type":"Point"}
}