{
  "id": 2018791,
  "type": "Feature",
  "properties": {
    "tgn:hierarchy":[
        "tgn:2018791",
        "tgn:1000001",
        "tgn:7012149",
        "tgn:1002793",
        "tgn:7007240",
        "tgn:7029392"
    ],
    "tgn:id":2018791,
    "tgn:name":"Camp Mack",
    "tgn:placetype":[
        "aat:300008347",
        "aat:300387210"
    ]
},
  "bbox": [],
  "geometry": {"coordinates":[-81.3667,27.9667],"type":"Point"}
}