<<<<<<< HEAD
{
  "id": 7119887,
  "type": "Feature",
  "properties": {
    "tgn:hierarchy":[
        "tgn:7119887",
        "tgn:1000003",
        "tgn:7003687",
        "tgn:7000084",
        "tgn:7029392"
    ],
    "tgn:id":7119887,
    "tgn:name":"Kolonie Peine",
    "tgn:placetype":[
        "aat:300000206"
    ]
},
  "bbox": [],
  "geometry": {"coordinates":[11.25,52.483333],"type":"Point"}
}
=======
{"geometry":{"type":"Point","coordinates":[11.250000,52.483333]},"type":"Feature","properties":{"hierarchy":["tgn:7119887","tgn:1000003","tgn:7003687","tgn:7000084","tgn:7029392"],"placetype":["aat:300000206"],"id":7119887,"name:xx":"Kolonie Peine"}}
>>>>>>> 03f74aca74312dbeaf24d7e61306dd6a786dc3d0
