{
  "id": 1046202,
  "type": "Feature",
  "properties": {
    "tgn:hierarchy":[
        "tgn:1046202",
        "tgn:1000003",
        "tgn:7003122",
        "tgn:1001753",
        "tgn:1000080",
        "tgn:7029392"
    ],
    "tgn:id":1046202,
    "tgn:name":"Priolo Gargallo",
    "tgn:placetype":[
        "aat:300008347"
    ]
},
  "bbox": [],
  "geometry": {"coordinates":[15.183333,37.15],"type":"Point"}
}