{
  "id": 7466291,
  "type": "Feature",
  "properties": {
    "tgn:hierarchy":[
        "tgn:7466291",
        "tgn:7002445",
        "tgn:1000003",
        "tgn:7008131",
        "tgn:7008591",
        "tgn:7029392"
    ],
    "tgn:id":7466291,
    "tgn:name:en":"Blackwater, River",
    "tgn:placetype":[
        "aat:300008699"
    ]
},
  "bbox": [],
  "geometry": {"coordinates":[0.883333,51.733333],"type":"Point"}
}