{
  "id": 2240606,
  "type": "Feature",
  "properties": {
    "tgn:hierarchy":[
        "tgn:2240606",
        "tgn:1000001",
        "tgn:7020676",
        "tgn:7012149",
        "tgn:7007256",
        "tgn:7029392"
    ],
    "tgn:id":2240606,
    "tgn:name":"Claibert Lake",
    "tgn:placetype":[
        "aat:300008680"
    ]
},
  "bbox": [],
  "geometry": {"coordinates":[-92.8333,29.6833],"type":"Point"}
}