{
  "id": 2472987,
  "type": "Feature",
  "properties": {
    "tgn:hierarchy":[
        "tgn:2472987",
        "tgn:1000001",
        "tgn:7012149",
        "tgn:1002540",
        "tgn:7007520",
        "tgn:7029392"
    ],
    "tgn:id":2472987,
    "tgn:name":"Low Lake",
    "tgn:placetype":[
        "aat:300008680"
    ]
},
  "bbox": [],
  "geometry": {"coordinates":[-85.65,43.15],"type":"Point"}
}