{
  "id": 7440065,
  "type": "Feature",
  "properties": {
    "tgn:hierarchy":[
        "tgn:7440065",
        "tgn:1000001",
        "tgn:1001893",
        "tgn:7005560",
        "tgn:7029392"
    ],
    "tgn:id":7440065,
    "tgn:name":"Santa Clara",
    "tgn:placetype":[
        "aat:300008347"
    ]
},
  "bbox": [],
  "geometry": {"coordinates":[-98.766667,19.85],"type":"Point"}
}