{
  "id": 7075479,
  "type": "Feature",
  "properties": {
    "tgn:hierarchy":[
        "tgn:7075479",
        "tgn:7003692",
        "tgn:1000003",
        "tgn:7000084",
        "tgn:7029392"
    ],
    "tgn:id":7075479,
    "tgn:name":"Z\u00f6binger Forst",
    "tgn:placetype":[
        "aat:300008863"
    ]
},
  "bbox": [],
  "geometry": {"coordinates":[10.283333,48.916667],"type":"Point"}
}