{
  "id": 2502112,
  "type": "Feature",
  "properties": {
    "tgn:hierarchy":[
        "tgn:2502112",
        "tgn:1000001",
        "tgn:7012149",
        "tgn:2001521",
        "tgn:7007709",
        "tgn:7029392"
    ],
    "tgn:id":2502112,
    "tgn:name":"McKenzie, Lake",
    "tgn:placetype":[
        "aat:300006191"
    ]
},
  "bbox": [],
  "geometry": {"coordinates":[-79.5667,35.1667],"type":"Point"}
}