{
  "id": 2334579,
  "type": "Feature",
  "properties": {
    "tgn:hierarchy":[
        "tgn:2334579",
        "tgn:1000001",
        "tgn:7006451",
        "tgn:7012149",
        "tgn:2000099",
        "tgn:7029392"
    ],
    "tgn:id":2334579,
    "tgn:name":"Forestdale Canyon Tank",
    "tgn:placetype":[
        "aat:300006191"
    ]
},
  "bbox": [],
  "geometry": {"coordinates":[-110.05,34.1667],"type":"Point"}
}