{
  "id": 2359630,
  "type": "Feature",
  "properties": {
    "tgn:hierarchy":[
        "tgn:2359630",
        "tgn:1000001",
        "tgn:7012149",
        "tgn:7007564",
        "tgn:7029392"
    ],
    "tgn:id":2359630,
    "tgn:name":"Grants Pond",
    "tgn:placetype":[
        "aat:300008680"
    ]
},
  "bbox": [],
  "geometry": {"coordinates":[-71.8833,43.5833],"type":"Point"}
}