<<<<<<< HEAD
{
  "id": 2153475,
  "type": "Feature",
  "properties": {
    "tgn:hierarchy":[
        "tgn:2153475",
        "tgn:1000001",
        "tgn:7012149",
        "tgn:1002263",
        "tgn:7007826",
        "tgn:7029392"
    ],
    "tgn:id":2153475,
    "tgn:name":"Beans Creek",
    "tgn:placetype":[
        "aat:300008706"
    ]
},
  "bbox": [],
  "geometry": {"coordinates":[-95.15,31.8167],"type":"Point"}
}
=======
{"geometry":{"type":"Point","coordinates":[-95.150000,31.816700]},"type":"Feature","properties":{"hierarchy":["tgn:2153475","tgn:1000001","tgn:7012149","tgn:1002263","tgn:7007826","tgn:7029392"],"placetype":["aat:300008706"],"id":2153475,"name:xx":"Beans Creek"}}
>>>>>>> 03f74aca74312dbeaf24d7e61306dd6a786dc3d0
