{
  "id": 2721819,
  "type": "Feature",
  "properties": {
    "tgn:hierarchy":[
        "tgn:2721819",
        "tgn:1000001",
        "tgn:7012149",
        "tgn:2002387",
        "tgn:7007923",
        "tgn:7029392"
    ],
    "tgn:id":2721819,
    "tgn:name":"Timber Creek",
    "tgn:placetype":[
        "aat:300008706"
    ]
},
  "bbox": [],
  "geometry": {"coordinates":[-104.4667,43.65],"type":"Point"}
}