{
  "id": 2420193,
  "type": "Feature",
  "properties": {
    "tgn:hierarchy":[
        "tgn:2420193",
        "tgn:1000001",
        "tgn:7012149",
        "tgn:2002118",
        "tgn:7007827",
        "tgn:7029392"
    ],
    "tgn:id":2420193,
    "tgn:name":"Jefferson Hollow",
    "tgn:placetype":[
        "aat:300008761"
    ]
},
  "bbox": [],
  "geometry": {"coordinates":[-111.7667,40.5833],"type":"Point"}
}