<<<<<<< HEAD
{
  "id": 2256947,
  "type": "Feature",
  "properties": {
    "tgn:hierarchy":[
        "tgn:2256947",
        "tgn:1000001",
        "tgn:7012149",
        "tgn:2000811",
        "tgn:7007255",
        "tgn:7029392"
    ],
    "tgn:id":2256947,
    "tgn:name":"Corn Branch",
    "tgn:placetype":[
        "aat:300008699"
    ]
},
  "bbox": [],
  "geometry": {"coordinates":[-83.3833,37.05],"type":"Point"}
}
=======
{"geometry":{"type":"Point","coordinates":[-83.383300,37.050000]},"type":"Feature","properties":{"hierarchy":["tgn:2256947","tgn:1000001","tgn:7012149","tgn:2000811","tgn:7007255","tgn:7029392"],"placetype":["aat:300008699"],"id":2256947,"name:xx":"Corn Branch"}}
>>>>>>> 03f74aca74312dbeaf24d7e61306dd6a786dc3d0
