{
  "id": 2309725,
  "type": "Feature",
  "properties": {
    "tgn:hierarchy":[
        "tgn:2309725",
        "tgn:1000001",
        "tgn:7012149",
        "tgn:2000637",
        "tgn:7007253",
        "tgn:7029392"
    ],
    "tgn:id":2309725,
    "tgn:name":"Easter, Lake",
    "tgn:placetype":[
        "aat:300006191"
    ]
},
  "bbox": [],
  "geometry": {"coordinates":[-93.55,41.5333],"type":"Point"}
}