{
  "id": 2738706,
  "type": "Feature",
  "properties": {
    "tgn:hierarchy":[
        "tgn:2738706",
        "tgn:7006450",
        "tgn:1000001",
        "tgn:7030517",
        "tgn:7012149",
        "tgn:7029392"
    ],
    "tgn:id":2738706,
    "tgn:name":"Union Creek",
    "tgn:placetype":[
        "aat:300008706"
    ]
},
  "bbox": [],
  "geometry": {"coordinates":[-156.8167,59.0833],"type":"Point"}
}