{
  "id": 7588862,
  "type": "Feature",
  "properties": {
    "tgn:hierarchy":[
        "tgn:7588862",
        "tgn:1000004",
        "tgn:7000198",
        "tgn:7000799",
        "tgn:7029392"
    ],
    "tgn:id":7588862,
    "tgn:name:en":"Khad Telian",
    "tgn:placetype":[
        "aat:300008347"
    ]
},
  "bbox": [],
  "geometry": {"coordinates":[74.154429,33.339461],"type":"Point"}
}