{
  "id": 2373091,
  "type": "Feature",
  "properties": {
    "tgn:hierarchy":[
        "tgn:2373091",
        "tgn:1000001",
        "tgn:7012149",
        "tgn:2001879",
        "tgn:7007825",
        "tgn:7029392"
    ],
    "tgn:id":2373091,
    "tgn:name":"Halls Creek",
    "tgn:placetype":[
        "aat:300008706"
    ]
},
  "bbox": [],
  "geometry": {"coordinates":[-87.7833,36.1833],"type":"Point"}
}