{
  "id": 7115135,
  "type": "Feature",
  "properties": {
    "tgn:hierarchy":[
        "tgn:7115135",
        "tgn:7003669",
        "tgn:1000003",
        "tgn:7000084",
        "tgn:7029392"
    ],
    "tgn:id":7115135,
    "tgn:name":"Ochsenfurter Forst",
    "tgn:placetype":[
        "aat:300008863"
    ]
},
  "bbox": [],
  "geometry": {"coordinates":[10.066667,49.683333],"type":"Point"}
}