{
  "id": 2369299,
  "type": "Feature",
  "properties": {
    "tgn:hierarchy":[
        "tgn:2369299",
        "tgn:1000001",
        "tgn:7012149",
        "tgn:2000905",
        "tgn:7007256",
        "tgn:7029392"
    ],
    "tgn:id":2369299,
    "tgn:name":"Gum Swamp",
    "tgn:placetype":[
        "aat:300008905"
    ]
},
  "bbox": [],
  "geometry": {"coordinates":[-89.9333,30.4833],"type":"Point"}
}