{
  "id": 1042178,
  "type": "Feature",
  "properties": {
    "tgn:hierarchy":[
        "tgn:1042178",
        "tgn:7002681",
        "tgn:7001395",
        "tgn:1000003",
        "tgn:1000074",
        "tgn:7011052",
        "tgn:7029392"
    ],
    "tgn:id":1042178,
    "tgn:name":"Palo\u00fakia",
    "tgn:placetype":[
        "aat:300008347"
    ]
},
  "bbox": [],
  "geometry": {"coordinates":[23.521771,37.965714],"type":"Point"}
}