{
  "id": 1132615,
  "type": "Feature",
  "properties": {
    "tgn:hierarchy":[
        "tgn:1132615",
        "tgn:1000001",
        "tgn:7012149",
        "tgn:7007254",
        "tgn:7029392"
    ],
    "tgn:id":1132615,
    "tgn:name":"Buffalo Creek",
    "tgn:placetype":[
        "aat:300008706"
    ]
},
  "bbox": [],
  "geometry": {"coordinates":[-98.1333,39.6667],"type":"Point"}
}