{
  "id": 1101667,
  "type": "Feature",
  "properties": {
    "tgn:hierarchy":[
        "tgn:1101667",
        "tgn:1000001",
        "tgn:7012149",
        "tgn:7007157",
        "tgn:7029392"
    ],
    "tgn:id":1101667,
    "tgn:name":"Lassen Volcanic National Park",
    "tgn:placetype":[
        "aat:300008189"
    ]
},
  "bbox": [],
  "geometry": {"coordinates":[-121.3667,40.4667],"type":"Point"}
}