{
  "id": 2571629,
  "type": "Feature",
  "properties": {
    "tgn:hierarchy":[
        "tgn:2571629",
        "tgn:1000001",
        "tgn:7012149",
        "tgn:2002275",
        "tgn:7013961",
        "tgn:7029392"
    ],
    "tgn:id":2571629,
    "tgn:name":"Paw Paw",
    "tgn:placetype":[
        "aat:300008347"
    ]
},
  "bbox": [],
  "geometry": {"coordinates":[-80.15,39.5333],"type":"Point"}
}