<<<<<<< HEAD
{
  "id": 7028447,
  "type": "Feature",
  "properties": {
    "tgn:hierarchy":[
        "tgn:7028447",
        "tgn:7002445",
        "tgn:1000003",
        "tgn:7008160",
        "tgn:7008591",
        "tgn:7012005",
        "tgn:7029392"
    ],
    "tgn:id":7028447,
    "tgn:name":"Bowthorpe",
    "tgn:placetype":[
        "aat:300000874",
        "aat:300008372",
        "aat:300387092"
    ]
},
  "bbox": [],
  "geometry": {"coordinates":[1.203,52.634],"type":"Point"}
}
=======
{"geometry":{"type":"Point","coordinates":[1.203000,52.634000]},"type":"Feature","properties":{"hierarchy":["tgn:7028447","tgn:7002445","tgn:1000003","tgn:7008160","tgn:7008591","tgn:7012005","tgn:7029392"],"placetype":["aat:300000874","aat:300008372","aat:300387092"],"id":7028447,"name:xx":"Bowthorpe"}}
>>>>>>> 03f74aca74312dbeaf24d7e61306dd6a786dc3d0
