{
  "id": 1032827,
  "type": "Feature",
  "properties": {
    "tgn:hierarchy":[
        "tgn:1032827",
        "tgn:1000003",
        "tgn:7002892",
        "tgn:1000070",
        "tgn:7029392"
    ],
    "tgn:id":1032827,
    "tgn:name":"Cozes",
    "tgn:placetype":[
        "aat:300008347"
    ]
},
  "bbox": [],
  "geometry": {"coordinates":[-0.8333,45.5833],"type":"Point"}
}