{
  "id": 2335396,
  "type": "Feature",
  "properties": {
    "tgn:hierarchy":[
        "tgn:2335396",
        "tgn:1000001",
        "tgn:7012149",
        "tgn:7007713",
        "tgn:7029392"
    ],
    "tgn:id":2335396,
    "tgn:name":"Fort Meade Veterans Administration Watershed",
    "tgn:placetype":[
        "aat:300055621"
    ]
},
  "bbox": [],
  "geometry": {"coordinates":[-103.55,44.3667],"type":"Point"}
}