<<<<<<< HEAD
{
  "id": 2335396,
  "type": "Feature",
  "properties": {
    "tgn:hierarchy":[
        "tgn:2335396",
        "tgn:1000001",
        "tgn:7012149",
        "tgn:7007713",
        "tgn:7029392"
    ],
    "tgn:id":2335396,
    "tgn:name":"Fort Meade Veterans Administration Watershed",
    "tgn:placetype":[
        "aat:300055621"
    ]
},
  "bbox": [],
  "geometry": {"coordinates":[-103.55,44.3667],"type":"Point"}
}
=======
{"geometry":{"type":"Point","coordinates":[-103.550000,44.366700]},"type":"Feature","properties":{"hierarchy":["tgn:2335396","tgn:1000001","tgn:7012149","tgn:7007713","tgn:7029392"],"placetype":["aat:300055621"],"id":2335396,"name:xx":"Fort Meade Veterans Administration Watershed"}}
>>>>>>> 03f74aca74312dbeaf24d7e61306dd6a786dc3d0
