<<<<<<< HEAD
{
  "id": 7355787,
  "type": "Feature",
  "properties": {
    "tgn:hierarchy":[
        "tgn:7355787",
        "tgn:1001835",
        "tgn:1000001",
        "tgn:7005560",
        "tgn:7029392"
    ],
    "tgn:id":7355787,
    "tgn:name":"Chico, Valle",
    "tgn:placetype":[
        "aat:300008761"
    ]
},
  "bbox": [],
  "geometry": {"coordinates":[-115.1,30.766667],"type":"Point"}
}
=======
{"geometry":{"type":"Point","coordinates":[-115.100000,30.766667]},"type":"Feature","properties":{"hierarchy":["tgn:7355787","tgn:1001835","tgn:1000001","tgn:7005560","tgn:7029392"],"placetype":["aat:300008761"],"id":7355787,"name:xx":"Chico, Valle"}}
>>>>>>> 03f74aca74312dbeaf24d7e61306dd6a786dc3d0
