{
  "id": 2424872,
  "type": "Feature",
  "properties": {
    "tgn:hierarchy":[
        "tgn:2424872",
        "tgn:1000001",
        "tgn:7012149",
        "tgn:1002400",
        "tgn:7007255",
        "tgn:7029392"
    ],
    "tgn:id":2424872,
    "tgn:name":"Johnson Hill",
    "tgn:placetype":[
        "aat:300008798"
    ]
},
  "bbox": [],
  "geometry": {"coordinates":[-84.8833,38.7667],"type":"Point"}
}