{
  "id": 7023029,
  "type": "Feature",
  "properties": {
    "tgn:hierarchy":[
        "tgn:7023029",
        "tgn:1000001",
        "tgn:7012149",
        "tgn:7007523",
        "tgn:7029392"
    ],
    "tgn:id":7023029,
    "tgn:name":"Goggins Mountain",
    "tgn:placetype":[
        "aat:300008798"
    ]
},
  "bbox": [],
  "geometry": {"coordinates":[-90.8833,37.5333],"type":"Point"}
}