<<<<<<< HEAD
{
  "id": 7023029,
  "type": "Feature",
  "properties": {
    "tgn:hierarchy":[
        "tgn:7023029",
        "tgn:1000001",
        "tgn:7012149",
        "tgn:7007523",
        "tgn:7029392"
    ],
    "tgn:id":7023029,
    "tgn:name":"Goggins Mountain",
    "tgn:placetype":[
        "aat:300008798"
    ]
},
  "bbox": [],
  "geometry": {"coordinates":[-90.8833,37.5333],"type":"Point"}
}
=======
{"geometry":{"type":"Point","coordinates":[-90.883300,37.533300]},"type":"Feature","properties":{"hierarchy":["tgn:7023029","tgn:1000001","tgn:7012149","tgn:7007523","tgn:7029392"],"placetype":["aat:300008798"],"id":7023029,"name:xx":"Goggins Mountain"}}
>>>>>>> 03f74aca74312dbeaf24d7e61306dd6a786dc3d0
