{
  "id": 2611647,
  "type": "Feature",
  "properties": {
    "tgn:hierarchy":[
        "tgn:2611647",
        "tgn:1000001",
        "tgn:7012149",
        "tgn:7007826",
        "tgn:7029392"
    ],
    "tgn:id":2611647,
    "tgn:name":"Red Mountain Branch",
    "tgn:placetype":[
        "aat:300008699"
    ]
},
  "bbox": [],
  "geometry": {"coordinates":[-98.75,30.95],"type":"Point"}
}