{
  "id": 2675967,
  "type": "Feature",
  "properties": {
    "tgn:hierarchy":[
        "tgn:2675967",
        "tgn:1000001",
        "tgn:7012149",
        "tgn:2000998",
        "tgn:7007520",
        "tgn:7029392"
    ],
    "tgn:id":2675967,
    "tgn:name":"Soper Creek",
    "tgn:placetype":[
        "aat:300008706"
    ]
},
  "bbox": [],
  "geometry": {"coordinates":[-85.55,44.4333],"type":"Point"}
}