<<<<<<< HEAD
{
  "id": 7353229,
  "type": "Feature",
  "properties": {
    "tgn:hierarchy":[
        "tgn:7353229",
        "tgn:1000001",
        "tgn:7005595",
        "tgn:7005560",
        "tgn:7029392"
    ],
    "tgn:id":7353229,
    "tgn:name":"Bebelama",
    "tgn:placetype":[
        "aat:300008347"
    ]
},
  "bbox": [],
  "geometry": {"coordinates":[-107.4,25.05],"type":"Point"}
}
=======
{"geometry":{"type":"Point","coordinates":[-107.400000,25.050000]},"type":"Feature","properties":{"hierarchy":["tgn:7353229","tgn:1000001","tgn:7005595","tgn:7005560","tgn:7029392"],"placetype":["aat:300008347"],"id":7353229,"name:xx":"Bebelama"}}
>>>>>>> 03f74aca74312dbeaf24d7e61306dd6a786dc3d0
