{
  "id": 7388223,
  "type": "Feature",
  "properties": {
    "tgn:hierarchy":[
        "tgn:7388223",
        "tgn:1000001",
        "tgn:7005597",
        "tgn:7005560",
        "tgn:7029392"
    ],
    "tgn:id":7388223,
    "tgn:name":"Puerto el Alicreado",
    "tgn:placetype":[
        "aat:300008699"
    ]
},
  "bbox": [],
  "geometry": {"coordinates":[-99.75,23.066667],"type":"Point"}
}