{
  "id": 7096396,
  "type": "Feature",
  "properties": {
    "tgn:hierarchy":[
        "tgn:7096396",
        "tgn:7003692",
        "tgn:1000003",
        "tgn:7000084",
        "tgn:7029392"
    ],
    "tgn:id":7096396,
    "tgn:name":"Schweizerhof",
    "tgn:placetype":[
        "aat:300000206"
    ]
},
  "bbox": [],
  "geometry": {"coordinates":[10.216667,48.983333],"type":"Point"}
}