{
  "id": 2255183,
  "type": "Feature",
  "properties": {
    "tgn:hierarchy":[
        "tgn:2255183",
        "tgn:1000001",
        "tgn:7012149",
        "tgn:2000814",
        "tgn:7007255",
        "tgn:7029392"
    ],
    "tgn:id":2255183,
    "tgn:name":"Cooper Landing",
    "tgn:placetype":[
        "aat:300008347"
    ]
},
  "bbox": [],
  "geometry": {"coordinates":[-88.3333,37.05],"type":"Point"}
}