{
  "id": 2493250,
  "type": "Feature",
  "properties": {
    "tgn:hierarchy":[
        "tgn:2493250",
        "tgn:1000001",
        "tgn:7012149",
        "tgn:1003020",
        "tgn:7007920",
        "tgn:7029392"
    ],
    "tgn:id":2493250,
    "tgn:name":"Marmot Ridge",
    "tgn:placetype":[
        "aat:300266640"
    ]
},
  "bbox": [],
  "geometry": {"coordinates":[-121.9167,48.7667],"type":"Point"}
}