{
  "id": 7356272,
  "type": "Feature",
  "properties": {
    "tgn:hierarchy":[
        "tgn:7356272",
        "tgn:1000001",
        "tgn:7005594",
        "tgn:7005560",
        "tgn:7029392"
    ],
    "tgn:id":7356272,
    "tgn:name":"Cerro de San Pedro",
    "tgn:placetype":[
        "aat:300008347"
    ]
},
  "bbox": [],
  "geometry": {"coordinates":[-100.816667,22.216667],"type":"Point"}
}