{
  "id": 2606215,
  "type": "Feature",
  "properties": {
    "tgn:hierarchy":[
        "tgn:2606215",
        "tgn:7006450",
        "tgn:1000001",
        "tgn:7012149",
        "tgn:2000085",
        "tgn:7029392"
    ],
    "tgn:id":2606215,
    "tgn:name":"Rainy Mountain",
    "tgn:placetype":[
        "aat:300008798"
    ]
},
  "bbox": [],
  "geometry": {"coordinates":[-145.85,63.2667],"type":"Point"}
}