{
  "id": 2745279,
  "type": "Feature",
  "properties": {
    "tgn:hierarchy":[
        "tgn:2745279",
        "tgn:1000001",
        "tgn:2001350",
        "tgn:7012149",
        "tgn:7007525",
        "tgn:7029392"
    ],
    "tgn:id":2745279,
    "tgn:name":"Vincent Valley",
    "tgn:placetype":[
        "aat:300386845"
    ]
},
  "bbox": [],
  "geometry": {"coordinates":[-102.1333,41.8333],"type":"Point"}
}