{
  "id": 1094638,
  "type": "Feature",
  "properties": {
    "tgn:hierarchy":[
        "tgn:1094638",
        "tgn:7001242",
        "tgn:1001697",
        "tgn:1000203",
        "tgn:7029392"
    ],
    "tgn:id":1094638,
    "tgn:name":"Kihundo",
    "tgn:placetype":[
        "aat:300008347"
    ]
},
  "bbox": [],
  "geometry": {"coordinates":[38.9833,-9.4167],"type":"Point"}
}