<<<<<<< HEAD
{
  "id": 7486335,
  "type": "Feature",
  "properties": {
    "tgn:hierarchy":[
        "tgn:7486335",
        "tgn:1000004",
        "tgn:7001014",
        "tgn:1000141",
        "tgn:7029392"
    ],
    "tgn:id":7486335,
    "tgn:name":"Maming",
    "tgn:placetype":[
        "aat:300008347"
    ]
},
  "bbox": [],
  "geometry": {"coordinates":[120.27588,23.696604],"type":"Point"}
}
=======
{"geometry":{"type":"Point","coordinates":[120.275880,23.696604]},"type":"Feature","properties":{"hierarchy":["tgn:7486335","tgn:1000004","tgn:7001014","tgn:1000141","tgn:7029392"],"placetype":["aat:300008347"],"id":7486335,"name:xx":"Maming"}}
>>>>>>> 03f74aca74312dbeaf24d7e61306dd6a786dc3d0
