{
  "id": 2565878,
  "type": "Feature",
  "properties": {
    "tgn:hierarchy":[
        "tgn:2565878",
        "tgn:1000001",
        "tgn:7012149",
        "tgn:7019014",
        "tgn:7007251",
        "tgn:7029392"
    ],
    "tgn:id":2565878,
    "tgn:name":"Palm Beach",
    "tgn:placetype":[
        "aat:300008347"
    ]
},
  "bbox": [],
  "geometry": {"coordinates":[-88.1833,42.3667],"type":"Point"}
}