<<<<<<< HEAD
{
  "id": 7478688,
  "type": "Feature",
  "properties": {
    "tgn:hierarchy":[
        "tgn:7478688",
        "tgn:1000004",
        "tgn:7489179",
        "tgn:1000141",
        "tgn:7029392"
    ],
    "tgn:id":7478688,
    "tgn:name":"Wugu Qiao",
    "tgn:placetype":[
        "aat:300007836"
    ]
},
  "bbox": [],
  "geometry": {"coordinates":[121.818807,24.667973],"type":"Point"}
}
=======
{"geometry":{"type":"Point","coordinates":[121.818807,24.667973]},"type":"Feature","properties":{"hierarchy":["tgn:7478688","tgn:1000004","tgn:7489179","tgn:1000141","tgn:7029392"],"placetype":["aat:300007836"],"id":7478688,"name:xx":"Wugu Qiao"}}
>>>>>>> 03f74aca74312dbeaf24d7e61306dd6a786dc3d0
