{
  "id": 2229609,
  "type": "Feature",
  "properties": {
    "tgn:hierarchy":[
        "tgn:2229609",
        "tgn:1000001",
        "tgn:7012149",
        "tgn:2002129",
        "tgn:7007827",
        "tgn:7029392"
    ],
    "tgn:id":2229609,
    "tgn:name":"Cedar Ridge",
    "tgn:placetype":[
        "aat:300008347"
    ]
},
  "bbox": [],
  "geometry": {"coordinates":[-112.0333,41.1833],"type":"Point"}
}