{
  "id": 2004472,
  "type": "Feature",
  "properties": {
    "tgn:hierarchy":[
        "tgn:2004472",
        "tgn:7002659",
        "tgn:1000001",
        "tgn:7012149",
        "tgn:2000050",
        "tgn:7029392"
    ],
    "tgn:id":2004472,
    "tgn:name":"Mitylene",
    "tgn:placetype":[
        "aat:300387016"
    ]
},
  "bbox": [],
  "geometry": {"coordinates":[-86.1667,32.3667],"type":"Point"}
}