{
  "id": 2752159,
  "type": "Feature",
  "properties": {
    "tgn:hierarchy":[
        "tgn:2752159",
        "tgn:1000001",
        "tgn:2000924",
        "tgn:7012149",
        "tgn:7007515",
        "tgn:7029392"
    ],
    "tgn:id":2752159,
    "tgn:name":"Wash Ledge",
    "tgn:placetype":[
        "aat:300132348"
    ]
},
  "bbox": [],
  "geometry": {"coordinates":[-69.35,43.85],"type":"Point"}
}