{
  "id": 2535307,
  "type": "Feature",
  "properties": {
    "tgn:hierarchy":[
        "tgn:2535307",
        "tgn:7006450",
        "tgn:1000001",
        "tgn:7030517",
        "tgn:7012149",
        "tgn:7029392"
    ],
    "tgn:id":2535307,
    "tgn:name":"Nanuktuk Creek",
    "tgn:placetype":[
        "aat:300008706"
    ]
},
  "bbox": [],
  "geometry": {"coordinates":[-155.0333,59.0333],"type":"Point"}
}