{
  "id": 1084482,
  "type": "Feature",
  "properties": {
    "tgn:hierarchy":[
        "tgn:1084482",
        "tgn:1000004",
        "tgn:1001147",
        "tgn:1000135",
        "tgn:7029392"
    ],
    "tgn:id":1084482,
    "tgn:name":"Nagiba",
    "tgn:placetype":[
        "aat:300008347"
    ]
},
  "bbox": [],
  "geometry": {"coordinates":[120.8833,13.6833],"type":"Point"}
}