{
  "id": 2394575,
  "type": "Feature",
  "properties": {
    "tgn:hierarchy":[
        "tgn:2394575",
        "tgn:1000001",
        "tgn:7012149",
        "tgn:1002750",
        "tgn:7007252",
        "tgn:7029392"
    ],
    "tgn:id":2394575,
    "tgn:name":"Hogs Defeat Creek",
    "tgn:placetype":[
        "aat:300008706"
    ]
},
  "bbox": [],
  "geometry": {"coordinates":[-86.4167,38.4833],"type":"Point"}
}