{
  "id": 7459330,
  "type": "Feature",
  "properties": {
    "tgn:hierarchy":[
        "tgn:7459330",
        "tgn:7002444",
        "tgn:1000003",
        "tgn:7008082",
        "tgn:7008591",
        "tgn:7029392"
    ],
    "tgn:id":7459330,
    "tgn:name:en":"Mhuilinn, Sg\u00f9rr a'",
    "tgn:placetype":[
        "aat:300008795"
    ]
},
  "bbox": [],
  "geometry": {"coordinates":[-4.95,57.566667],"type":"Point"}
}