{
  "id": 2116436,
  "type": "Feature",
  "properties": {
    "tgn:hierarchy":[
        "tgn:2116436",
        "tgn:1000001",
        "tgn:7012149",
        "tgn:1002742",
        "tgn:7007920",
        "tgn:7029392"
    ],
    "tgn:id":2116436,
    "tgn:name":"Oroville",
    "tgn:placetype":[
        "aat:300008347"
    ]
},
  "bbox": [],
  "geometry": {"coordinates":[-119.4333,48.9333],"type":"Point"}
}