{
  "id": 2465095,
  "type": "Feature",
  "properties": {
    "tgn:hierarchy":[
        "tgn:2465095",
        "tgn:1000001",
        "tgn:7006451",
        "tgn:7012149",
        "tgn:2000098",
        "tgn:7029392"
    ],
    "tgn:id":2465095,
    "tgn:name":"Lola Mine",
    "tgn:placetype":[
        "aat:300000390"
    ]
},
  "bbox": [],
  "geometry": {"coordinates":[-113.7167,34.35],"type":"Point"}
}