{
  "id": 7491484,
  "type": "Feature",
  "properties": {
    "tgn:hierarchy":[
        "tgn:7491484",
        "tgn:1000004",
        "tgn:7001013",
        "tgn:1000141",
        "tgn:7029392"
    ],
    "tgn:id":7491484,
    "tgn:name":"Daku Cun",
    "tgn:placetype":[
        "aat:300387173"
    ]
},
  "bbox": [],
  "geometry": {"coordinates":[121.129943,25.001514],"type":"Point"}
}