{
  "id": 7275627,
  "type": "Feature",
  "properties": {
    "tgn:hierarchy":[
        "tgn:7275627",
        "tgn:7002464",
        "tgn:1000049",
        "tgn:1000002",
        "tgn:7029392"
    ],
    "tgn:id":7275627,
    "tgn:name":"Tres Cumbres, Cerro",
    "tgn:placetype":[
        "aat:300008795"
    ]
},
  "bbox": [],
  "geometry": {"coordinates":[-69.85,-20.766667],"type":"Point"}
}