{
  "id": 2379916,
  "type": "Feature",
  "properties": {
    "tgn:hierarchy":[
        "tgn:2379916",
        "tgn:1000001",
        "tgn:7012149",
        "tgn:7007158",
        "tgn:2000246",
        "tgn:7029392"
    ],
    "tgn:id":2379916,
    "tgn:name":"Hat Springs Creek",
    "tgn:placetype":[
        "aat:300008706"
    ]
},
  "bbox": [],
  "geometry": {"coordinates":[-106.5333,38.0167],"type":"Point"}
}