{
  "id": 2281033,
  "type": "Feature",
  "properties": {
    "tgn:hierarchy":[
        "tgn:2281033",
        "tgn:1000001",
        "tgn:2000939",
        "tgn:7012149",
        "tgn:7007516",
        "tgn:7029392"
    ],
    "tgn:id":2281033,
    "tgn:name":"Deep Harbor",
    "tgn:placetype":[
        "aat:300008347"
    ]
},
  "bbox": [],
  "geometry": {"coordinates":[-76.3167,38.7167],"type":"Point"}
}