{
  "id": 7016830,
  "type": "Feature",
  "properties": {
    "tgn:hierarchy":[
        "tgn:7016830",
        "tgn:1001942",
        "tgn:1000047",
        "tgn:7002457",
        "tgn:1000002",
        "tgn:7029392"
    ],
    "tgn:id":7016830,
    "tgn:name":"Timbira",
    "tgn:placetype":[
        "aat:300008707"
    ]
},
  "bbox": [],
  "geometry": {"coordinates":[-43.2167,-22.6833],"type":"Point"}
}