{
  "id": 2750021,
  "type": "Feature",
  "properties": {
    "tgn:hierarchy":[
        "tgn:2750021",
        "tgn:1000001",
        "tgn:7012149",
        "tgn:2002015",
        "tgn:7007826",
        "tgn:7029392"
    ],
    "tgn:id":2750021,
    "tgn:name":"Walter Creek",
    "tgn:placetype":[
        "aat:300008706"
    ]
},
  "bbox": [],
  "geometry": {"coordinates":[-98.55,29.8167],"type":"Point"}
}