{
  "id": 7578129,
  "type": "Feature",
  "properties": {
    "tgn:hierarchy":[
        "tgn:7578129",
        "tgn:1001828",
        "tgn:1000004",
        "tgn:7000198",
        "tgn:7029392"
    ],
    "tgn:id":7578129,
    "tgn:name:en":"Tripur\u0101ntakam",
    "tgn:placetype":[
        "aat:300008347"
    ]
},
  "bbox": [],
  "geometry": {"coordinates":[79.45,15.983333],"type":"Point"}
}