<<<<<<< HEAD
{
  "id": 7378610,
  "type": "Feature",
  "properties": {
    "tgn:hierarchy":[
        "tgn:7378610",
        "tgn:7005581",
        "tgn:1000001",
        "tgn:7005560",
        "tgn:7029392"
    ],
    "tgn:id":7378610,
    "tgn:name":"Los Pilares",
    "tgn:placetype":[
        "aat:300008347"
    ]
},
  "bbox": [],
  "geometry": {"coordinates":[-106.4,26.816667],"type":"Point"}
}
=======
{"geometry":{"type":"Point","coordinates":[-106.400000,26.816667]},"type":"Feature","properties":{"hierarchy":["tgn:7378610","tgn:7005581","tgn:1000001","tgn:7005560","tgn:7029392"],"placetype":["aat:300008347"],"id":7378610,"name:xx":"Los Pilares"}}
>>>>>>> 03f74aca74312dbeaf24d7e61306dd6a786dc3d0
