{
  "id": 2414814,
  "type": "Feature",
  "properties": {
    "tgn:hierarchy":[
        "tgn:2414814",
        "tgn:1000001",
        "tgn:7006451",
        "tgn:2000095",
        "tgn:7012149",
        "tgn:7029392"
    ],
    "tgn:id":2414814,
    "tgn:name":"Isabell Spring",
    "tgn:placetype":[
        "aat:300008697"
    ]
},
  "bbox": [],
  "geometry": {"coordinates":[-109.1833,33.7667],"type":"Point"}
}