{
  "id": 2167178,
  "type": "Feature",
  "properties": {
    "tgn:hierarchy":[
        "tgn:2167178",
        "tgn:1000001",
        "tgn:7012149",
        "tgn:7019676",
        "tgn:7007566",
        "tgn:7029392"
    ],
    "tgn:id":2167178,
    "tgn:name":"Big Cedar Tank",
    "tgn:placetype":[
        "aat:300006191"
    ]
},
  "bbox": [],
  "geometry": {"coordinates":[-107.4333,35.6833],"type":"Point"}
}