{
  "id": 2603181,
  "type": "Feature",
  "properties": {
    "tgn:hierarchy":[
        "tgn:2603181",
        "tgn:1000001",
        "tgn:1002218",
        "tgn:7012149",
        "tgn:7007157",
        "tgn:7029392"
    ],
    "tgn:id":2603181,
    "tgn:name":"Quartz Creek",
    "tgn:placetype":[
        "aat:300008706"
    ]
},
  "bbox": [],
  "geometry": {"coordinates":[-121.1833,39.6167],"type":"Point"}
}