{
  "id": 2590910,
  "type": "Feature",
  "properties": {
    "tgn:hierarchy":[
        "tgn:2590910",
        "tgn:1000001",
        "tgn:7012149",
        "tgn:2002296",
        "tgn:7013961",
        "tgn:7029392"
    ],
    "tgn:id":2590910,
    "tgn:name":"Polecat Knob",
    "tgn:placetype":[
        "aat:300008798"
    ]
},
  "bbox": [],
  "geometry": {"coordinates":[-79.75,39.0667],"type":"Point"}
}