{
  "id": 7001815,
  "type": "Feature",
  "properties": {
    "tgn:hierarchy":[
        "tgn:7001815",
        "tgn:1000004",
        "tgn:7002077",
        "tgn:1000111",
        "tgn:7029392"
    ],
    "tgn:id":7001815,
    "tgn:name":"Xingtai",
    "tgn:placetype":[
        "aat:300008347",
        "aat:300008375"
    ]
},
  "bbox": [],
  "geometry": {"coordinates":[114.4667,37.1333],"type":"Point"}
}