{
  "id": 2022926,
  "type": "Feature",
  "properties": {
    "tgn:hierarchy":[
        "tgn:2022926",
        "tgn:1000001",
        "tgn:2000314",
        "tgn:7012149",
        "tgn:7007248",
        "tgn:7029392"
    ],
    "tgn:id":2022926,
    "tgn:name":"Fort Oglethorpe",
    "tgn:placetype":[
        "aat:300008347"
    ]
},
  "bbox": [],
  "geometry": {"coordinates":[-85.25,34.9333],"type":"Point"}
}