{
  "id": 2423249,
  "type": "Feature",
  "properties": {
    "tgn:hierarchy":[
        "tgn:2423249",
        "tgn:1000001",
        "tgn:7012149",
        "tgn:2002250",
        "tgn:7007920",
        "tgn:7029392"
    ],
    "tgn:id":2423249,
    "tgn:name":"Joes Ridge",
    "tgn:placetype":[
        "aat:300266640"
    ]
},
  "bbox": [],
  "geometry": {"coordinates":[-117.7667,48.5333],"type":"Point"}
}