{
  "id": 7522555,
  "type": "Feature",
  "properties": {
    "tgn:hierarchy":[
        "tgn:7522555",
        "tgn:7001242",
        "tgn:7016833",
        "tgn:1001335",
        "tgn:7029392"
    ],
    "tgn:id":7522555,
    "tgn:name":"Kawm as Sa\u1e29\u0101yit",
    "tgn:placetype":[
        "aat:300008347"
    ]
},
  "bbox": [],
  "geometry": {"coordinates":[31.209438,31.325325],"type":"Point"}
}