{
  "id": 1029243,
  "type": "Feature",
  "properties": {
    "tgn:hierarchy":[
        "tgn:1029243",
        "tgn:7002445",
        "tgn:1000003",
        "tgn:7008127",
        "tgn:7008591",
        "tgn:7029392"
    ],
    "tgn:id":1029243,
    "tgn:name:en":"Ferryhill",
    "tgn:placetype":[
        "aat:300008347"
    ]
},
  "bbox": [],
  "geometry": {"coordinates":[-1.55,54.683333],"type":"Point"}
}