{
  "id": 7139589,
  "type": "Feature",
  "properties": {
    "tgn:hierarchy":[
        "tgn:7139589",
        "tgn:7003669",
        "tgn:1000003",
        "tgn:7000084",
        "tgn:7029392"
    ],
    "tgn:id":7139589,
    "tgn:name":"Leimitz",
    "tgn:placetype":[
        "aat:300008347"
    ]
},
  "bbox": [],
  "geometry": {"coordinates":[11.95,50.316667],"type":"Point"}
}