{
  "id": 2170393,
  "type": "Feature",
  "properties": {
    "tgn:hierarchy":[
        "tgn:2170393",
        "tgn:1000001",
        "tgn:2002148",
        "tgn:7012149",
        "tgn:7007919",
        "tgn:7029392"
    ],
    "tgn:id":2170393,
    "tgn:name":"Big Rock Branch",
    "tgn:placetype":[
        "aat:300008699"
    ]
},
  "bbox": [],
  "geometry": {"coordinates":[-82.1167,37.2167],"type":"Point"}
}