{
  "id": 2005974,
  "type": "Feature",
  "properties": {
    "tgn:hierarchy":[
        "tgn:2005974",
        "tgn:7006450",
        "tgn:1000001",
        "tgn:7019698",
        "tgn:7012149",
        "tgn:7029392"
    ],
    "tgn:id":2005974,
    "tgn:name":"Clam Gulch",
    "tgn:placetype":[
        "aat:300008347"
    ]
},
  "bbox": [],
  "geometry": {"coordinates":[-151.3833,60.2167],"type":"Point"}
}