{
  "id": 1075636,
  "type": "Feature",
  "properties": {
    "tgn:hierarchy":[
        "tgn:1075636",
        "tgn:1000004",
        "tgn:1001869",
        "tgn:7000198",
        "tgn:7029392"
    ],
    "tgn:id":1075636,
    "tgn:name":"Jodiya",
    "tgn:placetype":[
        "aat:300008347"
    ]
},
  "bbox": [],
  "geometry": {"coordinates":[70.283333,22.716667],"type":"Point"}
}