{
  "id": 2316176,
  "type": "Feature",
  "properties": {
    "tgn:hierarchy":[
        "tgn:2316176",
        "tgn:1000001",
        "tgn:7012149",
        "tgn:2002018",
        "tgn:7007826",
        "tgn:7029392"
    ],
    "tgn:id":2316176,
    "tgn:name":"Elm Valley",
    "tgn:placetype":[
        "aat:300008761"
    ]
},
  "bbox": [],
  "geometry": {"coordinates":[-98.95,30.0667],"type":"Point"}
}