{
  "id": 7251476,
  "type": "Feature",
  "properties": {
    "tgn:hierarchy":[
        "tgn:7251476",
        "tgn:7007877",
        "tgn:1000003",
        "tgn:1000063",
        "tgn:4012014",
        "tgn:7029392"
    ],
    "tgn:id":7251476,
    "tgn:name":"Pierre qui Tourne, Bois de la",
    "tgn:placetype":[
        "aat:300008863"
    ]
},
  "bbox": [],
  "geometry": {"coordinates":[4.233333,50.15],"type":"Point"}
}