<<<<<<< HEAD
{
  "id": 7357544,
  "type": "Feature",
  "properties": {
    "tgn:hierarchy":[
        "tgn:7357544",
        "tgn:1000001",
        "tgn:1001960",
        "tgn:7005560",
        "tgn:7029392"
    ],
    "tgn:id":7357544,
    "tgn:name":"Rancho Culantrillo",
    "tgn:placetype":[
        "aat:300000241"
    ]
},
  "bbox": [],
  "geometry": {"coordinates":[-109.85,30.6],"type":"Point"}
}
=======
{"geometry":{"type":"Point","coordinates":[-109.850000,30.600000]},"type":"Feature","properties":{"hierarchy":["tgn:7357544","tgn:1000001","tgn:1001960","tgn:7005560","tgn:7029392"],"placetype":["aat:300000241"],"id":7357544,"name:xx":"Rancho Culantrillo"}}
>>>>>>> 03f74aca74312dbeaf24d7e61306dd6a786dc3d0
