{
  "id": 2422510,
  "type": "Feature",
  "properties": {
    "tgn:hierarchy":[
        "tgn:2422510",
        "tgn:1000001",
        "tgn:7012149",
        "tgn:1003026",
        "tgn:7007826",
        "tgn:7029392"
    ],
    "tgn:id":2422510,
    "tgn:name":"Jinks Branch",
    "tgn:placetype":[
        "aat:300008347"
    ]
},
  "bbox": [],
  "geometry": {"coordinates":[-97.8833,30.6333],"type":"Point"}
}