{
  "id": 2113686,
  "type": "Feature",
  "properties": {
    "tgn:hierarchy":[
        "tgn:2113686",
        "tgn:1000001",
        "tgn:7012149",
        "tgn:1002425",
        "tgn:7007919",
        "tgn:7029392"
    ],
    "tgn:id":2113686,
    "tgn:name":"Pleasant Shade",
    "tgn:placetype":[
        "aat:300008347",
        "aat:300387210"
    ]
},
  "bbox": [],
  "geometry": {"coordinates":[-77.6333,36.75],"type":"Point"}
}