{
  "id": 2425165,
  "type": "Feature",
  "properties": {
    "tgn:hierarchy":[
        "tgn:2425165",
        "tgn:1000001",
        "tgn:2000873",
        "tgn:7012149",
        "tgn:7007256",
        "tgn:7029392"
    ],
    "tgn:id":2425165,
    "tgn:name":"Johnson Landing",
    "tgn:placetype":[
        "aat:300008347"
    ]
},
  "bbox": [],
  "geometry": {"coordinates":[-92.4333,30.9667],"type":"Point"}
}