{
  "id": 2083636,
  "type": "Feature",
  "properties": {
    "tgn:hierarchy":[
        "tgn:2083636",
        "tgn:1000001",
        "tgn:7012149",
        "tgn:2001660",
        "tgn:7007707",
        "tgn:7029392"
    ],
    "tgn:id":2083636,
    "tgn:name":"Mountain Park",
    "tgn:placetype":[
        "aat:300008347"
    ]
},
  "bbox": [],
  "geometry": {"coordinates":[-98.9333,34.6833],"type":"Point"}
}