<<<<<<< HEAD
{
  "id": 7029430,
  "type": "Feature",
  "properties": {
    "tgn:hierarchy":[
        "tgn:7029430",
        "tgn:7002445",
        "tgn:1000003",
        "tgn:7019057",
        "tgn:7008591",
        "tgn:7029392"
    ],
    "tgn:id":7029430,
    "tgn:name":"Wold Newton",
    "tgn:placetype":[
        "aat:300008347",
        "aat:300008372"
    ]
},
  "bbox": [],
  "geometry": {"coordinates":[-0.4,54.133333],"type":"Point"}
}
=======
{"geometry":{"type":"Point","coordinates":[-0.400000,54.133333]},"type":"Feature","properties":{"hierarchy":["tgn:7029430","tgn:7002445","tgn:1000003","tgn:7019057","tgn:7008591","tgn:7029392"],"placetype":["aat:300008347","aat:300008372"],"id":7029430,"name:xx":"Wold Newton"}}
>>>>>>> 03f74aca74312dbeaf24d7e61306dd6a786dc3d0
