{
  "id": 2188389,
  "type": "Feature",
  "properties": {
    "tgn:hierarchy":[
        "tgn:2188389",
        "tgn:1000001",
        "tgn:7012149",
        "tgn:7014510",
        "tgn:7007920",
        "tgn:7029392"
    ],
    "tgn:id":2188389,
    "tgn:name":"Boston Peak",
    "tgn:placetype":[
        "aat:300008798"
    ]
},
  "bbox": [],
  "geometry": {"coordinates":[-121.0333,48.4833],"type":"Point"}
}