{
  "id": 1011331,
  "type": "Feature",
  "properties": {
    "tgn:hierarchy":[
        "tgn:1011331",
        "tgn:7001242",
        "tgn:1000149",
        "tgn:1000835",
        "tgn:7029392"
    ],
    "tgn:id":1011331,
    "tgn:name":"Tr\u00eas Pontas, Cabo das",
    "tgn:placetype":[
        "aat:300008850"
    ]
},
  "bbox": [],
  "geometry": {"coordinates":[13.5333,-10.4667],"type":"Point"}
}