{
  "id": 7231196,
  "type": "Feature",
  "properties": {
    "tgn:hierarchy":[
        "tgn:7231196",
        "tgn:7002690",
        "tgn:7012056",
        "tgn:1000003",
        "tgn:1000074",
        "tgn:7029392"
    ],
    "tgn:id":7231196,
    "tgn:name":"Kouv\u00e1ra",
    "tgn:placetype":[
        "aat:300008795"
    ]
},
  "bbox": [],
  "geometry": {"coordinates":[23.633333,35.45],"type":"Point"}
}