{
  "id": 7429348,
  "type": "Feature",
  "properties": {
    "tgn:hierarchy":[
        "tgn:7429348",
        "tgn:1001853",
        "tgn:1000001",
        "tgn:7005560",
        "tgn:7029392"
    ],
    "tgn:id":7429348,
    "tgn:name":"Los \u00c1ngeles",
    "tgn:placetype":[
        "aat:300008347"
    ]
},
  "bbox": [],
  "geometry": {"coordinates":[-101.016667,25.116667],"type":"Point"}
}