{
  "id": 2636439,
  "type": "Feature",
  "properties": {
    "tgn:hierarchy":[
        "tgn:2636439",
        "tgn:1000001",
        "tgn:7012149",
        "tgn:2001276",
        "tgn:7007524",
        "tgn:7029392"
    ],
    "tgn:id":2636439,
    "tgn:name":"Sag, The",
    "tgn:placetype":[
        "aat:300386845"
    ]
},
  "bbox": [],
  "geometry": {"coordinates":[-106.65,47.75],"type":"Point"}
}