{
  "id": 7511576,
  "type": "Feature",
  "properties": {
    "tgn:hierarchy":[
        "tgn:7511576",
        "tgn:1009227",
        "tgn:1000226",
        "tgn:7018437",
        "tgn:1000006",
        "tgn:7029392"
    ],
    "tgn:id":7511576,
    "tgn:name:en":"Lowburn Ferry",
    "tgn:placetype":[
        "aat:300008347"
    ]
},
  "bbox": [],
  "geometry": {"coordinates":[169.216667,-45.016667],"type":"Point"}
}