{
  "id": 2673890,
  "type": "Feature",
  "properties": {
    "tgn:hierarchy":[
        "tgn:2673890",
        "tgn:1000001",
        "tgn:7012149",
        "tgn:2000220",
        "tgn:7007158",
        "tgn:7029392"
    ],
    "tgn:id":2673890,
    "tgn:name":"Snow Lake",
    "tgn:placetype":[
        "aat:300008680"
    ]
},
  "bbox": [],
  "geometry": {"coordinates":[-105.8833,40.4667],"type":"Point"}
}