{
  "id": 2727945,
  "type": "Feature",
  "properties": {
    "tgn:hierarchy":[
        "tgn:2727945",
        "tgn:1000001",
        "tgn:7006451",
        "tgn:7012149",
        "tgn:2000101",
        "tgn:7029392"
    ],
    "tgn:id":2727945,
    "tgn:name":"Trap Canyon",
    "tgn:placetype":[
        "aat:300008761"
    ]
},
  "bbox": [],
  "geometry": {"coordinates":[-111.2667,33.45],"type":"Point"}
}