{
  "id": 1069078,
  "type": "Feature",
  "properties": {
    "tgn:hierarchy":[
        "tgn:1069078",
        "tgn:1000004",
        "tgn:7016672",
        "tgn:1000111",
        "tgn:7029392"
    ],
    "tgn:id":1069078,
    "tgn:name":"Huwan",
    "tgn:placetype":[
        "aat:300008347"
    ]
},
  "bbox": [],
  "geometry": {"coordinates":[114.85,31.6833],"type":"Point"}
}