{
  "id": 7254700,
  "type": "Feature",
  "properties": {
    "tgn:hierarchy":[
        "tgn:7254700",
        "tgn:7003460",
        "tgn:1000003",
        "tgn:1000063",
        "tgn:4012014",
        "tgn:7029392"
    ],
    "tgn:id":7254700,
    "tgn:name":"S\u00e9rez\u00e9",
    "tgn:placetype":[
        "aat:300008347"
    ]
},
  "bbox": [],
  "geometry": {"coordinates":[5.866667,50.633333],"type":"Point"}
}