{
  "id": 1093508,
  "type": "Feature",
  "properties": {
    "tgn:hierarchy":[
        "tgn:1093508",
        "tgn:7001242",
        "tgn:7017584",
        "tgn:1000193",
        "tgn:7029392"
    ],
    "tgn:id":1093508,
    "tgn:name":"Piketberg",
    "tgn:placetype":[
        "aat:300008347"
    ]
},
  "bbox": [],
  "geometry": {"coordinates":[18.75,-32.9167],"type":"Point"}
}