{
  "id": 7482511,
  "type": "Feature",
  "properties": {
    "tgn:hierarchy":[
        "tgn:7482511",
        "tgn:7469009",
        "tgn:1000004",
        "tgn:1000141",
        "tgn:7029392"
    ],
    "tgn:id":7482511,
    "tgn:name":"Wanggongyin",
    "tgn:placetype":[
        "aat:300387036"
    ]
},
  "bbox": [],
  "geometry": {"coordinates":[118.300278,24.445556],"type":"Point"}
}