<<<<<<< HEAD
{
  "id": 7482511,
  "type": "Feature",
  "properties": {
    "tgn:hierarchy":[
        "tgn:7482511",
        "tgn:7469009",
        "tgn:1000004",
        "tgn:1000141",
        "tgn:7029392"
    ],
    "tgn:id":7482511,
    "tgn:name":"Wanggongyin",
    "tgn:placetype":[
        "aat:300387036"
    ]
},
  "bbox": [],
  "geometry": {"coordinates":[118.300278,24.445556],"type":"Point"}
}
=======
{"geometry":{"type":"Point","coordinates":[118.300278,24.445556]},"type":"Feature","properties":{"hierarchy":["tgn:7482511","tgn:7469009","tgn:1000004","tgn:1000141","tgn:7029392"],"placetype":["aat:300387036"],"id":7482511,"name:xx":"Wanggongyin"}}
>>>>>>> 03f74aca74312dbeaf24d7e61306dd6a786dc3d0
