{
  "id": 2291072,
  "type": "Feature",
  "properties": {
    "tgn:hierarchy":[
        "tgn:2291072",
        "tgn:1000001",
        "tgn:7012149",
        "tgn:2000539",
        "tgn:7007251",
        "tgn:7029392"
    ],
    "tgn:id":2291072,
    "tgn:name":"Dog Walk",
    "tgn:placetype":[
        "aat:300008347"
    ]
},
  "bbox": [],
  "geometry": {"coordinates":[-88.9167,37.75],"type":"Point"}
}