{
  "id": 2523901,
  "type": "Feature",
  "properties": {
    "tgn:hierarchy":[
        "tgn:2523901",
        "tgn:1000001",
        "tgn:7012149",
        "tgn:2002302",
        "tgn:7013961",
        "tgn:7029392"
    ],
    "tgn:id":2523901,
    "tgn:name":"Morehead Ridge",
    "tgn:placetype":[
        "aat:300266640"
    ]
},
  "bbox": [],
  "geometry": {"coordinates":[-81.4667,39.0667],"type":"Point"}
}