{
  "id": 7517483,
  "type": "Feature",
  "properties": {
    "tgn:hierarchy":[
        "tgn:7517483",
        "tgn:1009227",
        "tgn:7001866",
        "tgn:1000226",
        "tgn:1000006",
        "tgn:7029392"
    ],
    "tgn:id":7517483,
    "tgn:name:en":"McLeod",
    "tgn:placetype":[
        "aat:300008795"
    ]
},
  "bbox": [],
  "geometry": {"coordinates":[170.783333,-44.633333],"type":"Point"}
}