{
  "id": 7403141,
  "type": "Feature",
  "properties": {
    "tgn:hierarchy":[
        "tgn:7403141",
        "tgn:1000001",
        "tgn:7005600",
        "tgn:7005560",
        "tgn:7029392"
    ],
    "tgn:id":7403141,
    "tgn:name":"San Rom\u00e1n",
    "tgn:placetype":[
        "aat:300008347"
    ]
},
  "bbox": [],
  "geometry": {"coordinates":[-87.733333,20.958333],"type":"Point"}
}