{
  "id": 2358977,
  "type": "Feature",
  "properties": {
    "tgn:hierarchy":[
        "tgn:2358977",
        "tgn:1000001",
        "tgn:7012149",
        "tgn:1002392",
        "tgn:7007157",
        "tgn:7029392"
    ],
    "tgn:id":2358977,
    "tgn:name":"Granite Hill",
    "tgn:placetype":[
        "aat:300008798"
    ]
},
  "bbox": [],
  "geometry": {"coordinates":[-119.35,36.6833],"type":"Point"}
}