{
  "id": 2352957,
  "type": "Feature",
  "properties": {
    "tgn:hierarchy":[
        "tgn:2352957",
        "tgn:1000001",
        "tgn:2002366",
        "tgn:7012149",
        "tgn:7007923",
        "tgn:7029392"
    ],
    "tgn:id":2352957,
    "tgn:name":"Godes Springs",
    "tgn:placetype":[
        "aat:300008697"
    ]
},
  "bbox": [],
  "geometry": {"coordinates":[-108.0833,44.9333],"type":"Point"}
}