<<<<<<< HEAD
{
  "id": 2334632,
  "type": "Feature",
  "properties": {
    "tgn:hierarchy":[
        "tgn:2334632",
        "tgn:1000001",
        "tgn:7012149",
        "tgn:2001067",
        "tgn:7007521",
        "tgn:7029392"
    ],
    "tgn:id":2334632,
    "tgn:name":"Forge Lake",
    "tgn:placetype":[
        "aat:300008680"
    ]
},
  "bbox": [],
  "geometry": {"coordinates":[-92.3667,47.4833],"type":"Point"}
}
=======
{"geometry":{"type":"Point","coordinates":[-92.366700,47.483300]},"type":"Feature","properties":{"hierarchy":["tgn:2334632","tgn:1000001","tgn:7012149","tgn:2001067","tgn:7007521","tgn:7029392"],"placetype":["aat:300008680"],"id":2334632,"name:xx":"Forge Lake"}}
>>>>>>> 03f74aca74312dbeaf24d7e61306dd6a786dc3d0
