{
  "id": 7257375,
  "type": "Feature",
  "properties": {
    "tgn:hierarchy":[
        "tgn:7257375",
        "tgn:7593113",
        "tgn:7016620",
        "tgn:7593112",
        "tgn:1000001",
        "tgn:7029392"
    ],
    "tgn:id":7257375,
    "tgn:name:nl":"Tera Hundu",
    "tgn:placetype":[
        "aat:300387200"
    ]
},
  "bbox": [],
  "geometry": {"coordinates":[-68.266667,12.183333],"type":"Point"}
}