{
  "id": 1040035,
  "type": "Feature",
  "properties": {
    "tgn:hierarchy":[
        "tgn:1040035",
        "tgn:1000003",
        "tgn:7003677",
        "tgn:7000084",
        "tgn:7029392"
    ],
    "tgn:id":1040035,
    "tgn:name":"Langschede",
    "tgn:placetype":[
        "aat:300008347"
    ]
},
  "bbox": [],
  "geometry": {"coordinates":[7.716667,51.483333],"type":"Point"}
}