{
  "id": 2086736,
  "type": "Feature",
  "properties": {
    "tgn:hierarchy":[
        "tgn:2086736",
        "tgn:1000001",
        "tgn:7012149",
        "tgn:1002876",
        "tgn:7007710",
        "tgn:7029392"
    ],
    "tgn:id":2086736,
    "tgn:name":"Brockton",
    "tgn:placetype":[
        "aat:300008347"
    ]
},
  "bbox": [],
  "geometry": {"coordinates":[-76.0667,40.7333],"type":"Point"}
}