{
  "id": 2688035,
  "type": "Feature",
  "properties": {
    "tgn:hierarchy":[
        "tgn:2688035",
        "tgn:1000001",
        "tgn:7012149",
        "tgn:7007523",
        "tgn:7029392"
    ],
    "tgn:id":2688035,
    "tgn:name":"Springfield Plain",
    "tgn:placetype":[
        "aat:300055621"
    ]
},
  "bbox": [],
  "geometry": {"coordinates":[-94.6167,36.7333],"type":"Point"}
}