{
  "id": 2237779,
  "type": "Feature",
  "properties": {
    "tgn:hierarchy":[
        "tgn:2237779",
        "tgn:1000001",
        "tgn:7012149",
        "tgn:7007709",
        "tgn:7029392"
    ],
    "tgn:id":2237779,
    "tgn:name":"Chinquapin Creek",
    "tgn:placetype":[
        "aat:300008706"
    ]
},
  "bbox": [],
  "geometry": {"coordinates":[-80.5833,36.05],"type":"Point"}
}