{
  "id": 7096445,
  "type": "Feature",
  "properties": {
    "tgn:hierarchy":[
        "tgn:7096445",
        "tgn:7000096",
        "tgn:1000003",
        "tgn:7000084",
        "tgn:7029392"
    ],
    "tgn:id":7096445,
    "tgn:name":"Siedlung Erika",
    "tgn:placetype":[
        "aat:300008347"
    ]
},
  "bbox": [],
  "geometry": {"coordinates":[13.783333,51.633333],"type":"Point"}
}