{
  "id": 7151280,
  "type": "Feature",
  "properties": {
    "tgn:hierarchy":[
        "tgn:7151280",
        "tgn:7000096",
        "tgn:1000003",
        "tgn:7000084",
        "tgn:7029392"
    ],
    "tgn:id":7151280,
    "tgn:name":"Jesar Graben",
    "tgn:placetype":[
        "aat:300008699"
    ]
},
  "bbox": [],
  "geometry": {"coordinates":[14.316667,52.666667],"type":"Point"}
}