{
  "id": 1045326,
  "type": "Feature",
  "properties": {
    "tgn:hierarchy":[
        "tgn:1045326",
        "tgn:1003478",
        "tgn:1000003",
        "tgn:7003120",
        "tgn:1000080",
        "tgn:7029392"
    ],
    "tgn:id":1045326,
    "tgn:name":"Meina",
    "tgn:placetype":[
        "aat:300008347"
    ]
},
  "bbox": [],
  "geometry": {"coordinates":[8.533333,45.783333],"type":"Point"}
}