{
  "id": 2374971,
  "type": "Feature",
  "properties": {
    "tgn:hierarchy":[
        "tgn:2374971",
        "tgn:1000001",
        "tgn:1002724",
        "tgn:7012149",
        "tgn:7007517",
        "tgn:7029392"
    ],
    "tgn:id":2374971,
    "tgn:name":"Hangman Island",
    "tgn:placetype":[
        "aat:300008791"
    ]
},
  "bbox": [],
  "geometry": {"coordinates":[-70.9667,42.2833],"type":"Point"}
}