{
  "id": 7490117,
  "type": "Feature",
  "properties": {
    "tgn:hierarchy":[
        "tgn:7490117",
        "tgn:7488858",
        "tgn:1000004",
        "tgn:1000141",
        "tgn:7029392"
    ],
    "tgn:id":7490117,
    "tgn:name":"Dacheng Li",
    "tgn:placetype":[
        "aat:300387173"
    ]
},
  "bbox": [],
  "geometry": {"coordinates":[120.953944,23.976611],"type":"Point"}
}