{
  "id": 2215719,
  "type": "Feature",
  "properties": {
    "tgn:hierarchy":[
        "tgn:2215719",
        "tgn:1000001",
        "tgn:7012149",
        "tgn:2002248",
        "tgn:7007920",
        "tgn:7029392"
    ],
    "tgn:id":2215719,
    "tgn:name":"Camden",
    "tgn:placetype":[
        "aat:300008347"
    ]
},
  "bbox": [],
  "geometry": {"coordinates":[-117.2333,48.0333],"type":"Point"}
}