{
  "id": 1002621,
  "type": "Feature",
  "properties": {
    "tgn:hierarchy":[
        "tgn:1002621",
        "tgn:1000001",
        "tgn:7012149",
        "tgn:7007157",
        "tgn:7029392"
    ],
    "tgn:id":1002621,
    "tgn:name":"Madera",
    "tgn:placetype":[
        "aat:300387145",
        "aat:300000771"
    ]
},
  "bbox": [],
  "geometry": {"coordinates":[-119.8333,37.1667],"type":"Point"}
}