{
  "id": 7504434,
  "type": "Feature",
  "properties": {
    "tgn:hierarchy":[
        "tgn:7504434",
        "tgn:1008380",
        "tgn:1000226",
        "tgn:7000512",
        "tgn:1000006",
        "tgn:7029392"
    ],
    "tgn:id":7504434,
    "tgn:name:en":"Wairongomai Stream",
    "tgn:placetype":[
        "aat:300008699"
    ]
},
  "bbox": [],
  "geometry": {"coordinates":[175.133333,-40.716667],"type":"Point"}
}