{
  "id": 1113599,
  "type": "Feature",
  "properties": {
    "tgn:hierarchy":[
        "tgn:1113599",
        "tgn:7005685",
        "tgn:1000001",
        "tgn:7024197",
        "tgn:7029392"
    ],
    "tgn:id":1113599,
    "tgn:name":"Pelly Bay",
    "tgn:placetype":[
        "aat:300132316"
    ]
},
  "bbox": [],
  "geometry": {"coordinates":[-89.85,68.8833],"type":"Point"}
}