{
  "id": 2001565,
  "type": "Feature",
  "properties": {
    "tgn:hierarchy":[
        "tgn:2001565",
        "tgn:1000001",
        "tgn:7012149",
        "tgn:7007705",
        "tgn:7029392"
    ],
    "tgn:id":2001565,
    "tgn:name":"Cass",
    "tgn:placetype":[
        "aat:300387145",
        "aat:300000771"
    ]
},
  "bbox": [],
  "geometry": {"coordinates":[-97.2167,46.9333],"type":"Point"}
}