{
  "id": 2486668,
  "type": "Feature",
  "properties": {
    "tgn:hierarchy":[
        "tgn:2486668",
        "tgn:1000001",
        "tgn:2001427",
        "tgn:7012149",
        "tgn:7007564",
        "tgn:7029392"
    ],
    "tgn:id":2486668,
    "tgn:name":"Ledge Pond",
    "tgn:placetype":[
        "aat:300008680"
    ]
},
  "bbox": [],
  "geometry": {"coordinates":[-72.0833,43.4167],"type":"Point"}
}