{
  "id": 2585049,
  "type": "Feature",
  "properties": {
    "tgn:hierarchy":[
        "tgn:2585049",
        "tgn:1000001",
        "tgn:2001704",
        "tgn:7012149",
        "tgn:7007708",
        "tgn:7029392"
    ],
    "tgn:id":2585049,
    "tgn:name":"Pinnacle Point",
    "tgn:placetype":[
        "aat:300008798"
    ]
},
  "bbox": [],
  "geometry": {"coordinates":[-123.9167,42.6833],"type":"Point"}
}