{
  "id": 2465040,
  "type": "Feature",
  "properties": {
    "tgn:hierarchy":[
        "tgn:2465040",
        "tgn:1000001",
        "tgn:2001267",
        "tgn:7012149",
        "tgn:7007524",
        "tgn:7029392"
    ],
    "tgn:id":2465040,
    "tgn:name":"Lohse Spring",
    "tgn:placetype":[
        "aat:300008697"
    ]
},
  "bbox": [],
  "geometry": {"coordinates":[-109.7833,47.7333],"type":"Point"}
}