{
  "id": 7492568,
  "type": "Feature",
  "properties": {
    "tgn:hierarchy":[
        "tgn:7492568",
        "tgn:1000004",
        "tgn:1000454",
        "tgn:1000141",
        "tgn:7029392"
    ],
    "tgn:id":7492568,
    "tgn:name":"Tanzinei",
    "tgn:placetype":[
        "aat:300008347"
    ]
},
  "bbox": [],
  "geometry": {"coordinates":[121.614194,25.2287],"type":"Point"}
}