{
  "id": 2736773,
  "type": "Feature",
  "properties": {
    "tgn:hierarchy":[
        "tgn:2736773",
        "tgn:1000001",
        "tgn:7012149",
        "tgn:2002118",
        "tgn:7007827",
        "tgn:7029392"
    ],
    "tgn:id":2736773,
    "tgn:name":"Twins at Little Willow",
    "tgn:placetype":[
        "aat:300008347"
    ]
},
  "bbox": [],
  "geometry": {"coordinates":[-111.8833,40.55],"type":"Point"}
}