{
  "id": 2340261,
  "type": "Feature",
  "properties": {
    "tgn:hierarchy":[
        "tgn:2340261",
        "tgn:1000001",
        "tgn:7012149",
        "tgn:7007254",
        "tgn:7029392"
    ],
    "tgn:id":2340261,
    "tgn:name":"French Creek",
    "tgn:placetype":[
        "aat:300008706"
    ]
},
  "bbox": [],
  "geometry": {"coordinates":[-96.15,39.65],"type":"Point"}
}