{
  "id": 2694925,
  "type": "Feature",
  "properties": {
    "tgn:hierarchy":[
        "tgn:2694925",
        "tgn:1000001",
        "tgn:2000275",
        "tgn:7012149",
        "tgn:7007240",
        "tgn:7029392"
    ],
    "tgn:id":2694925,
    "tgn:name":"Still Bay",
    "tgn:placetype":[
        "aat:300008905"
    ]
},
  "bbox": [],
  "geometry": {"coordinates":[-83.2167,29.9833],"type":"Point"}
}