{
  "id": 2023210,
  "type": "Feature",
  "properties": {
    "tgn:hierarchy":[
        "tgn:2023210",
        "tgn:1000001",
        "tgn:7012149",
        "tgn:2000369",
        "tgn:7007248",
        "tgn:7029392"
    ],
    "tgn:id":2023210,
    "tgn:name":"Hoschton",
    "tgn:placetype":[
        "aat:300008347"
    ]
},
  "bbox": [],
  "geometry": {"coordinates":[-83.75,34.0833],"type":"Point"}
}