{
  "id": 7532495,
  "type": "Feature",
  "properties": {
    "tgn:hierarchy":[
        "tgn:7532495",
        "tgn:7001242",
        "tgn:7016833",
        "tgn:7001336",
        "tgn:7029392"
    ],
    "tgn:id":7532495,
    "tgn:name:en":"Abu Khisheib, W\u00e2di",
    "tgn:placetype":[
        "aat:300379998"
    ]
},
  "bbox": [],
  "geometry": {"coordinates":[34.133739,27.847044],"type":"Point"}
}