<<<<<<< HEAD
{
  "id": 7369500,
  "type": "Feature",
  "properties": {
    "tgn:hierarchy":[
        "tgn:7369500",
        "tgn:7005581",
        "tgn:1000001",
        "tgn:7005560",
        "tgn:7029392"
    ],
    "tgn:id":7369500,
    "tgn:name":"Jabali, Puerto del",
    "tgn:placetype":[
        "aat:300259572"
    ]
},
  "bbox": [],
  "geometry": {"coordinates":[-104.45,26.95],"type":"Point"}
}
=======
{"geometry":{"type":"Point","coordinates":[-104.450000,26.950000]},"type":"Feature","properties":{"hierarchy":["tgn:7369500","tgn:7005581","tgn:1000001","tgn:7005560","tgn:7029392"],"placetype":["aat:300259572"],"id":7369500,"name:xx":"Jabali, Puerto del"}}
>>>>>>> 03f74aca74312dbeaf24d7e61306dd6a786dc3d0
