{
  "id": 2408154,
  "type": "Feature",
  "properties": {
    "tgn:hierarchy":[
        "tgn:2408154",
        "tgn:1000001",
        "tgn:7012149",
        "tgn:2001851",
        "tgn:7007825",
        "tgn:7029392"
    ],
    "tgn:id":2408154,
    "tgn:name":"Hurricane Ridge",
    "tgn:placetype":[
        "aat:300266640"
    ]
},
  "bbox": [],
  "geometry": {"coordinates":[-83.0167,35.8333],"type":"Point"}
}