{
  "id": 2723341,
  "type": "Feature",
  "properties": {
    "tgn:hierarchy":[
        "tgn:2723341",
        "tgn:1000001",
        "tgn:7012149",
        "tgn:1002631",
        "tgn:7007240",
        "tgn:7029392"
    ],
    "tgn:id":2723341,
    "tgn:name":"Tobe Lake",
    "tgn:placetype":[
        "aat:300008680"
    ]
},
  "bbox": [],
  "geometry": {"coordinates":[-81.85,29.1667],"type":"Point"}
}