{
  "id": 7241280,
  "type": "Feature",
  "properties": {
    "tgn:hierarchy":[
        "tgn:7241280",
        "tgn:7003460",
        "tgn:1000003",
        "tgn:1000063",
        "tgn:4012014",
        "tgn:7029392"
    ],
    "tgn:id":7241280,
    "tgn:name":"Kijs",
    "tgn:placetype":[
        "aat:300008347"
    ]
},
  "bbox": [],
  "geometry": {"coordinates":[5.85,50.716667],"type":"Point"}
}