{
  "id": 7316860,
  "type": "Feature",
  "properties": {
    "tgn:hierarchy":[
        "tgn:7316860",
        "tgn:1001708",
        "tgn:1000049",
        "tgn:1000002",
        "tgn:7029392"
    ],
    "tgn:id":7316860,
    "tgn:name":"Chivato, Morro",
    "tgn:placetype":[
        "aat:300008795"
    ]
},
  "bbox": [],
  "geometry": {"coordinates":[-71.083333,-34.116667],"type":"Point"}
}