<<<<<<< HEAD
{
  "id": 7027955,
  "type": "Feature",
  "properties": {
    "tgn:hierarchy":[
        "tgn:7027955",
        "tgn:7002445",
        "tgn:1000003",
        "tgn:7008157",
        "tgn:7008591",
        "tgn:7029392"
    ],
    "tgn:id":7027955,
    "tgn:name:en":"Langton",
    "tgn:placetype":[
        "aat:300008347",
        "aat:300008372"
    ]
},
  "bbox": [],
  "geometry": {"coordinates":[-0.15,53.2],"type":"Point"}
}
=======
{"geometry":{"type":"Point","coordinates":[-0.150000,53.200000]},"type":"Feature","properties":{"hierarchy":["tgn:7027955","tgn:7002445","tgn:1000003","tgn:7008157","tgn:7008591","tgn:7029392"],"placetype":["aat:300008347","aat:300008372"],"name:en":"Langton","id":7027955}}
>>>>>>> 03f74aca74312dbeaf24d7e61306dd6a786dc3d0
