{
  "id": 2514794,
  "type": "Feature",
  "properties": {
    "tgn:hierarchy":[
        "tgn:2514794",
        "tgn:1000001",
        "tgn:7012149",
        "tgn:2000491",
        "tgn:7007250",
        "tgn:7029392"
    ],
    "tgn:id":2514794,
    "tgn:name":"Miller Peak",
    "tgn:placetype":[
        "aat:300008798"
    ]
},
  "bbox": [],
  "geometry": {"coordinates":[-115.7667,47.0333],"type":"Point"}
}