{
  "id": 2265229,
  "type": "Feature",
  "properties": {
    "tgn:hierarchy":[
        "tgn:2265229",
        "tgn:1000001",
        "tgn:2002370",
        "tgn:7012149",
        "tgn:7007923",
        "tgn:7029392"
    ],
    "tgn:id":2265229,
    "tgn:name":"Cranberry Spring",
    "tgn:placetype":[
        "aat:300008697"
    ]
},
  "bbox": [],
  "geometry": {"coordinates":[-104.2333,44.4167],"type":"Point"}
}