{
  "id": 7486870,
  "type": "Feature",
  "properties": {
    "tgn:hierarchy":[
        "tgn:7486870",
        "tgn:1000004",
        "tgn:7001014",
        "tgn:1000141",
        "tgn:7029392"
    ],
    "tgn:id":7486870,
    "tgn:name":"Meilin",
    "tgn:placetype":[
        "aat:300008347"
    ]
},
  "bbox": [],
  "geometry": {"coordinates":[120.598611,23.702222],"type":"Point"}
}