{
  "id": 2487343,
  "type": "Feature",
  "properties": {
    "tgn:hierarchy":[
        "tgn:2487343",
        "tgn:1000001",
        "tgn:7012149",
        "tgn:1002640",
        "tgn:7007252",
        "tgn:7029392"
    ],
    "tgn:id":2487343,
    "tgn:name":"Leffert Ditch",
    "tgn:placetype":[
        "aat:300006075"
    ]
},
  "bbox": [],
  "geometry": {"coordinates":[-86.2667,41.25],"type":"Point"}
}