{
  "id": 7584404,
  "type": "Feature",
  "properties": {
    "tgn:hierarchy":[
        "tgn:7584404",
        "tgn:1000004",
        "tgn:7000198",
        "tgn:1001894",
        "tgn:7029392"
    ],
    "tgn:id":7584404,
    "tgn:name:en":"Majna Protected Forest",
    "tgn:placetype":[
        "aat:300008865"
    ]
},
  "bbox": [],
  "geometry": {"coordinates":[78.967043,24.83758],"type":"Point"}
}