{
  "id": 7505739,
  "type": "Feature",
  "properties": {
    "tgn:hierarchy":[
        "tgn:7505739",
        "tgn:1008380",
        "tgn:7000507",
        "tgn:1000226",
        "tgn:1000006",
        "tgn:7029392"
    ],
    "tgn:id":7505739,
    "tgn:name:en":"Tory Shoal",
    "tgn:placetype":[
        "aat:300387036"
    ]
},
  "bbox": [],
  "geometry": {"coordinates":[174.083333,-36.416667],"type":"Point"}
}