{
  "id": 1135100,
  "type": "Feature",
  "properties": {
    "tgn:hierarchy":[
        "tgn:1135100",
        "tgn:1000001",
        "tgn:7012149",
        "tgn:7007710",
        "tgn:7029392"
    ],
    "tgn:id":1135100,
    "tgn:name":"Wissahickon Creek",
    "tgn:placetype":[
        "aat:300008706"
    ]
},
  "bbox": [],
  "geometry": {"coordinates":[-75.25,40.2333],"type":"Point"}
}