{
  "id": 2707357,
  "type": "Feature",
  "properties": {
    "tgn:hierarchy":[
        "tgn:2707357",
        "tgn:1000001",
        "tgn:7012149",
        "tgn:2002248",
        "tgn:7007920",
        "tgn:7029392"
    ],
    "tgn:id":2707357,
    "tgn:name":"Sweet Creek",
    "tgn:placetype":[
        "aat:300008706"
    ]
},
  "bbox": [],
  "geometry": {"coordinates":[-117.4833,48.85],"type":"Point"}
}