{
  "id": 2142052,
  "type": "Feature",
  "properties": {
    "tgn:hierarchy":[
        "tgn:2142052",
        "tgn:1000001",
        "tgn:7012149",
        "tgn:2001516",
        "tgn:7007709",
        "tgn:7029392"
    ],
    "tgn:id":2142052,
    "tgn:name":"Back Branch",
    "tgn:placetype":[
        "aat:300008699"
    ]
},
  "bbox": [],
  "geometry": {"coordinates":[-82.8167,35.7833],"type":"Point"}
}