{
  "id": 7477627,
  "type": "Feature",
  "properties": {
    "tgn:hierarchy":[
        "tgn:7477627",
        "tgn:7488858",
        "tgn:1000004",
        "tgn:1000141",
        "tgn:7029392"
    ],
    "tgn:id":7477627,
    "tgn:name":"Nangang Erhao Qiao",
    "tgn:placetype":[
        "aat:300007836"
    ]
},
  "bbox": [],
  "geometry": {"coordinates":[120.870583,23.954636],"type":"Point"}
}