{
  "id": 2160698,
  "type": "Feature",
  "properties": {
    "tgn:hierarchy":[
        "tgn:2160698",
        "tgn:1000001",
        "tgn:7012149",
        "tgn:2001138",
        "tgn:7007522",
        "tgn:7029392"
    ],
    "tgn:id":2160698,
    "tgn:name":"Belaire Estates",
    "tgn:placetype":[
        "aat:300008347"
    ]
},
  "bbox": [],
  "geometry": {"coordinates":[-88.7167,33.4667],"type":"Point"}
}