{
  "id": 1042682,
  "type": "Feature",
  "properties": {
    "tgn:hierarchy":[
        "tgn:1042682",
        "tgn:7003503",
        "tgn:7003478",
        "tgn:1000003",
        "tgn:1000078",
        "tgn:7029392"
    ],
    "tgn:id":1042682,
    "tgn:name":"Carrickmacross",
    "tgn:placetype":[
        "aat:300008347"
    ]
},
  "bbox": [],
  "geometry": {"coordinates":[-6.7167,53.9667],"type":"Point"}
}