{
  "id": 2690060,
  "type": "Feature",
  "properties": {
    "tgn:hierarchy":[
        "tgn:2690060",
        "tgn:1000001",
        "tgn:7006451",
        "tgn:7012149",
        "tgn:2000102",
        "tgn:7029392"
    ],
    "tgn:id":2690060,
    "tgn:name":"Stacey Lake",
    "tgn:placetype":[
        "aat:300008680"
    ]
},
  "bbox": [],
  "geometry": {"coordinates":[-110.85,31.3667],"type":"Point"}
}