{
  "id": 7010192,
  "type": "Feature",
  "properties": {
    "tgn:hierarchy":[
        "tgn:7010192",
        "tgn:1000004",
        "tgn:6003149",
        "tgn:7002435",
        "tgn:7029392"
    ],
    "tgn:id":7010192,
    "tgn:name":"Malaya Pera",
    "tgn:placetype":[
        "aat:300008347"
    ]
},
  "bbox": [],
  "geometry": {"coordinates":[54.8667,64.1833],"type":"Point"}
}