{
  "id": 7057841,
  "type": "Feature",
  "properties": {
    "tgn:hierarchy":[
        "tgn:7057841",
        "tgn:1001724",
        "tgn:1000003",
        "tgn:7003121",
        "tgn:1000080",
        "tgn:7029392"
    ],
    "tgn:id":7057841,
    "tgn:name":"Torre Argentina",
    "tgn:placetype":[
        "aat:300004847"
    ]
},
  "bbox": [],
  "geometry": {"coordinates":[8.45,40.316667],"type":"Point"}
}