<<<<<<< HEAD
{
  "id": 7057841,
  "type": "Feature",
  "properties": {
    "tgn:hierarchy":[
        "tgn:7057841",
        "tgn:1001724",
        "tgn:1000003",
        "tgn:7003121",
        "tgn:1000080",
        "tgn:7029392"
    ],
    "tgn:id":7057841,
    "tgn:name":"Torre Argentina",
    "tgn:placetype":[
        "aat:300004847"
    ]
},
  "bbox": [],
  "geometry": {"coordinates":[8.45,40.316667],"type":"Point"}
}
=======
{"geometry":{"type":"Point","coordinates":[8.450000,40.316667]},"type":"Feature","properties":{"hierarchy":["tgn:7057841","tgn:1001724","tgn:1000003","tgn:7003121","tgn:1000080","tgn:7029392"],"placetype":["aat:300004847"],"id":7057841,"name:xx":"Torre Argentina"}}
>>>>>>> 03f74aca74312dbeaf24d7e61306dd6a786dc3d0
