{
  "id": 1058755,
  "type": "Feature",
  "properties": {
    "tgn:hierarchy":[
        "tgn:1058755",
        "tgn:7011683",
        "tgn:1000004",
        "tgn:7006661",
        "tgn:7029392"
    ],
    "tgn:id":1058755,
    "tgn:name":"Pungan",
    "tgn:placetype":[
        "aat:300008347"
    ]
},
  "bbox": [],
  "geometry": {"coordinates":[70.8333,40.75],"type":"Point"}
}