<<<<<<< HEAD
{
  "id": 2156421,
  "type": "Feature",
  "properties": {
    "tgn:hierarchy":[
        "tgn:2156421",
        "tgn:1000001",
        "tgn:7012149",
        "tgn:2001538",
        "tgn:7007709",
        "tgn:7029392"
    ],
    "tgn:id":2156421,
    "tgn:name":"Bearskin Swamp",
    "tgn:placetype":[
        "aat:300008699"
    ]
},
  "bbox": [],
  "geometry": {"coordinates":[-78.45,35.0833],"type":"Point"}
}
=======
{"geometry":{"type":"Point","coordinates":[-78.450000,35.083300]},"type":"Feature","properties":{"hierarchy":["tgn:2156421","tgn:1000001","tgn:7012149","tgn:2001538","tgn:7007709","tgn:7029392"],"placetype":["aat:300008699"],"id":2156421,"name:xx":"Bearskin Swamp"}}
>>>>>>> 03f74aca74312dbeaf24d7e61306dd6a786dc3d0
