{
  "id": 1090619,
  "type": "Feature",
  "properties": {
    "tgn:hierarchy":[
        "tgn:1090619",
        "tgn:7001242",
        "tgn:1000409",
        "tgn:1000171",
        "tgn:7029392"
    ],
    "tgn:id":1090619,
    "tgn:name":"Zorzor",
    "tgn:placetype":[
        "aat:300008347"
    ]
},
  "bbox": [],
  "geometry": {"coordinates":[-9.4667,7.7667],"type":"Point"}
}