{
  "id": 7582359,
  "type": "Feature",
  "properties": {
    "tgn:hierarchy":[
        "tgn:7582359",
        "tgn:1000004",
        "tgn:7000198",
        "tgn:7016722",
        "tgn:7029392"
    ],
    "tgn:id":7582359,
    "tgn:name:en":"Sati",
    "tgn:placetype":[
        "aat:300008347"
    ]
},
  "bbox": [],
  "geometry": {"coordinates":[78.327616,24.827378],"type":"Point"}
}