{
  "id": 7500537,
  "type": "Feature",
  "properties": {
    "tgn:hierarchy":[
        "tgn:7500537",
        "tgn:1000004",
        "tgn:7001009",
        "tgn:1000141",
        "tgn:7029392"
    ],
    "tgn:id":7500537,
    "tgn:name":"Hongtai Zhongxue",
    "tgn:placetype":[
        "aat:300006495"
    ]
},
  "bbox": [],
  "geometry": {"coordinates":[120.7452,24.1586],"type":"Point"}
}