{
  "id": 7255203,
  "type": "Feature",
  "properties": {
    "tgn:hierarchy":[
        "tgn:7255203",
        "tgn:7018238",
        "tgn:1000003",
        "tgn:1000063",
        "tgn:4012014",
        "tgn:7029392"
    ],
    "tgn:id":7255203,
    "tgn:name":"Rixensart, Bois de",
    "tgn:placetype":[
        "aat:300008863"
    ]
},
  "bbox": [],
  "geometry": {"coordinates":[4.55,50.716667],"type":"Point"}
}