<<<<<<< HEAD
{
  "id": 2156901,
  "type": "Feature",
  "properties": {
    "tgn:hierarchy":[
        "tgn:2156901",
        "tgn:2000947",
        "tgn:1000001",
        "tgn:7012149",
        "tgn:7007520",
        "tgn:7029392"
    ],
    "tgn:id":2156901,
    "tgn:name":"Beaufort Lake",
    "tgn:placetype":[
        "aat:300008680"
    ]
},
  "bbox": [],
  "geometry": {"coordinates":[-88.1833,46.5333],"type":"Point"}
}
=======
{"geometry":{"type":"Point","coordinates":[-88.183300,46.533300]},"type":"Feature","properties":{"hierarchy":["tgn:2156901","tgn:2000947","tgn:1000001","tgn:7012149","tgn:7007520","tgn:7029392"],"placetype":["aat:300008680"],"id":2156901,"name:xx":"Beaufort Lake"}}
>>>>>>> 03f74aca74312dbeaf24d7e61306dd6a786dc3d0
