{
  "id": 2156901,
  "type": "Feature",
  "properties": {
    "tgn:hierarchy":[
        "tgn:2156901",
        "tgn:2000947",
        "tgn:1000001",
        "tgn:7012149",
        "tgn:7007520",
        "tgn:7029392"
    ],
    "tgn:id":2156901,
    "tgn:name":"Beaufort Lake",
    "tgn:placetype":[
        "aat:300008680"
    ]
},
  "bbox": [],
  "geometry": {"coordinates":[-88.1833,46.5333],"type":"Point"}
}