{
  "id": 2433878,
  "type": "Feature",
  "properties": {
    "tgn:hierarchy":[
        "tgn:2433878",
        "tgn:1000001",
        "tgn:7012149",
        "tgn:2001719",
        "tgn:7007708",
        "tgn:7029392"
    ],
    "tgn:id":2433878,
    "tgn:name":"Kelly Mountain",
    "tgn:placetype":[
        "aat:300008798"
    ]
},
  "bbox": [],
  "geometry": {"coordinates":[-119.2667,45.1833],"type":"Point"}
}