{
  "id": 2075460,
  "type": "Feature",
  "properties": {
    "tgn:hierarchy":[
        "tgn:2075460",
        "tgn:1000001",
        "tgn:7012149",
        "tgn:2001520",
        "tgn:7007709",
        "tgn:7029392"
    ],
    "tgn:id":2075460,
    "tgn:name":"Liberty Hill",
    "tgn:placetype":[
        "aat:300008347",
        "aat:300387210"
    ]
},
  "bbox": [],
  "geometry": {"coordinates":[-79.9833,35.3333],"type":"Point"}
}