{
  "id": 7290541,
  "type": "Feature",
  "properties": {
    "tgn:hierarchy":[
        "tgn:7290541",
        "tgn:1001630",
        "tgn:1000049",
        "tgn:1000002",
        "tgn:7029392"
    ],
    "tgn:id":7290541,
    "tgn:name":"Dichosa, Portezuelo de la",
    "tgn:placetype":[
        "aat:300259572"
    ]
},
  "bbox": [],
  "geometry": {"coordinates":[-70.166667,-27.983333],"type":"Point"}
}