{
  "id": 7478757,
  "type": "Feature",
  "properties": {
    "tgn:hierarchy":[
        "tgn:7478757",
        "tgn:7488858",
        "tgn:1000004",
        "tgn:1000141",
        "tgn:7029392"
    ],
    "tgn:id":7478757,
    "tgn:name":"Yuetaohu",
    "tgn:placetype":[
        "aat:300008347"
    ]
},
  "bbox": [],
  "geometry": {"coordinates":[120.826597,23.960753],"type":"Point"}
}