{
  "id": 2759659,
  "type": "Feature",
  "properties": {
    "tgn:hierarchy":[
        "tgn:2759659",
        "tgn:1000001",
        "tgn:7012149",
        "tgn:2001708",
        "tgn:7007708",
        "tgn:7029392"
    ],
    "tgn:id":2759659,
    "tgn:name":"West Fork Grub Creek",
    "tgn:placetype":[
        "aat:300008706"
    ]
},
  "bbox": [],
  "geometry": {"coordinates":[-118.9333,44.4667],"type":"Point"}
}