{
  "id": 7498504,
  "type": "Feature",
  "properties": {
    "tgn:hierarchy":[
        "tgn:7498504",
        "tgn:1000004",
        "tgn:7001009",
        "tgn:1000141",
        "tgn:7029392"
    ],
    "tgn:id":7498504,
    "tgn:name":"Bao'an Qiao",
    "tgn:placetype":[
        "aat:300007836"
    ]
},
  "bbox": [],
  "geometry": {"coordinates":[120.61383,24.149062],"type":"Point"}
}