<<<<<<< HEAD
{
  "id": 2761025,
  "type": "Feature",
  "properties": {
    "tgn:hierarchy":[
        "tgn:2761025",
        "tgn:1000001",
        "tgn:7012149",
        "tgn:2000926",
        "tgn:7007515",
        "tgn:7029392"
    ],
    "tgn:id":2761025,
    "tgn:name":"West Kennebago Mountain",
    "tgn:placetype":[
        "aat:300008798"
    ]
},
  "bbox": [],
  "geometry": {"coordinates":[-70.8167,45.1],"type":"Point"}
}
=======
{"geometry":{"type":"Point","coordinates":[-70.816700,45.100000]},"type":"Feature","properties":{"hierarchy":["tgn:2761025","tgn:1000001","tgn:7012149","tgn:2000926","tgn:7007515","tgn:7029392"],"placetype":["aat:300008798"],"id":2761025,"name:xx":"West Kennebago Mountain"}}
>>>>>>> 03f74aca74312dbeaf24d7e61306dd6a786dc3d0
