{
  "id": 7545283,
  "type": "Feature",
  "properties": {
    "tgn:hierarchy":[
        "tgn:7545283",
        "tgn:1000004",
        "tgn:7000198",
        "tgn:7001797",
        "tgn:7029392"
    ],
    "tgn:id":7545283,
    "tgn:name:en":"Bhav\u0101n\u012bs\u0101gar Reservoir",
    "tgn:placetype":[
        "aat:300006191"
    ]
},
  "bbox": [],
  "geometry": {"coordinates":[77.083333,11.416667],"type":"Point"}
}