{
  "id": 2144740,
  "type": "Feature",
  "properties": {
    "tgn:hierarchy":[
        "tgn:2144740",
        "tgn:1000001",
        "tgn:2000920",
        "tgn:7012149",
        "tgn:7007515",
        "tgn:7029392"
    ],
    "tgn:id":2144740,
    "tgn:name":"Bald Hill",
    "tgn:placetype":[
        "aat:300008798"
    ]
},
  "bbox": [],
  "geometry": {"coordinates":[-70.3167,44.0167],"type":"Point"}
}