{
  "id": 2132084,
  "type": "Feature",
  "properties": {
    "tgn:hierarchy":[
        "tgn:2132084",
        "tgn:1000001",
        "tgn:7012149",
        "tgn:7007157",
        "tgn:1002894",
        "tgn:7029392"
    ],
    "tgn:id":2132084,
    "tgn:name":"American Hill Mine",
    "tgn:placetype":[
        "aat:300000390"
    ]
},
  "bbox": [],
  "geometry": {"coordinates":[-120.75,39.4667],"type":"Point"}
}