{
  "id": 1093651,
  "type": "Feature",
  "properties": {
    "tgn:hierarchy":[
        "tgn:1093651",
        "tgn:7001242",
        "tgn:7017582",
        "tgn:1000193",
        "tgn:7029392"
    ],
    "tgn:id":1093651,
    "tgn:name":"Springfield",
    "tgn:placetype":[
        "aat:300008347"
    ]
},
  "bbox": [],
  "geometry": {"coordinates":[22.8833,-29.0333],"type":"Point"}
}