{
  "id": 7069292,
  "type": "Feature",
  "properties": {
    "tgn:hierarchy":[
        "tgn:7069292",
        "tgn:7003692",
        "tgn:1000003",
        "tgn:7000084",
        "tgn:7029392"
    ],
    "tgn:id":7069292,
    "tgn:name":"Tiefensall",
    "tgn:placetype":[
        "aat:300008347"
    ]
},
  "bbox": [],
  "geometry": {"coordinates":[9.541111,49.250278],"type":"Point"}
}