{
  "id": 2684944,
  "type": "Feature",
  "properties": {
    "tgn:hierarchy":[
        "tgn:2684944",
        "tgn:1000001",
        "tgn:7012149",
        "tgn:1002562",
        "tgn:7007251",
        "tgn:7029392"
    ],
    "tgn:id":2684944,
    "tgn:name":"Split Rock Lake",
    "tgn:placetype":[
        "aat:300008680"
    ]
},
  "bbox": [],
  "geometry": {"coordinates":[-89.05,41.3167],"type":"Point"}
}