{
  "id": 2681044,
  "type": "Feature",
  "properties": {
    "tgn:hierarchy":[
        "tgn:2681044",
        "tgn:1000001",
        "tgn:7012149",
        "tgn:1003038",
        "tgn:7007517",
        "tgn:7029392"
    ],
    "tgn:id":2681044,
    "tgn:name":"South Meadow Brook",
    "tgn:placetype":[
        "aat:300008699"
    ]
},
  "bbox": [],
  "geometry": {"coordinates":[-71.7333,42.4167],"type":"Point"}
}