{
  "id": 7048681,
  "type": "Feature",
  "properties": {
    "tgn:hierarchy":[
        "tgn:7048681",
        "tgn:1001724",
        "tgn:1000003",
        "tgn:7003121",
        "tgn:1000080",
        "tgn:7029392"
    ],
    "tgn:id":7048681,
    "tgn:name":"Ginepro, Cala",
    "tgn:placetype":[
        "aat:300132317"
    ]
},
  "bbox": [],
  "geometry": {"coordinates":[9.783333,40.433333],"type":"Point"}
}