{
  "id": 2711273,
  "type": "Feature",
  "properties": {
    "tgn:hierarchy":[
        "tgn:2711273",
        "tgn:1000001",
        "tgn:7012149",
        "tgn:2002027",
        "tgn:7007826",
        "tgn:7029392"
    ],
    "tgn:id":2711273,
    "tgn:name":"Tanque La Trampa Los Chivos",
    "tgn:placetype":[
        "aat:300006191"
    ]
},
  "bbox": [],
  "geometry": {"coordinates":[-98.8333,28.3833],"type":"Point"}
}