{
  "id": 2714591,
  "type": "Feature",
  "properties": {
    "tgn:hierarchy":[
        "tgn:2714591",
        "tgn:1000001",
        "tgn:7012149",
        "tgn:2001151",
        "tgn:7007522",
        "tgn:7029392"
    ],
    "tgn:id":2714591,
    "tgn:name":"Ten Mile",
    "tgn:placetype":[
        "aat:300008347"
    ]
},
  "bbox": [],
  "geometry": {"coordinates":[-89.1333,30.75],"type":"Point"}
}