{
  "id": 2380443,
  "type": "Feature",
  "properties": {
    "tgn:hierarchy":[
        "tgn:2380443",
        "tgn:1000001",
        "tgn:7012149",
        "tgn:7029392"
    ],
    "tgn:id":2380443,
    "tgn:name":"Haulover Inlet",
    "tgn:placetype":[
        "aat:300132316"
    ]
},
  "bbox": [],
  "geometry": {"coordinates":[-76.7667,38.1667],"type":"Point"}
}