{
  "id": 7591370,
  "type": "Feature",
  "properties": {
    "tgn:hierarchy":[
        "tgn:7591370",
        "tgn:1000004",
        "tgn:7000198",
        "tgn:7000799",
        "tgn:7029392"
    ],
    "tgn:id":7591370,
    "tgn:name:en":"B\u0101ne Chak",
    "tgn:placetype":[
        "aat:300008347"
    ]
},
  "bbox": [],
  "geometry": {"coordinates":[74.880556,32.602778],"type":"Point"}
}