{
  "id": 2449523,
  "type": "Feature",
  "properties": {
    "tgn:hierarchy":[
        "tgn:2449523",
        "tgn:1000001",
        "tgn:7012149",
        "tgn:2001442",
        "tgn:7007566",
        "tgn:7029392"
    ],
    "tgn:id":2449523,
    "tgn:name":"Lincoln Canyon Spring",
    "tgn:placetype":[
        "aat:300008697"
    ]
},
  "bbox": [],
  "geometry": {"coordinates":[-105.3667,33.5167],"type":"Point"}
}