{
  "id": 7282912,
  "type": "Feature",
  "properties": {
    "tgn:hierarchy":[
        "tgn:7282912",
        "tgn:1001695",
        "tgn:1000049",
        "tgn:1000002",
        "tgn:7029392"
    ],
    "tgn:id":7282912,
    "tgn:name":"Pelada, Loma",
    "tgn:placetype":[
        "aat:300008777"
    ]
},
  "bbox": [],
  "geometry": {"coordinates":[-71.883333,-34.216667],"type":"Point"}
}