{
  "id": 7563254,
  "type": "Feature",
  "properties": {
    "tgn:hierarchy":[
        "tgn:7563254",
        "tgn:1000004",
        "tgn:7000198",
        "tgn:7016722",
        "tgn:7029392"
    ],
    "tgn:id":7563254,
    "tgn:name:en":"R\u0101mnagar",
    "tgn:placetype":[
        "aat:300008347"
    ]
},
  "bbox": [],
  "geometry": {"coordinates":[79.302812,25.434497],"type":"Point"}
}