{
  "id": 2464460,
  "type": "Feature",
  "properties": {
    "tgn:hierarchy":[
        "tgn:2464460",
        "tgn:2001727",
        "tgn:1000001",
        "tgn:7012149",
        "tgn:7007712",
        "tgn:7029392"
    ],
    "tgn:id":2464460,
    "tgn:name":"Log Branch",
    "tgn:placetype":[
        "aat:300008699"
    ]
},
  "bbox": [],
  "geometry": {"coordinates":[-81.3333,33.05],"type":"Point"}
}