<<<<<<< HEAD
{
  "id": 7353380,
  "type": "Feature",
  "properties": {
    "tgn:hierarchy":[
        "tgn:7353380",
        "tgn:1000001",
        "tgn:7005595",
        "tgn:7005560",
        "tgn:7029392"
    ],
    "tgn:id":7353380,
    "tgn:name":"Bellavista",
    "tgn:placetype":[
        "aat:300008347"
    ]
},
  "bbox": [],
  "geometry": {"coordinates":[-107.464722,24.814444],"type":"Point"}
}
=======
{"geometry":{"type":"Point","coordinates":[-107.464722,24.814444]},"type":"Feature","properties":{"hierarchy":["tgn:7353380","tgn:1000001","tgn:7005595","tgn:7005560","tgn:7029392"],"placetype":["aat:300008347"],"id":7353380,"name:xx":"Bellavista"}}
>>>>>>> 03f74aca74312dbeaf24d7e61306dd6a786dc3d0
