{
  "id": 2528807,
  "type": "Feature",
  "properties": {
    "tgn:hierarchy":[
        "tgn:2528807",
        "tgn:1000001",
        "tgn:2000316",
        "tgn:7012149",
        "tgn:7007248",
        "tgn:7029392"
    ],
    "tgn:id":2528807,
    "tgn:name":"Mud Creek",
    "tgn:placetype":[
        "aat:300008706"
    ]
},
  "bbox": [],
  "geometry": {"coordinates":[-80.9833,32.05],"type":"Point"}
}