{
  "id": 2703216,
  "type": "Feature",
  "properties": {
    "tgn:hierarchy":[
        "tgn:2703216",
        "tgn:1000001",
        "tgn:7012149",
        "tgn:2001716",
        "tgn:7007708",
        "tgn:7029392"
    ],
    "tgn:id":2703216,
    "tgn:name":"Summers Creek",
    "tgn:placetype":[
        "aat:300008706"
    ]
},
  "bbox": [],
  "geometry": {"coordinates":[-123.75,44.25],"type":"Point"}
}