{
  "id": 7338292,
  "type": "Feature",
  "properties": {
    "tgn:hierarchy":[
        "tgn:7338292",
        "tgn:7002818",
        "tgn:1001647",
        "tgn:1000003",
        "tgn:1000095",
        "tgn:7029392"
    ],
    "tgn:id":7338292,
    "tgn:name":"Castillo de Garcimu\u00f1oz",
    "tgn:placetype":[
        "aat:300008347"
    ]
},
  "bbox": [],
  "geometry": {"coordinates":[-2.383333,39.65],"type":"Point"}
}