{
  "id": 2603957,
  "type": "Feature",
  "properties": {
    "tgn:hierarchy":[
        "tgn:2603957",
        "tgn:1000001",
        "tgn:7012149",
        "tgn:2001420",
        "tgn:7007526",
        "tgn:7029392"
    ],
    "tgn:id":2603957,
    "tgn:name":"Quincy Mine",
    "tgn:placetype":[
        "aat:300000390"
    ]
},
  "bbox": [],
  "geometry": {"coordinates":[-114.95,39.2333],"type":"Point"}
}