{
  "id": 2697293,
  "type": "Feature",
  "properties": {
    "tgn:hierarchy":[
        "tgn:2697293",
        "tgn:1000001",
        "tgn:7012149",
        "tgn:7007922",
        "tgn:7029392"
    ],
    "tgn:id":2697293,
    "tgn:name":"Stony Creek",
    "tgn:placetype":[
        "aat:300008706"
    ]
},
  "bbox": [],
  "geometry": {"coordinates":[-88.15,43.55],"type":"Point"}
}