{
  "id": 2236909,
  "type": "Feature",
  "properties": {
    "tgn:hierarchy":[
        "tgn:2236909",
        "tgn:1000001",
        "tgn:7012149",
        "tgn:7007157",
        "tgn:1002706",
        "tgn:7029392"
    ],
    "tgn:id":2236909,
    "tgn:name":"Chiles Valley",
    "tgn:placetype":[
        "aat:300055621"
    ]
},
  "bbox": [],
  "geometry": {"coordinates":[-122.3167,38.5167],"type":"Point"}
}