<<<<<<< HEAD
{
  "id": 2336195,
  "type": "Feature",
  "properties": {
    "tgn:hierarchy":[
        "tgn:2336195",
        "tgn:1000001",
        "tgn:7012149",
        "tgn:1002677",
        "tgn:7007251",
        "tgn:7029392"
    ],
    "tgn:id":2336195,
    "tgn:name":"Foster Pond",
    "tgn:placetype":[
        "aat:300008680"
    ]
},
  "bbox": [],
  "geometry": {"coordinates":[-90.2167,38.3],"type":"Point"}
}
=======
{"geometry":{"type":"Point","coordinates":[-90.216700,38.300000]},"type":"Feature","properties":{"hierarchy":["tgn:2336195","tgn:1000001","tgn:7012149","tgn:1002677","tgn:7007251","tgn:7029392"],"placetype":["aat:300008680"],"id":2336195,"name:xx":"Foster Pond"}}
>>>>>>> 03f74aca74312dbeaf24d7e61306dd6a786dc3d0
