{
  "id": 2134893,
  "type": "Feature",
  "properties": {
    "tgn:hierarchy":[
        "tgn:2134893",
        "tgn:1000001",
        "tgn:7012149",
        "tgn:2002379",
        "tgn:7007923",
        "tgn:7029392"
    ],
    "tgn:id":2134893,
    "tgn:name":"Antelope Mountain",
    "tgn:placetype":[
        "aat:300008798"
    ]
},
  "bbox": [],
  "geometry": {"coordinates":[-109.4333,44.7833],"type":"Point"}
}