{
  "id": 7585965,
  "type": "Feature",
  "properties": {
    "tgn:hierarchy":[
        "tgn:7585965",
        "tgn:1000004",
        "tgn:7000198",
        "tgn:7000799",
        "tgn:7029392"
    ],
    "tgn:id":7585965,
    "tgn:name:en":"Chhampur S\u0101npatw\u0101r",
    "tgn:placetype":[
        "aat:300008347"
    ]
},
  "bbox": [],
  "geometry": {"coordinates":[74.133333,34.483333],"type":"Point"}
}