<<<<<<< HEAD
{
  "id": 7365460,
  "type": "Feature",
  "properties": {
    "tgn:hierarchy":[
        "tgn:7365460",
        "tgn:7005581",
        "tgn:1000001",
        "tgn:7005560",
        "tgn:7029392"
    ],
    "tgn:id":7365460,
    "tgn:name":"Fresnos, Arroyo de los",
    "tgn:placetype":[
        "aat:300008699"
    ]
},
  "bbox": [],
  "geometry": {"coordinates":[-107.1,29.666667],"type":"Point"}
}
=======
{"geometry":{"type":"Point","coordinates":[-107.100000,29.666667]},"type":"Feature","properties":{"hierarchy":["tgn:7365460","tgn:7005581","tgn:1000001","tgn:7005560","tgn:7029392"],"placetype":["aat:300008699"],"id":7365460,"name:xx":"Fresnos, Arroyo de los"}}
>>>>>>> 03f74aca74312dbeaf24d7e61306dd6a786dc3d0
