<<<<<<< HEAD
{
  "id": 2255646,
  "type": "Feature",
  "properties": {
    "tgn:hierarchy":[
        "tgn:2255646",
        "tgn:1000001",
        "tgn:2001749",
        "tgn:7012149",
        "tgn:7007712",
        "tgn:7029392"
    ],
    "tgn:id":2255646,
    "tgn:name":"Copes Mill Pond",
    "tgn:placetype":[
        "aat:300006191"
    ]
},
  "bbox": [],
  "geometry": {"coordinates":[-81.0833,33.0],"type":"Point"}
}
=======
{"geometry":{"type":"Point","coordinates":[-81.083300,33.000000]},"type":"Feature","properties":{"hierarchy":["tgn:2255646","tgn:1000001","tgn:2001749","tgn:7012149","tgn:7007712","tgn:7029392"],"placetype":["aat:300006191"],"id":2255646,"name:xx":"Copes Mill Pond"}}
>>>>>>> 03f74aca74312dbeaf24d7e61306dd6a786dc3d0
