{
  "id": 2691217,
  "type": "Feature",
  "properties": {
    "tgn:hierarchy":[
        "tgn:2691217",
        "tgn:7002659",
        "tgn:1000001",
        "tgn:7012149",
        "tgn:2000047",
        "tgn:7029392"
    ],
    "tgn:id":2691217,
    "tgn:name":"Stapler Ford",
    "tgn:placetype":[
        "aat:300008347"
    ]
},
  "bbox": [],
  "geometry": {"coordinates":[-86.3333,34.5167],"type":"Point"}
}