{
  "id": 7155038,
  "type": "Feature",
  "properties": {
    "tgn:hierarchy":[
        "tgn:7155038",
        "tgn:1000003",
        "tgn:7003688",
        "tgn:7000084",
        "tgn:7029392"
    ],
    "tgn:id":7155038,
    "tgn:name":"Kirchhofswarft",
    "tgn:placetype":[
        "aat:300008347"
    ]
},
  "bbox": [],
  "geometry": {"coordinates":[8.55,54.633333],"type":"Point"}
}