<<<<<<< HEAD
{
  "id": 2333831,
  "type": "Feature",
  "properties": {
    "tgn:hierarchy":[
        "tgn:2333831",
        "tgn:1000001",
        "tgn:7012149",
        "tgn:2002381",
        "tgn:7007923",
        "tgn:7029392"
    ],
    "tgn:id":2333831,
    "tgn:name":"Forbes Draw",
    "tgn:placetype":[
        "aat:300008761"
    ]
},
  "bbox": [],
  "geometry": {"coordinates":[-107.0167,44.7333],"type":"Point"}
}
=======
{"geometry":{"type":"Point","coordinates":[-107.016700,44.733300]},"type":"Feature","properties":{"hierarchy":["tgn:2333831","tgn:1000001","tgn:7012149","tgn:2002381","tgn:7007923","tgn:7029392"],"placetype":["aat:300008761"],"id":2333831,"name:xx":"Forbes Draw"}}
>>>>>>> 03f74aca74312dbeaf24d7e61306dd6a786dc3d0
