<<<<<<< HEAD
{
  "id": 2768626,
  "type": "Feature",
  "properties": {
    "tgn:hierarchy":[
        "tgn:2768626",
        "tgn:1000001",
        "tgn:7019982",
        "tgn:7012149",
        "tgn:7007517",
        "tgn:7029392"
    ],
    "tgn:id":2768626,
    "tgn:name":"Whiting Peak",
    "tgn:placetype":[
        "aat:300008798"
    ]
},
  "bbox": [],
  "geometry": {"coordinates":[-72.6333,42.25],"type":"Point"}
}
=======
{"geometry":{"type":"Point","coordinates":[-72.633300,42.250000]},"type":"Feature","properties":{"hierarchy":["tgn:2768626","tgn:1000001","tgn:7019982","tgn:7012149","tgn:7007517","tgn:7029392"],"placetype":["aat:300008798"],"id":2768626,"name:xx":"Whiting Peak"}}
>>>>>>> 03f74aca74312dbeaf24d7e61306dd6a786dc3d0
