{
  "id": 2494237,
  "type": "Feature",
  "properties": {
    "tgn:hierarchy":[
        "tgn:2494237",
        "tgn:1000001",
        "tgn:2001366",
        "tgn:7012149",
        "tgn:7007525",
        "tgn:7029392"
    ],
    "tgn:id":2494237,
    "tgn:name":"Martin Bay",
    "tgn:placetype":[
        "aat:300132316"
    ]
},
  "bbox": [],
  "geometry": {"coordinates":[-101.6833,41.2333],"type":"Point"}
}