{
  "id": 2606778,
  "type": "Feature",
  "properties": {
    "tgn:hierarchy":[
        "tgn:2606778",
        "tgn:1000001",
        "tgn:7012149",
        "tgn:1002990",
        "tgn:7007708",
        "tgn:7029392"
    ],
    "tgn:id":2606778,
    "tgn:name":"Ramsey Creek",
    "tgn:placetype":[
        "aat:300008706"
    ]
},
  "bbox": [],
  "geometry": {"coordinates":[-121.45,45.3833],"type":"Point"}
}