{
  "id": 2287415,
  "type": "Feature",
  "properties": {
    "tgn:hierarchy":[
        "tgn:2287415",
        "tgn:1000001",
        "tgn:7012149",
        "tgn:7007157",
        "tgn:1002858",
        "tgn:7029392"
    ],
    "tgn:id":2287415,
    "tgn:name":"Dictionary Hill",
    "tgn:placetype":[
        "aat:300008798"
    ]
},
  "bbox": [],
  "geometry": {"coordinates":[-116.9833,32.7167],"type":"Point"}
}