{
  "id": 7586454,
  "type": "Feature",
  "properties": {
    "tgn:hierarchy":[
        "tgn:7586454",
        "tgn:1000004",
        "tgn:7000198",
        "tgn:7000799",
        "tgn:7029392"
    ],
    "tgn:id":7586454,
    "tgn:name:en":"Gangabal Forest",
    "tgn:placetype":[
        "aat:300008863"
    ]
},
  "bbox": [],
  "geometry": {"coordinates":[74.983333,34.388889],"type":"Point"}
}