{
  "id": 2162728,
  "type": "Feature",
  "properties": {
    "tgn:hierarchy":[
        "tgn:2162728",
        "tgn:1000001",
        "tgn:7012149",
        "tgn:7007568",
        "tgn:7029392"
    ],
    "tgn:id":2162728,
    "tgn:name":"Bender Creek",
    "tgn:placetype":[
        "aat:300008706"
    ]
},
  "bbox": [],
  "geometry": {"coordinates":[-78.45,42.7833],"type":"Point"}
}