{
  "id": 2642778,
  "type": "Feature",
  "properties": {
    "tgn:hierarchy":[
        "tgn:2642778",
        "tgn:1000001",
        "tgn:7016172",
        "tgn:7012149",
        "tgn:2000153",
        "tgn:7029392"
    ],
    "tgn:id":2642778,
    "tgn:name":"Sandlick Mountain",
    "tgn:placetype":[
        "aat:300008798"
    ]
},
  "bbox": [],
  "geometry": {"coordinates":[-93.4333,34.7333],"type":"Point"}
}