{
  "id": 2289050,
  "type": "Feature",
  "properties": {
    "tgn:hierarchy":[
        "tgn:2289050",
        "tgn:1000001",
        "tgn:2002109",
        "tgn:7012149",
        "tgn:7007827",
        "tgn:7029392"
    ],
    "tgn:id":2289050,
    "tgn:name":"Divide Canyon",
    "tgn:placetype":[
        "aat:300008761"
    ]
},
  "bbox": [],
  "geometry": {"coordinates":[-110.9667,37.95],"type":"Point"}
}