{
  "id": 2171407,
  "type": "Feature",
  "properties": {
    "tgn:hierarchy":[
        "tgn:2171407",
        "tgn:1000001",
        "tgn:2001021",
        "tgn:7012149",
        "tgn:7007521",
        "tgn:7029392"
    ],
    "tgn:id":2171407,
    "tgn:name":"Big Springs Creek",
    "tgn:placetype":[
        "aat:300008706"
    ]
},
  "bbox": [],
  "geometry": {"coordinates":[-91.95,43.8167],"type":"Point"}
}