{
  "id": 2665268,
  "type": "Feature",
  "properties": {
    "tgn:hierarchy":[
        "tgn:2665268",
        "tgn:1000001",
        "tgn:7012149",
        "tgn:1002552",
        "tgn:7007920",
        "tgn:7029392"
    ],
    "tgn:id":2665268,
    "tgn:name":"Sinclair Inlet",
    "tgn:placetype":[
        "aat:300132316"
    ]
},
  "bbox": [],
  "geometry": {"coordinates":[-122.6333,47.5333],"type":"Point"}
}