<<<<<<< HEAD
{
  "id": 2768656,
  "type": "Feature",
  "properties": {
    "tgn:hierarchy":[
        "tgn:2768656",
        "tgn:1000001",
        "tgn:7020680",
        "tgn:7012149",
        "tgn:7007256",
        "tgn:7029392"
    ],
    "tgn:id":2768656,
    "tgn:name":"Whitley",
    "tgn:placetype":[
        "aat:300008347"
    ]
},
  "bbox": [],
  "geometry": {"coordinates":[-93.9833,32.1667],"type":"Point"}
}
=======
{"geometry":{"type":"Point","coordinates":[-93.983300,32.166700]},"type":"Feature","properties":{"hierarchy":["tgn:2768656","tgn:1000001","tgn:7020680","tgn:7012149","tgn:7007256","tgn:7029392"],"placetype":["aat:300008347"],"id":2768656,"name:xx":"Whitley"}}
>>>>>>> 03f74aca74312dbeaf24d7e61306dd6a786dc3d0
