{
  "id": 7464838,
  "type": "Feature",
  "properties": {
    "tgn:hierarchy":[
        "tgn:7464838",
        "tgn:7002444",
        "tgn:1000003",
        "tgn:7008082",
        "tgn:7008591",
        "tgn:7029392"
    ],
    "tgn:id":7464838,
    "tgn:name:en":"Bracora",
    "tgn:placetype":[
        "aat:300008347"
    ]
},
  "bbox": [],
  "geometry": {"coordinates":[-5.766667,56.983333],"type":"Point"}
}