{
  "id": 2394219,
  "type": "Feature",
  "properties": {
    "tgn:hierarchy":[
        "tgn:2394219",
        "tgn:1000001",
        "tgn:7012149",
        "tgn:2001718",
        "tgn:7007708",
        "tgn:7029392"
    ],
    "tgn:id":2394219,
    "tgn:name":"Hogback",
    "tgn:placetype":[
        "aat:300266640"
    ]
},
  "bbox": [],
  "geometry": {"coordinates":[-117.25,42.65],"type":"Point"}
}