<<<<<<< HEAD
{
  "id": 7362634,
  "type": "Feature",
  "properties": {
    "tgn:hierarchy":[
        "tgn:7362634",
        "tgn:7005581",
        "tgn:1000001",
        "tgn:7005560",
        "tgn:7029392"
    ],
    "tgn:id":7362634,
    "tgn:name":"Rancho El Embarcadero",
    "tgn:placetype":[
        "aat:300000241"
    ]
},
  "bbox": [],
  "geometry": {"coordinates":[-105.566667,27.55],"type":"Point"}
}
=======
{"geometry":{"type":"Point","coordinates":[-105.566667,27.550000]},"type":"Feature","properties":{"hierarchy":["tgn:7362634","tgn:7005581","tgn:1000001","tgn:7005560","tgn:7029392"],"placetype":["aat:300000241"],"id":7362634,"name:xx":"Rancho El Embarcadero"}}
>>>>>>> 03f74aca74312dbeaf24d7e61306dd6a786dc3d0
