{
  "id": 7362634,
  "type": "Feature",
  "properties": {
    "tgn:hierarchy":[
        "tgn:7362634",
        "tgn:7005581",
        "tgn:1000001",
        "tgn:7005560",
        "tgn:7029392"
    ],
    "tgn:id":7362634,
    "tgn:name":"Rancho El Embarcadero",
    "tgn:placetype":[
        "aat:300000241"
    ]
},
  "bbox": [],
  "geometry": {"coordinates":[-105.566667,27.55],"type":"Point"}
}