{
  "id": 2407745,
  "type": "Feature",
  "properties": {
    "tgn:hierarchy":[
        "tgn:2407745",
        "tgn:1000001",
        "tgn:2000272",
        "tgn:7012149",
        "tgn:7007240",
        "tgn:7029392"
    ],
    "tgn:id":2407745,
    "tgn:name":"Hurricane Bay",
    "tgn:placetype":[
        "aat:300008905"
    ]
},
  "bbox": [],
  "geometry": {"coordinates":[-85.6167,30.8333],"type":"Point"}
}