<<<<<<< HEAD
{
  "id": 2407745,
  "type": "Feature",
  "properties": {
    "tgn:hierarchy":[
        "tgn:2407745",
        "tgn:1000001",
        "tgn:2000272",
        "tgn:7012149",
        "tgn:7007240",
        "tgn:7029392"
    ],
    "tgn:id":2407745,
    "tgn:name":"Hurricane Bay",
    "tgn:placetype":[
        "aat:300008905"
    ]
},
  "bbox": [],
  "geometry": {"coordinates":[-85.6167,30.8333],"type":"Point"}
}
=======
{"geometry":{"type":"Point","coordinates":[-85.616700,30.833300]},"type":"Feature","properties":{"hierarchy":["tgn:2407745","tgn:1000001","tgn:2000272","tgn:7012149","tgn:7007240","tgn:7029392"],"placetype":["aat:300008905"],"id":2407745,"name:xx":"Hurricane Bay"}}
>>>>>>> 03f74aca74312dbeaf24d7e61306dd6a786dc3d0
