{
  "id": 2356203,
  "type": "Feature",
  "properties": {
    "tgn:hierarchy":[
        "tgn:2356203",
        "tgn:1000001",
        "tgn:2001264",
        "tgn:7012149",
        "tgn:7007524",
        "tgn:7029392"
    ],
    "tgn:id":2356203,
    "tgn:name":"Gooseberry Hollow",
    "tgn:placetype":[
        "aat:300008761"
    ]
},
  "bbox": [],
  "geometry": {"coordinates":[-108.45,45.1167],"type":"Point"}
}