{
  "id": 1013741,
  "type": "Feature",
  "properties": {
    "tgn:hierarchy":[
        "tgn:1013741",
        "tgn:7005735",
        "tgn:7005685",
        "tgn:1000001",
        "tgn:7013409",
        "tgn:7029392"
    ],
    "tgn:id":1013741,
    "tgn:name":"Sayward",
    "tgn:placetype":[
        "aat:300008347"
    ]
},
  "bbox": [],
  "geometry": {"coordinates":[-125.9667,50.3167],"type":"Point"}
}