{
  "id": 2567046,
  "type": "Feature",
  "properties": {
    "tgn:hierarchy":[
        "tgn:2567046",
        "tgn:1000001",
        "tgn:7012149",
        "tgn:2001856",
        "tgn:7007825",
        "tgn:7029392"
    ],
    "tgn:id":2567046,
    "tgn:name":"Panther Creek",
    "tgn:placetype":[
        "aat:300008706"
    ]
},
  "bbox": [],
  "geometry": {"coordinates":[-88.2167,35.55],"type":"Point"}
}