{
  "id": 7272168,
  "type": "Feature",
  "properties": {
    "tgn:hierarchy":[
        "tgn:7272168",
        "tgn:7003616",
        "tgn:1000003",
        "tgn:7016845",
        "tgn:7029392"
    ],
    "tgn:id":7272168,
    "tgn:name:nl":"Stoekveld",
    "tgn:placetype":[
        "aat:300387200"
    ]
},
  "bbox": [],
  "geometry": {"coordinates":[5.916667,53.15],"type":"Point"}
}