{
  "id": 1015491,
  "type": "Feature",
  "properties": {
    "tgn:hierarchy":[
        "tgn:1015491",
        "tgn:7005685",
        "tgn:1000001",
        "tgn:7005804",
        "tgn:7029392"
    ],
    "tgn:id":1015491,
    "tgn:name":"Magog",
    "tgn:placetype":[
        "aat:300008347"
    ]
},
  "bbox": [],
  "geometry": {"coordinates":[-72.15,45.2667],"type":"Point"}
}