{
  "id": 7286139,
  "type": "Feature",
  "properties": {
    "tgn:hierarchy":[
        "tgn:7286139",
        "tgn:1001637",
        "tgn:1000049",
        "tgn:1000002",
        "tgn:7029392"
    ],
    "tgn:id":7286139,
    "tgn:name":"Hualpencillo",
    "tgn:placetype":[
        "aat:300008347"
    ]
},
  "bbox": [],
  "geometry": {"coordinates":[-73.083333,-36.783333],"type":"Point"}
}