<<<<<<< HEAD
{
  "id": 2159064,
  "type": "Feature",
  "properties": {
    "tgn:hierarchy":[
        "tgn:2159064",
        "tgn:1000001",
        "tgn:2000468",
        "tgn:7012149",
        "tgn:7007250",
        "tgn:7029392"
    ],
    "tgn:id":2159064,
    "tgn:name":"Bed Springs Butte",
    "tgn:placetype":[
        "aat:300008798"
    ]
},
  "bbox": [],
  "geometry": {"coordinates":[-112.1167,44.2667],"type":"Point"}
}
=======
{"geometry":{"type":"Point","coordinates":[-112.116700,44.266700]},"type":"Feature","properties":{"hierarchy":["tgn:2159064","tgn:1000001","tgn:2000468","tgn:7012149","tgn:7007250","tgn:7029392"],"placetype":["aat:300008798"],"id":2159064,"name:xx":"Bed Springs Butte"}}
>>>>>>> 03f74aca74312dbeaf24d7e61306dd6a786dc3d0
