{
  "id": 2159064,
  "type": "Feature",
  "properties": {
    "tgn:hierarchy":[
        "tgn:2159064",
        "tgn:1000001",
        "tgn:2000468",
        "tgn:7012149",
        "tgn:7007250",
        "tgn:7029392"
    ],
    "tgn:id":2159064,
    "tgn:name":"Bed Springs Butte",
    "tgn:placetype":[
        "aat:300008798"
    ]
},
  "bbox": [],
  "geometry": {"coordinates":[-112.1167,44.2667],"type":"Point"}
}