{
  "id": 7010524,
  "type": "Feature",
  "properties": {
    "tgn:hierarchy":[
        "tgn:7010524",
        "tgn:1000453",
        "tgn:1000003",
        "tgn:7006278",
        "tgn:7029392"
    ],
    "tgn:id":7010524,
    "tgn:name":"Tiszaf\u00fcred",
    "tgn:placetype":[
        "aat:300008347"
    ]
},
  "bbox": [],
  "geometry": {"coordinates":[20.75,47.6333],"type":"Point"}
}