{
  "id": 7417013,
  "type": "Feature",
  "properties": {
    "tgn:hierarchy":[
        "tgn:7417013",
        "tgn:1000001",
        "tgn:7005596",
        "tgn:7005560",
        "tgn:7029392"
    ],
    "tgn:id":7417013,
    "tgn:name:es":"General Pedro Colorado",
    "tgn:placetype":[
        "aat:300008347"
    ]
},
  "bbox": [],
  "geometry": {"coordinates":[-93.675,18.033333],"type":"Point"}
}