{
  "id": 7545365,
  "type": "Feature",
  "properties": {
    "tgn:hierarchy":[
        "tgn:7545365",
        "tgn:1000004",
        "tgn:7000198",
        "tgn:1001894",
        "tgn:7029392"
    ],
    "tgn:id":7545365,
    "tgn:name:en":"B\u0101ria",
    "tgn:placetype":[
        "aat:300008347"
    ]
},
  "bbox": [],
  "geometry": {"coordinates":[80.288433,22.321029],"type":"Point"}
}