<<<<<<< HEAD
{
  "id": 7474905,
  "type": "Feature",
  "properties": {
    "tgn:hierarchy":[
        "tgn:7474905",
        "tgn:1000004",
        "tgn:7001014",
        "tgn:1000141",
        "tgn:7029392"
    ],
    "tgn:id":7474905,
    "tgn:name":"Yangming Guoxiao",
    "tgn:placetype":[
        "aat:300006495"
    ]
},
  "bbox": [],
  "geometry": {"coordinates":[120.355756,23.78523],"type":"Point"}
}
=======
{"geometry":{"type":"Point","coordinates":[120.355756,23.785230]},"type":"Feature","properties":{"hierarchy":["tgn:7474905","tgn:1000004","tgn:7001014","tgn:1000141","tgn:7029392"],"placetype":["aat:300006495"],"id":7474905,"name:xx":"Yangming Guoxiao"}}
>>>>>>> 03f74aca74312dbeaf24d7e61306dd6a786dc3d0
