<<<<<<< HEAD
{
  "id": 7249295,
  "type": "Feature",
  "properties": {
    "tgn:hierarchy":[
        "tgn:7249295",
        "tgn:7007877",
        "tgn:1000003",
        "tgn:1000063",
        "tgn:4012014",
        "tgn:7029392"
    ],
    "tgn:id":7249295,
    "tgn:name":"Ferme Poireau",
    "tgn:placetype":[
        "aat:300000206"
    ]
},
  "bbox": [],
  "geometry": {"coordinates":[4.266667,50.316667],"type":"Point"}
}
=======
{"geometry":{"type":"Point","coordinates":[4.266667,50.316667]},"type":"Feature","properties":{"hierarchy":["tgn:7249295","tgn:7007877","tgn:1000003","tgn:1000063","tgn:4012014","tgn:7029392"],"placetype":["aat:300000206"],"id":7249295,"name:xx":"Ferme Poireau"}}
>>>>>>> 03f74aca74312dbeaf24d7e61306dd6a786dc3d0
