{
  "id": 2279747,
  "type": "Feature",
  "properties": {
    "tgn:hierarchy":[
        "tgn:2279747",
        "tgn:1000001",
        "tgn:7012149",
        "tgn:7007250",
        "tgn:7029392"
    ],
    "tgn:id":2279747,
    "tgn:name":"Deadwood Creek",
    "tgn:placetype":[
        "aat:300008706"
    ]
},
  "bbox": [],
  "geometry": {"coordinates":[-112.4333,42.5167],"type":"Point"}
}