{
  "id": 2759788,
  "type": "Feature",
  "properties": {
    "tgn:hierarchy":[
        "tgn:2759788",
        "tgn:1000001",
        "tgn:7012149",
        "tgn:1002392",
        "tgn:7007157",
        "tgn:7029392"
    ],
    "tgn:id":2759788,
    "tgn:name":"West Fork Kennedy Creek",
    "tgn:placetype":[
        "aat:300008706"
    ]
},
  "bbox": [],
  "geometry": {"coordinates":[-118.65,36.8833],"type":"Point"}
}