{
  "id": 7139914,
  "type": "Feature",
  "properties": {
    "tgn:hierarchy":[
        "tgn:7139914",
        "tgn:1000003",
        "tgn:7000094",
        "tgn:7000084",
        "tgn:7029392"
    ],
    "tgn:id":7139914,
    "tgn:name":"Lauen",
    "tgn:placetype":[
        "aat:300008347"
    ]
},
  "bbox": [],
  "geometry": {"coordinates":[10.816667,53.883333],"type":"Point"}
}