<<<<<<< HEAD
{
  "id": 7174189,
  "type": "Feature",
  "properties": {
    "tgn:hierarchy":[
        "tgn:7174189",
        "tgn:1000003",
        "tgn:7003677",
        "tgn:7000084",
        "tgn:7029392"
    ],
    "tgn:id":7174189,
    "tgn:name":"Groppel",
    "tgn:placetype":[
        "aat:300387200"
    ]
},
  "bbox": [],
  "geometry": {"coordinates":[8.25,51.9],"type":"Point"}
}
=======
{"geometry":{"type":"Point","coordinates":[8.250000,51.900000]},"type":"Feature","properties":{"hierarchy":["tgn:7174189","tgn:1000003","tgn:7003677","tgn:7000084","tgn:7029392"],"placetype":["aat:300387200"],"id":7174189,"name:xx":"Groppel"}}
>>>>>>> 03f74aca74312dbeaf24d7e61306dd6a786dc3d0
