<<<<<<< HEAD
{
  "id": 7020258,
  "type": "Feature",
  "properties": {
    "tgn:hierarchy":[
        "tgn:7020258",
        "tgn:1000001",
        "tgn:7012149",
        "tgn:2001502",
        "tgn:7007709",
        "tgn:7029392"
    ],
    "tgn:id":7020258,
    "tgn:name":"Horse Pen Branch",
    "tgn:placetype":[
        "aat:300008699"
    ]
},
  "bbox": [],
  "geometry": {"coordinates":[-78.95,35.3167],"type":"Point"}
}
=======
{"geometry":{"type":"Point","coordinates":[-78.950000,35.316700]},"type":"Feature","properties":{"hierarchy":["tgn:7020258","tgn:1000001","tgn:7012149","tgn:2001502","tgn:7007709","tgn:7029392"],"placetype":["aat:300008699"],"id":7020258,"name:xx":"Horse Pen Branch"}}
>>>>>>> 03f74aca74312dbeaf24d7e61306dd6a786dc3d0
