{
  "id": 7431874,
  "type": "Feature",
  "properties": {
    "tgn:hierarchy":[
        "tgn:7431874",
        "tgn:7005583",
        "tgn:1000001",
        "tgn:7005560",
        "tgn:7029392"
    ],
    "tgn:id":7431874,
    "tgn:name":"San Juan de Ca\u00f1itas",
    "tgn:placetype":[
        "aat:300008347"
    ]
},
  "bbox": [],
  "geometry": {"coordinates":[-104.15,26.633333],"type":"Point"}
}