{
  "id": 2376443,
  "type": "Feature",
  "properties": {
    "tgn:hierarchy":[
        "tgn:2376443",
        "tgn:1000001",
        "tgn:7012149",
        "tgn:2002385",
        "tgn:7007923",
        "tgn:7029392"
    ],
    "tgn:id":2376443,
    "tgn:name":"Harding Hollow",
    "tgn:placetype":[
        "aat:300008761"
    ]
},
  "bbox": [],
  "geometry": {"coordinates":[-110.9333,41.0833],"type":"Point"}
}