{
  "id": 7286613,
  "type": "Feature",
  "properties": {
    "tgn:hierarchy":[
        "tgn:7286613",
        "tgn:1001708",
        "tgn:1000049",
        "tgn:1000002",
        "tgn:7029392"
    ],
    "tgn:id":7286613,
    "tgn:name":"Guindo, Loma del",
    "tgn:placetype":[
        "aat:300387002"
    ]
},
  "bbox": [],
  "geometry": {"coordinates":[-71.216667,-33.466667],"type":"Point"}
}