{
  "id": 7022303,
  "type": "Feature",
  "properties": {
    "tgn:hierarchy":[
        "tgn:7022303",
        "tgn:1000001",
        "tgn:7012149",
        "tgn:7007255",
        "tgn:7029392"
    ],
    "tgn:id":7022303,
    "tgn:name":"Arnold Fork",
    "tgn:placetype":[
        "aat:300008699"
    ]
},
  "bbox": [],
  "geometry": {"coordinates":[-82.7167,37.2833],"type":"Point"}
}