{
  "id": 7188242,
  "type": "Feature",
  "properties": {
    "tgn:hierarchy":[
        "tgn:7188242",
        "tgn:7003669",
        "tgn:1000003",
        "tgn:7000084",
        "tgn:7029392"
    ],
    "tgn:id":7188242,
    "tgn:name":"Esterthal",
    "tgn:placetype":[
        "aat:300000206"
    ]
},
  "bbox": [],
  "geometry": {"coordinates":[12.433333,48.733333],"type":"Point"}
}