{
  "id": 7574687,
  "type": "Feature",
  "properties": {
    "tgn:hierarchy":[
        "tgn:7574687",
        "tgn:1000004",
        "tgn:7000198",
        "tgn:7016722",
        "tgn:7029392"
    ],
    "tgn:id":7574687,
    "tgn:name:en":"Kureji",
    "tgn:placetype":[
        "aat:300008347"
    ]
},
  "bbox": [],
  "geometry": {"coordinates":[83.996263,25.857532],"type":"Point"}
}