{
  "id": 2246335,
  "type": "Feature",
  "properties": {
    "tgn:hierarchy":[
        "tgn:2246335",
        "tgn:1000001",
        "tgn:7012149",
        "tgn:2002116",
        "tgn:7007827",
        "tgn:7029392"
    ],
    "tgn:id":2246335,
    "tgn:name":"Coates Hollow",
    "tgn:placetype":[
        "aat:300008761"
    ]
},
  "bbox": [],
  "geometry": {"coordinates":[-112.1167,38.15],"type":"Point"}
}