{
  "id": 2545550,
  "type": "Feature",
  "properties": {
    "tgn:hierarchy":[
        "tgn:2545550",
        "tgn:1000001",
        "tgn:7012149",
        "tgn:2001304",
        "tgn:7007524",
        "tgn:7029392"
    ],
    "tgn:id":2545550,
    "tgn:name":"North Fork Bull River",
    "tgn:placetype":[
        "aat:300008707"
    ]
},
  "bbox": [],
  "geometry": {"coordinates":[-115.6833,48.2167],"type":"Point"}
}