<<<<<<< HEAD
{
  "id": 7376829,
  "type": "Feature",
  "properties": {
    "tgn:hierarchy":[
        "tgn:7376829",
        "tgn:7005581",
        "tgn:1000001",
        "tgn:7005560",
        "tgn:7029392"
    ],
    "tgn:id":7376829,
    "tgn:name":"La Parida",
    "tgn:placetype":[
        "aat:300008347"
    ]
},
  "bbox": [],
  "geometry": {"coordinates":[-106.6,26.866667],"type":"Point"}
}
=======
{"geometry":{"type":"Point","coordinates":[-106.600000,26.866667]},"type":"Feature","properties":{"hierarchy":["tgn:7376829","tgn:7005581","tgn:1000001","tgn:7005560","tgn:7029392"],"placetype":["aat:300008347"],"id":7376829,"name:xx":"La Parida"}}
>>>>>>> 03f74aca74312dbeaf24d7e61306dd6a786dc3d0
