{
  "id": 2580548,
  "type": "Feature",
  "properties": {
    "tgn:hierarchy":[
        "tgn:2580548",
        "tgn:1000001",
        "tgn:1002284",
        "tgn:7012149",
        "tgn:7007568",
        "tgn:7029392"
    ],
    "tgn:id":2580548,
    "tgn:name":"Pigeon Hill",
    "tgn:placetype":[
        "aat:300008798"
    ]
},
  "bbox": [],
  "geometry": {"coordinates":[-73.6667,44.4667],"type":"Point"}
}