{
  "id": 2369005,
  "type": "Feature",
  "properties": {
    "tgn:hierarchy":[
        "tgn:2369005",
        "tgn:1000001",
        "tgn:7012149",
        "tgn:1002464",
        "tgn:7007826",
        "tgn:7029392"
    ],
    "tgn:id":2369005,
    "tgn:name":"Gum Branch",
    "tgn:placetype":[
        "aat:300008699"
    ]
},
  "bbox": [],
  "geometry": {"coordinates":[-95.5167,32.2333],"type":"Point"}
}