{
  "id": 2576845,
  "type": "Feature",
  "properties": {
    "tgn:hierarchy":[
        "tgn:2576845",
        "tgn:1000001",
        "tgn:2002109",
        "tgn:7012149",
        "tgn:7007827",
        "tgn:7029392"
    ],
    "tgn:id":2576845,
    "tgn:name":"Pet Hollow",
    "tgn:placetype":[
        "aat:300008761"
    ]
},
  "bbox": [],
  "geometry": {"coordinates":[-111.7667,37.65],"type":"Point"}
}