{
  "id": 7033597,
  "type": "Feature",
  "properties": {
    "tgn:hierarchy":[
        "tgn:7033597",
        "tgn:7003127",
        "tgn:1000003",
        "tgn:7008516",
        "tgn:1000080",
        "tgn:7029392"
    ],
    "tgn:id":7033597,
    "tgn:name":"Carraie",
    "tgn:placetype":[
        "aat:300008347"
    ]
},
  "bbox": [],
  "geometry": {"coordinates":[12.188056,44.310556],"type":"Point"}
}