{
  "id": 7271326,
  "type": "Feature",
  "properties": {
    "tgn:concordances":{
        "gn:id":"2747516"
    },
    "tgn:hierarchy":[
        "tgn:7271326",
        "tgn:1000003",
        "tgn:7003635",
        "tgn:7016845",
        "tgn:7029392"
    ],
    "tgn:id":7271326,
    "tgn:name:nl":"Schoondorp",
    "tgn:placetype":[
        "aat:300008347"
    ]
},
  "bbox": [],
  "geometry": {"coordinates":[4.15,51.533333],"type":"Point"}
}