{
  "id": 7558225,
  "type": "Feature",
  "properties": {
    "tgn:hierarchy":[
        "tgn:7558225",
        "tgn:1000004",
        "tgn:7000198",
        "tgn:1001996",
        "tgn:7029392"
    ],
    "tgn:id":7558225,
    "tgn:name:en":"S\u0101ngla",
    "tgn:placetype":[
        "aat:300008347"
    ]
},
  "bbox": [],
  "geometry": {"coordinates":[78.272522,31.419099],"type":"Point"}
}