{
  "id": 1103103,
  "type": "Feature",
  "properties": {
    "tgn:hierarchy":[
        "tgn:1103103",
        "tgn:7003712",
        "tgn:1005101",
        "tgn:7069166",
        "tgn:7003670",
        "tgn:1000003",
        "tgn:7000084",
        "tgn:7029392"
    ],
    "tgn:id":1103103,
    "tgn:name":"Tiergarten",
    "tgn:placetype":[
        "aat:300008187"
    ]
},
  "bbox": [],
  "geometry": {"coordinates":[13.35,52.5167],"type":"Point"}
}