{
  "id": 7462819,
  "type": "Feature",
  "properties": {
    "tgn:hierarchy":[
        "tgn:7462819",
        "tgn:7002445",
        "tgn:1000003",
        "tgn:7008166",
        "tgn:7008591",
        "tgn:7029392"
    ],
    "tgn:id":7462819,
    "tgn:name:en":"Kirby Sigston",
    "tgn:placetype":[
        "aat:300008347"
    ]
},
  "bbox": [],
  "geometry": {"coordinates":[-1.35,54.35],"type":"Point"}
}