{
  "id": 7592091,
  "type": "Feature",
  "properties": {
    "tgn:hierarchy":[
        "tgn:7592091",
        "tgn:1000004",
        "tgn:7000198",
        "tgn:7031786",
        "tgn:7029392"
    ],
    "tgn:id":7592091,
    "tgn:name:en":"Prithvipur Branch",
    "tgn:placetype":[
        "aat:300006075"
    ]
},
  "bbox": [],
  "geometry": {"coordinates":[77.777841,30.420419],"type":"Point"}
}