{
  "id": 7500572,
  "type": "Feature",
  "properties": {
    "tgn:hierarchy":[
        "tgn:7500572",
        "tgn:1000957",
        "tgn:1000004",
        "tgn:1000141",
        "tgn:7029392"
    ],
    "tgn:id":7500572,
    "tgn:name":"Baimiweng Shan",
    "tgn:placetype":[
        "aat:300008777"
    ]
},
  "bbox": [],
  "geometry": {"coordinates":[121.733333,25.15],"type":"Point"}
}