{
  "id": 2294112,
  "type": "Feature",
  "properties": {
    "tgn:hierarchy":[
        "tgn:2294112",
        "tgn:1000001",
        "tgn:7012149",
        "tgn:2000893",
        "tgn:7007256",
        "tgn:7029392"
    ],
    "tgn:id":2294112,
    "tgn:name":"Dove Landing",
    "tgn:placetype":[
        "aat:300008347"
    ]
},
  "bbox": [],
  "geometry": {"coordinates":[-92.4667,30.95],"type":"Point"}
}