{
  "id": 7488338,
  "type": "Feature",
  "properties": {
    "tgn:hierarchy":[
        "tgn:7488338",
        "tgn:1000004",
        "tgn:7491221",
        "tgn:1000141",
        "tgn:7029392"
    ],
    "tgn:id":7488338,
    "tgn:name":"Lijia Xi",
    "tgn:placetype":[
        "aat:300008699"
    ]
},
  "bbox": [],
  "geometry": {"coordinates":[121.105833,22.707778],"type":"Point"}
}