{
  "id": 2702958,
  "type": "Feature",
  "properties": {
    "tgn:hierarchy":[
        "tgn:2702958",
        "tgn:1000001",
        "tgn:7012149",
        "tgn:7015666",
        "tgn:7007825",
        "tgn:7029392"
    ],
    "tgn:id":2702958,
    "tgn:name":"Sulphur Springs",
    "tgn:placetype":[
        "aat:300008347"
    ]
},
  "bbox": [],
  "geometry": {"coordinates":[-87.6167,35.7333],"type":"Point"}
}