{
  "id": 2748217,
  "type": "Feature",
  "properties": {
    "tgn:hierarchy":[
        "tgn:2748217",
        "tgn:1000001",
        "tgn:7012149",
        "tgn:2001917",
        "tgn:7007825",
        "tgn:7029392"
    ],
    "tgn:id":2748217,
    "tgn:name":"Walker Branch",
    "tgn:placetype":[
        "aat:300008699"
    ]
},
  "bbox": [],
  "geometry": {"coordinates":[-87.8667,36.5833],"type":"Point"}
}