{
  "id": 2057289,
  "type": "Feature",
  "properties": {
    "tgn:hierarchy":[
        "tgn:2057289",
        "tgn:1000001",
        "tgn:7012149",
        "tgn:2001118",
        "tgn:7007522",
        "tgn:7029392"
    ],
    "tgn:id":2057289,
    "tgn:name":"Prentiss",
    "tgn:placetype":[
        "aat:300008347",
        "aat:300008416"
    ]
},
  "bbox": [],
  "geometry": {"coordinates":[-89.8667,31.5833],"type":"Point"}
}