{
  "id": 2569118,
  "type": "Feature",
  "properties": {
    "tgn:hierarchy":[
        "tgn:2569118",
        "tgn:1000001",
        "tgn:7012149",
        "tgn:2000413",
        "tgn:7007248",
        "tgn:7029392"
    ],
    "tgn:id":2569118,
    "tgn:name":"Parkers Lake",
    "tgn:placetype":[
        "aat:300008680"
    ]
},
  "bbox": [],
  "geometry": {"coordinates":[-83.9333,33.75],"type":"Point"}
}