{
  "id": 7449442,
  "type": "Feature",
  "properties": {
    "tgn:hierarchy":[
        "tgn:7449442",
        "tgn:7002444",
        "tgn:1000003",
        "tgn:7008094",
        "tgn:7008591",
        "tgn:7029392"
    ],
    "tgn:id":7449442,
    "tgn:name:en":"Floddaybeg",
    "tgn:placetype":[
        "aat:300008791"
    ]
},
  "bbox": [],
  "geometry": {"coordinates":[-7.15,57.516667],"type":"Point"}
}