{
  "id": 2247891,
  "type": "Feature",
  "properties": {
    "tgn:hierarchy":[
        "tgn:2247891",
        "tgn:1000001",
        "tgn:7016172",
        "tgn:7012149",
        "tgn:7029392"
    ],
    "tgn:id":2247891,
    "tgn:name":"Coker Hollow",
    "tgn:placetype":[
        "aat:300008761"
    ]
},
  "bbox": [],
  "geometry": {"coordinates":[-92.8833,36.2833],"type":"Point"}
}