{
  "id": 1070513,
  "type": "Feature",
  "properties": {
    "tgn:hierarchy":[
        "tgn:1070513",
        "tgn:1000004",
        "tgn:7018118",
        "tgn:1000111",
        "tgn:7029392"
    ],
    "tgn:id":1070513,
    "tgn:name":"Mojiang",
    "tgn:placetype":[
        "aat:300008347"
    ]
},
  "bbox": [],
  "geometry": {"coordinates":[101.6667,23.45],"type":"Point"}
}