{
  "id": 4007816,
  "type": "Feature",
  "properties": {
    "tgn:hierarchy":[
        "tgn:4007816",
        "tgn:7002445",
        "tgn:1000003",
        "tgn:7029506",
        "tgn:7008591",
        "tgn:7029392"
    ],
    "tgn:id":4007816,
    "tgn:name":"New Oscott",
    "tgn:placetype":[
        "aat:300008347"
    ]
},
  "bbox": [],
  "geometry": {"coordinates":[-1.856,52.543],"type":"Point"}
}