{
  "id": 2749750,
  "type": "Feature",
  "properties": {
    "tgn:hierarchy":[
        "tgn:2749750",
        "tgn:1002176",
        "tgn:1000001",
        "tgn:7012149",
        "tgn:7007828",
        "tgn:7029392"
    ],
    "tgn:id":2749750,
    "tgn:name":"Walnut Hill",
    "tgn:placetype":[
        "aat:300008798"
    ]
},
  "bbox": [],
  "geometry": {"coordinates":[-73.2333,43.1667],"type":"Point"}
}