{
  "id": 2299863,
  "type": "Feature",
  "properties": {
    "tgn:hierarchy":[
        "tgn:2299863",
        "tgn:1000001",
        "tgn:7012149",
        "tgn:7007157",
        "tgn:1002608",
        "tgn:7029392"
    ],
    "tgn:id":2299863,
    "tgn:name":"Dudmore",
    "tgn:placetype":[
        "aat:300008347"
    ]
},
  "bbox": [],
  "geometry": {"coordinates":[-118.35,33.85],"type":"Point"}
}