{
  "id": 7172836,
  "type": "Feature",
  "properties": {
    "tgn:hierarchy":[
        "tgn:7172836",
        "tgn:1000003",
        "tgn:7003682",
        "tgn:7000084",
        "tgn:7029392"
    ],
    "tgn:id":7172836,
    "tgn:name":"Gro\u00dfe H\u00f6chst",
    "tgn:placetype":[
        "aat:300266640"
    ]
},
  "bbox": [],
  "geometry": {"coordinates":[7.65,49.083333],"type":"Point"}
}