<<<<<<< HEAD
{
  "id": 7059838,
  "type": "Feature",
  "properties": {
    "tgn:hierarchy":[
        "tgn:7059838",
        "tgn:7003669",
        "tgn:1000003",
        "tgn:7000084",
        "tgn:7029392"
    ],
    "tgn:id":7059838,
    "tgn:name":"Allerberg",
    "tgn:placetype":[
        "aat:300000206"
    ]
},
  "bbox": [],
  "geometry": {"coordinates":[12.783333,47.833333],"type":"Point"}
}
=======
{"geometry":{"type":"Point","coordinates":[12.783333,47.833333]},"type":"Feature","properties":{"hierarchy":["tgn:7059838","tgn:7003669","tgn:1000003","tgn:7000084","tgn:7029392"],"placetype":["aat:300000206"],"id":7059838,"name:xx":"Allerberg"}}
>>>>>>> 03f74aca74312dbeaf24d7e61306dd6a786dc3d0
