{
  "id": 2684634,
  "type": "Feature",
  "properties": {
    "tgn:hierarchy":[
        "tgn:2684634",
        "tgn:1000001",
        "tgn:7012149",
        "tgn:2000494",
        "tgn:7007250",
        "tgn:7029392"
    ],
    "tgn:id":2684634,
    "tgn:name":"Spink Barker Ditch",
    "tgn:placetype":[
        "aat:300006075"
    ]
},
  "bbox": [],
  "geometry": {"coordinates":[-116.05,44.8333],"type":"Point"}
}