{
  "id": 7538938,
  "type": "Feature",
  "properties": {
    "tgn:hierarchy":[
        "tgn:7538938",
        "tgn:7001242",
        "tgn:7016833",
        "tgn:1001418",
        "tgn:7029392"
    ],
    "tgn:id":7538938,
    "tgn:name:en":"S\u0101niyat as Sab\u012bl",
    "tgn:placetype":[
        "aat:300006207"
    ]
},
  "bbox": [],
  "geometry": {"coordinates":[25.578475,31.305026],"type":"Point"}
}