{
  "id": 7470505,
  "type": "Feature",
  "properties": {
    "tgn:hierarchy":[
        "tgn:7470505",
        "tgn:1000004",
        "tgn:7471332",
        "tgn:1000141",
        "tgn:7029392"
    ],
    "tgn:id":7470505,
    "tgn:name":"Jiujiabu",
    "tgn:placetype":[
        "aat:300008347"
    ]
},
  "bbox": [],
  "geometry": {"coordinates":[121.006944,24.807778],"type":"Point"}
}