{
  "id": 2412633,
  "type": "Feature",
  "properties": {
    "tgn:hierarchy":[
        "tgn:2412633",
        "tgn:2000934",
        "tgn:1000001",
        "tgn:7012149",
        "tgn:7007516",
        "tgn:7029392"
    ],
    "tgn:id":2412633,
    "tgn:name":"Indigo Tunnel",
    "tgn:placetype":[
        "aat:300006191"
    ]
},
  "bbox": [],
  "geometry": {"coordinates":[-78.3667,39.6333],"type":"Point"}
}