{
  "id": 2345337,
  "type": "Feature",
  "properties": {
    "tgn:hierarchy":[
        "tgn:2345337",
        "tgn:1000001",
        "tgn:2000319",
        "tgn:7012149",
        "tgn:7007248",
        "tgn:7029392"
    ],
    "tgn:id":2345337,
    "tgn:name":"Garland Mountain",
    "tgn:placetype":[
        "aat:300008798"
    ]
},
  "bbox": [],
  "geometry": {"coordinates":[-84.5833,34.35],"type":"Point"}
}