{
  "id": 2273684,
  "type": "Feature",
  "properties": {
    "tgn:hierarchy":[
        "tgn:2273684",
        "tgn:1000001",
        "tgn:7012149",
        "tgn:7007157",
        "tgn:2000186",
        "tgn:7029392"
    ],
    "tgn:id":2273684,
    "tgn:name":"D Flourney",
    "tgn:placetype":[
        "aat:300008347"
    ]
},
  "bbox": [],
  "geometry": {"coordinates":[-120.5167,41.2333],"type":"Point"}
}