{
  "id": 1118879,
  "type": "Feature",
  "properties": {
    "tgn:hierarchy":[
        "tgn:1118879",
        "tgn:1000003",
        "tgn:7003632",
        "tgn:7016845",
        "tgn:7029392"
    ],
    "tgn:id":1118879,
    "tgn:name":"Westeinder Plassen",
    "tgn:placetype":[
        "aat:300008680"
    ]
},
  "bbox": [],
  "geometry": {"coordinates":[4.733333,52.25],"type":"Point"}
}