<<<<<<< HEAD
{
  "id": 7379192,
  "type": "Feature",
  "properties": {
    "tgn:hierarchy":[
        "tgn:7379192",
        "tgn:7016644",
        "tgn:1000001",
        "tgn:7005560",
        "tgn:7029392"
    ],
    "tgn:id":7379192,
    "tgn:name":"Los Colomos",
    "tgn:placetype":[
        "aat:300008347"
    ]
},
  "bbox": [],
  "geometry": {"coordinates":[-103.75,19.4],"type":"Point"}
}
=======
{"geometry":{"type":"Point","coordinates":[-103.750000,19.400000]},"type":"Feature","properties":{"hierarchy":["tgn:7379192","tgn:7016644","tgn:1000001","tgn:7005560","tgn:7029392"],"placetype":["aat:300008347"],"id":7379192,"name:xx":"Los Colomos"}}
>>>>>>> 03f74aca74312dbeaf24d7e61306dd6a786dc3d0
