<<<<<<< HEAD
{
  "id": 7024446,
  "type": "Feature",
  "properties": {
    "tgn:hierarchy":[
        "tgn:7024446",
        "tgn:1000003",
        "tgn:1000070",
        "tgn:7029392"
    ],
    "tgn:id":7024446,
    "tgn:name":"Canal du Midi",
    "tgn:placetype":[
        "aat:300006075",
        "aat:300263063"
    ]
},
  "bbox": [],
  "geometry": {"coordinates":[1.9667,43.4333],"type":"Point"}
}
=======
{"geometry":{"type":"Point","coordinates":[1.966700,43.433300]},"type":"Feature","properties":{"hierarchy":["tgn:7024446","tgn:1000003","tgn:1000070","tgn:7029392"],"placetype":["aat:300006075","aat:300263063"],"id":7024446,"name:xx":"Canal du Midi"}}
>>>>>>> 03f74aca74312dbeaf24d7e61306dd6a786dc3d0
