{
  "id": 1091366,
  "type": "Feature",
  "properties": {
    "tgn:hierarchy":[
        "tgn:1091366",
        "tgn:7001242",
        "tgn:1000179",
        "tgn:7593686",
        "tgn:7029392"
    ],
    "tgn:id":1091366,
    "tgn:name":"Boumalne",
    "tgn:placetype":[
        "aat:300008347"
    ]
},
  "bbox": [],
  "geometry": {"coordinates":[-5.45,31.5333],"type":"Point"}
}