{
  "id": 2482128,
  "type": "Feature",
  "properties": {
    "tgn:hierarchy":[
        "tgn:2482128",
        "tgn:1000001",
        "tgn:2001742",
        "tgn:7012149",
        "tgn:7007712",
        "tgn:7029392"
    ],
    "tgn:id":2482128,
    "tgn:name":"Lang Branch",
    "tgn:placetype":[
        "aat:300008699"
    ]
},
  "bbox": [],
  "geometry": {"coordinates":[-80.3833,33.1333],"type":"Point"}
}