{
  "id": 7110602,
  "type": "Feature",
  "properties": {
    "tgn:hierarchy":[
        "tgn:7110602",
        "tgn:7003669",
        "tgn:1000003",
        "tgn:7000084",
        "tgn:7029392"
    ],
    "tgn:id":7110602,
    "tgn:name":"Rain",
    "tgn:placetype":[
        "aat:300008347"
    ]
},
  "bbox": [],
  "geometry": {"coordinates":[11.833333,47.75],"type":"Point"}
}