{
  "id": 2263356,
  "type": "Feature",
  "properties": {
    "tgn:hierarchy":[
        "tgn:2263356",
        "tgn:1000001",
        "tgn:1002283",
        "tgn:7012149",
        "tgn:7007520",
        "tgn:7029392"
    ],
    "tgn:id":2263356,
    "tgn:name":"Cox Drain",
    "tgn:placetype":[
        "aat:300006075"
    ]
},
  "bbox": [],
  "geometry": {"coordinates":[-84.6667,43.0833],"type":"Point"}
}