{
  "id": 7241189,
  "type": "Feature",
  "properties": {
    "tgn:hierarchy":[
        "tgn:7241189",
        "tgn:7003456",
        "tgn:1000003",
        "tgn:1000063",
        "tgn:7018236",
        "tgn:7029392"
    ],
    "tgn:id":7241189,
    "tgn:name":"Laakbeek",
    "tgn:placetype":[
        "aat:300008699"
    ]
},
  "bbox": [],
  "geometry": {"coordinates":[4.853641,51.225305],"type":"Point"}
}