{
  "id": 7274266,
  "type": "Feature",
  "properties": {
    "tgn:hierarchy":[
        "tgn:7274266",
        "tgn:1000003",
        "tgn:7003613",
        "tgn:7016845",
        "tgn:7029392"
    ],
    "tgn:id":7274266,
    "tgn:name:nl":"Zuidhorner Zuidertocht",
    "tgn:placetype":[
        "aat:300006075"
    ]
},
  "bbox": [],
  "geometry": {"coordinates":[6.416667,53.216667],"type":"Point"}
}