<<<<<<< HEAD
{
  "id": 2339977,
  "type": "Feature",
  "properties": {
    "tgn:hierarchy":[
        "tgn:2339977",
        "tgn:1000001",
        "tgn:7012149",
        "tgn:1002708",
        "tgn:7007568",
        "tgn:7029392"
    ],
    "tgn:id":2339977,
    "tgn:name":"Freeport Creek",
    "tgn:placetype":[
        "aat:300008706"
    ]
},
  "bbox": [],
  "geometry": {"coordinates":[-73.5667,40.65],"type":"Point"}
}
=======
{"geometry":{"type":"Point","coordinates":[-73.566700,40.650000]},"type":"Feature","properties":{"hierarchy":["tgn:2339977","tgn:1000001","tgn:7012149","tgn:1002708","tgn:7007568","tgn:7029392"],"placetype":["aat:300008706"],"id":2339977,"name:xx":"Freeport Creek"}}
>>>>>>> 03f74aca74312dbeaf24d7e61306dd6a786dc3d0
