{
  "id": 2759948,
  "type": "Feature",
  "properties": {
    "tgn:hierarchy":[
        "tgn:2759948",
        "tgn:2002239",
        "tgn:1000001",
        "tgn:7012149",
        "tgn:7007920",
        "tgn:7029392"
    ],
    "tgn:id":2759948,
    "tgn:name":"West Fork Menatchee Creek",
    "tgn:placetype":[
        "aat:300008706"
    ]
},
  "bbox": [],
  "geometry": {"coordinates":[-117.45,46.0833],"type":"Point"}
}