{
  "id": 7519570,
  "type": "Feature",
  "properties": {
    "tgn:hierarchy":[
        "tgn:7519570",
        "tgn:1009227",
        "tgn:7001866",
        "tgn:1000226",
        "tgn:1000006",
        "tgn:7029392"
    ],
    "tgn:id":7519570,
    "tgn:name:en":"Agnes Glacier",
    "tgn:placetype":[
        "aat:300008835"
    ]
},
  "bbox": [],
  "geometry": {"coordinates":[170.733333,-43.35],"type":"Point"}
}