{
  "id": 7103952,
  "type": "Feature",
  "properties": {
    "tgn:hierarchy":[
        "tgn:7103952",
        "tgn:1000003",
        "tgn:7003685",
        "tgn:7000084",
        "tgn:7029392"
    ],
    "tgn:id":7103952,
    "tgn:name":"Scheiben-Berg",
    "tgn:placetype":[
        "aat:300008777"
    ]
},
  "bbox": [],
  "geometry": {"coordinates":[13.466667,51.25],"type":"Point"}
}