{
  "id": 2636315,
  "type": "Feature",
  "properties": {
    "tgn:hierarchy":[
        "tgn:2636315",
        "tgn:7002659",
        "tgn:1000001",
        "tgn:2000007",
        "tgn:7012149",
        "tgn:7029392"
    ],
    "tgn:id":2636315,
    "tgn:name":"Saddler Mountain",
    "tgn:placetype":[
        "aat:300008798"
    ]
},
  "bbox": [],
  "geometry": {"coordinates":[-85.7333,33.9167],"type":"Point"}
}