{
  "id": 7240311,
  "type": "Feature",
  "properties": {
    "tgn:hierarchy":[
        "tgn:7240311",
        "tgn:7003460",
        "tgn:1000003",
        "tgn:1000063",
        "tgn:4012014",
        "tgn:7029392"
    ],
    "tgn:id":7240311,
    "tgn:name":"Eiterbach",
    "tgn:placetype":[
        "aat:300008699"
    ]
},
  "bbox": [],
  "geometry": {"coordinates":[6.2125,50.277222],"type":"Point"}
}