{
  "id": 2608704,
  "type": "Feature",
  "properties": {
    "tgn:hierarchy":[
        "tgn:2608704",
        "tgn:1000001",
        "tgn:7012149",
        "tgn:2002121",
        "tgn:7007827",
        "tgn:7029392"
    ],
    "tgn:id":2608704,
    "tgn:name":"Rattlesnake Point",
    "tgn:placetype":[
        "aat:300008798"
    ]
},
  "bbox": [],
  "geometry": {"coordinates":[-111.7667,38.9167],"type":"Point"}
}