{
  "id": 2756546,
  "type": "Feature",
  "properties": {
    "tgn:hierarchy":[
        "tgn:2756546",
        "tgn:1000001",
        "tgn:7012149",
        "tgn:7014097",
        "tgn:7007158",
        "tgn:7029392"
    ],
    "tgn:id":2756546,
    "tgn:name":"Wellington Gulch",
    "tgn:placetype":[
        "aat:300008761"
    ]
},
  "bbox": [],
  "geometry": {"coordinates":[-104.9667,38.9333],"type":"Point"}
}