{
  "id": 7016372,
  "type": "Feature",
  "properties": {
    "tgn:hierarchy":[
        "tgn:7016372",
        "tgn:1000001",
        "tgn:7012149",
        "tgn:1002752",
        "tgn:7007568",
        "tgn:7029392"
    ],
    "tgn:id":7016372,
    "tgn:name":"Morton",
    "tgn:placetype":[
        "aat:300008347",
        "aat:300387210"
    ]
},
  "bbox": [],
  "geometry": {"coordinates":[-77.9833,43.3167],"type":"Point"}
}