{
  "id": 7556388,
  "type": "Feature",
  "properties": {
    "tgn:hierarchy":[
        "tgn:7556388",
        "tgn:7001819",
        "tgn:1000004",
        "tgn:7000198",
        "tgn:7029392"
    ],
    "tgn:id":7556388,
    "tgn:name:en":"Phutang Chu",
    "tgn:placetype":[
        "aat:300008699"
    ]
},
  "bbox": [],
  "geometry": {"coordinates":[92.406659,27.208636],"type":"Point"}
}