{
  "id": 1126392,
  "type": "Feature",
  "properties": {
    "tgn:hierarchy":[
        "tgn:1126392",
        "tgn:7006237",
        "tgn:1000047",
        "tgn:7002457",
        "tgn:1000002",
        "tgn:7029392"
    ],
    "tgn:id":1126392,
    "tgn:name":"Louren\u00e7o Velho",
    "tgn:placetype":[
        "aat:300008707"
    ]
},
  "bbox": [],
  "geometry": {"coordinates":[-45.5167,-22.3667],"type":"Point"}
}