{
  "id": 7277438,
  "type": "Feature",
  "properties": {
    "tgn:hierarchy":[
        "tgn:7277438",
        "tgn:1001702",
        "tgn:1000049",
        "tgn:1000002",
        "tgn:7029392"
    ],
    "tgn:id":7277438,
    "tgn:name":"Vergara, Lago",
    "tgn:placetype":[
        "aat:300008680"
    ]
},
  "bbox": [],
  "geometry": {"coordinates":[-69.183333,-53.233333],"type":"Point"}
}