{
  "id": 2675205,
  "type": "Feature",
  "properties": {
    "tgn:hierarchy":[
        "tgn:2675205",
        "tgn:1000001",
        "tgn:7012149",
        "tgn:7007157",
        "tgn:7014004",
        "tgn:7029392"
    ],
    "tgn:id":2675205,
    "tgn:name":"Solambo Mine",
    "tgn:placetype":[
        "aat:300000390"
    ]
},
  "bbox": [],
  "geometry": {"coordinates":[-120.35,37.7167],"type":"Point"}
}