{
  "id": 7234684,
  "type": "Feature",
  "properties": {
    "tgn:hierarchy":[
        "tgn:7234684",
        "tgn:7002735",
        "tgn:7017076",
        "tgn:1000003",
        "tgn:1000074",
        "tgn:7029392"
    ],
    "tgn:id":7234684,
    "tgn:name":"A\u00ebt\u00f3vigla",
    "tgn:placetype":[
        "aat:300266640"
    ]
},
  "bbox": [],
  "geometry": {"coordinates":[22.766667,37.166667],"type":"Point"}
}