{
  "id": 2497699,
  "type": "Feature",
  "properties": {
    "tgn:hierarchy":[
        "tgn:2497699",
        "tgn:1000001",
        "tgn:7012149",
        "tgn:7014185",
        "tgn:7007710",
        "tgn:7029392"
    ],
    "tgn:id":2497699,
    "tgn:name":"Maybe Nasty Cave",
    "tgn:placetype":[
        "aat:300008746"
    ]
},
  "bbox": [],
  "geometry": {"coordinates":[-79.7167,39.7833],"type":"Point"}
}