{
  "id": 2018454,
  "type": "Feature",
  "properties": {
    "tgn:hierarchy":[
        "tgn:2018454",
        "tgn:1000001",
        "tgn:7012149",
        "tgn:2000280",
        "tgn:7007240",
        "tgn:7029392"
    ],
    "tgn:id":2018454,
    "tgn:name":"Andrews",
    "tgn:placetype":[
        "aat:300008347",
        "aat:300387210"
    ]
},
  "bbox": [],
  "geometry": {"coordinates":[-81.9333,30.7333],"type":"Point"}
}