{
  "id": 2455707,
  "type": "Feature",
  "properties": {
    "tgn:hierarchy":[
        "tgn:2455707",
        "tgn:1000001",
        "tgn:7012149",
        "tgn:2001989",
        "tgn:7007826",
        "tgn:7029392"
    ],
    "tgn:id":2455707,
    "tgn:name":"Little Grape Creek",
    "tgn:placetype":[
        "aat:300008706"
    ]
},
  "bbox": [],
  "geometry": {"coordinates":[-101.05,32.95],"type":"Point"}
}