{
  "id": 2416475,
  "type": "Feature",
  "properties": {
    "tgn:hierarchy":[
        "tgn:2416475",
        "tgn:1000001",
        "tgn:7012149",
        "tgn:2000370",
        "tgn:7007248",
        "tgn:7029392"
    ],
    "tgn:id":2416475,
    "tgn:name":"Jack Creek",
    "tgn:placetype":[
        "aat:300008706"
    ]
},
  "bbox": [],
  "geometry": {"coordinates":[-83.5667,33.3667],"type":"Point"}
}