{
  "id": 2428965,
  "type": "Feature",
  "properties": {
    "tgn:hierarchy":[
        "tgn:2428965",
        "tgn:2001726",
        "tgn:1000001",
        "tgn:7012149",
        "tgn:7007712",
        "tgn:7029392"
    ],
    "tgn:id":2428965,
    "tgn:name":"Jumping Gut Creek",
    "tgn:placetype":[
        "aat:300008706"
    ]
},
  "bbox": [],
  "geometry": {"coordinates":[-81.6333,33.7833],"type":"Point"}
}