{
  "id": 2128631,
  "type": "Feature",
  "properties": {
    "tgn:hierarchy":[
        "tgn:2128631",
        "tgn:1000001",
        "tgn:7012149",
        "tgn:2000927",
        "tgn:7007515",
        "tgn:7029392"
    ],
    "tgn:id":2128631,
    "tgn:name":"Alder Stream",
    "tgn:placetype":[
        "aat:300008699"
    ]
},
  "bbox": [],
  "geometry": {"coordinates":[-69.2333,44.9833],"type":"Point"}
}