{
  "id": 2497634,
  "type": "Feature",
  "properties": {
    "tgn:hierarchy":[
        "tgn:2497634",
        "tgn:1000001",
        "tgn:7012149",
        "tgn:2001721",
        "tgn:7007708",
        "tgn:7029392"
    ],
    "tgn:id":2497634,
    "tgn:name":"May Park Ditch",
    "tgn:placetype":[
        "aat:300006075"
    ]
},
  "bbox": [],
  "geometry": {"coordinates":[-118.05,45.3333],"type":"Point"}
}