{
  "id": 1126569,
  "type": "Feature",
  "properties": {
    "tgn:hierarchy":[
        "tgn:1126569",
        "tgn:1000003",
        "tgn:1000070",
        "tgn:7029392"
    ],
    "tgn:id":1126569,
    "tgn:name":"M\u00eame",
    "tgn:placetype":[
        "aat:300008707"
    ]
},
  "bbox": [],
  "geometry": {"coordinates":[0.65,48.1833],"type":"Point"}
}