{
  "id": 2217436,
  "type": "Feature",
  "properties": {
    "tgn:hierarchy":[
        "tgn:2217436",
        "tgn:1000001",
        "tgn:7012149",
        "tgn:2001233",
        "tgn:7007523",
        "tgn:7029392"
    ],
    "tgn:id":2217436,
    "tgn:name":"Campbell Cave",
    "tgn:placetype":[
        "aat:300008746"
    ]
},
  "bbox": [],
  "geometry": {"coordinates":[-92.2667,37.8333],"type":"Point"}
}