{
  "id": 7414749,
  "type": "Feature",
  "properties": {
    "tgn:hierarchy":[
        "tgn:7414749",
        "tgn:7005584",
        "tgn:1000001",
        "tgn:7005560",
        "tgn:7029392"
    ],
    "tgn:id":7414749,
    "tgn:name":"Mogotes",
    "tgn:placetype":[
        "aat:300008347"
    ]
},
  "bbox": [],
  "geometry": {"coordinates":[-101.475833,20.491944],"type":"Point"}
}