{
  "id": 7364676,
  "type": "Feature",
  "properties": {
    "tgn:hierarchy":[
        "tgn:7364676",
        "tgn:7005585",
        "tgn:1000001",
        "tgn:7005560",
        "tgn:7029392"
    ],
    "tgn:id":7364676,
    "tgn:name":"El Zapote",
    "tgn:placetype":[
        "aat:300008347"
    ]
},
  "bbox": [],
  "geometry": {"coordinates":[-99.533333,17.05],"type":"Point"}
}