{
  "id": 1011724,
  "type": "Feature",
  "properties": {
    "tgn:hierarchy":[
        "tgn:1011724",
        "tgn:1000573",
        "tgn:1000001",
        "tgn:7005554",
        "tgn:7029392"
    ],
    "tgn:id":1011724,
    "tgn:name":"Caxinas, Punta",
    "tgn:placetype":[
        "aat:300386846"
    ]
},
  "bbox": [],
  "geometry": {"coordinates":[-86.0333,16.0167],"type":"Point"}
}