<<<<<<< HEAD
{
  "id": 7358006,
  "type": "Feature",
  "properties": {
    "tgn:hierarchy":[
        "tgn:7358006",
        "tgn:1000001",
        "tgn:1001960",
        "tgn:7005560",
        "tgn:7029392"
    ],
    "tgn:id":7358006,
    "tgn:name":"Costa Rica",
    "tgn:placetype":[
        "aat:300008347"
    ]
},
  "bbox": [],
  "geometry": {"coordinates":[-112.6,31.323333],"type":"Point"}
}
=======
{"geometry":{"type":"Point","coordinates":[-112.600000,31.323333]},"type":"Feature","properties":{"hierarchy":["tgn:7358006","tgn:1000001","tgn:1001960","tgn:7005560","tgn:7029392"],"placetype":["aat:300008347"],"id":7358006,"name:xx":"Costa Rica"}}
>>>>>>> 03f74aca74312dbeaf24d7e61306dd6a786dc3d0
