{
  "id": 7504148,
  "type": "Feature",
  "properties": {
    "tgn:hierarchy":[
        "tgn:7504148",
        "tgn:1009227",
        "tgn:1000226",
        "tgn:7016729",
        "tgn:1000006",
        "tgn:7029392"
    ],
    "tgn:id":7504148,
    "tgn:name:en":"Washdyke Stream",
    "tgn:placetype":[
        "aat:300008699"
    ]
},
  "bbox": [],
  "geometry": {"coordinates":[173.933333,-42.083333],"type":"Point"}
}