<<<<<<< HEAD
{
  "id": 2707241,
  "type": "Feature",
  "properties": {
    "tgn:hierarchy":[
        "tgn:2707241",
        "tgn:1000001",
        "tgn:1002293",
        "tgn:7012149",
        "tgn:7007708",
        "tgn:7029392"
    ],
    "tgn:id":2707241,
    "tgn:name":"Swedetown",
    "tgn:placetype":[
        "aat:300008347"
    ]
},
  "bbox": [],
  "geometry": {"coordinates":[-123.1,46.0333],"type":"Point"}
}
=======
{"geometry":{"type":"Point","coordinates":[-123.100000,46.033300]},"type":"Feature","properties":{"hierarchy":["tgn:2707241","tgn:1000001","tgn:1002293","tgn:7012149","tgn:7007708","tgn:7029392"],"placetype":["aat:300008347"],"id":2707241,"name:xx":"Swedetown"}}
>>>>>>> 03f74aca74312dbeaf24d7e61306dd6a786dc3d0
