{
  "id": 7304952,
  "type": "Feature",
  "properties": {
    "tgn:hierarchy":[
        "tgn:7304952",
        "tgn:7002805",
        "tgn:7002758",
        "tgn:1000003",
        "tgn:1000095",
        "tgn:7029392"
    ],
    "tgn:id":7304952,
    "tgn:name":"La T\u00eda Luc\u00eda",
    "tgn:placetype":[
        "aat:300008347"
    ]
},
  "bbox": [],
  "geometry": {"coordinates":[-2.133333,37.266667],"type":"Point"}
}