{
  "id": 1118830,
  "type": "Feature",
  "properties": {
    "tgn:hierarchy":[
        "tgn:1118830",
        "tgn:1000001",
        "tgn:1002259",
        "tgn:7012149",
        "tgn:7007568",
        "tgn:7029392"
    ],
    "tgn:id":1118830,
    "tgn:name":"Cassadaga Lakes",
    "tgn:placetype":[
        "aat:300008680"
    ]
},
  "bbox": [],
  "geometry": {"coordinates":[-79.3167,42.3333],"type":"Point"}
}