{
  "id": 7358095,
  "type": "Feature",
  "properties": {
    "tgn:hierarchy":[
        "tgn:7358095",
        "tgn:1000001",
        "tgn:7005591",
        "tgn:7005560",
        "tgn:7029392"
    ],
    "tgn:id":7358095,
    "tgn:name":"Cuyamecalco Villa de Zaragoza",
    "tgn:placetype":[
        "aat:300008347"
    ]
},
  "bbox": [],
  "geometry": {"coordinates":[-96.833333,17.966667],"type":"Point"}
}