{
  "id": 7504584,
  "type": "Feature",
  "properties": {
    "tgn:hierarchy":[
        "tgn:7504584",
        "tgn:1008380",
        "tgn:7000507",
        "tgn:1000226",
        "tgn:1000006",
        "tgn:7029392"
    ],
    "tgn:id":7504584,
    "tgn:name:en":"McKenzie Bay",
    "tgn:placetype":[
        "aat:300132316"
    ]
},
  "bbox": [],
  "geometry": {"coordinates":[174.53,-35.833333],"type":"Point"}
}