<<<<<<< HEAD
{
  "id": 7356926,
  "type": "Feature",
  "properties": {
    "tgn:hierarchy":[
        "tgn:7356926",
        "tgn:7005581",
        "tgn:1000001",
        "tgn:7005560",
        "tgn:7029392"
    ],
    "tgn:id":7356926,
    "tgn:name":"Chiqueritos",
    "tgn:placetype":[
        "aat:300008347"
    ]
},
  "bbox": [],
  "geometry": {"coordinates":[-108.016667,28.483333],"type":"Point"}
}
=======
{"geometry":{"type":"Point","coordinates":[-108.016667,28.483333]},"type":"Feature","properties":{"hierarchy":["tgn:7356926","tgn:7005581","tgn:1000001","tgn:7005560","tgn:7029392"],"placetype":["aat:300008347"],"id":7356926,"name:xx":"Chiqueritos"}}
>>>>>>> 03f74aca74312dbeaf24d7e61306dd6a786dc3d0
