{
  "id": 7374200,
  "type": "Feature",
  "properties": {
    "tgn:hierarchy":[
        "tgn:7374200",
        "tgn:1000001",
        "tgn:1001893",
        "tgn:7005560",
        "tgn:7029392"
    ],
    "tgn:id":7374200,
    "tgn:name":"Laguna, Regi\u00f3n de la",
    "tgn:placetype":[
        "aat:300387346"
    ]
},
  "bbox": [],
  "geometry": {"coordinates":[-103.433333,25.55],"type":"Point"}
}