{
  "id": 7361049,
  "type": "Feature",
  "properties": {
    "tgn:hierarchy":[
        "tgn:7361049",
        "tgn:1001853",
        "tgn:1000001",
        "tgn:7005560",
        "tgn:7029392"
    ],
    "tgn:id":7361049,
    "tgn:name":"El Colorado",
    "tgn:placetype":[
        "aat:300008347"
    ]
},
  "bbox": [],
  "geometry": {"coordinates":[-103.566667,27.466667],"type":"Point"}
}