{
  "id": 7335385,
  "type": "Feature",
  "properties": {
    "tgn:hierarchy":[
        "tgn:7335385",
        "tgn:7002826",
        "tgn:7001158",
        "tgn:1000003",
        "tgn:1000095",
        "tgn:7029392"
    ],
    "tgn:id":7335385,
    "tgn:name":"Fresno de la Valduerna",
    "tgn:placetype":[
        "aat:300008347"
    ]
},
  "bbox": [],
  "geometry": {"coordinates":[-6.016667,42.333333],"type":"Point"}
}