{
  "id": 1125198,
  "type": "Feature",
  "properties": {
    "tgn:hierarchy":[
        "tgn:1125198",
        "tgn:1001944",
        "tgn:1000047",
        "tgn:7002456",
        "tgn:1000002",
        "tgn:7029392"
    ],
    "tgn:id":1125198,
    "tgn:name":"Jiparan\u00e1",
    "tgn:placetype":[
        "aat:300008707"
    ]
},
  "bbox": [],
  "geometry": {"coordinates":[-62.8667,-8.05],"type":"Point"}
}