{
  "id": 7179873,
  "type": "Feature",
  "properties": {
    "tgn:hierarchy":[
        "tgn:7179873",
        "tgn:1000003",
        "tgn:7003677",
        "tgn:7000084",
        "tgn:7029392"
    ],
    "tgn:id":7179873,
    "tgn:name":"Hahnen-Berg",
    "tgn:placetype":[
        "aat:300008777"
    ]
},
  "bbox": [],
  "geometry": {"coordinates":[6.516667,50.65],"type":"Point"}
}