{
  "id": 7478862,
  "type": "Feature",
  "properties": {
    "tgn:hierarchy":[
        "tgn:7478862",
        "tgn:7487020",
        "tgn:1000004",
        "tgn:1000141",
        "tgn:7029392"
    ],
    "tgn:id":7478862,
    "tgn:name":"Xinshan Qiao",
    "tgn:placetype":[
        "aat:300007836"
    ]
},
  "bbox": [],
  "geometry": {"coordinates":[120.936258,24.524254],"type":"Point"}
}