<<<<<<< HEAD
{
  "id": 7022322,
  "type": "Feature",
  "properties": {
    "tgn:hierarchy":[
        "tgn:7022322",
        "tgn:7002659",
        "tgn:1000001",
        "tgn:7012149",
        "tgn:7029392"
    ],
    "tgn:id":7022322,
    "tgn:name":"Bailey Brook",
    "tgn:placetype":[
        "aat:300008699"
    ]
},
  "bbox": [],
  "geometry": {"coordinates":[-86.8333,33.3333],"type":"Point"}
}
=======
{"geometry":{"type":"Point","coordinates":[-86.833300,33.333300]},"type":"Feature","properties":{"hierarchy":["tgn:7022322","tgn:7002659","tgn:1000001","tgn:7012149","tgn:7029392"],"placetype":["aat:300008699"],"id":7022322,"name:xx":"Bailey Brook"}}
>>>>>>> 03f74aca74312dbeaf24d7e61306dd6a786dc3d0
