{
  "id": 2294932,
  "type": "Feature",
  "properties": {
    "tgn:hierarchy":[
        "tgn:2294932",
        "tgn:7002659",
        "tgn:1000001",
        "tgn:7012149",
        "tgn:2000044",
        "tgn:7029392"
    ],
    "tgn:id":2294932,
    "tgn:name":"Drake Spring",
    "tgn:placetype":[
        "aat:300008697"
    ]
},
  "bbox": [],
  "geometry": {"coordinates":[-86.4833,34.6833],"type":"Point"}
}