{
  "id": 2525977,
  "type": "Feature",
  "properties": {
    "tgn:hierarchy":[
        "tgn:2525977",
        "tgn:7006450",
        "tgn:1000001",
        "tgn:7012149",
        "tgn:2000088",
        "tgn:7029392"
    ],
    "tgn:id":2525977,
    "tgn:name":"Mosman Island",
    "tgn:placetype":[
        "aat:300008791"
    ]
},
  "bbox": [],
  "geometry": {"coordinates":[-132.5333,56.05],"type":"Point"}
}