{
  "id": 2573125,
  "type": "Feature",
  "properties": {
    "tgn:hierarchy":[
        "tgn:2573125",
        "tgn:1000001",
        "tgn:7012149",
        "tgn:7007157",
        "tgn:1002894",
        "tgn:7029392"
    ],
    "tgn:id":2573125,
    "tgn:name":"Pearson Ravine",
    "tgn:placetype":[
        "aat:300008761"
    ]
},
  "bbox": [],
  "geometry": {"coordinates":[-120.85,39.7167],"type":"Point"}
}