{
  "id": 7060470,
  "type": "Feature",
  "properties": {
    "tgn:hierarchy":[
        "tgn:7060470",
        "tgn:1000003",
        "tgn:7003688",
        "tgn:7000084",
        "tgn:7029392"
    ],
    "tgn:id":7060470,
    "tgn:name":"Altendeich",
    "tgn:placetype":[
        "aat:300008347"
    ]
},
  "bbox": [],
  "geometry": {"coordinates":[9.583333,53.666667],"type":"Point"}
}