{
  "id": 7096691,
  "type": "Feature",
  "properties": {
    "tgn:hierarchy":[
        "tgn:7096691",
        "tgn:1000003",
        "tgn:7003687",
        "tgn:7000084",
        "tgn:7029392"
    ],
    "tgn:id":7096691,
    "tgn:name":"Siebigerode",
    "tgn:placetype":[
        "aat:300008347"
    ]
},
  "bbox": [],
  "geometry": {"coordinates":[11.433333,51.566667],"type":"Point"}
}