{
  "id": 2244081,
  "type": "Feature",
  "properties": {
    "tgn:hierarchy":[
        "tgn:2244081",
        "tgn:1000001",
        "tgn:2002107",
        "tgn:7012149",
        "tgn:7007827",
        "tgn:7029392"
    ],
    "tgn:id":2244081,
    "tgn:name":"Cliff Lake",
    "tgn:placetype":[
        "aat:300006191"
    ]
},
  "bbox": [],
  "geometry": {"coordinates":[-109.9833,40.7167],"type":"Point"}
}