{
  "id": 2172120,
  "type": "Feature",
  "properties": {
    "tgn:hierarchy":[
        "tgn:2172120",
        "tgn:1000001",
        "tgn:7012149",
        "tgn:7016166",
        "tgn:7007523",
        "tgn:7029392"
    ],
    "tgn:id":2172120,
    "tgn:name":"Biggs Lake",
    "tgn:placetype":[
        "aat:300006191"
    ]
},
  "bbox": [],
  "geometry": {"coordinates":[-90.9333,38.7833],"type":"Point"}
}