{
  "id": 2752458,
  "type": "Feature",
  "properties": {
    "tgn:hierarchy":[
        "tgn:2752458",
        "tgn:1000001",
        "tgn:7012149",
        "tgn:1002424",
        "tgn:7007706",
        "tgn:7029392"
    ],
    "tgn:id":2752458,
    "tgn:name":"Washington Mills",
    "tgn:placetype":[
        "aat:300008347"
    ]
},
  "bbox": [],
  "geometry": {"coordinates":[-84.0333,39.6333],"type":"Point"}
}