<<<<<<< HEAD
{
  "id": 7480359,
  "type": "Feature",
  "properties": {
    "tgn:hierarchy":[
        "tgn:7480359",
        "tgn:7001010",
        "tgn:1000004",
        "tgn:1000141",
        "tgn:7029392"
    ],
    "tgn:id":7480359,
    "tgn:name":"Disanhao Qiao",
    "tgn:placetype":[
        "aat:300007836"
    ]
},
  "bbox": [],
  "geometry": {"coordinates":[121.608889,23.992222],"type":"Point"}
}
=======
{"geometry":{"type":"Point","coordinates":[121.608889,23.992222]},"type":"Feature","properties":{"hierarchy":["tgn:7480359","tgn:7001010","tgn:1000004","tgn:1000141","tgn:7029392"],"placetype":["aat:300007836"],"id":7480359,"name:xx":"Disanhao Qiao"}}
>>>>>>> 03f74aca74312dbeaf24d7e61306dd6a786dc3d0
