{
  "id": 2383969,
  "type": "Feature",
  "properties": {
    "tgn:hierarchy":[
        "tgn:2383969",
        "tgn:1000001",
        "tgn:7012149",
        "tgn:2001297",
        "tgn:7007524",
        "tgn:7029392"
    ],
    "tgn:id":2383969,
    "tgn:name":"Hedum Draw",
    "tgn:placetype":[
        "aat:300008761"
    ]
},
  "bbox": [],
  "geometry": {"coordinates":[-106.05,45.2833],"type":"Point"}
}