{
  "id": 7337027,
  "type": "Feature",
  "properties": {
    "tgn:hierarchy":[
        "tgn:7337027",
        "tgn:7008911",
        "tgn:1000003",
        "tgn:7002763",
        "tgn:1000095",
        "tgn:7029392"
    ],
    "tgn:id":7337027,
    "tgn:name":"Cuero",
    "tgn:placetype":[
        "aat:300008347"
    ]
},
  "bbox": [],
  "geometry": {"coordinates":[-6.05,43.416667],"type":"Point"}
}