{
  "id": 7506640,
  "type": "Feature",
  "properties": {
    "tgn:hierarchy":[
        "tgn:7506640",
        "tgn:1009227",
        "tgn:1000226",
        "tgn:7016729",
        "tgn:1000006",
        "tgn:7029392"
    ],
    "tgn:id":7506640,
    "tgn:name:en":"Rileys Lookout",
    "tgn:placetype":[
        "aat:300011692"
    ]
},
  "bbox": [],
  "geometry": {"coordinates":[173.55,-42.466667],"type":"Point"}
}