{
  "id": 7177096,
  "type": "Feature",
  "properties": {
    "tgn:hierarchy":[
        "tgn:7177096",
        "tgn:7003669",
        "tgn:1000003",
        "tgn:7000084",
        "tgn:7029392"
    ],
    "tgn:id":7177096,
    "tgn:name":"Hard",
    "tgn:placetype":[
        "aat:300008347"
    ]
},
  "bbox": [],
  "geometry": {"coordinates":[12.083333,49.933333],"type":"Point"}
}