{
  "id": 7103668,
  "type": "Feature",
  "properties": {
    "tgn:hierarchy":[
        "tgn:7103668",
        "tgn:1000003",
        "tgn:7003676",
        "tgn:7000084",
        "tgn:7029392"
    ],
    "tgn:id":7103668,
    "tgn:name":"Sandkrug",
    "tgn:placetype":[
        "aat:300000206"
    ]
},
  "bbox": [],
  "geometry": {"coordinates":[7.666667,53.633333],"type":"Point"}
}