{
  "id": 7591860,
  "type": "Feature",
  "properties": {
    "tgn:hierarchy":[
        "tgn:7591860",
        "tgn:1000004",
        "tgn:7000198",
        "tgn:7031786",
        "tgn:7029392"
    ],
    "tgn:id":7591860,
    "tgn:name:en":"Ghulaita Nadi",
    "tgn:placetype":[
        "aat:300008699"
    ]
},
  "bbox": [],
  "geometry": {"coordinates":[77.951643,30.342647],"type":"Point"}
}