{
  "id": 2299412,
  "type": "Feature",
  "properties": {
    "tgn:hierarchy":[
        "tgn:2299412",
        "tgn:2000946",
        "tgn:1000001",
        "tgn:7012149",
        "tgn:7007520",
        "tgn:7029392"
    ],
    "tgn:id":2299412,
    "tgn:name":"Duck Lake Drain",
    "tgn:placetype":[
        "aat:300008699"
    ]
},
  "bbox": [],
  "geometry": {"coordinates":[-83.7333,44.0833],"type":"Point"}
}