<<<<<<< HEAD
{
  "id": 2768383,
  "type": "Feature",
  "properties": {
    "tgn:hierarchy":[
        "tgn:2768383",
        "tgn:1000001",
        "tgn:7012149",
        "tgn:2001766",
        "tgn:7007712",
        "tgn:7029392"
    ],
    "tgn:id":2768383,
    "tgn:name":"Whitestone Number One Pond",
    "tgn:placetype":[
        "aat:300006191"
    ]
},
  "bbox": [],
  "geometry": {"coordinates":[-81.8,34.9],"type":"Point"}
}
=======
{"geometry":{"type":"Point","coordinates":[-81.800000,34.900000]},"type":"Feature","properties":{"hierarchy":["tgn:2768383","tgn:1000001","tgn:7012149","tgn:2001766","tgn:7007712","tgn:7029392"],"placetype":["aat:300006191"],"id":2768383,"name:xx":"Whitestone Number One Pond"}}
>>>>>>> 03f74aca74312dbeaf24d7e61306dd6a786dc3d0
