{
  "id": 7176434,
  "type": "Feature",
  "properties": {
    "tgn:hierarchy":[
        "tgn:7176434",
        "tgn:1000003",
        "tgn:7003677",
        "tgn:7000084",
        "tgn:7029392"
    ],
    "tgn:id":7176434,
    "tgn:name":"Haltern",
    "tgn:placetype":[
        "aat:300008347"
    ]
},
  "bbox": [],
  "geometry": {"coordinates":[7.266667,52.116667],"type":"Point"}
}