<<<<<<< HEAD
{
  "id": 7024381,
  "type": "Feature",
  "properties": {
    "tgn:hierarchy":[
        "tgn:7024381",
        "tgn:7002745",
        "tgn:7017076",
        "tgn:1000003",
        "tgn:1000074",
        "tgn:7029392"
    ],
    "tgn:id":7024381,
    "tgn:name":"Kamares",
    "tgn:placetype":[
        "aat:300008347"
    ]
},
  "bbox": [],
  "geometry": {"coordinates":[22.516667,36.683333],"type":"Point"}
}
=======
{"geometry":{"type":"Point","coordinates":[22.516667,36.683333]},"type":"Feature","properties":{"hierarchy":["tgn:7024381","tgn:7002745","tgn:7017076","tgn:1000003","tgn:1000074","tgn:7029392"],"placetype":["aat:300008347"],"id":7024381,"name:xx":"Kamares"}}
>>>>>>> 03f74aca74312dbeaf24d7e61306dd6a786dc3d0
