{
  "id": 7541810,
  "type": "Feature",
  "properties": {
    "tgn:hierarchy":[
        "tgn:7541810",
        "tgn:7001242",
        "tgn:7016833",
        "tgn:7001335",
        "tgn:7029392"
    ],
    "tgn:id":7541810,
    "tgn:name":"Wakh\u0101m\u012b, Ra's al",
    "tgn:placetype":[
        "aat:300008798"
    ]
},
  "bbox": [],
  "geometry": {"coordinates":[34.120833,29.768333],"type":"Point"}
}