{
  "id": 2213458,
  "type": "Feature",
  "properties": {
    "tgn:hierarchy":[
        "tgn:2213458",
        "tgn:1000001",
        "tgn:7012149",
        "tgn:7015778",
        "tgn:7007919",
        "tgn:7029392"
    ],
    "tgn:id":2213458,
    "tgn:name":"Cabin Run",
    "tgn:placetype":[
        "aat:300008699"
    ]
},
  "bbox": [],
  "geometry": {"coordinates":[-77.45,38.7333],"type":"Point"}
}