<<<<<<< HEAD
{
  "id": 2769120,
  "type": "Feature",
  "properties": {
    "tgn:hierarchy":[
        "tgn:2769120",
        "tgn:1000001",
        "tgn:1002714",
        "tgn:7012149",
        "tgn:7007159",
        "tgn:7029392"
    ],
    "tgn:id":2769120,
    "tgn:name":"Whittle Brook",
    "tgn:placetype":[
        "aat:300008699"
    ]
},
  "bbox": [],
  "geometry": {"coordinates":[-72.2,41.5],"type":"Point"}
}
=======
{"geometry":{"type":"Point","coordinates":[-72.200000,41.500000]},"type":"Feature","properties":{"hierarchy":["tgn:2769120","tgn:1000001","tgn:1002714","tgn:7012149","tgn:7007159","tgn:7029392"],"placetype":["aat:300008699"],"id":2769120,"name:xx":"Whittle Brook"}}
>>>>>>> 03f74aca74312dbeaf24d7e61306dd6a786dc3d0
