{
  "id": 1008086,
  "type": "Feature",
  "properties": {
    "tgn:hierarchy":[
        "tgn:1008086",
        "tgn:1000821",
        "tgn:7001242",
        "tgn:1000180",
        "tgn:7029392"
    ],
    "tgn:id":1008086,
    "tgn:name":"Matemo, Ilha",
    "tgn:placetype":[
        "aat:300008791"
    ]
},
  "bbox": [],
  "geometry": {"coordinates":[40.6333,-12.25],"type":"Point"}
}