{
  "id": 7575084,
  "type": "Feature",
  "properties": {
    "tgn:hierarchy":[
        "tgn:7575084",
        "tgn:7001819",
        "tgn:1000004",
        "tgn:7000198",
        "tgn:7029392"
    ],
    "tgn:id":7575084,
    "tgn:name:en":"Kelingon",
    "tgn:placetype":[
        "aat:300008795"
    ]
},
  "bbox": [],
  "geometry": {"coordinates":[96.316667,28.716667],"type":"Point"}
}