{
  "id": 2723306,
  "type": "Feature",
  "properties": {
    "tgn:hierarchy":[
        "tgn:2723306",
        "tgn:1000001",
        "tgn:7012149",
        "tgn:2002179",
        "tgn:7007919",
        "tgn:7029392"
    ],
    "tgn:id":2723306,
    "tgn:name":"Tobacco Knob",
    "tgn:placetype":[
        "aat:300008798"
    ]
},
  "bbox": [],
  "geometry": {"coordinates":[-80.3333,36.6667],"type":"Point"}
}