{
  "id": 7584918,
  "type": "Feature",
  "properties": {
    "tgn:hierarchy":[
        "tgn:7584918",
        "tgn:1000004",
        "tgn:7000198",
        "tgn:1001894",
        "tgn:7029392"
    ],
    "tgn:id":7584918,
    "tgn:name:en":"Shiv Niv\u0101s B\u0101gh",
    "tgn:placetype":[
        "aat:300008090"
    ]
},
  "bbox": [],
  "geometry": {"coordinates":[78.802911,24.699755],"type":"Point"}
}