{
  "id": 7115435,
  "type": "Feature",
  "properties": {
    "tgn:hierarchy":[
        "tgn:7115435",
        "tgn:1000003",
        "tgn:7003689",
        "tgn:7000084",
        "tgn:7029392"
    ],
    "tgn:id":7115435,
    "tgn:name":"Paditz",
    "tgn:placetype":[
        "aat:300008347"
    ]
},
  "bbox": [],
  "geometry": {"coordinates":[12.466667,50.966667],"type":"Point"}
}