{
  "id": 2630703,
  "type": "Feature",
  "properties": {
    "tgn:hierarchy":[
        "tgn:2630703",
        "tgn:1000001",
        "tgn:7012149",
        "tgn:2000852",
        "tgn:7007255",
        "tgn:7029392"
    ],
    "tgn:id":2630703,
    "tgn:name":"Round Knob",
    "tgn:placetype":[
        "aat:300008798"
    ]
},
  "bbox": [],
  "geometry": {"coordinates":[-84.0667,36.75],"type":"Point"}
}