{
  "id": 2086031,
  "type": "Feature",
  "properties": {
    "tgn:hierarchy":[
        "tgn:2086031",
        "tgn:1002153",
        "tgn:1000001",
        "tgn:7012149",
        "tgn:7007710",
        "tgn:7029392"
    ],
    "tgn:id":2086031,
    "tgn:name":"Apollo",
    "tgn:placetype":[
        "aat:300008347"
    ]
},
  "bbox": [],
  "geometry": {"coordinates":[-79.5667,40.5667],"type":"Point"}
}