{
  "id": 1015142,
  "type": "Feature",
  "properties": {
    "tgn:hierarchy":[
        "tgn:1015142",
        "tgn:7005685",
        "tgn:1000001",
        "tgn:7013154",
        "tgn:7013251",
        "tgn:7029392"
    ],
    "tgn:id":1015142,
    "tgn:name":"Summerville",
    "tgn:placetype":[
        "aat:300008347"
    ]
},
  "bbox": [],
  "geometry": {"coordinates":[-79.5667,43.6167],"type":"Point"}
}