{
  "id": 2522709,
  "type": "Feature",
  "properties": {
    "tgn:hierarchy":[
        "tgn:2522709",
        "tgn:1000001",
        "tgn:7012149",
        "tgn:1002839",
        "tgn:7007826",
        "tgn:7029392"
    ],
    "tgn:id":2522709,
    "tgn:name":"Moore Branch",
    "tgn:placetype":[
        "aat:300008699"
    ]
},
  "bbox": [],
  "geometry": {"coordinates":[-94.6167,31.9333],"type":"Point"}
}