{
  "id": 2225801,
  "type": "Feature",
  "properties": {
    "tgn:hierarchy":[
        "tgn:2225801",
        "tgn:1002933",
        "tgn:1000001",
        "tgn:7012149",
        "tgn:7007239",
        "tgn:7029392"
    ],
    "tgn:id":2225801,
    "tgn:name":"Cat Hill Marsh",
    "tgn:placetype":[
        "aat:300008905"
    ]
},
  "bbox": [],
  "geometry": {"coordinates":[-75.05,38.5167],"type":"Point"}
}