{
  "id": 7580278,
  "type": "Feature",
  "properties": {
    "tgn:hierarchy":[
        "tgn:7580278",
        "tgn:1000004",
        "tgn:1001869",
        "tgn:7000198",
        "tgn:7029392"
    ],
    "tgn:id":7580278,
    "tgn:name:en":"V\u0101d\u0101sinor",
    "tgn:placetype":[
        "aat:300008347"
    ]
},
  "bbox": [],
  "geometry": {"coordinates":[73.333333,22.95],"type":"Point"}
}