{
  "id": 1020592,
  "type": "Feature",
  "properties": {
    "tgn:hierarchy":[
        "tgn:1020592",
        "tgn:1001942",
        "tgn:1000047",
        "tgn:7002457",
        "tgn:1000002",
        "tgn:7029392"
    ],
    "tgn:id":1020592,
    "tgn:name":"Amba\u00ed",
    "tgn:placetype":[
        "aat:300008347"
    ]
},
  "bbox": [],
  "geometry": {"coordinates":[-43.4667,-22.7167],"type":"Point"}
}