{
  "id": 2310806,
  "type": "Feature",
  "properties": {
    "tgn:hierarchy":[
        "tgn:2310806",
        "tgn:1000001",
        "tgn:2001944",
        "tgn:7012149",
        "tgn:7007826",
        "tgn:7029392"
    ],
    "tgn:id":2310806,
    "tgn:name":"Ector Lake",
    "tgn:placetype":[
        "aat:300008680"
    ]
},
  "bbox": [],
  "geometry": {"coordinates":[-94.2833,33.5667],"type":"Point"}
}