{
  "id": 7557764,
  "type": "Feature",
  "properties": {
    "tgn:hierarchy":[
        "tgn:7557764",
        "tgn:1000004",
        "tgn:7000198",
        "tgn:1001977",
        "tgn:7029392"
    ],
    "tgn:id":7557764,
    "tgn:name:en":"Pata La",
    "tgn:placetype":[
        "aat:300259572"
    ]
},
  "bbox": [],
  "geometry": {"coordinates":[88.85,27.716667],"type":"Point"}
}