{
  "id": 2717319,
  "type": "Feature",
  "properties": {
    "tgn:hierarchy":[
        "tgn:2717319",
        "tgn:1000001",
        "tgn:2000260",
        "tgn:7012149",
        "tgn:7007240",
        "tgn:7029392"
    ],
    "tgn:id":2717319,
    "tgn:name":"Thirty One Swamp",
    "tgn:placetype":[
        "aat:300008905"
    ]
},
  "bbox": [],
  "geometry": {"coordinates":[-85.2667,30.35],"type":"Point"}
}