{
  "id": 2119354,
  "type": "Feature",
  "properties": {
    "tgn:hierarchy":[
        "tgn:2119354",
        "tgn:1000001",
        "tgn:7012149",
        "tgn:2002298",
        "tgn:7013961",
        "tgn:7029392"
    ],
    "tgn:id":2119354,
    "tgn:name":"Nebo",
    "tgn:placetype":[
        "aat:300008347",
        "aat:300387210"
    ]
},
  "bbox": [],
  "geometry": {"coordinates":[-80.0833,38.9833],"type":"Point"}
}