{
  "id": 2354428,
  "type": "Feature",
  "properties": {
    "tgn:hierarchy":[
        "tgn:2354428",
        "tgn:1000001",
        "tgn:7012149",
        "tgn:7013941",
        "tgn:7007568",
        "tgn:7029392"
    ],
    "tgn:id":2354428,
    "tgn:name":"Goldsmith Range",
    "tgn:placetype":[
        "aat:300266640"
    ]
},
  "bbox": [],
  "geometry": {"coordinates":[-74.15,44.65],"type":"Point"}
}