{
  "id": 2506019,
  "type": "Feature",
  "properties": {
    "tgn:hierarchy":[
        "tgn:2506019",
        "tgn:1002300",
        "tgn:1000001",
        "tgn:7012149",
        "tgn:7007564",
        "tgn:7029392"
    ],
    "tgn:id":2506019,
    "tgn:name":"Meriden Hill",
    "tgn:placetype":[
        "aat:300008347"
    ]
},
  "bbox": [],
  "geometry": {"coordinates":[-71.55,44.7667],"type":"Point"}
}