{
  "id": 1080815,
  "type": "Feature",
  "properties": {
    "tgn:hierarchy":[
        "tgn:1080815",
        "tgn:7000895",
        "tgn:1000004",
        "tgn:1000977",
        "tgn:1000120",
        "tgn:7029392"
    ],
    "tgn:id":1080815,
    "tgn:name":"Mitake",
    "tgn:placetype":[
        "aat:300008347"
    ]
},
  "bbox": [],
  "geometry": {"coordinates":[137.1333,35.4167],"type":"Point"}
}