{
  "id": 7533842,
  "type": "Feature",
  "properties": {
    "tgn:hierarchy":[
        "tgn:7533842",
        "tgn:7001242",
        "tgn:7016833",
        "tgn:1001083",
        "tgn:7029392"
    ],
    "tgn:id":7533842,
    "tgn:name:en":"\u1e28amzah, Jabal",
    "tgn:placetype":[
        "aat:300008777"
    ]
},
  "bbox": [],
  "geometry": {"coordinates":[30.806196,30.134709],"type":"Point"}
}