{
  "id": 7552005,
  "type": "Feature",
  "properties": {
    "tgn:hierarchy":[
        "tgn:7552005",
        "tgn:1000004",
        "tgn:1001869",
        "tgn:7000198",
        "tgn:7029392"
    ],
    "tgn:id":7552005,
    "tgn:name:en":"Chikhli",
    "tgn:placetype":[
        "aat:300008347"
    ]
},
  "bbox": [],
  "geometry": {"coordinates":[73.066667,20.75],"type":"Point"}
}