{
  "id": 2417852,
  "type": "Feature",
  "properties": {
    "tgn:hierarchy":[
        "tgn:2417852",
        "tgn:2000563",
        "tgn:1000001",
        "tgn:7012149",
        "tgn:7007253",
        "tgn:7029392"
    ],
    "tgn:id":2417852,
    "tgn:name":"Jackson Island",
    "tgn:placetype":[
        "aat:300008791"
    ]
},
  "bbox": [],
  "geometry": {"coordinates":[-91.1333,43.1667],"type":"Point"}
}