{
  "id": 2061252,
  "type": "Feature",
  "properties": {
    "tgn:hierarchy":[
        "tgn:2061252",
        "tgn:1000001",
        "tgn:7012149",
        "tgn:2001273",
        "tgn:7007524",
        "tgn:7029392"
    ],
    "tgn:id":2061252,
    "tgn:name":"Denton",
    "tgn:placetype":[
        "aat:300008347"
    ]
},
  "bbox": [],
  "geometry": {"coordinates":[-109.9333,47.3167],"type":"Point"}
}