{
  "id": 1069144,
  "type": "Feature",
  "properties": {
    "tgn:hierarchy":[
        "tgn:1069144",
        "tgn:1000004",
        "tgn:1001390",
        "tgn:1000111",
        "tgn:7029392"
    ],
    "tgn:id":1069144,
    "tgn:name":"Jiangjiagou",
    "tgn:placetype":[
        "aat:300008347"
    ]
},
  "bbox": [],
  "geometry": {"coordinates":[121.7333,41.7333],"type":"Point"}
}