{
  "id": 1059122,
  "type": "Feature",
  "properties": {
    "tgn:hierarchy":[
        "tgn:1059122",
        "tgn:1000004",
        "tgn:1003417",
        "tgn:7018214",
        "tgn:7002435",
        "tgn:7029392"
    ],
    "tgn:id":1059122,
    "tgn:name":"Sayukino",
    "tgn:placetype":[
        "aat:300008347"
    ]
},
  "bbox": [],
  "geometry": {"coordinates":[41.9833,52.7833],"type":"Point"}
}