<<<<<<< HEAD
{
  "id": 7364821,
  "type": "Feature",
  "properties": {
    "tgn:hierarchy":[
        "tgn:7364821",
        "tgn:7005586",
        "tgn:1000001",
        "tgn:7005560",
        "tgn:7029392"
    ],
    "tgn:id":7364821,
    "tgn:name":"El Puerto",
    "tgn:placetype":[
        "aat:300008347"
    ]
},
  "bbox": [],
  "geometry": {"coordinates":[-103.016667,21.016667],"type":"Point"}
}
=======
{"geometry":{"type":"Point","coordinates":[-103.016667,21.016667]},"type":"Feature","properties":{"hierarchy":["tgn:7364821","tgn:7005586","tgn:1000001","tgn:7005560","tgn:7029392"],"placetype":["aat:300008347"],"id":7364821,"name:xx":"El Puerto"}}
>>>>>>> 03f74aca74312dbeaf24d7e61306dd6a786dc3d0
