{
  "id": 7476620,
  "type": "Feature",
  "properties": {
    "tgn:hierarchy":[
        "tgn:7476620",
        "tgn:1000004",
        "tgn:7004300",
        "tgn:1000141",
        "tgn:7029392"
    ],
    "tgn:id":7476620,
    "tgn:name":"Xiaoquzhao",
    "tgn:placetype":[
        "aat:300008791"
    ]
},
  "bbox": [],
  "geometry": {"coordinates":[119.651583,23.689378],"type":"Point"}
}