<<<<<<< HEAD
{
  "id": 7476620,
  "type": "Feature",
  "properties": {
    "tgn:hierarchy":[
        "tgn:7476620",
        "tgn:1000004",
        "tgn:7004300",
        "tgn:1000141",
        "tgn:7029392"
    ],
    "tgn:id":7476620,
    "tgn:name":"Xiaoquzhao",
    "tgn:placetype":[
        "aat:300008791"
    ]
},
  "bbox": [],
  "geometry": {"coordinates":[119.651583,23.689378],"type":"Point"}
}
=======
{"geometry":{"type":"Point","coordinates":[119.651583,23.689378]},"type":"Feature","properties":{"hierarchy":["tgn:7476620","tgn:1000004","tgn:7004300","tgn:1000141","tgn:7029392"],"placetype":["aat:300008791"],"id":7476620,"name:xx":"Xiaoquzhao"}}
>>>>>>> 03f74aca74312dbeaf24d7e61306dd6a786dc3d0
