{
  "id": 7511133,
  "type": "Feature",
  "properties": {
    "tgn:hierarchy":[
        "tgn:7511133",
        "tgn:1009227",
        "tgn:1000226",
        "tgn:7016822",
        "tgn:1000006",
        "tgn:7029392"
    ],
    "tgn:id":7511133,
    "tgn:name:en":"Slate Range",
    "tgn:placetype":[
        "aat:300008795"
    ]
},
  "bbox": [],
  "geometry": {"coordinates":[168.666667,-45.516667],"type":"Point"}
}