{
  "id": 7322901,
  "type": "Feature",
  "properties": {
    "tgn:hierarchy":[
        "tgn:7322901",
        "tgn:7002758",
        "tgn:7002841",
        "tgn:1000003",
        "tgn:1000095",
        "tgn:7029392"
    ],
    "tgn:id":7322901,
    "tgn:name":"Salado, Arroyo",
    "tgn:placetype":[
        "aat:300008699"
    ]
},
  "bbox": [],
  "geometry": {"coordinates":[-4.866667,37.416667],"type":"Point"}
}