{
  "id": 2419552,
  "type": "Feature",
  "properties": {
    "tgn:hierarchy":[
        "tgn:2419552",
        "tgn:1000001",
        "tgn:7012149",
        "tgn:2001308",
        "tgn:7007524",
        "tgn:7029392"
    ],
    "tgn:id":2419552,
    "tgn:name":"Jarrett Creek",
    "tgn:placetype":[
        "aat:300008706"
    ]
},
  "bbox": [],
  "geometry": {"coordinates":[-110.1333,45.6833],"type":"Point"}
}