{
  "id": 2195780,
  "type": "Feature",
  "properties": {
    "tgn:hierarchy":[
        "tgn:2195780",
        "tgn:1000001",
        "tgn:7012149",
        "tgn:1002613",
        "tgn:7007710",
        "tgn:7029392"
    ],
    "tgn:id":2195780,
    "tgn:name":"Broad Run",
    "tgn:placetype":[
        "aat:300008699"
    ]
},
  "bbox": [],
  "geometry": {"coordinates":[-76.65,41.2167],"type":"Point"}
}