{
  "id": 7402306,
  "type": "Feature",
  "properties": {
    "tgn:hierarchy":[
        "tgn:7402306",
        "tgn:1000001",
        "tgn:7005599",
        "tgn:7005560",
        "tgn:7029392"
    ],
    "tgn:id":7402306,
    "tgn:name":"Barranquillas",
    "tgn:placetype":[
        "aat:300008347"
    ]
},
  "bbox": [],
  "geometry": {"coordinates":[-97.066667,19.558333],"type":"Point"}
}