{
  "id": 1124746,
  "type": "Feature",
  "properties": {
    "tgn:hierarchy":[
        "tgn:1124746",
        "tgn:1001822",
        "tgn:1000047",
        "tgn:7002456",
        "tgn:1000002",
        "tgn:7029392"
    ],
    "tgn:id":1124746,
    "tgn:name":"Humait\u00e1",
    "tgn:placetype":[
        "aat:300008707"
    ]
},
  "bbox": [],
  "geometry": {"coordinates":[-72.7333,-8.2667],"type":"Point"}
}