{
  "id": 1107629,
  "type": "Feature",
  "properties": {
    "tgn:hierarchy":[
        "tgn:1107629",
        "tgn:1000001",
        "tgn:7012149",
        "tgn:7007158",
        "tgn:7029392"
    ],
    "tgn:id":1107629,
    "tgn:name":"West Spanish Peak",
    "tgn:placetype":[
        "aat:300008798"
    ]
},
  "bbox": [],
  "geometry": {"coordinates":[-104.9833,37.3667],"type":"Point"}
}