{
  "id": 2513452,
  "type": "Feature",
  "properties": {
    "tgn:hierarchy":[
        "tgn:2513452",
        "tgn:1000001",
        "tgn:7012149",
        "tgn:2124023",
        "tgn:7007248",
        "tgn:7029392"
    ],
    "tgn:id":2513452,
    "tgn:name":"Mill Lake",
    "tgn:placetype":[
        "aat:300008680"
    ]
},
  "bbox": [],
  "geometry": {"coordinates":[-84.1667,33.75],"type":"Point"}
}