{
  "id": 1108607,
  "type": "Feature",
  "properties": {
    "tgn:hierarchy":[
        "tgn:1108607",
        "tgn:1000003",
        "tgn:1000070",
        "tgn:7002895",
        "tgn:7029392"
    ],
    "tgn:id":1108607,
    "tgn:name":"Vars, Col du",
    "tgn:placetype":[
        "aat:300259572"
    ]
},
  "bbox": [],
  "geometry": {"coordinates":[6.7167,44.55],"type":"Point"}
}