{
  "id": 2478122,
  "type": "Feature",
  "properties": {
    "tgn:hierarchy":[
        "tgn:2478122",
        "tgn:7013313",
        "tgn:1000001",
        "tgn:7012149",
        "tgn:7007826",
        "tgn:7029392"
    ],
    "tgn:id":2478122,
    "tgn:name":"Mack Reef",
    "tgn:placetype":[
        "aat:300132348"
    ]
},
  "bbox": [],
  "geometry": {"coordinates":[-96.9667,28.0833],"type":"Point"}
}