{
  "id": 7255441,
  "type": "Feature",
  "properties": {
    "tgn:hierarchy":[
        "tgn:7255441",
        "tgn:7003466",
        "tgn:1000003",
        "tgn:1000063",
        "tgn:4012014",
        "tgn:7029392"
    ],
    "tgn:id":7255441,
    "tgn:name":"Rome",
    "tgn:placetype":[
        "aat:300008699"
    ]
},
  "bbox": [],
  "geometry": {"coordinates":[4.533333,50.016667],"type":"Point"}
}