{
  "id": 2603747,
  "type": "Feature",
  "properties": {
    "tgn:hierarchy":[
        "tgn:2603747",
        "tgn:1000001",
        "tgn:7012149",
        "tgn:1002870",
        "tgn:7007240",
        "tgn:7029392"
    ],
    "tgn:id":2603747,
    "tgn:name":"Quick Point",
    "tgn:placetype":[
        "aat:300008850"
    ]
},
  "bbox": [],
  "geometry": {"coordinates":[-82.5667,27.3333],"type":"Point"}
}