{
  "id": 2161192,
  "type": "Feature",
  "properties": {
    "tgn:hierarchy":[
        "tgn:2161192",
        "tgn:1000001",
        "tgn:2001733",
        "tgn:7012149",
        "tgn:7007712",
        "tgn:7029392"
    ],
    "tgn:id":2161192,
    "tgn:name":"Bell Hall Neck",
    "tgn:placetype":[
        "aat:300008850"
    ]
},
  "bbox": [],
  "geometry": {"coordinates":[-80.9167,33.8167],"type":"Point"}
}