{
  "id": 2474213,
  "type": "Feature",
  "properties": {
    "tgn:hierarchy":[
        "tgn:2474213",
        "tgn:1000001",
        "tgn:7012149",
        "tgn:2000238",
        "tgn:7007158",
        "tgn:7029392"
    ],
    "tgn:id":2474213,
    "tgn:name":"Lower Michigan Reservoir",
    "tgn:placetype":[
        "aat:300006191"
    ]
},
  "bbox": [],
  "geometry": {"coordinates":[-105.8833,39.4167],"type":"Point"}
}