{
  "id": 7399872,
  "type": "Feature",
  "properties": {
    "tgn:hierarchy":[
        "tgn:7399872",
        "tgn:1000001",
        "tgn:7005593",
        "tgn:7005560",
        "tgn:7029392"
    ],
    "tgn:id":7399872,
    "tgn:name":"Carrizal de Adjuntas",
    "tgn:placetype":[
        "aat:300008347"
    ]
},
  "bbox": [],
  "geometry": {"coordinates":[-99.558333,21.233333],"type":"Point"}
}