{
  "id": 7358011,
  "type": "Feature",
  "properties": {
    "tgn:hierarchy":[
        "tgn:7358011",
        "tgn:1000001",
        "tgn:7005591",
        "tgn:7005560",
        "tgn:7029392"
    ],
    "tgn:id":7358011,
    "tgn:name":"Costa Rica",
    "tgn:placetype":[
        "aat:300008347"
    ]
},
  "bbox": [],
  "geometry": {"coordinates":[-96.216667,15.916667],"type":"Point"}
}