{
  "id": 2444039,
  "type": "Feature",
  "properties": {
    "tgn:hierarchy":[
        "tgn:2444039",
        "tgn:1000001",
        "tgn:7012149",
        "tgn:1002521",
        "tgn:7007920",
        "tgn:7029392"
    ],
    "tgn:id":2444039,
    "tgn:name":"LaCrosse, Lake",
    "tgn:placetype":[
        "aat:300008680"
    ]
},
  "bbox": [],
  "geometry": {"coordinates":[-123.35,47.65],"type":"Point"}
}