<<<<<<< HEAD
{
  "id": 2252264,
  "type": "Feature",
  "properties": {
    "tgn:hierarchy":[
        "tgn:2252264",
        "tgn:1000001",
        "tgn:2001838",
        "tgn:7012149",
        "tgn:7007825",
        "tgn:7029392"
    ],
    "tgn:id":2252264,
    "tgn:name":"Coney Island",
    "tgn:placetype":[
        "aat:300008791"
    ]
},
  "bbox": [],
  "geometry": {"coordinates":[-86.4333,35.4667],"type":"Point"}
}
=======
{"geometry":{"type":"Point","coordinates":[-86.433300,35.466700]},"type":"Feature","properties":{"hierarchy":["tgn:2252264","tgn:1000001","tgn:2001838","tgn:7012149","tgn:7007825","tgn:7029392"],"placetype":["aat:300008791"],"id":2252264,"name:xx":"Coney Island"}}
>>>>>>> 03f74aca74312dbeaf24d7e61306dd6a786dc3d0
