{
  "id": 2252264,
  "type": "Feature",
  "properties": {
    "tgn:hierarchy":[
        "tgn:2252264",
        "tgn:1000001",
        "tgn:2001838",
        "tgn:7012149",
        "tgn:7007825",
        "tgn:7029392"
    ],
    "tgn:id":2252264,
    "tgn:name":"Coney Island",
    "tgn:placetype":[
        "aat:300008791"
    ]
},
  "bbox": [],
  "geometry": {"coordinates":[-86.4333,35.4667],"type":"Point"}
}