{
  "id": 2333716,
  "type": "Feature",
  "properties": {
    "tgn:hierarchy":[
        "tgn:2333716",
        "tgn:7006450",
        "tgn:1000001",
        "tgn:7012149",
        "tgn:7019760",
        "tgn:7029392"
    ],
    "tgn:id":2333716,
    "tgn:name":"Foot Island",
    "tgn:placetype":[
        "aat:300008791"
    ]
},
  "bbox": [],
  "geometry": {"coordinates":[-133.5167,57.2667],"type":"Point"}
}