<<<<<<< HEAD
{
  "id": 2333716,
  "type": "Feature",
  "properties": {
    "tgn:hierarchy":[
        "tgn:2333716",
        "tgn:7006450",
        "tgn:1000001",
        "tgn:7012149",
        "tgn:7019760",
        "tgn:7029392"
    ],
    "tgn:id":2333716,
    "tgn:name":"Foot Island",
    "tgn:placetype":[
        "aat:300008791"
    ]
},
  "bbox": [],
  "geometry": {"coordinates":[-133.5167,57.2667],"type":"Point"}
}
=======
{"geometry":{"type":"Point","coordinates":[-133.516700,57.266700]},"type":"Feature","properties":{"hierarchy":["tgn:2333716","tgn:7006450","tgn:1000001","tgn:7012149","tgn:7019760","tgn:7029392"],"placetype":["aat:300008791"],"id":2333716,"name:xx":"Foot Island"}}
>>>>>>> 03f74aca74312dbeaf24d7e61306dd6a786dc3d0
