{
  "id": 7592794,
  "type": "Feature",
  "properties": {
    "tgn:hierarchy":[
        "tgn:7592794",
        "tgn:1000004",
        "tgn:7000198",
        "tgn:7000799",
        "tgn:7029392"
    ],
    "tgn:id":7592794,
    "tgn:name:en":"Batw\u0101na",
    "tgn:placetype":[
        "aat:300008347"
    ]
},
  "bbox": [],
  "geometry": {"coordinates":[74.828266,32.88517],"type":"Point"}
}