{
  "id": 7343866,
  "type": "Feature",
  "properties": {
    "tgn:hierarchy":[
        "tgn:7343866",
        "tgn:7002818",
        "tgn:1001647",
        "tgn:1000003",
        "tgn:1000095",
        "tgn:7029392"
    ],
    "tgn:id":7343866,
    "tgn:name":"Cabrejas",
    "tgn:placetype":[
        "aat:300008347"
    ]
},
  "bbox": [],
  "geometry": {"coordinates":[-2.35,40.05],"type":"Point"}
}