{
  "id": 7381743,
  "type": "Feature",
  "properties": {
    "tgn:hierarchy":[
        "tgn:7381743",
        "tgn:1000001",
        "tgn:1001960",
        "tgn:7005560",
        "tgn:7029392"
    ],
    "tgn:id":7381743,
    "tgn:name":"Mesa de Galinda",
    "tgn:placetype":[
        "aat:300008347"
    ]
},
  "bbox": [],
  "geometry": {"coordinates":[-109.416667,28.383333],"type":"Point"}
}