{
  "id": 7473562,
  "type": "Feature",
  "properties": {
    "tgn:hierarchy":[
        "tgn:7473562",
        "tgn:1000004",
        "tgn:7489179",
        "tgn:1000141",
        "tgn:7029392"
    ],
    "tgn:id":7473562,
    "tgn:name":"Shuangxikou",
    "tgn:placetype":[
        "aat:300008347"
    ]
},
  "bbox": [],
  "geometry": {"coordinates":[121.620156,24.755444],"type":"Point"}
}