{
  "id": 7449640,
  "type": "Feature",
  "properties": {
    "tgn:hierarchy":[
        "tgn:7449640",
        "tgn:7002448",
        "tgn:7019157",
        "tgn:1000003",
        "tgn:7008591",
        "tgn:7029392"
    ],
    "tgn:id":7449640,
    "tgn:name:en":"Glendun River",
    "tgn:placetype":[
        "aat:300008699"
    ]
},
  "bbox": [],
  "geometry": {"coordinates":[-6.033333,55.133333],"type":"Point"}
}