{
  "id": 7415352,
  "type": "Feature",
  "properties": {
    "tgn:hierarchy":[
        "tgn:7415352",
        "tgn:7005584",
        "tgn:1000001",
        "tgn:7005560",
        "tgn:7029392"
    ],
    "tgn:id":7415352,
    "tgn:name":"Aldama",
    "tgn:placetype":[
        "aat:300008347"
    ]
},
  "bbox": [],
  "geometry": {"coordinates":[-99.810556,21.175556],"type":"Point"}
}