<<<<<<< HEAD
{
  "id": 2151934,
  "type": "Feature",
  "properties": {
    "tgn:hierarchy":[
        "tgn:2151934",
        "tgn:1000001",
        "tgn:7012149",
        "tgn:2000233",
        "tgn:7007158",
        "tgn:7029392"
    ],
    "tgn:id":2151934,
    "tgn:name":"Bauer Reservoir Number 1",
    "tgn:placetype":[
        "aat:300006191"
    ]
},
  "bbox": [],
  "geometry": {"coordinates":[-108.3,37.4],"type":"Point"}
}
=======
{"geometry":{"type":"Point","coordinates":[-108.300000,37.400000]},"type":"Feature","properties":{"hierarchy":["tgn:2151934","tgn:1000001","tgn:7012149","tgn:2000233","tgn:7007158","tgn:7029392"],"placetype":["aat:300006191"],"id":2151934,"name:xx":"Bauer Reservoir Number 1"}}
>>>>>>> 03f74aca74312dbeaf24d7e61306dd6a786dc3d0
