{
  "id": 2345741,
  "type": "Feature",
  "properties": {
    "tgn:hierarchy":[
        "tgn:2345741",
        "tgn:1000001",
        "tgn:2001705",
        "tgn:7012149",
        "tgn:7007708",
        "tgn:7029392"
    ],
    "tgn:id":2345741,
    "tgn:name":"Garrison Butte",
    "tgn:placetype":[
        "aat:300008798"
    ]
},
  "bbox": [],
  "geometry": {"coordinates":[-121.5333,44.3833],"type":"Point"}
}