{
  "id": 7145285,
  "type": "Feature",
  "properties": {
    "tgn:hierarchy":[
        "tgn:7145285",
        "tgn:1000003",
        "tgn:7003678",
        "tgn:7000084",
        "tgn:7029392"
    ],
    "tgn:id":7145285,
    "tgn:name":"K\u00f6lnische Kanzel",
    "tgn:placetype":[
        "aat:300387200"
    ]
},
  "bbox": [],
  "geometry": {"coordinates":[9.233333,51.183333],"type":"Point"}
}