<<<<<<< HEAD
{
  "id": 2403704,
  "type": "Feature",
  "properties": {
    "tgn:hierarchy":[
        "tgn:2403704",
        "tgn:1000001",
        "tgn:7012149",
        "tgn:7014589",
        "tgn:7007515",
        "tgn:7029392"
    ],
    "tgn:id":2403704,
    "tgn:name":"Howard Lake Mountain",
    "tgn:placetype":[
        "aat:300008798"
    ]
},
  "bbox": [],
  "geometry": {"coordinates":[-67.2333,45.0833],"type":"Point"}
}
=======
{"geometry":{"type":"Point","coordinates":[-67.233300,45.083300]},"type":"Feature","properties":{"hierarchy":["tgn:2403704","tgn:1000001","tgn:7012149","tgn:7014589","tgn:7007515","tgn:7029392"],"placetype":["aat:300008798"],"id":2403704,"name:xx":"Howard Lake Mountain"}}
>>>>>>> 03f74aca74312dbeaf24d7e61306dd6a786dc3d0
