{
  "id": 7565723,
  "type": "Feature",
  "properties": {
    "tgn:hierarchy":[
        "tgn:7565723",
        "tgn:1000004",
        "tgn:7000198",
        "tgn:7016722",
        "tgn:7029392"
    ],
    "tgn:id":7565723,
    "tgn:name:en":"Purwa Dal\u0101h\u0101r",
    "tgn:placetype":[
        "aat:300008347"
    ]
},
  "bbox": [],
  "geometry": {"coordinates":[79.593276,26.772722],"type":"Point"}
}