{
  "id": 7409058,
  "type": "Feature",
  "properties": {
    "tgn:hierarchy":[
        "tgn:7409058",
        "tgn:1000001",
        "tgn:7005590",
        "tgn:7005560",
        "tgn:7029392"
    ],
    "tgn:id":7409058,
    "tgn:name":"Arteaga, R\u00edo",
    "tgn:placetype":[
        "aat:300008699"
    ]
},
  "bbox": [],
  "geometry": {"coordinates":[-102.325,18.256944],"type":"Point"}
}