{
  "id": 2343496,
  "type": "Feature",
  "properties": {
    "tgn:hierarchy":[
        "tgn:2343496",
        "tgn:1000001",
        "tgn:7012149",
        "tgn:1002676",
        "tgn:7007240",
        "tgn:7029392"
    ],
    "tgn:id":2343496,
    "tgn:name":"Galdin Key",
    "tgn:placetype":[
        "aat:300008791"
    ]
},
  "bbox": [],
  "geometry": {"coordinates":[-81.5833,24.6833],"type":"Point"}
}