{
  "id": 2053646,
  "type": "Feature",
  "properties": {
    "tgn:hierarchy":[
        "tgn:2053646",
        "tgn:1000001",
        "tgn:7012149",
        "tgn:1002509",
        "tgn:7007520",
        "tgn:7029392"
    ],
    "tgn:id":2053646,
    "tgn:name":"Waterloo",
    "tgn:placetype":[
        "aat:300008347"
    ]
},
  "bbox": [],
  "geometry": {"coordinates":[-84.1333,42.35],"type":"Point"}
}