{
  "id": 1017933,
  "type": "Feature",
  "properties": {
    "tgn:hierarchy":[
        "tgn:1017933",
        "tgn:1001835",
        "tgn:1000001",
        "tgn:7005560",
        "tgn:7029392"
    ],
    "tgn:id":1017933,
    "tgn:name":"Nuevo Le\u00f3n",
    "tgn:placetype":[
        "aat:300008347"
    ]
},
  "bbox": [],
  "geometry": {"coordinates":[-115.188889,32.409444],"type":"Point"}
}