{
  "id": 2593117,
  "type": "Feature",
  "properties": {
    "tgn:hierarchy":[
        "tgn:2593117",
        "tgn:2000919",
        "tgn:1000001",
        "tgn:7012149",
        "tgn:7007515",
        "tgn:7029392"
    ],
    "tgn:id":2593117,
    "tgn:name":"Poplar Island Brook",
    "tgn:placetype":[
        "aat:300008699"
    ]
},
  "bbox": [],
  "geometry": {"coordinates":[-69.2167,47.1167],"type":"Point"}
}