{
  "id": 7555968,
  "type": "Feature",
  "properties": {
    "tgn:hierarchy":[
        "tgn:7555968",
        "tgn:1000004",
        "tgn:7000198",
        "tgn:1001977",
        "tgn:7029392"
    ],
    "tgn:id":7555968,
    "tgn:name:en":"Petr\u0101pol",
    "tgn:placetype":[
        "aat:300007783"
    ]
},
  "bbox": [],
  "geometry": {"coordinates":[88.833333,23.033333],"type":"Point"}
}