{
  "id": 2019627,
  "type": "Feature",
  "properties": {
    "tgn:hierarchy":[
        "tgn:2019627",
        "tgn:1000001",
        "tgn:7012149",
        "tgn:1002773",
        "tgn:7007240",
        "tgn:7029392"
    ],
    "tgn:id":2019627,
    "tgn:name":"Holiday",
    "tgn:placetype":[
        "aat:300008347"
    ]
},
  "bbox": [],
  "geometry": {"coordinates":[-82.7333,28.1833],"type":"Point"}
}