{
  "id": 7283114,
  "type": "Feature",
  "properties": {
    "tgn:hierarchy":[
        "tgn:7283114",
        "tgn:7002464",
        "tgn:1000049",
        "tgn:1000002",
        "tgn:7029392"
    ],
    "tgn:id":7283114,
    "tgn:name":"Pastos Grandes, Pampa",
    "tgn:placetype":[
        "aat:300008805"
    ]
},
  "bbox": [],
  "geometry": {"coordinates":[-69.683333,-17.85],"type":"Point"}
}