{
  "id": 7511527,
  "type": "Feature",
  "properties": {
    "tgn:hierarchy":[
        "tgn:7511527",
        "tgn:1009227",
        "tgn:7001866",
        "tgn:1000226",
        "tgn:1000006",
        "tgn:7029392"
    ],
    "tgn:id":7511527,
    "tgn:name:en":"Marion, Lake",
    "tgn:placetype":[
        "aat:300008680"
    ]
},
  "bbox": [],
  "geometry": {"coordinates":[172.233333,-42.683333],"type":"Point"}
}