{
  "id": 2206754,
  "type": "Feature",
  "properties": {
    "tgn:hierarchy":[
        "tgn:2206754",
        "tgn:1002176",
        "tgn:1000001",
        "tgn:7012149",
        "tgn:7007828",
        "tgn:7029392"
    ],
    "tgn:id":2206754,
    "tgn:name":"Bulls Head",
    "tgn:placetype":[
        "aat:300011692"
    ]
},
  "bbox": [],
  "geometry": {"coordinates":[-73.1167,43.05],"type":"Point"}
}