{
  "id": 7342179,
  "type": "Feature",
  "properties": {
    "tgn:hierarchy":[
        "tgn:7342179",
        "tgn:7001158",
        "tgn:7002850",
        "tgn:1000003",
        "tgn:1000095",
        "tgn:7029392"
    ],
    "tgn:id":7342179,
    "tgn:name":"Ca\u00f1izal",
    "tgn:placetype":[
        "aat:300008347"
    ]
},
  "bbox": [],
  "geometry": {"coordinates":[-5.366667,41.166667],"type":"Point"}
}