<<<<<<< HEAD
{
  "id": 7023213,
  "type": "Feature",
  "properties": {
    "tgn:hierarchy":[
        "tgn:7023213",
        "tgn:1000001",
        "tgn:7012149",
        "tgn:7029392"
    ],
    "tgn:id":7023213,
    "tgn:name":"Labyrinth Bay",
    "tgn:placetype":[
        "aat:300132316"
    ]
},
  "bbox": [],
  "geometry": {"coordinates":[-111.3,37.0],"type":"Point"}
}
=======
{"geometry":{"type":"Point","coordinates":[-111.300000,37.000000]},"type":"Feature","properties":{"hierarchy":["tgn:7023213","tgn:1000001","tgn:7012149","tgn:7029392"],"placetype":["aat:300132316"],"id":7023213,"name:xx":"Labyrinth Bay"}}
>>>>>>> 03f74aca74312dbeaf24d7e61306dd6a786dc3d0
