{
  "id": 2523732,
  "type": "Feature",
  "properties": {
    "tgn:hierarchy":[
        "tgn:2523732",
        "tgn:1000001",
        "tgn:7019560",
        "tgn:7012149",
        "tgn:7007566",
        "tgn:7029392"
    ],
    "tgn:id":2523732,
    "tgn:name":"Mora, Arroyo",
    "tgn:placetype":[
        "aat:300008699"
    ]
},
  "bbox": [],
  "geometry": {"coordinates":[-104.75,34.0333],"type":"Point"}
}