{
  "id": 7131537,
  "type": "Feature",
  "properties": {
    "tgn:hierarchy":[
        "tgn:7131537",
        "tgn:1000003",
        "tgn:7003677",
        "tgn:7000084",
        "tgn:7029392"
    ],
    "tgn:id":7131537,
    "tgn:name":"Marienloh",
    "tgn:placetype":[
        "aat:300008347"
    ]
},
  "bbox": [],
  "geometry": {"coordinates":[8.783333,51.766667],"type":"Point"}
}