{
  "id": 7090240,
  "type": "Feature",
  "properties": {
    "tgn:hierarchy":[
        "tgn:7090240",
        "tgn:1000003",
        "tgn:7003677",
        "tgn:7000084",
        "tgn:7029392"
    ],
    "tgn:id":7090240,
    "tgn:name":"Vohren",
    "tgn:placetype":[
        "aat:300387173"
    ]
},
  "bbox": [],
  "geometry": {"coordinates":[8.033333,51.933333],"type":"Point"}
}