<<<<<<< HEAD
{
  "id": 7178828,
  "type": "Feature",
  "properties": {
    "tgn:hierarchy":[
        "tgn:7178828",
        "tgn:7003669",
        "tgn:1000003",
        "tgn:7000084",
        "tgn:7029392"
    ],
    "tgn:id":7178828,
    "tgn:name":"Guggenberg",
    "tgn:placetype":[
        "aat:300008347"
    ]
},
  "bbox": [],
  "geometry": {"coordinates":[10.716667,48.216667],"type":"Point"}
}
=======
{"geometry":{"type":"Point","coordinates":[10.716667,48.216667]},"type":"Feature","properties":{"hierarchy":["tgn:7178828","tgn:7003669","tgn:1000003","tgn:7000084","tgn:7029392"],"placetype":["aat:300008347"],"id":7178828,"name:xx":"Guggenberg"}}
>>>>>>> 03f74aca74312dbeaf24d7e61306dd6a786dc3d0
