{
  "id": 7225078,
  "type": "Feature",
  "properties": {
    "tgn:hierarchy":[
        "tgn:7225078",
        "tgn:4003773",
        "tgn:7001395",
        "tgn:1000003",
        "tgn:1000074",
        "tgn:7029392"
    ],
    "tgn:id":7225078,
    "tgn:name":"R\u00edgani",
    "tgn:placetype":[
        "aat:300008347"
    ]
},
  "bbox": [],
  "geometry": {"coordinates":[21.416667,38.95],"type":"Point"}
}