<<<<<<< HEAD
{
  "id": 2250878,
  "type": "Feature",
  "properties": {
    "tgn:hierarchy":[
        "tgn:2250878",
        "tgn:1000001",
        "tgn:1002217",
        "tgn:7012149",
        "tgn:7007710",
        "tgn:7029392"
    ],
    "tgn:id":2250878,
    "tgn:name":"Columbia Hill",
    "tgn:placetype":[
        "aat:300008798"
    ]
},
  "bbox": [],
  "geometry": {"coordinates":[-79.7,41.1],"type":"Point"}
}
=======
{"geometry":{"type":"Point","coordinates":[-79.700000,41.100000]},"type":"Feature","properties":{"hierarchy":["tgn:2250878","tgn:1000001","tgn:1002217","tgn:7012149","tgn:7007710","tgn:7029392"],"placetype":["aat:300008798"],"id":2250878,"name:xx":"Columbia Hill"}}
>>>>>>> 03f74aca74312dbeaf24d7e61306dd6a786dc3d0
