{
  "id": 7302875,
  "type": "Feature",
  "properties": {
    "tgn:hierarchy":[
        "tgn:7302875",
        "tgn:7002834",
        "tgn:1000003",
        "tgn:7002786",
        "tgn:1000095",
        "tgn:7029392"
    ],
    "tgn:id":7302875,
    "tgn:name":"Padrones",
    "tgn:placetype":[
        "aat:300008347"
    ]
},
  "bbox": [],
  "geometry": {"coordinates":[-8.516667,42.15],"type":"Point"}
}