{
  "id": 7592997,
  "type": "Feature",
  "properties": {
    "tgn:hierarchy":[
        "tgn:7592997",
        "tgn:1000004",
        "tgn:7000198",
        "tgn:7000799",
        "tgn:7029392"
    ],
    "tgn:id":7592997,
    "tgn:name:en":"Phik\u0101r",
    "tgn:placetype":[
        "aat:300008347"
    ]
},
  "bbox": [],
  "geometry": {"coordinates":[76.195833,34.569444],"type":"Point"}
}