{
  "id": 2267206,
  "type": "Feature",
  "properties": {
    "tgn:hierarchy":[
        "tgn:2267206",
        "tgn:1000001",
        "tgn:2001477",
        "tgn:7012149",
        "tgn:7007709",
        "tgn:7029392"
    ],
    "tgn:id":2267206,
    "tgn:name":"Cricket Island",
    "tgn:placetype":[
        "aat:300008791"
    ]
},
  "bbox": [],
  "geometry": {"coordinates":[-76.1833,34.95],"type":"Point"}
}