{
  "id": 2765192,
  "type": "Feature",
  "properties": {
    "tgn:hierarchy":[
        "tgn:2765192",
        "tgn:7006450",
        "tgn:1000001",
        "tgn:7012149",
        "tgn:2124005",
        "tgn:7029392"
    ],
    "tgn:id":2765192,
    "tgn:name":"Whistler Creek",
    "tgn:placetype":[
        "aat:300008706"
    ]
},
  "bbox": [],
  "geometry": {"coordinates":[-145.2833,69.2167],"type":"Point"}
}