<<<<<<< HEAD
{
  "id": 2765192,
  "type": "Feature",
  "properties": {
    "tgn:hierarchy":[
        "tgn:2765192",
        "tgn:7006450",
        "tgn:1000001",
        "tgn:7012149",
        "tgn:2124005",
        "tgn:7029392"
    ],
    "tgn:id":2765192,
    "tgn:name":"Whistler Creek",
    "tgn:placetype":[
        "aat:300008706"
    ]
},
  "bbox": [],
  "geometry": {"coordinates":[-145.2833,69.2167],"type":"Point"}
}
=======
{"geometry":{"type":"Point","coordinates":[-145.283300,69.216700]},"type":"Feature","properties":{"hierarchy":["tgn:2765192","tgn:7006450","tgn:1000001","tgn:7012149","tgn:2124005","tgn:7029392"],"placetype":["aat:300008706"],"id":2765192,"name:xx":"Whistler Creek"}}
>>>>>>> 03f74aca74312dbeaf24d7e61306dd6a786dc3d0
