{
  "id": 2683509,
  "type": "Feature",
  "properties": {
    "tgn:hierarchy":[
        "tgn:2683509",
        "tgn:1000001",
        "tgn:1002601",
        "tgn:7012149",
        "tgn:7007159",
        "tgn:7029392"
    ],
    "tgn:id":2683509,
    "tgn:name":"Spaulding Pond",
    "tgn:placetype":[
        "aat:300006191"
    ]
},
  "bbox": [],
  "geometry": {"coordinates":[-73.1833,41.9667],"type":"Point"}
}