{
  "id": 7383514,
  "type": "Feature",
  "properties": {
    "tgn:hierarchy":[
        "tgn:7383514",
        "tgn:7005579",
        "tgn:1000001",
        "tgn:7005560",
        "tgn:7029392"
    ],
    "tgn:id":7383514,
    "tgn:name":"Papanton, Cerro",
    "tgn:placetype":[
        "aat:300008795"
    ]
},
  "bbox": [],
  "geometry": {"coordinates":[-102.733333,21.916667],"type":"Point"}
}