{
  "id": 1023739,
  "type": "Feature",
  "properties": {
    "tgn:hierarchy":[
        "tgn:1023739",
        "tgn:1000050",
        "tgn:1000694",
        "tgn:1000002",
        "tgn:7029392"
    ],
    "tgn:id":1023739,
    "tgn:name":"Cabuyaro",
    "tgn:placetype":[
        "aat:300008347"
    ]
},
  "bbox": [],
  "geometry": {"coordinates":[-72.7833,4.35],"type":"Point"}
}