{
  "id": 1062156,
  "type": "Feature",
  "properties": {
    "tgn:hierarchy":[
        "tgn:1062156",
        "tgn:7010420",
        "tgn:1000003",
        "tgn:7002795",
        "tgn:1000095",
        "tgn:7029392"
    ],
    "tgn:id":1062156,
    "tgn:name":"Las Rozas de Madrid",
    "tgn:placetype":[
        "aat:300008347"
    ]
},
  "bbox": [],
  "geometry": {"coordinates":[-3.866667,40.483333],"type":"Point"}
}