{
  "id": 2544203,
  "type": "Feature",
  "properties": {
    "tgn:hierarchy":[
        "tgn:2544203",
        "tgn:1000001",
        "tgn:2001336",
        "tgn:7012149",
        "tgn:7007525",
        "tgn:7029392"
    ],
    "tgn:id":2544203,
    "tgn:name":"North Branch Mud Creek",
    "tgn:placetype":[
        "aat:300008706"
    ]
},
  "bbox": [],
  "geometry": {"coordinates":[-99.7167,41.4667],"type":"Point"}
}