{
  "id": 2570967,
  "type": "Feature",
  "properties": {
    "tgn:hierarchy":[
        "tgn:2570967",
        "tgn:1000001",
        "tgn:7012149",
        "tgn:2000386",
        "tgn:7007248",
        "tgn:7029392"
    ],
    "tgn:id":2570967,
    "tgn:name":"Patterson Island",
    "tgn:placetype":[
        "aat:300008791"
    ]
},
  "bbox": [],
  "geometry": {"coordinates":[-81.3333,31.45],"type":"Point"}
}