<<<<<<< HEAD
{
  "id": 7379262,
  "type": "Feature",
  "properties": {
    "tgn:hierarchy":[
        "tgn:7379262",
        "tgn:7005586",
        "tgn:1000001",
        "tgn:7005560",
        "tgn:7029392"
    ],
    "tgn:id":7379262,
    "tgn:name":"Margarita",
    "tgn:placetype":[
        "aat:300008347"
    ]
},
  "bbox": [],
  "geometry": {"coordinates":[-103.8,22.583333],"type":"Point"}
}
=======
{"geometry":{"type":"Point","coordinates":[-103.800000,22.583333]},"type":"Feature","properties":{"hierarchy":["tgn:7379262","tgn:7005586","tgn:1000001","tgn:7005560","tgn:7029392"],"placetype":["aat:300008347"],"id":7379262,"name:xx":"Margarita"}}
>>>>>>> 03f74aca74312dbeaf24d7e61306dd6a786dc3d0
