{
  "id": 7584449,
  "type": "Feature",
  "properties": {
    "tgn:hierarchy":[
        "tgn:7584449",
        "tgn:1000004",
        "tgn:7000198",
        "tgn:7016788",
        "tgn:7029392"
    ],
    "tgn:id":7584449,
    "tgn:name:en":"Bh\u016br\u0101sar",
    "tgn:placetype":[
        "aat:300008347"
    ]
},
  "bbox": [],
  "geometry": {"coordinates":[75.364423,28.158686],"type":"Point"}
}