{
  "id": 7167037,
  "type": "Feature",
  "properties": {
    "tgn:hierarchy":[
        "tgn:7167037",
        "tgn:7000096",
        "tgn:1000003",
        "tgn:7000084",
        "tgn:7029392"
    ],
    "tgn:id":7167037,
    "tgn:name":"Heinrichsdorf",
    "tgn:placetype":[
        "aat:300008347"
    ]
},
  "bbox": [],
  "geometry": {"coordinates":[12.95,53.05],"type":"Point"}
}