{
  "id": 7585447,
  "type": "Feature",
  "properties": {
    "tgn:hierarchy":[
        "tgn:7585447",
        "tgn:1000004",
        "tgn:7000198",
        "tgn:7016722",
        "tgn:7029392"
    ],
    "tgn:id":7585447,
    "tgn:name:en":"Kharkhari N\u0101la",
    "tgn:placetype":[
        "aat:300266554",
        "aat:300008699"
    ]
},
  "bbox": [],
  "geometry": {"coordinates":[78.493992,24.877194],"type":"Point"}
}