<<<<<<< HEAD
{
  "id": 7243086,
  "type": "Feature",
  "properties": {
    "tgn:hierarchy":[
        "tgn:7243086",
        "tgn:7003457",
        "tgn:1000003",
        "tgn:1000063",
        "tgn:7018236",
        "tgn:7029392"
    ],
    "tgn:id":7243086,
    "tgn:name":"Maarke-Kerkem",
    "tgn:placetype":[
        "aat:300008347"
    ]
},
  "bbox": [],
  "geometry": {"coordinates":[3.665283,50.820377],"type":"Point"}
}
=======
{"geometry":{"type":"Point","coordinates":[3.665283,50.820377]},"type":"Feature","properties":{"hierarchy":["tgn:7243086","tgn:7003457","tgn:1000003","tgn:1000063","tgn:7018236","tgn:7029392"],"placetype":["aat:300008347"],"id":7243086,"name:xx":"Maarke-Kerkem"}}
>>>>>>> 03f74aca74312dbeaf24d7e61306dd6a786dc3d0
