{
  "id": 2107012,
  "type": "Feature",
  "properties": {
    "tgn:hierarchy":[
        "tgn:2107012",
        "tgn:1000001",
        "tgn:7012149",
        "tgn:2002024",
        "tgn:7007826",
        "tgn:7029392"
    ],
    "tgn:id":2107012,
    "tgn:name":"Ragtown",
    "tgn:placetype":[
        "aat:300008347",
        "aat:300387210"
    ]
},
  "bbox": [],
  "geometry": {"coordinates":[-95.7333,33.8333],"type":"Point"}
}