{
  "id": 7258072,
  "type": "Feature",
  "properties": {
    "tgn:hierarchy":[
        "tgn:7258072",
        "tgn:7003619",
        "tgn:1000003",
        "tgn:7016845",
        "tgn:7029392"
    ],
    "tgn:id":7258072,
    "tgn:name:nl":"Achterpark",
    "tgn:placetype":[
        "aat:300008187"
    ]
},
  "bbox": [],
  "geometry": {"coordinates":[5.916667,52.233333],"type":"Point"}
}