{
  "id": 7574685,
  "type": "Feature",
  "properties": {
    "tgn:hierarchy":[
        "tgn:7574685",
        "tgn:1000004",
        "tgn:7000198",
        "tgn:7016788",
        "tgn:7029392"
    ],
    "tgn:id":7574685,
    "tgn:name:en":"Kurgaon",
    "tgn:placetype":[
        "aat:300008347"
    ]
},
  "bbox": [],
  "geometry": {"coordinates":[76.854211,26.456001],"type":"Point"}
}