{
  "id": 7557534,
  "type": "Feature",
  "properties": {
    "tgn:hierarchy":[
        "tgn:7557534",
        "tgn:1001828",
        "tgn:1000004",
        "tgn:7000198",
        "tgn:7029392"
    ],
    "tgn:id":7557534,
    "tgn:name:en":"Polatala",
    "tgn:placetype":[
        "aat:300008347"
    ]
},
  "bbox": [],
  "geometry": {"coordinates":[78.683333,14.366667],"type":"Point"}
}