{
  "id": 2208015,
  "type": "Feature",
  "properties": {
    "tgn:hierarchy":[
        "tgn:2208015",
        "tgn:1000001",
        "tgn:7012149",
        "tgn:2001300",
        "tgn:7007524",
        "tgn:7029392"
    ],
    "tgn:id":2208015,
    "tgn:name":"Burke Gulch",
    "tgn:placetype":[
        "aat:300008761"
    ]
},
  "bbox": [],
  "geometry": {"coordinates":[-114.05,46.0333],"type":"Point"}
}