{
  "id": 7509630,
  "type": "Feature",
  "properties": {
    "tgn:hierarchy":[
        "tgn:7509630",
        "tgn:7000509",
        "tgn:1008380",
        "tgn:1000226",
        "tgn:1000006",
        "tgn:7029392"
    ],
    "tgn:id":7509630,
    "tgn:name:en":"Te Uru",
    "tgn:placetype":[
        "aat:300008795"
    ]
},
  "bbox": [],
  "geometry": {"coordinates":[176.783333,-38.35],"type":"Point"}
}