{
  "id": 2475709,
  "type": "Feature",
  "properties": {
    "tgn:hierarchy":[
        "tgn:2475709",
        "tgn:1000001",
        "tgn:7012149",
        "tgn:2001304",
        "tgn:7007524",
        "tgn:7029392"
    ],
    "tgn:id":2475709,
    "tgn:name":"Lucky Luke Mine",
    "tgn:placetype":[
        "aat:300000390"
    ]
},
  "bbox": [],
  "geometry": {"coordinates":[-115.4667,47.65],"type":"Point"}
}