{
  "id": 1054974,
  "type": "Feature",
  "properties": {
    "tgn:hierarchy":[
        "tgn:1054974",
        "tgn:1000004",
        "tgn:7011584",
        "tgn:7018214",
        "tgn:7002435",
        "tgn:7029392"
    ],
    "tgn:id":1054974,
    "tgn:name":"Kan\u00ebvka",
    "tgn:placetype":[
        "aat:300008347"
    ]
},
  "bbox": [],
  "geometry": {"coordinates":[39.6667,67.1333],"type":"Point"}
}