{
  "id": 7301502,
  "type": "Feature",
  "properties": {
    "tgn:hierarchy":[
        "tgn:7301502",
        "tgn:7002759",
        "tgn:7002843",
        "tgn:1000003",
        "tgn:1000095",
        "tgn:7029392"
    ],
    "tgn:id":7301502,
    "tgn:name":"Mirambel",
    "tgn:placetype":[
        "aat:300008347"
    ]
},
  "bbox": [],
  "geometry": {"coordinates":[-0.333333,40.583333],"type":"Point"}
}