{
  "id": 7063733,
  "type": "Feature",
  "properties": {
    "tgn:hierarchy":[
        "tgn:7063733",
        "tgn:1000003",
        "tgn:7003688",
        "tgn:7000084",
        "tgn:7029392"
    ],
    "tgn:id":7063733,
    "tgn:name":"Aukamp",
    "tgn:placetype":[
        "aat:300000206"
    ]
},
  "bbox": [],
  "geometry": {"coordinates":[9.433333,54.016667],"type":"Point"}
}