{
  "id": 7533723,
  "type": "Feature",
  "properties": {
    "tgn:hierarchy":[
        "tgn:7533723",
        "tgn:7001242",
        "tgn:7016833",
        "tgn:1001142",
        "tgn:7029392"
    ],
    "tgn:id":7533723,
    "tgn:name:en":"Kafr Jum'ah",
    "tgn:placetype":[
        "aat:300008347"
    ]
},
  "bbox": [],
  "geometry": {"coordinates":[30.948162,28.903966],"type":"Point"}
}