{
  "id": 2416495,
  "type": "Feature",
  "properties": {
    "tgn:hierarchy":[
        "tgn:2416495",
        "tgn:1000001",
        "tgn:7012149",
        "tgn:2000972",
        "tgn:7007520",
        "tgn:7029392"
    ],
    "tgn:id":2416495,
    "tgn:name":"Jack Creek",
    "tgn:placetype":[
        "aat:300008706"
    ]
},
  "bbox": [],
  "geometry": {"coordinates":[-85.7333,46.5167],"type":"Point"}
}