{
  "id": 7297901,
  "type": "Feature",
  "properties": {
    "tgn:hierarchy":[
        "tgn:7297901",
        "tgn:7002842",
        "tgn:7001158",
        "tgn:1000003",
        "tgn:1000095",
        "tgn:7029392"
    ],
    "tgn:id":7297901,
    "tgn:name":"Soliedra",
    "tgn:placetype":[
        "aat:300008347"
    ]
},
  "bbox": [],
  "geometry": {"coordinates":[-2.383333,41.466667],"type":"Point"}
}