<<<<<<< HEAD
{
  "id": 2404848,
  "type": "Feature",
  "properties": {
    "tgn:hierarchy":[
        "tgn:2404848",
        "tgn:1000001",
        "tgn:1002294",
        "tgn:7012149",
        "tgn:7007710",
        "tgn:7029392"
    ],
    "tgn:id":2404848,
    "tgn:name":"Huckleberry Ridge",
    "tgn:placetype":[
        "aat:300266640"
    ]
},
  "bbox": [],
  "geometry": {"coordinates":[-76.4667,41.2],"type":"Point"}
}
=======
{"geometry":{"type":"Point","coordinates":[-76.466700,41.200000]},"type":"Feature","properties":{"hierarchy":["tgn:2404848","tgn:1000001","tgn:1002294","tgn:7012149","tgn:7007710","tgn:7029392"],"placetype":["aat:300266640"],"id":2404848,"name:xx":"Huckleberry Ridge"}}
>>>>>>> 03f74aca74312dbeaf24d7e61306dd6a786dc3d0
