{
  "id": 2317663,
  "type": "Feature",
  "properties": {
    "tgn:hierarchy":[
        "tgn:2317663",
        "tgn:1000001",
        "tgn:7012149",
        "tgn:2000473",
        "tgn:7007250",
        "tgn:7029392"
    ],
    "tgn:id":2317663,
    "tgn:name":"Enget Creek",
    "tgn:placetype":[
        "aat:300008706"
    ]
},
  "bbox": [],
  "geometry": {"coordinates":[-111.2333,44.55],"type":"Point"}
}