{
  "id": 2177899,
  "type": "Feature",
  "properties": {
    "tgn:hierarchy":[
        "tgn:2177899",
        "tgn:1000001",
        "tgn:7012149",
        "tgn:7007157",
        "tgn:2000189",
        "tgn:7029392"
    ],
    "tgn:id":2177899,
    "tgn:name":"Blackberry Creek",
    "tgn:placetype":[
        "aat:300008706"
    ]
},
  "bbox": [],
  "geometry": {"coordinates":[-123.3167,41.2167],"type":"Point"}
}