{
  "id": 7363218,
  "type": "Feature",
  "properties": {
    "tgn:hierarchy":[
        "tgn:7363218",
        "tgn:1000001",
        "tgn:1001893",
        "tgn:7005560",
        "tgn:7029392"
    ],
    "tgn:id":7363218,
    "tgn:name":"El Cenicero",
    "tgn:placetype":[
        "aat:300008347"
    ]
},
  "bbox": [],
  "geometry": {"coordinates":[-99.166944,19.866111],"type":"Point"}
}