{
  "id": 1124801,
  "type": "Feature",
  "properties": {
    "tgn:hierarchy":[
        "tgn:1124801",
        "tgn:1001941",
        "tgn:1000047",
        "tgn:7002458",
        "tgn:1000002",
        "tgn:7029392"
    ],
    "tgn:id":1124801,
    "tgn:name":"Ibirapuit\u00e3",
    "tgn:placetype":[
        "aat:300008707"
    ]
},
  "bbox": [],
  "geometry": {"coordinates":[-55.95,-29.3667],"type":"Point"}
}