<<<<<<< HEAD
{
  "id": 7175729,
  "type": "Feature",
  "properties": {
    "tgn:hierarchy":[
        "tgn:7175729",
        "tgn:1000003",
        "tgn:7003676",
        "tgn:7000084",
        "tgn:7029392"
    ],
    "tgn:id":7175729,
    "tgn:name":"Bahnhof Gro\u00dfenmeer",
    "tgn:placetype":[
        "aat:300386961",
        "aat:300007783"
    ]
},
  "bbox": [],
  "geometry": {"coordinates":[8.3,53.266667],"type":"Point"}
}
=======
{"geometry":{"type":"Point","coordinates":[8.300000,53.266667]},"type":"Feature","properties":{"hierarchy":["tgn:7175729","tgn:1000003","tgn:7003676","tgn:7000084","tgn:7029392"],"placetype":["aat:300386961","aat:300007783"],"id":7175729,"name:xx":"Bahnhof Gro\u00dfenmeer"}}
>>>>>>> 03f74aca74312dbeaf24d7e61306dd6a786dc3d0
