{
  "id": 7425530,
  "type": "Feature",
  "properties": {
    "tgn:hierarchy":[
        "tgn:7425530",
        "tgn:7005581",
        "tgn:1000001",
        "tgn:7005560",
        "tgn:7029392"
    ],
    "tgn:id":7425530,
    "tgn:name":"San Blas",
    "tgn:placetype":[
        "aat:300008347"
    ]
},
  "bbox": [],
  "geometry": {"coordinates":[-108.533333,30.733333],"type":"Point"}
}