{
  "id": 1020680,
  "type": "Feature",
  "properties": {
    "tgn:hierarchy":[
        "tgn:1020680",
        "tgn:7005439",
        "tgn:1000047",
        "tgn:7002455",
        "tgn:1000002",
        "tgn:7029392"
    ],
    "tgn:id":1020680,
    "tgn:name":"Araruna",
    "tgn:placetype":[
        "aat:300008347"
    ]
},
  "bbox": [],
  "geometry": {"coordinates":[-35.7333,-6.5333],"type":"Point"}
}