{
  "id": 2618742,
  "type": "Feature",
  "properties": {
    "tgn:hierarchy":[
        "tgn:2618742",
        "tgn:1000001",
        "tgn:7012149",
        "tgn:2002274",
        "tgn:7013961",
        "tgn:7029392"
    ],
    "tgn:id":2618742,
    "tgn:name":"Right Fork Sandlick Creek",
    "tgn:placetype":[
        "aat:300008706"
    ]
},
  "bbox": [],
  "geometry": {"coordinates":[-81.5667,37.3333],"type":"Point"}
}