{
  "id": 7586483,
  "type": "Feature",
  "properties": {
    "tgn:hierarchy":[
        "tgn:7586483",
        "tgn:1000004",
        "tgn:7000198",
        "tgn:7000799",
        "tgn:7029392"
    ],
    "tgn:id":7586483,
    "tgn:name:en":"D\u0101ngarw\u0101r Kol",
    "tgn:placetype":[
        "aat:300008699"
    ]
},
  "bbox": [],
  "geometry": {"coordinates":[74.279167,34.434232],"type":"Point"}
}