<<<<<<< HEAD
{
  "id": 7374767,
  "type": "Feature",
  "properties": {
    "tgn:hierarchy":[
        "tgn:7374767",
        "tgn:7005581",
        "tgn:1000001",
        "tgn:7005560",
        "tgn:7029392"
    ],
    "tgn:id":7374767,
    "tgn:name":"La Boquilla",
    "tgn:placetype":[
        "aat:300008347"
    ]
},
  "bbox": [],
  "geometry": {"coordinates":[-107.2,28.516667],"type":"Point"}
}
=======
{"geometry":{"type":"Point","coordinates":[-107.200000,28.516667]},"type":"Feature","properties":{"hierarchy":["tgn:7374767","tgn:7005581","tgn:1000001","tgn:7005560","tgn:7029392"],"placetype":["aat:300008347"],"id":7374767,"name:xx":"La Boquilla"}}
>>>>>>> 03f74aca74312dbeaf24d7e61306dd6a786dc3d0
