{
  "id": 2770512,
  "type": "Feature",
  "properties": {
    "tgn:hierarchy":[
        "tgn:2770512",
        "tgn:1000001",
        "tgn:7016172",
        "tgn:7012149",
        "tgn:2000172",
        "tgn:7029392"
    ],
    "tgn:id":2770512,
    "tgn:name":"Wild Plum Lake",
    "tgn:placetype":[
        "aat:300006191"
    ]
},
  "bbox": [],
  "geometry": {"coordinates":[-91.5167,36.2667],"type":"Point"}
}