{
  "id": 7127372,
  "type": "Feature",
  "properties": {
    "tgn:hierarchy":[
        "tgn:7127372",
        "tgn:1000003",
        "tgn:7003678",
        "tgn:7000084",
        "tgn:7029392"
    ],
    "tgn:id":7127372,
    "tgn:name":"F\u00f6rsterei Nikolauspforte",
    "tgn:placetype":[
        "aat:300004792"
    ]
},
  "bbox": [],
  "geometry": {"coordinates":[8.55,49.966667],"type":"Point"}
}