{
  "id": 2336343,
  "type": "Feature",
  "properties": {
    "tgn:hierarchy":[
        "tgn:2336343",
        "tgn:1000001",
        "tgn:7012149",
        "tgn:1002612",
        "tgn:7007710",
        "tgn:7029392"
    ],
    "tgn:id":2336343,
    "tgn:name":"Foundryville",
    "tgn:placetype":[
        "aat:300008347"
    ]
},
  "bbox": [],
  "geometry": {"coordinates":[-75.8667,40.9833],"type":"Point"}
}