<<<<<<< HEAD
{
  "id": 2336343,
  "type": "Feature",
  "properties": {
    "tgn:hierarchy":[
        "tgn:2336343",
        "tgn:1000001",
        "tgn:7012149",
        "tgn:1002612",
        "tgn:7007710",
        "tgn:7029392"
    ],
    "tgn:id":2336343,
    "tgn:name":"Foundryville",
    "tgn:placetype":[
        "aat:300008347"
    ]
},
  "bbox": [],
  "geometry": {"coordinates":[-75.8667,40.9833],"type":"Point"}
}
=======
{"geometry":{"type":"Point","coordinates":[-75.866700,40.983300]},"type":"Feature","properties":{"hierarchy":["tgn:2336343","tgn:1000001","tgn:7012149","tgn:1002612","tgn:7007710","tgn:7029392"],"placetype":["aat:300008347"],"id":2336343,"name:xx":"Foundryville"}}
>>>>>>> 03f74aca74312dbeaf24d7e61306dd6a786dc3d0
