<<<<<<< HEAD
{
  "id": 7052744,
  "type": "Feature",
  "properties": {
    "tgn:hierarchy":[
        "tgn:7052744",
        "tgn:7003150",
        "tgn:1000003",
        "tgn:7003237",
        "tgn:1000080",
        "tgn:7029392"
    ],
    "tgn:id":7052744,
    "tgn:name":"Monticelli",
    "tgn:placetype":[
        "aat:300008347"
    ]
},
  "bbox": [],
  "geometry": {"coordinates":[9.65,45.25],"type":"Point"}
}
=======
{"geometry":{"type":"Point","coordinates":[9.650000,45.250000]},"type":"Feature","properties":{"hierarchy":["tgn:7052744","tgn:7003150","tgn:1000003","tgn:7003237","tgn:1000080","tgn:7029392"],"placetype":["aat:300008347"],"id":7052744,"name:xx":"Monticelli"}}
>>>>>>> 03f74aca74312dbeaf24d7e61306dd6a786dc3d0
