{
  "id": 7083596,
  "type": "Feature",
  "properties": {
    "tgn:hierarchy":[
        "tgn:7083596",
        "tgn:1000003",
        "tgn:7000094",
        "tgn:7000084",
        "tgn:7029392"
    ],
    "tgn:id":7083596,
    "tgn:name":"Wilhelmslust",
    "tgn:placetype":[
        "aat:300000206"
    ]
},
  "bbox": [],
  "geometry": {"coordinates":[13.75,53.533333],"type":"Point"}
}