<<<<<<< HEAD
{
  "id": 7171313,
  "type": "Feature",
  "properties": {
    "tgn:hierarchy":[
        "tgn:7171313",
        "tgn:7003669",
        "tgn:1000003",
        "tgn:7000084",
        "tgn:7029392"
    ],
    "tgn:id":7171313,
    "tgn:name":"Hirschberger",
    "tgn:placetype":[
        "aat:300000206"
    ]
},
  "bbox": [],
  "geometry": {"coordinates":[11.183333,47.9],"type":"Point"}
}
=======
{"geometry":{"type":"Point","coordinates":[11.183333,47.900000]},"type":"Feature","properties":{"hierarchy":["tgn:7171313","tgn:7003669","tgn:1000003","tgn:7000084","tgn:7029392"],"placetype":["aat:300000206"],"id":7171313,"name:xx":"Hirschberger"}}
>>>>>>> 03f74aca74312dbeaf24d7e61306dd6a786dc3d0
