{
  "id": 1092238,
  "type": "Feature",
  "properties": {
    "tgn:hierarchy":[
        "tgn:1092238",
        "tgn:7001242",
        "tgn:1001889",
        "tgn:1000182",
        "tgn:7029392"
    ],
    "tgn:id":1092238,
    "tgn:name":"Oshodi",
    "tgn:placetype":[
        "aat:300008347"
    ]
},
  "bbox": [],
  "geometry": {"coordinates":[3.3333,6.55],"type":"Point"}
}