{
  "id": 2410185,
  "type": "Feature",
  "properties": {
    "tgn:hierarchy":[
        "tgn:2410185",
        "tgn:1000001",
        "tgn:7012149",
        "tgn:2000479",
        "tgn:7007250",
        "tgn:7029392"
    ],
    "tgn:id":2410185,
    "tgn:name":"Independence Point",
    "tgn:placetype":[
        "aat:300008850"
    ]
},
  "bbox": [],
  "geometry": {"coordinates":[-116.7833,47.6667],"type":"Point"}
}