{
  "id": 1119518,
  "type": "Feature",
  "properties": {
    "tgn:hierarchy":[
        "tgn:1119518",
        "tgn:1001647",
        "tgn:1000003",
        "tgn:1000095",
        "tgn:7029392"
    ],
    "tgn:id":1119518,
    "tgn:name":"Buendia, Embalse de",
    "tgn:placetype":[
        "aat:300006191"
    ]
},
  "bbox": [],
  "geometry": {"coordinates":[-2.716667,40.416667],"type":"Point"}
}