{
  "id": 7586888,
  "type": "Feature",
  "properties": {
    "tgn:hierarchy":[
        "tgn:7586888",
        "tgn:1000004",
        "tgn:7000198",
        "tgn:7000799",
        "tgn:7029392"
    ],
    "tgn:id":7586888,
    "tgn:name:en":"H\u0101yan Forest",
    "tgn:placetype":[
        "aat:300008863"
    ]
},
  "bbox": [],
  "geometry": {"coordinates":[74.941667,34.216667],"type":"Point"}
}