{
  "id": 2707123,
  "type": "Feature",
  "properties": {
    "tgn:hierarchy":[
        "tgn:2707123",
        "tgn:1000001",
        "tgn:2001635",
        "tgn:7012149",
        "tgn:7007707",
        "tgn:7029392"
    ],
    "tgn:id":2707123,
    "tgn:name":"Swede Creek",
    "tgn:placetype":[
        "aat:300008706"
    ]
},
  "bbox": [],
  "geometry": {"coordinates":[-102.8667,36.75],"type":"Point"}
}