{
  "id": 2415417,
  "type": "Feature",
  "properties": {
    "tgn:hierarchy":[
        "tgn:2415417",
        "tgn:1000001",
        "tgn:1002473",
        "tgn:7012149",
        "tgn:7007240",
        "tgn:7029392"
    ],
    "tgn:id":2415417,
    "tgn:name":"Island Prairie Pond",
    "tgn:placetype":[
        "aat:300008680"
    ]
},
  "bbox": [],
  "geometry": {"coordinates":[-82.1333,28.5333],"type":"Point"}
}